/*     */ package akka.routing;
/*     */ 
/*     */ import java.util.List;
/*     */ import scala.Function1;
/*     */ import scala.Product;
/*     */ import scala.Serializable;
/*     */ import scala.collection.Iterator;
/*     */ import scala.collection.JavaConverters$;
/*     */ import scala.collection.Seq;
/*     */ import scala.collection.immutable.IndexedSeq;
/*     */ import scala.reflect.ScalaSignature;
/*     */ import scala.runtime.BoxesRunTime;
/*     */ import scala.runtime.ScalaRunTime$;
/*     */ 
/*     */ @ScalaSignature(bytes = "\006\001\005Ub\001B\001\003\001\036\021qAU8vi\026,7O\003\002\004\t\0059!o\\;uS:<'\"A\003\002\t\005\\7.Y\002\001'\021\001\001BD\t\021\005%aQ\"\001\006\013\003-\tQa]2bY\006L!!\004\006\003\r\005s\027PU3g!\tIq\"\003\002\021\025\t9\001K]8ek\016$\bCA\005\023\023\t\031\"B\001\007TKJL\027\r\\5{C\ndW\r\003\005\026\001\tU\r\021\"\001\027\003\035\021x.\036;fKN,\022a\006\t\0041uyR\"A\r\013\005iY\022!C5n[V$\030M\0317f\025\ta\"\"\001\006d_2dWm\031;j_:L!AH\r\003\025%sG-\032=fIN+\027\017\005\002!C5\t!!\003\002#\005\t1!k\\;uK\026D\001\002\n\001\003\022\003\006IaF\001\te>,H/Z3tA!)a\005\001C\001O\0051A(\0338jiz\"\"\001K\025\021\005\001\002\001\"B\013&\001\0049\002\"B\026\001\t\003a\023AC4fiJ{W\017^3fgV\tQ\006E\002/g}i\021a\f\006\003aE\nA!\036;jY*\t!'\001\003kCZ\f\027B\001\0330\005\021a\025n\035;\t\017Y\002\021\021!C\001o\005!1m\0349z)\tA\003\bC\004\026kA\005\t\031A\f\t\017i\002\021\023!C\001w\005q1m\0349zI\021,g-Y;mi\022\nT#\001\037+\005]i4&\001 \021\005}\"U\"\001!\013\005\005\023\025!C;oG\",7m[3e\025\t\031%\"\001\006b]:|G/\031;j_:L!!\022!\003#Ut7\r[3dW\026$g+\031:jC:\034W\rC\004H\001\005\005I\021\t%\002\033A\024x\016Z;diB\023XMZ5y+\005I\005C\001&N\033\005Y%B\001'2\003\021a\027M\\4\n\0059[%AB*ue&tw\rC\004Q\001\005\005I\021A)\002\031A\024x\016Z;di\006\023\030\016^=\026\003I\003\"!C*\n\005QS!aA%oi\"9a\013AA\001\n\0039\026A\0049s_\022,8\r^#mK6,g\016\036\013\0031n\003\"!C-\n\005iS!aA!os\"9A,VA\001\002\004\021\026a\001=%c!9a\fAA\001\n\003z\026a\0049s_\022,8\r^%uKJ\fGo\034:\026\003\001\0042!\0312Y\033\005Y\022BA2\034\005!IE/\032:bi>\024\bbB3\001\003\003%\tAZ\001\tG\006tW)];bYR\021qM\033\t\003\023!L!!\033\006\003\017\t{w\016\\3b]\"9A\fZA\001\002\004A\006b\0027\001\003\003%\t%\\\001\tQ\006\034\bnQ8eKR\t!\013C\004p\001\005\005I\021\t9\002\021Q|7\013\036:j]\036$\022!\023\005\be\002\t\t\021\"\021t\003\031)\027/^1mgR\021q\r\036\005\b9F\f\t\0211\001YQ\r\001a/\037\t\003\023]L!\001\037\006\003!M+'/[1m-\026\0248/[8o+&#e$A\001\b\017m\024\021\021!E\001y\0069!k\\;uK\026\034\bC\001\021~\r\035\t!!!A\t\002y\0342!`@\022!\031\t\t!a\002\030Q5\021\0211\001\006\004\003\013Q\021a\002:v]RLW.Z\005\005\003\023\t\031AA\tBEN$(/Y2u\rVt7\r^5p]FBaAJ?\005\002\0055A#\001?\t\017=l\030\021!C#a\"I\0211C?\002\002\023\005\025QC\001\006CB\004H.\037\013\004Q\005]\001BB\013\002\022\001\007q\003C\005\002\034u\f\t\021\"!\002\036\0059QO\\1qa2LH\003BA\020\003K\001B!CA\021/%\031\0211\005\006\003\r=\003H/[8o\021%\t9#!\007\002\002\003\007\001&A\002yIAB\021\"a\013~\003\003%I!!\f\002\027I,\027\r\032*fg>dg/\032\013\003\003_\0012ASA\031\023\r\t\031d\023\002\007\037\nTWm\031;")
/*     */ public class Routees implements Product, Serializable {
/*     */   public static final long serialVersionUID = 1L;
/*     */   
/*     */   private final IndexedSeq<Routee> routees;
/*     */   
/*     */   public IndexedSeq<Routee> routees() {
/* 379 */     return this.routees;
/*     */   }
/*     */   
/*     */   public Routees copy(IndexedSeq<Routee> routees) {
/* 379 */     return new Routees(routees);
/*     */   }
/*     */   
/*     */   public IndexedSeq<Routee> copy$default$1() {
/* 379 */     return routees();
/*     */   }
/*     */   
/*     */   public String productPrefix() {
/* 379 */     return "Routees";
/*     */   }
/*     */   
/*     */   public int productArity() {
/* 379 */     return 1;
/*     */   }
/*     */   
/*     */   public Object productElement(int x$1) {
/* 379 */     int i = x$1;
/* 379 */     switch (i) {
/*     */       default:
/* 379 */         throw new IndexOutOfBoundsException(BoxesRunTime.boxToInteger(x$1).toString());
/*     */       case 0:
/*     */         break;
/*     */     } 
/* 379 */     return routees();
/*     */   }
/*     */   
/*     */   public Iterator<Object> productIterator() {
/* 379 */     return ScalaRunTime$.MODULE$.typedProductIterator(this);
/*     */   }
/*     */   
/*     */   public boolean canEqual(Object x$1) {
/* 379 */     return x$1 instanceof Routees;
/*     */   }
/*     */   
/*     */   public int hashCode() {
/* 379 */     return ScalaRunTime$.MODULE$._hashCode(this);
/*     */   }
/*     */   
/*     */   public String toString() {
/* 379 */     return ScalaRunTime$.MODULE$._toString(this);
/*     */   }
/*     */   
/*     */   public boolean equals(Object x$1) {
/*     */     // Byte code:
/*     */     //   0: aload_0
/*     */     //   1: aload_1
/*     */     //   2: if_acmpeq -> 80
/*     */     //   5: aload_1
/*     */     //   6: astore_2
/*     */     //   7: aload_2
/*     */     //   8: instanceof akka/routing/Routees
/*     */     //   11: ifeq -> 19
/*     */     //   14: iconst_1
/*     */     //   15: istore_3
/*     */     //   16: goto -> 21
/*     */     //   19: iconst_0
/*     */     //   20: istore_3
/*     */     //   21: iload_3
/*     */     //   22: ifeq -> 84
/*     */     //   25: aload_1
/*     */     //   26: checkcast akka/routing/Routees
/*     */     //   29: astore #4
/*     */     //   31: aload_0
/*     */     //   32: invokevirtual routees : ()Lscala/collection/immutable/IndexedSeq;
/*     */     //   35: aload #4
/*     */     //   37: invokevirtual routees : ()Lscala/collection/immutable/IndexedSeq;
/*     */     //   40: astore #5
/*     */     //   42: dup
/*     */     //   43: ifnonnull -> 55
/*     */     //   46: pop
/*     */     //   47: aload #5
/*     */     //   49: ifnull -> 63
/*     */     //   52: goto -> 76
/*     */     //   55: aload #5
/*     */     //   57: invokevirtual equals : (Ljava/lang/Object;)Z
/*     */     //   60: ifeq -> 76
/*     */     //   63: aload #4
/*     */     //   65: aload_0
/*     */     //   66: invokevirtual canEqual : (Ljava/lang/Object;)Z
/*     */     //   69: ifeq -> 76
/*     */     //   72: iconst_1
/*     */     //   73: goto -> 77
/*     */     //   76: iconst_0
/*     */     //   77: ifeq -> 84
/*     */     //   80: iconst_1
/*     */     //   81: goto -> 85
/*     */     //   84: iconst_0
/*     */     //   85: ireturn
/*     */     // Line number table:
/*     */     //   Java source line number -> byte code offset
/*     */     //   #379	-> 0
/*     */     //   #63	-> 14
/*     */     //   #379	-> 21
/*     */     // Local variable table:
/*     */     //   start	length	slot	name	descriptor
/*     */     //   0	86	0	this	Lakka/routing/Routees;
/*     */     //   0	86	1	x$1	Ljava/lang/Object;
/*     */   }
/*     */   
/*     */   public Routees(IndexedSeq<Routee> routees) {
/* 379 */     Product.class.$init$(this);
/*     */   }
/*     */   
/*     */   public List<Routee> getRoutees() {
/* 385 */     return (List<Routee>)JavaConverters$.MODULE$.seqAsJavaListConverter((Seq)routees()).asJava();
/*     */   }
/*     */   
/*     */   public static <A> Function1<IndexedSeq<Routee>, A> andThen(Function1<Routees, A> paramFunction1) {
/*     */     return Routees$.MODULE$.andThen(paramFunction1);
/*     */   }
/*     */   
/*     */   public static <A> Function1<A, Routees> compose(Function1<A, IndexedSeq<Routee>> paramFunction1) {
/*     */     return Routees$.MODULE$.compose(paramFunction1);
/*     */   }
/*     */ }


/* Location:              D:\#source-code\TheFlightSims\TFSLibrary\World2Xplane\World2XPlane.jar!\akka\routing\Routees.class
 * Java compiler version: 6 (50.0)
 * JD-Core Version:       1.1.3
 */