/*     */ package scala.util.parsing.combinator;
/*     */ 
/*     */ import scala.Function0;
/*     */ import scala.Function1;
/*     */ import scala.MatchError;
/*     */ import scala.Option;
/*     */ import scala.Product;
/*     */ import scala.Serializable;
/*     */ import scala.Some;
/*     */ import scala.Tuple2;
/*     */ import scala.Tuple3;
/*     */ import scala.collection.Iterator;
/*     */ import scala.collection.immutable.List;
/*     */ import scala.collection.mutable.HashMap;
/*     */ import scala.reflect.ScalaSignature;
/*     */ import scala.runtime.AbstractFunction1;
/*     */ import scala.runtime.AbstractFunction3;
/*     */ import scala.runtime.BoxesRunTime;
/*     */ import scala.runtime.ObjectRef;
/*     */ import scala.runtime.VolatileByteRef;
/*     */ import scala.util.Either;
/*     */ import scala.util.Left;
/*     */ import scala.util.Right;
/*     */ import scala.util.parsing.input.Position;
/*     */ import scala.util.parsing.input.Reader;
/*     */ 
/*     */ @ScalaSignature(bytes = "\006\001\031eaaB\001\003!\003\r\ta\003\002\017!\006\0347N]1u!\006\0248/\032:t\025\t\031A!\001\006d_6\024\027N\\1u_JT!!\002\004\002\017A\f'o]5oO*\021q\001C\001\005kRLGNC\001\n\003\025\0318-\0317b\007\001\0312\001\001\007\021!\tia\"D\001\t\023\ty\001B\001\004B]f\024VM\032\t\003#Ii\021AA\005\003'\t\021q\001U1sg\026\0248\017C\003\026\001\021\005a#\001\004%S:LG\017\n\013\002/A\021Q\002G\005\0033!\021A!\0268ji\032!1\004\001\001\035\0055\001\026mY6sCR\024V-\0313feV\021QDJ\n\0035y\0012a\b\022%\033\005\001#BA\021\005\003\025Ig\016];u\023\t\031\003E\001\004SK\006$WM\035\t\003K\031b\001\001\002\004(5\021\025\r\001\013\002\002)F\021\021\006\f\t\003\033)J!a\013\005\003\0179{G\017[5oOB\021Q\"L\005\003]!\0211!\0218z\021!\001$D!A!\002\023q\022AC;oI\026\024H._5oO\")!G\007C\001g\0051A(\0338jiz\"\"\001\016\034\021\007URB%D\001\001\021\025\001\024\0071\001\037\021%A$D!A\001B\003%\021(\001\033tG\006d\027\rJ;uS2$\003/\031:tS:<GeY8nE&t\027\r^8sIA\0137m\033:biB\013'o]3sg\022\"3-Y2iK\002\002BAO B\0356\t1H\003\002={\0059Q.\036;bE2,'B\001 \t\003)\031w\016\0347fGRLwN\\\005\003\001n\022q\001S1tQ6\013\007\017\005\003\016\005\022[\025BA\"\t\005\031!V\017\0357feA\022Q)\023\t\004k\031C\025BA$\023\005\031\001\026M]:feB\021Q%\023\003\n\025^\n\t\021!A\003\002!\0221a\030\0232!\tyB*\003\002NA\tA\001k\\:ji&|g\016M\002P\007\002B!\016)\004~\031!\021\013\001#S\005%iU-\\8F]R\024\0300F\002T\007g\031B\001\025\007U/B\021Q\"V\005\003-\"\021q\001\025:pIV\034G\017\005\002\0161&\021\021\f\003\002\r'\026\024\030.\0317ju\006\024G.\032\005\t7B\023\t\032!C\0019\006\t!/F\001^!\025qf-[B\001\035\tyFM\004\002aG6\t\021M\003\002c\025\0051AH]8pizJ\021!C\005\003K\"\tq\001]1dW\006<W-\003\002hQ\n1Q)\033;iKJT!!\032\005\021\005URg\001B6\001\t2\024!\001\024*\024\t)dAk\026\005\t]*\024\t\032!C\001_\006!1/Z3e+\005\001\bGA9v!\r)$\017^\005\003gJ\0211\002U1sg\026\024Vm];miB\021Q%\036\003\nm^\f\t\021!A\003\002!\0221a\030\0236\021!A(N!E!B\023I\030!B:fK\022\004\003G\001>}!\r)$o\037\t\003Kq$\021B^<\002\002\003\005)\021\001\025\t\021yT'\0211A\005\002}\f\001b]3fI~#S-\035\013\004/\005\005\001\"CA\002{\006\005\t\031AA\003\003\rAH%\r\031\005\003\017\tY\001\005\0036e\006%\001cA\023\002\f\021Iao^A\001\002\003\025\t\001\013\005\013\003\037Q'\0213A\005\002\005E\021\001\002:vY\026,\"!a\0051\t\005U\021\021\004\t\005k\031\0139\002E\002&\0033!1\"a\007\002\036\005\005\t\021!B\001Q\t\031q\f\n\034\t\025\005}!N!E!B\023\t\t#A\003sk2,\007\005\r\003\002$\005\035\002\003B\033G\003K\0012!JA\024\t-\tY\"!\b\002\002\003\005)\021\001\025\t\025\005-\"N!a\001\n\003\ti#\001\005sk2,w\fJ3r)\r9\022q\006\005\013\003\007\tI#!AA\002\005E\002\007BA\032\003o\001B!\016$\0026A\031Q%a\016\005\027\005m\021QDA\001\002\003\025\t\001\013\005\013\003wQ'\0213A\005\002\005u\022\001\0025fC\022,\"!a\020\021\0135\t\t%!\022\n\007\005\r\003B\001\004PaRLwN\034\t\004k\005\035cABA%\001\021\013YE\001\003IK\006$7#BA$\031Q;\006bCA(\003\017\022\t\032!C\001\003#\n!\002[3bIB\013'o]3s+\t\t\031\006\r\003\002V\005e\003\003B\033G\003/\0022!JA-\t-\tY&!\030\002\002\003\005)\021\001\025\003\007}#s\007C\006\002`\005\035#\021#Q!\n\005\005\024a\0035fC\022\004\026M]:fe\002\002D!a\031\002hA!QGRA3!\r)\023q\r\003\f\0037\ni&!A\001\002\013\005\001\006C\006\002l\005\035#\0211A\005\002\0055\024A\0045fC\022\004\026M]:fe~#S-\035\013\004/\005=\004BCA\002\003S\n\t\0211\001\002rA\"\0211OA<!\021)d)!\036\021\007\025\n9\bB\006\002\\\005u\023\021!A\001\006\003A\003bCA>\003\017\022\t\032!C\001\003{\n1\"\0338w_24X\rZ*fiV\021\021q\020\t\006=\006\005\025QQ\005\004\003\007C'\001\002'jgR\004D!a\"\002\fB!QGRAE!\r)\0231\022\003\f\003\033\013y)!A\001\002\013\005\001FA\002`IaB1\"!%\002H\tE\t\025)\003\002\024\006a\021N\034<pYZ,GmU3uAA)a,!!\002\026B\"\021qSAN!\021)d)!'\021\007\025\nY\nB\006\002\016\006=\025\021!A\001\006\003A\003bCAP\003\017\022\t\031!C\001\003C\013q\"\0338w_24X\rZ*fi~#S-\035\013\004/\005\r\006BCA\002\003;\013\t\0211\001\002&B)a,!!\002(B\"\021\021VAW!\021)d)a+\021\007\025\ni\013B\006\002\016\006=\025\021!A\001\006\003A\003bCAY\003\017\022\t\032!C\001\003g\013q!\032<bYN+G/\006\002\0026B)a,!!\0028B\"\021\021XA_!\021)d)a/\021\007\025\ni\fB\006\002@\006\005\027\021!A\001\006\003A#aA0%s!Y\0211YA$\005#\005\013\025BAc\003!)g/\0317TKR\004\003#\0020\002\002\006\035\007\007BAe\003\033\004B!\016$\002LB\031Q%!4\005\027\005}\026\021YA\001\002\003\025\t\001\013\005\f\003#\f9E!a\001\n\003\t\031.A\006fm\006d7+\032;`I\025\fHcA\f\002V\"Q\0211AAh\003\003\005\r!a6\021\013y\013\t)!71\t\005m\027q\034\t\005k\031\013i\016E\002&\003?$1\"a0\002B\006\005\t\021!B\001Q!9!'a\022\005\002\005\rH\003CA#\003K\fy/a?\t\021\005=\023\021\035a\001\003O\004D!!;\002nB!QGRAv!\r)\023Q\036\003\f\0037\n)/!A\001\002\013\005\001\006\003\005\002|\005\005\b\031AAy!\025q\026\021QAza\021\t)0!?\021\tU2\025q\037\t\004K\005eHaCAG\003_\f\t\021!A\003\002!B\001\"!-\002b\002\007\021Q \t\006=\006\005\025q \031\005\005\003\021)\001\005\0036\r\n\r\001cA\023\003\006\021Y\021qXA~\003\003\005\tQ!\001)\021!\021I!a\022\005\002\t-\021aB4fi\"+\027\rZ\013\003\005\033\0012!\016$-\021)\021\t\"a\022\002\002\023\005!1C\001\005G>\004\030\020\006\005\002F\tU!q\003B\r\021)\tyEa\004\021\002\003\007\021q\035\005\013\003w\022y\001%AA\002\005E\bBCAY\005\037\001\n\0211\001\002~\"Q!QDA$#\003%\tAa\b\002\035\r|\007/\037\023eK\032\fW\017\034;%cU\021!\021\005\026\005\005\033\021\031c\013\002\003&A!!q\005B\031\033\t\021IC\003\003\003,\t5\022!C;oG\",7m[3e\025\r\021y\003C\001\013C:tw\016^1uS>t\027\002\002B\032\005S\021\021#\0368dQ\026\0347.\0323WCJL\027M\\2f\021)\0219$a\022\022\002\023\005!\021H\001\017G>\004\030\020\n3fM\006,H\016\036\0233+\t\021YD\013\003\002\000\t\r\002B\003B \003\017\n\n\021\"\001\003B\005q1m\0349zI\021,g-Y;mi\022\032TC\001B\"U\021\t)La\t\t\025\t\035\023qIA\001\n\003\022I%A\007qe>$Wo\031;Qe\0264\027\016_\013\003\005\027\002BA!\024\003X5\021!q\n\006\005\005#\022\031&\001\003mC:<'B\001B+\003\021Q\027M^1\n\t\te#q\n\002\007'R\024\030N\\4\t\025\tu\023qIA\001\n\003\021y&\001\007qe>$Wo\031;Be&$\0300\006\002\003bA\031QBa\031\n\007\t\025\004BA\002J]RD!B!\033\002H\005\005I\021\001B6\0039\001(o\0343vGR,E.Z7f]R$2\001\fB7\021)\t\031Aa\032\002\002\003\007!\021\r\005\013\005c\n9%!A\005B\tM\024a\0049s_\022,8\r^%uKJ\fGo\034:\026\005\tU\004#\002B<\005sbS\"A\037\n\007\tmTH\001\005Ji\026\024\030\r^8s\021)\021y(a\022\002\002\023\005!\021Q\001\tG\006tW)];bYR!!1\021BE!\ri!QQ\005\004\005\017C!a\002\"p_2,\027M\034\005\n\003\007\021i(!AA\0021B!B!$\002H\005\005I\021\tBH\003!A\027m\0355D_\022,GC\001B1\021)\021\031*a\022\002\002\023\005#QS\001\ti>\034FO]5oOR\021!1\n\005\013\0053\0139%!A\005B\tm\025AB3rk\006d7\017\006\003\003\004\nu\005\"CA\002\005/\013\t\0211\001-\021)\021\tK\033BA\002\023\005!1U\001\tQ\026\fGm\030\023fcR\031qC!*\t\025\005\r!qTA\001\002\004\ty\004\003\006\003**\024\t\022)Q\005\003\tQ\001[3bI\002BaA\r6\005\002\t5FcB5\0030\ne&1\031\005\b]\n-\006\031\001BYa\021\021\031La.\021\tU\022(Q\027\t\004K\t]FA\003<\0030\006\005\t\021!B\001Q!A\021q\002BV\001\004\021Y\f\r\003\003>\n\005\007\003B\033G\005\0032!\nBa\t-\tYB!/\002\002\003\005)\021\001\025\t\021\005m\"1\026a\001\003AqAa2k\t\003\021I-\001\004hKR\004vn]\013\002\027\"I!\021\0036\002\002\023\005!Q\032\013\bS\n='\021\033Bj\021%q'1\032I\001\002\004\021\t\f\003\006\002\020\t-\007\023!a\001\005wC!\"a\017\003LB\005\t\031AA \021%\021iB[I\001\n\003\0219.\006\002\003Z*\"!1\034B\022!\r)$\017\f\005\n\005oQ\027\023!C\001\005?A\021Ba\020k#\003%\tA!9\026\005\t\r(\006BA \005GA\021Ba\022k\003\003%\tE!\023\t\023\tu#.!A\005\002\t}\003\"\003B5U\006\005I\021\001Bv)\ra#Q\036\005\013\003\007\021I/!AA\002\t\005\004\"\003B9U\006\005I\021\tB:\021%\021yH[A\001\n\003\021\031\020\006\003\003\004\nU\b\"CA\002\005c\f\t\0211\001-\021%\021iI[A\001\n\003\022y\tC\005\003\024*\f\t\021\"\021\003\026\"I!\021\0246\002\002\023\005#Q \013\005\005\007\023y\020C\005\002\004\tm\030\021!a\001YA\"11AB\004!\021)$o!\002\021\007\025\0329\001B\006\004\n\r-\021\021!A\001\006\003A#aA0%i!Q1Q\002)\003\022\003\006Kaa\004\002\005I\004\003#\0020gS\016E\001\007BB\n\007/\001B!\016:\004\026A\031Qea\006\005\027\r%11BA\001\002\003\025\t\001\013\005\013\0077\001&\0211A\005\002\ru\021!\002:`I\025\fHcA\f\004 !Q\0211AB\r\003\003\005\ra!\t\021\013y3\027na\t1\t\r\0252\021\006\t\005kI\0349\003E\002&\007S!1b!\003\004\f\005\005\t\021!B\001Q!1!\007\025C\001\007[!Baa\f\0046A!Q\007UB\031!\r)31\007\003\007OA#)\031\001\025\t\017m\033Y\0031\001\0048A)aLZ5\004:A\"11HB !\021)$o!\020\021\007\025\032y\004B\006\004\n\rU\022\021!A\001\006\003A\003bBB\"!\022\0051QI\001\nO\026$(+Z:vYR,\"aa\022\021\tU\0228\021\007\005\n\005#\001\026\021!C\001\007\027*Ba!\024\004TQ!1qJB+!\021)\004k!\025\021\007\025\032\031\006\002\004(\007\023\022\r\001\013\005\n7\016%\003\023!a\001\007oA\021B!\bQ#\003%\ta!\027\026\t\rm3qL\013\003\007;R3!\030B\022\t\03193q\013b\001Q!I!q\t)\002\002\023\005#\021\n\005\n\005;\002\026\021!C\001\005?B\021B!\033Q\003\003%\taa\032\025\0071\032I\007\003\006\002\004\r\025\024\021!a\001\005CB\021B!\035Q\003\003%\tEa\035\t\023\t}\004+!A\005\002\r=D\003\002BB\007cB\021\"a\001\004n\005\005\t\031\001\027\t\023\t5\005+!A\005B\t=\005\"\003BJ!\006\005I\021\tBK\021%\021I\nUA\001\n\003\032I\b\006\003\003\004\016m\004\"CA\002\007o\n\t\0211\001-!\r)3q\020\003\013\007\003;\024\021!A\001\006\003A#aA0%e!Y1Q\021\016\003\002\003\005\013\021BBD\003u\0328-\0317bIU$\030\016\034\023qCJ\034\030N\\4%G>l'-\0338bi>\024H\005U1dWJ\fG\017U1sg\026\0248\017\n\023sK\016,(o]5p]\"+\027\rZ:!!\025QthSA#\0211\031YI\007B\001\002\004%\t\001ABG\003e\0328-\0317bIU$\030\016\034\023qCJ\034\030N\\4%G>l'-\0338bi>\024H\005U1dWJ\fG\017U1sg\026\0248\017\n\023meN#\030mY6`I\025\fHcA\f\004\020\"Q\0211ABE\003\003\005\ra!%\021\ty\013\t)\033\005\f\007+S\"\021!A!B\023\031\t*\001\034tG\006d\027\rJ;uS2$\003/\031:tS:<GeY8nE&t\027\r^8sIA\0137m\033:biB\013'o]3sg\022\"CN]*uC\016\\\007\005C\004\004\032j!\tea'\002\rM|WO]2f+\t\031i\n\005\003\003N\r}\025\002BBQ\005\037\022Ab\0215beN+\027/^3oG\026Dqa!*\033\t\003\022y&\001\004pM\032\034X\r\036\005\b\007SSB\021ABV\003\0251\027N]:u+\005!\003bBBX5\021\0051\021W\001\005e\026\034H/F\001\037\021\035\031)L\007C\001\005\023\f1\001]8t\021\035\031IL\007C\001\007w\013Q!\031;F]\022,\"Aa!\t\031\r}&D!AC\002\023\005\001a!1\002gM\034\027\r\\1%kRLG\016\n9beNLgn\032\023d_6\024\027N\\1u_J$\003+Y2le\006$\b+\031:tKJ\034H\005J2bG\",W#A\035\t\031\r\025'D!A\001\002\023\005\001aa2\002uM\034\027\r\\1%kRLG\016\n9beNLgn\032\023d_6\024\027N\\1u_J$\003+Y2le\006$\b+\031:tKJ\034H\005J4fi\032\023x.\\\"bG\",W\003BBe\007#$Baa3\004TB)Q\"!\021\004NB!Q\007UBh!\r)3\021\033\003\007O\r\r'\031\001\025\t\021\rU71\031a\001\007/\f\021\001\035\t\005k\031\033y\r\003\007\004\\j\021\t\021!A\005\002\001\031i.A tG\006d\027\rJ;uS2$\003/\031:tS:<GeY8nE&t\027\r^8sIA\0137m\033:biB\013'o]3sg\022\"S\017\0353bi\026\034\025m\0315f\003:$w)\032;\026\t\r}7Q\035\013\007\007C\0349oa;\021\tU\00261\035\t\004K\r\025HAB\024\004Z\n\007\001\006\003\005\004V\016e\007\031ABu!\021)dia9\t\021\r58\021\034a\001\007C\f\021a\036\005\r\007cT\"\021!b\001\n\003\00111_\001=g\016\fG.\031\023vi&dG\005]1sg&tw\rJ2p[\nLg.\031;pe\022\002\026mY6sCR\004\026M]:feN$CE]3dkJ\034\030n\0348IK\006$7/\006\002\004\b\"a1q\037\016\003\002\003\007I\021\001\001\004z\006)4oY1mC\022*H/\0337%a\006\0248/\0338hI\r|WNY5oCR|'\017\n)bG.\024\030\r\036)beN,'o\035\023%YJ\034F/Y2l+\t\031\t\nC\004\004~\002!\tea@\002\rAD'/Y:f+\021!\t\001b\007\025\t\021\rAQ\004\t\006k\021\025A\021\004\004\b\t\017\001\021\021\001C\005\0055\001\026mY6sCR\004\026M]:feV!A1\002C\t'\021!)\001\"\004\021\tU2Eq\002\t\004K\021EAaB\024\005\006\021\025\r\001\013\005\be\021\025A\021\001C\013)\t!9\002E\0036\t\013!y\001E\002&\t7!aaJB~\005\004A\003\002CBk\007w\004\r\001b\b\021\tU2E\021\004\005\b\tG\001A\021\002C\023\003A9W\r\036)pg\032\023x.\034*fgVdG\017F\002L\tOAqa\027C\021\001\004!I\003\r\003\005,\021=\002\003B\033s\t[\0012!\nC\030\t-!\t\004b\n\002\002\003\005)\021\001\025\003\007}#3gB\005\0056\001\t\t\021#\003\0058\005IQ*Z7p\013:$(/\037\t\004k\021eb\001C)\001\003\003EI\001b\017\024\t\021eBb\026\005\be\021eB\021\001C )\t!9\004\003\006\003\024\022e\022\021!C#\005+C!\002\"\022\005:\005\005I\021\021C$\003\025\t\007\017\0357z+\021!I\005b\024\025\t\021-C\021\013\t\005kA#i\005E\002&\t\037\"aa\nC\"\005\004A\003bB.\005D\001\007A1\013\t\006=\032LGQ\013\031\005\t/\"Y\006\005\0036e\022e\003cA\023\005\\\021Y1\021\002C)\003\003\005\tQ!\001)\021)!y\006\"\017\002\002\023\005E\021M\001\bk:\f\007\017\0357z+\021!\031\007b\034\025\t\021\025Dq\r\t\005\033\005\005S\f\003\006\005j\021u\023\021!a\001\tW\n1\001\037\0231!\021)\004\013\"\034\021\007\025\"y\007\002\004(\t;\022\r\001\013\005\013\tg\"I$!A\005\n\021U\024a\003:fC\022\024Vm]8mm\026$\"\001b\036\021\t\t5C\021P\005\005\tw\022yE\001\004PE*,7\r^\004\n\t\002\021\021!E\005\t\003\013!\001\024*\021\007U\"\031I\002\005l\001\005\005\t\022\002CC'\025!\031\tb\"X!-!I\tb$\005\024\022m\025qH5\016\005\021-%b\001CG\021\0059!/\0368uS6,\027\002\002CI\t\027\023\021#\0212tiJ\f7\r\036$v]\016$\030n\03484a\021!)\n\"'\021\tU\022Hq\023\t\004K\021eEA\003<\005\004\006\005\t\021!B\001QA\"AQ\024CQ!\021)d\tb(\021\007\025\"\t\013B\006\002\034\021\r\025\021!A\001\006\003A\003b\002\032\005\004\022\005AQ\025\013\003\t\003C!Ba%\005\004\006\005IQ\tBK\021)!)\005b!\002\002\023\005E1\026\013\bS\0225Fq\027Ca\021\035qG\021\026a\001\t_\003D\001\"-\0056B!QG\035CZ!\r)CQ\027\003\013m\0225\026\021!A\001\006\003A\003\002CA\b\tS\003\r\001\"/1\t\021mFq\030\t\005k\031#i\fE\002&\t#1\"a\007\0058\006\005\t\021!B\001Q!A\0211\bCU\001\004\ty\004\003\006\005`\021\r\025\021!CA\t\013$B\001b2\005PB)Q\"!\021\005JBIQ\002b3\003\\\n5\021qH\005\004\t\033D!A\002+va2,7\007C\005\005j\021\r\027\021!a\001S\"QA1\017CB\003\003%I\001\"\036\b\023\021U\007!!A\t\n\021]\027\001\002%fC\022\0042!\016Cm\r%\tI\005AA\001\022\023!YnE\003\005Z\022uw\013\005\007\005\n\022=Eq\034Ct\tc\f)\005\r\003\005b\022\025\b\003B\033G\tG\0042!\nCs\t-\tY\006\"7\002\002\003\005)\021\001\025\021\013y\013\t\t\";1\t\021-Hq\036\t\005k\031#i\017E\002&\t_$1\"!$\005Z\006\005\t\021!B\001QA)a,!!\005tB\"AQ\037C}!\021)d\tb>\021\007\025\"I\020B\006\002@\022e\027\021!A\001\006\003A\003b\002\032\005Z\022\005AQ \013\003\t/D!Ba%\005Z\006\005IQ\tBK\021)!)\005\"7\002\002\023\005U1\001\013\t\003\013*)!b\004\006\034!A\021qJC\001\001\004)9\001\r\003\006\n\0255\001\003B\033G\013\027\0012!JC\007\t-\tY&\"\002\002\002\003\005)\021\001\025\t\021\005mT\021\001a\001\013#\001RAXAA\013'\001D!\"\006\006\032A!QGRC\f!\r)S\021\004\003\f\003\033+y!!A\001\002\013\005\001\006\003\005\0022\026\005\001\031AC\017!\025q\026\021QC\020a\021)\t#\"\n\021\tU2U1\005\t\004K\025\025BaCA`\0137\t\t\021!A\003\002!B!\002b\030\005Z\006\005I\021QC\025)\021)Y#b\017\021\0135\t\t%\"\f\021\0235!YM!\004\0060\025e\002CBC\031\013o\t))\004\002\0064)\031QQG\037\002\023%lW.\036;bE2,\027\002BAB\013g\001b!\"\r\0068\005]\006B\003C5\013O\t\t\0211\001\002F!QA1\017Cm\003\003%I\001\"\036\t\017\025\005\003\001b\001\006D\005q\001/\031:tKJ\024\004/Y2le\006$X\003BC#\013\027\"B!b\022\006NA)Q\007\"\002\006JA\031Q%b\023\005\r\035*yD1\001)\021%\031).b\020\005\002\004)y\005E\003\016\013#*)&C\002\006T!\021\001\002\0202z]\006lWM\020\t\005k\031+I\005C\004\006Z\001!I!b\027\002\rI,7-\0317m)\031)i&\"\033\006vA)Q\"!\021\006`A\"Q\021MC3!\021)\004+b\031\021\007\025*)\007B\006\006h\025]\023\021!A\001\006\003A#\001B0%cEB\001b!6\006X\001\007Q1\016\031\005\013[*\t\b\005\0036\r\026=\004cA\023\006r\021YQ1OC5\003\003\005\tQ!\001)\005\021yF%\r\031\t\021\025]Tq\013a\001\013s\n!!\0338\021\tURR1\020\t\004k\025u\024bAC@%\t!Q\t\\3n\021\035)\031\t\001C\005\013\013\013qa]3ukBd%\013F\004\030\013\017+\031*b(\t\021\rUW\021\021a\001\013\023\003D!b#\006\020B!QGRCG!\r)Sq\022\003\f\013#+9)!A\001\002\013\005\001F\001\003`IE\032\004\002CC<\013\003\003\r!\"&1\t\025]U1\024\t\005ki)I\nE\002&\0137#1\"\"(\006\024\006\005\t\021!B\001Q\t!q\fJ\0315\021\035)\t+\"!A\002%\f\021B]3d\t\026$Xm\031;\t\017\025\025\006\001\"\003\006(\006AAN]!og^,'/\006\003\006*\026=F\003CCV\013c+),b.\021\tU\022XQ\026\t\004K\025=FAB\024\006$\n\007\001\006\003\005\004V\026\r\006\031ACZ!\021)d)\",\t\021\025]T1\025a\001\013sBq!\"/\006$\002\007\021.\001\005he><\030M\0317f\021\035)i\f\001C\001\013\013A!\\3n_V!Q\021YCd)\021)\031-\"3\021\013U\")!\"2\021\007\025*9\r\002\004(\013w\023\r\001\013\005\t\007+,Y\f1\001\006LB!QGRCc\021\035)y\r\001C\005\013#\fAa\032:poV!Q1[Cm)!)).b7\006`\026\005\b\003B\033s\013/\0042!JCm\t\0319SQ\032b\001Q!A1Q[Cg\001\004)i\016\005\0036\r\026]\007\002CBX\013\033\004\r!\"\037\t\021\005mRQ\032a\001\003\013BA\"\":\001\003\003\005I\021BCt\013g\fAb];qKJ$\003\017\033:bg\026,B!\";\006pR!Q1^Cy!\021)d)\"<\021\007\025*y\017\002\004(\013G\024\r\001\013\005\t\007+,\031\0171\001\006l&\0311Q \n\t\031\025]\b!!A\001\n\023)IP\"\006\002\031M,\b/\032:%!\006\0248/\032:\026\t\025mh\021\001\013\005\013{4\031\001\005\0036\r\026}\bcA\023\007\002\0211q%\">C\002!B\001B\"\002\006v\002\007aqA\001\002MB9QB\"\003\007\016\031M\021b\001D\006\021\tIa)\0368di&|g.\r\t\004k\031=\021b\001D\t%\t)\021J\0349viB!QG]C\000\023\r19BE\001\007!\006\0248/\032:")
/*     */ public interface PackratParsers extends Parsers {
/*     */   <T> Parsers.Parser<T> scala$util$parsing$combinator$PackratParsers$$super$phrase(Parsers.Parser<T> paramParser);
/*     */   
/*     */   <T> Parsers.Parser<T> scala$util$parsing$combinator$PackratParsers$$super$Parser(Function1<Reader<Object>, Parsers.ParseResult<T>> paramFunction1);
/*     */   
/*     */   <T> PackratParser<T> phrase(Parsers.Parser<T> paramParser);
/*     */   
/*     */   MemoEntry$ scala$util$parsing$combinator$PackratParsers$$MemoEntry();
/*     */   
/*     */   LR$ scala$util$parsing$combinator$PackratParsers$$LR();
/*     */   
/*     */   Head$ scala$util$parsing$combinator$PackratParsers$$Head();
/*     */   
/*     */   <T> PackratParser<T> parser2packrat(Function0<Parsers.Parser<T>> paramFunction0);
/*     */   
/*     */   <T> PackratParser<T> memo(Parsers.Parser<T> paramParser);
/*     */   
/*     */   public class PackratReader<T> extends Reader<T> {
/*     */     public final Reader<T> scala$util$parsing$combinator$PackratParsers$PackratReader$$underlying;
/*     */     
/*  67 */     private final HashMap<Tuple2<Parsers.Parser<?>, Position>, PackratParsers.MemoEntry<?>> scala$util$parsing$combinator$PackratParsers$$cache = scala.collection.mutable.HashMap$.MODULE$.empty();
/*     */     
/*     */     public HashMap<Tuple2<Parsers.Parser<?>, Position>, PackratParsers.MemoEntry<?>> scala$util$parsing$combinator$PackratParsers$$cache() {
/*  67 */       return this.scala$util$parsing$combinator$PackratParsers$$cache;
/*     */     }
/*     */     
/*     */     public <T> Option<PackratParsers.MemoEntry<T>> scala$util$parsing$combinator$PackratParsers$$getFromCache(Parsers.Parser p) {
/*  70 */       return scala$util$parsing$combinator$PackratParsers$$cache().get(new Tuple2(p, pos()));
/*     */     }
/*     */     
/*     */     public <T> PackratParsers.MemoEntry<T> scala$util$parsing$combinator$PackratParsers$$updateCacheAndGet(Parsers.Parser p, PackratParsers.MemoEntry<T> w) {
/*  74 */       scala$util$parsing$combinator$PackratParsers$$cache().put(new Tuple2(p, pos()), w);
/*  75 */       return w;
/*     */     }
/*     */     
/*  80 */     private final HashMap<Position, PackratParsers.Head> scala$util$parsing$combinator$PackratParsers$$recursionHeads = scala.collection.mutable.HashMap$.MODULE$.empty();
/*     */     
/*     */     public HashMap<Position, PackratParsers.Head> scala$util$parsing$combinator$PackratParsers$$recursionHeads() {
/*  80 */       return this.scala$util$parsing$combinator$PackratParsers$$recursionHeads;
/*     */     }
/*     */     
/*  83 */     private List<PackratParsers.LR> scala$util$parsing$combinator$PackratParsers$$lrStack = (List<PackratParsers.LR>)scala.collection.immutable.Nil$.MODULE$;
/*     */     
/*     */     public List<PackratParsers.LR> scala$util$parsing$combinator$PackratParsers$$lrStack() {
/*  83 */       return this.scala$util$parsing$combinator$PackratParsers$$lrStack;
/*     */     }
/*     */     
/*     */     public void scala$util$parsing$combinator$PackratParsers$$lrStack_$eq(List<PackratParsers.LR> x$1) {
/*  83 */       this.scala$util$parsing$combinator$PackratParsers$$lrStack = x$1;
/*     */     }
/*     */     
/*     */     public CharSequence source() {
/*  85 */       return this.scala$util$parsing$combinator$PackratParsers$PackratReader$$underlying.source();
/*     */     }
/*     */     
/*     */     public int offset() {
/*  86 */       return this.scala$util$parsing$combinator$PackratParsers$PackratReader$$underlying.offset();
/*     */     }
/*     */     
/*     */     public T first() {
/*  88 */       return (T)this.scala$util$parsing$combinator$PackratParsers$PackratReader$$underlying.first();
/*     */     }
/*     */     
/*     */     public Reader<T> rest() {
/*  89 */       return new PackratParsers$PackratReader$$anon$3(this);
/*     */     }
/*     */     
/*     */     public class PackratParsers$PackratReader$$anon$3 extends PackratReader<T> {
/*     */       private final HashMap<Tuple2<Parsers.Parser<?>, Position>, PackratParsers.MemoEntry<?>> scala$util$parsing$combinator$PackratParsers$$cache;
/*     */       
/*     */       private final HashMap<Position, PackratParsers.Head> scala$util$parsing$combinator$PackratParsers$$recursionHeads;
/*     */       
/*     */       public PackratParsers$PackratReader$$anon$3(PackratParsers.PackratReader $outer) {
/*  89 */         super($outer.scala$util$parsing$combinator$PackratParsers$PackratReader$$$outer(), $outer.scala$util$parsing$combinator$PackratParsers$PackratReader$$underlying.rest());
/*  90 */         this.scala$util$parsing$combinator$PackratParsers$$cache = $outer.scala$util$parsing$combinator$PackratParsers$$cache();
/*  91 */         this.scala$util$parsing$combinator$PackratParsers$$recursionHeads = $outer.scala$util$parsing$combinator$PackratParsers$$recursionHeads();
/*  92 */         scala$util$parsing$combinator$PackratParsers$$lrStack_$eq($outer.scala$util$parsing$combinator$PackratParsers$$lrStack());
/*     */       }
/*     */       
/*     */       public HashMap<Tuple2<Parsers.Parser<?>, Position>, PackratParsers.MemoEntry<?>> scala$util$parsing$combinator$PackratParsers$$cache() {
/*     */         return this.scala$util$parsing$combinator$PackratParsers$$cache;
/*     */       }
/*     */       
/*     */       public HashMap<Position, PackratParsers.Head> scala$util$parsing$combinator$PackratParsers$$recursionHeads() {
/*     */         return this.scala$util$parsing$combinator$PackratParsers$$recursionHeads;
/*     */       }
/*     */     }
/*     */     
/*     */     public Position pos() {
/*  95 */       return this.scala$util$parsing$combinator$PackratParsers$PackratReader$$underlying.pos();
/*     */     }
/*     */     
/*     */     public boolean atEnd() {
/*  96 */       return this.scala$util$parsing$combinator$PackratParsers$PackratReader$$underlying.atEnd();
/*     */     }
/*     */     
/*     */     public PackratReader(PackratParsers $outer, Reader<T> underlying) {}
/*     */   }
/*     */   
/*     */   public class PackratParsers$$anon$1 extends PackratParser<T> {
/*     */     private final Parsers.Parser q$1;
/*     */     
/*     */     public PackratParsers$$anon$1(PackratParsers $outer, Parsers.Parser q$1) {
/* 107 */       super($outer);
/*     */     }
/*     */     
/*     */     public Parsers.ParseResult<T> apply(Reader<?> in) {
/*     */       Parsers.ParseResult<T> parseResult;
/* 108 */       if (in instanceof PackratParsers.PackratReader && ((PackratParsers.PackratReader)in).scala$util$parsing$combinator$PackratParsers$PackratReader$$$outer() == this.$outer) {
/* 108 */         PackratParsers.PackratReader packratReader = (PackratParsers.PackratReader)in;
/* 108 */         parseResult = this.q$1.apply(packratReader);
/*     */       } else {
/* 110 */         parseResult = this.q$1.apply(new PackratParsers.PackratReader(this.$outer, in));
/*     */       } 
/*     */       return parseResult;
/*     */     }
/*     */   }
/*     */   
/*     */   public class MemoEntry$ implements Serializable {
/*     */     public final String toString() {
/* 119 */       return "MemoEntry";
/*     */     }
/*     */     
/*     */     public <T> PackratParsers.MemoEntry<T> apply(Either<PackratParsers.LR, Parsers.ParseResult<?>> r) {
/* 119 */       return new PackratParsers.MemoEntry<T>(this.$outer, r);
/*     */     }
/*     */     
/*     */     public <T> Option<Either<PackratParsers.LR, Parsers.ParseResult<?>>> unapply(PackratParsers.MemoEntry x$0) {
/* 119 */       return (x$0 == null) ? (Option<Either<PackratParsers.LR, Parsers.ParseResult<?>>>)scala.None$.MODULE$ : (Option<Either<PackratParsers.LR, Parsers.ParseResult<?>>>)new Some(x$0.r());
/*     */     }
/*     */     
/*     */     private Object readResolve() {
/* 119 */       return this.$outer.scala$util$parsing$combinator$PackratParsers$$MemoEntry();
/*     */     }
/*     */     
/*     */     public MemoEntry$(PackratParsers $outer) {}
/*     */   }
/*     */   
/*     */   public class MemoEntry<T> implements Product, Serializable {
/*     */     private Either<PackratParsers.LR, Parsers.ParseResult<?>> r;
/*     */     
/*     */     public Either<PackratParsers.LR, Parsers.ParseResult<?>> r() {
/* 119 */       return this.r;
/*     */     }
/*     */     
/*     */     public void r_$eq(Either<PackratParsers.LR, Parsers.ParseResult<?>> x$1) {
/* 119 */       this.r = x$1;
/*     */     }
/*     */     
/*     */     public <T> MemoEntry<T> copy(Either<PackratParsers.LR, Parsers.ParseResult<?>> r) {
/* 119 */       return new MemoEntry(scala$util$parsing$combinator$PackratParsers$MemoEntry$$$outer(), r);
/*     */     }
/*     */     
/*     */     public <T> Either<PackratParsers.LR, Parsers.ParseResult<?>> copy$default$1() {
/* 119 */       return r();
/*     */     }
/*     */     
/*     */     public String productPrefix() {
/* 119 */       return "MemoEntry";
/*     */     }
/*     */     
/*     */     public int productArity() {
/* 119 */       return 1;
/*     */     }
/*     */     
/*     */     public Object productElement(int x$1) {
/* 119 */       switch (x$1) {
/*     */         default:
/* 119 */           throw new IndexOutOfBoundsException(BoxesRunTime.boxToInteger(x$1).toString());
/*     */         case 0:
/*     */           break;
/*     */       } 
/* 119 */       return r();
/*     */     }
/*     */     
/*     */     public Iterator<Object> productIterator() {
/* 119 */       return scala.runtime.ScalaRunTime$.MODULE$.typedProductIterator(this);
/*     */     }
/*     */     
/*     */     public boolean canEqual(Object x$1) {
/* 119 */       return x$1 instanceof MemoEntry;
/*     */     }
/*     */     
/*     */     public int hashCode() {
/* 119 */       return scala.runtime.ScalaRunTime$.MODULE$._hashCode(this);
/*     */     }
/*     */     
/*     */     public String toString() {
/* 119 */       return scala.runtime.ScalaRunTime$.MODULE$._toString(this);
/*     */     }
/*     */     
/*     */     public boolean equals(Object x$1) {
/*     */       // Byte code:
/*     */       //   0: aload_0
/*     */       //   1: aload_1
/*     */       //   2: if_acmpeq -> 75
/*     */       //   5: aload_1
/*     */       //   6: instanceof scala/util/parsing/combinator/PackratParsers$MemoEntry
/*     */       //   9: ifeq -> 17
/*     */       //   12: iconst_1
/*     */       //   13: istore_2
/*     */       //   14: goto -> 19
/*     */       //   17: iconst_0
/*     */       //   18: istore_2
/*     */       //   19: iload_2
/*     */       //   20: ifeq -> 79
/*     */       //   23: aload_1
/*     */       //   24: checkcast scala/util/parsing/combinator/PackratParsers$MemoEntry
/*     */       //   27: astore #4
/*     */       //   29: aload_0
/*     */       //   30: invokevirtual r : ()Lscala/util/Either;
/*     */       //   33: aload #4
/*     */       //   35: invokevirtual r : ()Lscala/util/Either;
/*     */       //   38: astore_3
/*     */       //   39: dup
/*     */       //   40: ifnonnull -> 51
/*     */       //   43: pop
/*     */       //   44: aload_3
/*     */       //   45: ifnull -> 58
/*     */       //   48: goto -> 71
/*     */       //   51: aload_3
/*     */       //   52: invokevirtual equals : (Ljava/lang/Object;)Z
/*     */       //   55: ifeq -> 71
/*     */       //   58: aload #4
/*     */       //   60: aload_0
/*     */       //   61: invokevirtual canEqual : (Ljava/lang/Object;)Z
/*     */       //   64: ifeq -> 71
/*     */       //   67: iconst_1
/*     */       //   68: goto -> 72
/*     */       //   71: iconst_0
/*     */       //   72: ifeq -> 79
/*     */       //   75: iconst_1
/*     */       //   76: goto -> 80
/*     */       //   79: iconst_0
/*     */       //   80: ireturn
/*     */       // Line number table:
/*     */       //   Java source line number -> byte code offset
/*     */       //   #119	-> 0
/*     */       //   #236	-> 12
/*     */       //   #119	-> 19
/*     */       // Local variable table:
/*     */       //   start	length	slot	name	descriptor
/*     */       //   0	81	0	this	Lscala/util/parsing/combinator/PackratParsers$MemoEntry;
/*     */       //   0	81	1	x$1	Ljava/lang/Object;
/*     */     }
/*     */     
/*     */     public MemoEntry(PackratParsers $outer, Either<PackratParsers.LR, Parsers.ParseResult<?>> r) {
/* 119 */       Product.class.$init$(this);
/*     */     }
/*     */     
/*     */     public Parsers.ParseResult<T> getResult() {
/* 120 */       Either<PackratParsers.LR, Parsers.ParseResult<?>> either = r();
/* 121 */       if (either instanceof Left) {
/* 121 */         Left left = (Left)either;
/* 121 */         if (left.a() != null)
/* 121 */           return (Parsers.ParseResult)((PackratParsers.LR)left.a()).seed(); 
/*     */       } 
/* 122 */       if (either instanceof Right) {
/* 122 */         Right right = (Right)either;
/* 122 */         Parsers.ParseResult parseResult = (Parsers.ParseResult)right.b();
/*     */       } 
/*     */       throw new MatchError(either);
/*     */     }
/*     */   }
/*     */   
/*     */   public class LR$ extends AbstractFunction3<Parsers.ParseResult<?>, Parsers.Parser<?>, Option<Head>, LR> implements Serializable {
/*     */     public final String toString() {
/* 126 */       return "LR";
/*     */     }
/*     */     
/*     */     public PackratParsers.LR apply(Parsers.ParseResult<?> seed, Parsers.Parser<?> rule, Option<PackratParsers.Head> head) {
/* 126 */       return new PackratParsers.LR(this.$outer, seed, rule, head);
/*     */     }
/*     */     
/*     */     public Option<Tuple3<Parsers.ParseResult<Object>, Parsers.Parser<Object>, Option<PackratParsers.Head>>> unapply(PackratParsers.LR x$0) {
/* 126 */       return (x$0 == null) ? (Option<Tuple3<Parsers.ParseResult<Object>, Parsers.Parser<Object>, Option<PackratParsers.Head>>>)scala.None$.MODULE$ : (Option<Tuple3<Parsers.ParseResult<Object>, Parsers.Parser<Object>, Option<PackratParsers.Head>>>)new Some(new Tuple3(x$0.seed(), x$0.rule(), x$0.head()));
/*     */     }
/*     */     
/*     */     private Object readResolve() {
/* 126 */       return this.$outer.scala$util$parsing$combinator$PackratParsers$$LR();
/*     */     }
/*     */     
/*     */     public LR$(PackratParsers $outer) {}
/*     */   }
/*     */   
/*     */   public class LR implements Product, Serializable {
/*     */     private Parsers.ParseResult<?> seed;
/*     */     
/*     */     private Parsers.Parser<?> rule;
/*     */     
/*     */     private Option<PackratParsers.Head> head;
/*     */     
/*     */     public Parsers.ParseResult<?> seed() {
/* 126 */       return this.seed;
/*     */     }
/*     */     
/*     */     public void seed_$eq(Parsers.ParseResult<?> x$1) {
/* 126 */       this.seed = x$1;
/*     */     }
/*     */     
/*     */     public Parsers.Parser<?> rule() {
/* 126 */       return this.rule;
/*     */     }
/*     */     
/*     */     public void rule_$eq(Parsers.Parser<?> x$1) {
/* 126 */       this.rule = x$1;
/*     */     }
/*     */     
/*     */     public Option<PackratParsers.Head> head() {
/* 126 */       return this.head;
/*     */     }
/*     */     
/*     */     public void head_$eq(Option<PackratParsers.Head> x$1) {
/* 126 */       this.head = x$1;
/*     */     }
/*     */     
/*     */     public LR copy(Parsers.ParseResult<?> seed, Parsers.Parser<?> rule, Option<PackratParsers.Head> head) {
/* 126 */       return new LR(scala$util$parsing$combinator$PackratParsers$LR$$$outer(), seed, rule, head);
/*     */     }
/*     */     
/*     */     public Parsers.ParseResult<Object> copy$default$1() {
/* 126 */       return (Parsers.ParseResult)seed();
/*     */     }
/*     */     
/*     */     public Parsers.Parser<Object> copy$default$2() {
/* 126 */       return (Parsers.Parser)rule();
/*     */     }
/*     */     
/*     */     public Option<PackratParsers.Head> copy$default$3() {
/* 126 */       return head();
/*     */     }
/*     */     
/*     */     public String productPrefix() {
/* 126 */       return "LR";
/*     */     }
/*     */     
/*     */     public int productArity() {
/* 126 */       return 3;
/*     */     }
/*     */     
/*     */     public Object productElement(int x$1) {
/* 126 */       switch (x$1) {
/*     */         default:
/* 126 */           throw new IndexOutOfBoundsException(BoxesRunTime.boxToInteger(x$1).toString());
/*     */         case 2:
/*     */         
/*     */         case 1:
/*     */         
/*     */         case 0:
/*     */           break;
/*     */       } 
/* 126 */       return seed();
/*     */     }
/*     */     
/*     */     public Iterator<Object> productIterator() {
/* 126 */       return scala.runtime.ScalaRunTime$.MODULE$.typedProductIterator(this);
/*     */     }
/*     */     
/*     */     public boolean canEqual(Object x$1) {
/* 126 */       return x$1 instanceof LR;
/*     */     }
/*     */     
/*     */     public int hashCode() {
/* 126 */       return scala.runtime.ScalaRunTime$.MODULE$._hashCode(this);
/*     */     }
/*     */     
/*     */     public String toString() {
/* 126 */       return scala.runtime.ScalaRunTime$.MODULE$._toString(this);
/*     */     }
/*     */     
/*     */     public boolean equals(Object x$1) {
/*     */       // Byte code:
/*     */       //   0: aload_0
/*     */       //   1: aload_1
/*     */       //   2: if_acmpeq -> 139
/*     */       //   5: aload_1
/*     */       //   6: instanceof scala/util/parsing/combinator/PackratParsers$LR
/*     */       //   9: ifeq -> 17
/*     */       //   12: iconst_1
/*     */       //   13: istore_2
/*     */       //   14: goto -> 19
/*     */       //   17: iconst_0
/*     */       //   18: istore_2
/*     */       //   19: iload_2
/*     */       //   20: ifeq -> 143
/*     */       //   23: aload_1
/*     */       //   24: checkcast scala/util/parsing/combinator/PackratParsers$LR
/*     */       //   27: astore #6
/*     */       //   29: aload_0
/*     */       //   30: invokevirtual seed : ()Lscala/util/parsing/combinator/Parsers$ParseResult;
/*     */       //   33: aload #6
/*     */       //   35: invokevirtual seed : ()Lscala/util/parsing/combinator/Parsers$ParseResult;
/*     */       //   38: astore_3
/*     */       //   39: dup
/*     */       //   40: ifnonnull -> 51
/*     */       //   43: pop
/*     */       //   44: aload_3
/*     */       //   45: ifnull -> 58
/*     */       //   48: goto -> 135
/*     */       //   51: aload_3
/*     */       //   52: invokevirtual equals : (Ljava/lang/Object;)Z
/*     */       //   55: ifeq -> 135
/*     */       //   58: aload_0
/*     */       //   59: invokevirtual rule : ()Lscala/util/parsing/combinator/Parsers$Parser;
/*     */       //   62: aload #6
/*     */       //   64: invokevirtual rule : ()Lscala/util/parsing/combinator/Parsers$Parser;
/*     */       //   67: astore #4
/*     */       //   69: dup
/*     */       //   70: ifnonnull -> 82
/*     */       //   73: pop
/*     */       //   74: aload #4
/*     */       //   76: ifnull -> 90
/*     */       //   79: goto -> 135
/*     */       //   82: aload #4
/*     */       //   84: invokevirtual equals : (Ljava/lang/Object;)Z
/*     */       //   87: ifeq -> 135
/*     */       //   90: aload_0
/*     */       //   91: invokevirtual head : ()Lscala/Option;
/*     */       //   94: aload #6
/*     */       //   96: invokevirtual head : ()Lscala/Option;
/*     */       //   99: astore #5
/*     */       //   101: dup
/*     */       //   102: ifnonnull -> 114
/*     */       //   105: pop
/*     */       //   106: aload #5
/*     */       //   108: ifnull -> 122
/*     */       //   111: goto -> 135
/*     */       //   114: aload #5
/*     */       //   116: invokevirtual equals : (Ljava/lang/Object;)Z
/*     */       //   119: ifeq -> 135
/*     */       //   122: aload #6
/*     */       //   124: aload_0
/*     */       //   125: invokevirtual canEqual : (Ljava/lang/Object;)Z
/*     */       //   128: ifeq -> 135
/*     */       //   131: iconst_1
/*     */       //   132: goto -> 136
/*     */       //   135: iconst_0
/*     */       //   136: ifeq -> 143
/*     */       //   139: iconst_1
/*     */       //   140: goto -> 144
/*     */       //   143: iconst_0
/*     */       //   144: ireturn
/*     */       // Line number table:
/*     */       //   Java source line number -> byte code offset
/*     */       //   #126	-> 0
/*     */       //   #236	-> 12
/*     */       //   #126	-> 19
/*     */       // Local variable table:
/*     */       //   start	length	slot	name	descriptor
/*     */       //   0	145	0	this	Lscala/util/parsing/combinator/PackratParsers$LR;
/*     */       //   0	145	1	x$1	Ljava/lang/Object;
/*     */     }
/*     */     
/*     */     public LR(PackratParsers $outer, Parsers.ParseResult<?> seed, Parsers.Parser<?> rule, Option<PackratParsers.Head> head) {
/* 126 */       Product.class.$init$(this);
/*     */     }
/*     */     
/*     */     public Position getPos() {
/* 127 */       return PackratParsers$class.scala$util$parsing$combinator$PackratParsers$$getPosFromResult(scala$util$parsing$combinator$PackratParsers$LR$$$outer(), seed());
/*     */     }
/*     */   }
/*     */   
/*     */   public class Head$ extends AbstractFunction3<Parsers.Parser<?>, List<Parsers.Parser<?>>, List<Parsers.Parser<?>>, Head> implements Serializable {
/*     */     public final String toString() {
/* 130 */       return "Head";
/*     */     }
/*     */     
/*     */     public PackratParsers.Head apply(Parsers.Parser<?> headParser, List<Parsers.Parser<?>> involvedSet, List<Parsers.Parser<?>> evalSet) {
/* 130 */       return new PackratParsers.Head(this.$outer, headParser, involvedSet, evalSet);
/*     */     }
/*     */     
/*     */     public Option<Tuple3<Parsers.Parser<Object>, List<Parsers.Parser<?>>, List<Parsers.Parser<?>>>> unapply(PackratParsers.Head x$0) {
/* 130 */       return (x$0 == null) ? (Option<Tuple3<Parsers.Parser<Object>, List<Parsers.Parser<?>>, List<Parsers.Parser<?>>>>)scala.None$.MODULE$ : (Option<Tuple3<Parsers.Parser<Object>, List<Parsers.Parser<?>>, List<Parsers.Parser<?>>>>)new Some(new Tuple3(x$0.headParser(), x$0.involvedSet(), x$0.evalSet()));
/*     */     }
/*     */     
/*     */     private Object readResolve() {
/* 130 */       return this.$outer.scala$util$parsing$combinator$PackratParsers$$Head();
/*     */     }
/*     */     
/*     */     public Head$(PackratParsers $outer) {}
/*     */   }
/*     */   
/*     */   public class Head implements Product, Serializable {
/*     */     private Parsers.Parser<?> headParser;
/*     */     
/*     */     private List<Parsers.Parser<?>> involvedSet;
/*     */     
/*     */     private List<Parsers.Parser<?>> evalSet;
/*     */     
/*     */     public Parsers.Parser<?> headParser() {
/* 130 */       return this.headParser;
/*     */     }
/*     */     
/*     */     public void headParser_$eq(Parsers.Parser<?> x$1) {
/* 130 */       this.headParser = x$1;
/*     */     }
/*     */     
/*     */     public List<Parsers.Parser<?>> involvedSet() {
/* 130 */       return this.involvedSet;
/*     */     }
/*     */     
/*     */     public void involvedSet_$eq(List<Parsers.Parser<?>> x$1) {
/* 130 */       this.involvedSet = x$1;
/*     */     }
/*     */     
/*     */     public List<Parsers.Parser<?>> evalSet() {
/* 130 */       return this.evalSet;
/*     */     }
/*     */     
/*     */     public void evalSet_$eq(List<Parsers.Parser<?>> x$1) {
/* 130 */       this.evalSet = x$1;
/*     */     }
/*     */     
/*     */     public Head copy(Parsers.Parser<?> headParser, List<Parsers.Parser<?>> involvedSet, List<Parsers.Parser<?>> evalSet) {
/* 130 */       return new Head(scala$util$parsing$combinator$PackratParsers$Head$$$outer(), headParser, involvedSet, evalSet);
/*     */     }
/*     */     
/*     */     public Parsers.Parser<Object> copy$default$1() {
/* 130 */       return (Parsers.Parser)headParser();
/*     */     }
/*     */     
/*     */     public List<Parsers.Parser<?>> copy$default$2() {
/* 130 */       return involvedSet();
/*     */     }
/*     */     
/*     */     public List<Parsers.Parser<?>> copy$default$3() {
/* 130 */       return evalSet();
/*     */     }
/*     */     
/*     */     public String productPrefix() {
/* 130 */       return "Head";
/*     */     }
/*     */     
/*     */     public int productArity() {
/* 130 */       return 3;
/*     */     }
/*     */     
/*     */     public Object productElement(int x$1) {
/* 130 */       switch (x$1) {
/*     */         default:
/* 130 */           throw new IndexOutOfBoundsException(BoxesRunTime.boxToInteger(x$1).toString());
/*     */         case 2:
/*     */         
/*     */         case 1:
/*     */         
/*     */         case 0:
/*     */           break;
/*     */       } 
/* 130 */       return headParser();
/*     */     }
/*     */     
/*     */     public Iterator<Object> productIterator() {
/* 130 */       return scala.runtime.ScalaRunTime$.MODULE$.typedProductIterator(this);
/*     */     }
/*     */     
/*     */     public boolean canEqual(Object x$1) {
/* 130 */       return x$1 instanceof Head;
/*     */     }
/*     */     
/*     */     public int hashCode() {
/* 130 */       return scala.runtime.ScalaRunTime$.MODULE$._hashCode(this);
/*     */     }
/*     */     
/*     */     public String toString() {
/* 130 */       return scala.runtime.ScalaRunTime$.MODULE$._toString(this);
/*     */     }
/*     */     
/*     */     public boolean equals(Object x$1) {
/*     */       // Byte code:
/*     */       //   0: aload_0
/*     */       //   1: aload_1
/*     */       //   2: if_acmpeq -> 139
/*     */       //   5: aload_1
/*     */       //   6: instanceof scala/util/parsing/combinator/PackratParsers$Head
/*     */       //   9: ifeq -> 17
/*     */       //   12: iconst_1
/*     */       //   13: istore_2
/*     */       //   14: goto -> 19
/*     */       //   17: iconst_0
/*     */       //   18: istore_2
/*     */       //   19: iload_2
/*     */       //   20: ifeq -> 143
/*     */       //   23: aload_1
/*     */       //   24: checkcast scala/util/parsing/combinator/PackratParsers$Head
/*     */       //   27: astore #6
/*     */       //   29: aload_0
/*     */       //   30: invokevirtual headParser : ()Lscala/util/parsing/combinator/Parsers$Parser;
/*     */       //   33: aload #6
/*     */       //   35: invokevirtual headParser : ()Lscala/util/parsing/combinator/Parsers$Parser;
/*     */       //   38: astore_3
/*     */       //   39: dup
/*     */       //   40: ifnonnull -> 51
/*     */       //   43: pop
/*     */       //   44: aload_3
/*     */       //   45: ifnull -> 58
/*     */       //   48: goto -> 135
/*     */       //   51: aload_3
/*     */       //   52: invokevirtual equals : (Ljava/lang/Object;)Z
/*     */       //   55: ifeq -> 135
/*     */       //   58: aload_0
/*     */       //   59: invokevirtual involvedSet : ()Lscala/collection/immutable/List;
/*     */       //   62: aload #6
/*     */       //   64: invokevirtual involvedSet : ()Lscala/collection/immutable/List;
/*     */       //   67: astore #4
/*     */       //   69: dup
/*     */       //   70: ifnonnull -> 82
/*     */       //   73: pop
/*     */       //   74: aload #4
/*     */       //   76: ifnull -> 90
/*     */       //   79: goto -> 135
/*     */       //   82: aload #4
/*     */       //   84: invokevirtual equals : (Ljava/lang/Object;)Z
/*     */       //   87: ifeq -> 135
/*     */       //   90: aload_0
/*     */       //   91: invokevirtual evalSet : ()Lscala/collection/immutable/List;
/*     */       //   94: aload #6
/*     */       //   96: invokevirtual evalSet : ()Lscala/collection/immutable/List;
/*     */       //   99: astore #5
/*     */       //   101: dup
/*     */       //   102: ifnonnull -> 114
/*     */       //   105: pop
/*     */       //   106: aload #5
/*     */       //   108: ifnull -> 122
/*     */       //   111: goto -> 135
/*     */       //   114: aload #5
/*     */       //   116: invokevirtual equals : (Ljava/lang/Object;)Z
/*     */       //   119: ifeq -> 135
/*     */       //   122: aload #6
/*     */       //   124: aload_0
/*     */       //   125: invokevirtual canEqual : (Ljava/lang/Object;)Z
/*     */       //   128: ifeq -> 135
/*     */       //   131: iconst_1
/*     */       //   132: goto -> 136
/*     */       //   135: iconst_0
/*     */       //   136: ifeq -> 143
/*     */       //   139: iconst_1
/*     */       //   140: goto -> 144
/*     */       //   143: iconst_0
/*     */       //   144: ireturn
/*     */       // Line number table:
/*     */       //   Java source line number -> byte code offset
/*     */       //   #130	-> 0
/*     */       //   #236	-> 12
/*     */       //   #130	-> 19
/*     */       // Local variable table:
/*     */       //   start	length	slot	name	descriptor
/*     */       //   0	145	0	this	Lscala/util/parsing/combinator/PackratParsers$Head;
/*     */       //   0	145	1	x$1	Ljava/lang/Object;
/*     */     }
/*     */     
/*     */     public Head(PackratParsers $outer, Parsers.Parser<?> headParser, List<Parsers.Parser<?>> involvedSet, List<Parsers.Parser<?>> evalSet) {
/* 130 */       Product.class.$init$(this);
/*     */     }
/*     */     
/*     */     public Parsers.Parser<Object> getHead() {
/* 131 */       return (Parsers.Parser)headParser();
/*     */     }
/*     */   }
/*     */   
/*     */   public abstract class PackratParser<T> extends Parsers.Parser<T> {
/*     */     public PackratParser(PackratParsers $outer) {
/* 137 */       super($outer);
/*     */     }
/*     */   }
/*     */   
/*     */   public class PackratParsers$$anonfun$parser2packrat$1 extends AbstractFunction1<Reader<Object>, Parsers.ParseResult<T>> implements Serializable {
/*     */     public static final long serialVersionUID = 0L;
/*     */     
/*     */     private final ObjectRef q$lzy$1;
/*     */     
/*     */     private final Function0 p$3;
/*     */     
/*     */     private final VolatileByteRef bitmap$0$1;
/*     */     
/*     */     public final Parsers.ParseResult<T> apply(Reader in) {
/* 147 */       return PackratParsers$class.q$2(this.$outer, this.q$lzy$1, this.p$3, this.bitmap$0$1).apply(in);
/*     */     }
/*     */     
/*     */     public PackratParsers$$anonfun$parser2packrat$1(PackratParsers $outer, ObjectRef q$lzy$1, Function0 p$3, VolatileByteRef bitmap$0$1) {}
/*     */   }
/*     */   
/*     */   public class PackratParsers$$anonfun$scala$util$parsing$combinator$PackratParsers$$recall$1 extends AbstractFunction1<Parsers.Parser<?>, Object> implements Serializable {
/*     */     public static final long serialVersionUID = 0L;
/*     */     
/*     */     private final Parsers.Parser p$1;
/*     */     
/*     */     public final boolean apply(Parsers.Parser x$2) {
/* 171 */       Parsers.Parser parser = this.p$1;
/* 171 */       if (x$2 == null) {
/* 171 */         if (parser != null);
/* 171 */       } else if (x$2.equals(parser)) {
/*     */       
/*     */       } 
/*     */     }
/*     */     
/*     */     public PackratParsers$$anonfun$scala$util$parsing$combinator$PackratParsers$$recall$1(PackratParsers $outer, Parsers.Parser p$1) {}
/*     */   }
/*     */   
/*     */   public class PackratParsers$$anonfun$scala$util$parsing$combinator$PackratParsers$$setupLR$1 extends AbstractFunction1<LR, Object> implements Serializable {
/*     */     public static final long serialVersionUID = 0L;
/*     */     
/*     */     private final Parsers.Parser p$2;
/*     */     
/*     */     public final boolean apply(PackratParsers.LR x$3) {
/* 191 */       Parsers.Parser parser = this.p$2;
/* 191 */       if (x$3.rule() == null) {
/* 191 */         x$3.rule();
/* 191 */         if (parser != null);
/* 191 */       } else if (x$3.rule().equals(parser)) {
/*     */       
/*     */       } 
/*     */     }
/*     */     
/*     */     public PackratParsers$$anonfun$scala$util$parsing$combinator$PackratParsers$$setupLR$1(PackratParsers $outer, Parsers.Parser p$2) {}
/*     */   }
/*     */   
/*     */   public class PackratParsers$$anon$2 extends PackratParser<T> {
/*     */     private final Parsers.Parser p$4;
/*     */     
/*     */     public PackratParsers$$anon$2(PackratParsers $outer, Parsers.Parser p$4) {
/* 234 */       super($outer);
/*     */     }
/*     */     
/*     */     public Parsers.ParseResult<T> apply(Reader in) {
/*     */       // Byte code:
/*     */       //   0: aload_1
/*     */       //   1: checkcast scala/util/parsing/combinator/PackratParsers$PackratReader
/*     */       //   4: astore #8
/*     */       //   6: aload_0
/*     */       //   7: getfield $outer : Lscala/util/parsing/combinator/PackratParsers;
/*     */       //   10: aload_0
/*     */       //   11: getfield p$4 : Lscala/util/parsing/combinator/Parsers$Parser;
/*     */       //   14: aload #8
/*     */       //   16: invokestatic scala$util$parsing$combinator$PackratParsers$$recall : (Lscala/util/parsing/combinator/PackratParsers;Lscala/util/parsing/combinator/Parsers$Parser;Lscala/util/parsing/combinator/PackratParsers$PackratReader;)Lscala/Option;
/*     */       //   19: astore #16
/*     */       //   21: getstatic scala/None$.MODULE$ : Lscala/None$;
/*     */       //   24: dup
/*     */       //   25: ifnonnull -> 37
/*     */       //   28: pop
/*     */       //   29: aload #16
/*     */       //   31: ifnull -> 45
/*     */       //   34: goto -> 265
/*     */       //   37: aload #16
/*     */       //   39: invokevirtual equals : (Ljava/lang/Object;)Z
/*     */       //   42: ifeq -> 265
/*     */       //   45: new scala/util/parsing/combinator/PackratParsers$LR
/*     */       //   48: dup
/*     */       //   49: aload_0
/*     */       //   50: getfield $outer : Lscala/util/parsing/combinator/PackratParsers;
/*     */       //   53: new scala/util/parsing/combinator/Parsers$Failure
/*     */       //   56: dup
/*     */       //   57: aload_0
/*     */       //   58: getfield $outer : Lscala/util/parsing/combinator/PackratParsers;
/*     */       //   61: ldc 'Base Failure'
/*     */       //   63: aload_1
/*     */       //   64: invokespecial <init> : (Lscala/util/parsing/combinator/Parsers;Ljava/lang/String;Lscala/util/parsing/input/Reader;)V
/*     */       //   67: aload_0
/*     */       //   68: getfield p$4 : Lscala/util/parsing/combinator/Parsers$Parser;
/*     */       //   71: getstatic scala/None$.MODULE$ : Lscala/None$;
/*     */       //   74: invokespecial <init> : (Lscala/util/parsing/combinator/PackratParsers;Lscala/util/parsing/combinator/Parsers$ParseResult;Lscala/util/parsing/combinator/Parsers$Parser;Lscala/Option;)V
/*     */       //   77: astore_3
/*     */       //   78: aload #8
/*     */       //   80: aload #8
/*     */       //   82: invokevirtual scala$util$parsing$combinator$PackratParsers$$lrStack : ()Lscala/collection/immutable/List;
/*     */       //   85: aload_3
/*     */       //   86: invokevirtual $colon$colon : (Ljava/lang/Object;)Lscala/collection/immutable/List;
/*     */       //   89: invokevirtual scala$util$parsing$combinator$PackratParsers$$lrStack_$eq : (Lscala/collection/immutable/List;)V
/*     */       //   92: aload #8
/*     */       //   94: aload_0
/*     */       //   95: getfield p$4 : Lscala/util/parsing/combinator/Parsers$Parser;
/*     */       //   98: new scala/util/parsing/combinator/PackratParsers$MemoEntry
/*     */       //   101: dup
/*     */       //   102: aload_0
/*     */       //   103: getfield $outer : Lscala/util/parsing/combinator/PackratParsers;
/*     */       //   106: getstatic scala/package$.MODULE$ : Lscala/package$;
/*     */       //   109: invokevirtual Left : ()Lscala/util/Left$;
/*     */       //   112: aload_3
/*     */       //   113: invokevirtual apply : (Ljava/lang/Object;)Lscala/util/Left;
/*     */       //   116: invokespecial <init> : (Lscala/util/parsing/combinator/PackratParsers;Lscala/util/Either;)V
/*     */       //   119: invokevirtual scala$util$parsing$combinator$PackratParsers$$updateCacheAndGet : (Lscala/util/parsing/combinator/Parsers$Parser;Lscala/util/parsing/combinator/PackratParsers$MemoEntry;)Lscala/util/parsing/combinator/PackratParsers$MemoEntry;
/*     */       //   122: pop
/*     */       //   123: aload_0
/*     */       //   124: getfield p$4 : Lscala/util/parsing/combinator/Parsers$Parser;
/*     */       //   127: aload_1
/*     */       //   128: invokevirtual apply : (Lscala/util/parsing/input/Reader;)Lscala/util/parsing/combinator/Parsers$ParseResult;
/*     */       //   131: astore_2
/*     */       //   132: aload #8
/*     */       //   134: aload #8
/*     */       //   136: invokevirtual scala$util$parsing$combinator$PackratParsers$$lrStack : ()Lscala/collection/immutable/List;
/*     */       //   139: invokevirtual tail : ()Ljava/lang/Object;
/*     */       //   142: checkcast scala/collection/immutable/List
/*     */       //   145: invokevirtual scala$util$parsing$combinator$PackratParsers$$lrStack_$eq : (Lscala/collection/immutable/List;)V
/*     */       //   148: aload_3
/*     */       //   149: invokevirtual head : ()Lscala/Option;
/*     */       //   152: astore #6
/*     */       //   154: getstatic scala/None$.MODULE$ : Lscala/None$;
/*     */       //   157: dup
/*     */       //   158: ifnonnull -> 170
/*     */       //   161: pop
/*     */       //   162: aload #6
/*     */       //   164: ifnull -> 178
/*     */       //   167: goto -> 215
/*     */       //   170: aload #6
/*     */       //   172: invokevirtual equals : (Ljava/lang/Object;)Z
/*     */       //   175: ifeq -> 215
/*     */       //   178: aload #8
/*     */       //   180: aload_0
/*     */       //   181: getfield p$4 : Lscala/util/parsing/combinator/Parsers$Parser;
/*     */       //   184: new scala/util/parsing/combinator/PackratParsers$MemoEntry
/*     */       //   187: dup
/*     */       //   188: aload_0
/*     */       //   189: getfield $outer : Lscala/util/parsing/combinator/PackratParsers;
/*     */       //   192: getstatic scala/package$.MODULE$ : Lscala/package$;
/*     */       //   195: invokevirtual Right : ()Lscala/util/Right$;
/*     */       //   198: aload_2
/*     */       //   199: invokevirtual apply : (Ljava/lang/Object;)Lscala/util/Right;
/*     */       //   202: invokespecial <init> : (Lscala/util/parsing/combinator/PackratParsers;Lscala/util/Either;)V
/*     */       //   205: invokevirtual scala$util$parsing$combinator$PackratParsers$$updateCacheAndGet : (Lscala/util/parsing/combinator/Parsers$Parser;Lscala/util/parsing/combinator/PackratParsers$MemoEntry;)Lscala/util/parsing/combinator/PackratParsers$MemoEntry;
/*     */       //   208: pop
/*     */       //   209: aload_2
/*     */       //   210: astore #5
/*     */       //   212: goto -> 248
/*     */       //   215: aload #6
/*     */       //   217: instanceof scala/Some
/*     */       //   220: ifeq -> 255
/*     */       //   223: aload_3
/*     */       //   224: aload_2
/*     */       //   225: invokevirtual seed_$eq : (Lscala/util/parsing/combinator/Parsers$ParseResult;)V
/*     */       //   228: aload_0
/*     */       //   229: getfield $outer : Lscala/util/parsing/combinator/PackratParsers;
/*     */       //   232: aload_0
/*     */       //   233: getfield p$4 : Lscala/util/parsing/combinator/Parsers$Parser;
/*     */       //   236: aload #8
/*     */       //   238: aload_3
/*     */       //   239: invokestatic scala$util$parsing$combinator$PackratParsers$$lrAnswer : (Lscala/util/parsing/combinator/PackratParsers;Lscala/util/parsing/combinator/Parsers$Parser;Lscala/util/parsing/combinator/PackratParsers$PackratReader;Lscala/util/parsing/combinator/PackratParsers$LR;)Lscala/util/parsing/combinator/Parsers$ParseResult;
/*     */       //   242: astore #4
/*     */       //   244: aload #4
/*     */       //   246: astore #5
/*     */       //   248: aload #5
/*     */       //   250: astore #14
/*     */       //   252: goto -> 427
/*     */       //   255: new scala/MatchError
/*     */       //   258: dup
/*     */       //   259: aload #6
/*     */       //   261: invokespecial <init> : (Ljava/lang/Object;)V
/*     */       //   264: athrow
/*     */       //   265: aload #16
/*     */       //   267: instanceof scala/Some
/*     */       //   270: ifeq -> 440
/*     */       //   273: aload #16
/*     */       //   275: checkcast scala/Some
/*     */       //   278: astore #7
/*     */       //   280: aload #7
/*     */       //   282: invokevirtual x : ()Ljava/lang/Object;
/*     */       //   285: checkcast scala/util/parsing/combinator/PackratParsers$MemoEntry
/*     */       //   288: astore #15
/*     */       //   290: aload #15
/*     */       //   292: ifnull -> 372
/*     */       //   295: aload #15
/*     */       //   297: invokevirtual r : ()Lscala/util/Either;
/*     */       //   300: instanceof scala/util/Left
/*     */       //   303: ifeq -> 372
/*     */       //   306: aload #15
/*     */       //   308: invokevirtual r : ()Lscala/util/Either;
/*     */       //   311: checkcast scala/util/Left
/*     */       //   314: astore #9
/*     */       //   316: aload_0
/*     */       //   317: getfield $outer : Lscala/util/parsing/combinator/PackratParsers;
/*     */       //   320: aload_0
/*     */       //   321: getfield p$4 : Lscala/util/parsing/combinator/Parsers$Parser;
/*     */       //   324: aload #8
/*     */       //   326: aload #9
/*     */       //   328: invokevirtual a : ()Ljava/lang/Object;
/*     */       //   331: checkcast scala/util/parsing/combinator/PackratParsers$LR
/*     */       //   334: invokestatic scala$util$parsing$combinator$PackratParsers$$setupLR : (Lscala/util/parsing/combinator/PackratParsers;Lscala/util/parsing/combinator/Parsers$Parser;Lscala/util/parsing/combinator/PackratParsers$PackratReader;Lscala/util/parsing/combinator/PackratParsers$LR;)V
/*     */       //   337: aload #9
/*     */       //   339: invokevirtual a : ()Ljava/lang/Object;
/*     */       //   342: checkcast scala/util/parsing/combinator/PackratParsers$LR
/*     */       //   345: astore #10
/*     */       //   347: aload #10
/*     */       //   349: ifnull -> 362
/*     */       //   352: aload #10
/*     */       //   354: invokevirtual seed : ()Lscala/util/parsing/combinator/Parsers$ParseResult;
/*     */       //   357: astore #13
/*     */       //   359: goto -> 423
/*     */       //   362: new scala/MatchError
/*     */       //   365: dup
/*     */       //   366: aload #10
/*     */       //   368: invokespecial <init> : (Ljava/lang/Object;)V
/*     */       //   371: athrow
/*     */       //   372: aload #15
/*     */       //   374: ifnull -> 430
/*     */       //   377: aload #15
/*     */       //   379: invokevirtual r : ()Lscala/util/Either;
/*     */       //   382: instanceof scala/util/Right
/*     */       //   385: ifeq -> 430
/*     */       //   388: aload #15
/*     */       //   390: invokevirtual r : ()Lscala/util/Either;
/*     */       //   393: checkcast scala/util/Right
/*     */       //   396: astore #11
/*     */       //   398: aload #11
/*     */       //   400: invokevirtual b : ()Ljava/lang/Object;
/*     */       //   403: instanceof scala/util/parsing/combinator/Parsers$ParseResult
/*     */       //   406: ifeq -> 430
/*     */       //   409: aload #11
/*     */       //   411: invokevirtual b : ()Ljava/lang/Object;
/*     */       //   414: checkcast scala/util/parsing/combinator/Parsers$ParseResult
/*     */       //   417: astore #12
/*     */       //   419: aload #12
/*     */       //   421: astore #13
/*     */       //   423: aload #13
/*     */       //   425: astore #14
/*     */       //   427: aload #14
/*     */       //   429: areturn
/*     */       //   430: new scala/MatchError
/*     */       //   433: dup
/*     */       //   434: aload #15
/*     */       //   436: invokespecial <init> : (Ljava/lang/Object;)V
/*     */       //   439: athrow
/*     */       //   440: new scala/MatchError
/*     */       //   443: dup
/*     */       //   444: aload #16
/*     */       //   446: invokespecial <init> : (Ljava/lang/Object;)V
/*     */       //   449: athrow
/*     */       // Line number table:
/*     */       //   Java source line number -> byte code offset
/*     */       //   #239	-> 0
/*     */       //   #242	-> 6
/*     */       //   #245	-> 21
/*     */       //   #243	-> 21
/*     */       //   #246	-> 45
/*     */       //   #247	-> 78
/*     */       //   #249	-> 92
/*     */       //   #251	-> 123
/*     */       //   #253	-> 132
/*     */       //   #255	-> 148
/*     */       //   #256	-> 154
/*     */       //   #258	-> 178
/*     */       //   #259	-> 209
/*     */       //   #256	-> 210
/*     */       //   #260	-> 215
/*     */       //   #262	-> 223
/*     */       //   #264	-> 228
/*     */       //   #265	-> 244
/*     */       //   #260	-> 246
/*     */       //   #255	-> 248
/*     */       //   #245	-> 250
/*     */       //   #255	-> 255
/*     */       //   #268	-> 265
/*     */       //   #243	-> 280
/*     */       //   #270	-> 282
/*     */       //   #271	-> 297
/*     */       //   #270	-> 306
/*     */       //   #271	-> 308
/*     */       //   #272	-> 316
/*     */       //   #270	-> 326
/*     */       //   #272	-> 328
/*     */       //   #270	-> 337
/*     */       //   #274	-> 339
/*     */       //   #271	-> 357
/*     */       //   #274	-> 362
/*     */       //   #270	-> 372
/*     */       //   #276	-> 379
/*     */       //   #270	-> 388
/*     */       //   #276	-> 390
/*     */       //   #270	-> 398
/*     */       //   #276	-> 400
/*     */       //   #270	-> 409
/*     */       //   #276	-> 411
/*     */       //   #270	-> 423
/*     */       //   #243	-> 427
/*     */       //   #270	-> 430
/*     */       //   #243	-> 440
/*     */       // Local variable table:
/*     */       //   start	length	slot	name	descriptor
/*     */       //   0	450	0	this	Lscala/util/parsing/combinator/PackratParsers$$anon$2;
/*     */       //   0	450	1	in	Lscala/util/parsing/input/Reader;
/*     */       //   6	423	8	inMem	Lscala/util/parsing/combinator/PackratParsers$PackratReader;
/*     */       //   21	408	16	m	Lscala/Option;
/*     */       //   78	172	3	base	Lscala/util/parsing/combinator/PackratParsers$LR;
/*     */       //   132	118	2	tempRes	Lscala/util/parsing/combinator/Parsers$ParseResult;
/*     */       //   244	2	4	res	Lscala/util/parsing/combinator/Parsers$ParseResult;
/*     */     }
/*     */   }
/*     */ }


/* Location:              D:\#source-code\TheFlightSims\TFSLibrary\World2Xplane\World2XPlane.jar!\scal\\util\parsing\combinator\PackratParsers.class
 * Java compiler version: 6 (50.0)
 * JD-Core Version:       1.1.3
 */