/*     */ package scala.util.parsing.combinator;
/*     */ 
/*     */ import scala.Function0;
/*     */ import scala.Function1;
/*     */ import scala.Function2;
/*     */ import scala.MatchError;
/*     */ import scala.Option;
/*     */ import scala.PartialFunction;
/*     */ import scala.Product;
/*     */ import scala.Serializable;
/*     */ import scala.Some;
/*     */ import scala.Tuple2;
/*     */ import scala.collection.Iterable;
/*     */ import scala.collection.Iterator;
/*     */ import scala.collection.LinearSeqOptimized;
/*     */ import scala.collection.immutable.List;
/*     */ import scala.collection.mutable.ListBuffer;
/*     */ import scala.collection.mutable.StringBuilder;
/*     */ import scala.reflect.ScalaSignature;
/*     */ import scala.runtime.AbstractFunction0;
/*     */ import scala.runtime.AbstractFunction1;
/*     */ import scala.runtime.AbstractFunction2;
/*     */ import scala.runtime.BoxedUnit;
/*     */ import scala.runtime.BoxesRunTime;
/*     */ import scala.runtime.ObjectRef;
/*     */ import scala.runtime.VolatileByteRef;
/*     */ import scala.util.DynamicVariable;
/*     */ import scala.util.parsing.input.Reader;
/*     */ 
/*     */ @ScalaSignature(bytes = "\006\001%\reaB\001\003!\003\r\ta\003\002\b!\006\0248/\032:t\025\t\031A!\001\006d_6\024\027N\\1u_JT!!\002\004\002\017A\f'o]5oO*\021q\001C\001\005kRLGNC\001\n\003\025\0318-\0317b\007\001\031\"\001\001\007\021\0055qQ\"\001\005\n\005=A!AB!osJ+g\rC\003\022\001\021\005!#\001\004%S:LG\017\n\013\002'A\021Q\002F\005\003+!\021A!\0268ji\022)q\003\001B\0011\t!Q\t\\3n#\tIB\004\005\002\0165%\0211\004\003\002\b\035>$\b.\0338h!\tiQ$\003\002\037\021\t\031\021I\\=\006\t\001\002\001!\t\002\006\023:\004X\017\036\t\004E\025:S\"A\022\013\005\021\"\021!B5oaV$\030B\001\024$\005\031\021V-\0313feB\021\001FF\007\002\001\031)!\006AA\021W\tY\001+\031:tKJ+7/\0367u+\ta3g\005\002*\031!)a&\013C\001_\0051A(\0338jiz\"\022\001\r\t\004Q%\n\004C\001\0324\031\001!a\001N\025\005\006\004A\"!\001+\t\013YJc\021A\034\002\0075\f\007/\006\0029wQ\021\021(\020\t\004Q%R\004C\001\032<\t\025aTG1\001\031\005\005)\006\"\002 6\001\004y\024!\0014\021\t5\001\025GO\005\003\003\"\021\021BR;oGRLwN\\\031\t\013\rKc\021\001#\002\0255\f\007\017U1si&\fG.\006\002F\021R\031a)S'\021\007!Js\t\005\0023\021\022)AH\021b\0011!)aH\021a\001\025B!QbS\031H\023\ta\005BA\bQCJ$\030.\0317Gk:\034G/[8o\021\025q%\t1\001P\003\025)'O]8s!\021i\001)\r)\021\005E#fBA\007S\023\t\031\006\"\001\004Qe\026$WMZ\005\003+Z\023aa\025;sS:<'BA*\t\021\025A\026F\"\001Z\003=1G.\031;NCB<\026\016\0365OKb$XC\001.^)\tYf\fE\002)Sq\003\"AM/\005\013q:&\031\001\r\t\013y:\006\031A0\021\t5\001\025\007\031\t\005\033\001\0137\f\005\002)?!)1-\013D\001I\006ya-\0337uKJ<\026\016\0365FeJ|'\017\006\0031K.d\007\"\0024c\001\0049\027!\0019\021\t5\001\025\007\033\t\003\033%L!A\033\005\003\017\t{w\016\\3b]\")aJ\031a\001\037\")QN\031a\001C\006A\001o\\:ji&|g\016C\003pS\031\005\001/\001\004baB,g\016Z\013\003cR$\"A\035<\021\007!J3\017\005\0023i\022)AH\034b\001kF\021\021\007\b\005\007o:$\t\031\001=\002\003\005\0042!D=s\023\tQ\bB\001\005=Eft\027-\\3?\021\025a\030\006\"\001~\003\035I7/R7qif,\022\001\033\005\007&2\t!!\001\002\007\035,G/F\0012\021\035\t)!\013C\001\003\017\t\021bZ3u\037J,En]3\026\t\005%\021Q\002\013\005\003\027\t\t\002E\0023\003\033!q!a\004\002\004\t\007QOA\001C\021%\t\031\"a\001\005\002\004\t)\"A\004eK\032\fW\017\034;\021\t5I\0301\002\005\n\0033I#\031!D\001\0037\tAA\\3yiV\t\021\r\003\005\002 %\022\rQ\"\001~\003)\031XoY2fgN4W\017\\\025\006S\005\r\"\021\024\004\b\003K\001\021\021EA\024\005%qunU;dG\026\0348o\005\003\002$\005%\002c\001\025*3!Y\021QFA\022\005\013\007I\021AA\030\003\ri7oZ\013\002!\"Q\0211GA\022\005\003\005\013\021\002)\002\t5\034x\r\t\005\f\0033\t\031C!b\001\n\003\nY\002\003\006\002:\005\r\"\021!Q\001\n\005\fQA\\3yi\002BqALA\022\t\003\ti\004\006\004\002@\005\005\0231\t\t\004Q\005\r\002bBA\027\003w\001\r\001\025\005\b\0033\tY\0041\001b\021%\ty\"a\tC\002\023\005Q\020\003\005\002J\005\r\002\025!\003i\003-\031XoY2fgN4W\017\034\021\t\017Y\n\031\003\"\001\002NU!\021qJA,)\021\ty$!\025\t\017y\nY\0051\001\002TA)Q\002Q\r\002VA\031!'a\026\005\rq\nYE1\001\031\021\035\031\0251\005C\001\0037*B!!\030\002dQ1\021qLA3\003S\002B\001K\025\002bA\031!'a\031\005\rq\nIF1\001\031\021\035q\024\021\fa\001\003O\002R!D&\032\003CBqATA-\001\004\tY\007\005\003\016\001f\001\006b\002-\002$\021\005\021qN\013\005\003c\n9\b\006\003\002t\005e\004\003\002\025*\003k\0022AMA<\t\031a\024Q\016b\0011!9a(!\034A\002\005m\004#B\007A3\005u\004#B\007AC\006M\004bB2\002$\021\005\021\021\021\013\t\003S\t\031)a\"\002\n\"9a-a A\002\005\025\005\003B\007A3!DqATA@\001\004\tY\007\003\004n\003\002\r!\031\005\b\006\rB\021AAG+\005I\022FBA\022\003#\023IE\002\004\002\024\002\001\025Q\023\002\006\013J\024xN]\n\t\003#\013y$a&\002\036B\031Q\"!'\n\007\005m\005BA\004Qe>$Wo\031;\021\0075\ty*C\002\002\"\"\021AbU3sS\006d\027N_1cY\026D1\"!\f\002\022\nU\r\021\"\021\0020!a\0211GAI\005#\005\013\021\002)\002,!Y\021\021DAI\005+\007I\021IA\016\0211\tI$!%\003\022\003\006I!YA\033\021\035q\023\021\023C\001\003[#b!a,\0022\006M\006c\001\025\002\022\"9\021QFAV\001\004\001\006bBA\r\003W\003\r!\031\005\t\003o\013\t\n\"\021\002:\006AAo\\*ue&tw\r\006\002\002<B!\021QXAd\033\t\tyL\003\003\002B\006\r\027\001\0027b]\036T!!!2\002\t)\fg/Y\005\004+\006}\006bB8\002\022\022\005\0211Z\013\005\003\033\f\031\016\006\003\002P\006U\007\003\002\025*\003#\0042AMAj\t\031a\024\021\032b\0011!Aq/!3\005\002\004\t9\016\005\003\016s\006=\007BCAn\003#\013\t\021\"\001\002^\006!1m\0349z)\031\ty+a8\002b\"I\021QFAm!\003\005\r\001\025\005\n\0033\tI\016%AA\002\005D!\"!:\002\022F\005I\021AAt\0039\031w\016]=%I\0264\027-\0367uIE*\"!!;+\007A\013Yo\013\002\002nB!\021q^A}\033\t\t\tP\003\003\002t\006U\030!C;oG\",7m[3e\025\r\t9\020C\001\013C:tw\016^1uS>t\027\002BA~\003c\024\021#\0368dQ\026\0347.\0323WCJL\027M\\2f\021)\ty0!%\022\002\023\005!\021A\001\017G>\004\030\020\n3fM\006,H\016\036\0233+\t\021\031AK\002b\003WD!Ba\002\002\022\006\005I\021\tB\005\0035\001(o\0343vGR\004&/\0324jqV\021\0211\030\005\013\005\033\t\t*!A\005\002\t=\021\001\0049s_\022,8\r^!sSRLXC\001B\t!\ri!1C\005\004\005+A!aA%oi\"Q!\021DAI\003\003%\tAa\007\002\035A\024x\016Z;di\026cW-\\3oiR\031AD!\b\t\025\t}!qCA\001\002\004\021\t\"A\002yIEB!Ba\t\002\022\006\005I\021\tB\023\003=\001(o\0343vGRLE/\032:bi>\024XC\001B\024!\025\021ICa\f\035\033\t\021YCC\002\003.!\t!bY8mY\026\034G/[8o\023\021\021\tDa\013\003\021%#XM]1u_JD!B!\016\002\022\006\005I\021\001B\034\003!\031\027M\\#rk\006dGc\0015\003:!I!q\004B\032\003\003\005\r\001\b\005\013\005{\t\t*!A\005B\t}\022\001\0035bg\"\034u\016Z3\025\005\tE\001B\003B\"\003#\013\t\021\"\021\003F\0051Q-];bYN$2\001\033B$\021%\021yB!\021\002\002\003\007AD\002\004\003L\001\001%Q\n\002\b\r\006LG.\036:f'!\021I%a\020\002\030\006u\005bCA\027\005\023\022)\032!C!\003_AA\"a\r\003J\tE\t\025!\003Q\003WA1\"!\007\003J\tU\r\021\"\021\002\034!a\021\021\bB%\005#\005\013\021B1\0026!9aF!\023\005\002\teCC\002B.\005;\022y\006E\002)\005\023Bq!!\f\003X\001\007\001\013C\004\002\032\t]\003\031A1\t\021\005]&\021\nC!\003sCqa\034B%\t\003\021)'\006\003\003h\t5D\003\002B5\005_\002B\001K\025\003lA\031!G!\034\005\rq\022\031G1\001\031\021!9(1\rCA\002\tE\004\003B\007z\005SB!\"a7\003J\005\005I\021\001B;)\031\021YFa\036\003z!I\021Q\006B:!\003\005\r\001\025\005\n\0033\021\031\b%AA\002\005D!\"!:\003JE\005I\021AAt\021)\tyP!\023\022\002\023\005!\021\001\005\013\005\017\021I%!A\005B\t%\001B\003B\007\005\023\n\t\021\"\001\003\020!Q!\021\004B%\003\003%\tA!\"\025\007q\0219\t\003\006\003 \t\r\025\021!a\001\005#A!Ba\t\003J\005\005I\021\tB\023\021)\021)D!\023\002\002\023\005!Q\022\013\004Q\n=\005\"\003B\020\005\027\013\t\0211\001\035\021)\021iD!\023\002\002\023\005#q\b\005\013\005\007\022I%!A\005B\tUEc\0015\003\030\"I!q\004BJ\003\003\005\r\001\b\004\007\0057\003\001I!(\003\017M+8mY3tgV!!q\024BS'!\021IJ!)\002\030\006u\005\003\002\025*\005G\0032A\rBS\t\035!$\021\024CC\002aA1B!+\003\032\nU\r\021\"\001\003,\0061!/Z:vYR,\"Aa)\t\027\t=&\021\024B\tB\003%!1U\001\be\026\034X\017\034;!\021-\tIB!'\003\026\004%\t%a\007\t\025\005e\"\021\024B\tB\003%\021\rC\004/\0053#\tAa.\025\r\te&1\030B_!\025A#\021\024BR\021!\021IK!.A\002\t\r\006bBA\r\005k\003\r!\031\005\bm\teE\021\001Ba+\021\021\031M!3\025\t\t\025'1\032\t\006Q\te%q\031\t\004e\t%GA\002\037\003@\n\007\001\004C\004?\005\003\rA!4\021\r5\001%1\025Bd\021\035\031%\021\024C\001\005#,BAa5\003ZR1!Q\033Bn\005?\004B\001K\025\003XB\031!G!7\005\rq\022yM1\001\031\021\035q$q\032a\001\005;\004b!D&\003$\n]\007b\002(\003P\002\007!\021\035\t\006\033\001\023\031\013\025\005\b1\neE\021\001Bs+\021\0219O!<\025\t\t%(q\036\t\005Q%\022Y\017E\0023\005[$a\001\020Br\005\004A\002b\002 \003d\002\007!\021\037\t\007\033\001\023\031Ka=\021\0135\001\025M!;\t\017\r\024I\n\"\001\003xRA!\021\025B}\005{\024y\020C\004g\005k\004\rAa?\021\0135\001%1\0255\t\0179\023)\0201\001\003b\"1QN!>A\002\005Dqa\034BM\t\003\031\031!\006\003\004\006\r-A\003BB\004\007\037\001B\001K\025\004\nA\031!ga\003\005\017q\032\tA1\001\004\016E\031!1\025\017\t\021]\034\t\001\"a\001\007#\001B!D=\004\b!9qP!'\005\002\t-\006\002CA\\\0053#\t%!/\t\023\005}!\021\024b\001\n\003i\b\002CA%\0053\003\013\021\0025\t\025\005m'\021TA\001\n\003\031i\"\006\003\004 \r\025BCBB\021\007O\031I\003E\003)\0053\033\031\003E\0023\007K!a\001NB\016\005\004A\002B\003BU\0077\001\n\0211\001\004$!I\021\021DB\016!\003\005\r!\031\005\013\003K\024I*%A\005\002\r5R\003BB\030\007g)\"a!\r+\t\t\r\0261\036\003\007i\r-\"\031\001\r\t\025\005}(\021TI\001\n\003\0319$\006\003\003\002\reBA\002\033\0046\t\007\001\004\003\006\003\b\te\025\021!C!\005\023A!B!\004\003\032\006\005I\021\001B\b\021)\021IB!'\002\002\023\0051\021\t\013\0049\r\r\003B\003B\020\007\t\t\0211\001\003\022!Q!1\005BM\003\003%\tE!\n\t\025\tU\"\021TA\001\n\003\031I\005F\002i\007\027B\021Ba\b\004H\005\005\t\031\001\017\t\025\tu\"\021TA\001\n\003\022y\004\003\006\003D\te\025\021!C!\007#\"2\001[B*\021%\021yba\024\002\002\003\007AdB\005\004X\001\t\t\021#\001\004Z\00591+^2dKN\034\bc\001\025\004\\\031I!1\024\001\002\002#\0051QL\n\006\0077b\021Q\024\005\b]\rmC\021AB1)\t\031I\006\003\006\0028\016m\023\021!C#\003sC!ba\032\004\\\005\005I\021QB5\003\025\t\007\017\0357z+\021\031Yg!\035\025\r\r541OB;!\025A#\021TB8!\r\0214\021\017\003\007i\r\025$\031\001\r\t\021\t%6Q\ra\001\007_Bq!!\007\004f\001\007\021\r\003\006\004z\rm\023\021!CA\007w\nq!\0368baBd\0270\006\003\004~\r5E\003BB@\007\037\003R!DBA\007\013K1aa!\t\005\031y\005\017^5p]B1Qba\"\004\f\006L1a!#\t\005\031!V\017\0357feA\031!g!$\005\rQ\0329H1\001\031\021)\031\tja\036\002\002\003\00711S\001\004q\022\002\004#\002\025\003\032\016-\005BCBL\0077\n\t\021\"\003\004\032\006Y!/Z1e%\026\034x\016\034<f)\t\031Y\n\005\003\002>\016u\025\002BBP\003\023aa\0242kK\016$\bBCBR\001!\025\r\021\"\003\004&\006\001B.Y:u\035>\034VoY2fgN4\026M]\013\003\007O\003ba!+\004,\016=V\"\001\004\n\007\r5fAA\bEs:\fW.[2WCJL\027M\0317f!\025i1\021QA \021)\031\031\f\001E\001B\003&1qU\001\022Y\006\034HOT8Tk\016\034Wm]:WCJ\004\003bBB\\\001\021\0051\021X\001\016Y\006\034HOT8Tk\016\034Wm]:\026\005\005}\002\006CB[\007{\033\031ma2\021\0075\031y,C\002\004B\"\021!\002Z3qe\026\034\027\r^3eC\t\031)-A mCN$hj\\*vG\016,7o\035\021xCN\004cn\034;!i\"\024X-\0313.g\0064W\rI1oI\002:\030\016\0347!E\026\004#/Z7pm\026$\007%\0338!e9\n\024G\f\031\"\005\r%\027A\002\032/cAr\003\007C\004\004N\002!\taa4\002#1\f7\017\036(p'V\0347-Z:t?\022*\027\017F\002\024\007#D\001ba5\004L\002\007\021qH\001\002q\"B11ZB_\007\007\0349mB\004\004Z\002A\taa7\002\0239{7+^2dKN\034\bc\001\025\004^\0329\021Q\005\001\t\002\r}7cABo\031!9af!8\005\002\r\rHCABn\021!\031Ih!8\005\002\r\035X\003BBu\007k$Baa;\004pB)Qb!!\004nB)Qba\"QC\"A11[Bs\001\004\031\t\020\005\003)S\rM\bc\001\032\004v\0221Ag!:C\002a9\021b!?\001\003\003E\taa?\002\017\031\013\027\016\\;sKB\031\001f!@\007\023\t-\003!!A\t\002\r}8CBB\t\003\ti\n\005\005\005\004\021%\001+\031B.\033\t!)AC\002\005\b!\tqA];oi&lW-\003\003\005\f\021\025!!E!cgR\024\030m\031;Gk:\034G/[8oe!9af!@\005\002\021=ACAB~\021)\t9l!@\002\002\023\025\023\021\030\005\013\007O\032i0!A\005\002\022UAC\002B.\t/!I\002C\004\002.\021M\001\031\001)\t\017\005eA1\003a\001C\"Q1\021PB\003\003%\t\t\"\b\025\t\r-Hq\004\005\013\007##Y\"!AA\002\tm\003BCBL\007{\f\t\021\"\003\004\032\036IAQ\005\001\002\002#\005AqE\001\006\013J\024xN\035\t\004Q\021%b!CAJ\001\005\005\t\022\001C\026'\031!I\003\"\f\002\036BAA1\001C\005!\006\fy\013C\004/\tS!\t\001\"\r\025\005\021\035\002BCA\\\tS\t\t\021\"\022\002:\"Q1q\rC\025\003\003%\t\tb\016\025\r\005=F\021\bC\036\021\035\ti\003\"\016A\002ACq!!\007\0056\001\007\021\r\003\006\004z\021%\022\021!CA\t!Baa;\005B!Q1\021\023C\037\003\003\005\r!a,\t\025\r]E\021FA\001\n\023\031I\nC\004\005H\001!\t\001\"\023\002\rA\013'o]3s+\021!YE\",\025\t\0215cq\026\t\006Q\021=c1\026\004\b\t#\002\021\021\001C*\005\031\001\026M]:feV!AQ\013C/'\025!y\005\004C,!\025i\001)\031C-!\021A\023\006b\027\021\007I\"i\006B\0045\t\037\")\031\001\r\t\0179\"y\005\"\001\005bQ\021A1\r\t\006Q\021=C1\f\005\013\tO\"y\0051A\005\n\005=\022\001\0028b[\026D!\002b\033\005P\001\007I\021\002C7\003!q\027-\\3`I\025\fHcA\n\005p!I!q\004C5\003\003\005\r\001\025\005\t\tg\"y\005)Q\005!\006)a.Y7fA!AAq\017C(\t\003!I(A\003oC6,G\r\006\003\005|\021uTB\001C(\021\035!y\b\"\036A\002A\013\021A\034\005\t\003o#y\005\"\021\002:\"A1q\rC(\r\003!)\t\006\003\005Z\021\035\005b\002CE\t\007\003\r!Y\001\003S:D\001\002\"$\005P\021\005AqR\001\bM2\fG/T1q+\021!\t\nb&\025\t\021ME\021\024\t\006Q\021=CQ\023\t\004e\021]EA\002\037\005\f\n\007\001\004C\004?\t\027\003\r\001b'\021\r5\001E1\fCJ\021\0351Dq\nC\001\t?+B\001\")\005(R!A1\025CU!\025ACq\nCS!\r\021Dq\025\003\007y\021u%\031\001\r\t\017y\"i\n1\001\005,B1Q\002\021C.\tKC\001\002b,\005P\021\005A\021W\001\007M&dG/\032:\025\t\021\rD1\027\005\bM\0225\006\031\001C[!\025i\001\tb\027i\021!!I\fb\024\005\002\021m\026AC<ji\"4\025\016\034;feR!A1\rC_\021\0351Gq\027a\001\tkCqa\034C(\t\003!\t-\006\003\005D\022%G\003\002Cc\t\033\004R\001\013C(\t\017\0042A\rCe\t\035aDq\030b\001\t\027\f2\001b\027\035\021%!y\rb0\005\002\004!\t.\001\002qaA!Q\"\037CcQ!!y\f\"6\005^\022\005\b\003\002Cl\t3l!!!>\n\t\021m\027Q\037\002\n[&<'/\031;j_:\f#\001b8\002\003\037!\006.\032\021dC2dWFY=.]\006lW\rI1sOVlWM\034;!SN\004SM^1mk\006$X\r\032\021bi\002jwn\035;!_:\034W\r\t9fe\002\032wN\\:ueV\034G/\0323!!\006\0248/\032:!_\nTWm\031;-A%t7\017^3bI\002zg\rI8oA\0254XM]=!]\026,G\r\t;iCR\004\023M]5tKN\004C-\036:j]\036\004\003/\031:tS:<g&\t\002\005d\006)!GL\035/a!AAq\035C(\t\003!I/\001\004%i&dG-Z\013\005\tW,i\007\006\003\005n\026=\004#\002\025\005P\021=\bc\002\025\005r\022mS1\016\004\007\tg\004\001\t\">\003\r\021\"\030\016\0343f+\031!90\"\001\006\022M9A\021\037\007\002\030\006u\005b\003C~\tc\024)\032!C\001\t{\f!aX\031\026\005\021}\bc\001\032\006\002\021AQ1\001Cy\t\013\007\001DA\001b\021-)9\001\"=\003\022\003\006I\001b@\002\007}\013\004\005C\006\006\f\021E(Q3A\005\002\0255\021AA03+\t)y\001E\0023\013#!\001\"b\005\005r\022\025\r\001\007\002\002E\"YQq\003Cy\005#\005\013\021BC\b\003\ry&\007\t\005\b]\021EH\021AC\016)\031)i\"b\b\006\"A9\001\006\"=\005\000\026=\001\002\003C~\0133\001\r\001b@\t\021\025-Q\021\004a\001\013\037A\001\"a.\005r\022\005\023\021\030\005\013\0037$\t0!A\005\002\025\035RCBC\025\013_)\031\004\006\004\006,\025URq\007\t\bQ\021EXQFC\031!\r\021Tq\006\003\b\013\007))C1\001\031!\r\021T1\007\003\b\013'))C1\001\031\021)!Y0\"\n\021\002\003\007QQ\006\005\013\013\027))\003%AA\002\025E\002BCAs\tc\f\n\021\"\001\006<U1QQHC!\013\007*\"!b\020+\t\021}\0301\036\003\b\013\007)ID1\001\031\t\035)\031\"\"\017C\002aA!\"a@\005rF\005I\021AC$+\031)I%\"\024\006PU\021Q1\n\026\005\013\037\tY\017B\004\006\004\025\025#\031\001\r\005\017\025MQQ\tb\0011!Q!q\001Cy\003\003%\tE!\003\t\025\t5A\021_A\001\n\003\021y\001\003\006\003\032\021E\030\021!C\001\013/\"2\001HC-\021)\021y\"\"\026\002\002\003\007!\021\003\005\013\005G!\t0!A\005B\t\025\002B\003B\033\tc\f\t\021\"\001\006`Q\031\001.\"\031\t\023\t}QQLA\001\002\004a\002B\003B\037\tc\f\t\021\"\021\003@!Q!1\tCy\003\003%\t%b\032\025\007!,I\007C\005\003 \025\025\024\021!a\0019A\031!'\"\034\005\rq\")O1\001\031\021%)\t\b\":\005\002\004)\031(A\001r!\021i\0210\"\036\021\013!\"y%b\033)\021\021\025HQ\033Co\tCD\001\"b\037\005P\021\005QQP\001\017IQLG\016Z3%OJ,\027\r^3s+\021)y(\"\"\025\t\025\005Uq\021\t\006Q\021=S1\021\t\004e\025\025EA\002\037\006z\t\007\001\004C\005\006r\025eD\0211\001\006\nB!Q\"_CAQ!)I\b\"6\005^\022\005\b\002CCH\t\037\"\t!\"%\002\027\021bWm]:%i&dG-Z\013\005\013'+i\n\006\003\005d\025U\005\"CC9\013\033#\t\031ACL!\021i\0210\"'\021\013!\"y%b'\021\007I*i\n\002\004=\013\033\023\r\001\007\025\t\013\033#)\016\"8\005b\"AQ1\025C(\t\003))+A\006%i&dG-\032\023cC:<W\003BCT\013_#B!\"+\0062B)\001\006b\024\006,B9\001\006\"=\005\\\0255\006c\001\032\0060\0221A(\")C\002aA\001BZCQ\t\003\007Q1\027\t\005\033e,)\fE\003)\t\037*i\013\003\005\006:\022=C\021AC^\003\021!#-\031:\026\t\025uV1\031\013\005\013+)\rE\003)\t\037*\t\rE\0023\013\007$q\001PC\\\005\004!Y\rC\005\006r\025]F\0211\001\006HB!Q\"_C`\021!)Y\rb\024\005\002\0255\027\001\004\023cCJ$#-\031:%E\006\024X\003BCh\013+$B!\"5\006XB)\001\006b\024\006TB\031!'\"6\005\017q*IM1\001\005L\"IQ\021\\Ce\t\003\007Q1\\\001\003cB\002B!D=\006R\"BQ\021\032Ck\t;$\t\017\003\005\006b\022=C\021ACr\003\031!S\017\035\023vaV!QQ]Cv)\021)9/\"<\021\013!\"y%\";\021\007I*Y\017\002\004=\013?\024\r\001\007\005\b}\025}\007\031ACx!\031i\001\tb\027\006j\"AQ1\037C(\t\003))0A\005%kB$S\017\035\023vaV!Qq_C)\021)I0b@\021\013!\"y%b?\021\007I*i\020\002\004=\013c\024\r\001\007\005\n\r\003)\t\020\"a\001\r\007\t\021A\036\t\005\033e,Y\020\013\005\006r\022UGQ\034Cq\021!1I\001b\024\005\002\031-\021!\003\023va\022\nX.\031:l+\0211iAb\005\025\r\031=aQ\003D\r!\025ACq\nD\t!\r\021d1\003\003\007y\031\035!\031\001\r\t\017y29\0011\001\007\030A1Qb\023C.\r#AqA\024D\004\001\0041Y\002E\003\016\001\022m\003\013\003\005\007\n\021=C\021\001D\020+\0211\tCb\n\025\t\031\rb\021\006\t\006Q\021=cQ\005\t\004e\031\035BA\002\037\007\036\t\007\001\004C\004?\r;\001\rAb\013\021\r5YE1\fD\023\021!1y\003b\024\005\002\031E\022\001B5oi>,BAb\r\007:Q!aQ\007D\036!\025ACq\nD\034!\r\021d\021\b\003\007y\0315\"\031\001\r\t\021\031ubQ\006a\001\r\t!AZ9\021\r5\001E1\fD\033\021!1\031\005b\024\005\002\031\025\023\001\005\023he\026\fG/\032:%OJ,\027\r^3s+\02119E\"\024\025\t\031%cq\n\t\006Q\021=c1\n\t\004e\0315CA\002\037\007B\t\007\001\004\003\005\007>\031\005\003\031\001D)!\031i\001\tb\027\007J!AaQ\013C(\t\00319&\001\004%i&lWm]\013\003\r3\002R\001\013C(\r7\002bA\"\030\007n\021mc\002\002D0\rSrAA\"\031\007h5\021a1\r\006\004\rKR\021A\002\037s_>$h(C\001\n\023\r1Y\007C\001\ba\006\0347.Y4f\023\0211yG\"\035\003\t1K7\017\036\006\004\rWB\001\002\003D+\t\037\"\tA\"\036\026\t\031]dQ\020\013\005\rs2y\bE\003)\t\0372Y\bE\0023\r{\"q\001\020D:\005\004!Y\rC\005\007\002\032MD\0211\001\007\004\006\0311/\0329\021\t5IhQ\021\t\006Q\021=cq\021\t\n\033\031%e1\020D>\rwJ1Ab#\t\005%1UO\\2uS>t'\007\003\005\007\020\022=C\021\001D,\003\025!\003\017\\;t\021!1\031\nb\024\005\002\031U\025A\002\023r[\006\0248.\006\002\007\030B)\001\006b\024\007\032B)Qb!!\005\\!AaQ\024C(\t\0031y*\001\nxSRDg)Y5mkJ,W*Z:tC\036,G\003\002C2\rCCq!!\f\007\034\002\007\001\013\003\005\007&\022=C\021\001DT\003A9\030\016\0365FeJ|'/T3tg\006<W\r\006\003\005d\031%\006bBA\027\rG\003\r\001\025\t\004e\0315FA\002\033\005F\t\007\001\004C\004?\t\013\002\rA\"-\021\0135\001\025Mb-\021\t!Jc1\026\005\b\ro\003A\021\001D]\003)yenY3QCJ\034XM]\013\005\rw39\r\006\003\007>\032=(C\002D`\r\0074IM\002\004\007B\002\001aQ\030\002\ryI,g-\0338f[\026tGO\020\t\006Q\021=cQ\031\t\004e\031\035GA\002\033\0076\n\007\001\004E\003)\r\0274)MB\005\007N\002\001\n1!\001\007P\nQqJ\\2f!\006\0248/\032:\026\t\031Egq[\n\005\r\0274\031\016E\003)\t\0372)\016E\0023\r/$q\001\016Df\t\013\007\001\004\003\004\022\r\027$\tA\005\005\t\tO4Y\r\"\021\007^V!aq\034Dt)\0211\tO\";\021\013!\"yEb9\021\017!\"\tP\"6\007fB\031!Gb:\005\rq2YN1\001\031\021!1g1\034CA\002\031-\b\003B\007z\r[\004R\001\013C(\rKDqA\020D[\001\0041\t\020E\003\016\001\0064\031\020\005\003)S\031\025\007b\002D|\001\021\005a\021`\001\007G>lW.\033;\026\t\031mx\021\001\013\005\r{<\031\001E\003)\t\0372y\020E\0023\017\003!a\001\016D{\005\004A\002\002\0034\007v\022\005\ra\"\002\021\t5IhQ \005\b\017\023\001A\021AD\006\003\021)G.Z7\025\r\0355qqBD\n!\021ACqJ\024\t\017\035Eqq\001a\001!\006!1.\0338e\021\0351wq\001a\001\017+\001B!\004!(Q\"9q\021\002\001\005\002\035eA\003BD\007\0177Aqa\"\b\b\030\001\007q%A\001f\021\0359\t\003\001C\002\017G\ta!Y2dKB$H\003BD\007\017KAqa\"\b\b \001\007q\005C\004\b\"\001!\ta\"\013\026\t\035-r1\b\013\005\017[9y\004\006\003\b0\035M\002#\002\025\005P\035E\002#\002D/\r[:\003BCD\033\017O\t\t\021q\001\b8\005QQM^5eK:\034W\rJ\031\021\r5\001u\021HD\031!\r\021t1\b\003\b\017{99C1\001\031\005\t)5\013\003\005\bB\035\035\002\031AD\035\003\t)7\017C\004\b\"\001!\ta\"\022\026\t\035\035sQ\n\013\007\017\023:yeb\025\021\013!\"yeb\023\021\007I:i\005\002\004=\017\007\022\r\001\007\005\b\017#:\031\0051\001Q\003!)\007\020]3di\026$\007b\002 \bD\001\007qQ\013\t\006\033-;s1\n\005\b\0173\002A\021AD.\003!\t7mY3qi&3G\003BD/\017K\"Ba\"\004\b`!Aq\021MD,\001\0049\031'A\002feJ\004B!\004!(!\"9amb\026A\002\035U\001bBD5\001\021\005q1N\001\fC\016\034W\r\035;NCR\034\007.\006\003\bn\035MDCBD8\017k:9\bE\003)\t\037:\t\bE\0023\017g\"a\001PD4\005\004A\002bBD)\017O\002\r\001\025\005\b}\035\035\004\031AD=!\025i1jJD9\021\0359i\b\001C\001\017\n\021\"Y2dKB$8+Z9\026\t\035\005uQ\022\013\005\017\007;)\n\006\003\b0\035\025\005BCDD\017w\n\t\021q\001\b\n\006QQM^5eK:\034W\r\n\032\021\r5\001u1RDH!\r\021tQ\022\003\b\017{9YH1\001\031!\0251if\"%(\023\0219\031J\"\035\003\021%#XM]1cY\026D\001b\"\021\b|\001\007q1\022\005\b\0173\003A\021ADN\003\0351\027-\0337ve\026$Ba\"(\b B!\001\006b\024\032\021\035\ticb&A\002ACqa\"\031\001\t\0039\031\013\006\003\b\036\036\025\006bBA\027\017C\003\r\001\025\005\b\017S\003A\021ADV\003\035\031XoY2fgN,Ba\",\b4R!qqVD[!\025ACqJDY!\r\021t1\027\003\007i\035\035&\031\001\r\t\021\031\005qq\025a\001\017cCqa\"/\001\t\0039Y,A\002m_\036,Ba\"0\bFR!qqXDe)\0219\tmb2\021\013!\"yeb1\021\007I:)\r\002\0045\017o\023\r\001\007\005\b\tO:9\f1\001Q\021!1wq\027CA\002\035-\007\003B\007z\017\003Dqab4\001\t\0039\t.A\002sKB,Bab5\b\\R!qQ[Do!\025ACqJDl!\0311iF\"\034\bZB\031!gb7\005\rQ:iM1\001\031\021!1wQ\032CA\002\035}\007\003B\007z\017C\004R\001\013C(\0173Dqa\":\001\t\00399/\001\004sKB\034X\r]\013\005\017S<\t\020\006\004\bl\036Mx\021 \t\006Q\021=sQ\036\t\007\r;2igb<\021\007I:\t\020\002\0045\017G\024\r\001\007\005\tM\036\rH\0211\001\bvB!Q\"_D|!\025ACqJDx\021%)\thb9\005\002\0049Y\020\005\003\016s\036u\b\003\002\025\005PqAq\001#\001\001\t\003A\031!\001\003sKB\fT\003\002E\003\021\033!B\001c\002\t\020A)\001\006b\024\t\nA1aQ\fD7\021\027\0012A\rE\007\t\031!tq b\0011!Aamb@\005\002\004A\t\002\005\003\016s\"M\001#\002\025\005P!-\001b\002E\001\001\021\005\001rC\013\005\0213A\t\003\006\004\t\034!\r\0022\006\t\006Q\021=\003R\004\t\007\r;2i\007c\b\021\007IB\t\003\002\0045\021+\021\r\001\007\005\n\021KA)\002\"a\001\021O\tQAZ5sgR\004B!D=\t*A)\001\006b\024\t !IAq\032E\013\t\003\007\001r\005\025\t\021+!)\016c\f\005b\006\022\001\022G\001\002\034QCW\r\t1qa\001\0043-\0317m[\tLXF\\1nK\002\n'oZ;nK:$8\017I5tA\0254\030\r\\;bi\026$\007%\031;![>\034H\017I8oG\026\004\003/\032:!G>t7\017\036:vGR,G\r\t)beN,'\017I8cU\026\034G\017\f\021j]N$X-\0313!_\032\004sN\034\021fm\026\024\030\020\t8fK\022\004C\017[1uA\005\024\030n]3tA\021,(/\0338hAA\f'o]5oO:Bq\001#\016\001\t\003A9$\001\003sKBtU\003\002E\035\021\003\"b\001c\017\tD!\035\003#\002\025\005P!u\002C\002D/\r[By\004E\0023\021\003\"a\001\016E\032\005\004A\002\002\003E#\021g\001\rA!\005\002\0079,X\016\003\005g\021g!\t\031\001E%!\021i\021\020c\023\021\013!\"y\005c\020\t\017!=\003\001\"\001\tR\0059!/\03292g\026\004X\003\002E*\0217\"b\001#\026\t^!\r\004#\002\025\005P!]\003C\002D/\r[BI\006E\0023\0217\"a\001\016E'\005\004A\002\002\0034\tN\021\005\r\001c\030\021\t5I\b\022\r\t\006Q\021=\003\022\f\005\n\013cBi\005\"a\001\017wDq\001c\032\001\t\003AI'A\004dQ\006Lg\016\\\031\026\t!-\004\022\017\013\007\021[B\031\bc\036\021\013!\"y\005c\034\021\007IB\t\b\002\0045\021K\022\r\001\007\005\tM\"\025D\0211\001\tvA!Q\"\037E7\021%)\t\b#\032\005\002\004AI\b\005\003\016s\"m\004#\002\025\005P!u\004#C\007\007\n\"=\004r\016E8\021\035A9\007\001C\001\021\003+b\001c!\t\n\"]E\003\003EC\021\027Cy\t#'\021\013!\"y\005c\"\021\007IBI\t\002\0045\021\022\r\001\007\005\n\021KAy\b\"a\001\021\033\003B!D=\t\006\"Aa\rc \005\002\004A\t\n\005\003\016s\"M\005#\002\025\005P!U\005c\001\032\t\030\0221A\bc C\002aA\021\"\"\035\t\000\021\005\r\001c'\021\t5I\bR\024\t\006Q\021=\003r\024\t\n\033\031%\005r\021EK\021\017Cq\001c)\001\t\003A)+A\004dQ\006LgN]\031\026\r!\035\006r\027EW))AI\013c,\t:\"\005\007R\031\t\006Q\021=\0032\026\t\004e!5FA\002\037\t\"\n\007\001\004\003\005g\021C#\t\031\001EY!\021i\021\020c-\021\013!\"y\005#.\021\007IB9\f\002\0045\021C\023\r\001\007\005\n\013cB\t\013\"a\001\021w\003B!D=\t>B)\001\006b\024\t@BIQB\"#\t6\"-\0062\026\005\t\021\007D\t\0131\001\t@\00691m\\7cS:,\007\002\003E\023\021C\003\r\001c+\t\017!%\007\001\"\001\tL\006\031q\016\035;\026\t!5\007R\033\013\005\021\037D9\016E\003)\t\037B\t\016E\003\016\007\003C\031\016E\0023\021+$a\001\016Ed\005\004A\002\002\0034\tH\022\005\r\001#7\021\t5I\b2\034\t\006Q\021=\0032\033\005\b\021?\004A\021\001Eq\003\rqw\016^\013\005\021GDy\017\006\003\tf\"\035\b\003\002\025\005PMA\001B\032Eo\t\003\007\001\022\036\t\005\033eDY\017E\003)\t\037Bi\017E\0023\021_$a\001\016Eo\005\004A\002b\002Ez\001\021\005\001R_\001\006OV\f'\017Z\013\005\021oDi\020\006\003\tz\"}\b#\002\025\005P!m\bc\001\032\t~\0221A\007#=C\002aA\001B\032Ey\t\003\007\021\022\001\t\005\033eDI\020C\004\n\006\001!\t!c\002\002\025A|7/\033;j_:,G-\006\003\n\n%=A\003BE\006\0233\001R\001\013C(\023\033\0012AME\b\t\035!\0242\001b\001\023#\t2!GE\n!\r\021\023RC\005\004\023/\031#A\003)pg&$\030n\0348bY\"Aa-c\001\005\002\004IY\002\005\003\016s&-\001bBE\020\001\021\005\021\022E\001\007a\"\024\030m]3\026\t%\r\022\022\006\013\005\023KIY\003E\003)\t\037J9\003E\0023\023S!a\001NE\017\005\004A\002b\0024\n\036\001\007\021R\005\005\b\023_\001A\021AE\031\003\031i7\016T5tiV!\0212GE\036+\tI)\004\005\004\016\001&]\022r\b\t\bQ\021E\030\022HE\037!\r\021\0242\b\003\007i%5\"\031\001\r\021\r\031ucQNE\035!\031I\t%c\022\n:5\021\0212\t\006\005\023\013\022Y#A\005j[6,H/\0312mK&!aqNE\"\017%!9\017AA\001\022\003IY\005E\002)\023\0332\021\002b=\001\003\003E\t!c\024\024\013%5C\"!(\t\0179Ji\005\"\001\nTQ\021\0212\n\005\013\003oKi%!A\005F\005e\006BCB4\023\033\n\t\021\"!\nZU1\0212LE1\023K\"b!#\030\nh%%\004c\002\025\005r&}\0232\r\t\004e%\005DaBC\002\023/\022\r\001\007\t\004e%\025DaBC\n\023/\022\r\001\007\005\t\twL9\0061\001\n`!AQ1BE,\001\004I\031\007\003\006\004z%5\023\021!CA\023[*b!c\034\nx%mD\003BE9\023{\002R!DBA\023g\002r!DBD\023kJI\bE\0023\023o\"q!b\001\nl\t\007\001\004E\0023\023w\"q!b\005\nl\t\007\001\004\003\006\004\022&-\024\021!a\001\023\002r\001\013Cy\023kJI\b\003\006\004\030&5\023\021!C\005\0073\003")
/*     */ public interface Parsers {
/*     */   Success$ Success();
/*     */   
/*     */   DynamicVariable<Option<NoSuccess>> scala$util$parsing$combinator$Parsers$$lastNoSuccessVar();
/*     */   
/*     */   NoSuccess lastNoSuccess();
/*     */   
/*     */   void lastNoSuccess_$eq(NoSuccess paramNoSuccess);
/*     */   
/*     */   NoSuccess$ NoSuccess();
/*     */   
/*     */   Failure$ Failure();
/*     */   
/*     */   Error$ Error();
/*     */   
/*     */   <T> Parser<T> Parser(Function1<Reader<Object>, ParseResult<T>> paramFunction1);
/*     */   
/*     */   <T> Parser<T> OnceParser(Function1<Reader<Object>, ParseResult<T>> paramFunction1);
/*     */   
/*     */   <T> Parser<T> commit(Function0<Parser<T>> paramFunction0);
/*     */   
/*     */   Parser<Object> elem(String paramString, Function1<Object, Object> paramFunction1);
/*     */   
/*     */   Parser<Object> elem(Object paramObject);
/*     */   
/*     */   Parser<Object> accept(Object paramObject);
/*     */   
/*     */   <ES> Parser<List<Object>> accept(ES paramES, Function1<ES, List<Object>> paramFunction1);
/*     */   
/*     */   <U> Parser<U> accept(String paramString, PartialFunction<Object, U> paramPartialFunction);
/*     */   
/*     */   Parser<Object> acceptIf(Function1<Object, Object> paramFunction1, Function1<Object, String> paramFunction11);
/*     */   
/*     */   <U> Parser<U> acceptMatch(String paramString, PartialFunction<Object, U> paramPartialFunction);
/*     */   
/*     */   <ES> Parser<List<Object>> acceptSeq(ES paramES, Function1<ES, Iterable<Object>> paramFunction1);
/*     */   
/*     */   Parser<scala.runtime.Nothing$> failure(String paramString);
/*     */   
/*     */   Parser<scala.runtime.Nothing$> err(String paramString);
/*     */   
/*     */   <T> Parser<T> success(T paramT);
/*     */   
/*     */   <T> Parser<T> log(Function0<Parser<T>> paramFunction0, String paramString);
/*     */   
/*     */   <T> Parser<List<T>> rep(Function0<Parser<T>> paramFunction0);
/*     */   
/*     */   <T> Parser<List<T>> repsep(Function0<Parser<T>> paramFunction0, Function0<Parser<Object>> paramFunction01);
/*     */   
/*     */   <T> Parser<List<T>> rep1(Function0<Parser<T>> paramFunction0);
/*     */   
/*     */   <T> Parser<List<T>> rep1(Function0<Parser<T>> paramFunction01, Function0<Parser<T>> paramFunction02);
/*     */   
/*     */   <T> Parser<List<T>> repN(int paramInt, Function0<Parser<T>> paramFunction0);
/*     */   
/*     */   <T> Parser<List<T>> rep1sep(Function0<Parser<T>> paramFunction0, Function0<Parser<Object>> paramFunction01);
/*     */   
/*     */   <T> Parser<T> chainl1(Function0<Parser<T>> paramFunction0, Function0<Parser<Function2<T, T, T>>> paramFunction01);
/*     */   
/*     */   <T, U> Parser<T> chainl1(Function0<Parser<T>> paramFunction0, Function0<Parser<U>> paramFunction01, Function0<Parser<Function2<T, U, T>>> paramFunction02);
/*     */   
/*     */   <T, U> Parser<U> chainr1(Function0<Parser<T>> paramFunction0, Function0<Parser<Function2<T, U, U>>> paramFunction01, Function2<T, U, U> paramFunction2, U paramU);
/*     */   
/*     */   <T> Parser<Option<T>> opt(Function0<Parser<T>> paramFunction0);
/*     */   
/*     */   <T> Parser<BoxedUnit> not(Function0<Parser<T>> paramFunction0);
/*     */   
/*     */   <T> Parser<T> guard(Function0<Parser<T>> paramFunction0);
/*     */   
/*     */   <T extends scala.util.parsing.input.Positional> Parser<T> positioned(Function0<Parser<T>> paramFunction0);
/*     */   
/*     */   <T> Parser<T> phrase(Parser<T> paramParser);
/*     */   
/*     */   <T> Function1<$tilde<T, List<T>>, List<T>> mkList();
/*     */   
/*     */   $tilde$ $tilde();
/*     */   
/*     */   public abstract class ParseResult<T> {
/*     */     public ParseResult(Parsers $outer) {}
/*     */     
/*     */     public boolean isEmpty() {
/* 117 */       return !successful();
/*     */     }
/*     */     
/*     */     public <B> B getOrElse(Function0 default) {
/* 123 */       return isEmpty() ? (B)default.apply() : (B)get();
/*     */     }
/*     */     
/*     */     public abstract <U> ParseResult<U> map(Function1<T, U> param1Function1);
/*     */     
/*     */     public abstract <U> ParseResult<U> mapPartial(PartialFunction<T, U> param1PartialFunction, Function1<T, String> param1Function1);
/*     */     
/*     */     public abstract <U> ParseResult<U> flatMapWithNext(Function1<T, Function1<Reader<Object>, ParseResult<U>>> param1Function1);
/*     */     
/*     */     public abstract ParseResult<T> filterWithError(Function1<T, Object> param1Function1, Function1<T, String> param1Function11, Reader<Object> param1Reader);
/*     */     
/*     */     public abstract <U> ParseResult<U> append(Function0<ParseResult<U>> param1Function0);
/*     */     
/*     */     public abstract T get();
/*     */     
/*     */     public abstract Reader<Object> next();
/*     */     
/*     */     public abstract boolean successful();
/*     */   }
/*     */   
/*     */   public class Success$ implements Serializable {
/*     */     public final String toString() {
/* 135 */       return "Success";
/*     */     }
/*     */     
/*     */     public <T> Parsers.Success<T> apply(Object result, Reader next) {
/* 135 */       return new Parsers.Success<T>(this.$outer, (T)result, next);
/*     */     }
/*     */     
/*     */     public <T> Option<Tuple2<T, Reader<Object>>> unapply(Parsers.Success x$0) {
/* 135 */       return (x$0 == null) ? (Option<Tuple2<T, Reader<Object>>>)scala.None$.MODULE$ : (Option<Tuple2<T, Reader<Object>>>)new Some(new Tuple2(x$0.result(), x$0.next()));
/*     */     }
/*     */     
/*     */     private Object readResolve() {
/* 135 */       return this.$outer.Success();
/*     */     }
/*     */     
/*     */     public Success$(Parsers $outer) {}
/*     */   }
/*     */   
/*     */   public class Success<T> extends ParseResult<T> implements Product, Serializable {
/*     */     private final T result;
/*     */     
/*     */     private final Reader<Object> next;
/*     */     
/*     */     private final boolean successful;
/*     */     
/*     */     public T result() {
/* 135 */       return this.result;
/*     */     }
/*     */     
/*     */     public Reader<Object> next() {
/* 135 */       return this.next;
/*     */     }
/*     */     
/*     */     public <T> Success<T> copy(Object result, Reader<Object> next) {
/* 135 */       return new Success(scala$util$parsing$combinator$Parsers$Success$$$outer(), (T)result, next);
/*     */     }
/*     */     
/*     */     public <T> T copy$default$1() {
/* 135 */       return result();
/*     */     }
/*     */     
/*     */     public <T> Reader<Object> copy$default$2() {
/* 135 */       return next();
/*     */     }
/*     */     
/*     */     public String productPrefix() {
/* 135 */       return "Success";
/*     */     }
/*     */     
/*     */     public int productArity() {
/* 135 */       return 2;
/*     */     }
/*     */     
/*     */     public Object productElement(int x$1) {
/* 135 */       switch (x$1) {
/*     */         default:
/* 135 */           throw new IndexOutOfBoundsException(BoxesRunTime.boxToInteger(x$1).toString());
/*     */         case 1:
/*     */         
/*     */         case 0:
/*     */           break;
/*     */       } 
/* 135 */       return result();
/*     */     }
/*     */     
/*     */     public Iterator<Object> productIterator() {
/* 135 */       return scala.runtime.ScalaRunTime$.MODULE$.typedProductIterator(this);
/*     */     }
/*     */     
/*     */     public boolean canEqual(Object x$1) {
/* 135 */       return x$1 instanceof Success;
/*     */     }
/*     */     
/*     */     public int hashCode() {
/* 135 */       return scala.runtime.ScalaRunTime$.MODULE$._hashCode(this);
/*     */     }
/*     */     
/*     */     public boolean equals(Object x$1) {
/*     */       // Byte code:
/*     */       //   0: aload_0
/*     */       //   1: aload_1
/*     */       //   2: if_acmpeq -> 169
/*     */       //   5: aload_1
/*     */       //   6: instanceof scala/util/parsing/combinator/Parsers$Success
/*     */       //   9: ifeq -> 31
/*     */       //   12: aload_1
/*     */       //   13: checkcast scala/util/parsing/combinator/Parsers$Success
/*     */       //   16: invokevirtual scala$util$parsing$combinator$Parsers$Success$$$outer : ()Lscala/util/parsing/combinator/Parsers;
/*     */       //   19: aload_0
/*     */       //   20: invokevirtual scala$util$parsing$combinator$Parsers$Success$$$outer : ()Lscala/util/parsing/combinator/Parsers;
/*     */       //   23: if_acmpne -> 31
/*     */       //   26: iconst_1
/*     */       //   27: istore_2
/*     */       //   28: goto -> 33
/*     */       //   31: iconst_0
/*     */       //   32: istore_2
/*     */       //   33: iload_2
/*     */       //   34: ifeq -> 173
/*     */       //   37: aload_1
/*     */       //   38: checkcast scala/util/parsing/combinator/Parsers$Success
/*     */       //   41: astore #6
/*     */       //   43: aload_0
/*     */       //   44: invokevirtual result : ()Ljava/lang/Object;
/*     */       //   47: aload #6
/*     */       //   49: invokevirtual result : ()Ljava/lang/Object;
/*     */       //   52: astore #4
/*     */       //   54: dup
/*     */       //   55: astore_3
/*     */       //   56: aload #4
/*     */       //   58: if_acmpne -> 65
/*     */       //   61: iconst_1
/*     */       //   62: goto -> 117
/*     */       //   65: aload_3
/*     */       //   66: ifnonnull -> 73
/*     */       //   69: iconst_0
/*     */       //   70: goto -> 117
/*     */       //   73: aload_3
/*     */       //   74: instanceof java/lang/Number
/*     */       //   77: ifeq -> 92
/*     */       //   80: aload_3
/*     */       //   81: checkcast java/lang/Number
/*     */       //   84: aload #4
/*     */       //   86: invokestatic equalsNumObject : (Ljava/lang/Number;Ljava/lang/Object;)Z
/*     */       //   89: goto -> 117
/*     */       //   92: aload_3
/*     */       //   93: instanceof java/lang/Character
/*     */       //   96: ifeq -> 111
/*     */       //   99: aload_3
/*     */       //   100: checkcast java/lang/Character
/*     */       //   103: aload #4
/*     */       //   105: invokestatic equalsCharObject : (Ljava/lang/Character;Ljava/lang/Object;)Z
/*     */       //   108: goto -> 117
/*     */       //   111: aload_3
/*     */       //   112: aload #4
/*     */       //   114: invokevirtual equals : (Ljava/lang/Object;)Z
/*     */       //   117: ifeq -> 165
/*     */       //   120: aload_0
/*     */       //   121: invokevirtual next : ()Lscala/util/parsing/input/Reader;
/*     */       //   124: aload #6
/*     */       //   126: invokevirtual next : ()Lscala/util/parsing/input/Reader;
/*     */       //   129: astore #5
/*     */       //   131: dup
/*     */       //   132: ifnonnull -> 144
/*     */       //   135: pop
/*     */       //   136: aload #5
/*     */       //   138: ifnull -> 152
/*     */       //   141: goto -> 165
/*     */       //   144: aload #5
/*     */       //   146: invokevirtual equals : (Ljava/lang/Object;)Z
/*     */       //   149: ifeq -> 165
/*     */       //   152: aload #6
/*     */       //   154: aload_0
/*     */       //   155: invokevirtual canEqual : (Ljava/lang/Object;)Z
/*     */       //   158: ifeq -> 165
/*     */       //   161: iconst_1
/*     */       //   162: goto -> 166
/*     */       //   165: iconst_0
/*     */       //   166: ifeq -> 173
/*     */       //   169: iconst_1
/*     */       //   170: goto -> 174
/*     */       //   173: iconst_0
/*     */       //   174: ireturn
/*     */       // Line number table:
/*     */       //   Java source line number -> byte code offset
/*     */       //   #135	-> 0
/*     */       //   #236	-> 26
/*     */       //   #135	-> 33
/*     */       // Local variable table:
/*     */       //   start	length	slot	name	descriptor
/*     */       //   0	175	0	this	Lscala/util/parsing/combinator/Parsers$Success;
/*     */       //   0	175	1	x$1	Ljava/lang/Object;
/*     */     }
/*     */     
/*     */     public Success(Parsers $outer, Object result, Reader<Object> next) {
/* 135 */       super($outer);
/* 135 */       Product.class.$init$(this);
/* 155 */       this.successful = true;
/*     */     }
/*     */     
/*     */     public <U> Success<U> map(Function1 f) {
/*     */       return new Success(scala$util$parsing$combinator$Parsers$Success$$$outer(), (T)f.apply(result()), next());
/*     */     }
/*     */     
/*     */     public <U> Parsers.ParseResult<U> mapPartial(PartialFunction f, Function1 error) {
/*     */       return f.isDefinedAt(result()) ? new Success(scala$util$parsing$combinator$Parsers$Success$$$outer(), (T)f.apply(result()), next()) : new Parsers.Failure(scala$util$parsing$combinator$Parsers$Success$$$outer(), (String)error.apply(result()), next());
/*     */     }
/*     */     
/*     */     public <U> Parsers.ParseResult<U> flatMapWithNext(Function1 f) {
/*     */       return (Parsers.ParseResult<U>)((Function1)f.apply(result())).apply(next());
/*     */     }
/*     */     
/*     */     public Parsers.ParseResult<T> filterWithError(Function1 p, Function1 error, Reader position) {
/*     */       return BoxesRunTime.unboxToBoolean(p.apply(result())) ? this : new Parsers.Failure(scala$util$parsing$combinator$Parsers$Success$$$outer(), (String)error.apply(result()), position);
/*     */     }
/*     */     
/*     */     public <U> Parsers.ParseResult<U> append(Function0 a) {
/*     */       return this;
/*     */     }
/*     */     
/*     */     public T get() {
/*     */       return result();
/*     */     }
/*     */     
/*     */     public String toString() {
/*     */       return (new StringBuilder()).append("[").append(next().pos()).append("] parsed: ").append(result()).toString();
/*     */     }
/*     */     
/*     */     public boolean successful() {
/* 155 */       return this.successful;
/*     */     }
/*     */   }
/*     */   
/*     */   public abstract class NoSuccess extends ParseResult<scala.runtime.Nothing$> {
/*     */     private final String msg;
/*     */     
/*     */     private final Reader<Object> next;
/*     */     
/*     */     private final boolean successful;
/*     */     
/*     */     public String msg() {
/* 167 */       return this.msg;
/*     */     }
/*     */     
/*     */     public Reader<Object> next() {
/* 167 */       return this.next;
/*     */     }
/*     */     
/*     */     public NoSuccess(Parsers $outer, String msg, Reader next) {
/*     */       // Byte code:
/*     */       //   0: aload_0
/*     */       //   1: aload_2
/*     */       //   2: putfield msg : Ljava/lang/String;
/*     */       //   5: aload_0
/*     */       //   6: aload_3
/*     */       //   7: putfield next : Lscala/util/parsing/input/Reader;
/*     */       //   10: aload_0
/*     */       //   11: aload_1
/*     */       //   12: invokespecial <init> : (Lscala/util/parsing/combinator/Parsers;)V
/*     */       //   15: aload_0
/*     */       //   16: iconst_0
/*     */       //   17: putfield successful : Z
/*     */       //   20: aload_1
/*     */       //   21: invokeinterface scala$util$parsing$combinator$Parsers$$lastNoSuccessVar : ()Lscala/util/DynamicVariable;
/*     */       //   26: invokevirtual value : ()Ljava/lang/Object;
/*     */       //   29: checkcast scala/Option
/*     */       //   32: dup
/*     */       //   33: astore #4
/*     */       //   35: invokevirtual isEmpty : ()Z
/*     */       //   38: ifne -> 82
/*     */       //   41: aload #4
/*     */       //   43: invokevirtual get : ()Ljava/lang/Object;
/*     */       //   46: checkcast scala/util/parsing/combinator/Parsers$NoSuccess
/*     */       //   49: astore #6
/*     */       //   51: aload_0
/*     */       //   52: invokevirtual next : ()Lscala/util/parsing/input/Reader;
/*     */       //   55: invokevirtual pos : ()Lscala/util/parsing/input/Position;
/*     */       //   58: aload #6
/*     */       //   60: invokevirtual next : ()Lscala/util/parsing/input/Reader;
/*     */       //   63: invokevirtual pos : ()Lscala/util/parsing/input/Position;
/*     */       //   66: invokeinterface $less : (Lscala/util/parsing/input/Position;)Z
/*     */       //   71: ifeq -> 78
/*     */       //   74: iconst_0
/*     */       //   75: goto -> 79
/*     */       //   78: iconst_1
/*     */       //   79: ifeq -> 86
/*     */       //   82: iconst_1
/*     */       //   83: goto -> 87
/*     */       //   86: iconst_0
/*     */       //   87: ifeq -> 107
/*     */       //   90: aload_1
/*     */       //   91: invokeinterface scala$util$parsing$combinator$Parsers$$lastNoSuccessVar : ()Lscala/util/DynamicVariable;
/*     */       //   96: new scala/Some
/*     */       //   99: dup
/*     */       //   100: aload_0
/*     */       //   101: invokespecial <init> : (Ljava/lang/Object;)V
/*     */       //   104: invokevirtual value_$eq : (Ljava/lang/Object;)V
/*     */       //   107: return
/*     */       // Line number table:
/*     */       //   Java source line number -> byte code offset
/*     */       //   #167	-> 0
/*     */       //   #168	-> 15
/*     */       //   #170	-> 20
/*     */       //   #171	-> 90
/*     */       //   #167	-> 107
/*     */       // Local variable table:
/*     */       //   start	length	slot	name	descriptor
/*     */       //   0	108	0	this	Lscala/util/parsing/combinator/Parsers$NoSuccess;
/*     */       //   0	108	1	$outer	Lscala/util/parsing/combinator/Parsers;
/*     */       //   0	108	2	msg	Ljava/lang/String;
/*     */       //   0	108	3	next	Lscala/util/parsing/input/Reader;
/*     */     }
/*     */     
/*     */     public boolean successful() {
/* 168 */       return this.successful;
/*     */     }
/*     */     
/*     */     public <U> NoSuccess map(Function1 f) {
/* 173 */       return this;
/*     */     }
/*     */     
/*     */     public <U> Parsers.ParseResult<U> mapPartial(PartialFunction f, Function1 error) {
/* 174 */       return this;
/*     */     }
/*     */     
/*     */     public <U> Parsers.ParseResult<U> flatMapWithNext(Function1 f) {
/* 177 */       return this;
/*     */     }
/*     */     
/*     */     public Parsers.ParseResult<scala.runtime.Nothing$> filterWithError(Function1 p, Function1 error, Reader position) {
/* 179 */       return this;
/*     */     }
/*     */     
/*     */     public scala.runtime.Nothing$ get() {
/* 181 */       return scala.sys.package$.MODULE$.error("No result when parsing failed");
/*     */     }
/*     */   }
/*     */   
/*     */   public class NoSuccess$ {
/*     */     public NoSuccess$(Parsers $outer) {}
/*     */     
/*     */     public <T> Option<Tuple2<String, Reader<Object>>> unapply(Parsers.ParseResult x) {
/*     */       scala.None$ none$;
/* 185 */       if (x instanceof Parsers.Failure) {
/* 185 */         Parsers.Failure failure = (Parsers.Failure)x;
/* 186 */         Some some = new Some(new Tuple2(failure.msg(), failure.next()));
/*     */       } else {
/* 187 */         if (x instanceof Parsers.Error)
/* 187 */           Parsers.Error error = (Parsers.Error)x; 
/* 188 */         none$ = scala.None$.MODULE$;
/*     */       } 
/*     */       return (Option<Tuple2<String, Reader<Object>>>)none$;
/*     */     }
/*     */   }
/*     */   
/*     */   public class Failure$ extends AbstractFunction2<String, Reader<Object>, Failure> implements Serializable {
/*     */     public final String toString() {
/* 198 */       return "Failure";
/*     */     }
/*     */     
/*     */     public Parsers.Failure apply(String msg, Reader<Object> next) {
/* 198 */       return new Parsers.Failure(this.$outer, msg, next);
/*     */     }
/*     */     
/*     */     public Option<Tuple2<String, Reader<Object>>> unapply(Parsers.Failure x$0) {
/* 198 */       return (x$0 == null) ? (Option<Tuple2<String, Reader<Object>>>)scala.None$.MODULE$ : (Option<Tuple2<String, Reader<Object>>>)new Some(new Tuple2(x$0.msg(), x$0.next()));
/*     */     }
/*     */     
/*     */     private Object readResolve() {
/* 198 */       return this.$outer.Failure();
/*     */     }
/*     */     
/*     */     public Failure$(Parsers $outer) {}
/*     */   }
/*     */   
/*     */   public class Failure extends NoSuccess implements Product, Serializable {
/*     */     public String msg() {
/* 198 */       return super.msg();
/*     */     }
/*     */     
/*     */     public Reader<Object> next() {
/* 198 */       return super.next();
/*     */     }
/*     */     
/*     */     public Failure copy(String msg, Reader<Object> next) {
/* 198 */       return new Failure(scala$util$parsing$combinator$Parsers$Failure$$$outer(), msg, next);
/*     */     }
/*     */     
/*     */     public String copy$default$1() {
/* 198 */       return msg();
/*     */     }
/*     */     
/*     */     public Reader<Object> copy$default$2() {
/* 198 */       return next();
/*     */     }
/*     */     
/*     */     public String productPrefix() {
/* 198 */       return "Failure";
/*     */     }
/*     */     
/*     */     public int productArity() {
/* 198 */       return 2;
/*     */     }
/*     */     
/*     */     public Object productElement(int x$1) {
/* 198 */       switch (x$1) {
/*     */         default:
/* 198 */           throw new IndexOutOfBoundsException(BoxesRunTime.boxToInteger(x$1).toString());
/*     */         case 1:
/*     */         
/*     */         case 0:
/*     */           break;
/*     */       } 
/* 198 */       return msg();
/*     */     }
/*     */     
/*     */     public Iterator<Object> productIterator() {
/* 198 */       return scala.runtime.ScalaRunTime$.MODULE$.typedProductIterator(this);
/*     */     }
/*     */     
/*     */     public boolean canEqual(Object x$1) {
/* 198 */       return x$1 instanceof Failure;
/*     */     }
/*     */     
/*     */     public int hashCode() {
/* 198 */       return scala.runtime.ScalaRunTime$.MODULE$._hashCode(this);
/*     */     }
/*     */     
/*     */     public boolean equals(Object x$1) {
/*     */       // Byte code:
/*     */       //   0: aload_0
/*     */       //   1: aload_1
/*     */       //   2: if_acmpeq -> 121
/*     */       //   5: aload_1
/*     */       //   6: instanceof scala/util/parsing/combinator/Parsers$Failure
/*     */       //   9: ifeq -> 31
/*     */       //   12: aload_1
/*     */       //   13: checkcast scala/util/parsing/combinator/Parsers$Failure
/*     */       //   16: invokevirtual scala$util$parsing$combinator$Parsers$Failure$$$outer : ()Lscala/util/parsing/combinator/Parsers;
/*     */       //   19: aload_0
/*     */       //   20: invokevirtual scala$util$parsing$combinator$Parsers$Failure$$$outer : ()Lscala/util/parsing/combinator/Parsers;
/*     */       //   23: if_acmpne -> 31
/*     */       //   26: iconst_1
/*     */       //   27: istore_2
/*     */       //   28: goto -> 33
/*     */       //   31: iconst_0
/*     */       //   32: istore_2
/*     */       //   33: iload_2
/*     */       //   34: ifeq -> 125
/*     */       //   37: aload_1
/*     */       //   38: checkcast scala/util/parsing/combinator/Parsers$Failure
/*     */       //   41: astore #5
/*     */       //   43: aload_0
/*     */       //   44: invokevirtual msg : ()Ljava/lang/String;
/*     */       //   47: aload #5
/*     */       //   49: invokevirtual msg : ()Ljava/lang/String;
/*     */       //   52: astore_3
/*     */       //   53: dup
/*     */       //   54: ifnonnull -> 65
/*     */       //   57: pop
/*     */       //   58: aload_3
/*     */       //   59: ifnull -> 72
/*     */       //   62: goto -> 117
/*     */       //   65: aload_3
/*     */       //   66: invokevirtual equals : (Ljava/lang/Object;)Z
/*     */       //   69: ifeq -> 117
/*     */       //   72: aload_0
/*     */       //   73: invokevirtual next : ()Lscala/util/parsing/input/Reader;
/*     */       //   76: aload #5
/*     */       //   78: invokevirtual next : ()Lscala/util/parsing/input/Reader;
/*     */       //   81: astore #4
/*     */       //   83: dup
/*     */       //   84: ifnonnull -> 96
/*     */       //   87: pop
/*     */       //   88: aload #4
/*     */       //   90: ifnull -> 104
/*     */       //   93: goto -> 117
/*     */       //   96: aload #4
/*     */       //   98: invokevirtual equals : (Ljava/lang/Object;)Z
/*     */       //   101: ifeq -> 117
/*     */       //   104: aload #5
/*     */       //   106: aload_0
/*     */       //   107: invokevirtual canEqual : (Ljava/lang/Object;)Z
/*     */       //   110: ifeq -> 117
/*     */       //   113: iconst_1
/*     */       //   114: goto -> 118
/*     */       //   117: iconst_0
/*     */       //   118: ifeq -> 125
/*     */       //   121: iconst_1
/*     */       //   122: goto -> 126
/*     */       //   125: iconst_0
/*     */       //   126: ireturn
/*     */       // Line number table:
/*     */       //   Java source line number -> byte code offset
/*     */       //   #198	-> 0
/*     */       //   #236	-> 26
/*     */       //   #198	-> 33
/*     */       // Local variable table:
/*     */       //   start	length	slot	name	descriptor
/*     */       //   0	127	0	this	Lscala/util/parsing/combinator/Parsers$Failure;
/*     */       //   0	127	1	x$1	Ljava/lang/Object;
/*     */     }
/*     */     
/*     */     public Failure(Parsers $outer, String msg, Reader<Object> next) {
/* 198 */       super($outer, msg, next);
/* 198 */       Product.class.$init$(this);
/*     */     }
/*     */     
/*     */     public String toString() {
/* 200 */       return (new StringBuilder()).append("[").append(next().pos()).append("] failure: ").append(msg()).append("\n\n").append(next().pos().longString()).toString();
/*     */     }
/*     */     
/*     */     public <U> Parsers.ParseResult<U> append(Function0 a) {
/* 202 */       Parsers.ParseResult alt = (Parsers.ParseResult)a.apply();
/* 203 */       if (alt instanceof Parsers.Success) {
/* 203 */         Parsers.ParseResult parseResult = alt;
/*     */       } else {
/* 204 */         if (alt instanceof Parsers.NoSuccess)
/* 204 */           return alt.next().pos().$less(next().pos()) ? this : alt; 
/*     */         throw new MatchError(alt);
/*     */       } 
/*     */       return (Parsers.ParseResult<U>)SYNTHETIC_LOCAL_VARIABLE_2;
/*     */     }
/*     */   }
/*     */   
/*     */   public class Error$ extends AbstractFunction2<String, Reader<Object>, Error> implements Serializable {
/*     */     public final String toString() {
/* 215 */       return "Error";
/*     */     }
/*     */     
/*     */     public Parsers.Error apply(String msg, Reader<Object> next) {
/* 215 */       return new Parsers.Error(this.$outer, msg, next);
/*     */     }
/*     */     
/*     */     public Option<Tuple2<String, Reader<Object>>> unapply(Parsers.Error x$0) {
/* 215 */       return (x$0 == null) ? (Option<Tuple2<String, Reader<Object>>>)scala.None$.MODULE$ : (Option<Tuple2<String, Reader<Object>>>)new Some(new Tuple2(x$0.msg(), x$0.next()));
/*     */     }
/*     */     
/*     */     private Object readResolve() {
/* 215 */       return this.$outer.Error();
/*     */     }
/*     */     
/*     */     public Error$(Parsers $outer) {}
/*     */   }
/*     */   
/*     */   public class Error extends NoSuccess implements Product, Serializable {
/*     */     public String msg() {
/* 215 */       return super.msg();
/*     */     }
/*     */     
/*     */     public Reader<Object> next() {
/* 215 */       return super.next();
/*     */     }
/*     */     
/*     */     public Error copy(String msg, Reader<Object> next) {
/* 215 */       return new Error(scala$util$parsing$combinator$Parsers$Error$$$outer(), msg, next);
/*     */     }
/*     */     
/*     */     public String copy$default$1() {
/* 215 */       return msg();
/*     */     }
/*     */     
/*     */     public Reader<Object> copy$default$2() {
/* 215 */       return next();
/*     */     }
/*     */     
/*     */     public String productPrefix() {
/* 215 */       return "Error";
/*     */     }
/*     */     
/*     */     public int productArity() {
/* 215 */       return 2;
/*     */     }
/*     */     
/*     */     public Object productElement(int x$1) {
/* 215 */       switch (x$1) {
/*     */         default:
/* 215 */           throw new IndexOutOfBoundsException(BoxesRunTime.boxToInteger(x$1).toString());
/*     */         case 1:
/*     */         
/*     */         case 0:
/*     */           break;
/*     */       } 
/* 215 */       return msg();
/*     */     }
/*     */     
/*     */     public Iterator<Object> productIterator() {
/* 215 */       return scala.runtime.ScalaRunTime$.MODULE$.typedProductIterator(this);
/*     */     }
/*     */     
/*     */     public boolean canEqual(Object x$1) {
/* 215 */       return x$1 instanceof Error;
/*     */     }
/*     */     
/*     */     public int hashCode() {
/* 215 */       return scala.runtime.ScalaRunTime$.MODULE$._hashCode(this);
/*     */     }
/*     */     
/*     */     public boolean equals(Object x$1) {
/*     */       // Byte code:
/*     */       //   0: aload_0
/*     */       //   1: aload_1
/*     */       //   2: if_acmpeq -> 121
/*     */       //   5: aload_1
/*     */       //   6: instanceof scala/util/parsing/combinator/Parsers$Error
/*     */       //   9: ifeq -> 31
/*     */       //   12: aload_1
/*     */       //   13: checkcast scala/util/parsing/combinator/Parsers$Error
/*     */       //   16: invokevirtual scala$util$parsing$combinator$Parsers$Error$$$outer : ()Lscala/util/parsing/combinator/Parsers;
/*     */       //   19: aload_0
/*     */       //   20: invokevirtual scala$util$parsing$combinator$Parsers$Error$$$outer : ()Lscala/util/parsing/combinator/Parsers;
/*     */       //   23: if_acmpne -> 31
/*     */       //   26: iconst_1
/*     */       //   27: istore_2
/*     */       //   28: goto -> 33
/*     */       //   31: iconst_0
/*     */       //   32: istore_2
/*     */       //   33: iload_2
/*     */       //   34: ifeq -> 125
/*     */       //   37: aload_1
/*     */       //   38: checkcast scala/util/parsing/combinator/Parsers$Error
/*     */       //   41: astore #5
/*     */       //   43: aload_0
/*     */       //   44: invokevirtual msg : ()Ljava/lang/String;
/*     */       //   47: aload #5
/*     */       //   49: invokevirtual msg : ()Ljava/lang/String;
/*     */       //   52: astore_3
/*     */       //   53: dup
/*     */       //   54: ifnonnull -> 65
/*     */       //   57: pop
/*     */       //   58: aload_3
/*     */       //   59: ifnull -> 72
/*     */       //   62: goto -> 117
/*     */       //   65: aload_3
/*     */       //   66: invokevirtual equals : (Ljava/lang/Object;)Z
/*     */       //   69: ifeq -> 117
/*     */       //   72: aload_0
/*     */       //   73: invokevirtual next : ()Lscala/util/parsing/input/Reader;
/*     */       //   76: aload #5
/*     */       //   78: invokevirtual next : ()Lscala/util/parsing/input/Reader;
/*     */       //   81: astore #4
/*     */       //   83: dup
/*     */       //   84: ifnonnull -> 96
/*     */       //   87: pop
/*     */       //   88: aload #4
/*     */       //   90: ifnull -> 104
/*     */       //   93: goto -> 117
/*     */       //   96: aload #4
/*     */       //   98: invokevirtual equals : (Ljava/lang/Object;)Z
/*     */       //   101: ifeq -> 117
/*     */       //   104: aload #5
/*     */       //   106: aload_0
/*     */       //   107: invokevirtual canEqual : (Ljava/lang/Object;)Z
/*     */       //   110: ifeq -> 117
/*     */       //   113: iconst_1
/*     */       //   114: goto -> 118
/*     */       //   117: iconst_0
/*     */       //   118: ifeq -> 125
/*     */       //   121: iconst_1
/*     */       //   122: goto -> 126
/*     */       //   125: iconst_0
/*     */       //   126: ireturn
/*     */       // Line number table:
/*     */       //   Java source line number -> byte code offset
/*     */       //   #215	-> 0
/*     */       //   #236	-> 26
/*     */       //   #215	-> 33
/*     */       // Local variable table:
/*     */       //   start	length	slot	name	descriptor
/*     */       //   0	127	0	this	Lscala/util/parsing/combinator/Parsers$Error;
/*     */       //   0	127	1	x$1	Ljava/lang/Object;
/*     */     }
/*     */     
/*     */     public Error(Parsers $outer, String msg, Reader<Object> next) {
/* 215 */       super($outer, msg, next);
/* 215 */       Product.class.$init$(this);
/*     */     }
/*     */     
/*     */     public String toString() {
/* 217 */       return (new StringBuilder()).append("[").append(next().pos()).append("] error: ").append(msg()).append("\n\n").append(next().pos().longString()).toString();
/*     */     }
/*     */     
/*     */     public <U> Parsers.ParseResult<U> append(Function0 a) {
/* 218 */       return this;
/*     */     }
/*     */   }
/*     */   
/*     */   public class Parsers$$anon$3 extends Parser<T> {
/*     */     private final Function1 f$4;
/*     */     
/*     */     public Parsers.ParseResult<T> apply(Reader in) {
/* 222 */       return (Parsers.ParseResult<T>)this.f$4.apply(in);
/*     */     }
/*     */     
/*     */     public Parsers$$anon$3(Parsers $outer, Function1 f$4) {
/* 222 */       super($outer);
/*     */     }
/*     */   }
/*     */   
/*     */   public class Parsers$$anon$1 extends Parser<T> implements OnceParser<T> {
/*     */     private final Function1 f$5;
/*     */     
/*     */     public <U> Parsers.Parser<Parsers.$tilde<T, U>> $tilde(Function0 p) {
/* 225 */       return Parsers.OnceParser$class.$tilde(this, p);
/*     */     }
/*     */     
/*     */     public Parsers.ParseResult<T> apply(Reader in) {
/* 225 */       return (Parsers.ParseResult<T>)this.f$5.apply(in);
/*     */     }
/*     */     
/*     */     public Parsers$$anon$1(Parsers $outer, Function1 f$5) {
/* 225 */       super($outer);
/* 225 */       Parsers.OnceParser$class.$init$(this);
/*     */     }
/*     */   }
/*     */   
/*     */   public abstract class Parser<T> implements Function1<Reader<Object>, ParseResult<T>> {
/*     */     private String name;
/*     */     
/*     */     public boolean apply$mcZD$sp(double v1) {
/* 230 */       return Function1.class.apply$mcZD$sp(this, v1);
/*     */     }
/*     */     
/*     */     public double apply$mcDD$sp(double v1) {
/* 230 */       return Function1.class.apply$mcDD$sp(this, v1);
/*     */     }
/*     */     
/*     */     public float apply$mcFD$sp(double v1) {
/* 230 */       return Function1.class.apply$mcFD$sp(this, v1);
/*     */     }
/*     */     
/*     */     public int apply$mcID$sp(double v1) {
/* 230 */       return Function1.class.apply$mcID$sp(this, v1);
/*     */     }
/*     */     
/*     */     public long apply$mcJD$sp(double v1) {
/* 230 */       return Function1.class.apply$mcJD$sp(this, v1);
/*     */     }
/*     */     
/*     */     public void apply$mcVD$sp(double v1) {
/* 230 */       Function1.class.apply$mcVD$sp(this, v1);
/*     */     }
/*     */     
/*     */     public boolean apply$mcZF$sp(float v1) {
/* 230 */       return Function1.class.apply$mcZF$sp(this, v1);
/*     */     }
/*     */     
/*     */     public double apply$mcDF$sp(float v1) {
/* 230 */       return Function1.class.apply$mcDF$sp(this, v1);
/*     */     }
/*     */     
/*     */     public float apply$mcFF$sp(float v1) {
/* 230 */       return Function1.class.apply$mcFF$sp(this, v1);
/*     */     }
/*     */     
/*     */     public int apply$mcIF$sp(float v1) {
/* 230 */       return Function1.class.apply$mcIF$sp(this, v1);
/*     */     }
/*     */     
/*     */     public long apply$mcJF$sp(float v1) {
/* 230 */       return Function1.class.apply$mcJF$sp(this, v1);
/*     */     }
/*     */     
/*     */     public void apply$mcVF$sp(float v1) {
/* 230 */       Function1.class.apply$mcVF$sp(this, v1);
/*     */     }
/*     */     
/*     */     public boolean apply$mcZI$sp(int v1) {
/* 230 */       return Function1.class.apply$mcZI$sp(this, v1);
/*     */     }
/*     */     
/*     */     public double apply$mcDI$sp(int v1) {
/* 230 */       return Function1.class.apply$mcDI$sp(this, v1);
/*     */     }
/*     */     
/*     */     public float apply$mcFI$sp(int v1) {
/* 230 */       return Function1.class.apply$mcFI$sp(this, v1);
/*     */     }
/*     */     
/*     */     public int apply$mcII$sp(int v1) {
/* 230 */       return Function1.class.apply$mcII$sp(this, v1);
/*     */     }
/*     */     
/*     */     public long apply$mcJI$sp(int v1) {
/* 230 */       return Function1.class.apply$mcJI$sp(this, v1);
/*     */     }
/*     */     
/*     */     public void apply$mcVI$sp(int v1) {
/* 230 */       Function1.class.apply$mcVI$sp(this, v1);
/*     */     }
/*     */     
/*     */     public boolean apply$mcZJ$sp(long v1) {
/* 230 */       return Function1.class.apply$mcZJ$sp(this, v1);
/*     */     }
/*     */     
/*     */     public double apply$mcDJ$sp(long v1) {
/* 230 */       return Function1.class.apply$mcDJ$sp(this, v1);
/*     */     }
/*     */     
/*     */     public float apply$mcFJ$sp(long v1) {
/* 230 */       return Function1.class.apply$mcFJ$sp(this, v1);
/*     */     }
/*     */     
/*     */     public int apply$mcIJ$sp(long v1) {
/* 230 */       return Function1.class.apply$mcIJ$sp(this, v1);
/*     */     }
/*     */     
/*     */     public long apply$mcJJ$sp(long v1) {
/* 230 */       return Function1.class.apply$mcJJ$sp(this, v1);
/*     */     }
/*     */     
/*     */     public void apply$mcVJ$sp(long v1) {
/* 230 */       Function1.class.apply$mcVJ$sp(this, v1);
/*     */     }
/*     */     
/*     */     public <A> Function1<A, Parsers.ParseResult<T>> compose(Function1 g) {
/* 230 */       return Function1.class.compose(this, g);
/*     */     }
/*     */     
/*     */     public <A> Function1<A, Object> compose$mcZD$sp(Function1 g) {
/* 230 */       return Function1.class.compose$mcZD$sp(this, g);
/*     */     }
/*     */     
/*     */     public <A> Function1<A, Object> compose$mcDD$sp(Function1 g) {
/* 230 */       return Function1.class.compose$mcDD$sp(this, g);
/*     */     }
/*     */     
/*     */     public <A> Function1<A, Object> compose$mcFD$sp(Function1 g) {
/* 230 */       return Function1.class.compose$mcFD$sp(this, g);
/*     */     }
/*     */     
/*     */     public <A> Function1<A, Object> compose$mcID$sp(Function1 g) {
/* 230 */       return Function1.class.compose$mcID$sp(this, g);
/*     */     }
/*     */     
/*     */     public <A> Function1<A, Object> compose$mcJD$sp(Function1 g) {
/* 230 */       return Function1.class.compose$mcJD$sp(this, g);
/*     */     }
/*     */     
/*     */     public <A> Function1<A, BoxedUnit> compose$mcVD$sp(Function1 g) {
/* 230 */       return Function1.class.compose$mcVD$sp(this, g);
/*     */     }
/*     */     
/*     */     public <A> Function1<A, Object> compose$mcZF$sp(Function1 g) {
/* 230 */       return Function1.class.compose$mcZF$sp(this, g);
/*     */     }
/*     */     
/*     */     public <A> Function1<A, Object> compose$mcDF$sp(Function1 g) {
/* 230 */       return Function1.class.compose$mcDF$sp(this, g);
/*     */     }
/*     */     
/*     */     public <A> Function1<A, Object> compose$mcFF$sp(Function1 g) {
/* 230 */       return Function1.class.compose$mcFF$sp(this, g);
/*     */     }
/*     */     
/*     */     public <A> Function1<A, Object> compose$mcIF$sp(Function1 g) {
/* 230 */       return Function1.class.compose$mcIF$sp(this, g);
/*     */     }
/*     */     
/*     */     public <A> Function1<A, Object> compose$mcJF$sp(Function1 g) {
/* 230 */       return Function1.class.compose$mcJF$sp(this, g);
/*     */     }
/*     */     
/*     */     public <A> Function1<A, BoxedUnit> compose$mcVF$sp(Function1 g) {
/* 230 */       return Function1.class.compose$mcVF$sp(this, g);
/*     */     }
/*     */     
/*     */     public <A> Function1<A, Object> compose$mcZI$sp(Function1 g) {
/* 230 */       return Function1.class.compose$mcZI$sp(this, g);
/*     */     }
/*     */     
/*     */     public <A> Function1<A, Object> compose$mcDI$sp(Function1 g) {
/* 230 */       return Function1.class.compose$mcDI$sp(this, g);
/*     */     }
/*     */     
/*     */     public <A> Function1<A, Object> compose$mcFI$sp(Function1 g) {
/* 230 */       return Function1.class.compose$mcFI$sp(this, g);
/*     */     }
/*     */     
/*     */     public <A> Function1<A, Object> compose$mcII$sp(Function1 g) {
/* 230 */       return Function1.class.compose$mcII$sp(this, g);
/*     */     }
/*     */     
/*     */     public <A> Function1<A, Object> compose$mcJI$sp(Function1 g) {
/* 230 */       return Function1.class.compose$mcJI$sp(this, g);
/*     */     }
/*     */     
/*     */     public <A> Function1<A, BoxedUnit> compose$mcVI$sp(Function1 g) {
/* 230 */       return Function1.class.compose$mcVI$sp(this, g);
/*     */     }
/*     */     
/*     */     public <A> Function1<A, Object> compose$mcZJ$sp(Function1 g) {
/* 230 */       return Function1.class.compose$mcZJ$sp(this, g);
/*     */     }
/*     */     
/*     */     public <A> Function1<A, Object> compose$mcDJ$sp(Function1 g) {
/* 230 */       return Function1.class.compose$mcDJ$sp(this, g);
/*     */     }
/*     */     
/*     */     public <A> Function1<A, Object> compose$mcFJ$sp(Function1 g) {
/* 230 */       return Function1.class.compose$mcFJ$sp(this, g);
/*     */     }
/*     */     
/*     */     public <A> Function1<A, Object> compose$mcIJ$sp(Function1 g) {
/* 230 */       return Function1.class.compose$mcIJ$sp(this, g);
/*     */     }
/*     */     
/*     */     public <A> Function1<A, Object> compose$mcJJ$sp(Function1 g) {
/* 230 */       return Function1.class.compose$mcJJ$sp(this, g);
/*     */     }
/*     */     
/*     */     public <A> Function1<A, BoxedUnit> compose$mcVJ$sp(Function1 g) {
/* 230 */       return Function1.class.compose$mcVJ$sp(this, g);
/*     */     }
/*     */     
/*     */     public <A> Function1<Reader<Object>, A> andThen(Function1 g) {
/* 230 */       return Function1.class.andThen(this, g);
/*     */     }
/*     */     
/*     */     public <A> Function1<Object, A> andThen$mcZD$sp(Function1 g) {
/* 230 */       return Function1.class.andThen$mcZD$sp(this, g);
/*     */     }
/*     */     
/*     */     public <A> Function1<Object, A> andThen$mcDD$sp(Function1 g) {
/* 230 */       return Function1.class.andThen$mcDD$sp(this, g);
/*     */     }
/*     */     
/*     */     public <A> Function1<Object, A> andThen$mcFD$sp(Function1 g) {
/* 230 */       return Function1.class.andThen$mcFD$sp(this, g);
/*     */     }
/*     */     
/*     */     public <A> Function1<Object, A> andThen$mcID$sp(Function1 g) {
/* 230 */       return Function1.class.andThen$mcID$sp(this, g);
/*     */     }
/*     */     
/*     */     public <A> Function1<Object, A> andThen$mcJD$sp(Function1 g) {
/* 230 */       return Function1.class.andThen$mcJD$sp(this, g);
/*     */     }
/*     */     
/*     */     public <A> Function1<Object, A> andThen$mcVD$sp(Function1 g) {
/* 230 */       return Function1.class.andThen$mcVD$sp(this, g);
/*     */     }
/*     */     
/*     */     public <A> Function1<Object, A> andThen$mcZF$sp(Function1 g) {
/* 230 */       return Function1.class.andThen$mcZF$sp(this, g);
/*     */     }
/*     */     
/*     */     public <A> Function1<Object, A> andThen$mcDF$sp(Function1 g) {
/* 230 */       return Function1.class.andThen$mcDF$sp(this, g);
/*     */     }
/*     */     
/*     */     public <A> Function1<Object, A> andThen$mcFF$sp(Function1 g) {
/* 230 */       return Function1.class.andThen$mcFF$sp(this, g);
/*     */     }
/*     */     
/*     */     public <A> Function1<Object, A> andThen$mcIF$sp(Function1 g) {
/* 230 */       return Function1.class.andThen$mcIF$sp(this, g);
/*     */     }
/*     */     
/*     */     public <A> Function1<Object, A> andThen$mcJF$sp(Function1 g) {
/* 230 */       return Function1.class.andThen$mcJF$sp(this, g);
/*     */     }
/*     */     
/*     */     public <A> Function1<Object, A> andThen$mcVF$sp(Function1 g) {
/* 230 */       return Function1.class.andThen$mcVF$sp(this, g);
/*     */     }
/*     */     
/*     */     public <A> Function1<Object, A> andThen$mcZI$sp(Function1 g) {
/* 230 */       return Function1.class.andThen$mcZI$sp(this, g);
/*     */     }
/*     */     
/*     */     public <A> Function1<Object, A> andThen$mcDI$sp(Function1 g) {
/* 230 */       return Function1.class.andThen$mcDI$sp(this, g);
/*     */     }
/*     */     
/*     */     public <A> Function1<Object, A> andThen$mcFI$sp(Function1 g) {
/* 230 */       return Function1.class.andThen$mcFI$sp(this, g);
/*     */     }
/*     */     
/*     */     public <A> Function1<Object, A> andThen$mcII$sp(Function1 g) {
/* 230 */       return Function1.class.andThen$mcII$sp(this, g);
/*     */     }
/*     */     
/*     */     public <A> Function1<Object, A> andThen$mcJI$sp(Function1 g) {
/* 230 */       return Function1.class.andThen$mcJI$sp(this, g);
/*     */     }
/*     */     
/*     */     public <A> Function1<Object, A> andThen$mcVI$sp(Function1 g) {
/* 230 */       return Function1.class.andThen$mcVI$sp(this, g);
/*     */     }
/*     */     
/*     */     public <A> Function1<Object, A> andThen$mcZJ$sp(Function1 g) {
/* 230 */       return Function1.class.andThen$mcZJ$sp(this, g);
/*     */     }
/*     */     
/*     */     public <A> Function1<Object, A> andThen$mcDJ$sp(Function1 g) {
/* 230 */       return Function1.class.andThen$mcDJ$sp(this, g);
/*     */     }
/*     */     
/*     */     public <A> Function1<Object, A> andThen$mcFJ$sp(Function1 g) {
/* 230 */       return Function1.class.andThen$mcFJ$sp(this, g);
/*     */     }
/*     */     
/*     */     public <A> Function1<Object, A> andThen$mcIJ$sp(Function1 g) {
/* 230 */       return Function1.class.andThen$mcIJ$sp(this, g);
/*     */     }
/*     */     
/*     */     public <A> Function1<Object, A> andThen$mcJJ$sp(Function1 g) {
/* 230 */       return Function1.class.andThen$mcJJ$sp(this, g);
/*     */     }
/*     */     
/*     */     public <A> Function1<Object, A> andThen$mcVJ$sp(Function1 g) {
/* 230 */       return Function1.class.andThen$mcVJ$sp(this, g);
/*     */     }
/*     */     
/*     */     public Parser(Parsers $outer) {
/* 230 */       Function1.class.$init$(this);
/* 231 */       this.name = "";
/*     */     }
/*     */     
/*     */     private String name() {
/* 231 */       return this.name;
/*     */     }
/*     */     
/*     */     private void name_$eq(String x$1) {
/* 231 */       this.name = x$1;
/*     */     }
/*     */     
/*     */     public Parser<T> named(String n) {
/* 232 */       name_$eq(n);
/* 232 */       return this;
/*     */     }
/*     */     
/*     */     public String toString() {
/* 233 */       return (new StringBuilder()).append("Parser (").append(name()).append(")").toString();
/*     */     }
/*     */     
/*     */     public <U> Parser<U> flatMap(Function1 f) {
/* 239 */       return scala$util$parsing$combinator$Parsers$Parser$$$outer().Parser((Function1<Reader<Object>, Parsers.ParseResult<U>>)new Parsers$Parser$$anonfun$flatMap$1(this, (Parser<T>)f));
/*     */     }
/*     */     
/*     */     public class Parsers$Parser$$anonfun$flatMap$1 extends AbstractFunction1<Reader<Object>, Parsers.ParseResult<U>> implements Serializable {
/*     */       public static final long serialVersionUID = 0L;
/*     */       
/*     */       private final Function1 f$1;
/*     */       
/*     */       public final Parsers.ParseResult<U> apply(Reader in) {
/* 239 */         return this.$outer.apply(in).flatMapWithNext(this.f$1);
/*     */       }
/*     */       
/*     */       public Parsers$Parser$$anonfun$flatMap$1(Parsers.Parser $outer, Function1 f$1) {}
/*     */     }
/*     */     
/*     */     public <U> Parser<U> map(Function1 f) {
/* 242 */       return scala$util$parsing$combinator$Parsers$Parser$$$outer().Parser((Function1<Reader<Object>, Parsers.ParseResult<U>>)new Parsers$Parser$$anonfun$map$1(this, (Parser<T>)f));
/*     */     }
/*     */     
/*     */     public class Parsers$Parser$$anonfun$map$1 extends AbstractFunction1<Reader<Object>, Parsers.ParseResult<U>> implements Serializable {
/*     */       public static final long serialVersionUID = 0L;
/*     */       
/*     */       private final Function1 f$2;
/*     */       
/*     */       public final Parsers.ParseResult<U> apply(Reader in) {
/* 242 */         return this.$outer.apply(in).map(this.f$2);
/*     */       }
/*     */       
/*     */       public Parsers$Parser$$anonfun$map$1(Parsers.Parser $outer, Function1 f$2) {}
/*     */     }
/*     */     
/*     */     public Parser<T> filter(Function1<T, Object> p) {
/* 245 */       return withFilter(p);
/*     */     }
/*     */     
/*     */     public Parser<T> withFilter(Function1 p) {
/* 248 */       return scala$util$parsing$combinator$Parsers$Parser$$$outer().Parser((Function1<Reader<Object>, Parsers.ParseResult<T>>)new Parsers$Parser$$anonfun$withFilter$1(this, (Parser<T>)p));
/*     */     }
/*     */     
/*     */     public class Parsers$Parser$$anonfun$withFilter$1 extends AbstractFunction1<Reader<Object>, Parsers.ParseResult<T>> implements Serializable {
/*     */       public static final long serialVersionUID = 0L;
/*     */       
/*     */       private final Function1 p$1;
/*     */       
/*     */       public final Parsers.ParseResult<T> apply(Reader in) {
/* 248 */         return this.$outer.apply(in).filterWithError(this.p$1, (Function1<T, String>)new Parsers$Parser$$anonfun$withFilter$1$$anonfun$apply$1(this), in);
/*     */       }
/*     */       
/*     */       public Parsers$Parser$$anonfun$withFilter$1(Parsers.Parser $outer, Function1 p$1) {}
/*     */       
/*     */       public class Parsers$Parser$$anonfun$withFilter$1$$anonfun$apply$1 extends AbstractFunction1<T, String> implements Serializable {
/*     */         public static final long serialVersionUID = 0L;
/*     */         
/*     */         public final String apply(Object x$1) {
/* 248 */           return (new StringBuilder()).append("Input doesn't match filter: ").append(x$1).toString();
/*     */         }
/*     */         
/*     */         public Parsers$Parser$$anonfun$withFilter$1$$anonfun$apply$1(Parsers$Parser$$anonfun$withFilter$1 $outer) {}
/*     */       }
/*     */     }
/*     */     
/*     */     public <U> Parser<U> append(Function0 p0) {
/* 253 */       ObjectRef p$lzy = new ObjectRef(null);
/* 253 */       VolatileByteRef bitmap$0 = new VolatileByteRef((byte)0);
/* 254 */       return scala$util$parsing$combinator$Parsers$Parser$$$outer().Parser((Function1<Reader<Object>, Parsers.ParseResult<U>>)new Parsers$Parser$$anonfun$append$1(this, p0, p$lzy, (Parser<T>)bitmap$0));
/*     */     }
/*     */     
/*     */     private final Parser p$lzycompute$1(Function0 p0$1, ObjectRef p$lzy$1, VolatileByteRef bitmap$0$1) {
/*     */       synchronized (this) {
/*     */         if ((byte)(bitmap$0$1.elem & 0x1) == 0) {
/*     */           p$lzy$1.elem = p0$1.apply();
/*     */           bitmap$0$1.elem = (byte)(bitmap$0$1.elem | 0x1);
/*     */         } 
/*     */         /* monitor exit ThisExpression{InnerObjectType{ObjectType{scala/util/parsing/combinator/Parsers}.Lscala/util/parsing/combinator/Parsers$Parser;}} */
/*     */         return (Parser)p$lzy$1.elem;
/*     */       } 
/*     */     }
/*     */     
/*     */     public final Parser scala$util$parsing$combinator$Parsers$Parser$$p$2(Function0 p0$1, ObjectRef p$lzy$1, VolatileByteRef bitmap$0$1) {
/*     */       return ((byte)(bitmap$0$1.elem & 0x1) == 0) ? p$lzycompute$1(p0$1, p$lzy$1, bitmap$0$1) : (Parser)p$lzy$1.elem;
/*     */     }
/*     */     
/*     */     public class Parsers$Parser$$anonfun$append$1 extends AbstractFunction1<Reader<Object>, Parsers.ParseResult<U>> implements Serializable {
/*     */       public static final long serialVersionUID = 0L;
/*     */       
/*     */       public final Function0 p0$1;
/*     */       
/*     */       public final ObjectRef p$lzy$1;
/*     */       
/*     */       public final VolatileByteRef bitmap$0$1;
/*     */       
/*     */       public final Parsers.ParseResult<U> apply(Reader in) {
/* 254 */         return this.$outer.apply(in).append((Function0)new Parsers$Parser$$anonfun$append$1$$anonfun$apply$2(this, ($anonfun$append$1)in));
/*     */       }
/*     */       
/*     */       public Parsers$Parser$$anonfun$append$1(Parsers.Parser $outer, Function0 p0$1, ObjectRef p$lzy$1, VolatileByteRef bitmap$0$1) {}
/*     */       
/*     */       public class Parsers$Parser$$anonfun$append$1$$anonfun$apply$2 extends AbstractFunction0<Parsers.ParseResult<U>> implements Serializable {
/*     */         public static final long serialVersionUID = 0L;
/*     */         
/*     */         private final Reader in$2;
/*     */         
/*     */         public final Parsers.ParseResult<U> apply() {
/* 254 */           return this.$outer.$outer.scala$util$parsing$combinator$Parsers$Parser$$p$2(this.$outer.p0$1, this.$outer.p$lzy$1, this.$outer.bitmap$0$1).apply(this.in$2);
/*     */         }
/*     */         
/*     */         public Parsers$Parser$$anonfun$append$1$$anonfun$apply$2(Parsers$Parser$$anonfun$append$1 $outer, Reader in$2) {}
/*     */       }
/*     */     }
/*     */     
/*     */     public <U> Parser<Parsers.$tilde<T, U>> $tilde(Function0 q) {
/* 272 */       ObjectRef p$lzy = new ObjectRef(null);
/* 272 */       VolatileByteRef bitmap$0 = new VolatileByteRef((byte)0);
/* 273 */       return flatMap((Function1<?, Parser<Parsers.$tilde<T, U>>>)new Parsers$Parser$$anonfun$$tilde$1(this, q, p$lzy, (Parser<T>)bitmap$0)).named("~");
/*     */     }
/*     */     
/*     */     private final Parser p$lzycompute$2(Function0 q$1, ObjectRef p$lzy$2, VolatileByteRef bitmap$0$2) {
/*     */       synchronized (this) {
/*     */         if ((byte)(bitmap$0$2.elem & 0x1) == 0) {
/*     */           p$lzy$2.elem = q$1.apply();
/*     */           bitmap$0$2.elem = (byte)(bitmap$0$2.elem | 0x1);
/*     */         } 
/*     */         /* monitor exit ThisExpression{InnerObjectType{ObjectType{scala/util/parsing/combinator/Parsers}.Lscala/util/parsing/combinator/Parsers$Parser;}} */
/*     */         return (Parser)p$lzy$2.elem;
/*     */       } 
/*     */     }
/*     */     
/*     */     public final Parser scala$util$parsing$combinator$Parsers$Parser$$p$3(Function0 q$1, ObjectRef p$lzy$2, VolatileByteRef bitmap$0$2) {
/*     */       return ((byte)(bitmap$0$2.elem & 0x1) == 0) ? p$lzycompute$2(q$1, p$lzy$2, bitmap$0$2) : (Parser)p$lzy$2.elem;
/*     */     }
/*     */     
/*     */     public class Parsers$Parser$$anonfun$$tilde$1 extends AbstractFunction1<T, Parser<Parsers.$tilde<T, U>>> implements Serializable {
/*     */       public static final long serialVersionUID = 0L;
/*     */       
/*     */       private final Function0 q$1;
/*     */       
/*     */       private final ObjectRef p$lzy$2;
/*     */       
/*     */       private final VolatileByteRef bitmap$0$2;
/*     */       
/*     */       public final Parsers.Parser<Parsers.$tilde<T, U>> apply(Object a) {
/* 273 */         return this.$outer.scala$util$parsing$combinator$Parsers$Parser$$p$3(this.q$1, this.p$lzy$2, this.bitmap$0$2).map((Function1)new Parsers$Parser$$anonfun$$tilde$1$$anonfun$apply$3(this, ($anonfun$$tilde$1)a));
/*     */       }
/*     */       
/*     */       public Parsers$Parser$$anonfun$$tilde$1(Parsers.Parser $outer, Function0 q$1, ObjectRef p$lzy$2, VolatileByteRef bitmap$0$2) {}
/*     */       
/*     */       public class Parsers$Parser$$anonfun$$tilde$1$$anonfun$apply$3 extends AbstractFunction1<U, Parsers.$tilde<T, U>> implements Serializable {
/*     */         public static final long serialVersionUID = 0L;
/*     */         
/*     */         private final Object a$1;
/*     */         
/*     */         public final Parsers.$tilde<T, U> apply(Object b) {
/* 273 */           return new Parsers.$tilde<T, U>(this.$outer.$outer.scala$util$parsing$combinator$Parsers$Parser$$$outer(), (T)this.a$1, (U)b);
/*     */         }
/*     */         
/*     */         public Parsers$Parser$$anonfun$$tilde$1$$anonfun$apply$3(Parsers$Parser$$anonfun$$tilde$1 $outer, Object a$1) {}
/*     */       }
/*     */     }
/*     */     
/*     */     public <U> Parser<U> $tilde$greater(Function0 q) {
/* 285 */       ObjectRef p$lzy = new ObjectRef(null);
/* 285 */       VolatileByteRef bitmap$0 = new VolatileByteRef((byte)0);
/* 286 */       return flatMap((Function1<?, Parser<U>>)new Parsers$Parser$$anonfun$$tilde$greater$1(this, q, p$lzy, (Parser<T>)bitmap$0)).named("~>");
/*     */     }
/*     */     
/*     */     private final Parser p$lzycompute$3(Function0 q$2, ObjectRef p$lzy$3, VolatileByteRef bitmap$0$3) {
/*     */       synchronized (this) {
/*     */         if ((byte)(bitmap$0$3.elem & 0x1) == 0) {
/*     */           p$lzy$3.elem = q$2.apply();
/*     */           bitmap$0$3.elem = (byte)(bitmap$0$3.elem | 0x1);
/*     */         } 
/*     */         /* monitor exit ThisExpression{InnerObjectType{ObjectType{scala/util/parsing/combinator/Parsers}.Lscala/util/parsing/combinator/Parsers$Parser;}} */
/*     */         return (Parser)p$lzy$3.elem;
/*     */       } 
/*     */     }
/*     */     
/*     */     public final Parser scala$util$parsing$combinator$Parsers$Parser$$p$4(Function0 q$2, ObjectRef p$lzy$3, VolatileByteRef bitmap$0$3) {
/*     */       return ((byte)(bitmap$0$3.elem & 0x1) == 0) ? p$lzycompute$3(q$2, p$lzy$3, bitmap$0$3) : (Parser)p$lzy$3.elem;
/*     */     }
/*     */     
/*     */     public class Parsers$Parser$$anonfun$$tilde$greater$1 extends AbstractFunction1<T, Parser<U>> implements Serializable {
/*     */       public static final long serialVersionUID = 0L;
/*     */       
/*     */       private final Function0 q$2;
/*     */       
/*     */       private final ObjectRef p$lzy$3;
/*     */       
/*     */       private final VolatileByteRef bitmap$0$3;
/*     */       
/*     */       public final Parsers.Parser<U> apply(Object a) {
/* 286 */         return this.$outer.scala$util$parsing$combinator$Parsers$Parser$$p$4(this.q$2, this.p$lzy$3, this.bitmap$0$3).map((Function1)new Parsers$Parser$$anonfun$$tilde$greater$1$$anonfun$apply$4(this));
/*     */       }
/*     */       
/*     */       public Parsers$Parser$$anonfun$$tilde$greater$1(Parsers.Parser $outer, Function0 q$2, ObjectRef p$lzy$3, VolatileByteRef bitmap$0$3) {}
/*     */       
/*     */       public class Parsers$Parser$$anonfun$$tilde$greater$1$$anonfun$apply$4 extends AbstractFunction1<U, U> implements Serializable {
/*     */         public static final long serialVersionUID = 0L;
/*     */         
/*     */         public final U apply(Object b) {
/* 286 */           return (U)b;
/*     */         }
/*     */         
/*     */         public Parsers$Parser$$anonfun$$tilde$greater$1$$anonfun$apply$4(Parsers$Parser$$anonfun$$tilde$greater$1 $outer) {}
/*     */       }
/*     */     }
/*     */     
/*     */     public <U> Parser<T> $less$tilde(Function0 q) {
/* 300 */       ObjectRef p$lzy = new ObjectRef(null);
/* 300 */       VolatileByteRef bitmap$0 = new VolatileByteRef((byte)0);
/* 301 */       return flatMap((Function1<?, Parser<T>>)new Parsers$Parser$$anonfun$$less$tilde$1(this, q, p$lzy, (Parser<T>)bitmap$0)).named("<~");
/*     */     }
/*     */     
/*     */     private final Parser p$lzycompute$4(Function0 q$3, ObjectRef p$lzy$4, VolatileByteRef bitmap$0$4) {
/*     */       synchronized (this) {
/*     */         if ((byte)(bitmap$0$4.elem & 0x1) == 0) {
/*     */           p$lzy$4.elem = q$3.apply();
/*     */           bitmap$0$4.elem = (byte)(bitmap$0$4.elem | 0x1);
/*     */         } 
/*     */         /* monitor exit ThisExpression{InnerObjectType{ObjectType{scala/util/parsing/combinator/Parsers}.Lscala/util/parsing/combinator/Parsers$Parser;}} */
/*     */         return (Parser)p$lzy$4.elem;
/*     */       } 
/*     */     }
/*     */     
/*     */     public final Parser scala$util$parsing$combinator$Parsers$Parser$$p$5(Function0 q$3, ObjectRef p$lzy$4, VolatileByteRef bitmap$0$4) {
/*     */       return ((byte)(bitmap$0$4.elem & 0x1) == 0) ? p$lzycompute$4(q$3, p$lzy$4, bitmap$0$4) : (Parser)p$lzy$4.elem;
/*     */     }
/*     */     
/*     */     public class Parsers$Parser$$anonfun$$less$tilde$1 extends AbstractFunction1<T, Parser<T>> implements Serializable {
/*     */       public static final long serialVersionUID = 0L;
/*     */       
/*     */       private final Function0 q$3;
/*     */       
/*     */       private final ObjectRef p$lzy$4;
/*     */       
/*     */       private final VolatileByteRef bitmap$0$4;
/*     */       
/*     */       public final Parsers.Parser<T> apply(Object a) {
/* 301 */         return this.$outer.scala$util$parsing$combinator$Parsers$Parser$$p$5(this.q$3, this.p$lzy$4, this.bitmap$0$4).map((Function1)new Parsers$Parser$$anonfun$$less$tilde$1$$anonfun$apply$5(this, ($anonfun$$less$tilde$1)a));
/*     */       }
/*     */       
/*     */       public Parsers$Parser$$anonfun$$less$tilde$1(Parsers.Parser $outer, Function0 q$3, ObjectRef p$lzy$4, VolatileByteRef bitmap$0$4) {}
/*     */       
/*     */       public class Parsers$Parser$$anonfun$$less$tilde$1$$anonfun$apply$5 extends AbstractFunction1<U, T> implements Serializable {
/*     */         public static final long serialVersionUID = 0L;
/*     */         
/*     */         private final Object a$2;
/*     */         
/*     */         public final T apply(Object b) {
/* 301 */           return (T)this.a$2;
/*     */         }
/*     */         
/*     */         public Parsers$Parser$$anonfun$$less$tilde$1$$anonfun$apply$5(Parsers$Parser$$anonfun$$less$tilde$1 $outer, Object a$2) {}
/*     */       }
/*     */     }
/*     */     
/*     */     public <U> Parser<Parsers.$tilde<T, U>> $tilde$bang(Function0 p) {
/* 320 */       return scala$util$parsing$combinator$Parsers$Parser$$$outer().OnceParser(flatMap((Function1<?, Parser<Parsers.$tilde<T, U>>>)new Parsers$Parser$$anonfun$$tilde$bang$1(this, (Parser<T>)p)).named("~!"));
/*     */     }
/*     */     
/*     */     public class Parsers$Parser$$anonfun$$tilde$bang$1 extends AbstractFunction1<T, Parser<Parsers.$tilde<T, U>>> implements Serializable {
/*     */       public static final long serialVersionUID = 0L;
/*     */       
/*     */       private final Function0 p$6;
/*     */       
/*     */       public final Parsers.Parser<Parsers.$tilde<T, U>> apply(Object a) {
/* 320 */         return this.$outer.scala$util$parsing$combinator$Parsers$Parser$$$outer().commit(this.p$6).map((Function1)new Parsers$Parser$$anonfun$$tilde$bang$1$$anonfun$apply$6(this, ($anonfun$$tilde$bang$1)a));
/*     */       }
/*     */       
/*     */       public Parsers$Parser$$anonfun$$tilde$bang$1(Parsers.Parser $outer, Function0 p$6) {}
/*     */       
/*     */       public class Parsers$Parser$$anonfun$$tilde$bang$1$$anonfun$apply$6 extends AbstractFunction1<U, Parsers.$tilde<T, U>> implements Serializable {
/*     */         public static final long serialVersionUID = 0L;
/*     */         
/*     */         private final Object a$3;
/*     */         
/*     */         public final Parsers.$tilde<T, U> apply(Object b) {
/* 320 */           return new Parsers.$tilde<T, U>(this.$outer.$outer.scala$util$parsing$combinator$Parsers$Parser$$$outer(), (T)this.a$3, (U)b);
/*     */         }
/*     */         
/*     */         public Parsers$Parser$$anonfun$$tilde$bang$1$$anonfun$apply$6(Parsers$Parser$$anonfun$$tilde$bang$1 $outer, Object a$3) {}
/*     */       }
/*     */     }
/*     */     
/*     */     public <U> Parser<U> $bar(Function0<Parser<U>> q) {
/* 333 */       return append(q).named("|");
/*     */     }
/*     */     
/*     */     public <U> Parser<U> $bar$bar$bar(Function0 q0) {
/* 345 */       return new Parsers$Parser$$anon$4(this, (Parser<T>)q0);
/*     */     }
/*     */     
/*     */     public class Parsers$Parser$$anon$4 extends Parser<U> {
/*     */       private Parsers.Parser<U> q;
/*     */       
/*     */       private final Function0 q0$1;
/*     */       
/*     */       private volatile boolean bitmap$0;
/*     */       
/*     */       public Parsers$Parser$$anon$4(Parsers.Parser $outer, Function0 q0$1) {
/* 345 */         super($outer.scala$util$parsing$combinator$Parsers$Parser$$$outer());
/*     */       }
/*     */       
/*     */       private Parsers.Parser q$lzycompute() {
/* 346 */         synchronized (this) {
/* 346 */           if (!this.bitmap$0) {
/* 346 */             this.q = (Parsers.Parser<U>)this.q0$1.apply();
/* 346 */             this.bitmap$0 = true;
/*     */           } 
/*     */           /* monitor exit ThisExpression{ObjectType{scala/util/parsing/combinator/Parsers$Parser$$anon$4}} */
/* 346 */           this.q0$1 = null;
/* 346 */           return this.q;
/*     */         } 
/*     */       }
/*     */       
/*     */       private Parsers.Parser<U> q() {
/* 346 */         return this.bitmap$0 ? this.q : q$lzycompute();
/*     */       }
/*     */       
/*     */       public Parsers.ParseResult<U> apply(Reader in) {
/* 348 */         Parsers.ParseResult res1 = this.$outer.apply(in);
/* 349 */         Parsers.ParseResult<U> res2 = q().apply(in);
/* 351 */         Tuple2 tuple2 = new Tuple2(res1, res2);
/* 351 */         if (tuple2 != null && tuple2
/* 352 */           ._1() instanceof Parsers.Success) {
/* 352 */           Parsers.Success success = (Parsers.Success)tuple2._1();
/* 352 */           if (tuple2._2() instanceof Parsers.Success) {
/* 352 */             Parsers.Success success1 = (Parsers.Success)tuple2._2();
/* 352 */             return success1.next().pos().$less(success.next().pos()) ? success : success1;
/*     */           } 
/*     */         } 
/* 353 */         if (tuple2 != null && tuple2._1() instanceof Parsers.Success) {
/* 353 */           Parsers.Success success2 = (Parsers.Success)tuple2._1(), success1 = success2;
/* 354 */         } else if (tuple2 != null && tuple2._2() instanceof Parsers.Success) {
/* 354 */           Parsers.Success success2 = (Parsers.Success)tuple2._2(), success1 = success2;
/* 355 */         } else if (tuple2 != null && tuple2._1() instanceof Parsers.Error) {
/* 355 */           Parsers.Error error2 = (Parsers.Error)tuple2._1(), error1 = error2;
/*     */         } else {
/* 356 */           if (tuple2 != null && tuple2._1() instanceof Parsers.Failure) {
/* 356 */             Parsers.Failure failure = (Parsers.Failure)tuple2._1();
/* 356 */             Option<Tuple2<String, Reader<Object>>> option = this.$outer.scala$util$parsing$combinator$Parsers$Parser$$$outer().NoSuccess().unapply((Parsers.ParseResult)tuple2._2());
/* 356 */             if (!option.isEmpty())
/* 356 */               return ((Reader)((Tuple2)option.get())._2()).pos().$less(failure.next().pos()) ? failure : (Parsers.ParseResult)tuple2._2(); 
/*     */           } 
/*     */           throw new MatchError(tuple2);
/*     */         } 
/*     */         return (Parsers.ParseResult<U>)SYNTHETIC_LOCAL_VARIABLE_7;
/*     */       }
/*     */       
/*     */       public String toString() {
/* 359 */         return "|||";
/*     */       }
/*     */     }
/*     */     
/*     */     public <U> Parser<U> $up$up(Function1<?, U> f) {
/* 370 */       return map(f).named((new StringBuilder()).append(toString()).append("^^").toString());
/*     */     }
/*     */     
/*     */     public <U> Parser<U> $up$up$up(Function0 v) {
/* 383 */       return (new Parsers$Parser$$anon$5(this, (Parser<T>)v)).named((new StringBuilder()).append(toString()).append("^^^").toString());
/*     */     }
/*     */     
/*     */     public class Parsers$Parser$$anon$5 extends Parser<U> {
/*     */       private U v0;
/*     */       
/*     */       private final Function0 v$1;
/*     */       
/*     */       private volatile boolean bitmap$0;
/*     */       
/*     */       public Parsers$Parser$$anon$5(Parsers.Parser $outer, Function0 v$1) {
/*     */         super($outer.scala$util$parsing$combinator$Parsers$Parser$$$outer());
/*     */       }
/*     */       
/*     */       private Object v0$lzycompute() {
/*     */         synchronized (this) {
/*     */           if (!this.bitmap$0) {
/*     */             this.v0 = (U)this.v$1.apply();
/*     */             this.bitmap$0 = true;
/*     */           } 
/*     */           /* monitor exit ThisExpression{ObjectType{scala/util/parsing/combinator/Parsers$Parser$$anon$5}} */
/*     */           this.v$1 = null;
/*     */           return this.v0;
/*     */         } 
/*     */       }
/*     */       
/*     */       public U v0() {
/*     */         return this.bitmap$0 ? this.v0 : (U)v0$lzycompute();
/*     */       }
/*     */       
/*     */       public Parsers.ParseResult<U> apply(Reader in) {
/*     */         return this.$outer.apply(in).map((Function1)new Parsers$Parser$$anon$5$$anonfun$apply$7(this));
/*     */       }
/*     */       
/*     */       public class Parsers$Parser$$anon$5$$anonfun$apply$7 extends AbstractFunction1<T, U> implements Serializable {
/*     */         public static final long serialVersionUID = 0L;
/*     */         
/*     */         public final U apply(Object x) {
/*     */           return (U)this.$outer.v0();
/*     */         }
/*     */         
/*     */         public Parsers$Parser$$anon$5$$anonfun$apply$7(Parsers$Parser$$anon$5 $outer) {}
/*     */       }
/*     */     }
/*     */     
/*     */     public <U> Parser<U> $up$qmark(PartialFunction f, Function1 error) {
/* 399 */       return scala$util$parsing$combinator$Parsers$Parser$$$outer().<U>Parser((Function1<Reader<Object>, Parsers.ParseResult<U>>)new Parsers$Parser$$anonfun$$up$qmark$1(this, f, (Parser<T>)error)).named((new StringBuilder()).append(toString()).append("^?").toString());
/*     */     }
/*     */     
/*     */     public class Parsers$Parser$$anonfun$$up$qmark$1 extends AbstractFunction1<Reader<Object>, Parsers.ParseResult<U>> implements Serializable {
/*     */       public static final long serialVersionUID = 0L;
/*     */       
/*     */       private final PartialFunction f$3;
/*     */       
/*     */       private final Function1 error$1;
/*     */       
/*     */       public Parsers$Parser$$anonfun$$up$qmark$1(Parsers.Parser $outer, PartialFunction f$3, Function1 error$1) {}
/*     */       
/*     */       public final Parsers.ParseResult<U> apply(Reader in) {
/* 399 */         return this.$outer.apply(in).mapPartial(this.f$3, this.error$1);
/*     */       }
/*     */     }
/*     */     
/*     */     public <U> Parser<U> $up$qmark(PartialFunction<?, U> f) {
/* 411 */       return $up$qmark(f, (Function1<?, String>)new Parsers$Parser$$anonfun$$up$qmark$2(this));
/*     */     }
/*     */     
/*     */     public class Parsers$Parser$$anonfun$$up$qmark$2 extends AbstractFunction1<T, String> implements Serializable {
/*     */       public static final long serialVersionUID = 0L;
/*     */       
/*     */       public final String apply(Object r) {
/* 411 */         return (new StringBuilder()).append("Constructor function not defined at ").append(r).toString();
/*     */       }
/*     */       
/*     */       public Parsers$Parser$$anonfun$$up$qmark$2(Parsers.Parser $outer) {}
/*     */     }
/*     */     
/*     */     public <U> Parser<U> into(Function1<?, Parser<U>> fq) {
/* 435 */       return flatMap(fq);
/*     */     }
/*     */     
/*     */     public <U> Parser<U> $greater$greater(Function1<?, Parser<U>> fq) {
/* 440 */       return into(fq);
/*     */     }
/*     */     
/*     */     public Parser<List<T>> $times() {
/* 446 */       return scala$util$parsing$combinator$Parsers$Parser$$$outer().rep((Function0<Parser<T>>)new Parsers$Parser$$anonfun$$times$1(this));
/*     */     }
/*     */     
/*     */     public class Parsers$Parser$$anonfun$$times$1 extends AbstractFunction0<Parser<T>> implements Serializable {
/*     */       public static final long serialVersionUID = 0L;
/*     */       
/*     */       public final Parsers.Parser<T> apply() {
/* 446 */         return this.$outer;
/*     */       }
/*     */       
/*     */       public Parsers$Parser$$anonfun$$times$1(Parsers.Parser $outer) {}
/*     */     }
/*     */     
/*     */     public <U> Parser<U> $times(Function0<Parser<Function2<U, U, U>>> sep) {
/* 454 */       return scala$util$parsing$combinator$Parsers$Parser$$$outer().chainl1((Function0<Parser<U>>)new Parsers$Parser$$anonfun$$times$2(this), sep);
/*     */     }
/*     */     
/*     */     public class Parsers$Parser$$anonfun$$times$2 extends AbstractFunction0<Parser<T>> implements Serializable {
/*     */       public static final long serialVersionUID = 0L;
/*     */       
/*     */       public final Parsers.Parser<T> apply() {
/* 454 */         return this.$outer;
/*     */       }
/*     */       
/*     */       public Parsers$Parser$$anonfun$$times$2(Parsers.Parser $outer) {}
/*     */     }
/*     */     
/*     */     public Parser<List<T>> $plus() {
/* 462 */       return scala$util$parsing$combinator$Parsers$Parser$$$outer().rep1((Function0<Parser<T>>)new Parsers$Parser$$anonfun$$plus$1(this));
/*     */     }
/*     */     
/*     */     public class Parsers$Parser$$anonfun$$plus$1 extends AbstractFunction0<Parser<T>> implements Serializable {
/*     */       public static final long serialVersionUID = 0L;
/*     */       
/*     */       public final Parsers.Parser<T> apply() {
/* 462 */         return this.$outer;
/*     */       }
/*     */       
/*     */       public Parsers$Parser$$anonfun$$plus$1(Parsers.Parser $outer) {}
/*     */     }
/*     */     
/*     */     public Parser<Option<T>> $qmark() {
/* 468 */       return scala$util$parsing$combinator$Parsers$Parser$$$outer().opt((Function0<Parser<T>>)new Parsers$Parser$$anonfun$$qmark$1(this));
/*     */     }
/*     */     
/*     */     public class Parsers$Parser$$anonfun$$qmark$1 extends AbstractFunction0<Parser<T>> implements Serializable {
/*     */       public static final long serialVersionUID = 0L;
/*     */       
/*     */       public final Parsers.Parser<T> apply() {
/* 468 */         return this.$outer;
/*     */       }
/*     */       
/*     */       public Parsers$Parser$$anonfun$$qmark$1(Parsers.Parser $outer) {}
/*     */     }
/*     */     
/*     */     public Parser<T> withFailureMessage(String msg) {
/* 491 */       return scala$util$parsing$combinator$Parsers$Parser$$$outer().Parser((Function1<Reader<Object>, Parsers.ParseResult<T>>)new Parsers$Parser$$anonfun$withFailureMessage$1(this, (Parser<T>)msg));
/*     */     }
/*     */     
/*     */     public class Parsers$Parser$$anonfun$withFailureMessage$1 extends AbstractFunction1<Reader<Object>, Parsers.ParseResult<T>> implements Serializable {
/*     */       public static final long serialVersionUID = 0L;
/*     */       
/*     */       private final String msg$1;
/*     */       
/*     */       public Parsers$Parser$$anonfun$withFailureMessage$1(Parsers.Parser $outer, String msg$1) {}
/*     */       
/*     */       public final Parsers.ParseResult<T> apply(Reader in) {
/* 492 */         Parsers.ParseResult<T> parseResult = this.$outer.apply(in);
/* 493 */         if (parseResult instanceof Parsers.Failure)
/* 493 */           Parsers.Failure failure1 = (Parsers.Failure)parseResult, failure2 = new Parsers.Failure(this.$outer.scala$util$parsing$combinator$Parsers$Parser$$$outer(), this.msg$1, failure1.next()); 
/* 494 */         return parseResult;
/*     */       }
/*     */     }
/*     */     
/*     */     public Parser<T> withErrorMessage(String msg) {
/* 519 */       return scala$util$parsing$combinator$Parsers$Parser$$$outer().Parser((Function1<Reader<Object>, Parsers.ParseResult<T>>)new Parsers$Parser$$anonfun$withErrorMessage$1(this, (Parser<T>)msg));
/*     */     }
/*     */     
/*     */     public abstract Parsers.ParseResult<T> apply(Reader<Object> param1Reader);
/*     */     
/*     */     public class Parsers$Parser$$anonfun$withErrorMessage$1 extends AbstractFunction1<Reader<Object>, Parsers.ParseResult<T>> implements Serializable {
/*     */       public static final long serialVersionUID = 0L;
/*     */       
/*     */       private final String msg$2;
/*     */       
/*     */       public Parsers$Parser$$anonfun$withErrorMessage$1(Parsers.Parser $outer, String msg$2) {}
/*     */       
/*     */       public final Parsers.ParseResult<T> apply(Reader in) {
/* 520 */         Parsers.ParseResult<T> parseResult = this.$outer.apply(in);
/* 521 */         if (parseResult instanceof Parsers.Error)
/* 521 */           Parsers.Error error1 = (Parsers.Error)parseResult, error2 = new Parsers.Error(this.$outer.scala$util$parsing$combinator$Parsers$Parser$$$outer(), this.msg$2, error1.next()); 
/* 522 */         return parseResult;
/*     */       }
/*     */     }
/*     */   }
/*     */   
/*     */   public class Parsers$$anonfun$commit$1 extends AbstractFunction1<Reader<Object>, Serializable> implements Serializable {
/*     */     public static final long serialVersionUID = 0L;
/*     */     
/*     */     private final Function0 p$8;
/*     */     
/*     */     public Parsers$$anonfun$commit$1(Parsers $outer, Function0 p$8) {}
/*     */     
/*     */     public final Serializable apply(Reader in) {
/*     */       Parsers.Error error;
/* 532 */       Parsers.ParseResult parseResult = ((Parsers.Parser)this.p$8.apply()).apply(in);
/* 533 */       if (parseResult instanceof Parsers.Success) {
/* 533 */         Parsers.Success success1 = (Parsers.Success)parseResult, success2 = success1;
/* 534 */       } else if (parseResult instanceof Parsers.Error) {
/* 534 */         Parsers.Error error1 = (Parsers.Error)parseResult;
/*     */       } else {
/* 535 */         if (parseResult instanceof Parsers.Failure)
/* 535 */           Parsers.Failure failure = (Parsers.Failure)parseResult; 
/*     */         throw new MatchError(parseResult);
/*     */       } 
/*     */       return error;
/*     */     }
/*     */   }
/*     */   
/*     */   public class Parsers$$anonfun$elem$1 extends AbstractFunction1<Object, String> implements Serializable {
/*     */     public static final long serialVersionUID = 0L;
/*     */     
/*     */     private final String kind$1;
/*     */     
/*     */     public final String apply(Object inEl) {
/* 551 */       return (new StringBuilder()).append(this.kind$1).append(" expected").toString();
/*     */     }
/*     */     
/*     */     public Parsers$$anonfun$elem$1(Parsers $outer, String kind$1) {}
/*     */   }
/*     */   
/*     */   public class Parsers$$anonfun$accept$1 extends AbstractFunction1<Object, Object> implements Serializable {
/*     */     public static final long serialVersionUID = 0L;
/*     */     
/*     */     private final Object e$1;
/*     */     
/*     */     public final boolean apply(Object x$2) {
/* 572 */       Object object = this.e$1;
/* 572 */       return ((x$2 == object) ? true : ((x$2 == null) ? false : ((x$2 instanceof Number) ? BoxesRunTime.equalsNumObject((Number)x$2, object) : ((x$2 instanceof Character) ? BoxesRunTime.equalsCharObject((Character)x$2, object) : x$2.equals(object)))));
/*     */     }
/*     */     
/*     */     public Parsers$$anonfun$accept$1(Parsers $outer, Object e$1) {}
/*     */   }
/*     */   
/*     */   public class Parsers$$anonfun$accept$2 extends AbstractFunction1<Object, String> implements Serializable {
/*     */     public static final long serialVersionUID = 0L;
/*     */     
/*     */     private final Object e$1;
/*     */     
/*     */     public final String apply(Object x$3) {
/* 572 */       return (new StringBuilder()).append("`").append(this.e$1).append("' expected but ").append(x$3).append(" found").toString();
/*     */     }
/*     */     
/*     */     public Parsers$$anonfun$accept$2(Parsers $outer, Object e$1) {}
/*     */   }
/*     */   
/*     */   public class Parsers$$anonfun$acceptIf$1 extends AbstractFunction1<Reader<Object>, ParseResult<Object>> implements Serializable {
/*     */     public static final long serialVersionUID = 0L;
/*     */     
/*     */     private final Function1 p$9;
/*     */     
/*     */     private final Function1 err$1;
/*     */     
/*     */     public Parsers$$anonfun$acceptIf$1(Parsers $outer, Function1 p$9, Function1 err$1) {}
/*     */     
/*     */     public final Parsers.ParseResult<Object> apply(Reader<Object> in) {
/* 607 */       return in.atEnd() ? new Parsers.Failure(this.$outer, "end of input", in) : (
/* 608 */         BoxesRunTime.unboxToBoolean(this.p$9.apply(in.first())) ? new Parsers.Success(this.$outer, in.first(), in.rest()) : 
/* 609 */         new Parsers.Failure(this.$outer, (String)this.err$1.apply(in.first()), in));
/*     */     }
/*     */   }
/*     */   
/*     */   public class Parsers$$anonfun$acceptMatch$1 extends AbstractFunction1<Reader<Object>, ParseResult<U>> implements Serializable {
/*     */     public static final long serialVersionUID = 0L;
/*     */     
/*     */     private final String expected$1;
/*     */     
/*     */     private final PartialFunction f$6;
/*     */     
/*     */     public Parsers$$anonfun$acceptMatch$1(Parsers $outer, String expected$1, PartialFunction f$6) {}
/*     */     
/*     */     public final Parsers.ParseResult<U> apply(Reader<Object> in) {
/* 626 */       return in.atEnd() ? new Parsers.Failure(this.$outer, "end of input", in) : (
/* 627 */         this.f$6.isDefinedAt(in.first()) ? new Parsers.Success<U>(this.$outer, (U)this.f$6.apply(in.first()), in.rest()) : 
/* 628 */         new Parsers.Failure(this.$outer, (new StringBuilder()).append(this.expected$1).append(" expected").toString(), in));
/*     */     }
/*     */   }
/*     */   
/*     */   public class Parsers$$anonfun$acceptSeq$1 extends AbstractFunction2<Object, Parser<List<Object>>, Parser<List<Object>>> implements Serializable {
/*     */     public static final long serialVersionUID = 0L;
/*     */     
/*     */     public final Parsers.Parser<List<Object>> apply(Object x, Parsers.Parser pxs) {
/* 639 */       return this.$outer.accept(x).$tilde((Function0<Parsers.Parser<?>>)new Parsers$$anonfun$acceptSeq$1$$anonfun$apply$8(this, pxs)).$up$up(this.$outer.mkList());
/*     */     }
/*     */     
/*     */     public Parsers$$anonfun$acceptSeq$1(Parsers $outer) {}
/*     */     
/*     */     public class Parsers$$anonfun$acceptSeq$1$$anonfun$apply$8 extends AbstractFunction0<Parsers.Parser<List<Object>>> implements Serializable {
/*     */       public static final long serialVersionUID = 0L;
/*     */       
/*     */       private final Parsers.Parser pxs$1;
/*     */       
/*     */       public final Parsers.Parser<List<Object>> apply() {
/* 639 */         return this.pxs$1;
/*     */       }
/*     */       
/*     */       public Parsers$$anonfun$acceptSeq$1$$anonfun$apply$8(Parsers$$anonfun$acceptSeq$1 $outer, Parsers.Parser pxs$1) {}
/*     */     }
/*     */   }
/*     */   
/*     */   public class Parsers$$anonfun$failure$1 extends AbstractFunction1<Reader<Object>, Failure> implements Serializable {
/*     */     public static final long serialVersionUID = 0L;
/*     */     
/*     */     private final String msg$3;
/*     */     
/*     */     public final Parsers.Failure apply(Reader<Object> in) {
/* 646 */       return new Parsers.Failure(this.$outer, this.msg$3, in);
/*     */     }
/*     */     
/*     */     public Parsers$$anonfun$failure$1(Parsers $outer, String msg$3) {}
/*     */   }
/*     */   
/*     */   public class Parsers$$anonfun$err$1 extends AbstractFunction1<Reader<Object>, Error> implements Serializable {
/*     */     public static final long serialVersionUID = 0L;
/*     */     
/*     */     private final String msg$4;
/*     */     
/*     */     public final Parsers.Error apply(Reader<Object> in) {
/* 653 */       return new Parsers.Error(this.$outer, this.msg$4, in);
/*     */     }
/*     */     
/*     */     public Parsers$$anonfun$err$1(Parsers $outer, String msg$4) {}
/*     */   }
/*     */   
/*     */   public class Parsers$$anonfun$success$1 extends AbstractFunction1<Reader<Object>, Success<T>> implements Serializable {
/*     */     public static final long serialVersionUID = 0L;
/*     */     
/*     */     private final Object v$2;
/*     */     
/*     */     public final Parsers.Success<T> apply(Reader in) {
/* 660 */       return new Parsers.Success<T>(this.$outer, (T)this.v$2, in);
/*     */     }
/*     */     
/*     */     public Parsers$$anonfun$success$1(Parsers $outer, Object v$2) {}
/*     */   }
/*     */   
/*     */   public class Parsers$$anonfun$log$1 extends AbstractFunction1<Reader<Object>, ParseResult<T>> implements Serializable {
/*     */     public static final long serialVersionUID = 0L;
/*     */     
/*     */     private final Function0 p$10;
/*     */     
/*     */     private final String name$1;
/*     */     
/*     */     public Parsers$$anonfun$log$1(Parsers $outer, Function0 p$10, String name$1) {}
/*     */     
/*     */     public final Parsers.ParseResult<T> apply(Reader in) {
/* 667 */       scala.Predef$.MODULE$.println((new StringBuilder()).append("trying ").append(this.name$1).append(" at ").append(in).toString());
/* 668 */       Parsers.ParseResult<T> r = ((Parsers.Parser)this.p$10.apply()).apply(in);
/* 669 */       scala.Predef$.MODULE$.println((new StringBuilder()).append(this.name$1).append(" --> ").append(r).toString());
/* 670 */       return r;
/*     */     }
/*     */   }
/*     */   
/*     */   public class Parsers$$anonfun$rep$1 extends AbstractFunction0<Parser<List<scala.runtime.Nothing$>>> implements Serializable {
/*     */     public static final long serialVersionUID = 0L;
/*     */     
/*     */     public final Parsers.Parser<List<scala.runtime.Nothing$>> apply() {
/* 681 */       return (Parsers.Parser)this.$outer.success(scala.collection.immutable.Nil$.MODULE$);
/*     */     }
/*     */     
/*     */     public Parsers$$anonfun$rep$1(Parsers $outer) {}
/*     */   }
/*     */   
/*     */   public class Parsers$$anonfun$repsep$1 extends AbstractFunction0<Parser<List<scala.runtime.Nothing$>>> implements Serializable {
/*     */     public static final long serialVersionUID = 0L;
/*     */     
/*     */     public final Parsers.Parser<List<scala.runtime.Nothing$>> apply() {
/* 696 */       return (Parsers.Parser)this.$outer.success(scala.collection.immutable.Nil$.MODULE$);
/*     */     }
/*     */     
/*     */     public Parsers$$anonfun$repsep$1(Parsers $outer) {}
/*     */   }
/*     */   
/*     */   public class Parsers$$anonfun$rep1$1 extends AbstractFunction1<Reader<Object>, ParseResult<List<T>>> implements Serializable {
/*     */     public static final long serialVersionUID = 0L;
/*     */     
/*     */     private final Function0 first$1;
/*     */     
/*     */     private final Function0 p0$4;
/*     */     
/*     */     public Parsers$$anonfun$rep1$1(Parsers $outer, Function0 first$1, Function0 p0$4) {}
/*     */     
/*     */     public final Parsers.ParseResult<List<T>> apply(Reader in) {
/* 722 */       ObjectRef p$lzy = new ObjectRef(null);
/*     */       VolatileByteRef bitmap$0 = new VolatileByteRef((byte)0);
/* 723 */       ListBuffer elems = new ListBuffer();
/* 736 */       Parsers.ParseResult parseResult = ((Parsers.Parser)this.first$1.apply()).apply(in);
/* 737 */       if (parseResult instanceof Parsers.Success) {
/* 737 */         Parsers.Success success = (Parsers.Success)parseResult;
/* 737 */         elems.$plus$eq(success.result());
/*     */       } 
/* 738 */       if (parseResult instanceof Parsers.NoSuccess) {
/*     */         Parsers.NoSuccess noSuccess;
/* 738 */         return noSuccess = (Parsers.NoSuccess)parseResult;
/*     */       } 
/*     */       throw new MatchError(parseResult);
/*     */     }
/*     */     
/*     */     private final Parsers.Parser p$lzycompute$5(ObjectRef p$lzy$5, VolatileByteRef bitmap$0$5) {
/*     */       synchronized (this) {
/*     */         if ((byte)(bitmap$0$5.elem & 0x1) == 0) {
/*     */           p$lzy$5.elem = this.p0$4.apply();
/*     */           bitmap$0$5.elem = (byte)(bitmap$0$5.elem | 0x1);
/*     */         } 
/*     */         /* monitor exit ThisExpression{ObjectType{scala/util/parsing/combinator/Parsers$$anonfun$rep1$1}} */
/*     */         return (Parsers.Parser)p$lzy$5.elem;
/*     */       } 
/*     */     }
/*     */     
/*     */     private final Parsers.Parser p$7(ObjectRef p$lzy$5, VolatileByteRef bitmap$0$5) {
/*     */       return ((byte)(bitmap$0$5.elem & 0x1) == 0) ? p$lzycompute$5(p$lzy$5, bitmap$0$5) : (Parsers.Parser)p$lzy$5.elem;
/*     */     }
/*     */     
/*     */     private final Parsers.ParseResult continue$1(Reader in, ObjectRef p$lzy$5, ListBuffer elems$1, VolatileByteRef bitmap$0$5) {
/*     */       Parsers.Parser p0 = p$7(p$lzy$5, bitmap$0$5);
/*     */       return applyp$1(in, elems$1, p0);
/*     */     }
/*     */     
/*     */     private final Parsers.ParseResult applyp$1(Reader in0, ListBuffer elems$1, Parsers.Parser p0$2) {
/*     */       while (true) {
/*     */         Parsers.Success<List> success;
/*     */         Parsers.ParseResult parseResult = p0$2.apply(in0);
/*     */         if (parseResult instanceof Parsers.Success) {
/*     */           Parsers.Success success1 = (Parsers.Success)parseResult;
/*     */           elems$1.$plus$eq(success1.result());
/*     */         } 
/*     */         if (parseResult instanceof Parsers.Error) {
/*     */           Parsers.Error error1 = (Parsers.Error)parseResult, error2 = error1;
/*     */         } else {
/*     */           success = new Parsers.Success<List>(this.$outer, elems$1.toList(), in0);
/*     */         } 
/*     */         return success;
/*     */       } 
/*     */     }
/*     */   }
/*     */   
/*     */   public class Parsers$$anonfun$repN$1 extends AbstractFunction1<Reader<Object>, ParseResult<List<T>>> implements Serializable {
/*     */     public static final long serialVersionUID = 0L;
/*     */     
/*     */     private final int num$1;
/*     */     
/*     */     private final Function0 p$11;
/*     */     
/*     */     public Parsers$$anonfun$repN$1(Parsers $outer, int num$1, Function0 p$11) {}
/*     */     
/*     */     public final Parsers.ParseResult<List<T>> apply(Reader in) {
/* 754 */       ListBuffer elems = new ListBuffer();
/* 755 */       Parsers.Parser p0 = (Parsers.Parser)this.p$11.apply();
/* 764 */       return applyp$2(in, elems, p0);
/*     */     }
/*     */     
/*     */     private final Parsers.ParseResult applyp$2(Reader in0, ListBuffer elems$2, Parsers.Parser p0$3) {
/*     */       while (true) {
/*     */         if (elems$2.length() == this.num$1)
/*     */           return new Parsers.Success<List>(this.$outer, elems$2.toList(), in0); 
/*     */         Parsers.ParseResult parseResult = p0$3.apply(in0);
/*     */         if (parseResult instanceof Parsers.Success) {
/*     */           Parsers.Success success = (Parsers.Success)parseResult;
/*     */           elems$2.$plus$eq(success.result());
/*     */         } 
/*     */         if (parseResult instanceof Parsers.NoSuccess)
/*     */           return parseResult; 
/*     */         throw new MatchError(parseResult);
/*     */       } 
/*     */     }
/*     */   }
/*     */   
/*     */   public class Parsers$$anonfun$rep1sep$1 extends AbstractFunction0<Parser<List<T>>> implements Serializable {
/*     */     public static final long serialVersionUID = 0L;
/*     */     
/*     */     public final Function0 p$12;
/*     */     
/*     */     public final Function0 q$4;
/*     */     
/*     */     public final Parsers.Parser<List<T>> apply() {
/* 780 */       return this.$outer.rep((Function0<Parsers.Parser<T>>)new Parsers$$anonfun$rep1sep$1$$anonfun$apply$9(this));
/*     */     }
/*     */     
/*     */     public Parsers$$anonfun$rep1sep$1(Parsers $outer, Function0 p$12, Function0 q$4) {}
/*     */     
/*     */     public class Parsers$$anonfun$rep1sep$1$$anonfun$apply$9 extends AbstractFunction0<Parsers.Parser<T>> implements Serializable {
/*     */       public static final long serialVersionUID = 0L;
/*     */       
/*     */       public final Parsers.Parser<T> apply() {
/* 780 */         return ((Parsers.Parser)this.$outer.q$4.apply()).$tilde$greater(this.$outer.p$12);
/*     */       }
/*     */       
/*     */       public Parsers$$anonfun$rep1sep$1$$anonfun$apply$9(Parsers$$anonfun$rep1sep$1 $outer) {}
/*     */     }
/*     */   }
/*     */   
/*     */   public class Parsers$$anonfun$rep1sep$2 extends AbstractFunction1<$tilde<T, List<T>>, List<T>> implements Serializable {
/*     */     public static final long serialVersionUID = 0L;
/*     */     
/*     */     public final List<T> apply(Parsers.$tilde x0$1) {
/* 780 */       if (x0$1 != null) {
/* 780 */         Object object = x0$1._1();
/* 780 */         return ((List)x0$1._2()).$colon$colon(object);
/*     */       } 
/* 780 */       throw new MatchError(x0$1);
/*     */     }
/*     */     
/*     */     public Parsers$$anonfun$rep1sep$2(Parsers $outer) {}
/*     */   }
/*     */   
/*     */   public class Parsers$$anonfun$chainl1$1 extends AbstractFunction0<Parser<List<$tilde<Function2<T, U, T>, U>>>> implements Serializable {
/*     */     public static final long serialVersionUID = 0L;
/*     */     
/*     */     public final Function0 p$13;
/*     */     
/*     */     public final Function0 q$5;
/*     */     
/*     */     public final Parsers.Parser<List<Parsers.$tilde<Function2<T, U, T>, U>>> apply() {
/* 807 */       return this.$outer.rep((Function0<Parsers.Parser<Parsers.$tilde<Function2<T, U, T>, U>>>)new Parsers$$anonfun$chainl1$1$$anonfun$apply$10(this));
/*     */     }
/*     */     
/*     */     public Parsers$$anonfun$chainl1$1(Parsers $outer, Function0 p$13, Function0 q$5) {}
/*     */     
/*     */     public class Parsers$$anonfun$chainl1$1$$anonfun$apply$10 extends AbstractFunction0<Parsers.Parser<Parsers.$tilde<Function2<T, U, T>, U>>> implements Serializable {
/*     */       public static final long serialVersionUID = 0L;
/*     */       
/*     */       public final Parsers.Parser<Parsers.$tilde<Function2<T, U, T>, U>> apply() {
/* 807 */         return ((Parsers.Parser<Function2<T, U, T>>)this.$outer.q$5.apply()).$tilde(this.$outer.p$13);
/*     */       }
/*     */       
/*     */       public Parsers$$anonfun$chainl1$1$$anonfun$apply$10(Parsers$$anonfun$chainl1$1 $outer) {}
/*     */     }
/*     */   }
/*     */   
/*     */   public class Parsers$$anonfun$chainl1$2 extends AbstractFunction1<$tilde<T, List<$tilde<Function2<T, U, T>, U>>>, T> implements Serializable {
/*     */     public static final long serialVersionUID = 0L;
/*     */     
/*     */     public final T apply(Parsers.$tilde x0$2) {
/* 807 */       if (x0$2 != null)
/* 807 */         return (T)((LinearSeqOptimized)x0$2
/* 808 */           ._2()).foldLeft(x0$2._1(), (Function2)new Parsers$$anonfun$chainl1$2$$anonfun$apply$11(this)); 
/*     */       throw new MatchError(x0$2);
/*     */     }
/*     */     
/*     */     public Parsers$$anonfun$chainl1$2(Parsers $outer) {}
/*     */     
/*     */     public class Parsers$$anonfun$chainl1$2$$anonfun$apply$11 extends AbstractFunction2<T, Parsers.$tilde<Function2<T, U, T>, U>, T> implements Serializable {
/*     */       public static final long serialVersionUID = 0L;
/*     */       
/*     */       public final T apply(Object x0$3, Parsers.$tilde x1$1) {
/* 808 */         Tuple2 tuple2 = new Tuple2(x0$3, x1$1);
/* 808 */         if (tuple2 != null && tuple2._2() != null)
/* 808 */           return (T)((Function2)((Parsers.$tilde)tuple2._2())._1()).apply(tuple2._1(), ((Parsers.$tilde)tuple2._2())._2()); 
/* 808 */         throw new MatchError(tuple2);
/*     */       }
/*     */       
/*     */       public Parsers$$anonfun$chainl1$2$$anonfun$apply$11(Parsers$$anonfun$chainl1$2 $outer) {}
/*     */     }
/*     */   }
/*     */   
/*     */   public class Parsers$$anonfun$chainr1$1 extends AbstractFunction0<Parser<List<$tilde<Function2<T, U, U>, T>>>> implements Serializable {
/*     */     public static final long serialVersionUID = 0L;
/*     */     
/*     */     public final Function0 p$14;
/*     */     
/*     */     public final Function0 q$6;
/*     */     
/*     */     public final Parsers.Parser<List<Parsers.$tilde<Function2<T, U, U>, T>>> apply() {
/* 825 */       return this.$outer.rep((Function0<Parsers.Parser<Parsers.$tilde<Function2<T, U, U>, T>>>)new Parsers$$anonfun$chainr1$1$$anonfun$apply$12(this));
/*     */     }
/*     */     
/*     */     public Parsers$$anonfun$chainr1$1(Parsers $outer, Function0 p$14, Function0 q$6) {}
/*     */     
/*     */     public class Parsers$$anonfun$chainr1$1$$anonfun$apply$12 extends AbstractFunction0<Parsers.Parser<Parsers.$tilde<Function2<T, U, U>, T>>> implements Serializable {
/*     */       public static final long serialVersionUID = 0L;
/*     */       
/*     */       public final Parsers.Parser<Parsers.$tilde<Function2<T, U, U>, T>> apply() {
/* 825 */         return ((Parsers.Parser<Function2<T, U, U>>)this.$outer.q$6.apply()).$tilde(this.$outer.p$14);
/*     */       }
/*     */       
/*     */       public Parsers$$anonfun$chainr1$1$$anonfun$apply$12(Parsers$$anonfun$chainr1$1 $outer) {}
/*     */     }
/*     */   }
/*     */   
/*     */   public class Parsers$$anonfun$chainr1$2 extends AbstractFunction1<$tilde<T, List<$tilde<Function2<T, U, U>, T>>>, U> implements Serializable {
/*     */     public static final long serialVersionUID = 0L;
/*     */     
/*     */     private final Function2 combine$1;
/*     */     
/*     */     private final Object first$2;
/*     */     
/*     */     public final U apply(Parsers.$tilde x0$4) {
/* 825 */       if (x0$4 != null) {
/* 826 */         Parsers.$tilde<Function2, Object> $tilde1 = new Parsers.$tilde<Function2, Object>(this.$outer, this.combine$1, x0$4._1());
/* 826 */         return (U)((List)x0$4._2()).$colon$colon($tilde1).foldRight(this.first$2, (Function2)new Parsers$$anonfun$chainr1$2$$anonfun$apply$13(this));
/*     */       } 
/*     */       throw new MatchError(x0$4);
/*     */     }
/*     */     
/*     */     public Parsers$$anonfun$chainr1$2(Parsers $outer, Function2 combine$1, Object first$2) {}
/*     */     
/*     */     public class Parsers$$anonfun$chainr1$2$$anonfun$apply$13 extends AbstractFunction2<Parsers.$tilde<Function2<T, U, U>, T>, U, U> implements Serializable {
/*     */       public static final long serialVersionUID = 0L;
/*     */       
/*     */       public final U apply(Parsers.$tilde x0$5, Object x1$2) {
/* 826 */         Tuple2 tuple2 = new Tuple2(x0$5, x1$2);
/* 826 */         if (tuple2 != null && tuple2._1() != null)
/* 826 */           return (U)((Function2)((Parsers.$tilde)tuple2._1())._1()).apply(((Parsers.$tilde)tuple2._1())._2(), tuple2._2()); 
/* 826 */         throw new MatchError(tuple2);
/*     */       }
/*     */       
/*     */       public Parsers$$anonfun$chainr1$2$$anonfun$apply$13(Parsers$$anonfun$chainr1$2 $outer) {}
/*     */     }
/*     */   }
/*     */   
/*     */   public class Parsers$$anonfun$opt$1 extends AbstractFunction1<T, Some<T>> implements Serializable {
/*     */     public static final long serialVersionUID = 0L;
/*     */     
/*     */     public final Some<T> apply(Object x) {
/* 838 */       return new Some(x);
/*     */     }
/*     */     
/*     */     public Parsers$$anonfun$opt$1(Parsers $outer) {}
/*     */   }
/*     */   
/*     */   public class Parsers$$anonfun$opt$2 extends AbstractFunction0<Parser<scala.None$>> implements Serializable {
/*     */     public static final long serialVersionUID = 0L;
/*     */     
/*     */     public final Parsers.Parser<scala.None$> apply() {
/* 838 */       return this.$outer.success(scala.None$.MODULE$);
/*     */     }
/*     */     
/*     */     public Parsers$$anonfun$opt$2(Parsers $outer) {}
/*     */   }
/*     */   
/*     */   public class Parsers$$anonfun$not$1 extends AbstractFunction1<Reader<Object>, ParseResult<BoxedUnit>> implements Serializable {
/*     */     public static final long serialVersionUID = 0L;
/*     */     
/*     */     private final Function0 p$15;
/*     */     
/*     */     public Parsers$$anonfun$not$1(Parsers $outer, Function0 p$15) {}
/*     */     
/*     */     public final Parsers.ParseResult<BoxedUnit> apply(Reader<Object> in) {
/*     */       Parsers.Success<BoxedUnit> success;
/* 844 */       Parsers.ParseResult parseResult = ((Parsers.Parser)this.p$15.apply()).apply(in);
/* 845 */       if (parseResult instanceof Parsers.Success) {
/* 845 */         Parsers.Failure failure = new Parsers.Failure(this.$outer, "Expected failure", in);
/*     */       } else {
/* 846 */         success = new Parsers.Success<BoxedUnit>(this.$outer, BoxedUnit.UNIT, in);
/*     */       } 
/*     */       return success;
/*     */     }
/*     */   }
/*     */   
/*     */   public class Parsers$$anonfun$guard$1 extends AbstractFunction1<Reader<Object>, ParseResult<T>> implements Serializable {
/*     */     public static final long serialVersionUID = 0L;
/*     */     
/*     */     private final Function0 p$16;
/*     */     
/*     */     public Parsers$$anonfun$guard$1(Parsers $outer, Function0 p$16) {}
/*     */     
/*     */     public final Parsers.ParseResult<T> apply(Reader in) {
/* 859 */       Parsers.ParseResult<T> parseResult = ((Parsers.Parser)this.p$16.apply()).apply(in);
/* 860 */       if (parseResult instanceof Parsers.Success)
/* 860 */         Parsers.Success success1 = (Parsers.Success)parseResult, success2 = new Parsers.Success(this.$outer, success1.result(), in); 
/* 861 */       return parseResult;
/*     */     }
/*     */   }
/*     */   
/*     */   public class Parsers$$anonfun$positioned$1 extends AbstractFunction1<Reader<Object>, ParseResult<T>> implements Serializable {
/*     */     public static final long serialVersionUID = 0L;
/*     */     
/*     */     private final Function0 p$17;
/*     */     
/*     */     public Parsers$$anonfun$positioned$1(Parsers $outer, Function0 p$17) {}
/*     */     
/*     */     public final Parsers.ParseResult<T> apply(Reader in) {
/*     */       // Byte code:
/*     */       //   0: aload_0
/*     */       //   1: getfield p$17 : Lscala/Function0;
/*     */       //   4: invokeinterface apply : ()Ljava/lang/Object;
/*     */       //   9: checkcast scala/util/parsing/combinator/Parsers$Parser
/*     */       //   12: aload_1
/*     */       //   13: invokevirtual apply : (Lscala/util/parsing/input/Reader;)Lscala/util/parsing/combinator/Parsers$ParseResult;
/*     */       //   16: astore_2
/*     */       //   17: aload_2
/*     */       //   18: instanceof scala/util/parsing/combinator/Parsers$Success
/*     */       //   21: ifeq -> 110
/*     */       //   24: aload_2
/*     */       //   25: checkcast scala/util/parsing/combinator/Parsers$Success
/*     */       //   28: astore_3
/*     */       //   29: new scala/util/parsing/combinator/Parsers$Success
/*     */       //   32: dup
/*     */       //   33: aload_0
/*     */       //   34: getfield $outer : Lscala/util/parsing/combinator/Parsers;
/*     */       //   37: aload_3
/*     */       //   38: invokevirtual result : ()Ljava/lang/Object;
/*     */       //   41: checkcast scala/util/parsing/input/Positional
/*     */       //   44: invokeinterface pos : ()Lscala/util/parsing/input/Position;
/*     */       //   49: getstatic scala/util/parsing/input/NoPosition$.MODULE$ : Lscala/util/parsing/input/NoPosition$;
/*     */       //   52: astore #5
/*     */       //   54: dup
/*     */       //   55: ifnonnull -> 67
/*     */       //   58: pop
/*     */       //   59: aload #5
/*     */       //   61: ifnull -> 75
/*     */       //   64: goto -> 94
/*     */       //   67: aload #5
/*     */       //   69: invokevirtual equals : (Ljava/lang/Object;)Z
/*     */       //   72: ifeq -> 94
/*     */       //   75: aload_3
/*     */       //   76: invokevirtual result : ()Ljava/lang/Object;
/*     */       //   79: checkcast scala/util/parsing/input/Positional
/*     */       //   82: aload_1
/*     */       //   83: invokevirtual pos : ()Lscala/util/parsing/input/Position;
/*     */       //   86: invokeinterface setPos : (Lscala/util/parsing/input/Position;)Lscala/util/parsing/input/Positional;
/*     */       //   91: goto -> 98
/*     */       //   94: aload_3
/*     */       //   95: invokevirtual result : ()Ljava/lang/Object;
/*     */       //   98: aload_3
/*     */       //   99: invokevirtual next : ()Lscala/util/parsing/input/Reader;
/*     */       //   102: invokespecial <init> : (Lscala/util/parsing/combinator/Parsers;Ljava/lang/Object;Lscala/util/parsing/input/Reader;)V
/*     */       //   105: astore #4
/*     */       //   107: goto -> 127
/*     */       //   110: aload_2
/*     */       //   111: instanceof scala/util/parsing/combinator/Parsers$NoSuccess
/*     */       //   114: ifeq -> 130
/*     */       //   117: aload_2
/*     */       //   118: checkcast scala/util/parsing/combinator/Parsers$NoSuccess
/*     */       //   121: astore #6
/*     */       //   123: aload #6
/*     */       //   125: astore #4
/*     */       //   127: aload #4
/*     */       //   129: areturn
/*     */       //   130: new scala/MatchError
/*     */       //   133: dup
/*     */       //   134: aload_2
/*     */       //   135: invokespecial <init> : (Ljava/lang/Object;)V
/*     */       //   138: athrow
/*     */       // Line number table:
/*     */       //   Java source line number -> byte code offset
/*     */       //   #874	-> 0
/*     */       //   #875	-> 17
/*     */       //   #874	-> 37
/*     */       //   #875	-> 38
/*     */       //   #874	-> 75
/*     */       //   #875	-> 76
/*     */       //   #874	-> 94
/*     */       //   #875	-> 95
/*     */       //   #874	-> 98
/*     */       //   #875	-> 99
/*     */       //   #876	-> 110
/*     */       //   #874	-> 127
/*     */       // Local variable table:
/*     */       //   start	length	slot	name	descriptor
/*     */       //   0	139	0	this	Lscala/util/parsing/combinator/Parsers$$anonfun$positioned$1;
/*     */       //   0	139	1	in	Lscala/util/parsing/input/Reader;
/*     */     }
/*     */   }
/*     */   
/*     */   public class Parsers$$anon$2 extends Parser<T> {
/*     */     public final Parsers.Parser p$18;
/*     */     
/*     */     public Parsers$$anon$2(Parsers $outer, Parsers.Parser p$18) {
/* 889 */       super($outer);
/*     */     }
/*     */     
/*     */     public Parsers.ParseResult<T> apply(Reader in) {
/* 890 */       return (Parsers.ParseResult<T>)this.$outer.scala$util$parsing$combinator$Parsers$$lastNoSuccessVar().withValue(scala.None$.MODULE$, 
/* 891 */           (Function0)new Parsers$$anon$2$$anonfun$apply$14(this, in));
/*     */     }
/*     */     
/*     */     public class Parsers$$anon$2$$anonfun$apply$14 extends AbstractFunction0<Parsers.ParseResult<T>> implements Serializable {
/*     */       public static final long serialVersionUID = 0L;
/*     */       
/*     */       private final Reader in$1;
/*     */       
/*     */       public final Parsers.ParseResult<T> apply() {
/* 891 */         Parsers.ParseResult parseResult = this.$outer.p$18.apply(this.in$1);
/* 892 */         if (parseResult instanceof Parsers.Success) {
/*     */           Option option1, option2;
/* 892 */           Parsers.Success success = (Parsers.Success)parseResult;
/* 896 */           Parsers$$anon$2$$anonfun$apply$14$$anonfun$apply$16 parsers$$anon$2$$anonfun$apply$14$$anonfun$apply$16 = new Parsers$$anon$2$$anonfun$apply$14$$anonfun$apply$16(this, success);
/*     */         } 
/*     */         Option option;
/* 897 */         return (option = (Option)this.$outer.scala$util$parsing$combinator$Parsers$$anon$$$outer().scala$util$parsing$combinator$Parsers$$lastNoSuccessVar().value()).isEmpty() ? parseResult : (Parsers.ParseResult)option.get();
/*     */       }
/*     */       
/*     */       public Parsers$$anon$2$$anonfun$apply$14(Parsers$$anon$2 $outer, Reader in$1) {}
/*     */       
/*     */       public class Parsers$$anon$2$$anonfun$apply$14$$anonfun$apply$16 extends AbstractFunction0<Parsers.Failure> implements Serializable {
/*     */         public static final long serialVersionUID = 0L;
/*     */         
/*     */         private final Parsers.Success x2$1;
/*     */         
/*     */         public final Parsers.Failure apply() {
/*     */           return new Parsers.Failure(this.$outer.$outer.scala$util$parsing$combinator$Parsers$$anon$$$outer(), "end of input expected", this.x2$1.next());
/*     */         }
/*     */         
/*     */         public Parsers$$anon$2$$anonfun$apply$14$$anonfun$apply$16(Parsers$$anon$2$$anonfun$apply$14 $outer, Parsers.Success x2$1) {}
/*     */       }
/*     */     }
/*     */   }
/*     */   
/*     */   public class Parsers$$anonfun$mkList$1 extends AbstractFunction1<$tilde<T, List<T>>, List<T>> implements Serializable {
/*     */     public static final long serialVersionUID = 0L;
/*     */     
/*     */     public final List<T> apply(Parsers.$tilde x$7) {
/* 903 */       if (x$7 != null) {
/* 903 */         Object object = x$7._1();
/* 903 */         return ((List)x$7._2()).$colon$colon(object);
/*     */       } 
/* 903 */       throw new MatchError(x$7);
/*     */     }
/*     */     
/*     */     public Parsers$$anonfun$mkList$1(Parsers $outer) {}
/*     */   }
/*     */   
/*     */   public class $tilde$ implements Serializable {
/*     */     public final String toString() {
/* 918 */       return "~";
/*     */     }
/*     */     
/*     */     public <a, b> Parsers.$tilde<a, b> apply(Object _1, Object _2) {
/* 918 */       return new Parsers.$tilde<a, b>(this.$outer, (a)_1, (b)_2);
/*     */     }
/*     */     
/*     */     public <a, b> Option<Tuple2<a, b>> unapply(Parsers.$tilde x$0) {
/* 918 */       return (x$0 == null) ? (Option<Tuple2<a, b>>)scala.None$.MODULE$ : (Option<Tuple2<a, b>>)new Some(new Tuple2(x$0._1(), x$0._2()));
/*     */     }
/*     */     
/*     */     private Object readResolve() {
/* 918 */       return this.$outer.$tilde();
/*     */     }
/*     */     
/*     */     public $tilde$(Parsers $outer) {}
/*     */   }
/*     */   
/*     */   public class $tilde<a, b> implements Product, Serializable {
/*     */     private final a _1;
/*     */     
/*     */     private final b _2;
/*     */     
/*     */     public a _1() {
/* 918 */       return this._1;
/*     */     }
/*     */     
/*     */     public b _2() {
/* 918 */       return this._2;
/*     */     }
/*     */     
/*     */     public <a, b> $tilde<a, b> copy(Object _1, Object _2) {
/* 918 */       return new $tilde(scala$util$parsing$combinator$Parsers$$tilde$$$outer(), (a)_1, (b)_2);
/*     */     }
/*     */     
/*     */     public <a, b> a copy$default$1() {
/* 918 */       return _1();
/*     */     }
/*     */     
/*     */     public <a, b> b copy$default$2() {
/* 918 */       return _2();
/*     */     }
/*     */     
/*     */     public String productPrefix() {
/* 918 */       return "~";
/*     */     }
/*     */     
/*     */     public int productArity() {
/* 918 */       return 2;
/*     */     }
/*     */     
/*     */     public Object productElement(int x$1) {
/* 918 */       switch (x$1) {
/*     */         default:
/* 918 */           throw new IndexOutOfBoundsException(BoxesRunTime.boxToInteger(x$1).toString());
/*     */         case 1:
/*     */         
/*     */         case 0:
/*     */           break;
/*     */       } 
/* 918 */       return _1();
/*     */     }
/*     */     
/*     */     public Iterator<Object> productIterator() {
/* 918 */       return scala.runtime.ScalaRunTime$.MODULE$.typedProductIterator(this);
/*     */     }
/*     */     
/*     */     public boolean canEqual(Object x$1) {
/* 918 */       return x$1 instanceof $tilde;
/*     */     }
/*     */     
/*     */     public int hashCode() {
/* 918 */       return scala.runtime.ScalaRunTime$.MODULE$._hashCode(this);
/*     */     }
/*     */     
/*     */     public boolean equals(Object x$1) {
/*     */       // Byte code:
/*     */       //   0: aload_0
/*     */       //   1: aload_1
/*     */       //   2: if_acmpeq -> 221
/*     */       //   5: aload_1
/*     */       //   6: instanceof scala/util/parsing/combinator/Parsers$$tilde
/*     */       //   9: ifeq -> 31
/*     */       //   12: aload_1
/*     */       //   13: checkcast scala/util/parsing/combinator/Parsers$$tilde
/*     */       //   16: invokevirtual scala$util$parsing$combinator$Parsers$$tilde$$$outer : ()Lscala/util/parsing/combinator/Parsers;
/*     */       //   19: aload_0
/*     */       //   20: invokevirtual scala$util$parsing$combinator$Parsers$$tilde$$$outer : ()Lscala/util/parsing/combinator/Parsers;
/*     */       //   23: if_acmpne -> 31
/*     */       //   26: iconst_1
/*     */       //   27: istore_2
/*     */       //   28: goto -> 33
/*     */       //   31: iconst_0
/*     */       //   32: istore_2
/*     */       //   33: iload_2
/*     */       //   34: ifeq -> 225
/*     */       //   37: aload_1
/*     */       //   38: checkcast scala/util/parsing/combinator/Parsers$$tilde
/*     */       //   41: astore #7
/*     */       //   43: aload_0
/*     */       //   44: invokevirtual _1 : ()Ljava/lang/Object;
/*     */       //   47: aload #7
/*     */       //   49: invokevirtual _1 : ()Ljava/lang/Object;
/*     */       //   52: astore #4
/*     */       //   54: dup
/*     */       //   55: astore_3
/*     */       //   56: aload #4
/*     */       //   58: if_acmpne -> 65
/*     */       //   61: iconst_1
/*     */       //   62: goto -> 117
/*     */       //   65: aload_3
/*     */       //   66: ifnonnull -> 73
/*     */       //   69: iconst_0
/*     */       //   70: goto -> 117
/*     */       //   73: aload_3
/*     */       //   74: instanceof java/lang/Number
/*     */       //   77: ifeq -> 92
/*     */       //   80: aload_3
/*     */       //   81: checkcast java/lang/Number
/*     */       //   84: aload #4
/*     */       //   86: invokestatic equalsNumObject : (Ljava/lang/Number;Ljava/lang/Object;)Z
/*     */       //   89: goto -> 117
/*     */       //   92: aload_3
/*     */       //   93: instanceof java/lang/Character
/*     */       //   96: ifeq -> 111
/*     */       //   99: aload_3
/*     */       //   100: checkcast java/lang/Character
/*     */       //   103: aload #4
/*     */       //   105: invokestatic equalsCharObject : (Ljava/lang/Character;Ljava/lang/Object;)Z
/*     */       //   108: goto -> 117
/*     */       //   111: aload_3
/*     */       //   112: aload #4
/*     */       //   114: invokevirtual equals : (Ljava/lang/Object;)Z
/*     */       //   117: ifeq -> 217
/*     */       //   120: aload_0
/*     */       //   121: invokevirtual _2 : ()Ljava/lang/Object;
/*     */       //   124: aload #7
/*     */       //   126: invokevirtual _2 : ()Ljava/lang/Object;
/*     */       //   129: astore #6
/*     */       //   131: dup
/*     */       //   132: astore #5
/*     */       //   134: aload #6
/*     */       //   136: if_acmpne -> 143
/*     */       //   139: iconst_1
/*     */       //   140: goto -> 201
/*     */       //   143: aload #5
/*     */       //   145: ifnonnull -> 152
/*     */       //   148: iconst_0
/*     */       //   149: goto -> 201
/*     */       //   152: aload #5
/*     */       //   154: instanceof java/lang/Number
/*     */       //   157: ifeq -> 173
/*     */       //   160: aload #5
/*     */       //   162: checkcast java/lang/Number
/*     */       //   165: aload #6
/*     */       //   167: invokestatic equalsNumObject : (Ljava/lang/Number;Ljava/lang/Object;)Z
/*     */       //   170: goto -> 201
/*     */       //   173: aload #5
/*     */       //   175: instanceof java/lang/Character
/*     */       //   178: ifeq -> 194
/*     */       //   181: aload #5
/*     */       //   183: checkcast java/lang/Character
/*     */       //   186: aload #6
/*     */       //   188: invokestatic equalsCharObject : (Ljava/lang/Character;Ljava/lang/Object;)Z
/*     */       //   191: goto -> 201
/*     */       //   194: aload #5
/*     */       //   196: aload #6
/*     */       //   198: invokevirtual equals : (Ljava/lang/Object;)Z
/*     */       //   201: ifeq -> 217
/*     */       //   204: aload #7
/*     */       //   206: aload_0
/*     */       //   207: invokevirtual canEqual : (Ljava/lang/Object;)Z
/*     */       //   210: ifeq -> 217
/*     */       //   213: iconst_1
/*     */       //   214: goto -> 218
/*     */       //   217: iconst_0
/*     */       //   218: ifeq -> 225
/*     */       //   221: iconst_1
/*     */       //   222: goto -> 226
/*     */       //   225: iconst_0
/*     */       //   226: ireturn
/*     */       // Line number table:
/*     */       //   Java source line number -> byte code offset
/*     */       //   #918	-> 0
/*     */       //   #236	-> 26
/*     */       //   #918	-> 33
/*     */       // Local variable table:
/*     */       //   start	length	slot	name	descriptor
/*     */       //   0	227	0	this	Lscala/util/parsing/combinator/Parsers$$tilde;
/*     */       //   0	227	1	x$1	Ljava/lang/Object;
/*     */     }
/*     */     
/*     */     public $tilde(Parsers $outer, Object _1, Object _2) {
/* 918 */       Product.class.$init$(this);
/*     */     }
/*     */     
/*     */     public String toString() {
/* 919 */       return (new StringBuilder()).append("(").append(_1()).append("~").append(_2()).append(")").toString();
/*     */     }
/*     */   }
/*     */   
/*     */   public interface OnceParser<T> {
/*     */     <U> Parsers.Parser<Parsers.$tilde<T, U>> $tilde(Function0<Parsers.Parser<U>> param1Function0);
/*     */     
/*     */     public class Parsers$OnceParser$$anonfun$$tilde$2 extends AbstractFunction1<T, Parsers.Parser<Parsers.$tilde<T, U>>> implements Serializable {
/*     */       public static final long serialVersionUID = 0L;
/*     */       
/*     */       private final Function0 p$19;
/*     */       
/*     */       public final Parsers.Parser<Parsers.$tilde<T, U>> apply(Object a) {
/* 926 */         return this.$outer.scala$util$parsing$combinator$Parsers$OnceParser$$$outer().commit(this.p$19).map((Function1)new Parsers$OnceParser$$anonfun$$tilde$2$$anonfun$apply$18(this, ($anonfun$$tilde$2)a));
/*     */       }
/*     */       
/*     */       public Parsers$OnceParser$$anonfun$$tilde$2(Parsers.OnceParser $outer, Function0 p$19) {}
/*     */       
/*     */       public class Parsers$OnceParser$$anonfun$$tilde$2$$anonfun$apply$18 extends AbstractFunction1<U, Parsers.$tilde<T, U>> implements Serializable {
/*     */         public static final long serialVersionUID = 0L;
/*     */         
/*     */         private final Object a$4;
/*     */         
/*     */         public final Parsers.$tilde<T, U> apply(Object b) {
/* 926 */           return new Parsers.$tilde<T, U>(this.$outer.$outer.scala$util$parsing$combinator$Parsers$OnceParser$$$outer(), (T)this.a$4, (U)b);
/*     */         }
/*     */         
/*     */         public Parsers$OnceParser$$anonfun$$tilde$2$$anonfun$apply$18(Parsers$OnceParser$$anonfun$$tilde$2 $outer, Object a$4) {}
/*     */       }
/*     */     }
/*     */   }
/*     */   
/*     */   public abstract class OnceParser$class {
/*     */     public static void $init$(Parsers.OnceParser $this) {}
/*     */     
/*     */     public static Parsers.Parser $tilde(Parsers.OnceParser $this, Function0 p) {
/* 926 */       return $this.scala$util$parsing$combinator$Parsers$OnceParser$$$outer().OnceParser(((Parsers.Parser)$this).flatMap((Function1)new Parsers$OnceParser$$anonfun$$tilde$2($this, (Parsers.OnceParser<T>)p)).named("~"));
/*     */     }
/*     */   }
/*     */ }


/* Location:              D:\#source-code\TheFlightSims\TFSLibrary\World2Xplane\World2XPlane.jar!\scal\\util\parsing\combinator\Parsers.class
 * Java compiler version: 6 (50.0)
 * JD-Core Version:       1.1.3
 */