/*    */ package scala;
/*    */ 
/*    */ import scala.collection.Iterator;
/*    */ import scala.collection.mutable.StringBuilder;
/*    */ import scala.reflect.ScalaSignature;
/*    */ import scala.runtime.ScalaRunTime$;
/*    */ 
/*    */ @ScalaSignature(bytes = "\006\001\031%e\001B\001\003\001\026\021q\001V;qY\026\f\004HC\001\004\003\025\0318-\0317b\007\001)2C\002\t\033;\001\032c%\013\0270eUB4HP!E\017*\033R\001A\004\f\031>\003\"\001C\005\016\003\tI!A\003\002\003\r\005s\027PU3g!QAABD\r\035?\t*\003f\013\0302i]RT\bQ\"G\023&\021QB\001\002\n!J|G-^2uca\002\"a\004\t\r\001\0211\021\003\001CC\002I\021!\001V\031\022\005M1\002C\001\005\025\023\t)\"AA\004O_RD\027N\\4\021\005!9\022B\001\r\003\005\r\te.\037\t\003\037i!aa\007\001\005\006\004\021\"A\001+3!\tyQ\004\002\004\037\001\021\025\rA\005\002\003)N\002\"a\004\021\005\r\005\002AQ1\001\023\005\t!F\007\005\002\020G\0211A\005\001CC\002I\021!\001V\033\021\005=1CAB\024\001\t\013\007!C\001\002UmA\021q\"\013\003\007U\001!)\031\001\n\003\005Q;\004CA\b-\t\031i\003\001\"b\001%\t\021A\013\017\t\003\037=\"a\001\r\001\005\006\004\021\"A\001+:!\ty!\007\002\0044\001\021\025\rA\005\002\004)F\002\004CA\b6\t\0311\004\001\"b\001%\t\031A+M\031\021\005=ADAB\035\001\t\013\007!CA\002UcI\002\"aD\036\005\rq\002AQ1\001\023\005\r!\026g\r\t\003\037y\"aa\020\001\005\006\004\021\"a\001+2iA\021q\"\021\003\007\005\002!)\031\001\n\003\007Q\013T\007\005\002\020\t\0221Q\t\001CC\002I\0211\001V\0317!\tyq\t\002\004I\001\021\025\rA\005\002\004)F:\004CA\bK\t\031Y\005\001\"b\001%\t\031A+\r\035\021\005!i\025B\001(\003\005\035\001&o\0343vGR\004\"\001\003)\n\005E\023!\001D*fe&\fG.\033>bE2,\007\002C*\001\005+\007I\021\001+\002\005}\013T#\001\b\t\021Y\003!\021#Q\001\n9\t1aX\031!\021!A\006A!f\001\n\003I\026AA03+\005I\002\002C.\001\005#\005\013\021B\r\002\007}\023\004\005\003\005^\001\tU\r\021\"\001_\003\ty6'F\001\035\021!\001\007A!E!\002\023a\022aA04A!A!\r\001BK\002\023\0051-\001\002`iU\tq\004\003\005f\001\tE\t\025!\003 \003\ryF\007\t\005\tO\002\021)\032!C\001Q\006\021q,N\013\002E!A!\016\001B\tB\003%!%A\002`k\001B\001\002\034\001\003\026\004%\t!\\\001\003?Z*\022!\n\005\t_\002\021\t\022)A\005K\005\031qL\016\021\t\021E\004!Q3A\005\002I\f!aX\034\026\003!B\001\002\036\001\003\022\003\006I\001K\001\004?^\002\003\002\003<\001\005+\007I\021A<\002\005}CT#A\026\t\021e\004!\021#Q\001\n-\n1a\030\035!\021!Y\bA!f\001\n\003a\030AA0:+\005q\003\002\003@\001\005#\005\013\021\002\030\002\007}K\004\005\003\006\002\002\001\021)\032!C\001\003\007\t1aX\0311+\005\t\004\"CA\004\001\tE\t\025!\0032\003\021y\026\007\r\021\t\025\005-\001A!f\001\n\003\ti!A\002`cE*\022\001\016\005\n\003#\001!\021#Q\001\nQ\nAaX\0312A!Q\021Q\003\001\003\026\004%\t!a\006\002\007}\013$'F\0018\021%\tY\002\001B\tB\003%q'\001\003`cI\002\003BCA\020\001\tU\r\021\"\001\002\"\005\031q,M\032\026\003iB\021\"!\n\001\005#\005\013\021\002\036\002\t}\0134\007\t\005\013\003S\001!Q3A\005\002\005-\022aA02iU\tQ\bC\005\0020\001\021\t\022)A\005{\005!q,\r\033!\021)\t\031\004\001BK\002\023\005\021QG\001\004?F*T#\001!\t\023\005e\002A!E!\002\023\001\025\001B02k\001B!\"!\020\001\005+\007I\021AA \003\ry\026GN\013\002\007\"I\0211\t\001\003\022\003\006IaQ\001\005?F2\004\005\003\006\002H\001\021)\032!C\001\003\023\n1aX\0318+\0051\005\"CA'\001\tE\t\025!\003G\003\021y\026g\016\021\t\025\005E\003A!f\001\n\003\t\031&A\002`ca*\022!\023\005\n\003/\002!\021#Q\001\n%\013AaX\0319A!9\0211\f\001\005\002\005u\023A\002\037j]&$h\b\006\024\002`\005\005\0241MA3\003O\nI'a\033\002n\005=\024\021OA:\003k\n9(!\037\002|\005u\024qPAA\003\007\003B\003\003\001\0173qy\"%\n\025,]E\"tGO\037A\007\032K\005BB*\002Z\001\007a\002\003\004Y\0033\002\r!\007\005\007;\006e\003\031\001\017\t\r\t\fI\0061\001 \021\0319\027\021\fa\001E!1A.!\027A\002\025Ba!]A-\001\004A\003B\002<\002Z\001\0071\006\003\004|\0033\002\rA\f\005\b\003\003\tI\0061\0012\021\035\tY!!\027A\002QBq!!\006\002Z\001\007q\007C\004\002 \005e\003\031\001\036\t\017\005%\022\021\fa\001{!9\0211GA-\001\004\001\005bBA\037\0033\002\ra\021\005\b\003\017\nI\0061\001G\021\035\t\t&!\027A\002%Cq!a\"\001\t\003\nI)\001\005u_N#(/\0338h)\t\tY\t\005\003\002\016\006]UBAAH\025\021\t\t*a%\002\t1\fgn\032\006\003\003+\013AA[1wC&!\021\021TAH\005\031\031FO]5oO\"I\021Q\024\001\002\002\023\005\021qT\001\005G>\004\0300\006\024\002\"\006\035\0261VAX\003g\0139,a/\002@\006\r\027qYAf\003\037\f\031.a6\002\\\006}\0271]At\003W$b%a)\002n\006=\030\021_Az\003k\f90!?\002|\006u\030q B\001\005\007\021)Aa\002\003\n\t-!Q\002B\b!\031B\001!!*\002*\0065\026\021WA[\003s\013i,!1\002F\006%\027QZAi\003+\fI.!8\002b\006\025\030\021\036\t\004\037\005\035FAB\t\002\034\n\007!\003E\002\020\003W#aaGAN\005\004\021\002cA\b\0020\0221a$a'C\002I\0012aDAZ\t\031\t\0231\024b\001%A\031q\"a.\005\r\021\nYJ1\001\023!\ry\0211\030\003\007O\005m%\031\001\n\021\007=\ty\f\002\004+\0037\023\rA\005\t\004\037\005\rGAB\027\002\034\n\007!\003E\002\020\003\017$a\001MAN\005\004\021\002cA\b\002L\02211'a'C\002I\0012aDAh\t\0311\0241\024b\001%A\031q\"a5\005\re\nYJ1\001\023!\ry\021q\033\003\007y\005m%\031\001\n\021\007=\tY\016\002\004@\0037\023\rA\005\t\004\037\005}GA\002\"\002\034\n\007!\003E\002\020\003G$a!RAN\005\004\021\002cA\b\002h\0221\001*a'C\002I\0012aDAv\t\031Y\0251\024b\001%!I1+a'\021\002\003\007\021Q\025\005\n1\006m\005\023!a\001\003SC\021\"XAN!\003\005\r!!,\t\023\t\fY\n%AA\002\005E\006\"C4\002\034B\005\t\031AA[\021%a\0271\024I\001\002\004\tI\fC\005r\0037\003\n\0211\001\002>\"Ia/a'\021\002\003\007\021\021\031\005\nw\006m\005\023!a\001\003\013D!\"!\001\002\034B\005\t\031AAe\021)\tY!a'\021\002\003\007\021Q\032\005\013\003+\tY\n%AA\002\005E\007BCA\020\0037\003\n\0211\001\002V\"Q\021\021FAN!\003\005\r!!7\t\025\005M\0221\024I\001\002\004\ti\016\003\006\002>\005m\005\023!a\001\003CD!\"a\022\002\034B\005\t\031AAs\021)\t\t&a'\021\002\003\007\021\021\036\005\n\005'\001\021\023!C\001\005+\tabY8qs\022\"WMZ1vYR$\023'\006\024\003\030\t5\"q\006B\031\005g\021)Da\016\003:\tm\"Q\bB \005\003\022\031E!\022\003H\t%#1\nB'\005\037*\"A!\007+\0079\021Yb\013\002\003\036A!!q\004B\025\033\t\021\tC\003\003\003$\t\025\022!C;oG\",7m[3e\025\r\0219CA\001\013C:tw\016^1uS>t\027\002\002B\026\005C\021\021#\0368dQ\026\0347.\0323WCJL\027M\\2f\t\031\t\"\021\003b\001%\02111D!\005C\002I!aA\bB\t\005\004\021BAB\021\003\022\t\007!\003\002\004%\005#\021\rA\005\003\007O\tE!\031\001\n\005\r)\022\tB1\001\023\t\031i#\021\003b\001%\0211\001G!\005C\002I!aa\rB\t\005\004\021BA\002\034\003\022\t\007!\003\002\004:\005#\021\rA\005\003\007y\tE!\031\001\n\005\r}\022\tB1\001\023\t\031\021%\021\003b\001%\0211QI!\005C\002I!a\001\023B\t\005\004\021BAB&\003\022\t\007!\003C\005\003T\001\t\n\021\"\001\003V\005q1m\0349zI\021,g-Y;mi\022\022TC\nB,\0057\022iFa\030\003b\t\r$Q\rB4\005S\022YG!\034\003p\tE$1\017B;\005o\022IHa\037\003~U\021!\021\f\026\0043\tmAAB\t\003R\t\007!\003\002\004\034\005#\022\rA\005\003\007=\tE#\031\001\n\005\r\005\022\tF1\001\023\t\031!#\021\013b\001%\0211qE!\025C\002I!aA\013B)\005\004\021BAB\027\003R\t\007!\003\002\0041\005#\022\rA\005\003\007g\tE#\031\001\n\005\rY\022\tF1\001\023\t\031I$\021\013b\001%\0211AH!\025C\002I!aa\020B)\005\004\021BA\002\"\003R\t\007!\003\002\004F\005#\022\rA\005\003\007\021\nE#\031\001\n\005\r-\023\tF1\001\023\021%\021\t\tAI\001\n\003\021\031)\001\bd_BLH\005Z3gCVdG\017J\032\026M\t\025%\021\022BF\005\033\023yI!%\003\024\nU%q\023BM\0057\023iJa(\003\"\n\r&Q\025BT\005S\023Y+\006\002\003\b*\032ADa\007\005\rE\021yH1\001\023\t\031Y\"q\020b\001%\0211aDa C\002I!a!\tB@\005\004\021BA\002\023\003\000\t\007!\003\002\004(\005\022\rA\005\003\007U\t}$\031\001\n\005\r5\022yH1\001\023\t\031\001$q\020b\001%\02111Ga C\002I!aA\016B@\005\004\021BAB\035\003\000\t\007!\003\002\004=\005\022\rA\005\003\007\t}$\031\001\n\005\r\t\023yH1\001\023\t\031)%q\020b\001%\0211\001Ja C\002I!aa\023B@\005\004\021\002\"\003BX\001E\005I\021\001BY\0039\031w\016]=%I\0264\027-\0367uIQ*bEa-\0038\ne&1\030B_\005\023\tMa1\003F\n\035'\021\032Bf\005\033\024yM!5\003T\nU'q\033Bm+\t\021)LK\002 \0057!a!\005BW\005\004\021BAB\016\003.\n\007!\003\002\004\037\005[\023\rA\005\003\007C\t5&\031\001\n\005\r\021\022iK1\001\023\t\0319#Q\026b\001%\0211!F!,C\002I!a!\fBW\005\004\021BA\002\031\003.\n\007!\003\002\0044\005[\023\rA\005\003\007m\t5&\031\001\n\005\re\022iK1\001\023\t\031a$Q\026b\001%\0211qH!,C\002I!aA\021BW\005\004\021BAB#\003.\n\007!\003\002\004I\005[\023\rA\005\003\007\027\n5&\031\001\n\t\023\tu\007!%A\005\002\t}\027AD2paf$C-\0324bk2$H%N\013'\005C\024)Oa:\003j\n-(Q\036Bx\005c\024\031P!>\003x\ne(1 B\005\034\taa\001\004\006\r\035QC\001BrU\r\021#1\004\003\007#\tm'\031\001\n\005\rm\021YN1\001\023\t\031q\"1\034b\001%\0211\021Ea7C\002I!a\001\nBn\005\004\021BAB\024\003\\\n\007!\003\002\004+\0057\024\rA\005\003\007[\tm'\031\001\n\005\rA\022YN1\001\023\t\031\031$1\034b\001%\0211aGa7C\002I!a!\017Bn\005\004\021BA\002\037\003\\\n\007!\003\002\004@\0057\024\rA\005\003\007\005\nm'\031\001\n\005\r\025\023YN1\001\023\t\031A%1\034b\001%\02111Ja7C\002IA\021ba\003\001#\003%\ta!\004\002\035\r|\007/\037\023eK\032\fW\017\034;%mU13qBB\n\007+\0319b!\007\004\034\ru1qDB\021\007G\031)ca\n\004*\r-2QFB\030\007c\031\031d!\016\026\005\rE!fA\023\003\034\0211\021c!\003C\002I!aaGB\005\005\004\021BA\002\020\004\n\t\007!\003\002\004\"\007\023\021\rA\005\003\007I\r%!\031\001\n\005\r\035\032IA1\001\023\t\031Q3\021\002b\001%\0211Qf!\003C\002I!a\001MB\005\005\004\021BAB\032\004\n\t\007!\003\002\0047\007\023\021\rA\005\003\007s\r%!\031\001\n\005\rq\032IA1\001\023\t\031y4\021\002b\001%\0211!i!\003C\002I!a!RB\005\005\004\021BA\002%\004\n\t\007!\003\002\004L\007\023\021\rA\005\005\n\007s\001\021\023!C\001\007w\tabY8qs\022\"WMZ1vYR$s'\006\024\004>\r\00531IB#\007\017\032Iea\023\004N\r=3\021KB*\007+\0329f!\027\004\\\ru3qLB1\007G*\"aa\020+\007!\022Y\002\002\004\022\007o\021\rA\005\003\0077\r]\"\031\001\n\005\ry\0319D1\001\023\t\031\t3q\007b\001%\0211Aea\016C\002I!aaJB\034\005\004\021BA\002\026\0048\t\007!\003\002\004.\007o\021\rA\005\003\007a\r]\"\031\001\n\005\rM\0329D1\001\023\t\03114q\007b\001%\0211\021ha\016C\002I!a\001PB\034\005\004\021BAB \0048\t\007!\003\002\004C\007o\021\rA\005\003\007\013\016]\"\031\001\n\005\r!\0339D1\001\023\t\031Y5q\007b\001%!I1q\r\001\022\002\023\0051\021N\001\017G>\004\030\020\n3fM\006,H\016\036\0239+\031\032Yga\034\004r\rM4QOB<\007s\032Yh! \004\000\r\00551QBC\007\017\033Iia#\004\016\016=5\021S\013\003\007[R3a\013B\016\t\031\t2Q\rb\001%\02111d!\032C\002I!aAHB3\005\004\021BAB\021\004f\t\007!\003\002\004%\007K\022\rA\005\003\007O\r\025$\031\001\n\005\r)\032)G1\001\023\t\031i3Q\rb\001%\0211\001g!\032C\002I!aaMB3\005\004\021BA\002\034\004f\t\007!\003\002\004:\007K\022\rA\005\003\007y\r\025$\031\001\n\005\r}\032)G1\001\023\t\031\0215Q\rb\001%\0211Qi!\032C\002I!a\001SB3\005\004\021BAB&\004f\t\007!\003C\005\004\026\002\t\n\021\"\001\004\030\006q1m\0349zI\021,g-Y;mi\022JTCJBM\007;\033yj!)\004$\016\0256qUBU\007W\033ika,\0042\016M6QWB\\\007s\033Yl!0\004@V\02111\024\026\004]\tmAAB\t\004\024\n\007!\003\002\004\034\007'\023\rA\005\003\007=\rM%\031\001\n\005\r\005\032\031J1\001\023\t\031!31\023b\001%\0211qea%C\002I!aAKBJ\005\004\021BAB\027\004\024\n\007!\003\002\0041\007'\023\rA\005\003\007g\rM%\031\001\n\005\rY\032\031J1\001\023\t\031I41\023b\001%\0211Aha%C\002I!aaPBJ\005\004\021BA\002\"\004\024\n\007!\003\002\004F\007'\023\rA\005\003\007\021\016M%\031\001\n\005\r-\033\031J1\001\023\021%\031\031\rAI\001\n\003\031)-A\bd_BLH\005Z3gCVdG\017J\0311+\031\0329ma3\004N\016=7\021[Bj\007+\0349n!7\004\\\016u7q\\Bq\007G\034)oa:\004j\016-8Q^\013\003\007\023T3!\rB\016\t\031\t2\021\031b\001%\02111d!1C\002I!aAHBa\005\004\021BAB\021\004B\n\007!\003\002\004%\007\003\024\rA\005\003\007O\r\005'\031\001\n\005\r)\032\tM1\001\023\t\031i3\021\031b\001%\0211\001g!1C\002I!aaMBa\005\004\021BA\002\034\004B\n\007!\003\002\004:\007\003\024\rA\005\003\007y\r\005'\031\001\n\005\r}\032\tM1\001\023\t\031\0215\021\031b\001%\0211Qi!1C\002I!a\001SBa\005\004\021BAB&\004B\n\007!\003C\005\004r\002\t\n\021\"\001\004t\006y1m\0349zI\021,g-Y;mi\022\n\024'\006\024\004v\016e81`B\007$\t\001b\001\005\006\021\035A\021\002C\006\t\033!y\001\"\005\005\024\021UAq\003C\r\t7)\"aa>+\007Q\022Y\002\002\004\022\007_\024\rA\005\003\0077\r=(\031\001\n\005\ry\031yO1\001\023\t\031\t3q\036b\001%\0211Aea<C\002I!aaJBx\005\004\021BA\002\026\004p\n\007!\003\002\004.\007_\024\rA\005\003\007a\r=(\031\001\n\005\rM\032yO1\001\023\t\03114q\036b\001%\0211\021ha<C\002I!a\001PBx\005\004\021BAB \004p\n\007!\003\002\004C\007_\024\rA\005\003\007\013\016=(\031\001\n\005\r!\033yO1\001\023\t\031Y5q\036b\001%!IAq\004\001\022\002\023\005A\021E\001\020G>\004\030\020\n3fM\006,H\016\036\0232eU1C1\005C\024\tS!Y\003\"\f\0050\021EB1\007C\033\to!I\004b\017\005>\021}B\021\tC\"\t\013\"9\005\"\023\026\005\021\025\"fA\034\003\034\0211\021\003\"\bC\002I!aa\007C\017\005\004\021BA\002\020\005\036\t\007!\003\002\004\"\t;\021\rA\005\003\007I\021u!\031\001\n\005\r\035\"iB1\001\023\t\031QCQ\004b\001%\0211Q\006\"\bC\002I!a\001\rC\017\005\004\021BAB\032\005\036\t\007!\003\002\0047\t;\021\rA\005\003\007s\021u!\031\001\n\005\rq\"iB1\001\023\t\031yDQ\004b\001%\0211!\t\"\bC\002I!a!\022C\017\005\004\021BA\002%\005\036\t\007!\003\002\004L\t;\021\rA\005\005\n\t\033\002\021\023!C\001\t\037\nqbY8qs\022\"WMZ1vYR$\023gM\013'\t#\")\006b\026\005Z\021mCQ\fC0\tC\"\031\007\"\032\005h\021%D1\016C7\t_\"\t\bb\035\005v\021]TC\001C*U\rQ$1\004\003\007#\021-#\031\001\n\005\rm!YE1\001\023\t\031qB1\nb\001%\0211\021\005b\023C\002I!a\001\nC&\005\004\021BAB\024\005L\t\007!\003\002\004+\t\027\022\rA\005\003\007[\021-#\031\001\n\005\rA\"YE1\001\023\t\031\031D1\nb\001%\0211a\007b\023C\002I!a!\017C&\005\004\021BA\002\037\005L\t\007!\003\002\004@\t\027\022\rA\005\003\007\005\022-#\031\001\n\005\r\025#YE1\001\023\t\031AE1\nb\001%\02111\nb\023C\002IA\021\002b\037\001#\003%\t\001\" \002\037\r|\007/\037\023eK\032\fW\017\034;%cQ*b\005b \005\004\022\025Eq\021CE\t\027#i\tb$\005\022\022MEQ\023CL\t3#Y\n\"(\005 \022\005F1\025CS+\t!\tIK\002>\0057!a!\005C=\005\004\021BAB\016\005z\t\007!\003\002\004\037\ts\022\rA\005\003\007C\021e$\031\001\n\005\r\021\"IH1\001\023\t\0319C\021\020b\001%\0211!\006\"\037C\002I!a!\fC=\005\004\021BA\002\031\005z\t\007!\003\002\0044\ts\022\rA\005\003\007m\021e$\031\001\n\005\re\"IH1\001\023\t\031aD\021\020b\001%\0211q\b\"\037C\002I!aA\021C=\005\004\021BAB#\005z\t\007!\003\002\004I\ts\022\rA\005\003\007\027\022e$\031\001\n\t\023\021%\006!%A\005\002\021-\026aD2paf$C-\0324bk2$H%M\033\026M\0215F\021\027CZ\tk#9\f\"/\005<\022uFq\030Ca\t\007$)\rb2\005J\022-GQ\032Ch\t#$\031.\006\002\0050*\032\001Ia\007\005\rE!9K1\001\023\t\031YBq\025b\001%\0211a\004b*C\002I!a!\tCT\005\004\021BA\002\023\005(\n\007!\003\002\004(\tO\023\rA\005\003\007U\021\035&\031\001\n\005\r5\"9K1\001\023\t\031\001Dq\025b\001%\02111\007b*C\002I!aA\016CT\005\004\021BAB\035\005(\n\007!\003\002\004=\tO\023\rA\005\003\007\021\035&\031\001\n\005\r\t#9K1\001\023\t\031)Eq\025b\001%\0211\001\nb*C\002I!aa\023CT\005\004\021\002\"\003Cl\001E\005I\021\001Cm\003=\031w\016]=%I\0264\027-\0367uIE2TC\nCn\t?$\t\017b9\005f\022\035H\021\036Cv\t[$y\017\"=\005t\022UHq\037C}\tw$i\020b@\006\002U\021AQ\034\026\004\007\nmAAB\t\005V\n\007!\003\002\004\034\t+\024\rA\005\003\007=\021U'\031\001\n\005\r\005\")N1\001\023\t\031!CQ\033b\001%\0211q\005\"6C\002I!aA\013Ck\005\004\021BAB\027\005V\n\007!\003\002\0041\t+\024\rA\005\003\007g\021U'\031\001\n\005\rY\")N1\001\023\t\031IDQ\033b\001%\0211A\b\"6C\002I!aa\020Ck\005\004\021BA\002\"\005V\n\007!\003\002\004F\t+\024\rA\005\003\007\021\022U'\031\001\n\005\r-#)N1\001\023\021%))\001AI\001\n\003)9!A\bd_BLH\005Z3gCVdG\017J\0318+\031*I!\"\004\006\020\025EQ1CC\013\013/)I\"b\007\006\036\025}Q\021EC\022\013K)9#\"\013\006,\0255RqF\013\003\013\027Q3A\022B\016\t\031\tR1\001b\001%\02111$b\001C\002I!aAHC\002\005\004\021BAB\021\006\004\t\007!\003\002\004%\013\007\021\rA\005\003\007O\025\r!\031\001\n\005\r)*\031A1\001\023\t\031iS1\001b\001%\0211\001'b\001C\002I!aaMC\002\005\004\021BA\002\034\006\004\t\007!\003\002\004:\013\007\021\rA\005\003\007y\025\r!\031\001\n\005\r}*\031A1\001\023\t\031\021U1\001b\001%\0211Q)b\001C\002I!a\001SC\002\005\004\021BAB&\006\004\t\007!\003C\005\0064\001\t\n\021\"\001\0066\005y1m\0349zI\021,g-Y;mi\022\n\004(\006\024\0068\025mRQHC \013\003*\031%\"\022\006H\025%S1JC'\013\037*\t&b\025\006V\025]S\021LC.\013;*\"!\"\017+\007%\023Y\002\002\004\022\013c\021\rA\005\003\0077\025E\"\031\001\n\005\ry)\tD1\001\023\t\031\tS\021\007b\001%\0211A%\"\rC\002I!aaJC\031\005\004\021BA\002\026\0062\t\007!\003\002\004.\013c\021\rA\005\003\007a\025E\"\031\001\n\005\rM*\tD1\001\023\t\0311T\021\007b\001%\0211\021(\"\rC\002I!a\001PC\031\005\004\021BAB \0062\t\007!\003\002\004C\013c\021\rA\005\003\007\013\026E\"\031\001\n\005\r!+\tD1\001\023\t\031YU\021\007b\001%!IQ\021\r\001\002\002\023\005S1M\001\016aJ|G-^2u!J,g-\033=\026\005\005-\005\"CC4\001\005\005I\021IC5\003=\001(o\0343vGRLE/\032:bi>\024XCAC6!\025)i'b\035\027\033\t)yGC\002\006r\t\t!bY8mY\026\034G/[8o\023\021))(b\034\003\021%#XM]1u_JD\021\"\"\037\001\003\003%\t!b\037\002\021\r\fg.R9vC2$B!\" \006\004B\031\001\"b \n\007\025\005%AA\004C_>dW-\0318\t\023\025\025UqOA\001\002\0041\022a\001=%c!IQ\021\022\001\002\002\023\005S1R\001\tQ\006\034\bnQ8eKR\021QQ\022\t\004\021\025=\025bACI\005\t\031\021J\034;\t\023\025U\005!!A\005B\025]\025AB3rk\006d7\017\006\003\006~\025e\005\"CCC\013'\013\t\0211\001\027\017%)iJAA\001\022\003)y*A\004UkBdW-\r\035\021\007!)\tK\002\005\002\005\005\005\t\022ACR'\021)\tkB(\t\021\005mS\021\025C\001\013O#\"!b(\t\025\005\035U\021UA\001\n\013\nI\t\003\006\006.\026\005\026\021!CA\013_\013Q!\0319qYf,b%\"-\0068\026mVqXCb\013\017,Y-b4\006T\026]W1\\Cp\013G,9/b;\006p\026MXq_C~)\031*\031,\"@\006\000\032\005a1\001D\003\r\0171IAb\003\007\016\031=a\021\003D\n\r+19B\"\007\007\034\031uaq\004\t'\021\001)),\"/\006>\026\005WQYCe\013\033,\t.\"6\006Z\026uW\021]Cs\013S,i/\"=\006v\026e\bcA\b\0068\0221\021#b+C\002I\0012aDC^\t\031YR1\026b\001%A\031q\"b0\005\ry)YK1\001\023!\ryQ1\031\003\007C\025-&\031\001\n\021\007=)9\r\002\004%\013W\023\rA\005\t\004\037\025-GAB\024\006,\n\007!\003E\002\020\013\037$aAKCV\005\004\021\002cA\b\006T\0221Q&b+C\002I\0012aDCl\t\031\001T1\026b\001%A\031q\"b7\005\rM*YK1\001\023!\ryQq\034\003\007m\025-&\031\001\n\021\007=)\031\017\002\004:\013W\023\rA\005\t\004\037\025\035HA\002\037\006,\n\007!\003E\002\020\013W$aaPCV\005\004\021\002cA\b\006p\0221!)b+C\002I\0012aDCz\t\031)U1\026b\001%A\031q\"b>\005\r!+YK1\001\023!\ryQ1 \003\007\027\026-&\031\001\n\t\017M+Y\0131\001\0066\"9\001,b+A\002\025e\006bB/\006,\002\007QQ\030\005\bE\026-\006\031ACa\021\0359W1\026a\001\013\013Dq\001\\CV\001\004)I\rC\004r\013W\003\r!\"4\t\017Y,Y\0131\001\006R\"910b+A\002\025U\007\002CA\001\013W\003\r!\"7\t\021\005-Q1\026a\001\013;D\001\"!\006\006,\002\007Q\021\035\005\t\003?)Y\0131\001\006f\"A\021\021FCV\001\004)I\017\003\005\0024\025-\006\031ACw\021!\ti$b+A\002\025E\b\002CA$\013W\003\r!\">\t\021\005ES1\026a\001\013sD!Bb\t\006\"\006\005I\021\021D\023\003\035)h.\0319qYf,bEb\n\0074\031]b1\bD \r\00729Eb\023\007P\031Mcq\013D.\r?2\031Gb\032\007l\031=d1\017D<)\0211IC\"\037\021\013!1YCb\f\n\007\0315\"A\001\004PaRLwN\034\t'\021\0011\tD\"\016\007:\031ub\021\tD#\r\0232iE\"\025\007V\031ecQ\fD1\rK2IG\"\034\007r\031U\004cA\b\0074\0211\021C\"\tC\002I\0012a\004D\034\t\031Yb\021\005b\001%A\031qBb\017\005\ry1\tC1\001\023!\ryaq\b\003\007C\031\005\"\031\001\n\021\007=1\031\005\002\004%\rC\021\rA\005\t\004\037\031\035CAB\024\007\"\t\007!\003E\002\020\r\027\"aA\013D\021\005\004\021\002cA\b\007P\0211QF\"\tC\002I\0012a\004D*\t\031\001d\021\005b\001%A\031qBb\026\005\rM2\tC1\001\023!\rya1\f\003\007m\031\005\"\031\001\n\021\007=1y\006\002\004:\rC\021\rA\005\t\004\037\031\rDA\002\037\007\"\t\007!\003E\002\020\rO\"aa\020D\021\005\004\021\002cA\b\007l\0211!I\"\tC\002I\0012a\004D8\t\031)e\021\005b\001%A\031qBb\035\005\r!3\tC1\001\023!\ryaq\017\003\007\027\032\005\"\031\001\n\t\025\031md\021EA\001\002\0041y#A\002yIAB!Bb \006\"\006\005I\021\002DA\003-\021X-\0313SKN|GN^3\025\005\031\r\005\003BAG\r\013KAAb\"\002\020\n1qJ\0316fGR\004")
/*    */ public class Tuple18<T1, T2, T3, T4, T5, T6, T7, T8, T9, T10, T11, T12, T13, T14, T15, T16, T17, T18> implements Product18<T1, T2, T3, T4, T5, T6, T7, T8, T9, T10, T11, T12, T13, T14, T15, T16, T17, T18>, Product, Serializable {
/*    */   private final T1 _1;
/*    */   
/*    */   private final T2 _2;
/*    */   
/*    */   private final T3 _3;
/*    */   
/*    */   private final T4 _4;
/*    */   
/*    */   private final T5 _5;
/*    */   
/*    */   private final T6 _6;
/*    */   
/*    */   private final T7 _7;
/*    */   
/*    */   private final T8 _8;
/*    */   
/*    */   private final T9 _9;
/*    */   
/*    */   private final T10 _10;
/*    */   
/*    */   private final T11 _11;
/*    */   
/*    */   private final T12 _12;
/*    */   
/*    */   private final T13 _13;
/*    */   
/*    */   private final T14 _14;
/*    */   
/*    */   private final T15 _15;
/*    */   
/*    */   private final T16 _16;
/*    */   
/*    */   private final T17 _17;
/*    */   
/*    */   private final T18 _18;
/*    */   
/*    */   public int productArity() {
/* 35 */     return Product18$class.productArity(this);
/*    */   }
/*    */   
/*    */   public Object productElement(int n) throws IndexOutOfBoundsException {
/* 35 */     return Product18$class.productElement(this, n);
/*    */   }
/*    */   
/*    */   public T1 _1() {
/* 35 */     return this._1;
/*    */   }
/*    */   
/*    */   public T2 _2() {
/* 35 */     return this._2;
/*    */   }
/*    */   
/*    */   public T3 _3() {
/* 35 */     return this._3;
/*    */   }
/*    */   
/*    */   public T4 _4() {
/* 35 */     return this._4;
/*    */   }
/*    */   
/*    */   public T5 _5() {
/* 35 */     return this._5;
/*    */   }
/*    */   
/*    */   public T6 _6() {
/* 35 */     return this._6;
/*    */   }
/*    */   
/*    */   public T7 _7() {
/* 35 */     return this._7;
/*    */   }
/*    */   
/*    */   public T8 _8() {
/* 35 */     return this._8;
/*    */   }
/*    */   
/*    */   public T9 _9() {
/* 35 */     return this._9;
/*    */   }
/*    */   
/*    */   public T10 _10() {
/* 35 */     return this._10;
/*    */   }
/*    */   
/*    */   public T11 _11() {
/* 35 */     return this._11;
/*    */   }
/*    */   
/*    */   public T12 _12() {
/* 35 */     return this._12;
/*    */   }
/*    */   
/*    */   public T13 _13() {
/* 35 */     return this._13;
/*    */   }
/*    */   
/*    */   public T14 _14() {
/* 35 */     return this._14;
/*    */   }
/*    */   
/*    */   public T15 _15() {
/* 35 */     return this._15;
/*    */   }
/*    */   
/*    */   public T16 _16() {
/* 35 */     return this._16;
/*    */   }
/*    */   
/*    */   public T17 _17() {
/* 35 */     return this._17;
/*    */   }
/*    */   
/*    */   public T18 _18() {
/* 35 */     return this._18;
/*    */   }
/*    */   
/*    */   public <T1, T2, T3, T4, T5, T6, T7, T8, T9, T10, T11, T12, T13, T14, T15, T16, T17, T18> Tuple18<T1, T2, T3, T4, T5, T6, T7, T8, T9, T10, T11, T12, T13, T14, T15, T16, T17, T18> copy(Object _1, Object _2, Object _3, Object _4, Object _5, Object _6, Object _7, Object _8, Object _9, Object _10, Object _11, Object _12, Object _13, Object _14, Object _15, Object _16, Object _17, Object _18) {
/* 35 */     return new Tuple18((T1)_1, (T2)_2, (T3)_3, (T4)_4, (T5)_5, (T6)_6, (T7)_7, (T8)_8, (T9)_9, (T10)_10, (T11)_11, (T12)_12, (T13)_13, (T14)_14, (T15)_15, (T16)_16, (T17)_17, (T18)_18);
/*    */   }
/*    */   
/*    */   public <T1, T2, T3, T4, T5, T6, T7, T8, T9, T10, T11, T12, T13, T14, T15, T16, T17, T18> T1 copy$default$1() {
/* 35 */     return _1();
/*    */   }
/*    */   
/*    */   public <T1, T2, T3, T4, T5, T6, T7, T8, T9, T10, T11, T12, T13, T14, T15, T16, T17, T18> T2 copy$default$2() {
/* 35 */     return _2();
/*    */   }
/*    */   
/*    */   public <T1, T2, T3, T4, T5, T6, T7, T8, T9, T10, T11, T12, T13, T14, T15, T16, T17, T18> T3 copy$default$3() {
/* 35 */     return _3();
/*    */   }
/*    */   
/*    */   public <T1, T2, T3, T4, T5, T6, T7, T8, T9, T10, T11, T12, T13, T14, T15, T16, T17, T18> T4 copy$default$4() {
/* 35 */     return _4();
/*    */   }
/*    */   
/*    */   public <T1, T2, T3, T4, T5, T6, T7, T8, T9, T10, T11, T12, T13, T14, T15, T16, T17, T18> T5 copy$default$5() {
/* 35 */     return _5();
/*    */   }
/*    */   
/*    */   public <T1, T2, T3, T4, T5, T6, T7, T8, T9, T10, T11, T12, T13, T14, T15, T16, T17, T18> T6 copy$default$6() {
/* 35 */     return _6();
/*    */   }
/*    */   
/*    */   public <T1, T2, T3, T4, T5, T6, T7, T8, T9, T10, T11, T12, T13, T14, T15, T16, T17, T18> T7 copy$default$7() {
/* 35 */     return _7();
/*    */   }
/*    */   
/*    */   public <T1, T2, T3, T4, T5, T6, T7, T8, T9, T10, T11, T12, T13, T14, T15, T16, T17, T18> T8 copy$default$8() {
/* 35 */     return _8();
/*    */   }
/*    */   
/*    */   public <T1, T2, T3, T4, T5, T6, T7, T8, T9, T10, T11, T12, T13, T14, T15, T16, T17, T18> T9 copy$default$9() {
/* 35 */     return _9();
/*    */   }
/*    */   
/*    */   public <T1, T2, T3, T4, T5, T6, T7, T8, T9, T10, T11, T12, T13, T14, T15, T16, T17, T18> T10 copy$default$10() {
/* 35 */     return _10();
/*    */   }
/*    */   
/*    */   public <T1, T2, T3, T4, T5, T6, T7, T8, T9, T10, T11, T12, T13, T14, T15, T16, T17, T18> T11 copy$default$11() {
/* 35 */     return _11();
/*    */   }
/*    */   
/*    */   public <T1, T2, T3, T4, T5, T6, T7, T8, T9, T10, T11, T12, T13, T14, T15, T16, T17, T18> T12 copy$default$12() {
/* 35 */     return _12();
/*    */   }
/*    */   
/*    */   public <T1, T2, T3, T4, T5, T6, T7, T8, T9, T10, T11, T12, T13, T14, T15, T16, T17, T18> T13 copy$default$13() {
/* 35 */     return _13();
/*    */   }
/*    */   
/*    */   public <T1, T2, T3, T4, T5, T6, T7, T8, T9, T10, T11, T12, T13, T14, T15, T16, T17, T18> T14 copy$default$14() {
/* 35 */     return _14();
/*    */   }
/*    */   
/*    */   public <T1, T2, T3, T4, T5, T6, T7, T8, T9, T10, T11, T12, T13, T14, T15, T16, T17, T18> T15 copy$default$15() {
/* 35 */     return _15();
/*    */   }
/*    */   
/*    */   public <T1, T2, T3, T4, T5, T6, T7, T8, T9, T10, T11, T12, T13, T14, T15, T16, T17, T18> T16 copy$default$16() {
/* 35 */     return _16();
/*    */   }
/*    */   
/*    */   public <T1, T2, T3, T4, T5, T6, T7, T8, T9, T10, T11, T12, T13, T14, T15, T16, T17, T18> T17 copy$default$17() {
/* 35 */     return _17();
/*    */   }
/*    */   
/*    */   public <T1, T2, T3, T4, T5, T6, T7, T8, T9, T10, T11, T12, T13, T14, T15, T16, T17, T18> T18 copy$default$18() {
/* 35 */     return _18();
/*    */   }
/*    */   
/*    */   public String productPrefix() {
/* 35 */     return "Tuple18";
/*    */   }
/*    */   
/*    */   public Iterator<Object> productIterator() {
/* 35 */     return ScalaRunTime$.MODULE$.typedProductIterator(this);
/*    */   }
/*    */   
/*    */   public boolean canEqual(Object x$1) {
/* 35 */     return x$1 instanceof Tuple18;
/*    */   }
/*    */   
/*    */   public int hashCode() {
/* 35 */     return ScalaRunTime$.MODULE$._hashCode(this);
/*    */   }
/*    */   
/*    */   public boolean equals(Object x$1) {
/*    */     // Byte code:
/*    */     //   0: aload_0
/*    */     //   1: aload_1
/*    */     //   2: if_acmpeq -> 1551
/*    */     //   5: aload_1
/*    */     //   6: instanceof scala/Tuple18
/*    */     //   9: ifeq -> 17
/*    */     //   12: iconst_1
/*    */     //   13: istore_2
/*    */     //   14: goto -> 19
/*    */     //   17: iconst_0
/*    */     //   18: istore_2
/*    */     //   19: iload_2
/*    */     //   20: ifeq -> 1555
/*    */     //   23: aload_1
/*    */     //   24: checkcast scala/Tuple18
/*    */     //   27: astore #39
/*    */     //   29: aload_0
/*    */     //   30: invokevirtual _1 : ()Ljava/lang/Object;
/*    */     //   33: aload #39
/*    */     //   35: invokevirtual _1 : ()Ljava/lang/Object;
/*    */     //   38: astore #4
/*    */     //   40: dup
/*    */     //   41: astore_3
/*    */     //   42: aload #4
/*    */     //   44: if_acmpne -> 51
/*    */     //   47: iconst_1
/*    */     //   48: goto -> 103
/*    */     //   51: aload_3
/*    */     //   52: ifnonnull -> 59
/*    */     //   55: iconst_0
/*    */     //   56: goto -> 103
/*    */     //   59: aload_3
/*    */     //   60: instanceof java/lang/Number
/*    */     //   63: ifeq -> 78
/*    */     //   66: aload_3
/*    */     //   67: checkcast java/lang/Number
/*    */     //   70: aload #4
/*    */     //   72: invokestatic equalsNumObject : (Ljava/lang/Number;Ljava/lang/Object;)Z
/*    */     //   75: goto -> 103
/*    */     //   78: aload_3
/*    */     //   79: instanceof java/lang/Character
/*    */     //   82: ifeq -> 97
/*    */     //   85: aload_3
/*    */     //   86: checkcast java/lang/Character
/*    */     //   89: aload #4
/*    */     //   91: invokestatic equalsCharObject : (Ljava/lang/Character;Ljava/lang/Object;)Z
/*    */     //   94: goto -> 103
/*    */     //   97: aload_3
/*    */     //   98: aload #4
/*    */     //   100: invokevirtual equals : (Ljava/lang/Object;)Z
/*    */     //   103: ifeq -> 1547
/*    */     //   106: aload_0
/*    */     //   107: invokevirtual _2 : ()Ljava/lang/Object;
/*    */     //   110: aload #39
/*    */     //   112: invokevirtual _2 : ()Ljava/lang/Object;
/*    */     //   115: astore #6
/*    */     //   117: dup
/*    */     //   118: astore #5
/*    */     //   120: aload #6
/*    */     //   122: if_acmpne -> 129
/*    */     //   125: iconst_1
/*    */     //   126: goto -> 187
/*    */     //   129: aload #5
/*    */     //   131: ifnonnull -> 138
/*    */     //   134: iconst_0
/*    */     //   135: goto -> 187
/*    */     //   138: aload #5
/*    */     //   140: instanceof java/lang/Number
/*    */     //   143: ifeq -> 159
/*    */     //   146: aload #5
/*    */     //   148: checkcast java/lang/Number
/*    */     //   151: aload #6
/*    */     //   153: invokestatic equalsNumObject : (Ljava/lang/Number;Ljava/lang/Object;)Z
/*    */     //   156: goto -> 187
/*    */     //   159: aload #5
/*    */     //   161: instanceof java/lang/Character
/*    */     //   164: ifeq -> 180
/*    */     //   167: aload #5
/*    */     //   169: checkcast java/lang/Character
/*    */     //   172: aload #6
/*    */     //   174: invokestatic equalsCharObject : (Ljava/lang/Character;Ljava/lang/Object;)Z
/*    */     //   177: goto -> 187
/*    */     //   180: aload #5
/*    */     //   182: aload #6
/*    */     //   184: invokevirtual equals : (Ljava/lang/Object;)Z
/*    */     //   187: ifeq -> 1547
/*    */     //   190: aload_0
/*    */     //   191: invokevirtual _3 : ()Ljava/lang/Object;
/*    */     //   194: aload #39
/*    */     //   196: invokevirtual _3 : ()Ljava/lang/Object;
/*    */     //   199: astore #8
/*    */     //   201: dup
/*    */     //   202: astore #7
/*    */     //   204: aload #8
/*    */     //   206: if_acmpne -> 213
/*    */     //   209: iconst_1
/*    */     //   210: goto -> 271
/*    */     //   213: aload #7
/*    */     //   215: ifnonnull -> 222
/*    */     //   218: iconst_0
/*    */     //   219: goto -> 271
/*    */     //   222: aload #7
/*    */     //   224: instanceof java/lang/Number
/*    */     //   227: ifeq -> 243
/*    */     //   230: aload #7
/*    */     //   232: checkcast java/lang/Number
/*    */     //   235: aload #8
/*    */     //   237: invokestatic equalsNumObject : (Ljava/lang/Number;Ljava/lang/Object;)Z
/*    */     //   240: goto -> 271
/*    */     //   243: aload #7
/*    */     //   245: instanceof java/lang/Character
/*    */     //   248: ifeq -> 264
/*    */     //   251: aload #7
/*    */     //   253: checkcast java/lang/Character
/*    */     //   256: aload #8
/*    */     //   258: invokestatic equalsCharObject : (Ljava/lang/Character;Ljava/lang/Object;)Z
/*    */     //   261: goto -> 271
/*    */     //   264: aload #7
/*    */     //   266: aload #8
/*    */     //   268: invokevirtual equals : (Ljava/lang/Object;)Z
/*    */     //   271: ifeq -> 1547
/*    */     //   274: aload_0
/*    */     //   275: invokevirtual _4 : ()Ljava/lang/Object;
/*    */     //   278: aload #39
/*    */     //   280: invokevirtual _4 : ()Ljava/lang/Object;
/*    */     //   283: astore #10
/*    */     //   285: dup
/*    */     //   286: astore #9
/*    */     //   288: aload #10
/*    */     //   290: if_acmpne -> 297
/*    */     //   293: iconst_1
/*    */     //   294: goto -> 355
/*    */     //   297: aload #9
/*    */     //   299: ifnonnull -> 306
/*    */     //   302: iconst_0
/*    */     //   303: goto -> 355
/*    */     //   306: aload #9
/*    */     //   308: instanceof java/lang/Number
/*    */     //   311: ifeq -> 327
/*    */     //   314: aload #9
/*    */     //   316: checkcast java/lang/Number
/*    */     //   319: aload #10
/*    */     //   321: invokestatic equalsNumObject : (Ljava/lang/Number;Ljava/lang/Object;)Z
/*    */     //   324: goto -> 355
/*    */     //   327: aload #9
/*    */     //   329: instanceof java/lang/Character
/*    */     //   332: ifeq -> 348
/*    */     //   335: aload #9
/*    */     //   337: checkcast java/lang/Character
/*    */     //   340: aload #10
/*    */     //   342: invokestatic equalsCharObject : (Ljava/lang/Character;Ljava/lang/Object;)Z
/*    */     //   345: goto -> 355
/*    */     //   348: aload #9
/*    */     //   350: aload #10
/*    */     //   352: invokevirtual equals : (Ljava/lang/Object;)Z
/*    */     //   355: ifeq -> 1547
/*    */     //   358: aload_0
/*    */     //   359: invokevirtual _5 : ()Ljava/lang/Object;
/*    */     //   362: aload #39
/*    */     //   364: invokevirtual _5 : ()Ljava/lang/Object;
/*    */     //   367: astore #12
/*    */     //   369: dup
/*    */     //   370: astore #11
/*    */     //   372: aload #12
/*    */     //   374: if_acmpne -> 381
/*    */     //   377: iconst_1
/*    */     //   378: goto -> 439
/*    */     //   381: aload #11
/*    */     //   383: ifnonnull -> 390
/*    */     //   386: iconst_0
/*    */     //   387: goto -> 439
/*    */     //   390: aload #11
/*    */     //   392: instanceof java/lang/Number
/*    */     //   395: ifeq -> 411
/*    */     //   398: aload #11
/*    */     //   400: checkcast java/lang/Number
/*    */     //   403: aload #12
/*    */     //   405: invokestatic equalsNumObject : (Ljava/lang/Number;Ljava/lang/Object;)Z
/*    */     //   408: goto -> 439
/*    */     //   411: aload #11
/*    */     //   413: instanceof java/lang/Character
/*    */     //   416: ifeq -> 432
/*    */     //   419: aload #11
/*    */     //   421: checkcast java/lang/Character
/*    */     //   424: aload #12
/*    */     //   426: invokestatic equalsCharObject : (Ljava/lang/Character;Ljava/lang/Object;)Z
/*    */     //   429: goto -> 439
/*    */     //   432: aload #11
/*    */     //   434: aload #12
/*    */     //   436: invokevirtual equals : (Ljava/lang/Object;)Z
/*    */     //   439: ifeq -> 1547
/*    */     //   442: aload_0
/*    */     //   443: invokevirtual _6 : ()Ljava/lang/Object;
/*    */     //   446: aload #39
/*    */     //   448: invokevirtual _6 : ()Ljava/lang/Object;
/*    */     //   451: astore #14
/*    */     //   453: dup
/*    */     //   454: astore #13
/*    */     //   456: aload #14
/*    */     //   458: if_acmpne -> 465
/*    */     //   461: iconst_1
/*    */     //   462: goto -> 523
/*    */     //   465: aload #13
/*    */     //   467: ifnonnull -> 474
/*    */     //   470: iconst_0
/*    */     //   471: goto -> 523
/*    */     //   474: aload #13
/*    */     //   476: instanceof java/lang/Number
/*    */     //   479: ifeq -> 495
/*    */     //   482: aload #13
/*    */     //   484: checkcast java/lang/Number
/*    */     //   487: aload #14
/*    */     //   489: invokestatic equalsNumObject : (Ljava/lang/Number;Ljava/lang/Object;)Z
/*    */     //   492: goto -> 523
/*    */     //   495: aload #13
/*    */     //   497: instanceof java/lang/Character
/*    */     //   500: ifeq -> 516
/*    */     //   503: aload #13
/*    */     //   505: checkcast java/lang/Character
/*    */     //   508: aload #14
/*    */     //   510: invokestatic equalsCharObject : (Ljava/lang/Character;Ljava/lang/Object;)Z
/*    */     //   513: goto -> 523
/*    */     //   516: aload #13
/*    */     //   518: aload #14
/*    */     //   520: invokevirtual equals : (Ljava/lang/Object;)Z
/*    */     //   523: ifeq -> 1547
/*    */     //   526: aload_0
/*    */     //   527: invokevirtual _7 : ()Ljava/lang/Object;
/*    */     //   530: aload #39
/*    */     //   532: invokevirtual _7 : ()Ljava/lang/Object;
/*    */     //   535: astore #16
/*    */     //   537: dup
/*    */     //   538: astore #15
/*    */     //   540: aload #16
/*    */     //   542: if_acmpne -> 549
/*    */     //   545: iconst_1
/*    */     //   546: goto -> 607
/*    */     //   549: aload #15
/*    */     //   551: ifnonnull -> 558
/*    */     //   554: iconst_0
/*    */     //   555: goto -> 607
/*    */     //   558: aload #15
/*    */     //   560: instanceof java/lang/Number
/*    */     //   563: ifeq -> 579
/*    */     //   566: aload #15
/*    */     //   568: checkcast java/lang/Number
/*    */     //   571: aload #16
/*    */     //   573: invokestatic equalsNumObject : (Ljava/lang/Number;Ljava/lang/Object;)Z
/*    */     //   576: goto -> 607
/*    */     //   579: aload #15
/*    */     //   581: instanceof java/lang/Character
/*    */     //   584: ifeq -> 600
/*    */     //   587: aload #15
/*    */     //   589: checkcast java/lang/Character
/*    */     //   592: aload #16
/*    */     //   594: invokestatic equalsCharObject : (Ljava/lang/Character;Ljava/lang/Object;)Z
/*    */     //   597: goto -> 607
/*    */     //   600: aload #15
/*    */     //   602: aload #16
/*    */     //   604: invokevirtual equals : (Ljava/lang/Object;)Z
/*    */     //   607: ifeq -> 1547
/*    */     //   610: aload_0
/*    */     //   611: invokevirtual _8 : ()Ljava/lang/Object;
/*    */     //   614: aload #39
/*    */     //   616: invokevirtual _8 : ()Ljava/lang/Object;
/*    */     //   619: astore #18
/*    */     //   621: dup
/*    */     //   622: astore #17
/*    */     //   624: aload #18
/*    */     //   626: if_acmpne -> 633
/*    */     //   629: iconst_1
/*    */     //   630: goto -> 691
/*    */     //   633: aload #17
/*    */     //   635: ifnonnull -> 642
/*    */     //   638: iconst_0
/*    */     //   639: goto -> 691
/*    */     //   642: aload #17
/*    */     //   644: instanceof java/lang/Number
/*    */     //   647: ifeq -> 663
/*    */     //   650: aload #17
/*    */     //   652: checkcast java/lang/Number
/*    */     //   655: aload #18
/*    */     //   657: invokestatic equalsNumObject : (Ljava/lang/Number;Ljava/lang/Object;)Z
/*    */     //   660: goto -> 691
/*    */     //   663: aload #17
/*    */     //   665: instanceof java/lang/Character
/*    */     //   668: ifeq -> 684
/*    */     //   671: aload #17
/*    */     //   673: checkcast java/lang/Character
/*    */     //   676: aload #18
/*    */     //   678: invokestatic equalsCharObject : (Ljava/lang/Character;Ljava/lang/Object;)Z
/*    */     //   681: goto -> 691
/*    */     //   684: aload #17
/*    */     //   686: aload #18
/*    */     //   688: invokevirtual equals : (Ljava/lang/Object;)Z
/*    */     //   691: ifeq -> 1547
/*    */     //   694: aload_0
/*    */     //   695: invokevirtual _9 : ()Ljava/lang/Object;
/*    */     //   698: aload #39
/*    */     //   700: invokevirtual _9 : ()Ljava/lang/Object;
/*    */     //   703: astore #20
/*    */     //   705: dup
/*    */     //   706: astore #19
/*    */     //   708: aload #20
/*    */     //   710: if_acmpne -> 717
/*    */     //   713: iconst_1
/*    */     //   714: goto -> 775
/*    */     //   717: aload #19
/*    */     //   719: ifnonnull -> 726
/*    */     //   722: iconst_0
/*    */     //   723: goto -> 775
/*    */     //   726: aload #19
/*    */     //   728: instanceof java/lang/Number
/*    */     //   731: ifeq -> 747
/*    */     //   734: aload #19
/*    */     //   736: checkcast java/lang/Number
/*    */     //   739: aload #20
/*    */     //   741: invokestatic equalsNumObject : (Ljava/lang/Number;Ljava/lang/Object;)Z
/*    */     //   744: goto -> 775
/*    */     //   747: aload #19
/*    */     //   749: instanceof java/lang/Character
/*    */     //   752: ifeq -> 768
/*    */     //   755: aload #19
/*    */     //   757: checkcast java/lang/Character
/*    */     //   760: aload #20
/*    */     //   762: invokestatic equalsCharObject : (Ljava/lang/Character;Ljava/lang/Object;)Z
/*    */     //   765: goto -> 775
/*    */     //   768: aload #19
/*    */     //   770: aload #20
/*    */     //   772: invokevirtual equals : (Ljava/lang/Object;)Z
/*    */     //   775: ifeq -> 1547
/*    */     //   778: aload_0
/*    */     //   779: invokevirtual _10 : ()Ljava/lang/Object;
/*    */     //   782: aload #39
/*    */     //   784: invokevirtual _10 : ()Ljava/lang/Object;
/*    */     //   787: astore #22
/*    */     //   789: dup
/*    */     //   790: astore #21
/*    */     //   792: aload #22
/*    */     //   794: if_acmpne -> 801
/*    */     //   797: iconst_1
/*    */     //   798: goto -> 859
/*    */     //   801: aload #21
/*    */     //   803: ifnonnull -> 810
/*    */     //   806: iconst_0
/*    */     //   807: goto -> 859
/*    */     //   810: aload #21
/*    */     //   812: instanceof java/lang/Number
/*    */     //   815: ifeq -> 831
/*    */     //   818: aload #21
/*    */     //   820: checkcast java/lang/Number
/*    */     //   823: aload #22
/*    */     //   825: invokestatic equalsNumObject : (Ljava/lang/Number;Ljava/lang/Object;)Z
/*    */     //   828: goto -> 859
/*    */     //   831: aload #21
/*    */     //   833: instanceof java/lang/Character
/*    */     //   836: ifeq -> 852
/*    */     //   839: aload #21
/*    */     //   841: checkcast java/lang/Character
/*    */     //   844: aload #22
/*    */     //   846: invokestatic equalsCharObject : (Ljava/lang/Character;Ljava/lang/Object;)Z
/*    */     //   849: goto -> 859
/*    */     //   852: aload #21
/*    */     //   854: aload #22
/*    */     //   856: invokevirtual equals : (Ljava/lang/Object;)Z
/*    */     //   859: ifeq -> 1547
/*    */     //   862: aload_0
/*    */     //   863: invokevirtual _11 : ()Ljava/lang/Object;
/*    */     //   866: aload #39
/*    */     //   868: invokevirtual _11 : ()Ljava/lang/Object;
/*    */     //   871: astore #24
/*    */     //   873: dup
/*    */     //   874: astore #23
/*    */     //   876: aload #24
/*    */     //   878: if_acmpne -> 885
/*    */     //   881: iconst_1
/*    */     //   882: goto -> 943
/*    */     //   885: aload #23
/*    */     //   887: ifnonnull -> 894
/*    */     //   890: iconst_0
/*    */     //   891: goto -> 943
/*    */     //   894: aload #23
/*    */     //   896: instanceof java/lang/Number
/*    */     //   899: ifeq -> 915
/*    */     //   902: aload #23
/*    */     //   904: checkcast java/lang/Number
/*    */     //   907: aload #24
/*    */     //   909: invokestatic equalsNumObject : (Ljava/lang/Number;Ljava/lang/Object;)Z
/*    */     //   912: goto -> 943
/*    */     //   915: aload #23
/*    */     //   917: instanceof java/lang/Character
/*    */     //   920: ifeq -> 936
/*    */     //   923: aload #23
/*    */     //   925: checkcast java/lang/Character
/*    */     //   928: aload #24
/*    */     //   930: invokestatic equalsCharObject : (Ljava/lang/Character;Ljava/lang/Object;)Z
/*    */     //   933: goto -> 943
/*    */     //   936: aload #23
/*    */     //   938: aload #24
/*    */     //   940: invokevirtual equals : (Ljava/lang/Object;)Z
/*    */     //   943: ifeq -> 1547
/*    */     //   946: aload_0
/*    */     //   947: invokevirtual _12 : ()Ljava/lang/Object;
/*    */     //   950: aload #39
/*    */     //   952: invokevirtual _12 : ()Ljava/lang/Object;
/*    */     //   955: astore #26
/*    */     //   957: dup
/*    */     //   958: astore #25
/*    */     //   960: aload #26
/*    */     //   962: if_acmpne -> 969
/*    */     //   965: iconst_1
/*    */     //   966: goto -> 1027
/*    */     //   969: aload #25
/*    */     //   971: ifnonnull -> 978
/*    */     //   974: iconst_0
/*    */     //   975: goto -> 1027
/*    */     //   978: aload #25
/*    */     //   980: instanceof java/lang/Number
/*    */     //   983: ifeq -> 999
/*    */     //   986: aload #25
/*    */     //   988: checkcast java/lang/Number
/*    */     //   991: aload #26
/*    */     //   993: invokestatic equalsNumObject : (Ljava/lang/Number;Ljava/lang/Object;)Z
/*    */     //   996: goto -> 1027
/*    */     //   999: aload #25
/*    */     //   1001: instanceof java/lang/Character
/*    */     //   1004: ifeq -> 1020
/*    */     //   1007: aload #25
/*    */     //   1009: checkcast java/lang/Character
/*    */     //   1012: aload #26
/*    */     //   1014: invokestatic equalsCharObject : (Ljava/lang/Character;Ljava/lang/Object;)Z
/*    */     //   1017: goto -> 1027
/*    */     //   1020: aload #25
/*    */     //   1022: aload #26
/*    */     //   1024: invokevirtual equals : (Ljava/lang/Object;)Z
/*    */     //   1027: ifeq -> 1547
/*    */     //   1030: aload_0
/*    */     //   1031: invokevirtual _13 : ()Ljava/lang/Object;
/*    */     //   1034: aload #39
/*    */     //   1036: invokevirtual _13 : ()Ljava/lang/Object;
/*    */     //   1039: astore #28
/*    */     //   1041: dup
/*    */     //   1042: astore #27
/*    */     //   1044: aload #28
/*    */     //   1046: if_acmpne -> 1053
/*    */     //   1049: iconst_1
/*    */     //   1050: goto -> 1111
/*    */     //   1053: aload #27
/*    */     //   1055: ifnonnull -> 1062
/*    */     //   1058: iconst_0
/*    */     //   1059: goto -> 1111
/*    */     //   1062: aload #27
/*    */     //   1064: instanceof java/lang/Number
/*    */     //   1067: ifeq -> 1083
/*    */     //   1070: aload #27
/*    */     //   1072: checkcast java/lang/Number
/*    */     //   1075: aload #28
/*    */     //   1077: invokestatic equalsNumObject : (Ljava/lang/Number;Ljava/lang/Object;)Z
/*    */     //   1080: goto -> 1111
/*    */     //   1083: aload #27
/*    */     //   1085: instanceof java/lang/Character
/*    */     //   1088: ifeq -> 1104
/*    */     //   1091: aload #27
/*    */     //   1093: checkcast java/lang/Character
/*    */     //   1096: aload #28
/*    */     //   1098: invokestatic equalsCharObject : (Ljava/lang/Character;Ljava/lang/Object;)Z
/*    */     //   1101: goto -> 1111
/*    */     //   1104: aload #27
/*    */     //   1106: aload #28
/*    */     //   1108: invokevirtual equals : (Ljava/lang/Object;)Z
/*    */     //   1111: ifeq -> 1547
/*    */     //   1114: aload_0
/*    */     //   1115: invokevirtual _14 : ()Ljava/lang/Object;
/*    */     //   1118: aload #39
/*    */     //   1120: invokevirtual _14 : ()Ljava/lang/Object;
/*    */     //   1123: astore #30
/*    */     //   1125: dup
/*    */     //   1126: astore #29
/*    */     //   1128: aload #30
/*    */     //   1130: if_acmpne -> 1137
/*    */     //   1133: iconst_1
/*    */     //   1134: goto -> 1195
/*    */     //   1137: aload #29
/*    */     //   1139: ifnonnull -> 1146
/*    */     //   1142: iconst_0
/*    */     //   1143: goto -> 1195
/*    */     //   1146: aload #29
/*    */     //   1148: instanceof java/lang/Number
/*    */     //   1151: ifeq -> 1167
/*    */     //   1154: aload #29
/*    */     //   1156: checkcast java/lang/Number
/*    */     //   1159: aload #30
/*    */     //   1161: invokestatic equalsNumObject : (Ljava/lang/Number;Ljava/lang/Object;)Z
/*    */     //   1164: goto -> 1195
/*    */     //   1167: aload #29
/*    */     //   1169: instanceof java/lang/Character
/*    */     //   1172: ifeq -> 1188
/*    */     //   1175: aload #29
/*    */     //   1177: checkcast java/lang/Character
/*    */     //   1180: aload #30
/*    */     //   1182: invokestatic equalsCharObject : (Ljava/lang/Character;Ljava/lang/Object;)Z
/*    */     //   1185: goto -> 1195
/*    */     //   1188: aload #29
/*    */     //   1190: aload #30
/*    */     //   1192: invokevirtual equals : (Ljava/lang/Object;)Z
/*    */     //   1195: ifeq -> 1547
/*    */     //   1198: aload_0
/*    */     //   1199: invokevirtual _15 : ()Ljava/lang/Object;
/*    */     //   1202: aload #39
/*    */     //   1204: invokevirtual _15 : ()Ljava/lang/Object;
/*    */     //   1207: astore #32
/*    */     //   1209: dup
/*    */     //   1210: astore #31
/*    */     //   1212: aload #32
/*    */     //   1214: if_acmpne -> 1221
/*    */     //   1217: iconst_1
/*    */     //   1218: goto -> 1279
/*    */     //   1221: aload #31
/*    */     //   1223: ifnonnull -> 1230
/*    */     //   1226: iconst_0
/*    */     //   1227: goto -> 1279
/*    */     //   1230: aload #31
/*    */     //   1232: instanceof java/lang/Number
/*    */     //   1235: ifeq -> 1251
/*    */     //   1238: aload #31
/*    */     //   1240: checkcast java/lang/Number
/*    */     //   1243: aload #32
/*    */     //   1245: invokestatic equalsNumObject : (Ljava/lang/Number;Ljava/lang/Object;)Z
/*    */     //   1248: goto -> 1279
/*    */     //   1251: aload #31
/*    */     //   1253: instanceof java/lang/Character
/*    */     //   1256: ifeq -> 1272
/*    */     //   1259: aload #31
/*    */     //   1261: checkcast java/lang/Character
/*    */     //   1264: aload #32
/*    */     //   1266: invokestatic equalsCharObject : (Ljava/lang/Character;Ljava/lang/Object;)Z
/*    */     //   1269: goto -> 1279
/*    */     //   1272: aload #31
/*    */     //   1274: aload #32
/*    */     //   1276: invokevirtual equals : (Ljava/lang/Object;)Z
/*    */     //   1279: ifeq -> 1547
/*    */     //   1282: aload_0
/*    */     //   1283: invokevirtual _16 : ()Ljava/lang/Object;
/*    */     //   1286: aload #39
/*    */     //   1288: invokevirtual _16 : ()Ljava/lang/Object;
/*    */     //   1291: astore #34
/*    */     //   1293: dup
/*    */     //   1294: astore #33
/*    */     //   1296: aload #34
/*    */     //   1298: if_acmpne -> 1305
/*    */     //   1301: iconst_1
/*    */     //   1302: goto -> 1363
/*    */     //   1305: aload #33
/*    */     //   1307: ifnonnull -> 1314
/*    */     //   1310: iconst_0
/*    */     //   1311: goto -> 1363
/*    */     //   1314: aload #33
/*    */     //   1316: instanceof java/lang/Number
/*    */     //   1319: ifeq -> 1335
/*    */     //   1322: aload #33
/*    */     //   1324: checkcast java/lang/Number
/*    */     //   1327: aload #34
/*    */     //   1329: invokestatic equalsNumObject : (Ljava/lang/Number;Ljava/lang/Object;)Z
/*    */     //   1332: goto -> 1363
/*    */     //   1335: aload #33
/*    */     //   1337: instanceof java/lang/Character
/*    */     //   1340: ifeq -> 1356
/*    */     //   1343: aload #33
/*    */     //   1345: checkcast java/lang/Character
/*    */     //   1348: aload #34
/*    */     //   1350: invokestatic equalsCharObject : (Ljava/lang/Character;Ljava/lang/Object;)Z
/*    */     //   1353: goto -> 1363
/*    */     //   1356: aload #33
/*    */     //   1358: aload #34
/*    */     //   1360: invokevirtual equals : (Ljava/lang/Object;)Z
/*    */     //   1363: ifeq -> 1547
/*    */     //   1366: aload_0
/*    */     //   1367: invokevirtual _17 : ()Ljava/lang/Object;
/*    */     //   1370: aload #39
/*    */     //   1372: invokevirtual _17 : ()Ljava/lang/Object;
/*    */     //   1375: astore #36
/*    */     //   1377: dup
/*    */     //   1378: astore #35
/*    */     //   1380: aload #36
/*    */     //   1382: if_acmpne -> 1389
/*    */     //   1385: iconst_1
/*    */     //   1386: goto -> 1447
/*    */     //   1389: aload #35
/*    */     //   1391: ifnonnull -> 1398
/*    */     //   1394: iconst_0
/*    */     //   1395: goto -> 1447
/*    */     //   1398: aload #35
/*    */     //   1400: instanceof java/lang/Number
/*    */     //   1403: ifeq -> 1419
/*    */     //   1406: aload #35
/*    */     //   1408: checkcast java/lang/Number
/*    */     //   1411: aload #36
/*    */     //   1413: invokestatic equalsNumObject : (Ljava/lang/Number;Ljava/lang/Object;)Z
/*    */     //   1416: goto -> 1447
/*    */     //   1419: aload #35
/*    */     //   1421: instanceof java/lang/Character
/*    */     //   1424: ifeq -> 1440
/*    */     //   1427: aload #35
/*    */     //   1429: checkcast java/lang/Character
/*    */     //   1432: aload #36
/*    */     //   1434: invokestatic equalsCharObject : (Ljava/lang/Character;Ljava/lang/Object;)Z
/*    */     //   1437: goto -> 1447
/*    */     //   1440: aload #35
/*    */     //   1442: aload #36
/*    */     //   1444: invokevirtual equals : (Ljava/lang/Object;)Z
/*    */     //   1447: ifeq -> 1547
/*    */     //   1450: aload_0
/*    */     //   1451: invokevirtual _18 : ()Ljava/lang/Object;
/*    */     //   1454: aload #39
/*    */     //   1456: invokevirtual _18 : ()Ljava/lang/Object;
/*    */     //   1459: astore #38
/*    */     //   1461: dup
/*    */     //   1462: astore #37
/*    */     //   1464: aload #38
/*    */     //   1466: if_acmpne -> 1473
/*    */     //   1469: iconst_1
/*    */     //   1470: goto -> 1531
/*    */     //   1473: aload #37
/*    */     //   1475: ifnonnull -> 1482
/*    */     //   1478: iconst_0
/*    */     //   1479: goto -> 1531
/*    */     //   1482: aload #37
/*    */     //   1484: instanceof java/lang/Number
/*    */     //   1487: ifeq -> 1503
/*    */     //   1490: aload #37
/*    */     //   1492: checkcast java/lang/Number
/*    */     //   1495: aload #38
/*    */     //   1497: invokestatic equalsNumObject : (Ljava/lang/Number;Ljava/lang/Object;)Z
/*    */     //   1500: goto -> 1531
/*    */     //   1503: aload #37
/*    */     //   1505: instanceof java/lang/Character
/*    */     //   1508: ifeq -> 1524
/*    */     //   1511: aload #37
/*    */     //   1513: checkcast java/lang/Character
/*    */     //   1516: aload #38
/*    */     //   1518: invokestatic equalsCharObject : (Ljava/lang/Character;Ljava/lang/Object;)Z
/*    */     //   1521: goto -> 1531
/*    */     //   1524: aload #37
/*    */     //   1526: aload #38
/*    */     //   1528: invokevirtual equals : (Ljava/lang/Object;)Z
/*    */     //   1531: ifeq -> 1547
/*    */     //   1534: aload #39
/*    */     //   1536: aload_0
/*    */     //   1537: invokevirtual canEqual : (Ljava/lang/Object;)Z
/*    */     //   1540: ifeq -> 1547
/*    */     //   1543: iconst_1
/*    */     //   1544: goto -> 1548
/*    */     //   1547: iconst_0
/*    */     //   1548: ifeq -> 1555
/*    */     //   1551: iconst_1
/*    */     //   1552: goto -> 1556
/*    */     //   1555: iconst_0
/*    */     //   1556: ireturn
/*    */     // Line number table:
/*    */     //   Java source line number -> byte code offset
/*    */     //   #35	-> 0
/*    */     //   #236	-> 12
/*    */     //   #35	-> 19
/*    */     // Local variable table:
/*    */     //   start	length	slot	name	descriptor
/*    */     //   0	1557	0	this	Lscala/Tuple18;
/*    */     //   0	1557	1	x$1	Ljava/lang/Object;
/*    */   }
/*    */   
/*    */   public Tuple18(Object _1, Object _2, Object _3, Object _4, Object _5, Object _6, Object _7, Object _8, Object _9, Object _10, Object _11, Object _12, Object _13, Object _14, Object _15, Object _16, Object _17, Object _18) {
/* 35 */     Product$class.$init$(this);
/* 35 */     Product18$class.$init$(this);
/*    */   }
/*    */   
/*    */   public String toString() {
/* 39 */     return (new StringBuilder()).append("(").append(_1()).append(",").append(_2()).append(",").append(_3()).append(",").append(_4()).append(",").append(_5()).append(",").append(_6()).append(",").append(_7()).append(",").append(_8()).append(",").append(_9()).append(",").append(_10()).append(",").append(_11()).append(",").append(_12()).append(",").append(_13()).append(",").append(_14()).append(",").append(_15()).append(",").append(_16()).append(",").append(_17()).append(",").append(_18()).append(")").toString();
/*    */   }
/*    */ }


/* Location:              D:\#source-code\TheFlightSims\TFSLibrary\World2Xplane\World2XPlane.jar!\scala\Tuple18.class
 * Java compiler version: 6 (50.0)
 * JD-Core Version:       1.1.3
 */