/*    */ package scala;
/*    */ 
/*    */ import scala.collection.Iterator;
/*    */ import scala.collection.mutable.StringBuilder;
/*    */ import scala.reflect.ScalaSignature;
/*    */ import scala.runtime.ScalaRunTime$;
/*    */ 
/*    */ @ScalaSignature(bytes = "\006\001\r]a\001B\001\003\001\026\021a\001V;qY\026L$\"A\002\002\013M\034\027\r\\1\004\001UQa\001\005\016\036A\r2\023\006L\030\024\013\00191\"\r\033\021\005!IQ\"\001\002\n\005)\021!AB!osJ+g\rE\006\t\0319IBd\b\022&Q-r\023BA\007\003\005!\001&o\0343vGRL\004CA\b\021\031\001!a!\005\001\005\006\004\021\"A\001+2#\t\031b\003\005\002\t)%\021QC\001\002\b\035>$\b.\0338h!\tAq#\003\002\031\005\t\031\021I\\=\021\005=QBAB\016\001\t\013\007!C\001\002UeA\021q\"\b\003\007=\001!)\031\001\n\003\005Q\033\004CA\b!\t\031\t\003\001\"b\001%\t\021A\013\016\t\003\037\r\"a\001\n\001\005\006\004\021\"A\001+6!\tya\005\002\004(\001\021\025\rA\005\002\003)Z\002\"aD\025\005\r)\002AQ1\001\023\005\t!v\007\005\002\020Y\0211Q\006\001CC\002I\021!\001\026\035\021\005=yCA\002\031\001\t\013\007!C\001\002UsA\021\001BM\005\003g\t\021q\001\025:pIV\034G\017\005\002\tk%\021aG\001\002\r'\026\024\030.\0317ju\006\024G.\032\005\tq\001\021)\032!C\001s\005\021q,M\013\002\035!A1\b\001B\tB\003%a\"A\002`c\001B\001\"\020\001\003\026\004%\tAP\001\003?J*\022!\007\005\t\001\002\021\t\022)A\0053\005\031qL\r\021\t\021\t\003!Q3A\005\002\r\013!aX\032\026\003qA\001\"\022\001\003\022\003\006I\001H\001\004?N\002\003\002C$\001\005+\007I\021\001%\002\005}#T#A\020\t\021)\003!\021#Q\001\n}\t1a\030\033!\021!a\005A!f\001\n\003i\025AA06+\005\021\003\002C(\001\005#\005\013\021\002\022\002\007}+\004\005\003\005R\001\tU\r\021\"\001S\003\tyf'F\001&\021!!\006A!E!\002\023)\023aA07A!Aa\013\001BK\002\023\005q+\001\002`oU\t\001\006\003\005Z\001\tE\t\025!\003)\003\ryv\007\t\005\t7\002\021)\032!C\0019\006\021q\fO\013\002W!Aa\f\001B\tB\003%1&A\002`q\001B\001\002\031\001\003\026\004%\t!Y\001\003?f*\022A\f\005\tG\002\021\t\022)A\005]\005\031q,\017\021\t\013\025\004A\021\0014\002\rqJg.\033;?))9\007.\0336lY6tw\016\035\t\f\021\001q\021\004H\020#K!Zc\006C\0039I\002\007a\002C\003>I\002\007\021\004C\003CI\002\007A\004C\003HI\002\007q\004C\003MI\002\007!\005C\003RI\002\007Q\005C\003WI\002\007\001\006C\003\\I\002\0071\006C\003aI\002\007a\006C\003s\001\021\0053/\001\005u_N#(/\0338h)\005!\bCA;{\033\0051(BA<y\003\021a\027M\\4\013\003e\fAA[1wC&\0211P\036\002\007'R\024\030N\\4\t\017u\004\021\021!C\001}\006!1m\0349z+My\030QAA\005\003\033\t\t\"!\006\002\032\005u\021\021EA\023)Q\t\t!a\n\002*\005-\022QFA\030\003c\t\031$!\016\0028A!\002\002AA\002\003\017\tY!a\004\002\024\005]\0211DA\020\003G\0012aDA\003\t\025\tBP1\001\023!\ry\021\021\002\003\0067q\024\rA\005\t\004\037\0055A!\002\020}\005\004\021\002cA\b\002\022\021)\021\005 b\001%A\031q\"!\006\005\013\021b(\031\001\n\021\007=\tI\002B\003(y\n\007!\003E\002\020\003;!QA\013?C\002I\0012aDA\021\t\025iCP1\001\023!\ry\021Q\005\003\006aq\024\rA\005\005\tqq\004\n\0211\001\002\004!AQ\b I\001\002\004\t9\001\003\005CyB\005\t\031AA\006\021!9E\020%AA\002\005=\001\002\003'}!\003\005\r!a\005\t\021Ec\b\023!a\001\003/A\001B\026?\021\002\003\007\0211\004\005\t7r\004\n\0211\001\002 !A\001\r I\001\002\004\t\031\003C\005\002<\001\t\n\021\"\001\002>\005q1m\0349zI\021,g-Y;mi\022\nT\003FA \003+\n9&!\027\002\\\005u\023qLA1\003G\n)'\006\002\002B)\032a\"a\021,\005\005\025\003\003BA$\003#j!!!\023\013\t\005-\023QJ\001\nk:\034\007.Z2lK\022T1!a\024\003\003)\tgN\\8uCRLwN\\\005\005\003'\nIEA\tv]\016DWmY6fIZ\013'/[1oG\026$a!EA\035\005\004\021BAB\016\002:\t\007!\003\002\004\037\003s\021\rA\005\003\007C\005e\"\031\001\n\005\r\021\nID1\001\023\t\0319\023\021\bb\001%\0211!&!\017C\002I!a!LA\035\005\004\021BA\002\031\002:\t\007!\003C\005\002j\001\t\n\021\"\001\002l\005q1m\0349zI\021,g-Y;mi\022\022T\003FA7\003c\n\031(!\036\002x\005e\0241PA?\003\n\t)\006\002\002p)\032\021$a\021\005\rE\t9G1\001\023\t\031Y\022q\rb\001%\0211a$a\032C\002I!a!IA4\005\004\021BA\002\023\002h\t\007!\003\002\004(\003O\022\rA\005\003\007U\005\035$\031\001\n\005\r5\n9G1\001\023\t\031\001\024q\rb\001%!I\021Q\021\001\022\002\023\005\021qQ\001\017G>\004\030\020\n3fM\006,H\016\036\0234+Q\tI)!$\002\020\006E\0251SAK\003/\013I*a'\002\036V\021\0211\022\026\0049\005\rCAB\t\002\004\n\007!\003\002\004\034\003\007\023\rA\005\003\007=\005\r%\031\001\n\005\r\005\n\031I1\001\023\t\031!\0231\021b\001%\0211q%a!C\002I!aAKAB\005\004\021BAB\027\002\004\n\007!\003\002\0041\003\007\023\rA\005\005\n\003C\003\021\023!C\001\003G\013abY8qs\022\"WMZ1vYR$C'\006\013\002&\006%\0261VAW\003_\013\t,a-\0026\006]\026\021X\013\003\003OS3aHA\"\t\031\t\022q\024b\001%\02111$a(C\002I!aAHAP\005\004\021BAB\021\002 \n\007!\003\002\004%\003?\023\rA\005\003\007O\005}%\031\001\n\005\r)\nyJ1\001\023\t\031i\023q\024b\001%\0211\001'a(C\002IA\021\"!0\001#\003%\t!a0\002\035\r|\007/\037\023eK\032\fW\017\034;%kU!\022\021YAc\003\017\fI-a3\002N\006=\027\021[Aj\003+,\"!a1+\007\t\n\031\005\002\004\022\003w\023\rA\005\003\0077\005m&\031\001\n\005\ry\tYL1\001\023\t\031\t\0231\030b\001%\0211A%a/C\002I!aaJA^\005\004\021BA\002\026\002<\n\007!\003\002\004.\003w\023\rA\005\003\007a\005m&\031\001\n\t\023\005e\007!%A\005\002\005m\027AD2paf$C-\0324bk2$HEN\013\025\003;\f\t/a9\002f\006\035\030\021^Av\003[\fy/!=\026\005\005}'fA\023\002D\0211\021#a6C\002I!aaGAl\005\004\021BA\002\020\002X\n\007!\003\002\004\"\003/\024\rA\005\003\007I\005]'\031\001\n\005\r\035\n9N1\001\023\t\031Q\023q\033b\001%\0211Q&a6C\002I!a\001MAl\005\004\021\002\"CA{\001E\005I\021AA|\0039\031w\016]=%I\0264\027-\0367uI]*B#!?\002~\006}(\021\001B\002\005\013\0219A!\003\003\f\t5QCAA~U\rA\0231\t\003\007#\005M(\031\001\n\005\rm\t\031P1\001\023\t\031q\0221\037b\001%\0211\021%a=C\002I!a\001JAz\005\004\021BAB\024\002t\n\007!\003\002\004+\003g\024\rA\005\003\007[\005M(\031\001\n\005\rA\n\031P1\001\023\021%\021\t\002AI\001\n\003\021\031\"\001\bd_BLH\005Z3gCVdG\017\n\035\026)\tU!\021\004B\016\005;\021yB!\t\003$\t\025\"q\005B\025+\t\0219BK\002,\003\007\"a!\005B\b\005\004\021BAB\016\003\020\t\007!\003\002\004\037\005\037\021\rA\005\003\007C\t=!\031\001\n\005\r\021\022yA1\001\023\t\0319#q\002b\001%\0211!Fa\004C\002I!a!\fB\b\005\004\021BA\002\031\003\020\t\007!\003C\005\003.\001\t\n\021\"\001\0030\005q1m\0349zI\021,g-Y;mi\022JT\003\006B\031\005k\0219D!\017\003<\tu\"q\bB!\005\007\022)%\006\002\0034)\032a&a\021\005\rE\021YC1\001\023\t\031Y\"1\006b\001%\0211aDa\013C\002I!a!\tB\026\005\004\021BA\002\023\003,\t\007!\003\002\004(\005W\021\rA\005\003\007U\t-\"\031\001\n\005\r5\022YC1\001\023\t\031\001$1\006b\001%!I!\021\n\001\002\002\023\005#1J\001\016aJ|G-^2u!J,g-\033=\026\003QD\021Ba\024\001\003\003%\tE!\025\002\037A\024x\016Z;di&#XM]1u_J,\"Aa\025\021\013\tU#1\f\f\016\005\t]#b\001B-\005\005Q1m\0347mK\016$\030n\0348\n\t\tu#q\013\002\t\023R,'/\031;pe\"I!\021\r\001\002\002\023\005!1M\001\tG\006tW)];bYR!!Q\rB6!\rA!qM\005\004\005S\022!a\002\"p_2,\027M\034\005\n\005[\022y&!AA\002Y\t1\001\037\0232\021%\021\t\bAA\001\n\003\022\031(\001\005iCND7i\0343f)\t\021)\bE\002\t\005oJ1A!\037\003\005\rIe\016\036\005\n\005{\002\021\021!C!\005\na!Z9vC2\034H\003\002B3\005\003C\021B!\034\003|\005\005\t\031\001\f\b\023\t\025%!!A\t\002\t\035\025A\002+va2,\027\bE\002\t\005\0233\001\"\001\002\002\002#\005!1R\n\005\005\023;A\007C\004f\005\023#\tAa$\025\005\t\035\005\002\003:\003\n\006\005IQI:\t\025\tU%\021RA\001\n\003\0239*A\003baBd\0270\006\013\003\032\n}%1\025BT\005W\023yKa-\0038\nm&q\030\013\025\0057\023\tMa1\003F\n\035'\021\032Bf\005\033\024yM!5\021)!\001!Q\024BQ\005K\023IK!,\0032\nU&\021\030B_!\ry!q\024\003\007#\tM%\031\001\n\021\007=\021\031\013\002\004\034\005'\023\rA\005\t\004\037\t\035FA\002\020\003\024\n\007!\003E\002\020\005W#a!\tBJ\005\004\021\002cA\b\0030\0221AEa%C\002I\0012a\004BZ\t\0319#1\023b\001%A\031qBa.\005\r)\022\031J1\001\023!\ry!1\030\003\007[\tM%\031\001\n\021\007=\021y\f\002\0041\005'\023\rA\005\005\bq\tM\005\031\001BO\021\035i$1\023a\001\005CCqA\021BJ\001\004\021)\013C\004H\005'\003\rA!+\t\0171\023\031\n1\001\003.\"9\021Ka%A\002\tE\006b\002,\003\024\002\007!Q\027\005\b7\nM\005\031\001B]\021\035\001'1\023a\001\005{C!B!6\003\n\006\005I\021\021Bl\003\035)h.\0319qYf,BC!7\003f\n%(Q\036By\005k\024IP!@\004\002\r\025A\003\002Bn\007\017\001R\001\003Bo\005CL1Aa8\003\005\031y\005\017^5p]B!\002\002\001Br\005O\024YOa<\003t\n](1 B\000\007\007\0012a\004Bs\t\031\t\"1\033b\001%A\031qB!;\005\rm\021\031N1\001\023!\ry!Q\036\003\007=\tM'\031\001\n\021\007=\021\t\020\002\004\"\005'\024\rA\005\t\004\037\tUHA\002\023\003T\n\007!\003E\002\020\005s$aa\nBj\005\004\021\002cA\b\003~\0221!Fa5C\002I\0012aDB\001\t\031i#1\033b\001%A\031qb!\002\005\rA\022\031N1\001\023\021)\031IAa5\002\002\003\007!\021]\001\004q\022\002\004BCB\007\005\023\013\t\021\"\003\004\020\005Y!/Z1e%\026\034x\016\034<f)\t\031\t\002E\002v\007'I1a!\006w\005\031y%M[3di\002")
/*    */ public class Tuple9<T1, T2, T3, T4, T5, T6, T7, T8, T9> implements Product9<T1, T2, T3, T4, T5, T6, T7, T8, T9>, Product, Serializable {
/*    */   private final T1 _1;
/*    */   
/*    */   private final T2 _2;
/*    */   
/*    */   private final T3 _3;
/*    */   
/*    */   private final T4 _4;
/*    */   
/*    */   private final T5 _5;
/*    */   
/*    */   private final T6 _6;
/*    */   
/*    */   private final T7 _7;
/*    */   
/*    */   private final T8 _8;
/*    */   
/*    */   private final T9 _9;
/*    */   
/*    */   public int productArity() {
/* 26 */     return Product9$class.productArity(this);
/*    */   }
/*    */   
/*    */   public Object productElement(int n) throws IndexOutOfBoundsException {
/* 26 */     return Product9$class.productElement(this, n);
/*    */   }
/*    */   
/*    */   public T1 _1() {
/* 26 */     return this._1;
/*    */   }
/*    */   
/*    */   public T2 _2() {
/* 26 */     return this._2;
/*    */   }
/*    */   
/*    */   public T3 _3() {
/* 26 */     return this._3;
/*    */   }
/*    */   
/*    */   public T4 _4() {
/* 26 */     return this._4;
/*    */   }
/*    */   
/*    */   public T5 _5() {
/* 26 */     return this._5;
/*    */   }
/*    */   
/*    */   public T6 _6() {
/* 26 */     return this._6;
/*    */   }
/*    */   
/*    */   public T7 _7() {
/* 26 */     return this._7;
/*    */   }
/*    */   
/*    */   public T8 _8() {
/* 26 */     return this._8;
/*    */   }
/*    */   
/*    */   public T9 _9() {
/* 26 */     return this._9;
/*    */   }
/*    */   
/*    */   public <T1, T2, T3, T4, T5, T6, T7, T8, T9> Tuple9<T1, T2, T3, T4, T5, T6, T7, T8, T9> copy(Object _1, Object _2, Object _3, Object _4, Object _5, Object _6, Object _7, Object _8, Object _9) {
/* 26 */     return new Tuple9((T1)_1, (T2)_2, (T3)_3, (T4)_4, (T5)_5, (T6)_6, (T7)_7, (T8)_8, (T9)_9);
/*    */   }
/*    */   
/*    */   public <T1, T2, T3, T4, T5, T6, T7, T8, T9> T1 copy$default$1() {
/* 26 */     return _1();
/*    */   }
/*    */   
/*    */   public <T1, T2, T3, T4, T5, T6, T7, T8, T9> T2 copy$default$2() {
/* 26 */     return _2();
/*    */   }
/*    */   
/*    */   public <T1, T2, T3, T4, T5, T6, T7, T8, T9> T3 copy$default$3() {
/* 26 */     return _3();
/*    */   }
/*    */   
/*    */   public <T1, T2, T3, T4, T5, T6, T7, T8, T9> T4 copy$default$4() {
/* 26 */     return _4();
/*    */   }
/*    */   
/*    */   public <T1, T2, T3, T4, T5, T6, T7, T8, T9> T5 copy$default$5() {
/* 26 */     return _5();
/*    */   }
/*    */   
/*    */   public <T1, T2, T3, T4, T5, T6, T7, T8, T9> T6 copy$default$6() {
/* 26 */     return _6();
/*    */   }
/*    */   
/*    */   public <T1, T2, T3, T4, T5, T6, T7, T8, T9> T7 copy$default$7() {
/* 26 */     return _7();
/*    */   }
/*    */   
/*    */   public <T1, T2, T3, T4, T5, T6, T7, T8, T9> T8 copy$default$8() {
/* 26 */     return _8();
/*    */   }
/*    */   
/*    */   public <T1, T2, T3, T4, T5, T6, T7, T8, T9> T9 copy$default$9() {
/* 26 */     return _9();
/*    */   }
/*    */   
/*    */   public String productPrefix() {
/* 26 */     return "Tuple9";
/*    */   }
/*    */   
/*    */   public Iterator<Object> productIterator() {
/* 26 */     return ScalaRunTime$.MODULE$.typedProductIterator(this);
/*    */   }
/*    */   
/*    */   public boolean canEqual(Object x$1) {
/* 26 */     return x$1 instanceof Tuple9;
/*    */   }
/*    */   
/*    */   public int hashCode() {
/* 26 */     return ScalaRunTime$.MODULE$._hashCode(this);
/*    */   }
/*    */   
/*    */   public boolean equals(Object x$1) {
/*    */     // Byte code:
/*    */     //   0: aload_0
/*    */     //   1: aload_1
/*    */     //   2: if_acmpeq -> 795
/*    */     //   5: aload_1
/*    */     //   6: instanceof scala/Tuple9
/*    */     //   9: ifeq -> 17
/*    */     //   12: iconst_1
/*    */     //   13: istore_2
/*    */     //   14: goto -> 19
/*    */     //   17: iconst_0
/*    */     //   18: istore_2
/*    */     //   19: iload_2
/*    */     //   20: ifeq -> 799
/*    */     //   23: aload_1
/*    */     //   24: checkcast scala/Tuple9
/*    */     //   27: astore #21
/*    */     //   29: aload_0
/*    */     //   30: invokevirtual _1 : ()Ljava/lang/Object;
/*    */     //   33: aload #21
/*    */     //   35: invokevirtual _1 : ()Ljava/lang/Object;
/*    */     //   38: astore #4
/*    */     //   40: dup
/*    */     //   41: astore_3
/*    */     //   42: aload #4
/*    */     //   44: if_acmpne -> 51
/*    */     //   47: iconst_1
/*    */     //   48: goto -> 103
/*    */     //   51: aload_3
/*    */     //   52: ifnonnull -> 59
/*    */     //   55: iconst_0
/*    */     //   56: goto -> 103
/*    */     //   59: aload_3
/*    */     //   60: instanceof java/lang/Number
/*    */     //   63: ifeq -> 78
/*    */     //   66: aload_3
/*    */     //   67: checkcast java/lang/Number
/*    */     //   70: aload #4
/*    */     //   72: invokestatic equalsNumObject : (Ljava/lang/Number;Ljava/lang/Object;)Z
/*    */     //   75: goto -> 103
/*    */     //   78: aload_3
/*    */     //   79: instanceof java/lang/Character
/*    */     //   82: ifeq -> 97
/*    */     //   85: aload_3
/*    */     //   86: checkcast java/lang/Character
/*    */     //   89: aload #4
/*    */     //   91: invokestatic equalsCharObject : (Ljava/lang/Character;Ljava/lang/Object;)Z
/*    */     //   94: goto -> 103
/*    */     //   97: aload_3
/*    */     //   98: aload #4
/*    */     //   100: invokevirtual equals : (Ljava/lang/Object;)Z
/*    */     //   103: ifeq -> 791
/*    */     //   106: aload_0
/*    */     //   107: invokevirtual _2 : ()Ljava/lang/Object;
/*    */     //   110: aload #21
/*    */     //   112: invokevirtual _2 : ()Ljava/lang/Object;
/*    */     //   115: astore #6
/*    */     //   117: dup
/*    */     //   118: astore #5
/*    */     //   120: aload #6
/*    */     //   122: if_acmpne -> 129
/*    */     //   125: iconst_1
/*    */     //   126: goto -> 187
/*    */     //   129: aload #5
/*    */     //   131: ifnonnull -> 138
/*    */     //   134: iconst_0
/*    */     //   135: goto -> 187
/*    */     //   138: aload #5
/*    */     //   140: instanceof java/lang/Number
/*    */     //   143: ifeq -> 159
/*    */     //   146: aload #5
/*    */     //   148: checkcast java/lang/Number
/*    */     //   151: aload #6
/*    */     //   153: invokestatic equalsNumObject : (Ljava/lang/Number;Ljava/lang/Object;)Z
/*    */     //   156: goto -> 187
/*    */     //   159: aload #5
/*    */     //   161: instanceof java/lang/Character
/*    */     //   164: ifeq -> 180
/*    */     //   167: aload #5
/*    */     //   169: checkcast java/lang/Character
/*    */     //   172: aload #6
/*    */     //   174: invokestatic equalsCharObject : (Ljava/lang/Character;Ljava/lang/Object;)Z
/*    */     //   177: goto -> 187
/*    */     //   180: aload #5
/*    */     //   182: aload #6
/*    */     //   184: invokevirtual equals : (Ljava/lang/Object;)Z
/*    */     //   187: ifeq -> 791
/*    */     //   190: aload_0
/*    */     //   191: invokevirtual _3 : ()Ljava/lang/Object;
/*    */     //   194: aload #21
/*    */     //   196: invokevirtual _3 : ()Ljava/lang/Object;
/*    */     //   199: astore #8
/*    */     //   201: dup
/*    */     //   202: astore #7
/*    */     //   204: aload #8
/*    */     //   206: if_acmpne -> 213
/*    */     //   209: iconst_1
/*    */     //   210: goto -> 271
/*    */     //   213: aload #7
/*    */     //   215: ifnonnull -> 222
/*    */     //   218: iconst_0
/*    */     //   219: goto -> 271
/*    */     //   222: aload #7
/*    */     //   224: instanceof java/lang/Number
/*    */     //   227: ifeq -> 243
/*    */     //   230: aload #7
/*    */     //   232: checkcast java/lang/Number
/*    */     //   235: aload #8
/*    */     //   237: invokestatic equalsNumObject : (Ljava/lang/Number;Ljava/lang/Object;)Z
/*    */     //   240: goto -> 271
/*    */     //   243: aload #7
/*    */     //   245: instanceof java/lang/Character
/*    */     //   248: ifeq -> 264
/*    */     //   251: aload #7
/*    */     //   253: checkcast java/lang/Character
/*    */     //   256: aload #8
/*    */     //   258: invokestatic equalsCharObject : (Ljava/lang/Character;Ljava/lang/Object;)Z
/*    */     //   261: goto -> 271
/*    */     //   264: aload #7
/*    */     //   266: aload #8
/*    */     //   268: invokevirtual equals : (Ljava/lang/Object;)Z
/*    */     //   271: ifeq -> 791
/*    */     //   274: aload_0
/*    */     //   275: invokevirtual _4 : ()Ljava/lang/Object;
/*    */     //   278: aload #21
/*    */     //   280: invokevirtual _4 : ()Ljava/lang/Object;
/*    */     //   283: astore #10
/*    */     //   285: dup
/*    */     //   286: astore #9
/*    */     //   288: aload #10
/*    */     //   290: if_acmpne -> 297
/*    */     //   293: iconst_1
/*    */     //   294: goto -> 355
/*    */     //   297: aload #9
/*    */     //   299: ifnonnull -> 306
/*    */     //   302: iconst_0
/*    */     //   303: goto -> 355
/*    */     //   306: aload #9
/*    */     //   308: instanceof java/lang/Number
/*    */     //   311: ifeq -> 327
/*    */     //   314: aload #9
/*    */     //   316: checkcast java/lang/Number
/*    */     //   319: aload #10
/*    */     //   321: invokestatic equalsNumObject : (Ljava/lang/Number;Ljava/lang/Object;)Z
/*    */     //   324: goto -> 355
/*    */     //   327: aload #9
/*    */     //   329: instanceof java/lang/Character
/*    */     //   332: ifeq -> 348
/*    */     //   335: aload #9
/*    */     //   337: checkcast java/lang/Character
/*    */     //   340: aload #10
/*    */     //   342: invokestatic equalsCharObject : (Ljava/lang/Character;Ljava/lang/Object;)Z
/*    */     //   345: goto -> 355
/*    */     //   348: aload #9
/*    */     //   350: aload #10
/*    */     //   352: invokevirtual equals : (Ljava/lang/Object;)Z
/*    */     //   355: ifeq -> 791
/*    */     //   358: aload_0
/*    */     //   359: invokevirtual _5 : ()Ljava/lang/Object;
/*    */     //   362: aload #21
/*    */     //   364: invokevirtual _5 : ()Ljava/lang/Object;
/*    */     //   367: astore #12
/*    */     //   369: dup
/*    */     //   370: astore #11
/*    */     //   372: aload #12
/*    */     //   374: if_acmpne -> 381
/*    */     //   377: iconst_1
/*    */     //   378: goto -> 439
/*    */     //   381: aload #11
/*    */     //   383: ifnonnull -> 390
/*    */     //   386: iconst_0
/*    */     //   387: goto -> 439
/*    */     //   390: aload #11
/*    */     //   392: instanceof java/lang/Number
/*    */     //   395: ifeq -> 411
/*    */     //   398: aload #11
/*    */     //   400: checkcast java/lang/Number
/*    */     //   403: aload #12
/*    */     //   405: invokestatic equalsNumObject : (Ljava/lang/Number;Ljava/lang/Object;)Z
/*    */     //   408: goto -> 439
/*    */     //   411: aload #11
/*    */     //   413: instanceof java/lang/Character
/*    */     //   416: ifeq -> 432
/*    */     //   419: aload #11
/*    */     //   421: checkcast java/lang/Character
/*    */     //   424: aload #12
/*    */     //   426: invokestatic equalsCharObject : (Ljava/lang/Character;Ljava/lang/Object;)Z
/*    */     //   429: goto -> 439
/*    */     //   432: aload #11
/*    */     //   434: aload #12
/*    */     //   436: invokevirtual equals : (Ljava/lang/Object;)Z
/*    */     //   439: ifeq -> 791
/*    */     //   442: aload_0
/*    */     //   443: invokevirtual _6 : ()Ljava/lang/Object;
/*    */     //   446: aload #21
/*    */     //   448: invokevirtual _6 : ()Ljava/lang/Object;
/*    */     //   451: astore #14
/*    */     //   453: dup
/*    */     //   454: astore #13
/*    */     //   456: aload #14
/*    */     //   458: if_acmpne -> 465
/*    */     //   461: iconst_1
/*    */     //   462: goto -> 523
/*    */     //   465: aload #13
/*    */     //   467: ifnonnull -> 474
/*    */     //   470: iconst_0
/*    */     //   471: goto -> 523
/*    */     //   474: aload #13
/*    */     //   476: instanceof java/lang/Number
/*    */     //   479: ifeq -> 495
/*    */     //   482: aload #13
/*    */     //   484: checkcast java/lang/Number
/*    */     //   487: aload #14
/*    */     //   489: invokestatic equalsNumObject : (Ljava/lang/Number;Ljava/lang/Object;)Z
/*    */     //   492: goto -> 523
/*    */     //   495: aload #13
/*    */     //   497: instanceof java/lang/Character
/*    */     //   500: ifeq -> 516
/*    */     //   503: aload #13
/*    */     //   505: checkcast java/lang/Character
/*    */     //   508: aload #14
/*    */     //   510: invokestatic equalsCharObject : (Ljava/lang/Character;Ljava/lang/Object;)Z
/*    */     //   513: goto -> 523
/*    */     //   516: aload #13
/*    */     //   518: aload #14
/*    */     //   520: invokevirtual equals : (Ljava/lang/Object;)Z
/*    */     //   523: ifeq -> 791
/*    */     //   526: aload_0
/*    */     //   527: invokevirtual _7 : ()Ljava/lang/Object;
/*    */     //   530: aload #21
/*    */     //   532: invokevirtual _7 : ()Ljava/lang/Object;
/*    */     //   535: astore #16
/*    */     //   537: dup
/*    */     //   538: astore #15
/*    */     //   540: aload #16
/*    */     //   542: if_acmpne -> 549
/*    */     //   545: iconst_1
/*    */     //   546: goto -> 607
/*    */     //   549: aload #15
/*    */     //   551: ifnonnull -> 558
/*    */     //   554: iconst_0
/*    */     //   555: goto -> 607
/*    */     //   558: aload #15
/*    */     //   560: instanceof java/lang/Number
/*    */     //   563: ifeq -> 579
/*    */     //   566: aload #15
/*    */     //   568: checkcast java/lang/Number
/*    */     //   571: aload #16
/*    */     //   573: invokestatic equalsNumObject : (Ljava/lang/Number;Ljava/lang/Object;)Z
/*    */     //   576: goto -> 607
/*    */     //   579: aload #15
/*    */     //   581: instanceof java/lang/Character
/*    */     //   584: ifeq -> 600
/*    */     //   587: aload #15
/*    */     //   589: checkcast java/lang/Character
/*    */     //   592: aload #16
/*    */     //   594: invokestatic equalsCharObject : (Ljava/lang/Character;Ljava/lang/Object;)Z
/*    */     //   597: goto -> 607
/*    */     //   600: aload #15
/*    */     //   602: aload #16
/*    */     //   604: invokevirtual equals : (Ljava/lang/Object;)Z
/*    */     //   607: ifeq -> 791
/*    */     //   610: aload_0
/*    */     //   611: invokevirtual _8 : ()Ljava/lang/Object;
/*    */     //   614: aload #21
/*    */     //   616: invokevirtual _8 : ()Ljava/lang/Object;
/*    */     //   619: astore #18
/*    */     //   621: dup
/*    */     //   622: astore #17
/*    */     //   624: aload #18
/*    */     //   626: if_acmpne -> 633
/*    */     //   629: iconst_1
/*    */     //   630: goto -> 691
/*    */     //   633: aload #17
/*    */     //   635: ifnonnull -> 642
/*    */     //   638: iconst_0
/*    */     //   639: goto -> 691
/*    */     //   642: aload #17
/*    */     //   644: instanceof java/lang/Number
/*    */     //   647: ifeq -> 663
/*    */     //   650: aload #17
/*    */     //   652: checkcast java/lang/Number
/*    */     //   655: aload #18
/*    */     //   657: invokestatic equalsNumObject : (Ljava/lang/Number;Ljava/lang/Object;)Z
/*    */     //   660: goto -> 691
/*    */     //   663: aload #17
/*    */     //   665: instanceof java/lang/Character
/*    */     //   668: ifeq -> 684
/*    */     //   671: aload #17
/*    */     //   673: checkcast java/lang/Character
/*    */     //   676: aload #18
/*    */     //   678: invokestatic equalsCharObject : (Ljava/lang/Character;Ljava/lang/Object;)Z
/*    */     //   681: goto -> 691
/*    */     //   684: aload #17
/*    */     //   686: aload #18
/*    */     //   688: invokevirtual equals : (Ljava/lang/Object;)Z
/*    */     //   691: ifeq -> 791
/*    */     //   694: aload_0
/*    */     //   695: invokevirtual _9 : ()Ljava/lang/Object;
/*    */     //   698: aload #21
/*    */     //   700: invokevirtual _9 : ()Ljava/lang/Object;
/*    */     //   703: astore #20
/*    */     //   705: dup
/*    */     //   706: astore #19
/*    */     //   708: aload #20
/*    */     //   710: if_acmpne -> 717
/*    */     //   713: iconst_1
/*    */     //   714: goto -> 775
/*    */     //   717: aload #19
/*    */     //   719: ifnonnull -> 726
/*    */     //   722: iconst_0
/*    */     //   723: goto -> 775
/*    */     //   726: aload #19
/*    */     //   728: instanceof java/lang/Number
/*    */     //   731: ifeq -> 747
/*    */     //   734: aload #19
/*    */     //   736: checkcast java/lang/Number
/*    */     //   739: aload #20
/*    */     //   741: invokestatic equalsNumObject : (Ljava/lang/Number;Ljava/lang/Object;)Z
/*    */     //   744: goto -> 775
/*    */     //   747: aload #19
/*    */     //   749: instanceof java/lang/Character
/*    */     //   752: ifeq -> 768
/*    */     //   755: aload #19
/*    */     //   757: checkcast java/lang/Character
/*    */     //   760: aload #20
/*    */     //   762: invokestatic equalsCharObject : (Ljava/lang/Character;Ljava/lang/Object;)Z
/*    */     //   765: goto -> 775
/*    */     //   768: aload #19
/*    */     //   770: aload #20
/*    */     //   772: invokevirtual equals : (Ljava/lang/Object;)Z
/*    */     //   775: ifeq -> 791
/*    */     //   778: aload #21
/*    */     //   780: aload_0
/*    */     //   781: invokevirtual canEqual : (Ljava/lang/Object;)Z
/*    */     //   784: ifeq -> 791
/*    */     //   787: iconst_1
/*    */     //   788: goto -> 792
/*    */     //   791: iconst_0
/*    */     //   792: ifeq -> 799
/*    */     //   795: iconst_1
/*    */     //   796: goto -> 800
/*    */     //   799: iconst_0
/*    */     //   800: ireturn
/*    */     // Line number table:
/*    */     //   Java source line number -> byte code offset
/*    */     //   #26	-> 0
/*    */     //   #236	-> 12
/*    */     //   #26	-> 19
/*    */     // Local variable table:
/*    */     //   start	length	slot	name	descriptor
/*    */     //   0	801	0	this	Lscala/Tuple9;
/*    */     //   0	801	1	x$1	Ljava/lang/Object;
/*    */   }
/*    */   
/*    */   public Tuple9(Object _1, Object _2, Object _3, Object _4, Object _5, Object _6, Object _7, Object _8, Object _9) {
/* 26 */     Product$class.$init$(this);
/* 26 */     Product9$class.$init$(this);
/*    */   }
/*    */   
/*    */   public String toString() {
/* 29 */     return (new StringBuilder()).append("(").append(_1()).append(",").append(_2()).append(",").append(_3()).append(",").append(_4()).append(",").append(_5()).append(",").append(_6()).append(",").append(_7()).append(",").append(_8()).append(",").append(_9()).append(")").toString();
/*    */   }
/*    */ }


/* Location:              D:\#source-code\TheFlightSims\TFSLibrary\World2Xplane\World2XPlane.jar!\scala\Tuple9.class
 * Java compiler version: 6 (50.0)
 * JD-Core Version:       1.1.3
 */