/*    */ package scala;
/*    */ 
/*    */ import scala.collection.Iterator;
/*    */ import scala.collection.mutable.StringBuilder;
/*    */ import scala.reflect.ScalaSignature;
/*    */ import scala.runtime.ScalaRunTime$;
/*    */ 
/*    */ @ScalaSignature(bytes = "\006\001\021ea\001B\001\003\001\026\021q\001V;qY\026\f$GC\001\004\003\025\0318-\0317b\007\001)RB\002\t\033;\001\032c%\013\0270eUB4#\002\001\b\027ij\004C\001\005\n\033\005\021\021B\001\006\003\005\031\te.\037*fMBq\001\002\004\b\0329}\021S\005K\026/cQ:\024BA\007\003\005%\001&o\0343vGR\f$\007\005\002\020!1\001AAB\t\001\t\013\007!C\001\002UcE\0211C\006\t\003\021QI!!\006\002\003\0179{G\017[5oOB\021\001bF\005\0031\t\0211!\0218z!\ty!\004\002\004\034\001\021\025\rA\005\002\003)J\002\"aD\017\005\ry\001AQ1\001\023\005\t!6\007\005\002\020A\0211\021\005\001CC\002I\021!\001\026\033\021\005=\031CA\002\023\001\t\013\007!C\001\002UkA\021qB\n\003\007O\001!)\031\001\n\003\005Q3\004CA\b*\t\031Q\003\001\"b\001%\t\021Ak\016\t\003\0371\"a!\f\001\005\006\004\021\"A\001+9!\tyq\006\002\0041\001\021\025\rA\005\002\003)f\002\"a\004\032\005\rM\002AQ1\001\023\005\r!\026\007\r\t\003\037U\"aA\016\001\005\006\004\021\"a\001+2cA\021q\002\017\003\007s\001!)\031\001\n\003\007Q\013$\007\005\002\tw%\021AH\001\002\b!J|G-^2u!\tAa(\003\002@\005\ta1+\032:jC2L'0\0312mK\"A\021\t\001BK\002\023\005!)\001\002`cU\ta\002\003\005E\001\tE\t\025!\003\017\003\ry\026\007\t\005\t\r\002\021)\032!C\001\017\006\021qLM\013\0023!A\021\n\001B\tB\003%\021$A\002`e\001B\001b\023\001\003\026\004%\t\001T\001\003?N*\022\001\b\005\t\035\002\021\t\022)A\0059\005\031ql\r\021\t\021A\003!Q3A\005\002E\013!a\030\033\026\003}A\001b\025\001\003\022\003\006IaH\001\004?R\002\003\002C+\001\005+\007I\021\001,\002\005}+T#\001\022\t\021a\003!\021#Q\001\n\t\n1aX\033!\021!Q\006A!f\001\n\003Y\026AA07+\005)\003\002C/\001\005#\005\013\021B\023\002\007}3\004\005\003\005`\001\tU\r\021\"\001a\003\tyv'F\001)\021!\021\007A!E!\002\023A\023aA08A!AA\r\001BK\002\023\005Q-\001\002`qU\t1\006\003\005h\001\tE\t\025!\003,\003\ry\006\b\t\005\tS\002\021)\032!C\001U\006\021q,O\013\002]!AA\016\001B\tB\003%a&A\002`s\001B\001B\034\001\003\026\004%\ta\\\001\004?F\002T#A\031\t\021E\004!\021#Q\001\nE\nAaX\0311A!A1\017\001BK\002\023\005A/A\002`cE*\022\001\016\005\tm\002\021\t\022)A\005i\005!q,M\031!\021!A\bA!f\001\n\003I\030aA02eU\tq\007\003\005|\001\tE\t\025!\0038\003\021y\026G\r\021\t\013u\004A\021\001@\002\rqJg.\033;?)ey\030\021AA\002\003\013\t9!!\003\002\f\0055\021qBA\t\003'\t)\"a\006\021\035!\001a\"\007\017 E\025B3FL\0315o!)\021\t a\001\035!)a\t a\0013!)1\n a\0019!)\001\013 a\001?!)Q\013 a\001E!)!\f a\001K!)q\f a\001Q!)A\r a\001W!)\021\016 a\001]!)a\016 a\001c!)1\017 a\001i!)\001\020 a\001o!9\0211\004\001\005B\005u\021\001\003;p'R\024\030N\\4\025\005\005}\001\003BA\021\003Wi!!a\t\013\t\005\025\022qE\001\005Y\006twM\003\002\002*\005!!.\031<b\023\021\ti#a\t\003\rM#(/\0338h\021%\t\t\004AA\001\n\003\t\031$\001\003d_BLXCGA\033\003w\ty$a\021\002H\005-\023qJA*\003/\nY&a\030\002d\005\035DCGA\034\003S\nY'!\034\002p\005E\0241OA;\003o\nI(a\037\002~\005}\004C\007\005\001\003s\ti$!\021\002F\005%\023QJA)\003+\nI&!\030\002b\005\025\004cA\b\002<\0211\021#a\fC\002I\0012aDA \t\031Y\022q\006b\001%A\031q\"a\021\005\ry\tyC1\001\023!\ry\021q\t\003\007C\005=\"\031\001\n\021\007=\tY\005\002\004%\003_\021\rA\005\t\004\037\005=CAB\024\0020\t\007!\003E\002\020\003'\"aAKA\030\005\004\021\002cA\b\002X\0211Q&a\fC\002I\0012aDA.\t\031\001\024q\006b\001%A\031q\"a\030\005\rM\nyC1\001\023!\ry\0211\r\003\007m\005=\"\031\001\n\021\007=\t9\007\002\004:\003_\021\rA\005\005\n\003\006=\002\023!a\001\003sA\021BRA\030!\003\005\r!!\020\t\023-\013y\003%AA\002\005\005\003\"\003)\0020A\005\t\031AA#\021%)\026q\006I\001\002\004\tI\005C\005[\003_\001\n\0211\001\002N!Iq,a\f\021\002\003\007\021\021\013\005\nI\006=\002\023!a\001\003+B\021\"[A\030!\003\005\r!!\027\t\0239\fy\003%AA\002\005u\003\"C:\0020A\005\t\031AA1\021%A\030q\006I\001\002\004\t)\007C\005\002\004\002\t\n\021\"\001\002\006\006q1m\0349zI\021,g-Y;mi\022\nTCGAD\003;\013y*!)\002$\006\025\026qUAU\003W\013i+a,\0022\006MVCAAEU\rq\0211R\026\003\003\033\003B!a$\002\0326\021\021\021\023\006\005\003'\013)*A\005v]\016DWmY6fI*\031\021q\023\002\002\025\005tgn\034;bi&|g.\003\003\002\034\006E%!E;oG\",7m[3e-\006\024\030.\0318dK\0221\021#!!C\002I!aaGAA\005\004\021BA\002\020\002\002\n\007!\003\002\004\"\003\003\023\rA\005\003\007I\005\005%\031\001\n\005\r\035\n\tI1\001\023\t\031Q\023\021\021b\001%\0211Q&!!C\002I!a\001MAA\005\004\021BAB\032\002\002\n\007!\003\002\0047\003\003\023\rA\005\003\007s\005\005%\031\001\n\t\023\005]\006!%A\005\002\005e\026AD2paf$C-\0324bk2$HEM\013\033\003w\013y,!1\002D\006\025\027qYAe\003\027\fi-a4\002R\006M\027Q[\013\003\003{S3!GAF\t\031\t\022Q\027b\001%\02111$!.C\002I!aAHA[\005\004\021BAB\021\0026\n\007!\003\002\004%\003k\023\rA\005\003\007O\005U&\031\001\n\005\r)\n)L1\001\023\t\031i\023Q\027b\001%\0211\001'!.C\002I!aaMA[\005\004\021BA\002\034\0026\n\007!\003\002\004:\003k\023\rA\005\005\n\0033\004\021\023!C\001\0037\fabY8qs\022\"WMZ1vYR$3'\006\016\002^\006\005\0301]As\003O\fI/a;\002n\006=\030\021_Az\003k\f90\006\002\002`*\032A$a#\005\rE\t9N1\001\023\t\031Y\022q\033b\001%\0211a$a6C\002I!a!IAl\005\004\021BA\002\023\002X\n\007!\003\002\004(\003/\024\rA\005\003\007U\005]'\031\001\n\005\r5\n9N1\001\023\t\031\001\024q\033b\001%\02111'a6C\002I!aANAl\005\004\021BAB\035\002X\n\007!\003C\005\002|\002\t\n\021\"\001\002~\006q1m\0349zI\021,g-Y;mi\022\"TCGA\000\005\007\021)Aa\002\003\n\t-!Q\002B\b\005#\021\031B!\006\003\030\teQC\001B\001U\ry\0221\022\003\007#\005e(\031\001\n\005\rm\tIP1\001\023\t\031q\022\021 b\001%\0211\021%!?C\002I!a\001JA}\005\004\021BAB\024\002z\n\007!\003\002\004+\003s\024\rA\005\003\007[\005e(\031\001\n\005\rA\nIP1\001\023\t\031\031\024\021 b\001%\0211a'!?C\002I!a!OA}\005\004\021\002\"\003B\017\001E\005I\021\001B\020\0039\031w\016]=%I\0264\027-\0367uIU*\"D!\t\003&\t\035\"\021\006B\026\005[\021yC!\r\0034\tU\"q\007B\035\005w)\"Aa\t+\007\t\nY\t\002\004\022\0057\021\rA\005\003\0077\tm!\031\001\n\005\ry\021YB1\001\023\t\031\t#1\004b\001%\0211AEa\007C\002I!aa\nB\016\005\004\021BA\002\026\003\034\t\007!\003\002\004.\0057\021\rA\005\003\007a\tm!\031\001\n\005\rM\022YB1\001\023\t\0311$1\004b\001%\0211\021Ha\007C\002IA\021Ba\020\001#\003%\tA!\021\002\035\r|\007/\037\023eK\032\fW\017\034;%mUQ\"1\tB$\005\023\022YE!\024\003P\tE#1\013B+\005/\022IFa\027\003^U\021!Q\t\026\004K\005-EAB\t\003>\t\007!\003\002\004\034\005{\021\rA\005\003\007=\tu\"\031\001\n\005\r\005\022iD1\001\023\t\031!#Q\bb\001%\0211qE!\020C\002I!aA\013B\037\005\004\021BAB\027\003>\t\007!\003\002\0041\005{\021\rA\005\003\007g\tu\"\031\001\n\005\rY\022iD1\001\023\t\031I$Q\bb\001%!I!\021\r\001\022\002\023\005!1M\001\017G>\004\030\020\n3fM\006,H\016\036\0238+i\021)G!\033\003l\t5$q\016B9\005g\022)Ha\036\003z\tm$Q\020B@+\t\0219GK\002)\003\027#a!\005B0\005\004\021BAB\016\003`\t\007!\003\002\004\037\005?\022\rA\005\003\007C\t}#\031\001\n\005\r\021\022yF1\001\023\t\0319#q\fb\001%\0211!Fa\030C\002I!a!\fB0\005\004\021BA\002\031\003`\t\007!\003\002\0044\005?\022\rA\005\003\007m\t}#\031\001\n\005\re\022yF1\001\023\021%\021\031\tAI\001\n\003\021))\001\bd_BLH\005Z3gCVdG\017\n\035\0265\t\035%1\022BG\005\037\023\tJa%\003\026\n]%\021\024BN\005;\023yJ!)\026\005\t%%fA\026\002\f\0221\021C!!C\002I!aa\007BA\005\004\021BA\002\020\003\002\n\007!\003\002\004\"\005\003\023\rA\005\003\007I\t\005%\031\001\n\005\r\035\022\tI1\001\023\t\031Q#\021\021b\001%\0211QF!!C\002I!a\001\rBA\005\004\021BAB\032\003\002\n\007!\003\002\0047\005\003\023\rA\005\003\007s\t\005%\031\001\n\t\023\t\025\006!%A\005\002\t\035\026AD2paf$C-\0324bk2$H%O\013\033\005S\023iKa,\0032\nM&Q\027B\\\005s\023YL!0\003@\n\005'1Y\013\003\005WS3ALAF\t\031\t\"1\025b\001%\02111Da)C\002I!aA\bBR\005\004\021BAB\021\003$\n\007!\003\002\004%\005G\023\rA\005\003\007O\t\r&\031\001\n\005\r)\022\031K1\001\023\t\031i#1\025b\001%\0211\001Ga)C\002I!aa\rBR\005\004\021BA\002\034\003$\n\007!\003\002\004:\005G\023\rA\005\005\n\005\017\004\021\023!C\001\005\023\fqbY8qs\022\"WMZ1vYR$\023\007M\013\033\005\027\024yM!5\003T\nU'q\033Bm\0057\024iNa8\003b\n\r(Q]\013\003\005\033T3!MAF\t\031\t\"Q\031b\001%\02111D!2C\002I!aA\bBc\005\004\021BAB\021\003F\n\007!\003\002\004%\005\013\024\rA\005\003\007O\t\025'\031\001\n\005\r)\022)M1\001\023\t\031i#Q\031b\001%\0211\001G!2C\002I!aa\rBc\005\004\021BA\002\034\003F\n\007!\003\002\004:\005\013\024\rA\005\005\n\005S\004\021\023!C\001\005W\fqbY8qs\022\"WMZ1vYR$\023'M\013\033\005[\024\tPa=\003v\n](\021 B~\005{\024yp!\001\004\004\r\0251qA\013\003\005_T3\001NAF\t\031\t\"q\035b\001%\02111Da:C\002I!aA\bBt\005\004\021BAB\021\003h\n\007!\003\002\004%\005O\024\rA\005\003\007O\t\035(\031\001\n\005\r)\0229O1\001\023\t\031i#q\035b\001%\0211\001Ga:C\002I!aa\rBt\005\004\021BA\002\034\003h\n\007!\003\002\004:\005O\024\rA\005\005\n\007\027\001\021\023!C\001\007\033\tqbY8qs\022\"WMZ1vYR$\023GM\013\033\007\037\031\031b!\006\004\030\re11DB\017\007?\031\tca\t\004&\r\0352\021F\013\003\007#Q3aNAF\t\031\t2\021\002b\001%\02111d!\003C\002I!aAHB\005\005\004\021BAB\021\004\n\t\007!\003\002\004%\007\023\021\rA\005\003\007O\r%!\031\001\n\005\r)\032IA1\001\023\t\031i3\021\002b\001%\0211\001g!\003C\002I!aaMB\005\005\004\021BA\002\034\004\n\t\007!\003\002\004:\007\023\021\rA\005\005\n\007[\001\021\021!C!\007_\tQ\002\035:pIV\034G\017\025:fM&DXCAA\020\021%\031\031\004AA\001\n\003\032)$A\bqe>$Wo\031;Ji\026\024\030\r^8s+\t\0319\004E\003\004:\r}b#\004\002\004<)\0311Q\b\002\002\025\r|G\016\\3di&|g.\003\003\004B\rm\"\001C%uKJ\fGo\034:\t\023\r\025\003!!A\005\002\r\035\023\001C2b]\026\013X/\0317\025\t\r%3q\n\t\004\021\r-\023bAB'\005\t9!i\\8mK\006t\007\"CB)\007\007\n\t\0211\001\027\003\rAH%\r\005\n\007+\002\021\021!C!\007/\n\001\002[1tQ\016{G-\032\013\003\0073\0022\001CB.\023\r\031iF\001\002\004\023:$\b\"CB1\001\005\005I\021IB2\003\031)\027/^1mgR!1\021JB3\021%\031\tfa\030\002\002\003\007acB\005\004j\t\t\t\021#\001\004l\0059A+\0369mKF\022\004c\001\005\004n\031A\021AAA\001\022\003\031yg\005\003\004n\035i\004bB?\004n\021\00511\017\013\003\007WB!\"a\007\004n\005\005IQIA\017\021)\031Ih!\034\002\002\023\00551P\001\006CB\004H._\013\033\007{\032\031ia\"\004\f\016=51SBL\0077\033yja)\004(\016-6q\026\013\033\007\032\tla-\0046\016]6\021XB^\007{\033yl!1\004D\016\0257q\031\t\033\021\001\031\ti!\"\004\n\01655\021SBK\0073\033ij!)\004&\016%6Q\026\t\004\037\r\rEAB\t\004x\t\007!\003E\002\020\007\017#aaGB<\005\004\021\002cA\b\004\f\0221ada\036C\002I\0012aDBH\t\031\t3q\017b\001%A\031qba%\005\r\021\0329H1\001\023!\ry1q\023\003\007O\r]$\031\001\n\021\007=\031Y\n\002\004+\007o\022\rA\005\t\004\037\r}EAB\027\004x\t\007!\003E\002\020\007G#a\001MB<\005\004\021\002cA\b\004(\02211ga\036C\002I\0012aDBV\t\03114q\017b\001%A\031qba,\005\re\0329H1\001\023\021\035\t5q\017a\001\007\003CqARB<\001\004\031)\tC\004L\007o\002\ra!#\t\017A\0339\b1\001\004\016\"9Qka\036A\002\rE\005b\002.\004x\001\0071Q\023\005\b?\016]\004\031ABM\021\035!7q\017a\001\007;Cq![B<\001\004\031\t\013C\004o\007o\002\ra!*\t\017M\0349\b1\001\004*\"9\001pa\036A\002\r5\006BCBf\007[\n\t\021\"!\004N\0069QO\\1qa2LXCGBh\0077\034yna9\004h\016-8q^Bz\007o\034Ypa@\005\004\021\035A\003BBi\t\023\001R\001CBj\007/L1a!6\003\005\031y\005\017^5p]BQ\002\002ABm\007;\034\to!:\004j\01658\021_B{\007s\034i\020\"\001\005\006A\031qba7\005\rE\031IM1\001\023!\ry1q\034\003\0077\r%'\031\001\n\021\007=\031\031\017\002\004\037\007\023\024\rA\005\t\004\037\r\035HAB\021\004J\n\007!\003E\002\020\007W$a\001JBe\005\004\021\002cA\b\004p\0221qe!3C\002I\0012aDBz\t\031Q3\021\032b\001%A\031qba>\005\r5\032IM1\001\023!\ry11 \003\007a\r%'\031\001\n\021\007=\031y\020\002\0044\007\023\024\rA\005\t\004\037\021\rAA\002\034\004J\n\007!\003E\002\020\t\017!a!OBe\005\004\021\002B\003C\006\007\023\f\t\0211\001\004X\006\031\001\020\n\031\t\025\021=1QNA\001\n\023!\t\"A\006sK\006$'+Z:pYZ,GC\001C\n!\021\t\t\003\"\006\n\t\021]\0211\005\002\007\037\nTWm\031;")
/*    */ public class Tuple12<T1, T2, T3, T4, T5, T6, T7, T8, T9, T10, T11, T12> implements Product12<T1, T2, T3, T4, T5, T6, T7, T8, T9, T10, T11, T12>, Product, Serializable {
/*    */   private final T1 _1;
/*    */   
/*    */   private final T2 _2;
/*    */   
/*    */   private final T3 _3;
/*    */   
/*    */   private final T4 _4;
/*    */   
/*    */   private final T5 _5;
/*    */   
/*    */   private final T6 _6;
/*    */   
/*    */   private final T7 _7;
/*    */   
/*    */   private final T8 _8;
/*    */   
/*    */   private final T9 _9;
/*    */   
/*    */   private final T10 _10;
/*    */   
/*    */   private final T11 _11;
/*    */   
/*    */   private final T12 _12;
/*    */   
/*    */   public int productArity() {
/* 29 */     return Product12$class.productArity(this);
/*    */   }
/*    */   
/*    */   public Object productElement(int n) throws IndexOutOfBoundsException {
/* 29 */     return Product12$class.productElement(this, n);
/*    */   }
/*    */   
/*    */   public T1 _1() {
/* 29 */     return this._1;
/*    */   }
/*    */   
/*    */   public T2 _2() {
/* 29 */     return this._2;
/*    */   }
/*    */   
/*    */   public T3 _3() {
/* 29 */     return this._3;
/*    */   }
/*    */   
/*    */   public T4 _4() {
/* 29 */     return this._4;
/*    */   }
/*    */   
/*    */   public T5 _5() {
/* 29 */     return this._5;
/*    */   }
/*    */   
/*    */   public T6 _6() {
/* 29 */     return this._6;
/*    */   }
/*    */   
/*    */   public T7 _7() {
/* 29 */     return this._7;
/*    */   }
/*    */   
/*    */   public T8 _8() {
/* 29 */     return this._8;
/*    */   }
/*    */   
/*    */   public T9 _9() {
/* 29 */     return this._9;
/*    */   }
/*    */   
/*    */   public T10 _10() {
/* 29 */     return this._10;
/*    */   }
/*    */   
/*    */   public T11 _11() {
/* 29 */     return this._11;
/*    */   }
/*    */   
/*    */   public T12 _12() {
/* 29 */     return this._12;
/*    */   }
/*    */   
/*    */   public <T1, T2, T3, T4, T5, T6, T7, T8, T9, T10, T11, T12> Tuple12<T1, T2, T3, T4, T5, T6, T7, T8, T9, T10, T11, T12> copy(Object _1, Object _2, Object _3, Object _4, Object _5, Object _6, Object _7, Object _8, Object _9, Object _10, Object _11, Object _12) {
/* 29 */     return new Tuple12((T1)_1, (T2)_2, (T3)_3, (T4)_4, (T5)_5, (T6)_6, (T7)_7, (T8)_8, (T9)_9, (T10)_10, (T11)_11, (T12)_12);
/*    */   }
/*    */   
/*    */   public <T1, T2, T3, T4, T5, T6, T7, T8, T9, T10, T11, T12> T1 copy$default$1() {
/* 29 */     return _1();
/*    */   }
/*    */   
/*    */   public <T1, T2, T3, T4, T5, T6, T7, T8, T9, T10, T11, T12> T2 copy$default$2() {
/* 29 */     return _2();
/*    */   }
/*    */   
/*    */   public <T1, T2, T3, T4, T5, T6, T7, T8, T9, T10, T11, T12> T3 copy$default$3() {
/* 29 */     return _3();
/*    */   }
/*    */   
/*    */   public <T1, T2, T3, T4, T5, T6, T7, T8, T9, T10, T11, T12> T4 copy$default$4() {
/* 29 */     return _4();
/*    */   }
/*    */   
/*    */   public <T1, T2, T3, T4, T5, T6, T7, T8, T9, T10, T11, T12> T5 copy$default$5() {
/* 29 */     return _5();
/*    */   }
/*    */   
/*    */   public <T1, T2, T3, T4, T5, T6, T7, T8, T9, T10, T11, T12> T6 copy$default$6() {
/* 29 */     return _6();
/*    */   }
/*    */   
/*    */   public <T1, T2, T3, T4, T5, T6, T7, T8, T9, T10, T11, T12> T7 copy$default$7() {
/* 29 */     return _7();
/*    */   }
/*    */   
/*    */   public <T1, T2, T3, T4, T5, T6, T7, T8, T9, T10, T11, T12> T8 copy$default$8() {
/* 29 */     return _8();
/*    */   }
/*    */   
/*    */   public <T1, T2, T3, T4, T5, T6, T7, T8, T9, T10, T11, T12> T9 copy$default$9() {
/* 29 */     return _9();
/*    */   }
/*    */   
/*    */   public <T1, T2, T3, T4, T5, T6, T7, T8, T9, T10, T11, T12> T10 copy$default$10() {
/* 29 */     return _10();
/*    */   }
/*    */   
/*    */   public <T1, T2, T3, T4, T5, T6, T7, T8, T9, T10, T11, T12> T11 copy$default$11() {
/* 29 */     return _11();
/*    */   }
/*    */   
/*    */   public <T1, T2, T3, T4, T5, T6, T7, T8, T9, T10, T11, T12> T12 copy$default$12() {
/* 29 */     return _12();
/*    */   }
/*    */   
/*    */   public String productPrefix() {
/* 29 */     return "Tuple12";
/*    */   }
/*    */   
/*    */   public Iterator<Object> productIterator() {
/* 29 */     return ScalaRunTime$.MODULE$.typedProductIterator(this);
/*    */   }
/*    */   
/*    */   public boolean canEqual(Object x$1) {
/* 29 */     return x$1 instanceof Tuple12;
/*    */   }
/*    */   
/*    */   public int hashCode() {
/* 29 */     return ScalaRunTime$.MODULE$._hashCode(this);
/*    */   }
/*    */   
/*    */   public boolean equals(Object x$1) {
/*    */     // Byte code:
/*    */     //   0: aload_0
/*    */     //   1: aload_1
/*    */     //   2: if_acmpeq -> 1047
/*    */     //   5: aload_1
/*    */     //   6: instanceof scala/Tuple12
/*    */     //   9: ifeq -> 17
/*    */     //   12: iconst_1
/*    */     //   13: istore_2
/*    */     //   14: goto -> 19
/*    */     //   17: iconst_0
/*    */     //   18: istore_2
/*    */     //   19: iload_2
/*    */     //   20: ifeq -> 1051
/*    */     //   23: aload_1
/*    */     //   24: checkcast scala/Tuple12
/*    */     //   27: astore #27
/*    */     //   29: aload_0
/*    */     //   30: invokevirtual _1 : ()Ljava/lang/Object;
/*    */     //   33: aload #27
/*    */     //   35: invokevirtual _1 : ()Ljava/lang/Object;
/*    */     //   38: astore #4
/*    */     //   40: dup
/*    */     //   41: astore_3
/*    */     //   42: aload #4
/*    */     //   44: if_acmpne -> 51
/*    */     //   47: iconst_1
/*    */     //   48: goto -> 103
/*    */     //   51: aload_3
/*    */     //   52: ifnonnull -> 59
/*    */     //   55: iconst_0
/*    */     //   56: goto -> 103
/*    */     //   59: aload_3
/*    */     //   60: instanceof java/lang/Number
/*    */     //   63: ifeq -> 78
/*    */     //   66: aload_3
/*    */     //   67: checkcast java/lang/Number
/*    */     //   70: aload #4
/*    */     //   72: invokestatic equalsNumObject : (Ljava/lang/Number;Ljava/lang/Object;)Z
/*    */     //   75: goto -> 103
/*    */     //   78: aload_3
/*    */     //   79: instanceof java/lang/Character
/*    */     //   82: ifeq -> 97
/*    */     //   85: aload_3
/*    */     //   86: checkcast java/lang/Character
/*    */     //   89: aload #4
/*    */     //   91: invokestatic equalsCharObject : (Ljava/lang/Character;Ljava/lang/Object;)Z
/*    */     //   94: goto -> 103
/*    */     //   97: aload_3
/*    */     //   98: aload #4
/*    */     //   100: invokevirtual equals : (Ljava/lang/Object;)Z
/*    */     //   103: ifeq -> 1043
/*    */     //   106: aload_0
/*    */     //   107: invokevirtual _2 : ()Ljava/lang/Object;
/*    */     //   110: aload #27
/*    */     //   112: invokevirtual _2 : ()Ljava/lang/Object;
/*    */     //   115: astore #6
/*    */     //   117: dup
/*    */     //   118: astore #5
/*    */     //   120: aload #6
/*    */     //   122: if_acmpne -> 129
/*    */     //   125: iconst_1
/*    */     //   126: goto -> 187
/*    */     //   129: aload #5
/*    */     //   131: ifnonnull -> 138
/*    */     //   134: iconst_0
/*    */     //   135: goto -> 187
/*    */     //   138: aload #5
/*    */     //   140: instanceof java/lang/Number
/*    */     //   143: ifeq -> 159
/*    */     //   146: aload #5
/*    */     //   148: checkcast java/lang/Number
/*    */     //   151: aload #6
/*    */     //   153: invokestatic equalsNumObject : (Ljava/lang/Number;Ljava/lang/Object;)Z
/*    */     //   156: goto -> 187
/*    */     //   159: aload #5
/*    */     //   161: instanceof java/lang/Character
/*    */     //   164: ifeq -> 180
/*    */     //   167: aload #5
/*    */     //   169: checkcast java/lang/Character
/*    */     //   172: aload #6
/*    */     //   174: invokestatic equalsCharObject : (Ljava/lang/Character;Ljava/lang/Object;)Z
/*    */     //   177: goto -> 187
/*    */     //   180: aload #5
/*    */     //   182: aload #6
/*    */     //   184: invokevirtual equals : (Ljava/lang/Object;)Z
/*    */     //   187: ifeq -> 1043
/*    */     //   190: aload_0
/*    */     //   191: invokevirtual _3 : ()Ljava/lang/Object;
/*    */     //   194: aload #27
/*    */     //   196: invokevirtual _3 : ()Ljava/lang/Object;
/*    */     //   199: astore #8
/*    */     //   201: dup
/*    */     //   202: astore #7
/*    */     //   204: aload #8
/*    */     //   206: if_acmpne -> 213
/*    */     //   209: iconst_1
/*    */     //   210: goto -> 271
/*    */     //   213: aload #7
/*    */     //   215: ifnonnull -> 222
/*    */     //   218: iconst_0
/*    */     //   219: goto -> 271
/*    */     //   222: aload #7
/*    */     //   224: instanceof java/lang/Number
/*    */     //   227: ifeq -> 243
/*    */     //   230: aload #7
/*    */     //   232: checkcast java/lang/Number
/*    */     //   235: aload #8
/*    */     //   237: invokestatic equalsNumObject : (Ljava/lang/Number;Ljava/lang/Object;)Z
/*    */     //   240: goto -> 271
/*    */     //   243: aload #7
/*    */     //   245: instanceof java/lang/Character
/*    */     //   248: ifeq -> 264
/*    */     //   251: aload #7
/*    */     //   253: checkcast java/lang/Character
/*    */     //   256: aload #8
/*    */     //   258: invokestatic equalsCharObject : (Ljava/lang/Character;Ljava/lang/Object;)Z
/*    */     //   261: goto -> 271
/*    */     //   264: aload #7
/*    */     //   266: aload #8
/*    */     //   268: invokevirtual equals : (Ljava/lang/Object;)Z
/*    */     //   271: ifeq -> 1043
/*    */     //   274: aload_0
/*    */     //   275: invokevirtual _4 : ()Ljava/lang/Object;
/*    */     //   278: aload #27
/*    */     //   280: invokevirtual _4 : ()Ljava/lang/Object;
/*    */     //   283: astore #10
/*    */     //   285: dup
/*    */     //   286: astore #9
/*    */     //   288: aload #10
/*    */     //   290: if_acmpne -> 297
/*    */     //   293: iconst_1
/*    */     //   294: goto -> 355
/*    */     //   297: aload #9
/*    */     //   299: ifnonnull -> 306
/*    */     //   302: iconst_0
/*    */     //   303: goto -> 355
/*    */     //   306: aload #9
/*    */     //   308: instanceof java/lang/Number
/*    */     //   311: ifeq -> 327
/*    */     //   314: aload #9
/*    */     //   316: checkcast java/lang/Number
/*    */     //   319: aload #10
/*    */     //   321: invokestatic equalsNumObject : (Ljava/lang/Number;Ljava/lang/Object;)Z
/*    */     //   324: goto -> 355
/*    */     //   327: aload #9
/*    */     //   329: instanceof java/lang/Character
/*    */     //   332: ifeq -> 348
/*    */     //   335: aload #9
/*    */     //   337: checkcast java/lang/Character
/*    */     //   340: aload #10
/*    */     //   342: invokestatic equalsCharObject : (Ljava/lang/Character;Ljava/lang/Object;)Z
/*    */     //   345: goto -> 355
/*    */     //   348: aload #9
/*    */     //   350: aload #10
/*    */     //   352: invokevirtual equals : (Ljava/lang/Object;)Z
/*    */     //   355: ifeq -> 1043
/*    */     //   358: aload_0
/*    */     //   359: invokevirtual _5 : ()Ljava/lang/Object;
/*    */     //   362: aload #27
/*    */     //   364: invokevirtual _5 : ()Ljava/lang/Object;
/*    */     //   367: astore #12
/*    */     //   369: dup
/*    */     //   370: astore #11
/*    */     //   372: aload #12
/*    */     //   374: if_acmpne -> 381
/*    */     //   377: iconst_1
/*    */     //   378: goto -> 439
/*    */     //   381: aload #11
/*    */     //   383: ifnonnull -> 390
/*    */     //   386: iconst_0
/*    */     //   387: goto -> 439
/*    */     //   390: aload #11
/*    */     //   392: instanceof java/lang/Number
/*    */     //   395: ifeq -> 411
/*    */     //   398: aload #11
/*    */     //   400: checkcast java/lang/Number
/*    */     //   403: aload #12
/*    */     //   405: invokestatic equalsNumObject : (Ljava/lang/Number;Ljava/lang/Object;)Z
/*    */     //   408: goto -> 439
/*    */     //   411: aload #11
/*    */     //   413: instanceof java/lang/Character
/*    */     //   416: ifeq -> 432
/*    */     //   419: aload #11
/*    */     //   421: checkcast java/lang/Character
/*    */     //   424: aload #12
/*    */     //   426: invokestatic equalsCharObject : (Ljava/lang/Character;Ljava/lang/Object;)Z
/*    */     //   429: goto -> 439
/*    */     //   432: aload #11
/*    */     //   434: aload #12
/*    */     //   436: invokevirtual equals : (Ljava/lang/Object;)Z
/*    */     //   439: ifeq -> 1043
/*    */     //   442: aload_0
/*    */     //   443: invokevirtual _6 : ()Ljava/lang/Object;
/*    */     //   446: aload #27
/*    */     //   448: invokevirtual _6 : ()Ljava/lang/Object;
/*    */     //   451: astore #14
/*    */     //   453: dup
/*    */     //   454: astore #13
/*    */     //   456: aload #14
/*    */     //   458: if_acmpne -> 465
/*    */     //   461: iconst_1
/*    */     //   462: goto -> 523
/*    */     //   465: aload #13
/*    */     //   467: ifnonnull -> 474
/*    */     //   470: iconst_0
/*    */     //   471: goto -> 523
/*    */     //   474: aload #13
/*    */     //   476: instanceof java/lang/Number
/*    */     //   479: ifeq -> 495
/*    */     //   482: aload #13
/*    */     //   484: checkcast java/lang/Number
/*    */     //   487: aload #14
/*    */     //   489: invokestatic equalsNumObject : (Ljava/lang/Number;Ljava/lang/Object;)Z
/*    */     //   492: goto -> 523
/*    */     //   495: aload #13
/*    */     //   497: instanceof java/lang/Character
/*    */     //   500: ifeq -> 516
/*    */     //   503: aload #13
/*    */     //   505: checkcast java/lang/Character
/*    */     //   508: aload #14
/*    */     //   510: invokestatic equalsCharObject : (Ljava/lang/Character;Ljava/lang/Object;)Z
/*    */     //   513: goto -> 523
/*    */     //   516: aload #13
/*    */     //   518: aload #14
/*    */     //   520: invokevirtual equals : (Ljava/lang/Object;)Z
/*    */     //   523: ifeq -> 1043
/*    */     //   526: aload_0
/*    */     //   527: invokevirtual _7 : ()Ljava/lang/Object;
/*    */     //   530: aload #27
/*    */     //   532: invokevirtual _7 : ()Ljava/lang/Object;
/*    */     //   535: astore #16
/*    */     //   537: dup
/*    */     //   538: astore #15
/*    */     //   540: aload #16
/*    */     //   542: if_acmpne -> 549
/*    */     //   545: iconst_1
/*    */     //   546: goto -> 607
/*    */     //   549: aload #15
/*    */     //   551: ifnonnull -> 558
/*    */     //   554: iconst_0
/*    */     //   555: goto -> 607
/*    */     //   558: aload #15
/*    */     //   560: instanceof java/lang/Number
/*    */     //   563: ifeq -> 579
/*    */     //   566: aload #15
/*    */     //   568: checkcast java/lang/Number
/*    */     //   571: aload #16
/*    */     //   573: invokestatic equalsNumObject : (Ljava/lang/Number;Ljava/lang/Object;)Z
/*    */     //   576: goto -> 607
/*    */     //   579: aload #15
/*    */     //   581: instanceof java/lang/Character
/*    */     //   584: ifeq -> 600
/*    */     //   587: aload #15
/*    */     //   589: checkcast java/lang/Character
/*    */     //   592: aload #16
/*    */     //   594: invokestatic equalsCharObject : (Ljava/lang/Character;Ljava/lang/Object;)Z
/*    */     //   597: goto -> 607
/*    */     //   600: aload #15
/*    */     //   602: aload #16
/*    */     //   604: invokevirtual equals : (Ljava/lang/Object;)Z
/*    */     //   607: ifeq -> 1043
/*    */     //   610: aload_0
/*    */     //   611: invokevirtual _8 : ()Ljava/lang/Object;
/*    */     //   614: aload #27
/*    */     //   616: invokevirtual _8 : ()Ljava/lang/Object;
/*    */     //   619: astore #18
/*    */     //   621: dup
/*    */     //   622: astore #17
/*    */     //   624: aload #18
/*    */     //   626: if_acmpne -> 633
/*    */     //   629: iconst_1
/*    */     //   630: goto -> 691
/*    */     //   633: aload #17
/*    */     //   635: ifnonnull -> 642
/*    */     //   638: iconst_0
/*    */     //   639: goto -> 691
/*    */     //   642: aload #17
/*    */     //   644: instanceof java/lang/Number
/*    */     //   647: ifeq -> 663
/*    */     //   650: aload #17
/*    */     //   652: checkcast java/lang/Number
/*    */     //   655: aload #18
/*    */     //   657: invokestatic equalsNumObject : (Ljava/lang/Number;Ljava/lang/Object;)Z
/*    */     //   660: goto -> 691
/*    */     //   663: aload #17
/*    */     //   665: instanceof java/lang/Character
/*    */     //   668: ifeq -> 684
/*    */     //   671: aload #17
/*    */     //   673: checkcast java/lang/Character
/*    */     //   676: aload #18
/*    */     //   678: invokestatic equalsCharObject : (Ljava/lang/Character;Ljava/lang/Object;)Z
/*    */     //   681: goto -> 691
/*    */     //   684: aload #17
/*    */     //   686: aload #18
/*    */     //   688: invokevirtual equals : (Ljava/lang/Object;)Z
/*    */     //   691: ifeq -> 1043
/*    */     //   694: aload_0
/*    */     //   695: invokevirtual _9 : ()Ljava/lang/Object;
/*    */     //   698: aload #27
/*    */     //   700: invokevirtual _9 : ()Ljava/lang/Object;
/*    */     //   703: astore #20
/*    */     //   705: dup
/*    */     //   706: astore #19
/*    */     //   708: aload #20
/*    */     //   710: if_acmpne -> 717
/*    */     //   713: iconst_1
/*    */     //   714: goto -> 775
/*    */     //   717: aload #19
/*    */     //   719: ifnonnull -> 726
/*    */     //   722: iconst_0
/*    */     //   723: goto -> 775
/*    */     //   726: aload #19
/*    */     //   728: instanceof java/lang/Number
/*    */     //   731: ifeq -> 747
/*    */     //   734: aload #19
/*    */     //   736: checkcast java/lang/Number
/*    */     //   739: aload #20
/*    */     //   741: invokestatic equalsNumObject : (Ljava/lang/Number;Ljava/lang/Object;)Z
/*    */     //   744: goto -> 775
/*    */     //   747: aload #19
/*    */     //   749: instanceof java/lang/Character
/*    */     //   752: ifeq -> 768
/*    */     //   755: aload #19
/*    */     //   757: checkcast java/lang/Character
/*    */     //   760: aload #20
/*    */     //   762: invokestatic equalsCharObject : (Ljava/lang/Character;Ljava/lang/Object;)Z
/*    */     //   765: goto -> 775
/*    */     //   768: aload #19
/*    */     //   770: aload #20
/*    */     //   772: invokevirtual equals : (Ljava/lang/Object;)Z
/*    */     //   775: ifeq -> 1043
/*    */     //   778: aload_0
/*    */     //   779: invokevirtual _10 : ()Ljava/lang/Object;
/*    */     //   782: aload #27
/*    */     //   784: invokevirtual _10 : ()Ljava/lang/Object;
/*    */     //   787: astore #22
/*    */     //   789: dup
/*    */     //   790: astore #21
/*    */     //   792: aload #22
/*    */     //   794: if_acmpne -> 801
/*    */     //   797: iconst_1
/*    */     //   798: goto -> 859
/*    */     //   801: aload #21
/*    */     //   803: ifnonnull -> 810
/*    */     //   806: iconst_0
/*    */     //   807: goto -> 859
/*    */     //   810: aload #21
/*    */     //   812: instanceof java/lang/Number
/*    */     //   815: ifeq -> 831
/*    */     //   818: aload #21
/*    */     //   820: checkcast java/lang/Number
/*    */     //   823: aload #22
/*    */     //   825: invokestatic equalsNumObject : (Ljava/lang/Number;Ljava/lang/Object;)Z
/*    */     //   828: goto -> 859
/*    */     //   831: aload #21
/*    */     //   833: instanceof java/lang/Character
/*    */     //   836: ifeq -> 852
/*    */     //   839: aload #21
/*    */     //   841: checkcast java/lang/Character
/*    */     //   844: aload #22
/*    */     //   846: invokestatic equalsCharObject : (Ljava/lang/Character;Ljava/lang/Object;)Z
/*    */     //   849: goto -> 859
/*    */     //   852: aload #21
/*    */     //   854: aload #22
/*    */     //   856: invokevirtual equals : (Ljava/lang/Object;)Z
/*    */     //   859: ifeq -> 1043
/*    */     //   862: aload_0
/*    */     //   863: invokevirtual _11 : ()Ljava/lang/Object;
/*    */     //   866: aload #27
/*    */     //   868: invokevirtual _11 : ()Ljava/lang/Object;
/*    */     //   871: astore #24
/*    */     //   873: dup
/*    */     //   874: astore #23
/*    */     //   876: aload #24
/*    */     //   878: if_acmpne -> 885
/*    */     //   881: iconst_1
/*    */     //   882: goto -> 943
/*    */     //   885: aload #23
/*    */     //   887: ifnonnull -> 894
/*    */     //   890: iconst_0
/*    */     //   891: goto -> 943
/*    */     //   894: aload #23
/*    */     //   896: instanceof java/lang/Number
/*    */     //   899: ifeq -> 915
/*    */     //   902: aload #23
/*    */     //   904: checkcast java/lang/Number
/*    */     //   907: aload #24
/*    */     //   909: invokestatic equalsNumObject : (Ljava/lang/Number;Ljava/lang/Object;)Z
/*    */     //   912: goto -> 943
/*    */     //   915: aload #23
/*    */     //   917: instanceof java/lang/Character
/*    */     //   920: ifeq -> 936
/*    */     //   923: aload #23
/*    */     //   925: checkcast java/lang/Character
/*    */     //   928: aload #24
/*    */     //   930: invokestatic equalsCharObject : (Ljava/lang/Character;Ljava/lang/Object;)Z
/*    */     //   933: goto -> 943
/*    */     //   936: aload #23
/*    */     //   938: aload #24
/*    */     //   940: invokevirtual equals : (Ljava/lang/Object;)Z
/*    */     //   943: ifeq -> 1043
/*    */     //   946: aload_0
/*    */     //   947: invokevirtual _12 : ()Ljava/lang/Object;
/*    */     //   950: aload #27
/*    */     //   952: invokevirtual _12 : ()Ljava/lang/Object;
/*    */     //   955: astore #26
/*    */     //   957: dup
/*    */     //   958: astore #25
/*    */     //   960: aload #26
/*    */     //   962: if_acmpne -> 969
/*    */     //   965: iconst_1
/*    */     //   966: goto -> 1027
/*    */     //   969: aload #25
/*    */     //   971: ifnonnull -> 978
/*    */     //   974: iconst_0
/*    */     //   975: goto -> 1027
/*    */     //   978: aload #25
/*    */     //   980: instanceof java/lang/Number
/*    */     //   983: ifeq -> 999
/*    */     //   986: aload #25
/*    */     //   988: checkcast java/lang/Number
/*    */     //   991: aload #26
/*    */     //   993: invokestatic equalsNumObject : (Ljava/lang/Number;Ljava/lang/Object;)Z
/*    */     //   996: goto -> 1027
/*    */     //   999: aload #25
/*    */     //   1001: instanceof java/lang/Character
/*    */     //   1004: ifeq -> 1020
/*    */     //   1007: aload #25
/*    */     //   1009: checkcast java/lang/Character
/*    */     //   1012: aload #26
/*    */     //   1014: invokestatic equalsCharObject : (Ljava/lang/Character;Ljava/lang/Object;)Z
/*    */     //   1017: goto -> 1027
/*    */     //   1020: aload #25
/*    */     //   1022: aload #26
/*    */     //   1024: invokevirtual equals : (Ljava/lang/Object;)Z
/*    */     //   1027: ifeq -> 1043
/*    */     //   1030: aload #27
/*    */     //   1032: aload_0
/*    */     //   1033: invokevirtual canEqual : (Ljava/lang/Object;)Z
/*    */     //   1036: ifeq -> 1043
/*    */     //   1039: iconst_1
/*    */     //   1040: goto -> 1044
/*    */     //   1043: iconst_0
/*    */     //   1044: ifeq -> 1051
/*    */     //   1047: iconst_1
/*    */     //   1048: goto -> 1052
/*    */     //   1051: iconst_0
/*    */     //   1052: ireturn
/*    */     // Line number table:
/*    */     //   Java source line number -> byte code offset
/*    */     //   #29	-> 0
/*    */     //   #236	-> 12
/*    */     //   #29	-> 19
/*    */     // Local variable table:
/*    */     //   start	length	slot	name	descriptor
/*    */     //   0	1053	0	this	Lscala/Tuple12;
/*    */     //   0	1053	1	x$1	Ljava/lang/Object;
/*    */   }
/*    */   
/*    */   public Tuple12(Object _1, Object _2, Object _3, Object _4, Object _5, Object _6, Object _7, Object _8, Object _9, Object _10, Object _11, Object _12) {
/* 29 */     Product$class.$init$(this);
/* 29 */     Product12$class.$init$(this);
/*    */   }
/*    */   
/*    */   public String toString() {
/* 33 */     return (new StringBuilder()).append("(").append(_1()).append(",").append(_2()).append(",").append(_3()).append(",").append(_4()).append(",").append(_5()).append(",").append(_6()).append(",").append(_7()).append(",").append(_8()).append(",").append(_9()).append(",").append(_10()).append(",").append(_11()).append(",").append(_12()).append(")").toString();
/*    */   }
/*    */ }


/* Location:              D:\#source-code\TheFlightSims\TFSLibrary\World2Xplane\World2XPlane.jar!\scala\Tuple12.class
 * Java compiler version: 6 (50.0)
 * JD-Core Version:       1.1.3
 */