/*    */ package scala;
/*    */ 
/*    */ import scala.collection.Iterator;
/*    */ import scala.collection.mutable.StringBuilder;
/*    */ import scala.reflect.ScalaSignature;
/*    */ import scala.runtime.ScalaRunTime$;
/*    */ 
/*    */ @ScalaSignature(bytes = "\006\001\035ed\001B\001\003\001\026\021q\001V;qY\026\024\004GC\001\004\003\025\0318-\0317b\007\001)RC\002\t\033;\001\032c%\013\0270eUB4HP!E\017*k\005kE\003\001\017-\021V\013\005\002\t\0235\t!!\003\002\013\005\t1\021I\\=SK\032\004b\003\003\007\0173qy\"%\n\025,]E\"tGO\037A\007\032KEjT\005\003\033\t\021\021\002\025:pIV\034GO\r\031\021\005=\001B\002\001\003\007#\001!)\031\001\n\003\005Q\013\024CA\n\027!\tAA#\003\002\026\005\t9aj\034;iS:<\007C\001\005\030\023\tA\"AA\002B]f\004\"a\004\016\005\rm\001AQ1\001\023\005\t!&\007\005\002\020;\0211a\004\001CC\002I\021!\001V\032\021\005=\001CAB\021\001\t\013\007!C\001\002UiA\021qb\t\003\007I\001!)\031\001\n\003\005Q+\004CA\b'\t\0319\003\001\"b\001%\t\021AK\016\t\003\037%\"aA\013\001\005\006\004\021\"A\001+8!\tyA\006\002\004.\001\021\025\rA\005\002\003)b\002\"aD\030\005\rA\002AQ1\001\023\005\t!\026\b\005\002\020e\02111\007\001CC\002I\0211\001V\0311!\tyQ\007\002\0047\001\021\025\rA\005\002\004)F\n\004CA\b9\t\031I\004\001\"b\001%\t\031A+\r\032\021\005=YDA\002\037\001\t\013\007!CA\002UcM\002\"a\004 \005\r}\002AQ1\001\023\005\r!\026\007\016\t\003\037\005#aA\021\001\005\006\004\021\"a\001+2kA\021q\002\022\003\007\013\002!)\031\001\n\003\007Q\013d\007\005\002\020\017\0221\001\n\001CC\002I\0211\001V\0318!\ty!\n\002\004L\001\021\025\rA\005\002\004)FB\004CA\bN\t\031q\005\001\"b\001%\t\031A+M\035\021\005=\001FAB)\001\t\013\007!CA\002UeA\002\"\001C*\n\005Q\023!a\002)s_\022,8\r\036\t\003\021YK!a\026\002\003\031M+'/[1mSj\f'\r\\3\t\021e\003!Q3A\005\002i\013!aX\031\026\0039A\001\002\030\001\003\022\003\006IAD\001\004?F\002\003\002\0030\001\005+\007I\021A0\002\005}\023T#A\r\t\021\005\004!\021#Q\001\ne\t1a\030\032!\021!\031\007A!f\001\n\003!\027AA04+\005a\002\002\0034\001\005#\005\013\021\002\017\002\007}\033\004\005\003\005i\001\tU\r\021\"\001j\003\tyF'F\001 \021!Y\007A!E!\002\023y\022aA05A!AQ\016\001BK\002\023\005a.\001\002`kU\t!\005\003\005q\001\tE\t\025!\003#\003\ryV\007\t\005\te\002\021)\032!C\001g\006\021qLN\013\002K!AQ\017\001B\tB\003%Q%A\002`m\001B\001b\036\001\003\026\004%\t\001_\001\003?^*\022\001\013\005\tu\002\021\t\022)A\005Q\005\031ql\016\021\t\021q\004!Q3A\005\002u\f!a\030\035\026\003-B\001b \001\003\022\003\006IaK\001\004?b\002\003BCA\002\001\tU\r\021\"\001\002\006\005\021q,O\013\002]!I\021\021\002\001\003\022\003\006IAL\001\004?f\002\003BCA\007\001\tU\r\021\"\001\002\020\005\031q,\r\031\026\003EB\021\"a\005\001\005#\005\013\021B\031\002\t}\013\004\007\t\005\013\003/\001!Q3A\005\002\005e\021aA02cU\tA\007C\005\002\036\001\021\t\022)A\005i\005!q,M\031!\021)\t\t\003\001BK\002\023\005\0211E\001\004?F\022T#A\034\t\023\005\035\002A!E!\002\0239\024\001B02e\001B!\"a\013\001\005+\007I\021AA\027\003\ry\026gM\013\002u!I\021\021\007\001\003\022\003\006IAO\001\005?F\032\004\005\003\006\0026\001\021)\032!C\001\003o\t1aX\0315+\005i\004\"CA\036\001\tE\t\025!\003>\003\021y\026\007\016\021\t\025\005}\002A!f\001\n\003\t\t%A\002`cU*\022\001\021\005\n\003\013\002!\021#Q\001\n\001\013AaX\0316A!Q\021\021\n\001\003\026\004%\t!a\023\002\007}\013d'F\001D\021%\ty\005\001B\tB\003%1)\001\003`cY\002\003BCA*\001\tU\r\021\"\001\002V\005\031q,M\034\026\003\031C\021\"!\027\001\005#\005\013\021\002$\002\t}\013t\007\t\005\013\003;\002!Q3A\005\002\005}\023aA02qU\t\021\nC\005\002d\001\021\t\022)A\005\023\006!q,\r\035!\021)\t9\007\001BK\002\023\005\021\021N\001\004?FJT#\001'\t\023\0055\004A!E!\002\023a\025\001B02s\001B!\"!\035\001\005+\007I\021AA:\003\ry&\007M\013\002\037\"I\021q\017\001\003\022\003\006IaT\001\005?J\002\004\005C\004\002|\001!\t!! \002\rqJg.\033;?))\ny(!!\002\004\006\025\025qQAE\003\027\013i)a$\002\022\006M\025QSAL\0033\013Y*!(\002 \006\005\0261UAS\003O\003b\003\003\001\0173qy\"%\n\025,]E\"tGO\037A\007\032KEj\024\005\0073\006e\004\031\001\b\t\ry\013I\b1\001\032\021\031\031\027\021\020a\0019!1\001.!\037A\002}Aa!\\A=\001\004\021\003B\002:\002z\001\007Q\005\003\004x\003s\002\r\001\013\005\007y\006e\004\031A\026\t\017\005\r\021\021\020a\001]!9\021QBA=\001\004\t\004bBA\f\003s\002\r\001\016\005\b\003C\tI\b1\0018\021\035\tY#!\037A\002iBq!!\016\002z\001\007Q\bC\004\002@\005e\004\031\001!\t\017\005%\023\021\020a\001\007\"9\0211KA=\001\0041\005bBA/\003s\002\r!\023\005\b\003O\nI\b1\001M\021\035\t\t(!\037A\002=Cq!a+\001\t\003\ni+\001\005u_N#(/\0338h)\t\ty\013\005\003\0022\006mVBAAZ\025\021\t),a.\002\t1\fgn\032\006\003\003s\013AA[1wC&!\021QXAZ\005\031\031FO]5oO\"I\021\021\031\001\002\002\023\005\0211Y\001\005G>\004\0300\006\026\002F\006-\027qZAj\003/\fY.a8\002d\006\035\0301^Ax\003g\f90a?\002\000\n\r!q\001B\006\005\037\021\031Ba\006\025U\005\035'\021\004B\016\005;\021yB!\t\003$\t\025\"q\005B\025\005W\021iCa\f\0032\tM\"Q\007B\034\005s\021YD!\020\003@AQ\003\002AAe\003\033\f\t.!6\002Z\006u\027\021]As\003S\fi/!=\002v\006e\030Q B\001\005\013\021IA!\004\003\022\tU\001cA\b\002L\0221\021#a0C\002I\0012aDAh\t\031Y\022q\030b\001%A\031q\"a5\005\ry\tyL1\001\023!\ry\021q\033\003\007C\005}&\031\001\n\021\007=\tY\016\002\004%\003\023\rA\005\t\004\037\005}GAB\024\002@\n\007!\003E\002\020\003G$aAKA`\005\004\021\002cA\b\002h\0221Q&a0C\002I\0012aDAv\t\031\001\024q\030b\001%A\031q\"a<\005\rM\nyL1\001\023!\ry\0211\037\003\007m\005}&\031\001\n\021\007=\t9\020\002\004:\003\023\rA\005\t\004\037\005mHA\002\037\002@\n\007!\003E\002\020\003$aaPA`\005\004\021\002cA\b\003\004\0211!)a0C\002I\0012a\004B\004\t\031)\025q\030b\001%A\031qBa\003\005\r!\013yL1\001\023!\ry!q\002\003\007\027\006}&\031\001\n\021\007=\021\031\002\002\004O\003\023\rA\005\t\004\037\t]AAB)\002@\n\007!\003C\005Z\003\003\n\0211\001\002J\"Ia,a0\021\002\003\007\021Q\032\005\nG\006}\006\023!a\001\003#D\021\002[A`!\003\005\r!!6\t\0235\fy\f%AA\002\005e\007\"\003:\002@B\005\t\031AAo\021%9\030q\030I\001\002\004\t\t\017C\005}\003\003\n\0211\001\002f\"Q\0211AA`!\003\005\r!!;\t\025\0055\021q\030I\001\002\004\ti\017\003\006\002\030\005}\006\023!a\001\003cD!\"!\t\002@B\005\t\031AA{\021)\tY#a0\021\002\003\007\021\021 \005\013\003k\ty\f%AA\002\005u\bBCA \003\003\n\0211\001\003\002!Q\021\021JA`!\003\005\rA!\002\t\025\005M\023q\030I\001\002\004\021I\001\003\006\002^\005}\006\023!a\001\005\033A!\"a\032\002@B\005\t\031\001B\t\021)\t\t(a0\021\002\003\007!Q\003\005\n\005\007\002\021\023!C\001\005\013\nabY8qs\022\"WMZ1vYR$\023'\006\026\003H\tu#q\fB1\005G\022)Ga\032\003j\t-$Q\016B8\005c\022\031H!\036\003x\te$1\020B?\005\022\tIa!\026\005\t%#f\001\b\003L-\022!Q\n\t\005\005\037\022I&\004\002\003R)!!1\013B+\003%)hn\0315fG.,GMC\002\003X\t\t!\"\0318o_R\fG/[8o\023\021\021YF!\025\003#Ut7\r[3dW\026$g+\031:jC:\034W\r\002\004\022\005\003\022\rA\005\003\0077\t\005#\031\001\n\005\ry\021\tE1\001\023\t\031\t#\021\tb\001%\0211AE!\021C\002I!aa\nB!\005\004\021BA\002\026\003B\t\007!\003\002\004.\005\003\022\rA\005\003\007a\t\005#\031\001\n\005\rM\022\tE1\001\023\t\0311$\021\tb\001%\0211\021H!\021C\002I!a\001\020B!\005\004\021BAB \003B\t\007!\003\002\004C\005\003\022\rA\005\003\007\013\n\005#\031\001\n\005\r!\023\tE1\001\023\t\031Y%\021\tb\001%\0211aJ!\021C\002I!a!\025B!\005\004\021\002\"\003BD\001E\005I\021\001BE\0039\031w\016]=%I\0264\027-\0367uII*\"Fa#\003\020\nE%1\023BK\005/\023IJa'\003\036\n}%\021\025BR\005K\0239K!+\003,\n5&q\026BY\005g\023),\006\002\003\016*\032\021Da\023\005\rE\021)I1\001\023\t\031Y\"Q\021b\001%\0211aD!\"C\002I!a!\tBC\005\004\021BA\002\023\003\006\n\007!\003\002\004(\005\013\023\rA\005\003\007U\t\025%\031\001\n\005\r5\022)I1\001\023\t\031\001$Q\021b\001%\02111G!\"C\002I!aA\016BC\005\004\021BAB\035\003\006\n\007!\003\002\004=\005\013\023\rA\005\003\007\t\025%\031\001\n\005\r\t\023)I1\001\023\t\031)%Q\021b\001%\0211\001J!\"C\002I!aa\023BC\005\004\021BA\002(\003\006\n\007!\003\002\004R\005\013\023\rA\005\005\n\005s\003\021\023!C\001\005w\013abY8qs\022\"WMZ1vYR$3'\006\026\003>\n\005'1\031Bc\005\017\024IMa3\003N\n='\021\033Bj\005+\0249N!7\003\\\nu'q\034Bq\005G\024)Oa:\026\005\t}&f\001\017\003L\0211\021Ca.C\002I!aa\007B\\\005\004\021BA\002\020\0038\n\007!\003\002\004\"\005o\023\rA\005\003\007I\t]&\031\001\n\005\r\035\0229L1\001\023\t\031Q#q\027b\001%\0211QFa.C\002I!a\001\rB\\\005\004\021BAB\032\0038\n\007!\003\002\0047\005o\023\rA\005\003\007s\t]&\031\001\n\005\rq\0229L1\001\023\t\031y$q\027b\001%\0211!Ia.C\002I!a!\022B\\\005\004\021BA\002%\0038\n\007!\003\002\004L\005o\023\rA\005\003\007\035\n]&\031\001\n\005\rE\0239L1\001\023\021%\021Y\017AI\001\n\003\021i/\001\bd_BLH\005Z3gCVdG\017\n\033\026U\t=(1\037B{\005o\024IPa?\003~\n}8\021AB\002\007\013\0319a!\003\004\f\r51qBB\t\007'\031)ba\006\004\032U\021!\021\037\026\004?\t-CAB\t\003j\n\007!\003\002\004\034\005S\024\rA\005\003\007=\t%(\031\001\n\005\r\005\022IO1\001\023\t\031!#\021\036b\001%\0211qE!;C\002I!aA\013Bu\005\004\021BAB\027\003j\n\007!\003\002\0041\005S\024\rA\005\003\007g\t%(\031\001\n\005\rY\022IO1\001\023\t\031I$\021\036b\001%\0211AH!;C\002I!aa\020Bu\005\004\021BA\002\"\003j\n\007!\003\002\004F\005S\024\rA\005\003\007\021\n%(\031\001\n\005\r-\023IO1\001\023\t\031q%\021\036b\001%\0211\021K!;C\002IA\021b!\b\001#\003%\taa\b\002\035\r|\007/\037\023eK\032\fW\017\034;%kUQ3\021EB\023\007O\031Ica\013\004.\r=2\021GB\032\007k\0319d!\017\004<\ru2qHB!\007\007\032)ea\022\004J\r-SCAB\022U\r\021#1\n\003\007#\rm!\031\001\n\005\rm\031YB1\001\023\t\031q21\004b\001%\0211\021ea\007C\002I!a\001JB\016\005\004\021BAB\024\004\034\t\007!\003\002\004+\0077\021\rA\005\003\007[\rm!\031\001\n\005\rA\032YB1\001\023\t\031\03141\004b\001%\0211aga\007C\002I!a!OB\016\005\004\021BA\002\037\004\034\t\007!\003\002\004@\0077\021\rA\005\003\007\005\016m!\031\001\n\005\r\025\033YB1\001\023\t\031A51\004b\001%\02111ja\007C\002I!aATB\016\005\004\021BAB)\004\034\t\007!\003C\005\004P\001\t\n\021\"\001\004R\005q1m\0349zI\021,g-Y;mi\0222TCKB*\007/\032Ifa\027\004^\r}3\021MB2\007K\0329g!\033\004l\r54qNB9\007g\032)ha\036\004z\rm4QP\013\003\007+R3!\nB&\t\031\t2Q\nb\001%\02111d!\024C\002I!aAHB'\005\004\021BAB\021\004N\t\007!\003\002\004%\007\033\022\rA\005\003\007O\r5#\031\001\n\005\r)\032iE1\001\023\t\031i3Q\nb\001%\0211\001g!\024C\002I!aaMB'\005\004\021BA\002\034\004N\t\007!\003\002\004:\007\033\022\rA\005\003\007y\r5#\031\001\n\005\r}\032iE1\001\023\t\031\0215Q\nb\001%\0211Qi!\024C\002I!a\001SB'\005\004\021BAB&\004N\t\007!\003\002\004O\007\033\022\rA\005\003\007#\0165#\031\001\n\t\023\r\005\005!%A\005\002\r\r\025AD2paf$C-\0324bk2$HeN\013+\007\013\033Iia#\004\016\016=5\021SBJ\007+\0339j!'\004\034\016u5qTBQ\007G\033)ka*\004*\016-6QVBX+\t\0319IK\002)\005\027\"a!EB@\005\004\021BAB\016\004\000\t\007!\003\002\004\037\007\022\rA\005\003\007C\r}$\031\001\n\005\r\021\032yH1\001\023\t\03193q\020b\001%\0211!fa C\002I!a!LB@\005\004\021BA\002\031\004\000\t\007!\003\002\0044\007\022\rA\005\003\007m\r}$\031\001\n\005\re\032yH1\001\023\t\031a4q\020b\001%\0211qha C\002I!aAQB@\005\004\021BAB#\004\000\t\007!\003\002\004I\007\022\rA\005\003\007\027\016}$\031\001\n\005\r9\033yH1\001\023\t\031\t6q\020b\001%!I11\027\001\022\002\023\0051QW\001\017G>\004\030\020\n3fM\006,H\016\036\0239+)\0329la/\004>\016}6\021YBb\007\013\0349m!3\004L\01657qZBi\007'\034)na6\004Z\016m7Q\\Bp\007C,\"a!/+\007-\022Y\005\002\004\022\007c\023\rA\005\003\0077\rE&\031\001\n\005\ry\031\tL1\001\023\t\031\t3\021\027b\001%\0211Ae!-C\002I!aaJBY\005\004\021BA\002\026\0042\n\007!\003\002\004.\007c\023\rA\005\003\007a\rE&\031\001\n\005\rM\032\tL1\001\023\t\03114\021\027b\001%\0211\021h!-C\002I!a\001PBY\005\004\021BAB \0042\n\007!\003\002\004C\007c\023\rA\005\003\007\013\016E&\031\001\n\005\r!\033\tL1\001\023\t\031Y5\021\027b\001%\0211aj!-C\002I!a!UBY\005\004\021\002\"CBs\001E\005I\021ABt\0039\031w\016]=%I\0264\027-\0367uIe*\"f!;\004n\016=8\021_Bz\007k\0349p!?\004|\016u8q C\001\t\007!)\001b\002\005\n\021-AQ\002C\b\t#!\031\"\006\002\004l*\032aFa\023\005\rE\031\031O1\001\023\t\031Y21\035b\001%\0211ada9C\002I!a!IBr\005\004\021BA\002\023\004d\n\007!\003\002\004(\007G\024\rA\005\003\007U\r\r(\031\001\n\005\r5\032\031O1\001\023\t\031\00141\035b\001%\02111ga9C\002I!aANBr\005\004\021BAB\035\004d\n\007!\003\002\004=\007G\024\rA\005\003\007\r\r(\031\001\n\005\r\t\033\031O1\001\023\t\031)51\035b\001%\0211\001ja9C\002I!aaSBr\005\004\021BA\002(\004d\n\007!\003\002\004R\007G\024\rA\005\005\n\t/\001\021\023!C\001\t3\tqbY8qs\022\"WMZ1vYR$\023\007M\013+\t7!y\002\"\t\005$\021\025Bq\005C\025\tW!i\003b\f\0052\021MBQ\007C\034\ts!Y\004\"\020\005@\021\005C1\tC#+\t!iBK\0022\005\027\"a!\005C\013\005\004\021BAB\016\005\026\t\007!\003\002\004\037\t+\021\rA\005\003\007C\021U!\031\001\n\005\r\021\")B1\001\023\t\0319CQ\003b\001%\0211!\006\"\006C\002I!a!\fC\013\005\004\021BA\002\031\005\026\t\007!\003\002\0044\t+\021\rA\005\003\007m\021U!\031\001\n\005\re\")B1\001\023\t\031aDQ\003b\001%\0211q\b\"\006C\002I!aA\021C\013\005\004\021BAB#\005\026\t\007!\003\002\004I\t+\021\rA\005\003\007\027\022U!\031\001\n\005\r9#)B1\001\023\t\031\tFQ\003b\001%!IA\021\n\001\022\002\023\005A1J\001\020G>\004\030\020\n3fM\006,H\016\036\0232cUQCQ\nC)\t'\")\006b\026\005Z\021mCQ\fC0\tC\"\031\007\"\032\005h\021%D1\016C7\t_\"\t\bb\035\005v\021]TC\001C(U\r!$1\n\003\007#\021\035#\031\001\n\005\rm!9E1\001\023\t\031qBq\tb\001%\0211\021\005b\022C\002I!a\001\nC$\005\004\021BAB\024\005H\t\007!\003\002\004+\t\017\022\rA\005\003\007[\021\035#\031\001\n\005\rA\"9E1\001\023\t\031\031Dq\tb\001%\0211a\007b\022C\002I!a!\017C$\005\004\021BA\002\037\005H\t\007!\003\002\004@\t\017\022\rA\005\003\007\005\022\035#\031\001\n\005\r\025#9E1\001\023\t\031AEq\tb\001%\02111\nb\022C\002I!aA\024C$\005\004\021BAB)\005H\t\007!\003C\005\005|\001\t\n\021\"\001\005~\005y1m\0349zI\021,g-Y;mi\022\n$'\006\026\005\000\021\rEQ\021CD\t\023#Y\t\"$\005\020\022EE1\023CK\t/#I\nb'\005\036\022}E\021\025CR\tK#9\013\"+\026\005\021\005%fA\034\003L\0211\021\003\"\037C\002I!aa\007C=\005\004\021BA\002\020\005z\t\007!\003\002\004\"\ts\022\rA\005\003\007I\021e$\031\001\n\005\r\035\"IH1\001\023\t\031QC\021\020b\001%\0211Q\006\"\037C\002I!a\001\rC=\005\004\021BAB\032\005z\t\007!\003\002\0047\ts\022\rA\005\003\007s\021e$\031\001\n\005\rq\"IH1\001\023\t\031yD\021\020b\001%\0211!\t\"\037C\002I!a!\022C=\005\004\021BA\002%\005z\t\007!\003\002\004L\ts\022\rA\005\003\007\035\022e$\031\001\n\005\rE#IH1\001\023\021%!i\013AI\001\n\003!y+A\bd_BLH\005Z3gCVdG\017J\0314+)\"\t\f\".\0058\022eF1\030C_\t#\t\rb1\005F\022\035G\021\032Cf\t\033$y\r\"5\005T\022UGq\033Cm\t7,\"\001b-+\007i\022Y\005\002\004\022\tW\023\rA\005\003\0077\021-&\031\001\n\005\ry!YK1\001\023\t\031\tC1\026b\001%\0211A\005b+C\002I!aa\nCV\005\004\021BA\002\026\005,\n\007!\003\002\004.\tW\023\rA\005\003\007a\021-&\031\001\n\005\rM\"YK1\001\023\t\0311D1\026b\001%\0211\021\bb+C\002I!a\001\020CV\005\004\021BAB \005,\n\007!\003\002\004C\tW\023\rA\005\003\007\013\022-&\031\001\n\005\r!#YK1\001\023\t\031YE1\026b\001%\0211a\nb+C\002I!a!\025CV\005\004\021\002\"\003Cp\001E\005I\021\001Cq\003=\031w\016]=%I\0264\027-\0367uIE\"TC\013Cr\tO$I\017b;\005n\022=H\021\037Cz\tk$9\020\"?\005|\022uHq`C\001\013\007))!b\002\006\n\025-QQB\013\003\tKT3!\020B&\t\031\tBQ\034b\001%\02111\004\"8C\002I!aA\bCo\005\004\021BAB\021\005^\n\007!\003\002\004%\t;\024\rA\005\003\007O\021u'\031\001\n\005\r)\"iN1\001\023\t\031iCQ\034b\001%\0211\001\007\"8C\002I!aa\rCo\005\004\021BA\002\034\005^\n\007!\003\002\004:\t;\024\rA\005\003\007y\021u'\031\001\n\005\r}\"iN1\001\023\t\031\021EQ\034b\001%\0211Q\t\"8C\002I!a\001\023Co\005\004\021BAB&\005^\n\007!\003\002\004O\t;\024\rA\005\003\007#\022u'\031\001\n\t\023\025E\001!%A\005\002\025M\021aD2paf$C-\0324bk2$H%M\033\026U\025UQ\021DC\016\013;)y\"\"\t\006$\025\025RqEC\025\013W)i#b\f\0062\025MRQGC\034\013s)Y$\"\020\006@U\021Qq\003\026\004\001\n-CAB\t\006\020\t\007!\003\002\004\034\013\037\021\rA\005\003\007=\025=!\031\001\n\005\r\005*yA1\001\023\t\031!Sq\002b\001%\0211q%b\004C\002I!aAKC\b\005\004\021BAB\027\006\020\t\007!\003\002\0041\013\037\021\rA\005\003\007g\025=!\031\001\n\005\rY*yA1\001\023\t\031ITq\002b\001%\0211A(b\004C\002I!aaPC\b\005\004\021BA\002\"\006\020\t\007!\003\002\004F\013\037\021\rA\005\003\007\021\026=!\031\001\n\005\r-+yA1\001\023\t\031qUq\002b\001%\0211\021+b\004C\002IA\021\"b\021\001#\003%\t!\"\022\002\037\r|\007/\037\023eK\032\fW\017\034;%cY*\"&b\022\006L\0255SqJC)\013'*)&b\026\006Z\025mSQLC0\013C*\031'\"\032\006h\025%T1NC7\013_*\t(\006\002\006J)\0321Ia\023\005\rE)\tE1\001\023\t\031YR\021\tb\001%\0211a$\"\021C\002I!a!IC!\005\004\021BA\002\023\006B\t\007!\003\002\004(\013\003\022\rA\005\003\007U\025\005#\031\001\n\005\r5*\tE1\001\023\t\031\001T\021\tb\001%\02111'\"\021C\002I!aANC!\005\004\021BAB\035\006B\t\007!\003\002\004=\013\003\022\rA\005\003\007\025\005#\031\001\n\005\r\t+\tE1\001\023\t\031)U\021\tb\001%\0211\001*\"\021C\002I!aaSC!\005\004\021BA\002(\006B\t\007!\003\002\004R\013\003\022\rA\005\005\n\013k\002\021\023!C\001\013o\nqbY8qs\022\"WMZ1vYR$\023gN\013+\013s*i(b \006\002\026\rUQQCD\013\023+Y)\"$\006\020\026EU1SCK\013/+I*b'\006\036\026}U\021UCR+\t)YHK\002G\005\027\"a!EC:\005\004\021BAB\016\006t\t\007!\003\002\004\037\013g\022\rA\005\003\007C\025M$\031\001\n\005\r\021*\031H1\001\023\t\0319S1\017b\001%\0211!&b\035C\002I!a!LC:\005\004\021BA\002\031\006t\t\007!\003\002\0044\013g\022\rA\005\003\007m\025M$\031\001\n\005\re*\031H1\001\023\t\031aT1\017b\001%\0211q(b\035C\002I!aAQC:\005\004\021BAB#\006t\t\007!\003\002\004I\013g\022\rA\005\003\007\027\026M$\031\001\n\005\r9+\031H1\001\023\t\031\tV1\017b\001%!IQq\025\001\022\002\023\005Q\021V\001\020G>\004\030\020\n3fM\006,H\016\036\0232qUQS1VCX\013c+\031,\".\0068\026eV1XC_\013+\t-b1\006F\026\035W\021ZCf\013\033,y-\"5\006T\026UWCACWU\rI%1\n\003\007#\025\025&\031\001\n\005\rm))K1\001\023\t\031qRQ\025b\001%\0211\021%\"*C\002I!a\001JCS\005\004\021BAB\024\006&\n\007!\003\002\004+\013K\023\rA\005\003\007[\025\025&\031\001\n\005\rA*)K1\001\023\t\031\031TQ\025b\001%\0211a'\"*C\002I!a!OCS\005\004\021BA\002\037\006&\n\007!\003\002\004@\013K\023\rA\005\003\007\005\026\025&\031\001\n\005\r\025+)K1\001\023\t\031AUQ\025b\001%\02111*\"*C\002I!aATCS\005\004\021BAB)\006&\n\007!\003C\005\006Z\002\t\n\021\"\001\006\\\006y1m\0349zI\021,g-Y;mi\022\n\024(\006\026\006^\026\005X1]Cs\013O,I/b;\006n\026=X\021_Cz\013k,90\"?\006|\026uXq D\001\r\0071)Ab\002\026\005\025}'f\001'\003L\0211\021#b6C\002I!aaGCl\005\004\021BA\002\020\006X\n\007!\003\002\004\"\013/\024\rA\005\003\007I\025]'\031\001\n\005\r\035*9N1\001\023\t\031QSq\033b\001%\0211Q&b6C\002I!a\001MCl\005\004\021BAB\032\006X\n\007!\003\002\0047\013/\024\rA\005\003\007s\025]'\031\001\n\005\rq*9N1\001\023\t\031yTq\033b\001%\0211!)b6C\002I!a!RCl\005\004\021BA\002%\006X\n\007!\003\002\004L\013/\024\rA\005\003\007\035\026]'\031\001\n\005\rE+9N1\001\023\021%1Y\001AI\001\n\0031i!A\bd_BLH\005Z3gCVdG\017\n\0321+)2yAb\005\007\026\031]a\021\004D\016\r;1yB\"\t\007$\031\025bq\005D\025\rW1iCb\f\0072\031MbQ\007D\034\rs)\"A\"\005+\007=\023Y\005\002\004\022\r\023\021\rA\005\003\0077\031%!\031\001\n\005\ry1IA1\001\023\t\031\tc\021\002b\001%\0211AE\"\003C\002I!aa\nD\005\005\004\021BA\002\026\007\n\t\007!\003\002\004.\r\023\021\rA\005\003\007a\031%!\031\001\n\005\rM2IA1\001\023\t\0311d\021\002b\001%\0211\021H\"\003C\002I!a\001\020D\005\005\004\021BAB \007\n\t\007!\003\002\004C\r\023\021\rA\005\003\007\013\032%!\031\001\n\005\r!3IA1\001\023\t\031Ye\021\002b\001%\0211aJ\"\003C\002I!a!\025D\005\005\004\021\002\"\003D\037\001\005\005I\021\tD \0035\001(o\0343vGR\004&/\0324jqV\021\021q\026\005\n\r\007\002\021\021!C!\r\013\nq\002\035:pIV\034G/\023;fe\006$xN]\013\003\r\017\002RA\"\023\007PYi!Ab\023\013\007\0315#!\001\006d_2dWm\031;j_:LAA\"\025\007L\tA\021\n^3sCR|'\017C\005\007V\001\t\t\021\"\001\007X\005A1-\0318FcV\fG\016\006\003\007Z\031}\003c\001\005\007\\%\031aQ\f\002\003\017\t{w\016\\3b]\"Ia\021\rD*\003\003\005\rAF\001\004q\022\n\004\"\003D3\001\005\005I\021\tD4\003!A\027m\0355D_\022,GC\001D5!\rAa1N\005\004\r[\022!aA%oi\"Ia\021\017\001\002\002\023\005c1O\001\007KF,\030\r\\:\025\t\031ecQ\017\005\n\rC2y'!AA\002Y9\021B\"\037\003\003\003E\tAb\037\002\017Q+\b\017\\33aA\031\001B\" \007\021\005\021\021\021!E\001\r\032BA\" \b+\"A\0211\020D?\t\0031\031\t\006\002\007|!Q\0211\026D?\003\003%)%!,\t\025\031%eQPA\001\n\0033Y)A\003baBd\0270\006\026\007\016\032Meq\023DN\r?3\031Kb*\007,\032=f1\027D\\\rw3yLb1\007H\032-gq\032Dj\r/4YNb8\025U\031=e\021\035Dr\rK49O\";\007l\0325hq\036Dy\rg4)Pb>\007z\032mhQ D\000\017\0039\031a\"\002\b\bAQ\003\002\001DI\r+3IJ\"(\007\"\032\025f\021\026DW\rc3)L\"/\007>\032\005gQ\031De\r\0334\tN\"6\007Z\032u\007cA\b\007\024\0221\021Cb\"C\002I\0012a\004DL\t\031Ybq\021b\001%A\031qBb'\005\ry19I1\001\023!\ryaq\024\003\007C\031\035%\031\001\n\021\007=1\031\013\002\004%\r\017\023\rA\005\t\004\037\031\035FAB\024\007\b\n\007!\003E\002\020\rW#aA\013DD\005\004\021\002cA\b\0070\0221QFb\"C\002I\0012a\004DZ\t\031\001dq\021b\001%A\031qBb.\005\rM29I1\001\023!\rya1\030\003\007m\031\035%\031\001\n\021\007=1y\f\002\004:\r\017\023\rA\005\t\004\037\031\rGA\002\037\007\b\n\007!\003E\002\020\r\017$aa\020DD\005\004\021\002cA\b\007L\0221!Ib\"C\002I\0012a\004Dh\t\031)eq\021b\001%A\031qBb5\005\r!39I1\001\023!\ryaq\033\003\007\027\032\035%\031\001\n\021\007=1Y\016\002\004O\r\017\023\rA\005\t\004\037\031}GAB)\007\b\n\007!\003C\004Z\r\017\003\rA\"%\t\017y39\t1\001\007\026\"91Mb\"A\002\031e\005b\0025\007\b\002\007aQ\024\005\b[\032\035\005\031\001DQ\021\035\021hq\021a\001\rKCqa\036DD\001\0041I\013C\004}\r\017\003\rA\",\t\021\005\raq\021a\001\rcC\001\"!\004\007\b\002\007aQ\027\005\t\003/19\t1\001\007:\"A\021\021\005DD\001\0041i\f\003\005\002,\031\035\005\031\001Da\021!\t)Db\"A\002\031\025\007\002CA \r\017\003\rA\"3\t\021\005%cq\021a\001\r\033D\001\"a\025\007\b\002\007a\021\033\005\t\003;29\t1\001\007V\"A\021q\rDD\001\0041I\016\003\005\002r\031\035\005\031\001Do\021)9YA\" \002\002\023\005uQB\001\bk:\f\007\017\0357z+):yab\007\b \035\rrqED\026\017_9\031db\016\b<\035}r1ID$\017\027:yeb\025\bX\035msqLD2\017O\"Ba\"\005\bjA)\001bb\005\b\030%\031qQ\003\002\003\r=\003H/[8o!)B\001a\"\007\b\036\035\005rQED\025\017[9\td\"\016\b:\035ur\021ID#\017\023:ie\"\025\bV\035esQLD1\017K\0022aDD\016\t\031\tr\021\002b\001%A\031qbb\b\005\rm9IA1\001\023!\ryq1\005\003\007=\035%!\031\001\n\021\007=99\003\002\004\"\017\023\021\rA\005\t\004\037\035-BA\002\023\b\n\t\007!\003E\002\020\017_!aaJD\005\005\004\021\002cA\b\b4\0211!f\"\003C\002I\0012aDD\034\t\031is\021\002b\001%A\031qbb\017\005\rA:IA1\001\023!\ryqq\b\003\007g\035%!\031\001\n\021\007=9\031\005\002\0047\017\023\021\rA\005\t\004\037\035\035CAB\035\b\n\t\007!\003E\002\020\017\027\"a\001PD\005\005\004\021\002cA\b\bP\0211qh\"\003C\002I\0012aDD*\t\031\021u\021\002b\001%A\031qbb\026\005\r\025;IA1\001\023!\ryq1\f\003\007\021\036%!\031\001\n\021\007=9y\006\002\004L\017\023\021\rA\005\t\004\037\035\rDA\002(\b\n\t\007!\003E\002\020\017O\"a!UD\005\005\004\021\002BCD6\017\023\t\t\0211\001\b\030\005\031\001\020\n\031\t\025\035=dQPA\001\n\0239\t(A\006sK\006$'+Z:pYZ,GCAD:!\021\t\tl\"\036\n\t\035]\0241\027\002\007\037\nTWm\031;")
/*    */ public class Tuple20<T1, T2, T3, T4, T5, T6, T7, T8, T9, T10, T11, T12, T13, T14, T15, T16, T17, T18, T19, T20> implements Product20<T1, T2, T3, T4, T5, T6, T7, T8, T9, T10, T11, T12, T13, T14, T15, T16, T17, T18, T19, T20>, Product, Serializable {
/*    */   private final T1 _1;
/*    */   
/*    */   private final T2 _2;
/*    */   
/*    */   private final T3 _3;
/*    */   
/*    */   private final T4 _4;
/*    */   
/*    */   private final T5 _5;
/*    */   
/*    */   private final T6 _6;
/*    */   
/*    */   private final T7 _7;
/*    */   
/*    */   private final T8 _8;
/*    */   
/*    */   private final T9 _9;
/*    */   
/*    */   private final T10 _10;
/*    */   
/*    */   private final T11 _11;
/*    */   
/*    */   private final T12 _12;
/*    */   
/*    */   private final T13 _13;
/*    */   
/*    */   private final T14 _14;
/*    */   
/*    */   private final T15 _15;
/*    */   
/*    */   private final T16 _16;
/*    */   
/*    */   private final T17 _17;
/*    */   
/*    */   private final T18 _18;
/*    */   
/*    */   private final T19 _19;
/*    */   
/*    */   private final T20 _20;
/*    */   
/*    */   public int productArity() {
/* 37 */     return Product20$class.productArity(this);
/*    */   }
/*    */   
/*    */   public Object productElement(int n) throws IndexOutOfBoundsException {
/* 37 */     return Product20$class.productElement(this, n);
/*    */   }
/*    */   
/*    */   public T1 _1() {
/* 37 */     return this._1;
/*    */   }
/*    */   
/*    */   public T2 _2() {
/* 37 */     return this._2;
/*    */   }
/*    */   
/*    */   public T3 _3() {
/* 37 */     return this._3;
/*    */   }
/*    */   
/*    */   public T4 _4() {
/* 37 */     return this._4;
/*    */   }
/*    */   
/*    */   public T5 _5() {
/* 37 */     return this._5;
/*    */   }
/*    */   
/*    */   public T6 _6() {
/* 37 */     return this._6;
/*    */   }
/*    */   
/*    */   public T7 _7() {
/* 37 */     return this._7;
/*    */   }
/*    */   
/*    */   public T8 _8() {
/* 37 */     return this._8;
/*    */   }
/*    */   
/*    */   public T9 _9() {
/* 37 */     return this._9;
/*    */   }
/*    */   
/*    */   public T10 _10() {
/* 37 */     return this._10;
/*    */   }
/*    */   
/*    */   public T11 _11() {
/* 37 */     return this._11;
/*    */   }
/*    */   
/*    */   public T12 _12() {
/* 37 */     return this._12;
/*    */   }
/*    */   
/*    */   public T13 _13() {
/* 37 */     return this._13;
/*    */   }
/*    */   
/*    */   public T14 _14() {
/* 37 */     return this._14;
/*    */   }
/*    */   
/*    */   public T15 _15() {
/* 37 */     return this._15;
/*    */   }
/*    */   
/*    */   public T16 _16() {
/* 37 */     return this._16;
/*    */   }
/*    */   
/*    */   public T17 _17() {
/* 37 */     return this._17;
/*    */   }
/*    */   
/*    */   public T18 _18() {
/* 37 */     return this._18;
/*    */   }
/*    */   
/*    */   public T19 _19() {
/* 37 */     return this._19;
/*    */   }
/*    */   
/*    */   public T20 _20() {
/* 37 */     return this._20;
/*    */   }
/*    */   
/*    */   public <T1, T2, T3, T4, T5, T6, T7, T8, T9, T10, T11, T12, T13, T14, T15, T16, T17, T18, T19, T20> Tuple20<T1, T2, T3, T4, T5, T6, T7, T8, T9, T10, T11, T12, T13, T14, T15, T16, T17, T18, T19, T20> copy(Object _1, Object _2, Object _3, Object _4, Object _5, Object _6, Object _7, Object _8, Object _9, Object _10, Object _11, Object _12, Object _13, Object _14, Object _15, Object _16, Object _17, Object _18, Object _19, Object _20) {
/* 37 */     return new Tuple20((T1)_1, (T2)_2, (T3)_3, (T4)_4, (T5)_5, (T6)_6, (T7)_7, (T8)_8, (T9)_9, (T10)_10, (T11)_11, (T12)_12, (T13)_13, (T14)_14, (T15)_15, (T16)_16, (T17)_17, (T18)_18, (T19)_19, (T20)_20);
/*    */   }
/*    */   
/*    */   public <T1, T2, T3, T4, T5, T6, T7, T8, T9, T10, T11, T12, T13, T14, T15, T16, T17, T18, T19, T20> T1 copy$default$1() {
/* 37 */     return _1();
/*    */   }
/*    */   
/*    */   public <T1, T2, T3, T4, T5, T6, T7, T8, T9, T10, T11, T12, T13, T14, T15, T16, T17, T18, T19, T20> T2 copy$default$2() {
/* 37 */     return _2();
/*    */   }
/*    */   
/*    */   public <T1, T2, T3, T4, T5, T6, T7, T8, T9, T10, T11, T12, T13, T14, T15, T16, T17, T18, T19, T20> T3 copy$default$3() {
/* 37 */     return _3();
/*    */   }
/*    */   
/*    */   public <T1, T2, T3, T4, T5, T6, T7, T8, T9, T10, T11, T12, T13, T14, T15, T16, T17, T18, T19, T20> T4 copy$default$4() {
/* 37 */     return _4();
/*    */   }
/*    */   
/*    */   public <T1, T2, T3, T4, T5, T6, T7, T8, T9, T10, T11, T12, T13, T14, T15, T16, T17, T18, T19, T20> T5 copy$default$5() {
/* 37 */     return _5();
/*    */   }
/*    */   
/*    */   public <T1, T2, T3, T4, T5, T6, T7, T8, T9, T10, T11, T12, T13, T14, T15, T16, T17, T18, T19, T20> T6 copy$default$6() {
/* 37 */     return _6();
/*    */   }
/*    */   
/*    */   public <T1, T2, T3, T4, T5, T6, T7, T8, T9, T10, T11, T12, T13, T14, T15, T16, T17, T18, T19, T20> T7 copy$default$7() {
/* 37 */     return _7();
/*    */   }
/*    */   
/*    */   public <T1, T2, T3, T4, T5, T6, T7, T8, T9, T10, T11, T12, T13, T14, T15, T16, T17, T18, T19, T20> T8 copy$default$8() {
/* 37 */     return _8();
/*    */   }
/*    */   
/*    */   public <T1, T2, T3, T4, T5, T6, T7, T8, T9, T10, T11, T12, T13, T14, T15, T16, T17, T18, T19, T20> T9 copy$default$9() {
/* 37 */     return _9();
/*    */   }
/*    */   
/*    */   public <T1, T2, T3, T4, T5, T6, T7, T8, T9, T10, T11, T12, T13, T14, T15, T16, T17, T18, T19, T20> T10 copy$default$10() {
/* 37 */     return _10();
/*    */   }
/*    */   
/*    */   public <T1, T2, T3, T4, T5, T6, T7, T8, T9, T10, T11, T12, T13, T14, T15, T16, T17, T18, T19, T20> T11 copy$default$11() {
/* 37 */     return _11();
/*    */   }
/*    */   
/*    */   public <T1, T2, T3, T4, T5, T6, T7, T8, T9, T10, T11, T12, T13, T14, T15, T16, T17, T18, T19, T20> T12 copy$default$12() {
/* 37 */     return _12();
/*    */   }
/*    */   
/*    */   public <T1, T2, T3, T4, T5, T6, T7, T8, T9, T10, T11, T12, T13, T14, T15, T16, T17, T18, T19, T20> T13 copy$default$13() {
/* 37 */     return _13();
/*    */   }
/*    */   
/*    */   public <T1, T2, T3, T4, T5, T6, T7, T8, T9, T10, T11, T12, T13, T14, T15, T16, T17, T18, T19, T20> T14 copy$default$14() {
/* 37 */     return _14();
/*    */   }
/*    */   
/*    */   public <T1, T2, T3, T4, T5, T6, T7, T8, T9, T10, T11, T12, T13, T14, T15, T16, T17, T18, T19, T20> T15 copy$default$15() {
/* 37 */     return _15();
/*    */   }
/*    */   
/*    */   public <T1, T2, T3, T4, T5, T6, T7, T8, T9, T10, T11, T12, T13, T14, T15, T16, T17, T18, T19, T20> T16 copy$default$16() {
/* 37 */     return _16();
/*    */   }
/*    */   
/*    */   public <T1, T2, T3, T4, T5, T6, T7, T8, T9, T10, T11, T12, T13, T14, T15, T16, T17, T18, T19, T20> T17 copy$default$17() {
/* 37 */     return _17();
/*    */   }
/*    */   
/*    */   public <T1, T2, T3, T4, T5, T6, T7, T8, T9, T10, T11, T12, T13, T14, T15, T16, T17, T18, T19, T20> T18 copy$default$18() {
/* 37 */     return _18();
/*    */   }
/*    */   
/*    */   public <T1, T2, T3, T4, T5, T6, T7, T8, T9, T10, T11, T12, T13, T14, T15, T16, T17, T18, T19, T20> T19 copy$default$19() {
/* 37 */     return _19();
/*    */   }
/*    */   
/*    */   public <T1, T2, T3, T4, T5, T6, T7, T8, T9, T10, T11, T12, T13, T14, T15, T16, T17, T18, T19, T20> T20 copy$default$20() {
/* 37 */     return _20();
/*    */   }
/*    */   
/*    */   public String productPrefix() {
/* 37 */     return "Tuple20";
/*    */   }
/*    */   
/*    */   public Iterator<Object> productIterator() {
/* 37 */     return ScalaRunTime$.MODULE$.typedProductIterator(this);
/*    */   }
/*    */   
/*    */   public boolean canEqual(Object x$1) {
/* 37 */     return x$1 instanceof Tuple20;
/*    */   }
/*    */   
/*    */   public int hashCode() {
/* 37 */     return ScalaRunTime$.MODULE$._hashCode(this);
/*    */   }
/*    */   
/*    */   public boolean equals(Object x$1) {
/*    */     // Byte code:
/*    */     //   0: aload_0
/*    */     //   1: aload_1
/*    */     //   2: if_acmpeq -> 1719
/*    */     //   5: aload_1
/*    */     //   6: instanceof scala/Tuple20
/*    */     //   9: ifeq -> 17
/*    */     //   12: iconst_1
/*    */     //   13: istore_2
/*    */     //   14: goto -> 19
/*    */     //   17: iconst_0
/*    */     //   18: istore_2
/*    */     //   19: iload_2
/*    */     //   20: ifeq -> 1723
/*    */     //   23: aload_1
/*    */     //   24: checkcast scala/Tuple20
/*    */     //   27: astore #43
/*    */     //   29: aload_0
/*    */     //   30: invokevirtual _1 : ()Ljava/lang/Object;
/*    */     //   33: aload #43
/*    */     //   35: invokevirtual _1 : ()Ljava/lang/Object;
/*    */     //   38: astore #4
/*    */     //   40: dup
/*    */     //   41: astore_3
/*    */     //   42: aload #4
/*    */     //   44: if_acmpne -> 51
/*    */     //   47: iconst_1
/*    */     //   48: goto -> 103
/*    */     //   51: aload_3
/*    */     //   52: ifnonnull -> 59
/*    */     //   55: iconst_0
/*    */     //   56: goto -> 103
/*    */     //   59: aload_3
/*    */     //   60: instanceof java/lang/Number
/*    */     //   63: ifeq -> 78
/*    */     //   66: aload_3
/*    */     //   67: checkcast java/lang/Number
/*    */     //   70: aload #4
/*    */     //   72: invokestatic equalsNumObject : (Ljava/lang/Number;Ljava/lang/Object;)Z
/*    */     //   75: goto -> 103
/*    */     //   78: aload_3
/*    */     //   79: instanceof java/lang/Character
/*    */     //   82: ifeq -> 97
/*    */     //   85: aload_3
/*    */     //   86: checkcast java/lang/Character
/*    */     //   89: aload #4
/*    */     //   91: invokestatic equalsCharObject : (Ljava/lang/Character;Ljava/lang/Object;)Z
/*    */     //   94: goto -> 103
/*    */     //   97: aload_3
/*    */     //   98: aload #4
/*    */     //   100: invokevirtual equals : (Ljava/lang/Object;)Z
/*    */     //   103: ifeq -> 1715
/*    */     //   106: aload_0
/*    */     //   107: invokevirtual _2 : ()Ljava/lang/Object;
/*    */     //   110: aload #43
/*    */     //   112: invokevirtual _2 : ()Ljava/lang/Object;
/*    */     //   115: astore #6
/*    */     //   117: dup
/*    */     //   118: astore #5
/*    */     //   120: aload #6
/*    */     //   122: if_acmpne -> 129
/*    */     //   125: iconst_1
/*    */     //   126: goto -> 187
/*    */     //   129: aload #5
/*    */     //   131: ifnonnull -> 138
/*    */     //   134: iconst_0
/*    */     //   135: goto -> 187
/*    */     //   138: aload #5
/*    */     //   140: instanceof java/lang/Number
/*    */     //   143: ifeq -> 159
/*    */     //   146: aload #5
/*    */     //   148: checkcast java/lang/Number
/*    */     //   151: aload #6
/*    */     //   153: invokestatic equalsNumObject : (Ljava/lang/Number;Ljava/lang/Object;)Z
/*    */     //   156: goto -> 187
/*    */     //   159: aload #5
/*    */     //   161: instanceof java/lang/Character
/*    */     //   164: ifeq -> 180
/*    */     //   167: aload #5
/*    */     //   169: checkcast java/lang/Character
/*    */     //   172: aload #6
/*    */     //   174: invokestatic equalsCharObject : (Ljava/lang/Character;Ljava/lang/Object;)Z
/*    */     //   177: goto -> 187
/*    */     //   180: aload #5
/*    */     //   182: aload #6
/*    */     //   184: invokevirtual equals : (Ljava/lang/Object;)Z
/*    */     //   187: ifeq -> 1715
/*    */     //   190: aload_0
/*    */     //   191: invokevirtual _3 : ()Ljava/lang/Object;
/*    */     //   194: aload #43
/*    */     //   196: invokevirtual _3 : ()Ljava/lang/Object;
/*    */     //   199: astore #8
/*    */     //   201: dup
/*    */     //   202: astore #7
/*    */     //   204: aload #8
/*    */     //   206: if_acmpne -> 213
/*    */     //   209: iconst_1
/*    */     //   210: goto -> 271
/*    */     //   213: aload #7
/*    */     //   215: ifnonnull -> 222
/*    */     //   218: iconst_0
/*    */     //   219: goto -> 271
/*    */     //   222: aload #7
/*    */     //   224: instanceof java/lang/Number
/*    */     //   227: ifeq -> 243
/*    */     //   230: aload #7
/*    */     //   232: checkcast java/lang/Number
/*    */     //   235: aload #8
/*    */     //   237: invokestatic equalsNumObject : (Ljava/lang/Number;Ljava/lang/Object;)Z
/*    */     //   240: goto -> 271
/*    */     //   243: aload #7
/*    */     //   245: instanceof java/lang/Character
/*    */     //   248: ifeq -> 264
/*    */     //   251: aload #7
/*    */     //   253: checkcast java/lang/Character
/*    */     //   256: aload #8
/*    */     //   258: invokestatic equalsCharObject : (Ljava/lang/Character;Ljava/lang/Object;)Z
/*    */     //   261: goto -> 271
/*    */     //   264: aload #7
/*    */     //   266: aload #8
/*    */     //   268: invokevirtual equals : (Ljava/lang/Object;)Z
/*    */     //   271: ifeq -> 1715
/*    */     //   274: aload_0
/*    */     //   275: invokevirtual _4 : ()Ljava/lang/Object;
/*    */     //   278: aload #43
/*    */     //   280: invokevirtual _4 : ()Ljava/lang/Object;
/*    */     //   283: astore #10
/*    */     //   285: dup
/*    */     //   286: astore #9
/*    */     //   288: aload #10
/*    */     //   290: if_acmpne -> 297
/*    */     //   293: iconst_1
/*    */     //   294: goto -> 355
/*    */     //   297: aload #9
/*    */     //   299: ifnonnull -> 306
/*    */     //   302: iconst_0
/*    */     //   303: goto -> 355
/*    */     //   306: aload #9
/*    */     //   308: instanceof java/lang/Number
/*    */     //   311: ifeq -> 327
/*    */     //   314: aload #9
/*    */     //   316: checkcast java/lang/Number
/*    */     //   319: aload #10
/*    */     //   321: invokestatic equalsNumObject : (Ljava/lang/Number;Ljava/lang/Object;)Z
/*    */     //   324: goto -> 355
/*    */     //   327: aload #9
/*    */     //   329: instanceof java/lang/Character
/*    */     //   332: ifeq -> 348
/*    */     //   335: aload #9
/*    */     //   337: checkcast java/lang/Character
/*    */     //   340: aload #10
/*    */     //   342: invokestatic equalsCharObject : (Ljava/lang/Character;Ljava/lang/Object;)Z
/*    */     //   345: goto -> 355
/*    */     //   348: aload #9
/*    */     //   350: aload #10
/*    */     //   352: invokevirtual equals : (Ljava/lang/Object;)Z
/*    */     //   355: ifeq -> 1715
/*    */     //   358: aload_0
/*    */     //   359: invokevirtual _5 : ()Ljava/lang/Object;
/*    */     //   362: aload #43
/*    */     //   364: invokevirtual _5 : ()Ljava/lang/Object;
/*    */     //   367: astore #12
/*    */     //   369: dup
/*    */     //   370: astore #11
/*    */     //   372: aload #12
/*    */     //   374: if_acmpne -> 381
/*    */     //   377: iconst_1
/*    */     //   378: goto -> 439
/*    */     //   381: aload #11
/*    */     //   383: ifnonnull -> 390
/*    */     //   386: iconst_0
/*    */     //   387: goto -> 439
/*    */     //   390: aload #11
/*    */     //   392: instanceof java/lang/Number
/*    */     //   395: ifeq -> 411
/*    */     //   398: aload #11
/*    */     //   400: checkcast java/lang/Number
/*    */     //   403: aload #12
/*    */     //   405: invokestatic equalsNumObject : (Ljava/lang/Number;Ljava/lang/Object;)Z
/*    */     //   408: goto -> 439
/*    */     //   411: aload #11
/*    */     //   413: instanceof java/lang/Character
/*    */     //   416: ifeq -> 432
/*    */     //   419: aload #11
/*    */     //   421: checkcast java/lang/Character
/*    */     //   424: aload #12
/*    */     //   426: invokestatic equalsCharObject : (Ljava/lang/Character;Ljava/lang/Object;)Z
/*    */     //   429: goto -> 439
/*    */     //   432: aload #11
/*    */     //   434: aload #12
/*    */     //   436: invokevirtual equals : (Ljava/lang/Object;)Z
/*    */     //   439: ifeq -> 1715
/*    */     //   442: aload_0
/*    */     //   443: invokevirtual _6 : ()Ljava/lang/Object;
/*    */     //   446: aload #43
/*    */     //   448: invokevirtual _6 : ()Ljava/lang/Object;
/*    */     //   451: astore #14
/*    */     //   453: dup
/*    */     //   454: astore #13
/*    */     //   456: aload #14
/*    */     //   458: if_acmpne -> 465
/*    */     //   461: iconst_1
/*    */     //   462: goto -> 523
/*    */     //   465: aload #13
/*    */     //   467: ifnonnull -> 474
/*    */     //   470: iconst_0
/*    */     //   471: goto -> 523
/*    */     //   474: aload #13
/*    */     //   476: instanceof java/lang/Number
/*    */     //   479: ifeq -> 495
/*    */     //   482: aload #13
/*    */     //   484: checkcast java/lang/Number
/*    */     //   487: aload #14
/*    */     //   489: invokestatic equalsNumObject : (Ljava/lang/Number;Ljava/lang/Object;)Z
/*    */     //   492: goto -> 523
/*    */     //   495: aload #13
/*    */     //   497: instanceof java/lang/Character
/*    */     //   500: ifeq -> 516
/*    */     //   503: aload #13
/*    */     //   505: checkcast java/lang/Character
/*    */     //   508: aload #14
/*    */     //   510: invokestatic equalsCharObject : (Ljava/lang/Character;Ljava/lang/Object;)Z
/*    */     //   513: goto -> 523
/*    */     //   516: aload #13
/*    */     //   518: aload #14
/*    */     //   520: invokevirtual equals : (Ljava/lang/Object;)Z
/*    */     //   523: ifeq -> 1715
/*    */     //   526: aload_0
/*    */     //   527: invokevirtual _7 : ()Ljava/lang/Object;
/*    */     //   530: aload #43
/*    */     //   532: invokevirtual _7 : ()Ljava/lang/Object;
/*    */     //   535: astore #16
/*    */     //   537: dup
/*    */     //   538: astore #15
/*    */     //   540: aload #16
/*    */     //   542: if_acmpne -> 549
/*    */     //   545: iconst_1
/*    */     //   546: goto -> 607
/*    */     //   549: aload #15
/*    */     //   551: ifnonnull -> 558
/*    */     //   554: iconst_0
/*    */     //   555: goto -> 607
/*    */     //   558: aload #15
/*    */     //   560: instanceof java/lang/Number
/*    */     //   563: ifeq -> 579
/*    */     //   566: aload #15
/*    */     //   568: checkcast java/lang/Number
/*    */     //   571: aload #16
/*    */     //   573: invokestatic equalsNumObject : (Ljava/lang/Number;Ljava/lang/Object;)Z
/*    */     //   576: goto -> 607
/*    */     //   579: aload #15
/*    */     //   581: instanceof java/lang/Character
/*    */     //   584: ifeq -> 600
/*    */     //   587: aload #15
/*    */     //   589: checkcast java/lang/Character
/*    */     //   592: aload #16
/*    */     //   594: invokestatic equalsCharObject : (Ljava/lang/Character;Ljava/lang/Object;)Z
/*    */     //   597: goto -> 607
/*    */     //   600: aload #15
/*    */     //   602: aload #16
/*    */     //   604: invokevirtual equals : (Ljava/lang/Object;)Z
/*    */     //   607: ifeq -> 1715
/*    */     //   610: aload_0
/*    */     //   611: invokevirtual _8 : ()Ljava/lang/Object;
/*    */     //   614: aload #43
/*    */     //   616: invokevirtual _8 : ()Ljava/lang/Object;
/*    */     //   619: astore #18
/*    */     //   621: dup
/*    */     //   622: astore #17
/*    */     //   624: aload #18
/*    */     //   626: if_acmpne -> 633
/*    */     //   629: iconst_1
/*    */     //   630: goto -> 691
/*    */     //   633: aload #17
/*    */     //   635: ifnonnull -> 642
/*    */     //   638: iconst_0
/*    */     //   639: goto -> 691
/*    */     //   642: aload #17
/*    */     //   644: instanceof java/lang/Number
/*    */     //   647: ifeq -> 663
/*    */     //   650: aload #17
/*    */     //   652: checkcast java/lang/Number
/*    */     //   655: aload #18
/*    */     //   657: invokestatic equalsNumObject : (Ljava/lang/Number;Ljava/lang/Object;)Z
/*    */     //   660: goto -> 691
/*    */     //   663: aload #17
/*    */     //   665: instanceof java/lang/Character
/*    */     //   668: ifeq -> 684
/*    */     //   671: aload #17
/*    */     //   673: checkcast java/lang/Character
/*    */     //   676: aload #18
/*    */     //   678: invokestatic equalsCharObject : (Ljava/lang/Character;Ljava/lang/Object;)Z
/*    */     //   681: goto -> 691
/*    */     //   684: aload #17
/*    */     //   686: aload #18
/*    */     //   688: invokevirtual equals : (Ljava/lang/Object;)Z
/*    */     //   691: ifeq -> 1715
/*    */     //   694: aload_0
/*    */     //   695: invokevirtual _9 : ()Ljava/lang/Object;
/*    */     //   698: aload #43
/*    */     //   700: invokevirtual _9 : ()Ljava/lang/Object;
/*    */     //   703: astore #20
/*    */     //   705: dup
/*    */     //   706: astore #19
/*    */     //   708: aload #20
/*    */     //   710: if_acmpne -> 717
/*    */     //   713: iconst_1
/*    */     //   714: goto -> 775
/*    */     //   717: aload #19
/*    */     //   719: ifnonnull -> 726
/*    */     //   722: iconst_0
/*    */     //   723: goto -> 775
/*    */     //   726: aload #19
/*    */     //   728: instanceof java/lang/Number
/*    */     //   731: ifeq -> 747
/*    */     //   734: aload #19
/*    */     //   736: checkcast java/lang/Number
/*    */     //   739: aload #20
/*    */     //   741: invokestatic equalsNumObject : (Ljava/lang/Number;Ljava/lang/Object;)Z
/*    */     //   744: goto -> 775
/*    */     //   747: aload #19
/*    */     //   749: instanceof java/lang/Character
/*    */     //   752: ifeq -> 768
/*    */     //   755: aload #19
/*    */     //   757: checkcast java/lang/Character
/*    */     //   760: aload #20
/*    */     //   762: invokestatic equalsCharObject : (Ljava/lang/Character;Ljava/lang/Object;)Z
/*    */     //   765: goto -> 775
/*    */     //   768: aload #19
/*    */     //   770: aload #20
/*    */     //   772: invokevirtual equals : (Ljava/lang/Object;)Z
/*    */     //   775: ifeq -> 1715
/*    */     //   778: aload_0
/*    */     //   779: invokevirtual _10 : ()Ljava/lang/Object;
/*    */     //   782: aload #43
/*    */     //   784: invokevirtual _10 : ()Ljava/lang/Object;
/*    */     //   787: astore #22
/*    */     //   789: dup
/*    */     //   790: astore #21
/*    */     //   792: aload #22
/*    */     //   794: if_acmpne -> 801
/*    */     //   797: iconst_1
/*    */     //   798: goto -> 859
/*    */     //   801: aload #21
/*    */     //   803: ifnonnull -> 810
/*    */     //   806: iconst_0
/*    */     //   807: goto -> 859
/*    */     //   810: aload #21
/*    */     //   812: instanceof java/lang/Number
/*    */     //   815: ifeq -> 831
/*    */     //   818: aload #21
/*    */     //   820: checkcast java/lang/Number
/*    */     //   823: aload #22
/*    */     //   825: invokestatic equalsNumObject : (Ljava/lang/Number;Ljava/lang/Object;)Z
/*    */     //   828: goto -> 859
/*    */     //   831: aload #21
/*    */     //   833: instanceof java/lang/Character
/*    */     //   836: ifeq -> 852
/*    */     //   839: aload #21
/*    */     //   841: checkcast java/lang/Character
/*    */     //   844: aload #22
/*    */     //   846: invokestatic equalsCharObject : (Ljava/lang/Character;Ljava/lang/Object;)Z
/*    */     //   849: goto -> 859
/*    */     //   852: aload #21
/*    */     //   854: aload #22
/*    */     //   856: invokevirtual equals : (Ljava/lang/Object;)Z
/*    */     //   859: ifeq -> 1715
/*    */     //   862: aload_0
/*    */     //   863: invokevirtual _11 : ()Ljava/lang/Object;
/*    */     //   866: aload #43
/*    */     //   868: invokevirtual _11 : ()Ljava/lang/Object;
/*    */     //   871: astore #24
/*    */     //   873: dup
/*    */     //   874: astore #23
/*    */     //   876: aload #24
/*    */     //   878: if_acmpne -> 885
/*    */     //   881: iconst_1
/*    */     //   882: goto -> 943
/*    */     //   885: aload #23
/*    */     //   887: ifnonnull -> 894
/*    */     //   890: iconst_0
/*    */     //   891: goto -> 943
/*    */     //   894: aload #23
/*    */     //   896: instanceof java/lang/Number
/*    */     //   899: ifeq -> 915
/*    */     //   902: aload #23
/*    */     //   904: checkcast java/lang/Number
/*    */     //   907: aload #24
/*    */     //   909: invokestatic equalsNumObject : (Ljava/lang/Number;Ljava/lang/Object;)Z
/*    */     //   912: goto -> 943
/*    */     //   915: aload #23
/*    */     //   917: instanceof java/lang/Character
/*    */     //   920: ifeq -> 936
/*    */     //   923: aload #23
/*    */     //   925: checkcast java/lang/Character
/*    */     //   928: aload #24
/*    */     //   930: invokestatic equalsCharObject : (Ljava/lang/Character;Ljava/lang/Object;)Z
/*    */     //   933: goto -> 943
/*    */     //   936: aload #23
/*    */     //   938: aload #24
/*    */     //   940: invokevirtual equals : (Ljava/lang/Object;)Z
/*    */     //   943: ifeq -> 1715
/*    */     //   946: aload_0
/*    */     //   947: invokevirtual _12 : ()Ljava/lang/Object;
/*    */     //   950: aload #43
/*    */     //   952: invokevirtual _12 : ()Ljava/lang/Object;
/*    */     //   955: astore #26
/*    */     //   957: dup
/*    */     //   958: astore #25
/*    */     //   960: aload #26
/*    */     //   962: if_acmpne -> 969
/*    */     //   965: iconst_1
/*    */     //   966: goto -> 1027
/*    */     //   969: aload #25
/*    */     //   971: ifnonnull -> 978
/*    */     //   974: iconst_0
/*    */     //   975: goto -> 1027
/*    */     //   978: aload #25
/*    */     //   980: instanceof java/lang/Number
/*    */     //   983: ifeq -> 999
/*    */     //   986: aload #25
/*    */     //   988: checkcast java/lang/Number
/*    */     //   991: aload #26
/*    */     //   993: invokestatic equalsNumObject : (Ljava/lang/Number;Ljava/lang/Object;)Z
/*    */     //   996: goto -> 1027
/*    */     //   999: aload #25
/*    */     //   1001: instanceof java/lang/Character
/*    */     //   1004: ifeq -> 1020
/*    */     //   1007: aload #25
/*    */     //   1009: checkcast java/lang/Character
/*    */     //   1012: aload #26
/*    */     //   1014: invokestatic equalsCharObject : (Ljava/lang/Character;Ljava/lang/Object;)Z
/*    */     //   1017: goto -> 1027
/*    */     //   1020: aload #25
/*    */     //   1022: aload #26
/*    */     //   1024: invokevirtual equals : (Ljava/lang/Object;)Z
/*    */     //   1027: ifeq -> 1715
/*    */     //   1030: aload_0
/*    */     //   1031: invokevirtual _13 : ()Ljava/lang/Object;
/*    */     //   1034: aload #43
/*    */     //   1036: invokevirtual _13 : ()Ljava/lang/Object;
/*    */     //   1039: astore #28
/*    */     //   1041: dup
/*    */     //   1042: astore #27
/*    */     //   1044: aload #28
/*    */     //   1046: if_acmpne -> 1053
/*    */     //   1049: iconst_1
/*    */     //   1050: goto -> 1111
/*    */     //   1053: aload #27
/*    */     //   1055: ifnonnull -> 1062
/*    */     //   1058: iconst_0
/*    */     //   1059: goto -> 1111
/*    */     //   1062: aload #27
/*    */     //   1064: instanceof java/lang/Number
/*    */     //   1067: ifeq -> 1083
/*    */     //   1070: aload #27
/*    */     //   1072: checkcast java/lang/Number
/*    */     //   1075: aload #28
/*    */     //   1077: invokestatic equalsNumObject : (Ljava/lang/Number;Ljava/lang/Object;)Z
/*    */     //   1080: goto -> 1111
/*    */     //   1083: aload #27
/*    */     //   1085: instanceof java/lang/Character
/*    */     //   1088: ifeq -> 1104
/*    */     //   1091: aload #27
/*    */     //   1093: checkcast java/lang/Character
/*    */     //   1096: aload #28
/*    */     //   1098: invokestatic equalsCharObject : (Ljava/lang/Character;Ljava/lang/Object;)Z
/*    */     //   1101: goto -> 1111
/*    */     //   1104: aload #27
/*    */     //   1106: aload #28
/*    */     //   1108: invokevirtual equals : (Ljava/lang/Object;)Z
/*    */     //   1111: ifeq -> 1715
/*    */     //   1114: aload_0
/*    */     //   1115: invokevirtual _14 : ()Ljava/lang/Object;
/*    */     //   1118: aload #43
/*    */     //   1120: invokevirtual _14 : ()Ljava/lang/Object;
/*    */     //   1123: astore #30
/*    */     //   1125: dup
/*    */     //   1126: astore #29
/*    */     //   1128: aload #30
/*    */     //   1130: if_acmpne -> 1137
/*    */     //   1133: iconst_1
/*    */     //   1134: goto -> 1195
/*    */     //   1137: aload #29
/*    */     //   1139: ifnonnull -> 1146
/*    */     //   1142: iconst_0
/*    */     //   1143: goto -> 1195
/*    */     //   1146: aload #29
/*    */     //   1148: instanceof java/lang/Number
/*    */     //   1151: ifeq -> 1167
/*    */     //   1154: aload #29
/*    */     //   1156: checkcast java/lang/Number
/*    */     //   1159: aload #30
/*    */     //   1161: invokestatic equalsNumObject : (Ljava/lang/Number;Ljava/lang/Object;)Z
/*    */     //   1164: goto -> 1195
/*    */     //   1167: aload #29
/*    */     //   1169: instanceof java/lang/Character
/*    */     //   1172: ifeq -> 1188
/*    */     //   1175: aload #29
/*    */     //   1177: checkcast java/lang/Character
/*    */     //   1180: aload #30
/*    */     //   1182: invokestatic equalsCharObject : (Ljava/lang/Character;Ljava/lang/Object;)Z
/*    */     //   1185: goto -> 1195
/*    */     //   1188: aload #29
/*    */     //   1190: aload #30
/*    */     //   1192: invokevirtual equals : (Ljava/lang/Object;)Z
/*    */     //   1195: ifeq -> 1715
/*    */     //   1198: aload_0
/*    */     //   1199: invokevirtual _15 : ()Ljava/lang/Object;
/*    */     //   1202: aload #43
/*    */     //   1204: invokevirtual _15 : ()Ljava/lang/Object;
/*    */     //   1207: astore #32
/*    */     //   1209: dup
/*    */     //   1210: astore #31
/*    */     //   1212: aload #32
/*    */     //   1214: if_acmpne -> 1221
/*    */     //   1217: iconst_1
/*    */     //   1218: goto -> 1279
/*    */     //   1221: aload #31
/*    */     //   1223: ifnonnull -> 1230
/*    */     //   1226: iconst_0
/*    */     //   1227: goto -> 1279
/*    */     //   1230: aload #31
/*    */     //   1232: instanceof java/lang/Number
/*    */     //   1235: ifeq -> 1251
/*    */     //   1238: aload #31
/*    */     //   1240: checkcast java/lang/Number
/*    */     //   1243: aload #32
/*    */     //   1245: invokestatic equalsNumObject : (Ljava/lang/Number;Ljava/lang/Object;)Z
/*    */     //   1248: goto -> 1279
/*    */     //   1251: aload #31
/*    */     //   1253: instanceof java/lang/Character
/*    */     //   1256: ifeq -> 1272
/*    */     //   1259: aload #31
/*    */     //   1261: checkcast java/lang/Character
/*    */     //   1264: aload #32
/*    */     //   1266: invokestatic equalsCharObject : (Ljava/lang/Character;Ljava/lang/Object;)Z
/*    */     //   1269: goto -> 1279
/*    */     //   1272: aload #31
/*    */     //   1274: aload #32
/*    */     //   1276: invokevirtual equals : (Ljava/lang/Object;)Z
/*    */     //   1279: ifeq -> 1715
/*    */     //   1282: aload_0
/*    */     //   1283: invokevirtual _16 : ()Ljava/lang/Object;
/*    */     //   1286: aload #43
/*    */     //   1288: invokevirtual _16 : ()Ljava/lang/Object;
/*    */     //   1291: astore #34
/*    */     //   1293: dup
/*    */     //   1294: astore #33
/*    */     //   1296: aload #34
/*    */     //   1298: if_acmpne -> 1305
/*    */     //   1301: iconst_1
/*    */     //   1302: goto -> 1363
/*    */     //   1305: aload #33
/*    */     //   1307: ifnonnull -> 1314
/*    */     //   1310: iconst_0
/*    */     //   1311: goto -> 1363
/*    */     //   1314: aload #33
/*    */     //   1316: instanceof java/lang/Number
/*    */     //   1319: ifeq -> 1335
/*    */     //   1322: aload #33
/*    */     //   1324: checkcast java/lang/Number
/*    */     //   1327: aload #34
/*    */     //   1329: invokestatic equalsNumObject : (Ljava/lang/Number;Ljava/lang/Object;)Z
/*    */     //   1332: goto -> 1363
/*    */     //   1335: aload #33
/*    */     //   1337: instanceof java/lang/Character
/*    */     //   1340: ifeq -> 1356
/*    */     //   1343: aload #33
/*    */     //   1345: checkcast java/lang/Character
/*    */     //   1348: aload #34
/*    */     //   1350: invokestatic equalsCharObject : (Ljava/lang/Character;Ljava/lang/Object;)Z
/*    */     //   1353: goto -> 1363
/*    */     //   1356: aload #33
/*    */     //   1358: aload #34
/*    */     //   1360: invokevirtual equals : (Ljava/lang/Object;)Z
/*    */     //   1363: ifeq -> 1715
/*    */     //   1366: aload_0
/*    */     //   1367: invokevirtual _17 : ()Ljava/lang/Object;
/*    */     //   1370: aload #43
/*    */     //   1372: invokevirtual _17 : ()Ljava/lang/Object;
/*    */     //   1375: astore #36
/*    */     //   1377: dup
/*    */     //   1378: astore #35
/*    */     //   1380: aload #36
/*    */     //   1382: if_acmpne -> 1389
/*    */     //   1385: iconst_1
/*    */     //   1386: goto -> 1447
/*    */     //   1389: aload #35
/*    */     //   1391: ifnonnull -> 1398
/*    */     //   1394: iconst_0
/*    */     //   1395: goto -> 1447
/*    */     //   1398: aload #35
/*    */     //   1400: instanceof java/lang/Number
/*    */     //   1403: ifeq -> 1419
/*    */     //   1406: aload #35
/*    */     //   1408: checkcast java/lang/Number
/*    */     //   1411: aload #36
/*    */     //   1413: invokestatic equalsNumObject : (Ljava/lang/Number;Ljava/lang/Object;)Z
/*    */     //   1416: goto -> 1447
/*    */     //   1419: aload #35
/*    */     //   1421: instanceof java/lang/Character
/*    */     //   1424: ifeq -> 1440
/*    */     //   1427: aload #35
/*    */     //   1429: checkcast java/lang/Character
/*    */     //   1432: aload #36
/*    */     //   1434: invokestatic equalsCharObject : (Ljava/lang/Character;Ljava/lang/Object;)Z
/*    */     //   1437: goto -> 1447
/*    */     //   1440: aload #35
/*    */     //   1442: aload #36
/*    */     //   1444: invokevirtual equals : (Ljava/lang/Object;)Z
/*    */     //   1447: ifeq -> 1715
/*    */     //   1450: aload_0
/*    */     //   1451: invokevirtual _18 : ()Ljava/lang/Object;
/*    */     //   1454: aload #43
/*    */     //   1456: invokevirtual _18 : ()Ljava/lang/Object;
/*    */     //   1459: astore #38
/*    */     //   1461: dup
/*    */     //   1462: astore #37
/*    */     //   1464: aload #38
/*    */     //   1466: if_acmpne -> 1473
/*    */     //   1469: iconst_1
/*    */     //   1470: goto -> 1531
/*    */     //   1473: aload #37
/*    */     //   1475: ifnonnull -> 1482
/*    */     //   1478: iconst_0
/*    */     //   1479: goto -> 1531
/*    */     //   1482: aload #37
/*    */     //   1484: instanceof java/lang/Number
/*    */     //   1487: ifeq -> 1503
/*    */     //   1490: aload #37
/*    */     //   1492: checkcast java/lang/Number
/*    */     //   1495: aload #38
/*    */     //   1497: invokestatic equalsNumObject : (Ljava/lang/Number;Ljava/lang/Object;)Z
/*    */     //   1500: goto -> 1531
/*    */     //   1503: aload #37
/*    */     //   1505: instanceof java/lang/Character
/*    */     //   1508: ifeq -> 1524
/*    */     //   1511: aload #37
/*    */     //   1513: checkcast java/lang/Character
/*    */     //   1516: aload #38
/*    */     //   1518: invokestatic equalsCharObject : (Ljava/lang/Character;Ljava/lang/Object;)Z
/*    */     //   1521: goto -> 1531
/*    */     //   1524: aload #37
/*    */     //   1526: aload #38
/*    */     //   1528: invokevirtual equals : (Ljava/lang/Object;)Z
/*    */     //   1531: ifeq -> 1715
/*    */     //   1534: aload_0
/*    */     //   1535: invokevirtual _19 : ()Ljava/lang/Object;
/*    */     //   1538: aload #43
/*    */     //   1540: invokevirtual _19 : ()Ljava/lang/Object;
/*    */     //   1543: astore #40
/*    */     //   1545: dup
/*    */     //   1546: astore #39
/*    */     //   1548: aload #40
/*    */     //   1550: if_acmpne -> 1557
/*    */     //   1553: iconst_1
/*    */     //   1554: goto -> 1615
/*    */     //   1557: aload #39
/*    */     //   1559: ifnonnull -> 1566
/*    */     //   1562: iconst_0
/*    */     //   1563: goto -> 1615
/*    */     //   1566: aload #39
/*    */     //   1568: instanceof java/lang/Number
/*    */     //   1571: ifeq -> 1587
/*    */     //   1574: aload #39
/*    */     //   1576: checkcast java/lang/Number
/*    */     //   1579: aload #40
/*    */     //   1581: invokestatic equalsNumObject : (Ljava/lang/Number;Ljava/lang/Object;)Z
/*    */     //   1584: goto -> 1615
/*    */     //   1587: aload #39
/*    */     //   1589: instanceof java/lang/Character
/*    */     //   1592: ifeq -> 1608
/*    */     //   1595: aload #39
/*    */     //   1597: checkcast java/lang/Character
/*    */     //   1600: aload #40
/*    */     //   1602: invokestatic equalsCharObject : (Ljava/lang/Character;Ljava/lang/Object;)Z
/*    */     //   1605: goto -> 1615
/*    */     //   1608: aload #39
/*    */     //   1610: aload #40
/*    */     //   1612: invokevirtual equals : (Ljava/lang/Object;)Z
/*    */     //   1615: ifeq -> 1715
/*    */     //   1618: aload_0
/*    */     //   1619: invokevirtual _20 : ()Ljava/lang/Object;
/*    */     //   1622: aload #43
/*    */     //   1624: invokevirtual _20 : ()Ljava/lang/Object;
/*    */     //   1627: astore #42
/*    */     //   1629: dup
/*    */     //   1630: astore #41
/*    */     //   1632: aload #42
/*    */     //   1634: if_acmpne -> 1641
/*    */     //   1637: iconst_1
/*    */     //   1638: goto -> 1699
/*    */     //   1641: aload #41
/*    */     //   1643: ifnonnull -> 1650
/*    */     //   1646: iconst_0
/*    */     //   1647: goto -> 1699
/*    */     //   1650: aload #41
/*    */     //   1652: instanceof java/lang/Number
/*    */     //   1655: ifeq -> 1671
/*    */     //   1658: aload #41
/*    */     //   1660: checkcast java/lang/Number
/*    */     //   1663: aload #42
/*    */     //   1665: invokestatic equalsNumObject : (Ljava/lang/Number;Ljava/lang/Object;)Z
/*    */     //   1668: goto -> 1699
/*    */     //   1671: aload #41
/*    */     //   1673: instanceof java/lang/Character
/*    */     //   1676: ifeq -> 1692
/*    */     //   1679: aload #41
/*    */     //   1681: checkcast java/lang/Character
/*    */     //   1684: aload #42
/*    */     //   1686: invokestatic equalsCharObject : (Ljava/lang/Character;Ljava/lang/Object;)Z
/*    */     //   1689: goto -> 1699
/*    */     //   1692: aload #41
/*    */     //   1694: aload #42
/*    */     //   1696: invokevirtual equals : (Ljava/lang/Object;)Z
/*    */     //   1699: ifeq -> 1715
/*    */     //   1702: aload #43
/*    */     //   1704: aload_0
/*    */     //   1705: invokevirtual canEqual : (Ljava/lang/Object;)Z
/*    */     //   1708: ifeq -> 1715
/*    */     //   1711: iconst_1
/*    */     //   1712: goto -> 1716
/*    */     //   1715: iconst_0
/*    */     //   1716: ifeq -> 1723
/*    */     //   1719: iconst_1
/*    */     //   1720: goto -> 1724
/*    */     //   1723: iconst_0
/*    */     //   1724: ireturn
/*    */     // Line number table:
/*    */     //   Java source line number -> byte code offset
/*    */     //   #37	-> 0
/*    */     //   #236	-> 12
/*    */     //   #37	-> 19
/*    */     // Local variable table:
/*    */     //   start	length	slot	name	descriptor
/*    */     //   0	1725	0	this	Lscala/Tuple20;
/*    */     //   0	1725	1	x$1	Ljava/lang/Object;
/*    */   }
/*    */   
/*    */   public Tuple20(Object _1, Object _2, Object _3, Object _4, Object _5, Object _6, Object _7, Object _8, Object _9, Object _10, Object _11, Object _12, Object _13, Object _14, Object _15, Object _16, Object _17, Object _18, Object _19, Object _20) {
/* 37 */     Product$class.$init$(this);
/* 37 */     Product20$class.$init$(this);
/*    */   }
/*    */   
/*    */   public String toString() {
/* 41 */     return (new StringBuilder()).append("(").append(_1()).append(",").append(_2()).append(",").append(_3()).append(",").append(_4()).append(",").append(_5()).append(",").append(_6()).append(",").append(_7()).append(",").append(_8()).append(",").append(_9()).append(",").append(_10()).append(",").append(_11()).append(",").append(_12()).append(",").append(_13()).append(",").append(_14()).append(",").append(_15()).append(",").append(_16()).append(",").append(_17()).append(",").append(_18()).append(",").append(_19()).append(",").append(_20()).append(")").toString();
/*    */   }
/*    */ }


/* Location:              D:\#source-code\TheFlightSims\TFSLibrary\World2Xplane\World2XPlane.jar!\scala\Tuple20.class
 * Java compiler version: 6 (50.0)
 * JD-Core Version:       1.1.3
 */