/*    */ package scala;
/*    */ 
/*    */ import scala.collection.Iterator;
/*    */ import scala.collection.mutable.StringBuilder;
/*    */ import scala.reflect.ScalaSignature;
/*    */ import scala.runtime.ScalaRunTime$;
/*    */ 
/*    */ @ScalaSignature(bytes = "\006\001\021eg\001B\001\003\001\026\021q\001V;qY\026\fDGC\001\004\003\025\0318-\0317b\007\001)rB\002\t\033;\001\032c%\013\0270eUB4HP\n\006\001\035Y\001i\021\t\003\021%i\021AA\005\003\025\t\021a!\0218z%\0264\007\003\005\005\r\035earDI\023)W9\nDg\016\036>\023\ti!AA\005Qe>$Wo\031;2iA\021q\002\005\007\001\t\031\t\002\001\"b\001%\t\021A+M\t\003'Y\001\"\001\003\013\n\005U\021!a\002(pi\"Lgn\032\t\003\021]I!\001\007\002\003\007\005s\027\020\005\002\0205\02111\004\001CC\002I\021!\001\026\032\021\005=iBA\002\020\001\t\013\007!C\001\002UgA\021q\002\t\003\007C\001!)\031\001\n\003\005Q#\004CA\b$\t\031!\003\001\"b\001%\t\021A+\016\t\003\037\031\"aa\n\001\005\006\004\021\"A\001+7!\ty\021\006\002\004+\001\021\025\rA\005\002\003)^\002\"a\004\027\005\r5\002AQ1\001\023\005\t!\006\b\005\002\020_\0211\001\007\001CC\002I\021!\001V\035\021\005=\021DAB\032\001\t\013\007!CA\002UcA\002\"aD\033\005\rY\002AQ1\001\023\005\r!\026'\r\t\003\037a\"a!\017\001\005\006\004\021\"a\001+2eA\021qb\017\003\007y\001!)\031\001\n\003\007Q\0134\007\005\002\020}\0211q\b\001CC\002I\0211\001V\0315!\tA\021)\003\002C\005\t9\001K]8ek\016$\bC\001\005E\023\t)%A\001\007TKJL\027\r\\5{C\ndW\r\003\005H\001\tU\r\021\"\001I\003\ty\026'F\001\017\021!Q\005A!E!\002\023q\021aA02A!AA\n\001BK\002\023\005Q*\001\002`eU\t\021\004\003\005P\001\tE\t\025!\003\032\003\ry&\007\t\005\t#\002\021)\032!C\001%\006\021qlM\013\0029!AA\013\001B\tB\003%A$A\002`g\001B\001B\026\001\003\026\004%\taV\001\003?R*\022a\b\005\t3\002\021\t\022)A\005?\005\031q\f\016\021\t\021m\003!Q3A\005\002q\013!aX\033\026\003\tB\001B\030\001\003\022\003\006IAI\001\004?V\002\003\002\0031\001\005+\007I\021A1\002\005}3T#A\023\t\021\r\004!\021#Q\001\n\025\n1a\030\034!\021!)\007A!f\001\n\0031\027AA08+\005A\003\002\0035\001\005#\005\013\021\002\025\002\007};\004\005\003\005k\001\tU\r\021\"\001l\003\ty\006(F\001,\021!i\007A!E!\002\023Y\023aA09A!Aq\016\001BK\002\023\005\001/\001\002`sU\ta\006\003\005s\001\tE\t\025!\003/\003\ry\026\b\t\005\ti\002\021)\032!C\001k\006\031q,\r\031\026\003EB\001b\036\001\003\022\003\006I!M\001\005?F\002\004\005\003\005z\001\tU\r\021\"\001{\003\ry\026'M\013\002i!AA\020\001B\tB\003%A'\001\003`cE\002\003\002\003@\001\005+\007I\021A@\002\007}\013$'F\0018\021%\t\031\001\001B\tB\003%q'\001\003`cI\002\003BCA\004\001\tU\r\021\"\001\002\n\005\031q,M\032\026\003iB\021\"!\004\001\005#\005\013\021\002\036\002\t}\0134\007\t\005\013\003#\001!Q3A\005\002\005M\021aA02iU\tQ\bC\005\002\030\001\021\t\022)A\005{\005!q,\r\033!\021\035\tY\002\001C\001\003;\ta\001P5oSRtDCHA\020\003C\t\031#!\n\002(\005%\0221FA\027\003_\t\t$a\r\0026\005]\022\021HA\036!AA\001AD\r\035?\t*\003f\013\0302i]RT\b\003\004H\0033\001\rA\004\005\007\031\006e\001\031A\r\t\rE\013I\0021\001\035\021\0311\026\021\004a\001?!11,!\007A\002\tBa\001YA\r\001\004)\003BB3\002\032\001\007\001\006\003\004k\0033\001\ra\013\005\007_\006e\001\031\001\030\t\rQ\fI\0021\0012\021\031I\030\021\004a\001i!1a0!\007A\002]Bq!a\002\002\032\001\007!\bC\004\002\022\005e\001\031A\037\t\017\005}\002\001\"\021\002B\005AAo\\*ue&tw\r\006\002\002DA!\021QIA(\033\t\t9E\003\003\002J\005-\023\001\0027b]\036T!!!\024\002\t)\fg/Y\005\005\003#\n9E\001\004TiJLgn\032\005\n\003+\002\021\021!C\001\003/\nAaY8qsVq\022\021LA0\003G\n9'a\033\002p\005M\024qOA>\003\n\031)a\"\002\f\006=\0251\023\013\037\0037\n)*a&\002\032\006m\025QTAP\003C\013\031+!*\002(\006%\0261VAW\003_\003b\004\003\001\002^\005\005\024QMA5\003[\n\t(!\036\002z\005u\024\021QAC\003\023\013i)!%\021\007=\ty\006\002\004\022\003'\022\rA\005\t\004\037\005\rDAB\016\002T\t\007!\003E\002\020\003O\"aAHA*\005\004\021\002cA\b\002l\0211\021%a\025C\002I\0012aDA8\t\031!\0231\013b\001%A\031q\"a\035\005\r\035\n\031F1\001\023!\ry\021q\017\003\007U\005M#\031\001\n\021\007=\tY\b\002\004.\003'\022\rA\005\t\004\037\005}DA\002\031\002T\t\007!\003E\002\020\003\007#aaMA*\005\004\021\002cA\b\002\b\0221a'a\025C\002I\0012aDAF\t\031I\0241\013b\001%A\031q\"a$\005\rq\n\031F1\001\023!\ry\0211\023\003\007\005M#\031\001\n\t\023\035\013\031\006%AA\002\005u\003\"\003'\002TA\005\t\031AA1\021%\t\0261\013I\001\002\004\t)\007C\005W\003'\002\n\0211\001\002j!I1,a\025\021\002\003\007\021Q\016\005\nA\006M\003\023!a\001\003cB\021\"ZA*!\003\005\r!!\036\t\023)\f\031\006%AA\002\005e\004\"C8\002TA\005\t\031AA?\021%!\0301\013I\001\002\004\t\t\tC\005z\003'\002\n\0211\001\002\006\"Ia0a\025\021\002\003\007\021\021\022\005\013\003\017\t\031\006%AA\002\0055\005BCA\t\003'\002\n\0211\001\002\022\"I\0211\027\001\022\002\023\005\021QW\001\017G>\004\030\020\n3fM\006,H\016\036\0232+y\t9,!4\002P\006E\0271[Ak\003/\fI.a7\002^\006}\027\021]Ar\003K\f9/\006\002\002:*\032a\"a/,\005\005u\006\003BA`\003\023l!!!1\013\t\005\r\027QY\001\nk:\034\007.Z2lK\022T1!a2\003\003)\tgN\\8uCRLwN\\\005\005\003\027\f\tMA\tv]\016DWmY6fIZ\013'/[1oG\026$a!EAY\005\004\021BAB\016\0022\n\007!\003\002\004\037\003c\023\rA\005\003\007C\005E&\031\001\n\005\r\021\n\tL1\001\023\t\0319\023\021\027b\001%\0211!&!-C\002I!a!LAY\005\004\021BA\002\031\0022\n\007!\003\002\0044\003c\023\rA\005\003\007m\005E&\031\001\n\005\re\n\tL1\001\023\t\031a\024\021\027b\001%\0211q(!-C\002IA\021\"a;\001#\003%\t!!<\002\035\r|\007/\037\023eK\032\fW\017\034;%eUq\022q^Az\003k\f90!?\002|\006u\030q B\001\005\007\021)Aa\002\003\n\t-!QB\013\003\003cT3!GA^\t\031\t\022\021\036b\001%\02111$!;C\002I!aAHAu\005\004\021BAB\021\002j\n\007!\003\002\004%\003S\024\rA\005\003\007O\005%(\031\001\n\005\r)\nIO1\001\023\t\031i\023\021\036b\001%\0211\001'!;C\002I!aaMAu\005\004\021BA\002\034\002j\n\007!\003\002\004:\003S\024\rA\005\003\007y\005%(\031\001\n\005\r}\nIO1\001\023\021%\021\t\002AI\001\n\003\021\031\"\001\bd_BLH\005Z3gCVdG\017J\032\026=\tU!\021\004B\016\005;\021yB!\t\003$\t\025\"q\005B\025\005W\021iCa\f\0032\tMRC\001B\fU\ra\0221\030\003\007#\t=!\031\001\n\005\rm\021yA1\001\023\t\031q\"q\002b\001%\0211\021Ea\004C\002I!a\001\nB\b\005\004\021BAB\024\003\020\t\007!\003\002\004+\005\037\021\rA\005\003\007[\t=!\031\001\n\005\rA\022yA1\001\023\t\031\031$q\002b\001%\0211aGa\004C\002I!a!\017B\b\005\004\021BA\002\037\003\020\t\007!\003\002\004@\005\037\021\rA\005\005\n\005o\001\021\023!C\001\005s\tabY8qs\022\"WMZ1vYR$C'\006\020\003<\t}\"\021\tB\"\005\013\0229E!\023\003L\t5#q\nB)\005'\022)Fa\026\003ZU\021!Q\b\026\004?\005mFAB\t\0036\t\007!\003\002\004\034\005k\021\rA\005\003\007=\tU\"\031\001\n\005\r\005\022)D1\001\023\t\031!#Q\007b\001%\0211qE!\016C\002I!aA\013B\033\005\004\021BAB\027\0036\t\007!\003\002\0041\005k\021\rA\005\003\007g\tU\"\031\001\n\005\rY\022)D1\001\023\t\031I$Q\007b\001%\0211AH!\016C\002I!aa\020B\033\005\004\021\002\"\003B/\001E\005I\021\001B0\0039\031w\016]=%I\0264\027-\0367uIU*bD!\031\003f\t\035$\021\016B6\005[\022yG!\035\003t\tU$q\017B=\005w\022iHa \026\005\t\r$f\001\022\002<\0221\021Ca\027C\002I!aa\007B.\005\004\021BA\002\020\003\\\t\007!\003\002\004\"\0057\022\rA\005\003\007I\tm#\031\001\n\005\r\035\022YF1\001\023\t\031Q#1\fb\001%\0211QFa\027C\002I!a\001\rB.\005\004\021BAB\032\003\\\t\007!\003\002\0047\0057\022\rA\005\003\007s\tm#\031\001\n\005\rq\022YF1\001\023\t\031y$1\fb\001%!I!1\021\001\022\002\023\005!QQ\001\017G>\004\030\020\n3fM\006,H\016\036\0237+y\0219Ia#\003\016\n=%\021\023BJ\005+\0239J!'\003\034\nu%q\024BQ\005G\023)+\006\002\003\n*\032Q%a/\005\rE\021\tI1\001\023\t\031Y\"\021\021b\001%\0211aD!!C\002I!a!\tBA\005\004\021BA\002\023\003\002\n\007!\003\002\004(\005\003\023\rA\005\003\007U\t\005%\031\001\n\005\r5\022\tI1\001\023\t\031\001$\021\021b\001%\02111G!!C\002I!aA\016BA\005\004\021BAB\035\003\002\n\007!\003\002\004=\005\003\023\rA\005\003\007\t\005%\031\001\n\t\023\t%\006!%A\005\002\t-\026AD2paf$C-\0324bk2$HeN\013\037\005[\023\tLa-\0036\n]&\021\030B^\005{\023yL!1\003D\n\025'q\031Be\005\027,\"Aa,+\007!\nY\f\002\004\022\005O\023\rA\005\003\0077\t\035&\031\001\n\005\ry\0219K1\001\023\t\031\t#q\025b\001%\0211AEa*C\002I!aa\nBT\005\004\021BA\002\026\003(\n\007!\003\002\004.\005O\023\rA\005\003\007a\t\035&\031\001\n\005\rM\0229K1\001\023\t\0311$q\025b\001%\0211\021Ha*C\002I!a\001\020BT\005\004\021BAB \003(\n\007!\003C\005\003P\002\t\n\021\"\001\003R\006q1m\0349zI\021,g-Y;mi\022BTC\bBj\005/\024INa7\003^\n}'\021\035Br\005K\0249O!;\003l\n5(q\036By+\t\021)NK\002,\003w#a!\005Bg\005\004\021BAB\016\003N\n\007!\003\002\004\037\005\033\024\rA\005\003\007C\t5'\031\001\n\005\r\021\022iM1\001\023\t\0319#Q\032b\001%\0211!F!4C\002I!a!\fBg\005\004\021BA\002\031\003N\n\007!\003\002\0044\005\033\024\rA\005\003\007m\t5'\031\001\n\005\re\022iM1\001\023\t\031a$Q\032b\001%\0211qH!4C\002IA\021B!>\001#\003%\tAa>\002\035\r|\007/\037\023eK\032\fW\017\034;%sUq\"\021 B\005\034\taa\001\004\006\r\0351\021BB\006\007\033\031ya!\005\004\024\rU1qC\013\003\005wT3ALA^\t\031\t\"1\037b\001%\02111Da=C\002I!aA\bBz\005\004\021BAB\021\003t\n\007!\003\002\004%\005g\024\rA\005\003\007O\tM(\031\001\n\005\r)\022\031P1\001\023\t\031i#1\037b\001%\0211\001Ga=C\002I!aa\rBz\005\004\021BA\002\034\003t\n\007!\003\002\004:\005g\024\rA\005\003\007y\tM(\031\001\n\005\r}\022\031P1\001\023\021%\031Y\002AI\001\n\003\031i\"A\bd_BLH\005Z3gCVdG\017J\0311+y\031yba\t\004&\r\0352\021FB\026\007[\031yc!\r\0044\rU2qGB\035\007w\031i$\006\002\004\")\032\021'a/\005\rE\031IB1\001\023\t\031Y2\021\004b\001%\0211ad!\007C\002I!a!IB\r\005\004\021BA\002\023\004\032\t\007!\003\002\004(\0073\021\rA\005\003\007U\re!\031\001\n\005\r5\032IB1\001\023\t\031\0014\021\004b\001%\02111g!\007C\002I!aANB\r\005\004\021BAB\035\004\032\t\007!\003\002\004=\0073\021\rA\005\003\007\re!\031\001\n\t\023\r\005\003!%A\005\002\r\r\023aD2paf$C-\0324bk2$H%M\031\026=\r\0253\021JB&\007\033\032ye!\025\004T\rU3qKB-\0077\032ifa\030\004b\r\rTCAB$U\r!\0241\030\003\007#\r}\"\031\001\n\005\rm\031yD1\001\023\t\031q2q\bb\001%\0211\021ea\020C\002I!a\001JB \005\004\021BAB\024\004@\t\007!\003\002\004+\007\021\rA\005\003\007[\r}\"\031\001\n\005\rA\032yD1\001\023\t\031\0314q\bb\001%\0211aga\020C\002I!a!OB \005\004\021BA\002\037\004@\t\007!\003\002\004@\007\021\rA\005\005\n\007O\002\021\023!C\001\007S\nqbY8qs\022\"WMZ1vYR$\023GM\013\037\007W\032yg!\035\004t\rU4qOB=\007w\032iha \004\002\016\r5QQBD\007\023+\"a!\034+\007]\nY\f\002\004\022\007K\022\rA\005\003\0077\r\025$\031\001\n\005\ry\031)G1\001\023\t\031\t3Q\rb\001%\0211Ae!\032C\002I!aaJB3\005\004\021BA\002\026\004f\t\007!\003\002\004.\007K\022\rA\005\003\007a\r\025$\031\001\n\005\rM\032)G1\001\023\t\03114Q\rb\001%\0211\021h!\032C\002I!a\001PB3\005\004\021BAB \004f\t\007!\003C\005\004\016\002\t\n\021\"\001\004\020\006y1m\0349zI\021,g-Y;mi\022\n4'\006\020\004\022\016U5qSBM\0077\033ija(\004\"\016\r6QUBT\007S\033Yk!,\0040V\02111\023\026\004u\005mFAB\t\004\f\n\007!\003\002\004\034\007\027\023\rA\005\003\007=\r-%\031\001\n\005\r\005\032YI1\001\023\t\031!31\022b\001%\0211qea#C\002I!aAKBF\005\004\021BAB\027\004\f\n\007!\003\002\0041\007\027\023\rA\005\003\007g\r-%\031\001\n\005\rY\032YI1\001\023\t\031I41\022b\001%\0211Aha#C\002I!aaPBF\005\004\021\002\"CBZ\001E\005I\021AB[\003=\031w\016]=%I\0264\027-\0367uIE\"TCHB\\\007w\033ila0\004B\016\r7QYBd\007\023\034Ym!4\004P\016E71[Bk+\t\031ILK\002>\003w#a!EBY\005\004\021BAB\016\0042\n\007!\003\002\004\037\007c\023\rA\005\003\007C\rE&\031\001\n\005\r\021\032\tL1\001\023\t\03193\021\027b\001%\0211!f!-C\002I!a!LBY\005\004\021BA\002\031\0042\n\007!\003\002\0044\007c\023\rA\005\003\007m\rE&\031\001\n\005\re\032\tL1\001\023\t\031a4\021\027b\001%\0211qh!-C\002IA\021b!7\001\003\003%\tea7\002\033A\024x\016Z;diB\023XMZ5y+\t\t\031\005C\005\004`\002\t\t\021\"\021\004b\006y\001O]8ek\016$\030\n^3sCR|'/\006\002\004dB)1Q]Bv-5\0211q\035\006\004\007S\024\021AC2pY2,7\r^5p]&!1Q^Bt\005!IE/\032:bi>\024\b\"CBy\001\005\005I\021ABz\003!\031\027M\\#rk\006dG\003BB{\007w\0042\001CB|\023\r\031IP\001\002\b\005>|G.Z1o\021%\031ipa<\002\002\003\007a#A\002yIEB\021\002\"\001\001\003\003%\t\005b\001\002\021!\f7\017[\"pI\026$\"\001\"\002\021\007!!9!C\002\005\n\t\0211!\0238u\021%!i\001AA\001\n\003\"y!\001\004fcV\fGn\035\013\005\007k$\t\002C\005\004~\022-\021\021!a\001-\035IAQ\003\002\002\002#\005AqC\001\b)V\004H.Z\0315!\rAA\021\004\004\t\003\t\t\t\021#\001\005\034M!A\021D\004D\021!\tY\002\"\007\005\002\021}AC\001C\f\021)\ty\004\"\007\002\002\023\025\023\021\t\005\013\tK!I\"!A\005\002\022\035\022!B1qa2LXC\bC\025\t_!\031\004b\016\005<\021}B1\tC$\t\027\"y\005b\025\005X\021mCq\fC2)y!Y\003\"\032\005h\021%D1\016C7\t_\"\t\bb\035\005v\021]D\021\020C>\t{\"y\b\005\020\t\001\0215B\021\007C\033\ts!i\004\"\021\005F\021%CQ\nC)\t+\"I\006\"\030\005bA\031q\002b\f\005\rE!\031C1\001\023!\ryA1\007\003\0077\021\r\"\031\001\n\021\007=!9\004\002\004\037\tG\021\rA\005\t\004\037\021mBAB\021\005$\t\007!\003E\002\020\t!a\001\nC\022\005\004\021\002cA\b\005D\0211q\005b\tC\002I\0012a\004C$\t\031QC1\005b\001%A\031q\002b\023\005\r5\"\031C1\001\023!\ryAq\n\003\007a\021\r\"\031\001\n\021\007=!\031\006\002\0044\tG\021\rA\005\t\004\037\021]CA\002\034\005$\t\007!\003E\002\020\t7\"a!\017C\022\005\004\021\002cA\b\005`\0211A\bb\tC\002I\0012a\004C2\t\031yD1\005b\001%!9q\tb\tA\002\0215\002b\002'\005$\001\007A\021\007\005\b#\022\r\002\031\001C\033\021\0351F1\005a\001\tsAqa\027C\022\001\004!i\004C\004a\tG\001\r\001\"\021\t\017\025$\031\0031\001\005F!9!\016b\tA\002\021%\003bB8\005$\001\007AQ\n\005\bi\022\r\002\031\001C)\021\035IH1\005a\001\t+BqA C\022\001\004!I\006\003\005\002\b\021\r\002\031\001C/\021!\t\t\002b\tA\002\021\005\004B\003CB\t3\t\t\021\"!\005\006\0069QO\\1qa2LXC\bCD\t'#9\nb'\005 \022\rFq\025CV\t_#\031\fb.\005<\022}F1\031Cd)\021!I\t\"3\021\013!!Y\tb$\n\007\0215%A\001\004PaRLwN\034\t\037\021\001!\t\n\"&\005\032\022uE\021\025CS\tS#i\013\"-\0056\022eFQ\030Ca\t\013\0042a\004CJ\t\031\tB\021\021b\001%A\031q\002b&\005\rm!\tI1\001\023!\ryA1\024\003\007=\021\005%\031\001\n\021\007=!y\n\002\004\"\t\003\023\rA\005\t\004\037\021\rFA\002\023\005\002\n\007!\003E\002\020\tO#aa\nCA\005\004\021\002cA\b\005,\0221!\006\"!C\002I\0012a\004CX\t\031iC\021\021b\001%A\031q\002b-\005\rA\"\tI1\001\023!\ryAq\027\003\007g\021\005%\031\001\n\021\007=!Y\f\002\0047\t\003\023\rA\005\t\004\037\021}FAB\035\005\002\n\007!\003E\002\020\t\007$a\001\020CA\005\004\021\002cA\b\005H\0221q\b\"!C\002IA!\002b3\005\002\006\005\t\031\001CH\003\rAH\005\r\005\013\t\037$I\"!A\005\n\021E\027a\003:fC\022\024Vm]8mm\026$\"\001b5\021\t\005\025CQ[\005\005\t/\f9E\001\004PE*,7\r\036")
/*    */ public class Tuple14<T1, T2, T3, T4, T5, T6, T7, T8, T9, T10, T11, T12, T13, T14> implements Product14<T1, T2, T3, T4, T5, T6, T7, T8, T9, T10, T11, T12, T13, T14>, Product, Serializable {
/*    */   private final T1 _1;
/*    */   
/*    */   private final T2 _2;
/*    */   
/*    */   private final T3 _3;
/*    */   
/*    */   private final T4 _4;
/*    */   
/*    */   private final T5 _5;
/*    */   
/*    */   private final T6 _6;
/*    */   
/*    */   private final T7 _7;
/*    */   
/*    */   private final T8 _8;
/*    */   
/*    */   private final T9 _9;
/*    */   
/*    */   private final T10 _10;
/*    */   
/*    */   private final T11 _11;
/*    */   
/*    */   private final T12 _12;
/*    */   
/*    */   private final T13 _13;
/*    */   
/*    */   private final T14 _14;
/*    */   
/*    */   public int productArity() {
/* 31 */     return Product14$class.productArity(this);
/*    */   }
/*    */   
/*    */   public Object productElement(int n) throws IndexOutOfBoundsException {
/* 31 */     return Product14$class.productElement(this, n);
/*    */   }
/*    */   
/*    */   public T1 _1() {
/* 31 */     return this._1;
/*    */   }
/*    */   
/*    */   public T2 _2() {
/* 31 */     return this._2;
/*    */   }
/*    */   
/*    */   public T3 _3() {
/* 31 */     return this._3;
/*    */   }
/*    */   
/*    */   public T4 _4() {
/* 31 */     return this._4;
/*    */   }
/*    */   
/*    */   public T5 _5() {
/* 31 */     return this._5;
/*    */   }
/*    */   
/*    */   public T6 _6() {
/* 31 */     return this._6;
/*    */   }
/*    */   
/*    */   public T7 _7() {
/* 31 */     return this._7;
/*    */   }
/*    */   
/*    */   public T8 _8() {
/* 31 */     return this._8;
/*    */   }
/*    */   
/*    */   public T9 _9() {
/* 31 */     return this._9;
/*    */   }
/*    */   
/*    */   public T10 _10() {
/* 31 */     return this._10;
/*    */   }
/*    */   
/*    */   public T11 _11() {
/* 31 */     return this._11;
/*    */   }
/*    */   
/*    */   public T12 _12() {
/* 31 */     return this._12;
/*    */   }
/*    */   
/*    */   public T13 _13() {
/* 31 */     return this._13;
/*    */   }
/*    */   
/*    */   public T14 _14() {
/* 31 */     return this._14;
/*    */   }
/*    */   
/*    */   public <T1, T2, T3, T4, T5, T6, T7, T8, T9, T10, T11, T12, T13, T14> Tuple14<T1, T2, T3, T4, T5, T6, T7, T8, T9, T10, T11, T12, T13, T14> copy(Object _1, Object _2, Object _3, Object _4, Object _5, Object _6, Object _7, Object _8, Object _9, Object _10, Object _11, Object _12, Object _13, Object _14) {
/* 31 */     return new Tuple14((T1)_1, (T2)_2, (T3)_3, (T4)_4, (T5)_5, (T6)_6, (T7)_7, (T8)_8, (T9)_9, (T10)_10, (T11)_11, (T12)_12, (T13)_13, (T14)_14);
/*    */   }
/*    */   
/*    */   public <T1, T2, T3, T4, T5, T6, T7, T8, T9, T10, T11, T12, T13, T14> T1 copy$default$1() {
/* 31 */     return _1();
/*    */   }
/*    */   
/*    */   public <T1, T2, T3, T4, T5, T6, T7, T8, T9, T10, T11, T12, T13, T14> T2 copy$default$2() {
/* 31 */     return _2();
/*    */   }
/*    */   
/*    */   public <T1, T2, T3, T4, T5, T6, T7, T8, T9, T10, T11, T12, T13, T14> T3 copy$default$3() {
/* 31 */     return _3();
/*    */   }
/*    */   
/*    */   public <T1, T2, T3, T4, T5, T6, T7, T8, T9, T10, T11, T12, T13, T14> T4 copy$default$4() {
/* 31 */     return _4();
/*    */   }
/*    */   
/*    */   public <T1, T2, T3, T4, T5, T6, T7, T8, T9, T10, T11, T12, T13, T14> T5 copy$default$5() {
/* 31 */     return _5();
/*    */   }
/*    */   
/*    */   public <T1, T2, T3, T4, T5, T6, T7, T8, T9, T10, T11, T12, T13, T14> T6 copy$default$6() {
/* 31 */     return _6();
/*    */   }
/*    */   
/*    */   public <T1, T2, T3, T4, T5, T6, T7, T8, T9, T10, T11, T12, T13, T14> T7 copy$default$7() {
/* 31 */     return _7();
/*    */   }
/*    */   
/*    */   public <T1, T2, T3, T4, T5, T6, T7, T8, T9, T10, T11, T12, T13, T14> T8 copy$default$8() {
/* 31 */     return _8();
/*    */   }
/*    */   
/*    */   public <T1, T2, T3, T4, T5, T6, T7, T8, T9, T10, T11, T12, T13, T14> T9 copy$default$9() {
/* 31 */     return _9();
/*    */   }
/*    */   
/*    */   public <T1, T2, T3, T4, T5, T6, T7, T8, T9, T10, T11, T12, T13, T14> T10 copy$default$10() {
/* 31 */     return _10();
/*    */   }
/*    */   
/*    */   public <T1, T2, T3, T4, T5, T6, T7, T8, T9, T10, T11, T12, T13, T14> T11 copy$default$11() {
/* 31 */     return _11();
/*    */   }
/*    */   
/*    */   public <T1, T2, T3, T4, T5, T6, T7, T8, T9, T10, T11, T12, T13, T14> T12 copy$default$12() {
/* 31 */     return _12();
/*    */   }
/*    */   
/*    */   public <T1, T2, T3, T4, T5, T6, T7, T8, T9, T10, T11, T12, T13, T14> T13 copy$default$13() {
/* 31 */     return _13();
/*    */   }
/*    */   
/*    */   public <T1, T2, T3, T4, T5, T6, T7, T8, T9, T10, T11, T12, T13, T14> T14 copy$default$14() {
/* 31 */     return _14();
/*    */   }
/*    */   
/*    */   public String productPrefix() {
/* 31 */     return "Tuple14";
/*    */   }
/*    */   
/*    */   public Iterator<Object> productIterator() {
/* 31 */     return ScalaRunTime$.MODULE$.typedProductIterator(this);
/*    */   }
/*    */   
/*    */   public boolean canEqual(Object x$1) {
/* 31 */     return x$1 instanceof Tuple14;
/*    */   }
/*    */   
/*    */   public int hashCode() {
/* 31 */     return ScalaRunTime$.MODULE$._hashCode(this);
/*    */   }
/*    */   
/*    */   public boolean equals(Object x$1) {
/*    */     // Byte code:
/*    */     //   0: aload_0
/*    */     //   1: aload_1
/*    */     //   2: if_acmpeq -> 1215
/*    */     //   5: aload_1
/*    */     //   6: instanceof scala/Tuple14
/*    */     //   9: ifeq -> 17
/*    */     //   12: iconst_1
/*    */     //   13: istore_2
/*    */     //   14: goto -> 19
/*    */     //   17: iconst_0
/*    */     //   18: istore_2
/*    */     //   19: iload_2
/*    */     //   20: ifeq -> 1219
/*    */     //   23: aload_1
/*    */     //   24: checkcast scala/Tuple14
/*    */     //   27: astore #31
/*    */     //   29: aload_0
/*    */     //   30: invokevirtual _1 : ()Ljava/lang/Object;
/*    */     //   33: aload #31
/*    */     //   35: invokevirtual _1 : ()Ljava/lang/Object;
/*    */     //   38: astore #4
/*    */     //   40: dup
/*    */     //   41: astore_3
/*    */     //   42: aload #4
/*    */     //   44: if_acmpne -> 51
/*    */     //   47: iconst_1
/*    */     //   48: goto -> 103
/*    */     //   51: aload_3
/*    */     //   52: ifnonnull -> 59
/*    */     //   55: iconst_0
/*    */     //   56: goto -> 103
/*    */     //   59: aload_3
/*    */     //   60: instanceof java/lang/Number
/*    */     //   63: ifeq -> 78
/*    */     //   66: aload_3
/*    */     //   67: checkcast java/lang/Number
/*    */     //   70: aload #4
/*    */     //   72: invokestatic equalsNumObject : (Ljava/lang/Number;Ljava/lang/Object;)Z
/*    */     //   75: goto -> 103
/*    */     //   78: aload_3
/*    */     //   79: instanceof java/lang/Character
/*    */     //   82: ifeq -> 97
/*    */     //   85: aload_3
/*    */     //   86: checkcast java/lang/Character
/*    */     //   89: aload #4
/*    */     //   91: invokestatic equalsCharObject : (Ljava/lang/Character;Ljava/lang/Object;)Z
/*    */     //   94: goto -> 103
/*    */     //   97: aload_3
/*    */     //   98: aload #4
/*    */     //   100: invokevirtual equals : (Ljava/lang/Object;)Z
/*    */     //   103: ifeq -> 1211
/*    */     //   106: aload_0
/*    */     //   107: invokevirtual _2 : ()Ljava/lang/Object;
/*    */     //   110: aload #31
/*    */     //   112: invokevirtual _2 : ()Ljava/lang/Object;
/*    */     //   115: astore #6
/*    */     //   117: dup
/*    */     //   118: astore #5
/*    */     //   120: aload #6
/*    */     //   122: if_acmpne -> 129
/*    */     //   125: iconst_1
/*    */     //   126: goto -> 187
/*    */     //   129: aload #5
/*    */     //   131: ifnonnull -> 138
/*    */     //   134: iconst_0
/*    */     //   135: goto -> 187
/*    */     //   138: aload #5
/*    */     //   140: instanceof java/lang/Number
/*    */     //   143: ifeq -> 159
/*    */     //   146: aload #5
/*    */     //   148: checkcast java/lang/Number
/*    */     //   151: aload #6
/*    */     //   153: invokestatic equalsNumObject : (Ljava/lang/Number;Ljava/lang/Object;)Z
/*    */     //   156: goto -> 187
/*    */     //   159: aload #5
/*    */     //   161: instanceof java/lang/Character
/*    */     //   164: ifeq -> 180
/*    */     //   167: aload #5
/*    */     //   169: checkcast java/lang/Character
/*    */     //   172: aload #6
/*    */     //   174: invokestatic equalsCharObject : (Ljava/lang/Character;Ljava/lang/Object;)Z
/*    */     //   177: goto -> 187
/*    */     //   180: aload #5
/*    */     //   182: aload #6
/*    */     //   184: invokevirtual equals : (Ljava/lang/Object;)Z
/*    */     //   187: ifeq -> 1211
/*    */     //   190: aload_0
/*    */     //   191: invokevirtual _3 : ()Ljava/lang/Object;
/*    */     //   194: aload #31
/*    */     //   196: invokevirtual _3 : ()Ljava/lang/Object;
/*    */     //   199: astore #8
/*    */     //   201: dup
/*    */     //   202: astore #7
/*    */     //   204: aload #8
/*    */     //   206: if_acmpne -> 213
/*    */     //   209: iconst_1
/*    */     //   210: goto -> 271
/*    */     //   213: aload #7
/*    */     //   215: ifnonnull -> 222
/*    */     //   218: iconst_0
/*    */     //   219: goto -> 271
/*    */     //   222: aload #7
/*    */     //   224: instanceof java/lang/Number
/*    */     //   227: ifeq -> 243
/*    */     //   230: aload #7
/*    */     //   232: checkcast java/lang/Number
/*    */     //   235: aload #8
/*    */     //   237: invokestatic equalsNumObject : (Ljava/lang/Number;Ljava/lang/Object;)Z
/*    */     //   240: goto -> 271
/*    */     //   243: aload #7
/*    */     //   245: instanceof java/lang/Character
/*    */     //   248: ifeq -> 264
/*    */     //   251: aload #7
/*    */     //   253: checkcast java/lang/Character
/*    */     //   256: aload #8
/*    */     //   258: invokestatic equalsCharObject : (Ljava/lang/Character;Ljava/lang/Object;)Z
/*    */     //   261: goto -> 271
/*    */     //   264: aload #7
/*    */     //   266: aload #8
/*    */     //   268: invokevirtual equals : (Ljava/lang/Object;)Z
/*    */     //   271: ifeq -> 1211
/*    */     //   274: aload_0
/*    */     //   275: invokevirtual _4 : ()Ljava/lang/Object;
/*    */     //   278: aload #31
/*    */     //   280: invokevirtual _4 : ()Ljava/lang/Object;
/*    */     //   283: astore #10
/*    */     //   285: dup
/*    */     //   286: astore #9
/*    */     //   288: aload #10
/*    */     //   290: if_acmpne -> 297
/*    */     //   293: iconst_1
/*    */     //   294: goto -> 355
/*    */     //   297: aload #9
/*    */     //   299: ifnonnull -> 306
/*    */     //   302: iconst_0
/*    */     //   303: goto -> 355
/*    */     //   306: aload #9
/*    */     //   308: instanceof java/lang/Number
/*    */     //   311: ifeq -> 327
/*    */     //   314: aload #9
/*    */     //   316: checkcast java/lang/Number
/*    */     //   319: aload #10
/*    */     //   321: invokestatic equalsNumObject : (Ljava/lang/Number;Ljava/lang/Object;)Z
/*    */     //   324: goto -> 355
/*    */     //   327: aload #9
/*    */     //   329: instanceof java/lang/Character
/*    */     //   332: ifeq -> 348
/*    */     //   335: aload #9
/*    */     //   337: checkcast java/lang/Character
/*    */     //   340: aload #10
/*    */     //   342: invokestatic equalsCharObject : (Ljava/lang/Character;Ljava/lang/Object;)Z
/*    */     //   345: goto -> 355
/*    */     //   348: aload #9
/*    */     //   350: aload #10
/*    */     //   352: invokevirtual equals : (Ljava/lang/Object;)Z
/*    */     //   355: ifeq -> 1211
/*    */     //   358: aload_0
/*    */     //   359: invokevirtual _5 : ()Ljava/lang/Object;
/*    */     //   362: aload #31
/*    */     //   364: invokevirtual _5 : ()Ljava/lang/Object;
/*    */     //   367: astore #12
/*    */     //   369: dup
/*    */     //   370: astore #11
/*    */     //   372: aload #12
/*    */     //   374: if_acmpne -> 381
/*    */     //   377: iconst_1
/*    */     //   378: goto -> 439
/*    */     //   381: aload #11
/*    */     //   383: ifnonnull -> 390
/*    */     //   386: iconst_0
/*    */     //   387: goto -> 439
/*    */     //   390: aload #11
/*    */     //   392: instanceof java/lang/Number
/*    */     //   395: ifeq -> 411
/*    */     //   398: aload #11
/*    */     //   400: checkcast java/lang/Number
/*    */     //   403: aload #12
/*    */     //   405: invokestatic equalsNumObject : (Ljava/lang/Number;Ljava/lang/Object;)Z
/*    */     //   408: goto -> 439
/*    */     //   411: aload #11
/*    */     //   413: instanceof java/lang/Character
/*    */     //   416: ifeq -> 432
/*    */     //   419: aload #11
/*    */     //   421: checkcast java/lang/Character
/*    */     //   424: aload #12
/*    */     //   426: invokestatic equalsCharObject : (Ljava/lang/Character;Ljava/lang/Object;)Z
/*    */     //   429: goto -> 439
/*    */     //   432: aload #11
/*    */     //   434: aload #12
/*    */     //   436: invokevirtual equals : (Ljava/lang/Object;)Z
/*    */     //   439: ifeq -> 1211
/*    */     //   442: aload_0
/*    */     //   443: invokevirtual _6 : ()Ljava/lang/Object;
/*    */     //   446: aload #31
/*    */     //   448: invokevirtual _6 : ()Ljava/lang/Object;
/*    */     //   451: astore #14
/*    */     //   453: dup
/*    */     //   454: astore #13
/*    */     //   456: aload #14
/*    */     //   458: if_acmpne -> 465
/*    */     //   461: iconst_1
/*    */     //   462: goto -> 523
/*    */     //   465: aload #13
/*    */     //   467: ifnonnull -> 474
/*    */     //   470: iconst_0
/*    */     //   471: goto -> 523
/*    */     //   474: aload #13
/*    */     //   476: instanceof java/lang/Number
/*    */     //   479: ifeq -> 495
/*    */     //   482: aload #13
/*    */     //   484: checkcast java/lang/Number
/*    */     //   487: aload #14
/*    */     //   489: invokestatic equalsNumObject : (Ljava/lang/Number;Ljava/lang/Object;)Z
/*    */     //   492: goto -> 523
/*    */     //   495: aload #13
/*    */     //   497: instanceof java/lang/Character
/*    */     //   500: ifeq -> 516
/*    */     //   503: aload #13
/*    */     //   505: checkcast java/lang/Character
/*    */     //   508: aload #14
/*    */     //   510: invokestatic equalsCharObject : (Ljava/lang/Character;Ljava/lang/Object;)Z
/*    */     //   513: goto -> 523
/*    */     //   516: aload #13
/*    */     //   518: aload #14
/*    */     //   520: invokevirtual equals : (Ljava/lang/Object;)Z
/*    */     //   523: ifeq -> 1211
/*    */     //   526: aload_0
/*    */     //   527: invokevirtual _7 : ()Ljava/lang/Object;
/*    */     //   530: aload #31
/*    */     //   532: invokevirtual _7 : ()Ljava/lang/Object;
/*    */     //   535: astore #16
/*    */     //   537: dup
/*    */     //   538: astore #15
/*    */     //   540: aload #16
/*    */     //   542: if_acmpne -> 549
/*    */     //   545: iconst_1
/*    */     //   546: goto -> 607
/*    */     //   549: aload #15
/*    */     //   551: ifnonnull -> 558
/*    */     //   554: iconst_0
/*    */     //   555: goto -> 607
/*    */     //   558: aload #15
/*    */     //   560: instanceof java/lang/Number
/*    */     //   563: ifeq -> 579
/*    */     //   566: aload #15
/*    */     //   568: checkcast java/lang/Number
/*    */     //   571: aload #16
/*    */     //   573: invokestatic equalsNumObject : (Ljava/lang/Number;Ljava/lang/Object;)Z
/*    */     //   576: goto -> 607
/*    */     //   579: aload #15
/*    */     //   581: instanceof java/lang/Character
/*    */     //   584: ifeq -> 600
/*    */     //   587: aload #15
/*    */     //   589: checkcast java/lang/Character
/*    */     //   592: aload #16
/*    */     //   594: invokestatic equalsCharObject : (Ljava/lang/Character;Ljava/lang/Object;)Z
/*    */     //   597: goto -> 607
/*    */     //   600: aload #15
/*    */     //   602: aload #16
/*    */     //   604: invokevirtual equals : (Ljava/lang/Object;)Z
/*    */     //   607: ifeq -> 1211
/*    */     //   610: aload_0
/*    */     //   611: invokevirtual _8 : ()Ljava/lang/Object;
/*    */     //   614: aload #31
/*    */     //   616: invokevirtual _8 : ()Ljava/lang/Object;
/*    */     //   619: astore #18
/*    */     //   621: dup
/*    */     //   622: astore #17
/*    */     //   624: aload #18
/*    */     //   626: if_acmpne -> 633
/*    */     //   629: iconst_1
/*    */     //   630: goto -> 691
/*    */     //   633: aload #17
/*    */     //   635: ifnonnull -> 642
/*    */     //   638: iconst_0
/*    */     //   639: goto -> 691
/*    */     //   642: aload #17
/*    */     //   644: instanceof java/lang/Number
/*    */     //   647: ifeq -> 663
/*    */     //   650: aload #17
/*    */     //   652: checkcast java/lang/Number
/*    */     //   655: aload #18
/*    */     //   657: invokestatic equalsNumObject : (Ljava/lang/Number;Ljava/lang/Object;)Z
/*    */     //   660: goto -> 691
/*    */     //   663: aload #17
/*    */     //   665: instanceof java/lang/Character
/*    */     //   668: ifeq -> 684
/*    */     //   671: aload #17
/*    */     //   673: checkcast java/lang/Character
/*    */     //   676: aload #18
/*    */     //   678: invokestatic equalsCharObject : (Ljava/lang/Character;Ljava/lang/Object;)Z
/*    */     //   681: goto -> 691
/*    */     //   684: aload #17
/*    */     //   686: aload #18
/*    */     //   688: invokevirtual equals : (Ljava/lang/Object;)Z
/*    */     //   691: ifeq -> 1211
/*    */     //   694: aload_0
/*    */     //   695: invokevirtual _9 : ()Ljava/lang/Object;
/*    */     //   698: aload #31
/*    */     //   700: invokevirtual _9 : ()Ljava/lang/Object;
/*    */     //   703: astore #20
/*    */     //   705: dup
/*    */     //   706: astore #19
/*    */     //   708: aload #20
/*    */     //   710: if_acmpne -> 717
/*    */     //   713: iconst_1
/*    */     //   714: goto -> 775
/*    */     //   717: aload #19
/*    */     //   719: ifnonnull -> 726
/*    */     //   722: iconst_0
/*    */     //   723: goto -> 775
/*    */     //   726: aload #19
/*    */     //   728: instanceof java/lang/Number
/*    */     //   731: ifeq -> 747
/*    */     //   734: aload #19
/*    */     //   736: checkcast java/lang/Number
/*    */     //   739: aload #20
/*    */     //   741: invokestatic equalsNumObject : (Ljava/lang/Number;Ljava/lang/Object;)Z
/*    */     //   744: goto -> 775
/*    */     //   747: aload #19
/*    */     //   749: instanceof java/lang/Character
/*    */     //   752: ifeq -> 768
/*    */     //   755: aload #19
/*    */     //   757: checkcast java/lang/Character
/*    */     //   760: aload #20
/*    */     //   762: invokestatic equalsCharObject : (Ljava/lang/Character;Ljava/lang/Object;)Z
/*    */     //   765: goto -> 775
/*    */     //   768: aload #19
/*    */     //   770: aload #20
/*    */     //   772: invokevirtual equals : (Ljava/lang/Object;)Z
/*    */     //   775: ifeq -> 1211
/*    */     //   778: aload_0
/*    */     //   779: invokevirtual _10 : ()Ljava/lang/Object;
/*    */     //   782: aload #31
/*    */     //   784: invokevirtual _10 : ()Ljava/lang/Object;
/*    */     //   787: astore #22
/*    */     //   789: dup
/*    */     //   790: astore #21
/*    */     //   792: aload #22
/*    */     //   794: if_acmpne -> 801
/*    */     //   797: iconst_1
/*    */     //   798: goto -> 859
/*    */     //   801: aload #21
/*    */     //   803: ifnonnull -> 810
/*    */     //   806: iconst_0
/*    */     //   807: goto -> 859
/*    */     //   810: aload #21
/*    */     //   812: instanceof java/lang/Number
/*    */     //   815: ifeq -> 831
/*    */     //   818: aload #21
/*    */     //   820: checkcast java/lang/Number
/*    */     //   823: aload #22
/*    */     //   825: invokestatic equalsNumObject : (Ljava/lang/Number;Ljava/lang/Object;)Z
/*    */     //   828: goto -> 859
/*    */     //   831: aload #21
/*    */     //   833: instanceof java/lang/Character
/*    */     //   836: ifeq -> 852
/*    */     //   839: aload #21
/*    */     //   841: checkcast java/lang/Character
/*    */     //   844: aload #22
/*    */     //   846: invokestatic equalsCharObject : (Ljava/lang/Character;Ljava/lang/Object;)Z
/*    */     //   849: goto -> 859
/*    */     //   852: aload #21
/*    */     //   854: aload #22
/*    */     //   856: invokevirtual equals : (Ljava/lang/Object;)Z
/*    */     //   859: ifeq -> 1211
/*    */     //   862: aload_0
/*    */     //   863: invokevirtual _11 : ()Ljava/lang/Object;
/*    */     //   866: aload #31
/*    */     //   868: invokevirtual _11 : ()Ljava/lang/Object;
/*    */     //   871: astore #24
/*    */     //   873: dup
/*    */     //   874: astore #23
/*    */     //   876: aload #24
/*    */     //   878: if_acmpne -> 885
/*    */     //   881: iconst_1
/*    */     //   882: goto -> 943
/*    */     //   885: aload #23
/*    */     //   887: ifnonnull -> 894
/*    */     //   890: iconst_0
/*    */     //   891: goto -> 943
/*    */     //   894: aload #23
/*    */     //   896: instanceof java/lang/Number
/*    */     //   899: ifeq -> 915
/*    */     //   902: aload #23
/*    */     //   904: checkcast java/lang/Number
/*    */     //   907: aload #24
/*    */     //   909: invokestatic equalsNumObject : (Ljava/lang/Number;Ljava/lang/Object;)Z
/*    */     //   912: goto -> 943
/*    */     //   915: aload #23
/*    */     //   917: instanceof java/lang/Character
/*    */     //   920: ifeq -> 936
/*    */     //   923: aload #23
/*    */     //   925: checkcast java/lang/Character
/*    */     //   928: aload #24
/*    */     //   930: invokestatic equalsCharObject : (Ljava/lang/Character;Ljava/lang/Object;)Z
/*    */     //   933: goto -> 943
/*    */     //   936: aload #23
/*    */     //   938: aload #24
/*    */     //   940: invokevirtual equals : (Ljava/lang/Object;)Z
/*    */     //   943: ifeq -> 1211
/*    */     //   946: aload_0
/*    */     //   947: invokevirtual _12 : ()Ljava/lang/Object;
/*    */     //   950: aload #31
/*    */     //   952: invokevirtual _12 : ()Ljava/lang/Object;
/*    */     //   955: astore #26
/*    */     //   957: dup
/*    */     //   958: astore #25
/*    */     //   960: aload #26
/*    */     //   962: if_acmpne -> 969
/*    */     //   965: iconst_1
/*    */     //   966: goto -> 1027
/*    */     //   969: aload #25
/*    */     //   971: ifnonnull -> 978
/*    */     //   974: iconst_0
/*    */     //   975: goto -> 1027
/*    */     //   978: aload #25
/*    */     //   980: instanceof java/lang/Number
/*    */     //   983: ifeq -> 999
/*    */     //   986: aload #25
/*    */     //   988: checkcast java/lang/Number
/*    */     //   991: aload #26
/*    */     //   993: invokestatic equalsNumObject : (Ljava/lang/Number;Ljava/lang/Object;)Z
/*    */     //   996: goto -> 1027
/*    */     //   999: aload #25
/*    */     //   1001: instanceof java/lang/Character
/*    */     //   1004: ifeq -> 1020
/*    */     //   1007: aload #25
/*    */     //   1009: checkcast java/lang/Character
/*    */     //   1012: aload #26
/*    */     //   1014: invokestatic equalsCharObject : (Ljava/lang/Character;Ljava/lang/Object;)Z
/*    */     //   1017: goto -> 1027
/*    */     //   1020: aload #25
/*    */     //   1022: aload #26
/*    */     //   1024: invokevirtual equals : (Ljava/lang/Object;)Z
/*    */     //   1027: ifeq -> 1211
/*    */     //   1030: aload_0
/*    */     //   1031: invokevirtual _13 : ()Ljava/lang/Object;
/*    */     //   1034: aload #31
/*    */     //   1036: invokevirtual _13 : ()Ljava/lang/Object;
/*    */     //   1039: astore #28
/*    */     //   1041: dup
/*    */     //   1042: astore #27
/*    */     //   1044: aload #28
/*    */     //   1046: if_acmpne -> 1053
/*    */     //   1049: iconst_1
/*    */     //   1050: goto -> 1111
/*    */     //   1053: aload #27
/*    */     //   1055: ifnonnull -> 1062
/*    */     //   1058: iconst_0
/*    */     //   1059: goto -> 1111
/*    */     //   1062: aload #27
/*    */     //   1064: instanceof java/lang/Number
/*    */     //   1067: ifeq -> 1083
/*    */     //   1070: aload #27
/*    */     //   1072: checkcast java/lang/Number
/*    */     //   1075: aload #28
/*    */     //   1077: invokestatic equalsNumObject : (Ljava/lang/Number;Ljava/lang/Object;)Z
/*    */     //   1080: goto -> 1111
/*    */     //   1083: aload #27
/*    */     //   1085: instanceof java/lang/Character
/*    */     //   1088: ifeq -> 1104
/*    */     //   1091: aload #27
/*    */     //   1093: checkcast java/lang/Character
/*    */     //   1096: aload #28
/*    */     //   1098: invokestatic equalsCharObject : (Ljava/lang/Character;Ljava/lang/Object;)Z
/*    */     //   1101: goto -> 1111
/*    */     //   1104: aload #27
/*    */     //   1106: aload #28
/*    */     //   1108: invokevirtual equals : (Ljava/lang/Object;)Z
/*    */     //   1111: ifeq -> 1211
/*    */     //   1114: aload_0
/*    */     //   1115: invokevirtual _14 : ()Ljava/lang/Object;
/*    */     //   1118: aload #31
/*    */     //   1120: invokevirtual _14 : ()Ljava/lang/Object;
/*    */     //   1123: astore #30
/*    */     //   1125: dup
/*    */     //   1126: astore #29
/*    */     //   1128: aload #30
/*    */     //   1130: if_acmpne -> 1137
/*    */     //   1133: iconst_1
/*    */     //   1134: goto -> 1195
/*    */     //   1137: aload #29
/*    */     //   1139: ifnonnull -> 1146
/*    */     //   1142: iconst_0
/*    */     //   1143: goto -> 1195
/*    */     //   1146: aload #29
/*    */     //   1148: instanceof java/lang/Number
/*    */     //   1151: ifeq -> 1167
/*    */     //   1154: aload #29
/*    */     //   1156: checkcast java/lang/Number
/*    */     //   1159: aload #30
/*    */     //   1161: invokestatic equalsNumObject : (Ljava/lang/Number;Ljava/lang/Object;)Z
/*    */     //   1164: goto -> 1195
/*    */     //   1167: aload #29
/*    */     //   1169: instanceof java/lang/Character
/*    */     //   1172: ifeq -> 1188
/*    */     //   1175: aload #29
/*    */     //   1177: checkcast java/lang/Character
/*    */     //   1180: aload #30
/*    */     //   1182: invokestatic equalsCharObject : (Ljava/lang/Character;Ljava/lang/Object;)Z
/*    */     //   1185: goto -> 1195
/*    */     //   1188: aload #29
/*    */     //   1190: aload #30
/*    */     //   1192: invokevirtual equals : (Ljava/lang/Object;)Z
/*    */     //   1195: ifeq -> 1211
/*    */     //   1198: aload #31
/*    */     //   1200: aload_0
/*    */     //   1201: invokevirtual canEqual : (Ljava/lang/Object;)Z
/*    */     //   1204: ifeq -> 1211
/*    */     //   1207: iconst_1
/*    */     //   1208: goto -> 1212
/*    */     //   1211: iconst_0
/*    */     //   1212: ifeq -> 1219
/*    */     //   1215: iconst_1
/*    */     //   1216: goto -> 1220
/*    */     //   1219: iconst_0
/*    */     //   1220: ireturn
/*    */     // Line number table:
/*    */     //   Java source line number -> byte code offset
/*    */     //   #31	-> 0
/*    */     //   #236	-> 12
/*    */     //   #31	-> 19
/*    */     // Local variable table:
/*    */     //   start	length	slot	name	descriptor
/*    */     //   0	1221	0	this	Lscala/Tuple14;
/*    */     //   0	1221	1	x$1	Ljava/lang/Object;
/*    */   }
/*    */   
/*    */   public Tuple14(Object _1, Object _2, Object _3, Object _4, Object _5, Object _6, Object _7, Object _8, Object _9, Object _10, Object _11, Object _12, Object _13, Object _14) {
/* 31 */     Product$class.$init$(this);
/* 31 */     Product14$class.$init$(this);
/*    */   }
/*    */   
/*    */   public String toString() {
/* 35 */     return (new StringBuilder()).append("(").append(_1()).append(",").append(_2()).append(",").append(_3()).append(",").append(_4()).append(",").append(_5()).append(",").append(_6()).append(",").append(_7()).append(",").append(_8()).append(",").append(_9()).append(",").append(_10()).append(",").append(_11()).append(",").append(_12()).append(",").append(_13()).append(",").append(_14()).append(")").toString();
/*    */   }
/*    */ }


/* Location:              D:\#source-code\TheFlightSims\TFSLibrary\World2Xplane\World2XPlane.jar!\scala\Tuple14.class
 * Java compiler version: 6 (50.0)
 * JD-Core Version:       1.1.3
 */