/*    */ package scala;
/*    */ 
/*    */ import scala.collection.Iterator;
/*    */ import scala.collection.mutable.StringBuilder;
/*    */ import scala.reflect.ScalaSignature;
/*    */ import scala.runtime.ScalaRunTime$;
/*    */ 
/*    */ @ScalaSignature(bytes = "\006\001\r}f\001B\001\003\001\026\021q\001V;qY\026\f\024GC\001\004\003\025\0318-\0317b\007\001)BB\002\t\033;\001\032c%\013\0270eU\032R\001A\004\foi\002\"\001C\005\016\003\tI!A\003\002\003\r\005s\027PU3g!5AABD\r\035?\t*\003f\013\0302i%\021QB\001\002\n!J|G-^2ucE\002\"a\004\t\r\001\0211\021\003\001CC\002I\021!\001V\031\022\005M1\002C\001\005\025\023\t)\"AA\004O_RD\027N\\4\021\005!9\022B\001\r\003\005\r\te.\037\t\003\037i!aa\007\001\005\006\004\021\"A\001+3!\tyQ\004\002\004\037\001\021\025\rA\005\002\003)N\002\"a\004\021\005\r\005\002AQ1\001\023\005\t!F\007\005\002\020G\0211A\005\001CC\002I\021!\001V\033\021\005=1CAB\024\001\t\013\007!C\001\002UmA\021q\"\013\003\007U\001!)\031\001\n\003\005Q;\004CA\b-\t\031i\003\001\"b\001%\t\021A\013\017\t\003\037=\"a\001\r\001\005\006\004\021\"A\001+:!\ty!\007\002\0044\001\021\025\rA\005\002\004)F\002\004CA\b6\t\0311\004\001\"b\001%\t\031A+M\031\021\005!A\024BA\035\003\005\035\001&o\0343vGR\004\"\001C\036\n\005q\022!\001D*fe&\fG.\033>bE2,\007\002\003 \001\005+\007I\021A \002\005}\013T#\001\b\t\021\005\003!\021#Q\001\n9\t1aX\031!\021!\031\005A!f\001\n\003!\025AA03+\005I\002\002\003$\001\005#\005\013\021B\r\002\007}\023\004\005\003\005I\001\tU\r\021\"\001J\003\ty6'F\001\035\021!Y\005A!E!\002\023a\022aA04A!AQ\n\001BK\002\023\005a*\001\002`iU\tq\004\003\005Q\001\tE\t\025!\003 \003\ryF\007\t\005\t%\002\021)\032!C\001'\006\021q,N\013\002E!AQ\013\001B\tB\003%!%A\002`k\001B\001b\026\001\003\026\004%\t\001W\001\003?Z*\022!\n\005\t5\002\021\t\022)A\005K\005\031qL\016\021\t\021q\003!Q3A\005\002u\013!aX\034\026\003!B\001b\030\001\003\022\003\006I\001K\001\004?^\002\003\002C1\001\005+\007I\021\0012\002\005}CT#A\026\t\021\021\004!\021#Q\001\n-\n1a\030\035!\021!1\007A!f\001\n\0039\027AA0:+\005q\003\002C5\001\005#\005\013\021\002\030\002\007}K\004\005\003\005l\001\tU\r\021\"\001m\003\ry\026\007M\013\002c!Aa\016\001B\tB\003%\021'\001\003`cA\002\003\002\0039\001\005+\007I\021A9\002\007}\013\024'F\0015\021!\031\bA!E!\002\023!\024\001B02c\001BQ!\036\001\005\002Y\fa\001P5oSRtDcD<ysj\\H0 @\000\003\003\t\031!!\002\021\033!\001a\"\007\017 E\025B3FL\0315\021\025qD\0171\001\017\021\025\031E\0171\001\032\021\025AE\0171\001\035\021\025iE\0171\001 \021\025\021F\0171\001#\021\0259F\0171\001&\021\025aF\0171\001)\021\025\tG\0171\001,\021\0251G\0171\001/\021\025YG\0171\0012\021\025\001H\0171\0015\021\035\tI\001\001C!\003\027\t\001\002^8TiJLgn\032\013\003\003\033\001B!a\004\002\0325\021\021\021\003\006\005\003'\t)\"\001\003mC:<'BAA\f\003\021Q\027M^1\n\t\005m\021\021\003\002\007'R\024\030N\\4\t\023\005}\001!!A\005\002\005\005\022\001B2paf,\002$a\t\002*\0055\022\021GA\033\003s\ti$!\021\002F\005%\023QJA))a\t)#a\025\002V\005]\023\021LA.\003;\ny&!\031\002d\005\025\024q\r\t\031\021\001\t9#a\013\0020\005M\022qGA\036\003\t\031%a\022\002L\005=\003cA\b\002*\0211\021#!\bC\002I\0012aDA\027\t\031Y\022Q\004b\001%A\031q\"!\r\005\ry\tiB1\001\023!\ry\021Q\007\003\007C\005u!\031\001\n\021\007=\tI\004\002\004%\003;\021\rA\005\t\004\037\005uBAB\024\002\036\t\007!\003E\002\020\003\003\"aAKA\017\005\004\021\002cA\b\002F\0211Q&!\bC\002I\0012aDA%\t\031\001\024Q\004b\001%A\031q\"!\024\005\rM\niB1\001\023!\ry\021\021\013\003\007m\005u!\031\001\n\t\023y\ni\002%AA\002\005\035\002\"C\"\002\036A\005\t\031AA\026\021%A\025Q\004I\001\002\004\ty\003C\005N\003;\001\n\0211\001\0024!I!+!\b\021\002\003\007\021q\007\005\n/\006u\001\023!a\001\003wA\021\002XA\017!\003\005\r!a\020\t\023\005\fi\002%AA\002\005\r\003\"\0034\002\036A\005\t\031AA$\021%Y\027Q\004I\001\002\004\tY\005C\005q\003;\001\n\0211\001\002P!I\0211\016\001\022\002\023\005\021QN\001\017G>\004\030\020\n3fM\006,H\016\036\0232+a\ty'!\"\002\b\006%\0251RAG\003\037\013\t*a%\002\026\006]\025\021T\013\003\003cR3ADA:W\t\t)\b\005\003\002x\005\005UBAA=\025\021\tY(! \002\023Ut7\r[3dW\026$'bAA@\005\005Q\021M\0348pi\006$\030n\0348\n\t\005\r\025\021\020\002\022k:\034\007.Z2lK\0224\026M]5b]\016,GAB\t\002j\t\007!\003\002\004\034\003S\022\rA\005\003\007=\005%$\031\001\n\005\r\005\nIG1\001\023\t\031!\023\021\016b\001%\0211q%!\033C\002I!aAKA5\005\004\021BAB\027\002j\t\007!\003\002\0041\003S\022\rA\005\003\007g\005%$\031\001\n\005\rY\nIG1\001\023\021%\ti\nAI\001\n\003\ty*\001\bd_BLH\005Z3gCVdG\017\n\032\0261\005\005\026QUAT\003S\013Y+!,\0020\006E\0261WA[\003o\013I,\006\002\002$*\032\021$a\035\005\rE\tYJ1\001\023\t\031Y\0221\024b\001%\0211a$a'C\002I!a!IAN\005\004\021BA\002\023\002\034\n\007!\003\002\004(\0037\023\rA\005\003\007U\005m%\031\001\n\005\r5\nYJ1\001\023\t\031\001\0241\024b\001%\02111'a'C\002I!aANAN\005\004\021\002\"CA_\001E\005I\021AA`\0039\031w\016]=%I\0264\027-\0367uIM*\002$!1\002F\006\035\027\021ZAf\003\033\fy-!5\002T\006U\027q[Am+\t\t\031MK\002\035\003g\"a!EA^\005\004\021BAB\016\002<\n\007!\003\002\004\037\003w\023\rA\005\003\007C\005m&\031\001\n\005\r\021\nYL1\001\023\t\0319\0231\030b\001%\0211!&a/C\002I!a!LA^\005\004\021BA\002\031\002<\n\007!\003\002\0044\003w\023\rA\005\003\007m\005m&\031\001\n\t\023\005u\007!%A\005\002\005}\027AD2paf$C-\0324bk2$H\005N\013\031\003C\f)/a:\002j\006-\030Q^Ax\003c\f\0310!>\002x\006eXCAArU\ry\0221\017\003\007#\005m'\031\001\n\005\rm\tYN1\001\023\t\031q\0221\034b\001%\0211\021%a7C\002I!a\001JAn\005\004\021BAB\024\002\\\n\007!\003\002\004+\0037\024\rA\005\003\007[\005m'\031\001\n\005\rA\nYN1\001\023\t\031\031\0241\034b\001%\0211a'a7C\002IA\021\"!@\001#\003%\t!a@\002\035\r|\007/\037\023eK\032\fW\017\034;%kUA\"\021\001B\003\005\017\021IAa\003\003\016\t=!\021\003B\n\005+\0219B!\007\026\005\t\r!f\001\022\002t\0211\021#a?C\002I!aaGA~\005\004\021BA\002\020\002|\n\007!\003\002\004\"\003w\024\rA\005\003\007I\005m(\031\001\n\005\r\035\nYP1\001\023\t\031Q\0231 b\001%\0211Q&a?C\002I!a\001MA~\005\004\021BAB\032\002|\n\007!\003\002\0047\003w\024\rA\005\005\n\005;\001\021\023!C\001\005?\tabY8qs\022\"WMZ1vYR$c'\006\r\003\"\t\025\"q\005B\025\005W\021iCa\f\0032\tM\"Q\007B\034\005s)\"Aa\t+\007\025\n\031\b\002\004\022\0057\021\rA\005\003\0077\tm!\031\001\n\005\ry\021YB1\001\023\t\031\t#1\004b\001%\0211AEa\007C\002I!aa\nB\016\005\004\021BA\002\026\003\034\t\007!\003\002\004.\0057\021\rA\005\003\007a\tm!\031\001\n\005\rM\022YB1\001\023\t\0311$1\004b\001%!I!Q\b\001\022\002\023\005!qH\001\017G>\004\030\020\n3fM\006,H\016\036\0238+a\021\tE!\022\003H\t%#1\nB'\005\037\022\tFa\025\003V\t]#\021L\013\003\005\007R3\001KA:\t\031\t\"1\bb\001%\02111Da\017C\002I!aA\bB\036\005\004\021BAB\021\003<\t\007!\003\002\004%\005w\021\rA\005\003\007O\tm\"\031\001\n\005\r)\022YD1\001\023\t\031i#1\bb\001%\0211\001Ga\017C\002I!aa\rB\036\005\004\021BA\002\034\003<\t\007!\003C\005\003^\001\t\n\021\"\001\003`\005q1m\0349zI\021,g-Y;mi\022BT\003\007B1\005K\0229G!\033\003l\t5$q\016B9\005g\022)Ha\036\003zU\021!1\r\026\004W\005MDAB\t\003\\\t\007!\003\002\004\034\0057\022\rA\005\003\007=\tm#\031\001\n\005\r\005\022YF1\001\023\t\031!#1\fb\001%\0211qEa\027C\002I!aA\013B.\005\004\021BAB\027\003\\\t\007!\003\002\0041\0057\022\rA\005\003\007g\tm#\031\001\n\005\rY\022YF1\001\023\021%\021i\bAI\001\n\003\021y(\001\bd_BLH\005Z3gCVdG\017J\035\0261\t\005%Q\021BD\005\023\023YI!$\003\020\nE%1\023BK\005/\023I*\006\002\003\004*\032a&a\035\005\rE\021YH1\001\023\t\031Y\"1\020b\001%\0211aDa\037C\002I!a!\tB>\005\004\021BA\002\023\003|\t\007!\003\002\004(\005w\022\rA\005\003\007U\tm$\031\001\n\005\r5\022YH1\001\023\t\031\001$1\020b\001%\02111Ga\037C\002I!aA\016B>\005\004\021\002\"\003BO\001E\005I\021\001BP\003=\031w\016]=%I\0264\027-\0367uIE\002T\003\007BQ\005K\0239K!+\003,\n5&q\026BY\005g\023)La.\003:V\021!1\025\026\004c\005MDAB\t\003\034\n\007!\003\002\004\034\0057\023\rA\005\003\007=\tm%\031\001\n\005\r\005\022YJ1\001\023\t\031!#1\024b\001%\0211qEa'C\002I!aA\013BN\005\004\021BAB\027\003\034\n\007!\003\002\0041\0057\023\rA\005\003\007g\tm%\031\001\n\005\rY\022YJ1\001\023\021%\021i\fAI\001\n\003\021y,A\bd_BLH\005Z3gCVdG\017J\0312+a\021\tM!2\003H\n%'1\032Bg\005\037\024\tNa5\003V\n]'\021\\\013\003\005\007T3\001NA:\t\031\t\"1\030b\001%\02111Da/C\002I!aA\bB^\005\004\021BAB\021\003<\n\007!\003\002\004%\005w\023\rA\005\003\007O\tm&\031\001\n\005\r)\022YL1\001\023\t\031i#1\030b\001%\0211\001Ga/C\002I!aa\rB^\005\004\021BA\002\034\003<\n\007!\003C\005\003^\002\t\t\021\"\021\003`\006i\001O]8ek\016$\bK]3gSb,\"!!\004\t\023\t\r\b!!A\005B\t\025\030a\0049s_\022,8\r^%uKJ\fGo\034:\026\005\t\035\b#\002Bu\005_4RB\001Bv\025\r\021iOA\001\013G>dG.Z2uS>t\027\002\002By\005W\024\001\"\023;fe\006$xN\035\005\n\005k\004\021\021!C\001\005o\f\001bY1o\013F,\030\r\034\013\005\005s\024y\020E\002\t\005wL1A!@\003\005\035\021un\0347fC:D\021b!\001\003t\006\005\t\031\001\f\002\007a$\023\007C\005\004\006\001\t\t\021\"\021\004\b\005A\001.Y:i\007>$W\r\006\002\004\nA\031\001ba\003\n\007\r5!AA\002J]RD\021b!\005\001\003\003%\tea\005\002\r\025\fX/\0317t)\021\021Ip!\006\t\023\r\0051qBA\001\002\0041r!CB\r\005\005\005\t\022AB\016\003\035!V\017\0357fcE\0022\001CB\017\r!\t!!!A\t\002\r}1\003BB\017\017iBq!^B\017\t\003\031\031\003\006\002\004\034!Q\021\021BB\017\003\003%)%a\003\t\025\r%2QDA\001\n\003\033Y#A\003baBd\0270\006\r\004.\rM2qGB\036\007\031\031ea\022\004L\r=31KB,\0077\"\002da\f\004^\r}3\021MB2\007K\0329g!\033\004l\r54qNB9!aA\001a!\r\0046\re2QHB!\007\013\032Ie!\024\004R\rU3\021\f\t\004\037\rMBAB\t\004(\t\007!\003E\002\020\007o!aaGB\024\005\004\021\002cA\b\004<\0211ada\nC\002I\0012aDB \t\031\t3q\005b\001%A\031qba\021\005\r\021\0329C1\001\023!\ry1q\t\003\007O\r\035\"\031\001\n\021\007=\031Y\005\002\004+\007O\021\rA\005\t\004\037\r=CAB\027\004(\t\007!\003E\002\020\007'\"a\001MB\024\005\004\021\002cA\b\004X\02111ga\nC\002I\0012aDB.\t\03114q\005b\001%!9aha\nA\002\rE\002bB\"\004(\001\0071Q\007\005\b\021\016\035\002\031AB\035\021\035i5q\005a\001\007{AqAUB\024\001\004\031\t\005C\004X\007O\001\ra!\022\t\017q\0339\0031\001\004J!9\021ma\nA\002\r5\003b\0024\004(\001\0071\021\013\005\bW\016\035\002\031AB+\021\035\0018q\005a\001\0073B!b!\036\004\036\005\005I\021QB<\003\035)h.\0319qYf,\002d!\037\004\006\016%5QRBI\007+\033Ij!(\004\"\016\0256\021VBW)\021\031Yha,\021\013!\031ih!!\n\007\r}$A\001\004PaRLwN\034\t\031\021\001\031\031ia\"\004\f\016=51SBL\0077\033yja)\004(\016-\006cA\b\004\006\0221\021ca\035C\002I\0012aDBE\t\031Y21\017b\001%A\031qb!$\005\ry\031\031H1\001\023!\ry1\021\023\003\007C\rM$\031\001\n\021\007=\031)\n\002\004%\007g\022\rA\005\t\004\037\reEAB\024\004t\t\007!\003E\002\020\007;#aAKB:\005\004\021\002cA\b\004\"\0221Qfa\035C\002I\0012aDBS\t\031\00141\017b\001%A\031qb!+\005\rM\032\031H1\001\023!\ry1Q\026\003\007m\rM$\031\001\n\t\025\rE61OA\001\002\004\031\t)A\002yIAB!b!.\004\036\005\005I\021BB\\\003-\021X-\0313SKN|GN^3\025\005\re\006\003BA\b\007wKAa!0\002\022\t1qJ\0316fGR\004")
/*    */ public class Tuple11<T1, T2, T3, T4, T5, T6, T7, T8, T9, T10, T11> implements Product11<T1, T2, T3, T4, T5, T6, T7, T8, T9, T10, T11>, Product, Serializable {
/*    */   private final T1 _1;
/*    */   
/*    */   private final T2 _2;
/*    */   
/*    */   private final T3 _3;
/*    */   
/*    */   private final T4 _4;
/*    */   
/*    */   private final T5 _5;
/*    */   
/*    */   private final T6 _6;
/*    */   
/*    */   private final T7 _7;
/*    */   
/*    */   private final T8 _8;
/*    */   
/*    */   private final T9 _9;
/*    */   
/*    */   private final T10 _10;
/*    */   
/*    */   private final T11 _11;
/*    */   
/*    */   public int productArity() {
/* 28 */     return Product11$class.productArity(this);
/*    */   }
/*    */   
/*    */   public Object productElement(int n) throws IndexOutOfBoundsException {
/* 28 */     return Product11$class.productElement(this, n);
/*    */   }
/*    */   
/*    */   public T1 _1() {
/* 28 */     return this._1;
/*    */   }
/*    */   
/*    */   public T2 _2() {
/* 28 */     return this._2;
/*    */   }
/*    */   
/*    */   public T3 _3() {
/* 28 */     return this._3;
/*    */   }
/*    */   
/*    */   public T4 _4() {
/* 28 */     return this._4;
/*    */   }
/*    */   
/*    */   public T5 _5() {
/* 28 */     return this._5;
/*    */   }
/*    */   
/*    */   public T6 _6() {
/* 28 */     return this._6;
/*    */   }
/*    */   
/*    */   public T7 _7() {
/* 28 */     return this._7;
/*    */   }
/*    */   
/*    */   public T8 _8() {
/* 28 */     return this._8;
/*    */   }
/*    */   
/*    */   public T9 _9() {
/* 28 */     return this._9;
/*    */   }
/*    */   
/*    */   public T10 _10() {
/* 28 */     return this._10;
/*    */   }
/*    */   
/*    */   public T11 _11() {
/* 28 */     return this._11;
/*    */   }
/*    */   
/*    */   public <T1, T2, T3, T4, T5, T6, T7, T8, T9, T10, T11> Tuple11<T1, T2, T3, T4, T5, T6, T7, T8, T9, T10, T11> copy(Object _1, Object _2, Object _3, Object _4, Object _5, Object _6, Object _7, Object _8, Object _9, Object _10, Object _11) {
/* 28 */     return new Tuple11((T1)_1, (T2)_2, (T3)_3, (T4)_4, (T5)_5, (T6)_6, (T7)_7, (T8)_8, (T9)_9, (T10)_10, (T11)_11);
/*    */   }
/*    */   
/*    */   public <T1, T2, T3, T4, T5, T6, T7, T8, T9, T10, T11> T1 copy$default$1() {
/* 28 */     return _1();
/*    */   }
/*    */   
/*    */   public <T1, T2, T3, T4, T5, T6, T7, T8, T9, T10, T11> T2 copy$default$2() {
/* 28 */     return _2();
/*    */   }
/*    */   
/*    */   public <T1, T2, T3, T4, T5, T6, T7, T8, T9, T10, T11> T3 copy$default$3() {
/* 28 */     return _3();
/*    */   }
/*    */   
/*    */   public <T1, T2, T3, T4, T5, T6, T7, T8, T9, T10, T11> T4 copy$default$4() {
/* 28 */     return _4();
/*    */   }
/*    */   
/*    */   public <T1, T2, T3, T4, T5, T6, T7, T8, T9, T10, T11> T5 copy$default$5() {
/* 28 */     return _5();
/*    */   }
/*    */   
/*    */   public <T1, T2, T3, T4, T5, T6, T7, T8, T9, T10, T11> T6 copy$default$6() {
/* 28 */     return _6();
/*    */   }
/*    */   
/*    */   public <T1, T2, T3, T4, T5, T6, T7, T8, T9, T10, T11> T7 copy$default$7() {
/* 28 */     return _7();
/*    */   }
/*    */   
/*    */   public <T1, T2, T3, T4, T5, T6, T7, T8, T9, T10, T11> T8 copy$default$8() {
/* 28 */     return _8();
/*    */   }
/*    */   
/*    */   public <T1, T2, T3, T4, T5, T6, T7, T8, T9, T10, T11> T9 copy$default$9() {
/* 28 */     return _9();
/*    */   }
/*    */   
/*    */   public <T1, T2, T3, T4, T5, T6, T7, T8, T9, T10, T11> T10 copy$default$10() {
/* 28 */     return _10();
/*    */   }
/*    */   
/*    */   public <T1, T2, T3, T4, T5, T6, T7, T8, T9, T10, T11> T11 copy$default$11() {
/* 28 */     return _11();
/*    */   }
/*    */   
/*    */   public String productPrefix() {
/* 28 */     return "Tuple11";
/*    */   }
/*    */   
/*    */   public Iterator<Object> productIterator() {
/* 28 */     return ScalaRunTime$.MODULE$.typedProductIterator(this);
/*    */   }
/*    */   
/*    */   public boolean canEqual(Object x$1) {
/* 28 */     return x$1 instanceof Tuple11;
/*    */   }
/*    */   
/*    */   public int hashCode() {
/* 28 */     return ScalaRunTime$.MODULE$._hashCode(this);
/*    */   }
/*    */   
/*    */   public boolean equals(Object x$1) {
/*    */     // Byte code:
/*    */     //   0: aload_0
/*    */     //   1: aload_1
/*    */     //   2: if_acmpeq -> 963
/*    */     //   5: aload_1
/*    */     //   6: instanceof scala/Tuple11
/*    */     //   9: ifeq -> 17
/*    */     //   12: iconst_1
/*    */     //   13: istore_2
/*    */     //   14: goto -> 19
/*    */     //   17: iconst_0
/*    */     //   18: istore_2
/*    */     //   19: iload_2
/*    */     //   20: ifeq -> 967
/*    */     //   23: aload_1
/*    */     //   24: checkcast scala/Tuple11
/*    */     //   27: astore #25
/*    */     //   29: aload_0
/*    */     //   30: invokevirtual _1 : ()Ljava/lang/Object;
/*    */     //   33: aload #25
/*    */     //   35: invokevirtual _1 : ()Ljava/lang/Object;
/*    */     //   38: astore #4
/*    */     //   40: dup
/*    */     //   41: astore_3
/*    */     //   42: aload #4
/*    */     //   44: if_acmpne -> 51
/*    */     //   47: iconst_1
/*    */     //   48: goto -> 103
/*    */     //   51: aload_3
/*    */     //   52: ifnonnull -> 59
/*    */     //   55: iconst_0
/*    */     //   56: goto -> 103
/*    */     //   59: aload_3
/*    */     //   60: instanceof java/lang/Number
/*    */     //   63: ifeq -> 78
/*    */     //   66: aload_3
/*    */     //   67: checkcast java/lang/Number
/*    */     //   70: aload #4
/*    */     //   72: invokestatic equalsNumObject : (Ljava/lang/Number;Ljava/lang/Object;)Z
/*    */     //   75: goto -> 103
/*    */     //   78: aload_3
/*    */     //   79: instanceof java/lang/Character
/*    */     //   82: ifeq -> 97
/*    */     //   85: aload_3
/*    */     //   86: checkcast java/lang/Character
/*    */     //   89: aload #4
/*    */     //   91: invokestatic equalsCharObject : (Ljava/lang/Character;Ljava/lang/Object;)Z
/*    */     //   94: goto -> 103
/*    */     //   97: aload_3
/*    */     //   98: aload #4
/*    */     //   100: invokevirtual equals : (Ljava/lang/Object;)Z
/*    */     //   103: ifeq -> 959
/*    */     //   106: aload_0
/*    */     //   107: invokevirtual _2 : ()Ljava/lang/Object;
/*    */     //   110: aload #25
/*    */     //   112: invokevirtual _2 : ()Ljava/lang/Object;
/*    */     //   115: astore #6
/*    */     //   117: dup
/*    */     //   118: astore #5
/*    */     //   120: aload #6
/*    */     //   122: if_acmpne -> 129
/*    */     //   125: iconst_1
/*    */     //   126: goto -> 187
/*    */     //   129: aload #5
/*    */     //   131: ifnonnull -> 138
/*    */     //   134: iconst_0
/*    */     //   135: goto -> 187
/*    */     //   138: aload #5
/*    */     //   140: instanceof java/lang/Number
/*    */     //   143: ifeq -> 159
/*    */     //   146: aload #5
/*    */     //   148: checkcast java/lang/Number
/*    */     //   151: aload #6
/*    */     //   153: invokestatic equalsNumObject : (Ljava/lang/Number;Ljava/lang/Object;)Z
/*    */     //   156: goto -> 187
/*    */     //   159: aload #5
/*    */     //   161: instanceof java/lang/Character
/*    */     //   164: ifeq -> 180
/*    */     //   167: aload #5
/*    */     //   169: checkcast java/lang/Character
/*    */     //   172: aload #6
/*    */     //   174: invokestatic equalsCharObject : (Ljava/lang/Character;Ljava/lang/Object;)Z
/*    */     //   177: goto -> 187
/*    */     //   180: aload #5
/*    */     //   182: aload #6
/*    */     //   184: invokevirtual equals : (Ljava/lang/Object;)Z
/*    */     //   187: ifeq -> 959
/*    */     //   190: aload_0
/*    */     //   191: invokevirtual _3 : ()Ljava/lang/Object;
/*    */     //   194: aload #25
/*    */     //   196: invokevirtual _3 : ()Ljava/lang/Object;
/*    */     //   199: astore #8
/*    */     //   201: dup
/*    */     //   202: astore #7
/*    */     //   204: aload #8
/*    */     //   206: if_acmpne -> 213
/*    */     //   209: iconst_1
/*    */     //   210: goto -> 271
/*    */     //   213: aload #7
/*    */     //   215: ifnonnull -> 222
/*    */     //   218: iconst_0
/*    */     //   219: goto -> 271
/*    */     //   222: aload #7
/*    */     //   224: instanceof java/lang/Number
/*    */     //   227: ifeq -> 243
/*    */     //   230: aload #7
/*    */     //   232: checkcast java/lang/Number
/*    */     //   235: aload #8
/*    */     //   237: invokestatic equalsNumObject : (Ljava/lang/Number;Ljava/lang/Object;)Z
/*    */     //   240: goto -> 271
/*    */     //   243: aload #7
/*    */     //   245: instanceof java/lang/Character
/*    */     //   248: ifeq -> 264
/*    */     //   251: aload #7
/*    */     //   253: checkcast java/lang/Character
/*    */     //   256: aload #8
/*    */     //   258: invokestatic equalsCharObject : (Ljava/lang/Character;Ljava/lang/Object;)Z
/*    */     //   261: goto -> 271
/*    */     //   264: aload #7
/*    */     //   266: aload #8
/*    */     //   268: invokevirtual equals : (Ljava/lang/Object;)Z
/*    */     //   271: ifeq -> 959
/*    */     //   274: aload_0
/*    */     //   275: invokevirtual _4 : ()Ljava/lang/Object;
/*    */     //   278: aload #25
/*    */     //   280: invokevirtual _4 : ()Ljava/lang/Object;
/*    */     //   283: astore #10
/*    */     //   285: dup
/*    */     //   286: astore #9
/*    */     //   288: aload #10
/*    */     //   290: if_acmpne -> 297
/*    */     //   293: iconst_1
/*    */     //   294: goto -> 355
/*    */     //   297: aload #9
/*    */     //   299: ifnonnull -> 306
/*    */     //   302: iconst_0
/*    */     //   303: goto -> 355
/*    */     //   306: aload #9
/*    */     //   308: instanceof java/lang/Number
/*    */     //   311: ifeq -> 327
/*    */     //   314: aload #9
/*    */     //   316: checkcast java/lang/Number
/*    */     //   319: aload #10
/*    */     //   321: invokestatic equalsNumObject : (Ljava/lang/Number;Ljava/lang/Object;)Z
/*    */     //   324: goto -> 355
/*    */     //   327: aload #9
/*    */     //   329: instanceof java/lang/Character
/*    */     //   332: ifeq -> 348
/*    */     //   335: aload #9
/*    */     //   337: checkcast java/lang/Character
/*    */     //   340: aload #10
/*    */     //   342: invokestatic equalsCharObject : (Ljava/lang/Character;Ljava/lang/Object;)Z
/*    */     //   345: goto -> 355
/*    */     //   348: aload #9
/*    */     //   350: aload #10
/*    */     //   352: invokevirtual equals : (Ljava/lang/Object;)Z
/*    */     //   355: ifeq -> 959
/*    */     //   358: aload_0
/*    */     //   359: invokevirtual _5 : ()Ljava/lang/Object;
/*    */     //   362: aload #25
/*    */     //   364: invokevirtual _5 : ()Ljava/lang/Object;
/*    */     //   367: astore #12
/*    */     //   369: dup
/*    */     //   370: astore #11
/*    */     //   372: aload #12
/*    */     //   374: if_acmpne -> 381
/*    */     //   377: iconst_1
/*    */     //   378: goto -> 439
/*    */     //   381: aload #11
/*    */     //   383: ifnonnull -> 390
/*    */     //   386: iconst_0
/*    */     //   387: goto -> 439
/*    */     //   390: aload #11
/*    */     //   392: instanceof java/lang/Number
/*    */     //   395: ifeq -> 411
/*    */     //   398: aload #11
/*    */     //   400: checkcast java/lang/Number
/*    */     //   403: aload #12
/*    */     //   405: invokestatic equalsNumObject : (Ljava/lang/Number;Ljava/lang/Object;)Z
/*    */     //   408: goto -> 439
/*    */     //   411: aload #11
/*    */     //   413: instanceof java/lang/Character
/*    */     //   416: ifeq -> 432
/*    */     //   419: aload #11
/*    */     //   421: checkcast java/lang/Character
/*    */     //   424: aload #12
/*    */     //   426: invokestatic equalsCharObject : (Ljava/lang/Character;Ljava/lang/Object;)Z
/*    */     //   429: goto -> 439
/*    */     //   432: aload #11
/*    */     //   434: aload #12
/*    */     //   436: invokevirtual equals : (Ljava/lang/Object;)Z
/*    */     //   439: ifeq -> 959
/*    */     //   442: aload_0
/*    */     //   443: invokevirtual _6 : ()Ljava/lang/Object;
/*    */     //   446: aload #25
/*    */     //   448: invokevirtual _6 : ()Ljava/lang/Object;
/*    */     //   451: astore #14
/*    */     //   453: dup
/*    */     //   454: astore #13
/*    */     //   456: aload #14
/*    */     //   458: if_acmpne -> 465
/*    */     //   461: iconst_1
/*    */     //   462: goto -> 523
/*    */     //   465: aload #13
/*    */     //   467: ifnonnull -> 474
/*    */     //   470: iconst_0
/*    */     //   471: goto -> 523
/*    */     //   474: aload #13
/*    */     //   476: instanceof java/lang/Number
/*    */     //   479: ifeq -> 495
/*    */     //   482: aload #13
/*    */     //   484: checkcast java/lang/Number
/*    */     //   487: aload #14
/*    */     //   489: invokestatic equalsNumObject : (Ljava/lang/Number;Ljava/lang/Object;)Z
/*    */     //   492: goto -> 523
/*    */     //   495: aload #13
/*    */     //   497: instanceof java/lang/Character
/*    */     //   500: ifeq -> 516
/*    */     //   503: aload #13
/*    */     //   505: checkcast java/lang/Character
/*    */     //   508: aload #14
/*    */     //   510: invokestatic equalsCharObject : (Ljava/lang/Character;Ljava/lang/Object;)Z
/*    */     //   513: goto -> 523
/*    */     //   516: aload #13
/*    */     //   518: aload #14
/*    */     //   520: invokevirtual equals : (Ljava/lang/Object;)Z
/*    */     //   523: ifeq -> 959
/*    */     //   526: aload_0
/*    */     //   527: invokevirtual _7 : ()Ljava/lang/Object;
/*    */     //   530: aload #25
/*    */     //   532: invokevirtual _7 : ()Ljava/lang/Object;
/*    */     //   535: astore #16
/*    */     //   537: dup
/*    */     //   538: astore #15
/*    */     //   540: aload #16
/*    */     //   542: if_acmpne -> 549
/*    */     //   545: iconst_1
/*    */     //   546: goto -> 607
/*    */     //   549: aload #15
/*    */     //   551: ifnonnull -> 558
/*    */     //   554: iconst_0
/*    */     //   555: goto -> 607
/*    */     //   558: aload #15
/*    */     //   560: instanceof java/lang/Number
/*    */     //   563: ifeq -> 579
/*    */     //   566: aload #15
/*    */     //   568: checkcast java/lang/Number
/*    */     //   571: aload #16
/*    */     //   573: invokestatic equalsNumObject : (Ljava/lang/Number;Ljava/lang/Object;)Z
/*    */     //   576: goto -> 607
/*    */     //   579: aload #15
/*    */     //   581: instanceof java/lang/Character
/*    */     //   584: ifeq -> 600
/*    */     //   587: aload #15
/*    */     //   589: checkcast java/lang/Character
/*    */     //   592: aload #16
/*    */     //   594: invokestatic equalsCharObject : (Ljava/lang/Character;Ljava/lang/Object;)Z
/*    */     //   597: goto -> 607
/*    */     //   600: aload #15
/*    */     //   602: aload #16
/*    */     //   604: invokevirtual equals : (Ljava/lang/Object;)Z
/*    */     //   607: ifeq -> 959
/*    */     //   610: aload_0
/*    */     //   611: invokevirtual _8 : ()Ljava/lang/Object;
/*    */     //   614: aload #25
/*    */     //   616: invokevirtual _8 : ()Ljava/lang/Object;
/*    */     //   619: astore #18
/*    */     //   621: dup
/*    */     //   622: astore #17
/*    */     //   624: aload #18
/*    */     //   626: if_acmpne -> 633
/*    */     //   629: iconst_1
/*    */     //   630: goto -> 691
/*    */     //   633: aload #17
/*    */     //   635: ifnonnull -> 642
/*    */     //   638: iconst_0
/*    */     //   639: goto -> 691
/*    */     //   642: aload #17
/*    */     //   644: instanceof java/lang/Number
/*    */     //   647: ifeq -> 663
/*    */     //   650: aload #17
/*    */     //   652: checkcast java/lang/Number
/*    */     //   655: aload #18
/*    */     //   657: invokestatic equalsNumObject : (Ljava/lang/Number;Ljava/lang/Object;)Z
/*    */     //   660: goto -> 691
/*    */     //   663: aload #17
/*    */     //   665: instanceof java/lang/Character
/*    */     //   668: ifeq -> 684
/*    */     //   671: aload #17
/*    */     //   673: checkcast java/lang/Character
/*    */     //   676: aload #18
/*    */     //   678: invokestatic equalsCharObject : (Ljava/lang/Character;Ljava/lang/Object;)Z
/*    */     //   681: goto -> 691
/*    */     //   684: aload #17
/*    */     //   686: aload #18
/*    */     //   688: invokevirtual equals : (Ljava/lang/Object;)Z
/*    */     //   691: ifeq -> 959
/*    */     //   694: aload_0
/*    */     //   695: invokevirtual _9 : ()Ljava/lang/Object;
/*    */     //   698: aload #25
/*    */     //   700: invokevirtual _9 : ()Ljava/lang/Object;
/*    */     //   703: astore #20
/*    */     //   705: dup
/*    */     //   706: astore #19
/*    */     //   708: aload #20
/*    */     //   710: if_acmpne -> 717
/*    */     //   713: iconst_1
/*    */     //   714: goto -> 775
/*    */     //   717: aload #19
/*    */     //   719: ifnonnull -> 726
/*    */     //   722: iconst_0
/*    */     //   723: goto -> 775
/*    */     //   726: aload #19
/*    */     //   728: instanceof java/lang/Number
/*    */     //   731: ifeq -> 747
/*    */     //   734: aload #19
/*    */     //   736: checkcast java/lang/Number
/*    */     //   739: aload #20
/*    */     //   741: invokestatic equalsNumObject : (Ljava/lang/Number;Ljava/lang/Object;)Z
/*    */     //   744: goto -> 775
/*    */     //   747: aload #19
/*    */     //   749: instanceof java/lang/Character
/*    */     //   752: ifeq -> 768
/*    */     //   755: aload #19
/*    */     //   757: checkcast java/lang/Character
/*    */     //   760: aload #20
/*    */     //   762: invokestatic equalsCharObject : (Ljava/lang/Character;Ljava/lang/Object;)Z
/*    */     //   765: goto -> 775
/*    */     //   768: aload #19
/*    */     //   770: aload #20
/*    */     //   772: invokevirtual equals : (Ljava/lang/Object;)Z
/*    */     //   775: ifeq -> 959
/*    */     //   778: aload_0
/*    */     //   779: invokevirtual _10 : ()Ljava/lang/Object;
/*    */     //   782: aload #25
/*    */     //   784: invokevirtual _10 : ()Ljava/lang/Object;
/*    */     //   787: astore #22
/*    */     //   789: dup
/*    */     //   790: astore #21
/*    */     //   792: aload #22
/*    */     //   794: if_acmpne -> 801
/*    */     //   797: iconst_1
/*    */     //   798: goto -> 859
/*    */     //   801: aload #21
/*    */     //   803: ifnonnull -> 810
/*    */     //   806: iconst_0
/*    */     //   807: goto -> 859
/*    */     //   810: aload #21
/*    */     //   812: instanceof java/lang/Number
/*    */     //   815: ifeq -> 831
/*    */     //   818: aload #21
/*    */     //   820: checkcast java/lang/Number
/*    */     //   823: aload #22
/*    */     //   825: invokestatic equalsNumObject : (Ljava/lang/Number;Ljava/lang/Object;)Z
/*    */     //   828: goto -> 859
/*    */     //   831: aload #21
/*    */     //   833: instanceof java/lang/Character
/*    */     //   836: ifeq -> 852
/*    */     //   839: aload #21
/*    */     //   841: checkcast java/lang/Character
/*    */     //   844: aload #22
/*    */     //   846: invokestatic equalsCharObject : (Ljava/lang/Character;Ljava/lang/Object;)Z
/*    */     //   849: goto -> 859
/*    */     //   852: aload #21
/*    */     //   854: aload #22
/*    */     //   856: invokevirtual equals : (Ljava/lang/Object;)Z
/*    */     //   859: ifeq -> 959
/*    */     //   862: aload_0
/*    */     //   863: invokevirtual _11 : ()Ljava/lang/Object;
/*    */     //   866: aload #25
/*    */     //   868: invokevirtual _11 : ()Ljava/lang/Object;
/*    */     //   871: astore #24
/*    */     //   873: dup
/*    */     //   874: astore #23
/*    */     //   876: aload #24
/*    */     //   878: if_acmpne -> 885
/*    */     //   881: iconst_1
/*    */     //   882: goto -> 943
/*    */     //   885: aload #23
/*    */     //   887: ifnonnull -> 894
/*    */     //   890: iconst_0
/*    */     //   891: goto -> 943
/*    */     //   894: aload #23
/*    */     //   896: instanceof java/lang/Number
/*    */     //   899: ifeq -> 915
/*    */     //   902: aload #23
/*    */     //   904: checkcast java/lang/Number
/*    */     //   907: aload #24
/*    */     //   909: invokestatic equalsNumObject : (Ljava/lang/Number;Ljava/lang/Object;)Z
/*    */     //   912: goto -> 943
/*    */     //   915: aload #23
/*    */     //   917: instanceof java/lang/Character
/*    */     //   920: ifeq -> 936
/*    */     //   923: aload #23
/*    */     //   925: checkcast java/lang/Character
/*    */     //   928: aload #24
/*    */     //   930: invokestatic equalsCharObject : (Ljava/lang/Character;Ljava/lang/Object;)Z
/*    */     //   933: goto -> 943
/*    */     //   936: aload #23
/*    */     //   938: aload #24
/*    */     //   940: invokevirtual equals : (Ljava/lang/Object;)Z
/*    */     //   943: ifeq -> 959
/*    */     //   946: aload #25
/*    */     //   948: aload_0
/*    */     //   949: invokevirtual canEqual : (Ljava/lang/Object;)Z
/*    */     //   952: ifeq -> 959
/*    */     //   955: iconst_1
/*    */     //   956: goto -> 960
/*    */     //   959: iconst_0
/*    */     //   960: ifeq -> 967
/*    */     //   963: iconst_1
/*    */     //   964: goto -> 968
/*    */     //   967: iconst_0
/*    */     //   968: ireturn
/*    */     // Line number table:
/*    */     //   Java source line number -> byte code offset
/*    */     //   #28	-> 0
/*    */     //   #236	-> 12
/*    */     //   #28	-> 19
/*    */     // Local variable table:
/*    */     //   start	length	slot	name	descriptor
/*    */     //   0	969	0	this	Lscala/Tuple11;
/*    */     //   0	969	1	x$1	Ljava/lang/Object;
/*    */   }
/*    */   
/*    */   public Tuple11(Object _1, Object _2, Object _3, Object _4, Object _5, Object _6, Object _7, Object _8, Object _9, Object _10, Object _11) {
/* 28 */     Product$class.$init$(this);
/* 28 */     Product11$class.$init$(this);
/*    */   }
/*    */   
/*    */   public String toString() {
/* 31 */     return (new StringBuilder()).append("(").append(_1()).append(",").append(_2()).append(",").append(_3()).append(",").append(_4()).append(",").append(_5()).append(",").append(_6()).append(",").append(_7()).append(",").append(_8()).append(",").append(_9()).append(",").append(_10()).append(",").append(_11()).append(")").toString();
/*    */   }
/*    */ }


/* Location:              D:\#source-code\TheFlightSims\TFSLibrary\World2Xplane\World2XPlane.jar!\scala\Tuple11.class
 * Java compiler version: 6 (50.0)
 * JD-Core Version:       1.1.3
 */