/*    */ package scala;
/*    */ 
/*    */ import scala.collection.Iterator;
/*    */ import scala.collection.mutable.StringBuilder;
/*    */ import scala.reflect.ScalaSignature;
/*    */ import scala.runtime.ScalaRunTime$;
/*    */ 
/*    */ @ScalaSignature(bytes = "\006\001\005]h\001B\001\003\001\026\021a\001V;qY\026,$\"A\002\002\013M\034\027\r\\1\004\001U1a\001\005\016\036A\r\032R\001A\004\fK!\002\"\001C\005\016\003\tI!A\003\002\003\r\005s\027PU3g!\035AABD\r\035?\tJ!!\004\002\003\021A\023x\016Z;diV\002\"a\004\t\r\001\0211\021\003\001CC\002I\021!\001V\031\022\005M1\002C\001\005\025\023\t)\"AA\004O_RD\027N\\4\021\005!9\022B\001\r\003\005\r\te.\037\t\003\037i!aa\007\001\005\006\004\021\"A\001+3!\tyQ\004\002\004\037\001\021\025\rA\005\002\003)N\002\"a\004\021\005\r\005\002AQ1\001\023\005\t!F\007\005\002\020G\0211A\005\001CC\002I\021!\001V\033\021\005!1\023BA\024\003\005\035\001&o\0343vGR\004\"\001C\025\n\005)\022!\001D*fe&\fG.\033>bE2,\007\002\003\027\001\005+\007I\021A\027\002\005}\013T#\001\b\t\021=\002!\021#Q\001\n9\t1aX\031!\021!\t\004A!f\001\n\003\021\024AA03+\005I\002\002\003\033\001\005#\005\013\021B\r\002\007}\023\004\005\003\0057\001\tU\r\021\"\0018\003\ty6'F\001\035\021!I\004A!E!\002\023a\022aA04A!A1\b\001BK\002\023\005A(\001\002`iU\tq\004\003\005?\001\tE\t\025!\003 \003\ryF\007\t\005\t\001\002\021)\032!C\001\003\006\021q,N\013\002E!A1\t\001B\tB\003%!%A\002`k\001BQ!\022\001\005\002\031\013a\001P5oSRtDCB$I\023*[E\nE\004\t\0019IBd\b\022\t\0131\"\005\031\001\b\t\013E\"\005\031A\r\t\013Y\"\005\031\001\017\t\013m\"\005\031A\020\t\013\001#\005\031\001\022\t\0139\003A\021I(\002\021Q|7\013\036:j]\036$\022\001\025\t\003#Zk\021A\025\006\003'R\013A\001\\1oO*\tQ+\001\003kCZ\f\027BA,S\005\031\031FO]5oO\"9\021\fAA\001\n\003Q\026\001B2paf,ba\0270aE\0224GC\002/hQ&T7\016E\004\t\001u{\026mY3\021\005=qF!B\tY\005\004\021\002CA\ba\t\025Y\002L1\001\023!\ty!\rB\003\0371\n\007!\003\005\002\020I\022)\021\005\027b\001%A\021qB\032\003\006Ia\023\rA\005\005\bYa\003\n\0211\001^\021\035\t\004\f%AA\002}CqA\016-\021\002\003\007\021\rC\004<1B\005\t\031A2\t\017\001C\006\023!a\001K\"9Q\016AI\001\n\003q\027AD2paf$C-\0324bk2$H%M\013\007_j\\H0 @\026\003AT#AD9,\003I\004\"a\035=\016\003QT!!\036<\002\023Ut7\r[3dW\026$'BA<\003\003)\tgN\\8uCRLwN\\\005\003sR\024\021#\0368dQ\026\0347.\0323WCJL\027M\\2f\t\025\tBN1\001\023\t\025YBN1\001\023\t\025qBN1\001\023\t\025\tCN1\001\023\t\025!CN1\001\023\021%\t\t\001AI\001\n\003\t\031!\001\bd_BLH\005Z3gCVdG\017\n\032\026\031\005\025\021\021BA\006\003\033\ty!!\005\026\005\005\035!FA\rr\t\025\trP1\001\023\t\025YrP1\001\023\t\025qrP1\001\023\t\025\tsP1\001\023\t\025!sP1\001\023\021%\t)\002AI\001\n\003\t9\"\001\bd_BLH\005Z3gCVdG\017J\032\026\031\005e\021QDA\020\003C\t\031#!\n\026\005\005m!F\001\017r\t\031\t\0221\003b\001%\02111$a\005C\002I!aAHA\n\005\004\021BAB\021\002\024\t\007!\003\002\004%\003'\021\rA\005\005\n\003S\001\021\023!C\001\003W\tabY8qs\022\"WMZ1vYR$C'\006\007\002.\005E\0221GA\033\003o\tI$\006\002\0020)\022q$\035\003\007#\005\035\"\031\001\n\005\rm\t9C1\001\023\t\031q\022q\005b\001%\0211\021%a\nC\002I!a\001JA\024\005\004\021\002\"CA\037\001E\005I\021AA \0039\031w\016]=%I\0264\027-\0367uIU*B\"!\021\002F\005\035\023\021JA&\003\033*\"!a\021+\005\t\nHAB\t\002<\t\007!\003\002\004\034\003w\021\rA\005\003\007=\005m\"\031\001\n\005\r\005\nYD1\001\023\t\031!\0231\bb\001%!I\021\021\013\001\002\002\023\005\0231K\001\016aJ|G-^2u!J,g-\033=\026\003AC\021\"a\026\001\003\003%\t%!\027\002\037A\024x\016Z;di&#XM]1u_J,\"!a\027\021\013\005u\0231\r\f\016\005\005}#bAA1\005\005Q1m\0347mK\016$\030n\0348\n\t\005\025\024q\f\002\t\023R,'/\031;pe\"I\021\021\016\001\002\002\023\005\0211N\001\tG\006tW)];bYR!\021QNA:!\rA\021qN\005\004\003c\022!a\002\"p_2,\027M\034\005\n\003k\n9'!AA\002Y\t1\001\037\0232\021%\tI\bAA\001\n\003\nY(\001\005iCND7i\0343f)\t\ti\bE\002\t\003J1!!!\003\005\rIe\016\036\005\n\003\013\003\021\021!C!\003\017\013a!Z9vC2\034H\003BA7\003\023C\021\"!\036\002\004\006\005\t\031\001\f\b\023\0055%!!A\t\002\005=\025A\002+va2,W\007E\002\t\003#3\001\"\001\002\002\002#\005\0211S\n\005\003#;\001\006C\004F\003##\t!a&\025\005\005=\005\002\003(\002\022\006\005IQI(\t\025\005u\025\021SA\001\n\003\013y*A\003baBd\0270\006\007\002\"\006\035\0261VAX\003g\0139\f\006\007\002$\006e\0261XA_\003\013\t\r\005\007\t\001\005\025\026\021VAW\003c\013)\fE\002\020\003O#a!EAN\005\004\021\002cA\b\002,\02211$a'C\002I\0012aDAX\t\031q\0221\024b\001%A\031q\"a-\005\r\005\nYJ1\001\023!\ry\021q\027\003\007I\005m%\031\001\n\t\0171\nY\n1\001\002&\"9\021'a'A\002\005%\006b\002\034\002\034\002\007\021Q\026\005\bw\005m\005\031AAY\021\035\001\0251\024a\001\003kC!\"!2\002\022\006\005I\021QAd\003\035)h.\0319qYf,B\"!3\002V\006e\027Q\\Aq\003K$B!a3\002hB)\001\"!4\002R&\031\021q\032\002\003\r=\003H/[8o!1A\001!a5\002X\006m\027q\\Ar!\ry\021Q\033\003\007#\005\r'\031\001\n\021\007=\tI\016\002\004\034\003\007\024\rA\005\t\004\037\005uGA\002\020\002D\n\007!\003E\002\020\003C$a!IAb\005\004\021\002cA\b\002f\0221A%a1C\002IA!\"!;\002D\006\005\t\031AAi\003\rAH\005\r\005\013\003[\f\t*!A\005\n\005=\030a\003:fC\022\024Vm]8mm\026$\"!!=\021\007E\013\0310C\002\002vJ\023aa\0242kK\016$\b")
/*    */ public class Tuple5<T1, T2, T3, T4, T5> implements Product5<T1, T2, T3, T4, T5>, Product, Serializable {
/*    */   private final T1 _1;
/*    */   
/*    */   private final T2 _2;
/*    */   
/*    */   private final T3 _3;
/*    */   
/*    */   private final T4 _4;
/*    */   
/*    */   private final T5 _5;
/*    */   
/*    */   public int productArity() {
/* 22 */     return Product5$class.productArity(this);
/*    */   }
/*    */   
/*    */   public Object productElement(int n) throws IndexOutOfBoundsException {
/* 22 */     return Product5$class.productElement(this, n);
/*    */   }
/*    */   
/*    */   public T1 _1() {
/* 22 */     return this._1;
/*    */   }
/*    */   
/*    */   public T2 _2() {
/* 22 */     return this._2;
/*    */   }
/*    */   
/*    */   public T3 _3() {
/* 22 */     return this._3;
/*    */   }
/*    */   
/*    */   public T4 _4() {
/* 22 */     return this._4;
/*    */   }
/*    */   
/*    */   public T5 _5() {
/* 22 */     return this._5;
/*    */   }
/*    */   
/*    */   public <T1, T2, T3, T4, T5> Tuple5<T1, T2, T3, T4, T5> copy(Object _1, Object _2, Object _3, Object _4, Object _5) {
/* 22 */     return new Tuple5((T1)_1, (T2)_2, (T3)_3, (T4)_4, (T5)_5);
/*    */   }
/*    */   
/*    */   public <T1, T2, T3, T4, T5> T1 copy$default$1() {
/* 22 */     return _1();
/*    */   }
/*    */   
/*    */   public <T1, T2, T3, T4, T5> T2 copy$default$2() {
/* 22 */     return _2();
/*    */   }
/*    */   
/*    */   public <T1, T2, T3, T4, T5> T3 copy$default$3() {
/* 22 */     return _3();
/*    */   }
/*    */   
/*    */   public <T1, T2, T3, T4, T5> T4 copy$default$4() {
/* 22 */     return _4();
/*    */   }
/*    */   
/*    */   public <T1, T2, T3, T4, T5> T5 copy$default$5() {
/* 22 */     return _5();
/*    */   }
/*    */   
/*    */   public String productPrefix() {
/* 22 */     return "Tuple5";
/*    */   }
/*    */   
/*    */   public Iterator<Object> productIterator() {
/* 22 */     return ScalaRunTime$.MODULE$.typedProductIterator(this);
/*    */   }
/*    */   
/*    */   public boolean canEqual(Object x$1) {
/* 22 */     return x$1 instanceof Tuple5;
/*    */   }
/*    */   
/*    */   public int hashCode() {
/* 22 */     return ScalaRunTime$.MODULE$._hashCode(this);
/*    */   }
/*    */   
/*    */   public boolean equals(Object x$1) {
/*    */     // Byte code:
/*    */     //   0: aload_0
/*    */     //   1: aload_1
/*    */     //   2: if_acmpeq -> 459
/*    */     //   5: aload_1
/*    */     //   6: instanceof scala/Tuple5
/*    */     //   9: ifeq -> 17
/*    */     //   12: iconst_1
/*    */     //   13: istore_2
/*    */     //   14: goto -> 19
/*    */     //   17: iconst_0
/*    */     //   18: istore_2
/*    */     //   19: iload_2
/*    */     //   20: ifeq -> 463
/*    */     //   23: aload_1
/*    */     //   24: checkcast scala/Tuple5
/*    */     //   27: astore #13
/*    */     //   29: aload_0
/*    */     //   30: invokevirtual _1 : ()Ljava/lang/Object;
/*    */     //   33: aload #13
/*    */     //   35: invokevirtual _1 : ()Ljava/lang/Object;
/*    */     //   38: astore #4
/*    */     //   40: dup
/*    */     //   41: astore_3
/*    */     //   42: aload #4
/*    */     //   44: if_acmpne -> 51
/*    */     //   47: iconst_1
/*    */     //   48: goto -> 103
/*    */     //   51: aload_3
/*    */     //   52: ifnonnull -> 59
/*    */     //   55: iconst_0
/*    */     //   56: goto -> 103
/*    */     //   59: aload_3
/*    */     //   60: instanceof java/lang/Number
/*    */     //   63: ifeq -> 78
/*    */     //   66: aload_3
/*    */     //   67: checkcast java/lang/Number
/*    */     //   70: aload #4
/*    */     //   72: invokestatic equalsNumObject : (Ljava/lang/Number;Ljava/lang/Object;)Z
/*    */     //   75: goto -> 103
/*    */     //   78: aload_3
/*    */     //   79: instanceof java/lang/Character
/*    */     //   82: ifeq -> 97
/*    */     //   85: aload_3
/*    */     //   86: checkcast java/lang/Character
/*    */     //   89: aload #4
/*    */     //   91: invokestatic equalsCharObject : (Ljava/lang/Character;Ljava/lang/Object;)Z
/*    */     //   94: goto -> 103
/*    */     //   97: aload_3
/*    */     //   98: aload #4
/*    */     //   100: invokevirtual equals : (Ljava/lang/Object;)Z
/*    */     //   103: ifeq -> 455
/*    */     //   106: aload_0
/*    */     //   107: invokevirtual _2 : ()Ljava/lang/Object;
/*    */     //   110: aload #13
/*    */     //   112: invokevirtual _2 : ()Ljava/lang/Object;
/*    */     //   115: astore #6
/*    */     //   117: dup
/*    */     //   118: astore #5
/*    */     //   120: aload #6
/*    */     //   122: if_acmpne -> 129
/*    */     //   125: iconst_1
/*    */     //   126: goto -> 187
/*    */     //   129: aload #5
/*    */     //   131: ifnonnull -> 138
/*    */     //   134: iconst_0
/*    */     //   135: goto -> 187
/*    */     //   138: aload #5
/*    */     //   140: instanceof java/lang/Number
/*    */     //   143: ifeq -> 159
/*    */     //   146: aload #5
/*    */     //   148: checkcast java/lang/Number
/*    */     //   151: aload #6
/*    */     //   153: invokestatic equalsNumObject : (Ljava/lang/Number;Ljava/lang/Object;)Z
/*    */     //   156: goto -> 187
/*    */     //   159: aload #5
/*    */     //   161: instanceof java/lang/Character
/*    */     //   164: ifeq -> 180
/*    */     //   167: aload #5
/*    */     //   169: checkcast java/lang/Character
/*    */     //   172: aload #6
/*    */     //   174: invokestatic equalsCharObject : (Ljava/lang/Character;Ljava/lang/Object;)Z
/*    */     //   177: goto -> 187
/*    */     //   180: aload #5
/*    */     //   182: aload #6
/*    */     //   184: invokevirtual equals : (Ljava/lang/Object;)Z
/*    */     //   187: ifeq -> 455
/*    */     //   190: aload_0
/*    */     //   191: invokevirtual _3 : ()Ljava/lang/Object;
/*    */     //   194: aload #13
/*    */     //   196: invokevirtual _3 : ()Ljava/lang/Object;
/*    */     //   199: astore #8
/*    */     //   201: dup
/*    */     //   202: astore #7
/*    */     //   204: aload #8
/*    */     //   206: if_acmpne -> 213
/*    */     //   209: iconst_1
/*    */     //   210: goto -> 271
/*    */     //   213: aload #7
/*    */     //   215: ifnonnull -> 222
/*    */     //   218: iconst_0
/*    */     //   219: goto -> 271
/*    */     //   222: aload #7
/*    */     //   224: instanceof java/lang/Number
/*    */     //   227: ifeq -> 243
/*    */     //   230: aload #7
/*    */     //   232: checkcast java/lang/Number
/*    */     //   235: aload #8
/*    */     //   237: invokestatic equalsNumObject : (Ljava/lang/Number;Ljava/lang/Object;)Z
/*    */     //   240: goto -> 271
/*    */     //   243: aload #7
/*    */     //   245: instanceof java/lang/Character
/*    */     //   248: ifeq -> 264
/*    */     //   251: aload #7
/*    */     //   253: checkcast java/lang/Character
/*    */     //   256: aload #8
/*    */     //   258: invokestatic equalsCharObject : (Ljava/lang/Character;Ljava/lang/Object;)Z
/*    */     //   261: goto -> 271
/*    */     //   264: aload #7
/*    */     //   266: aload #8
/*    */     //   268: invokevirtual equals : (Ljava/lang/Object;)Z
/*    */     //   271: ifeq -> 455
/*    */     //   274: aload_0
/*    */     //   275: invokevirtual _4 : ()Ljava/lang/Object;
/*    */     //   278: aload #13
/*    */     //   280: invokevirtual _4 : ()Ljava/lang/Object;
/*    */     //   283: astore #10
/*    */     //   285: dup
/*    */     //   286: astore #9
/*    */     //   288: aload #10
/*    */     //   290: if_acmpne -> 297
/*    */     //   293: iconst_1
/*    */     //   294: goto -> 355
/*    */     //   297: aload #9
/*    */     //   299: ifnonnull -> 306
/*    */     //   302: iconst_0
/*    */     //   303: goto -> 355
/*    */     //   306: aload #9
/*    */     //   308: instanceof java/lang/Number
/*    */     //   311: ifeq -> 327
/*    */     //   314: aload #9
/*    */     //   316: checkcast java/lang/Number
/*    */     //   319: aload #10
/*    */     //   321: invokestatic equalsNumObject : (Ljava/lang/Number;Ljava/lang/Object;)Z
/*    */     //   324: goto -> 355
/*    */     //   327: aload #9
/*    */     //   329: instanceof java/lang/Character
/*    */     //   332: ifeq -> 348
/*    */     //   335: aload #9
/*    */     //   337: checkcast java/lang/Character
/*    */     //   340: aload #10
/*    */     //   342: invokestatic equalsCharObject : (Ljava/lang/Character;Ljava/lang/Object;)Z
/*    */     //   345: goto -> 355
/*    */     //   348: aload #9
/*    */     //   350: aload #10
/*    */     //   352: invokevirtual equals : (Ljava/lang/Object;)Z
/*    */     //   355: ifeq -> 455
/*    */     //   358: aload_0
/*    */     //   359: invokevirtual _5 : ()Ljava/lang/Object;
/*    */     //   362: aload #13
/*    */     //   364: invokevirtual _5 : ()Ljava/lang/Object;
/*    */     //   367: astore #12
/*    */     //   369: dup
/*    */     //   370: astore #11
/*    */     //   372: aload #12
/*    */     //   374: if_acmpne -> 381
/*    */     //   377: iconst_1
/*    */     //   378: goto -> 439
/*    */     //   381: aload #11
/*    */     //   383: ifnonnull -> 390
/*    */     //   386: iconst_0
/*    */     //   387: goto -> 439
/*    */     //   390: aload #11
/*    */     //   392: instanceof java/lang/Number
/*    */     //   395: ifeq -> 411
/*    */     //   398: aload #11
/*    */     //   400: checkcast java/lang/Number
/*    */     //   403: aload #12
/*    */     //   405: invokestatic equalsNumObject : (Ljava/lang/Number;Ljava/lang/Object;)Z
/*    */     //   408: goto -> 439
/*    */     //   411: aload #11
/*    */     //   413: instanceof java/lang/Character
/*    */     //   416: ifeq -> 432
/*    */     //   419: aload #11
/*    */     //   421: checkcast java/lang/Character
/*    */     //   424: aload #12
/*    */     //   426: invokestatic equalsCharObject : (Ljava/lang/Character;Ljava/lang/Object;)Z
/*    */     //   429: goto -> 439
/*    */     //   432: aload #11
/*    */     //   434: aload #12
/*    */     //   436: invokevirtual equals : (Ljava/lang/Object;)Z
/*    */     //   439: ifeq -> 455
/*    */     //   442: aload #13
/*    */     //   444: aload_0
/*    */     //   445: invokevirtual canEqual : (Ljava/lang/Object;)Z
/*    */     //   448: ifeq -> 455
/*    */     //   451: iconst_1
/*    */     //   452: goto -> 456
/*    */     //   455: iconst_0
/*    */     //   456: ifeq -> 463
/*    */     //   459: iconst_1
/*    */     //   460: goto -> 464
/*    */     //   463: iconst_0
/*    */     //   464: ireturn
/*    */     // Line number table:
/*    */     //   Java source line number -> byte code offset
/*    */     //   #22	-> 0
/*    */     //   #236	-> 12
/*    */     //   #22	-> 19
/*    */     // Local variable table:
/*    */     //   start	length	slot	name	descriptor
/*    */     //   0	465	0	this	Lscala/Tuple5;
/*    */     //   0	465	1	x$1	Ljava/lang/Object;
/*    */   }
/*    */   
/*    */   public Tuple5(Object _1, Object _2, Object _3, Object _4, Object _5) {
/* 22 */     Product$class.$init$(this);
/* 22 */     Product5$class.$init$(this);
/*    */   }
/*    */   
/*    */   public String toString() {
/* 25 */     return (new StringBuilder()).append("(").append(_1()).append(",").append(_2()).append(",").append(_3()).append(",").append(_4()).append(",").append(_5()).append(")").toString();
/*    */   }
/*    */ }


/* Location:              D:\#source-code\TheFlightSims\TFSLibrary\World2Xplane\World2XPlane.jar!\scala\Tuple5.class
 * Java compiler version: 6 (50.0)
 * JD-Core Version:       1.1.3
 */