/*    */ package scala;
/*    */ 
/*    */ import scala.collection.Iterator;
/*    */ import scala.collection.mutable.StringBuilder;
/*    */ import scala.reflect.ScalaSignature;
/*    */ import scala.runtime.ScalaRunTime$;
/*    */ 
/*    */ @ScalaSignature(bytes = "\006\001\031}h\001B\001\003\001\026\021q\001V;qY\026\f\024HC\001\004\003\025\0318-\0317b\007\001)BC\002\t\033;\001\032c%\013\0270eUB4HP!E\017*k5#\002\001\b\027=\023\006C\001\005\n\033\005\021\021B\001\006\003\005\031\te.\037*fMB)\002\002\004\b\0329}\021S\005K\026/cQ:$(\020!D\r&c\025BA\007\003\005%\001&o\0343vGR\f\024\b\005\002\020!1\001AAB\t\001\t\013\007!C\001\002UcE\0211C\006\t\003\021QI!!\006\002\003\0179{G\017[5oOB\021\001bF\005\0031\t\0211!\0218z!\ty!\004\002\004\034\001\021\025\rA\005\002\003)J\002\"aD\017\005\ry\001AQ1\001\023\005\t!6\007\005\002\020A\0211\021\005\001CC\002I\021!\001\026\033\021\005=\031CA\002\023\001\t\013\007!C\001\002UkA\021qB\n\003\007O\001!)\031\001\n\003\005Q3\004CA\b*\t\031Q\003\001\"b\001%\t\021Ak\016\t\003\0371\"a!\f\001\005\006\004\021\"A\001+9!\tyq\006\002\0041\001\021\025\rA\005\002\003)f\002\"a\004\032\005\rM\002AQ1\001\023\005\r!\026\007\r\t\003\037U\"aA\016\001\005\006\004\021\"a\001+2cA\021q\002\017\003\007s\001!)\031\001\n\003\007Q\013$\007\005\002\020w\0211A\b\001CC\002I\0211\001V\0314!\tya\b\002\004@\001\021\025\rA\005\002\004)F\"\004CA\bB\t\031\021\005\001\"b\001%\t\031A+M\033\021\005=!EAB#\001\t\013\007!CA\002UcY\002\"aD$\005\r!\003AQ1\001\023\005\r!\026g\016\t\003\037)#aa\023\001\005\006\004\021\"a\001+2qA\021q\"\024\003\007\035\002!)\031\001\n\003\007Q\013\024\b\005\002\t!&\021\021K\001\002\b!J|G-^2u!\tA1+\003\002U\005\ta1+\032:jC2L'0\0312mK\"Aa\013\001BK\002\023\005q+\001\002`cU\ta\002\003\005Z\001\tE\t\025!\003\017\003\ry\026\007\t\005\t7\002\021)\032!C\0019\006\021qLM\013\0023!Aa\f\001B\tB\003%\021$A\002`e\001B\001\002\031\001\003\026\004%\t!Y\001\003?N*\022\001\b\005\tG\002\021\t\022)A\0059\005\031ql\r\021\t\021\025\004!Q3A\005\002\031\f!a\030\033\026\003}A\001\002\033\001\003\022\003\006IaH\001\004?R\002\003\002\0036\001\005+\007I\021A6\002\005}+T#\001\022\t\0215\004!\021#Q\001\n\t\n1aX\033!\021!y\007A!f\001\n\003\001\030AA07+\005)\003\002\003:\001\005#\005\013\021B\023\002\007}3\004\005\003\005u\001\tU\r\021\"\001v\003\tyv'F\001)\021!9\bA!E!\002\023A\023aA08A!A\021\020\001BK\002\023\005!0\001\002`qU\t1\006\003\005}\001\tE\t\025!\003,\003\ry\006\b\t\005\t}\002\021)\032!C\001\006\021q,O\013\002]!I\0211\001\001\003\022\003\006IAL\001\004?f\002\003BCA\004\001\tU\r\021\"\001\002\n\005\031q,\r\031\026\003EB\021\"!\004\001\005#\005\013\021B\031\002\t}\013\004\007\t\005\013\003#\001!Q3A\005\002\005M\021aA02cU\tA\007C\005\002\030\001\021\t\022)A\005i\005!q,M\031!\021)\tY\002\001BK\002\023\005\021QD\001\004?F\022T#A\034\t\023\005\005\002A!E!\002\0239\024\001B02e\001B!\"!\n\001\005+\007I\021AA\024\003\ry\026gM\013\002u!I\0211\006\001\003\022\003\006IAO\001\005?F\032\004\005\003\006\0020\001\021)\032!C\001\003c\t1aX\0315+\005i\004\"CA\033\001\tE\t\025!\003>\003\021y\026\007\016\021\t\025\005e\002A!f\001\n\003\tY$A\002`cU*\022\001\021\005\n\003\001!\021#Q\001\n\001\013AaX\0316A!Q\0211\t\001\003\026\004%\t!!\022\002\007}\013d'F\001D\021%\tI\005\001B\tB\003%1)\001\003`cY\002\003BCA'\001\tU\r\021\"\001\002P\005\031q,M\034\026\003\031C\021\"a\025\001\005#\005\013\021\002$\002\t}\013t\007\t\005\013\003/\002!Q3A\005\002\005e\023aA02qU\t\021\nC\005\002^\001\021\t\022)A\005\023\006!q,\r\035!\021)\t\t\007\001BK\002\023\005\0211M\001\004?FJT#\001'\t\023\005\035\004A!E!\002\023a\025\001B02s\001Bq!a\033\001\t\003\ti'\001\004=S:LGO\020\013)\003_\n\t(a\035\002v\005]\024\021PA>\003{\ny(!!\002\004\006\025\025qQAE\003\027\013i)a$\002\022\006M\025Q\023\t\026\021\001q\021\004H\020#K!Zc&\r\0338uu\0025IR%M\021\0311\026\021\016a\001\035!11,!\033A\002eAa\001YA5\001\004a\002BB3\002j\001\007q\004\003\004k\003S\002\rA\t\005\007_\006%\004\031A\023\t\rQ\fI\0071\001)\021\031I\030\021\016a\001W!1a0!\033A\0029Bq!a\002\002j\001\007\021\007C\004\002\022\005%\004\031\001\033\t\017\005m\021\021\016a\001o!9\021QEA5\001\004Q\004bBA\030\003S\002\r!\020\005\b\003s\tI\0071\001A\021\035\t\031%!\033A\002\rCq!!\024\002j\001\007a\tC\004\002X\005%\004\031A%\t\017\005\005\024\021\016a\001\031\"9\021\021\024\001\005B\005m\025\001\003;p'R\024\030N\\4\025\005\005u\005\003BAP\003Sk!!!)\013\t\005\r\026QU\001\005Y\006twM\003\002\002(\006!!.\031<b\023\021\tY+!)\003\rM#(/\0338h\021%\ty\013AA\001\n\003\t\t,\001\003d_BLX\003KAZ\003s\013i,!1\002F\006%\027QZAi\003+\fI.!8\002b\006\025\030\021^Aw\003c\f)0!?\002~\n\005A\003KA[\005\007\021)Aa\002\003\n\t-!Q\002B\b\005#\021\031B!\006\003\030\te!1\004B\017\005?\021\tCa\t\003&\t\035\002\003\013\005\001\003o\013Y,a0\002D\006\035\0271ZAh\003'\f9.a7\002`\006\r\030q]Av\003_\f\0310a>\002|\006}\bcA\b\002:\0221\021#!,C\002I\0012aDA_\t\031Y\022Q\026b\001%A\031q\"!1\005\ry\tiK1\001\023!\ry\021Q\031\003\007C\0055&\031\001\n\021\007=\tI\r\002\004%\003[\023\rA\005\t\004\037\0055GAB\024\002.\n\007!\003E\002\020\003#$aAKAW\005\004\021\002cA\b\002V\0221Q&!,C\002I\0012aDAm\t\031\001\024Q\026b\001%A\031q\"!8\005\rM\niK1\001\023!\ry\021\021\035\003\007m\0055&\031\001\n\021\007=\t)\017\002\004:\003[\023\rA\005\t\004\037\005%HA\002\037\002.\n\007!\003E\002\020\003[$aaPAW\005\004\021\002cA\b\002r\0221!)!,C\002I\0012aDA{\t\031)\025Q\026b\001%A\031q\"!?\005\r!\013iK1\001\023!\ry\021Q \003\007\027\0065&\031\001\n\021\007=\021\t\001\002\004O\003[\023\rA\005\005\n-\0065\006\023!a\001\003oC\021bWAW!\003\005\r!a/\t\023\001\fi\013%AA\002\005}\006\"C3\002.B\005\t\031AAb\021%Q\027Q\026I\001\002\004\t9\rC\005p\003[\003\n\0211\001\002L\"IA/!,\021\002\003\007\021q\032\005\ns\0065\006\023!a\001\003'D\021B`AW!\003\005\r!a6\t\025\005\035\021Q\026I\001\002\004\tY\016\003\006\002\022\0055\006\023!a\001\003?D!\"a\007\002.B\005\t\031AAr\021)\t)#!,\021\002\003\007\021q\035\005\013\003_\ti\013%AA\002\005-\bBCA\035\003[\003\n\0211\001\002p\"Q\0211IAW!\003\005\r!a=\t\025\0055\023Q\026I\001\002\004\t9\020\003\006\002X\0055\006\023!a\001\003wD!\"!\031\002.B\005\t\031AA\000\021%\021Y\003AI\001\n\003\021i#\001\bd_BLH\005Z3gCVdG\017J\031\026Q\t=\"Q\tB$\005\023\022YE!\024\003P\tE#1\013B+\005/\022IFa\027\003^\t}#\021\rB2\005K\0229G!\033\026\005\tE\"f\001\b\0034-\022!Q\007\t\005\005o\021\t%\004\002\003:)!!1\bB\037\003%)hn\0315fG.,GMC\002\003@\t\t!\"\0318o_R\fG/[8o\023\021\021\031E!\017\003#Ut7\r[3dW\026$g+\031:jC:\034W\r\002\004\022\005S\021\rA\005\003\0077\t%\"\031\001\n\005\ry\021IC1\001\023\t\031\t#\021\006b\001%\0211AE!\013C\002I!aa\nB\025\005\004\021BA\002\026\003*\t\007!\003\002\004.\005S\021\rA\005\003\007a\t%\"\031\001\n\005\rM\022IC1\001\023\t\0311$\021\006b\001%\0211\021H!\013C\002I!a\001\020B\025\005\004\021BAB \003*\t\007!\003\002\004C\005S\021\rA\005\003\007\013\n%\"\031\001\n\005\r!\023IC1\001\023\t\031Y%\021\006b\001%\0211aJ!\013C\002IA\021B!\034\001#\003%\tAa\034\002\035\r|\007/\037\023eK\032\fW\017\034;%eUA#\021\017B;\005o\022IHa\037\003~\t}$\021\021BB\005\013\0239I!#\003\f\n5%q\022BI\005'\023)Ja&\003\032V\021!1\017\026\0043\tMBAB\t\003l\t\007!\003\002\004\034\005W\022\rA\005\003\007=\t-$\031\001\n\005\r\005\022YG1\001\023\t\031!#1\016b\001%\0211qEa\033C\002I!aA\013B6\005\004\021BAB\027\003l\t\007!\003\002\0041\005W\022\rA\005\003\007g\t-$\031\001\n\005\rY\022YG1\001\023\t\031I$1\016b\001%\0211AHa\033C\002I!aa\020B6\005\004\021BA\002\"\003l\t\007!\003\002\004F\005W\022\rA\005\003\007\021\n-$\031\001\n\005\r-\023YG1\001\023\t\031q%1\016b\001%!I!Q\024\001\022\002\023\005!qT\001\017G>\004\030\020\n3fM\006,H\016\036\0234+!\022\tK!*\003(\n%&1\026BW\005_\023\tLa-\0036\n]&\021\030B^\005{\023yL!1\003D\n\025'q\031Be+\t\021\031KK\002\035\005g!a!\005BN\005\004\021BAB\016\003\034\n\007!\003\002\004\037\0057\023\rA\005\003\007C\tm%\031\001\n\005\r\021\022YJ1\001\023\t\0319#1\024b\001%\0211!Fa'C\002I!a!\fBN\005\004\021BA\002\031\003\034\n\007!\003\002\0044\0057\023\rA\005\003\007m\tm%\031\001\n\005\re\022YJ1\001\023\t\031a$1\024b\001%\0211qHa'C\002I!aA\021BN\005\004\021BAB#\003\034\n\007!\003\002\004I\0057\023\rA\005\003\007\027\nm%\031\001\n\005\r9\023YJ1\001\023\021%\021i\rAI\001\n\003\021y-\001\bd_BLH\005Z3gCVdG\017\n\033\026Q\tE'Q\033Bl\0053\024YN!8\003`\n\005(1\035Bs\005O\024IOa;\003n\n=(\021\037Bz\005k\0249P!?\026\005\tM'fA\020\0034\0211\021Ca3C\002I!aa\007Bf\005\004\021BA\002\020\003L\n\007!\003\002\004\"\005\027\024\rA\005\003\007I\t-'\031\001\n\005\r\035\022YM1\001\023\t\031Q#1\032b\001%\0211QFa3C\002I!a\001\rBf\005\004\021BAB\032\003L\n\007!\003\002\0047\005\027\024\rA\005\003\007s\t-'\031\001\n\005\rq\022YM1\001\023\t\031y$1\032b\001%\0211!Ia3C\002I!a!\022Bf\005\004\021BA\002%\003L\n\007!\003\002\004L\005\027\024\rA\005\003\007\035\n-'\031\001\n\t\023\tu\b!%A\005\002\t}\030AD2paf$C-\0324bk2$H%N\013)\007\003\031)aa\002\004\n\r-1QBB\b\007#\031\031b!\006\004\030\re11DB\017\007?\031\tca\t\004&\r\0352\021F\013\003\007\007Q3A\tB\032\t\031\t\"1 b\001%\02111Da?C\002I!aA\bB~\005\004\021BAB\021\003|\n\007!\003\002\004%\005w\024\rA\005\003\007O\tm(\031\001\n\005\r)\022YP1\001\023\t\031i#1 b\001%\0211\001Ga?C\002I!aa\rB~\005\004\021BA\002\034\003|\n\007!\003\002\004:\005w\024\rA\005\003\007y\tm(\031\001\n\005\r}\022YP1\001\023\t\031\021%1 b\001%\0211QIa?C\002I!a\001\023B~\005\004\021BAB&\003|\n\007!\003\002\004O\005w\024\rA\005\005\n\007[\001\021\023!C\001\007_\tabY8qs\022\"WMZ1vYR$c'\006\025\0042\rU2qGB\035\007w\031ida\020\004B\r\r3QIB$\007\023\032Ye!\024\004P\rE31KB+\007/\032I&\006\002\0044)\032QEa\r\005\rE\031YC1\001\023\t\031Y21\006b\001%\0211ada\013C\002I!a!IB\026\005\004\021BA\002\023\004,\t\007!\003\002\004(\007W\021\rA\005\003\007U\r-\"\031\001\n\005\r5\032YC1\001\023\t\031\00141\006b\001%\02111ga\013C\002I!aANB\026\005\004\021BAB\035\004,\t\007!\003\002\004=\007W\021\rA\005\003\007\r-\"\031\001\n\005\r\t\033YC1\001\023\t\031)51\006b\001%\0211\001ja\013C\002I!aaSB\026\005\004\021BA\002(\004,\t\007!\003C\005\004^\001\t\n\021\"\001\004`\005q1m\0349zI\021,g-Y;mi\022:T\003KB1\007K\0329g!\033\004l\r54qNB9\007g\032)ha\036\004z\rm4QPB@\007\003\033\031i!\"\004\b\016%UCAB2U\rA#1\007\003\007#\rm#\031\001\n\005\rm\031YF1\001\023\t\031q21\fb\001%\0211\021ea\027C\002I!a\001JB.\005\004\021BAB\024\004\\\t\007!\003\002\004+\0077\022\rA\005\003\007[\rm#\031\001\n\005\rA\032YF1\001\023\t\031\03141\fb\001%\0211aga\027C\002I!a!OB.\005\004\021BA\002\037\004\\\t\007!\003\002\004@\0077\022\rA\005\003\007\005\016m#\031\001\n\005\r\025\033YF1\001\023\t\031A51\fb\001%\02111ja\027C\002I!aATB.\005\004\021\002\"CBG\001E\005I\021ABH\0039\031w\016]=%I\0264\027-\0367uIa*\002f!%\004\026\016]5\021TBN\007;\033yj!)\004$\016\0256qUBU\007W\033ika,\0042\016M6QWB\\\007s+\"aa%+\007-\022\031\004\002\004\022\007\027\023\rA\005\003\0077\r-%\031\001\n\005\ry\031YI1\001\023\t\031\t31\022b\001%\0211Aea#C\002I!aaJBF\005\004\021BA\002\026\004\f\n\007!\003\002\004.\007\027\023\rA\005\003\007a\r-%\031\001\n\005\rM\032YI1\001\023\t\031141\022b\001%\0211\021ha#C\002I!a\001PBF\005\004\021BAB \004\f\n\007!\003\002\004C\007\027\023\rA\005\003\007\013\016-%\031\001\n\005\r!\033YI1\001\023\t\031Y51\022b\001%\0211aja#C\002IA\021b!0\001#\003%\taa0\002\035\r|\007/\037\023eK\032\fW\017\034;%sUA3\021YBc\007\017\034Ima3\004N\016=7\021[Bj\007+\0349n!7\004\\\016u7q\\Bq\007G\034)oa:\004jV\02111\031\026\004]\tMBAB\t\004<\n\007!\003\002\004\034\007w\023\rA\005\003\007=\rm&\031\001\n\005\r\005\032YL1\001\023\t\031!31\030b\001%\0211qea/C\002I!aAKB^\005\004\021BAB\027\004<\n\007!\003\002\0041\007w\023\rA\005\003\007g\rm&\031\001\n\005\rY\032YL1\001\023\t\031I41\030b\001%\0211Aha/C\002I!aaPB^\005\004\021BA\002\"\004<\n\007!\003\002\004F\007w\023\rA\005\003\007\021\016m&\031\001\n\005\r-\033YL1\001\023\t\031q51\030b\001%!I1Q\036\001\022\002\023\0051q^\001\020G>\004\030\020\n3fM\006,H\016\036\0232aUA3\021_B{\007o\034Ipa?\004~\016}H\021\001C\002\t\013!9\001\"\003\005\f\0215Aq\002C\t\t'!)\002b\006\005\032U\02111\037\026\004c\tMBAB\t\004l\n\007!\003\002\004\034\007W\024\rA\005\003\007=\r-(\031\001\n\005\r\005\032YO1\001\023\t\031!31\036b\001%\0211qea;C\002I!aAKBv\005\004\021BAB\027\004l\n\007!\003\002\0041\007W\024\rA\005\003\007g\r-(\031\001\n\005\rY\032YO1\001\023\t\031I41\036b\001%\0211Aha;C\002I!aaPBv\005\004\021BA\002\"\004l\n\007!\003\002\004F\007W\024\rA\005\003\007\021\016-(\031\001\n\005\r-\033YO1\001\023\t\031q51\036b\001%!IAQ\004\001\022\002\023\005AqD\001\020G>\004\030\020\n3fM\006,H\016\036\0232cUAC\021\005C\023\tO!I\003b\013\005.\021=B\021\007C\032\tk!9\004\"\017\005<\021uBq\bC!\t\007\")\005b\022\005JU\021A1\005\026\004i\tMBAB\t\005\034\t\007!\003\002\004\034\t7\021\rA\005\003\007=\021m!\031\001\n\005\r\005\"YB1\001\023\t\031!C1\004b\001%\0211q\005b\007C\002I!aA\013C\016\005\004\021BAB\027\005\034\t\007!\003\002\0041\t7\021\rA\005\003\007g\021m!\031\001\n\005\rY\"YB1\001\023\t\031ID1\004b\001%\0211A\bb\007C\002I!aa\020C\016\005\004\021BA\002\"\005\034\t\007!\003\002\004F\t7\021\rA\005\003\007\021\022m!\031\001\n\005\r-#YB1\001\023\t\031qE1\004b\001%!IAQ\n\001\022\002\023\005AqJ\001\020G>\004\030\020\n3fM\006,H\016\036\0232eUAC\021\013C+\t/\"I\006b\027\005^\021}C\021\rC2\tK\"9\007\"\033\005l\0215Dq\016C9\tg\")\bb\036\005zU\021A1\013\026\004o\tMBAB\t\005L\t\007!\003\002\004\034\t\027\022\rA\005\003\007=\021-#\031\001\n\005\r\005\"YE1\001\023\t\031!C1\nb\001%\0211q\005b\023C\002I!aA\013C&\005\004\021BAB\027\005L\t\007!\003\002\0041\t\027\022\rA\005\003\007g\021-#\031\001\n\005\rY\"YE1\001\023\t\031ID1\nb\001%\0211A\bb\023C\002I!aa\020C&\005\004\021BA\002\"\005L\t\007!\003\002\004F\t\027\022\rA\005\003\007\021\022-#\031\001\n\005\r-#YE1\001\023\t\031qE1\nb\001%!IAQ\020\001\022\002\023\005AqP\001\020G>\004\030\020\n3fM\006,H\016\036\0232gUAC\021\021CC\t\017#I\tb#\005\016\022=E\021\023CJ\t+#9\n\"'\005\034\022uEq\024CQ\tG#)\013b*\005*V\021A1\021\026\004u\tMBAB\t\005|\t\007!\003\002\004\034\tw\022\rA\005\003\007=\021m$\031\001\n\005\r\005\"YH1\001\023\t\031!C1\020b\001%\0211q\005b\037C\002I!aA\013C>\005\004\021BAB\027\005|\t\007!\003\002\0041\tw\022\rA\005\003\007g\021m$\031\001\n\005\rY\"YH1\001\023\t\031ID1\020b\001%\0211A\bb\037C\002I!aa\020C>\005\004\021BA\002\"\005|\t\007!\003\002\004F\tw\022\rA\005\003\007\021\022m$\031\001\n\005\r-#YH1\001\023\t\031qE1\020b\001%!IAQ\026\001\022\002\023\005AqV\001\020G>\004\030\020\n3fM\006,H\016\036\0232iUAC\021\027C[\to#I\fb/\005>\022}F\021\031Cb\t\013$9\r\"3\005L\0225Gq\032Ci\t'$)\016b6\005ZV\021A1\027\026\004{\tMBAB\t\005,\n\007!\003\002\004\034\tW\023\rA\005\003\007=\021-&\031\001\n\005\r\005\"YK1\001\023\t\031!C1\026b\001%\0211q\005b+C\002I!aA\013CV\005\004\021BAB\027\005,\n\007!\003\002\0041\tW\023\rA\005\003\007g\021-&\031\001\n\005\rY\"YK1\001\023\t\031ID1\026b\001%\0211A\bb+C\002I!aa\020CV\005\004\021BA\002\"\005,\n\007!\003\002\004F\tW\023\rA\005\003\007\021\022-&\031\001\n\005\r-#YK1\001\023\t\031qE1\026b\001%!IAQ\034\001\022\002\023\005Aq\\\001\020G>\004\030\020\n3fM\006,H\016\036\0232kUAC\021\035Cs\tO$I\017b;\005n\022=H\021\037Cz\tk$9\020\"?\005|\022uHq`C\001\013\007))!b\002\006\nU\021A1\035\026\004\001\nMBAB\t\005\\\n\007!\003\002\004\034\t7\024\rA\005\003\007=\021m'\031\001\n\005\r\005\"YN1\001\023\t\031!C1\034b\001%\0211q\005b7C\002I!aA\013Cn\005\004\021BAB\027\005\\\n\007!\003\002\0041\t7\024\rA\005\003\007g\021m'\031\001\n\005\rY\"YN1\001\023\t\031ID1\034b\001%\0211A\bb7C\002I!aa\020Cn\005\004\021BA\002\"\005\\\n\007!\003\002\004F\t7\024\rA\005\003\007\021\022m'\031\001\n\005\r-#YN1\001\023\t\031qE1\034b\001%!IQQ\002\001\022\002\023\005QqB\001\020G>\004\030\020\n3fM\006,H\016\036\0232mUAS\021CC\013\013/)I\"b\007\006\036\025}Q\021EC\022\013K)9#\"\013\006,\0255RqFC\031\013g))$b\016\006:U\021Q1\003\026\004\007\nMBAB\t\006\f\t\007!\003\002\004\034\013\027\021\rA\005\003\007=\025-!\031\001\n\005\r\005*YA1\001\023\t\031!S1\002b\001%\0211q%b\003C\002I!aAKC\006\005\004\021BAB\027\006\f\t\007!\003\002\0041\013\027\021\rA\005\003\007g\025-!\031\001\n\005\rY*YA1\001\023\t\031IT1\002b\001%\0211A(b\003C\002I!aaPC\006\005\004\021BA\002\"\006\f\t\007!\003\002\004F\013\027\021\rA\005\003\007\021\026-!\031\001\n\005\r-+YA1\001\023\t\031qU1\002b\001%!IQQ\b\001\022\002\023\005QqH\001\020G>\004\030\020\n3fM\006,H\016\036\0232oUAS\021IC#\013\017*I%b\023\006N\025=S\021KC*\013+*9&\"\027\006\\\025uSqLC1\013G*)'b\032\006jU\021Q1\t\026\004\r\nMBAB\t\006<\t\007!\003\002\004\034\013w\021\rA\005\003\007=\025m\"\031\001\n\005\r\005*YD1\001\023\t\031!S1\bb\001%\0211q%b\017C\002I!aAKC\036\005\004\021BAB\027\006<\t\007!\003\002\0041\013w\021\rA\005\003\007g\025m\"\031\001\n\005\rY*YD1\001\023\t\031IT1\bb\001%\0211A(b\017C\002I!aaPC\036\005\004\021BA\002\"\006<\t\007!\003\002\004F\013w\021\rA\005\003\007\021\026m\"\031\001\n\005\r-+YD1\001\023\t\031qU1\bb\001%!IQQ\016\001\022\002\023\005QqN\001\020G>\004\030\020\n3fM\006,H\016\036\0232qUAS\021OC;\013o*I(b\037\006~\025}T\021QCB\013\013+9)\"#\006\f\0265UqRCI\013'+)*b&\006\032V\021Q1\017\026\004\023\nMBAB\t\006l\t\007!\003\002\004\034\013W\022\rA\005\003\007=\025-$\031\001\n\005\r\005*YG1\001\023\t\031!S1\016b\001%\0211q%b\033C\002I!aAKC6\005\004\021BAB\027\006l\t\007!\003\002\0041\013W\022\rA\005\003\007g\025-$\031\001\n\005\rY*YG1\001\023\t\031IT1\016b\001%\0211A(b\033C\002I!aaPC6\005\004\021BA\002\"\006l\t\007!\003\002\004F\013W\022\rA\005\003\007\021\026-$\031\001\n\005\r-+YG1\001\023\t\031qU1\016b\001%!IQQ\024\001\022\002\023\005QqT\001\020G>\004\030\020\n3fM\006,H\016\036\0232sUAS\021UCS\013O+I+b+\006.\026=V\021WCZ\013k+9,\"/\006<\026uVqXCa\013\007,)-b2\006JV\021Q1\025\026\004\031\nMBAB\t\006\034\n\007!\003\002\004\034\0137\023\rA\005\003\007=\025m%\031\001\n\005\r\005*YJ1\001\023\t\031!S1\024b\001%\0211q%b'C\002I!aAKCN\005\004\021BAB\027\006\034\n\007!\003\002\0041\0137\023\rA\005\003\007g\025m%\031\001\n\005\rY*YJ1\001\023\t\031IT1\024b\001%\0211A(b'C\002I!aaPCN\005\004\021BA\002\"\006\034\n\007!\003\002\004F\0137\023\rA\005\003\007\021\026m%\031\001\n\005\r-+YJ1\001\023\t\031qU1\024b\001%!IQQ\032\001\002\002\023\005SqZ\001\016aJ|G-^2u!J,g-\033=\026\005\005u\005\"CCj\001\005\005I\021ICk\003=\001(o\0343vGRLE/\032:bi>\024XCACl!\025)I.b8\027\033\t)YNC\002\006^\n\t!bY8mY\026\034G/[8o\023\021)\t/b7\003\021%#XM]1u_JD\021\"\":\001\003\003%\t!b:\002\021\r\fg.R9vC2$B!\";\006pB\031\001\"b;\n\007\0255(AA\004C_>dW-\0318\t\023\025EX1]A\001\002\0041\022a\001=%c!IQQ\037\001\002\002\023\005Sq_\001\tQ\006\034\bnQ8eKR\021Q\021 \t\004\021\025m\030bAC\005\t\031\021J\034;\t\023\031\005\001!!A\005B\031\r\021AB3rk\006d7\017\006\003\006j\032\025\001\"CCy\013\f\t\0211\001\027\017%1IAAA\001\022\0031Y!A\004UkBdW-M\035\021\007!1iA\002\005\002\005\005\005\t\022\001D\b'\0211ia\002*\t\021\005-dQ\002C\001\r'!\"Ab\003\t\025\005eeQBA\001\n\013\nY\n\003\006\007\032\0315\021\021!CA\r7\tQ!\0319qYf,\002F\"\b\007$\031\035b1\006D\030\rg19Db\017\007@\031\rcq\tD&\r\0372\031Fb\026\007\\\031}c1\rD4\rW\"\002Fb\b\007n\031=d\021\017D:\rk29H\"\037\007|\031udq\020DA\r\0073)Ib\"\007\n\032-eQ\022DH\r#\003\002\006\003\001\007\"\031\025b\021\006D\027\rc1)D\"\017\007>\031\005cQ\tD%\r\0332\tF\"\026\007Z\031uc\021\rD3\rS\0022a\004D\022\t\031\tbq\003b\001%A\031qBb\n\005\rm19B1\001\023!\rya1\006\003\007=\031]!\031\001\n\021\007=1y\003\002\004\"\r/\021\rA\005\t\004\037\031MBA\002\023\007\030\t\007!\003E\002\020\ro!aa\nD\f\005\004\021\002cA\b\007<\0211!Fb\006C\002I\0012a\004D \t\031icq\003b\001%A\031qBb\021\005\rA29B1\001\023!\ryaq\t\003\007g\031]!\031\001\n\021\007=1Y\005\002\0047\r/\021\rA\005\t\004\037\031=CAB\035\007\030\t\007!\003E\002\020\r'\"a\001\020D\f\005\004\021\002cA\b\007X\0211qHb\006C\002I\0012a\004D.\t\031\021eq\003b\001%A\031qBb\030\005\r\02539B1\001\023!\rya1\r\003\007\021\032]!\031\001\n\021\007=19\007\002\004L\r/\021\rA\005\t\004\037\031-DA\002(\007\030\t\007!\003C\004W\r/\001\rA\"\t\t\017m39\0021\001\007&!9\001Mb\006A\002\031%\002bB3\007\030\001\007aQ\006\005\bU\032]\001\031\001D\031\021\035ygq\003a\001\rkAq\001\036D\f\001\0041I\004C\004z\r/\001\rA\"\020\t\017y49\0021\001\007B!A\021q\001D\f\001\0041)\005\003\005\002\022\031]\001\031\001D%\021!\tYBb\006A\002\0315\003\002CA\023\r/\001\rA\"\025\t\021\005=bq\003a\001\r+B\001\"!\017\007\030\001\007a\021\f\005\t\003\00729\0021\001\007^!A\021Q\nD\f\001\0041\t\007\003\005\002X\031]\001\031\001D3\021!\t\tGb\006A\002\031%\004B\003DK\r\033\t\t\021\"!\007\030\0069QO\\1qa2LX\003\013DM\rK3IK\",\0072\032Uf\021\030D_\r\0034)M\"3\007N\032EgQ\033Dm\r;4\tO\":\007j\0325H\003\002DN\r_\004R\001\003DO\rCK1Ab(\003\005\031y\005\017^5p]BA\003\002\001DR\rO3YKb,\0074\032]f1\030D`\r\00749Mb3\007P\032Mgq\033Dn\r?4\031Ob:\007lB\031qB\"*\005\rE1\031J1\001\023!\rya\021\026\003\0077\031M%\031\001\n\021\007=1i\013\002\004\037\r'\023\rA\005\t\004\037\031EFAB\021\007\024\n\007!\003E\002\020\rk#a\001\nDJ\005\004\021\002cA\b\007:\0221qEb%C\002I\0012a\004D_\t\031Qc1\023b\001%A\031qB\"1\005\r52\031J1\001\023!\ryaQ\031\003\007a\031M%\031\001\n\021\007=1I\r\002\0044\r'\023\rA\005\t\004\037\0315GA\002\034\007\024\n\007!\003E\002\020\r#$a!\017DJ\005\004\021\002cA\b\007V\0221AHb%C\002I\0012a\004Dm\t\031yd1\023b\001%A\031qB\"8\005\r\t3\031J1\001\023!\rya\021\035\003\007\013\032M%\031\001\n\021\007=1)\017\002\004I\r'\023\rA\005\t\004\037\031%HAB&\007\024\n\007!\003E\002\020\r[$aA\024DJ\005\004\021\002B\003Dy\r'\013\t\0211\001\007\"\006\031\001\020\n\031\t\025\031UhQBA\001\n\023190A\006sK\006$'+Z:pYZ,GC\001D}!\021\tyJb?\n\t\031u\030\021\025\002\007\037\nTWm\031;")
/*    */ public class Tuple19<T1, T2, T3, T4, T5, T6, T7, T8, T9, T10, T11, T12, T13, T14, T15, T16, T17, T18, T19> implements Product19<T1, T2, T3, T4, T5, T6, T7, T8, T9, T10, T11, T12, T13, T14, T15, T16, T17, T18, T19>, Product, Serializable {
/*    */   private final T1 _1;
/*    */   
/*    */   private final T2 _2;
/*    */   
/*    */   private final T3 _3;
/*    */   
/*    */   private final T4 _4;
/*    */   
/*    */   private final T5 _5;
/*    */   
/*    */   private final T6 _6;
/*    */   
/*    */   private final T7 _7;
/*    */   
/*    */   private final T8 _8;
/*    */   
/*    */   private final T9 _9;
/*    */   
/*    */   private final T10 _10;
/*    */   
/*    */   private final T11 _11;
/*    */   
/*    */   private final T12 _12;
/*    */   
/*    */   private final T13 _13;
/*    */   
/*    */   private final T14 _14;
/*    */   
/*    */   private final T15 _15;
/*    */   
/*    */   private final T16 _16;
/*    */   
/*    */   private final T17 _17;
/*    */   
/*    */   private final T18 _18;
/*    */   
/*    */   private final T19 _19;
/*    */   
/*    */   public int productArity() {
/* 36 */     return Product19$class.productArity(this);
/*    */   }
/*    */   
/*    */   public Object productElement(int n) throws IndexOutOfBoundsException {
/* 36 */     return Product19$class.productElement(this, n);
/*    */   }
/*    */   
/*    */   public T1 _1() {
/* 36 */     return this._1;
/*    */   }
/*    */   
/*    */   public T2 _2() {
/* 36 */     return this._2;
/*    */   }
/*    */   
/*    */   public T3 _3() {
/* 36 */     return this._3;
/*    */   }
/*    */   
/*    */   public T4 _4() {
/* 36 */     return this._4;
/*    */   }
/*    */   
/*    */   public T5 _5() {
/* 36 */     return this._5;
/*    */   }
/*    */   
/*    */   public T6 _6() {
/* 36 */     return this._6;
/*    */   }
/*    */   
/*    */   public T7 _7() {
/* 36 */     return this._7;
/*    */   }
/*    */   
/*    */   public T8 _8() {
/* 36 */     return this._8;
/*    */   }
/*    */   
/*    */   public T9 _9() {
/* 36 */     return this._9;
/*    */   }
/*    */   
/*    */   public T10 _10() {
/* 36 */     return this._10;
/*    */   }
/*    */   
/*    */   public T11 _11() {
/* 36 */     return this._11;
/*    */   }
/*    */   
/*    */   public T12 _12() {
/* 36 */     return this._12;
/*    */   }
/*    */   
/*    */   public T13 _13() {
/* 36 */     return this._13;
/*    */   }
/*    */   
/*    */   public T14 _14() {
/* 36 */     return this._14;
/*    */   }
/*    */   
/*    */   public T15 _15() {
/* 36 */     return this._15;
/*    */   }
/*    */   
/*    */   public T16 _16() {
/* 36 */     return this._16;
/*    */   }
/*    */   
/*    */   public T17 _17() {
/* 36 */     return this._17;
/*    */   }
/*    */   
/*    */   public T18 _18() {
/* 36 */     return this._18;
/*    */   }
/*    */   
/*    */   public T19 _19() {
/* 36 */     return this._19;
/*    */   }
/*    */   
/*    */   public <T1, T2, T3, T4, T5, T6, T7, T8, T9, T10, T11, T12, T13, T14, T15, T16, T17, T18, T19> Tuple19<T1, T2, T3, T4, T5, T6, T7, T8, T9, T10, T11, T12, T13, T14, T15, T16, T17, T18, T19> copy(Object _1, Object _2, Object _3, Object _4, Object _5, Object _6, Object _7, Object _8, Object _9, Object _10, Object _11, Object _12, Object _13, Object _14, Object _15, Object _16, Object _17, Object _18, Object _19) {
/* 36 */     return new Tuple19((T1)_1, (T2)_2, (T3)_3, (T4)_4, (T5)_5, (T6)_6, (T7)_7, (T8)_8, (T9)_9, (T10)_10, (T11)_11, (T12)_12, (T13)_13, (T14)_14, (T15)_15, (T16)_16, (T17)_17, (T18)_18, (T19)_19);
/*    */   }
/*    */   
/*    */   public <T1, T2, T3, T4, T5, T6, T7, T8, T9, T10, T11, T12, T13, T14, T15, T16, T17, T18, T19> T1 copy$default$1() {
/* 36 */     return _1();
/*    */   }
/*    */   
/*    */   public <T1, T2, T3, T4, T5, T6, T7, T8, T9, T10, T11, T12, T13, T14, T15, T16, T17, T18, T19> T2 copy$default$2() {
/* 36 */     return _2();
/*    */   }
/*    */   
/*    */   public <T1, T2, T3, T4, T5, T6, T7, T8, T9, T10, T11, T12, T13, T14, T15, T16, T17, T18, T19> T3 copy$default$3() {
/* 36 */     return _3();
/*    */   }
/*    */   
/*    */   public <T1, T2, T3, T4, T5, T6, T7, T8, T9, T10, T11, T12, T13, T14, T15, T16, T17, T18, T19> T4 copy$default$4() {
/* 36 */     return _4();
/*    */   }
/*    */   
/*    */   public <T1, T2, T3, T4, T5, T6, T7, T8, T9, T10, T11, T12, T13, T14, T15, T16, T17, T18, T19> T5 copy$default$5() {
/* 36 */     return _5();
/*    */   }
/*    */   
/*    */   public <T1, T2, T3, T4, T5, T6, T7, T8, T9, T10, T11, T12, T13, T14, T15, T16, T17, T18, T19> T6 copy$default$6() {
/* 36 */     return _6();
/*    */   }
/*    */   
/*    */   public <T1, T2, T3, T4, T5, T6, T7, T8, T9, T10, T11, T12, T13, T14, T15, T16, T17, T18, T19> T7 copy$default$7() {
/* 36 */     return _7();
/*    */   }
/*    */   
/*    */   public <T1, T2, T3, T4, T5, T6, T7, T8, T9, T10, T11, T12, T13, T14, T15, T16, T17, T18, T19> T8 copy$default$8() {
/* 36 */     return _8();
/*    */   }
/*    */   
/*    */   public <T1, T2, T3, T4, T5, T6, T7, T8, T9, T10, T11, T12, T13, T14, T15, T16, T17, T18, T19> T9 copy$default$9() {
/* 36 */     return _9();
/*    */   }
/*    */   
/*    */   public <T1, T2, T3, T4, T5, T6, T7, T8, T9, T10, T11, T12, T13, T14, T15, T16, T17, T18, T19> T10 copy$default$10() {
/* 36 */     return _10();
/*    */   }
/*    */   
/*    */   public <T1, T2, T3, T4, T5, T6, T7, T8, T9, T10, T11, T12, T13, T14, T15, T16, T17, T18, T19> T11 copy$default$11() {
/* 36 */     return _11();
/*    */   }
/*    */   
/*    */   public <T1, T2, T3, T4, T5, T6, T7, T8, T9, T10, T11, T12, T13, T14, T15, T16, T17, T18, T19> T12 copy$default$12() {
/* 36 */     return _12();
/*    */   }
/*    */   
/*    */   public <T1, T2, T3, T4, T5, T6, T7, T8, T9, T10, T11, T12, T13, T14, T15, T16, T17, T18, T19> T13 copy$default$13() {
/* 36 */     return _13();
/*    */   }
/*    */   
/*    */   public <T1, T2, T3, T4, T5, T6, T7, T8, T9, T10, T11, T12, T13, T14, T15, T16, T17, T18, T19> T14 copy$default$14() {
/* 36 */     return _14();
/*    */   }
/*    */   
/*    */   public <T1, T2, T3, T4, T5, T6, T7, T8, T9, T10, T11, T12, T13, T14, T15, T16, T17, T18, T19> T15 copy$default$15() {
/* 36 */     return _15();
/*    */   }
/*    */   
/*    */   public <T1, T2, T3, T4, T5, T6, T7, T8, T9, T10, T11, T12, T13, T14, T15, T16, T17, T18, T19> T16 copy$default$16() {
/* 36 */     return _16();
/*    */   }
/*    */   
/*    */   public <T1, T2, T3, T4, T5, T6, T7, T8, T9, T10, T11, T12, T13, T14, T15, T16, T17, T18, T19> T17 copy$default$17() {
/* 36 */     return _17();
/*    */   }
/*    */   
/*    */   public <T1, T2, T3, T4, T5, T6, T7, T8, T9, T10, T11, T12, T13, T14, T15, T16, T17, T18, T19> T18 copy$default$18() {
/* 36 */     return _18();
/*    */   }
/*    */   
/*    */   public <T1, T2, T3, T4, T5, T6, T7, T8, T9, T10, T11, T12, T13, T14, T15, T16, T17, T18, T19> T19 copy$default$19() {
/* 36 */     return _19();
/*    */   }
/*    */   
/*    */   public String productPrefix() {
/* 36 */     return "Tuple19";
/*    */   }
/*    */   
/*    */   public Iterator<Object> productIterator() {
/* 36 */     return ScalaRunTime$.MODULE$.typedProductIterator(this);
/*    */   }
/*    */   
/*    */   public boolean canEqual(Object x$1) {
/* 36 */     return x$1 instanceof Tuple19;
/*    */   }
/*    */   
/*    */   public int hashCode() {
/* 36 */     return ScalaRunTime$.MODULE$._hashCode(this);
/*    */   }
/*    */   
/*    */   public boolean equals(Object x$1) {
/*    */     // Byte code:
/*    */     //   0: aload_0
/*    */     //   1: aload_1
/*    */     //   2: if_acmpeq -> 1635
/*    */     //   5: aload_1
/*    */     //   6: instanceof scala/Tuple19
/*    */     //   9: ifeq -> 17
/*    */     //   12: iconst_1
/*    */     //   13: istore_2
/*    */     //   14: goto -> 19
/*    */     //   17: iconst_0
/*    */     //   18: istore_2
/*    */     //   19: iload_2
/*    */     //   20: ifeq -> 1639
/*    */     //   23: aload_1
/*    */     //   24: checkcast scala/Tuple19
/*    */     //   27: astore #41
/*    */     //   29: aload_0
/*    */     //   30: invokevirtual _1 : ()Ljava/lang/Object;
/*    */     //   33: aload #41
/*    */     //   35: invokevirtual _1 : ()Ljava/lang/Object;
/*    */     //   38: astore #4
/*    */     //   40: dup
/*    */     //   41: astore_3
/*    */     //   42: aload #4
/*    */     //   44: if_acmpne -> 51
/*    */     //   47: iconst_1
/*    */     //   48: goto -> 103
/*    */     //   51: aload_3
/*    */     //   52: ifnonnull -> 59
/*    */     //   55: iconst_0
/*    */     //   56: goto -> 103
/*    */     //   59: aload_3
/*    */     //   60: instanceof java/lang/Number
/*    */     //   63: ifeq -> 78
/*    */     //   66: aload_3
/*    */     //   67: checkcast java/lang/Number
/*    */     //   70: aload #4
/*    */     //   72: invokestatic equalsNumObject : (Ljava/lang/Number;Ljava/lang/Object;)Z
/*    */     //   75: goto -> 103
/*    */     //   78: aload_3
/*    */     //   79: instanceof java/lang/Character
/*    */     //   82: ifeq -> 97
/*    */     //   85: aload_3
/*    */     //   86: checkcast java/lang/Character
/*    */     //   89: aload #4
/*    */     //   91: invokestatic equalsCharObject : (Ljava/lang/Character;Ljava/lang/Object;)Z
/*    */     //   94: goto -> 103
/*    */     //   97: aload_3
/*    */     //   98: aload #4
/*    */     //   100: invokevirtual equals : (Ljava/lang/Object;)Z
/*    */     //   103: ifeq -> 1631
/*    */     //   106: aload_0
/*    */     //   107: invokevirtual _2 : ()Ljava/lang/Object;
/*    */     //   110: aload #41
/*    */     //   112: invokevirtual _2 : ()Ljava/lang/Object;
/*    */     //   115: astore #6
/*    */     //   117: dup
/*    */     //   118: astore #5
/*    */     //   120: aload #6
/*    */     //   122: if_acmpne -> 129
/*    */     //   125: iconst_1
/*    */     //   126: goto -> 187
/*    */     //   129: aload #5
/*    */     //   131: ifnonnull -> 138
/*    */     //   134: iconst_0
/*    */     //   135: goto -> 187
/*    */     //   138: aload #5
/*    */     //   140: instanceof java/lang/Number
/*    */     //   143: ifeq -> 159
/*    */     //   146: aload #5
/*    */     //   148: checkcast java/lang/Number
/*    */     //   151: aload #6
/*    */     //   153: invokestatic equalsNumObject : (Ljava/lang/Number;Ljava/lang/Object;)Z
/*    */     //   156: goto -> 187
/*    */     //   159: aload #5
/*    */     //   161: instanceof java/lang/Character
/*    */     //   164: ifeq -> 180
/*    */     //   167: aload #5
/*    */     //   169: checkcast java/lang/Character
/*    */     //   172: aload #6
/*    */     //   174: invokestatic equalsCharObject : (Ljava/lang/Character;Ljava/lang/Object;)Z
/*    */     //   177: goto -> 187
/*    */     //   180: aload #5
/*    */     //   182: aload #6
/*    */     //   184: invokevirtual equals : (Ljava/lang/Object;)Z
/*    */     //   187: ifeq -> 1631
/*    */     //   190: aload_0
/*    */     //   191: invokevirtual _3 : ()Ljava/lang/Object;
/*    */     //   194: aload #41
/*    */     //   196: invokevirtual _3 : ()Ljava/lang/Object;
/*    */     //   199: astore #8
/*    */     //   201: dup
/*    */     //   202: astore #7
/*    */     //   204: aload #8
/*    */     //   206: if_acmpne -> 213
/*    */     //   209: iconst_1
/*    */     //   210: goto -> 271
/*    */     //   213: aload #7
/*    */     //   215: ifnonnull -> 222
/*    */     //   218: iconst_0
/*    */     //   219: goto -> 271
/*    */     //   222: aload #7
/*    */     //   224: instanceof java/lang/Number
/*    */     //   227: ifeq -> 243
/*    */     //   230: aload #7
/*    */     //   232: checkcast java/lang/Number
/*    */     //   235: aload #8
/*    */     //   237: invokestatic equalsNumObject : (Ljava/lang/Number;Ljava/lang/Object;)Z
/*    */     //   240: goto -> 271
/*    */     //   243: aload #7
/*    */     //   245: instanceof java/lang/Character
/*    */     //   248: ifeq -> 264
/*    */     //   251: aload #7
/*    */     //   253: checkcast java/lang/Character
/*    */     //   256: aload #8
/*    */     //   258: invokestatic equalsCharObject : (Ljava/lang/Character;Ljava/lang/Object;)Z
/*    */     //   261: goto -> 271
/*    */     //   264: aload #7
/*    */     //   266: aload #8
/*    */     //   268: invokevirtual equals : (Ljava/lang/Object;)Z
/*    */     //   271: ifeq -> 1631
/*    */     //   274: aload_0
/*    */     //   275: invokevirtual _4 : ()Ljava/lang/Object;
/*    */     //   278: aload #41
/*    */     //   280: invokevirtual _4 : ()Ljava/lang/Object;
/*    */     //   283: astore #10
/*    */     //   285: dup
/*    */     //   286: astore #9
/*    */     //   288: aload #10
/*    */     //   290: if_acmpne -> 297
/*    */     //   293: iconst_1
/*    */     //   294: goto -> 355
/*    */     //   297: aload #9
/*    */     //   299: ifnonnull -> 306
/*    */     //   302: iconst_0
/*    */     //   303: goto -> 355
/*    */     //   306: aload #9
/*    */     //   308: instanceof java/lang/Number
/*    */     //   311: ifeq -> 327
/*    */     //   314: aload #9
/*    */     //   316: checkcast java/lang/Number
/*    */     //   319: aload #10
/*    */     //   321: invokestatic equalsNumObject : (Ljava/lang/Number;Ljava/lang/Object;)Z
/*    */     //   324: goto -> 355
/*    */     //   327: aload #9
/*    */     //   329: instanceof java/lang/Character
/*    */     //   332: ifeq -> 348
/*    */     //   335: aload #9
/*    */     //   337: checkcast java/lang/Character
/*    */     //   340: aload #10
/*    */     //   342: invokestatic equalsCharObject : (Ljava/lang/Character;Ljava/lang/Object;)Z
/*    */     //   345: goto -> 355
/*    */     //   348: aload #9
/*    */     //   350: aload #10
/*    */     //   352: invokevirtual equals : (Ljava/lang/Object;)Z
/*    */     //   355: ifeq -> 1631
/*    */     //   358: aload_0
/*    */     //   359: invokevirtual _5 : ()Ljava/lang/Object;
/*    */     //   362: aload #41
/*    */     //   364: invokevirtual _5 : ()Ljava/lang/Object;
/*    */     //   367: astore #12
/*    */     //   369: dup
/*    */     //   370: astore #11
/*    */     //   372: aload #12
/*    */     //   374: if_acmpne -> 381
/*    */     //   377: iconst_1
/*    */     //   378: goto -> 439
/*    */     //   381: aload #11
/*    */     //   383: ifnonnull -> 390
/*    */     //   386: iconst_0
/*    */     //   387: goto -> 439
/*    */     //   390: aload #11
/*    */     //   392: instanceof java/lang/Number
/*    */     //   395: ifeq -> 411
/*    */     //   398: aload #11
/*    */     //   400: checkcast java/lang/Number
/*    */     //   403: aload #12
/*    */     //   405: invokestatic equalsNumObject : (Ljava/lang/Number;Ljava/lang/Object;)Z
/*    */     //   408: goto -> 439
/*    */     //   411: aload #11
/*    */     //   413: instanceof java/lang/Character
/*    */     //   416: ifeq -> 432
/*    */     //   419: aload #11
/*    */     //   421: checkcast java/lang/Character
/*    */     //   424: aload #12
/*    */     //   426: invokestatic equalsCharObject : (Ljava/lang/Character;Ljava/lang/Object;)Z
/*    */     //   429: goto -> 439
/*    */     //   432: aload #11
/*    */     //   434: aload #12
/*    */     //   436: invokevirtual equals : (Ljava/lang/Object;)Z
/*    */     //   439: ifeq -> 1631
/*    */     //   442: aload_0
/*    */     //   443: invokevirtual _6 : ()Ljava/lang/Object;
/*    */     //   446: aload #41
/*    */     //   448: invokevirtual _6 : ()Ljava/lang/Object;
/*    */     //   451: astore #14
/*    */     //   453: dup
/*    */     //   454: astore #13
/*    */     //   456: aload #14
/*    */     //   458: if_acmpne -> 465
/*    */     //   461: iconst_1
/*    */     //   462: goto -> 523
/*    */     //   465: aload #13
/*    */     //   467: ifnonnull -> 474
/*    */     //   470: iconst_0
/*    */     //   471: goto -> 523
/*    */     //   474: aload #13
/*    */     //   476: instanceof java/lang/Number
/*    */     //   479: ifeq -> 495
/*    */     //   482: aload #13
/*    */     //   484: checkcast java/lang/Number
/*    */     //   487: aload #14
/*    */     //   489: invokestatic equalsNumObject : (Ljava/lang/Number;Ljava/lang/Object;)Z
/*    */     //   492: goto -> 523
/*    */     //   495: aload #13
/*    */     //   497: instanceof java/lang/Character
/*    */     //   500: ifeq -> 516
/*    */     //   503: aload #13
/*    */     //   505: checkcast java/lang/Character
/*    */     //   508: aload #14
/*    */     //   510: invokestatic equalsCharObject : (Ljava/lang/Character;Ljava/lang/Object;)Z
/*    */     //   513: goto -> 523
/*    */     //   516: aload #13
/*    */     //   518: aload #14
/*    */     //   520: invokevirtual equals : (Ljava/lang/Object;)Z
/*    */     //   523: ifeq -> 1631
/*    */     //   526: aload_0
/*    */     //   527: invokevirtual _7 : ()Ljava/lang/Object;
/*    */     //   530: aload #41
/*    */     //   532: invokevirtual _7 : ()Ljava/lang/Object;
/*    */     //   535: astore #16
/*    */     //   537: dup
/*    */     //   538: astore #15
/*    */     //   540: aload #16
/*    */     //   542: if_acmpne -> 549
/*    */     //   545: iconst_1
/*    */     //   546: goto -> 607
/*    */     //   549: aload #15
/*    */     //   551: ifnonnull -> 558
/*    */     //   554: iconst_0
/*    */     //   555: goto -> 607
/*    */     //   558: aload #15
/*    */     //   560: instanceof java/lang/Number
/*    */     //   563: ifeq -> 579
/*    */     //   566: aload #15
/*    */     //   568: checkcast java/lang/Number
/*    */     //   571: aload #16
/*    */     //   573: invokestatic equalsNumObject : (Ljava/lang/Number;Ljava/lang/Object;)Z
/*    */     //   576: goto -> 607
/*    */     //   579: aload #15
/*    */     //   581: instanceof java/lang/Character
/*    */     //   584: ifeq -> 600
/*    */     //   587: aload #15
/*    */     //   589: checkcast java/lang/Character
/*    */     //   592: aload #16
/*    */     //   594: invokestatic equalsCharObject : (Ljava/lang/Character;Ljava/lang/Object;)Z
/*    */     //   597: goto -> 607
/*    */     //   600: aload #15
/*    */     //   602: aload #16
/*    */     //   604: invokevirtual equals : (Ljava/lang/Object;)Z
/*    */     //   607: ifeq -> 1631
/*    */     //   610: aload_0
/*    */     //   611: invokevirtual _8 : ()Ljava/lang/Object;
/*    */     //   614: aload #41
/*    */     //   616: invokevirtual _8 : ()Ljava/lang/Object;
/*    */     //   619: astore #18
/*    */     //   621: dup
/*    */     //   622: astore #17
/*    */     //   624: aload #18
/*    */     //   626: if_acmpne -> 633
/*    */     //   629: iconst_1
/*    */     //   630: goto -> 691
/*    */     //   633: aload #17
/*    */     //   635: ifnonnull -> 642
/*    */     //   638: iconst_0
/*    */     //   639: goto -> 691
/*    */     //   642: aload #17
/*    */     //   644: instanceof java/lang/Number
/*    */     //   647: ifeq -> 663
/*    */     //   650: aload #17
/*    */     //   652: checkcast java/lang/Number
/*    */     //   655: aload #18
/*    */     //   657: invokestatic equalsNumObject : (Ljava/lang/Number;Ljava/lang/Object;)Z
/*    */     //   660: goto -> 691
/*    */     //   663: aload #17
/*    */     //   665: instanceof java/lang/Character
/*    */     //   668: ifeq -> 684
/*    */     //   671: aload #17
/*    */     //   673: checkcast java/lang/Character
/*    */     //   676: aload #18
/*    */     //   678: invokestatic equalsCharObject : (Ljava/lang/Character;Ljava/lang/Object;)Z
/*    */     //   681: goto -> 691
/*    */     //   684: aload #17
/*    */     //   686: aload #18
/*    */     //   688: invokevirtual equals : (Ljava/lang/Object;)Z
/*    */     //   691: ifeq -> 1631
/*    */     //   694: aload_0
/*    */     //   695: invokevirtual _9 : ()Ljava/lang/Object;
/*    */     //   698: aload #41
/*    */     //   700: invokevirtual _9 : ()Ljava/lang/Object;
/*    */     //   703: astore #20
/*    */     //   705: dup
/*    */     //   706: astore #19
/*    */     //   708: aload #20
/*    */     //   710: if_acmpne -> 717
/*    */     //   713: iconst_1
/*    */     //   714: goto -> 775
/*    */     //   717: aload #19
/*    */     //   719: ifnonnull -> 726
/*    */     //   722: iconst_0
/*    */     //   723: goto -> 775
/*    */     //   726: aload #19
/*    */     //   728: instanceof java/lang/Number
/*    */     //   731: ifeq -> 747
/*    */     //   734: aload #19
/*    */     //   736: checkcast java/lang/Number
/*    */     //   739: aload #20
/*    */     //   741: invokestatic equalsNumObject : (Ljava/lang/Number;Ljava/lang/Object;)Z
/*    */     //   744: goto -> 775
/*    */     //   747: aload #19
/*    */     //   749: instanceof java/lang/Character
/*    */     //   752: ifeq -> 768
/*    */     //   755: aload #19
/*    */     //   757: checkcast java/lang/Character
/*    */     //   760: aload #20
/*    */     //   762: invokestatic equalsCharObject : (Ljava/lang/Character;Ljava/lang/Object;)Z
/*    */     //   765: goto -> 775
/*    */     //   768: aload #19
/*    */     //   770: aload #20
/*    */     //   772: invokevirtual equals : (Ljava/lang/Object;)Z
/*    */     //   775: ifeq -> 1631
/*    */     //   778: aload_0
/*    */     //   779: invokevirtual _10 : ()Ljava/lang/Object;
/*    */     //   782: aload #41
/*    */     //   784: invokevirtual _10 : ()Ljava/lang/Object;
/*    */     //   787: astore #22
/*    */     //   789: dup
/*    */     //   790: astore #21
/*    */     //   792: aload #22
/*    */     //   794: if_acmpne -> 801
/*    */     //   797: iconst_1
/*    */     //   798: goto -> 859
/*    */     //   801: aload #21
/*    */     //   803: ifnonnull -> 810
/*    */     //   806: iconst_0
/*    */     //   807: goto -> 859
/*    */     //   810: aload #21
/*    */     //   812: instanceof java/lang/Number
/*    */     //   815: ifeq -> 831
/*    */     //   818: aload #21
/*    */     //   820: checkcast java/lang/Number
/*    */     //   823: aload #22
/*    */     //   825: invokestatic equalsNumObject : (Ljava/lang/Number;Ljava/lang/Object;)Z
/*    */     //   828: goto -> 859
/*    */     //   831: aload #21
/*    */     //   833: instanceof java/lang/Character
/*    */     //   836: ifeq -> 852
/*    */     //   839: aload #21
/*    */     //   841: checkcast java/lang/Character
/*    */     //   844: aload #22
/*    */     //   846: invokestatic equalsCharObject : (Ljava/lang/Character;Ljava/lang/Object;)Z
/*    */     //   849: goto -> 859
/*    */     //   852: aload #21
/*    */     //   854: aload #22
/*    */     //   856: invokevirtual equals : (Ljava/lang/Object;)Z
/*    */     //   859: ifeq -> 1631
/*    */     //   862: aload_0
/*    */     //   863: invokevirtual _11 : ()Ljava/lang/Object;
/*    */     //   866: aload #41
/*    */     //   868: invokevirtual _11 : ()Ljava/lang/Object;
/*    */     //   871: astore #24
/*    */     //   873: dup
/*    */     //   874: astore #23
/*    */     //   876: aload #24
/*    */     //   878: if_acmpne -> 885
/*    */     //   881: iconst_1
/*    */     //   882: goto -> 943
/*    */     //   885: aload #23
/*    */     //   887: ifnonnull -> 894
/*    */     //   890: iconst_0
/*    */     //   891: goto -> 943
/*    */     //   894: aload #23
/*    */     //   896: instanceof java/lang/Number
/*    */     //   899: ifeq -> 915
/*    */     //   902: aload #23
/*    */     //   904: checkcast java/lang/Number
/*    */     //   907: aload #24
/*    */     //   909: invokestatic equalsNumObject : (Ljava/lang/Number;Ljava/lang/Object;)Z
/*    */     //   912: goto -> 943
/*    */     //   915: aload #23
/*    */     //   917: instanceof java/lang/Character
/*    */     //   920: ifeq -> 936
/*    */     //   923: aload #23
/*    */     //   925: checkcast java/lang/Character
/*    */     //   928: aload #24
/*    */     //   930: invokestatic equalsCharObject : (Ljava/lang/Character;Ljava/lang/Object;)Z
/*    */     //   933: goto -> 943
/*    */     //   936: aload #23
/*    */     //   938: aload #24
/*    */     //   940: invokevirtual equals : (Ljava/lang/Object;)Z
/*    */     //   943: ifeq -> 1631
/*    */     //   946: aload_0
/*    */     //   947: invokevirtual _12 : ()Ljava/lang/Object;
/*    */     //   950: aload #41
/*    */     //   952: invokevirtual _12 : ()Ljava/lang/Object;
/*    */     //   955: astore #26
/*    */     //   957: dup
/*    */     //   958: astore #25
/*    */     //   960: aload #26
/*    */     //   962: if_acmpne -> 969
/*    */     //   965: iconst_1
/*    */     //   966: goto -> 1027
/*    */     //   969: aload #25
/*    */     //   971: ifnonnull -> 978
/*    */     //   974: iconst_0
/*    */     //   975: goto -> 1027
/*    */     //   978: aload #25
/*    */     //   980: instanceof java/lang/Number
/*    */     //   983: ifeq -> 999
/*    */     //   986: aload #25
/*    */     //   988: checkcast java/lang/Number
/*    */     //   991: aload #26
/*    */     //   993: invokestatic equalsNumObject : (Ljava/lang/Number;Ljava/lang/Object;)Z
/*    */     //   996: goto -> 1027
/*    */     //   999: aload #25
/*    */     //   1001: instanceof java/lang/Character
/*    */     //   1004: ifeq -> 1020
/*    */     //   1007: aload #25
/*    */     //   1009: checkcast java/lang/Character
/*    */     //   1012: aload #26
/*    */     //   1014: invokestatic equalsCharObject : (Ljava/lang/Character;Ljava/lang/Object;)Z
/*    */     //   1017: goto -> 1027
/*    */     //   1020: aload #25
/*    */     //   1022: aload #26
/*    */     //   1024: invokevirtual equals : (Ljava/lang/Object;)Z
/*    */     //   1027: ifeq -> 1631
/*    */     //   1030: aload_0
/*    */     //   1031: invokevirtual _13 : ()Ljava/lang/Object;
/*    */     //   1034: aload #41
/*    */     //   1036: invokevirtual _13 : ()Ljava/lang/Object;
/*    */     //   1039: astore #28
/*    */     //   1041: dup
/*    */     //   1042: astore #27
/*    */     //   1044: aload #28
/*    */     //   1046: if_acmpne -> 1053
/*    */     //   1049: iconst_1
/*    */     //   1050: goto -> 1111
/*    */     //   1053: aload #27
/*    */     //   1055: ifnonnull -> 1062
/*    */     //   1058: iconst_0
/*    */     //   1059: goto -> 1111
/*    */     //   1062: aload #27
/*    */     //   1064: instanceof java/lang/Number
/*    */     //   1067: ifeq -> 1083
/*    */     //   1070: aload #27
/*    */     //   1072: checkcast java/lang/Number
/*    */     //   1075: aload #28
/*    */     //   1077: invokestatic equalsNumObject : (Ljava/lang/Number;Ljava/lang/Object;)Z
/*    */     //   1080: goto -> 1111
/*    */     //   1083: aload #27
/*    */     //   1085: instanceof java/lang/Character
/*    */     //   1088: ifeq -> 1104
/*    */     //   1091: aload #27
/*    */     //   1093: checkcast java/lang/Character
/*    */     //   1096: aload #28
/*    */     //   1098: invokestatic equalsCharObject : (Ljava/lang/Character;Ljava/lang/Object;)Z
/*    */     //   1101: goto -> 1111
/*    */     //   1104: aload #27
/*    */     //   1106: aload #28
/*    */     //   1108: invokevirtual equals : (Ljava/lang/Object;)Z
/*    */     //   1111: ifeq -> 1631
/*    */     //   1114: aload_0
/*    */     //   1115: invokevirtual _14 : ()Ljava/lang/Object;
/*    */     //   1118: aload #41
/*    */     //   1120: invokevirtual _14 : ()Ljava/lang/Object;
/*    */     //   1123: astore #30
/*    */     //   1125: dup
/*    */     //   1126: astore #29
/*    */     //   1128: aload #30
/*    */     //   1130: if_acmpne -> 1137
/*    */     //   1133: iconst_1
/*    */     //   1134: goto -> 1195
/*    */     //   1137: aload #29
/*    */     //   1139: ifnonnull -> 1146
/*    */     //   1142: iconst_0
/*    */     //   1143: goto -> 1195
/*    */     //   1146: aload #29
/*    */     //   1148: instanceof java/lang/Number
/*    */     //   1151: ifeq -> 1167
/*    */     //   1154: aload #29
/*    */     //   1156: checkcast java/lang/Number
/*    */     //   1159: aload #30
/*    */     //   1161: invokestatic equalsNumObject : (Ljava/lang/Number;Ljava/lang/Object;)Z
/*    */     //   1164: goto -> 1195
/*    */     //   1167: aload #29
/*    */     //   1169: instanceof java/lang/Character
/*    */     //   1172: ifeq -> 1188
/*    */     //   1175: aload #29
/*    */     //   1177: checkcast java/lang/Character
/*    */     //   1180: aload #30
/*    */     //   1182: invokestatic equalsCharObject : (Ljava/lang/Character;Ljava/lang/Object;)Z
/*    */     //   1185: goto -> 1195
/*    */     //   1188: aload #29
/*    */     //   1190: aload #30
/*    */     //   1192: invokevirtual equals : (Ljava/lang/Object;)Z
/*    */     //   1195: ifeq -> 1631
/*    */     //   1198: aload_0
/*    */     //   1199: invokevirtual _15 : ()Ljava/lang/Object;
/*    */     //   1202: aload #41
/*    */     //   1204: invokevirtual _15 : ()Ljava/lang/Object;
/*    */     //   1207: astore #32
/*    */     //   1209: dup
/*    */     //   1210: astore #31
/*    */     //   1212: aload #32
/*    */     //   1214: if_acmpne -> 1221
/*    */     //   1217: iconst_1
/*    */     //   1218: goto -> 1279
/*    */     //   1221: aload #31
/*    */     //   1223: ifnonnull -> 1230
/*    */     //   1226: iconst_0
/*    */     //   1227: goto -> 1279
/*    */     //   1230: aload #31
/*    */     //   1232: instanceof java/lang/Number
/*    */     //   1235: ifeq -> 1251
/*    */     //   1238: aload #31
/*    */     //   1240: checkcast java/lang/Number
/*    */     //   1243: aload #32
/*    */     //   1245: invokestatic equalsNumObject : (Ljava/lang/Number;Ljava/lang/Object;)Z
/*    */     //   1248: goto -> 1279
/*    */     //   1251: aload #31
/*    */     //   1253: instanceof java/lang/Character
/*    */     //   1256: ifeq -> 1272
/*    */     //   1259: aload #31
/*    */     //   1261: checkcast java/lang/Character
/*    */     //   1264: aload #32
/*    */     //   1266: invokestatic equalsCharObject : (Ljava/lang/Character;Ljava/lang/Object;)Z
/*    */     //   1269: goto -> 1279
/*    */     //   1272: aload #31
/*    */     //   1274: aload #32
/*    */     //   1276: invokevirtual equals : (Ljava/lang/Object;)Z
/*    */     //   1279: ifeq -> 1631
/*    */     //   1282: aload_0
/*    */     //   1283: invokevirtual _16 : ()Ljava/lang/Object;
/*    */     //   1286: aload #41
/*    */     //   1288: invokevirtual _16 : ()Ljava/lang/Object;
/*    */     //   1291: astore #34
/*    */     //   1293: dup
/*    */     //   1294: astore #33
/*    */     //   1296: aload #34
/*    */     //   1298: if_acmpne -> 1305
/*    */     //   1301: iconst_1
/*    */     //   1302: goto -> 1363
/*    */     //   1305: aload #33
/*    */     //   1307: ifnonnull -> 1314
/*    */     //   1310: iconst_0
/*    */     //   1311: goto -> 1363
/*    */     //   1314: aload #33
/*    */     //   1316: instanceof java/lang/Number
/*    */     //   1319: ifeq -> 1335
/*    */     //   1322: aload #33
/*    */     //   1324: checkcast java/lang/Number
/*    */     //   1327: aload #34
/*    */     //   1329: invokestatic equalsNumObject : (Ljava/lang/Number;Ljava/lang/Object;)Z
/*    */     //   1332: goto -> 1363
/*    */     //   1335: aload #33
/*    */     //   1337: instanceof java/lang/Character
/*    */     //   1340: ifeq -> 1356
/*    */     //   1343: aload #33
/*    */     //   1345: checkcast java/lang/Character
/*    */     //   1348: aload #34
/*    */     //   1350: invokestatic equalsCharObject : (Ljava/lang/Character;Ljava/lang/Object;)Z
/*    */     //   1353: goto -> 1363
/*    */     //   1356: aload #33
/*    */     //   1358: aload #34
/*    */     //   1360: invokevirtual equals : (Ljava/lang/Object;)Z
/*    */     //   1363: ifeq -> 1631
/*    */     //   1366: aload_0
/*    */     //   1367: invokevirtual _17 : ()Ljava/lang/Object;
/*    */     //   1370: aload #41
/*    */     //   1372: invokevirtual _17 : ()Ljava/lang/Object;
/*    */     //   1375: astore #36
/*    */     //   1377: dup
/*    */     //   1378: astore #35
/*    */     //   1380: aload #36
/*    */     //   1382: if_acmpne -> 1389
/*    */     //   1385: iconst_1
/*    */     //   1386: goto -> 1447
/*    */     //   1389: aload #35
/*    */     //   1391: ifnonnull -> 1398
/*    */     //   1394: iconst_0
/*    */     //   1395: goto -> 1447
/*    */     //   1398: aload #35
/*    */     //   1400: instanceof java/lang/Number
/*    */     //   1403: ifeq -> 1419
/*    */     //   1406: aload #35
/*    */     //   1408: checkcast java/lang/Number
/*    */     //   1411: aload #36
/*    */     //   1413: invokestatic equalsNumObject : (Ljava/lang/Number;Ljava/lang/Object;)Z
/*    */     //   1416: goto -> 1447
/*    */     //   1419: aload #35
/*    */     //   1421: instanceof java/lang/Character
/*    */     //   1424: ifeq -> 1440
/*    */     //   1427: aload #35
/*    */     //   1429: checkcast java/lang/Character
/*    */     //   1432: aload #36
/*    */     //   1434: invokestatic equalsCharObject : (Ljava/lang/Character;Ljava/lang/Object;)Z
/*    */     //   1437: goto -> 1447
/*    */     //   1440: aload #35
/*    */     //   1442: aload #36
/*    */     //   1444: invokevirtual equals : (Ljava/lang/Object;)Z
/*    */     //   1447: ifeq -> 1631
/*    */     //   1450: aload_0
/*    */     //   1451: invokevirtual _18 : ()Ljava/lang/Object;
/*    */     //   1454: aload #41
/*    */     //   1456: invokevirtual _18 : ()Ljava/lang/Object;
/*    */     //   1459: astore #38
/*    */     //   1461: dup
/*    */     //   1462: astore #37
/*    */     //   1464: aload #38
/*    */     //   1466: if_acmpne -> 1473
/*    */     //   1469: iconst_1
/*    */     //   1470: goto -> 1531
/*    */     //   1473: aload #37
/*    */     //   1475: ifnonnull -> 1482
/*    */     //   1478: iconst_0
/*    */     //   1479: goto -> 1531
/*    */     //   1482: aload #37
/*    */     //   1484: instanceof java/lang/Number
/*    */     //   1487: ifeq -> 1503
/*    */     //   1490: aload #37
/*    */     //   1492: checkcast java/lang/Number
/*    */     //   1495: aload #38
/*    */     //   1497: invokestatic equalsNumObject : (Ljava/lang/Number;Ljava/lang/Object;)Z
/*    */     //   1500: goto -> 1531
/*    */     //   1503: aload #37
/*    */     //   1505: instanceof java/lang/Character
/*    */     //   1508: ifeq -> 1524
/*    */     //   1511: aload #37
/*    */     //   1513: checkcast java/lang/Character
/*    */     //   1516: aload #38
/*    */     //   1518: invokestatic equalsCharObject : (Ljava/lang/Character;Ljava/lang/Object;)Z
/*    */     //   1521: goto -> 1531
/*    */     //   1524: aload #37
/*    */     //   1526: aload #38
/*    */     //   1528: invokevirtual equals : (Ljava/lang/Object;)Z
/*    */     //   1531: ifeq -> 1631
/*    */     //   1534: aload_0
/*    */     //   1535: invokevirtual _19 : ()Ljava/lang/Object;
/*    */     //   1538: aload #41
/*    */     //   1540: invokevirtual _19 : ()Ljava/lang/Object;
/*    */     //   1543: astore #40
/*    */     //   1545: dup
/*    */     //   1546: astore #39
/*    */     //   1548: aload #40
/*    */     //   1550: if_acmpne -> 1557
/*    */     //   1553: iconst_1
/*    */     //   1554: goto -> 1615
/*    */     //   1557: aload #39
/*    */     //   1559: ifnonnull -> 1566
/*    */     //   1562: iconst_0
/*    */     //   1563: goto -> 1615
/*    */     //   1566: aload #39
/*    */     //   1568: instanceof java/lang/Number
/*    */     //   1571: ifeq -> 1587
/*    */     //   1574: aload #39
/*    */     //   1576: checkcast java/lang/Number
/*    */     //   1579: aload #40
/*    */     //   1581: invokestatic equalsNumObject : (Ljava/lang/Number;Ljava/lang/Object;)Z
/*    */     //   1584: goto -> 1615
/*    */     //   1587: aload #39
/*    */     //   1589: instanceof java/lang/Character
/*    */     //   1592: ifeq -> 1608
/*    */     //   1595: aload #39
/*    */     //   1597: checkcast java/lang/Character
/*    */     //   1600: aload #40
/*    */     //   1602: invokestatic equalsCharObject : (Ljava/lang/Character;Ljava/lang/Object;)Z
/*    */     //   1605: goto -> 1615
/*    */     //   1608: aload #39
/*    */     //   1610: aload #40
/*    */     //   1612: invokevirtual equals : (Ljava/lang/Object;)Z
/*    */     //   1615: ifeq -> 1631
/*    */     //   1618: aload #41
/*    */     //   1620: aload_0
/*    */     //   1621: invokevirtual canEqual : (Ljava/lang/Object;)Z
/*    */     //   1624: ifeq -> 1631
/*    */     //   1627: iconst_1
/*    */     //   1628: goto -> 1632
/*    */     //   1631: iconst_0
/*    */     //   1632: ifeq -> 1639
/*    */     //   1635: iconst_1
/*    */     //   1636: goto -> 1640
/*    */     //   1639: iconst_0
/*    */     //   1640: ireturn
/*    */     // Line number table:
/*    */     //   Java source line number -> byte code offset
/*    */     //   #36	-> 0
/*    */     //   #236	-> 12
/*    */     //   #36	-> 19
/*    */     // Local variable table:
/*    */     //   start	length	slot	name	descriptor
/*    */     //   0	1641	0	this	Lscala/Tuple19;
/*    */     //   0	1641	1	x$1	Ljava/lang/Object;
/*    */   }
/*    */   
/*    */   public Tuple19(Object _1, Object _2, Object _3, Object _4, Object _5, Object _6, Object _7, Object _8, Object _9, Object _10, Object _11, Object _12, Object _13, Object _14, Object _15, Object _16, Object _17, Object _18, Object _19) {
/* 36 */     Product$class.$init$(this);
/* 36 */     Product19$class.$init$(this);
/*    */   }
/*    */   
/*    */   public String toString() {
/* 40 */     return (new StringBuilder()).append("(").append(_1()).append(",").append(_2()).append(",").append(_3()).append(",").append(_4()).append(",").append(_5()).append(",").append(_6()).append(",").append(_7()).append(",").append(_8()).append(",").append(_9()).append(",").append(_10()).append(",").append(_11()).append(",").append(_12()).append(",").append(_13()).append(",").append(_14()).append(",").append(_15()).append(",").append(_16()).append(",").append(_17()).append(",").append(_18()).append(",").append(_19()).append(")").toString();
/*    */   }
/*    */ }


/* Location:              D:\#source-code\TheFlightSims\TFSLibrary\World2Xplane\World2XPlane.jar!\scala\Tuple19.class
 * Java compiler version: 6 (50.0)
 * JD-Core Version:       1.1.3
 */