/*    */ package scala;
/*    */ 
/*    */ import scala.collection.Iterator;
/*    */ import scala.collection.mutable.StringBuilder;
/*    */ import scala.reflect.ScalaSignature;
/*    */ import scala.runtime.BoxesRunTime;
/*    */ import scala.runtime.ScalaRunTime$;
/*    */ 
/*    */ @ScalaSignature(bytes = "\006\001\t\025a\001B\001\003\001\026\021a\001V;qY\026\024$\"A\002\002\013M\034\027\r\\1\004\001U\031a\001\005\032\024\013\00191BO\037\021\005!IQ\"\001\002\n\005)\021!AB!osJ+g\r\005\003\t\0319\t\024BA\007\003\005!\001&o\0343vGR\024\004CA\b\021\031\001!\021\"\005\001!\002\003%)\031\001\n\003\005Q\013\024CA\n\027!\tAA#\003\002\026\005\t9aj\034;iS:<\007C\001\005\030\023\tA\"AA\002B]fDs\001\005\016\036C\025JS\006\005\002\t7%\021AD\001\002\fgB,7-[1mSj,G-\r\003%=}\001cB\001\005 \023\t\001#!A\002J]R\fD\001\n\022$I9\021\001bI\005\003I\t\tA\001T8oOF\"AEJ\024)\035\tAq%\003\002)\005\0051Ai\\;cY\026\fD\001\n\026,Y9\021\001bK\005\003Y\t\tAa\0215beF\"AEL\0301\035\tAq&\003\0021\005\0059!i\\8mK\006t\007CA\b3\t%\031\004\001)A\001\n\013\007!C\001\002Ue!:!GG\0337oaJ\024\007\002\023\037?\001\nD\001\n\022$IE\"AEJ\024)c\021!#f\013\0272\t\021rs\006\r\t\003\021mJ!\001\020\002\003\017A\023x\016Z;diB\021\001BP\005\003\t\021AbU3sS\006d\027N_1cY\026D\001\"\021\001\003\026\004%\tAQ\001\003?F*\022A\004\005\t\t\002\021\t\022)A\005\035\005\031q,\r\021\t\021\031\003!Q3A\005\002\035\013!a\030\032\026\003EB\001\"\023\001\003\022\003\006I!M\001\004?J\002\003\"B&\001\t\003a\025A\002\037j]&$h\bF\002N\035>\003B\001\003\001\017c!)\021I\023a\001\035!)aI\023a\001c!)\021\013\001C!%\006AAo\\*ue&tw\rF\001T!\t!\026,D\001V\025\t1v+\001\003mC:<'\"\001-\002\t)\fg/Y\005\0035V\023aa\025;sS:<\007\"\002/\001\t\003i\026\001B:xCB,\022A\030\t\005\021\001\td\002C\004a\001\005\005I\021A1\002\t\r|\007/_\013\004E\026lGcA2ukB!\001\002\0013m!\tyQ\rB\005\022?\002\006\t\021!b\001%!:QMG4iS*\\\027\007\002\023\037?\001\nD\001\n\022$IE\"AEJ\024)c\021!#f\013\0272\t\021rs\006\r\t\003\0375$\021bM0!\002\003\005)\031\001\n)\0175Tr\016]9sgF\"AEH\020!c\021!#e\t\0232\t\0212s\005K\031\005I)ZC&\r\003%]=\002\004bB!`!\003\005\r\001\032\005\b\r~\003\n\0211\001m\021\0359\b!%A\005\002a\fabY8qs\022\"WMZ1vYR$\023'F\003z\003\023\t9\"F\001{U\tq1pK\001}!\ri\030QA\007\002}*\031q0!\001\002\023Ut7\r[3dW\026$'bAA\002\005\005Q\021M\0348pi\006$\030n\0348\n\007\005\035aPA\tv]\016DWmY6fIZ\013'/[1oG\026$\021\"\005<!\002\003\005)\031\001\n)\033\005%!$!\004\002\020\005E\0211CA\013c\021!cd\b\0212\t\021\0223\005J\031\005I\031:\003&\r\003%U-b\023\007\002\023/_A\"\021b\r<!\002\003\005)\031\001\n)\033\005]!$a\007\002\036\005}\021\021EA\022c\021!cd\b\0212\t\021\0223\005J\031\005I\031:\003&\r\003%U-b\023\007\002\023/_AB\021\"a\n\001#\003%\t!!\013\002\035\r|\007/\037\023eK\032\fW\017\034;%eU1\0211FA\030\003{)\"!!\f+\005EZHAC\t\002&\001\006\t\021!b\001%!j\021q\006\016\0024\005U\022qGA\035\003w\tD\001\n\020 AE\"AEI\022%c\021!ce\n\0252\t\021R3\006L\031\005I9z\003\007\002\0064\003K\001\013\021!AC\002IAS\"!\020\033\003\003\n\031%!\022\002H\005%\023\007\002\023\037?\001\nD\001\n\022$IE\"AEJ\024)c\021!#f\013\0272\t\021rs\006\r\005\n\003\033\002\021\021!C!\003\037\nQ\002\035:pIV\034G\017\025:fM&DX#A*\t\023\005M\003!!A\005B\005U\023a\0049s_\022,8\r^%uKJ\fGo\034:\026\005\005]\003#BA-\003?2RBAA.\025\r\tiFA\001\013G>dG.Z2uS>t\027\002BA1\0037\022\001\"\023;fe\006$xN\035\005\n\003K\002\021\021!C\001\003O\n\001bY1o\013F,\030\r\034\013\005\003S\ny\007E\002\t\003WJ1!!\034\003\005\035\021un\0347fC:D\021\"!\035\002d\005\005\t\031\001\f\002\007a$\023\007C\005\002v\001\t\t\021\"\021\002x\005A\001.Y:i\007>$W\r\006\002\002zA\031\001\"a\037\n\007\005u$AA\002J]RD\021\"!!\001\003\003%\t%a!\002\r\025\fX/\0317t)\021\tI'!\"\t\023\005E\024qPA\001\002\0041r!CAE\005\005\005\t\022AAF\003\031!V\017\0357feA\031\001\"!$\007\021\005\021\021\021!E\001\003\037\033B!!$\b{!91*!$\005\002\005MECAAF\021!\t\026QRA\001\n\013\022\006BCAM\003\033\013\t\021\"!\002\034\006)\021\r\0359msV1\021QTAR\003g#b!a(\002B\006\r\007C\002\005\001\003C\013\t\fE\002\020\003G#!\"EALA\003\005\tQ1\001\023Q5\t\031KGAT\003S\013Y+!,\0020F\"AEH\020!c\021!#e\t\0232\t\0212s\005K\031\005I)ZC&\r\003%]=\002\004cA\b\0024\022Q1'a&!\002\003\005)\031\001\n)\033\005M&$a.\002:\006m\026QXA`c\021!cd\b\0212\t\021\0223\005J\031\005I\031:\003&\r\003%U-b\023\007\002\023/_ABq!QAL\001\004\t\t\013C\004G\003/\003\r!!-\t\025\005\035\027QRA\001\n\003\013I-A\004v]\006\004\b\017\\=\026\r\005-\027q[At)\021\ti-!>\021\013!\ty-a5\n\007\005E'A\001\004PaRLwN\034\t\007\021\001\t).!:\021\007=\t9\016\002\006\022\003\013\004\013\021!AC\002IAS\"a6\033\0037\fi.a8\002b\006\r\030\007\002\023\037?\001\nD\001\n\022$IE\"AEJ\024)c\021!#f\013\0272\t\021rs\006\r\t\004\037\005\035HAC\032\002F\002\006\t\021!b\001%!j\021q\035\016\002l\0065\030q^Ay\003g\fD\001\n\020 AE\"AEI\022%c\021!ce\n\0252\t\021R3\006L\031\005I9z\003\007\003\006\002x\006\025\027\021!a\001\003'\f1\001\037\0231\021)\tY0!$\002\002\023%\021Q`\001\fe\026\fGMU3t_24X\r\006\002\002\000B\031AK!\001\n\007\t\rQK\001\004PE*,7\r\036")
/*    */ public class Tuple2<T1, T2> implements Product2<T1, T2>, Product, Serializable {
/*    */   public final T1 _1;
/*    */   
/*    */   public final T2 _2;
/*    */   
/*    */   public int productArity() {
/* 19 */     return Product2$class.productArity(this);
/*    */   }
/*    */   
/*    */   public Object productElement(int n) throws IndexOutOfBoundsException {
/* 19 */     return Product2$class.productElement(this, n);
/*    */   }
/*    */   
/*    */   public T1 _1() {
/* 19 */     return this._1;
/*    */   }
/*    */   
/*    */   public T2 _2() {
/* 19 */     return this._2;
/*    */   }
/*    */   
/*    */   public <T1, T2> Tuple2<T1, T2> copy(Object _1, Object _2) {
/* 19 */     return new Tuple2((T1)_1, (T2)_2);
/*    */   }
/*    */   
/*    */   public <T1, T2> T1 copy$default$1() {
/* 19 */     return _1();
/*    */   }
/*    */   
/*    */   public <T1, T2> T2 copy$default$2() {
/* 19 */     return _2();
/*    */   }
/*    */   
/*    */   public String productPrefix() {
/* 19 */     return "Tuple2";
/*    */   }
/*    */   
/*    */   public Iterator<Object> productIterator() {
/* 19 */     return ScalaRunTime$.MODULE$.typedProductIterator(this);
/*    */   }
/*    */   
/*    */   public boolean canEqual(Object x$1) {
/* 19 */     return x$1 instanceof Tuple2;
/*    */   }
/*    */   
/*    */   public int hashCode() {
/* 19 */     return ScalaRunTime$.MODULE$._hashCode(this);
/*    */   }
/*    */   
/*    */   public boolean equals(Object x$1) {
/*    */     // Byte code:
/*    */     //   0: aload_0
/*    */     //   1: aload_1
/*    */     //   2: if_acmpeq -> 207
/*    */     //   5: aload_1
/*    */     //   6: instanceof scala/Tuple2
/*    */     //   9: ifeq -> 17
/*    */     //   12: iconst_1
/*    */     //   13: istore_2
/*    */     //   14: goto -> 19
/*    */     //   17: iconst_0
/*    */     //   18: istore_2
/*    */     //   19: iload_2
/*    */     //   20: ifeq -> 211
/*    */     //   23: aload_1
/*    */     //   24: checkcast scala/Tuple2
/*    */     //   27: astore #7
/*    */     //   29: aload_0
/*    */     //   30: invokevirtual _1 : ()Ljava/lang/Object;
/*    */     //   33: aload #7
/*    */     //   35: invokevirtual _1 : ()Ljava/lang/Object;
/*    */     //   38: astore #4
/*    */     //   40: dup
/*    */     //   41: astore_3
/*    */     //   42: aload #4
/*    */     //   44: if_acmpne -> 51
/*    */     //   47: iconst_1
/*    */     //   48: goto -> 103
/*    */     //   51: aload_3
/*    */     //   52: ifnonnull -> 59
/*    */     //   55: iconst_0
/*    */     //   56: goto -> 103
/*    */     //   59: aload_3
/*    */     //   60: instanceof java/lang/Number
/*    */     //   63: ifeq -> 78
/*    */     //   66: aload_3
/*    */     //   67: checkcast java/lang/Number
/*    */     //   70: aload #4
/*    */     //   72: invokestatic equalsNumObject : (Ljava/lang/Number;Ljava/lang/Object;)Z
/*    */     //   75: goto -> 103
/*    */     //   78: aload_3
/*    */     //   79: instanceof java/lang/Character
/*    */     //   82: ifeq -> 97
/*    */     //   85: aload_3
/*    */     //   86: checkcast java/lang/Character
/*    */     //   89: aload #4
/*    */     //   91: invokestatic equalsCharObject : (Ljava/lang/Character;Ljava/lang/Object;)Z
/*    */     //   94: goto -> 103
/*    */     //   97: aload_3
/*    */     //   98: aload #4
/*    */     //   100: invokevirtual equals : (Ljava/lang/Object;)Z
/*    */     //   103: ifeq -> 203
/*    */     //   106: aload_0
/*    */     //   107: invokevirtual _2 : ()Ljava/lang/Object;
/*    */     //   110: aload #7
/*    */     //   112: invokevirtual _2 : ()Ljava/lang/Object;
/*    */     //   115: astore #6
/*    */     //   117: dup
/*    */     //   118: astore #5
/*    */     //   120: aload #6
/*    */     //   122: if_acmpne -> 129
/*    */     //   125: iconst_1
/*    */     //   126: goto -> 187
/*    */     //   129: aload #5
/*    */     //   131: ifnonnull -> 138
/*    */     //   134: iconst_0
/*    */     //   135: goto -> 187
/*    */     //   138: aload #5
/*    */     //   140: instanceof java/lang/Number
/*    */     //   143: ifeq -> 159
/*    */     //   146: aload #5
/*    */     //   148: checkcast java/lang/Number
/*    */     //   151: aload #6
/*    */     //   153: invokestatic equalsNumObject : (Ljava/lang/Number;Ljava/lang/Object;)Z
/*    */     //   156: goto -> 187
/*    */     //   159: aload #5
/*    */     //   161: instanceof java/lang/Character
/*    */     //   164: ifeq -> 180
/*    */     //   167: aload #5
/*    */     //   169: checkcast java/lang/Character
/*    */     //   172: aload #6
/*    */     //   174: invokestatic equalsCharObject : (Ljava/lang/Character;Ljava/lang/Object;)Z
/*    */     //   177: goto -> 187
/*    */     //   180: aload #5
/*    */     //   182: aload #6
/*    */     //   184: invokevirtual equals : (Ljava/lang/Object;)Z
/*    */     //   187: ifeq -> 203
/*    */     //   190: aload #7
/*    */     //   192: aload_0
/*    */     //   193: invokevirtual canEqual : (Ljava/lang/Object;)Z
/*    */     //   196: ifeq -> 203
/*    */     //   199: iconst_1
/*    */     //   200: goto -> 204
/*    */     //   203: iconst_0
/*    */     //   204: ifeq -> 211
/*    */     //   207: iconst_1
/*    */     //   208: goto -> 212
/*    */     //   211: iconst_0
/*    */     //   212: ireturn
/*    */     // Line number table:
/*    */     //   Java source line number -> byte code offset
/*    */     //   #19	-> 0
/*    */     //   #236	-> 12
/*    */     //   #19	-> 19
/*    */     // Local variable table:
/*    */     //   start	length	slot	name	descriptor
/*    */     //   0	213	0	this	Lscala/Tuple2;
/*    */     //   0	213	1	x$1	Ljava/lang/Object;
/*    */   }
/*    */   
/*    */   public boolean _1$mcZ$sp() {
/* 19 */     return BoxesRunTime.unboxToBoolean(_1());
/*    */   }
/*    */   
/*    */   public char _1$mcC$sp() {
/* 19 */     return BoxesRunTime.unboxToChar(_1());
/*    */   }
/*    */   
/*    */   public double _1$mcD$sp() {
/* 19 */     return BoxesRunTime.unboxToDouble(_1());
/*    */   }
/*    */   
/*    */   public int _1$mcI$sp() {
/* 19 */     return BoxesRunTime.unboxToInt(_1());
/*    */   }
/*    */   
/*    */   public long _1$mcJ$sp() {
/* 19 */     return BoxesRunTime.unboxToLong(_1());
/*    */   }
/*    */   
/*    */   public boolean _2$mcZ$sp() {
/* 19 */     return BoxesRunTime.unboxToBoolean(_2());
/*    */   }
/*    */   
/*    */   public char _2$mcC$sp() {
/* 19 */     return BoxesRunTime.unboxToChar(_2());
/*    */   }
/*    */   
/*    */   public double _2$mcD$sp() {
/* 19 */     return BoxesRunTime.unboxToDouble(_2());
/*    */   }
/*    */   
/*    */   public int _2$mcI$sp() {
/* 19 */     return BoxesRunTime.unboxToInt(_2());
/*    */   }
/*    */   
/*    */   public long _2$mcJ$sp() {
/* 19 */     return BoxesRunTime.unboxToLong(_2());
/*    */   }
/*    */   
/*    */   public Tuple2<Object, Object> copy$mZZc$sp(boolean _1, boolean _2) {
/* 19 */     return new Tuple2$mcZZ$sp(_1, _2);
/*    */   }
/*    */   
/*    */   public Tuple2<Object, Object> copy$mZCc$sp(boolean _1, char _2) {
/* 19 */     return new Tuple2$mcZC$sp(_1, _2);
/*    */   }
/*    */   
/*    */   public Tuple2<Object, Object> copy$mZDc$sp(boolean _1, double _2) {
/* 19 */     return new Tuple2$mcZD$sp(_1, _2);
/*    */   }
/*    */   
/*    */   public Tuple2<Object, Object> copy$mZIc$sp(boolean _1, int _2) {
/* 19 */     return new Tuple2$mcZI$sp(_1, _2);
/*    */   }
/*    */   
/*    */   public Tuple2<Object, Object> copy$mZJc$sp(boolean _1, long _2) {
/* 19 */     return new Tuple2$mcZJ$sp(_1, _2);
/*    */   }
/*    */   
/*    */   public Tuple2<Object, Object> copy$mCZc$sp(char _1, boolean _2) {
/* 19 */     return new Tuple2$mcCZ$sp(_1, _2);
/*    */   }
/*    */   
/*    */   public Tuple2<Object, Object> copy$mCCc$sp(char _1, char _2) {
/* 19 */     return new Tuple2$mcCC$sp(_1, _2);
/*    */   }
/*    */   
/*    */   public Tuple2<Object, Object> copy$mCDc$sp(char _1, double _2) {
/* 19 */     return new Tuple2$mcCD$sp(_1, _2);
/*    */   }
/*    */   
/*    */   public Tuple2<Object, Object> copy$mCIc$sp(char _1, int _2) {
/* 19 */     return new Tuple2$mcCI$sp(_1, _2);
/*    */   }
/*    */   
/*    */   public Tuple2<Object, Object> copy$mCJc$sp(char _1, long _2) {
/* 19 */     return new Tuple2$mcCJ$sp(_1, _2);
/*    */   }
/*    */   
/*    */   public Tuple2<Object, Object> copy$mDZc$sp(double _1, boolean _2) {
/* 19 */     return new Tuple2$mcDZ$sp(_1, _2);
/*    */   }
/*    */   
/*    */   public Tuple2<Object, Object> copy$mDCc$sp(double _1, char _2) {
/* 19 */     return new Tuple2$mcDC$sp(_1, _2);
/*    */   }
/*    */   
/*    */   public Tuple2<Object, Object> copy$mDDc$sp(double _1, double _2) {
/* 19 */     return new Tuple2$mcDD$sp(_1, _2);
/*    */   }
/*    */   
/*    */   public Tuple2<Object, Object> copy$mDIc$sp(double _1, int _2) {
/* 19 */     return new Tuple2$mcDI$sp(_1, _2);
/*    */   }
/*    */   
/*    */   public Tuple2<Object, Object> copy$mDJc$sp(double _1, long _2) {
/* 19 */     return new Tuple2$mcDJ$sp(_1, _2);
/*    */   }
/*    */   
/*    */   public Tuple2<Object, Object> copy$mIZc$sp(int _1, boolean _2) {
/* 19 */     return new Tuple2$mcIZ$sp(_1, _2);
/*    */   }
/*    */   
/*    */   public Tuple2<Object, Object> copy$mICc$sp(int _1, char _2) {
/* 19 */     return new Tuple2$mcIC$sp(_1, _2);
/*    */   }
/*    */   
/*    */   public Tuple2<Object, Object> copy$mIDc$sp(int _1, double _2) {
/* 19 */     return new Tuple2$mcID$sp(_1, _2);
/*    */   }
/*    */   
/*    */   public Tuple2<Object, Object> copy$mIIc$sp(int _1, int _2) {
/* 19 */     return new Tuple2$mcII$sp(_1, _2);
/*    */   }
/*    */   
/*    */   public Tuple2<Object, Object> copy$mIJc$sp(int _1, long _2) {
/* 19 */     return new Tuple2$mcIJ$sp(_1, _2);
/*    */   }
/*    */   
/*    */   public Tuple2<Object, Object> copy$mJZc$sp(long _1, boolean _2) {
/* 19 */     return new Tuple2$mcJZ$sp(_1, _2);
/*    */   }
/*    */   
/*    */   public Tuple2<Object, Object> copy$mJCc$sp(long _1, char _2) {
/* 19 */     return new Tuple2$mcJC$sp(_1, _2);
/*    */   }
/*    */   
/*    */   public Tuple2<Object, Object> copy$mJDc$sp(long _1, double _2) {
/* 19 */     return new Tuple2$mcJD$sp(_1, _2);
/*    */   }
/*    */   
/*    */   public Tuple2<Object, Object> copy$mJIc$sp(long _1, int _2) {
/* 19 */     return new Tuple2$mcJI$sp(_1, _2);
/*    */   }
/*    */   
/*    */   public Tuple2<Object, Object> copy$mJJc$sp(long _1, long _2) {
/* 19 */     return new Tuple2$mcJJ$sp(_1, _2);
/*    */   }
/*    */   
/*    */   public <T1, T2> boolean copy$default$1$mcZ$sp() {
/* 19 */     return BoxesRunTime.unboxToBoolean(copy$default$1());
/*    */   }
/*    */   
/*    */   public <T1, T2> char copy$default$1$mcC$sp() {
/* 19 */     return BoxesRunTime.unboxToChar(copy$default$1());
/*    */   }
/*    */   
/*    */   public <T1, T2> double copy$default$1$mcD$sp() {
/* 19 */     return BoxesRunTime.unboxToDouble(copy$default$1());
/*    */   }
/*    */   
/*    */   public <T1, T2> int copy$default$1$mcI$sp() {
/* 19 */     return BoxesRunTime.unboxToInt(copy$default$1());
/*    */   }
/*    */   
/*    */   public <T1, T2> long copy$default$1$mcJ$sp() {
/* 19 */     return BoxesRunTime.unboxToLong(copy$default$1());
/*    */   }
/*    */   
/*    */   public <T1, T2> boolean copy$default$2$mcZ$sp() {
/* 19 */     return BoxesRunTime.unboxToBoolean(copy$default$2());
/*    */   }
/*    */   
/*    */   public <T1, T2> char copy$default$2$mcC$sp() {
/* 19 */     return BoxesRunTime.unboxToChar(copy$default$2());
/*    */   }
/*    */   
/*    */   public <T1, T2> double copy$default$2$mcD$sp() {
/* 19 */     return BoxesRunTime.unboxToDouble(copy$default$2());
/*    */   }
/*    */   
/*    */   public <T1, T2> int copy$default$2$mcI$sp() {
/* 19 */     return BoxesRunTime.unboxToInt(copy$default$2());
/*    */   }
/*    */   
/*    */   public <T1, T2> long copy$default$2$mcJ$sp() {
/* 19 */     return BoxesRunTime.unboxToLong(copy$default$2());
/*    */   }
/*    */   
/*    */   public boolean specInstance$() {
/* 19 */     return false;
/*    */   }
/*    */   
/*    */   public Tuple2(Object _1, Object _2) {
/* 19 */     Product$class.$init$(this);
/* 19 */     Product2$class.$init$(this);
/*    */   }
/*    */   
/*    */   public String toString() {
/* 22 */     return (new StringBuilder()).append("(").append(_1()).append(",").append(_2()).append(")").toString();
/*    */   }
/*    */   
/*    */   public Tuple2<T2, T1> swap() {
/* 28 */     return new Tuple2((T1)_2(), (T2)_1());
/*    */   }
/*    */   
/*    */   public Tuple2<Object, Object> swap$mcZZ$sp() {
/* 28 */     return (Tuple2)swap();
/*    */   }
/*    */   
/*    */   public Tuple2<Object, Object> swap$mcZC$sp() {
/* 28 */     return (Tuple2)swap();
/*    */   }
/*    */   
/*    */   public Tuple2<Object, Object> swap$mcZD$sp() {
/* 28 */     return (Tuple2)swap();
/*    */   }
/*    */   
/*    */   public Tuple2<Object, Object> swap$mcZI$sp() {
/* 28 */     return (Tuple2)swap();
/*    */   }
/*    */   
/*    */   public Tuple2<Object, Object> swap$mcZJ$sp() {
/* 28 */     return (Tuple2)swap();
/*    */   }
/*    */   
/*    */   public Tuple2<Object, Object> swap$mcCZ$sp() {
/* 28 */     return (Tuple2)swap();
/*    */   }
/*    */   
/*    */   public Tuple2<Object, Object> swap$mcCC$sp() {
/* 28 */     return (Tuple2)swap();
/*    */   }
/*    */   
/*    */   public Tuple2<Object, Object> swap$mcCD$sp() {
/* 28 */     return (Tuple2)swap();
/*    */   }
/*    */   
/*    */   public Tuple2<Object, Object> swap$mcCI$sp() {
/* 28 */     return (Tuple2)swap();
/*    */   }
/*    */   
/*    */   public Tuple2<Object, Object> swap$mcCJ$sp() {
/* 28 */     return (Tuple2)swap();
/*    */   }
/*    */   
/*    */   public Tuple2<Object, Object> swap$mcDZ$sp() {
/* 28 */     return (Tuple2)swap();
/*    */   }
/*    */   
/*    */   public Tuple2<Object, Object> swap$mcDC$sp() {
/* 28 */     return (Tuple2)swap();
/*    */   }
/*    */   
/*    */   public Tuple2<Object, Object> swap$mcDD$sp() {
/* 28 */     return (Tuple2)swap();
/*    */   }
/*    */   
/*    */   public Tuple2<Object, Object> swap$mcDI$sp() {
/* 28 */     return (Tuple2)swap();
/*    */   }
/*    */   
/*    */   public Tuple2<Object, Object> swap$mcDJ$sp() {
/* 28 */     return (Tuple2)swap();
/*    */   }
/*    */   
/*    */   public Tuple2<Object, Object> swap$mcIZ$sp() {
/* 28 */     return (Tuple2)swap();
/*    */   }
/*    */   
/*    */   public Tuple2<Object, Object> swap$mcIC$sp() {
/* 28 */     return (Tuple2)swap();
/*    */   }
/*    */   
/*    */   public Tuple2<Object, Object> swap$mcID$sp() {
/* 28 */     return (Tuple2)swap();
/*    */   }
/*    */   
/*    */   public Tuple2<Object, Object> swap$mcII$sp() {
/* 28 */     return (Tuple2)swap();
/*    */   }
/*    */   
/*    */   public Tuple2<Object, Object> swap$mcIJ$sp() {
/* 28 */     return (Tuple2)swap();
/*    */   }
/*    */   
/*    */   public Tuple2<Object, Object> swap$mcJZ$sp() {
/* 28 */     return (Tuple2)swap();
/*    */   }
/*    */   
/*    */   public Tuple2<Object, Object> swap$mcJC$sp() {
/* 28 */     return (Tuple2)swap();
/*    */   }
/*    */   
/*    */   public Tuple2<Object, Object> swap$mcJD$sp() {
/* 28 */     return (Tuple2)swap();
/*    */   }
/*    */   
/*    */   public Tuple2<Object, Object> swap$mcJI$sp() {
/* 28 */     return (Tuple2)swap();
/*    */   }
/*    */   
/*    */   public Tuple2<Object, Object> swap$mcJJ$sp() {
/* 28 */     return (Tuple2)swap();
/*    */   }
/*    */ }


/* Location:              D:\#source-code\TheFlightSims\TFSLibrary\World2Xplane\World2XPlane.jar!\scala\Tuple2.class
 * Java compiler version: 6 (50.0)
 * JD-Core Version:       1.1.3
 */