/*    */ package scala;
/*    */ 
/*    */ import scala.collection.Iterator;
/*    */ import scala.collection.mutable.StringBuilder;
/*    */ import scala.reflect.ScalaSignature;
/*    */ import scala.runtime.ScalaRunTime$;
/*    */ 
/*    */ @ScalaSignature(bytes = "\006\001\021]d\001B\001\003\001\026\021q\001V;qY\026\f4GC\001\004\003\025\0318-\0317b\007\001)bB\002\t\033;\001\032c%\013\0270eUB4hE\003\001\017-i\004\t\005\002\t\0235\t!!\003\002\013\005\t1\021I\\=SK\032\004r\002\003\007\0173qy\"%\n\025,]E\"tGO\005\003\033\t\021\021\002\025:pIV\034G/M\032\021\005=\001B\002\001\003\007#\001!)\031\001\n\003\005Q\013\024CA\n\027!\tAA#\003\002\026\005\t9aj\034;iS:<\007C\001\005\030\023\tA\"AA\002B]f\004\"a\004\016\005\rm\001AQ1\001\023\005\t!&\007\005\002\020;\0211a\004\001CC\002I\021!\001V\032\021\005=\001CAB\021\001\t\013\007!C\001\002UiA\021qb\t\003\007I\001!)\031\001\n\003\005Q+\004CA\b'\t\0319\003\001\"b\001%\t\021AK\016\t\003\037%\"aA\013\001\005\006\004\021\"A\001+8!\tyA\006\002\004.\001\021\025\rA\005\002\003)b\002\"aD\030\005\rA\002AQ1\001\023\005\t!\026\b\005\002\020e\02111\007\001CC\002I\0211\001V\0311!\tyQ\007\002\0047\001\021\025\rA\005\002\004)F\n\004CA\b9\t\031I\004\001\"b\001%\t\031A+\r\032\021\005=YDA\002\037\001\t\013\007!CA\002UcM\002\"\001\003 \n\005}\022!a\002)s_\022,8\r\036\t\003\021\005K!A\021\002\003\031M+'/[1mSj\f'\r\\3\t\021\021\003!Q3A\005\002\025\013!aX\031\026\0039A\001b\022\001\003\022\003\006IAD\001\004?F\002\003\002C%\001\005+\007I\021\001&\002\005}\023T#A\r\t\0211\003!\021#Q\001\ne\t1a\030\032!\021!q\005A!f\001\n\003y\025AA04+\005a\002\002C)\001\005#\005\013\021\002\017\002\007}\033\004\005\003\005T\001\tU\r\021\"\001U\003\tyF'F\001 \021!1\006A!E!\002\023y\022aA05A!A\001\f\001BK\002\023\005\021,\001\002`kU\t!\005\003\005\\\001\tE\t\025!\003#\003\ryV\007\t\005\t;\002\021)\032!C\001=\006\021qLN\013\002K!A\001\r\001B\tB\003%Q%A\002`m\001B\001B\031\001\003\026\004%\taY\001\003?^*\022\001\013\005\tK\002\021\t\022)A\005Q\005\031ql\016\021\t\021\035\004!Q3A\005\002!\f!a\030\035\026\003-B\001B\033\001\003\022\003\006IaK\001\004?b\002\003\002\0037\001\005+\007I\021A7\002\005}KT#\001\030\t\021=\004!\021#Q\001\n9\n1aX\035!\021!\t\bA!f\001\n\003\021\030aA02aU\t\021\007\003\005u\001\tE\t\025!\0032\003\021y\026\007\r\021\t\021Y\004!Q3A\005\002]\f1aX\0312+\005!\004\002C=\001\005#\005\013\021\002\033\002\t}\013\024\007\t\005\tw\002\021)\032!C\001y\006\031q,\r\032\026\003]B\001B \001\003\022\003\006IaN\001\005?F\022\004\005\003\006\002\002\001\021)\032!C\001\003\007\t1aX\0314+\005Q\004\"CA\004\001\tE\t\025!\003;\003\021y\026g\r\021\t\017\005-\001\001\"\001\002\016\0051A(\0338jiz\"B$a\004\002\022\005M\021QCA\f\0033\tY\"!\b\002 \005\005\0221EA\023\003O\tI\003E\b\t\0019IBd\b\022&Q-r\023\007N\034;\021\031!\025\021\002a\001\035!1\021*!\003A\002eAaATA\005\001\004a\002BB*\002\n\001\007q\004\003\004Y\003\023\001\rA\t\005\007;\006%\001\031A\023\t\r\t\fI\0011\001)\021\0319\027\021\002a\001W!1A.!\003A\0029Ba!]A\005\001\004\t\004B\002<\002\n\001\007A\007\003\004|\003\023\001\ra\016\005\b\003\003\tI\0011\001;\021\035\ti\003\001C!\003_\t\001\002^8TiJLgn\032\013\003\003c\001B!a\r\002>5\021\021Q\007\006\005\003o\tI$\001\003mC:<'BAA\036\003\021Q\027M^1\n\t\005}\022Q\007\002\007'R\024\030N\\4\t\023\005\r\003!!A\005\002\005\025\023\001B2paf,B$a\022\002N\005E\023QKA-\003;\n\t'!\032\002j\0055\024\021OA;\003s\ni\b\006\017\002J\005}\024\021QAB\003\013\0139)!#\002\f\0065\025qRAI\003'\013)*a&\0219!\001\0211JA(\003'\n9&a\027\002`\005\r\024qMA6\003_\n\031(a\036\002|A\031q\"!\024\005\rE\t\tE1\001\023!\ry\021\021\013\003\0077\005\005#\031\001\n\021\007=\t)\006\002\004\037\003\003\022\rA\005\t\004\037\005eCAB\021\002B\t\007!\003E\002\020\003;\"a\001JA!\005\004\021\002cA\b\002b\0211q%!\021C\002I\0012aDA3\t\031Q\023\021\tb\001%A\031q\"!\033\005\r5\n\tE1\001\023!\ry\021Q\016\003\007a\005\005#\031\001\n\021\007=\t\t\b\002\0044\003\003\022\rA\005\t\004\037\005UDA\002\034\002B\t\007!\003E\002\020\003s\"a!OA!\005\004\021\002cA\b\002~\0211A(!\021C\002IA\021\002RA!!\003\005\r!a\023\t\023%\013\t\005%AA\002\005=\003\"\003(\002BA\005\t\031AA*\021%\031\026\021\tI\001\002\004\t9\006C\005Y\003\003\002\n\0211\001\002\\!IQ,!\021\021\002\003\007\021q\f\005\nE\006\005\003\023!a\001\003GB\021bZA!!\003\005\r!a\032\t\0231\f\t\005%AA\002\005-\004\"C9\002BA\005\t\031AA8\021%1\030\021\tI\001\002\004\t\031\bC\005|\003\003\002\n\0211\001\002x!Q\021\021AA!!\003\005\r!a\037\t\023\005m\005!%A\005\002\005u\025AD2paf$C-\0324bk2$H%M\013\035\003?\013),a.\002:\006m\026QXA`\003\003\f\031-!2\002H\006%\0271ZAg+\t\t\tKK\002\017\003G[#!!*\021\t\005\035\026\021W\007\003\003SSA!a+\002.\006IQO\\2iK\016\\W\r\032\006\004\003_\023\021AC1o]>$\030\r^5p]&!\0211WAU\005E)hn\0315fG.,GMV1sS\006t7-\032\003\007#\005e%\031\001\n\005\rm\tIJ1\001\023\t\031q\022\021\024b\001%\0211\021%!'C\002I!a\001JAM\005\004\021BAB\024\002\032\n\007!\003\002\004+\0033\023\rA\005\003\007[\005e%\031\001\n\005\rA\nIJ1\001\023\t\031\031\024\021\024b\001%\0211a'!'C\002I!a!OAM\005\004\021BA\002\037\002\032\n\007!\003C\005\002R\002\t\n\021\"\001\002T\006q1m\0349zI\021,g-Y;mi\022\022T\003HAk\0033\fY.!8\002`\006\005\0301]As\003O\fI/a;\002n\006=\030\021_\013\003\003/T3!GAR\t\031\t\022q\032b\001%\02111$a4C\002I!aAHAh\005\004\021BAB\021\002P\n\007!\003\002\004%\003\037\024\rA\005\003\007O\005='\031\001\n\005\r)\nyM1\001\023\t\031i\023q\032b\001%\0211\001'a4C\002I!aaMAh\005\004\021BA\002\034\002P\n\007!\003\002\004:\003\037\024\rA\005\003\007y\005='\031\001\n\t\023\005U\b!%A\005\002\005]\030AD2paf$C-\0324bk2$HeM\013\035\003s\fi0a@\003\002\t\r!Q\001B\004\005\023\021YA!\004\003\020\tE!1\003B\013+\t\tYPK\002\035\003G#a!EAz\005\004\021BAB\016\002t\n\007!\003\002\004\037\003g\024\rA\005\003\007C\005M(\031\001\n\005\r\021\n\031P1\001\023\t\0319\0231\037b\001%\0211!&a=C\002I!a!LAz\005\004\021BA\002\031\002t\n\007!\003\002\0044\003g\024\rA\005\003\007m\005M(\031\001\n\005\re\n\031P1\001\023\t\031a\0241\037b\001%!I!\021\004\001\022\002\023\005!1D\001\017G>\004\030\020\n3fM\006,H\016\036\0235+q\021iB!\t\003$\t\025\"q\005B\025\005W\021iCa\f\0032\tM\"Q\007B\034\005s)\"Aa\b+\007}\t\031\013\002\004\022\005/\021\rA\005\003\0077\t]!\031\001\n\005\ry\0219B1\001\023\t\031\t#q\003b\001%\0211AEa\006C\002I!aa\nB\f\005\004\021BA\002\026\003\030\t\007!\003\002\004.\005/\021\rA\005\003\007a\t]!\031\001\n\005\rM\0229B1\001\023\t\0311$q\003b\001%\0211\021Ha\006C\002I!a\001\020B\f\005\004\021\002\"\003B\037\001E\005I\021\001B \0039\031w\016]=%I\0264\027-\0367uIU*BD!\021\003F\t\035#\021\nB&\005\033\022yE!\025\003T\tU#q\013B-\0057\022i&\006\002\003D)\032!%a)\005\rE\021YD1\001\023\t\031Y\"1\bb\001%\0211aDa\017C\002I!a!\tB\036\005\004\021BA\002\023\003<\t\007!\003\002\004(\005w\021\rA\005\003\007U\tm\"\031\001\n\005\r5\022YD1\001\023\t\031\001$1\bb\001%\02111Ga\017C\002I!aA\016B\036\005\004\021BAB\035\003<\t\007!\003\002\004=\005w\021\rA\005\005\n\005C\002\021\023!C\001\005G\nabY8qs\022\"WMZ1vYR$c'\006\017\003f\t%$1\016B7\005_\022\tHa\035\003v\t]$\021\020B>\005{\022yH!!\026\005\t\035$fA\023\002$\0221\021Ca\030C\002I!aa\007B0\005\004\021BA\002\020\003`\t\007!\003\002\004\"\005?\022\rA\005\003\007I\t}#\031\001\n\005\r\035\022yF1\001\023\t\031Q#q\fb\001%\0211QFa\030C\002I!a\001\rB0\005\004\021BAB\032\003`\t\007!\003\002\0047\005?\022\rA\005\003\007s\t}#\031\001\n\005\rq\022yF1\001\023\021%\021)\tAI\001\n\003\0219)\001\bd_BLH\005Z3gCVdG\017J\034\0269\t%%Q\022BH\005#\023\031J!&\003\030\ne%1\024BO\005?\023\tKa)\003&V\021!1\022\026\004Q\005\rFAB\t\003\004\n\007!\003\002\004\034\005\007\023\rA\005\003\007=\t\r%\031\001\n\005\r\005\022\031I1\001\023\t\031!#1\021b\001%\0211qEa!C\002I!aA\013BB\005\004\021BAB\027\003\004\n\007!\003\002\0041\005\007\023\rA\005\003\007g\t\r%\031\001\n\005\rY\022\031I1\001\023\t\031I$1\021b\001%\0211AHa!C\002IA\021B!+\001#\003%\tAa+\002\035\r|\007/\037\023eK\032\fW\017\034;%qUa\"Q\026BY\005g\023)La.\003:\nm&Q\030B`\005\003\024\031M!2\003H\n%WC\001BXU\rY\0231\025\003\007#\t\035&\031\001\n\005\rm\0219K1\001\023\t\031q\"q\025b\001%\0211\021Ea*C\002I!a\001\nBT\005\004\021BAB\024\003(\n\007!\003\002\004+\005O\023\rA\005\003\007[\t\035&\031\001\n\005\rA\0229K1\001\023\t\031\031$q\025b\001%\0211aGa*C\002I!a!\017BT\005\004\021BA\002\037\003(\n\007!\003C\005\003N\002\t\n\021\"\001\003P\006q1m\0349zI\021,g-Y;mi\022JT\003\bBi\005+\0249N!7\003\\\nu'q\034Bq\005G\024)Oa:\003j\n-(Q^\013\003\005'T3ALAR\t\031\t\"1\032b\001%\02111Da3C\002I!aA\bBf\005\004\021BAB\021\003L\n\007!\003\002\004%\005\027\024\rA\005\003\007O\t-'\031\001\n\005\r)\022YM1\001\023\t\031i#1\032b\001%\0211\001Ga3C\002I!aa\rBf\005\004\021BA\002\034\003L\n\007!\003\002\004:\005\027\024\rA\005\003\007y\t-'\031\001\n\t\023\tE\b!%A\005\002\tM\030aD2paf$C-\0324bk2$H%\r\031\0269\tU(\021 B~\005{\024yp!\001\004\004\r\0251qAB\005\007\027\031iaa\004\004\022U\021!q\037\026\004c\005\rFAB\t\003p\n\007!\003\002\004\034\005_\024\rA\005\003\007=\t=(\031\001\n\005\r\005\022yO1\001\023\t\031!#q\036b\001%\0211qEa<C\002I!aA\013Bx\005\004\021BAB\027\003p\n\007!\003\002\0041\005_\024\rA\005\003\007g\t=(\031\001\n\005\rY\022yO1\001\023\t\031I$q\036b\001%\0211AHa<C\002IA\021b!\006\001#\003%\taa\006\002\037\r|\007/\037\023eK\032\fW\017\034;%cE*Bd!\007\004\036\r}1\021EB\022\007K\0319c!\013\004,\r52qFB\031\007g\031)$\006\002\004\034)\032A'a)\005\rE\031\031B1\001\023\t\031Y21\003b\001%\0211ada\005C\002I!a!IB\n\005\004\021BA\002\023\004\024\t\007!\003\002\004(\007'\021\rA\005\003\007U\rM!\031\001\n\005\r5\032\031B1\001\023\t\031\00141\003b\001%\02111ga\005C\002I!aANB\n\005\004\021BAB\035\004\024\t\007!\003\002\004=\007'\021\rA\005\005\n\007s\001\021\023!C\001\007w\tqbY8qs\022\"WMZ1vYR$\023GM\013\035\007{\031\tea\021\004F\r\0353\021JB&\007\033\032ye!\025\004T\rU3qKB-+\t\031yDK\0028\003G#a!EB\034\005\004\021BAB\016\0048\t\007!\003\002\004\037\007o\021\rA\005\003\007C\r]\"\031\001\n\005\r\021\0329D1\001\023\t\03193q\007b\001%\0211!fa\016C\002I!a!LB\034\005\004\021BA\002\031\0048\t\007!\003\002\0044\007o\021\rA\005\003\007m\r]\"\031\001\n\005\re\0329D1\001\023\t\031a4q\007b\001%!I1Q\f\001\022\002\023\0051qL\001\020G>\004\030\020\n3fM\006,H\016\036\0232gUa2\021MB3\007O\032Iga\033\004n\r=4\021OB:\007k\0329h!\037\004|\ruTCAB2U\rQ\0241\025\003\007#\rm#\031\001\n\005\rm\031YF1\001\023\t\031q21\fb\001%\0211\021ea\027C\002I!a\001JB.\005\004\021BAB\024\004\\\t\007!\003\002\004+\0077\022\rA\005\003\007[\rm#\031\001\n\005\rA\032YF1\001\023\t\031\03141\fb\001%\0211aga\027C\002I!a!OB.\005\004\021BA\002\037\004\\\t\007!\003C\005\004\002\002\t\t\021\"\021\004\004\006i\001O]8ek\016$\bK]3gSb,\"!!\r\t\023\r\035\005!!A\005B\r%\025a\0049s_\022,8\r^%uKJ\fGo\034:\026\005\r-\005#BBG\007'3RBABH\025\r\031\tJA\001\013G>dG.Z2uS>t\027\002BBK\007\037\023\001\"\023;fe\006$xN\035\005\n\0073\003\021\021!C\001\0077\013\001bY1o\013F,\030\r\034\013\005\007;\033\031\013E\002\t\007?K1a!)\003\005\035\021un\0347fC:D\021b!*\004\030\006\005\t\031\001\f\002\007a$\023\007C\005\004*\002\t\t\021\"\021\004,\006A\001.Y:i\007>$W\r\006\002\004.B\031\001ba,\n\007\rE&AA\002J]RD\021b!.\001\003\003%\tea.\002\r\025\fX/\0317t)\021\031ij!/\t\023\r\02561WA\001\002\0041r!CB_\005\005\005\t\022AB`\003\035!V\017\0357fcM\0022\001CBa\r!\t!!!A\t\002\r\r7\003BBa\017\001C\001\"a\003\004B\022\0051q\031\013\003\007C!\"!\f\004B\006\005IQIA\030\021)\031im!1\002\002\023\0055qZ\001\006CB\004H._\013\035\007#\0349na7\004`\016\r8q]Bv\007_\034\031pa>\004|\016}H1\001C\004)q\031\031\016\"\003\005\f\0215Aq\002C\t\t'!)\002b\006\005\032\021mAQ\004C\020\tC\001B\004\003\001\004V\016e7Q\\Bq\007K\034Io!<\004r\016U8\021`B\t\003!)\001E\002\020\007/$a!EBf\005\004\021\002cA\b\004\\\02211da3C\002I\0012aDBp\t\031q21\032b\001%A\031qba9\005\r\005\032YM1\001\023!\ry1q\035\003\007I\r-'\031\001\n\021\007=\031Y\017\002\004(\007\027\024\rA\005\t\004\037\r=HA\002\026\004L\n\007!\003E\002\020\007g$a!LBf\005\004\021\002cA\b\004x\0221\001ga3C\002I\0012aDB~\t\031\03141\032b\001%A\031qba@\005\rY\032YM1\001\023!\ryA1\001\003\007s\r-'\031\001\n\021\007=!9\001\002\004=\007\027\024\rA\005\005\b\t\016-\007\031ABk\021\035I51\032a\001\0073DqATBf\001\004\031i\016C\004T\007\027\004\ra!9\t\017a\033Y\r1\001\004f\"9Qla3A\002\r%\bb\0022\004L\002\0071Q\036\005\bO\016-\007\031ABy\021\035a71\032a\001\007kDq!]Bf\001\004\031I\020C\004w\007\027\004\ra!@\t\017m\034Y\r1\001\005\002!A\021\021ABf\001\004!)\001\003\006\005&\r\005\027\021!CA\tO\tq!\0368baBd\0270\006\017\005*\021UB\021\bC\037\t\003\")\005\"\023\005N\021ECQ\013C-\t;\"\t\007\"\032\025\t\021-Bq\r\t\006\021\0215B\021G\005\004\t_\021!AB(qi&|g\016\005\017\t\001\021MBq\007C\036\t!\031\005b\022\005L\021=C1\013C,\t7\"y\006b\031\021\007=!)\004\002\004\022\tG\021\rA\005\t\004\037\021eBAB\016\005$\t\007!\003E\002\020\t{!aA\bC\022\005\004\021\002cA\b\005B\0211\021\005b\tC\002I\0012a\004C#\t\031!C1\005b\001%A\031q\002\"\023\005\r\035\"\031C1\001\023!\ryAQ\n\003\007U\021\r\"\031\001\n\021\007=!\t\006\002\004.\tG\021\rA\005\t\004\037\021UCA\002\031\005$\t\007!\003E\002\020\t3\"aa\rC\022\005\004\021\002cA\b\005^\0211a\007b\tC\002I\0012a\004C1\t\031ID1\005b\001%A\031q\002\"\032\005\rq\"\031C1\001\023\021)!I\007b\t\002\002\003\007A\021G\001\004q\022\002\004B\003C7\007\003\f\t\021\"\003\005p\005Y!/Z1e%\026\034x\016\034<f)\t!\t\b\005\003\0024\021M\024\002\002C;\003k\021aa\0242kK\016$\b")
/*    */ public class Tuple13<T1, T2, T3, T4, T5, T6, T7, T8, T9, T10, T11, T12, T13> implements Product13<T1, T2, T3, T4, T5, T6, T7, T8, T9, T10, T11, T12, T13>, Product, Serializable {
/*    */   private final T1 _1;
/*    */   
/*    */   private final T2 _2;
/*    */   
/*    */   private final T3 _3;
/*    */   
/*    */   private final T4 _4;
/*    */   
/*    */   private final T5 _5;
/*    */   
/*    */   private final T6 _6;
/*    */   
/*    */   private final T7 _7;
/*    */   
/*    */   private final T8 _8;
/*    */   
/*    */   private final T9 _9;
/*    */   
/*    */   private final T10 _10;
/*    */   
/*    */   private final T11 _11;
/*    */   
/*    */   private final T12 _12;
/*    */   
/*    */   private final T13 _13;
/*    */   
/*    */   public int productArity() {
/* 30 */     return Product13$class.productArity(this);
/*    */   }
/*    */   
/*    */   public Object productElement(int n) throws IndexOutOfBoundsException {
/* 30 */     return Product13$class.productElement(this, n);
/*    */   }
/*    */   
/*    */   public T1 _1() {
/* 30 */     return this._1;
/*    */   }
/*    */   
/*    */   public T2 _2() {
/* 30 */     return this._2;
/*    */   }
/*    */   
/*    */   public T3 _3() {
/* 30 */     return this._3;
/*    */   }
/*    */   
/*    */   public T4 _4() {
/* 30 */     return this._4;
/*    */   }
/*    */   
/*    */   public T5 _5() {
/* 30 */     return this._5;
/*    */   }
/*    */   
/*    */   public T6 _6() {
/* 30 */     return this._6;
/*    */   }
/*    */   
/*    */   public T7 _7() {
/* 30 */     return this._7;
/*    */   }
/*    */   
/*    */   public T8 _8() {
/* 30 */     return this._8;
/*    */   }
/*    */   
/*    */   public T9 _9() {
/* 30 */     return this._9;
/*    */   }
/*    */   
/*    */   public T10 _10() {
/* 30 */     return this._10;
/*    */   }
/*    */   
/*    */   public T11 _11() {
/* 30 */     return this._11;
/*    */   }
/*    */   
/*    */   public T12 _12() {
/* 30 */     return this._12;
/*    */   }
/*    */   
/*    */   public T13 _13() {
/* 30 */     return this._13;
/*    */   }
/*    */   
/*    */   public <T1, T2, T3, T4, T5, T6, T7, T8, T9, T10, T11, T12, T13> Tuple13<T1, T2, T3, T4, T5, T6, T7, T8, T9, T10, T11, T12, T13> copy(Object _1, Object _2, Object _3, Object _4, Object _5, Object _6, Object _7, Object _8, Object _9, Object _10, Object _11, Object _12, Object _13) {
/* 30 */     return new Tuple13((T1)_1, (T2)_2, (T3)_3, (T4)_4, (T5)_5, (T6)_6, (T7)_7, (T8)_8, (T9)_9, (T10)_10, (T11)_11, (T12)_12, (T13)_13);
/*    */   }
/*    */   
/*    */   public <T1, T2, T3, T4, T5, T6, T7, T8, T9, T10, T11, T12, T13> T1 copy$default$1() {
/* 30 */     return _1();
/*    */   }
/*    */   
/*    */   public <T1, T2, T3, T4, T5, T6, T7, T8, T9, T10, T11, T12, T13> T2 copy$default$2() {
/* 30 */     return _2();
/*    */   }
/*    */   
/*    */   public <T1, T2, T3, T4, T5, T6, T7, T8, T9, T10, T11, T12, T13> T3 copy$default$3() {
/* 30 */     return _3();
/*    */   }
/*    */   
/*    */   public <T1, T2, T3, T4, T5, T6, T7, T8, T9, T10, T11, T12, T13> T4 copy$default$4() {
/* 30 */     return _4();
/*    */   }
/*    */   
/*    */   public <T1, T2, T3, T4, T5, T6, T7, T8, T9, T10, T11, T12, T13> T5 copy$default$5() {
/* 30 */     return _5();
/*    */   }
/*    */   
/*    */   public <T1, T2, T3, T4, T5, T6, T7, T8, T9, T10, T11, T12, T13> T6 copy$default$6() {
/* 30 */     return _6();
/*    */   }
/*    */   
/*    */   public <T1, T2, T3, T4, T5, T6, T7, T8, T9, T10, T11, T12, T13> T7 copy$default$7() {
/* 30 */     return _7();
/*    */   }
/*    */   
/*    */   public <T1, T2, T3, T4, T5, T6, T7, T8, T9, T10, T11, T12, T13> T8 copy$default$8() {
/* 30 */     return _8();
/*    */   }
/*    */   
/*    */   public <T1, T2, T3, T4, T5, T6, T7, T8, T9, T10, T11, T12, T13> T9 copy$default$9() {
/* 30 */     return _9();
/*    */   }
/*    */   
/*    */   public <T1, T2, T3, T4, T5, T6, T7, T8, T9, T10, T11, T12, T13> T10 copy$default$10() {
/* 30 */     return _10();
/*    */   }
/*    */   
/*    */   public <T1, T2, T3, T4, T5, T6, T7, T8, T9, T10, T11, T12, T13> T11 copy$default$11() {
/* 30 */     return _11();
/*    */   }
/*    */   
/*    */   public <T1, T2, T3, T4, T5, T6, T7, T8, T9, T10, T11, T12, T13> T12 copy$default$12() {
/* 30 */     return _12();
/*    */   }
/*    */   
/*    */   public <T1, T2, T3, T4, T5, T6, T7, T8, T9, T10, T11, T12, T13> T13 copy$default$13() {
/* 30 */     return _13();
/*    */   }
/*    */   
/*    */   public String productPrefix() {
/* 30 */     return "Tuple13";
/*    */   }
/*    */   
/*    */   public Iterator<Object> productIterator() {
/* 30 */     return ScalaRunTime$.MODULE$.typedProductIterator(this);
/*    */   }
/*    */   
/*    */   public boolean canEqual(Object x$1) {
/* 30 */     return x$1 instanceof Tuple13;
/*    */   }
/*    */   
/*    */   public int hashCode() {
/* 30 */     return ScalaRunTime$.MODULE$._hashCode(this);
/*    */   }
/*    */   
/*    */   public boolean equals(Object x$1) {
/*    */     // Byte code:
/*    */     //   0: aload_0
/*    */     //   1: aload_1
/*    */     //   2: if_acmpeq -> 1131
/*    */     //   5: aload_1
/*    */     //   6: instanceof scala/Tuple13
/*    */     //   9: ifeq -> 17
/*    */     //   12: iconst_1
/*    */     //   13: istore_2
/*    */     //   14: goto -> 19
/*    */     //   17: iconst_0
/*    */     //   18: istore_2
/*    */     //   19: iload_2
/*    */     //   20: ifeq -> 1135
/*    */     //   23: aload_1
/*    */     //   24: checkcast scala/Tuple13
/*    */     //   27: astore #29
/*    */     //   29: aload_0
/*    */     //   30: invokevirtual _1 : ()Ljava/lang/Object;
/*    */     //   33: aload #29
/*    */     //   35: invokevirtual _1 : ()Ljava/lang/Object;
/*    */     //   38: astore #4
/*    */     //   40: dup
/*    */     //   41: astore_3
/*    */     //   42: aload #4
/*    */     //   44: if_acmpne -> 51
/*    */     //   47: iconst_1
/*    */     //   48: goto -> 103
/*    */     //   51: aload_3
/*    */     //   52: ifnonnull -> 59
/*    */     //   55: iconst_0
/*    */     //   56: goto -> 103
/*    */     //   59: aload_3
/*    */     //   60: instanceof java/lang/Number
/*    */     //   63: ifeq -> 78
/*    */     //   66: aload_3
/*    */     //   67: checkcast java/lang/Number
/*    */     //   70: aload #4
/*    */     //   72: invokestatic equalsNumObject : (Ljava/lang/Number;Ljava/lang/Object;)Z
/*    */     //   75: goto -> 103
/*    */     //   78: aload_3
/*    */     //   79: instanceof java/lang/Character
/*    */     //   82: ifeq -> 97
/*    */     //   85: aload_3
/*    */     //   86: checkcast java/lang/Character
/*    */     //   89: aload #4
/*    */     //   91: invokestatic equalsCharObject : (Ljava/lang/Character;Ljava/lang/Object;)Z
/*    */     //   94: goto -> 103
/*    */     //   97: aload_3
/*    */     //   98: aload #4
/*    */     //   100: invokevirtual equals : (Ljava/lang/Object;)Z
/*    */     //   103: ifeq -> 1127
/*    */     //   106: aload_0
/*    */     //   107: invokevirtual _2 : ()Ljava/lang/Object;
/*    */     //   110: aload #29
/*    */     //   112: invokevirtual _2 : ()Ljava/lang/Object;
/*    */     //   115: astore #6
/*    */     //   117: dup
/*    */     //   118: astore #5
/*    */     //   120: aload #6
/*    */     //   122: if_acmpne -> 129
/*    */     //   125: iconst_1
/*    */     //   126: goto -> 187
/*    */     //   129: aload #5
/*    */     //   131: ifnonnull -> 138
/*    */     //   134: iconst_0
/*    */     //   135: goto -> 187
/*    */     //   138: aload #5
/*    */     //   140: instanceof java/lang/Number
/*    */     //   143: ifeq -> 159
/*    */     //   146: aload #5
/*    */     //   148: checkcast java/lang/Number
/*    */     //   151: aload #6
/*    */     //   153: invokestatic equalsNumObject : (Ljava/lang/Number;Ljava/lang/Object;)Z
/*    */     //   156: goto -> 187
/*    */     //   159: aload #5
/*    */     //   161: instanceof java/lang/Character
/*    */     //   164: ifeq -> 180
/*    */     //   167: aload #5
/*    */     //   169: checkcast java/lang/Character
/*    */     //   172: aload #6
/*    */     //   174: invokestatic equalsCharObject : (Ljava/lang/Character;Ljava/lang/Object;)Z
/*    */     //   177: goto -> 187
/*    */     //   180: aload #5
/*    */     //   182: aload #6
/*    */     //   184: invokevirtual equals : (Ljava/lang/Object;)Z
/*    */     //   187: ifeq -> 1127
/*    */     //   190: aload_0
/*    */     //   191: invokevirtual _3 : ()Ljava/lang/Object;
/*    */     //   194: aload #29
/*    */     //   196: invokevirtual _3 : ()Ljava/lang/Object;
/*    */     //   199: astore #8
/*    */     //   201: dup
/*    */     //   202: astore #7
/*    */     //   204: aload #8
/*    */     //   206: if_acmpne -> 213
/*    */     //   209: iconst_1
/*    */     //   210: goto -> 271
/*    */     //   213: aload #7
/*    */     //   215: ifnonnull -> 222
/*    */     //   218: iconst_0
/*    */     //   219: goto -> 271
/*    */     //   222: aload #7
/*    */     //   224: instanceof java/lang/Number
/*    */     //   227: ifeq -> 243
/*    */     //   230: aload #7
/*    */     //   232: checkcast java/lang/Number
/*    */     //   235: aload #8
/*    */     //   237: invokestatic equalsNumObject : (Ljava/lang/Number;Ljava/lang/Object;)Z
/*    */     //   240: goto -> 271
/*    */     //   243: aload #7
/*    */     //   245: instanceof java/lang/Character
/*    */     //   248: ifeq -> 264
/*    */     //   251: aload #7
/*    */     //   253: checkcast java/lang/Character
/*    */     //   256: aload #8
/*    */     //   258: invokestatic equalsCharObject : (Ljava/lang/Character;Ljava/lang/Object;)Z
/*    */     //   261: goto -> 271
/*    */     //   264: aload #7
/*    */     //   266: aload #8
/*    */     //   268: invokevirtual equals : (Ljava/lang/Object;)Z
/*    */     //   271: ifeq -> 1127
/*    */     //   274: aload_0
/*    */     //   275: invokevirtual _4 : ()Ljava/lang/Object;
/*    */     //   278: aload #29
/*    */     //   280: invokevirtual _4 : ()Ljava/lang/Object;
/*    */     //   283: astore #10
/*    */     //   285: dup
/*    */     //   286: astore #9
/*    */     //   288: aload #10
/*    */     //   290: if_acmpne -> 297
/*    */     //   293: iconst_1
/*    */     //   294: goto -> 355
/*    */     //   297: aload #9
/*    */     //   299: ifnonnull -> 306
/*    */     //   302: iconst_0
/*    */     //   303: goto -> 355
/*    */     //   306: aload #9
/*    */     //   308: instanceof java/lang/Number
/*    */     //   311: ifeq -> 327
/*    */     //   314: aload #9
/*    */     //   316: checkcast java/lang/Number
/*    */     //   319: aload #10
/*    */     //   321: invokestatic equalsNumObject : (Ljava/lang/Number;Ljava/lang/Object;)Z
/*    */     //   324: goto -> 355
/*    */     //   327: aload #9
/*    */     //   329: instanceof java/lang/Character
/*    */     //   332: ifeq -> 348
/*    */     //   335: aload #9
/*    */     //   337: checkcast java/lang/Character
/*    */     //   340: aload #10
/*    */     //   342: invokestatic equalsCharObject : (Ljava/lang/Character;Ljava/lang/Object;)Z
/*    */     //   345: goto -> 355
/*    */     //   348: aload #9
/*    */     //   350: aload #10
/*    */     //   352: invokevirtual equals : (Ljava/lang/Object;)Z
/*    */     //   355: ifeq -> 1127
/*    */     //   358: aload_0
/*    */     //   359: invokevirtual _5 : ()Ljava/lang/Object;
/*    */     //   362: aload #29
/*    */     //   364: invokevirtual _5 : ()Ljava/lang/Object;
/*    */     //   367: astore #12
/*    */     //   369: dup
/*    */     //   370: astore #11
/*    */     //   372: aload #12
/*    */     //   374: if_acmpne -> 381
/*    */     //   377: iconst_1
/*    */     //   378: goto -> 439
/*    */     //   381: aload #11
/*    */     //   383: ifnonnull -> 390
/*    */     //   386: iconst_0
/*    */     //   387: goto -> 439
/*    */     //   390: aload #11
/*    */     //   392: instanceof java/lang/Number
/*    */     //   395: ifeq -> 411
/*    */     //   398: aload #11
/*    */     //   400: checkcast java/lang/Number
/*    */     //   403: aload #12
/*    */     //   405: invokestatic equalsNumObject : (Ljava/lang/Number;Ljava/lang/Object;)Z
/*    */     //   408: goto -> 439
/*    */     //   411: aload #11
/*    */     //   413: instanceof java/lang/Character
/*    */     //   416: ifeq -> 432
/*    */     //   419: aload #11
/*    */     //   421: checkcast java/lang/Character
/*    */     //   424: aload #12
/*    */     //   426: invokestatic equalsCharObject : (Ljava/lang/Character;Ljava/lang/Object;)Z
/*    */     //   429: goto -> 439
/*    */     //   432: aload #11
/*    */     //   434: aload #12
/*    */     //   436: invokevirtual equals : (Ljava/lang/Object;)Z
/*    */     //   439: ifeq -> 1127
/*    */     //   442: aload_0
/*    */     //   443: invokevirtual _6 : ()Ljava/lang/Object;
/*    */     //   446: aload #29
/*    */     //   448: invokevirtual _6 : ()Ljava/lang/Object;
/*    */     //   451: astore #14
/*    */     //   453: dup
/*    */     //   454: astore #13
/*    */     //   456: aload #14
/*    */     //   458: if_acmpne -> 465
/*    */     //   461: iconst_1
/*    */     //   462: goto -> 523
/*    */     //   465: aload #13
/*    */     //   467: ifnonnull -> 474
/*    */     //   470: iconst_0
/*    */     //   471: goto -> 523
/*    */     //   474: aload #13
/*    */     //   476: instanceof java/lang/Number
/*    */     //   479: ifeq -> 495
/*    */     //   482: aload #13
/*    */     //   484: checkcast java/lang/Number
/*    */     //   487: aload #14
/*    */     //   489: invokestatic equalsNumObject : (Ljava/lang/Number;Ljava/lang/Object;)Z
/*    */     //   492: goto -> 523
/*    */     //   495: aload #13
/*    */     //   497: instanceof java/lang/Character
/*    */     //   500: ifeq -> 516
/*    */     //   503: aload #13
/*    */     //   505: checkcast java/lang/Character
/*    */     //   508: aload #14
/*    */     //   510: invokestatic equalsCharObject : (Ljava/lang/Character;Ljava/lang/Object;)Z
/*    */     //   513: goto -> 523
/*    */     //   516: aload #13
/*    */     //   518: aload #14
/*    */     //   520: invokevirtual equals : (Ljava/lang/Object;)Z
/*    */     //   523: ifeq -> 1127
/*    */     //   526: aload_0
/*    */     //   527: invokevirtual _7 : ()Ljava/lang/Object;
/*    */     //   530: aload #29
/*    */     //   532: invokevirtual _7 : ()Ljava/lang/Object;
/*    */     //   535: astore #16
/*    */     //   537: dup
/*    */     //   538: astore #15
/*    */     //   540: aload #16
/*    */     //   542: if_acmpne -> 549
/*    */     //   545: iconst_1
/*    */     //   546: goto -> 607
/*    */     //   549: aload #15
/*    */     //   551: ifnonnull -> 558
/*    */     //   554: iconst_0
/*    */     //   555: goto -> 607
/*    */     //   558: aload #15
/*    */     //   560: instanceof java/lang/Number
/*    */     //   563: ifeq -> 579
/*    */     //   566: aload #15
/*    */     //   568: checkcast java/lang/Number
/*    */     //   571: aload #16
/*    */     //   573: invokestatic equalsNumObject : (Ljava/lang/Number;Ljava/lang/Object;)Z
/*    */     //   576: goto -> 607
/*    */     //   579: aload #15
/*    */     //   581: instanceof java/lang/Character
/*    */     //   584: ifeq -> 600
/*    */     //   587: aload #15
/*    */     //   589: checkcast java/lang/Character
/*    */     //   592: aload #16
/*    */     //   594: invokestatic equalsCharObject : (Ljava/lang/Character;Ljava/lang/Object;)Z
/*    */     //   597: goto -> 607
/*    */     //   600: aload #15
/*    */     //   602: aload #16
/*    */     //   604: invokevirtual equals : (Ljava/lang/Object;)Z
/*    */     //   607: ifeq -> 1127
/*    */     //   610: aload_0
/*    */     //   611: invokevirtual _8 : ()Ljava/lang/Object;
/*    */     //   614: aload #29
/*    */     //   616: invokevirtual _8 : ()Ljava/lang/Object;
/*    */     //   619: astore #18
/*    */     //   621: dup
/*    */     //   622: astore #17
/*    */     //   624: aload #18
/*    */     //   626: if_acmpne -> 633
/*    */     //   629: iconst_1
/*    */     //   630: goto -> 691
/*    */     //   633: aload #17
/*    */     //   635: ifnonnull -> 642
/*    */     //   638: iconst_0
/*    */     //   639: goto -> 691
/*    */     //   642: aload #17
/*    */     //   644: instanceof java/lang/Number
/*    */     //   647: ifeq -> 663
/*    */     //   650: aload #17
/*    */     //   652: checkcast java/lang/Number
/*    */     //   655: aload #18
/*    */     //   657: invokestatic equalsNumObject : (Ljava/lang/Number;Ljava/lang/Object;)Z
/*    */     //   660: goto -> 691
/*    */     //   663: aload #17
/*    */     //   665: instanceof java/lang/Character
/*    */     //   668: ifeq -> 684
/*    */     //   671: aload #17
/*    */     //   673: checkcast java/lang/Character
/*    */     //   676: aload #18
/*    */     //   678: invokestatic equalsCharObject : (Ljava/lang/Character;Ljava/lang/Object;)Z
/*    */     //   681: goto -> 691
/*    */     //   684: aload #17
/*    */     //   686: aload #18
/*    */     //   688: invokevirtual equals : (Ljava/lang/Object;)Z
/*    */     //   691: ifeq -> 1127
/*    */     //   694: aload_0
/*    */     //   695: invokevirtual _9 : ()Ljava/lang/Object;
/*    */     //   698: aload #29
/*    */     //   700: invokevirtual _9 : ()Ljava/lang/Object;
/*    */     //   703: astore #20
/*    */     //   705: dup
/*    */     //   706: astore #19
/*    */     //   708: aload #20
/*    */     //   710: if_acmpne -> 717
/*    */     //   713: iconst_1
/*    */     //   714: goto -> 775
/*    */     //   717: aload #19
/*    */     //   719: ifnonnull -> 726
/*    */     //   722: iconst_0
/*    */     //   723: goto -> 775
/*    */     //   726: aload #19
/*    */     //   728: instanceof java/lang/Number
/*    */     //   731: ifeq -> 747
/*    */     //   734: aload #19
/*    */     //   736: checkcast java/lang/Number
/*    */     //   739: aload #20
/*    */     //   741: invokestatic equalsNumObject : (Ljava/lang/Number;Ljava/lang/Object;)Z
/*    */     //   744: goto -> 775
/*    */     //   747: aload #19
/*    */     //   749: instanceof java/lang/Character
/*    */     //   752: ifeq -> 768
/*    */     //   755: aload #19
/*    */     //   757: checkcast java/lang/Character
/*    */     //   760: aload #20
/*    */     //   762: invokestatic equalsCharObject : (Ljava/lang/Character;Ljava/lang/Object;)Z
/*    */     //   765: goto -> 775
/*    */     //   768: aload #19
/*    */     //   770: aload #20
/*    */     //   772: invokevirtual equals : (Ljava/lang/Object;)Z
/*    */     //   775: ifeq -> 1127
/*    */     //   778: aload_0
/*    */     //   779: invokevirtual _10 : ()Ljava/lang/Object;
/*    */     //   782: aload #29
/*    */     //   784: invokevirtual _10 : ()Ljava/lang/Object;
/*    */     //   787: astore #22
/*    */     //   789: dup
/*    */     //   790: astore #21
/*    */     //   792: aload #22
/*    */     //   794: if_acmpne -> 801
/*    */     //   797: iconst_1
/*    */     //   798: goto -> 859
/*    */     //   801: aload #21
/*    */     //   803: ifnonnull -> 810
/*    */     //   806: iconst_0
/*    */     //   807: goto -> 859
/*    */     //   810: aload #21
/*    */     //   812: instanceof java/lang/Number
/*    */     //   815: ifeq -> 831
/*    */     //   818: aload #21
/*    */     //   820: checkcast java/lang/Number
/*    */     //   823: aload #22
/*    */     //   825: invokestatic equalsNumObject : (Ljava/lang/Number;Ljava/lang/Object;)Z
/*    */     //   828: goto -> 859
/*    */     //   831: aload #21
/*    */     //   833: instanceof java/lang/Character
/*    */     //   836: ifeq -> 852
/*    */     //   839: aload #21
/*    */     //   841: checkcast java/lang/Character
/*    */     //   844: aload #22
/*    */     //   846: invokestatic equalsCharObject : (Ljava/lang/Character;Ljava/lang/Object;)Z
/*    */     //   849: goto -> 859
/*    */     //   852: aload #21
/*    */     //   854: aload #22
/*    */     //   856: invokevirtual equals : (Ljava/lang/Object;)Z
/*    */     //   859: ifeq -> 1127
/*    */     //   862: aload_0
/*    */     //   863: invokevirtual _11 : ()Ljava/lang/Object;
/*    */     //   866: aload #29
/*    */     //   868: invokevirtual _11 : ()Ljava/lang/Object;
/*    */     //   871: astore #24
/*    */     //   873: dup
/*    */     //   874: astore #23
/*    */     //   876: aload #24
/*    */     //   878: if_acmpne -> 885
/*    */     //   881: iconst_1
/*    */     //   882: goto -> 943
/*    */     //   885: aload #23
/*    */     //   887: ifnonnull -> 894
/*    */     //   890: iconst_0
/*    */     //   891: goto -> 943
/*    */     //   894: aload #23
/*    */     //   896: instanceof java/lang/Number
/*    */     //   899: ifeq -> 915
/*    */     //   902: aload #23
/*    */     //   904: checkcast java/lang/Number
/*    */     //   907: aload #24
/*    */     //   909: invokestatic equalsNumObject : (Ljava/lang/Number;Ljava/lang/Object;)Z
/*    */     //   912: goto -> 943
/*    */     //   915: aload #23
/*    */     //   917: instanceof java/lang/Character
/*    */     //   920: ifeq -> 936
/*    */     //   923: aload #23
/*    */     //   925: checkcast java/lang/Character
/*    */     //   928: aload #24
/*    */     //   930: invokestatic equalsCharObject : (Ljava/lang/Character;Ljava/lang/Object;)Z
/*    */     //   933: goto -> 943
/*    */     //   936: aload #23
/*    */     //   938: aload #24
/*    */     //   940: invokevirtual equals : (Ljava/lang/Object;)Z
/*    */     //   943: ifeq -> 1127
/*    */     //   946: aload_0
/*    */     //   947: invokevirtual _12 : ()Ljava/lang/Object;
/*    */     //   950: aload #29
/*    */     //   952: invokevirtual _12 : ()Ljava/lang/Object;
/*    */     //   955: astore #26
/*    */     //   957: dup
/*    */     //   958: astore #25
/*    */     //   960: aload #26
/*    */     //   962: if_acmpne -> 969
/*    */     //   965: iconst_1
/*    */     //   966: goto -> 1027
/*    */     //   969: aload #25
/*    */     //   971: ifnonnull -> 978
/*    */     //   974: iconst_0
/*    */     //   975: goto -> 1027
/*    */     //   978: aload #25
/*    */     //   980: instanceof java/lang/Number
/*    */     //   983: ifeq -> 999
/*    */     //   986: aload #25
/*    */     //   988: checkcast java/lang/Number
/*    */     //   991: aload #26
/*    */     //   993: invokestatic equalsNumObject : (Ljava/lang/Number;Ljava/lang/Object;)Z
/*    */     //   996: goto -> 1027
/*    */     //   999: aload #25
/*    */     //   1001: instanceof java/lang/Character
/*    */     //   1004: ifeq -> 1020
/*    */     //   1007: aload #25
/*    */     //   1009: checkcast java/lang/Character
/*    */     //   1012: aload #26
/*    */     //   1014: invokestatic equalsCharObject : (Ljava/lang/Character;Ljava/lang/Object;)Z
/*    */     //   1017: goto -> 1027
/*    */     //   1020: aload #25
/*    */     //   1022: aload #26
/*    */     //   1024: invokevirtual equals : (Ljava/lang/Object;)Z
/*    */     //   1027: ifeq -> 1127
/*    */     //   1030: aload_0
/*    */     //   1031: invokevirtual _13 : ()Ljava/lang/Object;
/*    */     //   1034: aload #29
/*    */     //   1036: invokevirtual _13 : ()Ljava/lang/Object;
/*    */     //   1039: astore #28
/*    */     //   1041: dup
/*    */     //   1042: astore #27
/*    */     //   1044: aload #28
/*    */     //   1046: if_acmpne -> 1053
/*    */     //   1049: iconst_1
/*    */     //   1050: goto -> 1111
/*    */     //   1053: aload #27
/*    */     //   1055: ifnonnull -> 1062
/*    */     //   1058: iconst_0
/*    */     //   1059: goto -> 1111
/*    */     //   1062: aload #27
/*    */     //   1064: instanceof java/lang/Number
/*    */     //   1067: ifeq -> 1083
/*    */     //   1070: aload #27
/*    */     //   1072: checkcast java/lang/Number
/*    */     //   1075: aload #28
/*    */     //   1077: invokestatic equalsNumObject : (Ljava/lang/Number;Ljava/lang/Object;)Z
/*    */     //   1080: goto -> 1111
/*    */     //   1083: aload #27
/*    */     //   1085: instanceof java/lang/Character
/*    */     //   1088: ifeq -> 1104
/*    */     //   1091: aload #27
/*    */     //   1093: checkcast java/lang/Character
/*    */     //   1096: aload #28
/*    */     //   1098: invokestatic equalsCharObject : (Ljava/lang/Character;Ljava/lang/Object;)Z
/*    */     //   1101: goto -> 1111
/*    */     //   1104: aload #27
/*    */     //   1106: aload #28
/*    */     //   1108: invokevirtual equals : (Ljava/lang/Object;)Z
/*    */     //   1111: ifeq -> 1127
/*    */     //   1114: aload #29
/*    */     //   1116: aload_0
/*    */     //   1117: invokevirtual canEqual : (Ljava/lang/Object;)Z
/*    */     //   1120: ifeq -> 1127
/*    */     //   1123: iconst_1
/*    */     //   1124: goto -> 1128
/*    */     //   1127: iconst_0
/*    */     //   1128: ifeq -> 1135
/*    */     //   1131: iconst_1
/*    */     //   1132: goto -> 1136
/*    */     //   1135: iconst_0
/*    */     //   1136: ireturn
/*    */     // Line number table:
/*    */     //   Java source line number -> byte code offset
/*    */     //   #30	-> 0
/*    */     //   #236	-> 12
/*    */     //   #30	-> 19
/*    */     // Local variable table:
/*    */     //   start	length	slot	name	descriptor
/*    */     //   0	1137	0	this	Lscala/Tuple13;
/*    */     //   0	1137	1	x$1	Ljava/lang/Object;
/*    */   }
/*    */   
/*    */   public Tuple13(Object _1, Object _2, Object _3, Object _4, Object _5, Object _6, Object _7, Object _8, Object _9, Object _10, Object _11, Object _12, Object _13) {
/* 30 */     Product$class.$init$(this);
/* 30 */     Product13$class.$init$(this);
/*    */   }
/*    */   
/*    */   public String toString() {
/* 34 */     return (new StringBuilder()).append("(").append(_1()).append(",").append(_2()).append(",").append(_3()).append(",").append(_4()).append(",").append(_5()).append(",").append(_6()).append(",").append(_7()).append(",").append(_8()).append(",").append(_9()).append(",").append(_10()).append(",").append(_11()).append(",").append(_12()).append(",").append(_13()).append(")").toString();
/*    */   }
/*    */ }


/* Location:              D:\#source-code\TheFlightSims\TFSLibrary\World2Xplane\World2XPlane.jar!\scala\Tuple13.class
 * Java compiler version: 6 (50.0)
 * JD-Core Version:       1.1.3
 */