/*    */ package scala;
/*    */ 
/*    */ import scala.collection.Iterator;
/*    */ import scala.collection.mutable.StringBuilder;
/*    */ import scala.reflect.ScalaSignature;
/*    */ import scala.runtime.ScalaRunTime$;
/*    */ 
/*    */ @ScalaSignature(bytes = "\006\001\teb\001B\001\003\001\026\021a\001V;qY\0264$\"A\002\002\013M\034\027\r\\1\004\001U9a\001\005\016\036A\r23#\002\001\b\027!Z\003C\001\005\n\033\005\021\021B\001\006\003\005\031\te.\037*fMBA\001\002\004\b\0329}\021S%\003\002\016\005\tA\001K]8ek\016$h\007\005\002\020!1\001AAB\t\001\t\013\007!C\001\002UcE\0211C\006\t\003\021QI!!\006\002\003\0179{G\017[5oOB\021\001bF\005\0031\t\0211!\0218z!\ty!\004\002\004\034\001\021\025\rA\005\002\003)J\002\"aD\017\005\ry\001AQ1\001\023\005\t!6\007\005\002\020A\0211\021\005\001CC\002I\021!\001\026\033\021\005=\031CA\002\023\001\t\013\007!C\001\002UkA\021qB\n\003\007O\001!)\031\001\n\003\005Q3\004C\001\005*\023\tQ#AA\004Qe>$Wo\031;\021\005!a\023BA\027\003\0051\031VM]5bY&T\030M\0317f\021!y\003A!f\001\n\003\001\024AA02+\005q\001\002\003\032\001\005#\005\013\021\002\b\002\007}\013\004\005\003\0055\001\tU\r\021\"\0016\003\ty&'F\001\032\021!9\004A!E!\002\023I\022aA03A!A\021\b\001BK\002\023\005!(\001\002`gU\tA\004\003\005=\001\tE\t\025!\003\035\003\ry6\007\t\005\t}\001\021)\032!C\001\005\021q\fN\013\002?!A\021\t\001B\tB\003%q$A\002`i\001B\001b\021\001\003\026\004%\t\001R\001\003?V*\022A\t\005\t\r\002\021\t\022)A\005E\005\031q,\016\021\t\021!\003!Q3A\005\002%\013!a\030\034\026\003\025B\001b\023\001\003\022\003\006I!J\001\004?Z\002\003\"B'\001\t\003q\025A\002\037j]&$h\bF\004P!F\0236\013V+\021\021!\001a\"\007\017 E\025BQa\f'A\0029AQ\001\016'A\002eAQ!\017'A\002qAQA\020'A\002}AQa\021'A\002\tBQ\001\023'A\002\025BQa\026\001\005Ba\013\001\002^8TiJLgn\032\013\0023B\021!lX\007\0027*\021A,X\001\005Y\006twMC\001_\003\021Q\027M^1\n\005\001\\&AB*ue&tw\rC\004c\001\005\005I\021A2\002\t\r|\007/_\013\bI\036L7.\\8r)\035)'o\035;vm^\004\002\002\003\001gQ*dg\016\035\t\003\037\035$Q!E1C\002I\001\"aD5\005\013m\t'\031\001\n\021\005=YG!\002\020b\005\004\021\002CA\bn\t\025\t\023M1\001\023!\tyq\016B\003%C\n\007!\003\005\002\020c\022)q%\031b\001%!9q&\031I\001\002\0041\007b\002\033b!\003\005\r\001\033\005\bs\005\004\n\0211\001k\021\035q\024\r%AA\0021DqaQ1\021\002\003\007a\016C\004ICB\005\t\031\0019\t\017e\004\021\023!C\001u\006q1m\0349zI\021,g-Y;mi\022\nT#D>\002\016\005=\021\021CA\n\003+\t9\"F\001}U\tqQpK\001!\ry\030\021B\007\003\003\003QA!a\001\002\006\005IQO\\2iK\016\\W\r\032\006\004\003\017\021\021AC1o]>$\030\r^5p]&!\0211BA\001\005E)hn\0315fG.,GMV1sS\006t7-\032\003\006#a\024\rA\005\003\0067a\024\rA\005\003\006=a\024\rA\005\003\006Ca\024\rA\005\003\006Ia\024\rA\005\003\006Oa\024\rA\005\005\n\0037\001\021\023!C\001\003;\tabY8qs\022\"WMZ1vYR$#'\006\b\002 \005\r\022QEA\024\003S\tY#!\f\026\005\005\005\"FA\r~\t\031\t\022\021\004b\001%\02111$!\007C\002I!aAHA\r\005\004\021BAB\021\002\032\t\007!\003\002\004%\0033\021\rA\005\003\007O\005e!\031\001\n\t\023\005E\002!%A\005\002\005M\022AD2paf$C-\0324bk2$HeM\013\017\003k\tI$a\017\002>\005}\022\021IA\"+\t\t9D\013\002\035{\0221\021#a\fC\002I!aaGA\030\005\004\021BA\002\020\0020\t\007!\003\002\004\"\003_\021\rA\005\003\007I\005=\"\031\001\n\005\r\035\nyC1\001\023\021%\t9\005AI\001\n\003\tI%\001\bd_BLH\005Z3gCVdG\017\n\033\026\035\005-\023qJA)\003'\n)&a\026\002ZU\021\021Q\n\026\003?u$a!EA#\005\004\021BAB\016\002F\t\007!\003\002\004\037\003\013\022\rA\005\003\007C\005\025#\031\001\n\005\r\021\n)E1\001\023\t\0319\023Q\tb\001%!I\021Q\f\001\022\002\023\005\021qL\001\017G>\004\030\020\n3fM\006,H\016\036\0236+9\t\t'!\032\002h\005%\0241NA7\003_*\"!a\031+\005\tjHAB\t\002\\\t\007!\003\002\004\034\0037\022\rA\005\003\007=\005m#\031\001\n\005\r\005\nYF1\001\023\t\031!\0231\fb\001%\0211q%a\027C\002IA\021\"a\035\001#\003%\t!!\036\002\035\r|\007/\037\023eK\032\fW\017\034;%mUq\021qOA>\003{\ny(!!\002\004\006\025UCAA=U\t)S\020\002\004\022\003c\022\rA\005\003\0077\005E$\031\001\n\005\ry\t\tH1\001\023\t\031\t\023\021\017b\001%\0211A%!\035C\002I!aaJA9\005\004\021\002\"CAE\001\005\005I\021IAF\0035\001(o\0343vGR\004&/\0324jqV\t\021\fC\005\002\020\002\t\t\021\"\021\002\022\006y\001O]8ek\016$\030\n^3sCR|'/\006\002\002\024B)\021QSAN-5\021\021q\023\006\004\0033\023\021AC2pY2,7\r^5p]&!\021QTAL\005!IE/\032:bi>\024\b\"CAQ\001\005\005I\021AAR\003!\031\027M\\#rk\006dG\003BAS\003W\0032\001CAT\023\r\tIK\001\002\b\005>|G.Z1o\021%\ti+a(\002\002\003\007a#A\002yIEB\021\"!-\001\003\003%\t%a-\002\021!\f7\017[\"pI\026$\"!!.\021\007!\t9,C\002\002:\n\0211!\0238u\021%\ti\fAA\001\n\003\ny,\001\004fcV\fGn\035\013\005\003K\013\t\rC\005\002.\006m\026\021!a\001-\035I\021Q\031\002\002\002#\005\021qY\001\007)V\004H.\032\034\021\007!\tIM\002\005\002\005\005\005\t\022AAf'\021\tImB\026\t\0175\013I\r\"\001\002PR\021\021q\031\005\t/\006%\027\021!C#1\"Q\021Q[Ae\003\003%\t)a6\002\013\005\004\b\017\\=\026\035\005e\027q\\Ar\003O\fY/a<\002tRq\0211\\A{\003o\fI0a?\002~\006}\bC\004\005\001\003;\f\t/!:\002j\0065\030\021\037\t\004\037\005}GAB\t\002T\n\007!\003E\002\020\003G$aaGAj\005\004\021\002cA\b\002h\0221a$a5C\002I\0012aDAv\t\031\t\0231\033b\001%A\031q\"a<\005\r\021\n\031N1\001\023!\ry\0211\037\003\007O\005M'\031\001\n\t\017=\n\031\0161\001\002^\"9A'a5A\002\005\005\bbB\035\002T\002\007\021Q\035\005\b}\005M\007\031AAu\021\035\031\0251\033a\001\003[Dq\001SAj\001\004\t\t\020\003\006\003\004\005%\027\021!CA\005\013\tq!\0368baBd\0270\006\b\003\b\tM!q\003B\016\005?\021\031Ca\n\025\t\t%!\021\006\t\006\021\t-!qB\005\004\005\033\021!AB(qi&|g\016\005\b\t\001\tE!Q\003B\r\005;\021\tC!\n\021\007=\021\031\002\002\004\022\005\003\021\rA\005\t\004\037\t]AAB\016\003\002\t\007!\003E\002\020\0057!aA\bB\001\005\004\021\002cA\b\003 \0211\021E!\001C\002I\0012a\004B\022\t\031!#\021\001b\001%A\031qBa\n\005\r\035\022\tA1\001\023\021)\021YC!\001\002\002\003\007!qB\001\004q\022\002\004B\003B\030\003\023\f\t\021\"\003\0032\005Y!/Z1e%\026\034x\016\034<f)\t\021\031\004E\002[\005kI1Aa\016\\\005\031y%M[3di\002")
/*    */ public class Tuple6<T1, T2, T3, T4, T5, T6> implements Product6<T1, T2, T3, T4, T5, T6>, Product, Serializable {
/*    */   private final T1 _1;
/*    */   
/*    */   private final T2 _2;
/*    */   
/*    */   private final T3 _3;
/*    */   
/*    */   private final T4 _4;
/*    */   
/*    */   private final T5 _5;
/*    */   
/*    */   private final T6 _6;
/*    */   
/*    */   public int productArity() {
/* 23 */     return Product6$class.productArity(this);
/*    */   }
/*    */   
/*    */   public Object productElement(int n) throws IndexOutOfBoundsException {
/* 23 */     return Product6$class.productElement(this, n);
/*    */   }
/*    */   
/*    */   public T1 _1() {
/* 23 */     return this._1;
/*    */   }
/*    */   
/*    */   public T2 _2() {
/* 23 */     return this._2;
/*    */   }
/*    */   
/*    */   public T3 _3() {
/* 23 */     return this._3;
/*    */   }
/*    */   
/*    */   public T4 _4() {
/* 23 */     return this._4;
/*    */   }
/*    */   
/*    */   public T5 _5() {
/* 23 */     return this._5;
/*    */   }
/*    */   
/*    */   public T6 _6() {
/* 23 */     return this._6;
/*    */   }
/*    */   
/*    */   public <T1, T2, T3, T4, T5, T6> Tuple6<T1, T2, T3, T4, T5, T6> copy(Object _1, Object _2, Object _3, Object _4, Object _5, Object _6) {
/* 23 */     return new Tuple6((T1)_1, (T2)_2, (T3)_3, (T4)_4, (T5)_5, (T6)_6);
/*    */   }
/*    */   
/*    */   public <T1, T2, T3, T4, T5, T6> T1 copy$default$1() {
/* 23 */     return _1();
/*    */   }
/*    */   
/*    */   public <T1, T2, T3, T4, T5, T6> T2 copy$default$2() {
/* 23 */     return _2();
/*    */   }
/*    */   
/*    */   public <T1, T2, T3, T4, T5, T6> T3 copy$default$3() {
/* 23 */     return _3();
/*    */   }
/*    */   
/*    */   public <T1, T2, T3, T4, T5, T6> T4 copy$default$4() {
/* 23 */     return _4();
/*    */   }
/*    */   
/*    */   public <T1, T2, T3, T4, T5, T6> T5 copy$default$5() {
/* 23 */     return _5();
/*    */   }
/*    */   
/*    */   public <T1, T2, T3, T4, T5, T6> T6 copy$default$6() {
/* 23 */     return _6();
/*    */   }
/*    */   
/*    */   public String productPrefix() {
/* 23 */     return "Tuple6";
/*    */   }
/*    */   
/*    */   public Iterator<Object> productIterator() {
/* 23 */     return ScalaRunTime$.MODULE$.typedProductIterator(this);
/*    */   }
/*    */   
/*    */   public boolean canEqual(Object x$1) {
/* 23 */     return x$1 instanceof Tuple6;
/*    */   }
/*    */   
/*    */   public int hashCode() {
/* 23 */     return ScalaRunTime$.MODULE$._hashCode(this);
/*    */   }
/*    */   
/*    */   public boolean equals(Object x$1) {
/*    */     // Byte code:
/*    */     //   0: aload_0
/*    */     //   1: aload_1
/*    */     //   2: if_acmpeq -> 543
/*    */     //   5: aload_1
/*    */     //   6: instanceof scala/Tuple6
/*    */     //   9: ifeq -> 17
/*    */     //   12: iconst_1
/*    */     //   13: istore_2
/*    */     //   14: goto -> 19
/*    */     //   17: iconst_0
/*    */     //   18: istore_2
/*    */     //   19: iload_2
/*    */     //   20: ifeq -> 547
/*    */     //   23: aload_1
/*    */     //   24: checkcast scala/Tuple6
/*    */     //   27: astore #15
/*    */     //   29: aload_0
/*    */     //   30: invokevirtual _1 : ()Ljava/lang/Object;
/*    */     //   33: aload #15
/*    */     //   35: invokevirtual _1 : ()Ljava/lang/Object;
/*    */     //   38: astore #4
/*    */     //   40: dup
/*    */     //   41: astore_3
/*    */     //   42: aload #4
/*    */     //   44: if_acmpne -> 51
/*    */     //   47: iconst_1
/*    */     //   48: goto -> 103
/*    */     //   51: aload_3
/*    */     //   52: ifnonnull -> 59
/*    */     //   55: iconst_0
/*    */     //   56: goto -> 103
/*    */     //   59: aload_3
/*    */     //   60: instanceof java/lang/Number
/*    */     //   63: ifeq -> 78
/*    */     //   66: aload_3
/*    */     //   67: checkcast java/lang/Number
/*    */     //   70: aload #4
/*    */     //   72: invokestatic equalsNumObject : (Ljava/lang/Number;Ljava/lang/Object;)Z
/*    */     //   75: goto -> 103
/*    */     //   78: aload_3
/*    */     //   79: instanceof java/lang/Character
/*    */     //   82: ifeq -> 97
/*    */     //   85: aload_3
/*    */     //   86: checkcast java/lang/Character
/*    */     //   89: aload #4
/*    */     //   91: invokestatic equalsCharObject : (Ljava/lang/Character;Ljava/lang/Object;)Z
/*    */     //   94: goto -> 103
/*    */     //   97: aload_3
/*    */     //   98: aload #4
/*    */     //   100: invokevirtual equals : (Ljava/lang/Object;)Z
/*    */     //   103: ifeq -> 539
/*    */     //   106: aload_0
/*    */     //   107: invokevirtual _2 : ()Ljava/lang/Object;
/*    */     //   110: aload #15
/*    */     //   112: invokevirtual _2 : ()Ljava/lang/Object;
/*    */     //   115: astore #6
/*    */     //   117: dup
/*    */     //   118: astore #5
/*    */     //   120: aload #6
/*    */     //   122: if_acmpne -> 129
/*    */     //   125: iconst_1
/*    */     //   126: goto -> 187
/*    */     //   129: aload #5
/*    */     //   131: ifnonnull -> 138
/*    */     //   134: iconst_0
/*    */     //   135: goto -> 187
/*    */     //   138: aload #5
/*    */     //   140: instanceof java/lang/Number
/*    */     //   143: ifeq -> 159
/*    */     //   146: aload #5
/*    */     //   148: checkcast java/lang/Number
/*    */     //   151: aload #6
/*    */     //   153: invokestatic equalsNumObject : (Ljava/lang/Number;Ljava/lang/Object;)Z
/*    */     //   156: goto -> 187
/*    */     //   159: aload #5
/*    */     //   161: instanceof java/lang/Character
/*    */     //   164: ifeq -> 180
/*    */     //   167: aload #5
/*    */     //   169: checkcast java/lang/Character
/*    */     //   172: aload #6
/*    */     //   174: invokestatic equalsCharObject : (Ljava/lang/Character;Ljava/lang/Object;)Z
/*    */     //   177: goto -> 187
/*    */     //   180: aload #5
/*    */     //   182: aload #6
/*    */     //   184: invokevirtual equals : (Ljava/lang/Object;)Z
/*    */     //   187: ifeq -> 539
/*    */     //   190: aload_0
/*    */     //   191: invokevirtual _3 : ()Ljava/lang/Object;
/*    */     //   194: aload #15
/*    */     //   196: invokevirtual _3 : ()Ljava/lang/Object;
/*    */     //   199: astore #8
/*    */     //   201: dup
/*    */     //   202: astore #7
/*    */     //   204: aload #8
/*    */     //   206: if_acmpne -> 213
/*    */     //   209: iconst_1
/*    */     //   210: goto -> 271
/*    */     //   213: aload #7
/*    */     //   215: ifnonnull -> 222
/*    */     //   218: iconst_0
/*    */     //   219: goto -> 271
/*    */     //   222: aload #7
/*    */     //   224: instanceof java/lang/Number
/*    */     //   227: ifeq -> 243
/*    */     //   230: aload #7
/*    */     //   232: checkcast java/lang/Number
/*    */     //   235: aload #8
/*    */     //   237: invokestatic equalsNumObject : (Ljava/lang/Number;Ljava/lang/Object;)Z
/*    */     //   240: goto -> 271
/*    */     //   243: aload #7
/*    */     //   245: instanceof java/lang/Character
/*    */     //   248: ifeq -> 264
/*    */     //   251: aload #7
/*    */     //   253: checkcast java/lang/Character
/*    */     //   256: aload #8
/*    */     //   258: invokestatic equalsCharObject : (Ljava/lang/Character;Ljava/lang/Object;)Z
/*    */     //   261: goto -> 271
/*    */     //   264: aload #7
/*    */     //   266: aload #8
/*    */     //   268: invokevirtual equals : (Ljava/lang/Object;)Z
/*    */     //   271: ifeq -> 539
/*    */     //   274: aload_0
/*    */     //   275: invokevirtual _4 : ()Ljava/lang/Object;
/*    */     //   278: aload #15
/*    */     //   280: invokevirtual _4 : ()Ljava/lang/Object;
/*    */     //   283: astore #10
/*    */     //   285: dup
/*    */     //   286: astore #9
/*    */     //   288: aload #10
/*    */     //   290: if_acmpne -> 297
/*    */     //   293: iconst_1
/*    */     //   294: goto -> 355
/*    */     //   297: aload #9
/*    */     //   299: ifnonnull -> 306
/*    */     //   302: iconst_0
/*    */     //   303: goto -> 355
/*    */     //   306: aload #9
/*    */     //   308: instanceof java/lang/Number
/*    */     //   311: ifeq -> 327
/*    */     //   314: aload #9
/*    */     //   316: checkcast java/lang/Number
/*    */     //   319: aload #10
/*    */     //   321: invokestatic equalsNumObject : (Ljava/lang/Number;Ljava/lang/Object;)Z
/*    */     //   324: goto -> 355
/*    */     //   327: aload #9
/*    */     //   329: instanceof java/lang/Character
/*    */     //   332: ifeq -> 348
/*    */     //   335: aload #9
/*    */     //   337: checkcast java/lang/Character
/*    */     //   340: aload #10
/*    */     //   342: invokestatic equalsCharObject : (Ljava/lang/Character;Ljava/lang/Object;)Z
/*    */     //   345: goto -> 355
/*    */     //   348: aload #9
/*    */     //   350: aload #10
/*    */     //   352: invokevirtual equals : (Ljava/lang/Object;)Z
/*    */     //   355: ifeq -> 539
/*    */     //   358: aload_0
/*    */     //   359: invokevirtual _5 : ()Ljava/lang/Object;
/*    */     //   362: aload #15
/*    */     //   364: invokevirtual _5 : ()Ljava/lang/Object;
/*    */     //   367: astore #12
/*    */     //   369: dup
/*    */     //   370: astore #11
/*    */     //   372: aload #12
/*    */     //   374: if_acmpne -> 381
/*    */     //   377: iconst_1
/*    */     //   378: goto -> 439
/*    */     //   381: aload #11
/*    */     //   383: ifnonnull -> 390
/*    */     //   386: iconst_0
/*    */     //   387: goto -> 439
/*    */     //   390: aload #11
/*    */     //   392: instanceof java/lang/Number
/*    */     //   395: ifeq -> 411
/*    */     //   398: aload #11
/*    */     //   400: checkcast java/lang/Number
/*    */     //   403: aload #12
/*    */     //   405: invokestatic equalsNumObject : (Ljava/lang/Number;Ljava/lang/Object;)Z
/*    */     //   408: goto -> 439
/*    */     //   411: aload #11
/*    */     //   413: instanceof java/lang/Character
/*    */     //   416: ifeq -> 432
/*    */     //   419: aload #11
/*    */     //   421: checkcast java/lang/Character
/*    */     //   424: aload #12
/*    */     //   426: invokestatic equalsCharObject : (Ljava/lang/Character;Ljava/lang/Object;)Z
/*    */     //   429: goto -> 439
/*    */     //   432: aload #11
/*    */     //   434: aload #12
/*    */     //   436: invokevirtual equals : (Ljava/lang/Object;)Z
/*    */     //   439: ifeq -> 539
/*    */     //   442: aload_0
/*    */     //   443: invokevirtual _6 : ()Ljava/lang/Object;
/*    */     //   446: aload #15
/*    */     //   448: invokevirtual _6 : ()Ljava/lang/Object;
/*    */     //   451: astore #14
/*    */     //   453: dup
/*    */     //   454: astore #13
/*    */     //   456: aload #14
/*    */     //   458: if_acmpne -> 465
/*    */     //   461: iconst_1
/*    */     //   462: goto -> 523
/*    */     //   465: aload #13
/*    */     //   467: ifnonnull -> 474
/*    */     //   470: iconst_0
/*    */     //   471: goto -> 523
/*    */     //   474: aload #13
/*    */     //   476: instanceof java/lang/Number
/*    */     //   479: ifeq -> 495
/*    */     //   482: aload #13
/*    */     //   484: checkcast java/lang/Number
/*    */     //   487: aload #14
/*    */     //   489: invokestatic equalsNumObject : (Ljava/lang/Number;Ljava/lang/Object;)Z
/*    */     //   492: goto -> 523
/*    */     //   495: aload #13
/*    */     //   497: instanceof java/lang/Character
/*    */     //   500: ifeq -> 516
/*    */     //   503: aload #13
/*    */     //   505: checkcast java/lang/Character
/*    */     //   508: aload #14
/*    */     //   510: invokestatic equalsCharObject : (Ljava/lang/Character;Ljava/lang/Object;)Z
/*    */     //   513: goto -> 523
/*    */     //   516: aload #13
/*    */     //   518: aload #14
/*    */     //   520: invokevirtual equals : (Ljava/lang/Object;)Z
/*    */     //   523: ifeq -> 539
/*    */     //   526: aload #15
/*    */     //   528: aload_0
/*    */     //   529: invokevirtual canEqual : (Ljava/lang/Object;)Z
/*    */     //   532: ifeq -> 539
/*    */     //   535: iconst_1
/*    */     //   536: goto -> 540
/*    */     //   539: iconst_0
/*    */     //   540: ifeq -> 547
/*    */     //   543: iconst_1
/*    */     //   544: goto -> 548
/*    */     //   547: iconst_0
/*    */     //   548: ireturn
/*    */     // Line number table:
/*    */     //   Java source line number -> byte code offset
/*    */     //   #23	-> 0
/*    */     //   #236	-> 12
/*    */     //   #23	-> 19
/*    */     // Local variable table:
/*    */     //   start	length	slot	name	descriptor
/*    */     //   0	549	0	this	Lscala/Tuple6;
/*    */     //   0	549	1	x$1	Ljava/lang/Object;
/*    */   }
/*    */   
/*    */   public Tuple6(Object _1, Object _2, Object _3, Object _4, Object _5, Object _6) {
/* 23 */     Product$class.$init$(this);
/* 23 */     Product6$class.$init$(this);
/*    */   }
/*    */   
/*    */   public String toString() {
/* 26 */     return (new StringBuilder()).append("(").append(_1()).append(",").append(_2()).append(",").append(_3()).append(",").append(_4()).append(",").append(_5()).append(",").append(_6()).append(")").toString();
/*    */   }
/*    */ }


/* Location:              D:\#source-code\TheFlightSims\TFSLibrary\World2Xplane\World2XPlane.jar!\scala\Tuple6.class
 * Java compiler version: 6 (50.0)
 * JD-Core Version:       1.1.3
 */