/*    */ package scala;
/*    */ 
/*    */ import scala.collection.Iterator;
/*    */ import scala.collection.mutable.StringBuilder;
/*    */ import scala.reflect.ScalaSignature;
/*    */ import scala.runtime.ScalaRunTime$;
/*    */ 
/*    */ @ScalaSignature(bytes = "\006\001\005}d\001B\001\003\001\026\021a\001V;qY\026\034$\"A\002\002\013M\034\027\r\\1\004\001U!a\001\005\016\036'\025\001qaC\020#!\tA\021\"D\001\003\023\tQ!A\001\004B]f\024VM\032\t\006\0211q\021\004H\005\003\033\t\021\001\002\025:pIV\034Go\r\t\003\037Aa\001\001\002\004\022\001\021\025\rA\005\002\003)F\n\"a\005\f\021\005!!\022BA\013\003\005\035qu\016\0365j]\036\004\"\001C\f\n\005a\021!aA!osB\021qB\007\003\0077\001!)\031\001\n\003\005Q\023\004CA\b\036\t\031q\002\001\"b\001%\t\021Ak\r\t\003\021\001J!!\t\002\003\017A\023x\016Z;diB\021\001bI\005\003I\t\021AbU3sS\006d\027N_1cY\026D\001B\n\001\003\026\004%\taJ\001\003?F*\022A\004\005\tS\001\021\t\022)A\005\035\005\031q,\r\021\t\021-\002!Q3A\005\0021\n!a\030\032\026\003eA\001B\f\001\003\022\003\006I!G\001\004?J\002\003\002\003\031\001\005+\007I\021A\031\002\005}\033T#\001\017\t\021M\002!\021#Q\001\nq\t1aX\032!\021\025)\004\001\"\0017\003\031a\024N\\5u}Q!q\007O\035;!\025A\001AD\r\035\021\0251C\0071\001\017\021\025YC\0071\001\032\021\025\001D\0071\001\035\021\025a\004\001\"\021>\003!!xn\025;sS:<G#\001 \021\005}\"U\"\001!\013\005\005\023\025\001\0027b]\036T\021aQ\001\005U\0064\030-\003\002F\001\n11\013\036:j]\036Dqa\022\001\002\002\023\005\001*\001\003d_BLX\003B%M\035B#BAS)S'B)\001\002A&N\037B\021q\002\024\003\006#\031\023\rA\005\t\003\0379#Qa\007$C\002I\001\"a\004)\005\013y1%\031\001\n\t\017\0312\005\023!a\001\027\"91F\022I\001\002\004i\005b\002\031G!\003\005\ra\024\005\b+\002\t\n\021\"\001W\0039\031w\016]=%I\0264\027-\0367uIE*Ba\0262dIV\t\001L\013\002\0173.\n!\f\005\002\\A6\tAL\003\002^=\006IQO\\2iK\016\\W\r\032\006\003?\n\t!\"\0318o_R\fG/[8o\023\t\tGLA\tv]\016DWmY6fIZ\013'/[1oG\026$Q!\005+C\002I!Qa\007+C\002I!QA\b+C\002IAqA\032\001\022\002\023\005q-\001\bd_BLH\005Z3gCVdG\017\n\032\026\t!T7\016\\\013\002S*\022\021$\027\003\006#\025\024\rA\005\003\0067\025\024\rA\005\003\006=\025\024\rA\005\005\b]\002\t\n\021\"\001p\0039\031w\016]=%I\0264\027-\0367uIM*B\001\035:tiV\t\021O\013\002\0353\022)\021#\034b\001%\021)1$\034b\001%\021)a$\034b\001%!9a\017AA\001\n\003:\030!\0049s_\022,8\r\036)sK\032L\0070F\001?\021\035I\b!!A\005Bi\fq\002\035:pIV\034G/\023;fe\006$xN]\013\002wB\031Ap \f\016\003uT!A \002\002\025\r|G\016\\3di&|g.C\002\002\002u\024\001\"\023;fe\006$xN\035\005\n\003\013\001\021\021!C\001\003\017\t\001bY1o\013F,\030\r\034\013\005\003\023\ty\001E\002\t\003\027I1!!\004\003\005\035\021un\0347fC:D\021\"!\005\002\004\005\005\t\031\001\f\002\007a$\023\007C\005\002\026\001\t\t\021\"\021\002\030\005A\001.Y:i\007>$W\r\006\002\002\032A\031\001\"a\007\n\007\005u!AA\002J]RD\021\"!\t\001\003\003%\t%a\t\002\r\025\fX/\0317t)\021\tI!!\n\t\023\005E\021qDA\001\002\0041r!CA\025\005\005\005\t\022AA\026\003\031!V\017\0357fgA\031\001\"!\f\007\021\005\021\021\021!E\001\003_\031B!!\f\bE!9Q'!\f\005\002\005MBCAA\026\021!a\024QFA\001\n\013j\004BCA\035\003[\t\t\021\"!\002<\005)\021\r\0359msVA\021QHA\"\003\017\nY\005\006\005\002@\0055\023qJA)!!A\001!!\021\002F\005%\003cA\b\002D\0211\021#a\016C\002I\0012aDA$\t\031Y\022q\007b\001%A\031q\"a\023\005\ry\t9D1\001\023\021\0351\023q\007a\001\003\003BqaKA\034\001\004\t)\005C\0041\003o\001\r!!\023\t\025\005U\023QFA\001\n\003\0139&A\004v]\006\004\b\017\\=\026\021\005e\023QMA5\003[\"B!a\027\002pA)\001\"!\030\002b%\031\021q\f\002\003\r=\003H/[8o!!A\001!a\031\002h\005-\004cA\b\002f\0211\021#a\025C\002I\0012aDA5\t\031Y\0221\013b\001%A\031q\"!\034\005\ry\t\031F1\001\023\021)\t\t(a\025\002\002\003\007\021\021M\001\004q\022\002\004BCA;\003[\t\t\021\"\003\002x\005Y!/Z1e%\026\034x\016\034<f)\t\tI\bE\002@\003wJ1!! A\005\031y%M[3di\002")
/*    */ public class Tuple3<T1, T2, T3> implements Product3<T1, T2, T3>, Product, Serializable {
/*    */   private final T1 _1;
/*    */   
/*    */   private final T2 _2;
/*    */   
/*    */   private final T3 _3;
/*    */   
/*    */   public int productArity() {
/* 20 */     return Product3$class.productArity(this);
/*    */   }
/*    */   
/*    */   public Object productElement(int n) throws IndexOutOfBoundsException {
/* 20 */     return Product3$class.productElement(this, n);
/*    */   }
/*    */   
/*    */   public T1 _1() {
/* 20 */     return this._1;
/*    */   }
/*    */   
/*    */   public T2 _2() {
/* 20 */     return this._2;
/*    */   }
/*    */   
/*    */   public T3 _3() {
/* 20 */     return this._3;
/*    */   }
/*    */   
/*    */   public <T1, T2, T3> Tuple3<T1, T2, T3> copy(Object _1, Object _2, Object _3) {
/* 20 */     return new Tuple3((T1)_1, (T2)_2, (T3)_3);
/*    */   }
/*    */   
/*    */   public <T1, T2, T3> T1 copy$default$1() {
/* 20 */     return _1();
/*    */   }
/*    */   
/*    */   public <T1, T2, T3> T2 copy$default$2() {
/* 20 */     return _2();
/*    */   }
/*    */   
/*    */   public <T1, T2, T3> T3 copy$default$3() {
/* 20 */     return _3();
/*    */   }
/*    */   
/*    */   public String productPrefix() {
/* 20 */     return "Tuple3";
/*    */   }
/*    */   
/*    */   public Iterator<Object> productIterator() {
/* 20 */     return ScalaRunTime$.MODULE$.typedProductIterator(this);
/*    */   }
/*    */   
/*    */   public boolean canEqual(Object x$1) {
/* 20 */     return x$1 instanceof Tuple3;
/*    */   }
/*    */   
/*    */   public int hashCode() {
/* 20 */     return ScalaRunTime$.MODULE$._hashCode(this);
/*    */   }
/*    */   
/*    */   public boolean equals(Object x$1) {
/*    */     // Byte code:
/*    */     //   0: aload_0
/*    */     //   1: aload_1
/*    */     //   2: if_acmpeq -> 291
/*    */     //   5: aload_1
/*    */     //   6: instanceof scala/Tuple3
/*    */     //   9: ifeq -> 17
/*    */     //   12: iconst_1
/*    */     //   13: istore_2
/*    */     //   14: goto -> 19
/*    */     //   17: iconst_0
/*    */     //   18: istore_2
/*    */     //   19: iload_2
/*    */     //   20: ifeq -> 295
/*    */     //   23: aload_1
/*    */     //   24: checkcast scala/Tuple3
/*    */     //   27: astore #9
/*    */     //   29: aload_0
/*    */     //   30: invokevirtual _1 : ()Ljava/lang/Object;
/*    */     //   33: aload #9
/*    */     //   35: invokevirtual _1 : ()Ljava/lang/Object;
/*    */     //   38: astore #4
/*    */     //   40: dup
/*    */     //   41: astore_3
/*    */     //   42: aload #4
/*    */     //   44: if_acmpne -> 51
/*    */     //   47: iconst_1
/*    */     //   48: goto -> 103
/*    */     //   51: aload_3
/*    */     //   52: ifnonnull -> 59
/*    */     //   55: iconst_0
/*    */     //   56: goto -> 103
/*    */     //   59: aload_3
/*    */     //   60: instanceof java/lang/Number
/*    */     //   63: ifeq -> 78
/*    */     //   66: aload_3
/*    */     //   67: checkcast java/lang/Number
/*    */     //   70: aload #4
/*    */     //   72: invokestatic equalsNumObject : (Ljava/lang/Number;Ljava/lang/Object;)Z
/*    */     //   75: goto -> 103
/*    */     //   78: aload_3
/*    */     //   79: instanceof java/lang/Character
/*    */     //   82: ifeq -> 97
/*    */     //   85: aload_3
/*    */     //   86: checkcast java/lang/Character
/*    */     //   89: aload #4
/*    */     //   91: invokestatic equalsCharObject : (Ljava/lang/Character;Ljava/lang/Object;)Z
/*    */     //   94: goto -> 103
/*    */     //   97: aload_3
/*    */     //   98: aload #4
/*    */     //   100: invokevirtual equals : (Ljava/lang/Object;)Z
/*    */     //   103: ifeq -> 287
/*    */     //   106: aload_0
/*    */     //   107: invokevirtual _2 : ()Ljava/lang/Object;
/*    */     //   110: aload #9
/*    */     //   112: invokevirtual _2 : ()Ljava/lang/Object;
/*    */     //   115: astore #6
/*    */     //   117: dup
/*    */     //   118: astore #5
/*    */     //   120: aload #6
/*    */     //   122: if_acmpne -> 129
/*    */     //   125: iconst_1
/*    */     //   126: goto -> 187
/*    */     //   129: aload #5
/*    */     //   131: ifnonnull -> 138
/*    */     //   134: iconst_0
/*    */     //   135: goto -> 187
/*    */     //   138: aload #5
/*    */     //   140: instanceof java/lang/Number
/*    */     //   143: ifeq -> 159
/*    */     //   146: aload #5
/*    */     //   148: checkcast java/lang/Number
/*    */     //   151: aload #6
/*    */     //   153: invokestatic equalsNumObject : (Ljava/lang/Number;Ljava/lang/Object;)Z
/*    */     //   156: goto -> 187
/*    */     //   159: aload #5
/*    */     //   161: instanceof java/lang/Character
/*    */     //   164: ifeq -> 180
/*    */     //   167: aload #5
/*    */     //   169: checkcast java/lang/Character
/*    */     //   172: aload #6
/*    */     //   174: invokestatic equalsCharObject : (Ljava/lang/Character;Ljava/lang/Object;)Z
/*    */     //   177: goto -> 187
/*    */     //   180: aload #5
/*    */     //   182: aload #6
/*    */     //   184: invokevirtual equals : (Ljava/lang/Object;)Z
/*    */     //   187: ifeq -> 287
/*    */     //   190: aload_0
/*    */     //   191: invokevirtual _3 : ()Ljava/lang/Object;
/*    */     //   194: aload #9
/*    */     //   196: invokevirtual _3 : ()Ljava/lang/Object;
/*    */     //   199: astore #8
/*    */     //   201: dup
/*    */     //   202: astore #7
/*    */     //   204: aload #8
/*    */     //   206: if_acmpne -> 213
/*    */     //   209: iconst_1
/*    */     //   210: goto -> 271
/*    */     //   213: aload #7
/*    */     //   215: ifnonnull -> 222
/*    */     //   218: iconst_0
/*    */     //   219: goto -> 271
/*    */     //   222: aload #7
/*    */     //   224: instanceof java/lang/Number
/*    */     //   227: ifeq -> 243
/*    */     //   230: aload #7
/*    */     //   232: checkcast java/lang/Number
/*    */     //   235: aload #8
/*    */     //   237: invokestatic equalsNumObject : (Ljava/lang/Number;Ljava/lang/Object;)Z
/*    */     //   240: goto -> 271
/*    */     //   243: aload #7
/*    */     //   245: instanceof java/lang/Character
/*    */     //   248: ifeq -> 264
/*    */     //   251: aload #7
/*    */     //   253: checkcast java/lang/Character
/*    */     //   256: aload #8
/*    */     //   258: invokestatic equalsCharObject : (Ljava/lang/Character;Ljava/lang/Object;)Z
/*    */     //   261: goto -> 271
/*    */     //   264: aload #7
/*    */     //   266: aload #8
/*    */     //   268: invokevirtual equals : (Ljava/lang/Object;)Z
/*    */     //   271: ifeq -> 287
/*    */     //   274: aload #9
/*    */     //   276: aload_0
/*    */     //   277: invokevirtual canEqual : (Ljava/lang/Object;)Z
/*    */     //   280: ifeq -> 287
/*    */     //   283: iconst_1
/*    */     //   284: goto -> 288
/*    */     //   287: iconst_0
/*    */     //   288: ifeq -> 295
/*    */     //   291: iconst_1
/*    */     //   292: goto -> 296
/*    */     //   295: iconst_0
/*    */     //   296: ireturn
/*    */     // Line number table:
/*    */     //   Java source line number -> byte code offset
/*    */     //   #20	-> 0
/*    */     //   #236	-> 12
/*    */     //   #20	-> 19
/*    */     // Local variable table:
/*    */     //   start	length	slot	name	descriptor
/*    */     //   0	297	0	this	Lscala/Tuple3;
/*    */     //   0	297	1	x$1	Ljava/lang/Object;
/*    */   }
/*    */   
/*    */   public Tuple3(Object _1, Object _2, Object _3) {
/* 20 */     Product$class.$init$(this);
/* 20 */     Product3$class.$init$(this);
/*    */   }
/*    */   
/*    */   public String toString() {
/* 23 */     return (new StringBuilder()).append("(").append(_1()).append(",").append(_2()).append(",").append(_3()).append(")").toString();
/*    */   }
/*    */ }


/* Location:              D:\#source-code\TheFlightSims\TFSLibrary\World2Xplane\World2XPlane.jar!\scala\Tuple3.class
 * Java compiler version: 6 (50.0)
 * JD-Core Version:       1.1.3
 */