/*    */ package scala;
/*    */ 
/*    */ import scala.collection.Iterator;
/*    */ import scala.collection.mutable.StringBuilder;
/*    */ import scala.reflect.ScalaSignature;
/*    */ import scala.runtime.ScalaRunTime$;
/*    */ 
/*    */ @ScalaSignature(bytes = "\006\001\t}d\001B\001\003\001\026\021a\001V;qY\026<$\"A\002\002\013M\034\027\r\\1\004\001UAa\001\005\016\036A\r2\023fE\003\001\017-Yc\006\005\002\t\0235\t!!\003\002\013\005\t1\021I\\=SK\032\004\022\002\003\007\0173qy\"%\n\025\n\0055\021!\001\003)s_\022,8\r^\034\021\005=\001B\002\001\003\007#\001!)\031\001\n\003\005Q\013\024CA\n\027!\tAA#\003\002\026\005\t9aj\034;iS:<\007C\001\005\030\023\tA\"AA\002B]f\004\"a\004\016\005\rm\001AQ1\001\023\005\t!&\007\005\002\020;\0211a\004\001CC\002I\021!\001V\032\021\005=\001CAB\021\001\t\013\007!C\001\002UiA\021qb\t\003\007I\001!)\031\001\n\003\005Q+\004CA\b'\t\0319\003\001\"b\001%\t\021AK\016\t\003\037%\"aA\013\001\005\006\004\021\"A\001+8!\tAA&\003\002.\005\t9\001K]8ek\016$\bC\001\0050\023\t\001$A\001\007TKJL\027\r\\5{C\ndW\r\003\0053\001\tU\r\021\"\0014\003\ty\026'F\001\017\021!)\004A!E!\002\023q\021aA02A!Aq\007\001BK\002\023\005\001(\001\002`eU\t\021\004\003\005;\001\tE\t\025!\003\032\003\ry&\007\t\005\ty\001\021)\032!C\001{\005\021qlM\013\0029!Aq\b\001B\tB\003%A$A\002`g\001B\001\"\021\001\003\026\004%\tAQ\001\003?R*\022a\b\005\t\t\002\021\t\022)A\005?\005\031q\f\016\021\t\021\031\003!Q3A\005\002\035\013!aX\033\026\003\tB\001\"\023\001\003\022\003\006IAI\001\004?V\002\003\002C&\001\005+\007I\021\001'\002\005}3T#A\023\t\0219\003!\021#Q\001\n\025\n1a\030\034!\021!\001\006A!f\001\n\003\t\026AA08+\005A\003\002C*\001\005#\005\013\021\002\025\002\007};\004\005C\003V\001\021\005a+\001\004=S:LGO\020\013\t/bK&l\027/^=BI\001\002\001\b\0329}\021S\005\013\005\006eQ\003\rA\004\005\006oQ\003\r!\007\005\006yQ\003\r\001\b\005\006\003R\003\ra\b\005\006\rR\003\rA\t\005\006\027R\003\r!\n\005\006!R\003\r\001\013\005\006A\002!\t%Y\001\ti>\034FO]5oOR\t!\r\005\002dQ6\tAM\003\002fM\006!A.\0318h\025\0059\027\001\0026bm\006L!!\0333\003\rM#(/\0338h\021\035Y\007!!A\005\0021\fAaY8qsVAQ\016\035:umbTH\020\006\007o{z|\030\021AA\002\003\013\t9\001E\005\t\001=\f8/^<zwB\021q\002\035\003\006#)\024\rA\005\t\003\037I$Qa\0076C\002I\001\"a\004;\005\013yQ'\031\001\n\021\005=1H!B\021k\005\004\021\002CA\by\t\025!#N1\001\023!\ty!\020B\003(U\n\007!\003\005\002\020y\022)!F\033b\001%!9!G\033I\001\002\004y\007bB\034k!\003\005\r!\035\005\by)\004\n\0211\001t\021\035\t%\016%AA\002UDqA\0226\021\002\003\007q\017C\004LUB\005\t\031A=\t\017AS\007\023!a\001w\"I\0211\002\001\022\002\023\005\021QB\001\017G>\004\030\020\n3fM\006,H\016\036\0232+A\ty!!\n\002(\005%\0221FA\027\003_\t\t$\006\002\002\022)\032a\"a\005,\005\005U\001\003BA\f\003Ci!!!\007\013\t\005m\021QD\001\nk:\034\007.Z2lK\022T1!a\b\003\003)\tgN\\8uCRLwN\\\005\005\003G\tIBA\tv]\016DWmY6fIZ\013'/[1oG\026$a!EA\005\005\004\021BAB\016\002\n\t\007!\003\002\004\037\003\023\021\rA\005\003\007C\005%!\031\001\n\005\r\021\nIA1\001\023\t\0319\023\021\002b\001%\0211!&!\003C\002IA\021\"!\016\001#\003%\t!a\016\002\035\r|\007/\037\023eK\032\fW\017\034;%eU\001\022\021HA\037\003\t\t%a\021\002F\005\035\023\021J\013\003\003wQ3!GA\n\t\031\t\0221\007b\001%\02111$a\rC\002I!aAHA\032\005\004\021BAB\021\0024\t\007!\003\002\004%\003g\021\rA\005\003\007O\005M\"\031\001\n\005\r)\n\031D1\001\023\021%\ti\005AI\001\n\003\ty%\001\bd_BLH\005Z3gCVdG\017J\032\026!\005E\023QKA,\0033\nY&!\030\002`\005\005TCAA*U\ra\0221\003\003\007#\005-#\031\001\n\005\rm\tYE1\001\023\t\031q\0221\nb\001%\0211\021%a\023C\002I!a\001JA&\005\004\021BAB\024\002L\t\007!\003\002\004+\003\027\022\rA\005\005\n\003K\002\021\023!C\001\003O\nabY8qs\022\"WMZ1vYR$C'\006\t\002j\0055\024qNA9\003g\n)(a\036\002zU\021\0211\016\026\004?\005MAAB\t\002d\t\007!\003\002\004\034\003G\022\rA\005\003\007=\005\r$\031\001\n\005\r\005\n\031G1\001\023\t\031!\0231\rb\001%\0211q%a\031C\002I!aAKA2\005\004\021\002\"CA?\001E\005I\021AA@\0039\031w\016]=%I\0264\027-\0367uIU*\002#!!\002\006\006\035\025\021RAF\003\033\013y)!%\026\005\005\r%f\001\022\002\024\0211\021#a\037C\002I!aaGA>\005\004\021BA\002\020\002|\t\007!\003\002\004\"\003w\022\rA\005\003\007I\005m$\031\001\n\005\r\035\nYH1\001\023\t\031Q\0231\020b\001%!I\021Q\023\001\022\002\023\005\021qS\001\017G>\004\030\020\n3fM\006,H\016\036\0237+A\tI*!(\002 \006\005\0261UAS\003O\013I+\006\002\002\034*\032Q%a\005\005\rE\t\031J1\001\023\t\031Y\0221\023b\001%\0211a$a%C\002I!a!IAJ\005\004\021BA\002\023\002\024\n\007!\003\002\004(\003'\023\rA\005\003\007U\005M%\031\001\n\t\023\0055\006!%A\005\002\005=\026AD2paf$C-\0324bk2$HeN\013\021\003c\013),a.\002:\006m\026QXA`\003\003,\"!a-+\007!\n\031\002\002\004\022\003W\023\rA\005\003\0077\005-&\031\001\n\005\ry\tYK1\001\023\t\031\t\0231\026b\001%\0211A%a+C\002I!aaJAV\005\004\021BA\002\026\002,\n\007!\003C\005\002F\002\t\t\021\"\021\002H\006i\001O]8ek\016$\bK]3gSb,\022A\031\005\n\003\027\004\021\021!C!\003\033\fq\002\035:pIV\034G/\023;fe\006$xN]\013\003\003\037\004R!!5\002XZi!!a5\013\007\005U'!\001\006d_2dWm\031;j_:LA!!7\002T\nA\021\n^3sCR|'\017C\005\002^\002\t\t\021\"\001\002`\006A1-\0318FcV\fG\016\006\003\002b\006\035\bc\001\005\002d&\031\021Q\035\002\003\017\t{w\016\\3b]\"I\021\021^An\003\003\005\rAF\001\004q\022\n\004\"CAw\001\005\005I\021IAx\003!A\027m\0355D_\022,GCAAy!\rA\0211_\005\004\003k\024!aA%oi\"I\021\021 \001\002\002\023\005\0231`\001\007KF,\030\r\\:\025\t\005\005\030Q \005\n\003S\f90!AA\002Y9\021B!\001\003\003\003E\tAa\001\002\rQ+\b\017\\38!\rA!Q\001\004\t\003\t\t\t\021#\001\003\bM!!QA\004/\021\035)&Q\001C\001\005\027!\"Aa\001\t\021\001\024)!!A\005F\005D!B!\005\003\006\005\005I\021\021B\n\003\025\t\007\017\0357z+A\021)Ba\007\003 \t\r\"q\005B\026\005_\021\031\004\006\t\003\030\tU\"q\007B\035\005w\021iDa\020\003BA\001\002\002\001B\r\005;\021\tC!\n\003*\t5\"\021\007\t\004\037\tmAAB\t\003\020\t\007!\003E\002\020\005?!aa\007B\b\005\004\021\002cA\b\003$\0211aDa\004C\002I\0012a\004B\024\t\031\t#q\002b\001%A\031qBa\013\005\r\021\022yA1\001\023!\ry!q\006\003\007O\t=!\031\001\n\021\007=\021\031\004\002\004+\005\037\021\rA\005\005\be\t=\001\031\001B\r\021\0359$q\002a\001\005;Aq\001\020B\b\001\004\021\t\003C\004B\005\037\001\rA!\n\t\017\031\023y\0011\001\003*!91Ja\004A\002\t5\002b\002)\003\020\001\007!\021\007\005\013\005\013\022)!!A\005\002\n\035\023aB;oCB\004H._\013\021\005\023\022)F!\027\003^\t\005$Q\rB5\005[\"BAa\023\003pA)\001B!\024\003R%\031!q\n\002\003\r=\003H/[8o!AA\001Aa\025\003X\tm#q\fB2\005O\022Y\007E\002\020\005+\"a!\005B\"\005\004\021\002cA\b\003Z\02111Da\021C\002I\0012a\004B/\t\031q\"1\tb\001%A\031qB!\031\005\r\005\022\031E1\001\023!\ry!Q\r\003\007I\t\r#\031\001\n\021\007=\021I\007\002\004(\005\007\022\rA\005\t\004\037\t5DA\002\026\003D\t\007!\003\003\006\003r\t\r\023\021!a\001\005#\n1\001\037\0231\021)\021)H!\002\002\002\023%!qO\001\fe\026\fGMU3t_24X\r\006\002\003zA\0311Ma\037\n\007\tuDM\001\004PE*,7\r\036")
/*    */ public class Tuple7<T1, T2, T3, T4, T5, T6, T7> implements Product7<T1, T2, T3, T4, T5, T6, T7>, Product, Serializable {
/*    */   private final T1 _1;
/*    */   
/*    */   private final T2 _2;
/*    */   
/*    */   private final T3 _3;
/*    */   
/*    */   private final T4 _4;
/*    */   
/*    */   private final T5 _5;
/*    */   
/*    */   private final T6 _6;
/*    */   
/*    */   private final T7 _7;
/*    */   
/*    */   public int productArity() {
/* 24 */     return Product7$class.productArity(this);
/*    */   }
/*    */   
/*    */   public Object productElement(int n) throws IndexOutOfBoundsException {
/* 24 */     return Product7$class.productElement(this, n);
/*    */   }
/*    */   
/*    */   public T1 _1() {
/* 24 */     return this._1;
/*    */   }
/*    */   
/*    */   public T2 _2() {
/* 24 */     return this._2;
/*    */   }
/*    */   
/*    */   public T3 _3() {
/* 24 */     return this._3;
/*    */   }
/*    */   
/*    */   public T4 _4() {
/* 24 */     return this._4;
/*    */   }
/*    */   
/*    */   public T5 _5() {
/* 24 */     return this._5;
/*    */   }
/*    */   
/*    */   public T6 _6() {
/* 24 */     return this._6;
/*    */   }
/*    */   
/*    */   public T7 _7() {
/* 24 */     return this._7;
/*    */   }
/*    */   
/*    */   public <T1, T2, T3, T4, T5, T6, T7> Tuple7<T1, T2, T3, T4, T5, T6, T7> copy(Object _1, Object _2, Object _3, Object _4, Object _5, Object _6, Object _7) {
/* 24 */     return new Tuple7((T1)_1, (T2)_2, (T3)_3, (T4)_4, (T5)_5, (T6)_6, (T7)_7);
/*    */   }
/*    */   
/*    */   public <T1, T2, T3, T4, T5, T6, T7> T1 copy$default$1() {
/* 24 */     return _1();
/*    */   }
/*    */   
/*    */   public <T1, T2, T3, T4, T5, T6, T7> T2 copy$default$2() {
/* 24 */     return _2();
/*    */   }
/*    */   
/*    */   public <T1, T2, T3, T4, T5, T6, T7> T3 copy$default$3() {
/* 24 */     return _3();
/*    */   }
/*    */   
/*    */   public <T1, T2, T3, T4, T5, T6, T7> T4 copy$default$4() {
/* 24 */     return _4();
/*    */   }
/*    */   
/*    */   public <T1, T2, T3, T4, T5, T6, T7> T5 copy$default$5() {
/* 24 */     return _5();
/*    */   }
/*    */   
/*    */   public <T1, T2, T3, T4, T5, T6, T7> T6 copy$default$6() {
/* 24 */     return _6();
/*    */   }
/*    */   
/*    */   public <T1, T2, T3, T4, T5, T6, T7> T7 copy$default$7() {
/* 24 */     return _7();
/*    */   }
/*    */   
/*    */   public String productPrefix() {
/* 24 */     return "Tuple7";
/*    */   }
/*    */   
/*    */   public Iterator<Object> productIterator() {
/* 24 */     return ScalaRunTime$.MODULE$.typedProductIterator(this);
/*    */   }
/*    */   
/*    */   public boolean canEqual(Object x$1) {
/* 24 */     return x$1 instanceof Tuple7;
/*    */   }
/*    */   
/*    */   public int hashCode() {
/* 24 */     return ScalaRunTime$.MODULE$._hashCode(this);
/*    */   }
/*    */   
/*    */   public boolean equals(Object x$1) {
/*    */     // Byte code:
/*    */     //   0: aload_0
/*    */     //   1: aload_1
/*    */     //   2: if_acmpeq -> 627
/*    */     //   5: aload_1
/*    */     //   6: instanceof scala/Tuple7
/*    */     //   9: ifeq -> 17
/*    */     //   12: iconst_1
/*    */     //   13: istore_2
/*    */     //   14: goto -> 19
/*    */     //   17: iconst_0
/*    */     //   18: istore_2
/*    */     //   19: iload_2
/*    */     //   20: ifeq -> 631
/*    */     //   23: aload_1
/*    */     //   24: checkcast scala/Tuple7
/*    */     //   27: astore #17
/*    */     //   29: aload_0
/*    */     //   30: invokevirtual _1 : ()Ljava/lang/Object;
/*    */     //   33: aload #17
/*    */     //   35: invokevirtual _1 : ()Ljava/lang/Object;
/*    */     //   38: astore #4
/*    */     //   40: dup
/*    */     //   41: astore_3
/*    */     //   42: aload #4
/*    */     //   44: if_acmpne -> 51
/*    */     //   47: iconst_1
/*    */     //   48: goto -> 103
/*    */     //   51: aload_3
/*    */     //   52: ifnonnull -> 59
/*    */     //   55: iconst_0
/*    */     //   56: goto -> 103
/*    */     //   59: aload_3
/*    */     //   60: instanceof java/lang/Number
/*    */     //   63: ifeq -> 78
/*    */     //   66: aload_3
/*    */     //   67: checkcast java/lang/Number
/*    */     //   70: aload #4
/*    */     //   72: invokestatic equalsNumObject : (Ljava/lang/Number;Ljava/lang/Object;)Z
/*    */     //   75: goto -> 103
/*    */     //   78: aload_3
/*    */     //   79: instanceof java/lang/Character
/*    */     //   82: ifeq -> 97
/*    */     //   85: aload_3
/*    */     //   86: checkcast java/lang/Character
/*    */     //   89: aload #4
/*    */     //   91: invokestatic equalsCharObject : (Ljava/lang/Character;Ljava/lang/Object;)Z
/*    */     //   94: goto -> 103
/*    */     //   97: aload_3
/*    */     //   98: aload #4
/*    */     //   100: invokevirtual equals : (Ljava/lang/Object;)Z
/*    */     //   103: ifeq -> 623
/*    */     //   106: aload_0
/*    */     //   107: invokevirtual _2 : ()Ljava/lang/Object;
/*    */     //   110: aload #17
/*    */     //   112: invokevirtual _2 : ()Ljava/lang/Object;
/*    */     //   115: astore #6
/*    */     //   117: dup
/*    */     //   118: astore #5
/*    */     //   120: aload #6
/*    */     //   122: if_acmpne -> 129
/*    */     //   125: iconst_1
/*    */     //   126: goto -> 187
/*    */     //   129: aload #5
/*    */     //   131: ifnonnull -> 138
/*    */     //   134: iconst_0
/*    */     //   135: goto -> 187
/*    */     //   138: aload #5
/*    */     //   140: instanceof java/lang/Number
/*    */     //   143: ifeq -> 159
/*    */     //   146: aload #5
/*    */     //   148: checkcast java/lang/Number
/*    */     //   151: aload #6
/*    */     //   153: invokestatic equalsNumObject : (Ljava/lang/Number;Ljava/lang/Object;)Z
/*    */     //   156: goto -> 187
/*    */     //   159: aload #5
/*    */     //   161: instanceof java/lang/Character
/*    */     //   164: ifeq -> 180
/*    */     //   167: aload #5
/*    */     //   169: checkcast java/lang/Character
/*    */     //   172: aload #6
/*    */     //   174: invokestatic equalsCharObject : (Ljava/lang/Character;Ljava/lang/Object;)Z
/*    */     //   177: goto -> 187
/*    */     //   180: aload #5
/*    */     //   182: aload #6
/*    */     //   184: invokevirtual equals : (Ljava/lang/Object;)Z
/*    */     //   187: ifeq -> 623
/*    */     //   190: aload_0
/*    */     //   191: invokevirtual _3 : ()Ljava/lang/Object;
/*    */     //   194: aload #17
/*    */     //   196: invokevirtual _3 : ()Ljava/lang/Object;
/*    */     //   199: astore #8
/*    */     //   201: dup
/*    */     //   202: astore #7
/*    */     //   204: aload #8
/*    */     //   206: if_acmpne -> 213
/*    */     //   209: iconst_1
/*    */     //   210: goto -> 271
/*    */     //   213: aload #7
/*    */     //   215: ifnonnull -> 222
/*    */     //   218: iconst_0
/*    */     //   219: goto -> 271
/*    */     //   222: aload #7
/*    */     //   224: instanceof java/lang/Number
/*    */     //   227: ifeq -> 243
/*    */     //   230: aload #7
/*    */     //   232: checkcast java/lang/Number
/*    */     //   235: aload #8
/*    */     //   237: invokestatic equalsNumObject : (Ljava/lang/Number;Ljava/lang/Object;)Z
/*    */     //   240: goto -> 271
/*    */     //   243: aload #7
/*    */     //   245: instanceof java/lang/Character
/*    */     //   248: ifeq -> 264
/*    */     //   251: aload #7
/*    */     //   253: checkcast java/lang/Character
/*    */     //   256: aload #8
/*    */     //   258: invokestatic equalsCharObject : (Ljava/lang/Character;Ljava/lang/Object;)Z
/*    */     //   261: goto -> 271
/*    */     //   264: aload #7
/*    */     //   266: aload #8
/*    */     //   268: invokevirtual equals : (Ljava/lang/Object;)Z
/*    */     //   271: ifeq -> 623
/*    */     //   274: aload_0
/*    */     //   275: invokevirtual _4 : ()Ljava/lang/Object;
/*    */     //   278: aload #17
/*    */     //   280: invokevirtual _4 : ()Ljava/lang/Object;
/*    */     //   283: astore #10
/*    */     //   285: dup
/*    */     //   286: astore #9
/*    */     //   288: aload #10
/*    */     //   290: if_acmpne -> 297
/*    */     //   293: iconst_1
/*    */     //   294: goto -> 355
/*    */     //   297: aload #9
/*    */     //   299: ifnonnull -> 306
/*    */     //   302: iconst_0
/*    */     //   303: goto -> 355
/*    */     //   306: aload #9
/*    */     //   308: instanceof java/lang/Number
/*    */     //   311: ifeq -> 327
/*    */     //   314: aload #9
/*    */     //   316: checkcast java/lang/Number
/*    */     //   319: aload #10
/*    */     //   321: invokestatic equalsNumObject : (Ljava/lang/Number;Ljava/lang/Object;)Z
/*    */     //   324: goto -> 355
/*    */     //   327: aload #9
/*    */     //   329: instanceof java/lang/Character
/*    */     //   332: ifeq -> 348
/*    */     //   335: aload #9
/*    */     //   337: checkcast java/lang/Character
/*    */     //   340: aload #10
/*    */     //   342: invokestatic equalsCharObject : (Ljava/lang/Character;Ljava/lang/Object;)Z
/*    */     //   345: goto -> 355
/*    */     //   348: aload #9
/*    */     //   350: aload #10
/*    */     //   352: invokevirtual equals : (Ljava/lang/Object;)Z
/*    */     //   355: ifeq -> 623
/*    */     //   358: aload_0
/*    */     //   359: invokevirtual _5 : ()Ljava/lang/Object;
/*    */     //   362: aload #17
/*    */     //   364: invokevirtual _5 : ()Ljava/lang/Object;
/*    */     //   367: astore #12
/*    */     //   369: dup
/*    */     //   370: astore #11
/*    */     //   372: aload #12
/*    */     //   374: if_acmpne -> 381
/*    */     //   377: iconst_1
/*    */     //   378: goto -> 439
/*    */     //   381: aload #11
/*    */     //   383: ifnonnull -> 390
/*    */     //   386: iconst_0
/*    */     //   387: goto -> 439
/*    */     //   390: aload #11
/*    */     //   392: instanceof java/lang/Number
/*    */     //   395: ifeq -> 411
/*    */     //   398: aload #11
/*    */     //   400: checkcast java/lang/Number
/*    */     //   403: aload #12
/*    */     //   405: invokestatic equalsNumObject : (Ljava/lang/Number;Ljava/lang/Object;)Z
/*    */     //   408: goto -> 439
/*    */     //   411: aload #11
/*    */     //   413: instanceof java/lang/Character
/*    */     //   416: ifeq -> 432
/*    */     //   419: aload #11
/*    */     //   421: checkcast java/lang/Character
/*    */     //   424: aload #12
/*    */     //   426: invokestatic equalsCharObject : (Ljava/lang/Character;Ljava/lang/Object;)Z
/*    */     //   429: goto -> 439
/*    */     //   432: aload #11
/*    */     //   434: aload #12
/*    */     //   436: invokevirtual equals : (Ljava/lang/Object;)Z
/*    */     //   439: ifeq -> 623
/*    */     //   442: aload_0
/*    */     //   443: invokevirtual _6 : ()Ljava/lang/Object;
/*    */     //   446: aload #17
/*    */     //   448: invokevirtual _6 : ()Ljava/lang/Object;
/*    */     //   451: astore #14
/*    */     //   453: dup
/*    */     //   454: astore #13
/*    */     //   456: aload #14
/*    */     //   458: if_acmpne -> 465
/*    */     //   461: iconst_1
/*    */     //   462: goto -> 523
/*    */     //   465: aload #13
/*    */     //   467: ifnonnull -> 474
/*    */     //   470: iconst_0
/*    */     //   471: goto -> 523
/*    */     //   474: aload #13
/*    */     //   476: instanceof java/lang/Number
/*    */     //   479: ifeq -> 495
/*    */     //   482: aload #13
/*    */     //   484: checkcast java/lang/Number
/*    */     //   487: aload #14
/*    */     //   489: invokestatic equalsNumObject : (Ljava/lang/Number;Ljava/lang/Object;)Z
/*    */     //   492: goto -> 523
/*    */     //   495: aload #13
/*    */     //   497: instanceof java/lang/Character
/*    */     //   500: ifeq -> 516
/*    */     //   503: aload #13
/*    */     //   505: checkcast java/lang/Character
/*    */     //   508: aload #14
/*    */     //   510: invokestatic equalsCharObject : (Ljava/lang/Character;Ljava/lang/Object;)Z
/*    */     //   513: goto -> 523
/*    */     //   516: aload #13
/*    */     //   518: aload #14
/*    */     //   520: invokevirtual equals : (Ljava/lang/Object;)Z
/*    */     //   523: ifeq -> 623
/*    */     //   526: aload_0
/*    */     //   527: invokevirtual _7 : ()Ljava/lang/Object;
/*    */     //   530: aload #17
/*    */     //   532: invokevirtual _7 : ()Ljava/lang/Object;
/*    */     //   535: astore #16
/*    */     //   537: dup
/*    */     //   538: astore #15
/*    */     //   540: aload #16
/*    */     //   542: if_acmpne -> 549
/*    */     //   545: iconst_1
/*    */     //   546: goto -> 607
/*    */     //   549: aload #15
/*    */     //   551: ifnonnull -> 558
/*    */     //   554: iconst_0
/*    */     //   555: goto -> 607
/*    */     //   558: aload #15
/*    */     //   560: instanceof java/lang/Number
/*    */     //   563: ifeq -> 579
/*    */     //   566: aload #15
/*    */     //   568: checkcast java/lang/Number
/*    */     //   571: aload #16
/*    */     //   573: invokestatic equalsNumObject : (Ljava/lang/Number;Ljava/lang/Object;)Z
/*    */     //   576: goto -> 607
/*    */     //   579: aload #15
/*    */     //   581: instanceof java/lang/Character
/*    */     //   584: ifeq -> 600
/*    */     //   587: aload #15
/*    */     //   589: checkcast java/lang/Character
/*    */     //   592: aload #16
/*    */     //   594: invokestatic equalsCharObject : (Ljava/lang/Character;Ljava/lang/Object;)Z
/*    */     //   597: goto -> 607
/*    */     //   600: aload #15
/*    */     //   602: aload #16
/*    */     //   604: invokevirtual equals : (Ljava/lang/Object;)Z
/*    */     //   607: ifeq -> 623
/*    */     //   610: aload #17
/*    */     //   612: aload_0
/*    */     //   613: invokevirtual canEqual : (Ljava/lang/Object;)Z
/*    */     //   616: ifeq -> 623
/*    */     //   619: iconst_1
/*    */     //   620: goto -> 624
/*    */     //   623: iconst_0
/*    */     //   624: ifeq -> 631
/*    */     //   627: iconst_1
/*    */     //   628: goto -> 632
/*    */     //   631: iconst_0
/*    */     //   632: ireturn
/*    */     // Line number table:
/*    */     //   Java source line number -> byte code offset
/*    */     //   #24	-> 0
/*    */     //   #236	-> 12
/*    */     //   #24	-> 19
/*    */     // Local variable table:
/*    */     //   start	length	slot	name	descriptor
/*    */     //   0	633	0	this	Lscala/Tuple7;
/*    */     //   0	633	1	x$1	Ljava/lang/Object;
/*    */   }
/*    */   
/*    */   public Tuple7(Object _1, Object _2, Object _3, Object _4, Object _5, Object _6, Object _7) {
/* 24 */     Product$class.$init$(this);
/* 24 */     Product7$class.$init$(this);
/*    */   }
/*    */   
/*    */   public String toString() {
/* 27 */     return (new StringBuilder()).append("(").append(_1()).append(",").append(_2()).append(",").append(_3()).append(",").append(_4()).append(",").append(_5()).append(",").append(_6()).append(",").append(_7()).append(")").toString();
/*    */   }
/*    */ }


/* Location:              D:\#source-code\TheFlightSims\TFSLibrary\World2Xplane\World2XPlane.jar!\scala\Tuple7.class
 * Java compiler version: 6 (50.0)
 * JD-Core Version:       1.1.3
 */