/*    */ package scala;
/*    */ 
/*    */ import scala.collection.Iterator;
/*    */ import scala.collection.mutable.StringBuilder;
/*    */ import scala.reflect.ScalaSignature;
/*    */ import scala.runtime.ScalaRunTime$;
/*    */ 
/*    */ @ScalaSignature(bytes = "\006\001\035]h\001B\001\003\001\026\021q\001V;qY\026\024\024GC\001\004\003\025\0318-\0317b\007\001)bC\002\t\033;\001\032c%\013\0270eUB4HP!E\017*k\005kU\n\006\001\035YQ\013\027\t\003\021%i\021AA\005\003\025\t\021a!\0218z%\0264\007c\006\005\r\035earDI\023)W9\nDg\016\036>\001\0163\025\nT(S\023\ti!AA\005Qe>$Wo\031;3cA\021q\002\005\007\001\t\031\t\002\001\"b\001%\t\021A+M\t\003'Y\001\"\001\003\013\n\005U\021!a\002(pi\"Lgn\032\t\003\021]I!\001\007\002\003\007\005s\027\020\005\002\0205\02111\004\001CC\002I\021!\001\026\032\021\005=iBA\002\020\001\t\013\007!C\001\002UgA\021q\002\t\003\007C\001!)\031\001\n\003\005Q#\004CA\b$\t\031!\003\001\"b\001%\t\021A+\016\t\003\037\031\"aa\n\001\005\006\004\021\"A\001+7!\ty\021\006\002\004+\001\021\025\rA\005\002\003)^\002\"a\004\027\005\r5\002AQ1\001\023\005\t!\006\b\005\002\020_\0211\001\007\001CC\002I\021!\001V\035\021\005=\021DAB\032\001\t\013\007!CA\002UcA\002\"aD\033\005\rY\002AQ1\001\023\005\r!\026'\r\t\003\037a\"a!\017\001\005\006\004\021\"a\001+2eA\021qb\017\003\007y\001!)\031\001\n\003\007Q\0134\007\005\002\020}\0211q\b\001CC\002I\0211\001V\0315!\ty\021\t\002\004C\001\021\025\rA\005\002\004)F*\004CA\bE\t\031)\005\001\"b\001%\t\031A+\r\034\021\005=9EA\002%\001\t\013\007!CA\002Uc]\002\"a\004&\005\r-\003AQ1\001\023\005\r!\026\007\017\t\003\0375#aA\024\001\005\006\004\021\"a\001+2sA\021q\002\025\003\007#\002!)\031\001\n\003\007Q\023\004\007\005\002\020'\0221A\013\001CC\002I\0211\001\026\0322!\tAa+\003\002X\005\t9\001K]8ek\016$\bC\001\005Z\023\tQ&A\001\007TKJL\027\r\\5{C\ndW\r\003\005]\001\tU\r\021\"\001^\003\ty\026'F\001\017\021!y\006A!E!\002\023q\021aA02A!A\021\r\001BK\002\023\005!-\001\002`eU\t\021\004\003\005e\001\tE\t\025!\003\032\003\ry&\007\t\005\tM\002\021)\032!C\001O\006\021qlM\013\0029!A\021\016\001B\tB\003%A$A\002`g\001B\001b\033\001\003\026\004%\t\001\\\001\003?R*\022a\b\005\t]\002\021\t\022)A\005?\005\031q\f\016\021\t\021A\004!Q3A\005\002E\f!aX\033\026\003\tB\001b\035\001\003\022\003\006IAI\001\004?V\002\003\002C;\001\005+\007I\021\001<\002\005}3T#A\023\t\021a\004!\021#Q\001\n\025\n1a\030\034!\021!Q\bA!f\001\n\003Y\030AA08+\005A\003\002C?\001\005#\005\013\021\002\025\002\007};\004\005C\005\000\001\tU\r\021\"\001\002\002\005\021q\fO\013\002W!I\021Q\001\001\003\022\003\006IaK\001\004?b\002\003BCA\005\001\tU\r\021\"\001\002\f\005\021q,O\013\002]!I\021q\002\001\003\022\003\006IAL\001\004?f\002\003BCA\n\001\tU\r\021\"\001\002\026\005\031q,\r\031\026\003EB\021\"!\007\001\005#\005\013\021B\031\002\t}\013\004\007\t\005\013\003;\001!Q3A\005\002\005}\021aA02cU\tA\007C\005\002$\001\021\t\022)A\005i\005!q,M\031!\021)\t9\003\001BK\002\023\005\021\021F\001\004?F\022T#A\034\t\023\0055\002A!E!\002\0239\024\001B02e\001B!\"!\r\001\005+\007I\021AA\032\003\ry\026gM\013\002u!I\021q\007\001\003\022\003\006IAO\001\005?F\032\004\005\003\006\002<\001\021)\032!C\001\003{\t1aX\0315+\005i\004\"CA!\001\tE\t\025!\003>\003\021y\026\007\016\021\t\025\005\025\003A!f\001\n\003\t9%A\002`cU*\022\001\021\005\n\003\027\002!\021#Q\001\n\001\013AaX\0316A!Q\021q\n\001\003\026\004%\t!!\025\002\007}\013d'F\001D\021%\t)\006\001B\tB\003%1)\001\003`cY\002\003BCA-\001\tU\r\021\"\001\002\\\005\031q,M\034\026\003\031C\021\"a\030\001\005#\005\013\021\002$\002\t}\013t\007\t\005\013\003G\002!Q3A\005\002\005\025\024aA02qU\t\021\nC\005\002j\001\021\t\022)A\005\023\006!q,\r\035!\021)\ti\007\001BK\002\023\005\021qN\001\004?FJT#\001'\t\023\005M\004A!E!\002\023a\025\001B02s\001B!\"a\036\001\005+\007I\021AA=\003\ry&\007M\013\002\037\"I\021Q\020\001\003\022\003\006IaT\001\005?J\002\004\005\003\006\002\002\002\021)\032!C\001\003\007\0131a\030\0322+\005\021\006\"CAD\001\tE\t\025!\003S\003\021y&'\r\021\t\017\005-\005\001\"\001\002\016\0061A(\0338jiz\"B&a$\002\022\006M\025QSAL\0033\013Y*!(\002 \006\005\0261UAS\003O\013I+a+\002.\006=\026\021WAZ\003k\0139,!/\021/!\001a\"\007\017 E\025B3FL\0315oij\004i\021$J\031>\023\006B\002/\002\n\002\007a\002\003\004b\003\023\003\r!\007\005\007M\006%\005\031\001\017\t\r-\fI\t1\001 \021\031\001\030\021\022a\001E!1Q/!#A\002\025BaA_AE\001\004A\003BB@\002\n\002\0071\006C\004\002\n\005%\005\031\001\030\t\017\005M\021\021\022a\001c!9\021QDAE\001\004!\004bBA\024\003\023\003\ra\016\005\b\003c\tI\t1\001;\021\035\tY$!#A\002uBq!!\022\002\n\002\007\001\tC\004\002P\005%\005\031A\"\t\017\005e\023\021\022a\001\r\"9\0211MAE\001\004I\005bBA7\003\023\003\r\001\024\005\b\003o\nI\t1\001P\021\035\t\t)!#A\002ICq!!0\001\t\003\ny,\001\005u_N#(/\0338h)\t\t\t\r\005\003\002D\0065WBAAc\025\021\t9-!3\002\t1\fgn\032\006\003\003\027\fAA[1wC&!\021qZAc\005\031\031FO]5oO\"I\0211\033\001\002\002\023\005\021Q[\001\005G>\004\0300\006\027\002X\006u\027\021]As\003S\fi/!=\002v\006e\030Q B\001\005\013\021IA!\004\003\022\tU!\021\004B\017\005C\021)C!\013\003.Qa\023\021\034B\030\005c\021\031D!\016\0038\te\"1\bB\037\005\021\tEa\021\003F\t\035#\021\nB&\005\033\022yE!\025\003T\tU#q\013\t-\021\001\tY.a8\002d\006\035\0301^Ax\003g\f90a?\002\000\n\r!q\001B\006\005\037\021\031Ba\006\003\034\t}!1\005B\024\005W\0012aDAo\t\031\t\022\021\033b\001%A\031q\"!9\005\rm\t\tN1\001\023!\ry\021Q\035\003\007=\005E'\031\001\n\021\007=\tI\017\002\004\"\003#\024\rA\005\t\004\037\0055HA\002\023\002R\n\007!\003E\002\020\003c$aaJAi\005\004\021\002cA\b\002v\0221!&!5C\002I\0012aDA}\t\031i\023\021\033b\001%A\031q\"!@\005\rA\n\tN1\001\023!\ry!\021\001\003\007g\005E'\031\001\n\021\007=\021)\001\002\0047\003#\024\rA\005\t\004\037\t%AAB\035\002R\n\007!\003E\002\020\005\033!a\001PAi\005\004\021\002cA\b\003\022\0211q(!5C\002I\0012a\004B\013\t\031\021\025\021\033b\001%A\031qB!\007\005\r\025\013\tN1\001\023!\ry!Q\004\003\007\021\006E'\031\001\n\021\007=\021\t\003\002\004L\003#\024\rA\005\t\004\037\t\025BA\002(\002R\n\007!\003E\002\020\005S!a!UAi\005\004\021\002cA\b\003.\0211A+!5C\002IA\021\002XAi!\003\005\r!a7\t\023\005\f\t\016%AA\002\005}\007\"\0034\002RB\005\t\031AAr\021%Y\027\021\033I\001\002\004\t9\017C\005q\003#\004\n\0211\001\002l\"IQ/!5\021\002\003\007\021q\036\005\nu\006E\007\023!a\001\003gD\021b`Ai!\003\005\r!a>\t\025\005%\021\021\033I\001\002\004\tY\020\003\006\002\024\005E\007\023!a\001\003D!\"!\b\002RB\005\t\031\001B\002\021)\t9#!5\021\002\003\007!q\001\005\013\003c\t\t\016%AA\002\t-\001BCA\036\003#\004\n\0211\001\003\020!Q\021QIAi!\003\005\rAa\005\t\025\005=\023\021\033I\001\002\004\0219\002\003\006\002Z\005E\007\023!a\001\0057A!\"a\031\002RB\005\t\031\001B\020\021)\ti'!5\021\002\003\007!1\005\005\013\003o\n\t\016%AA\002\t\035\002BCAA\003#\004\n\0211\001\003,!I!1\f\001\022\002\023\005!QL\001\017G>\004\030\020\n3fM\006,H\016\036\0232+1\022yF!\036\003x\te$1\020B?\005\022\tIa!\003\006\n\035%\021\022BF\005\033\023yI!%\003\024\nU%q\023BM\0057\023i*\006\002\003b)\032aBa\031,\005\t\025\004\003\002B4\005cj!A!\033\013\t\t-$QN\001\nk:\034\007.Z2lK\022T1Aa\034\003\003)\tgN\\8uCRLwN\\\005\005\005g\022IGA\tv]\016DWmY6fIZ\013'/[1oG\026$a!\005B-\005\004\021BAB\016\003Z\t\007!\003\002\004\037\0053\022\rA\005\003\007C\te#\031\001\n\005\r\021\022IF1\001\023\t\0319#\021\fb\001%\0211!F!\027C\002I!a!\fB-\005\004\021BA\002\031\003Z\t\007!\003\002\0044\0053\022\rA\005\003\007m\te#\031\001\n\005\re\022IF1\001\023\t\031a$\021\fb\001%\0211qH!\027C\002I!aA\021B-\005\004\021BAB#\003Z\t\007!\003\002\004I\0053\022\rA\005\003\007\027\ne#\031\001\n\005\r9\023IF1\001\023\t\031\t&\021\fb\001%\0211AK!\027C\002IA\021B!)\001#\003%\tAa)\002\035\r|\007/\037\023eK\032\fW\017\034;%eUa#Q\025BU\005W\023iKa,\0032\nM&Q\027B\\\005s\023YL!0\003@\n\005'1\031Bc\005\017\024IMa3\003N\n='\021[\013\003\005OS3!\007B2\t\031\t\"q\024b\001%\02111Da(C\002I!aA\bBP\005\004\021BAB\021\003 \n\007!\003\002\004%\005?\023\rA\005\003\007O\t}%\031\001\n\005\r)\022yJ1\001\023\t\031i#q\024b\001%\0211\001Ga(C\002I!aa\rBP\005\004\021BA\002\034\003 \n\007!\003\002\004:\005?\023\rA\005\003\007y\t}%\031\001\n\005\r}\022yJ1\001\023\t\031\021%q\024b\001%\0211QIa(C\002I!a\001\023BP\005\004\021BAB&\003 \n\007!\003\002\004O\005?\023\rA\005\003\007#\n}%\031\001\n\005\rQ\023yJ1\001\023\021%\021)\016AI\001\n\003\0219.\001\bd_BLH\005Z3gCVdG\017J\032\026Y\te'Q\034Bp\005C\024\031O!:\003h\n%(1\036Bw\005_\024\tPa=\003v\n](\021 B~\005{\024yp!\001\004\004\r\025QC\001BnU\ra\"1\r\003\007#\tM'\031\001\n\005\rm\021\031N1\001\023\t\031q\"1\033b\001%\0211\021Ea5C\002I!a\001\nBj\005\004\021BAB\024\003T\n\007!\003\002\004+\005'\024\rA\005\003\007[\tM'\031\001\n\005\rA\022\031N1\001\023\t\031\031$1\033b\001%\0211aGa5C\002I!a!\017Bj\005\004\021BA\002\037\003T\n\007!\003\002\004@\005'\024\rA\005\003\007\005\nM'\031\001\n\005\r\025\023\031N1\001\023\t\031A%1\033b\001%\02111Ja5C\002I!aA\024Bj\005\004\021BAB)\003T\n\007!\003\002\004U\005'\024\rA\005\005\n\007\023\001\021\023!C\001\007\027\tabY8qs\022\"WMZ1vYR$C'\006\027\004\016\rE11CB\013\007/\031Iba\007\004\036\r}1\021EB\022\007K\0319c!\013\004,\r52qFB\031\007g\031)da\016\004:U\0211q\002\026\004?\t\rDAB\t\004\b\t\007!\003\002\004\034\007\017\021\rA\005\003\007=\r\035!\031\001\n\005\r\005\0329A1\001\023\t\031!3q\001b\001%\0211qea\002C\002I!aAKB\004\005\004\021BAB\027\004\b\t\007!\003\002\0041\007\017\021\rA\005\003\007g\r\035!\031\001\n\005\rY\0329A1\001\023\t\031I4q\001b\001%\0211Aha\002C\002I!aaPB\004\005\004\021BA\002\"\004\b\t\007!\003\002\004F\007\017\021\rA\005\003\007\021\016\035!\031\001\n\005\r-\0339A1\001\023\t\031q5q\001b\001%\0211\021ka\002C\002I!a\001VB\004\005\004\021\002\"CB\037\001E\005I\021AB \0039\031w\016]=%I\0264\027-\0367uIU*Bf!\021\004F\r\0353\021JB&\007\033\032ye!\025\004T\rU3qKB-\0077\032ifa\030\004b\r\r4QMB4\007S\032Yg!\034\026\005\r\r#f\001\022\003d\0211\021ca\017C\002I!aaGB\036\005\004\021BA\002\020\004<\t\007!\003\002\004\"\007w\021\rA\005\003\007I\rm\"\031\001\n\005\r\035\032YD1\001\023\t\031Q31\bb\001%\0211Qfa\017C\002I!a\001MB\036\005\004\021BAB\032\004<\t\007!\003\002\0047\007w\021\rA\005\003\007s\rm\"\031\001\n\005\rq\032YD1\001\023\t\031y41\bb\001%\0211!ia\017C\002I!a!RB\036\005\004\021BA\002%\004<\t\007!\003\002\004L\007w\021\rA\005\003\007\035\016m\"\031\001\n\005\rE\033YD1\001\023\t\031!61\bb\001%!I1\021\017\001\022\002\023\00511O\001\017G>\004\030\020\n3fM\006,H\016\036\0237+1\032)h!\037\004|\ru4qPBA\007\007\033)ia\"\004\n\016-5QRBH\007#\033\031j!&\004\030\016e51TBO\007?\033\t+\006\002\004x)\032QEa\031\005\rE\031yG1\001\023\t\031Y2q\016b\001%\0211ada\034C\002I!a!IB8\005\004\021BA\002\023\004p\t\007!\003\002\004(\007_\022\rA\005\003\007U\r=$\031\001\n\005\r5\032yG1\001\023\t\031\0014q\016b\001%\02111ga\034C\002I!aANB8\005\004\021BAB\035\004p\t\007!\003\002\004=\007_\022\rA\005\003\007\r=$\031\001\n\005\r\t\033yG1\001\023\t\031)5q\016b\001%\0211\001ja\034C\002I!aaSB8\005\004\021BA\002(\004p\t\007!\003\002\004R\007_\022\rA\005\003\007)\016=$\031\001\n\t\023\r\025\006!%A\005\002\r\035\026AD2paf$C-\0324bk2$HeN\013-\007S\033ika,\0042\016M6QWB\\\007s\033Yl!0\004@\016\00571YBc\007\017\034Ima3\004N\016=7\021[Bj\007+,\"aa++\007!\022\031\007\002\004\022\007G\023\rA\005\003\0077\r\r&\031\001\n\005\ry\031\031K1\001\023\t\031\t31\025b\001%\0211Aea)C\002I!aaJBR\005\004\021BA\002\026\004$\n\007!\003\002\004.\007G\023\rA\005\003\007a\r\r&\031\001\n\005\rM\032\031K1\001\023\t\031141\025b\001%\0211\021ha)C\002I!a\001PBR\005\004\021BAB \004$\n\007!\003\002\004C\007G\023\rA\005\003\007\013\016\r&\031\001\n\005\r!\033\031K1\001\023\t\031Y51\025b\001%\0211aja)C\002I!a!UBR\005\004\021BA\002+\004$\n\007!\003C\005\004Z\002\t\n\021\"\001\004\\\006q1m\0349zI\021,g-Y;mi\022BT\003LBo\007C\034\031o!:\004h\016%81^Bw\007_\034\tpa=\004v\016]8\021`B~\007{\034y\020\"\001\005\004\021\025Aq\001C\005+\t\031yNK\002,\005G\"a!EBl\005\004\021BAB\016\004X\n\007!\003\002\004\037\007/\024\rA\005\003\007C\r]'\031\001\n\005\r\021\0329N1\001\023\t\03193q\033b\001%\0211!fa6C\002I!a!LBl\005\004\021BA\002\031\004X\n\007!\003\002\0044\007/\024\rA\005\003\007m\r]'\031\001\n\005\re\0329N1\001\023\t\031a4q\033b\001%\0211qha6C\002I!aAQBl\005\004\021BAB#\004X\n\007!\003\002\004I\007/\024\rA\005\003\007\027\016]'\031\001\n\005\r9\0339N1\001\023\t\031\t6q\033b\001%\0211Aka6C\002IA\021\002\"\004\001#\003%\t\001b\004\002\035\r|\007/\037\023eK\032\fW\017\034;%sUaC\021\003C\013\t/!I\002b\007\005\036\021}A\021\005C\022\tK!9\003\"\013\005,\0215Bq\006C\031\tg!)\004b\016\005:\021mBQH\013\003\t'Q3A\fB2\t\031\tB1\002b\001%\02111\004b\003C\002I!aA\bC\006\005\004\021BAB\021\005\f\t\007!\003\002\004%\t\027\021\rA\005\003\007O\021-!\031\001\n\005\r)\"YA1\001\023\t\031iC1\002b\001%\0211\001\007b\003C\002I!aa\rC\006\005\004\021BA\002\034\005\f\t\007!\003\002\004:\t\027\021\rA\005\003\007y\021-!\031\001\n\005\r}\"YA1\001\023\t\031\021E1\002b\001%\0211Q\tb\003C\002I!a\001\023C\006\005\004\021BAB&\005\f\t\007!\003\002\004O\t\027\021\rA\005\003\007#\022-!\031\001\n\005\rQ#YA1\001\023\021%!\t\005AI\001\n\003!\031%A\bd_BLH\005Z3gCVdG\017J\0311+1\")\005\"\023\005L\0215Cq\nC)\t'\")\006b\026\005Z\021mCQ\fC0\tC\"\031\007\"\032\005h\021%D1\016C7\t_\"\t(\006\002\005H)\032\021Ga\031\005\rE!yD1\001\023\t\031YBq\bb\001%\0211a\004b\020C\002I!a!\tC \005\004\021BA\002\023\005@\t\007!\003\002\004(\t\021\rA\005\003\007U\021}\"\031\001\n\005\r5\"yD1\001\023\t\031\001Dq\bb\001%\02111\007b\020C\002I!aA\016C \005\004\021BAB\035\005@\t\007!\003\002\004=\t\021\rA\005\003\007\021}\"\031\001\n\005\r\t#yD1\001\023\t\031)Eq\bb\001%\0211\001\nb\020C\002I!aa\023C \005\004\021BA\002(\005@\t\007!\003\002\004R\t\021\rA\005\003\007)\022}\"\031\001\n\t\023\021U\004!%A\005\002\021]\024aD2paf$C-\0324bk2$H%M\031\026Y\021eDQ\020C@\t\003#\031\t\"\"\005\b\022%E1\022CG\t\037#\t\nb%\005\026\022]E\021\024CN\t;#y\n\")\005$\022\025VC\001C>U\r!$1\r\003\007#\021M$\031\001\n\005\rm!\031H1\001\023\t\031qB1\017b\001%\0211\021\005b\035C\002I!a\001\nC:\005\004\021BAB\024\005t\t\007!\003\002\004+\tg\022\rA\005\003\007[\021M$\031\001\n\005\rA\"\031H1\001\023\t\031\031D1\017b\001%\0211a\007b\035C\002I!a!\017C:\005\004\021BA\002\037\005t\t\007!\003\002\004@\tg\022\rA\005\003\007\005\022M$\031\001\n\005\r\025#\031H1\001\023\t\031AE1\017b\001%\02111\nb\035C\002I!aA\024C:\005\004\021BAB)\005t\t\007!\003\002\004U\tg\022\rA\005\005\n\tS\003\021\023!C\001\tW\013qbY8qs\022\"WMZ1vYR$\023GM\013-\t[#\t\fb-\0056\022]F\021\030C^\t{#y\f\"1\005D\022\025Gq\031Ce\t\027$i\rb4\005R\022MGQ\033Cl\t3,\"\001b,+\007]\022\031\007\002\004\022\tO\023\rA\005\003\0077\021\035&\031\001\n\005\ry!9K1\001\023\t\031\tCq\025b\001%\0211A\005b*C\002I!aa\nCT\005\004\021BA\002\026\005(\n\007!\003\002\004.\tO\023\rA\005\003\007a\021\035&\031\001\n\005\rM\"9K1\001\023\t\0311Dq\025b\001%\0211\021\bb*C\002I!a\001\020CT\005\004\021BAB \005(\n\007!\003\002\004C\tO\023\rA\005\003\007\013\022\035&\031\001\n\005\r!#9K1\001\023\t\031YEq\025b\001%\0211a\nb*C\002I!a!\025CT\005\004\021BA\002+\005(\n\007!\003C\005\005^\002\t\n\021\"\001\005`\006y1m\0349zI\021,g-Y;mi\022\n4'\006\027\005b\022\025Hq\035Cu\tW$i\017b<\005r\022MHQ\037C|\ts$Y\020\"@\005\000\026\005Q1AC\003\013\017)I!b\003\006\016U\021A1\035\026\004u\t\rDAB\t\005\\\n\007!\003\002\004\034\t7\024\rA\005\003\007=\021m'\031\001\n\005\r\005\"YN1\001\023\t\031!C1\034b\001%\0211q\005b7C\002I!aA\013Cn\005\004\021BAB\027\005\\\n\007!\003\002\0041\t7\024\rA\005\003\007g\021m'\031\001\n\005\rY\"YN1\001\023\t\031ID1\034b\001%\0211A\bb7C\002I!aa\020Cn\005\004\021BA\002\"\005\\\n\007!\003\002\004F\t7\024\rA\005\003\007\021\022m'\031\001\n\005\r-#YN1\001\023\t\031qE1\034b\001%\0211\021\013b7C\002I!a\001\026Cn\005\004\021\002\"CC\t\001E\005I\021AC\n\003=\031w\016]=%I\0264\027-\0367uIE\"T\003LC\013\0133)Y\"\"\b\006 \025\005R1EC\023\013O)I#b\013\006.\025=R\021GC\032\013k)9$\"\017\006<\025uRqHC!+\t)9BK\002>\005G\"a!EC\b\005\004\021BAB\016\006\020\t\007!\003\002\004\037\013\037\021\rA\005\003\007C\025=!\031\001\n\005\r\021*yA1\001\023\t\0319Sq\002b\001%\0211!&b\004C\002I!a!LC\b\005\004\021BA\002\031\006\020\t\007!\003\002\0044\013\037\021\rA\005\003\007m\025=!\031\001\n\005\re*yA1\001\023\t\031aTq\002b\001%\0211q(b\004C\002I!aAQC\b\005\004\021BAB#\006\020\t\007!\003\002\004I\013\037\021\rA\005\003\007\027\026=!\031\001\n\005\r9+yA1\001\023\t\031\tVq\002b\001%\0211A+b\004C\002IA\021\"\"\022\001#\003%\t!b\022\002\037\r|\007/\037\023eK\032\fW\017\034;%cU*B&\"\023\006N\025=S\021KC*\013+*9&\"\027\006\\\025uSqLC1\013G*)'b\032\006j\025-TQNC8\013c*\031(\"\036\026\005\025-#f\001!\003d\0211\021#b\021C\002I!aaGC\"\005\004\021BA\002\020\006D\t\007!\003\002\004\"\013\007\022\rA\005\003\007I\025\r#\031\001\n\005\r\035*\031E1\001\023\t\031QS1\tb\001%\0211Q&b\021C\002I!a\001MC\"\005\004\021BAB\032\006D\t\007!\003\002\0047\013\007\022\rA\005\003\007s\025\r#\031\001\n\005\rq*\031E1\001\023\t\031yT1\tb\001%\0211!)b\021C\002I!a!RC\"\005\004\021BA\002%\006D\t\007!\003\002\004L\013\007\022\rA\005\003\007\035\026\r#\031\001\n\005\rE+\031E1\001\023\t\031!V1\tb\001%!IQ\021\020\001\022\002\023\005Q1P\001\020G>\004\030\020\n3fM\006,H\016\036\0232mUaSQPCA\013\007+))b\"\006\n\026-UQRCH\013#+\031*\"&\006\030\026eU1TCO\013?+\t+b)\006&\026\035V\021V\013\003\013R3a\021B2\t\031\tRq\017b\001%\02111$b\036C\002I!aAHC<\005\004\021BAB\021\006x\t\007!\003\002\004%\013o\022\rA\005\003\007O\025]$\031\001\n\005\r)*9H1\001\023\t\031iSq\017b\001%\0211\001'b\036C\002I!aaMC<\005\004\021BA\002\034\006x\t\007!\003\002\004:\013o\022\rA\005\003\007y\025]$\031\001\n\005\r}*9H1\001\023\t\031\021Uq\017b\001%\0211Q)b\036C\002I!a\001SC<\005\004\021BAB&\006x\t\007!\003\002\004O\013o\022\rA\005\003\007#\026]$\031\001\n\005\rQ+9H1\001\023\021%)i\013AI\001\n\003)y+A\bd_BLH\005Z3gCVdG\017J\0318+1*\t,\".\0068\026eV1XC_\013+\t-b1\006F\026\035W\021ZCf\013\033,y-\"5\006T\026UWq[Cm\0137,i.\006\002\0064*\032aIa\031\005\rE)YK1\001\023\t\031YR1\026b\001%\0211a$b+C\002I!a!ICV\005\004\021BA\002\023\006,\n\007!\003\002\004(\013W\023\rA\005\003\007U\025-&\031\001\n\005\r5*YK1\001\023\t\031\001T1\026b\001%\02111'b+C\002I!aANCV\005\004\021BAB\035\006,\n\007!\003\002\004=\013W\023\rA\005\003\007\025-&\031\001\n\005\r\t+YK1\001\023\t\031)U1\026b\001%\0211\001*b+C\002I!aaSCV\005\004\021BA\002(\006,\n\007!\003\002\004R\013W\023\rA\005\003\007)\026-&\031\001\n\t\023\025\005\b!%A\005\002\025\r\030aD2paf$C-\0324bk2$H%\r\035\026Y\025\025X\021^Cv\013[,y/\"=\006t\026UXq_C}\013w,i0b@\007\002\031\raQ\001D\004\r\0231YA\"\004\007\020\031EQCACtU\rI%1\r\003\007#\025}'\031\001\n\005\rm)yN1\001\023\t\031qRq\034b\001%\0211\021%b8C\002I!a\001JCp\005\004\021BAB\024\006`\n\007!\003\002\004+\013?\024\rA\005\003\007[\025}'\031\001\n\005\rA*yN1\001\023\t\031\031Tq\034b\001%\0211a'b8C\002I!a!OCp\005\004\021BA\002\037\006`\n\007!\003\002\004@\013?\024\rA\005\003\007\005\026}'\031\001\n\005\r\025+yN1\001\023\t\031AUq\034b\001%\02111*b8C\002I!aATCp\005\004\021BAB)\006`\n\007!\003\002\004U\013?\024\rA\005\005\n\r+\001\021\023!C\001\r/\tqbY8qs\022\"WMZ1vYR$\023'O\013-\r31iBb\b\007\"\031\rbQ\005D\024\rS1YC\"\f\0070\031Eb1\007D\033\ro1IDb\017\007>\031}b\021\tD\"\r\013*\"Ab\007+\0071\023\031\007\002\004\022\r'\021\rA\005\003\0077\031M!\031\001\n\005\ry1\031B1\001\023\t\031\tc1\003b\001%\0211AEb\005C\002I!aa\nD\n\005\004\021BA\002\026\007\024\t\007!\003\002\004.\r'\021\rA\005\003\007a\031M!\031\001\n\005\rM2\031B1\001\023\t\0311d1\003b\001%\0211\021Hb\005C\002I!a\001\020D\n\005\004\021BAB \007\024\t\007!\003\002\004C\r'\021\rA\005\003\007\013\032M!\031\001\n\005\r!3\031B1\001\023\t\031Ye1\003b\001%\0211aJb\005C\002I!a!\025D\n\005\004\021BA\002+\007\024\t\007!\003C\005\007J\001\t\n\021\"\001\007L\005y1m\0349zI\021,g-Y;mi\022\022\004'\006\027\007N\031Ec1\013D+\r/2IFb\027\007^\031}c\021\rD2\rK29G\"\033\007l\0315dq\016D9\rg2)Hb\036\007zU\021aq\n\026\004\037\n\rDAB\t\007H\t\007!\003\002\004\034\r\017\022\rA\005\003\007=\031\035#\031\001\n\005\r\00529E1\001\023\t\031!cq\tb\001%\0211qEb\022C\002I!aA\013D$\005\004\021BAB\027\007H\t\007!\003\002\0041\r\017\022\rA\005\003\007g\031\035#\031\001\n\005\rY29E1\001\023\t\031Idq\tb\001%\0211AHb\022C\002I!aa\020D$\005\004\021BA\002\"\007H\t\007!\003\002\004F\r\017\022\rA\005\003\007\021\032\035#\031\001\n\005\r-39E1\001\023\t\031qeq\tb\001%\0211\021Kb\022C\002I!a\001\026D$\005\004\021\002\"\003D?\001E\005I\021\001D@\003=\031w\016]=%I\0264\027-\0367uII\nT\003\fDA\r\01339I\"#\007\f\0325eq\022DI\r'3)Jb&\007\032\032meQ\024DP\rC3\031K\"*\007(\032%f1\026DW+\t1\031IK\002S\005G\"a!\005D>\005\004\021BAB\016\007|\t\007!\003\002\004\037\rw\022\rA\005\003\007C\031m$\031\001\n\005\r\0212YH1\001\023\t\0319c1\020b\001%\0211!Fb\037C\002I!a!\fD>\005\004\021BA\002\031\007|\t\007!\003\002\0044\rw\022\rA\005\003\007m\031m$\031\001\n\005\re2YH1\001\023\t\031ad1\020b\001%\0211qHb\037C\002I!aA\021D>\005\004\021BAB#\007|\t\007!\003\002\004I\rw\022\rA\005\003\007\027\032m$\031\001\n\005\r93YH1\001\023\t\031\tf1\020b\001%\0211AKb\037C\002IA\021B\"-\001\003\003%\tEb-\002\033A\024x\016Z;diB\023XMZ5y+\t\t\t\rC\005\0078\002\t\t\021\"\021\007:\006y\001O]8ek\016$\030\n^3sCR|'/\006\002\007<B)aQ\030Db-5\021aq\030\006\004\r\003\024\021AC2pY2,7\r^5p]&!aQ\031D`\005!IE/\032:bi>\024\b\"\003De\001\005\005I\021\001Df\003!\031\027M\\#rk\006dG\003\002Dg\r'\0042\001\003Dh\023\r1\tN\001\002\b\005>|G.Z1o\021%1)Nb2\002\002\003\007a#A\002yIEB\021B\"7\001\003\003%\tEb7\002\021!\f7\017[\"pI\026$\"A\"8\021\007!1y.C\002\007b\n\0211!\0238u\021%1)\017AA\001\n\00329/\001\004fcV\fGn\035\013\005\r\0334I\017C\005\007V\032\r\030\021!a\001-\035IaQ\036\002\002\002#\005aq^\001\b)V\004H.\032\0322!\rAa\021\037\004\t\003\t\t\t\021#\001\007tN!a\021_\004Y\021!\tYI\"=\005\002\031]HC\001Dx\021)\tiL\"=\002\002\023\025\023q\030\005\013\r{4\t0!A\005\002\032}\030!B1qa2LX\003LD\001\017\0179Yab\004\b\024\035]q1DD\020\017G99cb\013\b0\035MrqGD\036\0179\031eb\022\bL\035=s1KD,)1:\031a\"\027\b\\\035usqLD1\017G:)gb\032\bj\035-tQND8\017c:\031h\"\036\bx\035et1PD?\017:\t\t\005\027\t\001\035\025q\021BD\007\017#9)b\"\007\b\036\035\005rQED\025\017[9\td\"\016\b:\035ur\021ID#\017\023:ie\"\025\bVA\031qbb\002\005\rE1YP1\001\023!\ryq1\002\003\0077\031m(\031\001\n\021\007=9y\001\002\004\037\rw\024\rA\005\t\004\037\035MAAB\021\007|\n\007!\003E\002\020\017/!a\001\nD~\005\004\021\002cA\b\b\034\0211qEb?C\002I\0012aDD\020\t\031Qc1 b\001%A\031qbb\t\005\r52YP1\001\023!\ryqq\005\003\007a\031m(\031\001\n\021\007=9Y\003\002\0044\rw\024\rA\005\t\004\037\035=BA\002\034\007|\n\007!\003E\002\020\017g!a!\017D~\005\004\021\002cA\b\b8\0211AHb?C\002I\0012aDD\036\t\031yd1 b\001%A\031qbb\020\005\r\t3YP1\001\023!\ryq1\t\003\007\013\032m(\031\001\n\021\007=99\005\002\004I\rw\024\rA\005\t\004\037\035-CAB&\007|\n\007!\003E\002\020\017\037\"aA\024D~\005\004\021\002cA\b\bT\0211\021Kb?C\002I\0012aDD,\t\031!f1 b\001%!9ALb?A\002\035\025\001bB1\007|\002\007q\021\002\005\bM\032m\b\031AD\007\021\035Yg1 a\001\017#Aq\001\035D~\001\0049)\002C\004v\rw\004\ra\"\007\t\017i4Y\0201\001\b\036!9qPb?A\002\035\005\002\002CA\005\rw\004\ra\"\n\t\021\005Ma1 a\001\017SA\001\"!\b\007|\002\007qQ\006\005\t\003O1Y\0201\001\b2!A\021\021\007D~\001\0049)\004\003\005\002<\031m\b\031AD\035\021!\t)Eb?A\002\035u\002\002CA(\rw\004\ra\"\021\t\021\005ec1 a\001\017\013B\001\"a\031\007|\002\007q\021\n\005\t\003[2Y\0201\001\bN!A\021q\017D~\001\0049\t\006\003\005\002\002\032m\b\031AD+\021)9)I\"=\002\002\023\005uqQ\001\bk:\f\007\017\0357z+1:Ii\"&\b\032\036uu\021UDS\017S;ik\"-\b6\036evQXDa\017\013<Im\"4\bR\036Uw\021\\Do\017C<)\017\006\003\b\f\036\035\b#\002\005\b\016\036E\025bADH\005\t1q\n\035;j_:\004B\006\003\001\b\024\036]u1TDP\017G;9kb+\b0\036MvqWD^\017;\031mb2\bL\036=w1[Dl\0177<ynb9\021\007=9)\n\002\004\022\017\007\023\rA\005\t\004\037\035eEAB\016\b\004\n\007!\003E\002\020\017;#aAHDB\005\004\021\002cA\b\b\"\0221\021eb!C\002I\0012aDDS\t\031!s1\021b\001%A\031qb\"+\005\r\035:\031I1\001\023!\ryqQ\026\003\007U\035\r%\031\001\n\021\007=9\t\f\002\004.\017\007\023\rA\005\t\004\037\035UFA\002\031\b\004\n\007!\003E\002\020\017s#aaMDB\005\004\021\002cA\b\b>\0221agb!C\002I\0012aDDa\t\031It1\021b\001%A\031qb\"2\005\rq:\031I1\001\023!\ryq\021\032\003\007\035\r%\031\001\n\021\007=9i\r\002\004C\017\007\023\rA\005\t\004\037\035EGAB#\b\004\n\007!\003E\002\020\017+$a\001SDB\005\004\021\002cA\b\bZ\02211jb!C\002I\0012aDDo\t\031qu1\021b\001%A\031qb\"9\005\rE;\031I1\001\023!\ryqQ\035\003\007)\036\r%\031\001\n\t\025\035%x1QA\001\002\0049\t*A\002yIAB!b\"<\007r\006\005I\021BDx\003-\021X-\0313SKN|GN^3\025\005\035E\b\003BAb\017gLAa\">\002F\n1qJ\0316fGR\004")
/*    */ public class Tuple21<T1, T2, T3, T4, T5, T6, T7, T8, T9, T10, T11, T12, T13, T14, T15, T16, T17, T18, T19, T20, T21> implements Product21<T1, T2, T3, T4, T5, T6, T7, T8, T9, T10, T11, T12, T13, T14, T15, T16, T17, T18, T19, T20, T21>, Product, Serializable {
/*    */   private final T1 _1;
/*    */   
/*    */   private final T2 _2;
/*    */   
/*    */   private final T3 _3;
/*    */   
/*    */   private final T4 _4;
/*    */   
/*    */   private final T5 _5;
/*    */   
/*    */   private final T6 _6;
/*    */   
/*    */   private final T7 _7;
/*    */   
/*    */   private final T8 _8;
/*    */   
/*    */   private final T9 _9;
/*    */   
/*    */   private final T10 _10;
/*    */   
/*    */   private final T11 _11;
/*    */   
/*    */   private final T12 _12;
/*    */   
/*    */   private final T13 _13;
/*    */   
/*    */   private final T14 _14;
/*    */   
/*    */   private final T15 _15;
/*    */   
/*    */   private final T16 _16;
/*    */   
/*    */   private final T17 _17;
/*    */   
/*    */   private final T18 _18;
/*    */   
/*    */   private final T19 _19;
/*    */   
/*    */   private final T20 _20;
/*    */   
/*    */   private final T21 _21;
/*    */   
/*    */   public int productArity() {
/* 38 */     return Product21$class.productArity(this);
/*    */   }
/*    */   
/*    */   public Object productElement(int n) throws IndexOutOfBoundsException {
/* 38 */     return Product21$class.productElement(this, n);
/*    */   }
/*    */   
/*    */   public T1 _1() {
/* 38 */     return this._1;
/*    */   }
/*    */   
/*    */   public T2 _2() {
/* 38 */     return this._2;
/*    */   }
/*    */   
/*    */   public T3 _3() {
/* 38 */     return this._3;
/*    */   }
/*    */   
/*    */   public T4 _4() {
/* 38 */     return this._4;
/*    */   }
/*    */   
/*    */   public T5 _5() {
/* 38 */     return this._5;
/*    */   }
/*    */   
/*    */   public T6 _6() {
/* 38 */     return this._6;
/*    */   }
/*    */   
/*    */   public T7 _7() {
/* 38 */     return this._7;
/*    */   }
/*    */   
/*    */   public T8 _8() {
/* 38 */     return this._8;
/*    */   }
/*    */   
/*    */   public T9 _9() {
/* 38 */     return this._9;
/*    */   }
/*    */   
/*    */   public T10 _10() {
/* 38 */     return this._10;
/*    */   }
/*    */   
/*    */   public T11 _11() {
/* 38 */     return this._11;
/*    */   }
/*    */   
/*    */   public T12 _12() {
/* 38 */     return this._12;
/*    */   }
/*    */   
/*    */   public T13 _13() {
/* 38 */     return this._13;
/*    */   }
/*    */   
/*    */   public T14 _14() {
/* 38 */     return this._14;
/*    */   }
/*    */   
/*    */   public T15 _15() {
/* 38 */     return this._15;
/*    */   }
/*    */   
/*    */   public T16 _16() {
/* 38 */     return this._16;
/*    */   }
/*    */   
/*    */   public T17 _17() {
/* 38 */     return this._17;
/*    */   }
/*    */   
/*    */   public T18 _18() {
/* 38 */     return this._18;
/*    */   }
/*    */   
/*    */   public T19 _19() {
/* 38 */     return this._19;
/*    */   }
/*    */   
/*    */   public T20 _20() {
/* 38 */     return this._20;
/*    */   }
/*    */   
/*    */   public T21 _21() {
/* 38 */     return this._21;
/*    */   }
/*    */   
/*    */   public <T1, T2, T3, T4, T5, T6, T7, T8, T9, T10, T11, T12, T13, T14, T15, T16, T17, T18, T19, T20, T21> Tuple21<T1, T2, T3, T4, T5, T6, T7, T8, T9, T10, T11, T12, T13, T14, T15, T16, T17, T18, T19, T20, T21> copy(Object _1, Object _2, Object _3, Object _4, Object _5, Object _6, Object _7, Object _8, Object _9, Object _10, Object _11, Object _12, Object _13, Object _14, Object _15, Object _16, Object _17, Object _18, Object _19, Object _20, Object _21) {
/* 38 */     return new Tuple21((T1)_1, (T2)_2, (T3)_3, (T4)_4, (T5)_5, (T6)_6, (T7)_7, (T8)_8, (T9)_9, (T10)_10, (T11)_11, (T12)_12, (T13)_13, (T14)_14, (T15)_15, (T16)_16, (T17)_17, (T18)_18, (T19)_19, (T20)_20, (T21)_21);
/*    */   }
/*    */   
/*    */   public <T1, T2, T3, T4, T5, T6, T7, T8, T9, T10, T11, T12, T13, T14, T15, T16, T17, T18, T19, T20, T21> T1 copy$default$1() {
/* 38 */     return _1();
/*    */   }
/*    */   
/*    */   public <T1, T2, T3, T4, T5, T6, T7, T8, T9, T10, T11, T12, T13, T14, T15, T16, T17, T18, T19, T20, T21> T2 copy$default$2() {
/* 38 */     return _2();
/*    */   }
/*    */   
/*    */   public <T1, T2, T3, T4, T5, T6, T7, T8, T9, T10, T11, T12, T13, T14, T15, T16, T17, T18, T19, T20, T21> T3 copy$default$3() {
/* 38 */     return _3();
/*    */   }
/*    */   
/*    */   public <T1, T2, T3, T4, T5, T6, T7, T8, T9, T10, T11, T12, T13, T14, T15, T16, T17, T18, T19, T20, T21> T4 copy$default$4() {
/* 38 */     return _4();
/*    */   }
/*    */   
/*    */   public <T1, T2, T3, T4, T5, T6, T7, T8, T9, T10, T11, T12, T13, T14, T15, T16, T17, T18, T19, T20, T21> T5 copy$default$5() {
/* 38 */     return _5();
/*    */   }
/*    */   
/*    */   public <T1, T2, T3, T4, T5, T6, T7, T8, T9, T10, T11, T12, T13, T14, T15, T16, T17, T18, T19, T20, T21> T6 copy$default$6() {
/* 38 */     return _6();
/*    */   }
/*    */   
/*    */   public <T1, T2, T3, T4, T5, T6, T7, T8, T9, T10, T11, T12, T13, T14, T15, T16, T17, T18, T19, T20, T21> T7 copy$default$7() {
/* 38 */     return _7();
/*    */   }
/*    */   
/*    */   public <T1, T2, T3, T4, T5, T6, T7, T8, T9, T10, T11, T12, T13, T14, T15, T16, T17, T18, T19, T20, T21> T8 copy$default$8() {
/* 38 */     return _8();
/*    */   }
/*    */   
/*    */   public <T1, T2, T3, T4, T5, T6, T7, T8, T9, T10, T11, T12, T13, T14, T15, T16, T17, T18, T19, T20, T21> T9 copy$default$9() {
/* 38 */     return _9();
/*    */   }
/*    */   
/*    */   public <T1, T2, T3, T4, T5, T6, T7, T8, T9, T10, T11, T12, T13, T14, T15, T16, T17, T18, T19, T20, T21> T10 copy$default$10() {
/* 38 */     return _10();
/*    */   }
/*    */   
/*    */   public <T1, T2, T3, T4, T5, T6, T7, T8, T9, T10, T11, T12, T13, T14, T15, T16, T17, T18, T19, T20, T21> T11 copy$default$11() {
/* 38 */     return _11();
/*    */   }
/*    */   
/*    */   public <T1, T2, T3, T4, T5, T6, T7, T8, T9, T10, T11, T12, T13, T14, T15, T16, T17, T18, T19, T20, T21> T12 copy$default$12() {
/* 38 */     return _12();
/*    */   }
/*    */   
/*    */   public <T1, T2, T3, T4, T5, T6, T7, T8, T9, T10, T11, T12, T13, T14, T15, T16, T17, T18, T19, T20, T21> T13 copy$default$13() {
/* 38 */     return _13();
/*    */   }
/*    */   
/*    */   public <T1, T2, T3, T4, T5, T6, T7, T8, T9, T10, T11, T12, T13, T14, T15, T16, T17, T18, T19, T20, T21> T14 copy$default$14() {
/* 38 */     return _14();
/*    */   }
/*    */   
/*    */   public <T1, T2, T3, T4, T5, T6, T7, T8, T9, T10, T11, T12, T13, T14, T15, T16, T17, T18, T19, T20, T21> T15 copy$default$15() {
/* 38 */     return _15();
/*    */   }
/*    */   
/*    */   public <T1, T2, T3, T4, T5, T6, T7, T8, T9, T10, T11, T12, T13, T14, T15, T16, T17, T18, T19, T20, T21> T16 copy$default$16() {
/* 38 */     return _16();
/*    */   }
/*    */   
/*    */   public <T1, T2, T3, T4, T5, T6, T7, T8, T9, T10, T11, T12, T13, T14, T15, T16, T17, T18, T19, T20, T21> T17 copy$default$17() {
/* 38 */     return _17();
/*    */   }
/*    */   
/*    */   public <T1, T2, T3, T4, T5, T6, T7, T8, T9, T10, T11, T12, T13, T14, T15, T16, T17, T18, T19, T20, T21> T18 copy$default$18() {
/* 38 */     return _18();
/*    */   }
/*    */   
/*    */   public <T1, T2, T3, T4, T5, T6, T7, T8, T9, T10, T11, T12, T13, T14, T15, T16, T17, T18, T19, T20, T21> T19 copy$default$19() {
/* 38 */     return _19();
/*    */   }
/*    */   
/*    */   public <T1, T2, T3, T4, T5, T6, T7, T8, T9, T10, T11, T12, T13, T14, T15, T16, T17, T18, T19, T20, T21> T20 copy$default$20() {
/* 38 */     return _20();
/*    */   }
/*    */   
/*    */   public <T1, T2, T3, T4, T5, T6, T7, T8, T9, T10, T11, T12, T13, T14, T15, T16, T17, T18, T19, T20, T21> T21 copy$default$21() {
/* 38 */     return _21();
/*    */   }
/*    */   
/*    */   public String productPrefix() {
/* 38 */     return "Tuple21";
/*    */   }
/*    */   
/*    */   public Iterator<Object> productIterator() {
/* 38 */     return ScalaRunTime$.MODULE$.typedProductIterator(this);
/*    */   }
/*    */   
/*    */   public boolean canEqual(Object x$1) {
/* 38 */     return x$1 instanceof Tuple21;
/*    */   }
/*    */   
/*    */   public int hashCode() {
/* 38 */     return ScalaRunTime$.MODULE$._hashCode(this);
/*    */   }
/*    */   
/*    */   public boolean equals(Object x$1) {
/*    */     // Byte code:
/*    */     //   0: aload_0
/*    */     //   1: aload_1
/*    */     //   2: if_acmpeq -> 1803
/*    */     //   5: aload_1
/*    */     //   6: instanceof scala/Tuple21
/*    */     //   9: ifeq -> 17
/*    */     //   12: iconst_1
/*    */     //   13: istore_2
/*    */     //   14: goto -> 19
/*    */     //   17: iconst_0
/*    */     //   18: istore_2
/*    */     //   19: iload_2
/*    */     //   20: ifeq -> 1807
/*    */     //   23: aload_1
/*    */     //   24: checkcast scala/Tuple21
/*    */     //   27: astore #45
/*    */     //   29: aload_0
/*    */     //   30: invokevirtual _1 : ()Ljava/lang/Object;
/*    */     //   33: aload #45
/*    */     //   35: invokevirtual _1 : ()Ljava/lang/Object;
/*    */     //   38: astore #4
/*    */     //   40: dup
/*    */     //   41: astore_3
/*    */     //   42: aload #4
/*    */     //   44: if_acmpne -> 51
/*    */     //   47: iconst_1
/*    */     //   48: goto -> 103
/*    */     //   51: aload_3
/*    */     //   52: ifnonnull -> 59
/*    */     //   55: iconst_0
/*    */     //   56: goto -> 103
/*    */     //   59: aload_3
/*    */     //   60: instanceof java/lang/Number
/*    */     //   63: ifeq -> 78
/*    */     //   66: aload_3
/*    */     //   67: checkcast java/lang/Number
/*    */     //   70: aload #4
/*    */     //   72: invokestatic equalsNumObject : (Ljava/lang/Number;Ljava/lang/Object;)Z
/*    */     //   75: goto -> 103
/*    */     //   78: aload_3
/*    */     //   79: instanceof java/lang/Character
/*    */     //   82: ifeq -> 97
/*    */     //   85: aload_3
/*    */     //   86: checkcast java/lang/Character
/*    */     //   89: aload #4
/*    */     //   91: invokestatic equalsCharObject : (Ljava/lang/Character;Ljava/lang/Object;)Z
/*    */     //   94: goto -> 103
/*    */     //   97: aload_3
/*    */     //   98: aload #4
/*    */     //   100: invokevirtual equals : (Ljava/lang/Object;)Z
/*    */     //   103: ifeq -> 1799
/*    */     //   106: aload_0
/*    */     //   107: invokevirtual _2 : ()Ljava/lang/Object;
/*    */     //   110: aload #45
/*    */     //   112: invokevirtual _2 : ()Ljava/lang/Object;
/*    */     //   115: astore #6
/*    */     //   117: dup
/*    */     //   118: astore #5
/*    */     //   120: aload #6
/*    */     //   122: if_acmpne -> 129
/*    */     //   125: iconst_1
/*    */     //   126: goto -> 187
/*    */     //   129: aload #5
/*    */     //   131: ifnonnull -> 138
/*    */     //   134: iconst_0
/*    */     //   135: goto -> 187
/*    */     //   138: aload #5
/*    */     //   140: instanceof java/lang/Number
/*    */     //   143: ifeq -> 159
/*    */     //   146: aload #5
/*    */     //   148: checkcast java/lang/Number
/*    */     //   151: aload #6
/*    */     //   153: invokestatic equalsNumObject : (Ljava/lang/Number;Ljava/lang/Object;)Z
/*    */     //   156: goto -> 187
/*    */     //   159: aload #5
/*    */     //   161: instanceof java/lang/Character
/*    */     //   164: ifeq -> 180
/*    */     //   167: aload #5
/*    */     //   169: checkcast java/lang/Character
/*    */     //   172: aload #6
/*    */     //   174: invokestatic equalsCharObject : (Ljava/lang/Character;Ljava/lang/Object;)Z
/*    */     //   177: goto -> 187
/*    */     //   180: aload #5
/*    */     //   182: aload #6
/*    */     //   184: invokevirtual equals : (Ljava/lang/Object;)Z
/*    */     //   187: ifeq -> 1799
/*    */     //   190: aload_0
/*    */     //   191: invokevirtual _3 : ()Ljava/lang/Object;
/*    */     //   194: aload #45
/*    */     //   196: invokevirtual _3 : ()Ljava/lang/Object;
/*    */     //   199: astore #8
/*    */     //   201: dup
/*    */     //   202: astore #7
/*    */     //   204: aload #8
/*    */     //   206: if_acmpne -> 213
/*    */     //   209: iconst_1
/*    */     //   210: goto -> 271
/*    */     //   213: aload #7
/*    */     //   215: ifnonnull -> 222
/*    */     //   218: iconst_0
/*    */     //   219: goto -> 271
/*    */     //   222: aload #7
/*    */     //   224: instanceof java/lang/Number
/*    */     //   227: ifeq -> 243
/*    */     //   230: aload #7
/*    */     //   232: checkcast java/lang/Number
/*    */     //   235: aload #8
/*    */     //   237: invokestatic equalsNumObject : (Ljava/lang/Number;Ljava/lang/Object;)Z
/*    */     //   240: goto -> 271
/*    */     //   243: aload #7
/*    */     //   245: instanceof java/lang/Character
/*    */     //   248: ifeq -> 264
/*    */     //   251: aload #7
/*    */     //   253: checkcast java/lang/Character
/*    */     //   256: aload #8
/*    */     //   258: invokestatic equalsCharObject : (Ljava/lang/Character;Ljava/lang/Object;)Z
/*    */     //   261: goto -> 271
/*    */     //   264: aload #7
/*    */     //   266: aload #8
/*    */     //   268: invokevirtual equals : (Ljava/lang/Object;)Z
/*    */     //   271: ifeq -> 1799
/*    */     //   274: aload_0
/*    */     //   275: invokevirtual _4 : ()Ljava/lang/Object;
/*    */     //   278: aload #45
/*    */     //   280: invokevirtual _4 : ()Ljava/lang/Object;
/*    */     //   283: astore #10
/*    */     //   285: dup
/*    */     //   286: astore #9
/*    */     //   288: aload #10
/*    */     //   290: if_acmpne -> 297
/*    */     //   293: iconst_1
/*    */     //   294: goto -> 355
/*    */     //   297: aload #9
/*    */     //   299: ifnonnull -> 306
/*    */     //   302: iconst_0
/*    */     //   303: goto -> 355
/*    */     //   306: aload #9
/*    */     //   308: instanceof java/lang/Number
/*    */     //   311: ifeq -> 327
/*    */     //   314: aload #9
/*    */     //   316: checkcast java/lang/Number
/*    */     //   319: aload #10
/*    */     //   321: invokestatic equalsNumObject : (Ljava/lang/Number;Ljava/lang/Object;)Z
/*    */     //   324: goto -> 355
/*    */     //   327: aload #9
/*    */     //   329: instanceof java/lang/Character
/*    */     //   332: ifeq -> 348
/*    */     //   335: aload #9
/*    */     //   337: checkcast java/lang/Character
/*    */     //   340: aload #10
/*    */     //   342: invokestatic equalsCharObject : (Ljava/lang/Character;Ljava/lang/Object;)Z
/*    */     //   345: goto -> 355
/*    */     //   348: aload #9
/*    */     //   350: aload #10
/*    */     //   352: invokevirtual equals : (Ljava/lang/Object;)Z
/*    */     //   355: ifeq -> 1799
/*    */     //   358: aload_0
/*    */     //   359: invokevirtual _5 : ()Ljava/lang/Object;
/*    */     //   362: aload #45
/*    */     //   364: invokevirtual _5 : ()Ljava/lang/Object;
/*    */     //   367: astore #12
/*    */     //   369: dup
/*    */     //   370: astore #11
/*    */     //   372: aload #12
/*    */     //   374: if_acmpne -> 381
/*    */     //   377: iconst_1
/*    */     //   378: goto -> 439
/*    */     //   381: aload #11
/*    */     //   383: ifnonnull -> 390
/*    */     //   386: iconst_0
/*    */     //   387: goto -> 439
/*    */     //   390: aload #11
/*    */     //   392: instanceof java/lang/Number
/*    */     //   395: ifeq -> 411
/*    */     //   398: aload #11
/*    */     //   400: checkcast java/lang/Number
/*    */     //   403: aload #12
/*    */     //   405: invokestatic equalsNumObject : (Ljava/lang/Number;Ljava/lang/Object;)Z
/*    */     //   408: goto -> 439
/*    */     //   411: aload #11
/*    */     //   413: instanceof java/lang/Character
/*    */     //   416: ifeq -> 432
/*    */     //   419: aload #11
/*    */     //   421: checkcast java/lang/Character
/*    */     //   424: aload #12
/*    */     //   426: invokestatic equalsCharObject : (Ljava/lang/Character;Ljava/lang/Object;)Z
/*    */     //   429: goto -> 439
/*    */     //   432: aload #11
/*    */     //   434: aload #12
/*    */     //   436: invokevirtual equals : (Ljava/lang/Object;)Z
/*    */     //   439: ifeq -> 1799
/*    */     //   442: aload_0
/*    */     //   443: invokevirtual _6 : ()Ljava/lang/Object;
/*    */     //   446: aload #45
/*    */     //   448: invokevirtual _6 : ()Ljava/lang/Object;
/*    */     //   451: astore #14
/*    */     //   453: dup
/*    */     //   454: astore #13
/*    */     //   456: aload #14
/*    */     //   458: if_acmpne -> 465
/*    */     //   461: iconst_1
/*    */     //   462: goto -> 523
/*    */     //   465: aload #13
/*    */     //   467: ifnonnull -> 474
/*    */     //   470: iconst_0
/*    */     //   471: goto -> 523
/*    */     //   474: aload #13
/*    */     //   476: instanceof java/lang/Number
/*    */     //   479: ifeq -> 495
/*    */     //   482: aload #13
/*    */     //   484: checkcast java/lang/Number
/*    */     //   487: aload #14
/*    */     //   489: invokestatic equalsNumObject : (Ljava/lang/Number;Ljava/lang/Object;)Z
/*    */     //   492: goto -> 523
/*    */     //   495: aload #13
/*    */     //   497: instanceof java/lang/Character
/*    */     //   500: ifeq -> 516
/*    */     //   503: aload #13
/*    */     //   505: checkcast java/lang/Character
/*    */     //   508: aload #14
/*    */     //   510: invokestatic equalsCharObject : (Ljava/lang/Character;Ljava/lang/Object;)Z
/*    */     //   513: goto -> 523
/*    */     //   516: aload #13
/*    */     //   518: aload #14
/*    */     //   520: invokevirtual equals : (Ljava/lang/Object;)Z
/*    */     //   523: ifeq -> 1799
/*    */     //   526: aload_0
/*    */     //   527: invokevirtual _7 : ()Ljava/lang/Object;
/*    */     //   530: aload #45
/*    */     //   532: invokevirtual _7 : ()Ljava/lang/Object;
/*    */     //   535: astore #16
/*    */     //   537: dup
/*    */     //   538: astore #15
/*    */     //   540: aload #16
/*    */     //   542: if_acmpne -> 549
/*    */     //   545: iconst_1
/*    */     //   546: goto -> 607
/*    */     //   549: aload #15
/*    */     //   551: ifnonnull -> 558
/*    */     //   554: iconst_0
/*    */     //   555: goto -> 607
/*    */     //   558: aload #15
/*    */     //   560: instanceof java/lang/Number
/*    */     //   563: ifeq -> 579
/*    */     //   566: aload #15
/*    */     //   568: checkcast java/lang/Number
/*    */     //   571: aload #16
/*    */     //   573: invokestatic equalsNumObject : (Ljava/lang/Number;Ljava/lang/Object;)Z
/*    */     //   576: goto -> 607
/*    */     //   579: aload #15
/*    */     //   581: instanceof java/lang/Character
/*    */     //   584: ifeq -> 600
/*    */     //   587: aload #15
/*    */     //   589: checkcast java/lang/Character
/*    */     //   592: aload #16
/*    */     //   594: invokestatic equalsCharObject : (Ljava/lang/Character;Ljava/lang/Object;)Z
/*    */     //   597: goto -> 607
/*    */     //   600: aload #15
/*    */     //   602: aload #16
/*    */     //   604: invokevirtual equals : (Ljava/lang/Object;)Z
/*    */     //   607: ifeq -> 1799
/*    */     //   610: aload_0
/*    */     //   611: invokevirtual _8 : ()Ljava/lang/Object;
/*    */     //   614: aload #45
/*    */     //   616: invokevirtual _8 : ()Ljava/lang/Object;
/*    */     //   619: astore #18
/*    */     //   621: dup
/*    */     //   622: astore #17
/*    */     //   624: aload #18
/*    */     //   626: if_acmpne -> 633
/*    */     //   629: iconst_1
/*    */     //   630: goto -> 691
/*    */     //   633: aload #17
/*    */     //   635: ifnonnull -> 642
/*    */     //   638: iconst_0
/*    */     //   639: goto -> 691
/*    */     //   642: aload #17
/*    */     //   644: instanceof java/lang/Number
/*    */     //   647: ifeq -> 663
/*    */     //   650: aload #17
/*    */     //   652: checkcast java/lang/Number
/*    */     //   655: aload #18
/*    */     //   657: invokestatic equalsNumObject : (Ljava/lang/Number;Ljava/lang/Object;)Z
/*    */     //   660: goto -> 691
/*    */     //   663: aload #17
/*    */     //   665: instanceof java/lang/Character
/*    */     //   668: ifeq -> 684
/*    */     //   671: aload #17
/*    */     //   673: checkcast java/lang/Character
/*    */     //   676: aload #18
/*    */     //   678: invokestatic equalsCharObject : (Ljava/lang/Character;Ljava/lang/Object;)Z
/*    */     //   681: goto -> 691
/*    */     //   684: aload #17
/*    */     //   686: aload #18
/*    */     //   688: invokevirtual equals : (Ljava/lang/Object;)Z
/*    */     //   691: ifeq -> 1799
/*    */     //   694: aload_0
/*    */     //   695: invokevirtual _9 : ()Ljava/lang/Object;
/*    */     //   698: aload #45
/*    */     //   700: invokevirtual _9 : ()Ljava/lang/Object;
/*    */     //   703: astore #20
/*    */     //   705: dup
/*    */     //   706: astore #19
/*    */     //   708: aload #20
/*    */     //   710: if_acmpne -> 717
/*    */     //   713: iconst_1
/*    */     //   714: goto -> 775
/*    */     //   717: aload #19
/*    */     //   719: ifnonnull -> 726
/*    */     //   722: iconst_0
/*    */     //   723: goto -> 775
/*    */     //   726: aload #19
/*    */     //   728: instanceof java/lang/Number
/*    */     //   731: ifeq -> 747
/*    */     //   734: aload #19
/*    */     //   736: checkcast java/lang/Number
/*    */     //   739: aload #20
/*    */     //   741: invokestatic equalsNumObject : (Ljava/lang/Number;Ljava/lang/Object;)Z
/*    */     //   744: goto -> 775
/*    */     //   747: aload #19
/*    */     //   749: instanceof java/lang/Character
/*    */     //   752: ifeq -> 768
/*    */     //   755: aload #19
/*    */     //   757: checkcast java/lang/Character
/*    */     //   760: aload #20
/*    */     //   762: invokestatic equalsCharObject : (Ljava/lang/Character;Ljava/lang/Object;)Z
/*    */     //   765: goto -> 775
/*    */     //   768: aload #19
/*    */     //   770: aload #20
/*    */     //   772: invokevirtual equals : (Ljava/lang/Object;)Z
/*    */     //   775: ifeq -> 1799
/*    */     //   778: aload_0
/*    */     //   779: invokevirtual _10 : ()Ljava/lang/Object;
/*    */     //   782: aload #45
/*    */     //   784: invokevirtual _10 : ()Ljava/lang/Object;
/*    */     //   787: astore #22
/*    */     //   789: dup
/*    */     //   790: astore #21
/*    */     //   792: aload #22
/*    */     //   794: if_acmpne -> 801
/*    */     //   797: iconst_1
/*    */     //   798: goto -> 859
/*    */     //   801: aload #21
/*    */     //   803: ifnonnull -> 810
/*    */     //   806: iconst_0
/*    */     //   807: goto -> 859
/*    */     //   810: aload #21
/*    */     //   812: instanceof java/lang/Number
/*    */     //   815: ifeq -> 831
/*    */     //   818: aload #21
/*    */     //   820: checkcast java/lang/Number
/*    */     //   823: aload #22
/*    */     //   825: invokestatic equalsNumObject : (Ljava/lang/Number;Ljava/lang/Object;)Z
/*    */     //   828: goto -> 859
/*    */     //   831: aload #21
/*    */     //   833: instanceof java/lang/Character
/*    */     //   836: ifeq -> 852
/*    */     //   839: aload #21
/*    */     //   841: checkcast java/lang/Character
/*    */     //   844: aload #22
/*    */     //   846: invokestatic equalsCharObject : (Ljava/lang/Character;Ljava/lang/Object;)Z
/*    */     //   849: goto -> 859
/*    */     //   852: aload #21
/*    */     //   854: aload #22
/*    */     //   856: invokevirtual equals : (Ljava/lang/Object;)Z
/*    */     //   859: ifeq -> 1799
/*    */     //   862: aload_0
/*    */     //   863: invokevirtual _11 : ()Ljava/lang/Object;
/*    */     //   866: aload #45
/*    */     //   868: invokevirtual _11 : ()Ljava/lang/Object;
/*    */     //   871: astore #24
/*    */     //   873: dup
/*    */     //   874: astore #23
/*    */     //   876: aload #24
/*    */     //   878: if_acmpne -> 885
/*    */     //   881: iconst_1
/*    */     //   882: goto -> 943
/*    */     //   885: aload #23
/*    */     //   887: ifnonnull -> 894
/*    */     //   890: iconst_0
/*    */     //   891: goto -> 943
/*    */     //   894: aload #23
/*    */     //   896: instanceof java/lang/Number
/*    */     //   899: ifeq -> 915
/*    */     //   902: aload #23
/*    */     //   904: checkcast java/lang/Number
/*    */     //   907: aload #24
/*    */     //   909: invokestatic equalsNumObject : (Ljava/lang/Number;Ljava/lang/Object;)Z
/*    */     //   912: goto -> 943
/*    */     //   915: aload #23
/*    */     //   917: instanceof java/lang/Character
/*    */     //   920: ifeq -> 936
/*    */     //   923: aload #23
/*    */     //   925: checkcast java/lang/Character
/*    */     //   928: aload #24
/*    */     //   930: invokestatic equalsCharObject : (Ljava/lang/Character;Ljava/lang/Object;)Z
/*    */     //   933: goto -> 943
/*    */     //   936: aload #23
/*    */     //   938: aload #24
/*    */     //   940: invokevirtual equals : (Ljava/lang/Object;)Z
/*    */     //   943: ifeq -> 1799
/*    */     //   946: aload_0
/*    */     //   947: invokevirtual _12 : ()Ljava/lang/Object;
/*    */     //   950: aload #45
/*    */     //   952: invokevirtual _12 : ()Ljava/lang/Object;
/*    */     //   955: astore #26
/*    */     //   957: dup
/*    */     //   958: astore #25
/*    */     //   960: aload #26
/*    */     //   962: if_acmpne -> 969
/*    */     //   965: iconst_1
/*    */     //   966: goto -> 1027
/*    */     //   969: aload #25
/*    */     //   971: ifnonnull -> 978
/*    */     //   974: iconst_0
/*    */     //   975: goto -> 1027
/*    */     //   978: aload #25
/*    */     //   980: instanceof java/lang/Number
/*    */     //   983: ifeq -> 999
/*    */     //   986: aload #25
/*    */     //   988: checkcast java/lang/Number
/*    */     //   991: aload #26
/*    */     //   993: invokestatic equalsNumObject : (Ljava/lang/Number;Ljava/lang/Object;)Z
/*    */     //   996: goto -> 1027
/*    */     //   999: aload #25
/*    */     //   1001: instanceof java/lang/Character
/*    */     //   1004: ifeq -> 1020
/*    */     //   1007: aload #25
/*    */     //   1009: checkcast java/lang/Character
/*    */     //   1012: aload #26
/*    */     //   1014: invokestatic equalsCharObject : (Ljava/lang/Character;Ljava/lang/Object;)Z
/*    */     //   1017: goto -> 1027
/*    */     //   1020: aload #25
/*    */     //   1022: aload #26
/*    */     //   1024: invokevirtual equals : (Ljava/lang/Object;)Z
/*    */     //   1027: ifeq -> 1799
/*    */     //   1030: aload_0
/*    */     //   1031: invokevirtual _13 : ()Ljava/lang/Object;
/*    */     //   1034: aload #45
/*    */     //   1036: invokevirtual _13 : ()Ljava/lang/Object;
/*    */     //   1039: astore #28
/*    */     //   1041: dup
/*    */     //   1042: astore #27
/*    */     //   1044: aload #28
/*    */     //   1046: if_acmpne -> 1053
/*    */     //   1049: iconst_1
/*    */     //   1050: goto -> 1111
/*    */     //   1053: aload #27
/*    */     //   1055: ifnonnull -> 1062
/*    */     //   1058: iconst_0
/*    */     //   1059: goto -> 1111
/*    */     //   1062: aload #27
/*    */     //   1064: instanceof java/lang/Number
/*    */     //   1067: ifeq -> 1083
/*    */     //   1070: aload #27
/*    */     //   1072: checkcast java/lang/Number
/*    */     //   1075: aload #28
/*    */     //   1077: invokestatic equalsNumObject : (Ljava/lang/Number;Ljava/lang/Object;)Z
/*    */     //   1080: goto -> 1111
/*    */     //   1083: aload #27
/*    */     //   1085: instanceof java/lang/Character
/*    */     //   1088: ifeq -> 1104
/*    */     //   1091: aload #27
/*    */     //   1093: checkcast java/lang/Character
/*    */     //   1096: aload #28
/*    */     //   1098: invokestatic equalsCharObject : (Ljava/lang/Character;Ljava/lang/Object;)Z
/*    */     //   1101: goto -> 1111
/*    */     //   1104: aload #27
/*    */     //   1106: aload #28
/*    */     //   1108: invokevirtual equals : (Ljava/lang/Object;)Z
/*    */     //   1111: ifeq -> 1799
/*    */     //   1114: aload_0
/*    */     //   1115: invokevirtual _14 : ()Ljava/lang/Object;
/*    */     //   1118: aload #45
/*    */     //   1120: invokevirtual _14 : ()Ljava/lang/Object;
/*    */     //   1123: astore #30
/*    */     //   1125: dup
/*    */     //   1126: astore #29
/*    */     //   1128: aload #30
/*    */     //   1130: if_acmpne -> 1137
/*    */     //   1133: iconst_1
/*    */     //   1134: goto -> 1195
/*    */     //   1137: aload #29
/*    */     //   1139: ifnonnull -> 1146
/*    */     //   1142: iconst_0
/*    */     //   1143: goto -> 1195
/*    */     //   1146: aload #29
/*    */     //   1148: instanceof java/lang/Number
/*    */     //   1151: ifeq -> 1167
/*    */     //   1154: aload #29
/*    */     //   1156: checkcast java/lang/Number
/*    */     //   1159: aload #30
/*    */     //   1161: invokestatic equalsNumObject : (Ljava/lang/Number;Ljava/lang/Object;)Z
/*    */     //   1164: goto -> 1195
/*    */     //   1167: aload #29
/*    */     //   1169: instanceof java/lang/Character
/*    */     //   1172: ifeq -> 1188
/*    */     //   1175: aload #29
/*    */     //   1177: checkcast java/lang/Character
/*    */     //   1180: aload #30
/*    */     //   1182: invokestatic equalsCharObject : (Ljava/lang/Character;Ljava/lang/Object;)Z
/*    */     //   1185: goto -> 1195
/*    */     //   1188: aload #29
/*    */     //   1190: aload #30
/*    */     //   1192: invokevirtual equals : (Ljava/lang/Object;)Z
/*    */     //   1195: ifeq -> 1799
/*    */     //   1198: aload_0
/*    */     //   1199: invokevirtual _15 : ()Ljava/lang/Object;
/*    */     //   1202: aload #45
/*    */     //   1204: invokevirtual _15 : ()Ljava/lang/Object;
/*    */     //   1207: astore #32
/*    */     //   1209: dup
/*    */     //   1210: astore #31
/*    */     //   1212: aload #32
/*    */     //   1214: if_acmpne -> 1221
/*    */     //   1217: iconst_1
/*    */     //   1218: goto -> 1279
/*    */     //   1221: aload #31
/*    */     //   1223: ifnonnull -> 1230
/*    */     //   1226: iconst_0
/*    */     //   1227: goto -> 1279
/*    */     //   1230: aload #31
/*    */     //   1232: instanceof java/lang/Number
/*    */     //   1235: ifeq -> 1251
/*    */     //   1238: aload #31
/*    */     //   1240: checkcast java/lang/Number
/*    */     //   1243: aload #32
/*    */     //   1245: invokestatic equalsNumObject : (Ljava/lang/Number;Ljava/lang/Object;)Z
/*    */     //   1248: goto -> 1279
/*    */     //   1251: aload #31
/*    */     //   1253: instanceof java/lang/Character
/*    */     //   1256: ifeq -> 1272
/*    */     //   1259: aload #31
/*    */     //   1261: checkcast java/lang/Character
/*    */     //   1264: aload #32
/*    */     //   1266: invokestatic equalsCharObject : (Ljava/lang/Character;Ljava/lang/Object;)Z
/*    */     //   1269: goto -> 1279
/*    */     //   1272: aload #31
/*    */     //   1274: aload #32
/*    */     //   1276: invokevirtual equals : (Ljava/lang/Object;)Z
/*    */     //   1279: ifeq -> 1799
/*    */     //   1282: aload_0
/*    */     //   1283: invokevirtual _16 : ()Ljava/lang/Object;
/*    */     //   1286: aload #45
/*    */     //   1288: invokevirtual _16 : ()Ljava/lang/Object;
/*    */     //   1291: astore #34
/*    */     //   1293: dup
/*    */     //   1294: astore #33
/*    */     //   1296: aload #34
/*    */     //   1298: if_acmpne -> 1305
/*    */     //   1301: iconst_1
/*    */     //   1302: goto -> 1363
/*    */     //   1305: aload #33
/*    */     //   1307: ifnonnull -> 1314
/*    */     //   1310: iconst_0
/*    */     //   1311: goto -> 1363
/*    */     //   1314: aload #33
/*    */     //   1316: instanceof java/lang/Number
/*    */     //   1319: ifeq -> 1335
/*    */     //   1322: aload #33
/*    */     //   1324: checkcast java/lang/Number
/*    */     //   1327: aload #34
/*    */     //   1329: invokestatic equalsNumObject : (Ljava/lang/Number;Ljava/lang/Object;)Z
/*    */     //   1332: goto -> 1363
/*    */     //   1335: aload #33
/*    */     //   1337: instanceof java/lang/Character
/*    */     //   1340: ifeq -> 1356
/*    */     //   1343: aload #33
/*    */     //   1345: checkcast java/lang/Character
/*    */     //   1348: aload #34
/*    */     //   1350: invokestatic equalsCharObject : (Ljava/lang/Character;Ljava/lang/Object;)Z
/*    */     //   1353: goto -> 1363
/*    */     //   1356: aload #33
/*    */     //   1358: aload #34
/*    */     //   1360: invokevirtual equals : (Ljava/lang/Object;)Z
/*    */     //   1363: ifeq -> 1799
/*    */     //   1366: aload_0
/*    */     //   1367: invokevirtual _17 : ()Ljava/lang/Object;
/*    */     //   1370: aload #45
/*    */     //   1372: invokevirtual _17 : ()Ljava/lang/Object;
/*    */     //   1375: astore #36
/*    */     //   1377: dup
/*    */     //   1378: astore #35
/*    */     //   1380: aload #36
/*    */     //   1382: if_acmpne -> 1389
/*    */     //   1385: iconst_1
/*    */     //   1386: goto -> 1447
/*    */     //   1389: aload #35
/*    */     //   1391: ifnonnull -> 1398
/*    */     //   1394: iconst_0
/*    */     //   1395: goto -> 1447
/*    */     //   1398: aload #35
/*    */     //   1400: instanceof java/lang/Number
/*    */     //   1403: ifeq -> 1419
/*    */     //   1406: aload #35
/*    */     //   1408: checkcast java/lang/Number
/*    */     //   1411: aload #36
/*    */     //   1413: invokestatic equalsNumObject : (Ljava/lang/Number;Ljava/lang/Object;)Z
/*    */     //   1416: goto -> 1447
/*    */     //   1419: aload #35
/*    */     //   1421: instanceof java/lang/Character
/*    */     //   1424: ifeq -> 1440
/*    */     //   1427: aload #35
/*    */     //   1429: checkcast java/lang/Character
/*    */     //   1432: aload #36
/*    */     //   1434: invokestatic equalsCharObject : (Ljava/lang/Character;Ljava/lang/Object;)Z
/*    */     //   1437: goto -> 1447
/*    */     //   1440: aload #35
/*    */     //   1442: aload #36
/*    */     //   1444: invokevirtual equals : (Ljava/lang/Object;)Z
/*    */     //   1447: ifeq -> 1799
/*    */     //   1450: aload_0
/*    */     //   1451: invokevirtual _18 : ()Ljava/lang/Object;
/*    */     //   1454: aload #45
/*    */     //   1456: invokevirtual _18 : ()Ljava/lang/Object;
/*    */     //   1459: astore #38
/*    */     //   1461: dup
/*    */     //   1462: astore #37
/*    */     //   1464: aload #38
/*    */     //   1466: if_acmpne -> 1473
/*    */     //   1469: iconst_1
/*    */     //   1470: goto -> 1531
/*    */     //   1473: aload #37
/*    */     //   1475: ifnonnull -> 1482
/*    */     //   1478: iconst_0
/*    */     //   1479: goto -> 1531
/*    */     //   1482: aload #37
/*    */     //   1484: instanceof java/lang/Number
/*    */     //   1487: ifeq -> 1503
/*    */     //   1490: aload #37
/*    */     //   1492: checkcast java/lang/Number
/*    */     //   1495: aload #38
/*    */     //   1497: invokestatic equalsNumObject : (Ljava/lang/Number;Ljava/lang/Object;)Z
/*    */     //   1500: goto -> 1531
/*    */     //   1503: aload #37
/*    */     //   1505: instanceof java/lang/Character
/*    */     //   1508: ifeq -> 1524
/*    */     //   1511: aload #37
/*    */     //   1513: checkcast java/lang/Character
/*    */     //   1516: aload #38
/*    */     //   1518: invokestatic equalsCharObject : (Ljava/lang/Character;Ljava/lang/Object;)Z
/*    */     //   1521: goto -> 1531
/*    */     //   1524: aload #37
/*    */     //   1526: aload #38
/*    */     //   1528: invokevirtual equals : (Ljava/lang/Object;)Z
/*    */     //   1531: ifeq -> 1799
/*    */     //   1534: aload_0
/*    */     //   1535: invokevirtual _19 : ()Ljava/lang/Object;
/*    */     //   1538: aload #45
/*    */     //   1540: invokevirtual _19 : ()Ljava/lang/Object;
/*    */     //   1543: astore #40
/*    */     //   1545: dup
/*    */     //   1546: astore #39
/*    */     //   1548: aload #40
/*    */     //   1550: if_acmpne -> 1557
/*    */     //   1553: iconst_1
/*    */     //   1554: goto -> 1615
/*    */     //   1557: aload #39
/*    */     //   1559: ifnonnull -> 1566
/*    */     //   1562: iconst_0
/*    */     //   1563: goto -> 1615
/*    */     //   1566: aload #39
/*    */     //   1568: instanceof java/lang/Number
/*    */     //   1571: ifeq -> 1587
/*    */     //   1574: aload #39
/*    */     //   1576: checkcast java/lang/Number
/*    */     //   1579: aload #40
/*    */     //   1581: invokestatic equalsNumObject : (Ljava/lang/Number;Ljava/lang/Object;)Z
/*    */     //   1584: goto -> 1615
/*    */     //   1587: aload #39
/*    */     //   1589: instanceof java/lang/Character
/*    */     //   1592: ifeq -> 1608
/*    */     //   1595: aload #39
/*    */     //   1597: checkcast java/lang/Character
/*    */     //   1600: aload #40
/*    */     //   1602: invokestatic equalsCharObject : (Ljava/lang/Character;Ljava/lang/Object;)Z
/*    */     //   1605: goto -> 1615
/*    */     //   1608: aload #39
/*    */     //   1610: aload #40
/*    */     //   1612: invokevirtual equals : (Ljava/lang/Object;)Z
/*    */     //   1615: ifeq -> 1799
/*    */     //   1618: aload_0
/*    */     //   1619: invokevirtual _20 : ()Ljava/lang/Object;
/*    */     //   1622: aload #45
/*    */     //   1624: invokevirtual _20 : ()Ljava/lang/Object;
/*    */     //   1627: astore #42
/*    */     //   1629: dup
/*    */     //   1630: astore #41
/*    */     //   1632: aload #42
/*    */     //   1634: if_acmpne -> 1641
/*    */     //   1637: iconst_1
/*    */     //   1638: goto -> 1699
/*    */     //   1641: aload #41
/*    */     //   1643: ifnonnull -> 1650
/*    */     //   1646: iconst_0
/*    */     //   1647: goto -> 1699
/*    */     //   1650: aload #41
/*    */     //   1652: instanceof java/lang/Number
/*    */     //   1655: ifeq -> 1671
/*    */     //   1658: aload #41
/*    */     //   1660: checkcast java/lang/Number
/*    */     //   1663: aload #42
/*    */     //   1665: invokestatic equalsNumObject : (Ljava/lang/Number;Ljava/lang/Object;)Z
/*    */     //   1668: goto -> 1699
/*    */     //   1671: aload #41
/*    */     //   1673: instanceof java/lang/Character
/*    */     //   1676: ifeq -> 1692
/*    */     //   1679: aload #41
/*    */     //   1681: checkcast java/lang/Character
/*    */     //   1684: aload #42
/*    */     //   1686: invokestatic equalsCharObject : (Ljava/lang/Character;Ljava/lang/Object;)Z
/*    */     //   1689: goto -> 1699
/*    */     //   1692: aload #41
/*    */     //   1694: aload #42
/*    */     //   1696: invokevirtual equals : (Ljava/lang/Object;)Z
/*    */     //   1699: ifeq -> 1799
/*    */     //   1702: aload_0
/*    */     //   1703: invokevirtual _21 : ()Ljava/lang/Object;
/*    */     //   1706: aload #45
/*    */     //   1708: invokevirtual _21 : ()Ljava/lang/Object;
/*    */     //   1711: astore #44
/*    */     //   1713: dup
/*    */     //   1714: astore #43
/*    */     //   1716: aload #44
/*    */     //   1718: if_acmpne -> 1725
/*    */     //   1721: iconst_1
/*    */     //   1722: goto -> 1783
/*    */     //   1725: aload #43
/*    */     //   1727: ifnonnull -> 1734
/*    */     //   1730: iconst_0
/*    */     //   1731: goto -> 1783
/*    */     //   1734: aload #43
/*    */     //   1736: instanceof java/lang/Number
/*    */     //   1739: ifeq -> 1755
/*    */     //   1742: aload #43
/*    */     //   1744: checkcast java/lang/Number
/*    */     //   1747: aload #44
/*    */     //   1749: invokestatic equalsNumObject : (Ljava/lang/Number;Ljava/lang/Object;)Z
/*    */     //   1752: goto -> 1783
/*    */     //   1755: aload #43
/*    */     //   1757: instanceof java/lang/Character
/*    */     //   1760: ifeq -> 1776
/*    */     //   1763: aload #43
/*    */     //   1765: checkcast java/lang/Character
/*    */     //   1768: aload #44
/*    */     //   1770: invokestatic equalsCharObject : (Ljava/lang/Character;Ljava/lang/Object;)Z
/*    */     //   1773: goto -> 1783
/*    */     //   1776: aload #43
/*    */     //   1778: aload #44
/*    */     //   1780: invokevirtual equals : (Ljava/lang/Object;)Z
/*    */     //   1783: ifeq -> 1799
/*    */     //   1786: aload #45
/*    */     //   1788: aload_0
/*    */     //   1789: invokevirtual canEqual : (Ljava/lang/Object;)Z
/*    */     //   1792: ifeq -> 1799
/*    */     //   1795: iconst_1
/*    */     //   1796: goto -> 1800
/*    */     //   1799: iconst_0
/*    */     //   1800: ifeq -> 1807
/*    */     //   1803: iconst_1
/*    */     //   1804: goto -> 1808
/*    */     //   1807: iconst_0
/*    */     //   1808: ireturn
/*    */     // Line number table:
/*    */     //   Java source line number -> byte code offset
/*    */     //   #38	-> 0
/*    */     //   #236	-> 12
/*    */     //   #38	-> 19
/*    */     // Local variable table:
/*    */     //   start	length	slot	name	descriptor
/*    */     //   0	1809	0	this	Lscala/Tuple21;
/*    */     //   0	1809	1	x$1	Ljava/lang/Object;
/*    */   }
/*    */   
/*    */   public Tuple21(Object _1, Object _2, Object _3, Object _4, Object _5, Object _6, Object _7, Object _8, Object _9, Object _10, Object _11, Object _12, Object _13, Object _14, Object _15, Object _16, Object _17, Object _18, Object _19, Object _20, Object _21) {
/* 38 */     Product$class.$init$(this);
/* 38 */     Product21$class.$init$(this);
/*    */   }
/*    */   
/*    */   public String toString() {
/* 42 */     return (new StringBuilder()).append("(").append(_1()).append(",").append(_2()).append(",").append(_3()).append(",").append(_4()).append(",").append(_5()).append(",").append(_6()).append(",").append(_7()).append(",").append(_8()).append(",").append(_9()).append(",").append(_10()).append(",").append(_11()).append(",").append(_12()).append(",").append(_13()).append(",").append(_14()).append(",").append(_15()).append(",").append(_16()).append(",").append(_17()).append(",").append(_18()).append(",").append(_19()).append(",").append(_20()).append(",").append(_21()).append(")").toString();
/*    */   }
/*    */ }


/* Location:              D:\#source-code\TheFlightSims\TFSLibrary\World2Xplane\World2XPlane.jar!\scala\Tuple21.class
 * Java compiler version: 6 (50.0)
 * JD-Core Version:       1.1.3
 */