/*    */ package scala;
/*    */ 
/*    */ import scala.collection.Iterator;
/*    */ import scala.collection.mutable.StringBuilder;
/*    */ import scala.reflect.ScalaSignature;
/*    */ import scala.runtime.ScalaRunTime$;
/*    */ 
/*    */ @ScalaSignature(bytes = "\006\001\t%g\001B\001\003\001\026\021a\001V;qY\026D$\"A\002\002\013M\034\027\r\\1\004\001UIa\001\005\016\036A\r2\023\006L\n\006\001\035Ya&\r\t\003\021%i\021AA\005\003\025\t\021a!\0218z%\0264\007C\003\005\r\035earDI\023)W%\021QB\001\002\t!J|G-^2uqA\021q\002\005\007\001\t\031\t\002\001\"b\001%\t\021A+M\t\003'Y\001\"\001\003\013\n\005U\021!a\002(pi\"Lgn\032\t\003\021]I!\001\007\002\003\007\005s\027\020\005\002\0205\02111\004\001CC\002I\021!\001\026\032\021\005=iBA\002\020\001\t\013\007!C\001\002UgA\021q\002\t\003\007C\001!)\031\001\n\003\005Q#\004CA\b$\t\031!\003\001\"b\001%\t\021A+\016\t\003\037\031\"aa\n\001\005\006\004\021\"A\001+7!\ty\021\006\002\004+\001\021\025\rA\005\002\003)^\002\"a\004\027\005\r5\002AQ1\001\023\005\t!\006\b\005\002\t_%\021\001G\001\002\b!J|G-^2u!\tA!'\003\0024\005\ta1+\032:jC2L'0\0312mK\"AQ\007\001BK\002\023\005a'\001\002`cU\ta\002\003\0059\001\tE\t\025!\003\017\003\ry\026\007\t\005\tu\001\021)\032!C\001w\005\021qLM\013\0023!AQ\b\001B\tB\003%\021$A\002`e\001B\001b\020\001\003\026\004%\t\001Q\001\003?N*\022\001\b\005\t\005\002\021\t\022)A\0059\005\031ql\r\021\t\021\021\003!Q3A\005\002\025\013!a\030\033\026\003}A\001b\022\001\003\022\003\006IaH\001\004?R\002\003\002C%\001\005+\007I\021\001&\002\005}+T#\001\022\t\0211\003!\021#Q\001\n\t\n1aX\033!\021!q\005A!f\001\n\003y\025AA07+\005)\003\002C)\001\005#\005\013\021B\023\002\007}3\004\005\003\005T\001\tU\r\021\"\001U\003\tyv'F\001)\021!1\006A!E!\002\023A\023aA08A!A\001\f\001BK\002\023\005\021,\001\002`qU\t1\006\003\005\\\001\tE\t\025!\003,\003\ry\006\b\t\005\006;\002!\tAX\001\007y%t\027\016\036 \025\023}\003\027MY2eK\032<\007C\003\005\001\035earDI\023)W!)Q\007\030a\001\035!)!\b\030a\0013!)q\b\030a\0019!)A\t\030a\001?!)\021\n\030a\001E!)a\n\030a\001K!)1\013\030a\001Q!)\001\f\030a\001W!)\021\016\001C!U\006AAo\\*ue&tw\rF\001l!\ta\027/D\001n\025\tqw.\001\003mC:<'\"\0019\002\t)\fg/Y\005\003e6\024aa\025;sS:<\007b\002;\001\003\003%\t!^\001\005G>\004\0300F\007wsnlx0a\001\002\b\005-\021q\002\013\022o\006E\0211CA\013\003/\tI\"a\007\002\036\005}\001C\004\005\001qjdh0!\001\002\006\005%\021Q\002\t\003\037e$Q!E:C\002I\001\"aD>\005\013m\031(\031\001\n\021\005=iH!\002\020t\005\004\021\002CA\b\000\t\025\t3O1\001\023!\ry\0211\001\003\006IM\024\rA\005\t\004\037\005\035A!B\024t\005\004\021\002cA\b\002\f\021)!f\035b\001%A\031q\"a\004\005\0135\032(\031\001\n\t\017U\032\b\023!a\001q\"9!h\035I\001\002\004Q\bbB t!\003\005\r\001 \005\b\tN\004\n\0211\001\021!I5\017%AA\002\005\005\001\002\003(t!\003\005\r!!\002\t\021M\033\b\023!a\001\003\023A\001\002W:\021\002\003\007\021Q\002\005\n\003G\001\021\023!C\001\003K\tabY8qs\022\"WMZ1vYR$\023'\006\n\002(\005u\022qHA!\003\007\n)%a\022\002J\005-SCAA\025U\rq\0211F\026\003\003[\001B!a\f\002:5\021\021\021\007\006\005\003g\t)$A\005v]\016DWmY6fI*\031\021q\007\002\002\025\005tgn\034;bi&|g.\003\003\002<\005E\"!E;oG\",7m[3e-\006\024\030.\0318dK\0221\021#!\tC\002I!aaGA\021\005\004\021BA\002\020\002\"\t\007!\003\002\004\"\003C\021\rA\005\003\007I\005\005\"\031\001\n\005\r\035\n\tC1\001\023\t\031Q\023\021\005b\001%\0211Q&!\tC\002IA\021\"a\024\001#\003%\t!!\025\002\035\r|\007/\037\023eK\032\fW\017\034;%eU\021\0221KA,\0033\nY&!\030\002`\005\005\0241MA3+\t\t)FK\002\032\003W!a!EA'\005\004\021BAB\016\002N\t\007!\003\002\004\037\003\033\022\rA\005\003\007C\0055#\031\001\n\005\r\021\niE1\001\023\t\0319\023Q\nb\001%\0211!&!\024C\002I!a!LA'\005\004\021\002\"CA5\001E\005I\021AA6\0039\031w\016]=%I\0264\027-\0367uIM*\"#!\034\002r\005M\024QOA<\003s\nY(! \002\000U\021\021q\016\026\0049\005-BAB\t\002h\t\007!\003\002\004\034\003O\022\rA\005\003\007=\005\035$\031\001\n\005\r\005\n9G1\001\023\t\031!\023q\rb\001%\0211q%a\032C\002I!aAKA4\005\004\021BAB\027\002h\t\007!\003C\005\002\004\002\t\n\021\"\001\002\006\006q1m\0349zI\021,g-Y;mi\022\"TCEAD\003\027\013i)a$\002\022\006M\025QSAL\0033+\"!!#+\007}\tY\003\002\004\022\003\003\023\rA\005\003\0077\005\005%\031\001\n\005\ry\t\tI1\001\023\t\031\t\023\021\021b\001%\0211A%!!C\002I!aaJAA\005\004\021BA\002\026\002\002\n\007!\003\002\004.\003\003\023\rA\005\005\n\003;\003\021\023!C\001\003?\013abY8qs\022\"WMZ1vYR$S'\006\n\002\"\006\025\026qUAU\003W\013i+a,\0022\006MVCAARU\r\021\0231\006\003\007#\005m%\031\001\n\005\rm\tYJ1\001\023\t\031q\0221\024b\001%\0211\021%a'C\002I!a\001JAN\005\004\021BAB\024\002\034\n\007!\003\002\004+\0037\023\rA\005\003\007[\005m%\031\001\n\t\023\005]\006!%A\005\002\005e\026AD2paf$C-\0324bk2$HEN\013\023\003w\013y,!1\002D\006\025\027qYAe\003\027\fi-\006\002\002>*\032Q%a\013\005\rE\t)L1\001\023\t\031Y\022Q\027b\001%\0211a$!.C\002I!a!IA[\005\004\021BA\002\023\0026\n\007!\003\002\004(\003k\023\rA\005\003\007U\005U&\031\001\n\005\r5\n)L1\001\023\021%\t\t\016AI\001\n\003\t\031.\001\bd_BLH\005Z3gCVdG\017J\034\026%\005U\027\021\\An\003;\fy.!9\002d\006\025\030q]\013\003\003/T3\001KA\026\t\031\t\022q\032b\001%\02111$a4C\002I!aAHAh\005\004\021BAB\021\002P\n\007!\003\002\004%\003\037\024\rA\005\003\007O\005='\031\001\n\005\r)\nyM1\001\023\t\031i\023q\032b\001%!I\0211\036\001\022\002\023\005\021Q^\001\017G>\004\030\020\n3fM\006,H\016\036\0239+I\ty/a=\002v\006]\030\021`A~\003{\fyP!\001\026\005\005E(fA\026\002,\0211\021#!;C\002I!aaGAu\005\004\021BA\002\020\002j\n\007!\003\002\004\"\003S\024\rA\005\003\007I\005%(\031\001\n\005\r\035\nIO1\001\023\t\031Q\023\021\036b\001%\0211Q&!;C\002IA\021B!\002\001\003\003%\tEa\002\002\033A\024x\016Z;diB\023XMZ5y+\005Y\007\"\003B\006\001\005\005I\021\tB\007\003=\001(o\0343vGRLE/\032:bi>\024XC\001B\b!\025\021\tBa\006\027\033\t\021\031BC\002\003\026\t\t!bY8mY\026\034G/[8o\023\021\021IBa\005\003\021%#XM]1u_JD\021B!\b\001\003\003%\tAa\b\002\021\r\fg.R9vC2$BA!\t\003(A\031\001Ba\t\n\007\t\025\"AA\004C_>dW-\0318\t\023\t%\"1DA\001\002\0041\022a\001=%c!I!Q\006\001\002\002\023\005#qF\001\tQ\006\034\bnQ8eKR\021!\021\007\t\004\021\tM\022b\001B\033\005\t\031\021J\034;\t\023\te\002!!A\005B\tm\022AB3rk\006d7\017\006\003\003\"\tu\002\"\003B\025\005o\t\t\0211\001\027\017%\021\tEAA\001\022\003\021\031%\001\004UkBdW\r\017\t\004\021\t\025c\001C\001\003\003\003E\tAa\022\024\t\t\025s!\r\005\b;\n\025C\021\001B&)\t\021\031\005\003\005j\005\013\n\t\021\"\022k\021)\021\tF!\022\002\002\023\005%1K\001\006CB\004H._\013\023\005+\022YFa\030\003d\t\035$1\016B8\005g\0229\b\006\n\003X\te$1\020B?\005\022\tIa!\003\006\n\035\005C\005\005\001\0053\022iF!\031\003f\t%$Q\016B9\005k\0022a\004B.\t\031\t\"q\nb\001%A\031qBa\030\005\rm\021yE1\001\023!\ry!1\r\003\007=\t=#\031\001\n\021\007=\0219\007\002\004\"\005\037\022\rA\005\t\004\037\t-DA\002\023\003P\t\007!\003E\002\020\005_\"aa\nB(\005\004\021\002cA\b\003t\0211!Fa\024C\002I\0012a\004B<\t\031i#q\nb\001%!9QGa\024A\002\te\003b\002\036\003P\001\007!Q\f\005\b\t=\003\031\001B1\021\035!%q\na\001\005KBq!\023B(\001\004\021I\007C\004O\005\037\002\rA!\034\t\017M\023y\0051\001\003r!9\001La\024A\002\tU\004B\003BF\005\013\n\t\021\"!\003\016\0069QO\\1qa2LXC\005BH\0057\023yJa)\003(\n-&q\026BZ\005o#BA!%\003:B)\001Ba%\003\030&\031!Q\023\002\003\r=\003H/[8o!IA\001A!'\003\036\n\005&Q\025BU\005[\023\tL!.\021\007=\021Y\n\002\004\022\005\023\023\rA\005\t\004\037\t}EAB\016\003\n\n\007!\003E\002\020\005G#aA\bBE\005\004\021\002cA\b\003(\0221\021E!#C\002I\0012a\004BV\t\031!#\021\022b\001%A\031qBa,\005\r\035\022II1\001\023!\ry!1\027\003\007U\t%%\031\001\n\021\007=\0219\f\002\004.\005\023\023\rA\005\005\013\005w\023I)!AA\002\t]\025a\001=%a!Q!q\030B#\003\003%IA!1\002\027I,\027\r\032*fg>dg/\032\013\003\005\007\0042\001\034Bc\023\r\0219-\034\002\007\037\nTWm\031;")
/*    */ public class Tuple8<T1, T2, T3, T4, T5, T6, T7, T8> implements Product8<T1, T2, T3, T4, T5, T6, T7, T8>, Product, Serializable {
/*    */   private final T1 _1;
/*    */   
/*    */   private final T2 _2;
/*    */   
/*    */   private final T3 _3;
/*    */   
/*    */   private final T4 _4;
/*    */   
/*    */   private final T5 _5;
/*    */   
/*    */   private final T6 _6;
/*    */   
/*    */   private final T7 _7;
/*    */   
/*    */   private final T8 _8;
/*    */   
/*    */   public int productArity() {
/* 25 */     return Product8$class.productArity(this);
/*    */   }
/*    */   
/*    */   public Object productElement(int n) throws IndexOutOfBoundsException {
/* 25 */     return Product8$class.productElement(this, n);
/*    */   }
/*    */   
/*    */   public T1 _1() {
/* 25 */     return this._1;
/*    */   }
/*    */   
/*    */   public T2 _2() {
/* 25 */     return this._2;
/*    */   }
/*    */   
/*    */   public T3 _3() {
/* 25 */     return this._3;
/*    */   }
/*    */   
/*    */   public T4 _4() {
/* 25 */     return this._4;
/*    */   }
/*    */   
/*    */   public T5 _5() {
/* 25 */     return this._5;
/*    */   }
/*    */   
/*    */   public T6 _6() {
/* 25 */     return this._6;
/*    */   }
/*    */   
/*    */   public T7 _7() {
/* 25 */     return this._7;
/*    */   }
/*    */   
/*    */   public T8 _8() {
/* 25 */     return this._8;
/*    */   }
/*    */   
/*    */   public <T1, T2, T3, T4, T5, T6, T7, T8> Tuple8<T1, T2, T3, T4, T5, T6, T7, T8> copy(Object _1, Object _2, Object _3, Object _4, Object _5, Object _6, Object _7, Object _8) {
/* 25 */     return new Tuple8((T1)_1, (T2)_2, (T3)_3, (T4)_4, (T5)_5, (T6)_6, (T7)_7, (T8)_8);
/*    */   }
/*    */   
/*    */   public <T1, T2, T3, T4, T5, T6, T7, T8> T1 copy$default$1() {
/* 25 */     return _1();
/*    */   }
/*    */   
/*    */   public <T1, T2, T3, T4, T5, T6, T7, T8> T2 copy$default$2() {
/* 25 */     return _2();
/*    */   }
/*    */   
/*    */   public <T1, T2, T3, T4, T5, T6, T7, T8> T3 copy$default$3() {
/* 25 */     return _3();
/*    */   }
/*    */   
/*    */   public <T1, T2, T3, T4, T5, T6, T7, T8> T4 copy$default$4() {
/* 25 */     return _4();
/*    */   }
/*    */   
/*    */   public <T1, T2, T3, T4, T5, T6, T7, T8> T5 copy$default$5() {
/* 25 */     return _5();
/*    */   }
/*    */   
/*    */   public <T1, T2, T3, T4, T5, T6, T7, T8> T6 copy$default$6() {
/* 25 */     return _6();
/*    */   }
/*    */   
/*    */   public <T1, T2, T3, T4, T5, T6, T7, T8> T7 copy$default$7() {
/* 25 */     return _7();
/*    */   }
/*    */   
/*    */   public <T1, T2, T3, T4, T5, T6, T7, T8> T8 copy$default$8() {
/* 25 */     return _8();
/*    */   }
/*    */   
/*    */   public String productPrefix() {
/* 25 */     return "Tuple8";
/*    */   }
/*    */   
/*    */   public Iterator<Object> productIterator() {
/* 25 */     return ScalaRunTime$.MODULE$.typedProductIterator(this);
/*    */   }
/*    */   
/*    */   public boolean canEqual(Object x$1) {
/* 25 */     return x$1 instanceof Tuple8;
/*    */   }
/*    */   
/*    */   public int hashCode() {
/* 25 */     return ScalaRunTime$.MODULE$._hashCode(this);
/*    */   }
/*    */   
/*    */   public boolean equals(Object x$1) {
/*    */     // Byte code:
/*    */     //   0: aload_0
/*    */     //   1: aload_1
/*    */     //   2: if_acmpeq -> 711
/*    */     //   5: aload_1
/*    */     //   6: instanceof scala/Tuple8
/*    */     //   9: ifeq -> 17
/*    */     //   12: iconst_1
/*    */     //   13: istore_2
/*    */     //   14: goto -> 19
/*    */     //   17: iconst_0
/*    */     //   18: istore_2
/*    */     //   19: iload_2
/*    */     //   20: ifeq -> 715
/*    */     //   23: aload_1
/*    */     //   24: checkcast scala/Tuple8
/*    */     //   27: astore #19
/*    */     //   29: aload_0
/*    */     //   30: invokevirtual _1 : ()Ljava/lang/Object;
/*    */     //   33: aload #19
/*    */     //   35: invokevirtual _1 : ()Ljava/lang/Object;
/*    */     //   38: astore #4
/*    */     //   40: dup
/*    */     //   41: astore_3
/*    */     //   42: aload #4
/*    */     //   44: if_acmpne -> 51
/*    */     //   47: iconst_1
/*    */     //   48: goto -> 103
/*    */     //   51: aload_3
/*    */     //   52: ifnonnull -> 59
/*    */     //   55: iconst_0
/*    */     //   56: goto -> 103
/*    */     //   59: aload_3
/*    */     //   60: instanceof java/lang/Number
/*    */     //   63: ifeq -> 78
/*    */     //   66: aload_3
/*    */     //   67: checkcast java/lang/Number
/*    */     //   70: aload #4
/*    */     //   72: invokestatic equalsNumObject : (Ljava/lang/Number;Ljava/lang/Object;)Z
/*    */     //   75: goto -> 103
/*    */     //   78: aload_3
/*    */     //   79: instanceof java/lang/Character
/*    */     //   82: ifeq -> 97
/*    */     //   85: aload_3
/*    */     //   86: checkcast java/lang/Character
/*    */     //   89: aload #4
/*    */     //   91: invokestatic equalsCharObject : (Ljava/lang/Character;Ljava/lang/Object;)Z
/*    */     //   94: goto -> 103
/*    */     //   97: aload_3
/*    */     //   98: aload #4
/*    */     //   100: invokevirtual equals : (Ljava/lang/Object;)Z
/*    */     //   103: ifeq -> 707
/*    */     //   106: aload_0
/*    */     //   107: invokevirtual _2 : ()Ljava/lang/Object;
/*    */     //   110: aload #19
/*    */     //   112: invokevirtual _2 : ()Ljava/lang/Object;
/*    */     //   115: astore #6
/*    */     //   117: dup
/*    */     //   118: astore #5
/*    */     //   120: aload #6
/*    */     //   122: if_acmpne -> 129
/*    */     //   125: iconst_1
/*    */     //   126: goto -> 187
/*    */     //   129: aload #5
/*    */     //   131: ifnonnull -> 138
/*    */     //   134: iconst_0
/*    */     //   135: goto -> 187
/*    */     //   138: aload #5
/*    */     //   140: instanceof java/lang/Number
/*    */     //   143: ifeq -> 159
/*    */     //   146: aload #5
/*    */     //   148: checkcast java/lang/Number
/*    */     //   151: aload #6
/*    */     //   153: invokestatic equalsNumObject : (Ljava/lang/Number;Ljava/lang/Object;)Z
/*    */     //   156: goto -> 187
/*    */     //   159: aload #5
/*    */     //   161: instanceof java/lang/Character
/*    */     //   164: ifeq -> 180
/*    */     //   167: aload #5
/*    */     //   169: checkcast java/lang/Character
/*    */     //   172: aload #6
/*    */     //   174: invokestatic equalsCharObject : (Ljava/lang/Character;Ljava/lang/Object;)Z
/*    */     //   177: goto -> 187
/*    */     //   180: aload #5
/*    */     //   182: aload #6
/*    */     //   184: invokevirtual equals : (Ljava/lang/Object;)Z
/*    */     //   187: ifeq -> 707
/*    */     //   190: aload_0
/*    */     //   191: invokevirtual _3 : ()Ljava/lang/Object;
/*    */     //   194: aload #19
/*    */     //   196: invokevirtual _3 : ()Ljava/lang/Object;
/*    */     //   199: astore #8
/*    */     //   201: dup
/*    */     //   202: astore #7
/*    */     //   204: aload #8
/*    */     //   206: if_acmpne -> 213
/*    */     //   209: iconst_1
/*    */     //   210: goto -> 271
/*    */     //   213: aload #7
/*    */     //   215: ifnonnull -> 222
/*    */     //   218: iconst_0
/*    */     //   219: goto -> 271
/*    */     //   222: aload #7
/*    */     //   224: instanceof java/lang/Number
/*    */     //   227: ifeq -> 243
/*    */     //   230: aload #7
/*    */     //   232: checkcast java/lang/Number
/*    */     //   235: aload #8
/*    */     //   237: invokestatic equalsNumObject : (Ljava/lang/Number;Ljava/lang/Object;)Z
/*    */     //   240: goto -> 271
/*    */     //   243: aload #7
/*    */     //   245: instanceof java/lang/Character
/*    */     //   248: ifeq -> 264
/*    */     //   251: aload #7
/*    */     //   253: checkcast java/lang/Character
/*    */     //   256: aload #8
/*    */     //   258: invokestatic equalsCharObject : (Ljava/lang/Character;Ljava/lang/Object;)Z
/*    */     //   261: goto -> 271
/*    */     //   264: aload #7
/*    */     //   266: aload #8
/*    */     //   268: invokevirtual equals : (Ljava/lang/Object;)Z
/*    */     //   271: ifeq -> 707
/*    */     //   274: aload_0
/*    */     //   275: invokevirtual _4 : ()Ljava/lang/Object;
/*    */     //   278: aload #19
/*    */     //   280: invokevirtual _4 : ()Ljava/lang/Object;
/*    */     //   283: astore #10
/*    */     //   285: dup
/*    */     //   286: astore #9
/*    */     //   288: aload #10
/*    */     //   290: if_acmpne -> 297
/*    */     //   293: iconst_1
/*    */     //   294: goto -> 355
/*    */     //   297: aload #9
/*    */     //   299: ifnonnull -> 306
/*    */     //   302: iconst_0
/*    */     //   303: goto -> 355
/*    */     //   306: aload #9
/*    */     //   308: instanceof java/lang/Number
/*    */     //   311: ifeq -> 327
/*    */     //   314: aload #9
/*    */     //   316: checkcast java/lang/Number
/*    */     //   319: aload #10
/*    */     //   321: invokestatic equalsNumObject : (Ljava/lang/Number;Ljava/lang/Object;)Z
/*    */     //   324: goto -> 355
/*    */     //   327: aload #9
/*    */     //   329: instanceof java/lang/Character
/*    */     //   332: ifeq -> 348
/*    */     //   335: aload #9
/*    */     //   337: checkcast java/lang/Character
/*    */     //   340: aload #10
/*    */     //   342: invokestatic equalsCharObject : (Ljava/lang/Character;Ljava/lang/Object;)Z
/*    */     //   345: goto -> 355
/*    */     //   348: aload #9
/*    */     //   350: aload #10
/*    */     //   352: invokevirtual equals : (Ljava/lang/Object;)Z
/*    */     //   355: ifeq -> 707
/*    */     //   358: aload_0
/*    */     //   359: invokevirtual _5 : ()Ljava/lang/Object;
/*    */     //   362: aload #19
/*    */     //   364: invokevirtual _5 : ()Ljava/lang/Object;
/*    */     //   367: astore #12
/*    */     //   369: dup
/*    */     //   370: astore #11
/*    */     //   372: aload #12
/*    */     //   374: if_acmpne -> 381
/*    */     //   377: iconst_1
/*    */     //   378: goto -> 439
/*    */     //   381: aload #11
/*    */     //   383: ifnonnull -> 390
/*    */     //   386: iconst_0
/*    */     //   387: goto -> 439
/*    */     //   390: aload #11
/*    */     //   392: instanceof java/lang/Number
/*    */     //   395: ifeq -> 411
/*    */     //   398: aload #11
/*    */     //   400: checkcast java/lang/Number
/*    */     //   403: aload #12
/*    */     //   405: invokestatic equalsNumObject : (Ljava/lang/Number;Ljava/lang/Object;)Z
/*    */     //   408: goto -> 439
/*    */     //   411: aload #11
/*    */     //   413: instanceof java/lang/Character
/*    */     //   416: ifeq -> 432
/*    */     //   419: aload #11
/*    */     //   421: checkcast java/lang/Character
/*    */     //   424: aload #12
/*    */     //   426: invokestatic equalsCharObject : (Ljava/lang/Character;Ljava/lang/Object;)Z
/*    */     //   429: goto -> 439
/*    */     //   432: aload #11
/*    */     //   434: aload #12
/*    */     //   436: invokevirtual equals : (Ljava/lang/Object;)Z
/*    */     //   439: ifeq -> 707
/*    */     //   442: aload_0
/*    */     //   443: invokevirtual _6 : ()Ljava/lang/Object;
/*    */     //   446: aload #19
/*    */     //   448: invokevirtual _6 : ()Ljava/lang/Object;
/*    */     //   451: astore #14
/*    */     //   453: dup
/*    */     //   454: astore #13
/*    */     //   456: aload #14
/*    */     //   458: if_acmpne -> 465
/*    */     //   461: iconst_1
/*    */     //   462: goto -> 523
/*    */     //   465: aload #13
/*    */     //   467: ifnonnull -> 474
/*    */     //   470: iconst_0
/*    */     //   471: goto -> 523
/*    */     //   474: aload #13
/*    */     //   476: instanceof java/lang/Number
/*    */     //   479: ifeq -> 495
/*    */     //   482: aload #13
/*    */     //   484: checkcast java/lang/Number
/*    */     //   487: aload #14
/*    */     //   489: invokestatic equalsNumObject : (Ljava/lang/Number;Ljava/lang/Object;)Z
/*    */     //   492: goto -> 523
/*    */     //   495: aload #13
/*    */     //   497: instanceof java/lang/Character
/*    */     //   500: ifeq -> 516
/*    */     //   503: aload #13
/*    */     //   505: checkcast java/lang/Character
/*    */     //   508: aload #14
/*    */     //   510: invokestatic equalsCharObject : (Ljava/lang/Character;Ljava/lang/Object;)Z
/*    */     //   513: goto -> 523
/*    */     //   516: aload #13
/*    */     //   518: aload #14
/*    */     //   520: invokevirtual equals : (Ljava/lang/Object;)Z
/*    */     //   523: ifeq -> 707
/*    */     //   526: aload_0
/*    */     //   527: invokevirtual _7 : ()Ljava/lang/Object;
/*    */     //   530: aload #19
/*    */     //   532: invokevirtual _7 : ()Ljava/lang/Object;
/*    */     //   535: astore #16
/*    */     //   537: dup
/*    */     //   538: astore #15
/*    */     //   540: aload #16
/*    */     //   542: if_acmpne -> 549
/*    */     //   545: iconst_1
/*    */     //   546: goto -> 607
/*    */     //   549: aload #15
/*    */     //   551: ifnonnull -> 558
/*    */     //   554: iconst_0
/*    */     //   555: goto -> 607
/*    */     //   558: aload #15
/*    */     //   560: instanceof java/lang/Number
/*    */     //   563: ifeq -> 579
/*    */     //   566: aload #15
/*    */     //   568: checkcast java/lang/Number
/*    */     //   571: aload #16
/*    */     //   573: invokestatic equalsNumObject : (Ljava/lang/Number;Ljava/lang/Object;)Z
/*    */     //   576: goto -> 607
/*    */     //   579: aload #15
/*    */     //   581: instanceof java/lang/Character
/*    */     //   584: ifeq -> 600
/*    */     //   587: aload #15
/*    */     //   589: checkcast java/lang/Character
/*    */     //   592: aload #16
/*    */     //   594: invokestatic equalsCharObject : (Ljava/lang/Character;Ljava/lang/Object;)Z
/*    */     //   597: goto -> 607
/*    */     //   600: aload #15
/*    */     //   602: aload #16
/*    */     //   604: invokevirtual equals : (Ljava/lang/Object;)Z
/*    */     //   607: ifeq -> 707
/*    */     //   610: aload_0
/*    */     //   611: invokevirtual _8 : ()Ljava/lang/Object;
/*    */     //   614: aload #19
/*    */     //   616: invokevirtual _8 : ()Ljava/lang/Object;
/*    */     //   619: astore #18
/*    */     //   621: dup
/*    */     //   622: astore #17
/*    */     //   624: aload #18
/*    */     //   626: if_acmpne -> 633
/*    */     //   629: iconst_1
/*    */     //   630: goto -> 691
/*    */     //   633: aload #17
/*    */     //   635: ifnonnull -> 642
/*    */     //   638: iconst_0
/*    */     //   639: goto -> 691
/*    */     //   642: aload #17
/*    */     //   644: instanceof java/lang/Number
/*    */     //   647: ifeq -> 663
/*    */     //   650: aload #17
/*    */     //   652: checkcast java/lang/Number
/*    */     //   655: aload #18
/*    */     //   657: invokestatic equalsNumObject : (Ljava/lang/Number;Ljava/lang/Object;)Z
/*    */     //   660: goto -> 691
/*    */     //   663: aload #17
/*    */     //   665: instanceof java/lang/Character
/*    */     //   668: ifeq -> 684
/*    */     //   671: aload #17
/*    */     //   673: checkcast java/lang/Character
/*    */     //   676: aload #18
/*    */     //   678: invokestatic equalsCharObject : (Ljava/lang/Character;Ljava/lang/Object;)Z
/*    */     //   681: goto -> 691
/*    */     //   684: aload #17
/*    */     //   686: aload #18
/*    */     //   688: invokevirtual equals : (Ljava/lang/Object;)Z
/*    */     //   691: ifeq -> 707
/*    */     //   694: aload #19
/*    */     //   696: aload_0
/*    */     //   697: invokevirtual canEqual : (Ljava/lang/Object;)Z
/*    */     //   700: ifeq -> 707
/*    */     //   703: iconst_1
/*    */     //   704: goto -> 708
/*    */     //   707: iconst_0
/*    */     //   708: ifeq -> 715
/*    */     //   711: iconst_1
/*    */     //   712: goto -> 716
/*    */     //   715: iconst_0
/*    */     //   716: ireturn
/*    */     // Line number table:
/*    */     //   Java source line number -> byte code offset
/*    */     //   #25	-> 0
/*    */     //   #236	-> 12
/*    */     //   #25	-> 19
/*    */     // Local variable table:
/*    */     //   start	length	slot	name	descriptor
/*    */     //   0	717	0	this	Lscala/Tuple8;
/*    */     //   0	717	1	x$1	Ljava/lang/Object;
/*    */   }
/*    */   
/*    */   public Tuple8(Object _1, Object _2, Object _3, Object _4, Object _5, Object _6, Object _7, Object _8) {
/* 25 */     Product$class.$init$(this);
/* 25 */     Product8$class.$init$(this);
/*    */   }
/*    */   
/*    */   public String toString() {
/* 28 */     return (new StringBuilder()).append("(").append(_1()).append(",").append(_2()).append(",").append(_3()).append(",").append(_4()).append(",").append(_5()).append(",").append(_6()).append(",").append(_7()).append(",").append(_8()).append(")").toString();
/*    */   }
/*    */ }


/* Location:              D:\#source-code\TheFlightSims\TFSLibrary\World2Xplane\World2XPlane.jar!\scala\Tuple8.class
 * Java compiler version: 6 (50.0)
 * JD-Core Version:       1.1.3
 */