/*    */ package scala;
/*    */ 
/*    */ import scala.collection.Iterator;
/*    */ import scala.collection.mutable.StringBuilder;
/*    */ import scala.reflect.ScalaSignature;
/*    */ import scala.runtime.ScalaRunTime$;
/*    */ 
/*    */ @ScalaSignature(bytes = "\006\001\025%f\001B\001\003\001\026\021q\001V;qY\026\fdGC\001\004\003\025\0318-\0317b\007\001)\022C\002\t\033;\001\032c%\013\0270eUB4HP!E'\025\001qa\003$J!\tA\021\"D\001\003\023\tQ!A\001\004B]f\024VM\032\t\023\0211q\021\004H\020#K!Zc&\r\0338uu\0025)\003\002\016\005\tI\001K]8ek\016$\030G\016\t\003\037Aa\001\001\002\004\022\001\021\025\rA\005\002\003)F\n\"a\005\f\021\005!!\022BA\013\003\005\035qu\016\0365j]\036\004\"\001C\f\n\005a\021!aA!osB\021qB\007\003\0077\001!)\031\001\n\003\005Q\023\004CA\b\036\t\031q\002\001\"b\001%\t\021Ak\r\t\003\037\001\"a!\t\001\005\006\004\021\"A\001+5!\ty1\005\002\004%\001\021\025\rA\005\002\003)V\002\"a\004\024\005\r\035\002AQ1\001\023\005\t!f\007\005\002\020S\0211!\006\001CC\002I\021!\001V\034\021\005=aCAB\027\001\t\013\007!C\001\002UqA\021qb\f\003\007a\001!)\031\001\n\003\005QK\004CA\b3\t\031\031\004\001\"b\001%\t\031A+\r\031\021\005=)DA\002\034\001\t\013\007!CA\002UcE\002\"a\004\035\005\re\002AQ1\001\023\005\r!\026G\r\t\003\037m\"a\001\020\001\005\006\004\021\"a\001+2gA\021qB\020\003\007\001!)\031\001\n\003\007Q\013D\007\005\002\020\003\0221!\t\001CC\002I\0211\001V\0316!\tyA\t\002\004F\001\021\025\rA\005\002\004)F2\004C\001\005H\023\tA%AA\004Qe>$Wo\031;\021\005!Q\025BA&\003\0051\031VM]5bY&T\030M\0317f\021!i\005A!f\001\n\003q\025AA02+\005q\001\002\003)\001\005#\005\013\021\002\b\002\007}\013\004\005\003\005S\001\tU\r\021\"\001T\003\ty&'F\001\032\021!)\006A!E!\002\023I\022aA03A!Aq\013\001BK\002\023\005\001,\001\002`gU\tA\004\003\005[\001\tE\t\025!\003\035\003\ry6\007\t\005\t9\002\021)\032!C\001;\006\021q\fN\013\002?!Aq\f\001B\tB\003%q$A\002`i\001B\001\"\031\001\003\026\004%\tAY\001\003?V*\022A\t\005\tI\002\021\t\022)A\005E\005\031q,\016\021\t\021\031\004!Q3A\005\002\035\f!a\030\034\026\003\025B\001\"\033\001\003\022\003\006I!J\001\004?Z\002\003\002C6\001\005+\007I\021\0017\002\005};T#\001\025\t\0219\004!\021#Q\001\n!\n1aX\034!\021!\001\bA!f\001\n\003\t\030AA09+\005Y\003\002C:\001\005#\005\013\021B\026\002\007}C\004\005\003\005v\001\tU\r\021\"\001w\003\ty\026(F\001/\021!A\bA!E!\002\023q\023aA0:A!A!\020\001BK\002\023\00510A\002`cA*\022!\r\005\t{\002\021\t\022)A\005c\005!q,\r\031!\021%y\bA!f\001\n\003\t\t!A\002`cE*\022\001\016\005\n\003\013\001!\021#Q\001\nQ\nAaX\0312A!Q\021\021\002\001\003\026\004%\t!a\003\002\007}\013$'F\0018\021%\ty\001\001B\tB\003%q'\001\003`cI\002\003BCA\n\001\tU\r\021\"\001\002\026\005\031q,M\032\026\003iB\021\"!\007\001\005#\005\013\021\002\036\002\t}\0134\007\t\005\013\003;\001!Q3A\005\002\005}\021aA02iU\tQ\bC\005\002$\001\021\t\022)A\005{\005!q,\r\033!\021)\t9\003\001BK\002\023\005\021\021F\001\004?F*T#\001!\t\023\0055\002A!E!\002\023\001\025\001B02k\001B!\"!\r\001\005+\007I\021AA\032\003\ry\026GN\013\002\007\"I\021q\007\001\003\022\003\006IaQ\001\005?F2\004\005C\004\002<\001!\t!!\020\002\rqJg.\033;?)\t\ny$!\021\002D\005\025\023qIA%\003\027\ni%a\024\002R\005M\023QKA,\0033\nY&!\030\002`A\021\002\002\001\b\0329}\021S\005K\026/cQ:$(\020!D\021\031i\025\021\ba\001\035!1!+!\017A\002eAaaVA\035\001\004a\002B\002/\002:\001\007q\004\003\004b\003s\001\rA\t\005\007M\006e\002\031A\023\t\r-\fI\0041\001)\021\031\001\030\021\ba\001W!1Q/!\017A\0029BaA_A\035\001\004\t\004BB@\002:\001\007A\007C\004\002\n\005e\002\031A\034\t\017\005M\021\021\ba\001u!9\021QDA\035\001\004i\004bBA\024\003s\001\r\001\021\005\b\003c\tI\0041\001D\021\035\t\031\007\001C!\003K\n\001\002^8TiJLgn\032\013\003\003O\002B!!\033\002t5\021\0211\016\006\005\003[\ny'\001\003mC:<'BAA9\003\021Q\027M^1\n\t\005U\0241\016\002\007'R\024\030N\\4\t\023\005e\004!!A\005\002\005m\024\001B2paf,\"%! \002\004\006\035\0251RAH\003'\0139*a'\002 \006\r\026qUAV\003_\013\031,a.\002<\006}FCIA@\003\003\f\031-!2\002H\006%\0271ZAg\003\037\f\t.a5\002V\006]\027\021\\An\003;\fy\016\005\022\t\001\005\005\025QQAE\003\033\013\t*!&\002\032\006u\025\021UAS\003S\013i+!-\0026\006e\026Q\030\t\004\037\005\rEAB\t\002x\t\007!\003E\002\020\003\017#aaGA<\005\004\021\002cA\b\002\f\0221a$a\036C\002I\0012aDAH\t\031\t\023q\017b\001%A\031q\"a%\005\r\021\n9H1\001\023!\ry\021q\023\003\007O\005]$\031\001\n\021\007=\tY\n\002\004+\003o\022\rA\005\t\004\037\005}EAB\027\002x\t\007!\003E\002\020\003G#a\001MA<\005\004\021\002cA\b\002(\02211'a\036C\002I\0012aDAV\t\0311\024q\017b\001%A\031q\"a,\005\re\n9H1\001\023!\ry\0211\027\003\007y\005]$\031\001\n\021\007=\t9\f\002\004@\003o\022\rA\005\t\004\037\005mFA\002\"\002x\t\007!\003E\002\020\003#a!RA<\005\004\021\002\"C'\002xA\005\t\031AAA\021%\021\026q\017I\001\002\004\t)\tC\005X\003o\002\n\0211\001\002\n\"IA,a\036\021\002\003\007\021Q\022\005\nC\006]\004\023!a\001\003#C\021BZA<!\003\005\r!!&\t\023-\f9\b%AA\002\005e\005\"\0039\002xA\005\t\031AAO\021%)\030q\017I\001\002\004\t\t\013C\005{\003o\002\n\0211\001\002&\"Iq0a\036\021\002\003\007\021\021\026\005\013\003\023\t9\b%AA\002\0055\006BCA\n\003o\002\n\0211\001\0022\"Q\021QDA<!\003\005\r!!.\t\025\005\035\022q\017I\001\002\004\tI\f\003\006\0022\005]\004\023!a\001\003{C\021\"a9\001#\003%\t!!:\002\035\r|\007/\037\023eK\032\fW\017\034;%cU\021\023q]A\003\024\tAa\001\003\006\t\035!\021\002B\006\005\033\021yA!\005\003\024\tU!q\003B\r\0057)\"!!;+\0079\tYo\013\002\002nB!\021q^A}\033\t\t\tP\003\003\002t\006U\030!C;oG\",7m[3e\025\r\t9PA\001\013C:tw\016^1uS>t\027\002BA~\003c\024\021#\0368dQ\026\0347.\0323WCJL\027M\\2f\t\031\t\022\021\035b\001%\02111$!9C\002I!aAHAq\005\004\021BAB\021\002b\n\007!\003\002\004%\003C\024\rA\005\003\007O\005\005(\031\001\n\005\r)\n\tO1\001\023\t\031i\023\021\035b\001%\0211\001'!9C\002I!aaMAq\005\004\021BA\002\034\002b\n\007!\003\002\004:\003C\024\rA\005\003\007y\005\005(\031\001\n\005\r}\n\tO1\001\023\t\031\021\025\021\035b\001%\0211Q)!9C\002IA\021Ba\b\001#\003%\tA!\t\002\035\r|\007/\037\023eK\032\fW\017\034;%eU\021#1\005B\024\005S\021YC!\f\0030\tE\"1\007B\033\005o\021IDa\017\003>\t}\"\021\tB\"\005\013*\"A!\n+\007e\tY\017\002\004\022\005;\021\rA\005\003\0077\tu!\031\001\n\005\ry\021iB1\001\023\t\031\t#Q\004b\001%\0211AE!\bC\002I!aa\nB\017\005\004\021BA\002\026\003\036\t\007!\003\002\004.\005;\021\rA\005\003\007a\tu!\031\001\n\005\rM\022iB1\001\023\t\0311$Q\004b\001%\0211\021H!\bC\002I!a\001\020B\017\005\004\021BAB \003\036\t\007!\003\002\004C\005;\021\rA\005\003\007\013\nu!\031\001\n\t\023\t%\003!%A\005\002\t-\023AD2paf$C-\0324bk2$HeM\013#\005\033\022\tFa\025\003V\t]#\021\fB.\005;\022yF!\031\003d\t\025$q\rB5\005W\022iGa\034\026\005\t=#f\001\017\002l\0221\021Ca\022C\002I!aa\007B$\005\004\021BA\002\020\003H\t\007!\003\002\004\"\005\017\022\rA\005\003\007I\t\035#\031\001\n\005\r\035\0229E1\001\023\t\031Q#q\tb\001%\0211QFa\022C\002I!a\001\rB$\005\004\021BAB\032\003H\t\007!\003\002\0047\005\017\022\rA\005\003\007s\t\035#\031\001\n\005\rq\0229E1\001\023\t\031y$q\tb\001%\0211!Ia\022C\002I!a!\022B$\005\004\021\002\"\003B:\001E\005I\021\001B;\0039\031w\016]=%I\0264\027-\0367uIQ*\"Ea\036\003|\tu$q\020BA\005\007\023)Ia\"\003\n\n-%Q\022BH\005#\023\031J!&\003\030\neUC\001B=U\ry\0221\036\003\007#\tE$\031\001\n\005\rm\021\tH1\001\023\t\031q\"\021\017b\001%\0211\021E!\035C\002I!a\001\nB9\005\004\021BAB\024\003r\t\007!\003\002\004+\005c\022\rA\005\003\007[\tE$\031\001\n\005\rA\022\tH1\001\023\t\031\031$\021\017b\001%\0211aG!\035C\002I!a!\017B9\005\004\021BA\002\037\003r\t\007!\003\002\004@\005c\022\rA\005\003\007\005\nE$\031\001\n\005\r\025\023\tH1\001\023\021%\021i\nAI\001\n\003\021y*\001\bd_BLH\005Z3gCVdG\017J\033\026E\t\005&Q\025BT\005S\023YK!,\0030\nE&1\027B[\005o\023ILa/\003>\n}&\021\031Bb+\t\021\031KK\002#\003W$a!\005BN\005\004\021BAB\016\003\034\n\007!\003\002\004\037\0057\023\rA\005\003\007C\tm%\031\001\n\005\r\021\022YJ1\001\023\t\0319#1\024b\001%\0211!Fa'C\002I!a!\fBN\005\004\021BA\002\031\003\034\n\007!\003\002\0044\0057\023\rA\005\003\007m\tm%\031\001\n\005\re\022YJ1\001\023\t\031a$1\024b\001%\0211qHa'C\002I!aA\021BN\005\004\021BAB#\003\034\n\007!\003C\005\003H\002\t\n\021\"\001\003J\006q1m\0349zI\021,g-Y;mi\0222TC\tBf\005\037\024\tNa5\003V\n]'\021\034Bn\005;\024yN!9\003d\n\025(q\035Bu\005W\024i/\006\002\003N*\032Q%a;\005\rE\021)M1\001\023\t\031Y\"Q\031b\001%\0211aD!2C\002I!a!\tBc\005\004\021BA\002\023\003F\n\007!\003\002\004(\005\013\024\rA\005\003\007U\t\025'\031\001\n\005\r5\022)M1\001\023\t\031\001$Q\031b\001%\02111G!2C\002I!aA\016Bc\005\004\021BAB\035\003F\n\007!\003\002\004=\005\013\024\rA\005\003\007\t\025'\031\001\n\005\r\t\023)M1\001\023\t\031)%Q\031b\001%!I!\021\037\001\022\002\023\005!1_\001\017G>\004\030\020\n3fM\006,H\016\036\0238+\t\022)P!?\003|\nu(q`B\001\007\007\031)aa\002\004\n\r-1QBB\b\007#\031\031b!\006\004\030U\021!q\037\026\004Q\005-HAB\t\003p\n\007!\003\002\004\034\005_\024\rA\005\003\007=\t=(\031\001\n\005\r\005\022yO1\001\023\t\031!#q\036b\001%\0211qEa<C\002I!aA\013Bx\005\004\021BAB\027\003p\n\007!\003\002\0041\005_\024\rA\005\003\007g\t=(\031\001\n\005\rY\022yO1\001\023\t\031I$q\036b\001%\0211AHa<C\002I!aa\020Bx\005\004\021BA\002\"\003p\n\007!\003\002\004F\005_\024\rA\005\005\n\0077\001\021\023!C\001\007;\tabY8qs\022\"WMZ1vYR$\003(\006\022\004 \r\r2QEB\024\007S\031Yc!\f\0040\rE21GB\033\007o\031Ida\017\004>\r}2\021I\013\003\007CQ3aKAv\t\031\t2\021\004b\001%\02111d!\007C\002I!aAHB\r\005\004\021BAB\021\004\032\t\007!\003\002\004%\0073\021\rA\005\003\007O\re!\031\001\n\005\r)\032IB1\001\023\t\031i3\021\004b\001%\0211\001g!\007C\002I!aaMB\r\005\004\021BA\002\034\004\032\t\007!\003\002\004:\0073\021\rA\005\003\007y\re!\031\001\n\005\r}\032IB1\001\023\t\031\0215\021\004b\001%\0211Qi!\007C\002IA\021b!\022\001#\003%\taa\022\002\035\r|\007/\037\023eK\032\fW\017\034;%sU\0213\021JB'\007\037\032\tfa\025\004V\r]3\021LB.\007;\032yf!\031\004d\r\0254qMB5\007W*\"aa\023+\0079\nY\017\002\004\022\007\007\022\rA\005\003\0077\r\r#\031\001\n\005\ry\031\031E1\001\023\t\031\t31\tb\001%\0211Aea\021C\002I!aaJB\"\005\004\021BA\002\026\004D\t\007!\003\002\004.\007\007\022\rA\005\003\007a\r\r#\031\001\n\005\rM\032\031E1\001\023\t\031141\tb\001%\0211\021ha\021C\002I!a\001PB\"\005\004\021BAB \004D\t\007!\003\002\004C\007\007\022\rA\005\003\007\013\016\r#\031\001\n\t\023\r=\004!%A\005\002\rE\024aD2paf$C-\0324bk2$H%\r\031\026E\rM4qOB=\007w\032iha \004\002\016\r5QQBD\007\023\033Yi!$\004\020\016E51SBK+\t\031)HK\0022\003W$a!EB7\005\004\021BAB\016\004n\t\007!\003\002\004\037\007[\022\rA\005\003\007C\r5$\031\001\n\005\r\021\032iG1\001\023\t\03193Q\016b\001%\0211!f!\034C\002I!a!LB7\005\004\021BA\002\031\004n\t\007!\003\002\0044\007[\022\rA\005\003\007m\r5$\031\001\n\005\re\032iG1\001\023\t\031a4Q\016b\001%\0211qh!\034C\002I!aAQB7\005\004\021BAB#\004n\t\007!\003C\005\004\032\002\t\n\021\"\001\004\034\006y1m\0349zI\021,g-Y;mi\022\n\024'\006\022\004\036\016\00561UBS\007O\033Ika+\004.\016=6\021WBZ\007k\0339l!/\004<\016u6qX\013\003\007?S3\001NAv\t\031\t2q\023b\001%\02111da&C\002I!aAHBL\005\004\021BAB\021\004\030\n\007!\003\002\004%\007/\023\rA\005\003\007O\r]%\031\001\n\005\r)\0329J1\001\023\t\031i3q\023b\001%\0211\001ga&C\002I!aaMBL\005\004\021BA\002\034\004\030\n\007!\003\002\004:\007/\023\rA\005\003\007y\r]%\031\001\n\005\r}\0329J1\001\023\t\031\0215q\023b\001%\0211Qia&C\002IA\021ba1\001#\003%\ta!2\002\037\r|\007/\037\023eK\032\fW\017\034;%cI*\"ea2\004L\01657qZBi\007'\034)na6\004Z\016m7Q\\Bp\007C\034\031o!:\004h\016%XCABeU\r9\0241\036\003\007#\r\005'\031\001\n\005\rm\031\tM1\001\023\t\031q2\021\031b\001%\0211\021e!1C\002I!a\001JBa\005\004\021BAB\024\004B\n\007!\003\002\004+\007\003\024\rA\005\003\007[\r\005'\031\001\n\005\rA\032\tM1\001\023\t\031\0314\021\031b\001%\0211ag!1C\002I!a!OBa\005\004\021BA\002\037\004B\n\007!\003\002\004@\007\003\024\rA\005\003\007\005\016\005'\031\001\n\005\r\025\033\tM1\001\023\021%\031i\017AI\001\n\003\031y/A\bd_BLH\005Z3gCVdG\017J\0314+\t\032\tp!>\004x\016e81`B\007$\t\001b\001\005\006\021\035A\021\002C\006\t\033!y\001\"\005\005\024U\02111\037\026\004u\005-HAB\t\004l\n\007!\003\002\004\034\007W\024\rA\005\003\007=\r-(\031\001\n\005\r\005\032YO1\001\023\t\031!31\036b\001%\0211qea;C\002I!aAKBv\005\004\021BAB\027\004l\n\007!\003\002\0041\007W\024\rA\005\003\007g\r-(\031\001\n\005\rY\032YO1\001\023\t\031I41\036b\001%\0211Aha;C\002I!aaPBv\005\004\021BA\002\"\004l\n\007!\003\002\004F\007W\024\rA\005\005\n\t/\001\021\023!C\001\t3\tqbY8qs\022\"WMZ1vYR$\023\007N\013#\t7!y\002\"\t\005$\021\025Bq\005C\025\tW!i\003b\f\0052\021MBQ\007C\034\ts!Y\004\"\020\026\005\021u!fA\037\002l\0221\021\003\"\006C\002I!aa\007C\013\005\004\021BA\002\020\005\026\t\007!\003\002\004\"\t+\021\rA\005\003\007I\021U!\031\001\n\005\r\035\")B1\001\023\t\031QCQ\003b\001%\0211Q\006\"\006C\002I!a\001\rC\013\005\004\021BAB\032\005\026\t\007!\003\002\0047\t+\021\rA\005\003\007s\021U!\031\001\n\005\rq\")B1\001\023\t\031yDQ\003b\001%\0211!\t\"\006C\002I!a!\022C\013\005\004\021\002\"\003C!\001E\005I\021\001C\"\003=\031w\016]=%I\0264\027-\0367uIE*TC\tC#\t\023\"Y\005\"\024\005P\021EC1\013C+\t/\"I\006b\027\005^\021}C\021\rC2\tK\"9'\006\002\005H)\032\001)a;\005\rE!yD1\001\023\t\031YBq\bb\001%\0211a\004b\020C\002I!a!\tC \005\004\021BA\002\023\005@\t\007!\003\002\004(\t\021\rA\005\003\007U\021}\"\031\001\n\005\r5\"yD1\001\023\t\031\001Dq\bb\001%\02111\007b\020C\002I!aA\016C \005\004\021BAB\035\005@\t\007!\003\002\004=\t\021\rA\005\003\007\021}\"\031\001\n\005\r\t#yD1\001\023\t\031)Eq\bb\001%!IA1\016\001\022\002\023\005AQN\001\020G>\004\030\020\n3fM\006,H\016\036\0232mU\021Cq\016C:\tk\"9\b\"\037\005|\021uDq\020CA\t\007#)\tb\"\005\n\022-EQ\022CH\t#+\"\001\"\035+\007\r\013Y\017\002\004\022\tS\022\rA\005\003\0077\021%$\031\001\n\005\ry!IG1\001\023\t\031\tC\021\016b\001%\0211A\005\"\033C\002I!aa\nC5\005\004\021BA\002\026\005j\t\007!\003\002\004.\tS\022\rA\005\003\007a\021%$\031\001\n\005\rM\"IG1\001\023\t\0311D\021\016b\001%\0211\021\b\"\033C\002I!a\001\020C5\005\004\021BAB \005j\t\007!\003\002\004C\tS\022\rA\005\003\007\013\022%$\031\001\n\t\023\021U\005!!A\005B\021]\025!\0049s_\022,8\r\036)sK\032L\0070\006\002\002h!IA1\024\001\002\002\023\005CQT\001\020aJ|G-^2u\023R,'/\031;peV\021Aq\024\t\006\tC#9KF\007\003\tGS1\001\"*\003\003)\031w\016\0347fGRLwN\\\005\005\tS#\031K\001\005Ji\026\024\030\r^8s\021%!i\013AA\001\n\003!y+\001\005dC:,\025/^1m)\021!\t\fb.\021\007!!\031,C\002\0056\n\021qAQ8pY\026\fg\016C\005\005:\022-\026\021!a\001-\005\031\001\020J\031\t\023\021u\006!!A\005B\021}\026\001\0035bg\"\034u\016Z3\025\005\021\005\007c\001\005\005D&\031AQ\031\002\003\007%sG\017C\005\005J\002\t\t\021\"\021\005L\0061Q-];bYN$B\001\"-\005N\"IA\021\030Cd\003\003\005\rAF\004\n\t#\024\021\021!E\001\t'\fq\001V;qY\026\fd\007E\002\t\t+4\001\"\001\002\002\002#\005Aq[\n\005\t+<\021\n\003\005\002<\021UG\021\001Cn)\t!\031\016\003\006\002d\021U\027\021!C#\003KB!\002\"9\005V\006\005I\021\021Cr\003\025\t\007\017\0357z+\t\")\017b;\005p\022MHq\037C~\t,\031!b\002\006\f\025=Q1CC\f\0137)y\"b\t\006(Q\021Cq]C\025\013W)i#b\f\0062\025MRQGC\034\013s)Y$\"\020\006@\025\005S1IC#\013\017\002\"\005\003\001\005j\0225H\021\037C{\ts$i0\"\001\006\006\025%QQBC\t\013+)I\"\"\b\006\"\025\025\002cA\b\005l\0221\021\003b8C\002I\0012a\004Cx\t\031YBq\034b\001%A\031q\002b=\005\ry!yN1\001\023!\ryAq\037\003\007C\021}'\031\001\n\021\007=!Y\020\002\004%\t?\024\rA\005\t\004\037\021}HAB\024\005`\n\007!\003E\002\020\013\007!aA\013Cp\005\004\021\002cA\b\006\b\0211Q\006b8C\002I\0012aDC\006\t\031\001Dq\034b\001%A\031q\"b\004\005\rM\"yN1\001\023!\ryQ1\003\003\007m\021}'\031\001\n\021\007=)9\002\002\004:\t?\024\rA\005\t\004\037\025mAA\002\037\005`\n\007!\003E\002\020\013?!aa\020Cp\005\004\021\002cA\b\006$\0211!\tb8C\002I\0012aDC\024\t\031)Eq\034b\001%!9Q\nb8A\002\021%\bb\002*\005`\002\007AQ\036\005\b/\022}\007\031\001Cy\021\035aFq\034a\001\tkDq!\031Cp\001\004!I\020C\004g\t?\004\r\001\"@\t\017-$y\0161\001\006\002!9\001\017b8A\002\025\025\001bB;\005`\002\007Q\021\002\005\bu\022}\007\031AC\007\021\035yHq\034a\001\013#A\001\"!\003\005`\002\007QQ\003\005\t\003'!y\0161\001\006\032!A\021Q\004Cp\001\004)i\002\003\005\002(\021}\007\031AC\021\021!\t\t\004b8A\002\025\025\002BCC&\t+\f\t\021\"!\006N\0059QO\\1qa2LXCIC(\0137*y&b\031\006h\025-TqNC:\013o*Y(b \006\004\026\035U1RCH\013'+9\n\006\003\006R\025e\005#\002\005\006T\025]\023bAC+\005\t1q\n\035;j_:\004\"\005\003\001\006Z\025uS\021MC3\013S*i'\"\035\006v\025eTQPCA\013\013+I)\"$\006\022\026U\005cA\b\006\\\0211\021#\"\023C\002I\0012aDC0\t\031YR\021\nb\001%A\031q\"b\031\005\ry)IE1\001\023!\ryQq\r\003\007C\025%#\031\001\n\021\007=)Y\007\002\004%\013\023\022\rA\005\t\004\037\025=DAB\024\006J\t\007!\003E\002\020\013g\"aAKC%\005\004\021\002cA\b\006x\0211Q&\"\023C\002I\0012aDC>\t\031\001T\021\nb\001%A\031q\"b \005\rM*IE1\001\023!\ryQ1\021\003\007m\025%#\031\001\n\021\007=)9\t\002\004:\013\023\022\rA\005\t\004\037\025-EA\002\037\006J\t\007!\003E\002\020\013\037#aaPC%\005\004\021\002cA\b\006\024\0221!)\"\023C\002I\0012aDCL\t\031)U\021\nb\001%!QQ1TC%\003\003\005\r!b\026\002\007a$\003\007\003\006\006 \022U\027\021!C\005\013C\0131B]3bIJ+7o\0347wKR\021Q1\025\t\005\003S*)+\003\003\006(\006-$AB(cU\026\034G\017")
/*    */ public class Tuple16<T1, T2, T3, T4, T5, T6, T7, T8, T9, T10, T11, T12, T13, T14, T15, T16> implements Product16<T1, T2, T3, T4, T5, T6, T7, T8, T9, T10, T11, T12, T13, T14, T15, T16>, Product, Serializable {
/*    */   private final T1 _1;
/*    */   
/*    */   private final T2 _2;
/*    */   
/*    */   private final T3 _3;
/*    */   
/*    */   private final T4 _4;
/*    */   
/*    */   private final T5 _5;
/*    */   
/*    */   private final T6 _6;
/*    */   
/*    */   private final T7 _7;
/*    */   
/*    */   private final T8 _8;
/*    */   
/*    */   private final T9 _9;
/*    */   
/*    */   private final T10 _10;
/*    */   
/*    */   private final T11 _11;
/*    */   
/*    */   private final T12 _12;
/*    */   
/*    */   private final T13 _13;
/*    */   
/*    */   private final T14 _14;
/*    */   
/*    */   private final T15 _15;
/*    */   
/*    */   private final T16 _16;
/*    */   
/*    */   public int productArity() {
/* 33 */     return Product16$class.productArity(this);
/*    */   }
/*    */   
/*    */   public Object productElement(int n) throws IndexOutOfBoundsException {
/* 33 */     return Product16$class.productElement(this, n);
/*    */   }
/*    */   
/*    */   public T1 _1() {
/* 33 */     return this._1;
/*    */   }
/*    */   
/*    */   public T2 _2() {
/* 33 */     return this._2;
/*    */   }
/*    */   
/*    */   public T3 _3() {
/* 33 */     return this._3;
/*    */   }
/*    */   
/*    */   public T4 _4() {
/* 33 */     return this._4;
/*    */   }
/*    */   
/*    */   public T5 _5() {
/* 33 */     return this._5;
/*    */   }
/*    */   
/*    */   public T6 _6() {
/* 33 */     return this._6;
/*    */   }
/*    */   
/*    */   public T7 _7() {
/* 33 */     return this._7;
/*    */   }
/*    */   
/*    */   public T8 _8() {
/* 33 */     return this._8;
/*    */   }
/*    */   
/*    */   public T9 _9() {
/* 33 */     return this._9;
/*    */   }
/*    */   
/*    */   public T10 _10() {
/* 33 */     return this._10;
/*    */   }
/*    */   
/*    */   public T11 _11() {
/* 33 */     return this._11;
/*    */   }
/*    */   
/*    */   public T12 _12() {
/* 33 */     return this._12;
/*    */   }
/*    */   
/*    */   public T13 _13() {
/* 33 */     return this._13;
/*    */   }
/*    */   
/*    */   public T14 _14() {
/* 33 */     return this._14;
/*    */   }
/*    */   
/*    */   public T15 _15() {
/* 33 */     return this._15;
/*    */   }
/*    */   
/*    */   public T16 _16() {
/* 33 */     return this._16;
/*    */   }
/*    */   
/*    */   public <T1, T2, T3, T4, T5, T6, T7, T8, T9, T10, T11, T12, T13, T14, T15, T16> Tuple16<T1, T2, T3, T4, T5, T6, T7, T8, T9, T10, T11, T12, T13, T14, T15, T16> copy(Object _1, Object _2, Object _3, Object _4, Object _5, Object _6, Object _7, Object _8, Object _9, Object _10, Object _11, Object _12, Object _13, Object _14, Object _15, Object _16) {
/* 33 */     return new Tuple16((T1)_1, (T2)_2, (T3)_3, (T4)_4, (T5)_5, (T6)_6, (T7)_7, (T8)_8, (T9)_9, (T10)_10, (T11)_11, (T12)_12, (T13)_13, (T14)_14, (T15)_15, (T16)_16);
/*    */   }
/*    */   
/*    */   public <T1, T2, T3, T4, T5, T6, T7, T8, T9, T10, T11, T12, T13, T14, T15, T16> T1 copy$default$1() {
/* 33 */     return _1();
/*    */   }
/*    */   
/*    */   public <T1, T2, T3, T4, T5, T6, T7, T8, T9, T10, T11, T12, T13, T14, T15, T16> T2 copy$default$2() {
/* 33 */     return _2();
/*    */   }
/*    */   
/*    */   public <T1, T2, T3, T4, T5, T6, T7, T8, T9, T10, T11, T12, T13, T14, T15, T16> T3 copy$default$3() {
/* 33 */     return _3();
/*    */   }
/*    */   
/*    */   public <T1, T2, T3, T4, T5, T6, T7, T8, T9, T10, T11, T12, T13, T14, T15, T16> T4 copy$default$4() {
/* 33 */     return _4();
/*    */   }
/*    */   
/*    */   public <T1, T2, T3, T4, T5, T6, T7, T8, T9, T10, T11, T12, T13, T14, T15, T16> T5 copy$default$5() {
/* 33 */     return _5();
/*    */   }
/*    */   
/*    */   public <T1, T2, T3, T4, T5, T6, T7, T8, T9, T10, T11, T12, T13, T14, T15, T16> T6 copy$default$6() {
/* 33 */     return _6();
/*    */   }
/*    */   
/*    */   public <T1, T2, T3, T4, T5, T6, T7, T8, T9, T10, T11, T12, T13, T14, T15, T16> T7 copy$default$7() {
/* 33 */     return _7();
/*    */   }
/*    */   
/*    */   public <T1, T2, T3, T4, T5, T6, T7, T8, T9, T10, T11, T12, T13, T14, T15, T16> T8 copy$default$8() {
/* 33 */     return _8();
/*    */   }
/*    */   
/*    */   public <T1, T2, T3, T4, T5, T6, T7, T8, T9, T10, T11, T12, T13, T14, T15, T16> T9 copy$default$9() {
/* 33 */     return _9();
/*    */   }
/*    */   
/*    */   public <T1, T2, T3, T4, T5, T6, T7, T8, T9, T10, T11, T12, T13, T14, T15, T16> T10 copy$default$10() {
/* 33 */     return _10();
/*    */   }
/*    */   
/*    */   public <T1, T2, T3, T4, T5, T6, T7, T8, T9, T10, T11, T12, T13, T14, T15, T16> T11 copy$default$11() {
/* 33 */     return _11();
/*    */   }
/*    */   
/*    */   public <T1, T2, T3, T4, T5, T6, T7, T8, T9, T10, T11, T12, T13, T14, T15, T16> T12 copy$default$12() {
/* 33 */     return _12();
/*    */   }
/*    */   
/*    */   public <T1, T2, T3, T4, T5, T6, T7, T8, T9, T10, T11, T12, T13, T14, T15, T16> T13 copy$default$13() {
/* 33 */     return _13();
/*    */   }
/*    */   
/*    */   public <T1, T2, T3, T4, T5, T6, T7, T8, T9, T10, T11, T12, T13, T14, T15, T16> T14 copy$default$14() {
/* 33 */     return _14();
/*    */   }
/*    */   
/*    */   public <T1, T2, T3, T4, T5, T6, T7, T8, T9, T10, T11, T12, T13, T14, T15, T16> T15 copy$default$15() {
/* 33 */     return _15();
/*    */   }
/*    */   
/*    */   public <T1, T2, T3, T4, T5, T6, T7, T8, T9, T10, T11, T12, T13, T14, T15, T16> T16 copy$default$16() {
/* 33 */     return _16();
/*    */   }
/*    */   
/*    */   public String productPrefix() {
/* 33 */     return "Tuple16";
/*    */   }
/*    */   
/*    */   public Iterator<Object> productIterator() {
/* 33 */     return ScalaRunTime$.MODULE$.typedProductIterator(this);
/*    */   }
/*    */   
/*    */   public boolean canEqual(Object x$1) {
/* 33 */     return x$1 instanceof Tuple16;
/*    */   }
/*    */   
/*    */   public int hashCode() {
/* 33 */     return ScalaRunTime$.MODULE$._hashCode(this);
/*    */   }
/*    */   
/*    */   public boolean equals(Object x$1) {
/*    */     // Byte code:
/*    */     //   0: aload_0
/*    */     //   1: aload_1
/*    */     //   2: if_acmpeq -> 1383
/*    */     //   5: aload_1
/*    */     //   6: instanceof scala/Tuple16
/*    */     //   9: ifeq -> 17
/*    */     //   12: iconst_1
/*    */     //   13: istore_2
/*    */     //   14: goto -> 19
/*    */     //   17: iconst_0
/*    */     //   18: istore_2
/*    */     //   19: iload_2
/*    */     //   20: ifeq -> 1387
/*    */     //   23: aload_1
/*    */     //   24: checkcast scala/Tuple16
/*    */     //   27: astore #35
/*    */     //   29: aload_0
/*    */     //   30: invokevirtual _1 : ()Ljava/lang/Object;
/*    */     //   33: aload #35
/*    */     //   35: invokevirtual _1 : ()Ljava/lang/Object;
/*    */     //   38: astore #4
/*    */     //   40: dup
/*    */     //   41: astore_3
/*    */     //   42: aload #4
/*    */     //   44: if_acmpne -> 51
/*    */     //   47: iconst_1
/*    */     //   48: goto -> 103
/*    */     //   51: aload_3
/*    */     //   52: ifnonnull -> 59
/*    */     //   55: iconst_0
/*    */     //   56: goto -> 103
/*    */     //   59: aload_3
/*    */     //   60: instanceof java/lang/Number
/*    */     //   63: ifeq -> 78
/*    */     //   66: aload_3
/*    */     //   67: checkcast java/lang/Number
/*    */     //   70: aload #4
/*    */     //   72: invokestatic equalsNumObject : (Ljava/lang/Number;Ljava/lang/Object;)Z
/*    */     //   75: goto -> 103
/*    */     //   78: aload_3
/*    */     //   79: instanceof java/lang/Character
/*    */     //   82: ifeq -> 97
/*    */     //   85: aload_3
/*    */     //   86: checkcast java/lang/Character
/*    */     //   89: aload #4
/*    */     //   91: invokestatic equalsCharObject : (Ljava/lang/Character;Ljava/lang/Object;)Z
/*    */     //   94: goto -> 103
/*    */     //   97: aload_3
/*    */     //   98: aload #4
/*    */     //   100: invokevirtual equals : (Ljava/lang/Object;)Z
/*    */     //   103: ifeq -> 1379
/*    */     //   106: aload_0
/*    */     //   107: invokevirtual _2 : ()Ljava/lang/Object;
/*    */     //   110: aload #35
/*    */     //   112: invokevirtual _2 : ()Ljava/lang/Object;
/*    */     //   115: astore #6
/*    */     //   117: dup
/*    */     //   118: astore #5
/*    */     //   120: aload #6
/*    */     //   122: if_acmpne -> 129
/*    */     //   125: iconst_1
/*    */     //   126: goto -> 187
/*    */     //   129: aload #5
/*    */     //   131: ifnonnull -> 138
/*    */     //   134: iconst_0
/*    */     //   135: goto -> 187
/*    */     //   138: aload #5
/*    */     //   140: instanceof java/lang/Number
/*    */     //   143: ifeq -> 159
/*    */     //   146: aload #5
/*    */     //   148: checkcast java/lang/Number
/*    */     //   151: aload #6
/*    */     //   153: invokestatic equalsNumObject : (Ljava/lang/Number;Ljava/lang/Object;)Z
/*    */     //   156: goto -> 187
/*    */     //   159: aload #5
/*    */     //   161: instanceof java/lang/Character
/*    */     //   164: ifeq -> 180
/*    */     //   167: aload #5
/*    */     //   169: checkcast java/lang/Character
/*    */     //   172: aload #6
/*    */     //   174: invokestatic equalsCharObject : (Ljava/lang/Character;Ljava/lang/Object;)Z
/*    */     //   177: goto -> 187
/*    */     //   180: aload #5
/*    */     //   182: aload #6
/*    */     //   184: invokevirtual equals : (Ljava/lang/Object;)Z
/*    */     //   187: ifeq -> 1379
/*    */     //   190: aload_0
/*    */     //   191: invokevirtual _3 : ()Ljava/lang/Object;
/*    */     //   194: aload #35
/*    */     //   196: invokevirtual _3 : ()Ljava/lang/Object;
/*    */     //   199: astore #8
/*    */     //   201: dup
/*    */     //   202: astore #7
/*    */     //   204: aload #8
/*    */     //   206: if_acmpne -> 213
/*    */     //   209: iconst_1
/*    */     //   210: goto -> 271
/*    */     //   213: aload #7
/*    */     //   215: ifnonnull -> 222
/*    */     //   218: iconst_0
/*    */     //   219: goto -> 271
/*    */     //   222: aload #7
/*    */     //   224: instanceof java/lang/Number
/*    */     //   227: ifeq -> 243
/*    */     //   230: aload #7
/*    */     //   232: checkcast java/lang/Number
/*    */     //   235: aload #8
/*    */     //   237: invokestatic equalsNumObject : (Ljava/lang/Number;Ljava/lang/Object;)Z
/*    */     //   240: goto -> 271
/*    */     //   243: aload #7
/*    */     //   245: instanceof java/lang/Character
/*    */     //   248: ifeq -> 264
/*    */     //   251: aload #7
/*    */     //   253: checkcast java/lang/Character
/*    */     //   256: aload #8
/*    */     //   258: invokestatic equalsCharObject : (Ljava/lang/Character;Ljava/lang/Object;)Z
/*    */     //   261: goto -> 271
/*    */     //   264: aload #7
/*    */     //   266: aload #8
/*    */     //   268: invokevirtual equals : (Ljava/lang/Object;)Z
/*    */     //   271: ifeq -> 1379
/*    */     //   274: aload_0
/*    */     //   275: invokevirtual _4 : ()Ljava/lang/Object;
/*    */     //   278: aload #35
/*    */     //   280: invokevirtual _4 : ()Ljava/lang/Object;
/*    */     //   283: astore #10
/*    */     //   285: dup
/*    */     //   286: astore #9
/*    */     //   288: aload #10
/*    */     //   290: if_acmpne -> 297
/*    */     //   293: iconst_1
/*    */     //   294: goto -> 355
/*    */     //   297: aload #9
/*    */     //   299: ifnonnull -> 306
/*    */     //   302: iconst_0
/*    */     //   303: goto -> 355
/*    */     //   306: aload #9
/*    */     //   308: instanceof java/lang/Number
/*    */     //   311: ifeq -> 327
/*    */     //   314: aload #9
/*    */     //   316: checkcast java/lang/Number
/*    */     //   319: aload #10
/*    */     //   321: invokestatic equalsNumObject : (Ljava/lang/Number;Ljava/lang/Object;)Z
/*    */     //   324: goto -> 355
/*    */     //   327: aload #9
/*    */     //   329: instanceof java/lang/Character
/*    */     //   332: ifeq -> 348
/*    */     //   335: aload #9
/*    */     //   337: checkcast java/lang/Character
/*    */     //   340: aload #10
/*    */     //   342: invokestatic equalsCharObject : (Ljava/lang/Character;Ljava/lang/Object;)Z
/*    */     //   345: goto -> 355
/*    */     //   348: aload #9
/*    */     //   350: aload #10
/*    */     //   352: invokevirtual equals : (Ljava/lang/Object;)Z
/*    */     //   355: ifeq -> 1379
/*    */     //   358: aload_0
/*    */     //   359: invokevirtual _5 : ()Ljava/lang/Object;
/*    */     //   362: aload #35
/*    */     //   364: invokevirtual _5 : ()Ljava/lang/Object;
/*    */     //   367: astore #12
/*    */     //   369: dup
/*    */     //   370: astore #11
/*    */     //   372: aload #12
/*    */     //   374: if_acmpne -> 381
/*    */     //   377: iconst_1
/*    */     //   378: goto -> 439
/*    */     //   381: aload #11
/*    */     //   383: ifnonnull -> 390
/*    */     //   386: iconst_0
/*    */     //   387: goto -> 439
/*    */     //   390: aload #11
/*    */     //   392: instanceof java/lang/Number
/*    */     //   395: ifeq -> 411
/*    */     //   398: aload #11
/*    */     //   400: checkcast java/lang/Number
/*    */     //   403: aload #12
/*    */     //   405: invokestatic equalsNumObject : (Ljava/lang/Number;Ljava/lang/Object;)Z
/*    */     //   408: goto -> 439
/*    */     //   411: aload #11
/*    */     //   413: instanceof java/lang/Character
/*    */     //   416: ifeq -> 432
/*    */     //   419: aload #11
/*    */     //   421: checkcast java/lang/Character
/*    */     //   424: aload #12
/*    */     //   426: invokestatic equalsCharObject : (Ljava/lang/Character;Ljava/lang/Object;)Z
/*    */     //   429: goto -> 439
/*    */     //   432: aload #11
/*    */     //   434: aload #12
/*    */     //   436: invokevirtual equals : (Ljava/lang/Object;)Z
/*    */     //   439: ifeq -> 1379
/*    */     //   442: aload_0
/*    */     //   443: invokevirtual _6 : ()Ljava/lang/Object;
/*    */     //   446: aload #35
/*    */     //   448: invokevirtual _6 : ()Ljava/lang/Object;
/*    */     //   451: astore #14
/*    */     //   453: dup
/*    */     //   454: astore #13
/*    */     //   456: aload #14
/*    */     //   458: if_acmpne -> 465
/*    */     //   461: iconst_1
/*    */     //   462: goto -> 523
/*    */     //   465: aload #13
/*    */     //   467: ifnonnull -> 474
/*    */     //   470: iconst_0
/*    */     //   471: goto -> 523
/*    */     //   474: aload #13
/*    */     //   476: instanceof java/lang/Number
/*    */     //   479: ifeq -> 495
/*    */     //   482: aload #13
/*    */     //   484: checkcast java/lang/Number
/*    */     //   487: aload #14
/*    */     //   489: invokestatic equalsNumObject : (Ljava/lang/Number;Ljava/lang/Object;)Z
/*    */     //   492: goto -> 523
/*    */     //   495: aload #13
/*    */     //   497: instanceof java/lang/Character
/*    */     //   500: ifeq -> 516
/*    */     //   503: aload #13
/*    */     //   505: checkcast java/lang/Character
/*    */     //   508: aload #14
/*    */     //   510: invokestatic equalsCharObject : (Ljava/lang/Character;Ljava/lang/Object;)Z
/*    */     //   513: goto -> 523
/*    */     //   516: aload #13
/*    */     //   518: aload #14
/*    */     //   520: invokevirtual equals : (Ljava/lang/Object;)Z
/*    */     //   523: ifeq -> 1379
/*    */     //   526: aload_0
/*    */     //   527: invokevirtual _7 : ()Ljava/lang/Object;
/*    */     //   530: aload #35
/*    */     //   532: invokevirtual _7 : ()Ljava/lang/Object;
/*    */     //   535: astore #16
/*    */     //   537: dup
/*    */     //   538: astore #15
/*    */     //   540: aload #16
/*    */     //   542: if_acmpne -> 549
/*    */     //   545: iconst_1
/*    */     //   546: goto -> 607
/*    */     //   549: aload #15
/*    */     //   551: ifnonnull -> 558
/*    */     //   554: iconst_0
/*    */     //   555: goto -> 607
/*    */     //   558: aload #15
/*    */     //   560: instanceof java/lang/Number
/*    */     //   563: ifeq -> 579
/*    */     //   566: aload #15
/*    */     //   568: checkcast java/lang/Number
/*    */     //   571: aload #16
/*    */     //   573: invokestatic equalsNumObject : (Ljava/lang/Number;Ljava/lang/Object;)Z
/*    */     //   576: goto -> 607
/*    */     //   579: aload #15
/*    */     //   581: instanceof java/lang/Character
/*    */     //   584: ifeq -> 600
/*    */     //   587: aload #15
/*    */     //   589: checkcast java/lang/Character
/*    */     //   592: aload #16
/*    */     //   594: invokestatic equalsCharObject : (Ljava/lang/Character;Ljava/lang/Object;)Z
/*    */     //   597: goto -> 607
/*    */     //   600: aload #15
/*    */     //   602: aload #16
/*    */     //   604: invokevirtual equals : (Ljava/lang/Object;)Z
/*    */     //   607: ifeq -> 1379
/*    */     //   610: aload_0
/*    */     //   611: invokevirtual _8 : ()Ljava/lang/Object;
/*    */     //   614: aload #35
/*    */     //   616: invokevirtual _8 : ()Ljava/lang/Object;
/*    */     //   619: astore #18
/*    */     //   621: dup
/*    */     //   622: astore #17
/*    */     //   624: aload #18
/*    */     //   626: if_acmpne -> 633
/*    */     //   629: iconst_1
/*    */     //   630: goto -> 691
/*    */     //   633: aload #17
/*    */     //   635: ifnonnull -> 642
/*    */     //   638: iconst_0
/*    */     //   639: goto -> 691
/*    */     //   642: aload #17
/*    */     //   644: instanceof java/lang/Number
/*    */     //   647: ifeq -> 663
/*    */     //   650: aload #17
/*    */     //   652: checkcast java/lang/Number
/*    */     //   655: aload #18
/*    */     //   657: invokestatic equalsNumObject : (Ljava/lang/Number;Ljava/lang/Object;)Z
/*    */     //   660: goto -> 691
/*    */     //   663: aload #17
/*    */     //   665: instanceof java/lang/Character
/*    */     //   668: ifeq -> 684
/*    */     //   671: aload #17
/*    */     //   673: checkcast java/lang/Character
/*    */     //   676: aload #18
/*    */     //   678: invokestatic equalsCharObject : (Ljava/lang/Character;Ljava/lang/Object;)Z
/*    */     //   681: goto -> 691
/*    */     //   684: aload #17
/*    */     //   686: aload #18
/*    */     //   688: invokevirtual equals : (Ljava/lang/Object;)Z
/*    */     //   691: ifeq -> 1379
/*    */     //   694: aload_0
/*    */     //   695: invokevirtual _9 : ()Ljava/lang/Object;
/*    */     //   698: aload #35
/*    */     //   700: invokevirtual _9 : ()Ljava/lang/Object;
/*    */     //   703: astore #20
/*    */     //   705: dup
/*    */     //   706: astore #19
/*    */     //   708: aload #20
/*    */     //   710: if_acmpne -> 717
/*    */     //   713: iconst_1
/*    */     //   714: goto -> 775
/*    */     //   717: aload #19
/*    */     //   719: ifnonnull -> 726
/*    */     //   722: iconst_0
/*    */     //   723: goto -> 775
/*    */     //   726: aload #19
/*    */     //   728: instanceof java/lang/Number
/*    */     //   731: ifeq -> 747
/*    */     //   734: aload #19
/*    */     //   736: checkcast java/lang/Number
/*    */     //   739: aload #20
/*    */     //   741: invokestatic equalsNumObject : (Ljava/lang/Number;Ljava/lang/Object;)Z
/*    */     //   744: goto -> 775
/*    */     //   747: aload #19
/*    */     //   749: instanceof java/lang/Character
/*    */     //   752: ifeq -> 768
/*    */     //   755: aload #19
/*    */     //   757: checkcast java/lang/Character
/*    */     //   760: aload #20
/*    */     //   762: invokestatic equalsCharObject : (Ljava/lang/Character;Ljava/lang/Object;)Z
/*    */     //   765: goto -> 775
/*    */     //   768: aload #19
/*    */     //   770: aload #20
/*    */     //   772: invokevirtual equals : (Ljava/lang/Object;)Z
/*    */     //   775: ifeq -> 1379
/*    */     //   778: aload_0
/*    */     //   779: invokevirtual _10 : ()Ljava/lang/Object;
/*    */     //   782: aload #35
/*    */     //   784: invokevirtual _10 : ()Ljava/lang/Object;
/*    */     //   787: astore #22
/*    */     //   789: dup
/*    */     //   790: astore #21
/*    */     //   792: aload #22
/*    */     //   794: if_acmpne -> 801
/*    */     //   797: iconst_1
/*    */     //   798: goto -> 859
/*    */     //   801: aload #21
/*    */     //   803: ifnonnull -> 810
/*    */     //   806: iconst_0
/*    */     //   807: goto -> 859
/*    */     //   810: aload #21
/*    */     //   812: instanceof java/lang/Number
/*    */     //   815: ifeq -> 831
/*    */     //   818: aload #21
/*    */     //   820: checkcast java/lang/Number
/*    */     //   823: aload #22
/*    */     //   825: invokestatic equalsNumObject : (Ljava/lang/Number;Ljava/lang/Object;)Z
/*    */     //   828: goto -> 859
/*    */     //   831: aload #21
/*    */     //   833: instanceof java/lang/Character
/*    */     //   836: ifeq -> 852
/*    */     //   839: aload #21
/*    */     //   841: checkcast java/lang/Character
/*    */     //   844: aload #22
/*    */     //   846: invokestatic equalsCharObject : (Ljava/lang/Character;Ljava/lang/Object;)Z
/*    */     //   849: goto -> 859
/*    */     //   852: aload #21
/*    */     //   854: aload #22
/*    */     //   856: invokevirtual equals : (Ljava/lang/Object;)Z
/*    */     //   859: ifeq -> 1379
/*    */     //   862: aload_0
/*    */     //   863: invokevirtual _11 : ()Ljava/lang/Object;
/*    */     //   866: aload #35
/*    */     //   868: invokevirtual _11 : ()Ljava/lang/Object;
/*    */     //   871: astore #24
/*    */     //   873: dup
/*    */     //   874: astore #23
/*    */     //   876: aload #24
/*    */     //   878: if_acmpne -> 885
/*    */     //   881: iconst_1
/*    */     //   882: goto -> 943
/*    */     //   885: aload #23
/*    */     //   887: ifnonnull -> 894
/*    */     //   890: iconst_0
/*    */     //   891: goto -> 943
/*    */     //   894: aload #23
/*    */     //   896: instanceof java/lang/Number
/*    */     //   899: ifeq -> 915
/*    */     //   902: aload #23
/*    */     //   904: checkcast java/lang/Number
/*    */     //   907: aload #24
/*    */     //   909: invokestatic equalsNumObject : (Ljava/lang/Number;Ljava/lang/Object;)Z
/*    */     //   912: goto -> 943
/*    */     //   915: aload #23
/*    */     //   917: instanceof java/lang/Character
/*    */     //   920: ifeq -> 936
/*    */     //   923: aload #23
/*    */     //   925: checkcast java/lang/Character
/*    */     //   928: aload #24
/*    */     //   930: invokestatic equalsCharObject : (Ljava/lang/Character;Ljava/lang/Object;)Z
/*    */     //   933: goto -> 943
/*    */     //   936: aload #23
/*    */     //   938: aload #24
/*    */     //   940: invokevirtual equals : (Ljava/lang/Object;)Z
/*    */     //   943: ifeq -> 1379
/*    */     //   946: aload_0
/*    */     //   947: invokevirtual _12 : ()Ljava/lang/Object;
/*    */     //   950: aload #35
/*    */     //   952: invokevirtual _12 : ()Ljava/lang/Object;
/*    */     //   955: astore #26
/*    */     //   957: dup
/*    */     //   958: astore #25
/*    */     //   960: aload #26
/*    */     //   962: if_acmpne -> 969
/*    */     //   965: iconst_1
/*    */     //   966: goto -> 1027
/*    */     //   969: aload #25
/*    */     //   971: ifnonnull -> 978
/*    */     //   974: iconst_0
/*    */     //   975: goto -> 1027
/*    */     //   978: aload #25
/*    */     //   980: instanceof java/lang/Number
/*    */     //   983: ifeq -> 999
/*    */     //   986: aload #25
/*    */     //   988: checkcast java/lang/Number
/*    */     //   991: aload #26
/*    */     //   993: invokestatic equalsNumObject : (Ljava/lang/Number;Ljava/lang/Object;)Z
/*    */     //   996: goto -> 1027
/*    */     //   999: aload #25
/*    */     //   1001: instanceof java/lang/Character
/*    */     //   1004: ifeq -> 1020
/*    */     //   1007: aload #25
/*    */     //   1009: checkcast java/lang/Character
/*    */     //   1012: aload #26
/*    */     //   1014: invokestatic equalsCharObject : (Ljava/lang/Character;Ljava/lang/Object;)Z
/*    */     //   1017: goto -> 1027
/*    */     //   1020: aload #25
/*    */     //   1022: aload #26
/*    */     //   1024: invokevirtual equals : (Ljava/lang/Object;)Z
/*    */     //   1027: ifeq -> 1379
/*    */     //   1030: aload_0
/*    */     //   1031: invokevirtual _13 : ()Ljava/lang/Object;
/*    */     //   1034: aload #35
/*    */     //   1036: invokevirtual _13 : ()Ljava/lang/Object;
/*    */     //   1039: astore #28
/*    */     //   1041: dup
/*    */     //   1042: astore #27
/*    */     //   1044: aload #28
/*    */     //   1046: if_acmpne -> 1053
/*    */     //   1049: iconst_1
/*    */     //   1050: goto -> 1111
/*    */     //   1053: aload #27
/*    */     //   1055: ifnonnull -> 1062
/*    */     //   1058: iconst_0
/*    */     //   1059: goto -> 1111
/*    */     //   1062: aload #27
/*    */     //   1064: instanceof java/lang/Number
/*    */     //   1067: ifeq -> 1083
/*    */     //   1070: aload #27
/*    */     //   1072: checkcast java/lang/Number
/*    */     //   1075: aload #28
/*    */     //   1077: invokestatic equalsNumObject : (Ljava/lang/Number;Ljava/lang/Object;)Z
/*    */     //   1080: goto -> 1111
/*    */     //   1083: aload #27
/*    */     //   1085: instanceof java/lang/Character
/*    */     //   1088: ifeq -> 1104
/*    */     //   1091: aload #27
/*    */     //   1093: checkcast java/lang/Character
/*    */     //   1096: aload #28
/*    */     //   1098: invokestatic equalsCharObject : (Ljava/lang/Character;Ljava/lang/Object;)Z
/*    */     //   1101: goto -> 1111
/*    */     //   1104: aload #27
/*    */     //   1106: aload #28
/*    */     //   1108: invokevirtual equals : (Ljava/lang/Object;)Z
/*    */     //   1111: ifeq -> 1379
/*    */     //   1114: aload_0
/*    */     //   1115: invokevirtual _14 : ()Ljava/lang/Object;
/*    */     //   1118: aload #35
/*    */     //   1120: invokevirtual _14 : ()Ljava/lang/Object;
/*    */     //   1123: astore #30
/*    */     //   1125: dup
/*    */     //   1126: astore #29
/*    */     //   1128: aload #30
/*    */     //   1130: if_acmpne -> 1137
/*    */     //   1133: iconst_1
/*    */     //   1134: goto -> 1195
/*    */     //   1137: aload #29
/*    */     //   1139: ifnonnull -> 1146
/*    */     //   1142: iconst_0
/*    */     //   1143: goto -> 1195
/*    */     //   1146: aload #29
/*    */     //   1148: instanceof java/lang/Number
/*    */     //   1151: ifeq -> 1167
/*    */     //   1154: aload #29
/*    */     //   1156: checkcast java/lang/Number
/*    */     //   1159: aload #30
/*    */     //   1161: invokestatic equalsNumObject : (Ljava/lang/Number;Ljava/lang/Object;)Z
/*    */     //   1164: goto -> 1195
/*    */     //   1167: aload #29
/*    */     //   1169: instanceof java/lang/Character
/*    */     //   1172: ifeq -> 1188
/*    */     //   1175: aload #29
/*    */     //   1177: checkcast java/lang/Character
/*    */     //   1180: aload #30
/*    */     //   1182: invokestatic equalsCharObject : (Ljava/lang/Character;Ljava/lang/Object;)Z
/*    */     //   1185: goto -> 1195
/*    */     //   1188: aload #29
/*    */     //   1190: aload #30
/*    */     //   1192: invokevirtual equals : (Ljava/lang/Object;)Z
/*    */     //   1195: ifeq -> 1379
/*    */     //   1198: aload_0
/*    */     //   1199: invokevirtual _15 : ()Ljava/lang/Object;
/*    */     //   1202: aload #35
/*    */     //   1204: invokevirtual _15 : ()Ljava/lang/Object;
/*    */     //   1207: astore #32
/*    */     //   1209: dup
/*    */     //   1210: astore #31
/*    */     //   1212: aload #32
/*    */     //   1214: if_acmpne -> 1221
/*    */     //   1217: iconst_1
/*    */     //   1218: goto -> 1279
/*    */     //   1221: aload #31
/*    */     //   1223: ifnonnull -> 1230
/*    */     //   1226: iconst_0
/*    */     //   1227: goto -> 1279
/*    */     //   1230: aload #31
/*    */     //   1232: instanceof java/lang/Number
/*    */     //   1235: ifeq -> 1251
/*    */     //   1238: aload #31
/*    */     //   1240: checkcast java/lang/Number
/*    */     //   1243: aload #32
/*    */     //   1245: invokestatic equalsNumObject : (Ljava/lang/Number;Ljava/lang/Object;)Z
/*    */     //   1248: goto -> 1279
/*    */     //   1251: aload #31
/*    */     //   1253: instanceof java/lang/Character
/*    */     //   1256: ifeq -> 1272
/*    */     //   1259: aload #31
/*    */     //   1261: checkcast java/lang/Character
/*    */     //   1264: aload #32
/*    */     //   1266: invokestatic equalsCharObject : (Ljava/lang/Character;Ljava/lang/Object;)Z
/*    */     //   1269: goto -> 1279
/*    */     //   1272: aload #31
/*    */     //   1274: aload #32
/*    */     //   1276: invokevirtual equals : (Ljava/lang/Object;)Z
/*    */     //   1279: ifeq -> 1379
/*    */     //   1282: aload_0
/*    */     //   1283: invokevirtual _16 : ()Ljava/lang/Object;
/*    */     //   1286: aload #35
/*    */     //   1288: invokevirtual _16 : ()Ljava/lang/Object;
/*    */     //   1291: astore #34
/*    */     //   1293: dup
/*    */     //   1294: astore #33
/*    */     //   1296: aload #34
/*    */     //   1298: if_acmpne -> 1305
/*    */     //   1301: iconst_1
/*    */     //   1302: goto -> 1363
/*    */     //   1305: aload #33
/*    */     //   1307: ifnonnull -> 1314
/*    */     //   1310: iconst_0
/*    */     //   1311: goto -> 1363
/*    */     //   1314: aload #33
/*    */     //   1316: instanceof java/lang/Number
/*    */     //   1319: ifeq -> 1335
/*    */     //   1322: aload #33
/*    */     //   1324: checkcast java/lang/Number
/*    */     //   1327: aload #34
/*    */     //   1329: invokestatic equalsNumObject : (Ljava/lang/Number;Ljava/lang/Object;)Z
/*    */     //   1332: goto -> 1363
/*    */     //   1335: aload #33
/*    */     //   1337: instanceof java/lang/Character
/*    */     //   1340: ifeq -> 1356
/*    */     //   1343: aload #33
/*    */     //   1345: checkcast java/lang/Character
/*    */     //   1348: aload #34
/*    */     //   1350: invokestatic equalsCharObject : (Ljava/lang/Character;Ljava/lang/Object;)Z
/*    */     //   1353: goto -> 1363
/*    */     //   1356: aload #33
/*    */     //   1358: aload #34
/*    */     //   1360: invokevirtual equals : (Ljava/lang/Object;)Z
/*    */     //   1363: ifeq -> 1379
/*    */     //   1366: aload #35
/*    */     //   1368: aload_0
/*    */     //   1369: invokevirtual canEqual : (Ljava/lang/Object;)Z
/*    */     //   1372: ifeq -> 1379
/*    */     //   1375: iconst_1
/*    */     //   1376: goto -> 1380
/*    */     //   1379: iconst_0
/*    */     //   1380: ifeq -> 1387
/*    */     //   1383: iconst_1
/*    */     //   1384: goto -> 1388
/*    */     //   1387: iconst_0
/*    */     //   1388: ireturn
/*    */     // Line number table:
/*    */     //   Java source line number -> byte code offset
/*    */     //   #33	-> 0
/*    */     //   #236	-> 12
/*    */     //   #33	-> 19
/*    */     // Local variable table:
/*    */     //   start	length	slot	name	descriptor
/*    */     //   0	1389	0	this	Lscala/Tuple16;
/*    */     //   0	1389	1	x$1	Ljava/lang/Object;
/*    */   }
/*    */   
/*    */   public Tuple16(Object _1, Object _2, Object _3, Object _4, Object _5, Object _6, Object _7, Object _8, Object _9, Object _10, Object _11, Object _12, Object _13, Object _14, Object _15, Object _16) {
/* 33 */     Product$class.$init$(this);
/* 33 */     Product16$class.$init$(this);
/*    */   }
/*    */   
/*    */   public String toString() {
/* 37 */     return (new StringBuilder()).append("(").append(_1()).append(",").append(_2()).append(",").append(_3()).append(",").append(_4()).append(",").append(_5()).append(",").append(_6()).append(",").append(_7()).append(",").append(_8()).append(",").append(_9()).append(",").append(_10()).append(",").append(_11()).append(",").append(_12()).append(",").append(_13()).append(",").append(_14()).append(",").append(_15()).append(",").append(_16()).append(")").toString();
/*    */   }
/*    */ }


/* Location:              D:\#source-code\TheFlightSims\TFSLibrary\World2Xplane\World2XPlane.jar!\scala\Tuple16.class
 * Java compiler version: 6 (50.0)
 * JD-Core Version:       1.1.3
 */