/*    */ package scala;
/*    */ 
/*    */ import scala.collection.Iterator;
/*    */ import scala.collection.mutable.StringBuilder;
/*    */ import scala.reflect.ScalaSignature;
/*    */ import scala.runtime.ScalaRunTime$;
/*    */ 
/*    */ @ScalaSignature(bytes = "\006\001\025}b\001B\001\003\001\026\021q\001V;qY\026\fTGC\001\004\003\025\0318-\0317b\007\001)\002C\002\t\033;\001\032c%\013\0270eUB4HP!\024\013\00191b\021$\021\005!IQ\"\001\002\n\005)\021!AB!osJ+g\rE\t\t\0319IBd\b\022&Q-r\023\007N\034;{\001K!!\004\002\003\023A\023x\016Z;diF*\004CA\b\021\031\001!a!\005\001\005\006\004\021\"A\001+2#\t\031b\003\005\002\t)%\021QC\001\002\b\035>$\b.\0338h!\tAq#\003\002\031\005\t\031\021I\\=\021\005=QBAB\016\001\t\013\007!C\001\002UeA\021q\"\b\003\007=\001!)\031\001\n\003\005Q\033\004CA\b!\t\031\t\003\001\"b\001%\t\021A\013\016\t\003\037\r\"a\001\n\001\005\006\004\021\"A\001+6!\tya\005\002\004(\001\021\025\rA\005\002\003)Z\002\"aD\025\005\r)\002AQ1\001\023\005\t!v\007\005\002\020Y\0211Q\006\001CC\002I\021!\001\026\035\021\005=yCA\002\031\001\t\013\007!C\001\002UsA\021qB\r\003\007g\001!)\031\001\n\003\007Q\013\004\007\005\002\020k\0211a\007\001CC\002I\0211\001V\0312!\ty\001\b\002\004:\001\021\025\rA\005\002\004)F\022\004CA\b<\t\031a\004\001\"b\001%\t\031A+M\032\021\005=qDAB \001\t\013\007!CA\002UcQ\002\"aD!\005\r\t\003AQ1\001\023\005\r!\026'\016\t\003\021\021K!!\022\002\003\017A\023x\016Z;diB\021\001bR\005\003\021\n\021AbU3sS\006d\027N_1cY\026D\001B\023\001\003\026\004%\taS\001\003?F*\022A\004\005\t\033\002\021\t\022)A\005\035\005\031q,\r\021\t\021=\003!Q3A\005\002A\013!a\030\032\026\003eA\001B\025\001\003\022\003\006I!G\001\004?J\002\003\002\003+\001\005+\007I\021A+\002\005}\033T#\001\017\t\021]\003!\021#Q\001\nq\t1aX\032!\021!I\006A!f\001\n\003Q\026AA05+\005y\002\002\003/\001\005#\005\013\021B\020\002\007}#\004\005\003\005_\001\tU\r\021\"\001`\003\tyV'F\001#\021!\t\007A!E!\002\023\021\023aA06A!A1\r\001BK\002\023\005A-\001\002`mU\tQ\005\003\005g\001\tE\t\025!\003&\003\ryf\007\t\005\tQ\002\021)\032!C\001S\006\021qlN\013\002Q!A1\016\001B\tB\003%\001&A\002`o\001B\001\"\034\001\003\026\004%\tA\\\001\003?b*\022a\013\005\ta\002\021\t\022)A\005W\005\031q\f\017\021\t\021I\004!Q3A\005\002M\f!aX\035\026\0039B\001\"\036\001\003\022\003\006IAL\001\004?f\002\003\002C<\001\005+\007I\021\001=\002\007}\013\004'F\0012\021!Q\bA!E!\002\023\t\024\001B02a\001B\001\002 \001\003\026\004%\t!`\001\004?F\nT#\001\033\t\021}\004!\021#Q\001\nQ\nAaX\0312A!Q\0211\001\001\003\026\004%\t!!\002\002\007}\013$'F\0018\021%\tI\001\001B\tB\003%q'\001\003`cI\002\003BCA\007\001\tU\r\021\"\001\002\020\005\031q,M\032\026\003iB\021\"a\005\001\005#\005\013\021\002\036\002\t}\0134\007\t\005\013\003/\001!Q3A\005\002\005e\021aA02iU\tQ\bC\005\002\036\001\021\t\022)A\005{\005!q,\r\033!\021)\t\t\003\001BK\002\023\005\0211E\001\004?F*T#\001!\t\023\005\035\002A!E!\002\023\001\025\001B02k\001Bq!a\013\001\t\003\ti#\001\004=S:LGO\020\013!\003_\t\t$a\r\0026\005]\022\021HA\036\003{\ty$!\021\002D\005\025\023qIA%\003\027\ni\005E\t\t\0019IBd\b\022&Q-r\023\007N\034;{\001CaASA\025\001\004q\001BB(\002*\001\007\021\004\003\004U\003S\001\r\001\b\005\0073\006%\002\031A\020\t\ry\013I\0031\001#\021\031\031\027\021\006a\001K!1\001.!\013A\002!Ba!\\A\025\001\004Y\003B\002:\002*\001\007a\006\003\004x\003S\001\r!\r\005\007y\006%\002\031\001\033\t\017\005\r\021\021\006a\001o!9\021QBA\025\001\004Q\004bBA\f\003S\001\r!\020\005\b\003C\tI\0031\001A\021\035\t\t\006\001C!\003'\n\001\002^8TiJLgn\032\013\003\003+\002B!a\026\002b5\021\021\021\f\006\005\0037\ni&\001\003mC:<'BAA0\003\021Q\027M^1\n\t\005\r\024\021\f\002\007'R\024\030N\\4\t\023\005\035\004!!A\005\002\005%\024\001B2paf,\002%a\033\002r\005U\024\021PA?\003\003\013))!#\002\016\006E\025QSAM\003;\013\t+!*\002*R\001\023QNAV\003[\013y+!-\0024\006U\026qWA]\003w\013i,a0\002B\006\r\027QYAd!\001B\001!a\034\002t\005]\0241PA@\003\007\0139)a#\002\020\006M\025qSAN\003?\013\031+a*\021\007=\t\t\b\002\004\022\003K\022\rA\005\t\004\037\005UDAB\016\002f\t\007!\003E\002\020\003s\"aAHA3\005\004\021\002cA\b\002~\0211\021%!\032C\002I\0012aDAA\t\031!\023Q\rb\001%A\031q\"!\"\005\r\035\n)G1\001\023!\ry\021\021\022\003\007U\005\025$\031\001\n\021\007=\ti\t\002\004.\003K\022\rA\005\t\004\037\005EEA\002\031\002f\t\007!\003E\002\020\003+#aaMA3\005\004\021\002cA\b\002\032\0221a'!\032C\002I\0012aDAO\t\031I\024Q\rb\001%A\031q\"!)\005\rq\n)G1\001\023!\ry\021Q\025\003\007\005\025$\031\001\n\021\007=\tI\013\002\004C\003K\022\rA\005\005\n\025\006\025\004\023!a\001\003_B\021bTA3!\003\005\r!a\035\t\023Q\013)\007%AA\002\005]\004\"C-\002fA\005\t\031AA>\021%q\026Q\rI\001\002\004\ty\bC\005d\003K\002\n\0211\001\002\004\"I\001.!\032\021\002\003\007\021q\021\005\n[\006\025\004\023!a\001\003\027C\021B]A3!\003\005\r!a$\t\023]\f)\007%AA\002\005M\005\"\003?\002fA\005\t\031AAL\021)\t\031!!\032\021\002\003\007\0211\024\005\013\003\033\t)\007%AA\002\005}\005BCA\f\003K\002\n\0211\001\002$\"Q\021\021EA3!\003\005\r!a*\t\023\005-\007!%A\005\002\0055\027AD2paf$C-\0324bk2$H%M\013!\003\037\f)/a:\002j\006-\030Q^Ax\003c\f\0310!>\002x\006e\0301`A\003\024\t!\006\002\002R*\032a\"a5,\005\005U\007\003BAl\003Cl!!!7\013\t\005m\027Q\\\001\nk:\034\007.Z2lK\022T1!a8\003\003)\tgN\\8uCRLwN\\\005\005\003G\fINA\tv]\016DWmY6fIZ\013'/[1oG\026$a!EAe\005\004\021BAB\016\002J\n\007!\003\002\004\037\003\023\024\rA\005\003\007C\005%'\031\001\n\005\r\021\nIM1\001\023\t\0319\023\021\032b\001%\0211!&!3C\002I!a!LAe\005\004\021BA\002\031\002J\n\007!\003\002\0044\003\023\024\rA\005\003\007m\005%'\031\001\n\005\re\nIM1\001\023\t\031a\024\021\032b\001%\0211q(!3C\002I!aAQAe\005\004\021\002\"\003B\003\001E\005I\021\001B\004\0039\031w\016]=%I\0264\027-\0367uII*\002E!\003\003\016\t=!\021\003B\n\005+\0219B!\007\003\034\tu!q\004B\021\005G\021)Ca\n\003*U\021!1\002\026\0043\005MGAB\t\003\004\t\007!\003\002\004\034\005\007\021\rA\005\003\007=\t\r!\031\001\n\005\r\005\022\031A1\001\023\t\031!#1\001b\001%\0211qEa\001C\002I!aA\013B\002\005\004\021BAB\027\003\004\t\007!\003\002\0041\005\007\021\rA\005\003\007g\t\r!\031\001\n\005\rY\022\031A1\001\023\t\031I$1\001b\001%\0211AHa\001C\002I!aa\020B\002\005\004\021BA\002\"\003\004\t\007!\003C\005\003.\001\t\n\021\"\001\0030\005q1m\0349zI\021,g-Y;mi\022\032T\003\tB\031\005k\0219D!\017\003<\tu\"q\bB!\005\007\022)Ea\022\003J\t-#Q\nB(\005#*\"Aa\r+\007q\t\031\016\002\004\022\005W\021\rA\005\003\0077\t-\"\031\001\n\005\ry\021YC1\001\023\t\031\t#1\006b\001%\0211AEa\013C\002I!aa\nB\026\005\004\021BA\002\026\003,\t\007!\003\002\004.\005W\021\rA\005\003\007a\t-\"\031\001\n\005\rM\022YC1\001\023\t\0311$1\006b\001%\0211\021Ha\013C\002I!a\001\020B\026\005\004\021BAB \003,\t\007!\003\002\004C\005W\021\rA\005\005\n\005+\002\021\023!C\001\005/\nabY8qs\022\"WMZ1vYR$C'\006\021\003Z\tu#q\fB1\005G\022)Ga\032\003j\t-$Q\016B8\005c\022\031H!\036\003x\teTC\001B.U\ry\0221\033\003\007#\tM#\031\001\n\005\rm\021\031F1\001\023\t\031q\"1\013b\001%\0211\021Ea\025C\002I!a\001\nB*\005\004\021BAB\024\003T\t\007!\003\002\004+\005'\022\rA\005\003\007[\tM#\031\001\n\005\rA\022\031F1\001\023\t\031\031$1\013b\001%\0211aGa\025C\002I!a!\017B*\005\004\021BA\002\037\003T\t\007!\003\002\004@\005'\022\rA\005\003\007\005\nM#\031\001\n\t\023\tu\004!%A\005\002\t}\024AD2paf$C-\0324bk2$H%N\013!\005\003\023)Ia\"\003\n\n-%Q\022BH\005#\023\031J!&\003\030\ne%1\024BO\005?\023\t+\006\002\003\004*\032!%a5\005\rE\021YH1\001\023\t\031Y\"1\020b\001%\0211aDa\037C\002I!a!\tB>\005\004\021BA\002\023\003|\t\007!\003\002\004(\005w\022\rA\005\003\007U\tm$\031\001\n\005\r5\022YH1\001\023\t\031\001$1\020b\001%\02111Ga\037C\002I!aA\016B>\005\004\021BAB\035\003|\t\007!\003\002\004=\005w\022\rA\005\003\007\tm$\031\001\n\005\r\t\023YH1\001\023\021%\021)\013AI\001\n\003\0219+\001\bd_BLH\005Z3gCVdG\017\n\034\026A\t%&Q\026BX\005c\023\031L!.\0038\ne&1\030B_\005\023\tMa1\003F\n\035'\021Z\013\003\005WS3!JAj\t\031\t\"1\025b\001%\02111Da)C\002I!aA\bBR\005\004\021BAB\021\003$\n\007!\003\002\004%\005G\023\rA\005\003\007O\t\r&\031\001\n\005\r)\022\031K1\001\023\t\031i#1\025b\001%\0211\001Ga)C\002I!aa\rBR\005\004\021BA\002\034\003$\n\007!\003\002\004:\005G\023\rA\005\003\007y\t\r&\031\001\n\005\r}\022\031K1\001\023\t\031\021%1\025b\001%!I!Q\032\001\022\002\023\005!qZ\001\017G>\004\030\020\n3fM\006,H\016\036\0238+\001\022\tN!6\003X\ne'1\034Bo\005?\024\tOa9\003f\n\035(\021\036Bv\005[\024yO!=\026\005\tM'f\001\025\002T\0221\021Ca3C\002I!aa\007Bf\005\004\021BA\002\020\003L\n\007!\003\002\004\"\005\027\024\rA\005\003\007I\t-'\031\001\n\005\r\035\022YM1\001\023\t\031Q#1\032b\001%\0211QFa3C\002I!a\001\rBf\005\004\021BAB\032\003L\n\007!\003\002\0047\005\027\024\rA\005\003\007s\t-'\031\001\n\005\rq\022YM1\001\023\t\031y$1\032b\001%\0211!Ia3C\002IA\021B!>\001#\003%\tAa>\002\035\r|\007/\037\023eK\032\fW\017\034;%qU\001#\021 B\005\034\taa\001\004\006\r\0351\021BB\006\007\033\031ya!\005\004\024\rU1qCB\r+\t\021YPK\002,\003'$a!\005Bz\005\004\021BAB\016\003t\n\007!\003\002\004\037\005g\024\rA\005\003\007C\tM(\031\001\n\005\r\021\022\031P1\001\023\t\0319#1\037b\001%\0211!Fa=C\002I!a!\fBz\005\004\021BA\002\031\003t\n\007!\003\002\0044\005g\024\rA\005\003\007m\tM(\031\001\n\005\re\022\031P1\001\023\t\031a$1\037b\001%\0211qHa=C\002I!aA\021Bz\005\004\021\002\"CB\017\001E\005I\021AB\020\0039\031w\016]=%I\0264\027-\0367uIe*\002e!\t\004&\r\0352\021FB\026\007[\031yc!\r\0044\rU2qGB\035\007w\031ida\020\004BU\02111\005\026\004]\005MGAB\t\004\034\t\007!\003\002\004\034\0077\021\rA\005\003\007=\rm!\031\001\n\005\r\005\032YB1\001\023\t\031!31\004b\001%\0211qea\007C\002I!aAKB\016\005\004\021BAB\027\004\034\t\007!\003\002\0041\0077\021\rA\005\003\007g\rm!\031\001\n\005\rY\032YB1\001\023\t\031I41\004b\001%\0211Aha\007C\002I!aaPB\016\005\004\021BA\002\"\004\034\t\007!\003C\005\004F\001\t\n\021\"\001\004H\005y1m\0349zI\021,g-Y;mi\022\n\004'\006\021\004J\r53qJB)\007'\032)fa\026\004Z\rm3QLB0\007C\032\031g!\032\004h\r%TCAB&U\r\t\0241\033\003\007#\r\r#\031\001\n\005\rm\031\031E1\001\023\t\031q21\tb\001%\0211\021ea\021C\002I!a\001JB\"\005\004\021BAB\024\004D\t\007!\003\002\004+\007\007\022\rA\005\003\007[\r\r#\031\001\n\005\rA\032\031E1\001\023\t\031\03141\tb\001%\0211aga\021C\002I!a!OB\"\005\004\021BA\002\037\004D\t\007!\003\002\004@\007\007\022\rA\005\003\007\005\016\r#\031\001\n\t\023\r5\004!%A\005\002\r=\024aD2paf$C-\0324bk2$H%M\031\026A\rE4QOB<\007s\032Yh! \004\000\r\00551QBC\007\017\033Iia#\004\016\016=5\021S\013\003\007gR3\001NAj\t\031\t21\016b\001%\02111da\033C\002I!aAHB6\005\004\021BAB\021\004l\t\007!\003\002\004%\007W\022\rA\005\003\007O\r-$\031\001\n\005\r)\032YG1\001\023\t\031i31\016b\001%\0211\001ga\033C\002I!aaMB6\005\004\021BA\002\034\004l\t\007!\003\002\004:\007W\022\rA\005\003\007y\r-$\031\001\n\005\r}\032YG1\001\023\t\031\02151\016b\001%!I1Q\023\001\022\002\023\0051qS\001\020G>\004\030\020\n3fM\006,H\016\036\0232eU\0013\021TBO\007?\033\tka)\004&\016\0356\021VBV\007[\033yk!-\0044\016U6qWB]+\t\031YJK\0028\003'$a!EBJ\005\004\021BAB\016\004\024\n\007!\003\002\004\037\007'\023\rA\005\003\007C\rM%\031\001\n\005\r\021\032\031J1\001\023\t\031931\023b\001%\0211!fa%C\002I!a!LBJ\005\004\021BA\002\031\004\024\n\007!\003\002\0044\007'\023\rA\005\003\007m\rM%\031\001\n\005\re\032\031J1\001\023\t\031a41\023b\001%\0211qha%C\002I!aAQBJ\005\004\021\002\"CB_\001E\005I\021AB`\003=\031w\016]=%I\0264\027-\0367uIE\032T\003IBa\007\013\0349m!3\004L\01657qZBi\007'\034)na6\004Z\016m7Q\\Bp\007C,\"aa1+\007i\n\031\016\002\004\022\007w\023\rA\005\003\0077\rm&\031\001\n\005\ry\031YL1\001\023\t\031\t31\030b\001%\0211Aea/C\002I!aaJB^\005\004\021BA\002\026\004<\n\007!\003\002\004.\007w\023\rA\005\003\007a\rm&\031\001\n\005\rM\032YL1\001\023\t\031141\030b\001%\0211\021ha/C\002I!a\001PB^\005\004\021BAB \004<\n\007!\003\002\004C\007w\023\rA\005\005\n\007K\004\021\023!C\001\007O\fqbY8qs\022\"WMZ1vYR$\023\007N\013!\007S\034ioa<\004r\016M8Q_B|\007s\034Yp!@\004\000\022\005A1\001C\003\t\017!I!\006\002\004l*\032Q(a5\005\rE\031\031O1\001\023\t\031Y21\035b\001%\0211ada9C\002I!a!IBr\005\004\021BA\002\023\004d\n\007!\003\002\004(\007G\024\rA\005\003\007U\r\r(\031\001\n\005\r5\032\031O1\001\023\t\031\00141\035b\001%\02111ga9C\002I!aANBr\005\004\021BAB\035\004d\n\007!\003\002\004=\007G\024\rA\005\003\007\r\r(\031\001\n\005\r\t\033\031O1\001\023\021%!i\001AI\001\n\003!y!A\bd_BLH\005Z3gCVdG\017J\0316+\001\"\t\002\"\006\005\030\021eA1\004C\017\t?!\t\003b\t\005&\021\035B\021\006C\026\t[!y\003\"\r\026\005\021M!f\001!\002T\0221\021\003b\003C\002I!aa\007C\006\005\004\021BA\002\020\005\f\t\007!\003\002\004\"\t\027\021\rA\005\003\007I\021-!\031\001\n\005\r\035\"YA1\001\023\t\031QC1\002b\001%\0211Q\006b\003C\002I!a\001\rC\006\005\004\021BAB\032\005\f\t\007!\003\002\0047\t\027\021\rA\005\003\007s\021-!\031\001\n\005\rq\"YA1\001\023\t\031yD1\002b\001%\0211!\tb\003C\002IA\021\002\"\016\001\003\003%\t\005b\016\002\033A\024x\016Z;diB\023XMZ5y+\t\t)\006C\005\005<\001\t\t\021\"\021\005>\005y\001O]8ek\016$\030\n^3sCR|'/\006\002\005@A)A\021\tC$-5\021A1\t\006\004\t\013\022\021AC2pY2,7\r^5p]&!A\021\nC\"\005!IE/\032:bi>\024\b\"\003C'\001\005\005I\021\001C(\003!\031\027M\\#rk\006dG\003\002C)\t/\0022\001\003C*\023\r!)F\001\002\b\005>|G.Z1o\021%!I\006b\023\002\002\003\007a#A\002yIEB\021\002\"\030\001\003\003%\t\005b\030\002\021!\f7\017[\"pI\026$\"\001\"\031\021\007!!\031'C\002\005f\t\0211!\0238u\021%!I\007AA\001\n\003\"Y'\001\004fcV\fGn\035\013\005\t#\"i\007C\005\005Z\021\035\024\021!a\001-\035IA\021\017\002\002\002#\005A1O\001\b)V\004H.Z\0316!\rAAQ\017\004\t\003\t\t\t\021#\001\005xM!AQO\004G\021!\tY\003\"\036\005\002\021mDC\001C:\021)\t\t\006\"\036\002\002\023\025\0231\013\005\013\t\003#)(!A\005\002\022\r\025!B1qa2LX\003\tCC\t\027#y\tb%\005\030\022mEq\024CR\tO#Y\013b,\0054\022]F1\030C`\t\007$\002\005b\"\005F\022\035G\021\032Cf\t\033$y\r\"5\005T\022UGq\033Cm\t7$i\016b8\005bB\001\003\002\001CE\t\033#\t\n\"&\005\032\022uE\021\025CS\tS#i\013\"-\0056\022eFQ\030Ca!\ryA1\022\003\007#\021}$\031\001\n\021\007=!y\t\002\004\034\t\022\rA\005\t\004\037\021MEA\002\020\005\000\t\007!\003E\002\020\t/#a!\tC@\005\004\021\002cA\b\005\034\0221A\005b C\002I\0012a\004CP\t\0319Cq\020b\001%A\031q\002b)\005\r)\"yH1\001\023!\ryAq\025\003\007[\021}$\031\001\n\021\007=!Y\013\002\0041\t\022\rA\005\t\004\037\021=FAB\032\005\000\t\007!\003E\002\020\tg#aA\016C@\005\004\021\002cA\b\0058\0221\021\bb C\002I\0012a\004C^\t\031aDq\020b\001%A\031q\002b0\005\r}\"yH1\001\023!\ryA1\031\003\007\005\022}$\031\001\n\t\017)#y\b1\001\005\n\"9q\nb A\002\0215\005b\002+\005\000\001\007A\021\023\005\b3\022}\004\031\001CK\021\035qFq\020a\001\t3Cqa\031C@\001\004!i\nC\004i\t\002\r\001\")\t\0175$y\b1\001\005&\"9!\017b A\002\021%\006bB<\005\000\001\007AQ\026\005\by\022}\004\031\001CY\021!\t\031\001b A\002\021U\006\002CA\007\t\002\r\001\"/\t\021\005]Aq\020a\001\t{C\001\"!\t\005\000\001\007A\021\031\005\013\tK$)(!A\005\002\022\035\030aB;oCB\004H._\013!\tS$)\020\"?\005~\026\005QQAC\005\013\033)\t\"\"\006\006\032\025uQ\021EC\023\013S)i\003\006\003\005l\026=\002#\002\005\005n\022E\030b\001Cx\005\t1q\n\035;j_:\004\002\005\003\001\005t\022]H1 C\000\013\007)9!b\003\006\020\025MQqCC\016\013?)\031#b\n\006,A\031q\002\">\005\rE!\031O1\001\023!\ryA\021 \003\0077\021\r(\031\001\n\021\007=!i\020\002\004\037\tG\024\rA\005\t\004\037\025\005AAB\021\005d\n\007!\003E\002\020\013\013!a\001\nCr\005\004\021\002cA\b\006\n\0211q\005b9C\002I\0012aDC\007\t\031QC1\035b\001%A\031q\"\"\005\005\r5\"\031O1\001\023!\ryQQ\003\003\007a\021\r(\031\001\n\021\007=)I\002\002\0044\tG\024\rA\005\t\004\037\025uAA\002\034\005d\n\007!\003E\002\020\013C!a!\017Cr\005\004\021\002cA\b\006&\0211A\bb9C\002I\0012aDC\025\t\031yD1\035b\001%A\031q\"\"\f\005\r\t#\031O1\001\023\021))\t\004b9\002\002\003\007A\021_\001\004q\022\002\004BCC\033\tk\n\t\021\"\003\0068\005Y!/Z1e%\026\034x\016\034<f)\t)I\004\005\003\002X\025m\022\002BC\037\0033\022aa\0242kK\016$\b")
/*    */ public class Tuple15<T1, T2, T3, T4, T5, T6, T7, T8, T9, T10, T11, T12, T13, T14, T15> implements Product15<T1, T2, T3, T4, T5, T6, T7, T8, T9, T10, T11, T12, T13, T14, T15>, Product, Serializable {
/*    */   private final T1 _1;
/*    */   
/*    */   private final T2 _2;
/*    */   
/*    */   private final T3 _3;
/*    */   
/*    */   private final T4 _4;
/*    */   
/*    */   private final T5 _5;
/*    */   
/*    */   private final T6 _6;
/*    */   
/*    */   private final T7 _7;
/*    */   
/*    */   private final T8 _8;
/*    */   
/*    */   private final T9 _9;
/*    */   
/*    */   private final T10 _10;
/*    */   
/*    */   private final T11 _11;
/*    */   
/*    */   private final T12 _12;
/*    */   
/*    */   private final T13 _13;
/*    */   
/*    */   private final T14 _14;
/*    */   
/*    */   private final T15 _15;
/*    */   
/*    */   public int productArity() {
/* 32 */     return Product15$class.productArity(this);
/*    */   }
/*    */   
/*    */   public Object productElement(int n) throws IndexOutOfBoundsException {
/* 32 */     return Product15$class.productElement(this, n);
/*    */   }
/*    */   
/*    */   public T1 _1() {
/* 32 */     return this._1;
/*    */   }
/*    */   
/*    */   public T2 _2() {
/* 32 */     return this._2;
/*    */   }
/*    */   
/*    */   public T3 _3() {
/* 32 */     return this._3;
/*    */   }
/*    */   
/*    */   public T4 _4() {
/* 32 */     return this._4;
/*    */   }
/*    */   
/*    */   public T5 _5() {
/* 32 */     return this._5;
/*    */   }
/*    */   
/*    */   public T6 _6() {
/* 32 */     return this._6;
/*    */   }
/*    */   
/*    */   public T7 _7() {
/* 32 */     return this._7;
/*    */   }
/*    */   
/*    */   public T8 _8() {
/* 32 */     return this._8;
/*    */   }
/*    */   
/*    */   public T9 _9() {
/* 32 */     return this._9;
/*    */   }
/*    */   
/*    */   public T10 _10() {
/* 32 */     return this._10;
/*    */   }
/*    */   
/*    */   public T11 _11() {
/* 32 */     return this._11;
/*    */   }
/*    */   
/*    */   public T12 _12() {
/* 32 */     return this._12;
/*    */   }
/*    */   
/*    */   public T13 _13() {
/* 32 */     return this._13;
/*    */   }
/*    */   
/*    */   public T14 _14() {
/* 32 */     return this._14;
/*    */   }
/*    */   
/*    */   public T15 _15() {
/* 32 */     return this._15;
/*    */   }
/*    */   
/*    */   public <T1, T2, T3, T4, T5, T6, T7, T8, T9, T10, T11, T12, T13, T14, T15> Tuple15<T1, T2, T3, T4, T5, T6, T7, T8, T9, T10, T11, T12, T13, T14, T15> copy(Object _1, Object _2, Object _3, Object _4, Object _5, Object _6, Object _7, Object _8, Object _9, Object _10, Object _11, Object _12, Object _13, Object _14, Object _15) {
/* 32 */     return new Tuple15((T1)_1, (T2)_2, (T3)_3, (T4)_4, (T5)_5, (T6)_6, (T7)_7, (T8)_8, (T9)_9, (T10)_10, (T11)_11, (T12)_12, (T13)_13, (T14)_14, (T15)_15);
/*    */   }
/*    */   
/*    */   public <T1, T2, T3, T4, T5, T6, T7, T8, T9, T10, T11, T12, T13, T14, T15> T1 copy$default$1() {
/* 32 */     return _1();
/*    */   }
/*    */   
/*    */   public <T1, T2, T3, T4, T5, T6, T7, T8, T9, T10, T11, T12, T13, T14, T15> T2 copy$default$2() {
/* 32 */     return _2();
/*    */   }
/*    */   
/*    */   public <T1, T2, T3, T4, T5, T6, T7, T8, T9, T10, T11, T12, T13, T14, T15> T3 copy$default$3() {
/* 32 */     return _3();
/*    */   }
/*    */   
/*    */   public <T1, T2, T3, T4, T5, T6, T7, T8, T9, T10, T11, T12, T13, T14, T15> T4 copy$default$4() {
/* 32 */     return _4();
/*    */   }
/*    */   
/*    */   public <T1, T2, T3, T4, T5, T6, T7, T8, T9, T10, T11, T12, T13, T14, T15> T5 copy$default$5() {
/* 32 */     return _5();
/*    */   }
/*    */   
/*    */   public <T1, T2, T3, T4, T5, T6, T7, T8, T9, T10, T11, T12, T13, T14, T15> T6 copy$default$6() {
/* 32 */     return _6();
/*    */   }
/*    */   
/*    */   public <T1, T2, T3, T4, T5, T6, T7, T8, T9, T10, T11, T12, T13, T14, T15> T7 copy$default$7() {
/* 32 */     return _7();
/*    */   }
/*    */   
/*    */   public <T1, T2, T3, T4, T5, T6, T7, T8, T9, T10, T11, T12, T13, T14, T15> T8 copy$default$8() {
/* 32 */     return _8();
/*    */   }
/*    */   
/*    */   public <T1, T2, T3, T4, T5, T6, T7, T8, T9, T10, T11, T12, T13, T14, T15> T9 copy$default$9() {
/* 32 */     return _9();
/*    */   }
/*    */   
/*    */   public <T1, T2, T3, T4, T5, T6, T7, T8, T9, T10, T11, T12, T13, T14, T15> T10 copy$default$10() {
/* 32 */     return _10();
/*    */   }
/*    */   
/*    */   public <T1, T2, T3, T4, T5, T6, T7, T8, T9, T10, T11, T12, T13, T14, T15> T11 copy$default$11() {
/* 32 */     return _11();
/*    */   }
/*    */   
/*    */   public <T1, T2, T3, T4, T5, T6, T7, T8, T9, T10, T11, T12, T13, T14, T15> T12 copy$default$12() {
/* 32 */     return _12();
/*    */   }
/*    */   
/*    */   public <T1, T2, T3, T4, T5, T6, T7, T8, T9, T10, T11, T12, T13, T14, T15> T13 copy$default$13() {
/* 32 */     return _13();
/*    */   }
/*    */   
/*    */   public <T1, T2, T3, T4, T5, T6, T7, T8, T9, T10, T11, T12, T13, T14, T15> T14 copy$default$14() {
/* 32 */     return _14();
/*    */   }
/*    */   
/*    */   public <T1, T2, T3, T4, T5, T6, T7, T8, T9, T10, T11, T12, T13, T14, T15> T15 copy$default$15() {
/* 32 */     return _15();
/*    */   }
/*    */   
/*    */   public String productPrefix() {
/* 32 */     return "Tuple15";
/*    */   }
/*    */   
/*    */   public Iterator<Object> productIterator() {
/* 32 */     return ScalaRunTime$.MODULE$.typedProductIterator(this);
/*    */   }
/*    */   
/*    */   public boolean canEqual(Object x$1) {
/* 32 */     return x$1 instanceof Tuple15;
/*    */   }
/*    */   
/*    */   public int hashCode() {
/* 32 */     return ScalaRunTime$.MODULE$._hashCode(this);
/*    */   }
/*    */   
/*    */   public boolean equals(Object x$1) {
/*    */     // Byte code:
/*    */     //   0: aload_0
/*    */     //   1: aload_1
/*    */     //   2: if_acmpeq -> 1299
/*    */     //   5: aload_1
/*    */     //   6: instanceof scala/Tuple15
/*    */     //   9: ifeq -> 17
/*    */     //   12: iconst_1
/*    */     //   13: istore_2
/*    */     //   14: goto -> 19
/*    */     //   17: iconst_0
/*    */     //   18: istore_2
/*    */     //   19: iload_2
/*    */     //   20: ifeq -> 1303
/*    */     //   23: aload_1
/*    */     //   24: checkcast scala/Tuple15
/*    */     //   27: astore #33
/*    */     //   29: aload_0
/*    */     //   30: invokevirtual _1 : ()Ljava/lang/Object;
/*    */     //   33: aload #33
/*    */     //   35: invokevirtual _1 : ()Ljava/lang/Object;
/*    */     //   38: astore #4
/*    */     //   40: dup
/*    */     //   41: astore_3
/*    */     //   42: aload #4
/*    */     //   44: if_acmpne -> 51
/*    */     //   47: iconst_1
/*    */     //   48: goto -> 103
/*    */     //   51: aload_3
/*    */     //   52: ifnonnull -> 59
/*    */     //   55: iconst_0
/*    */     //   56: goto -> 103
/*    */     //   59: aload_3
/*    */     //   60: instanceof java/lang/Number
/*    */     //   63: ifeq -> 78
/*    */     //   66: aload_3
/*    */     //   67: checkcast java/lang/Number
/*    */     //   70: aload #4
/*    */     //   72: invokestatic equalsNumObject : (Ljava/lang/Number;Ljava/lang/Object;)Z
/*    */     //   75: goto -> 103
/*    */     //   78: aload_3
/*    */     //   79: instanceof java/lang/Character
/*    */     //   82: ifeq -> 97
/*    */     //   85: aload_3
/*    */     //   86: checkcast java/lang/Character
/*    */     //   89: aload #4
/*    */     //   91: invokestatic equalsCharObject : (Ljava/lang/Character;Ljava/lang/Object;)Z
/*    */     //   94: goto -> 103
/*    */     //   97: aload_3
/*    */     //   98: aload #4
/*    */     //   100: invokevirtual equals : (Ljava/lang/Object;)Z
/*    */     //   103: ifeq -> 1295
/*    */     //   106: aload_0
/*    */     //   107: invokevirtual _2 : ()Ljava/lang/Object;
/*    */     //   110: aload #33
/*    */     //   112: invokevirtual _2 : ()Ljava/lang/Object;
/*    */     //   115: astore #6
/*    */     //   117: dup
/*    */     //   118: astore #5
/*    */     //   120: aload #6
/*    */     //   122: if_acmpne -> 129
/*    */     //   125: iconst_1
/*    */     //   126: goto -> 187
/*    */     //   129: aload #5
/*    */     //   131: ifnonnull -> 138
/*    */     //   134: iconst_0
/*    */     //   135: goto -> 187
/*    */     //   138: aload #5
/*    */     //   140: instanceof java/lang/Number
/*    */     //   143: ifeq -> 159
/*    */     //   146: aload #5
/*    */     //   148: checkcast java/lang/Number
/*    */     //   151: aload #6
/*    */     //   153: invokestatic equalsNumObject : (Ljava/lang/Number;Ljava/lang/Object;)Z
/*    */     //   156: goto -> 187
/*    */     //   159: aload #5
/*    */     //   161: instanceof java/lang/Character
/*    */     //   164: ifeq -> 180
/*    */     //   167: aload #5
/*    */     //   169: checkcast java/lang/Character
/*    */     //   172: aload #6
/*    */     //   174: invokestatic equalsCharObject : (Ljava/lang/Character;Ljava/lang/Object;)Z
/*    */     //   177: goto -> 187
/*    */     //   180: aload #5
/*    */     //   182: aload #6
/*    */     //   184: invokevirtual equals : (Ljava/lang/Object;)Z
/*    */     //   187: ifeq -> 1295
/*    */     //   190: aload_0
/*    */     //   191: invokevirtual _3 : ()Ljava/lang/Object;
/*    */     //   194: aload #33
/*    */     //   196: invokevirtual _3 : ()Ljava/lang/Object;
/*    */     //   199: astore #8
/*    */     //   201: dup
/*    */     //   202: astore #7
/*    */     //   204: aload #8
/*    */     //   206: if_acmpne -> 213
/*    */     //   209: iconst_1
/*    */     //   210: goto -> 271
/*    */     //   213: aload #7
/*    */     //   215: ifnonnull -> 222
/*    */     //   218: iconst_0
/*    */     //   219: goto -> 271
/*    */     //   222: aload #7
/*    */     //   224: instanceof java/lang/Number
/*    */     //   227: ifeq -> 243
/*    */     //   230: aload #7
/*    */     //   232: checkcast java/lang/Number
/*    */     //   235: aload #8
/*    */     //   237: invokestatic equalsNumObject : (Ljava/lang/Number;Ljava/lang/Object;)Z
/*    */     //   240: goto -> 271
/*    */     //   243: aload #7
/*    */     //   245: instanceof java/lang/Character
/*    */     //   248: ifeq -> 264
/*    */     //   251: aload #7
/*    */     //   253: checkcast java/lang/Character
/*    */     //   256: aload #8
/*    */     //   258: invokestatic equalsCharObject : (Ljava/lang/Character;Ljava/lang/Object;)Z
/*    */     //   261: goto -> 271
/*    */     //   264: aload #7
/*    */     //   266: aload #8
/*    */     //   268: invokevirtual equals : (Ljava/lang/Object;)Z
/*    */     //   271: ifeq -> 1295
/*    */     //   274: aload_0
/*    */     //   275: invokevirtual _4 : ()Ljava/lang/Object;
/*    */     //   278: aload #33
/*    */     //   280: invokevirtual _4 : ()Ljava/lang/Object;
/*    */     //   283: astore #10
/*    */     //   285: dup
/*    */     //   286: astore #9
/*    */     //   288: aload #10
/*    */     //   290: if_acmpne -> 297
/*    */     //   293: iconst_1
/*    */     //   294: goto -> 355
/*    */     //   297: aload #9
/*    */     //   299: ifnonnull -> 306
/*    */     //   302: iconst_0
/*    */     //   303: goto -> 355
/*    */     //   306: aload #9
/*    */     //   308: instanceof java/lang/Number
/*    */     //   311: ifeq -> 327
/*    */     //   314: aload #9
/*    */     //   316: checkcast java/lang/Number
/*    */     //   319: aload #10
/*    */     //   321: invokestatic equalsNumObject : (Ljava/lang/Number;Ljava/lang/Object;)Z
/*    */     //   324: goto -> 355
/*    */     //   327: aload #9
/*    */     //   329: instanceof java/lang/Character
/*    */     //   332: ifeq -> 348
/*    */     //   335: aload #9
/*    */     //   337: checkcast java/lang/Character
/*    */     //   340: aload #10
/*    */     //   342: invokestatic equalsCharObject : (Ljava/lang/Character;Ljava/lang/Object;)Z
/*    */     //   345: goto -> 355
/*    */     //   348: aload #9
/*    */     //   350: aload #10
/*    */     //   352: invokevirtual equals : (Ljava/lang/Object;)Z
/*    */     //   355: ifeq -> 1295
/*    */     //   358: aload_0
/*    */     //   359: invokevirtual _5 : ()Ljava/lang/Object;
/*    */     //   362: aload #33
/*    */     //   364: invokevirtual _5 : ()Ljava/lang/Object;
/*    */     //   367: astore #12
/*    */     //   369: dup
/*    */     //   370: astore #11
/*    */     //   372: aload #12
/*    */     //   374: if_acmpne -> 381
/*    */     //   377: iconst_1
/*    */     //   378: goto -> 439
/*    */     //   381: aload #11
/*    */     //   383: ifnonnull -> 390
/*    */     //   386: iconst_0
/*    */     //   387: goto -> 439
/*    */     //   390: aload #11
/*    */     //   392: instanceof java/lang/Number
/*    */     //   395: ifeq -> 411
/*    */     //   398: aload #11
/*    */     //   400: checkcast java/lang/Number
/*    */     //   403: aload #12
/*    */     //   405: invokestatic equalsNumObject : (Ljava/lang/Number;Ljava/lang/Object;)Z
/*    */     //   408: goto -> 439
/*    */     //   411: aload #11
/*    */     //   413: instanceof java/lang/Character
/*    */     //   416: ifeq -> 432
/*    */     //   419: aload #11
/*    */     //   421: checkcast java/lang/Character
/*    */     //   424: aload #12
/*    */     //   426: invokestatic equalsCharObject : (Ljava/lang/Character;Ljava/lang/Object;)Z
/*    */     //   429: goto -> 439
/*    */     //   432: aload #11
/*    */     //   434: aload #12
/*    */     //   436: invokevirtual equals : (Ljava/lang/Object;)Z
/*    */     //   439: ifeq -> 1295
/*    */     //   442: aload_0
/*    */     //   443: invokevirtual _6 : ()Ljava/lang/Object;
/*    */     //   446: aload #33
/*    */     //   448: invokevirtual _6 : ()Ljava/lang/Object;
/*    */     //   451: astore #14
/*    */     //   453: dup
/*    */     //   454: astore #13
/*    */     //   456: aload #14
/*    */     //   458: if_acmpne -> 465
/*    */     //   461: iconst_1
/*    */     //   462: goto -> 523
/*    */     //   465: aload #13
/*    */     //   467: ifnonnull -> 474
/*    */     //   470: iconst_0
/*    */     //   471: goto -> 523
/*    */     //   474: aload #13
/*    */     //   476: instanceof java/lang/Number
/*    */     //   479: ifeq -> 495
/*    */     //   482: aload #13
/*    */     //   484: checkcast java/lang/Number
/*    */     //   487: aload #14
/*    */     //   489: invokestatic equalsNumObject : (Ljava/lang/Number;Ljava/lang/Object;)Z
/*    */     //   492: goto -> 523
/*    */     //   495: aload #13
/*    */     //   497: instanceof java/lang/Character
/*    */     //   500: ifeq -> 516
/*    */     //   503: aload #13
/*    */     //   505: checkcast java/lang/Character
/*    */     //   508: aload #14
/*    */     //   510: invokestatic equalsCharObject : (Ljava/lang/Character;Ljava/lang/Object;)Z
/*    */     //   513: goto -> 523
/*    */     //   516: aload #13
/*    */     //   518: aload #14
/*    */     //   520: invokevirtual equals : (Ljava/lang/Object;)Z
/*    */     //   523: ifeq -> 1295
/*    */     //   526: aload_0
/*    */     //   527: invokevirtual _7 : ()Ljava/lang/Object;
/*    */     //   530: aload #33
/*    */     //   532: invokevirtual _7 : ()Ljava/lang/Object;
/*    */     //   535: astore #16
/*    */     //   537: dup
/*    */     //   538: astore #15
/*    */     //   540: aload #16
/*    */     //   542: if_acmpne -> 549
/*    */     //   545: iconst_1
/*    */     //   546: goto -> 607
/*    */     //   549: aload #15
/*    */     //   551: ifnonnull -> 558
/*    */     //   554: iconst_0
/*    */     //   555: goto -> 607
/*    */     //   558: aload #15
/*    */     //   560: instanceof java/lang/Number
/*    */     //   563: ifeq -> 579
/*    */     //   566: aload #15
/*    */     //   568: checkcast java/lang/Number
/*    */     //   571: aload #16
/*    */     //   573: invokestatic equalsNumObject : (Ljava/lang/Number;Ljava/lang/Object;)Z
/*    */     //   576: goto -> 607
/*    */     //   579: aload #15
/*    */     //   581: instanceof java/lang/Character
/*    */     //   584: ifeq -> 600
/*    */     //   587: aload #15
/*    */     //   589: checkcast java/lang/Character
/*    */     //   592: aload #16
/*    */     //   594: invokestatic equalsCharObject : (Ljava/lang/Character;Ljava/lang/Object;)Z
/*    */     //   597: goto -> 607
/*    */     //   600: aload #15
/*    */     //   602: aload #16
/*    */     //   604: invokevirtual equals : (Ljava/lang/Object;)Z
/*    */     //   607: ifeq -> 1295
/*    */     //   610: aload_0
/*    */     //   611: invokevirtual _8 : ()Ljava/lang/Object;
/*    */     //   614: aload #33
/*    */     //   616: invokevirtual _8 : ()Ljava/lang/Object;
/*    */     //   619: astore #18
/*    */     //   621: dup
/*    */     //   622: astore #17
/*    */     //   624: aload #18
/*    */     //   626: if_acmpne -> 633
/*    */     //   629: iconst_1
/*    */     //   630: goto -> 691
/*    */     //   633: aload #17
/*    */     //   635: ifnonnull -> 642
/*    */     //   638: iconst_0
/*    */     //   639: goto -> 691
/*    */     //   642: aload #17
/*    */     //   644: instanceof java/lang/Number
/*    */     //   647: ifeq -> 663
/*    */     //   650: aload #17
/*    */     //   652: checkcast java/lang/Number
/*    */     //   655: aload #18
/*    */     //   657: invokestatic equalsNumObject : (Ljava/lang/Number;Ljava/lang/Object;)Z
/*    */     //   660: goto -> 691
/*    */     //   663: aload #17
/*    */     //   665: instanceof java/lang/Character
/*    */     //   668: ifeq -> 684
/*    */     //   671: aload #17
/*    */     //   673: checkcast java/lang/Character
/*    */     //   676: aload #18
/*    */     //   678: invokestatic equalsCharObject : (Ljava/lang/Character;Ljava/lang/Object;)Z
/*    */     //   681: goto -> 691
/*    */     //   684: aload #17
/*    */     //   686: aload #18
/*    */     //   688: invokevirtual equals : (Ljava/lang/Object;)Z
/*    */     //   691: ifeq -> 1295
/*    */     //   694: aload_0
/*    */     //   695: invokevirtual _9 : ()Ljava/lang/Object;
/*    */     //   698: aload #33
/*    */     //   700: invokevirtual _9 : ()Ljava/lang/Object;
/*    */     //   703: astore #20
/*    */     //   705: dup
/*    */     //   706: astore #19
/*    */     //   708: aload #20
/*    */     //   710: if_acmpne -> 717
/*    */     //   713: iconst_1
/*    */     //   714: goto -> 775
/*    */     //   717: aload #19
/*    */     //   719: ifnonnull -> 726
/*    */     //   722: iconst_0
/*    */     //   723: goto -> 775
/*    */     //   726: aload #19
/*    */     //   728: instanceof java/lang/Number
/*    */     //   731: ifeq -> 747
/*    */     //   734: aload #19
/*    */     //   736: checkcast java/lang/Number
/*    */     //   739: aload #20
/*    */     //   741: invokestatic equalsNumObject : (Ljava/lang/Number;Ljava/lang/Object;)Z
/*    */     //   744: goto -> 775
/*    */     //   747: aload #19
/*    */     //   749: instanceof java/lang/Character
/*    */     //   752: ifeq -> 768
/*    */     //   755: aload #19
/*    */     //   757: checkcast java/lang/Character
/*    */     //   760: aload #20
/*    */     //   762: invokestatic equalsCharObject : (Ljava/lang/Character;Ljava/lang/Object;)Z
/*    */     //   765: goto -> 775
/*    */     //   768: aload #19
/*    */     //   770: aload #20
/*    */     //   772: invokevirtual equals : (Ljava/lang/Object;)Z
/*    */     //   775: ifeq -> 1295
/*    */     //   778: aload_0
/*    */     //   779: invokevirtual _10 : ()Ljava/lang/Object;
/*    */     //   782: aload #33
/*    */     //   784: invokevirtual _10 : ()Ljava/lang/Object;
/*    */     //   787: astore #22
/*    */     //   789: dup
/*    */     //   790: astore #21
/*    */     //   792: aload #22
/*    */     //   794: if_acmpne -> 801
/*    */     //   797: iconst_1
/*    */     //   798: goto -> 859
/*    */     //   801: aload #21
/*    */     //   803: ifnonnull -> 810
/*    */     //   806: iconst_0
/*    */     //   807: goto -> 859
/*    */     //   810: aload #21
/*    */     //   812: instanceof java/lang/Number
/*    */     //   815: ifeq -> 831
/*    */     //   818: aload #21
/*    */     //   820: checkcast java/lang/Number
/*    */     //   823: aload #22
/*    */     //   825: invokestatic equalsNumObject : (Ljava/lang/Number;Ljava/lang/Object;)Z
/*    */     //   828: goto -> 859
/*    */     //   831: aload #21
/*    */     //   833: instanceof java/lang/Character
/*    */     //   836: ifeq -> 852
/*    */     //   839: aload #21
/*    */     //   841: checkcast java/lang/Character
/*    */     //   844: aload #22
/*    */     //   846: invokestatic equalsCharObject : (Ljava/lang/Character;Ljava/lang/Object;)Z
/*    */     //   849: goto -> 859
/*    */     //   852: aload #21
/*    */     //   854: aload #22
/*    */     //   856: invokevirtual equals : (Ljava/lang/Object;)Z
/*    */     //   859: ifeq -> 1295
/*    */     //   862: aload_0
/*    */     //   863: invokevirtual _11 : ()Ljava/lang/Object;
/*    */     //   866: aload #33
/*    */     //   868: invokevirtual _11 : ()Ljava/lang/Object;
/*    */     //   871: astore #24
/*    */     //   873: dup
/*    */     //   874: astore #23
/*    */     //   876: aload #24
/*    */     //   878: if_acmpne -> 885
/*    */     //   881: iconst_1
/*    */     //   882: goto -> 943
/*    */     //   885: aload #23
/*    */     //   887: ifnonnull -> 894
/*    */     //   890: iconst_0
/*    */     //   891: goto -> 943
/*    */     //   894: aload #23
/*    */     //   896: instanceof java/lang/Number
/*    */     //   899: ifeq -> 915
/*    */     //   902: aload #23
/*    */     //   904: checkcast java/lang/Number
/*    */     //   907: aload #24
/*    */     //   909: invokestatic equalsNumObject : (Ljava/lang/Number;Ljava/lang/Object;)Z
/*    */     //   912: goto -> 943
/*    */     //   915: aload #23
/*    */     //   917: instanceof java/lang/Character
/*    */     //   920: ifeq -> 936
/*    */     //   923: aload #23
/*    */     //   925: checkcast java/lang/Character
/*    */     //   928: aload #24
/*    */     //   930: invokestatic equalsCharObject : (Ljava/lang/Character;Ljava/lang/Object;)Z
/*    */     //   933: goto -> 943
/*    */     //   936: aload #23
/*    */     //   938: aload #24
/*    */     //   940: invokevirtual equals : (Ljava/lang/Object;)Z
/*    */     //   943: ifeq -> 1295
/*    */     //   946: aload_0
/*    */     //   947: invokevirtual _12 : ()Ljava/lang/Object;
/*    */     //   950: aload #33
/*    */     //   952: invokevirtual _12 : ()Ljava/lang/Object;
/*    */     //   955: astore #26
/*    */     //   957: dup
/*    */     //   958: astore #25
/*    */     //   960: aload #26
/*    */     //   962: if_acmpne -> 969
/*    */     //   965: iconst_1
/*    */     //   966: goto -> 1027
/*    */     //   969: aload #25
/*    */     //   971: ifnonnull -> 978
/*    */     //   974: iconst_0
/*    */     //   975: goto -> 1027
/*    */     //   978: aload #25
/*    */     //   980: instanceof java/lang/Number
/*    */     //   983: ifeq -> 999
/*    */     //   986: aload #25
/*    */     //   988: checkcast java/lang/Number
/*    */     //   991: aload #26
/*    */     //   993: invokestatic equalsNumObject : (Ljava/lang/Number;Ljava/lang/Object;)Z
/*    */     //   996: goto -> 1027
/*    */     //   999: aload #25
/*    */     //   1001: instanceof java/lang/Character
/*    */     //   1004: ifeq -> 1020
/*    */     //   1007: aload #25
/*    */     //   1009: checkcast java/lang/Character
/*    */     //   1012: aload #26
/*    */     //   1014: invokestatic equalsCharObject : (Ljava/lang/Character;Ljava/lang/Object;)Z
/*    */     //   1017: goto -> 1027
/*    */     //   1020: aload #25
/*    */     //   1022: aload #26
/*    */     //   1024: invokevirtual equals : (Ljava/lang/Object;)Z
/*    */     //   1027: ifeq -> 1295
/*    */     //   1030: aload_0
/*    */     //   1031: invokevirtual _13 : ()Ljava/lang/Object;
/*    */     //   1034: aload #33
/*    */     //   1036: invokevirtual _13 : ()Ljava/lang/Object;
/*    */     //   1039: astore #28
/*    */     //   1041: dup
/*    */     //   1042: astore #27
/*    */     //   1044: aload #28
/*    */     //   1046: if_acmpne -> 1053
/*    */     //   1049: iconst_1
/*    */     //   1050: goto -> 1111
/*    */     //   1053: aload #27
/*    */     //   1055: ifnonnull -> 1062
/*    */     //   1058: iconst_0
/*    */     //   1059: goto -> 1111
/*    */     //   1062: aload #27
/*    */     //   1064: instanceof java/lang/Number
/*    */     //   1067: ifeq -> 1083
/*    */     //   1070: aload #27
/*    */     //   1072: checkcast java/lang/Number
/*    */     //   1075: aload #28
/*    */     //   1077: invokestatic equalsNumObject : (Ljava/lang/Number;Ljava/lang/Object;)Z
/*    */     //   1080: goto -> 1111
/*    */     //   1083: aload #27
/*    */     //   1085: instanceof java/lang/Character
/*    */     //   1088: ifeq -> 1104
/*    */     //   1091: aload #27
/*    */     //   1093: checkcast java/lang/Character
/*    */     //   1096: aload #28
/*    */     //   1098: invokestatic equalsCharObject : (Ljava/lang/Character;Ljava/lang/Object;)Z
/*    */     //   1101: goto -> 1111
/*    */     //   1104: aload #27
/*    */     //   1106: aload #28
/*    */     //   1108: invokevirtual equals : (Ljava/lang/Object;)Z
/*    */     //   1111: ifeq -> 1295
/*    */     //   1114: aload_0
/*    */     //   1115: invokevirtual _14 : ()Ljava/lang/Object;
/*    */     //   1118: aload #33
/*    */     //   1120: invokevirtual _14 : ()Ljava/lang/Object;
/*    */     //   1123: astore #30
/*    */     //   1125: dup
/*    */     //   1126: astore #29
/*    */     //   1128: aload #30
/*    */     //   1130: if_acmpne -> 1137
/*    */     //   1133: iconst_1
/*    */     //   1134: goto -> 1195
/*    */     //   1137: aload #29
/*    */     //   1139: ifnonnull -> 1146
/*    */     //   1142: iconst_0
/*    */     //   1143: goto -> 1195
/*    */     //   1146: aload #29
/*    */     //   1148: instanceof java/lang/Number
/*    */     //   1151: ifeq -> 1167
/*    */     //   1154: aload #29
/*    */     //   1156: checkcast java/lang/Number
/*    */     //   1159: aload #30
/*    */     //   1161: invokestatic equalsNumObject : (Ljava/lang/Number;Ljava/lang/Object;)Z
/*    */     //   1164: goto -> 1195
/*    */     //   1167: aload #29
/*    */     //   1169: instanceof java/lang/Character
/*    */     //   1172: ifeq -> 1188
/*    */     //   1175: aload #29
/*    */     //   1177: checkcast java/lang/Character
/*    */     //   1180: aload #30
/*    */     //   1182: invokestatic equalsCharObject : (Ljava/lang/Character;Ljava/lang/Object;)Z
/*    */     //   1185: goto -> 1195
/*    */     //   1188: aload #29
/*    */     //   1190: aload #30
/*    */     //   1192: invokevirtual equals : (Ljava/lang/Object;)Z
/*    */     //   1195: ifeq -> 1295
/*    */     //   1198: aload_0
/*    */     //   1199: invokevirtual _15 : ()Ljava/lang/Object;
/*    */     //   1202: aload #33
/*    */     //   1204: invokevirtual _15 : ()Ljava/lang/Object;
/*    */     //   1207: astore #32
/*    */     //   1209: dup
/*    */     //   1210: astore #31
/*    */     //   1212: aload #32
/*    */     //   1214: if_acmpne -> 1221
/*    */     //   1217: iconst_1
/*    */     //   1218: goto -> 1279
/*    */     //   1221: aload #31
/*    */     //   1223: ifnonnull -> 1230
/*    */     //   1226: iconst_0
/*    */     //   1227: goto -> 1279
/*    */     //   1230: aload #31
/*    */     //   1232: instanceof java/lang/Number
/*    */     //   1235: ifeq -> 1251
/*    */     //   1238: aload #31
/*    */     //   1240: checkcast java/lang/Number
/*    */     //   1243: aload #32
/*    */     //   1245: invokestatic equalsNumObject : (Ljava/lang/Number;Ljava/lang/Object;)Z
/*    */     //   1248: goto -> 1279
/*    */     //   1251: aload #31
/*    */     //   1253: instanceof java/lang/Character
/*    */     //   1256: ifeq -> 1272
/*    */     //   1259: aload #31
/*    */     //   1261: checkcast java/lang/Character
/*    */     //   1264: aload #32
/*    */     //   1266: invokestatic equalsCharObject : (Ljava/lang/Character;Ljava/lang/Object;)Z
/*    */     //   1269: goto -> 1279
/*    */     //   1272: aload #31
/*    */     //   1274: aload #32
/*    */     //   1276: invokevirtual equals : (Ljava/lang/Object;)Z
/*    */     //   1279: ifeq -> 1295
/*    */     //   1282: aload #33
/*    */     //   1284: aload_0
/*    */     //   1285: invokevirtual canEqual : (Ljava/lang/Object;)Z
/*    */     //   1288: ifeq -> 1295
/*    */     //   1291: iconst_1
/*    */     //   1292: goto -> 1296
/*    */     //   1295: iconst_0
/*    */     //   1296: ifeq -> 1303
/*    */     //   1299: iconst_1
/*    */     //   1300: goto -> 1304
/*    */     //   1303: iconst_0
/*    */     //   1304: ireturn
/*    */     // Line number table:
/*    */     //   Java source line number -> byte code offset
/*    */     //   #32	-> 0
/*    */     //   #236	-> 12
/*    */     //   #32	-> 19
/*    */     // Local variable table:
/*    */     //   start	length	slot	name	descriptor
/*    */     //   0	1305	0	this	Lscala/Tuple15;
/*    */     //   0	1305	1	x$1	Ljava/lang/Object;
/*    */   }
/*    */   
/*    */   public Tuple15(Object _1, Object _2, Object _3, Object _4, Object _5, Object _6, Object _7, Object _8, Object _9, Object _10, Object _11, Object _12, Object _13, Object _14, Object _15) {
/* 32 */     Product$class.$init$(this);
/* 32 */     Product15$class.$init$(this);
/*    */   }
/*    */   
/*    */   public String toString() {
/* 36 */     return (new StringBuilder()).append("(").append(_1()).append(",").append(_2()).append(",").append(_3()).append(",").append(_4()).append(",").append(_5()).append(",").append(_6()).append(",").append(_7()).append(",").append(_8()).append(",").append(_9()).append(",").append(_10()).append(",").append(_11()).append(",").append(_12()).append(",").append(_13()).append(",").append(_14()).append(",").append(_15()).append(")").toString();
/*    */   }
/*    */ }


/* Location:              D:\#source-code\TheFlightSims\TFSLibrary\World2Xplane\World2XPlane.jar!\scala\Tuple15.class
 * Java compiler version: 6 (50.0)
 * JD-Core Version:       1.1.3
 */