/*    */ package scala;
/*    */ 
/*    */ import scala.collection.Iterator;
/*    */ import scala.collection.mutable.StringBuilder;
/*    */ import scala.reflect.ScalaSignature;
/*    */ import scala.runtime.ScalaRunTime$;
/*    */ 
/*    */ @ScalaSignature(bytes = "\006\001\r%d\001B\001\003\001\026\021q\001V;qY\026\f\004GC\001\004\003\025\0318-\0317b\007\001)2B\002\t\033;\001\032c%\013\0270eM)\001aB\0065oA\021\001\"C\007\002\005%\021!B\001\002\007\003:L(+\0324\021\031!aa\"\007\017 E\025B3FL\031\n\0055\021!!\003)s_\022,8\r^\0311!\ty\001\003\004\001\005\rE\001AQ1\001\023\005\t!\026'\005\002\024-A\021\001\002F\005\003+\t\021qAT8uQ&tw\r\005\002\t/%\021\001D\001\002\004\003:L\bCA\b\033\t\031Y\002\001\"b\001%\t\021AK\r\t\003\037u!aA\b\001\005\006\004\021\"A\001+4!\ty\001\005\002\004\"\001\021\025\rA\005\002\003)R\002\"aD\022\005\r\021\002AQ1\001\023\005\t!V\007\005\002\020M\0211q\005\001CC\002I\021!\001\026\034\021\005=ICA\002\026\001\t\013\007!C\001\002UoA\021q\002\f\003\007[\001!)\031\001\n\003\005QC\004CA\b0\t\031\001\004\001\"b\001%\t\021A+\017\t\003\037I\"aa\r\001\005\006\004\021\"a\001+2aA\021\001\"N\005\003m\t\021q\001\025:pIV\034G\017\005\002\tq%\021\021H\001\002\r'\026\024\030.\0317ju\006\024G.\032\005\tw\001\021)\032!C\001y\005\021q,M\013\002\035!Aa\b\001B\tB\003%a\"A\002`c\001B\001\002\021\001\003\026\004%\t!Q\001\003?J*\022!\007\005\t\007\002\021\t\022)A\0053\005\031qL\r\021\t\021\025\003!Q3A\005\002\031\013!aX\032\026\003qA\001\002\023\001\003\022\003\006I\001H\001\004?N\002\003\002\003&\001\005+\007I\021A&\002\005}#T#A\020\t\0215\003!\021#Q\001\n}\t1a\030\033!\021!y\005A!f\001\n\003\001\026AA06+\005\021\003\002\003*\001\005#\005\013\021\002\022\002\007}+\004\005\003\005U\001\tU\r\021\"\001V\003\tyf'F\001&\021!9\006A!E!\002\023)\023aA07A!A\021\f\001BK\002\023\005!,\001\002`oU\t\001\006\003\005]\001\tE\t\025!\003)\003\ryv\007\t\005\t=\002\021)\032!C\001?\006\021q\fO\013\002W!A\021\r\001B\tB\003%1&A\002`q\001B\001b\031\001\003\026\004%\t\001Z\001\003?f*\022A\f\005\tM\002\021\t\022)A\005]\005\031q,\017\021\t\021!\004!Q3A\005\002%\f1aX\0311+\005\t\004\002C6\001\005#\005\013\021B\031\002\t}\013\004\007\t\005\006[\002!\tA\\\001\007y%t\027\016\036 \025\027=\004\030O]:ukZ<\b0\037\t\r\021\001q\021\004H\020#K!Zc&\r\005\006w1\004\rA\004\005\006\0012\004\r!\007\005\006\0132\004\r\001\b\005\006\0252\004\ra\b\005\006\0372\004\rA\t\005\006)2\004\r!\n\005\00632\004\r\001\013\005\006=2\004\ra\013\005\006G2\004\rA\f\005\006Q2\004\r!\r\005\006w\002!\t\005`\001\ti>\034FO]5oOR\tQ\020E\002\003\017i\021a \006\005\003\003\t\031!\001\003mC:<'BAA\003\003\021Q\027M^1\n\007\005%qP\001\004TiJLgn\032\005\n\003\033\001\021\021!C\001\003\037\tAaY8qsV1\022\021CA\f\0037\ty\"a\t\002(\005-\022qFA\032\003o\tY\004\006\f\002\024\005u\022qHA!\003\007\n)%a\022\002J\005-\023QJA(!YA\001!!\006\002\032\005u\021\021EA\023\003S\ti#!\r\0026\005e\002cA\b\002\030\0211\021#a\003C\002I\0012aDA\016\t\031Y\0221\002b\001%A\031q\"a\b\005\ry\tYA1\001\023!\ry\0211\005\003\007C\005-!\031\001\n\021\007=\t9\003\002\004%\003\027\021\rA\005\t\004\037\005-BAB\024\002\f\t\007!\003E\002\020\003_!aAKA\006\005\004\021\002cA\b\0024\0211Q&a\003C\002I\0012aDA\034\t\031\001\0241\002b\001%A\031q\"a\017\005\rM\nYA1\001\023\021%Y\0241\002I\001\002\004\t)\002C\005A\003\027\001\n\0211\001\002\032!IQ)a\003\021\002\003\007\021Q\004\005\n\025\006-\001\023!a\001\003CA\021bTA\006!\003\005\r!!\n\t\023Q\013Y\001%AA\002\005%\002\"C-\002\fA\005\t\031AA\027\021%q\0261\002I\001\002\004\t\t\004C\005d\003\027\001\n\0211\001\0026!I\001.a\003\021\002\003\007\021\021\b\005\n\003'\002\021\023!C\001\003+\nabY8qs\022\"WMZ1vYR$\023'\006\f\002X\0055\024qNA9\003g\n)(a\036\002z\005m\024QPA@+\t\tIFK\002\017\0037Z#!!\030\021\t\005}\023\021N\007\003\003CRA!a\031\002f\005IQO\\2iK\016\\W\r\032\006\004\003O\022\021AC1o]>$\030\r^5p]&!\0211NA1\005E)hn\0315fG.,GMV1sS\006t7-\032\003\007#\005E#\031\001\n\005\rm\t\tF1\001\023\t\031q\022\021\013b\001%\0211\021%!\025C\002I!a\001JA)\005\004\021BAB\024\002R\t\007!\003\002\004+\003#\022\rA\005\003\007[\005E#\031\001\n\005\rA\n\tF1\001\023\t\031\031\024\021\013b\001%!I\0211\021\001\022\002\023\005\021QQ\001\017G>\004\030\020\n3fM\006,H\016\036\0233+Y\t9)a#\002\016\006=\025\021SAJ\003+\0139*!'\002\034\006uUCAAEU\rI\0221\f\003\007#\005\005%\031\001\n\005\rm\t\tI1\001\023\t\031q\022\021\021b\001%\0211\021%!!C\002I!a\001JAA\005\004\021BAB\024\002\002\n\007!\003\002\004+\003\003\023\rA\005\003\007[\005\005%\031\001\n\005\rA\n\tI1\001\023\t\031\031\024\021\021b\001%!I\021\021\025\001\022\002\023\005\0211U\001\017G>\004\030\020\n3fM\006,H\016\036\0234+Y\t)+!+\002,\0065\026qVAY\003g\013),a.\002:\006mVCAATU\ra\0221\f\003\007#\005}%\031\001\n\005\rm\tyJ1\001\023\t\031q\022q\024b\001%\0211\021%a(C\002I!a\001JAP\005\004\021BAB\024\002 \n\007!\003\002\004+\003?\023\rA\005\003\007[\005}%\031\001\n\005\rA\nyJ1\001\023\t\031\031\024q\024b\001%!I\021q\030\001\022\002\023\005\021\021Y\001\017G>\004\030\020\n3fM\006,H\016\036\0235+Y\t\031-a2\002J\006-\027QZAh\003#\f\031.!6\002X\006eWCAAcU\ry\0221\f\003\007#\005u&\031\001\n\005\rm\tiL1\001\023\t\031q\022Q\030b\001%\0211\021%!0C\002I!a\001JA_\005\004\021BAB\024\002>\n\007!\003\002\004+\003{\023\rA\005\003\007[\005u&\031\001\n\005\rA\niL1\001\023\t\031\031\024Q\030b\001%!I\021Q\034\001\022\002\023\005\021q\\\001\017G>\004\030\020\n3fM\006,H\016\036\0236+Y\t\t/!:\002h\006%\0301^Aw\003_\f\t0a=\002v\006]XCAArU\r\021\0231\f\003\007#\005m'\031\001\n\005\rm\tYN1\001\023\t\031q\0221\034b\001%\0211\021%a7C\002I!a\001JAn\005\004\021BAB\024\002\\\n\007!\003\002\004+\0037\024\rA\005\003\007[\005m'\031\001\n\005\rA\nYN1\001\023\t\031\031\0241\034b\001%!I\0211 \001\022\002\023\005\021Q`\001\017G>\004\030\020\n3fM\006,H\016\036\0237+Y\tyPa\001\003\006\t\035!\021\002B\006\005\033\021yA!\005\003\024\tUQC\001B\001U\r)\0231\f\003\007#\005e(\031\001\n\005\rm\tIP1\001\023\t\031q\022\021 b\001%\0211\021%!?C\002I!a\001JA}\005\004\021BAB\024\002z\n\007!\003\002\004+\003s\024\rA\005\003\007[\005e(\031\001\n\005\rA\nIP1\001\023\t\031\031\024\021 b\001%!I!\021\004\001\022\002\023\005!1D\001\017G>\004\030\020\n3fM\006,H\016\036\0238+Y\021iB!\t\003$\t\025\"q\005B\025\005W\021iCa\f\0032\tMRC\001B\020U\rA\0231\f\003\007#\t]!\031\001\n\005\rm\0219B1\001\023\t\031q\"q\003b\001%\0211\021Ea\006C\002I!a\001\nB\f\005\004\021BAB\024\003\030\t\007!\003\002\004+\005/\021\rA\005\003\007[\t]!\031\001\n\005\rA\0229B1\001\023\t\031\031$q\003b\001%!I!q\007\001\022\002\023\005!\021H\001\017G>\004\030\020\n3fM\006,H\016\036\0239+Y\021YDa\020\003B\t\r#Q\tB$\005\023\022YE!\024\003P\tESC\001B\037U\rY\0231\f\003\007#\tU\"\031\001\n\005\rm\021)D1\001\023\t\031q\"Q\007b\001%\0211\021E!\016C\002I!a\001\nB\033\005\004\021BAB\024\0036\t\007!\003\002\004+\005k\021\rA\005\003\007[\tU\"\031\001\n\005\rA\022)D1\001\023\t\031\031$Q\007b\001%!I!Q\013\001\022\002\023\005!qK\001\017G>\004\030\020\n3fM\006,H\016\036\023:+Y\021IF!\030\003`\t\005$1\rB3\005O\022IGa\033\003n\t=TC\001B.U\rq\0231\f\003\007#\tM#\031\001\n\005\rm\021\031F1\001\023\t\031q\"1\013b\001%\0211\021Ea\025C\002I!a\001\nB*\005\004\021BAB\024\003T\t\007!\003\002\004+\005'\022\rA\005\003\007[\tM#\031\001\n\005\rA\022\031F1\001\023\t\031\031$1\013b\001%!I!1\017\001\022\002\023\005!QO\001\020G>\004\030\020\n3fM\006,H\016\036\0232aU1\"q\017B>\005{\022yH!!\003\004\n\025%q\021BE\005\027\023i)\006\002\003z)\032\021'a\027\005\rE\021\tH1\001\023\t\031Y\"\021\017b\001%\0211aD!\035C\002I!a!\tB9\005\004\021BA\002\023\003r\t\007!\003\002\004(\005c\022\rA\005\003\007U\tE$\031\001\n\005\r5\022\tH1\001\023\t\031\001$\021\017b\001%\02111G!\035C\002IA\021B!%\001\003\003%\tEa%\002\033A\024x\016Z;diB\023XMZ5y+\005i\b\"\003BL\001\005\005I\021\tBM\003=\001(o\0343vGRLE/\032:bi>\024XC\001BN!\025\021iJa)\027\033\t\021yJC\002\003\"\n\t!bY8mY\026\034G/[8o\023\021\021)Ka(\003\021%#XM]1u_JD\021B!+\001\003\003%\tAa+\002\021\r\fg.R9vC2$BA!,\0034B\031\001Ba,\n\007\tE&AA\004C_>dW-\0318\t\023\tU&qUA\001\002\0041\022a\001=%c!I!\021\030\001\002\002\023\005#1X\001\tQ\006\034\bnQ8eKR\021!Q\030\t\004\021\t}\026b\001Ba\005\t\031\021J\034;\t\023\t\025\007!!A\005B\t\035\027AB3rk\006d7\017\006\003\003.\n%\007\"\003B[\005\007\f\t\0211\001\027\017%\021iMAA\001\022\003\021y-A\004UkBdW-\r\031\021\007!\021\tN\002\005\002\005\005\005\t\022\001Bj'\021\021\tnB\034\t\0175\024\t\016\"\001\003XR\021!q\032\005\tw\nE\027\021!C#y\"Q!Q\034Bi\003\003%\tIa8\002\013\005\004\b\017\\=\026-\t\005(q\035Bv\005_\024\031Pa>\003|\n}81AB\004\007\027!bCa9\004\016\r=1\021CB\n\007+\0319b!\007\004\034\ru1q\004\t\027\021\001\021)O!;\003n\nE(Q\037B}\005{\034\ta!\002\004\nA\031qBa:\005\rE\021YN1\001\023!\ry!1\036\003\0077\tm'\031\001\n\021\007=\021y\017\002\004\037\0057\024\rA\005\t\004\037\tMHAB\021\003\\\n\007!\003E\002\020\005o$a\001\nBn\005\004\021\002cA\b\003|\0221qEa7C\002I\0012a\004B\000\t\031Q#1\034b\001%A\031qba\001\005\r5\022YN1\001\023!\ry1q\001\003\007a\tm'\031\001\n\021\007=\031Y\001\002\0044\0057\024\rA\005\005\bw\tm\007\031\001Bs\021\035\001%1\034a\001\005SDq!\022Bn\001\004\021i\017C\004K\0057\004\rA!=\t\017=\023Y\0161\001\003v\"9AKa7A\002\te\bbB-\003\\\002\007!Q \005\b=\nm\007\031AB\001\021\035\031'1\034a\001\007\013Aq\001\033Bn\001\004\031I\001\003\006\004$\tE\027\021!CA\007K\tq!\0368baBd\0270\006\f\004(\rM2qGB\036\007\031\031ea\022\004L\r=31KB,)\021\031Ic!\027\021\013!\031Yca\f\n\007\r5\"A\001\004PaRLwN\034\t\027\021\001\031\td!\016\004:\ru2\021IB#\007\023\032ie!\025\004VA\031qba\r\005\rE\031\tC1\001\023!\ry1q\007\003\0077\r\005\"\031\001\n\021\007=\031Y\004\002\004\037\007C\021\rA\005\t\004\037\r}BAB\021\004\"\t\007!\003E\002\020\007\007\"a\001JB\021\005\004\021\002cA\b\004H\0211qe!\tC\002I\0012aDB&\t\031Q3\021\005b\001%A\031qba\024\005\r5\032\tC1\001\023!\ry11\013\003\007a\r\005\"\031\001\n\021\007=\0319\006\002\0044\007C\021\rA\005\005\013\0077\032\t#!AA\002\r=\022a\001=%a!Q1q\fBi\003\003%Ia!\031\002\027I,\027\r\032*fg>dg/\032\013\003\007G\0022A`B3\023\r\0319g \002\007\037\nTWm\031;")
/*    */ public class Tuple10<T1, T2, T3, T4, T5, T6, T7, T8, T9, T10> implements Product10<T1, T2, T3, T4, T5, T6, T7, T8, T9, T10>, Product, Serializable {
/*    */   private final T1 _1;
/*    */   
/*    */   private final T2 _2;
/*    */   
/*    */   private final T3 _3;
/*    */   
/*    */   private final T4 _4;
/*    */   
/*    */   private final T5 _5;
/*    */   
/*    */   private final T6 _6;
/*    */   
/*    */   private final T7 _7;
/*    */   
/*    */   private final T8 _8;
/*    */   
/*    */   private final T9 _9;
/*    */   
/*    */   private final T10 _10;
/*    */   
/*    */   public int productArity() {
/* 27 */     return Product10$class.productArity(this);
/*    */   }
/*    */   
/*    */   public Object productElement(int n) throws IndexOutOfBoundsException {
/* 27 */     return Product10$class.productElement(this, n);
/*    */   }
/*    */   
/*    */   public T1 _1() {
/* 27 */     return this._1;
/*    */   }
/*    */   
/*    */   public T2 _2() {
/* 27 */     return this._2;
/*    */   }
/*    */   
/*    */   public T3 _3() {
/* 27 */     return this._3;
/*    */   }
/*    */   
/*    */   public T4 _4() {
/* 27 */     return this._4;
/*    */   }
/*    */   
/*    */   public T5 _5() {
/* 27 */     return this._5;
/*    */   }
/*    */   
/*    */   public T6 _6() {
/* 27 */     return this._6;
/*    */   }
/*    */   
/*    */   public T7 _7() {
/* 27 */     return this._7;
/*    */   }
/*    */   
/*    */   public T8 _8() {
/* 27 */     return this._8;
/*    */   }
/*    */   
/*    */   public T9 _9() {
/* 27 */     return this._9;
/*    */   }
/*    */   
/*    */   public T10 _10() {
/* 27 */     return this._10;
/*    */   }
/*    */   
/*    */   public <T1, T2, T3, T4, T5, T6, T7, T8, T9, T10> Tuple10<T1, T2, T3, T4, T5, T6, T7, T8, T9, T10> copy(Object _1, Object _2, Object _3, Object _4, Object _5, Object _6, Object _7, Object _8, Object _9, Object _10) {
/* 27 */     return new Tuple10((T1)_1, (T2)_2, (T3)_3, (T4)_4, (T5)_5, (T6)_6, (T7)_7, (T8)_8, (T9)_9, (T10)_10);
/*    */   }
/*    */   
/*    */   public <T1, T2, T3, T4, T5, T6, T7, T8, T9, T10> T1 copy$default$1() {
/* 27 */     return _1();
/*    */   }
/*    */   
/*    */   public <T1, T2, T3, T4, T5, T6, T7, T8, T9, T10> T2 copy$default$2() {
/* 27 */     return _2();
/*    */   }
/*    */   
/*    */   public <T1, T2, T3, T4, T5, T6, T7, T8, T9, T10> T3 copy$default$3() {
/* 27 */     return _3();
/*    */   }
/*    */   
/*    */   public <T1, T2, T3, T4, T5, T6, T7, T8, T9, T10> T4 copy$default$4() {
/* 27 */     return _4();
/*    */   }
/*    */   
/*    */   public <T1, T2, T3, T4, T5, T6, T7, T8, T9, T10> T5 copy$default$5() {
/* 27 */     return _5();
/*    */   }
/*    */   
/*    */   public <T1, T2, T3, T4, T5, T6, T7, T8, T9, T10> T6 copy$default$6() {
/* 27 */     return _6();
/*    */   }
/*    */   
/*    */   public <T1, T2, T3, T4, T5, T6, T7, T8, T9, T10> T7 copy$default$7() {
/* 27 */     return _7();
/*    */   }
/*    */   
/*    */   public <T1, T2, T3, T4, T5, T6, T7, T8, T9, T10> T8 copy$default$8() {
/* 27 */     return _8();
/*    */   }
/*    */   
/*    */   public <T1, T2, T3, T4, T5, T6, T7, T8, T9, T10> T9 copy$default$9() {
/* 27 */     return _9();
/*    */   }
/*    */   
/*    */   public <T1, T2, T3, T4, T5, T6, T7, T8, T9, T10> T10 copy$default$10() {
/* 27 */     return _10();
/*    */   }
/*    */   
/*    */   public String productPrefix() {
/* 27 */     return "Tuple10";
/*    */   }
/*    */   
/*    */   public Iterator<Object> productIterator() {
/* 27 */     return ScalaRunTime$.MODULE$.typedProductIterator(this);
/*    */   }
/*    */   
/*    */   public boolean canEqual(Object x$1) {
/* 27 */     return x$1 instanceof Tuple10;
/*    */   }
/*    */   
/*    */   public int hashCode() {
/* 27 */     return ScalaRunTime$.MODULE$._hashCode(this);
/*    */   }
/*    */   
/*    */   public boolean equals(Object x$1) {
/*    */     // Byte code:
/*    */     //   0: aload_0
/*    */     //   1: aload_1
/*    */     //   2: if_acmpeq -> 879
/*    */     //   5: aload_1
/*    */     //   6: instanceof scala/Tuple10
/*    */     //   9: ifeq -> 17
/*    */     //   12: iconst_1
/*    */     //   13: istore_2
/*    */     //   14: goto -> 19
/*    */     //   17: iconst_0
/*    */     //   18: istore_2
/*    */     //   19: iload_2
/*    */     //   20: ifeq -> 883
/*    */     //   23: aload_1
/*    */     //   24: checkcast scala/Tuple10
/*    */     //   27: astore #23
/*    */     //   29: aload_0
/*    */     //   30: invokevirtual _1 : ()Ljava/lang/Object;
/*    */     //   33: aload #23
/*    */     //   35: invokevirtual _1 : ()Ljava/lang/Object;
/*    */     //   38: astore #4
/*    */     //   40: dup
/*    */     //   41: astore_3
/*    */     //   42: aload #4
/*    */     //   44: if_acmpne -> 51
/*    */     //   47: iconst_1
/*    */     //   48: goto -> 103
/*    */     //   51: aload_3
/*    */     //   52: ifnonnull -> 59
/*    */     //   55: iconst_0
/*    */     //   56: goto -> 103
/*    */     //   59: aload_3
/*    */     //   60: instanceof java/lang/Number
/*    */     //   63: ifeq -> 78
/*    */     //   66: aload_3
/*    */     //   67: checkcast java/lang/Number
/*    */     //   70: aload #4
/*    */     //   72: invokestatic equalsNumObject : (Ljava/lang/Number;Ljava/lang/Object;)Z
/*    */     //   75: goto -> 103
/*    */     //   78: aload_3
/*    */     //   79: instanceof java/lang/Character
/*    */     //   82: ifeq -> 97
/*    */     //   85: aload_3
/*    */     //   86: checkcast java/lang/Character
/*    */     //   89: aload #4
/*    */     //   91: invokestatic equalsCharObject : (Ljava/lang/Character;Ljava/lang/Object;)Z
/*    */     //   94: goto -> 103
/*    */     //   97: aload_3
/*    */     //   98: aload #4
/*    */     //   100: invokevirtual equals : (Ljava/lang/Object;)Z
/*    */     //   103: ifeq -> 875
/*    */     //   106: aload_0
/*    */     //   107: invokevirtual _2 : ()Ljava/lang/Object;
/*    */     //   110: aload #23
/*    */     //   112: invokevirtual _2 : ()Ljava/lang/Object;
/*    */     //   115: astore #6
/*    */     //   117: dup
/*    */     //   118: astore #5
/*    */     //   120: aload #6
/*    */     //   122: if_acmpne -> 129
/*    */     //   125: iconst_1
/*    */     //   126: goto -> 187
/*    */     //   129: aload #5
/*    */     //   131: ifnonnull -> 138
/*    */     //   134: iconst_0
/*    */     //   135: goto -> 187
/*    */     //   138: aload #5
/*    */     //   140: instanceof java/lang/Number
/*    */     //   143: ifeq -> 159
/*    */     //   146: aload #5
/*    */     //   148: checkcast java/lang/Number
/*    */     //   151: aload #6
/*    */     //   153: invokestatic equalsNumObject : (Ljava/lang/Number;Ljava/lang/Object;)Z
/*    */     //   156: goto -> 187
/*    */     //   159: aload #5
/*    */     //   161: instanceof java/lang/Character
/*    */     //   164: ifeq -> 180
/*    */     //   167: aload #5
/*    */     //   169: checkcast java/lang/Character
/*    */     //   172: aload #6
/*    */     //   174: invokestatic equalsCharObject : (Ljava/lang/Character;Ljava/lang/Object;)Z
/*    */     //   177: goto -> 187
/*    */     //   180: aload #5
/*    */     //   182: aload #6
/*    */     //   184: invokevirtual equals : (Ljava/lang/Object;)Z
/*    */     //   187: ifeq -> 875
/*    */     //   190: aload_0
/*    */     //   191: invokevirtual _3 : ()Ljava/lang/Object;
/*    */     //   194: aload #23
/*    */     //   196: invokevirtual _3 : ()Ljava/lang/Object;
/*    */     //   199: astore #8
/*    */     //   201: dup
/*    */     //   202: astore #7
/*    */     //   204: aload #8
/*    */     //   206: if_acmpne -> 213
/*    */     //   209: iconst_1
/*    */     //   210: goto -> 271
/*    */     //   213: aload #7
/*    */     //   215: ifnonnull -> 222
/*    */     //   218: iconst_0
/*    */     //   219: goto -> 271
/*    */     //   222: aload #7
/*    */     //   224: instanceof java/lang/Number
/*    */     //   227: ifeq -> 243
/*    */     //   230: aload #7
/*    */     //   232: checkcast java/lang/Number
/*    */     //   235: aload #8
/*    */     //   237: invokestatic equalsNumObject : (Ljava/lang/Number;Ljava/lang/Object;)Z
/*    */     //   240: goto -> 271
/*    */     //   243: aload #7
/*    */     //   245: instanceof java/lang/Character
/*    */     //   248: ifeq -> 264
/*    */     //   251: aload #7
/*    */     //   253: checkcast java/lang/Character
/*    */     //   256: aload #8
/*    */     //   258: invokestatic equalsCharObject : (Ljava/lang/Character;Ljava/lang/Object;)Z
/*    */     //   261: goto -> 271
/*    */     //   264: aload #7
/*    */     //   266: aload #8
/*    */     //   268: invokevirtual equals : (Ljava/lang/Object;)Z
/*    */     //   271: ifeq -> 875
/*    */     //   274: aload_0
/*    */     //   275: invokevirtual _4 : ()Ljava/lang/Object;
/*    */     //   278: aload #23
/*    */     //   280: invokevirtual _4 : ()Ljava/lang/Object;
/*    */     //   283: astore #10
/*    */     //   285: dup
/*    */     //   286: astore #9
/*    */     //   288: aload #10
/*    */     //   290: if_acmpne -> 297
/*    */     //   293: iconst_1
/*    */     //   294: goto -> 355
/*    */     //   297: aload #9
/*    */     //   299: ifnonnull -> 306
/*    */     //   302: iconst_0
/*    */     //   303: goto -> 355
/*    */     //   306: aload #9
/*    */     //   308: instanceof java/lang/Number
/*    */     //   311: ifeq -> 327
/*    */     //   314: aload #9
/*    */     //   316: checkcast java/lang/Number
/*    */     //   319: aload #10
/*    */     //   321: invokestatic equalsNumObject : (Ljava/lang/Number;Ljava/lang/Object;)Z
/*    */     //   324: goto -> 355
/*    */     //   327: aload #9
/*    */     //   329: instanceof java/lang/Character
/*    */     //   332: ifeq -> 348
/*    */     //   335: aload #9
/*    */     //   337: checkcast java/lang/Character
/*    */     //   340: aload #10
/*    */     //   342: invokestatic equalsCharObject : (Ljava/lang/Character;Ljava/lang/Object;)Z
/*    */     //   345: goto -> 355
/*    */     //   348: aload #9
/*    */     //   350: aload #10
/*    */     //   352: invokevirtual equals : (Ljava/lang/Object;)Z
/*    */     //   355: ifeq -> 875
/*    */     //   358: aload_0
/*    */     //   359: invokevirtual _5 : ()Ljava/lang/Object;
/*    */     //   362: aload #23
/*    */     //   364: invokevirtual _5 : ()Ljava/lang/Object;
/*    */     //   367: astore #12
/*    */     //   369: dup
/*    */     //   370: astore #11
/*    */     //   372: aload #12
/*    */     //   374: if_acmpne -> 381
/*    */     //   377: iconst_1
/*    */     //   378: goto -> 439
/*    */     //   381: aload #11
/*    */     //   383: ifnonnull -> 390
/*    */     //   386: iconst_0
/*    */     //   387: goto -> 439
/*    */     //   390: aload #11
/*    */     //   392: instanceof java/lang/Number
/*    */     //   395: ifeq -> 411
/*    */     //   398: aload #11
/*    */     //   400: checkcast java/lang/Number
/*    */     //   403: aload #12
/*    */     //   405: invokestatic equalsNumObject : (Ljava/lang/Number;Ljava/lang/Object;)Z
/*    */     //   408: goto -> 439
/*    */     //   411: aload #11
/*    */     //   413: instanceof java/lang/Character
/*    */     //   416: ifeq -> 432
/*    */     //   419: aload #11
/*    */     //   421: checkcast java/lang/Character
/*    */     //   424: aload #12
/*    */     //   426: invokestatic equalsCharObject : (Ljava/lang/Character;Ljava/lang/Object;)Z
/*    */     //   429: goto -> 439
/*    */     //   432: aload #11
/*    */     //   434: aload #12
/*    */     //   436: invokevirtual equals : (Ljava/lang/Object;)Z
/*    */     //   439: ifeq -> 875
/*    */     //   442: aload_0
/*    */     //   443: invokevirtual _6 : ()Ljava/lang/Object;
/*    */     //   446: aload #23
/*    */     //   448: invokevirtual _6 : ()Ljava/lang/Object;
/*    */     //   451: astore #14
/*    */     //   453: dup
/*    */     //   454: astore #13
/*    */     //   456: aload #14
/*    */     //   458: if_acmpne -> 465
/*    */     //   461: iconst_1
/*    */     //   462: goto -> 523
/*    */     //   465: aload #13
/*    */     //   467: ifnonnull -> 474
/*    */     //   470: iconst_0
/*    */     //   471: goto -> 523
/*    */     //   474: aload #13
/*    */     //   476: instanceof java/lang/Number
/*    */     //   479: ifeq -> 495
/*    */     //   482: aload #13
/*    */     //   484: checkcast java/lang/Number
/*    */     //   487: aload #14
/*    */     //   489: invokestatic equalsNumObject : (Ljava/lang/Number;Ljava/lang/Object;)Z
/*    */     //   492: goto -> 523
/*    */     //   495: aload #13
/*    */     //   497: instanceof java/lang/Character
/*    */     //   500: ifeq -> 516
/*    */     //   503: aload #13
/*    */     //   505: checkcast java/lang/Character
/*    */     //   508: aload #14
/*    */     //   510: invokestatic equalsCharObject : (Ljava/lang/Character;Ljava/lang/Object;)Z
/*    */     //   513: goto -> 523
/*    */     //   516: aload #13
/*    */     //   518: aload #14
/*    */     //   520: invokevirtual equals : (Ljava/lang/Object;)Z
/*    */     //   523: ifeq -> 875
/*    */     //   526: aload_0
/*    */     //   527: invokevirtual _7 : ()Ljava/lang/Object;
/*    */     //   530: aload #23
/*    */     //   532: invokevirtual _7 : ()Ljava/lang/Object;
/*    */     //   535: astore #16
/*    */     //   537: dup
/*    */     //   538: astore #15
/*    */     //   540: aload #16
/*    */     //   542: if_acmpne -> 549
/*    */     //   545: iconst_1
/*    */     //   546: goto -> 607
/*    */     //   549: aload #15
/*    */     //   551: ifnonnull -> 558
/*    */     //   554: iconst_0
/*    */     //   555: goto -> 607
/*    */     //   558: aload #15
/*    */     //   560: instanceof java/lang/Number
/*    */     //   563: ifeq -> 579
/*    */     //   566: aload #15
/*    */     //   568: checkcast java/lang/Number
/*    */     //   571: aload #16
/*    */     //   573: invokestatic equalsNumObject : (Ljava/lang/Number;Ljava/lang/Object;)Z
/*    */     //   576: goto -> 607
/*    */     //   579: aload #15
/*    */     //   581: instanceof java/lang/Character
/*    */     //   584: ifeq -> 600
/*    */     //   587: aload #15
/*    */     //   589: checkcast java/lang/Character
/*    */     //   592: aload #16
/*    */     //   594: invokestatic equalsCharObject : (Ljava/lang/Character;Ljava/lang/Object;)Z
/*    */     //   597: goto -> 607
/*    */     //   600: aload #15
/*    */     //   602: aload #16
/*    */     //   604: invokevirtual equals : (Ljava/lang/Object;)Z
/*    */     //   607: ifeq -> 875
/*    */     //   610: aload_0
/*    */     //   611: invokevirtual _8 : ()Ljava/lang/Object;
/*    */     //   614: aload #23
/*    */     //   616: invokevirtual _8 : ()Ljava/lang/Object;
/*    */     //   619: astore #18
/*    */     //   621: dup
/*    */     //   622: astore #17
/*    */     //   624: aload #18
/*    */     //   626: if_acmpne -> 633
/*    */     //   629: iconst_1
/*    */     //   630: goto -> 691
/*    */     //   633: aload #17
/*    */     //   635: ifnonnull -> 642
/*    */     //   638: iconst_0
/*    */     //   639: goto -> 691
/*    */     //   642: aload #17
/*    */     //   644: instanceof java/lang/Number
/*    */     //   647: ifeq -> 663
/*    */     //   650: aload #17
/*    */     //   652: checkcast java/lang/Number
/*    */     //   655: aload #18
/*    */     //   657: invokestatic equalsNumObject : (Ljava/lang/Number;Ljava/lang/Object;)Z
/*    */     //   660: goto -> 691
/*    */     //   663: aload #17
/*    */     //   665: instanceof java/lang/Character
/*    */     //   668: ifeq -> 684
/*    */     //   671: aload #17
/*    */     //   673: checkcast java/lang/Character
/*    */     //   676: aload #18
/*    */     //   678: invokestatic equalsCharObject : (Ljava/lang/Character;Ljava/lang/Object;)Z
/*    */     //   681: goto -> 691
/*    */     //   684: aload #17
/*    */     //   686: aload #18
/*    */     //   688: invokevirtual equals : (Ljava/lang/Object;)Z
/*    */     //   691: ifeq -> 875
/*    */     //   694: aload_0
/*    */     //   695: invokevirtual _9 : ()Ljava/lang/Object;
/*    */     //   698: aload #23
/*    */     //   700: invokevirtual _9 : ()Ljava/lang/Object;
/*    */     //   703: astore #20
/*    */     //   705: dup
/*    */     //   706: astore #19
/*    */     //   708: aload #20
/*    */     //   710: if_acmpne -> 717
/*    */     //   713: iconst_1
/*    */     //   714: goto -> 775
/*    */     //   717: aload #19
/*    */     //   719: ifnonnull -> 726
/*    */     //   722: iconst_0
/*    */     //   723: goto -> 775
/*    */     //   726: aload #19
/*    */     //   728: instanceof java/lang/Number
/*    */     //   731: ifeq -> 747
/*    */     //   734: aload #19
/*    */     //   736: checkcast java/lang/Number
/*    */     //   739: aload #20
/*    */     //   741: invokestatic equalsNumObject : (Ljava/lang/Number;Ljava/lang/Object;)Z
/*    */     //   744: goto -> 775
/*    */     //   747: aload #19
/*    */     //   749: instanceof java/lang/Character
/*    */     //   752: ifeq -> 768
/*    */     //   755: aload #19
/*    */     //   757: checkcast java/lang/Character
/*    */     //   760: aload #20
/*    */     //   762: invokestatic equalsCharObject : (Ljava/lang/Character;Ljava/lang/Object;)Z
/*    */     //   765: goto -> 775
/*    */     //   768: aload #19
/*    */     //   770: aload #20
/*    */     //   772: invokevirtual equals : (Ljava/lang/Object;)Z
/*    */     //   775: ifeq -> 875
/*    */     //   778: aload_0
/*    */     //   779: invokevirtual _10 : ()Ljava/lang/Object;
/*    */     //   782: aload #23
/*    */     //   784: invokevirtual _10 : ()Ljava/lang/Object;
/*    */     //   787: astore #22
/*    */     //   789: dup
/*    */     //   790: astore #21
/*    */     //   792: aload #22
/*    */     //   794: if_acmpne -> 801
/*    */     //   797: iconst_1
/*    */     //   798: goto -> 859
/*    */     //   801: aload #21
/*    */     //   803: ifnonnull -> 810
/*    */     //   806: iconst_0
/*    */     //   807: goto -> 859
/*    */     //   810: aload #21
/*    */     //   812: instanceof java/lang/Number
/*    */     //   815: ifeq -> 831
/*    */     //   818: aload #21
/*    */     //   820: checkcast java/lang/Number
/*    */     //   823: aload #22
/*    */     //   825: invokestatic equalsNumObject : (Ljava/lang/Number;Ljava/lang/Object;)Z
/*    */     //   828: goto -> 859
/*    */     //   831: aload #21
/*    */     //   833: instanceof java/lang/Character
/*    */     //   836: ifeq -> 852
/*    */     //   839: aload #21
/*    */     //   841: checkcast java/lang/Character
/*    */     //   844: aload #22
/*    */     //   846: invokestatic equalsCharObject : (Ljava/lang/Character;Ljava/lang/Object;)Z
/*    */     //   849: goto -> 859
/*    */     //   852: aload #21
/*    */     //   854: aload #22
/*    */     //   856: invokevirtual equals : (Ljava/lang/Object;)Z
/*    */     //   859: ifeq -> 875
/*    */     //   862: aload #23
/*    */     //   864: aload_0
/*    */     //   865: invokevirtual canEqual : (Ljava/lang/Object;)Z
/*    */     //   868: ifeq -> 875
/*    */     //   871: iconst_1
/*    */     //   872: goto -> 876
/*    */     //   875: iconst_0
/*    */     //   876: ifeq -> 883
/*    */     //   879: iconst_1
/*    */     //   880: goto -> 884
/*    */     //   883: iconst_0
/*    */     //   884: ireturn
/*    */     // Line number table:
/*    */     //   Java source line number -> byte code offset
/*    */     //   #27	-> 0
/*    */     //   #236	-> 12
/*    */     //   #27	-> 19
/*    */     // Local variable table:
/*    */     //   start	length	slot	name	descriptor
/*    */     //   0	885	0	this	Lscala/Tuple10;
/*    */     //   0	885	1	x$1	Ljava/lang/Object;
/*    */   }
/*    */   
/*    */   public Tuple10(Object _1, Object _2, Object _3, Object _4, Object _5, Object _6, Object _7, Object _8, Object _9, Object _10) {
/* 27 */     Product$class.$init$(this);
/* 27 */     Product10$class.$init$(this);
/*    */   }
/*    */   
/*    */   public String toString() {
/* 30 */     return (new StringBuilder()).append("(").append(_1()).append(",").append(_2()).append(",").append(_3()).append(",").append(_4()).append(",").append(_5()).append(",").append(_6()).append(",").append(_7()).append(",").append(_8()).append(",").append(_9()).append(",").append(_10()).append(")").toString();
/*    */   }
/*    */ }


/* Location:              D:\#source-code\TheFlightSims\TFSLibrary\World2Xplane\World2XPlane.jar!\scala\Tuple10.class
 * Java compiler version: 6 (50.0)
 * JD-Core Version:       1.1.3
 */