/*    */ package scala;
/*    */ 
/*    */ import scala.collection.Iterator;
/*    */ import scala.collection.mutable.StringBuilder;
/*    */ import scala.reflect.ScalaSignature;
/*    */ import scala.runtime.ScalaRunTime$;
/*    */ 
/*    */ @ScalaSignature(bytes = "\006\001\031]a\001B\001\003\001\026\021q\001V;qY\026\ftGC\001\004\003\025\0318-\0317b\007\001)\"C\002\t\033;\001\032c%\013\0270eUB4HP!E\017N)\001aB\006J\031B\021\001\"C\007\002\005%\021!B\001\002\007\003:L(+\0324\021'!aa\"\007\017 E\025B3FL\0315oij\004i\021$\n\0055\021!!\003)s_\022,8\r^\0318!\ty\001\003\004\001\005\rE\001AQ1\001\023\005\t!\026'\005\002\024-A\021\001\002F\005\003+\t\021qAT8uQ&tw\r\005\002\t/%\021\001D\001\002\004\003:L\bCA\b\033\t\031Y\002\001\"b\001%\t\021AK\r\t\003\037u!aA\b\001\005\006\004\021\"A\001+4!\ty\001\005\002\004\"\001\021\025\rA\005\002\003)R\002\"aD\022\005\r\021\002AQ1\001\023\005\t!V\007\005\002\020M\0211q\005\001CC\002I\021!\001\026\034\021\005=ICA\002\026\001\t\013\007!C\001\002UoA\021q\002\f\003\007[\001!)\031\001\n\003\005QC\004CA\b0\t\031\001\004\001\"b\001%\t\021A+\017\t\003\037I\"aa\r\001\005\006\004\021\"a\001+2aA\021q\"\016\003\007m\001!)\031\001\n\003\007Q\013\024\007\005\002\020q\0211\021\b\001CC\002I\0211\001V\0313!\ty1\b\002\004=\001\021\025\rA\005\002\004)F\032\004CA\b?\t\031y\004\001\"b\001%\t\031A+\r\033\021\005=\tEA\002\"\001\t\013\007!CA\002UcU\002\"a\004#\005\r\025\003AQ1\001\023\005\r!\026G\016\t\003\037\035#a\001\023\001\005\006\004\021\"a\001+2oA\021\001BS\005\003\027\n\021q\001\025:pIV\034G\017\005\002\t\033&\021aJ\001\002\r'\026\024\030.\0317ju\006\024G.\032\005\t!\002\021)\032!C\001#\006\021q,M\013\002\035!A1\013\001B\tB\003%a\"A\002`c\001B\001\"\026\001\003\026\004%\tAV\001\003?J*\022!\007\005\t1\002\021\t\022)A\0053\005\031qL\r\021\t\021i\003!Q3A\005\002m\013!aX\032\026\003qA\001\"\030\001\003\022\003\006I\001H\001\004?N\002\003\002C0\001\005+\007I\021\0011\002\005}#T#A\020\t\021\t\004!\021#Q\001\n}\t1a\030\033!\021!!\007A!f\001\n\003)\027AA06+\005\021\003\002C4\001\005#\005\013\021\002\022\002\007}+\004\005\003\005j\001\tU\r\021\"\001k\003\tyf'F\001&\021!a\007A!E!\002\023)\023aA07A!Aa\016\001BK\002\023\005q.\001\002`oU\t\001\006\003\005r\001\tE\t\025!\003)\003\ryv\007\t\005\tg\002\021)\032!C\001i\006\021q\fO\013\002W!Aa\017\001B\tB\003%1&A\002`q\001B\001\002\037\001\003\026\004%\t!_\001\003?f*\022A\f\005\tw\002\021\t\022)A\005]\005\031q,\017\021\t\021u\004!Q3A\005\002y\f1aX\0311+\005\t\004\"CA\001\001\tE\t\025!\0032\003\021y\026\007\r\021\t\025\005\025\001A!f\001\n\003\t9!A\002`cE*\022\001\016\005\n\003\027\001!\021#Q\001\nQ\nAaX\0312A!Q\021q\002\001\003\026\004%\t!!\005\002\007}\013$'F\0018\021%\t)\002\001B\tB\003%q'\001\003`cI\002\003BCA\r\001\tU\r\021\"\001\002\034\005\031q,M\032\026\003iB\021\"a\b\001\005#\005\013\021\002\036\002\t}\0134\007\t\005\013\003G\001!Q3A\005\002\005\025\022aA02iU\tQ\bC\005\002*\001\021\t\022)A\005{\005!q,\r\033!\021)\ti\003\001BK\002\023\005\021qF\001\004?F*T#\001!\t\023\005M\002A!E!\002\023\001\025\001B02k\001B!\"a\016\001\005+\007I\021AA\035\003\ry\026GN\013\002\007\"I\021Q\b\001\003\022\003\006IaQ\001\005?F2\004\005\003\006\002B\001\021)\032!C\001\003\007\n1aX\0318+\0051\005\"CA$\001\tE\t\025!\003G\003\021y\026g\016\021\t\017\005-\003\001\"\001\002N\0051A(\0338jiz\"B%a\024\002R\005M\023QKA,\0033\nY&!\030\002`\005\005\0241MA3\003O\nI'a\033\002n\005=\024\021\017\t\024\021\001q\021\004H\020#K!Zc&\r\0338uu\0025I\022\005\007!\006%\003\031\001\b\t\rU\013I\0051\001\032\021\031Q\026\021\na\0019!1q,!\023A\002}Aa\001ZA%\001\004\021\003BB5\002J\001\007Q\005\003\004o\003\023\002\r\001\013\005\007g\006%\003\031A\026\t\ra\fI\0051\001/\021\031i\030\021\na\001c!9\021QAA%\001\004!\004bBA\b\003\023\002\ra\016\005\b\0033\tI\0051\001;\021\035\t\031#!\023A\002uBq!!\f\002J\001\007\001\tC\004\0028\005%\003\031A\"\t\017\005\005\023\021\na\001\r\"9\021Q\017\001\005B\005]\024\001\003;p'R\024\030N\\4\025\005\005e\004\003BA>\003\013k!!! \013\t\005}\024\021Q\001\005Y\006twM\003\002\002\004\006!!.\031<b\023\021\t9)! \003\rM#(/\0338h\021%\tY\tAA\001\n\003\ti)\001\003d_BLX\003JAH\003+\013I*!(\002\"\006\025\026\021VAW\003c\013),!/\002>\006\005\027QYAe\003\033\f\t.!6\025I\005E\025q[Am\0037\fi.a8\002b\006\r\030Q]At\003S\fY/!<\002p\006E\0301_A{\003o\004B\005\003\001\002\024\006]\0251TAP\003G\0139+a+\0020\006M\026qWA^\003\013\031-a2\002L\006=\0271\033\t\004\037\005UEAB\t\002\n\n\007!\003E\002\020\0033#aaGAE\005\004\021\002cA\b\002\036\0221a$!#C\002I\0012aDAQ\t\031\t\023\021\022b\001%A\031q\"!*\005\r\021\nII1\001\023!\ry\021\021\026\003\007O\005%%\031\001\n\021\007=\ti\013\002\004+\003\023\023\rA\005\t\004\037\005EFAB\027\002\n\n\007!\003E\002\020\003k#a\001MAE\005\004\021\002cA\b\002:\02211'!#C\002I\0012aDA_\t\0311\024\021\022b\001%A\031q\"!1\005\re\nII1\001\023!\ry\021Q\031\003\007y\005%%\031\001\n\021\007=\tI\r\002\004@\003\023\023\rA\005\t\004\037\0055GA\002\"\002\n\n\007!\003E\002\020\003#$a!RAE\005\004\021\002cA\b\002V\0221\001*!#C\002IA\021\002UAE!\003\005\r!a%\t\023U\013I\t%AA\002\005]\005\"\003.\002\nB\005\t\031AAN\021%y\026\021\022I\001\002\004\ty\nC\005e\003\023\003\n\0211\001\002$\"I\021.!#\021\002\003\007\021q\025\005\n]\006%\005\023!a\001\003WC\021b]AE!\003\005\r!a,\t\023a\fI\t%AA\002\005M\006\"C?\002\nB\005\t\031AA\\\021)\t)!!#\021\002\003\007\0211\030\005\013\003\037\tI\t%AA\002\005}\006BCA\r\003\023\003\n\0211\001\002D\"Q\0211EAE!\003\005\r!a2\t\025\0055\022\021\022I\001\002\004\tY\r\003\006\0028\005%\005\023!a\001\003\037D!\"!\021\002\nB\005\t\031AAj\021%\tY\020AI\001\n\003\ti0\001\bd_BLH\005Z3gCVdG\017J\031\026I\005}(Q\003B\f\0053\021YB!\b\003 \t\005\"1\005B\023\005O\021ICa\013\003.\t=\"\021\007B\032\005k)\"A!\001+\0079\021\031a\013\002\003\006A!!q\001B\t\033\t\021IA\003\003\003\f\t5\021!C;oG\",7m[3e\025\r\021yAA\001\013C:tw\016^1uS>t\027\002\002B\n\005\023\021\021#\0368dQ\026\0347.\0323WCJL\027M\\2f\t\031\t\022\021 b\001%\02111$!?C\002I!aAHA}\005\004\021BAB\021\002z\n\007!\003\002\004%\003s\024\rA\005\003\007O\005e(\031\001\n\005\r)\nIP1\001\023\t\031i\023\021 b\001%\0211\001'!?C\002I!aaMA}\005\004\021BA\002\034\002z\n\007!\003\002\004:\003s\024\rA\005\003\007y\005e(\031\001\n\005\r}\nIP1\001\023\t\031\021\025\021 b\001%\0211Q)!?C\002I!a\001SA}\005\004\021\002\"\003B\035\001E\005I\021\001B\036\0039\031w\016]=%I\0264\027-\0367uII*BE!\020\003B\t\r#Q\tB$\005\023\022YE!\024\003P\tE#1\013B+\005/\022IFa\027\003^\t}#\021M\013\003\005Q3!\007B\002\t\031\t\"q\007b\001%\02111Da\016C\002I!aA\bB\034\005\004\021BAB\021\0038\t\007!\003\002\004%\005o\021\rA\005\003\007O\t]\"\031\001\n\005\r)\0229D1\001\023\t\031i#q\007b\001%\0211\001Ga\016C\002I!aa\rB\034\005\004\021BA\002\034\0038\t\007!\003\002\004:\005o\021\rA\005\003\007y\t]\"\031\001\n\005\r}\0229D1\001\023\t\031\021%q\007b\001%\0211QIa\016C\002I!a\001\023B\034\005\004\021\002\"\003B3\001E\005I\021\001B4\0039\031w\016]=%I\0264\027-\0367uIM*BE!\033\003n\t=$\021\017B:\005k\0229H!\037\003|\tu$q\020BA\005\007\023)Ia\"\003\n\n-%QR\013\003\005WR3\001\bB\002\t\031\t\"1\rb\001%\02111Da\031C\002I!aA\bB2\005\004\021BAB\021\003d\t\007!\003\002\004%\005G\022\rA\005\003\007O\t\r$\031\001\n\005\r)\022\031G1\001\023\t\031i#1\rb\001%\0211\001Ga\031C\002I!aa\rB2\005\004\021BA\002\034\003d\t\007!\003\002\004:\005G\022\rA\005\003\007y\t\r$\031\001\n\005\r}\022\031G1\001\023\t\031\021%1\rb\001%\0211QIa\031C\002I!a\001\023B2\005\004\021\002\"\003BI\001E\005I\021\001BJ\0039\031w\016]=%I\0264\027-\0367uIQ*BE!&\003\032\nm%Q\024BP\005C\023\031K!*\003(\n%&1\026BW\005_\023\tLa-\0036\n]&\021X\013\003\005/S3a\bB\002\t\031\t\"q\022b\001%\02111Da$C\002I!aA\bBH\005\004\021BAB\021\003\020\n\007!\003\002\004%\005\037\023\rA\005\003\007O\t=%\031\001\n\005\r)\022yI1\001\023\t\031i#q\022b\001%\0211\001Ga$C\002I!aa\rBH\005\004\021BA\002\034\003\020\n\007!\003\002\004:\005\037\023\rA\005\003\007y\t=%\031\001\n\005\r}\022yI1\001\023\t\031\021%q\022b\001%\0211QIa$C\002I!a\001\023BH\005\004\021\002\"\003B_\001E\005I\021\001B`\0039\031w\016]=%I\0264\027-\0367uIU*BE!1\003F\n\035'\021\032Bf\005\033\024yM!5\003T\nU'q\033Bm\0057\024iNa8\003b\n\r(Q]\013\003\005\007T3A\tB\002\t\031\t\"1\030b\001%\02111Da/C\002I!aA\bB^\005\004\021BAB\021\003<\n\007!\003\002\004%\005w\023\rA\005\003\007O\tm&\031\001\n\005\r)\022YL1\001\023\t\031i#1\030b\001%\0211\001Ga/C\002I!aa\rB^\005\004\021BA\002\034\003<\n\007!\003\002\004:\005w\023\rA\005\003\007y\tm&\031\001\n\005\r}\022YL1\001\023\t\031\021%1\030b\001%\0211QIa/C\002I!a\001\023B^\005\004\021\002\"\003Bu\001E\005I\021\001Bv\0039\031w\016]=%I\0264\027-\0367uIY*BE!<\003r\nM(Q\037B|\005s\024YP!@\003\000\016\00511AB\003\007\017\031Iaa\003\004\016\r=1\021C\013\003\005_T3!\nB\002\t\031\t\"q\035b\001%\02111Da:C\002I!aA\bBt\005\004\021BAB\021\003h\n\007!\003\002\004%\005O\024\rA\005\003\007O\t\035(\031\001\n\005\r)\0229O1\001\023\t\031i#q\035b\001%\0211\001Ga:C\002I!aa\rBt\005\004\021BA\002\034\003h\n\007!\003\002\004:\005O\024\rA\005\003\007y\t\035(\031\001\n\005\r}\0229O1\001\023\t\031\021%q\035b\001%\0211QIa:C\002I!a\001\023Bt\005\004\021\002\"CB\013\001E\005I\021AB\f\0039\031w\016]=%I\0264\027-\0367uI]*Be!\007\004\036\r}1\021EB\022\007K\0319c!\013\004,\r52qFB\031\007g\031)da\016\004:\rm2QH\013\003\0077Q3\001\013B\002\t\031\t21\003b\001%\02111da\005C\002I!aAHB\n\005\004\021BAB\021\004\024\t\007!\003\002\004%\007'\021\rA\005\003\007O\rM!\031\001\n\005\r)\032\031B1\001\023\t\031i31\003b\001%\0211\001ga\005C\002I!aaMB\n\005\004\021BA\002\034\004\024\t\007!\003\002\004:\007'\021\rA\005\003\007y\rM!\031\001\n\005\r}\032\031B1\001\023\t\031\02151\003b\001%\0211Qia\005C\002I!a\001SB\n\005\004\021\002\"CB!\001E\005I\021AB\"\0039\031w\016]=%I\0264\027-\0367uIa*Be!\022\004J\r-3QJB(\007#\032\031f!\026\004X\re31LB/\007?\032\tga\031\004f\r\0354\021N\013\003\007\017R3a\013B\002\t\031\t2q\bb\001%\02111da\020C\002I!aAHB \005\004\021BAB\021\004@\t\007!\003\002\004%\007\021\rA\005\003\007O\r}\"\031\001\n\005\r)\032yD1\001\023\t\031i3q\bb\001%\0211\001ga\020C\002I!aaMB \005\004\021BA\002\034\004@\t\007!\003\002\004:\007\021\rA\005\003\007y\r}\"\031\001\n\005\r}\032yD1\001\023\t\031\0215q\bb\001%\0211Qia\020C\002I!a\001SB \005\004\021\002\"CB7\001E\005I\021AB8\0039\031w\016]=%I\0264\027-\0367uIe*Be!\035\004v\r]4\021PB>\007{\032yh!!\004\004\016\0255qQBE\007\027\033iia$\004\022\016M5QS\013\003\007gR3A\fB\002\t\031\t21\016b\001%\02111da\033C\002I!aAHB6\005\004\021BAB\021\004l\t\007!\003\002\004%\007W\022\rA\005\003\007O\r-$\031\001\n\005\r)\032YG1\001\023\t\031i31\016b\001%\0211\001ga\033C\002I!aaMB6\005\004\021BA\002\034\004l\t\007!\003\002\004:\007W\022\rA\005\003\007y\r-$\031\001\n\005\r}\032YG1\001\023\t\031\02151\016b\001%\0211Qia\033C\002I!a\001SB6\005\004\021\002\"CBM\001E\005I\021ABN\003=\031w\016]=%I\0264\027-\0367uIE\002T\003JBO\007C\033\031k!*\004(\016%61VBW\007_\033\tla-\0046\016]6\021XB^\007{\033yl!1\026\005\r}%fA\031\003\004\0211\021ca&C\002I!aaGBL\005\004\021BA\002\020\004\030\n\007!\003\002\004\"\007/\023\rA\005\003\007I\r]%\031\001\n\005\r\035\0329J1\001\023\t\031Q3q\023b\001%\0211Qfa&C\002I!a\001MBL\005\004\021BAB\032\004\030\n\007!\003\002\0047\007/\023\rA\005\003\007s\r]%\031\001\n\005\rq\0329J1\001\023\t\031y4q\023b\001%\0211!ia&C\002I!a!RBL\005\004\021BA\002%\004\030\n\007!\003C\005\004F\002\t\n\021\"\001\004H\006y1m\0349zI\021,g-Y;mi\022\n\024'\006\023\004J\01657qZBi\007'\034)na6\004Z\016m7Q\\Bp\007C\034\031o!:\004h\016%81^Bw+\t\031YMK\0025\005\007!a!EBb\005\004\021BAB\016\004D\n\007!\003\002\004\037\007\007\024\rA\005\003\007C\r\r'\031\001\n\005\r\021\032\031M1\001\023\t\031931\031b\001%\0211!fa1C\002I!a!LBb\005\004\021BA\002\031\004D\n\007!\003\002\0044\007\007\024\rA\005\003\007m\r\r'\031\001\n\005\re\032\031M1\001\023\t\031a41\031b\001%\0211qha1C\002I!aAQBb\005\004\021BAB#\004D\n\007!\003\002\004I\007\007\024\rA\005\005\n\007c\004\021\023!C\001\007g\fqbY8qs\022\"WMZ1vYR$\023GM\013%\007k\034Ipa?\004~\016}H\021\001C\002\t\013!9\001\"\003\005\f\0215Aq\002C\t\t'!)\002b\006\005\032U\0211q\037\026\004o\t\rAAB\t\004p\n\007!\003\002\004\034\007_\024\rA\005\003\007=\r=(\031\001\n\005\r\005\032yO1\001\023\t\031!3q\036b\001%\0211qea<C\002I!aAKBx\005\004\021BAB\027\004p\n\007!\003\002\0041\007_\024\rA\005\003\007g\r=(\031\001\n\005\rY\032yO1\001\023\t\031I4q\036b\001%\0211Aha<C\002I!aaPBx\005\004\021BA\002\"\004p\n\007!\003\002\004F\007_\024\rA\005\003\007\021\016=(\031\001\n\t\023\021u\001!%A\005\002\021}\021aD2paf$C-\0324bk2$H%M\032\026I\021\005BQ\005C\024\tS!Y\003\"\f\0050\021EB1\007C\033\to!I\004b\017\005>\021}B\021\tC\"\t\013*\"\001b\t+\007i\022\031\001\002\004\022\t7\021\rA\005\003\0077\021m!\031\001\n\005\ry!YB1\001\023\t\031\tC1\004b\001%\0211A\005b\007C\002I!aa\nC\016\005\004\021BA\002\026\005\034\t\007!\003\002\004.\t7\021\rA\005\003\007a\021m!\031\001\n\005\rM\"YB1\001\023\t\0311D1\004b\001%\0211\021\bb\007C\002I!a\001\020C\016\005\004\021BAB \005\034\t\007!\003\002\004C\t7\021\rA\005\003\007\013\022m!\031\001\n\005\r!#YB1\001\023\021%!I\005AI\001\n\003!Y%A\bd_BLH\005Z3gCVdG\017J\0315+\021\"i\005\"\025\005T\021UCq\013C-\t7\"i\006b\030\005b\021\rDQ\rC4\tS\"Y\007\"\034\005p\021ETC\001C(U\ri$1\001\003\007#\021\035#\031\001\n\005\rm!9E1\001\023\t\031qBq\tb\001%\0211\021\005b\022C\002I!a\001\nC$\005\004\021BAB\024\005H\t\007!\003\002\004+\t\017\022\rA\005\003\007[\021\035#\031\001\n\005\rA\"9E1\001\023\t\031\031Dq\tb\001%\0211a\007b\022C\002I!a!\017C$\005\004\021BA\002\037\005H\t\007!\003\002\004@\t\017\022\rA\005\003\007\005\022\035#\031\001\n\005\r\025#9E1\001\023\t\031AEq\tb\001%!IAQ\017\001\022\002\023\005AqO\001\020G>\004\030\020\n3fM\006,H\016\036\0232kU!C\021\020C?\t\"\t\tb!\005\006\022\035E\021\022CF\t\033#y\t\"%\005\024\022UEq\023CM\t7#i*\006\002\005|)\032\001Ia\001\005\rE!\031H1\001\023\t\031YB1\017b\001%\0211a\004b\035C\002I!a!\tC:\005\004\021BA\002\023\005t\t\007!\003\002\004(\tg\022\rA\005\003\007U\021M$\031\001\n\005\r5\"\031H1\001\023\t\031\001D1\017b\001%\02111\007b\035C\002I!aA\016C:\005\004\021BAB\035\005t\t\007!\003\002\004=\tg\022\rA\005\003\007\021M$\031\001\n\005\r\t#\031H1\001\023\t\031)E1\017b\001%\0211\001\nb\035C\002IA\021\002\")\001#\003%\t\001b)\002\037\r|\007/\037\023eK\032\fW\017\034;%cY*B\005\"*\005*\022-FQ\026CX\tc#\031\f\".\0058\022eF1\030C_\t#\t\rb1\005F\022\035G\021Z\013\003\tOS3a\021B\002\t\031\tBq\024b\001%\02111\004b(C\002I!aA\bCP\005\004\021BAB\021\005 \n\007!\003\002\004%\t?\023\rA\005\003\007O\021}%\031\001\n\005\r)\"yJ1\001\023\t\031iCq\024b\001%\0211\001\007b(C\002I!aa\rCP\005\004\021BA\002\034\005 \n\007!\003\002\004:\t?\023\rA\005\003\007y\021}%\031\001\n\005\r}\"yJ1\001\023\t\031\021Eq\024b\001%\0211Q\tb(C\002I!a\001\023CP\005\004\021\002\"\003Cg\001E\005I\021\001Ch\003=\031w\016]=%I\0264\027-\0367uIE:T\003\nCi\t+$9\016\"7\005\\\022uGq\034Cq\tG$)\017b:\005j\022-HQ\036Cx\tc$\031\020\">\026\005\021M'f\001$\003\004\0211\021\003b3C\002I!aa\007Cf\005\004\021BA\002\020\005L\n\007!\003\002\004\"\t\027\024\rA\005\003\007I\021-'\031\001\n\005\r\035\"YM1\001\023\t\031QC1\032b\001%\0211Q\006b3C\002I!a\001\rCf\005\004\021BAB\032\005L\n\007!\003\002\0047\t\027\024\rA\005\003\007s\021-'\031\001\n\005\rq\"YM1\001\023\t\031yD1\032b\001%\0211!\tb3C\002I!a!\022Cf\005\004\021BA\002%\005L\n\007!\003C\005\005z\002\t\t\021\"\021\005|\006i\001O]8ek\016$\bK]3gSb,\"!!\037\t\023\021}\b!!A\005B\025\005\021a\0049s_\022,8\r^%uKJ\fGo\034:\026\005\025\r\001#BC\003\013\0271RBAC\004\025\r)IAA\001\013G>dG.Z2uS>t\027\002BC\007\013\017\021\001\"\023;fe\006$xN\035\005\n\013#\001\021\021!C\001\013'\t\001bY1o\013F,\030\r\034\013\005\013+)Y\002E\002\t\013/I1!\"\007\003\005\035\021un\0347fC:D\021\"\"\b\006\020\005\005\t\031\001\f\002\007a$\023\007C\005\006\"\001\t\t\021\"\021\006$\005A\001.Y:i\007>$W\r\006\002\006&A\031\001\"b\n\n\007\025%\"AA\002J]RD\021\"\"\f\001\003\003%\t%b\f\002\r\025\fX/\0317t)\021))\"\"\r\t\023\025uQ1FA\001\002\0041r!CC\033\005\005\005\t\022AC\034\003\035!V\017\0357fc]\0022\001CC\035\r!\t!!!A\t\002\025m2\003BC\035\0171C\001\"a\023\006:\021\005Qq\b\013\003\013oA!\"!\036\006:\005\005IQIA<\021)))%\"\017\002\002\023\005UqI\001\006CB\004H._\013%\013\023*y%b\025\006X\025mSqLC2\013O*Y'b\034\006t\025]T1PC@\013\007+9)b#\006\020R!S1JCI\013'+)*b&\006\032\026mUQTCP\013C+\031+\"*\006(\026%V1VCW\013_+\t\f\005\023\t\001\0255S\021KC+\0133*i&\"\031\006f\025%TQNC9\013k*I(\" \006\002\026\025U\021RCG!\ryQq\n\003\007#\025\r#\031\001\n\021\007=)\031\006\002\004\034\013\007\022\rA\005\t\004\037\025]CA\002\020\006D\t\007!\003E\002\020\0137\"a!IC\"\005\004\021\002cA\b\006`\0211A%b\021C\002I\0012aDC2\t\0319S1\tb\001%A\031q\"b\032\005\r)*\031E1\001\023!\ryQ1\016\003\007[\025\r#\031\001\n\021\007=)y\007\002\0041\013\007\022\rA\005\t\004\037\025MDAB\032\006D\t\007!\003E\002\020\013o\"aANC\"\005\004\021\002cA\b\006|\0211\021(b\021C\002I\0012aDC@\t\031aT1\tb\001%A\031q\"b!\005\r}*\031E1\001\023!\ryQq\021\003\007\005\026\r#\031\001\n\021\007=)Y\t\002\004F\013\007\022\rA\005\t\004\037\025=EA\002%\006D\t\007!\003C\004Q\013\007\002\r!\"\024\t\017U+\031\0051\001\006R!9!,b\021A\002\025U\003bB0\006D\001\007Q\021\f\005\bI\026\r\003\031AC/\021\035IW1\ta\001\013CBqA\\C\"\001\004))\007C\004t\013\007\002\r!\"\033\t\017a,\031\0051\001\006n!9Q0b\021A\002\025E\004\002CA\003\013\007\002\r!\"\036\t\021\005=Q1\ta\001\013sB\001\"!\007\006D\001\007QQ\020\005\t\003G)\031\0051\001\006\002\"A\021QFC\"\001\004))\t\003\005\0028\025\r\003\031ACE\021!\t\t%b\021A\002\0255\005BCC[\013s\t\t\021\"!\0068\0069QO\\1qa2LX\003JC]\013\013,I-\"4\006R\026UW\021\\Co\013C,)/\";\006n\026EXQ_C}\013{4\tA\"\002\025\t\025mfq\001\t\006\021\025uV\021Y\005\004\013\023!AB(qi&|g\016\005\023\t\001\025\rWqYCf\013\037,\031.b6\006\\\026}W1]Ct\013W,y/b=\006x\026mXq D\002!\ryQQ\031\003\007#\025M&\031\001\n\021\007=)I\r\002\004\034\013g\023\rA\005\t\004\037\0255GA\002\020\0064\n\007!\003E\002\020\013#$a!ICZ\005\004\021\002cA\b\006V\0221A%b-C\002I\0012aDCm\t\0319S1\027b\001%A\031q\"\"8\005\r)*\031L1\001\023!\ryQ\021\035\003\007[\025M&\031\001\n\021\007=))\017\002\0041\013g\023\rA\005\t\004\037\025%HAB\032\0064\n\007!\003E\002\020\013[$aANCZ\005\004\021\002cA\b\006r\0221\021(b-C\002I\0012aDC{\t\031aT1\027b\001%A\031q\"\"?\005\r}*\031L1\001\023!\ryQQ \003\007\005\026M&\031\001\n\021\007=1\t\001\002\004F\013g\023\rA\005\t\004\037\031\025AA\002%\0064\n\007!\003\003\006\007\n\025M\026\021!a\001\013\003\f1\001\037\0231\021)1i!\"\017\002\002\023%aqB\001\fe\026\fGMU3t_24X\r\006\002\007\022A!\0211\020D\n\023\0211)\"! \003\r=\023'.Z2u\001")
/*    */ public class Tuple17<T1, T2, T3, T4, T5, T6, T7, T8, T9, T10, T11, T12, T13, T14, T15, T16, T17> implements Product17<T1, T2, T3, T4, T5, T6, T7, T8, T9, T10, T11, T12, T13, T14, T15, T16, T17>, Product, Serializable {
/*    */   private final T1 _1;
/*    */   
/*    */   private final T2 _2;
/*    */   
/*    */   private final T3 _3;
/*    */   
/*    */   private final T4 _4;
/*    */   
/*    */   private final T5 _5;
/*    */   
/*    */   private final T6 _6;
/*    */   
/*    */   private final T7 _7;
/*    */   
/*    */   private final T8 _8;
/*    */   
/*    */   private final T9 _9;
/*    */   
/*    */   private final T10 _10;
/*    */   
/*    */   private final T11 _11;
/*    */   
/*    */   private final T12 _12;
/*    */   
/*    */   private final T13 _13;
/*    */   
/*    */   private final T14 _14;
/*    */   
/*    */   private final T15 _15;
/*    */   
/*    */   private final T16 _16;
/*    */   
/*    */   private final T17 _17;
/*    */   
/*    */   public int productArity() {
/* 34 */     return Product17$class.productArity(this);
/*    */   }
/*    */   
/*    */   public Object productElement(int n) throws IndexOutOfBoundsException {
/* 34 */     return Product17$class.productElement(this, n);
/*    */   }
/*    */   
/*    */   public T1 _1() {
/* 34 */     return this._1;
/*    */   }
/*    */   
/*    */   public T2 _2() {
/* 34 */     return this._2;
/*    */   }
/*    */   
/*    */   public T3 _3() {
/* 34 */     return this._3;
/*    */   }
/*    */   
/*    */   public T4 _4() {
/* 34 */     return this._4;
/*    */   }
/*    */   
/*    */   public T5 _5() {
/* 34 */     return this._5;
/*    */   }
/*    */   
/*    */   public T6 _6() {
/* 34 */     return this._6;
/*    */   }
/*    */   
/*    */   public T7 _7() {
/* 34 */     return this._7;
/*    */   }
/*    */   
/*    */   public T8 _8() {
/* 34 */     return this._8;
/*    */   }
/*    */   
/*    */   public T9 _9() {
/* 34 */     return this._9;
/*    */   }
/*    */   
/*    */   public T10 _10() {
/* 34 */     return this._10;
/*    */   }
/*    */   
/*    */   public T11 _11() {
/* 34 */     return this._11;
/*    */   }
/*    */   
/*    */   public T12 _12() {
/* 34 */     return this._12;
/*    */   }
/*    */   
/*    */   public T13 _13() {
/* 34 */     return this._13;
/*    */   }
/*    */   
/*    */   public T14 _14() {
/* 34 */     return this._14;
/*    */   }
/*    */   
/*    */   public T15 _15() {
/* 34 */     return this._15;
/*    */   }
/*    */   
/*    */   public T16 _16() {
/* 34 */     return this._16;
/*    */   }
/*    */   
/*    */   public T17 _17() {
/* 34 */     return this._17;
/*    */   }
/*    */   
/*    */   public <T1, T2, T3, T4, T5, T6, T7, T8, T9, T10, T11, T12, T13, T14, T15, T16, T17> Tuple17<T1, T2, T3, T4, T5, T6, T7, T8, T9, T10, T11, T12, T13, T14, T15, T16, T17> copy(Object _1, Object _2, Object _3, Object _4, Object _5, Object _6, Object _7, Object _8, Object _9, Object _10, Object _11, Object _12, Object _13, Object _14, Object _15, Object _16, Object _17) {
/* 34 */     return new Tuple17((T1)_1, (T2)_2, (T3)_3, (T4)_4, (T5)_5, (T6)_6, (T7)_7, (T8)_8, (T9)_9, (T10)_10, (T11)_11, (T12)_12, (T13)_13, (T14)_14, (T15)_15, (T16)_16, (T17)_17);
/*    */   }
/*    */   
/*    */   public <T1, T2, T3, T4, T5, T6, T7, T8, T9, T10, T11, T12, T13, T14, T15, T16, T17> T1 copy$default$1() {
/* 34 */     return _1();
/*    */   }
/*    */   
/*    */   public <T1, T2, T3, T4, T5, T6, T7, T8, T9, T10, T11, T12, T13, T14, T15, T16, T17> T2 copy$default$2() {
/* 34 */     return _2();
/*    */   }
/*    */   
/*    */   public <T1, T2, T3, T4, T5, T6, T7, T8, T9, T10, T11, T12, T13, T14, T15, T16, T17> T3 copy$default$3() {
/* 34 */     return _3();
/*    */   }
/*    */   
/*    */   public <T1, T2, T3, T4, T5, T6, T7, T8, T9, T10, T11, T12, T13, T14, T15, T16, T17> T4 copy$default$4() {
/* 34 */     return _4();
/*    */   }
/*    */   
/*    */   public <T1, T2, T3, T4, T5, T6, T7, T8, T9, T10, T11, T12, T13, T14, T15, T16, T17> T5 copy$default$5() {
/* 34 */     return _5();
/*    */   }
/*    */   
/*    */   public <T1, T2, T3, T4, T5, T6, T7, T8, T9, T10, T11, T12, T13, T14, T15, T16, T17> T6 copy$default$6() {
/* 34 */     return _6();
/*    */   }
/*    */   
/*    */   public <T1, T2, T3, T4, T5, T6, T7, T8, T9, T10, T11, T12, T13, T14, T15, T16, T17> T7 copy$default$7() {
/* 34 */     return _7();
/*    */   }
/*    */   
/*    */   public <T1, T2, T3, T4, T5, T6, T7, T8, T9, T10, T11, T12, T13, T14, T15, T16, T17> T8 copy$default$8() {
/* 34 */     return _8();
/*    */   }
/*    */   
/*    */   public <T1, T2, T3, T4, T5, T6, T7, T8, T9, T10, T11, T12, T13, T14, T15, T16, T17> T9 copy$default$9() {
/* 34 */     return _9();
/*    */   }
/*    */   
/*    */   public <T1, T2, T3, T4, T5, T6, T7, T8, T9, T10, T11, T12, T13, T14, T15, T16, T17> T10 copy$default$10() {
/* 34 */     return _10();
/*    */   }
/*    */   
/*    */   public <T1, T2, T3, T4, T5, T6, T7, T8, T9, T10, T11, T12, T13, T14, T15, T16, T17> T11 copy$default$11() {
/* 34 */     return _11();
/*    */   }
/*    */   
/*    */   public <T1, T2, T3, T4, T5, T6, T7, T8, T9, T10, T11, T12, T13, T14, T15, T16, T17> T12 copy$default$12() {
/* 34 */     return _12();
/*    */   }
/*    */   
/*    */   public <T1, T2, T3, T4, T5, T6, T7, T8, T9, T10, T11, T12, T13, T14, T15, T16, T17> T13 copy$default$13() {
/* 34 */     return _13();
/*    */   }
/*    */   
/*    */   public <T1, T2, T3, T4, T5, T6, T7, T8, T9, T10, T11, T12, T13, T14, T15, T16, T17> T14 copy$default$14() {
/* 34 */     return _14();
/*    */   }
/*    */   
/*    */   public <T1, T2, T3, T4, T5, T6, T7, T8, T9, T10, T11, T12, T13, T14, T15, T16, T17> T15 copy$default$15() {
/* 34 */     return _15();
/*    */   }
/*    */   
/*    */   public <T1, T2, T3, T4, T5, T6, T7, T8, T9, T10, T11, T12, T13, T14, T15, T16, T17> T16 copy$default$16() {
/* 34 */     return _16();
/*    */   }
/*    */   
/*    */   public <T1, T2, T3, T4, T5, T6, T7, T8, T9, T10, T11, T12, T13, T14, T15, T16, T17> T17 copy$default$17() {
/* 34 */     return _17();
/*    */   }
/*    */   
/*    */   public String productPrefix() {
/* 34 */     return "Tuple17";
/*    */   }
/*    */   
/*    */   public Iterator<Object> productIterator() {
/* 34 */     return ScalaRunTime$.MODULE$.typedProductIterator(this);
/*    */   }
/*    */   
/*    */   public boolean canEqual(Object x$1) {
/* 34 */     return x$1 instanceof Tuple17;
/*    */   }
/*    */   
/*    */   public int hashCode() {
/* 34 */     return ScalaRunTime$.MODULE$._hashCode(this);
/*    */   }
/*    */   
/*    */   public boolean equals(Object x$1) {
/*    */     // Byte code:
/*    */     //   0: aload_0
/*    */     //   1: aload_1
/*    */     //   2: if_acmpeq -> 1467
/*    */     //   5: aload_1
/*    */     //   6: instanceof scala/Tuple17
/*    */     //   9: ifeq -> 17
/*    */     //   12: iconst_1
/*    */     //   13: istore_2
/*    */     //   14: goto -> 19
/*    */     //   17: iconst_0
/*    */     //   18: istore_2
/*    */     //   19: iload_2
/*    */     //   20: ifeq -> 1471
/*    */     //   23: aload_1
/*    */     //   24: checkcast scala/Tuple17
/*    */     //   27: astore #37
/*    */     //   29: aload_0
/*    */     //   30: invokevirtual _1 : ()Ljava/lang/Object;
/*    */     //   33: aload #37
/*    */     //   35: invokevirtual _1 : ()Ljava/lang/Object;
/*    */     //   38: astore #4
/*    */     //   40: dup
/*    */     //   41: astore_3
/*    */     //   42: aload #4
/*    */     //   44: if_acmpne -> 51
/*    */     //   47: iconst_1
/*    */     //   48: goto -> 103
/*    */     //   51: aload_3
/*    */     //   52: ifnonnull -> 59
/*    */     //   55: iconst_0
/*    */     //   56: goto -> 103
/*    */     //   59: aload_3
/*    */     //   60: instanceof java/lang/Number
/*    */     //   63: ifeq -> 78
/*    */     //   66: aload_3
/*    */     //   67: checkcast java/lang/Number
/*    */     //   70: aload #4
/*    */     //   72: invokestatic equalsNumObject : (Ljava/lang/Number;Ljava/lang/Object;)Z
/*    */     //   75: goto -> 103
/*    */     //   78: aload_3
/*    */     //   79: instanceof java/lang/Character
/*    */     //   82: ifeq -> 97
/*    */     //   85: aload_3
/*    */     //   86: checkcast java/lang/Character
/*    */     //   89: aload #4
/*    */     //   91: invokestatic equalsCharObject : (Ljava/lang/Character;Ljava/lang/Object;)Z
/*    */     //   94: goto -> 103
/*    */     //   97: aload_3
/*    */     //   98: aload #4
/*    */     //   100: invokevirtual equals : (Ljava/lang/Object;)Z
/*    */     //   103: ifeq -> 1463
/*    */     //   106: aload_0
/*    */     //   107: invokevirtual _2 : ()Ljava/lang/Object;
/*    */     //   110: aload #37
/*    */     //   112: invokevirtual _2 : ()Ljava/lang/Object;
/*    */     //   115: astore #6
/*    */     //   117: dup
/*    */     //   118: astore #5
/*    */     //   120: aload #6
/*    */     //   122: if_acmpne -> 129
/*    */     //   125: iconst_1
/*    */     //   126: goto -> 187
/*    */     //   129: aload #5
/*    */     //   131: ifnonnull -> 138
/*    */     //   134: iconst_0
/*    */     //   135: goto -> 187
/*    */     //   138: aload #5
/*    */     //   140: instanceof java/lang/Number
/*    */     //   143: ifeq -> 159
/*    */     //   146: aload #5
/*    */     //   148: checkcast java/lang/Number
/*    */     //   151: aload #6
/*    */     //   153: invokestatic equalsNumObject : (Ljava/lang/Number;Ljava/lang/Object;)Z
/*    */     //   156: goto -> 187
/*    */     //   159: aload #5
/*    */     //   161: instanceof java/lang/Character
/*    */     //   164: ifeq -> 180
/*    */     //   167: aload #5
/*    */     //   169: checkcast java/lang/Character
/*    */     //   172: aload #6
/*    */     //   174: invokestatic equalsCharObject : (Ljava/lang/Character;Ljava/lang/Object;)Z
/*    */     //   177: goto -> 187
/*    */     //   180: aload #5
/*    */     //   182: aload #6
/*    */     //   184: invokevirtual equals : (Ljava/lang/Object;)Z
/*    */     //   187: ifeq -> 1463
/*    */     //   190: aload_0
/*    */     //   191: invokevirtual _3 : ()Ljava/lang/Object;
/*    */     //   194: aload #37
/*    */     //   196: invokevirtual _3 : ()Ljava/lang/Object;
/*    */     //   199: astore #8
/*    */     //   201: dup
/*    */     //   202: astore #7
/*    */     //   204: aload #8
/*    */     //   206: if_acmpne -> 213
/*    */     //   209: iconst_1
/*    */     //   210: goto -> 271
/*    */     //   213: aload #7
/*    */     //   215: ifnonnull -> 222
/*    */     //   218: iconst_0
/*    */     //   219: goto -> 271
/*    */     //   222: aload #7
/*    */     //   224: instanceof java/lang/Number
/*    */     //   227: ifeq -> 243
/*    */     //   230: aload #7
/*    */     //   232: checkcast java/lang/Number
/*    */     //   235: aload #8
/*    */     //   237: invokestatic equalsNumObject : (Ljava/lang/Number;Ljava/lang/Object;)Z
/*    */     //   240: goto -> 271
/*    */     //   243: aload #7
/*    */     //   245: instanceof java/lang/Character
/*    */     //   248: ifeq -> 264
/*    */     //   251: aload #7
/*    */     //   253: checkcast java/lang/Character
/*    */     //   256: aload #8
/*    */     //   258: invokestatic equalsCharObject : (Ljava/lang/Character;Ljava/lang/Object;)Z
/*    */     //   261: goto -> 271
/*    */     //   264: aload #7
/*    */     //   266: aload #8
/*    */     //   268: invokevirtual equals : (Ljava/lang/Object;)Z
/*    */     //   271: ifeq -> 1463
/*    */     //   274: aload_0
/*    */     //   275: invokevirtual _4 : ()Ljava/lang/Object;
/*    */     //   278: aload #37
/*    */     //   280: invokevirtual _4 : ()Ljava/lang/Object;
/*    */     //   283: astore #10
/*    */     //   285: dup
/*    */     //   286: astore #9
/*    */     //   288: aload #10
/*    */     //   290: if_acmpne -> 297
/*    */     //   293: iconst_1
/*    */     //   294: goto -> 355
/*    */     //   297: aload #9
/*    */     //   299: ifnonnull -> 306
/*    */     //   302: iconst_0
/*    */     //   303: goto -> 355
/*    */     //   306: aload #9
/*    */     //   308: instanceof java/lang/Number
/*    */     //   311: ifeq -> 327
/*    */     //   314: aload #9
/*    */     //   316: checkcast java/lang/Number
/*    */     //   319: aload #10
/*    */     //   321: invokestatic equalsNumObject : (Ljava/lang/Number;Ljava/lang/Object;)Z
/*    */     //   324: goto -> 355
/*    */     //   327: aload #9
/*    */     //   329: instanceof java/lang/Character
/*    */     //   332: ifeq -> 348
/*    */     //   335: aload #9
/*    */     //   337: checkcast java/lang/Character
/*    */     //   340: aload #10
/*    */     //   342: invokestatic equalsCharObject : (Ljava/lang/Character;Ljava/lang/Object;)Z
/*    */     //   345: goto -> 355
/*    */     //   348: aload #9
/*    */     //   350: aload #10
/*    */     //   352: invokevirtual equals : (Ljava/lang/Object;)Z
/*    */     //   355: ifeq -> 1463
/*    */     //   358: aload_0
/*    */     //   359: invokevirtual _5 : ()Ljava/lang/Object;
/*    */     //   362: aload #37
/*    */     //   364: invokevirtual _5 : ()Ljava/lang/Object;
/*    */     //   367: astore #12
/*    */     //   369: dup
/*    */     //   370: astore #11
/*    */     //   372: aload #12
/*    */     //   374: if_acmpne -> 381
/*    */     //   377: iconst_1
/*    */     //   378: goto -> 439
/*    */     //   381: aload #11
/*    */     //   383: ifnonnull -> 390
/*    */     //   386: iconst_0
/*    */     //   387: goto -> 439
/*    */     //   390: aload #11
/*    */     //   392: instanceof java/lang/Number
/*    */     //   395: ifeq -> 411
/*    */     //   398: aload #11
/*    */     //   400: checkcast java/lang/Number
/*    */     //   403: aload #12
/*    */     //   405: invokestatic equalsNumObject : (Ljava/lang/Number;Ljava/lang/Object;)Z
/*    */     //   408: goto -> 439
/*    */     //   411: aload #11
/*    */     //   413: instanceof java/lang/Character
/*    */     //   416: ifeq -> 432
/*    */     //   419: aload #11
/*    */     //   421: checkcast java/lang/Character
/*    */     //   424: aload #12
/*    */     //   426: invokestatic equalsCharObject : (Ljava/lang/Character;Ljava/lang/Object;)Z
/*    */     //   429: goto -> 439
/*    */     //   432: aload #11
/*    */     //   434: aload #12
/*    */     //   436: invokevirtual equals : (Ljava/lang/Object;)Z
/*    */     //   439: ifeq -> 1463
/*    */     //   442: aload_0
/*    */     //   443: invokevirtual _6 : ()Ljava/lang/Object;
/*    */     //   446: aload #37
/*    */     //   448: invokevirtual _6 : ()Ljava/lang/Object;
/*    */     //   451: astore #14
/*    */     //   453: dup
/*    */     //   454: astore #13
/*    */     //   456: aload #14
/*    */     //   458: if_acmpne -> 465
/*    */     //   461: iconst_1
/*    */     //   462: goto -> 523
/*    */     //   465: aload #13
/*    */     //   467: ifnonnull -> 474
/*    */     //   470: iconst_0
/*    */     //   471: goto -> 523
/*    */     //   474: aload #13
/*    */     //   476: instanceof java/lang/Number
/*    */     //   479: ifeq -> 495
/*    */     //   482: aload #13
/*    */     //   484: checkcast java/lang/Number
/*    */     //   487: aload #14
/*    */     //   489: invokestatic equalsNumObject : (Ljava/lang/Number;Ljava/lang/Object;)Z
/*    */     //   492: goto -> 523
/*    */     //   495: aload #13
/*    */     //   497: instanceof java/lang/Character
/*    */     //   500: ifeq -> 516
/*    */     //   503: aload #13
/*    */     //   505: checkcast java/lang/Character
/*    */     //   508: aload #14
/*    */     //   510: invokestatic equalsCharObject : (Ljava/lang/Character;Ljava/lang/Object;)Z
/*    */     //   513: goto -> 523
/*    */     //   516: aload #13
/*    */     //   518: aload #14
/*    */     //   520: invokevirtual equals : (Ljava/lang/Object;)Z
/*    */     //   523: ifeq -> 1463
/*    */     //   526: aload_0
/*    */     //   527: invokevirtual _7 : ()Ljava/lang/Object;
/*    */     //   530: aload #37
/*    */     //   532: invokevirtual _7 : ()Ljava/lang/Object;
/*    */     //   535: astore #16
/*    */     //   537: dup
/*    */     //   538: astore #15
/*    */     //   540: aload #16
/*    */     //   542: if_acmpne -> 549
/*    */     //   545: iconst_1
/*    */     //   546: goto -> 607
/*    */     //   549: aload #15
/*    */     //   551: ifnonnull -> 558
/*    */     //   554: iconst_0
/*    */     //   555: goto -> 607
/*    */     //   558: aload #15
/*    */     //   560: instanceof java/lang/Number
/*    */     //   563: ifeq -> 579
/*    */     //   566: aload #15
/*    */     //   568: checkcast java/lang/Number
/*    */     //   571: aload #16
/*    */     //   573: invokestatic equalsNumObject : (Ljava/lang/Number;Ljava/lang/Object;)Z
/*    */     //   576: goto -> 607
/*    */     //   579: aload #15
/*    */     //   581: instanceof java/lang/Character
/*    */     //   584: ifeq -> 600
/*    */     //   587: aload #15
/*    */     //   589: checkcast java/lang/Character
/*    */     //   592: aload #16
/*    */     //   594: invokestatic equalsCharObject : (Ljava/lang/Character;Ljava/lang/Object;)Z
/*    */     //   597: goto -> 607
/*    */     //   600: aload #15
/*    */     //   602: aload #16
/*    */     //   604: invokevirtual equals : (Ljava/lang/Object;)Z
/*    */     //   607: ifeq -> 1463
/*    */     //   610: aload_0
/*    */     //   611: invokevirtual _8 : ()Ljava/lang/Object;
/*    */     //   614: aload #37
/*    */     //   616: invokevirtual _8 : ()Ljava/lang/Object;
/*    */     //   619: astore #18
/*    */     //   621: dup
/*    */     //   622: astore #17
/*    */     //   624: aload #18
/*    */     //   626: if_acmpne -> 633
/*    */     //   629: iconst_1
/*    */     //   630: goto -> 691
/*    */     //   633: aload #17
/*    */     //   635: ifnonnull -> 642
/*    */     //   638: iconst_0
/*    */     //   639: goto -> 691
/*    */     //   642: aload #17
/*    */     //   644: instanceof java/lang/Number
/*    */     //   647: ifeq -> 663
/*    */     //   650: aload #17
/*    */     //   652: checkcast java/lang/Number
/*    */     //   655: aload #18
/*    */     //   657: invokestatic equalsNumObject : (Ljava/lang/Number;Ljava/lang/Object;)Z
/*    */     //   660: goto -> 691
/*    */     //   663: aload #17
/*    */     //   665: instanceof java/lang/Character
/*    */     //   668: ifeq -> 684
/*    */     //   671: aload #17
/*    */     //   673: checkcast java/lang/Character
/*    */     //   676: aload #18
/*    */     //   678: invokestatic equalsCharObject : (Ljava/lang/Character;Ljava/lang/Object;)Z
/*    */     //   681: goto -> 691
/*    */     //   684: aload #17
/*    */     //   686: aload #18
/*    */     //   688: invokevirtual equals : (Ljava/lang/Object;)Z
/*    */     //   691: ifeq -> 1463
/*    */     //   694: aload_0
/*    */     //   695: invokevirtual _9 : ()Ljava/lang/Object;
/*    */     //   698: aload #37
/*    */     //   700: invokevirtual _9 : ()Ljava/lang/Object;
/*    */     //   703: astore #20
/*    */     //   705: dup
/*    */     //   706: astore #19
/*    */     //   708: aload #20
/*    */     //   710: if_acmpne -> 717
/*    */     //   713: iconst_1
/*    */     //   714: goto -> 775
/*    */     //   717: aload #19
/*    */     //   719: ifnonnull -> 726
/*    */     //   722: iconst_0
/*    */     //   723: goto -> 775
/*    */     //   726: aload #19
/*    */     //   728: instanceof java/lang/Number
/*    */     //   731: ifeq -> 747
/*    */     //   734: aload #19
/*    */     //   736: checkcast java/lang/Number
/*    */     //   739: aload #20
/*    */     //   741: invokestatic equalsNumObject : (Ljava/lang/Number;Ljava/lang/Object;)Z
/*    */     //   744: goto -> 775
/*    */     //   747: aload #19
/*    */     //   749: instanceof java/lang/Character
/*    */     //   752: ifeq -> 768
/*    */     //   755: aload #19
/*    */     //   757: checkcast java/lang/Character
/*    */     //   760: aload #20
/*    */     //   762: invokestatic equalsCharObject : (Ljava/lang/Character;Ljava/lang/Object;)Z
/*    */     //   765: goto -> 775
/*    */     //   768: aload #19
/*    */     //   770: aload #20
/*    */     //   772: invokevirtual equals : (Ljava/lang/Object;)Z
/*    */     //   775: ifeq -> 1463
/*    */     //   778: aload_0
/*    */     //   779: invokevirtual _10 : ()Ljava/lang/Object;
/*    */     //   782: aload #37
/*    */     //   784: invokevirtual _10 : ()Ljava/lang/Object;
/*    */     //   787: astore #22
/*    */     //   789: dup
/*    */     //   790: astore #21
/*    */     //   792: aload #22
/*    */     //   794: if_acmpne -> 801
/*    */     //   797: iconst_1
/*    */     //   798: goto -> 859
/*    */     //   801: aload #21
/*    */     //   803: ifnonnull -> 810
/*    */     //   806: iconst_0
/*    */     //   807: goto -> 859
/*    */     //   810: aload #21
/*    */     //   812: instanceof java/lang/Number
/*    */     //   815: ifeq -> 831
/*    */     //   818: aload #21
/*    */     //   820: checkcast java/lang/Number
/*    */     //   823: aload #22
/*    */     //   825: invokestatic equalsNumObject : (Ljava/lang/Number;Ljava/lang/Object;)Z
/*    */     //   828: goto -> 859
/*    */     //   831: aload #21
/*    */     //   833: instanceof java/lang/Character
/*    */     //   836: ifeq -> 852
/*    */     //   839: aload #21
/*    */     //   841: checkcast java/lang/Character
/*    */     //   844: aload #22
/*    */     //   846: invokestatic equalsCharObject : (Ljava/lang/Character;Ljava/lang/Object;)Z
/*    */     //   849: goto -> 859
/*    */     //   852: aload #21
/*    */     //   854: aload #22
/*    */     //   856: invokevirtual equals : (Ljava/lang/Object;)Z
/*    */     //   859: ifeq -> 1463
/*    */     //   862: aload_0
/*    */     //   863: invokevirtual _11 : ()Ljava/lang/Object;
/*    */     //   866: aload #37
/*    */     //   868: invokevirtual _11 : ()Ljava/lang/Object;
/*    */     //   871: astore #24
/*    */     //   873: dup
/*    */     //   874: astore #23
/*    */     //   876: aload #24
/*    */     //   878: if_acmpne -> 885
/*    */     //   881: iconst_1
/*    */     //   882: goto -> 943
/*    */     //   885: aload #23
/*    */     //   887: ifnonnull -> 894
/*    */     //   890: iconst_0
/*    */     //   891: goto -> 943
/*    */     //   894: aload #23
/*    */     //   896: instanceof java/lang/Number
/*    */     //   899: ifeq -> 915
/*    */     //   902: aload #23
/*    */     //   904: checkcast java/lang/Number
/*    */     //   907: aload #24
/*    */     //   909: invokestatic equalsNumObject : (Ljava/lang/Number;Ljava/lang/Object;)Z
/*    */     //   912: goto -> 943
/*    */     //   915: aload #23
/*    */     //   917: instanceof java/lang/Character
/*    */     //   920: ifeq -> 936
/*    */     //   923: aload #23
/*    */     //   925: checkcast java/lang/Character
/*    */     //   928: aload #24
/*    */     //   930: invokestatic equalsCharObject : (Ljava/lang/Character;Ljava/lang/Object;)Z
/*    */     //   933: goto -> 943
/*    */     //   936: aload #23
/*    */     //   938: aload #24
/*    */     //   940: invokevirtual equals : (Ljava/lang/Object;)Z
/*    */     //   943: ifeq -> 1463
/*    */     //   946: aload_0
/*    */     //   947: invokevirtual _12 : ()Ljava/lang/Object;
/*    */     //   950: aload #37
/*    */     //   952: invokevirtual _12 : ()Ljava/lang/Object;
/*    */     //   955: astore #26
/*    */     //   957: dup
/*    */     //   958: astore #25
/*    */     //   960: aload #26
/*    */     //   962: if_acmpne -> 969
/*    */     //   965: iconst_1
/*    */     //   966: goto -> 1027
/*    */     //   969: aload #25
/*    */     //   971: ifnonnull -> 978
/*    */     //   974: iconst_0
/*    */     //   975: goto -> 1027
/*    */     //   978: aload #25
/*    */     //   980: instanceof java/lang/Number
/*    */     //   983: ifeq -> 999
/*    */     //   986: aload #25
/*    */     //   988: checkcast java/lang/Number
/*    */     //   991: aload #26
/*    */     //   993: invokestatic equalsNumObject : (Ljava/lang/Number;Ljava/lang/Object;)Z
/*    */     //   996: goto -> 1027
/*    */     //   999: aload #25
/*    */     //   1001: instanceof java/lang/Character
/*    */     //   1004: ifeq -> 1020
/*    */     //   1007: aload #25
/*    */     //   1009: checkcast java/lang/Character
/*    */     //   1012: aload #26
/*    */     //   1014: invokestatic equalsCharObject : (Ljava/lang/Character;Ljava/lang/Object;)Z
/*    */     //   1017: goto -> 1027
/*    */     //   1020: aload #25
/*    */     //   1022: aload #26
/*    */     //   1024: invokevirtual equals : (Ljava/lang/Object;)Z
/*    */     //   1027: ifeq -> 1463
/*    */     //   1030: aload_0
/*    */     //   1031: invokevirtual _13 : ()Ljava/lang/Object;
/*    */     //   1034: aload #37
/*    */     //   1036: invokevirtual _13 : ()Ljava/lang/Object;
/*    */     //   1039: astore #28
/*    */     //   1041: dup
/*    */     //   1042: astore #27
/*    */     //   1044: aload #28
/*    */     //   1046: if_acmpne -> 1053
/*    */     //   1049: iconst_1
/*    */     //   1050: goto -> 1111
/*    */     //   1053: aload #27
/*    */     //   1055: ifnonnull -> 1062
/*    */     //   1058: iconst_0
/*    */     //   1059: goto -> 1111
/*    */     //   1062: aload #27
/*    */     //   1064: instanceof java/lang/Number
/*    */     //   1067: ifeq -> 1083
/*    */     //   1070: aload #27
/*    */     //   1072: checkcast java/lang/Number
/*    */     //   1075: aload #28
/*    */     //   1077: invokestatic equalsNumObject : (Ljava/lang/Number;Ljava/lang/Object;)Z
/*    */     //   1080: goto -> 1111
/*    */     //   1083: aload #27
/*    */     //   1085: instanceof java/lang/Character
/*    */     //   1088: ifeq -> 1104
/*    */     //   1091: aload #27
/*    */     //   1093: checkcast java/lang/Character
/*    */     //   1096: aload #28
/*    */     //   1098: invokestatic equalsCharObject : (Ljava/lang/Character;Ljava/lang/Object;)Z
/*    */     //   1101: goto -> 1111
/*    */     //   1104: aload #27
/*    */     //   1106: aload #28
/*    */     //   1108: invokevirtual equals : (Ljava/lang/Object;)Z
/*    */     //   1111: ifeq -> 1463
/*    */     //   1114: aload_0
/*    */     //   1115: invokevirtual _14 : ()Ljava/lang/Object;
/*    */     //   1118: aload #37
/*    */     //   1120: invokevirtual _14 : ()Ljava/lang/Object;
/*    */     //   1123: astore #30
/*    */     //   1125: dup
/*    */     //   1126: astore #29
/*    */     //   1128: aload #30
/*    */     //   1130: if_acmpne -> 1137
/*    */     //   1133: iconst_1
/*    */     //   1134: goto -> 1195
/*    */     //   1137: aload #29
/*    */     //   1139: ifnonnull -> 1146
/*    */     //   1142: iconst_0
/*    */     //   1143: goto -> 1195
/*    */     //   1146: aload #29
/*    */     //   1148: instanceof java/lang/Number
/*    */     //   1151: ifeq -> 1167
/*    */     //   1154: aload #29
/*    */     //   1156: checkcast java/lang/Number
/*    */     //   1159: aload #30
/*    */     //   1161: invokestatic equalsNumObject : (Ljava/lang/Number;Ljava/lang/Object;)Z
/*    */     //   1164: goto -> 1195
/*    */     //   1167: aload #29
/*    */     //   1169: instanceof java/lang/Character
/*    */     //   1172: ifeq -> 1188
/*    */     //   1175: aload #29
/*    */     //   1177: checkcast java/lang/Character
/*    */     //   1180: aload #30
/*    */     //   1182: invokestatic equalsCharObject : (Ljava/lang/Character;Ljava/lang/Object;)Z
/*    */     //   1185: goto -> 1195
/*    */     //   1188: aload #29
/*    */     //   1190: aload #30
/*    */     //   1192: invokevirtual equals : (Ljava/lang/Object;)Z
/*    */     //   1195: ifeq -> 1463
/*    */     //   1198: aload_0
/*    */     //   1199: invokevirtual _15 : ()Ljava/lang/Object;
/*    */     //   1202: aload #37
/*    */     //   1204: invokevirtual _15 : ()Ljava/lang/Object;
/*    */     //   1207: astore #32
/*    */     //   1209: dup
/*    */     //   1210: astore #31
/*    */     //   1212: aload #32
/*    */     //   1214: if_acmpne -> 1221
/*    */     //   1217: iconst_1
/*    */     //   1218: goto -> 1279
/*    */     //   1221: aload #31
/*    */     //   1223: ifnonnull -> 1230
/*    */     //   1226: iconst_0
/*    */     //   1227: goto -> 1279
/*    */     //   1230: aload #31
/*    */     //   1232: instanceof java/lang/Number
/*    */     //   1235: ifeq -> 1251
/*    */     //   1238: aload #31
/*    */     //   1240: checkcast java/lang/Number
/*    */     //   1243: aload #32
/*    */     //   1245: invokestatic equalsNumObject : (Ljava/lang/Number;Ljava/lang/Object;)Z
/*    */     //   1248: goto -> 1279
/*    */     //   1251: aload #31
/*    */     //   1253: instanceof java/lang/Character
/*    */     //   1256: ifeq -> 1272
/*    */     //   1259: aload #31
/*    */     //   1261: checkcast java/lang/Character
/*    */     //   1264: aload #32
/*    */     //   1266: invokestatic equalsCharObject : (Ljava/lang/Character;Ljava/lang/Object;)Z
/*    */     //   1269: goto -> 1279
/*    */     //   1272: aload #31
/*    */     //   1274: aload #32
/*    */     //   1276: invokevirtual equals : (Ljava/lang/Object;)Z
/*    */     //   1279: ifeq -> 1463
/*    */     //   1282: aload_0
/*    */     //   1283: invokevirtual _16 : ()Ljava/lang/Object;
/*    */     //   1286: aload #37
/*    */     //   1288: invokevirtual _16 : ()Ljava/lang/Object;
/*    */     //   1291: astore #34
/*    */     //   1293: dup
/*    */     //   1294: astore #33
/*    */     //   1296: aload #34
/*    */     //   1298: if_acmpne -> 1305
/*    */     //   1301: iconst_1
/*    */     //   1302: goto -> 1363
/*    */     //   1305: aload #33
/*    */     //   1307: ifnonnull -> 1314
/*    */     //   1310: iconst_0
/*    */     //   1311: goto -> 1363
/*    */     //   1314: aload #33
/*    */     //   1316: instanceof java/lang/Number
/*    */     //   1319: ifeq -> 1335
/*    */     //   1322: aload #33
/*    */     //   1324: checkcast java/lang/Number
/*    */     //   1327: aload #34
/*    */     //   1329: invokestatic equalsNumObject : (Ljava/lang/Number;Ljava/lang/Object;)Z
/*    */     //   1332: goto -> 1363
/*    */     //   1335: aload #33
/*    */     //   1337: instanceof java/lang/Character
/*    */     //   1340: ifeq -> 1356
/*    */     //   1343: aload #33
/*    */     //   1345: checkcast java/lang/Character
/*    */     //   1348: aload #34
/*    */     //   1350: invokestatic equalsCharObject : (Ljava/lang/Character;Ljava/lang/Object;)Z
/*    */     //   1353: goto -> 1363
/*    */     //   1356: aload #33
/*    */     //   1358: aload #34
/*    */     //   1360: invokevirtual equals : (Ljava/lang/Object;)Z
/*    */     //   1363: ifeq -> 1463
/*    */     //   1366: aload_0
/*    */     //   1367: invokevirtual _17 : ()Ljava/lang/Object;
/*    */     //   1370: aload #37
/*    */     //   1372: invokevirtual _17 : ()Ljava/lang/Object;
/*    */     //   1375: astore #36
/*    */     //   1377: dup
/*    */     //   1378: astore #35
/*    */     //   1380: aload #36
/*    */     //   1382: if_acmpne -> 1389
/*    */     //   1385: iconst_1
/*    */     //   1386: goto -> 1447
/*    */     //   1389: aload #35
/*    */     //   1391: ifnonnull -> 1398
/*    */     //   1394: iconst_0
/*    */     //   1395: goto -> 1447
/*    */     //   1398: aload #35
/*    */     //   1400: instanceof java/lang/Number
/*    */     //   1403: ifeq -> 1419
/*    */     //   1406: aload #35
/*    */     //   1408: checkcast java/lang/Number
/*    */     //   1411: aload #36
/*    */     //   1413: invokestatic equalsNumObject : (Ljava/lang/Number;Ljava/lang/Object;)Z
/*    */     //   1416: goto -> 1447
/*    */     //   1419: aload #35
/*    */     //   1421: instanceof java/lang/Character
/*    */     //   1424: ifeq -> 1440
/*    */     //   1427: aload #35
/*    */     //   1429: checkcast java/lang/Character
/*    */     //   1432: aload #36
/*    */     //   1434: invokestatic equalsCharObject : (Ljava/lang/Character;Ljava/lang/Object;)Z
/*    */     //   1437: goto -> 1447
/*    */     //   1440: aload #35
/*    */     //   1442: aload #36
/*    */     //   1444: invokevirtual equals : (Ljava/lang/Object;)Z
/*    */     //   1447: ifeq -> 1463
/*    */     //   1450: aload #37
/*    */     //   1452: aload_0
/*    */     //   1453: invokevirtual canEqual : (Ljava/lang/Object;)Z
/*    */     //   1456: ifeq -> 1463
/*    */     //   1459: iconst_1
/*    */     //   1460: goto -> 1464
/*    */     //   1463: iconst_0
/*    */     //   1464: ifeq -> 1471
/*    */     //   1467: iconst_1
/*    */     //   1468: goto -> 1472
/*    */     //   1471: iconst_0
/*    */     //   1472: ireturn
/*    */     // Line number table:
/*    */     //   Java source line number -> byte code offset
/*    */     //   #34	-> 0
/*    */     //   #236	-> 12
/*    */     //   #34	-> 19
/*    */     // Local variable table:
/*    */     //   start	length	slot	name	descriptor
/*    */     //   0	1473	0	this	Lscala/Tuple17;
/*    */     //   0	1473	1	x$1	Ljava/lang/Object;
/*    */   }
/*    */   
/*    */   public Tuple17(Object _1, Object _2, Object _3, Object _4, Object _5, Object _6, Object _7, Object _8, Object _9, Object _10, Object _11, Object _12, Object _13, Object _14, Object _15, Object _16, Object _17) {
/* 34 */     Product$class.$init$(this);
/* 34 */     Product17$class.$init$(this);
/*    */   }
/*    */   
/*    */   public String toString() {
/* 38 */     return (new StringBuilder()).append("(").append(_1()).append(",").append(_2()).append(",").append(_3()).append(",").append(_4()).append(",").append(_5()).append(",").append(_6()).append(",").append(_7()).append(",").append(_8()).append(",").append(_9()).append(",").append(_10()).append(",").append(_11()).append(",").append(_12()).append(",").append(_13()).append(",").append(_14()).append(",").append(_15()).append(",").append(_16()).append(",").append(_17()).append(")").toString();
/*    */   }
/*    */ }


/* Location:              D:\#source-code\TheFlightSims\TFSLibrary\World2Xplane\World2XPlane.jar!\scala\Tuple17.class
 * Java compiler version: 6 (50.0)
 * JD-Core Version:       1.1.3
 */