/*    */ package scala;
/*    */ 
/*    */ import scala.collection.Iterator;
/*    */ import scala.collection.mutable.StringBuilder;
/*    */ import scala.reflect.ScalaSignature;
/*    */ import scala.runtime.ScalaRunTime$;
/*    */ 
/*    */ @ScalaSignature(bytes = "\006\001!ed\001B\001\003\001\026\021q\001V;qY\026\024$GC\001\004\003\025\0318-\0317b\007\001)rC\002\t\033;\001\032c%\013\0270eUB4HP!E\017*k\005k\025,\024\013\00191\002W.\021\005!IQ\"\001\002\n\005)\021!AB!osJ+g\r\005\r\t\0319IBd\b\022&Q-r\023\007N\034;{\001\033e)\023'P%VK!!\004\002\003\023A\023x\016Z;diJ\022\004CA\b\021\031\001!a!\005\001\005\006\004\021\"A\001+2#\t\031b\003\005\002\t)%\021QC\001\002\b\035>$\b.\0338h!\tAq#\003\002\031\005\t\031\021I\\=\021\005=QBAB\016\001\t\013\007!C\001\002UeA\021q\"\b\003\007=\001!)\031\001\n\003\005Q\033\004CA\b!\t\031\t\003\001\"b\001%\t\021A\013\016\t\003\037\r\"a\001\n\001\005\006\004\021\"A\001+6!\tya\005\002\004(\001\021\025\rA\005\002\003)Z\002\"aD\025\005\r)\002AQ1\001\023\005\t!v\007\005\002\020Y\0211Q\006\001CC\002I\021!\001\026\035\021\005=yCA\002\031\001\t\013\007!C\001\002UsA\021qB\r\003\007g\001!)\031\001\n\003\007Q\013\004\007\005\002\020k\0211a\007\001CC\002I\0211\001V\0312!\ty\001\b\002\004:\001\021\025\rA\005\002\004)F\022\004CA\b<\t\031a\004\001\"b\001%\t\031A+M\032\021\005=qDAB \001\t\013\007!CA\002UcQ\002\"aD!\005\r\t\003AQ1\001\023\005\r!\026'\016\t\003\037\021#a!\022\001\005\006\004\021\"a\001+2mA\021qb\022\003\007\021\002!)\031\001\n\003\007Q\013t\007\005\002\020\025\02211\n\001CC\002I\0211\001V\0319!\tyQ\n\002\004O\001\021\025\rA\005\002\004)FJ\004CA\bQ\t\031\t\006\001\"b\001%\t\031AK\r\031\021\005=\031FA\002+\001\t\013\007!CA\002UeE\002\"a\004,\005\r]\003AQ1\001\023\005\r!&G\r\t\003\021eK!A\027\002\003\017A\023x\016Z;diB\021\001\002X\005\003;\n\021AbU3sS\006d\027N_1cY\026D\001b\030\001\003\026\004%\t\001Y\001\003?F*\022A\004\005\tE\002\021\t\022)A\005\035\005\031q,\r\021\t\021\021\004!Q3A\005\002\025\f!a\030\032\026\003eA\001b\032\001\003\022\003\006I!G\001\004?J\002\003\002C5\001\005+\007I\021\0016\002\005}\033T#\001\017\t\0211\004!\021#Q\001\nq\t1aX\032!\021!q\007A!f\001\n\003y\027AA05+\005y\002\002C9\001\005#\005\013\021B\020\002\007}#\004\005\003\005t\001\tU\r\021\"\001u\003\tyV'F\001#\021!1\bA!E!\002\023\021\023aA06A!A\001\020\001BK\002\023\005\0210\001\002`mU\tQ\005\003\005|\001\tE\t\025!\003&\003\ryf\007\t\005\t{\002\021)\032!C\001}\006\021qlN\013\002Q!I\021\021\001\001\003\022\003\006I\001K\001\004?^\002\003BCA\003\001\tU\r\021\"\001\002\b\005\021q\fO\013\002W!I\0211\002\001\003\022\003\006IaK\001\004?b\002\003BCA\b\001\tU\r\021\"\001\002\022\005\021q,O\013\002]!I\021Q\003\001\003\022\003\006IAL\001\004?f\002\003BCA\r\001\tU\r\021\"\001\002\034\005\031q,\r\031\026\003EB\021\"a\b\001\005#\005\013\021B\031\002\t}\013\004\007\t\005\013\003G\001!Q3A\005\002\005\025\022aA02cU\tA\007C\005\002*\001\021\t\022)A\005i\005!q,M\031!\021)\ti\003\001BK\002\023\005\021qF\001\004?F\022T#A\034\t\023\005M\002A!E!\002\0239\024\001B02e\001B!\"a\016\001\005+\007I\021AA\035\003\ry\026gM\013\002u!I\021Q\b\001\003\022\003\006IAO\001\005?F\032\004\005\003\006\002B\001\021)\032!C\001\003\007\n1aX\0315+\005i\004\"CA$\001\tE\t\025!\003>\003\021y\026\007\016\021\t\025\005-\003A!f\001\n\003\ti%A\002`cU*\022\001\021\005\n\003#\002!\021#Q\001\n\001\013AaX\0316A!Q\021Q\013\001\003\026\004%\t!a\026\002\007}\013d'F\001D\021%\tY\006\001B\tB\003%1)\001\003`cY\002\003BCA0\001\tU\r\021\"\001\002b\005\031q,M\034\026\003\031C\021\"!\032\001\005#\005\013\021\002$\002\t}\013t\007\t\005\013\003S\002!Q3A\005\002\005-\024aA02qU\t\021\nC\005\002p\001\021\t\022)A\005\023\006!q,\r\035!\021)\t\031\b\001BK\002\023\005\021QO\001\004?FJT#\001'\t\023\005e\004A!E!\002\023a\025\001B02s\001B!\"! \001\005+\007I\021AA@\003\ry&\007M\013\002\037\"I\0211\021\001\003\022\003\006IaT\001\005?J\002\004\005\003\006\002\b\002\021)\032!C\001\003\023\0131a\030\0322+\005\021\006\"CAG\001\tE\t\025!\003S\003\021y&'\r\021\t\025\005E\005A!f\001\n\003\t\031*A\002`eI*\022!\026\005\n\003/\003!\021#Q\001\nU\013Aa\030\0323A!9\0211\024\001\005\002\005u\025A\002\037j]&$h\b\006\030\002 \006\005\0261UAS\003O\013I+a+\002.\006=\026\021WAZ\003k\0139,!/\002<\006u\026qXAa\003\007\f)-a2\002J\006-\007\003\007\005\001\035earDI\023)W9\nDg\016\036>\001\0163\025\nT(S+\"1q,!'A\0029Aa\001ZAM\001\004I\002BB5\002\032\002\007A\004\003\004o\0033\003\ra\b\005\007g\006e\005\031\001\022\t\ra\fI\n1\001&\021\031i\030\021\024a\001Q!9\021QAAM\001\004Y\003bBA\b\0033\003\rA\f\005\b\0033\tI\n1\0012\021\035\t\031#!'A\002QBq!!\f\002\032\002\007q\007C\004\0028\005e\005\031\001\036\t\017\005\005\023\021\024a\001{!9\0211JAM\001\004\001\005bBA+\0033\003\ra\021\005\b\003?\nI\n1\001G\021\035\tI'!'A\002%Cq!a\035\002\032\002\007A\nC\004\002~\005e\005\031A(\t\017\005\035\025\021\024a\001%\"9\021\021SAM\001\004)\006bBAh\001\021\005\023\021[\001\ti>\034FO]5oOR\021\0211\033\t\005\003+\fy.\004\002\002X*!\021\021\\An\003\021a\027M\\4\013\005\005u\027\001\0026bm\006LA!!9\002X\n11\013\036:j]\036D\021\"!:\001\003\003%\t!a:\002\t\r|\007/_\013/\003S\fy/a=\002x\006m\030q B\002\005\017\021YAa\004\003\024\t]!1\004B\020\005G\0219Ca\013\0030\tM\"q\007B\036\005\021\031\005\006\030\002l\n\025#q\tB%\005\027\022iEa\024\003R\tM#Q\013B,\0053\022YF!\030\003`\t\005$1\rB3\005O\022IGa\033\003n\t=\004C\f\005\001\003[\f\t0!>\002z\006u(\021\001B\003\005\023\021iA!\005\003\026\te!Q\004B\021\005K\021IC!\f\0032\tU\"\021\bB\037\005\003\0022aDAx\t\031\t\0221\035b\001%A\031q\"a=\005\rm\t\031O1\001\023!\ry\021q\037\003\007=\005\r(\031\001\n\021\007=\tY\020\002\004\"\003G\024\rA\005\t\004\037\005}HA\002\023\002d\n\007!\003E\002\020\005\007!aaJAr\005\004\021\002cA\b\003\b\0211!&a9C\002I\0012a\004B\006\t\031i\0231\035b\001%A\031qBa\004\005\rA\n\031O1\001\023!\ry!1\003\003\007g\005\r(\031\001\n\021\007=\0219\002\002\0047\003G\024\rA\005\t\004\037\tmAAB\035\002d\n\007!\003E\002\020\005?!a\001PAr\005\004\021\002cA\b\003$\0211q(a9C\002I\0012a\004B\024\t\031\021\0251\035b\001%A\031qBa\013\005\r\025\013\031O1\001\023!\ry!q\006\003\007\021\006\r(\031\001\n\021\007=\021\031\004\002\004L\003G\024\rA\005\t\004\037\t]BA\002(\002d\n\007!\003E\002\020\005w!a!UAr\005\004\021\002cA\b\003@\0211A+a9C\002I\0012a\004B\"\t\0319\0261\035b\001%!Iq,a9\021\002\003\007\021Q\036\005\nI\006\r\b\023!a\001\003cD\021\"[Ar!\003\005\r!!>\t\0239\f\031\017%AA\002\005e\b\"C:\002dB\005\t\031AA\021%A\0301\035I\001\002\004\021\t\001C\005~\003G\004\n\0211\001\003\006!Q\021QAAr!\003\005\rA!\003\t\025\005=\0211\035I\001\002\004\021i\001\003\006\002\032\005\r\b\023!a\001\005#A!\"a\t\002dB\005\t\031\001B\013\021)\ti#a9\021\002\003\007!\021\004\005\013\003o\t\031\017%AA\002\tu\001BCA!\003G\004\n\0211\001\003\"!Q\0211JAr!\003\005\rA!\n\t\025\005U\0231\035I\001\002\004\021I\003\003\006\002`\005\r\b\023!a\001\005[A!\"!\033\002dB\005\t\031\001B\031\021)\t\031(a9\021\002\003\007!Q\007\005\013\003{\n\031\017%AA\002\te\002BCAD\003G\004\n\0211\001\003>!Q\021\021SAr!\003\005\rA!\021\t\023\tM\004!%A\005\002\tU\024AD2paf$C-\0324bk2$H%M\013/\005o\022iIa$\003\022\nM%Q\023BL\0053\023YJ!(\003 \n\005&1\025BS\005O\023IKa+\003.\n=&\021\027BZ\005k\0239,\006\002\003z)\032aBa\037,\005\tu\004\003\002B@\005\023k!A!!\013\t\t\r%QQ\001\nk:\034\007.Z2lK\022T1Aa\"\003\003)\tgN\\8uCRLwN\\\005\005\005\027\023\tIA\tv]\016DWmY6fIZ\013'/[1oG\026$a!\005B9\005\004\021BAB\016\003r\t\007!\003\002\004\037\005c\022\rA\005\003\007C\tE$\031\001\n\005\r\021\022\tH1\001\023\t\0319#\021\017b\001%\0211!F!\035C\002I!a!\fB9\005\004\021BA\002\031\003r\t\007!\003\002\0044\005c\022\rA\005\003\007m\tE$\031\001\n\005\re\022\tH1\001\023\t\031a$\021\017b\001%\0211qH!\035C\002I!aA\021B9\005\004\021BAB#\003r\t\007!\003\002\004I\005c\022\rA\005\003\007\027\nE$\031\001\n\005\r9\023\tH1\001\023\t\031\t&\021\017b\001%\0211AK!\035C\002I!aa\026B9\005\004\021\002\"\003B^\001E\005I\021\001B_\0039\031w\016]=%I\0264\027-\0367uII*bFa0\003D\n\025'q\031Be\005\027\024iMa4\003R\nM'Q\033Bl\0053\024YN!8\003`\n\005(1\035Bs\005O\024IOa;\003nV\021!\021\031\026\0043\tmDAB\t\003:\n\007!\003\002\004\034\005s\023\rA\005\003\007=\te&\031\001\n\005\r\005\022IL1\001\023\t\031!#\021\030b\001%\0211qE!/C\002I!aA\013B]\005\004\021BAB\027\003:\n\007!\003\002\0041\005s\023\rA\005\003\007g\te&\031\001\n\005\rY\022IL1\001\023\t\031I$\021\030b\001%\0211AH!/C\002I!aa\020B]\005\004\021BA\002\"\003:\n\007!\003\002\004F\005s\023\rA\005\003\007\021\ne&\031\001\n\005\r-\023IL1\001\023\t\031q%\021\030b\001%\0211\021K!/C\002I!a\001\026B]\005\004\021BAB,\003:\n\007!\003C\005\003r\002\t\n\021\"\001\003t\006q1m\0349zI\021,g-Y;mi\022\032TC\fB{\005s\024YP!@\003\000\016\00511AB\003\007\017\031Iaa\003\004\016\r=1\021CB\n\007+\0319b!\007\004\034\ru1qDB\021\007G)\"Aa>+\007q\021Y\b\002\004\022\005_\024\rA\005\003\0077\t=(\031\001\n\005\ry\021yO1\001\023\t\031\t#q\036b\001%\0211AEa<C\002I!aa\nBx\005\004\021BA\002\026\003p\n\007!\003\002\004.\005_\024\rA\005\003\007a\t=(\031\001\n\005\rM\022yO1\001\023\t\0311$q\036b\001%\0211\021Ha<C\002I!a\001\020Bx\005\004\021BAB \003p\n\007!\003\002\004C\005_\024\rA\005\003\007\013\n=(\031\001\n\005\r!\023yO1\001\023\t\031Y%q\036b\001%\0211aJa<C\002I!a!\025Bx\005\004\021BA\002+\003p\n\007!\003\002\004X\005_\024\rA\005\005\n\007O\001\021\023!C\001\007S\tabY8qs\022\"WMZ1vYR$C'\006\030\004,\r=2\021GB\032\007k\0319d!\017\004<\ru2qHB!\007\007\032)ea\022\004J\r-3QJB(\007#\032\031f!\026\004X\reSCAB\027U\ry\"1\020\003\007#\r\025\"\031\001\n\005\rm\031)C1\001\023\t\031q2Q\005b\001%\0211\021e!\nC\002I!a\001JB\023\005\004\021BAB\024\004&\t\007!\003\002\004+\007K\021\rA\005\003\007[\r\025\"\031\001\n\005\rA\032)C1\001\023\t\031\0314Q\005b\001%\0211ag!\nC\002I!a!OB\023\005\004\021BA\002\037\004&\t\007!\003\002\004@\007K\021\rA\005\003\007\005\016\025\"\031\001\n\005\r\025\033)C1\001\023\t\031A5Q\005b\001%\02111j!\nC\002I!aATB\023\005\004\021BAB)\004&\t\007!\003\002\004U\007K\021\rA\005\003\007/\016\025\"\031\001\n\t\023\ru\003!%A\005\002\r}\023AD2paf$C-\0324bk2$H%N\013/\007C\032)ga\032\004j\r-4QNB8\007c\032\031h!\036\004x\re41PB?\007\032\tia!\004\006\016\0355\021RBF\007\033\033y)\006\002\004d)\032!Ea\037\005\rE\031YF1\001\023\t\031Y21\fb\001%\0211ada\027C\002I!a!IB.\005\004\021BA\002\023\004\\\t\007!\003\002\004(\0077\022\rA\005\003\007U\rm#\031\001\n\005\r5\032YF1\001\023\t\031\00141\fb\001%\02111ga\027C\002I!aANB.\005\004\021BAB\035\004\\\t\007!\003\002\004=\0077\022\rA\005\003\007\rm#\031\001\n\005\r\t\033YF1\001\023\t\031)51\fb\001%\0211\001ja\027C\002I!aaSB.\005\004\021BA\002(\004\\\t\007!\003\002\004R\0077\022\rA\005\003\007)\016m#\031\001\n\005\r]\033YF1\001\023\021%\031\031\nAI\001\n\003\031)*\001\bd_BLH\005Z3gCVdG\017\n\034\026]\r]51TBO\007?\033\tka)\004&\016\0356\021VBV\007[\033yk!-\0044\016U6qWB]\007w\033ila0\004B\016\r7QY\013\003\0073S3!\nB>\t\031\t2\021\023b\001%\02111d!%C\002I!aAHBI\005\004\021BAB\021\004\022\n\007!\003\002\004%\007#\023\rA\005\003\007O\rE%\031\001\n\005\r)\032\tJ1\001\023\t\031i3\021\023b\001%\0211\001g!%C\002I!aaMBI\005\004\021BA\002\034\004\022\n\007!\003\002\004:\007#\023\rA\005\003\007y\rE%\031\001\n\005\r}\032\tJ1\001\023\t\031\0215\021\023b\001%\0211Qi!%C\002I!a\001SBI\005\004\021BAB&\004\022\n\007!\003\002\004O\007#\023\rA\005\003\007#\016E%\031\001\n\005\rQ\033\tJ1\001\023\t\03196\021\023b\001%!I1\021\032\001\022\002\023\00511Z\001\017G>\004\030\020\n3fM\006,H\016\036\0238+9\032im!5\004T\016U7q[Bm\0077\034ina8\004b\016\r8Q]Bt\007S\034Yo!<\004p\016E81_B{\007o\034Ipa?\026\005\r='f\001\025\003|\0211\021ca2C\002I!aaGBd\005\004\021BA\002\020\004H\n\007!\003\002\004\"\007\017\024\rA\005\003\007I\r\035'\031\001\n\005\r\035\0329M1\001\023\t\031Q3q\031b\001%\0211Qfa2C\002I!a\001MBd\005\004\021BAB\032\004H\n\007!\003\002\0047\007\017\024\rA\005\003\007s\r\035'\031\001\n\005\rq\0329M1\001\023\t\031y4q\031b\001%\0211!ia2C\002I!a!RBd\005\004\021BA\002%\004H\n\007!\003\002\004L\007\017\024\rA\005\003\007\035\016\035'\031\001\n\005\rE\0339M1\001\023\t\031!6q\031b\001%\0211qka2C\002IA\021ba@\001#\003%\t\001\"\001\002\035\r|\007/\037\023eK\032\fW\017\034;%qUqC1\001C\004\t\023!Y\001\"\004\005\020\021EA1\003C\013\t/!I\002b\007\005\036\021}A\021\005C\022\tK!9\003\"\013\005,\0215Bq\006C\031+\t!)AK\002,\005w\"a!EB\005\004\021BAB\016\004~\n\007!\003\002\004\037\007{\024\rA\005\003\007C\ru(\031\001\n\005\r\021\032iP1\001\023\t\03193Q b\001%\0211!f!@C\002I!a!LB\005\004\021BA\002\031\004~\n\007!\003\002\0044\007{\024\rA\005\003\007m\ru(\031\001\n\005\re\032iP1\001\023\t\031a4Q b\001%\0211qh!@C\002I!aAQB\005\004\021BAB#\004~\n\007!\003\002\004I\007{\024\rA\005\003\007\027\016u(\031\001\n\005\r9\033iP1\001\023\t\031\t6Q b\001%\0211Ak!@C\002I!aaVB\005\004\021\002\"\003C\033\001E\005I\021\001C\034\0039\031w\016]=%I\0264\027-\0367uIe*b\006\"\017\005>\021}B\021\tC\"\t\013\"9\005\"\023\005L\0215Cq\nC)\t'\")\006b\026\005Z\021mCQ\fC0\tC\"\031\007\"\032\005hU\021A1\b\026\004]\tmDAB\t\0054\t\007!\003\002\004\034\tg\021\rA\005\003\007=\021M\"\031\001\n\005\r\005\"\031D1\001\023\t\031!C1\007b\001%\0211q\005b\rC\002I!aA\013C\032\005\004\021BAB\027\0054\t\007!\003\002\0041\tg\021\rA\005\003\007g\021M\"\031\001\n\005\rY\"\031D1\001\023\t\031ID1\007b\001%\0211A\bb\rC\002I!aa\020C\032\005\004\021BA\002\"\0054\t\007!\003\002\004F\tg\021\rA\005\003\007\021\022M\"\031\001\n\005\r-#\031D1\001\023\t\031qE1\007b\001%\0211\021\013b\rC\002I!a\001\026C\032\005\004\021BAB,\0054\t\007!\003C\005\005l\001\t\n\021\"\001\005n\005y1m\0349zI\021,g-Y;mi\022\n\004'\006\030\005p\021MDQ\017C<\ts\"Y\b\" \005\000\021\005E1\021CC\t\017#I\tb#\005\016\022=E\021\023CJ\t+#9\n\"'\005\034\022uUC\001C9U\r\t$1\020\003\007#\021%$\031\001\n\005\rm!IG1\001\023\t\031qB\021\016b\001%\0211\021\005\"\033C\002I!a\001\nC5\005\004\021BAB\024\005j\t\007!\003\002\004+\tS\022\rA\005\003\007[\021%$\031\001\n\005\rA\"IG1\001\023\t\031\031D\021\016b\001%\0211a\007\"\033C\002I!a!\017C5\005\004\021BA\002\037\005j\t\007!\003\002\004@\tS\022\rA\005\003\007\005\022%$\031\001\n\005\r\025#IG1\001\023\t\031AE\021\016b\001%\02111\n\"\033C\002I!aA\024C5\005\004\021BAB)\005j\t\007!\003\002\004U\tS\022\rA\005\003\007/\022%$\031\001\n\t\023\021\005\006!%A\005\002\021\r\026aD2paf$C-\0324bk2$H%M\031\026]\021\025F\021\026CV\t[#y\013\"-\0054\022UFq\027C]\tw#i\fb0\005B\022\rGQ\031Cd\t\023$Y\r\"4\005P\022EG1[\013\003\tOS3\001\016B>\t\031\tBq\024b\001%\02111\004b(C\002I!aA\bCP\005\004\021BAB\021\005 \n\007!\003\002\004%\t?\023\rA\005\003\007O\021}%\031\001\n\005\r)\"yJ1\001\023\t\031iCq\024b\001%\0211\001\007b(C\002I!aa\rCP\005\004\021BA\002\034\005 \n\007!\003\002\004:\t?\023\rA\005\003\007y\021}%\031\001\n\005\r}\"yJ1\001\023\t\031\021Eq\024b\001%\0211Q\tb(C\002I!a\001\023CP\005\004\021BAB&\005 \n\007!\003\002\004O\t?\023\rA\005\003\007#\022}%\031\001\n\005\rQ#yJ1\001\023\t\0319Fq\024b\001%!IAq\033\001\022\002\023\005A\021\\\001\020G>\004\030\020\n3fM\006,H\016\036\0232eUqC1\034Cp\tC$\031\017\":\005h\022%H1\036Cw\t_$\t\020b=\005v\022]H\021 C~\t{$y0\"\001\006\004\025\025QqAC\005+\t!iNK\0028\005w\"a!\005Ck\005\004\021BAB\016\005V\n\007!\003\002\004\037\t+\024\rA\005\003\007C\021U'\031\001\n\005\r\021\")N1\001\023\t\0319CQ\033b\001%\0211!\006\"6C\002I!a!\fCk\005\004\021BA\002\031\005V\n\007!\003\002\0044\t+\024\rA\005\003\007m\021U'\031\001\n\005\re\")N1\001\023\t\031aDQ\033b\001%\0211q\b\"6C\002I!aA\021Ck\005\004\021BAB#\005V\n\007!\003\002\004I\t+\024\rA\005\003\007\027\022U'\031\001\n\005\r9#)N1\001\023\t\031\tFQ\033b\001%\0211A\013\"6C\002I!aa\026Ck\005\004\021\002\"CC\007\001E\005I\021AC\b\003=\031w\016]=%I\0264\027-\0367uIE\032TCLC\t\013+)9\"\"\007\006\034\025uQqDC\021\013G))#b\n\006*\025-RQFC\030\013c)\031$\"\016\0068\025eR1HC\037\013)\"!b\005+\007i\022Y\b\002\004\022\013\027\021\rA\005\003\0077\025-!\031\001\n\005\ry)YA1\001\023\t\031\tS1\002b\001%\0211A%b\003C\002I!aaJC\006\005\004\021BA\002\026\006\f\t\007!\003\002\004.\013\027\021\rA\005\003\007a\025-!\031\001\n\005\rM*YA1\001\023\t\0311T1\002b\001%\0211\021(b\003C\002I!a\001PC\006\005\004\021BAB \006\f\t\007!\003\002\004C\013\027\021\rA\005\003\007\013\026-!\031\001\n\005\r!+YA1\001\023\t\031YU1\002b\001%\0211a*b\003C\002I!a!UC\006\005\004\021BA\002+\006\f\t\007!\003\002\004X\013\027\021\rA\005\005\n\013\007\002\021\023!C\001\013\013\nqbY8qs\022\"WMZ1vYR$\023\007N\013/\013\017*Y%\"\024\006P\025ES1KC+\013/*I&b\027\006^\025}S\021MC2\013K*9'\"\033\006l\0255TqNC9\013g*)(\006\002\006J)\032QHa\037\005\rE)\tE1\001\023\t\031YR\021\tb\001%\0211a$\"\021C\002I!a!IC!\005\004\021BA\002\023\006B\t\007!\003\002\004(\013\003\022\rA\005\003\007U\025\005#\031\001\n\005\r5*\tE1\001\023\t\031\001T\021\tb\001%\02111'\"\021C\002I!aANC!\005\004\021BAB\035\006B\t\007!\003\002\004=\013\003\022\rA\005\003\007\025\005#\031\001\n\005\r\t+\tE1\001\023\t\031)U\021\tb\001%\0211\001*\"\021C\002I!aaSC!\005\004\021BA\002(\006B\t\007!\003\002\004R\013\003\022\rA\005\003\007)\026\005#\031\001\n\005\r]+\tE1\001\023\021%)I\bAI\001\n\003)Y(A\bd_BLH\005Z3gCVdG\017J\0316+9*i(\"!\006\004\026\025UqQCE\013\027+i)b$\006\022\026MUQSCL\0133+Y*\"(\006 \026\005V1UCS\013O+I+b+\026\005\025}$f\001!\003|\0211\021#b\036C\002I!aaGC<\005\004\021BA\002\020\006x\t\007!\003\002\004\"\013o\022\rA\005\003\007I\025]$\031\001\n\005\r\035*9H1\001\023\t\031QSq\017b\001%\0211Q&b\036C\002I!a\001MC<\005\004\021BAB\032\006x\t\007!\003\002\0047\013o\022\rA\005\003\007s\025]$\031\001\n\005\rq*9H1\001\023\t\031yTq\017b\001%\0211!)b\036C\002I!a!RC<\005\004\021BA\002%\006x\t\007!\003\002\004L\013o\022\rA\005\003\007\035\026]$\031\001\n\005\rE+9H1\001\023\t\031!Vq\017b\001%\0211q+b\036C\002IA\021\"b,\001#\003%\t!\"-\002\037\r|\007/\037\023eK\032\fW\017\034;%cY*b&b-\0068\026eV1XC_\013+\t-b1\006F\026\035W\021ZCf\013\033,y-\"5\006T\026UWq[Cm\0137,i.b8\006bV\021QQ\027\026\004\007\nmDAB\t\006.\n\007!\003\002\004\034\013[\023\rA\005\003\007=\0255&\031\001\n\005\r\005*iK1\001\023\t\031!SQ\026b\001%\0211q%\",C\002I!aAKCW\005\004\021BAB\027\006.\n\007!\003\002\0041\013[\023\rA\005\003\007g\0255&\031\001\n\005\rY*iK1\001\023\t\031ITQ\026b\001%\0211A(\",C\002I!aaPCW\005\004\021BA\002\"\006.\n\007!\003\002\004F\013[\023\rA\005\003\007\021\0265&\031\001\n\005\r-+iK1\001\023\t\031qUQ\026b\001%\0211\021+\",C\002I!a\001VCW\005\004\021BAB,\006.\n\007!\003C\005\006f\002\t\n\021\"\001\006h\006y1m\0349zI\021,g-Y;mi\022\nt'\006\030\006j\0265Xq^Cy\013g,)0b>\006z\026mXQ`C\000\r\0031\031A\"\002\007\b\031%a1\002D\007\r\0371\tBb\005\007\026\031]QCACvU\r1%1\020\003\007#\025\r(\031\001\n\005\rm)\031O1\001\023\t\031qR1\035b\001%\0211\021%b9C\002I!a\001JCr\005\004\021BAB\024\006d\n\007!\003\002\004+\013G\024\rA\005\003\007[\025\r(\031\001\n\005\rA*\031O1\001\023\t\031\031T1\035b\001%\0211a'b9C\002I!a!OCr\005\004\021BA\002\037\006d\n\007!\003\002\004@\013G\024\rA\005\003\007\005\026\r(\031\001\n\005\r\025+\031O1\001\023\t\031AU1\035b\001%\02111*b9C\002I!aATCr\005\004\021BAB)\006d\n\007!\003\002\004U\013G\024\rA\005\003\007/\026\r(\031\001\n\t\023\031m\001!%A\005\002\031u\021aD2paf$C-\0324bk2$H%\r\035\026]\031}a1\005D\023\rO1ICb\013\007.\031=b\021\007D\032\rk19D\"\017\007<\031ubq\bD!\r\0072)Eb\022\007J\031-cQJ\013\003\rCQ3!\023B>\t\031\tb\021\004b\001%\02111D\"\007C\002I!aA\bD\r\005\004\021BAB\021\007\032\t\007!\003\002\004%\r3\021\rA\005\003\007O\031e!\031\001\n\005\r)2IB1\001\023\t\031ic\021\004b\001%\0211\001G\"\007C\002I!aa\rD\r\005\004\021BA\002\034\007\032\t\007!\003\002\004:\r3\021\rA\005\003\007y\031e!\031\001\n\005\r}2IB1\001\023\t\031\021e\021\004b\001%\0211QI\"\007C\002I!a\001\023D\r\005\004\021BAB&\007\032\t\007!\003\002\004O\r3\021\rA\005\003\007#\032e!\031\001\n\005\rQ3IB1\001\023\t\0319f\021\004b\001%!Ia\021\013\001\022\002\023\005a1K\001\020G>\004\030\020\n3fM\006,H\016\036\0232sUqcQ\013D-\r72iFb\030\007b\031\rdQ\rD4\rS2YG\"\034\007p\031Ed1\017D;\ro2IHb\037\007~\031}d\021\021DB+\t19FK\002M\005w\"a!\005D(\005\004\021BAB\016\007P\t\007!\003\002\004\037\r\037\022\rA\005\003\007C\031=#\031\001\n\005\r\0212yE1\001\023\t\0319cq\nb\001%\0211!Fb\024C\002I!a!\fD(\005\004\021BA\002\031\007P\t\007!\003\002\0044\r\037\022\rA\005\003\007m\031=#\031\001\n\005\re2yE1\001\023\t\031adq\nb\001%\0211qHb\024C\002I!aA\021D(\005\004\021BAB#\007P\t\007!\003\002\004I\r\037\022\rA\005\003\007\027\032=#\031\001\n\005\r93yE1\001\023\t\031\tfq\nb\001%\0211AKb\024C\002I!aa\026D(\005\004\021\002\"\003DD\001E\005I\021\001DE\003=\031w\016]=%I\0264\027-\0367uII\002TC\fDF\r\0373\tJb%\007\026\032]e\021\024DN\r;3yJ\")\007$\032\025fq\025DU\rW3iKb,\0072\032MfQ\027D\\\rs+\"A\"$+\007=\023Y\b\002\004\022\r\013\023\rA\005\003\0077\031\025%\031\001\n\005\ry1)I1\001\023\t\031\tcQ\021b\001%\0211AE\"\"C\002I!aa\nDC\005\004\021BA\002\026\007\006\n\007!\003\002\004.\r\013\023\rA\005\003\007a\031\025%\031\001\n\005\rM2)I1\001\023\t\0311dQ\021b\001%\0211\021H\"\"C\002I!a\001\020DC\005\004\021BAB \007\006\n\007!\003\002\004C\r\013\023\rA\005\003\007\013\032\025%\031\001\n\005\r!3)I1\001\023\t\031YeQ\021b\001%\0211aJ\"\"C\002I!a!\025DC\005\004\021BA\002+\007\006\n\007!\003\002\004X\r\013\023\rA\005\005\n\r{\003\021\023!C\001\r\013qbY8qs\022\"WMZ1vYR$#'M\013/\r\0034)Mb2\007J\032-gQ\032Dh\r#4\031N\"6\007X\032eg1\034Do\r?4\tOb9\007f\032\035h\021\036Dv\r[4y/\006\002\007D*\032!Ka\037\005\rE1YL1\001\023\t\031Yb1\030b\001%\0211aDb/C\002I!a!\tD^\005\004\021BA\002\023\007<\n\007!\003\002\004(\rw\023\rA\005\003\007U\031m&\031\001\n\005\r52YL1\001\023\t\031\001d1\030b\001%\02111Gb/C\002I!aA\016D^\005\004\021BAB\035\007<\n\007!\003\002\004=\rw\023\rA\005\003\007\031m&\031\001\n\005\r\t3YL1\001\023\t\031)e1\030b\001%\0211\001Jb/C\002I!aa\023D^\005\004\021BA\002(\007<\n\007!\003\002\004R\rw\023\rA\005\003\007)\032m&\031\001\n\005\r]3YL1\001\023\021%1\031\020AI\001\n\0031)0A\bd_BLH\005Z3gCVdG\017\n\0323+929Pb?\007~\032}x\021AD\002\017\01399a\"\003\b\f\0355qqBD\t\017'9)bb\006\b\032\035mqQDD\020\017C9\031c\"\n\026\005\031e(fA+\003|\0211\021C\"=C\002I!aa\007Dy\005\004\021BA\002\020\007r\n\007!\003\002\004\"\rc\024\rA\005\003\007I\031E(\031\001\n\005\r\0352\tP1\001\023\t\031Qc\021\037b\001%\0211QF\"=C\002I!a\001\rDy\005\004\021BAB\032\007r\n\007!\003\002\0047\rc\024\rA\005\003\007s\031E(\031\001\n\005\rq2\tP1\001\023\t\031yd\021\037b\001%\0211!I\"=C\002I!a!\022Dy\005\004\021BA\002%\007r\n\007!\003\002\004L\rc\024\rA\005\003\007\035\032E(\031\001\n\005\rE3\tP1\001\023\t\031!f\021\037b\001%\0211qK\"=C\002IA\021b\"\013\001\003\003%\teb\013\002\033A\024x\016Z;diB\023XMZ5y+\t\t\031\016C\005\b0\001\t\t\021\"\021\b2\005y\001O]8ek\016$\030\n^3sCR|'/\006\002\b4A)qQGD\036-5\021qq\007\006\004\017s\021\021AC2pY2,7\r^5p]&!qQHD\034\005!IE/\032:bi>\024\b\"CD!\001\005\005I\021AD\"\003!\031\027M\\#rk\006dG\003BD#\017\027\0022\001CD$\023\r9IE\001\002\b\005>|G.Z1o\021%9ieb\020\002\002\003\007a#A\002yIEB\021b\"\025\001\003\003%\teb\025\002\021!\f7\017[\"pI\026$\"a\"\026\021\007!99&C\002\bZ\t\0211!\0238u\021%9i\006AA\001\n\003:y&\001\004fcV\fGn\035\013\005\017\013:\t\007C\005\bN\035m\023\021!a\001-\035IqQ\r\002\002\002#\005qqM\001\b)V\004H.\032\0323!\rAq\021\016\004\t\003\t\t\t\021#\001\blM!q\021N\004\\\021!\tYj\"\033\005\002\035=DCAD4\021)\tym\"\033\002\002\023\025\023\021\033\005\013\017k:I'!A\005\002\036]\024!B1qa2LXCLD=\017:\031ib\"\b\f\036=u1SDL\0177;yjb)\b(\036-vqVDZ\017o;Ylb0\bD\036\035w1ZDh\017'$bfb\037\bV\036]w\021\\Dn\017;<yn\"9\bd\036\025xq]Du\017W<iob<\br\036MxQ_D|\017s<Yp\"@\b\000Bq\003\002AD?\017\003;)i\"#\b\016\036EuQSDM\017;;\tk\"*\b*\0365v\021WD[\017s;il\"1\bF\036%wQZDi!\ryqq\020\003\007#\035M$\031\001\n\021\007=9\031\t\002\004\034\017g\022\rA\005\t\004\037\035\035EA\002\020\bt\t\007!\003E\002\020\017\027#a!ID:\005\004\021\002cA\b\b\020\0221Aeb\035C\002I\0012aDDJ\t\0319s1\017b\001%A\031qbb&\005\r):\031H1\001\023!\ryq1\024\003\007[\035M$\031\001\n\021\007=9y\n\002\0041\017g\022\rA\005\t\004\037\035\rFAB\032\bt\t\007!\003E\002\020\017O#aAND:\005\004\021\002cA\b\b,\0221\021hb\035C\002I\0012aDDX\t\031at1\017b\001%A\031qbb-\005\r}:\031H1\001\023!\ryqq\027\003\007\005\036M$\031\001\n\021\007=9Y\f\002\004F\017g\022\rA\005\t\004\037\035}FA\002%\bt\t\007!\003E\002\020\017\007$aaSD:\005\004\021\002cA\b\bH\0221ajb\035C\002I\0012aDDf\t\031\tv1\017b\001%A\031qbb4\005\rQ;\031H1\001\023!\ryq1\033\003\007/\036M$\031\001\n\t\017};\031\b1\001\b~!9Amb\035A\002\035\005\005bB5\bt\001\007qQ\021\005\b]\036M\004\031ADE\021\035\031x1\017a\001\017\033Cq\001_D:\001\0049\t\nC\004~\017g\002\ra\"&\t\021\005\025q1\017a\001\0173C\001\"a\004\bt\001\007qQ\024\005\t\00339\031\b1\001\b\"\"A\0211ED:\001\0049)\013\003\005\002.\035M\004\031ADU\021!\t9db\035A\002\0355\006\002CA!\017g\002\ra\"-\t\021\005-s1\017a\001\017kC\001\"!\026\bt\001\007q\021\030\005\t\003?:\031\b1\001\b>\"A\021\021ND:\001\0049\t\r\003\005\002t\035M\004\031ADc\021!\tihb\035A\002\035%\007\002CAD\017g\002\ra\"4\t\021\005Eu1\017a\001\017#D!\002c\001\bj\005\005I\021\021E\003\003\035)h.\0319qYf,b\006c\002\t\024!]\0012\004E\020\021GA9\003c\013\t0!M\002r\007E\036\021A\031\005c\022\tL!=\0032\013E,\0217By\006c\031\thQ!\001\022\002E5!\025A\0012\002E\b\023\rAiA\001\002\007\037B$\030n\0348\021]!\001\001\022\003E\013\0213Ai\002#\t\t&!%\002R\006E\031\021kAI\004#\020\tB!\025\003\022\nE'\021#B)\006#\027\t^!\005\004R\r\t\004\037!MAAB\t\t\002\t\007!\003E\002\020\021/!aa\007E\001\005\004\021\002cA\b\t\034\0211a\004#\001C\002I\0012a\004E\020\t\031\t\003\022\001b\001%A\031q\002c\t\005\r\021B\tA1\001\023!\ry\001r\005\003\007O!\005!\031\001\n\021\007=AY\003\002\004+\021\003\021\rA\005\t\004\037!=BAB\027\t\002\t\007!\003E\002\020\021g!a\001\rE\001\005\004\021\002cA\b\t8\02111\007#\001C\002I\0012a\004E\036\t\0311\004\022\001b\001%A\031q\002c\020\005\reB\tA1\001\023!\ry\0012\t\003\007y!\005!\031\001\n\021\007=A9\005\002\004@\021\003\021\rA\005\t\004\037!-CA\002\"\t\002\t\007!\003E\002\020\021\037\"a!\022E\001\005\004\021\002cA\b\tT\0211\001\n#\001C\002I\0012a\004E,\t\031Y\005\022\001b\001%A\031q\002c\027\005\r9C\tA1\001\023!\ry\001r\f\003\007#\"\005!\031\001\n\021\007=A\031\007\002\004U\021\003\021\rA\005\t\004\037!\035DAB,\t\002\t\007!\003\003\006\tl!\005\021\021!a\001\021\037\t1\001\037\0231\021)Ayg\"\033\002\002\023%\001\022O\001\fe\026\fGMU3t_24X\r\006\002\ttA!\021Q\033E;\023\021A9(a6\003\r=\023'.Z2u\001")
/*    */ public class Tuple22<T1, T2, T3, T4, T5, T6, T7, T8, T9, T10, T11, T12, T13, T14, T15, T16, T17, T18, T19, T20, T21, T22> implements Product22<T1, T2, T3, T4, T5, T6, T7, T8, T9, T10, T11, T12, T13, T14, T15, T16, T17, T18, T19, T20, T21, T22>, Product, Serializable {
/*    */   private final T1 _1;
/*    */   
/*    */   private final T2 _2;
/*    */   
/*    */   private final T3 _3;
/*    */   
/*    */   private final T4 _4;
/*    */   
/*    */   private final T5 _5;
/*    */   
/*    */   private final T6 _6;
/*    */   
/*    */   private final T7 _7;
/*    */   
/*    */   private final T8 _8;
/*    */   
/*    */   private final T9 _9;
/*    */   
/*    */   private final T10 _10;
/*    */   
/*    */   private final T11 _11;
/*    */   
/*    */   private final T12 _12;
/*    */   
/*    */   private final T13 _13;
/*    */   
/*    */   private final T14 _14;
/*    */   
/*    */   private final T15 _15;
/*    */   
/*    */   private final T16 _16;
/*    */   
/*    */   private final T17 _17;
/*    */   
/*    */   private final T18 _18;
/*    */   
/*    */   private final T19 _19;
/*    */   
/*    */   private final T20 _20;
/*    */   
/*    */   private final T21 _21;
/*    */   
/*    */   private final T22 _22;
/*    */   
/*    */   public int productArity() {
/* 39 */     return Product22$class.productArity(this);
/*    */   }
/*    */   
/*    */   public Object productElement(int n) throws IndexOutOfBoundsException {
/* 39 */     return Product22$class.productElement(this, n);
/*    */   }
/*    */   
/*    */   public T1 _1() {
/* 39 */     return this._1;
/*    */   }
/*    */   
/*    */   public T2 _2() {
/* 39 */     return this._2;
/*    */   }
/*    */   
/*    */   public T3 _3() {
/* 39 */     return this._3;
/*    */   }
/*    */   
/*    */   public T4 _4() {
/* 39 */     return this._4;
/*    */   }
/*    */   
/*    */   public T5 _5() {
/* 39 */     return this._5;
/*    */   }
/*    */   
/*    */   public T6 _6() {
/* 39 */     return this._6;
/*    */   }
/*    */   
/*    */   public T7 _7() {
/* 39 */     return this._7;
/*    */   }
/*    */   
/*    */   public T8 _8() {
/* 39 */     return this._8;
/*    */   }
/*    */   
/*    */   public T9 _9() {
/* 39 */     return this._9;
/*    */   }
/*    */   
/*    */   public T10 _10() {
/* 39 */     return this._10;
/*    */   }
/*    */   
/*    */   public T11 _11() {
/* 39 */     return this._11;
/*    */   }
/*    */   
/*    */   public T12 _12() {
/* 39 */     return this._12;
/*    */   }
/*    */   
/*    */   public T13 _13() {
/* 39 */     return this._13;
/*    */   }
/*    */   
/*    */   public T14 _14() {
/* 39 */     return this._14;
/*    */   }
/*    */   
/*    */   public T15 _15() {
/* 39 */     return this._15;
/*    */   }
/*    */   
/*    */   public T16 _16() {
/* 39 */     return this._16;
/*    */   }
/*    */   
/*    */   public T17 _17() {
/* 39 */     return this._17;
/*    */   }
/*    */   
/*    */   public T18 _18() {
/* 39 */     return this._18;
/*    */   }
/*    */   
/*    */   public T19 _19() {
/* 39 */     return this._19;
/*    */   }
/*    */   
/*    */   public T20 _20() {
/* 39 */     return this._20;
/*    */   }
/*    */   
/*    */   public T21 _21() {
/* 39 */     return this._21;
/*    */   }
/*    */   
/*    */   public T22 _22() {
/* 39 */     return this._22;
/*    */   }
/*    */   
/*    */   public <T1, T2, T3, T4, T5, T6, T7, T8, T9, T10, T11, T12, T13, T14, T15, T16, T17, T18, T19, T20, T21, T22> Tuple22<T1, T2, T3, T4, T5, T6, T7, T8, T9, T10, T11, T12, T13, T14, T15, T16, T17, T18, T19, T20, T21, T22> copy(Object _1, Object _2, Object _3, Object _4, Object _5, Object _6, Object _7, Object _8, Object _9, Object _10, Object _11, Object _12, Object _13, Object _14, Object _15, Object _16, Object _17, Object _18, Object _19, Object _20, Object _21, Object _22) {
/* 39 */     return new Tuple22((T1)_1, (T2)_2, (T3)_3, (T4)_4, (T5)_5, (T6)_6, (T7)_7, (T8)_8, (T9)_9, (T10)_10, (T11)_11, (T12)_12, (T13)_13, (T14)_14, (T15)_15, (T16)_16, (T17)_17, (T18)_18, (T19)_19, (T20)_20, (T21)_21, (T22)_22);
/*    */   }
/*    */   
/*    */   public <T1, T2, T3, T4, T5, T6, T7, T8, T9, T10, T11, T12, T13, T14, T15, T16, T17, T18, T19, T20, T21, T22> T1 copy$default$1() {
/* 39 */     return _1();
/*    */   }
/*    */   
/*    */   public <T1, T2, T3, T4, T5, T6, T7, T8, T9, T10, T11, T12, T13, T14, T15, T16, T17, T18, T19, T20, T21, T22> T2 copy$default$2() {
/* 39 */     return _2();
/*    */   }
/*    */   
/*    */   public <T1, T2, T3, T4, T5, T6, T7, T8, T9, T10, T11, T12, T13, T14, T15, T16, T17, T18, T19, T20, T21, T22> T3 copy$default$3() {
/* 39 */     return _3();
/*    */   }
/*    */   
/*    */   public <T1, T2, T3, T4, T5, T6, T7, T8, T9, T10, T11, T12, T13, T14, T15, T16, T17, T18, T19, T20, T21, T22> T4 copy$default$4() {
/* 39 */     return _4();
/*    */   }
/*    */   
/*    */   public <T1, T2, T3, T4, T5, T6, T7, T8, T9, T10, T11, T12, T13, T14, T15, T16, T17, T18, T19, T20, T21, T22> T5 copy$default$5() {
/* 39 */     return _5();
/*    */   }
/*    */   
/*    */   public <T1, T2, T3, T4, T5, T6, T7, T8, T9, T10, T11, T12, T13, T14, T15, T16, T17, T18, T19, T20, T21, T22> T6 copy$default$6() {
/* 39 */     return _6();
/*    */   }
/*    */   
/*    */   public <T1, T2, T3, T4, T5, T6, T7, T8, T9, T10, T11, T12, T13, T14, T15, T16, T17, T18, T19, T20, T21, T22> T7 copy$default$7() {
/* 39 */     return _7();
/*    */   }
/*    */   
/*    */   public <T1, T2, T3, T4, T5, T6, T7, T8, T9, T10, T11, T12, T13, T14, T15, T16, T17, T18, T19, T20, T21, T22> T8 copy$default$8() {
/* 39 */     return _8();
/*    */   }
/*    */   
/*    */   public <T1, T2, T3, T4, T5, T6, T7, T8, T9, T10, T11, T12, T13, T14, T15, T16, T17, T18, T19, T20, T21, T22> T9 copy$default$9() {
/* 39 */     return _9();
/*    */   }
/*    */   
/*    */   public <T1, T2, T3, T4, T5, T6, T7, T8, T9, T10, T11, T12, T13, T14, T15, T16, T17, T18, T19, T20, T21, T22> T10 copy$default$10() {
/* 39 */     return _10();
/*    */   }
/*    */   
/*    */   public <T1, T2, T3, T4, T5, T6, T7, T8, T9, T10, T11, T12, T13, T14, T15, T16, T17, T18, T19, T20, T21, T22> T11 copy$default$11() {
/* 39 */     return _11();
/*    */   }
/*    */   
/*    */   public <T1, T2, T3, T4, T5, T6, T7, T8, T9, T10, T11, T12, T13, T14, T15, T16, T17, T18, T19, T20, T21, T22> T12 copy$default$12() {
/* 39 */     return _12();
/*    */   }
/*    */   
/*    */   public <T1, T2, T3, T4, T5, T6, T7, T8, T9, T10, T11, T12, T13, T14, T15, T16, T17, T18, T19, T20, T21, T22> T13 copy$default$13() {
/* 39 */     return _13();
/*    */   }
/*    */   
/*    */   public <T1, T2, T3, T4, T5, T6, T7, T8, T9, T10, T11, T12, T13, T14, T15, T16, T17, T18, T19, T20, T21, T22> T14 copy$default$14() {
/* 39 */     return _14();
/*    */   }
/*    */   
/*    */   public <T1, T2, T3, T4, T5, T6, T7, T8, T9, T10, T11, T12, T13, T14, T15, T16, T17, T18, T19, T20, T21, T22> T15 copy$default$15() {
/* 39 */     return _15();
/*    */   }
/*    */   
/*    */   public <T1, T2, T3, T4, T5, T6, T7, T8, T9, T10, T11, T12, T13, T14, T15, T16, T17, T18, T19, T20, T21, T22> T16 copy$default$16() {
/* 39 */     return _16();
/*    */   }
/*    */   
/*    */   public <T1, T2, T3, T4, T5, T6, T7, T8, T9, T10, T11, T12, T13, T14, T15, T16, T17, T18, T19, T20, T21, T22> T17 copy$default$17() {
/* 39 */     return _17();
/*    */   }
/*    */   
/*    */   public <T1, T2, T3, T4, T5, T6, T7, T8, T9, T10, T11, T12, T13, T14, T15, T16, T17, T18, T19, T20, T21, T22> T18 copy$default$18() {
/* 39 */     return _18();
/*    */   }
/*    */   
/*    */   public <T1, T2, T3, T4, T5, T6, T7, T8, T9, T10, T11, T12, T13, T14, T15, T16, T17, T18, T19, T20, T21, T22> T19 copy$default$19() {
/* 39 */     return _19();
/*    */   }
/*    */   
/*    */   public <T1, T2, T3, T4, T5, T6, T7, T8, T9, T10, T11, T12, T13, T14, T15, T16, T17, T18, T19, T20, T21, T22> T20 copy$default$20() {
/* 39 */     return _20();
/*    */   }
/*    */   
/*    */   public <T1, T2, T3, T4, T5, T6, T7, T8, T9, T10, T11, T12, T13, T14, T15, T16, T17, T18, T19, T20, T21, T22> T21 copy$default$21() {
/* 39 */     return _21();
/*    */   }
/*    */   
/*    */   public <T1, T2, T3, T4, T5, T6, T7, T8, T9, T10, T11, T12, T13, T14, T15, T16, T17, T18, T19, T20, T21, T22> T22 copy$default$22() {
/* 39 */     return _22();
/*    */   }
/*    */   
/*    */   public String productPrefix() {
/* 39 */     return "Tuple22";
/*    */   }
/*    */   
/*    */   public Iterator<Object> productIterator() {
/* 39 */     return ScalaRunTime$.MODULE$.typedProductIterator(this);
/*    */   }
/*    */   
/*    */   public boolean canEqual(Object x$1) {
/* 39 */     return x$1 instanceof Tuple22;
/*    */   }
/*    */   
/*    */   public int hashCode() {
/* 39 */     return ScalaRunTime$.MODULE$._hashCode(this);
/*    */   }
/*    */   
/*    */   public boolean equals(Object x$1) {
/*    */     // Byte code:
/*    */     //   0: aload_0
/*    */     //   1: aload_1
/*    */     //   2: if_acmpeq -> 1887
/*    */     //   5: aload_1
/*    */     //   6: instanceof scala/Tuple22
/*    */     //   9: ifeq -> 17
/*    */     //   12: iconst_1
/*    */     //   13: istore_2
/*    */     //   14: goto -> 19
/*    */     //   17: iconst_0
/*    */     //   18: istore_2
/*    */     //   19: iload_2
/*    */     //   20: ifeq -> 1891
/*    */     //   23: aload_1
/*    */     //   24: checkcast scala/Tuple22
/*    */     //   27: astore #47
/*    */     //   29: aload_0
/*    */     //   30: invokevirtual _1 : ()Ljava/lang/Object;
/*    */     //   33: aload #47
/*    */     //   35: invokevirtual _1 : ()Ljava/lang/Object;
/*    */     //   38: astore #4
/*    */     //   40: dup
/*    */     //   41: astore_3
/*    */     //   42: aload #4
/*    */     //   44: if_acmpne -> 51
/*    */     //   47: iconst_1
/*    */     //   48: goto -> 103
/*    */     //   51: aload_3
/*    */     //   52: ifnonnull -> 59
/*    */     //   55: iconst_0
/*    */     //   56: goto -> 103
/*    */     //   59: aload_3
/*    */     //   60: instanceof java/lang/Number
/*    */     //   63: ifeq -> 78
/*    */     //   66: aload_3
/*    */     //   67: checkcast java/lang/Number
/*    */     //   70: aload #4
/*    */     //   72: invokestatic equalsNumObject : (Ljava/lang/Number;Ljava/lang/Object;)Z
/*    */     //   75: goto -> 103
/*    */     //   78: aload_3
/*    */     //   79: instanceof java/lang/Character
/*    */     //   82: ifeq -> 97
/*    */     //   85: aload_3
/*    */     //   86: checkcast java/lang/Character
/*    */     //   89: aload #4
/*    */     //   91: invokestatic equalsCharObject : (Ljava/lang/Character;Ljava/lang/Object;)Z
/*    */     //   94: goto -> 103
/*    */     //   97: aload_3
/*    */     //   98: aload #4
/*    */     //   100: invokevirtual equals : (Ljava/lang/Object;)Z
/*    */     //   103: ifeq -> 1883
/*    */     //   106: aload_0
/*    */     //   107: invokevirtual _2 : ()Ljava/lang/Object;
/*    */     //   110: aload #47
/*    */     //   112: invokevirtual _2 : ()Ljava/lang/Object;
/*    */     //   115: astore #6
/*    */     //   117: dup
/*    */     //   118: astore #5
/*    */     //   120: aload #6
/*    */     //   122: if_acmpne -> 129
/*    */     //   125: iconst_1
/*    */     //   126: goto -> 187
/*    */     //   129: aload #5
/*    */     //   131: ifnonnull -> 138
/*    */     //   134: iconst_0
/*    */     //   135: goto -> 187
/*    */     //   138: aload #5
/*    */     //   140: instanceof java/lang/Number
/*    */     //   143: ifeq -> 159
/*    */     //   146: aload #5
/*    */     //   148: checkcast java/lang/Number
/*    */     //   151: aload #6
/*    */     //   153: invokestatic equalsNumObject : (Ljava/lang/Number;Ljava/lang/Object;)Z
/*    */     //   156: goto -> 187
/*    */     //   159: aload #5
/*    */     //   161: instanceof java/lang/Character
/*    */     //   164: ifeq -> 180
/*    */     //   167: aload #5
/*    */     //   169: checkcast java/lang/Character
/*    */     //   172: aload #6
/*    */     //   174: invokestatic equalsCharObject : (Ljava/lang/Character;Ljava/lang/Object;)Z
/*    */     //   177: goto -> 187
/*    */     //   180: aload #5
/*    */     //   182: aload #6
/*    */     //   184: invokevirtual equals : (Ljava/lang/Object;)Z
/*    */     //   187: ifeq -> 1883
/*    */     //   190: aload_0
/*    */     //   191: invokevirtual _3 : ()Ljava/lang/Object;
/*    */     //   194: aload #47
/*    */     //   196: invokevirtual _3 : ()Ljava/lang/Object;
/*    */     //   199: astore #8
/*    */     //   201: dup
/*    */     //   202: astore #7
/*    */     //   204: aload #8
/*    */     //   206: if_acmpne -> 213
/*    */     //   209: iconst_1
/*    */     //   210: goto -> 271
/*    */     //   213: aload #7
/*    */     //   215: ifnonnull -> 222
/*    */     //   218: iconst_0
/*    */     //   219: goto -> 271
/*    */     //   222: aload #7
/*    */     //   224: instanceof java/lang/Number
/*    */     //   227: ifeq -> 243
/*    */     //   230: aload #7
/*    */     //   232: checkcast java/lang/Number
/*    */     //   235: aload #8
/*    */     //   237: invokestatic equalsNumObject : (Ljava/lang/Number;Ljava/lang/Object;)Z
/*    */     //   240: goto -> 271
/*    */     //   243: aload #7
/*    */     //   245: instanceof java/lang/Character
/*    */     //   248: ifeq -> 264
/*    */     //   251: aload #7
/*    */     //   253: checkcast java/lang/Character
/*    */     //   256: aload #8
/*    */     //   258: invokestatic equalsCharObject : (Ljava/lang/Character;Ljava/lang/Object;)Z
/*    */     //   261: goto -> 271
/*    */     //   264: aload #7
/*    */     //   266: aload #8
/*    */     //   268: invokevirtual equals : (Ljava/lang/Object;)Z
/*    */     //   271: ifeq -> 1883
/*    */     //   274: aload_0
/*    */     //   275: invokevirtual _4 : ()Ljava/lang/Object;
/*    */     //   278: aload #47
/*    */     //   280: invokevirtual _4 : ()Ljava/lang/Object;
/*    */     //   283: astore #10
/*    */     //   285: dup
/*    */     //   286: astore #9
/*    */     //   288: aload #10
/*    */     //   290: if_acmpne -> 297
/*    */     //   293: iconst_1
/*    */     //   294: goto -> 355
/*    */     //   297: aload #9
/*    */     //   299: ifnonnull -> 306
/*    */     //   302: iconst_0
/*    */     //   303: goto -> 355
/*    */     //   306: aload #9
/*    */     //   308: instanceof java/lang/Number
/*    */     //   311: ifeq -> 327
/*    */     //   314: aload #9
/*    */     //   316: checkcast java/lang/Number
/*    */     //   319: aload #10
/*    */     //   321: invokestatic equalsNumObject : (Ljava/lang/Number;Ljava/lang/Object;)Z
/*    */     //   324: goto -> 355
/*    */     //   327: aload #9
/*    */     //   329: instanceof java/lang/Character
/*    */     //   332: ifeq -> 348
/*    */     //   335: aload #9
/*    */     //   337: checkcast java/lang/Character
/*    */     //   340: aload #10
/*    */     //   342: invokestatic equalsCharObject : (Ljava/lang/Character;Ljava/lang/Object;)Z
/*    */     //   345: goto -> 355
/*    */     //   348: aload #9
/*    */     //   350: aload #10
/*    */     //   352: invokevirtual equals : (Ljava/lang/Object;)Z
/*    */     //   355: ifeq -> 1883
/*    */     //   358: aload_0
/*    */     //   359: invokevirtual _5 : ()Ljava/lang/Object;
/*    */     //   362: aload #47
/*    */     //   364: invokevirtual _5 : ()Ljava/lang/Object;
/*    */     //   367: astore #12
/*    */     //   369: dup
/*    */     //   370: astore #11
/*    */     //   372: aload #12
/*    */     //   374: if_acmpne -> 381
/*    */     //   377: iconst_1
/*    */     //   378: goto -> 439
/*    */     //   381: aload #11
/*    */     //   383: ifnonnull -> 390
/*    */     //   386: iconst_0
/*    */     //   387: goto -> 439
/*    */     //   390: aload #11
/*    */     //   392: instanceof java/lang/Number
/*    */     //   395: ifeq -> 411
/*    */     //   398: aload #11
/*    */     //   400: checkcast java/lang/Number
/*    */     //   403: aload #12
/*    */     //   405: invokestatic equalsNumObject : (Ljava/lang/Number;Ljava/lang/Object;)Z
/*    */     //   408: goto -> 439
/*    */     //   411: aload #11
/*    */     //   413: instanceof java/lang/Character
/*    */     //   416: ifeq -> 432
/*    */     //   419: aload #11
/*    */     //   421: checkcast java/lang/Character
/*    */     //   424: aload #12
/*    */     //   426: invokestatic equalsCharObject : (Ljava/lang/Character;Ljava/lang/Object;)Z
/*    */     //   429: goto -> 439
/*    */     //   432: aload #11
/*    */     //   434: aload #12
/*    */     //   436: invokevirtual equals : (Ljava/lang/Object;)Z
/*    */     //   439: ifeq -> 1883
/*    */     //   442: aload_0
/*    */     //   443: invokevirtual _6 : ()Ljava/lang/Object;
/*    */     //   446: aload #47
/*    */     //   448: invokevirtual _6 : ()Ljava/lang/Object;
/*    */     //   451: astore #14
/*    */     //   453: dup
/*    */     //   454: astore #13
/*    */     //   456: aload #14
/*    */     //   458: if_acmpne -> 465
/*    */     //   461: iconst_1
/*    */     //   462: goto -> 523
/*    */     //   465: aload #13
/*    */     //   467: ifnonnull -> 474
/*    */     //   470: iconst_0
/*    */     //   471: goto -> 523
/*    */     //   474: aload #13
/*    */     //   476: instanceof java/lang/Number
/*    */     //   479: ifeq -> 495
/*    */     //   482: aload #13
/*    */     //   484: checkcast java/lang/Number
/*    */     //   487: aload #14
/*    */     //   489: invokestatic equalsNumObject : (Ljava/lang/Number;Ljava/lang/Object;)Z
/*    */     //   492: goto -> 523
/*    */     //   495: aload #13
/*    */     //   497: instanceof java/lang/Character
/*    */     //   500: ifeq -> 516
/*    */     //   503: aload #13
/*    */     //   505: checkcast java/lang/Character
/*    */     //   508: aload #14
/*    */     //   510: invokestatic equalsCharObject : (Ljava/lang/Character;Ljava/lang/Object;)Z
/*    */     //   513: goto -> 523
/*    */     //   516: aload #13
/*    */     //   518: aload #14
/*    */     //   520: invokevirtual equals : (Ljava/lang/Object;)Z
/*    */     //   523: ifeq -> 1883
/*    */     //   526: aload_0
/*    */     //   527: invokevirtual _7 : ()Ljava/lang/Object;
/*    */     //   530: aload #47
/*    */     //   532: invokevirtual _7 : ()Ljava/lang/Object;
/*    */     //   535: astore #16
/*    */     //   537: dup
/*    */     //   538: astore #15
/*    */     //   540: aload #16
/*    */     //   542: if_acmpne -> 549
/*    */     //   545: iconst_1
/*    */     //   546: goto -> 607
/*    */     //   549: aload #15
/*    */     //   551: ifnonnull -> 558
/*    */     //   554: iconst_0
/*    */     //   555: goto -> 607
/*    */     //   558: aload #15
/*    */     //   560: instanceof java/lang/Number
/*    */     //   563: ifeq -> 579
/*    */     //   566: aload #15
/*    */     //   568: checkcast java/lang/Number
/*    */     //   571: aload #16
/*    */     //   573: invokestatic equalsNumObject : (Ljava/lang/Number;Ljava/lang/Object;)Z
/*    */     //   576: goto -> 607
/*    */     //   579: aload #15
/*    */     //   581: instanceof java/lang/Character
/*    */     //   584: ifeq -> 600
/*    */     //   587: aload #15
/*    */     //   589: checkcast java/lang/Character
/*    */     //   592: aload #16
/*    */     //   594: invokestatic equalsCharObject : (Ljava/lang/Character;Ljava/lang/Object;)Z
/*    */     //   597: goto -> 607
/*    */     //   600: aload #15
/*    */     //   602: aload #16
/*    */     //   604: invokevirtual equals : (Ljava/lang/Object;)Z
/*    */     //   607: ifeq -> 1883
/*    */     //   610: aload_0
/*    */     //   611: invokevirtual _8 : ()Ljava/lang/Object;
/*    */     //   614: aload #47
/*    */     //   616: invokevirtual _8 : ()Ljava/lang/Object;
/*    */     //   619: astore #18
/*    */     //   621: dup
/*    */     //   622: astore #17
/*    */     //   624: aload #18
/*    */     //   626: if_acmpne -> 633
/*    */     //   629: iconst_1
/*    */     //   630: goto -> 691
/*    */     //   633: aload #17
/*    */     //   635: ifnonnull -> 642
/*    */     //   638: iconst_0
/*    */     //   639: goto -> 691
/*    */     //   642: aload #17
/*    */     //   644: instanceof java/lang/Number
/*    */     //   647: ifeq -> 663
/*    */     //   650: aload #17
/*    */     //   652: checkcast java/lang/Number
/*    */     //   655: aload #18
/*    */     //   657: invokestatic equalsNumObject : (Ljava/lang/Number;Ljava/lang/Object;)Z
/*    */     //   660: goto -> 691
/*    */     //   663: aload #17
/*    */     //   665: instanceof java/lang/Character
/*    */     //   668: ifeq -> 684
/*    */     //   671: aload #17
/*    */     //   673: checkcast java/lang/Character
/*    */     //   676: aload #18
/*    */     //   678: invokestatic equalsCharObject : (Ljava/lang/Character;Ljava/lang/Object;)Z
/*    */     //   681: goto -> 691
/*    */     //   684: aload #17
/*    */     //   686: aload #18
/*    */     //   688: invokevirtual equals : (Ljava/lang/Object;)Z
/*    */     //   691: ifeq -> 1883
/*    */     //   694: aload_0
/*    */     //   695: invokevirtual _9 : ()Ljava/lang/Object;
/*    */     //   698: aload #47
/*    */     //   700: invokevirtual _9 : ()Ljava/lang/Object;
/*    */     //   703: astore #20
/*    */     //   705: dup
/*    */     //   706: astore #19
/*    */     //   708: aload #20
/*    */     //   710: if_acmpne -> 717
/*    */     //   713: iconst_1
/*    */     //   714: goto -> 775
/*    */     //   717: aload #19
/*    */     //   719: ifnonnull -> 726
/*    */     //   722: iconst_0
/*    */     //   723: goto -> 775
/*    */     //   726: aload #19
/*    */     //   728: instanceof java/lang/Number
/*    */     //   731: ifeq -> 747
/*    */     //   734: aload #19
/*    */     //   736: checkcast java/lang/Number
/*    */     //   739: aload #20
/*    */     //   741: invokestatic equalsNumObject : (Ljava/lang/Number;Ljava/lang/Object;)Z
/*    */     //   744: goto -> 775
/*    */     //   747: aload #19
/*    */     //   749: instanceof java/lang/Character
/*    */     //   752: ifeq -> 768
/*    */     //   755: aload #19
/*    */     //   757: checkcast java/lang/Character
/*    */     //   760: aload #20
/*    */     //   762: invokestatic equalsCharObject : (Ljava/lang/Character;Ljava/lang/Object;)Z
/*    */     //   765: goto -> 775
/*    */     //   768: aload #19
/*    */     //   770: aload #20
/*    */     //   772: invokevirtual equals : (Ljava/lang/Object;)Z
/*    */     //   775: ifeq -> 1883
/*    */     //   778: aload_0
/*    */     //   779: invokevirtual _10 : ()Ljava/lang/Object;
/*    */     //   782: aload #47
/*    */     //   784: invokevirtual _10 : ()Ljava/lang/Object;
/*    */     //   787: astore #22
/*    */     //   789: dup
/*    */     //   790: astore #21
/*    */     //   792: aload #22
/*    */     //   794: if_acmpne -> 801
/*    */     //   797: iconst_1
/*    */     //   798: goto -> 859
/*    */     //   801: aload #21
/*    */     //   803: ifnonnull -> 810
/*    */     //   806: iconst_0
/*    */     //   807: goto -> 859
/*    */     //   810: aload #21
/*    */     //   812: instanceof java/lang/Number
/*    */     //   815: ifeq -> 831
/*    */     //   818: aload #21
/*    */     //   820: checkcast java/lang/Number
/*    */     //   823: aload #22
/*    */     //   825: invokestatic equalsNumObject : (Ljava/lang/Number;Ljava/lang/Object;)Z
/*    */     //   828: goto -> 859
/*    */     //   831: aload #21
/*    */     //   833: instanceof java/lang/Character
/*    */     //   836: ifeq -> 852
/*    */     //   839: aload #21
/*    */     //   841: checkcast java/lang/Character
/*    */     //   844: aload #22
/*    */     //   846: invokestatic equalsCharObject : (Ljava/lang/Character;Ljava/lang/Object;)Z
/*    */     //   849: goto -> 859
/*    */     //   852: aload #21
/*    */     //   854: aload #22
/*    */     //   856: invokevirtual equals : (Ljava/lang/Object;)Z
/*    */     //   859: ifeq -> 1883
/*    */     //   862: aload_0
/*    */     //   863: invokevirtual _11 : ()Ljava/lang/Object;
/*    */     //   866: aload #47
/*    */     //   868: invokevirtual _11 : ()Ljava/lang/Object;
/*    */     //   871: astore #24
/*    */     //   873: dup
/*    */     //   874: astore #23
/*    */     //   876: aload #24
/*    */     //   878: if_acmpne -> 885
/*    */     //   881: iconst_1
/*    */     //   882: goto -> 943
/*    */     //   885: aload #23
/*    */     //   887: ifnonnull -> 894
/*    */     //   890: iconst_0
/*    */     //   891: goto -> 943
/*    */     //   894: aload #23
/*    */     //   896: instanceof java/lang/Number
/*    */     //   899: ifeq -> 915
/*    */     //   902: aload #23
/*    */     //   904: checkcast java/lang/Number
/*    */     //   907: aload #24
/*    */     //   909: invokestatic equalsNumObject : (Ljava/lang/Number;Ljava/lang/Object;)Z
/*    */     //   912: goto -> 943
/*    */     //   915: aload #23
/*    */     //   917: instanceof java/lang/Character
/*    */     //   920: ifeq -> 936
/*    */     //   923: aload #23
/*    */     //   925: checkcast java/lang/Character
/*    */     //   928: aload #24
/*    */     //   930: invokestatic equalsCharObject : (Ljava/lang/Character;Ljava/lang/Object;)Z
/*    */     //   933: goto -> 943
/*    */     //   936: aload #23
/*    */     //   938: aload #24
/*    */     //   940: invokevirtual equals : (Ljava/lang/Object;)Z
/*    */     //   943: ifeq -> 1883
/*    */     //   946: aload_0
/*    */     //   947: invokevirtual _12 : ()Ljava/lang/Object;
/*    */     //   950: aload #47
/*    */     //   952: invokevirtual _12 : ()Ljava/lang/Object;
/*    */     //   955: astore #26
/*    */     //   957: dup
/*    */     //   958: astore #25
/*    */     //   960: aload #26
/*    */     //   962: if_acmpne -> 969
/*    */     //   965: iconst_1
/*    */     //   966: goto -> 1027
/*    */     //   969: aload #25
/*    */     //   971: ifnonnull -> 978
/*    */     //   974: iconst_0
/*    */     //   975: goto -> 1027
/*    */     //   978: aload #25
/*    */     //   980: instanceof java/lang/Number
/*    */     //   983: ifeq -> 999
/*    */     //   986: aload #25
/*    */     //   988: checkcast java/lang/Number
/*    */     //   991: aload #26
/*    */     //   993: invokestatic equalsNumObject : (Ljava/lang/Number;Ljava/lang/Object;)Z
/*    */     //   996: goto -> 1027
/*    */     //   999: aload #25
/*    */     //   1001: instanceof java/lang/Character
/*    */     //   1004: ifeq -> 1020
/*    */     //   1007: aload #25
/*    */     //   1009: checkcast java/lang/Character
/*    */     //   1012: aload #26
/*    */     //   1014: invokestatic equalsCharObject : (Ljava/lang/Character;Ljava/lang/Object;)Z
/*    */     //   1017: goto -> 1027
/*    */     //   1020: aload #25
/*    */     //   1022: aload #26
/*    */     //   1024: invokevirtual equals : (Ljava/lang/Object;)Z
/*    */     //   1027: ifeq -> 1883
/*    */     //   1030: aload_0
/*    */     //   1031: invokevirtual _13 : ()Ljava/lang/Object;
/*    */     //   1034: aload #47
/*    */     //   1036: invokevirtual _13 : ()Ljava/lang/Object;
/*    */     //   1039: astore #28
/*    */     //   1041: dup
/*    */     //   1042: astore #27
/*    */     //   1044: aload #28
/*    */     //   1046: if_acmpne -> 1053
/*    */     //   1049: iconst_1
/*    */     //   1050: goto -> 1111
/*    */     //   1053: aload #27
/*    */     //   1055: ifnonnull -> 1062
/*    */     //   1058: iconst_0
/*    */     //   1059: goto -> 1111
/*    */     //   1062: aload #27
/*    */     //   1064: instanceof java/lang/Number
/*    */     //   1067: ifeq -> 1083
/*    */     //   1070: aload #27
/*    */     //   1072: checkcast java/lang/Number
/*    */     //   1075: aload #28
/*    */     //   1077: invokestatic equalsNumObject : (Ljava/lang/Number;Ljava/lang/Object;)Z
/*    */     //   1080: goto -> 1111
/*    */     //   1083: aload #27
/*    */     //   1085: instanceof java/lang/Character
/*    */     //   1088: ifeq -> 1104
/*    */     //   1091: aload #27
/*    */     //   1093: checkcast java/lang/Character
/*    */     //   1096: aload #28
/*    */     //   1098: invokestatic equalsCharObject : (Ljava/lang/Character;Ljava/lang/Object;)Z
/*    */     //   1101: goto -> 1111
/*    */     //   1104: aload #27
/*    */     //   1106: aload #28
/*    */     //   1108: invokevirtual equals : (Ljava/lang/Object;)Z
/*    */     //   1111: ifeq -> 1883
/*    */     //   1114: aload_0
/*    */     //   1115: invokevirtual _14 : ()Ljava/lang/Object;
/*    */     //   1118: aload #47
/*    */     //   1120: invokevirtual _14 : ()Ljava/lang/Object;
/*    */     //   1123: astore #30
/*    */     //   1125: dup
/*    */     //   1126: astore #29
/*    */     //   1128: aload #30
/*    */     //   1130: if_acmpne -> 1137
/*    */     //   1133: iconst_1
/*    */     //   1134: goto -> 1195
/*    */     //   1137: aload #29
/*    */     //   1139: ifnonnull -> 1146
/*    */     //   1142: iconst_0
/*    */     //   1143: goto -> 1195
/*    */     //   1146: aload #29
/*    */     //   1148: instanceof java/lang/Number
/*    */     //   1151: ifeq -> 1167
/*    */     //   1154: aload #29
/*    */     //   1156: checkcast java/lang/Number
/*    */     //   1159: aload #30
/*    */     //   1161: invokestatic equalsNumObject : (Ljava/lang/Number;Ljava/lang/Object;)Z
/*    */     //   1164: goto -> 1195
/*    */     //   1167: aload #29
/*    */     //   1169: instanceof java/lang/Character
/*    */     //   1172: ifeq -> 1188
/*    */     //   1175: aload #29
/*    */     //   1177: checkcast java/lang/Character
/*    */     //   1180: aload #30
/*    */     //   1182: invokestatic equalsCharObject : (Ljava/lang/Character;Ljava/lang/Object;)Z
/*    */     //   1185: goto -> 1195
/*    */     //   1188: aload #29
/*    */     //   1190: aload #30
/*    */     //   1192: invokevirtual equals : (Ljava/lang/Object;)Z
/*    */     //   1195: ifeq -> 1883
/*    */     //   1198: aload_0
/*    */     //   1199: invokevirtual _15 : ()Ljava/lang/Object;
/*    */     //   1202: aload #47
/*    */     //   1204: invokevirtual _15 : ()Ljava/lang/Object;
/*    */     //   1207: astore #32
/*    */     //   1209: dup
/*    */     //   1210: astore #31
/*    */     //   1212: aload #32
/*    */     //   1214: if_acmpne -> 1221
/*    */     //   1217: iconst_1
/*    */     //   1218: goto -> 1279
/*    */     //   1221: aload #31
/*    */     //   1223: ifnonnull -> 1230
/*    */     //   1226: iconst_0
/*    */     //   1227: goto -> 1279
/*    */     //   1230: aload #31
/*    */     //   1232: instanceof java/lang/Number
/*    */     //   1235: ifeq -> 1251
/*    */     //   1238: aload #31
/*    */     //   1240: checkcast java/lang/Number
/*    */     //   1243: aload #32
/*    */     //   1245: invokestatic equalsNumObject : (Ljava/lang/Number;Ljava/lang/Object;)Z
/*    */     //   1248: goto -> 1279
/*    */     //   1251: aload #31
/*    */     //   1253: instanceof java/lang/Character
/*    */     //   1256: ifeq -> 1272
/*    */     //   1259: aload #31
/*    */     //   1261: checkcast java/lang/Character
/*    */     //   1264: aload #32
/*    */     //   1266: invokestatic equalsCharObject : (Ljava/lang/Character;Ljava/lang/Object;)Z
/*    */     //   1269: goto -> 1279
/*    */     //   1272: aload #31
/*    */     //   1274: aload #32
/*    */     //   1276: invokevirtual equals : (Ljava/lang/Object;)Z
/*    */     //   1279: ifeq -> 1883
/*    */     //   1282: aload_0
/*    */     //   1283: invokevirtual _16 : ()Ljava/lang/Object;
/*    */     //   1286: aload #47
/*    */     //   1288: invokevirtual _16 : ()Ljava/lang/Object;
/*    */     //   1291: astore #34
/*    */     //   1293: dup
/*    */     //   1294: astore #33
/*    */     //   1296: aload #34
/*    */     //   1298: if_acmpne -> 1305
/*    */     //   1301: iconst_1
/*    */     //   1302: goto -> 1363
/*    */     //   1305: aload #33
/*    */     //   1307: ifnonnull -> 1314
/*    */     //   1310: iconst_0
/*    */     //   1311: goto -> 1363
/*    */     //   1314: aload #33
/*    */     //   1316: instanceof java/lang/Number
/*    */     //   1319: ifeq -> 1335
/*    */     //   1322: aload #33
/*    */     //   1324: checkcast java/lang/Number
/*    */     //   1327: aload #34
/*    */     //   1329: invokestatic equalsNumObject : (Ljava/lang/Number;Ljava/lang/Object;)Z
/*    */     //   1332: goto -> 1363
/*    */     //   1335: aload #33
/*    */     //   1337: instanceof java/lang/Character
/*    */     //   1340: ifeq -> 1356
/*    */     //   1343: aload #33
/*    */     //   1345: checkcast java/lang/Character
/*    */     //   1348: aload #34
/*    */     //   1350: invokestatic equalsCharObject : (Ljava/lang/Character;Ljava/lang/Object;)Z
/*    */     //   1353: goto -> 1363
/*    */     //   1356: aload #33
/*    */     //   1358: aload #34
/*    */     //   1360: invokevirtual equals : (Ljava/lang/Object;)Z
/*    */     //   1363: ifeq -> 1883
/*    */     //   1366: aload_0
/*    */     //   1367: invokevirtual _17 : ()Ljava/lang/Object;
/*    */     //   1370: aload #47
/*    */     //   1372: invokevirtual _17 : ()Ljava/lang/Object;
/*    */     //   1375: astore #36
/*    */     //   1377: dup
/*    */     //   1378: astore #35
/*    */     //   1380: aload #36
/*    */     //   1382: if_acmpne -> 1389
/*    */     //   1385: iconst_1
/*    */     //   1386: goto -> 1447
/*    */     //   1389: aload #35
/*    */     //   1391: ifnonnull -> 1398
/*    */     //   1394: iconst_0
/*    */     //   1395: goto -> 1447
/*    */     //   1398: aload #35
/*    */     //   1400: instanceof java/lang/Number
/*    */     //   1403: ifeq -> 1419
/*    */     //   1406: aload #35
/*    */     //   1408: checkcast java/lang/Number
/*    */     //   1411: aload #36
/*    */     //   1413: invokestatic equalsNumObject : (Ljava/lang/Number;Ljava/lang/Object;)Z
/*    */     //   1416: goto -> 1447
/*    */     //   1419: aload #35
/*    */     //   1421: instanceof java/lang/Character
/*    */     //   1424: ifeq -> 1440
/*    */     //   1427: aload #35
/*    */     //   1429: checkcast java/lang/Character
/*    */     //   1432: aload #36
/*    */     //   1434: invokestatic equalsCharObject : (Ljava/lang/Character;Ljava/lang/Object;)Z
/*    */     //   1437: goto -> 1447
/*    */     //   1440: aload #35
/*    */     //   1442: aload #36
/*    */     //   1444: invokevirtual equals : (Ljava/lang/Object;)Z
/*    */     //   1447: ifeq -> 1883
/*    */     //   1450: aload_0
/*    */     //   1451: invokevirtual _18 : ()Ljava/lang/Object;
/*    */     //   1454: aload #47
/*    */     //   1456: invokevirtual _18 : ()Ljava/lang/Object;
/*    */     //   1459: astore #38
/*    */     //   1461: dup
/*    */     //   1462: astore #37
/*    */     //   1464: aload #38
/*    */     //   1466: if_acmpne -> 1473
/*    */     //   1469: iconst_1
/*    */     //   1470: goto -> 1531
/*    */     //   1473: aload #37
/*    */     //   1475: ifnonnull -> 1482
/*    */     //   1478: iconst_0
/*    */     //   1479: goto -> 1531
/*    */     //   1482: aload #37
/*    */     //   1484: instanceof java/lang/Number
/*    */     //   1487: ifeq -> 1503
/*    */     //   1490: aload #37
/*    */     //   1492: checkcast java/lang/Number
/*    */     //   1495: aload #38
/*    */     //   1497: invokestatic equalsNumObject : (Ljava/lang/Number;Ljava/lang/Object;)Z
/*    */     //   1500: goto -> 1531
/*    */     //   1503: aload #37
/*    */     //   1505: instanceof java/lang/Character
/*    */     //   1508: ifeq -> 1524
/*    */     //   1511: aload #37
/*    */     //   1513: checkcast java/lang/Character
/*    */     //   1516: aload #38
/*    */     //   1518: invokestatic equalsCharObject : (Ljava/lang/Character;Ljava/lang/Object;)Z
/*    */     //   1521: goto -> 1531
/*    */     //   1524: aload #37
/*    */     //   1526: aload #38
/*    */     //   1528: invokevirtual equals : (Ljava/lang/Object;)Z
/*    */     //   1531: ifeq -> 1883
/*    */     //   1534: aload_0
/*    */     //   1535: invokevirtual _19 : ()Ljava/lang/Object;
/*    */     //   1538: aload #47
/*    */     //   1540: invokevirtual _19 : ()Ljava/lang/Object;
/*    */     //   1543: astore #40
/*    */     //   1545: dup
/*    */     //   1546: astore #39
/*    */     //   1548: aload #40
/*    */     //   1550: if_acmpne -> 1557
/*    */     //   1553: iconst_1
/*    */     //   1554: goto -> 1615
/*    */     //   1557: aload #39
/*    */     //   1559: ifnonnull -> 1566
/*    */     //   1562: iconst_0
/*    */     //   1563: goto -> 1615
/*    */     //   1566: aload #39
/*    */     //   1568: instanceof java/lang/Number
/*    */     //   1571: ifeq -> 1587
/*    */     //   1574: aload #39
/*    */     //   1576: checkcast java/lang/Number
/*    */     //   1579: aload #40
/*    */     //   1581: invokestatic equalsNumObject : (Ljava/lang/Number;Ljava/lang/Object;)Z
/*    */     //   1584: goto -> 1615
/*    */     //   1587: aload #39
/*    */     //   1589: instanceof java/lang/Character
/*    */     //   1592: ifeq -> 1608
/*    */     //   1595: aload #39
/*    */     //   1597: checkcast java/lang/Character
/*    */     //   1600: aload #40
/*    */     //   1602: invokestatic equalsCharObject : (Ljava/lang/Character;Ljava/lang/Object;)Z
/*    */     //   1605: goto -> 1615
/*    */     //   1608: aload #39
/*    */     //   1610: aload #40
/*    */     //   1612: invokevirtual equals : (Ljava/lang/Object;)Z
/*    */     //   1615: ifeq -> 1883
/*    */     //   1618: aload_0
/*    */     //   1619: invokevirtual _20 : ()Ljava/lang/Object;
/*    */     //   1622: aload #47
/*    */     //   1624: invokevirtual _20 : ()Ljava/lang/Object;
/*    */     //   1627: astore #42
/*    */     //   1629: dup
/*    */     //   1630: astore #41
/*    */     //   1632: aload #42
/*    */     //   1634: if_acmpne -> 1641
/*    */     //   1637: iconst_1
/*    */     //   1638: goto -> 1699
/*    */     //   1641: aload #41
/*    */     //   1643: ifnonnull -> 1650
/*    */     //   1646: iconst_0
/*    */     //   1647: goto -> 1699
/*    */     //   1650: aload #41
/*    */     //   1652: instanceof java/lang/Number
/*    */     //   1655: ifeq -> 1671
/*    */     //   1658: aload #41
/*    */     //   1660: checkcast java/lang/Number
/*    */     //   1663: aload #42
/*    */     //   1665: invokestatic equalsNumObject : (Ljava/lang/Number;Ljava/lang/Object;)Z
/*    */     //   1668: goto -> 1699
/*    */     //   1671: aload #41
/*    */     //   1673: instanceof java/lang/Character
/*    */     //   1676: ifeq -> 1692
/*    */     //   1679: aload #41
/*    */     //   1681: checkcast java/lang/Character
/*    */     //   1684: aload #42
/*    */     //   1686: invokestatic equalsCharObject : (Ljava/lang/Character;Ljava/lang/Object;)Z
/*    */     //   1689: goto -> 1699
/*    */     //   1692: aload #41
/*    */     //   1694: aload #42
/*    */     //   1696: invokevirtual equals : (Ljava/lang/Object;)Z
/*    */     //   1699: ifeq -> 1883
/*    */     //   1702: aload_0
/*    */     //   1703: invokevirtual _21 : ()Ljava/lang/Object;
/*    */     //   1706: aload #47
/*    */     //   1708: invokevirtual _21 : ()Ljava/lang/Object;
/*    */     //   1711: astore #44
/*    */     //   1713: dup
/*    */     //   1714: astore #43
/*    */     //   1716: aload #44
/*    */     //   1718: if_acmpne -> 1725
/*    */     //   1721: iconst_1
/*    */     //   1722: goto -> 1783
/*    */     //   1725: aload #43
/*    */     //   1727: ifnonnull -> 1734
/*    */     //   1730: iconst_0
/*    */     //   1731: goto -> 1783
/*    */     //   1734: aload #43
/*    */     //   1736: instanceof java/lang/Number
/*    */     //   1739: ifeq -> 1755
/*    */     //   1742: aload #43
/*    */     //   1744: checkcast java/lang/Number
/*    */     //   1747: aload #44
/*    */     //   1749: invokestatic equalsNumObject : (Ljava/lang/Number;Ljava/lang/Object;)Z
/*    */     //   1752: goto -> 1783
/*    */     //   1755: aload #43
/*    */     //   1757: instanceof java/lang/Character
/*    */     //   1760: ifeq -> 1776
/*    */     //   1763: aload #43
/*    */     //   1765: checkcast java/lang/Character
/*    */     //   1768: aload #44
/*    */     //   1770: invokestatic equalsCharObject : (Ljava/lang/Character;Ljava/lang/Object;)Z
/*    */     //   1773: goto -> 1783
/*    */     //   1776: aload #43
/*    */     //   1778: aload #44
/*    */     //   1780: invokevirtual equals : (Ljava/lang/Object;)Z
/*    */     //   1783: ifeq -> 1883
/*    */     //   1786: aload_0
/*    */     //   1787: invokevirtual _22 : ()Ljava/lang/Object;
/*    */     //   1790: aload #47
/*    */     //   1792: invokevirtual _22 : ()Ljava/lang/Object;
/*    */     //   1795: astore #46
/*    */     //   1797: dup
/*    */     //   1798: astore #45
/*    */     //   1800: aload #46
/*    */     //   1802: if_acmpne -> 1809
/*    */     //   1805: iconst_1
/*    */     //   1806: goto -> 1867
/*    */     //   1809: aload #45
/*    */     //   1811: ifnonnull -> 1818
/*    */     //   1814: iconst_0
/*    */     //   1815: goto -> 1867
/*    */     //   1818: aload #45
/*    */     //   1820: instanceof java/lang/Number
/*    */     //   1823: ifeq -> 1839
/*    */     //   1826: aload #45
/*    */     //   1828: checkcast java/lang/Number
/*    */     //   1831: aload #46
/*    */     //   1833: invokestatic equalsNumObject : (Ljava/lang/Number;Ljava/lang/Object;)Z
/*    */     //   1836: goto -> 1867
/*    */     //   1839: aload #45
/*    */     //   1841: instanceof java/lang/Character
/*    */     //   1844: ifeq -> 1860
/*    */     //   1847: aload #45
/*    */     //   1849: checkcast java/lang/Character
/*    */     //   1852: aload #46
/*    */     //   1854: invokestatic equalsCharObject : (Ljava/lang/Character;Ljava/lang/Object;)Z
/*    */     //   1857: goto -> 1867
/*    */     //   1860: aload #45
/*    */     //   1862: aload #46
/*    */     //   1864: invokevirtual equals : (Ljava/lang/Object;)Z
/*    */     //   1867: ifeq -> 1883
/*    */     //   1870: aload #47
/*    */     //   1872: aload_0
/*    */     //   1873: invokevirtual canEqual : (Ljava/lang/Object;)Z
/*    */     //   1876: ifeq -> 1883
/*    */     //   1879: iconst_1
/*    */     //   1880: goto -> 1884
/*    */     //   1883: iconst_0
/*    */     //   1884: ifeq -> 1891
/*    */     //   1887: iconst_1
/*    */     //   1888: goto -> 1892
/*    */     //   1891: iconst_0
/*    */     //   1892: ireturn
/*    */     // Line number table:
/*    */     //   Java source line number -> byte code offset
/*    */     //   #39	-> 0
/*    */     //   #236	-> 12
/*    */     //   #39	-> 19
/*    */     // Local variable table:
/*    */     //   start	length	slot	name	descriptor
/*    */     //   0	1893	0	this	Lscala/Tuple22;
/*    */     //   0	1893	1	x$1	Ljava/lang/Object;
/*    */   }
/*    */   
/*    */   public Tuple22(Object _1, Object _2, Object _3, Object _4, Object _5, Object _6, Object _7, Object _8, Object _9, Object _10, Object _11, Object _12, Object _13, Object _14, Object _15, Object _16, Object _17, Object _18, Object _19, Object _20, Object _21, Object _22) {
/* 39 */     Product$class.$init$(this);
/* 39 */     Product22$class.$init$(this);
/*    */   }
/*    */   
/*    */   public String toString() {
/* 43 */     return (new StringBuilder()).append("(").append(_1()).append(",").append(_2()).append(",").append(_3()).append(",").append(_4()).append(",").append(_5()).append(",").append(_6()).append(",").append(_7()).append(",").append(_8()).append(",").append(_9()).append(",").append(_10()).append(",").append(_11()).append(",").append(_12()).append(",").append(_13()).append(",").append(_14()).append(",").append(_15()).append(",").append(_16()).append(",").append(_17()).append(",").append(_18()).append(",").append(_19()).append(",").append(_20()).append(",").append(_21()).append(",").append(_22()).append(")").toString();
/*    */   }
/*    */ }


/* Location:              D:\#source-code\TheFlightSims\TFSLibrary\World2Xplane\World2XPlane.jar!\scala\Tuple22.class
 * Java compiler version: 6 (50.0)
 * JD-Core Version:       1.1.3
 */