/*     */ package akka.actor;
/*     */ 
/*     */ import akka.dispatch.Dispatchers;
/*     */ import akka.dispatch.Mailboxes;
/*     */ import akka.event.EventStream;
/*     */ import akka.event.LoggingAdapter;
/*     */ import akka.japi.Util$;
/*     */ import akka.util.Reflect$;
/*     */ import akka.util.Timeout;
/*     */ import com.typesafe.config.Config;
/*     */ import com.typesafe.config.ConfigFactory;
/*     */ import scala.Function0;
/*     */ import scala.Function1;
/*     */ import scala.Option;
/*     */ import scala.Serializable;
/*     */ import scala.collection.Iterable;
/*     */ import scala.collection.immutable.Seq;
/*     */ import scala.concurrent.ExecutionContext;
/*     */ import scala.concurrent.ExecutionContextExecutor;
/*     */ import scala.concurrent.duration.Duration;
/*     */ import scala.reflect.ScalaSignature;
/*     */ import scala.runtime.AbstractFunction0;
/*     */ import scala.runtime.AbstractFunction1;
/*     */ import scala.runtime.BoxesRunTime;
/*     */ 
/*     */ @ScalaSignature(bytes = "\006\001\r}v!B\001\003\021\0039\021aC!di>\0248+_:uK6T!a\001\003\002\013\005\034Go\034:\013\003\025\tA!Y6lC\016\001\001C\001\005\n\033\005\021a!\002\006\003\021\003Y!aC!di>\0248+_:uK6\034\"!\003\007\021\0055\001R\"\001\b\013\003=\tQa]2bY\006L!!\005\b\003\r\005s\027PU3g\021\025\031\022\002\"\001\025\003\031a\024N\\5u}Q\tq\001C\004\027\023\t\007I\021A\f\002\017Y+'o]5p]V\t\001\004\005\002\03299\021QBG\005\00379\ta\001\025:fI\0264\027BA\017\037\005\031\031FO]5oO*\0211D\004\005\007A%\001\013\021\002\r\002\021Y+'o]5p]\002BqAI\005C\002\023\0051%A\004F]ZDu.\\3\026\003\021\0022!D\023\031\023\t1cB\001\004PaRLwN\034\005\007Q%\001\013\021\002\023\002\021\025sg\017S8nK\002BqAK\005C\002\023\0051%\001\006TsN$X-\034%p[\026Da\001L\005!\002\023!\023aC*zgR,W\016S8nK\002BqAL\005C\002\023\0051%\001\006HY>\024\027\r\034%p[\026Da\001M\005!\002\023!\023aC$m_\n\fG\016S8nK\002BQAM\005\005\002M\naa\031:fCR,G#\001\033\021\005!)d!\002\006\003\003\00314cA\033\roA\021\001\002O\005\003s\t\021q\"Q2u_J\024VM\032$bGR|'/\037\005\006'U\"\ta\r\005\006yU2\taF\001\005]\006lW\rC\003?k\031\005q(\001\005tKR$\030N\\4t+\005\001\005CA!C\035\tA\001A\002\003D\023\001!%\001C*fiRLgnZ:\024\005\tc\001\002\003$C\005\003\005\013\021B$\002\027\rd\027m]:M_\006$WM\035\t\003\0216k\021!\023\006\003\025.\013A\001\\1oO*\tA*\001\003kCZ\f\027B\001(J\005-\031E.Y:t\031>\fG-\032:\t\021A\023%\021!Q\001\nE\0131a\0314h!\t\021\026,D\001T\025\t!V+\001\004d_:4\027n\032\006\003-^\013\001\002^=qKN\fg-\032\006\0021\006\0311m\\7\n\005i\033&AB\"p]\032Lw\r\003\005=\005\n\025\r\021\"\002\030\021!i&I!A!\002\033A\022!\0028b[\026\004\003\"B\nC\t\003yF\003\0021cG\022\004\"!\031\"\016\003%AQA\0220A\002\035CQ\001\0250A\002ECQ\001\0200A\002aAq\001\026\"C\002\023\025a-F\001R\021\031A'\t)A\007#\00691m\0348gS\036\004\003b\0026C\005\004%)aF\001\016\007>tg-[4WKJ\034\030n\0348\t\r1\024\005\025!\004\031\0039\031uN\0344jOZ+'o]5p]\002BqA\034\"C\002\023\025q#A\007Qe>4\030\016Z3s\0072\f7o\035\005\007a\n\003\013Q\002\r\002\035A\023xN^5eKJ\034E.Y:tA!9!O\021b\001\n\0139\022aF*va\026\024h/[:peN#(/\031;fOf\034E.Y:t\021\031!(\t)A\0071\005A2+\0369feZL7o\034:TiJ\fG/Z4z\0072\f7o\035\021\t\017Y\024%\031!C\003o\006y1I]3bi&|g\016V5nK>,H/F\001y!\tIH0D\001{\025\tYH!\001\003vi&d\027BA?{\005\035!\026.\\3pkRDaa \"!\002\033A\030\001E\"sK\006$\030n\0348US6,w.\036;!\021!\t\031A\021b\001\n\0139\030\001F+ogR\f'\017^3e!V\034\b\016V5nK>,H\017C\004\002\b\t\003\013Q\002=\002+Us7\017^1si\026$\007+^:i)&lWm\\;uA!I\0211\002\"C\002\023\025\021QB\001\025'\026\024\030.\0317ju\026\fE\016\\'fgN\fw-Z:\026\005\005=\001cA\007\002\022%\031\0211\003\b\003\017\t{w\016\\3b]\"A\021q\003\"!\002\033\ty!A\013TKJL\027\r\\5{K\006cG.T3tg\006<Wm\035\021\t\023\005m!I1A\005\006\0055\021\001F*fe&\fG.\033>f\0032d7I]3bi>\0248\017\003\005\002 \t\003\013QBA\b\003U\031VM]5bY&TX-\0217m\007J,\027\r^8sg\002B\001\"a\tC\005\004%)aF\001\t\031><G*\032<fY\"9\021q\005\"!\002\033A\022!\003'pO2+g/\0327!\021!\tYC\021b\001\n\0139\022AD*uI>,H\017T8h\031\0264X\r\034\005\b\003_\021\005\025!\004\031\003=\031F\017Z8vi2{w\rT3wK2\004\003\"CA\032\005\n\007IQAA\033\003\035aunZ4feN,\"!a\016\021\013\005e\0221\t\r\016\005\005m\"\002BA\037\003\t\021\"[7nkR\f'\r\\3\013\007\005\005c\"\001\006d_2dWm\031;j_:LA!!\022\002<\t\0311+Z9\t\021\005%#\t)A\007\003o\t\001\002T8hO\026\0248\017\t\005\t\003\033\022%\031!C\003o\006\021Bj\\4hKJ\034F/\031:u)&lWm\\;u\021\035\t\tF\021Q\001\016a\f1\003T8hO\026\0248\013^1siRKW.Z8vi\002B\021\"!\026C\005\004%)!!\004\002!1{wmQ8oM&<wJ\\*uCJ$\b\002CA-\005\002\006i!a\004\002#1{wmQ8oM&<wJ\\*uCJ$\b\005C\005\002^\t\023\r\021\"\002\002`\005qAj\\4EK\006$G*\032;uKJ\034XCAA1!\ri\0211M\005\004\003Kr!aA%oi\"A\021\021\016\"!\002\033\t\t'A\bM_\036$U-\0313MKR$XM]:!\021%\tiG\021b\001\n\013\ti!\001\017M_\036$U-\0313MKR$XM]:EkJLgnZ*ikR$wn\0368\t\021\005E$\t)A\007\003\037\tQ\004T8h\t\026\fG\rT3ui\026\0248\017R;sS:<7\013[;uI><h\016\t\005\n\003k\022%\031!C\003\003\033\t\021#\0213e\031><w-\0338h%\026\034W-\033<f\021!\tIH\021Q\001\016\005=\021AE!eI2{wmZ5oOJ+7-Z5wK\002B\021\"! C\005\004%)!!\004\002!\021+'-^4BkR|'+Z2fSZ,\007\002CAA\005\002\006i!a\004\002#\021+'-^4BkR|'+Z2fSZ,\007\005C\005\002\006\n\023\r\021\"\002\002\016\005qA)\0322vO2Kg-Z2zG2,\007\002CAE\005\002\006i!a\004\002\037\021+'-^4MS\032,7-_2mK\002B\021\"!$C\005\004%)!!\004\002\033\031\033X\016R3ck\036,e/\0328u\021!\t\tJ\021Q\001\016\005=\021A\004$t[\022+'-^4Fm\026tG\017\t\005\n\003+\023%\031!C\003\003\033\t\001\003R3ck\036,e/\0328u'R\024X-Y7\t\021\005e%\t)A\007\003\037\t\021\003R3ck\036,e/\0328u'R\024X-Y7!\021%\tiJ\021b\001\n\013\ti!A\013EK\n,x-\0268iC:$G.\0323NKN\034\030mZ3\t\021\005\005&\t)A\007\003\037\ta\003R3ck\036,f\016[1oI2,G-T3tg\006<W\r\t\005\n\003K\023%\031!C\003\003\033\t1\004R3ck\036\024v.\036;fe6K7oY8oM&<WO]1uS>t\007\002CAU\005\002\006i!a\004\0029\021+'-^4S_V$XM]'jg\016|gNZ5hkJ\fG/[8oA!A\021Q\026\"C\002\023\0251%\001\003I_6,\007bBAY\005\002\006i\001J\001\006\021>lW\r\t\005\t\003k\023%\031!C\003/\005q1k\0315fIVdWM]\"mCN\034\bbBA]\005\002\006i\001G\001\020'\016DW\rZ;mKJ\034E.Y:tA!I\021Q\030\"C\002\023\025\021QB\001\f\t\006,Wn\0348jG&$\030\020\003\005\002B\n\003\013QBA\b\0031!\025-Z7p]&\034\027\016^=!\021%\t)M\021b\001\n\013\ti!A\nKm6,\0050\033;P]\032\013G/\0317FeJ|'\017\003\005\002J\n\003\013QBA\b\003QQe/\\#ySR|eNR1uC2,%O]8sA!I\021Q\032\"C\002\023\025\021qL\001\032\t\0264\027-\0367u-&\024H/^1m\035>$Wm\035$bGR|'\017\003\005\002R\n\003\013QBA1\003i!UMZ1vYR4\026N\035;vC2tu\016Z3t\r\006\034Go\034:!\021\035\t)N\021C!\003/\f\001\002^8TiJLgn\032\013\0021!9\0211\\\033\007\002\005u\027\001\0057pO\016{gNZ5hkJ\fG/[8o)\t\ty\016E\002\016\003CL1!a9\017\005\021)f.\033;\t\017\005\035XG\"\001\002j\006!A\005Z5w)\021\tY/!=\021\007!\ti/C\002\002p\n\021\021\"Q2u_J\004\026\r\0365\t\rq\n)\0171\001\031\021\035\t)0\016C\001\003o\fQa\0315jY\022$B!a;\002z\"9\021Q_Az\001\004A\002bBAtk\031\005\021Q \013\005\003W\fy\020C\004=\003w\004\rA!\001\021\013\t\r!1\003\r\017\t\t\025!q\002\b\005\005\017\021i!\004\002\003\n)\031!1\002\004\002\rq\022xn\034;?\023\005y\021b\001B\t\035\0059\001/Y2lC\036,\027\002\002B\013\005/\021\001\"\023;fe\006\024G.\032\006\004\005#q\001b\002B\016k\021\005!QD\001\013I\026\0348-\0328eC:$H\003BAv\005?A\001B!\t\003\032\001\007!1E\001\006]\006lWm\035\t\005\021\n\025\002$C\002\003\026%C\021B!\0136\005\004%\tAa\013\002\023M$\030M\035;US6,WC\001B\027!\ri!qF\005\004\005cq!\001\002'p]\036D\001B!\0166A\003%!QF\001\013gR\f'\017\036+j[\026\004\003b\002B\035k\021\005!1F\001\007kB$\030.\\3\t\017\tuRG\"\001\003@\005YQM^3oiN#(/Z1n+\t\021\t\005\005\003\003D\t%SB\001B#\025\r\0219\005B\001\006KZ,g\016^\005\005\005\027\022)EA\006Fm\026tGo\025;sK\006l\007b\002B(k\031\005!\021K\001\004Y><WC\001B*!\021\021\031E!\026\n\t\t]#Q\t\002\017\031><w-\0338h\003\022\f\007\017^3s\021\035\021Y&\016D\001\005;\n1\002Z3bI2+G\017^3sgV\021!q\f\t\004\021\t\005\024b\001B2\005\tA\021i\031;peJ+g\rC\004\003hU2\tA!\033\002\023M\034\007.\0323vY\026\024XC\001B6!\rA!QN\005\004\005_\022!!C*dQ\026$W\017\\3s\021\035\021\031(\016D\001\005k\n1\002Z5ta\006$8\r[3sgV\021!q\017\t\005\005s\022y(\004\002\003|)\031!Q\020\003\002\021\021L7\017]1uG\"LAA!!\003|\tYA)[:qCR\034\007.\032:t\021\035\021))\016D\002\005\017\013!\002Z5ta\006$8\r[3s+\t\021I\t\005\003\003\f\nEUB\001BG\025\r\021yID\001\013G>t7-\036:sK:$\030\002\002BJ\005\033\023\001$\022=fGV$\030n\0348D_:$X\r\037;Fq\026\034W\017^8s\021\035\0219*\016D\001\0053\013\021\"\\1jY\n|\0070Z:\026\005\tm\005\003\002B=\005;KAAa(\003|\tIQ*Y5mE>DXm\035\005\b\005G+d\021\001BS\003U\021XmZ5ti\026\024xJ\034+fe6Lg.\031;j_:,BAa*\0038R!\021q\034BU\021%\021YK!)\005\002\004\021i+\001\003d_\022,\007#B\007\0030\nM\026b\001BY\035\tAAHY=oC6,g\b\005\003\0036\n]F\002\001\003\t\005s\023\tK1\001\003<\n\tA+\005\003\003>\n\r\007cA\007\003@&\031!\021\031\b\003\0179{G\017[5oOB\031QB!2\n\007\t\035gBA\002B]fDqAa)6\r\003\021Y\r\006\003\002`\n5\007\002\003BV\005\023\004\rAa4\021\007!\023\t.C\002\003T&\023\001BU;o]\006\024G.\032\005\b\005/,d\021\001Bm\003A\tw/Y5u)\026\024X.\0338bi&|g\016\006\003\002`\nm\007\002\003Bo\005+\004\rAa8\002\017QLW.Z8viB!!\021\035Bt\033\t\021\031O\003\003\003f\n5\025\001\0033ve\006$\030n\0348\n\t\t%(1\035\002\t\tV\024\030\r^5p]\"9!q[\033\007\002\005u\007b\002Bxk\031\005\021Q\\\001\tg\",H\017Z8x]\"9!1_\033\007\002\0055\021\001D5t)\026\024X.\0338bi\026$\007b\002B|k\031\005!\021`\001\022e\026<\027n\035;fe\026CH/\0328tS>tW\003\002B~\005$BA!@\004\nA!!Q\027B\000\t!\021IL!>C\002\r\005\021\003\002B_\007\007\0012\001CB\003\023\r\0319A\001\002\n\013b$XM\\:j_:D\001ba\003\003v\002\0071QB\001\004Kb$\b#\002\005\004\020\tu\030bAB\t\005\tYQ\t\037;f]NLwN\\%e\021\035\031)\"\016D\001\007/\t\021\"\032=uK:\034\030n\0348\026\t\re1Q\004\013\005\0077\031y\002\005\003\0036\016uA\001\003B]\007'\021\ra!\001\t\021\r-11\003a\001\007C\001R\001CB\b\0077Aqa!\n6\r\003\0319#\001\007iCN,\005\020^3og&|g\016\006\003\002\020\r%\002\002CB\006\007G\001\raa\0131\t\r52\021\007\t\006\021\r=1q\006\t\005\005k\033\t\004\002\007\0044\r%\022\021!A\001\006\003\031\tAA\002`IIBaAM\005\005\002\r]Bc\001\033\004:!1Ah!\016A\002aAaAM\005\005\002\ruB#\002\033\004@\r\005\003B\002\037\004<\001\007\001\004\003\004U\007w\001\r!\025\005\007e%!\ta!\022\025\017Q\0329e!\023\004L!1Aha\021A\002aAa\001VB\"\001\004\t\006B\002$\004D\001\007q\t\003\0043\023\021\0051q\n\013\ni\rE31KB+\007/Ba\001PB'\001\004A\002B\002+\004N\001\007\021\013\003\004G\007\033\002\ra\022\005\t\0073\032i\0051\001\004\\\0059B-\0324bk2$X\t_3dkRLwN\\\"p]R,\007\020\036\t\005\005\027\033i&\003\003\004`\t5%\001E#yK\016,H/[8o\007>tG/\032=u\021\031\031\031'\003C\001g\005)\021\r\0359ms\"911M\005\005\002\r\035Dc\001\033\004j!1Ah!\032A\002aAqaa\031\n\t\003\031i\007F\0035\007_\032\t\b\003\004=\007W\002\r\001\007\005\007)\016-\004\031A)\t\017\r\r\024\002\"\001\004vQ9Aga\036\004z\rm\004B\002\037\004t\001\007\001\004\003\004U\007g\002\r!\025\005\007\r\016M\004\031A$\t\017\r\r\024\002\"\001\004\000QIAg!!\004\004\016\03551\022\005\007y\ru\004\031\001\r\t\023Q\033i\b%AA\002\r\025\005cA\007&#\"Iai! \021\002\003\0071\021\022\t\004\033\025:\005BCB-\007{\002\n\0211\001\004\016B!Q\"JB.\021!\031\t*\003C\001\t\rM\025a\0044j]\022\034E.Y:t\031>\fG-\032:\025\003\035C\021ba&\n#\003%\ta!'\002\037\005\004\b\017\\=%I\0264\027-\0367uII*\"aa'+\t\r\0255QT\026\003\007?\003Ba!)\004,6\02111\025\006\005\007K\0339+A\005v]\016DWmY6fI*\0311\021\026\b\002\025\005tgn\034;bi&|g.\003\003\004.\016\r&!E;oG\",7m[3e-\006\024\030.\0318dK\"I1\021W\005\022\002\023\00511W\001\020CB\004H.\037\023eK\032\fW\017\034;%gU\0211Q\027\026\005\007\023\033i\nC\005\004:&\t\n\021\"\001\004<\006y\021\r\0359ms\022\"WMZ1vYR$C'\006\002\004>*\"1QRBO\001")
/*     */ public abstract class ActorSystem implements ActorRefFactory {
/*     */   private final long startTime;
/*     */   
/*     */   public static class $anonfun$3 extends AbstractFunction0<Option<String>> implements Serializable {
/*     */     public static final long serialVersionUID = 0L;
/*     */     
/*     */     public final Option<String> apply() {
/*  38 */       return ActorSystem$.MODULE$.EnvHome();
/*     */     }
/*     */   }
/*     */   
/*     */   public static class ActorSystem$$anonfun$4 extends AbstractFunction0<ClassLoader> implements Serializable {
/*     */     public static final long serialVersionUID = 0L;
/*     */     
/*     */     public final ClassLoader apply() {
/* 139 */       return ActorSystem$.MODULE$.findClassLoader();
/*     */     }
/*     */   }
/*     */   
/*     */   public static class ActorSystem$$anonfun$5 extends AbstractFunction0<Config> implements Serializable {
/*     */     public static final long serialVersionUID = 0L;
/*     */     
/*     */     private final ClassLoader cl$1;
/*     */     
/*     */     public final Config apply() {
/* 140 */       return ConfigFactory.load(this.cl$1);
/*     */     }
/*     */     
/*     */     public ActorSystem$$anonfun$5(ClassLoader cl$1) {}
/*     */   }
/*     */   
/*     */   public static class Settings {
/*     */     private final String name;
/*     */     
/*     */     private final Config config;
/*     */     
/*     */     private final String ConfigVersion;
/*     */     
/*     */     private final String ProviderClass;
/*     */     
/*     */     private final String SupervisorStrategyClass;
/*     */     
/*     */     private final Timeout CreationTimeout;
/*     */     
/*     */     private final Timeout UnstartedPushTimeout;
/*     */     
/*     */     private final boolean SerializeAllMessages;
/*     */     
/*     */     private final boolean SerializeAllCreators;
/*     */     
/*     */     private final String LogLevel;
/*     */     
/*     */     private final String StdoutLogLevel;
/*     */     
/*     */     private final Seq<String> Loggers;
/*     */     
/*     */     private final Timeout LoggerStartTimeout;
/*     */     
/*     */     private final boolean LogConfigOnStart;
/*     */     
/*     */     private final int LogDeadLetters;
/*     */     
/*     */     private final boolean LogDeadLettersDuringShutdown;
/*     */     
/*     */     private final boolean AddLoggingReceive;
/*     */     
/*     */     private final boolean DebugAutoReceive;
/*     */     
/*     */     private final boolean DebugLifecycle;
/*     */     
/*     */     private final boolean FsmDebugEvent;
/*     */     
/*     */     private final boolean DebugEventStream;
/*     */     
/*     */     private final boolean DebugUnhandledMessage;
/*     */     
/*     */     private final boolean DebugRouterMisconfiguration;
/*     */     
/*     */     private final Option<String> Home;
/*     */     
/*     */     private final String SchedulerClass;
/*     */     
/*     */     private final boolean Daemonicity;
/*     */     
/*     */     private final boolean JvmExitOnFatalError;
/*     */     
/*     */     private final int DefaultVirtualNodesFactor;
/*     */     
/*     */     public final String name() {
/* 151 */       return this.name;
/*     */     }
/*     */     
/*     */     public Settings(ClassLoader classLoader, Config cfg, String name) {
/*     */       // Byte code:
/*     */       //   0: aload_0
/*     */       //   1: aload_3
/*     */       //   2: putfield name : Ljava/lang/String;
/*     */       //   5: aload_0
/*     */       //   6: invokespecial <init> : ()V
/*     */       //   9: aload_0
/*     */       //   10: aload_2
/*     */       //   11: aload_1
/*     */       //   12: invokestatic defaultReference : (Ljava/lang/ClassLoader;)Lcom/typesafe/config/Config;
/*     */       //   15: invokeinterface withFallback : (Lcom/typesafe/config/ConfigMergeable;)Lcom/typesafe/config/Config;
/*     */       //   20: astore #4
/*     */       //   22: aload #4
/*     */       //   24: aload_1
/*     */       //   25: invokestatic defaultReference : (Ljava/lang/ClassLoader;)Lcom/typesafe/config/Config;
/*     */       //   28: iconst_1
/*     */       //   29: anewarray java/lang/String
/*     */       //   32: dup
/*     */       //   33: iconst_0
/*     */       //   34: ldc 'akka'
/*     */       //   36: aastore
/*     */       //   37: invokeinterface checkValid : (Lcom/typesafe/config/Config;[Ljava/lang/String;)V
/*     */       //   42: aload #4
/*     */       //   44: putfield config : Lcom/typesafe/config/Config;
/*     */       //   47: aload_0
/*     */       //   48: aload_0
/*     */       //   49: invokevirtual config : ()Lcom/typesafe/config/Config;
/*     */       //   52: ldc 'akka.version'
/*     */       //   54: invokeinterface getString : (Ljava/lang/String;)Ljava/lang/String;
/*     */       //   59: putfield ConfigVersion : Ljava/lang/String;
/*     */       //   62: aload_0
/*     */       //   63: aload_0
/*     */       //   64: invokevirtual config : ()Lcom/typesafe/config/Config;
/*     */       //   67: ldc 'akka.actor.provider'
/*     */       //   69: invokeinterface getString : (Ljava/lang/String;)Ljava/lang/String;
/*     */       //   74: putfield ProviderClass : Ljava/lang/String;
/*     */       //   77: aload_0
/*     */       //   78: aload_0
/*     */       //   79: invokevirtual config : ()Lcom/typesafe/config/Config;
/*     */       //   82: ldc 'akka.actor.guardian-supervisor-strategy'
/*     */       //   84: invokeinterface getString : (Ljava/lang/String;)Ljava/lang/String;
/*     */       //   89: putfield SupervisorStrategyClass : Ljava/lang/String;
/*     */       //   92: aload_0
/*     */       //   93: new akka/util/Timeout
/*     */       //   96: dup
/*     */       //   97: getstatic akka/util/Helpers$ConfigOps$.MODULE$ : Lakka/util/Helpers$ConfigOps$;
/*     */       //   100: getstatic akka/util/Helpers$.MODULE$ : Lakka/util/Helpers$;
/*     */       //   103: aload_0
/*     */       //   104: invokevirtual config : ()Lcom/typesafe/config/Config;
/*     */       //   107: invokevirtual ConfigOps : (Lcom/typesafe/config/Config;)Lcom/typesafe/config/Config;
/*     */       //   110: ldc 'akka.actor.creation-timeout'
/*     */       //   112: invokevirtual getMillisDuration$extension : (Lcom/typesafe/config/Config;Ljava/lang/String;)Lscala/concurrent/duration/FiniteDuration;
/*     */       //   115: invokespecial <init> : (Lscala/concurrent/duration/FiniteDuration;)V
/*     */       //   118: putfield CreationTimeout : Lakka/util/Timeout;
/*     */       //   121: aload_0
/*     */       //   122: new akka/util/Timeout
/*     */       //   125: dup
/*     */       //   126: getstatic akka/util/Helpers$ConfigOps$.MODULE$ : Lakka/util/Helpers$ConfigOps$;
/*     */       //   129: getstatic akka/util/Helpers$.MODULE$ : Lakka/util/Helpers$;
/*     */       //   132: aload_0
/*     */       //   133: invokevirtual config : ()Lcom/typesafe/config/Config;
/*     */       //   136: invokevirtual ConfigOps : (Lcom/typesafe/config/Config;)Lcom/typesafe/config/Config;
/*     */       //   139: ldc 'akka.actor.unstarted-push-timeout'
/*     */       //   141: invokevirtual getMillisDuration$extension : (Lcom/typesafe/config/Config;Ljava/lang/String;)Lscala/concurrent/duration/FiniteDuration;
/*     */       //   144: invokespecial <init> : (Lscala/concurrent/duration/FiniteDuration;)V
/*     */       //   147: putfield UnstartedPushTimeout : Lakka/util/Timeout;
/*     */       //   150: aload_0
/*     */       //   151: aload_0
/*     */       //   152: invokevirtual config : ()Lcom/typesafe/config/Config;
/*     */       //   155: ldc 'akka.actor.serialize-messages'
/*     */       //   157: invokeinterface getBoolean : (Ljava/lang/String;)Z
/*     */       //   162: putfield SerializeAllMessages : Z
/*     */       //   165: aload_0
/*     */       //   166: aload_0
/*     */       //   167: invokevirtual config : ()Lcom/typesafe/config/Config;
/*     */       //   170: ldc 'akka.actor.serialize-creators'
/*     */       //   172: invokeinterface getBoolean : (Ljava/lang/String;)Z
/*     */       //   177: putfield SerializeAllCreators : Z
/*     */       //   180: aload_0
/*     */       //   181: aload_0
/*     */       //   182: invokevirtual config : ()Lcom/typesafe/config/Config;
/*     */       //   185: ldc 'akka.loglevel'
/*     */       //   187: invokeinterface getString : (Ljava/lang/String;)Ljava/lang/String;
/*     */       //   192: putfield LogLevel : Ljava/lang/String;
/*     */       //   195: aload_0
/*     */       //   196: aload_0
/*     */       //   197: invokevirtual config : ()Lcom/typesafe/config/Config;
/*     */       //   200: ldc 'akka.stdout-loglevel'
/*     */       //   202: invokeinterface getString : (Ljava/lang/String;)Ljava/lang/String;
/*     */       //   207: putfield StdoutLogLevel : Ljava/lang/String;
/*     */       //   210: aload_0
/*     */       //   211: getstatic akka/japi/Util$.MODULE$ : Lakka/japi/Util$;
/*     */       //   214: aload_0
/*     */       //   215: invokevirtual config : ()Lcom/typesafe/config/Config;
/*     */       //   218: ldc 'akka.loggers'
/*     */       //   220: invokeinterface getStringList : (Ljava/lang/String;)Ljava/util/List;
/*     */       //   225: invokevirtual immutableSeq : (Ljava/lang/Iterable;)Lscala/collection/immutable/Seq;
/*     */       //   228: putfield Loggers : Lscala/collection/immutable/Seq;
/*     */       //   231: aload_0
/*     */       //   232: new akka/util/Timeout
/*     */       //   235: dup
/*     */       //   236: getstatic akka/util/Helpers$ConfigOps$.MODULE$ : Lakka/util/Helpers$ConfigOps$;
/*     */       //   239: getstatic akka/util/Helpers$.MODULE$ : Lakka/util/Helpers$;
/*     */       //   242: aload_0
/*     */       //   243: invokevirtual config : ()Lcom/typesafe/config/Config;
/*     */       //   246: invokevirtual ConfigOps : (Lcom/typesafe/config/Config;)Lcom/typesafe/config/Config;
/*     */       //   249: ldc 'akka.logger-startup-timeout'
/*     */       //   251: invokevirtual getMillisDuration$extension : (Lcom/typesafe/config/Config;Ljava/lang/String;)Lscala/concurrent/duration/FiniteDuration;
/*     */       //   254: invokespecial <init> : (Lscala/concurrent/duration/FiniteDuration;)V
/*     */       //   257: putfield LoggerStartTimeout : Lakka/util/Timeout;
/*     */       //   260: aload_0
/*     */       //   261: aload_0
/*     */       //   262: invokevirtual config : ()Lcom/typesafe/config/Config;
/*     */       //   265: ldc 'akka.log-config-on-start'
/*     */       //   267: invokeinterface getBoolean : (Ljava/lang/String;)Z
/*     */       //   272: putfield LogConfigOnStart : Z
/*     */       //   275: aload_0
/*     */       //   276: aload_0
/*     */       //   277: invokevirtual config : ()Lcom/typesafe/config/Config;
/*     */       //   280: ldc 'akka.log-dead-letters'
/*     */       //   282: invokeinterface getString : (Ljava/lang/String;)Ljava/lang/String;
/*     */       //   287: invokevirtual toLowerCase : ()Ljava/lang/String;
/*     */       //   290: astore #5
/*     */       //   292: ldc 'off'
/*     */       //   294: aload #5
/*     */       //   296: astore #6
/*     */       //   298: dup
/*     */       //   299: ifnonnull -> 311
/*     */       //   302: pop
/*     */       //   303: aload #6
/*     */       //   305: ifnull -> 319
/*     */       //   308: goto -> 325
/*     */       //   311: aload #6
/*     */       //   313: invokevirtual equals : (Ljava/lang/Object;)Z
/*     */       //   316: ifeq -> 325
/*     */       //   319: iconst_1
/*     */       //   320: istore #7
/*     */       //   322: goto -> 361
/*     */       //   325: ldc 'false'
/*     */       //   327: aload #5
/*     */       //   329: astore #8
/*     */       //   331: dup
/*     */       //   332: ifnonnull -> 344
/*     */       //   335: pop
/*     */       //   336: aload #8
/*     */       //   338: ifnull -> 352
/*     */       //   341: goto -> 358
/*     */       //   344: aload #8
/*     */       //   346: invokevirtual equals : (Ljava/lang/Object;)Z
/*     */       //   349: ifeq -> 358
/*     */       //   352: iconst_1
/*     */       //   353: istore #7
/*     */       //   355: goto -> 361
/*     */       //   358: iconst_0
/*     */       //   359: istore #7
/*     */       //   361: iload #7
/*     */       //   363: ifeq -> 372
/*     */       //   366: iconst_0
/*     */       //   367: istore #9
/*     */       //   369: goto -> 466
/*     */       //   372: ldc 'on'
/*     */       //   374: aload #5
/*     */       //   376: astore #10
/*     */       //   378: dup
/*     */       //   379: ifnonnull -> 391
/*     */       //   382: pop
/*     */       //   383: aload #10
/*     */       //   385: ifnull -> 399
/*     */       //   388: goto -> 405
/*     */       //   391: aload #10
/*     */       //   393: invokevirtual equals : (Ljava/lang/Object;)Z
/*     */       //   396: ifeq -> 405
/*     */       //   399: iconst_1
/*     */       //   400: istore #11
/*     */       //   402: goto -> 441
/*     */       //   405: ldc 'true'
/*     */       //   407: aload #5
/*     */       //   409: astore #12
/*     */       //   411: dup
/*     */       //   412: ifnonnull -> 424
/*     */       //   415: pop
/*     */       //   416: aload #12
/*     */       //   418: ifnull -> 432
/*     */       //   421: goto -> 438
/*     */       //   424: aload #12
/*     */       //   426: invokevirtual equals : (Ljava/lang/Object;)Z
/*     */       //   429: ifeq -> 438
/*     */       //   432: iconst_1
/*     */       //   433: istore #11
/*     */       //   435: goto -> 441
/*     */       //   438: iconst_0
/*     */       //   439: istore #11
/*     */       //   441: iload #11
/*     */       //   443: ifeq -> 453
/*     */       //   446: ldc 2147483647
/*     */       //   448: istore #9
/*     */       //   450: goto -> 466
/*     */       //   453: aload_0
/*     */       //   454: invokevirtual config : ()Lcom/typesafe/config/Config;
/*     */       //   457: ldc 'akka.log-dead-letters'
/*     */       //   459: invokeinterface getInt : (Ljava/lang/String;)I
/*     */       //   464: istore #9
/*     */       //   466: iload #9
/*     */       //   468: putfield LogDeadLetters : I
/*     */       //   471: aload_0
/*     */       //   472: aload_0
/*     */       //   473: invokevirtual config : ()Lcom/typesafe/config/Config;
/*     */       //   476: ldc 'akka.log-dead-letters-during-shutdown'
/*     */       //   478: invokeinterface getBoolean : (Ljava/lang/String;)Z
/*     */       //   483: putfield LogDeadLettersDuringShutdown : Z
/*     */       //   486: aload_0
/*     */       //   487: aload_0
/*     */       //   488: invokevirtual config : ()Lcom/typesafe/config/Config;
/*     */       //   491: ldc 'akka.actor.debug.receive'
/*     */       //   493: invokeinterface getBoolean : (Ljava/lang/String;)Z
/*     */       //   498: putfield AddLoggingReceive : Z
/*     */       //   501: aload_0
/*     */       //   502: aload_0
/*     */       //   503: invokevirtual config : ()Lcom/typesafe/config/Config;
/*     */       //   506: ldc 'akka.actor.debug.autoreceive'
/*     */       //   508: invokeinterface getBoolean : (Ljava/lang/String;)Z
/*     */       //   513: putfield DebugAutoReceive : Z
/*     */       //   516: aload_0
/*     */       //   517: aload_0
/*     */       //   518: invokevirtual config : ()Lcom/typesafe/config/Config;
/*     */       //   521: ldc 'akka.actor.debug.lifecycle'
/*     */       //   523: invokeinterface getBoolean : (Ljava/lang/String;)Z
/*     */       //   528: putfield DebugLifecycle : Z
/*     */       //   531: aload_0
/*     */       //   532: aload_0
/*     */       //   533: invokevirtual config : ()Lcom/typesafe/config/Config;
/*     */       //   536: ldc 'akka.actor.debug.fsm'
/*     */       //   538: invokeinterface getBoolean : (Ljava/lang/String;)Z
/*     */       //   543: putfield FsmDebugEvent : Z
/*     */       //   546: aload_0
/*     */       //   547: aload_0
/*     */       //   548: invokevirtual config : ()Lcom/typesafe/config/Config;
/*     */       //   551: ldc 'akka.actor.debug.event-stream'
/*     */       //   553: invokeinterface getBoolean : (Ljava/lang/String;)Z
/*     */       //   558: putfield DebugEventStream : Z
/*     */       //   561: aload_0
/*     */       //   562: aload_0
/*     */       //   563: invokevirtual config : ()Lcom/typesafe/config/Config;
/*     */       //   566: ldc 'akka.actor.debug.unhandled'
/*     */       //   568: invokeinterface getBoolean : (Ljava/lang/String;)Z
/*     */       //   573: putfield DebugUnhandledMessage : Z
/*     */       //   576: aload_0
/*     */       //   577: aload_0
/*     */       //   578: invokevirtual config : ()Lcom/typesafe/config/Config;
/*     */       //   581: ldc 'akka.actor.debug.router-misconfiguration'
/*     */       //   583: invokeinterface getBoolean : (Ljava/lang/String;)Z
/*     */       //   588: putfield DebugRouterMisconfiguration : Z
/*     */       //   591: aload_0
/*     */       //   592: aload_0
/*     */       //   593: invokevirtual config : ()Lcom/typesafe/config/Config;
/*     */       //   596: ldc 'akka.home'
/*     */       //   598: invokeinterface getString : (Ljava/lang/String;)Ljava/lang/String;
/*     */       //   603: astore #13
/*     */       //   605: ldc ''
/*     */       //   607: aload #13
/*     */       //   609: astore #14
/*     */       //   611: dup
/*     */       //   612: ifnonnull -> 624
/*     */       //   615: pop
/*     */       //   616: aload #14
/*     */       //   618: ifnull -> 632
/*     */       //   621: goto -> 640
/*     */       //   624: aload #14
/*     */       //   626: invokevirtual equals : (Ljava/lang/Object;)Z
/*     */       //   629: ifeq -> 640
/*     */       //   632: getstatic scala/None$.MODULE$ : Lscala/None$;
/*     */       //   635: astore #15
/*     */       //   637: goto -> 651
/*     */       //   640: new scala/Some
/*     */       //   643: dup
/*     */       //   644: aload #13
/*     */       //   646: invokespecial <init> : (Ljava/lang/Object;)V
/*     */       //   649: astore #15
/*     */       //   651: aload #15
/*     */       //   653: putfield Home : Lscala/Option;
/*     */       //   656: aload_0
/*     */       //   657: aload_0
/*     */       //   658: invokevirtual config : ()Lcom/typesafe/config/Config;
/*     */       //   661: ldc_w 'akka.scheduler.implementation'
/*     */       //   664: invokeinterface getString : (Ljava/lang/String;)Ljava/lang/String;
/*     */       //   669: putfield SchedulerClass : Ljava/lang/String;
/*     */       //   672: aload_0
/*     */       //   673: aload_0
/*     */       //   674: invokevirtual config : ()Lcom/typesafe/config/Config;
/*     */       //   677: ldc_w 'akka.daemonic'
/*     */       //   680: invokeinterface getBoolean : (Ljava/lang/String;)Z
/*     */       //   685: putfield Daemonicity : Z
/*     */       //   688: aload_0
/*     */       //   689: aload_0
/*     */       //   690: invokevirtual config : ()Lcom/typesafe/config/Config;
/*     */       //   693: ldc_w 'akka.jvm-exit-on-fatal-error'
/*     */       //   696: invokeinterface getBoolean : (Ljava/lang/String;)Z
/*     */       //   701: putfield JvmExitOnFatalError : Z
/*     */       //   704: aload_0
/*     */       //   705: aload_0
/*     */       //   706: invokevirtual config : ()Lcom/typesafe/config/Config;
/*     */       //   709: ldc_w 'akka.actor.deployment.default.virtual-nodes-factor'
/*     */       //   712: invokeinterface getInt : (Ljava/lang/String;)I
/*     */       //   717: putfield DefaultVirtualNodesFactor : I
/*     */       //   720: aload_0
/*     */       //   721: invokevirtual ConfigVersion : ()Ljava/lang/String;
/*     */       //   724: getstatic akka/actor/ActorSystem$.MODULE$ : Lakka/actor/ActorSystem$;
/*     */       //   727: invokevirtual Version : ()Ljava/lang/String;
/*     */       //   730: astore #16
/*     */       //   732: dup
/*     */       //   733: ifnonnull -> 745
/*     */       //   736: pop
/*     */       //   737: aload #16
/*     */       //   739: ifnull -> 753
/*     */       //   742: goto -> 754
/*     */       //   745: aload #16
/*     */       //   747: invokevirtual equals : (Ljava/lang/Object;)Z
/*     */       //   750: ifeq -> 754
/*     */       //   753: return
/*     */       //   754: new akka/ConfigurationException
/*     */       //   757: dup
/*     */       //   758: new scala/collection/mutable/StringBuilder
/*     */       //   761: dup
/*     */       //   762: invokespecial <init> : ()V
/*     */       //   765: ldc_w 'Akka JAR version ['
/*     */       //   768: invokevirtual append : (Ljava/lang/Object;)Lscala/collection/mutable/StringBuilder;
/*     */       //   771: getstatic akka/actor/ActorSystem$.MODULE$ : Lakka/actor/ActorSystem$;
/*     */       //   774: invokevirtual Version : ()Ljava/lang/String;
/*     */       //   777: invokevirtual append : (Ljava/lang/Object;)Lscala/collection/mutable/StringBuilder;
/*     */       //   780: ldc_w '] does not match the provided config version ['
/*     */       //   783: invokevirtual append : (Ljava/lang/Object;)Lscala/collection/mutable/StringBuilder;
/*     */       //   786: aload_0
/*     */       //   787: invokevirtual ConfigVersion : ()Ljava/lang/String;
/*     */       //   790: invokevirtual append : (Ljava/lang/Object;)Lscala/collection/mutable/StringBuilder;
/*     */       //   793: ldc_w ']'
/*     */       //   796: invokevirtual append : (Ljava/lang/Object;)Lscala/collection/mutable/StringBuilder;
/*     */       //   799: invokevirtual toString : ()Ljava/lang/String;
/*     */       //   802: invokespecial <init> : (Ljava/lang/String;)V
/*     */       //   805: athrow
/*     */       // Line number table:
/*     */       //   Java source line number -> byte code offset
/*     */       //   #151	-> 0
/*     */       //   #158	-> 9
/*     */       //   #159	-> 10
/*     */       //   #160	-> 22
/*     */       //   #161	-> 42
/*     */       //   #158	-> 44
/*     */       //   #168	-> 47
/*     */       //   #169	-> 62
/*     */       //   #170	-> 77
/*     */       //   #171	-> 92
/*     */       //   #172	-> 121
/*     */       //   #174	-> 150
/*     */       //   #175	-> 165
/*     */       //   #177	-> 180
/*     */       //   #178	-> 195
/*     */       //   #179	-> 210
/*     */       //   #180	-> 231
/*     */       //   #181	-> 260
/*     */       //   #182	-> 275
/*     */       //   #183	-> 292
/*     */       //   #184	-> 372
/*     */       //   #185	-> 453
/*     */       //   #182	-> 466
/*     */       //   #187	-> 471
/*     */       //   #189	-> 486
/*     */       //   #190	-> 501
/*     */       //   #191	-> 516
/*     */       //   #192	-> 531
/*     */       //   #193	-> 546
/*     */       //   #194	-> 561
/*     */       //   #195	-> 576
/*     */       //   #197	-> 591
/*     */       //   #198	-> 605
/*     */       //   #199	-> 640
/*     */       //   #197	-> 651
/*     */       //   #202	-> 656
/*     */       //   #203	-> 672
/*     */       //   #204	-> 688
/*     */       //   #206	-> 704
/*     */       //   #208	-> 720
/*     */       //   #151	-> 753
/*     */       //   #209	-> 754
/*     */       // Local variable table:
/*     */       //   start	length	slot	name	descriptor
/*     */       //   0	806	0	this	Lakka/actor/ActorSystem$Settings;
/*     */       //   0	806	1	classLoader	Ljava/lang/ClassLoader;
/*     */       //   0	806	2	cfg	Lcom/typesafe/config/Config;
/*     */       //   0	806	3	name	Ljava/lang/String;
/*     */       //   22	22	4	config	Lcom/typesafe/config/Config;
/*     */     }
/*     */     
/*     */     public final Config config() {
/* 158 */       return this.config;
/*     */     }
/*     */     
/*     */     public final String ConfigVersion() {
/* 168 */       return this.ConfigVersion;
/*     */     }
/*     */     
/*     */     public final String ProviderClass() {
/* 169 */       return this.ProviderClass;
/*     */     }
/*     */     
/*     */     public final String SupervisorStrategyClass() {
/* 170 */       return this.SupervisorStrategyClass;
/*     */     }
/*     */     
/*     */     public final Timeout CreationTimeout() {
/* 171 */       return this.CreationTimeout;
/*     */     }
/*     */     
/*     */     public final Timeout UnstartedPushTimeout() {
/* 172 */       return this.UnstartedPushTimeout;
/*     */     }
/*     */     
/*     */     public final boolean SerializeAllMessages() {
/* 174 */       return this.SerializeAllMessages;
/*     */     }
/*     */     
/*     */     public final boolean SerializeAllCreators() {
/* 175 */       return this.SerializeAllCreators;
/*     */     }
/*     */     
/*     */     public final String LogLevel() {
/* 177 */       return this.LogLevel;
/*     */     }
/*     */     
/*     */     public final String StdoutLogLevel() {
/* 178 */       return this.StdoutLogLevel;
/*     */     }
/*     */     
/*     */     public final Seq<String> Loggers() {
/* 179 */       return this.Loggers;
/*     */     }
/*     */     
/*     */     public final Timeout LoggerStartTimeout() {
/* 180 */       return this.LoggerStartTimeout;
/*     */     }
/*     */     
/*     */     public final boolean LogConfigOnStart() {
/* 181 */       return this.LogConfigOnStart;
/*     */     }
/*     */     
/*     */     public final int LogDeadLetters() {
/* 182 */       return this.LogDeadLetters;
/*     */     }
/*     */     
/*     */     public final boolean LogDeadLettersDuringShutdown() {
/* 187 */       return this.LogDeadLettersDuringShutdown;
/*     */     }
/*     */     
/*     */     public final boolean AddLoggingReceive() {
/* 189 */       return this.AddLoggingReceive;
/*     */     }
/*     */     
/*     */     public final boolean DebugAutoReceive() {
/* 190 */       return this.DebugAutoReceive;
/*     */     }
/*     */     
/*     */     public final boolean DebugLifecycle() {
/* 191 */       return this.DebugLifecycle;
/*     */     }
/*     */     
/*     */     public final boolean FsmDebugEvent() {
/* 192 */       return this.FsmDebugEvent;
/*     */     }
/*     */     
/*     */     public final boolean DebugEventStream() {
/* 193 */       return this.DebugEventStream;
/*     */     }
/*     */     
/*     */     public final boolean DebugUnhandledMessage() {
/* 194 */       return this.DebugUnhandledMessage;
/*     */     }
/*     */     
/*     */     public final boolean DebugRouterMisconfiguration() {
/* 195 */       return this.DebugRouterMisconfiguration;
/*     */     }
/*     */     
/*     */     public final Option<String> Home() {
/* 197 */       return this.Home;
/*     */     }
/*     */     
/*     */     public final String SchedulerClass() {
/* 202 */       return this.SchedulerClass;
/*     */     }
/*     */     
/*     */     public final boolean Daemonicity() {
/* 203 */       return this.Daemonicity;
/*     */     }
/*     */     
/*     */     public final boolean JvmExitOnFatalError() {
/* 204 */       return this.JvmExitOnFatalError;
/*     */     }
/*     */     
/*     */     public final int DefaultVirtualNodesFactor() {
/* 206 */       return this.DefaultVirtualNodesFactor;
/*     */     }
/*     */     
/*     */     public String toString() {
/* 214 */       return config().root().render();
/*     */     }
/*     */   }
/*     */   
/*     */   public static class $anonfun$6 extends AbstractFunction1<Class<?>, Object> implements Serializable {
/*     */     public static final long serialVersionUID = 0L;
/*     */     
/*     */     public final boolean apply(Class c) {
/* 224 */       return (c != null && (
/* 225 */         c.getName().startsWith("akka.actor.ActorSystem") || 
/* 226 */         c.getName().startsWith("scala.Option") || 
/* 227 */         c.getName().startsWith("scala.collection.Iterator") || 
/* 228 */         c.getName().startsWith("akka.util.Reflect")));
/*     */     }
/*     */   }
/*     */   
/*     */   public static class ActorSystem$$anonfun$findClassLoader$1 extends AbstractFunction0<Option<ClassLoader>> implements Serializable {
/*     */     public static final long serialVersionUID = 0L;
/*     */     
/*     */     public final Option<ClassLoader> apply() {
/* 235 */       return Reflect$.MODULE$.getCallerClass().map((Function1)new ActorSystem$$anonfun$findClassLoader$1$$anonfun$apply$1(this));
/*     */     }
/*     */     
/*     */     public class ActorSystem$$anonfun$findClassLoader$1$$anonfun$apply$1 extends AbstractFunction1<Function1<Object, Class<?>>, ClassLoader> implements Serializable {
/*     */       public static final long serialVersionUID = 0L;
/*     */       
/*     */       public final ClassLoader apply(Function1 get) {
/* 235 */         return ActorSystem$.MODULE$.akka$actor$ActorSystem$$findCaller$1(get);
/*     */       }
/*     */       
/*     */       public ActorSystem$$anonfun$findClassLoader$1$$anonfun$apply$1(ActorSystem$$anonfun$findClassLoader$1 $outer) {}
/*     */     }
/*     */   }
/*     */   
/*     */   public static class ActorSystem$$anonfun$findClassLoader$2 extends AbstractFunction0<ClassLoader> implements Serializable {
/*     */     public static final long serialVersionUID = 0L;
/*     */     
/*     */     public final ClassLoader apply() {
/* 236 */       return ActorSystem$.MODULE$.getClass().getClassLoader();
/*     */     }
/*     */   }
/*     */   
/*     */   public ActorRef actorFor(ActorPath path) {
/* 271 */     return ActorRefFactory$class.actorFor(this, path);
/*     */   }
/*     */   
/*     */   public ActorRef actorFor(String path) {
/* 271 */     return ActorRefFactory$class.actorFor(this, path);
/*     */   }
/*     */   
/*     */   public ActorRef actorFor(Iterable path) {
/* 271 */     return ActorRefFactory$class.actorFor(this, path);
/*     */   }
/*     */   
/*     */   public ActorRef actorFor(Iterable path) {
/* 271 */     return ActorRefFactory$class.actorFor(this, path);
/*     */   }
/*     */   
/*     */   public ActorSelection actorSelection(String path) {
/* 271 */     return ActorRefFactory$class.actorSelection(this, path);
/*     */   }
/*     */   
/*     */   public ActorSelection actorSelection(ActorPath path) {
/* 271 */     return ActorRefFactory$class.actorSelection(this, path);
/*     */   }
/*     */   
/*     */   public ActorSystem() {
/* 271 */     ActorRefFactory$class.$init$(this);
/* 313 */     this.startTime = System.currentTimeMillis();
/*     */   }
/*     */   
/*     */   public ActorPath child(String child) {
/*     */     return $div(child);
/*     */   }
/*     */   
/*     */   public ActorPath descendant(Iterable names) {
/*     */     return $div((Iterable<String>)Util$.MODULE$.immutableSeq(names));
/*     */   }
/*     */   
/*     */   public long startTime() {
/* 313 */     return this.startTime;
/*     */   }
/*     */   
/*     */   public long uptime() {
/* 318 */     return (System.currentTimeMillis() - startTime()) / 1000L;
/*     */   }
/*     */   
/*     */   public static Option<ExecutionContext> apply$default$4() {
/*     */     return ActorSystem$.MODULE$.apply$default$4();
/*     */   }
/*     */   
/*     */   public static Option<ClassLoader> apply$default$3() {
/*     */     return ActorSystem$.MODULE$.apply$default$3();
/*     */   }
/*     */   
/*     */   public static Option<Config> apply$default$2() {
/*     */     return ActorSystem$.MODULE$.apply$default$2();
/*     */   }
/*     */   
/*     */   public static ActorSystem apply(String paramString, Option<Config> paramOption, Option<ClassLoader> paramOption1, Option<ExecutionContext> paramOption2) {
/*     */     return ActorSystem$.MODULE$.apply(paramString, paramOption, paramOption1, paramOption2);
/*     */   }
/*     */   
/*     */   public static ActorSystem apply(String paramString, Config paramConfig, ClassLoader paramClassLoader) {
/*     */     return ActorSystem$.MODULE$.apply(paramString, paramConfig, paramClassLoader);
/*     */   }
/*     */   
/*     */   public static ActorSystem apply(String paramString, Config paramConfig) {
/*     */     return ActorSystem$.MODULE$.apply(paramString, paramConfig);
/*     */   }
/*     */   
/*     */   public static ActorSystem apply(String paramString) {
/*     */     return ActorSystem$.MODULE$.apply(paramString);
/*     */   }
/*     */   
/*     */   public static ActorSystem apply() {
/*     */     return ActorSystem$.MODULE$.apply();
/*     */   }
/*     */   
/*     */   public static ActorSystem create(String paramString, Config paramConfig, ClassLoader paramClassLoader, ExecutionContext paramExecutionContext) {
/*     */     return ActorSystem$.MODULE$.create(paramString, paramConfig, paramClassLoader, paramExecutionContext);
/*     */   }
/*     */   
/*     */   public static ActorSystem create(String paramString, Config paramConfig, ClassLoader paramClassLoader) {
/*     */     return ActorSystem$.MODULE$.create(paramString, paramConfig, paramClassLoader);
/*     */   }
/*     */   
/*     */   public static ActorSystem create(String paramString, Config paramConfig) {
/*     */     return ActorSystem$.MODULE$.create(paramString, paramConfig);
/*     */   }
/*     */   
/*     */   public static ActorSystem create(String paramString) {
/*     */     return ActorSystem$.MODULE$.create(paramString);
/*     */   }
/*     */   
/*     */   public static ActorSystem create() {
/*     */     return ActorSystem$.MODULE$.create();
/*     */   }
/*     */   
/*     */   public static Option<String> GlobalHome() {
/*     */     return ActorSystem$.MODULE$.GlobalHome();
/*     */   }
/*     */   
/*     */   public static Option<String> SystemHome() {
/*     */     return ActorSystem$.MODULE$.SystemHome();
/*     */   }
/*     */   
/*     */   public static Option<String> EnvHome() {
/*     */     return ActorSystem$.MODULE$.EnvHome();
/*     */   }
/*     */   
/*     */   public static String Version() {
/*     */     return ActorSystem$.MODULE$.Version();
/*     */   }
/*     */   
/*     */   public abstract String name();
/*     */   
/*     */   public abstract Settings settings();
/*     */   
/*     */   public abstract void logConfiguration();
/*     */   
/*     */   public abstract ActorPath $div(String paramString);
/*     */   
/*     */   public abstract ActorPath $div(Iterable<String> paramIterable);
/*     */   
/*     */   public abstract EventStream eventStream();
/*     */   
/*     */   public abstract LoggingAdapter log();
/*     */   
/*     */   public abstract ActorRef deadLetters();
/*     */   
/*     */   public abstract Scheduler scheduler();
/*     */   
/*     */   public abstract Dispatchers dispatchers();
/*     */   
/*     */   public abstract ExecutionContextExecutor dispatcher();
/*     */   
/*     */   public abstract Mailboxes mailboxes();
/*     */   
/*     */   public abstract <T> void registerOnTermination(Function0<T> paramFunction0);
/*     */   
/*     */   public abstract void registerOnTermination(Runnable paramRunnable);
/*     */   
/*     */   public abstract void awaitTermination(Duration paramDuration);
/*     */   
/*     */   public abstract void awaitTermination();
/*     */   
/*     */   public abstract void shutdown();
/*     */   
/*     */   public abstract boolean isTerminated();
/*     */   
/*     */   public abstract <T extends Extension> T registerExtension(ExtensionId<T> paramExtensionId);
/*     */   
/*     */   public abstract <T extends Extension> T extension(ExtensionId<T> paramExtensionId);
/*     */   
/*     */   public abstract boolean hasExtension(ExtensionId<? extends Extension> paramExtensionId);
/*     */ }


/* Location:              D:\#source-code\TheFlightSims\TFSLibrary\World2Xplane\World2XPlane.jar!\akka\actor\ActorSystem.class
 * Java compiler version: 6 (50.0)
 * JD-Core Version:       1.1.3
 */