/*    */ package akka.actor;
/*    */ 
/*    */ import akka.routing.NoRouter$;
/*    */ import akka.routing.RouterConfig;
/*    */ import com.typesafe.config.Config;
/*    */ import com.typesafe.config.ConfigFactory;
/*    */ import scala.Product;
/*    */ import scala.Serializable;
/*    */ import scala.collection.Iterator;
/*    */ import scala.reflect.ScalaSignature;
/*    */ import scala.runtime.BoxesRunTime;
/*    */ import scala.runtime.ScalaRunTime$;
/*    */ 
/*    */ @ScalaSignature(bytes = "\006\001\tUq!B\001\003\021\0039\021A\002#fa2|\027P\003\002\004\t\005)\021m\031;pe*\tQ!\001\003bW.\f7\001\001\t\003\021%i\021A\001\004\006\025\tA\ta\003\002\007\t\026\004Hn\\=\024\007%a!\003\005\002\016!5\taBC\001\020\003\025\0318-\0317b\023\t\tbB\001\004B]f\024VM\032\t\003\033MI!\001\006\b\003\031M+'/[1mSj\f'\r\\3\t\013YIA\021A\f\002\rqJg.\033;?)\0059\001bB\r\n\005\004%)AG\001\022\035>$\025n\0359bi\016DWM]$jm\026tW#A\016\020\003q\t\023!H\001\001\021\031y\022\002)A\0077\005\021bj\034#jgB\fGo\0315fe\036Kg/\0328!\021\035\t\023B1A\005\006i\taBT8NC&d'm\034=HSZ,g\016\003\004$\023\001\006iaG\001\020\035>l\025-\0337c_b<\025N^3oA!9Q%\003b\001\n\0031\023!\0027pG\006dW#A\024\021\005!Ac\001\002\006\003\005&\032B\001\013\007+%A\021QbK\005\003Y9\021q\001\025:pIV\034G\017\003\005/Q\tU\r\021\"\0010\003\021\001\030\r\0365\026\003A\002\"!\r\033\017\0055\021\024BA\032\017\003\031\001&/\0323fM&\021QG\016\002\007'R\024\030N\\4\013\005Mr\001\002\003\035)\005#\005\013\021\002\031\002\013A\fG\017\033\021\t\021iB#Q3A\005\002m\naaY8oM&<W#\001\037\021\005u\032U\"\001 \013\005iz$B\001!B\003!!\030\020]3tC\032,'\"\001\"\002\007\r|W.\003\002E}\t11i\0348gS\036D\001B\022\025\003\022\003\006I\001P\001\bG>tg-[4!\021!A\005F!f\001\n\003I\025\001\004:pkR,'oQ8oM&<W#\001&\021\005-sU\"\001'\013\0055#\021a\002:pkRLgnZ\005\003\0372\023ABU8vi\026\0248i\0348gS\036D\001\"\025\025\003\022\003\006IAS\001\016e>,H/\032:D_:4\027n\032\021\t\021MC#Q3A\005\002Q\013Qa]2pa\026,\022!\026\t\003\021YK!a\026\002\003\013M\033w\016]3\t\021eC#\021#Q\001\nU\013aa]2pa\026\004\003\002C.)\005+\007I\021A\030\002\025\021L7\017]1uG\",'\017\003\005^Q\tE\t\025!\0031\003-!\027n\0359bi\016DWM\035\021\t\021}C#Q3A\005\002=\nq!\\1jY\n|\007\020\003\005bQ\tE\t\025!\0031\003!i\027-\0337c_b\004\003\"\002\f)\t\003\031GcB\024eK\032<\007.\033\005\b]\t\004\n\0211\0011\021\035Q$\r%AA\002qBq\001\0232\021\002\003\007!\nC\004TEB\005\t\031A+\t\017m\023\007\023!a\001a!9qL\031I\001\002\004\001\004\"\002\f)\t\003YGCA\024m\021\025i%\0161\001K\021\0251\002\006\"\001o)\r9s\016\035\005\006\0336\004\rA\023\005\006'6\004\r!\026\005\006-!\"\tA\035\013\003OMDQaU9A\002UCQ!\036\025\005\002Y\fAb^5uQ\032\013G\016\0342bG.$\"aJ<\t\013a$\b\031A\024\002\013=$\b.\032:\t\017iD\023\021!C\001w\006!1m\0349z)%9C0 @\000\003\003\t\031\001C\004/sB\005\t\031\001\031\t\017iJ\b\023!a\001y!9\001*\037I\001\002\004Q\005bB*z!\003\005\r!\026\005\b7f\004\n\0211\0011\021\035y\026\020%AA\002AB\021\"a\002)#\003%\t!!\003\002\035\r|\007/\037\023eK\032\fW\017\034;%cU\021\0211\002\026\004a\00551FAA\b!\021\t\t\"a\007\016\005\005M!\002BA\013\003/\t\021\"\0368dQ\026\0347.\0323\013\007\005ea\"\001\006b]:|G/\031;j_:LA!!\b\002\024\t\tRO\\2iK\016\\W\r\032,be&\fgnY3\t\023\005\005\002&%A\005\002\005\r\022AD2paf$C-\0324bk2$HEM\013\003\003KQ3\001PA\007\021%\tI\003KI\001\n\003\tY#\001\bd_BLH\005Z3gCVdG\017J\032\026\005\0055\"f\001&\002\016!I\021\021\007\025\022\002\023\005\0211G\001\017G>\004\030\020\n3fM\006,H\016\036\0235+\t\t)DK\002V\003\033A\021\"!\017)#\003%\t!!\003\002\035\r|\007/\037\023eK\032\fW\017\034;%k!I\021Q\b\025\022\002\023\005\021\021B\001\017G>\004\030\020\n3fM\006,H\016\036\0237\021%\t\t\005KA\001\n\003\n\031%A\007qe>$Wo\031;Qe\0264\027\016_\013\003\003\013\002B!a\022\002R5\021\021\021\n\006\005\003\027\ni%\001\003mC:<'BAA(\003\021Q\027M^1\n\007U\nI\005C\005\002V!\n\t\021\"\001\002X\005a\001O]8ek\016$\030I]5usV\021\021\021\f\t\004\033\005m\023bAA/\035\t\031\021J\034;\t\023\005\005\004&!A\005\002\005\r\024A\0049s_\022,8\r^#mK6,g\016\036\013\005\003K\nY\007E\002\016\003OJ1!!\033\017\005\r\te.\037\005\013\003[\ny&!AA\002\005e\023a\001=%c!I\021\021\017\025\002\002\023\005\0231O\001\020aJ|G-^2u\023R,'/\031;peV\021\021Q\017\t\007\003o\ni(!\032\016\005\005e$bAA>\035\005Q1m\0347mK\016$\030n\0348\n\t\005}\024\021\020\002\t\023R,'/\031;pe\"I\0211\021\025\002\002\023\005\021QQ\001\tG\006tW)];bYR!\021qQAG!\ri\021\021R\005\004\003\027s!a\002\"p_2,\027M\034\005\013\003[\n\t)!AA\002\005\025\004\"CAIQ\005\005I\021IAJ\003!A\027m\0355D_\022,GCAA-\021%\t9\nKA\001\n\003\nI*\001\005u_N#(/\0338h)\t\t)\005C\005\002\036\"\n\t\021\"\021\002 \0061Q-];bYN$B!a\"\002\"\"Q\021QNAN\003\003\005\r!!\032)\013!\n)+a+\021\0075\t9+C\002\002*:\021\001cU3sS\006dg+\032:tS>tW+\023#\037\003\tAq!a,\nA\003%q%\001\004m_\016\fG\016\t\005\n\003gK\021\021!CA\003k\013Q!\0319qYf$RbJA\\\003s\013Y,!0\002@\006\005\007\002\003\030\0022B\005\t\031\001\031\t\021i\n\t\f%AA\002qB\001\002SAY!\003\005\rA\023\005\t'\006E\006\023!a\001+\"A1,!-\021\002\003\007\001\007\003\005`\003c\003\n\0211\0011\021%\t)-CA\001\n\003\0139-A\004v]\006\004\b\017\\=\025\t\005%\027Q\033\t\006\033\005-\027qZ\005\004\003\033t!AB(qi&|g\016E\005\016\003#\004DHS+1a%\031\0211\033\b\003\rQ+\b\017\\37\021%\t9.a1\002\002\003\007q%A\002yIAB\021\"a7\n#\003%\t!!\003\0027\021bWm]:j]&$He\032:fCR,'\017\n3fM\006,H\016\036\0232\021%\ty.CI\001\n\003\t\031#A\016%Y\026\0348/\0338ji\022:'/Z1uKJ$C-\0324bk2$HE\r\005\n\003GL\021\023!C\001\003W\t1\004\n7fgNLg.\033;%OJ,\027\r^3sI\021,g-Y;mi\022\032\004\"CAt\023E\005I\021AA\032\003m!C.Z:tS:LG\017J4sK\006$XM\035\023eK\032\fW\017\034;%i!I\0211^\005\022\002\023\005\021\021B\001\034I1,7o]5oSR$sM]3bi\026\024H\005Z3gCVdG\017J\033\t\023\005=\030\"%A\005\002\005%\021a\007\023mKN\034\030N\\5uI\035\024X-\031;fe\022\"WMZ1vYR$c\007C\005\002t&\t\n\021\"\001\002\n\005y\021\r\0359ms\022\"WMZ1vYR$\023\007C\005\002x&\t\n\021\"\001\002$\005y\021\r\0359ms\022\"WMZ1vYR$#\007C\005\002|&\t\n\021\"\001\002,\005y\021\r\0359ms\022\"WMZ1vYR$3\007C\005\002\000&\t\n\021\"\001\0024\005y\021\r\0359ms\022\"WMZ1vYR$C\007C\005\003\004%\t\n\021\"\001\002\n\005y\021\r\0359ms\022\"WMZ1vYR$S\007C\005\003\b%\t\n\021\"\001\002\n\005y\021\r\0359ms\022\"WMZ1vYR$c\007C\005\003\f%\t\t\021\"\003\003\016\005Y!/Z1e%\026\034x\016\034<f)\t\021y\001\005\003\002H\tE\021\002\002B\n\003\023\022aa\0242kK\016$\b")
/*    */ public final class Deploy implements Product, Serializable {
/*    */   public static final long serialVersionUID = 2L;
/*    */   
/*    */   private final String path;
/*    */   
/*    */   private final Config config;
/*    */   
/*    */   private final RouterConfig routerConfig;
/*    */   
/*    */   private final Scope scope;
/*    */   
/*    */   private final String dispatcher;
/*    */   
/*    */   private final String mailbox;
/*    */   
/*    */   public Deploy copy(String path, Config config, RouterConfig routerConfig, Scope scope, String dispatcher, String mailbox) {
/* 38 */     return new Deploy(
/* 39 */         path, 
/* 40 */         config, 
/* 41 */         routerConfig, 
/* 42 */         scope, 
/* 43 */         dispatcher, 
/* 44 */         mailbox);
/*    */   }
/*    */   
/*    */   public String productPrefix() {
/*    */     return "Deploy";
/*    */   }
/*    */   
/*    */   public int productArity() {
/*    */     return 6;
/*    */   }
/*    */   
/*    */   public Object productElement(int x$1) {
/*    */     int i = x$1;
/*    */     switch (i) {
/*    */       default:
/*    */         throw new IndexOutOfBoundsException(BoxesRunTime.boxToInteger(x$1).toString());
/*    */       case 5:
/*    */       
/*    */       case 4:
/*    */       
/*    */       case 3:
/*    */       
/*    */       case 2:
/*    */       
/*    */       case 1:
/*    */       
/*    */       case 0:
/*    */         break;
/*    */     } 
/*    */     return path();
/*    */   }
/*    */   
/*    */   public Iterator<Object> productIterator() {
/*    */     return ScalaRunTime$.MODULE$.typedProductIterator(this);
/*    */   }
/*    */   
/*    */   public boolean canEqual(Object x$1) {
/*    */     return x$1 instanceof Deploy;
/*    */   }
/*    */   
/*    */   public int hashCode() {
/*    */     return ScalaRunTime$.MODULE$._hashCode(this);
/*    */   }
/*    */   
/*    */   public String toString() {
/*    */     return ScalaRunTime$.MODULE$._toString(this);
/*    */   }
/*    */   
/*    */   public boolean equals(Object x$1) {
/*    */     // Byte code:
/*    */     //   0: aload_0
/*    */     //   1: aload_1
/*    */     //   2: if_acmpeq -> 231
/*    */     //   5: aload_1
/*    */     //   6: astore_2
/*    */     //   7: aload_2
/*    */     //   8: instanceof akka/actor/Deploy
/*    */     //   11: ifeq -> 19
/*    */     //   14: iconst_1
/*    */     //   15: istore_3
/*    */     //   16: goto -> 21
/*    */     //   19: iconst_0
/*    */     //   20: istore_3
/*    */     //   21: iload_3
/*    */     //   22: ifeq -> 235
/*    */     //   25: aload_1
/*    */     //   26: checkcast akka/actor/Deploy
/*    */     //   29: astore #4
/*    */     //   31: aload_0
/*    */     //   32: invokevirtual path : ()Ljava/lang/String;
/*    */     //   35: aload #4
/*    */     //   37: invokevirtual path : ()Ljava/lang/String;
/*    */     //   40: astore #5
/*    */     //   42: dup
/*    */     //   43: ifnonnull -> 55
/*    */     //   46: pop
/*    */     //   47: aload #5
/*    */     //   49: ifnull -> 63
/*    */     //   52: goto -> 227
/*    */     //   55: aload #5
/*    */     //   57: invokevirtual equals : (Ljava/lang/Object;)Z
/*    */     //   60: ifeq -> 227
/*    */     //   63: aload_0
/*    */     //   64: invokevirtual config : ()Lcom/typesafe/config/Config;
/*    */     //   67: aload #4
/*    */     //   69: invokevirtual config : ()Lcom/typesafe/config/Config;
/*    */     //   72: astore #6
/*    */     //   74: dup
/*    */     //   75: ifnonnull -> 87
/*    */     //   78: pop
/*    */     //   79: aload #6
/*    */     //   81: ifnull -> 95
/*    */     //   84: goto -> 227
/*    */     //   87: aload #6
/*    */     //   89: invokevirtual equals : (Ljava/lang/Object;)Z
/*    */     //   92: ifeq -> 227
/*    */     //   95: aload_0
/*    */     //   96: invokevirtual routerConfig : ()Lakka/routing/RouterConfig;
/*    */     //   99: aload #4
/*    */     //   101: invokevirtual routerConfig : ()Lakka/routing/RouterConfig;
/*    */     //   104: astore #7
/*    */     //   106: dup
/*    */     //   107: ifnonnull -> 119
/*    */     //   110: pop
/*    */     //   111: aload #7
/*    */     //   113: ifnull -> 127
/*    */     //   116: goto -> 227
/*    */     //   119: aload #7
/*    */     //   121: invokevirtual equals : (Ljava/lang/Object;)Z
/*    */     //   124: ifeq -> 227
/*    */     //   127: aload_0
/*    */     //   128: invokevirtual scope : ()Lakka/actor/Scope;
/*    */     //   131: aload #4
/*    */     //   133: invokevirtual scope : ()Lakka/actor/Scope;
/*    */     //   136: astore #8
/*    */     //   138: dup
/*    */     //   139: ifnonnull -> 151
/*    */     //   142: pop
/*    */     //   143: aload #8
/*    */     //   145: ifnull -> 159
/*    */     //   148: goto -> 227
/*    */     //   151: aload #8
/*    */     //   153: invokevirtual equals : (Ljava/lang/Object;)Z
/*    */     //   156: ifeq -> 227
/*    */     //   159: aload_0
/*    */     //   160: invokevirtual dispatcher : ()Ljava/lang/String;
/*    */     //   163: aload #4
/*    */     //   165: invokevirtual dispatcher : ()Ljava/lang/String;
/*    */     //   168: astore #9
/*    */     //   170: dup
/*    */     //   171: ifnonnull -> 183
/*    */     //   174: pop
/*    */     //   175: aload #9
/*    */     //   177: ifnull -> 191
/*    */     //   180: goto -> 227
/*    */     //   183: aload #9
/*    */     //   185: invokevirtual equals : (Ljava/lang/Object;)Z
/*    */     //   188: ifeq -> 227
/*    */     //   191: aload_0
/*    */     //   192: invokevirtual mailbox : ()Ljava/lang/String;
/*    */     //   195: aload #4
/*    */     //   197: invokevirtual mailbox : ()Ljava/lang/String;
/*    */     //   200: astore #10
/*    */     //   202: dup
/*    */     //   203: ifnonnull -> 215
/*    */     //   206: pop
/*    */     //   207: aload #10
/*    */     //   209: ifnull -> 223
/*    */     //   212: goto -> 227
/*    */     //   215: aload #10
/*    */     //   217: invokevirtual equals : (Ljava/lang/Object;)Z
/*    */     //   220: ifeq -> 227
/*    */     //   223: iconst_1
/*    */     //   224: goto -> 228
/*    */     //   227: iconst_0
/*    */     //   228: ifeq -> 235
/*    */     //   231: iconst_1
/*    */     //   232: goto -> 236
/*    */     //   235: iconst_0
/*    */     //   236: ireturn
/*    */     // Line number table:
/*    */     //   Java source line number -> byte code offset
/*    */     //   #38	-> 0
/*    */     //   #63	-> 14
/*    */     //   #38	-> 21
/*    */     // Local variable table:
/*    */     //   start	length	slot	name	descriptor
/*    */     //   0	237	0	this	Lakka/actor/Deploy;
/*    */     //   0	237	1	x$1	Ljava/lang/Object;
/*    */   }
/*    */   
/*    */   public String path() {
/*    */     return this.path;
/*    */   }
/*    */   
/*    */   public String copy$default$1() {
/*    */     return path();
/*    */   }
/*    */   
/*    */   public Deploy(String path, Config config, RouterConfig routerConfig, Scope scope, String dispatcher, String mailbox) {
/*    */     Product.class.$init$(this);
/*    */   }
/*    */   
/*    */   public Config config() {
/*    */     return this.config;
/*    */   }
/*    */   
/*    */   public Config copy$default$2() {
/*    */     return config();
/*    */   }
/*    */   
/*    */   public RouterConfig routerConfig() {
/*    */     return this.routerConfig;
/*    */   }
/*    */   
/*    */   public RouterConfig copy$default$3() {
/*    */     return routerConfig();
/*    */   }
/*    */   
/*    */   public Scope scope() {
/*    */     return this.scope;
/*    */   }
/*    */   
/*    */   public Scope copy$default$4() {
/*    */     return scope();
/*    */   }
/*    */   
/*    */   public String dispatcher() {
/*    */     return this.dispatcher;
/*    */   }
/*    */   
/*    */   public String copy$default$5() {
/*    */     return dispatcher();
/*    */   }
/*    */   
/*    */   public String mailbox() {
/* 44 */     return this.mailbox;
/*    */   }
/*    */   
/*    */   public String copy$default$6() {
/* 44 */     return mailbox();
/*    */   }
/*    */   
/*    */   public Deploy(RouterConfig routing) {
/* 49 */     this("", ConfigFactory.empty(), routing, Deploy$.MODULE$.$lessinit$greater$default$4(), Deploy$.MODULE$.$lessinit$greater$default$5(), Deploy$.MODULE$.$lessinit$greater$default$6());
/*    */   }
/*    */   
/*    */   public Deploy(RouterConfig routing, Scope scope) {
/* 54 */     this("", ConfigFactory.empty(), routing, scope, Deploy$.MODULE$.$lessinit$greater$default$5(), Deploy$.MODULE$.$lessinit$greater$default$6());
/*    */   }
/*    */   
/*    */   public Deploy(Scope scope) {
/* 59 */     this("", ConfigFactory.empty(), (RouterConfig)NoRouter$.MODULE$, scope, Deploy$.MODULE$.$lessinit$greater$default$5(), Deploy$.MODULE$.$lessinit$greater$default$6());
/*    */   }
/*    */   
/*    */   public Deploy withFallback(Deploy other) {
/*    */     // Byte code:
/*    */     //   0: new akka/actor/Deploy
/*    */     //   3: dup
/*    */     //   4: aload_0
/*    */     //   5: invokevirtual path : ()Ljava/lang/String;
/*    */     //   8: aload_0
/*    */     //   9: invokevirtual config : ()Lcom/typesafe/config/Config;
/*    */     //   12: aload_1
/*    */     //   13: invokevirtual config : ()Lcom/typesafe/config/Config;
/*    */     //   16: invokeinterface withFallback : (Lcom/typesafe/config/ConfigMergeable;)Lcom/typesafe/config/Config;
/*    */     //   21: aload_0
/*    */     //   22: invokevirtual routerConfig : ()Lakka/routing/RouterConfig;
/*    */     //   25: aload_1
/*    */     //   26: invokevirtual routerConfig : ()Lakka/routing/RouterConfig;
/*    */     //   29: invokeinterface withFallback : (Lakka/routing/RouterConfig;)Lakka/routing/RouterConfig;
/*    */     //   34: aload_0
/*    */     //   35: invokevirtual scope : ()Lakka/actor/Scope;
/*    */     //   38: aload_1
/*    */     //   39: invokevirtual scope : ()Lakka/actor/Scope;
/*    */     //   42: invokeinterface withFallback : (Lakka/actor/Scope;)Lakka/actor/Scope;
/*    */     //   47: aload_0
/*    */     //   48: invokevirtual dispatcher : ()Ljava/lang/String;
/*    */     //   51: ldc ''
/*    */     //   53: astore_2
/*    */     //   54: dup
/*    */     //   55: ifnonnull -> 66
/*    */     //   58: pop
/*    */     //   59: aload_2
/*    */     //   60: ifnull -> 73
/*    */     //   63: goto -> 80
/*    */     //   66: aload_2
/*    */     //   67: invokevirtual equals : (Ljava/lang/Object;)Z
/*    */     //   70: ifeq -> 80
/*    */     //   73: aload_1
/*    */     //   74: invokevirtual dispatcher : ()Ljava/lang/String;
/*    */     //   77: goto -> 84
/*    */     //   80: aload_0
/*    */     //   81: invokevirtual dispatcher : ()Ljava/lang/String;
/*    */     //   84: aload_0
/*    */     //   85: invokevirtual mailbox : ()Ljava/lang/String;
/*    */     //   88: ldc ''
/*    */     //   90: astore_3
/*    */     //   91: dup
/*    */     //   92: ifnonnull -> 103
/*    */     //   95: pop
/*    */     //   96: aload_3
/*    */     //   97: ifnull -> 110
/*    */     //   100: goto -> 117
/*    */     //   103: aload_3
/*    */     //   104: invokevirtual equals : (Ljava/lang/Object;)Z
/*    */     //   107: ifeq -> 117
/*    */     //   110: aload_1
/*    */     //   111: invokevirtual mailbox : ()Ljava/lang/String;
/*    */     //   114: goto -> 121
/*    */     //   117: aload_0
/*    */     //   118: invokevirtual mailbox : ()Ljava/lang/String;
/*    */     //   121: invokespecial <init> : (Ljava/lang/String;Lcom/typesafe/config/Config;Lakka/routing/RouterConfig;Lakka/actor/Scope;Ljava/lang/String;Ljava/lang/String;)V
/*    */     //   124: areturn
/*    */     // Line number table:
/*    */     //   Java source line number -> byte code offset
/*    */     //   #67	-> 0
/*    */     //   #68	-> 4
/*    */     //   #69	-> 8
/*    */     //   #70	-> 21
/*    */     //   #71	-> 34
/*    */     //   #72	-> 47
/*    */     //   #73	-> 84
/*    */     //   #67	-> 121
/*    */     // Local variable table:
/*    */     //   start	length	slot	name	descriptor
/*    */     //   0	125	0	this	Lakka/actor/Deploy;
/*    */     //   0	125	1	other	Lakka/actor/Deploy;
/*    */   }
/*    */   
/*    */   public static String apply$default$6() {
/*    */     return Deploy$.MODULE$.apply$default$6();
/*    */   }
/*    */   
/*    */   public static String apply$default$5() {
/*    */     return Deploy$.MODULE$.apply$default$5();
/*    */   }
/*    */   
/*    */   public static Scope apply$default$4() {
/*    */     return Deploy$.MODULE$.apply$default$4();
/*    */   }
/*    */   
/*    */   public static RouterConfig apply$default$3() {
/*    */     return Deploy$.MODULE$.apply$default$3();
/*    */   }
/*    */   
/*    */   public static Config apply$default$2() {
/*    */     return Deploy$.MODULE$.apply$default$2();
/*    */   }
/*    */   
/*    */   public static String apply$default$1() {
/*    */     return Deploy$.MODULE$.apply$default$1();
/*    */   }
/*    */   
/*    */   public static String $lessinit$greater$default$6() {
/*    */     return Deploy$.MODULE$.$lessinit$greater$default$6();
/*    */   }
/*    */   
/*    */   public static String $lessinit$greater$default$5() {
/*    */     return Deploy$.MODULE$.$lessinit$greater$default$5();
/*    */   }
/*    */   
/*    */   public static Scope $lessinit$greater$default$4() {
/*    */     return Deploy$.MODULE$.$lessinit$greater$default$4();
/*    */   }
/*    */   
/*    */   public static RouterConfig $lessinit$greater$default$3() {
/*    */     return Deploy$.MODULE$.$lessinit$greater$default$3();
/*    */   }
/*    */   
/*    */   public static Config $lessinit$greater$default$2() {
/*    */     return Deploy$.MODULE$.$lessinit$greater$default$2();
/*    */   }
/*    */   
/*    */   public static String $lessinit$greater$default$1() {
/*    */     return Deploy$.MODULE$.$lessinit$greater$default$1();
/*    */   }
/*    */   
/*    */   public static Deploy local() {
/*    */     return Deploy$.MODULE$.local();
/*    */   }
/*    */   
/*    */   public static String NoMailboxGiven() {
/*    */     return Deploy$.MODULE$.NoMailboxGiven();
/*    */   }
/*    */   
/*    */   public static String NoDispatcherGiven() {
/*    */     return Deploy$.MODULE$.NoDispatcherGiven();
/*    */   }
/*    */ }


/* Location:              D:\#source-code\TheFlightSims\TFSLibrary\World2Xplane\World2XPlane.jar!\akka\actor\Deploy.class
 * Java compiler version: 6 (50.0)
 * JD-Core Version:       1.1.3
 */