/*     */ package akka.actor;
/*     */ 
/*     */ import akka.routing.Deafen;
/*     */ import akka.routing.Listen;
/*     */ import akka.routing.Listeners;
/*     */ import scala.Function1;
/*     */ import scala.Function2;
/*     */ import scala.Option;
/*     */ import scala.PartialFunction;
/*     */ import scala.Product;
/*     */ import scala.Serializable;
/*     */ import scala.Some;
/*     */ import scala.Tuple2;
/*     */ import scala.Tuple3;
/*     */ import scala.Tuple4;
/*     */ import scala.Tuple5;
/*     */ import scala.collection.Iterator;
/*     */ import scala.collection.immutable.List;
/*     */ import scala.collection.mutable.Map;
/*     */ import scala.collection.mutable.StringBuilder;
/*     */ import scala.concurrent.ExecutionContext;
/*     */ import scala.concurrent.ExecutionContextExecutor;
/*     */ import scala.concurrent.duration.Duration;
/*     */ import scala.concurrent.duration.FiniteDuration;
/*     */ import scala.reflect.ScalaSignature;
/*     */ import scala.runtime.AbstractFunction0;
/*     */ import scala.runtime.AbstractFunction1;
/*     */ import scala.runtime.AbstractPartialFunction;
/*     */ import scala.runtime.BoxedUnit;
/*     */ import scala.runtime.BoxesRunTime;
/*     */ import scala.runtime.Statics;
/*     */ import scala.runtime.TraitSetter;
/*     */ 
/*     */ @ScalaSignature(bytes = "\006\001-}v!B\001\003\021\0039\021a\001$T\033*\0211\001B\001\006C\016$xN\035\006\002\013\005!\021m[6b\007\001\001\"\001C\005\016\003\t1QA\003\002\t\002-\0211AR*N'\tIA\002\005\002\016!5\taBC\001\020\003\025\0318-\0317b\023\t\tbB\001\004B]f\024VM\032\005\006'%!\t\001F\001\007y%t\027\016\036 \025\003\0359QAF\005\t\002]\tABT;mY\032+hn\031;j_:\004\"\001G\r\016\003%1QAG\005\t\002m\021ABT;mY\032+hn\031;j_:\0342!\007\007\035!\021iQd\b\022\n\005yq!a\004)beRL\027\r\034$v]\016$\030n\0348\021\0055\001\023BA\021\017\005\r\te.\037\t\003\033\rJ!\001\n\b\003\0179{G\017[5oO\")1#\007C\001MQ\tq\003C\003)3\021\005\021&A\006jg\022+g-\0338fI\006#HC\001\026.!\ti1&\003\002-\035\t9!i\\8mK\006t\007\"\002\030(\001\004y\022!A8\t\013AJB\021A\031\002\013\005\004\b\017\\=\025\005\t\022\004\"\002\0300\001\004yb\001\002\033\n\001V\022AbQ;se\026tGo\025;bi\026,\"A\016&\024\tMbqG\017\t\003\033aJ!!\017\b\003\017A\023x\016Z;diB\021QbO\005\003y9\021AbU3sS\006d\027N_1cY\026D\001BP\032\003\026\004%\taP\001\007MNl'+\0324\026\003\001\003\"\001C!\n\005\t\023!\001C!di>\024(+\0324\t\021\021\033$\021#Q\001\n\001\013qAZ:n%\0264\007\005\003\005Gg\tU\r\021\"\001H\003\025\031H/\031;f+\005A\005CA%K\031\001!QaS\032C\0021\023\021aU\t\003E}A\001BT\032\003\022\003\006I\001S\001\007gR\fG/\032\021\t\013M\031D\021\001)\025\007E\0236\013E\002\031g!CQAP(A\002\001CQAR(A\002!Cq!V\032\002\002\023\005a+\001\003d_BLXCA,[)\rA6\f\030\t\0041MJ\006CA%[\t\025YEK1\001M\021\035qD\013%AA\002\001CqA\022+\021\002\003\007\021\fC\004_gE\005I\021A0\002\035\r|\007/\037\023eK\032\fW\017\034;%cU\021\001m[\013\002C*\022\001IY\026\002GB\021A-[\007\002K*\021amZ\001\nk:\034\007.Z2lK\022T!\001\033\b\002\025\005tgn\034;bi&|g.\003\002kK\n\tRO\\2iK\016\\W\r\032,be&\fgnY3\005\013-k&\031\001'\t\0175\034\024\023!C\001]\006q1m\0349zI\021,g-Y;mi\022\022TCA8r+\005\001(F\001%c\t\025YEN1\001M\021\035\0318'!A\005BQ\fQ\002\035:pIV\034G\017\025:fM&DX#A;\021\005Y\\X\"A<\013\005aL\030\001\0027b]\036T\021A_\001\005U\0064\030-\003\002}o\n11\013\036:j]\036DqA`\032\002\002\023\005q0\001\007qe>$Wo\031;Be&$\0300\006\002\002\002A\031Q\"a\001\n\007\005\025aBA\002J]RD\021\"!\0034\003\003%\t!a\003\002\035A\024x\016Z;di\026cW-\\3oiR\031q$!\004\t\025\005=\021qAA\001\002\004\t\t!A\002yIEB\021\"a\0054\003\003%\t%!\006\002\037A\024x\016Z;di&#XM]1u_J,\"!a\006\021\013\005e\021qD\020\016\005\005m!bAA\017\035\005Q1m\0347mK\016$\030n\0348\n\t\005\005\0221\004\002\t\023R,'/\031;pe\"I\021QE\032\002\002\023\005\021qE\001\tG\006tW)];bYR\031!&!\013\t\023\005=\0211EA\001\002\004y\002\"CA\027g\005\005I\021IA\030\003!A\027m\0355D_\022,GCAA\001\021%\t\031dMA\001\n\003\n)$\001\005u_N#(/\0338h)\005)\b\"CA\035g\005\005I\021IA\036\003\031)\027/^1mgR\031!&!\020\t\023\005=\021qGA\001\002\004yr!CA!\023\005\005\t\022AA\"\0031\031UO\035:f]R\034F/\031;f!\rA\022Q\t\004\ti%\t\t\021#\001\002HM!\021Q\t\007;\021\035\031\022Q\tC\001\003\027\"\"!a\021\t\025\005M\022QIA\001\n\013\n)\004C\0051\003\013\n\t\021\"!\002RU!\0211KA-)\031\t)&a\027\002^A!\001dMA,!\rI\025\021\f\003\007\027\006=#\031\001'\t\ry\ny\0051\001A\021\0351\025q\na\001\003/B!\"!\031\002F\005\005I\021QA2\003\035)h.\0319qYf,B!!\032\002vQ!\021qMA<!\025i\021\021NA7\023\r\tYG\004\002\007\037B$\030n\0348\021\r5\ty\007QA:\023\r\t\tH\004\002\007)V\004H.\032\032\021\007%\013)\b\002\004L\003?\022\r\001\024\005\013\003s\ny&!AA\002\005m\024a\001=%aA!\001dMA:\021)\ty(!\022\002\002\023%\021\021Q\001\fe\026\fGMU3t_24X\r\006\002\002\004B\031a/!\"\n\007\005\035uO\001\004PE*,7\r\036\004\007\003\027K\001)!$\003\025Q\023\030M\\:ji&|g.\006\003\002\020\006u5#BAE\031]R\004\"\003 \002\n\nU\r\021\"\001@\021%!\025\021\022B\tB\003%\001\tC\006\002\030\006%%Q3A\005\002\005e\025\001\0024s_6,\"!a'\021\007%\013i\n\002\004L\003\023\023\r\001\024\005\f\003C\013II!E!\002\023\tY*A\003ge>l\007\005C\006\002&\006%%Q3A\005\002\005e\025A\001;p\021-\tI+!#\003\022\003\006I!a'\002\007Q|\007\005C\004\024\003\023#\t!!,\025\021\005=\026\021WAZ\003k\003R\001GAE\0037CaAPAV\001\004\001\005\002CAL\003W\003\r!a'\t\021\005\025\0261\026a\001\0037C\021\"VAE\003\003%\t!!/\026\t\005m\026\021\031\013\t\003{\013\031-!2\002HB)\001$!#\002@B\031\021*!1\005\r-\0139L1\001M\021!q\024q\027I\001\002\004\001\005BCAL\003o\003\n\0211\001\002@\"Q\021QUA\\!\003\005\r!a0\t\023y\013I)%A\005\002\005-Wc\0011\002N\02211*!3C\0021C\021\"\\AE#\003%\t!!5\026\t\005M\027q[\013\003\003+T3!a'c\t\031Y\025q\032b\001\031\"Q\0211\\AE#\003%\t!!8\002\035\r|\007/\037\023eK\032\fW\017\034;%gU!\0211[Ap\t\031Y\025\021\034b\001\031\"A1/!#\002\002\023\005C\017\003\005\003\023\013\t\021\"\001\000\021)\tI!!#\002\002\023\005\021q\035\013\004?\005%\bBCA\b\003K\f\t\0211\001\002\002!Q\0211CAE\003\003%\t%!\006\t\025\005\025\022\021RA\001\n\003\ty\017F\002+\003cD\021\"a\004\002n\006\005\t\031A\020\t\025\0055\022\021RA\001\n\003\ny\003\003\006\0024\005%\025\021!C!\003kA!\"!\017\002\n\006\005I\021IA})\rQ\0231 \005\n\003\037\t90!AA\002}9\021\"a@\n\003\003E\tA!\001\002\025Q\023\030M\\:ji&|g\016E\002\031\005\0071\021\"a#\n\003\003E\tA!\002\024\t\t\rAB\017\005\b'\t\rA\021\001B\005)\t\021\t\001\003\006\0024\t\r\021\021!C#\003kA\021\002\rB\002\003\003%\tIa\004\026\t\tE!q\003\013\t\005'\021IBa\007\003\036A)\001$!#\003\026A\031\021Ja\006\005\r-\023iA1\001M\021\031q$Q\002a\001\001\"A\021q\023B\007\001\004\021)\002\003\005\002&\n5\001\031\001B\013\021)\t\tGa\001\002\002\023\005%\021E\013\005\005G\021y\003\006\003\003&\tE\002#B\007\002j\t\035\002\003C\007\003*\001\023iC!\f\n\007\t-bB\001\004UkBdWm\r\t\004\023\n=BAB&\003 \t\007A\n\003\006\002z\t}\021\021!a\001\005g\001R\001GAE\005[A!\"a \003\004\005\005I\021BAA\r\031\021I$\003!\003<\tY2+\0362tGJL'-\032+sC:\034\030\016^5p]\016\013G\016\034\"bG.\034RAa\016\roiB!Ba\020\0038\tU\r\021\"\001@\003!\t7\r^8s%\0264\007B\003B\"\005o\021\t\022)A\005\001\006I\021m\031;peJ+g\r\t\005\b'\t]B\021\001B$)\021\021IEa\023\021\007a\0219\004C\004\003@\t\025\003\031\001!\t\023U\0239$!A\005\002\t=C\003\002B%\005#B\021Ba\020\003NA\005\t\031\001!\t\021y\0239$%A\005\002\001D\001b\035B\034\003\003%\t\005\036\005\t}\n]\022\021!C\001\"Q\021\021\002B\034\003\003%\tAa\027\025\007}\021i\006\003\006\002\020\te\023\021!a\001\003\003A!\"a\005\0038\005\005I\021IA\013\021)\t)Ca\016\002\002\023\005!1\r\013\004U\t\025\004\"CA\b\005C\n\t\0211\001 \021)\tiCa\016\002\002\023\005\023q\006\005\013\003g\0219$!A\005B\005U\002BCA\035\005o\t\t\021\"\021\003nQ\031!Fa\034\t\023\005=!1NA\001\002\004yr!\003B:\023\005\005\t\022\001B;\003m\031VOY:de&\024W\r\026:b]NLG/[8o\007\006dGNQ1dWB\031\001Da\036\007\023\te\022\"!A\t\002\te4#\002B<\005wR\004c\002B?\005\007\003%\021J\007\003\005R1A!!\017\003\035\021XO\034;j[\026LAA!\"\003\000\t\t\022IY:ue\006\034GOR;oGRLwN\\\031\t\017M\0219\b\"\001\003\nR\021!Q\017\005\013\003g\0219(!A\005F\005U\002\"\003\031\003x\005\005I\021\021BH)\021\021IE!%\t\017\t}\"Q\022a\001\001\"Q\021\021\rB<\003\003%\tI!&\025\t\t]%\021\024\t\005\033\005%\004\t\003\006\002z\tM\025\021!a\001\005\023B!\"a \003x\005\005I\021BAA\r\031\021y*\003!\003\"\niRK\\:vEN\034'/\0332f)J\fgn]5uS>t7)\0317m\005\006\0347nE\003\003\03629$\b\003\006\003@\tu%Q3A\005\002}B!Ba\021\003\036\nE\t\025!\003A\021\035\031\"Q\024C\001\005S#BAa+\003.B\031\001D!(\t\017\t}\"q\025a\001\001\"IQK!(\002\002\023\005!\021\027\013\005\005W\023\031\fC\005\003@\t=\006\023!a\001\001\"AaL!(\022\002\023\005\001\r\003\005t\005;\013\t\021\"\021u\021!q(QTA\001\n\003y\bBCA\005\005;\013\t\021\"\001\003>R\031qDa0\t\025\005=!1XA\001\002\004\t\t\001\003\006\002\024\tu\025\021!C!\003+A!\"!\n\003\036\006\005I\021\001Bc)\rQ#q\031\005\n\003\037\021\031-!AA\002}A!\"!\f\003\036\006\005I\021IA\030\021)\t\031D!(\002\002\023\005\023Q\007\005\013\003s\021i*!A\005B\t=Gc\001\026\003R\"I\021q\002Bg\003\003\005\raH\004\n\005+L\021\021!E\001\005/\fQ$\0268tk\n\0348M]5cKR\023\030M\\:ji&|gnQ1mY\n\0137m\033\t\0041\teg!\003BP\023\005\005\t\022\001Bn'\025\021IN!8;!\035\021iHa!A\005WCqa\005Bm\t\003\021\t\017\006\002\003X\"Q\0211\007Bm\003\003%)%!\016\t\023A\022I.!A\005\002\n\035H\003\002BV\005SDqAa\020\003f\002\007\001\t\003\006\002b\te\027\021!CA\005[$BAa&\003p\"Q\021\021\020Bv\003\003\005\rAa+\t\025\005}$\021\\A\001\n\023\t\tIB\005\003v&\001\n1%\t\003x\n1!+Z1t_:\0342Aa=\rS!\021\031Pa?\004>\r\005dA\002B\023\001\023yPA\004GC&dWO]3\024\017\tmHb!\0018uA\031\001Da=\t\027\r\025!1 BK\002\023\0051qA\001\006G\006,8/Z\013\002?!Q11\002B~\005#\005\013\021B\020\002\r\r\fWo]3!\021\035\031\"1 C\001\007\037!Ba!\005\004\024A\031\001Da?\t\017\r\0251Q\002a\001?!IQKa?\002\002\023\0051q\003\013\005\007#\031I\002C\005\004\006\rU\001\023!a\001?!IaLa?\022\002\023\0051QD\013\003\007?Q#a\b2\t\021M\024Y0!A\005BQD\001B B~\003\003%\ta \005\013\003\023\021Y0!A\005\002\r\035BcA\020\004*!Q\021qBB\023\003\003\005\r!!\001\t\025\005M!1`A\001\n\003\n)\002\003\006\002&\tm\030\021!C\001\007_!2AKB\031\021%\tya!\f\002\002\003\007q\004\003\006\002.\tm\030\021!C!\003_A!\"a\r\003|\006\005I\021IA\033\021)\tIDa?\002\002\023\0053\021\b\013\004U\rm\002\"CA\b\007o\t\t\0211\001 \r\035\031y$\003EA\007\003\022aAT8s[\006d7cBB\037\031\r\005qG\017\005\b'\ruB\021AB#)\t\0319\005E\002\031\007{A\001b]B\037\003\003%\t\005\036\005\t}\016u\022\021!C\001\"Q\021\021BB\037\003\003%\taa\024\025\007}\031\t\006\003\006\002\020\r5\023\021!a\001\003\003A!\"a\005\004>\005\005I\021IA\013\021)\t)c!\020\002\002\023\0051q\013\013\004U\re\003\"CA\b\007+\n\t\0211\001 \021)\tic!\020\002\002\023\005\023q\006\005\013\003g\031i$!A\005B\005U\002BCA@\007{\t\t\021\"\003\002\002\032911M\005\t\002\016\025$\001C*ikR$wn\0368\024\017\r\005Db!\0018u!91c!\031\005\002\r%DCAB6!\rA2\021\r\005\tg\016\005\024\021!C!i\"Aap!\031\002\002\023\005q\020\003\006\002\n\r\005\024\021!C\001\007g\"2aHB;\021)\tya!\035\002\002\003\007\021\021\001\005\013\003'\031\t'!A\005B\005U\001BCA\023\007C\n\t\021\"\001\004|Q\031!f! \t\023\005=1\021PA\001\002\004y\002BCA\027\007C\n\t\021\"\021\0020!Q\0211GB1\003\003%\t%!\016\t\025\005}4\021MA\001\n\023\t\tiB\004\004\b&A\tia\022\002\r9{'/\\1m\017\035\031Y)\003EA\007W\n\001b\0255vi\022|wO\\\004\n\007\037K\021\021!E\001\007#\013qAR1jYV\024X\rE\002\031\007'3\021B!@\n\003\003E\ta!&\024\013\rM5q\023\036\021\017\tu$1Q\020\004\022!91ca%\005\002\rmECABI\021)\t\031da%\002\002\023\025\023Q\007\005\na\rM\025\021!CA\007C#Ba!\005\004$\"91QABP\001\004y\002BCA1\007'\013\t\021\"!\004(R!1\021VBV!\021i\021\021N\020\t\025\005e4QUA\001\002\004\031\t\002\003\006\002\000\rM\025\021!C\005\003\003;qa!-\n\021\003\033\031,\001\007Ti\006$X\rV5nK>,H\017E\002\031\007k3qaa.\n\021\003\033IL\001\007Ti\006$X\rV5nK>,HoE\003\004629$\bC\004\024\007k#\ta!0\025\005\rM\006\002C:\0046\006\005I\021\t;\t\021y\034),!A\005\002}D!\"!\003\0046\006\005I\021ABc)\ry2q\031\005\013\003\037\031\031-!AA\002\005\005\001BCA\n\007k\013\t\021\"\021\002\026!Q\021QEB[\003\003%\ta!4\025\007)\032y\rC\005\002\020\r-\027\021!a\001?!Q\021QFB[\003\003%\t%a\f\t\025\005M2QWA\001\n\003\n)\004\003\006\002\000\rU\026\021!C\005\003\0033aa!7\n\t\016m'!\004+j[\026|W\017^'be.,'oE\003\004X29$\bC\006\004`\016]'Q3A\005\002\r\005\030AC4f]\026\024\030\r^5p]V\02111\035\t\004\033\r\025\030bABt\035\t!Aj\0348h\021-\031Yoa6\003\022\003\006Iaa9\002\027\035,g.\032:bi&|g\016\t\005\b'\r]G\021ABx)\021\031\tpa=\021\007a\0319\016\003\005\004`\0165\b\031ABr\021%)6q[A\001\n\003\0319\020\006\003\004r\016e\bBCBp\007k\004\n\0211\001\004d\"Iala6\022\002\023\0051Q`\013\003\007T3aa9c\021!\0318q[A\001\n\003\"\b\002\003@\004X\006\005I\021A@\t\025\005%1q[A\001\n\003!9\001F\002 \t\023A!\"a\004\005\006\005\005\t\031AA\001\021)\t\031ba6\002\002\023\005\023Q\003\005\013\003K\0319.!A\005\002\021=Ac\001\026\005\022!I\021q\002C\007\003\003\005\ra\b\005\013\003[\0319.!A\005B\005=\002BCA\032\007/\f\t\021\"\021\0026!Q\021\021HBl\003\003%\t\005\"\007\025\007)\"Y\002C\005\002\020\021]\021\021!a\001?\035IAqD\005\002\002#%A\021E\001\016)&lWm\\;u\033\006\0248.\032:\021\007a!\031CB\005\004Z&\t\t\021#\003\005&M)A1\005C\024uAA!Q\020BB\007G\034\t\020C\004\024\tG!\t\001b\013\025\005\021\005\002BCA\032\tG\t\t\021\"\022\0026!I\001\007b\t\002\002\023\005E\021\007\013\005\007c$\031\004\003\005\004`\022=\002\031ABr\021)\t\t\007b\t\002\002\023\005Eq\007\013\005\ts!Y\004E\003\016\003S\032\031\017\003\006\002z\021U\022\021!a\001\007cD!\"a \005$\005\005I\021BAA\r\035!\t%\003!\005\t\007\022Q\001V5nKJ\034r\001b\020\r\t\013:$\bE\002\t\t\017J1\001\"\023\003\005\005runU3sS\006d\027N_1uS>tg+\032:jM&\034\027\r^5p]:+W\rZ3e\021-!i\005b\020\003\026\004%\t\001b\024\002\t9\fW.Z\013\003\t#\002B\001b\025\005Z9\031Q\002\"\026\n\007\021]c\"\001\004Qe\026$WMZ\005\004y\022m#b\001C,\035!YAq\fC \005#\005\013\021\002C)\003\025q\027-\\3!\021-!\031\007b\020\003\026\004%\taa\002\002\0075\034x\r\003\006\005h\021}\"\021#Q\001\n}\tA!\\:hA!YA1\016C \005+\007I\021\001C7\003\031\021X\r]3biV\t!\006\003\006\005r\021}\"\021#Q\001\n)\nqA]3qK\006$\b\005\003\006\004`\022}\"Q3A\005\002}D1ba;\005@\tE\t\025!\003\002\002!YA\021\020C \005\003\005\013\021\002C>\003\035\031wN\034;fqR\0042\001\003C?\023\r!yH\001\002\r\003\016$xN]\"p]R,\007\020\036\005\b'\021}B\021\001CB))!)\tb#\005\016\022=E\021\023\013\005\t\017#I\tE\002\031\tA\001\002\"\037\005\002\002\007A1\020\005\t\t\033\"\t\t1\001\005R!9A1\rCA\001\004y\002b\002C6\t\003\003\rA\013\005\t\007?$\t\t1\001\002\002!aAQ\023C \001\004\005\r\021\"\003\005\030\006\031!/\0324\026\005\021e\005#B\007\002j\021m\005c\001\005\005\036&\031Aq\024\002\003\027\r\013gnY3mY\006\024G.\032\005\r\tG#y\0041AA\002\023%AQU\001\be\0264w\fJ3r)\021!9\013\",\021\0075!I+C\002\005,:\021A!\0268ji\"Q\021q\002CQ\003\003\005\r\001\"'\t\023\021EFq\bQ!\n\021e\025\001\002:fM\002B!\002\".\005@\t\007I\021\002C\\\003%\0318\r[3ek2,'/\006\002\005:B\031\001\002b/\n\007\021u&AA\005TG\",G-\0367fe\"IA\021\031C A\003%A\021X\001\013g\016DW\rZ;mKJ\004\003B\003Cc\t\021\r\021b\003\005H\006\001R\r_3dkRLwN\\\"p]R,\007\020^\013\003\t\023\004B\001b3\005R6\021AQ\032\006\004\t\037t\021AC2p]\016,(O]3oi&!A1\033Cg\005a)\0050Z2vi&|gnQ8oi\026DH/\022=fGV$xN\035\005\n\t/$y\004)A\005\t\023\f\021#\032=fGV$\030n\0348D_:$X\r\037;!\021!!Y\016b\020\005\002\021u\027\001C:dQ\026$W\017\\3\025\r\021\035Fq\034Cq\021\031\031A\021\034a\001\001\"AA1\035Cm\001\004!)/A\004uS6,w.\036;\021\t\021\035HQ^\007\003\tSTA\001b;\005N\006AA-\036:bi&|g.\003\003\005p\022%(A\004$j]&$X\rR;sCRLwN\034\005\t\tg$y\004\"\001\005v\00611-\0318dK2$\"\001b*\t\023U#y$!A\005\002\021eHC\003C~\t,\t!b\001\006\006Q!Aq\021C\021!!I\bb>A\002\021m\004B\003C'\to\004\n\0211\001\005R!IA1\rC|!\003\005\ra\b\005\n\tW\"9\020%AA\002)B!ba8\005xB\005\t\031AA\001\021%qFqHI\001\n\003)I!\006\002\006\f)\032A\021\0132\t\0235$y$%A\005\002\ru\001BCAn\t\t\n\021\"\001\006\022U\021Q1\003\026\003U\tD!\"b\006\005@E\005I\021AC\r\0039\031w\016]=%I\0264\027-\0367uIQ*\"!b\007+\007\005\005!\r\003\005t\t\t\t\021\"\021u\021!qHqHA\001\n\003y\bBCA\005\t\t\t\021\"\001\006$Q\031q$\"\n\t\025\005=Q\021EA\001\002\004\t\t\001\003\006\002\024\021}\022\021!C!\003+A!\"!\n\005@\005\005I\021AC\026)\rQSQ\006\005\n\003\037)I#!AA\002}A!\"!\f\005@\005\005I\021IA\030\021)\t\031\004b\020\002\002\023\005\023Q\007\005\013\003s!y$!A\005B\025UBc\001\026\0068!I\021qBC\032\003\003\005\raH\004\013\013wI\021\021!E\001\t\025u\022!\002+j[\026\024\bc\001\r\006@\031QA\021I\005\002\002#\005A!\"\021\024\t\025}BB\017\005\b'\025}B\021AC#)\t)i\004\003\006\0024\025}\022\021!C#\003kA\021\002MC \003\003%\t)b\023\025\025\0255S\021KC*\013+*9\006\006\003\005\b\026=\003\002\003C=\013\023\002\r\001b\037\t\021\0215S\021\na\001\t#Bq\001b\031\006J\001\007q\004C\004\005l\025%\003\031\001\026\t\021\r}W\021\na\001\003\003A!\"!\031\006@\005\005I\021QC.)\021)i&\"\032\021\0135\tI'b\030\021\0235)\t\007\"\025 U\005\005\021bAC2\035\t1A+\0369mKRB!\"!\037\006Z\005\005\t\031\001CD\021)\ty(b\020\002\002\023%\021\021Q\004\b\013WJ\001\022AC7\0039!S.\0338vg\022:'/Z1uKJ\0042\001GC8\r\035)\t(\003E\001\013g\022a\002J7j]V\034He\032:fCR,'oE\002\006p1AqaEC8\t\003)9\b\006\002\006n!A\021\021MC8\t\003)Y(\006\003\006~\025%E\003BC@\013\027\003R!DCA\013\013K1!b!\017\005\021\031v.\\3\021\0175\ty'b\"\006\bB\031\021*\"#\005\r-+IH1\001M\021!)i)\"\037A\002\025\025\025AA5o\r\031)\t*\003!\006\024\nAAj\\4F]R\024\0300\006\004\006\026\026}UQV\n\006\013\037cqG\017\005\f\0133+yI!f\001\n\003)Y*A\005ti\006$XMT1nKV\021QQ\024\t\004\023\026}EAB&\006\020\n\007A\nC\006\006$\026=%\021#Q\001\n\025u\025AC:uCR,g*Y7fA!YQqUCH\005+\007I\021ACU\003%\031H/\031;f\t\006$\030-\006\002\006,B\031\021*\",\005\017\025=Vq\022b\001\031\n\tA\tC\006\0064\026=%\021#Q\001\n\025-\026AC:uCR,G)\031;bA!YQqWCH\005+\007I\021AB\004\003\025)g/\0328u\021))Y,b$\003\022\003\006IaH\001\007KZ,g\016\036\021\t\017M)y\t\"\001\006@RAQ\021YCb\013\013,9\rE\004\031\013\037+i*b+\t\021\025eUQ\030a\001\013;C\001\"b*\006>\002\007Q1\026\005\b\013o+i\f1\001 \021%)VqRA\001\n\003)Y-\006\004\006N\026MWq\033\013\t\013\037,I.b7\006^B9\001$b$\006R\026U\007cA%\006T\02211*\"3C\0021\0032!SCl\t\035)y+\"3C\0021C!\"\"'\006JB\005\t\031ACi\021))9+\"3\021\002\003\007QQ\033\005\n\013o+I\r%AA\002}A\021BXCH#\003%\t!\"9\026\r\025\rXq]Cu+\t))OK\002\006\036\n$aaSCp\005\004aEaBCX\013?\024\r\001\024\005\n[\026=\025\023!C\001\013[,b!b<\006t\026UXCACyU\r)YK\031\003\007\027\026-(\031\001'\005\017\025=V1\036b\001\031\"Q\0211\\CH#\003%\t!\"?\026\r\ruQ1`C\t\031YUq\037b\001\031\0229QqVC|\005\004a\005\002C:\006\020\006\005I\021\t;\t\021y,y)!A\005\002}D!\"!\003\006\020\006\005I\021\001D\003)\rybq\001\005\013\003\0371\031!!AA\002\005\005\001BCA\n\013\037\013\t\021\"\021\002\026!Q\021QECH\003\003%\tA\"\004\025\007)2y\001C\005\002\020\031-\021\021!a\001?!Q\021QFCH\003\003%\t%a\f\t\025\005MRqRA\001\n\003\n)\004\003\006\002:\025=\025\021!C!\r/!2A\013D\r\021%\tyA\"\006\002\002\003\007qdB\005\007\036%\t\t\021#\001\007 \005AAj\\4F]R\024\030\020E\002\031\rC1\021\"\"%\n\003\003E\tAb\t\024\t\031\005BB\017\005\b'\031\005B\021\001D\024)\t1y\002\003\006\0024\031\005\022\021!C#\003kA\021\002\rD\021\003\003%\tI\"\f\026\r\031=bQ\007D\035)!1\tDb\017\007>\031}\002c\002\r\006\020\032Mbq\007\t\004\023\032UBAB&\007,\t\007A\nE\002J\rs!q!b,\007,\t\007A\n\003\005\006\032\032-\002\031\001D\032\021!)9Kb\013A\002\031]\002bBC\\\rW\001\ra\b\005\013\003C2\t#!A\005\002\032\rSC\002D#\r\0332\t\006\006\003\007H\031M\003#B\007\002j\031%\003\003C\007\003*\031-cqJ\020\021\007%3i\005\002\004L\r\003\022\r\001\024\t\004\023\032ECaBCX\r\003\022\r\001\024\005\013\003s2\t%!AA\002\031U\003c\002\r\006\020\032-cq\n\005\013\0032\t#!A\005\n\005\005eA\002D.\023\0013iFA\003Ti\006$X-\006\004\007`\031\035d\021O\n\006\r3bqG\017\005\f\01333IF!f\001\n\0031\031'\006\002\007fA\031\021Jb\032\005\r-3IF1\001M\021-)\031K\"\027\003\022\003\006IA\"\032\t\027\025\035f\021\fBK\002\023\005aQN\013\003\r_\0022!\023D9\t\035)yK\"\027C\0021C1\"b-\007Z\tE\t\025!\003\007p!YA1\035D-\005+\007I\021\001D<+\t1I\bE\003\016\003S\")\017C\006\007~\031e#\021#Q\001\n\031e\024\001\003;j[\026|W\017\036\021\t\027\031\005e\021\fBK\002\023\005a1Q\001\013gR|\007OU3bg>tWC\001DC!\025i\021\021NB\001\021-1II\"\027\003\022\003\006IA\"\"\002\027M$x\016\035*fCN|g\016\t\005\f\r\0333IF!f\001\n\0031y)A\004sKBd\027.Z:\026\005\031E\005#\002DJ\rG{b\002\002DK\r?sAAb&\007\0366\021a\021\024\006\004\r73\021A\002\037s_>$h(C\001\020\023\r1\tKD\001\ba\006\0347.Y4f\023\0211)Kb*\003\t1K7\017\036\006\004\rCs\001b\003DV\r3\022\t\022)A\005\r#\013\001B]3qY&,7\017\t\005\b'\031eC\021\001DX)11\tLb-\0076\032]f\021\030D^!\035Ab\021\fD3\r_B\001\"\"'\007.\002\007aQ\r\005\t\013O3i\0131\001\007p!QA1\035DW!\003\005\rA\"\037\t\025\031\005eQ\026I\001\002\0041)\t\003\006\007\016\0325\006\023!a\001\r#C\001Bb0\007Z\021\005a\021Y\001\007M>\024X*\031=\025\t\031Ef1\031\005\t\tG4i\f1\001\007FB!Aq\035Dd\023\0211I\r\";\003\021\021+(/\031;j_:D\001B\"4\007Z\021\005aqZ\001\te\026\004H._5oOR!a\021\027Di\021\0351\031Nb3A\002}\t!B]3qYf4\026\r\\;f\021!19N\"\027\005\002\031e\027!B;tS:<G\003\002DY\r7D\001B\"8\007V\002\007aqN\001\016]\026DHo\025;bi\026$\025\r^3\t\023\031\005h\021\fC\001\t\031\r\030AD<ji\"\034Fo\0349SK\006\034xN\034\013\005\rc3)\017\003\005\007h\032}\007\031AB\001\003\031\021X-Y:p]\"IQK\"\027\002\002\023\005a1^\013\007\r[4\031Pb>\025\031\031=h\021 D~\r{4yp\"\001\021\017a1IF\"=\007vB\031\021Jb=\005\r-3IO1\001M!\rIeq\037\003\b\013_3IO1\001M\021))IJ\";\021\002\003\007a\021\037\005\013\013O3I\017%AA\002\031U\bB\003Cr\rS\004\n\0211\001\007z!Qa\021\021Du!\003\005\rA\"\"\t\025\0315e\021\036I\001\002\0041\t\nC\005_\r3\n\n\021\"\001\b\006U1qqAD\006\017\033)\"a\"\003+\007\031\025$\r\002\004L\017\007\021\r\001\024\003\b\013_;\031A1\001M\021%ig\021LI\001\n\0039\t\"\006\004\b\024\035]q\021D\013\003\017+Q3Ab\034c\t\031Yuq\002b\001\031\0229QqVD\b\005\004a\005BCAn\r3\n\n\021\"\001\b\036U1qqDD\022\017K)\"a\"\t+\007\031e$\r\002\004L\0177\021\r\001\024\003\b\013_;YB1\001M\021))9B\"\027\022\002\023\005q\021F\013\007\017W9yc\"\r\026\005\0355\"f\001DCE\02211jb\nC\0021#q!b,\b(\t\007A\n\003\006\b6\031e\023\023!C\001\017o\tabY8qs\022\"WMZ1vYR$S'\006\004\b:\035urqH\013\003\017wQ3A\"%c\t\031Yu1\007b\001\031\0229QqVD\032\005\004a\005\002C:\007Z\005\005I\021\t;\t\021y4I&!A\005\002}D!\"!\003\007Z\005\005I\021AD$)\ryr\021\n\005\013\003\0379)%!AA\002\005\005\001BCA\n\r3\n\t\021\"\021\002\026!Q\021Q\005D-\003\003%\tab\024\025\007):\t\006C\005\002\020\0355\023\021!a\001?!Q\021Q\006D-\003\003%\t%a\f\t\025\005Mb\021LA\001\n\003\n)\004\003\006\002:\031e\023\021!C!\0173\"2AKD.\021%\tyab\026\002\002\003\007qdB\005\b`%\t\t\021#\001\bb\005)1\013^1uKB\031\001db\031\007\023\031m\023\"!A\t\002\035\0254\003BD2\031iBqaED2\t\0039I\007\006\002\bb!Q\0211GD2\003\003%)%!\016\t\023A:\031'!A\005\002\036=TCBD9\017o:Y\b\006\007\bt\035utqPDA\017\007;)\tE\004\031\r3:)h\"\037\021\007%;9\b\002\004L\017[\022\r\001\024\t\004\023\036mDaBCX\017[\022\r\001\024\005\t\0133;i\0071\001\bv!AQqUD7\001\0049I\b\003\006\005d\0365\004\023!a\001\rsB!B\"!\bnA\005\t\031\001DC\021)1ii\"\034\021\002\003\007a\021\023\005\013\003C:\031'!A\005\002\036%UCBDF\017/;Y\n\006\003\b\016\036u\005#B\007\002j\035=\005#D\007\b\022\036Uu\021\024D=\r\0133\t*C\002\b\024:\021a\001V;qY\026,\004cA%\b\030\02211jb\"C\0021\0032!SDN\t\035)ykb\"C\0021C!\"!\037\b\b\006\005\t\031ADP!\035Ab\021LDK\0173C!bb)\bdE\005I\021ADS\003m!C.Z:tS:LG\017J4sK\006$XM\035\023eK\032\fW\017\034;%gU1qqDDT\017S#aaSDQ\005\004aEaBCX\017C\023\r\001\024\005\013\017[;\031'%A\005\002\035=\026a\007\023mKN\034\030N\\5uI\035\024X-\031;fe\022\"WMZ1vYR$C'\006\004\b,\035Ev1\027\003\007\027\036-&\031\001'\005\017\025=v1\026b\001\031\"QqqWD2#\003%\ta\"/\0027\021bWm]:j]&$He\032:fCR,'\017\n3fM\006,H\016\036\0236+\0319Idb/\b>\02211j\".C\0021#q!b,\b6\n\007A\n\003\006\bB\036\r\024\023!C\001\017\007\fq\"\0319qYf$C-\0324bk2$HeM\013\007\017?9)mb2\005\r-;yL1\001M\t\035)ykb0C\0021C!bb3\bdE\005I\021ADg\003=\t\007\017\0357zI\021,g-Y;mi\022\"TCBD\026\017\037<\t\016\002\004L\017\023\024\r\001\024\003\b\013_;IM1\001M\021)9)nb\031\022\002\023\005qq[\001\020CB\004H.\037\023eK\032\fW\017\034;%kU1q\021HDm\0177$aaSDj\005\004aEaBCX\017'\024\r\001\024\005\013\003:\031'!A\005\n\005\005eABDq\023\001;\031OA\003Fm\026tG/\006\003\bf\036E8cBDp\031\021\025sG\017\005\f\013o;yN!f\001\n\003\0319\001\003\006\006<\036}'\021#Q\001\n}A1\"b*\b`\nU\r\021\"\001\bnV\021qq\036\t\004\023\036EHaBCX\017?\024\r\001\024\005\f\013g;yN!E!\002\0239y\017C\004\024\017?$\tab>\025\r\035ex1`D!\025Arq\\Dx\021\035)9l\">A\002}A\001\"b*\bv\002\007qq\036\005\n+\036}\027\021!C\001\021\003)B\001c\001\t\nQ1\001R\001E\006\021\033\001R\001GDp\021\017\0012!\023E\005\t\035)ykb@C\0021C\021\"b.\b\000B\005\t\031A\020\t\025\025\035vq I\001\002\004A9\001C\005_\017?\f\n\021\"\001\t\022U!1Q\004E\n\t\035)y\013c\004C\0021C\021\"\\Dp#\003%\t\001c\006\026\t!e\001RD\013\003\0217Q3ab<c\t\035)y\013#\006C\0021C\001b]Dp\003\003%\t\005\036\005\t}\036}\027\021!C\001\"Q\021\021BDp\003\003%\t\001#\n\025\007}A9\003\003\006\002\020!\r\022\021!a\001\003\003A!\"a\005\b`\006\005I\021IA\013\021)\t)cb8\002\002\023\005\001R\006\013\004U!=\002\"CA\b\021W\t\t\0211\001 \021)\ticb8\002\002\023\005\023q\006\005\013\003g9y.!A\005B\005U\002BCA\035\017?\f\t\021\"\021\t8Q\031!\006#\017\t\023\005=\001RGA\001\002\004yr!\003E\037\023\005\005\t\022\001E \003\025)e/\0328u!\rA\002\022\t\004\n\017CL\021\021!E\001\021\007\032B\001#\021\ru!91\003#\021\005\002!\035CC\001E \021)\t\031\004#\021\002\002\023\025\023Q\007\005\na!\005\023\021!CA\021\033*B\001c\024\tVQ1\001\022\013E,\0213\002R\001GDp\021'\0022!\023E+\t\035)y\013c\023C\0021Cq!b.\tL\001\007q\004\003\005\006(\"-\003\031\001E*\021)\t\t\007#\021\002\002\023\005\005RL\013\005\021?B9\007\006\003\tb!%\004#B\007\002j!\r\004CB\007\002p}A)\007E\002J\021O\"q!b,\t\\\t\007A\n\003\006\002z!m\023\021!a\001\021W\002R\001GDp\021KB!\"a \tB\005\005I\021BAA\r\031A\t(\003!\tt\tI1\013^8q\013Z,g\016^\013\007\021kB9\tc%\024\017!=D\002\"\0228u!Yaq\035E8\005+\007I\021\001E=+\t\031\t\001C\006\t~!=$\021#Q\001\n\r\005\021a\002:fCN|g\016\t\005\f\021\003CyG!f\001\n\003A\031)\001\007dkJ\024XM\034;Ti\006$X-\006\002\t\006B\031\021\nc\"\005\r-CyG1\001M\021-AY\tc\034\003\022\003\006I\001#\"\002\033\r,(O]3oiN#\030\r^3!\021-)9\013c\034\003\026\004%\t\001c$\026\005!E\005cA%\t\024\0229Qq\026E8\005\004a\005bCCZ\021_\022\t\022)A\005\021#Cqa\005E8\t\003AI\n\006\005\t\034\"u\005r\024EQ!\035A\002r\016EC\021#C\001Bb:\t\030\002\0071\021\001\005\t\021\003C9\n1\001\t\006\"AQq\025EL\001\004A\t\nC\005V\021_\n\t\021\"\001\t&V1\001r\025EW\021c#\002\002#+\t4\"U\006r\027\t\b1!=\0042\026EX!\rI\005R\026\003\007\027\"\r&\031\001'\021\007%C\t\fB\004\0060\"\r&\031\001'\t\025\031\035\b2\025I\001\002\004\031\t\001\003\006\t\002\"\r\006\023!a\001\021WC!\"b*\t$B\005\t\031\001EX\021%q\006rNI\001\n\003AY,\006\004\t>\"\005\0072Y\013\003\021S3a!\001c\t\031Y\005\022\030b\001\031\0229Qq\026E]\005\004a\005\"C7\tpE\005I\021\001Ed+\031AI\r#4\tPV\021\0012\032\026\004\021\013\023GAB&\tF\n\007A\nB\004\0060\"\025'\031\001'\t\025\005m\007rNI\001\n\003A\031.\006\004\tV\"e\0072\\\013\003\021/T3\001#%c\t\031Y\005\022\033b\001\031\0229Qq\026Ei\005\004a\005\002C:\tp\005\005I\021\t;\t\021yDy'!A\005\002}D!\"!\003\tp\005\005I\021\001Er)\ry\002R\035\005\013\003\037A\t/!AA\002\005\005\001BCA\n\021_\n\t\021\"\021\002\026!Q\021Q\005E8\003\003%\t\001c;\025\007)Bi\017C\005\002\020!%\030\021!a\001?!Q\021Q\006E8\003\003%\t%a\f\t\025\005M\002rNA\001\n\003\n)\004\003\006\002:!=\024\021!C!\021k$2A\013E|\021%\ty\001c=\002\002\003\007qdB\005\t|&\t\t\021#\001\t~\006I1\013^8q\013Z,g\016\036\t\0041!}h!\003E9\023\005\005\t\022AE\001'\021Ay\020\004\036\t\017MAy\020\"\001\n\006Q\021\001R \005\013\003gAy0!A\005F\005U\002\"\003\031\t\000\006\005I\021QE\006+\031Ii!c\005\n\030QA\021rBE\r\0237Ii\002E\004\031\021_J\t\"#\006\021\007%K\031\002\002\004L\023\023\021\r\001\024\t\004\023&]AaBCX\023\023\021\r\001\024\005\t\rOLI\0011\001\004\002!A\001\022QE\005\001\004I\t\002\003\005\006(&%\001\031AE\013\021)\t\t\007c@\002\002\023\005\025\022E\013\007\023GIY#c\f\025\t%\025\022\022\007\t\006\033\005%\024r\005\t\n\033\t%2\021AE\025\023[\0012!SE\026\t\031Y\025r\004b\001\031B\031\021*c\f\005\017\025=\026r\004b\001\031\"Q\021\021PE\020\003\003\005\r!c\r\021\017aAy'#\013\n.!Q\021q\020E\000\003\003%I!!!\007\021)\021\001\023aA\001\023s)b!c\017\nb%\0254#CE\034\031%u\0222IE(!\rA\021rH\005\004\023\003\022!!B!di>\024\b\003BE#\023\027j!!c\022\013\007%%C!A\004s_V$\030N\\4\n\t%5\023r\t\002\n\031&\034H/\0328feN\0042\001CE)\023\rI\031F\001\002\r\003\016$xN\035'pO\036Lgn\032\005\t\023/J9\004\"\001\005v\0061A%\0338ji\022*qAb\027\n8\001IY\006\005\005\n^\031e\023rLE2\035\tA\001\001E\002J\023C\"aaSE\034\005\004a\005cA%\nf\0219QqVE\034\005\004aUaBDq\023o\001\021\022\016\t\007\023;:y.c\031\006\017!E\024r\007\001\nnAA\021R\fE8\023?J\031'B\004\nr%]\002!c\035\003\033M#\030\r^3Gk:\034G/[8o!\031iQ$#\036\nzA!\021rOE4\033\tI9\004\005\003\nx%eSaBE?\023o\001a\021\020\002\b)&lWm\\;u\013\035I\t)c\016\001\023\007\023\021\003\026:b]NLG/[8o\021\006tG\r\\3s!\031iQ$#\"\005(B9Q\"a\034\n`%}\003B\003E\037\023o\021\r\021\"\001\n\nV\021\0212\022\b\005\023;BY\004C\005\n\020&]\002\025!\003\n\f\0061QI^3oi\002B!\002c?\n8\t\007I\021AEJ+\tI)J\004\003\n^!e\b\"CEM\023o\001\013\021BEK\003)\031Fo\0349Fm\026tG\017\t\005\013\013WJ9D1A\005\002%uUCAEP\035\021Ii&\"\033\t\023%\r\026r\007Q\001\n%}\025a\004\023nS:,8\017J4sK\006$XM\035\021\t\025\rE\026r\007b\001\n\003I9+\006\002\n*:!\021RLBX\021%Ii+c\016!\002\023II+A\007Ti\006$X\rV5nK>,H\017\t\005\t\023cK9\004\"\002\n4\006!q\017[3o)\031I),#0\n@R!AqUE\\\021!II,c,A\002%m\026!D:uCR,g)\0368di&|g\016\005\003\nx%=\004\002CCM\023_\003\r!c\030\t\025%\005\027r\026I\001\002\004!)/\001\007ti\006$X\rV5nK>,H\017\003\005\nF&]BQAEd\003%\031H/\031:u/&$\b\016\006\005\005(&%\0272ZEg\021!)I*c1A\002%}\003\002CCT\023\007\004\r!c\031\t\025\021\r\0302\031I\001\002\004Iy\r\005\003\nx%m\004\002CEj\023o!)!#6\002\t\035|Go\034\013\005\023sJ9\016\003\005\nZ&E\007\031AE0\0035qW\r\037;Ti\006$XMT1nK\"A\021R\\E\034\t\013Iy.\001\003ti\006LHCAE=\021!I\031/c\016\005\006%}\027\001B:u_BD\001\"c9\n8\021\025\021r\035\013\005\023sJI\017\003\005\007h&\025\b\031AEv!\021IiFa=\t\021%\r\030r\007C\003\023_$b!#\037\nr&M\b\002\003Dt\023[\004\r!c;\t\021\025\035\026R\036a\001\023G2q!c>\n8\tIIPA\bUe\006t7OZ8s[\"+G\016]3s'\rI)\020\004\005\f\023{L)P!A!\002\023IY,\001\003gk:\034\007bB\n\nv\022\005!\022\001\013\005\025\007Q)\001\005\003\nx%U\b\002CE\023\004\r!c/\t\021\031]\027R\037C\001\025\023!B!c/\013\f!A!R\002F\004\001\004Qy!A\004b]\022$\006.\0328\021\r5i\022\022PE=\021!Q\031\"c\016\005\006)U\021!\003;sC:\034hm\034:n)\021Q\031Ac\006\t\021%u(\022\003a\001\023wC\001Bc\007\n8\021\025!RD\001\tg\026$H+[7feRQAq\025F\020\025CQ\031C#\n\t\021\0215#\022\004a\001\t#Bq\001b\031\013\032\001\007q\004\003\005\005d*e\001\031\001Cs\021%!YG#\007\021\002\003\007!\006\003\005\013*%]BQ\001F\026\003-\031\027M\\2fYRKW.\032:\025\t\021\035&R\006\005\t\t\033R9\0031\001\005R!A!\022GE\034\t\013Q\031$A\007jgRKW.\032:BGRLg/\032\013\004U)U\002\002\003C'\025_\001\r\001\"\025\t\021)e\022r\007C\003\025w\tqb]3u'R\fG/\032+j[\026|W\017\036\013\007\tOSiDc\020\t\017\031S9\0041\001\n`!AA1\035F\034\001\004Iy\rC\005\013D%]BQ\001\003\005n\005\021\022n]*uCR,G+[7fe\006\033G/\033<f\021!Q9%c\016\005\006)%\023\001D8o)J\fgn]5uS>tG\003\002CT\025\027B\001B#\024\013F\001\007!rJ\001\022iJ\fgn]5uS>t\007*\0318eY\026\024\b\003BE<\023B\001Bc\025\n8\021\035!RK\001\ti>$\030\r\034\032qMR!!r\nF,\021!QiE#\025A\002)e\003#C\007\013\\%}\023r\fCT\023\rQiF\004\002\n\rVt7\r^5p]JB\001B#\031\n8\021\025!2M\001\016_:$VM]7j]\006$\030n\0348\025\t\021\035&R\r\005\t\025ORy\0061\001\013j\005\021B/\032:nS:\fG/[8o\021\006tG\r\\3s!\031iQDc\033\005(B!\021rOE6\021!Qy'c\016\005\006)E\024!D<iK:,f\016[1oI2,G\r\006\003\005(*M\004\002CE]\025[\002\r!c/\t\021)]\024r\007C\003\tk\f!\"\0338ji&\fG.\033>f\021!)I*c\016\005\006)mTCAE0\021!)9+c\016\005\006)}TCAE2\021!Q\031)c\016\005\006)}\024!\0048fqR\034F/\031;f\t\006$\030\rC\005\013\b&]B\021\001\003\005n\005QA-\0322vO\0263XM\034;\t\031!\005\025r\007a\001\002\004%IAc#\026\005%e\004\002\004FH\023o\001\r\0211A\005\n)E\025\001E2veJ,g\016^*uCR,w\fJ3r)\021!9Kc%\t\025\005=!RRA\001\002\004II\bC\005\t\f&]\002\025)\003\nz!Q!\022TE\034\001\004%I\001b&\002\033QLW.Z8vi\032+H/\036:f\021)Qi*c\016A\002\023%!rT\001\022i&lWm\\;u\rV$XO]3`I\025\fH\003\002CT\025CC!\"a\004\013\034\006\005\t\031\001CM\021%Q)+c\016!B\023!I*\001\buS6,w.\036;GkR,(/\032\021\t\031)%\026r\007a\001\002\004%IAc#\002\0239,\007\020^*uCR,\007\002\004FW\023o\001\r\0211A\005\n)=\026!\0048fqR\034F/\031;f?\022*\027\017\006\003\005(*E\006BCA\b\025W\013\t\0211\001\nz!I!RWE\034A\003&\021\022P\001\013]\026DHo\025;bi\026\004\003BCBp\023o\001\r\021\"\003\004b\"Q!2XE\034\001\004%IA#0\002\035\035,g.\032:bi&|gn\030\023fcR!Aq\025F`\021)\tyA#/\002\002\003\00711\035\005\n\007WL9\004)Q\005\007GD!B#2\n8\t\007I\021\002Fd\003\031!\030.\\3sgV\021!\022\032\t\t\025\027T\t\016\"\025\013V6\021!R\032\006\005\025\037\fY\"A\004nkR\f'\r\\3\n\t)M'R\032\002\004\033\006\004\b\003BE/\tA\021B#7\n8\001\006IA#3\002\017QLW.\032:tA!Q!R\\E\034\005\004%IAc8\002\021QLW.\032:HK:,\"A#9\021\r\005e\021qDA\001\021%Q)/c\016!\002\023Q\t/A\005uS6,'oR3oA!Q!\022^E\034\005\004%IAc;\002\035M$\030\r^3Gk:\034G/[8ogV\021!R\036\t\t\025\027T\t.c\030\013pB1Q\"HE5\0237B\021Bc=\n8\001\006IA#<\002\037M$\030\r^3Gk:\034G/[8og\002B!Bc>\n8\t\007I\021\002F}\0035\031H/\031;f)&lWm\\;ugV\021!2 \t\t\025\027T\t.c\030\007z!I!r`E\034A\003%!2`\001\017gR\fG/\032+j[\026|W\017^:!\021!Y\031!c\016\005\n-\025\021\001\003:fO&\034H/\032:\025\021\021\0356rAF\005\027\033A\001\002\"\024\f\002\001\007\021r\f\005\t\027\027Y\t\0011\001\n<\006Aa-\0368di&|g\016\003\005\005d.\005\001\031AEh\021)Y\t\"c\016C\002\023%12C\001\023Q\006tG\r\\3Fm\026tG\017R3gCVdG/\006\002\n<\"I1rCE\034A\003%\0212X\001\024Q\006tG\r\\3Fm\026tG\017R3gCVdG\017\t\005\013\0277I9\0041A\005\n-M\021a\0035b]\022dW-\022<f]RD!bc\b\n8\001\007I\021BF\021\003=A\027M\0343mK\0263XM\034;`I\025\fH\003\002CT\027GA!\"a\004\f\036\005\005\t\031AE^\021%Y9#c\016!B\023IY,\001\007iC:$G.Z#wK:$\b\005\003\006\f,%]\002\031!C\005\027[\ta\002^3s[&t\027\r^3Fm\026tG/\006\002\013j!Q1\022GE\034\001\004%Iac\r\002%Q,'/\\5oCR,WI^3oi~#S-\035\013\005\tO[)\004\003\006\002\020-=\022\021!a\001\025SB\021b#\017\n8\001\006KA#\033\002\037Q,'/\\5oCR,WI^3oi\002B!b#\020\n8\001\007I\021BF \003=!(/\0318tSRLwN\\#wK:$XCAF!!\0311\031Jb)\013P!Q1RIE\034\001\004%Iac\022\002'Q\024\030M\\:ji&|g.\022<f]R|F%Z9\025\t\021\0356\022\n\005\013\003\037Y\031%!AA\002-\005\003\"CF'\023o\001\013\025BF!\003A!(/\0318tSRLwN\\#wK:$\b\005\003\005\fR%]B\021BF*\003AA\027M\0343mKR\023\030M\\:ji&|g\016\006\004\005(.U3\022\f\005\t\027/Zy\0051\001\n`\005!\001O]3w\021!YYfc\024A\002%}\023\001\0028fqRD\001bc\030\n8\021\0053\022M\001\be\026\034W-\033<f+\tY\031\007\005\003\nx-\025\024\002BF4\023\021qAU3dK&4X\r\003\005\fl%]B\021BF7\003)\001(o\\2fgNl5o\032\013\007\tO[ygc\035\t\017-E4\022\016a\001?\005)a/\0317vK\"91ROF5\001\004a\021AB:pkJ\034W\rC\005\fz%]B\021\001\003\f|\005a\001O]8dKN\034XI^3oiR1AqUF?\027B\001\"b.\fx\001\007\021R\017\005\b\027kZ9\b1\001\r\021%Y\031)c\016\005\002\021Y))\001\006baBd\027p\025;bi\026$B\001b*\f\b\"A!\022VFA\001\004II\bC\005\f\f&]B\021\001\003\f\016\006qQ.Y6f)J\fgn]5uS>tG\003\002CT\027\037C\001B#+\f\n\002\007\021\022\020\005\t\027'K9\004\"\021\005v\006A\001o\\:u'R|\007\017\003\005\f\030&]B\021BFM\003%!XM]7j]\006$X\r\006\003\005(.m\005\002\003FU\027+\003\r!#\037\t\021-}\025r\007C\t\027C\013a\002\\8h)\026\024X.\0338bi&|g\016\006\003\005(.\r\006\002\003Dt\027;\003\r!c;\t\025-\035\026rGI\001\n\013YI+\001\bxQ\026tG\005Z3gCVdG\017\n\032\026\005--&f\001CsE\"Q1rVE\034#\003%)a#-\002'M$\030M\035;XSRDG\005Z3gCVdG\017J\032\026\005-M&fAEhE\"Q1rWE\034#\003%)!\"\005\002%M,G\017V5nKJ$C-\0324bk2$H\005\016\005\016\027wK9$!A\001\n\023!)p#0\002\035M,\b/\032:%a>\034Ho\025;pa&!12SE \001")
/*     */ public interface FSM<S, D> extends Actor, Listeners, ActorLogging {
/*     */   void akka$actor$FSM$_setter_$Event_$eq(Event$ paramEvent$);
/*     */   
/*     */   void akka$actor$FSM$_setter_$StopEvent_$eq(StopEvent$ paramStopEvent$);
/*     */   
/*     */   void akka$actor$FSM$_setter_$$minus$greater_$eq($minus$greater$ param$minus$greater$);
/*     */   
/*     */   void akka$actor$FSM$_setter_$StateTimeout_$eq(StateTimeout$ paramStateTimeout$);
/*     */   
/*     */   void akka$actor$FSM$_setter_$akka$actor$FSM$$timers_$eq(Map paramMap);
/*     */   
/*     */   void akka$actor$FSM$_setter_$akka$actor$FSM$$timerGen_$eq(Iterator paramIterator);
/*     */   
/*     */   void akka$actor$FSM$_setter_$akka$actor$FSM$$stateFunctions_$eq(Map paramMap);
/*     */   
/*     */   void akka$actor$FSM$_setter_$akka$actor$FSM$$stateTimeouts_$eq(Map paramMap);
/*     */   
/*     */   void akka$actor$FSM$_setter_$akka$actor$FSM$$handleEventDefault_$eq(PartialFunction paramPartialFunction);
/*     */   
/*     */   void akka$actor$FSM$$super$postStop();
/*     */   
/*     */   Event$ Event();
/*     */   
/*     */   StopEvent$ StopEvent();
/*     */   
/*     */   $minus$greater$ $minus$greater();
/*     */   
/*     */   StateTimeout$ StateTimeout();
/*     */   
/*     */   void when(S paramS, FiniteDuration paramFiniteDuration, PartialFunction<Event<D>, State<S, D>> paramPartialFunction);
/*     */   
/*     */   FiniteDuration when$default$2();
/*     */   
/*     */   void startWith(S paramS, D paramD, Option<FiniteDuration> paramOption);
/*     */   
/*     */   Option<FiniteDuration> startWith$default$3();
/*     */   
/*     */   State<S, D> goto(S paramS);
/*     */   
/*     */   State<S, D> stay();
/*     */   
/*     */   State<S, D> stop();
/*     */   
/*     */   State<S, D> stop(Reason paramReason);
/*     */   
/*     */   State<S, D> stop(Reason paramReason, D paramD);
/*     */   
/*     */   TransformHelper transform(PartialFunction<Event<D>, State<S, D>> paramPartialFunction);
/*     */   
/*     */   void setTimer(String paramString, Object paramObject, FiniteDuration paramFiniteDuration, boolean paramBoolean);
/*     */   
/*     */   boolean setTimer$default$4();
/*     */   
/*     */   void cancelTimer(String paramString);
/*     */   
/*     */   boolean isTimerActive(String paramString);
/*     */   
/*     */   void setStateTimeout(S paramS, Option<FiniteDuration> paramOption);
/*     */   
/*     */   boolean isStateTimerActive();
/*     */   
/*     */   void onTransition(PartialFunction<Tuple2<S, S>, BoxedUnit> paramPartialFunction);
/*     */   
/*     */   PartialFunction<Tuple2<S, S>, BoxedUnit> total2pf(Function2<S, S, BoxedUnit> paramFunction2);
/*     */   
/*     */   void onTermination(PartialFunction<StopEvent<S, D>, BoxedUnit> paramPartialFunction);
/*     */   
/*     */   void whenUnhandled(PartialFunction<Event<D>, State<S, D>> paramPartialFunction);
/*     */   
/*     */   void initialize();
/*     */   
/*     */   S stateName();
/*     */   
/*     */   D stateData();
/*     */   
/*     */   D nextStateData();
/*     */   
/*     */   boolean debugEvent();
/*     */   
/*     */   State<S, D> akka$actor$FSM$$currentState();
/*     */   
/*     */   @TraitSetter
/*     */   void akka$actor$FSM$$currentState_$eq(State<S, D> paramState);
/*     */   
/*     */   Option<Cancellable> akka$actor$FSM$$timeoutFuture();
/*     */   
/*     */   @TraitSetter
/*     */   void akka$actor$FSM$$timeoutFuture_$eq(Option<Cancellable> paramOption);
/*     */   
/*     */   State<S, D> akka$actor$FSM$$nextState();
/*     */   
/*     */   @TraitSetter
/*     */   void akka$actor$FSM$$nextState_$eq(State<S, D> paramState);
/*     */   
/*     */   long akka$actor$FSM$$generation();
/*     */   
/*     */   @TraitSetter
/*     */   void akka$actor$FSM$$generation_$eq(long paramLong);
/*     */   
/*     */   Map<String, Timer> akka$actor$FSM$$timers();
/*     */   
/*     */   Iterator<Object> akka$actor$FSM$$timerGen();
/*     */   
/*     */   Map<S, PartialFunction<Event<D>, State<S, D>>> akka$actor$FSM$$stateFunctions();
/*     */   
/*     */   Map<S, Option<FiniteDuration>> akka$actor$FSM$$stateTimeouts();
/*     */   
/*     */   PartialFunction<Event<D>, State<S, D>> akka$actor$FSM$$handleEventDefault();
/*     */   
/*     */   PartialFunction<Event<D>, State<S, D>> akka$actor$FSM$$handleEvent();
/*     */   
/*     */   @TraitSetter
/*     */   void akka$actor$FSM$$handleEvent_$eq(PartialFunction<Event<D>, State<S, D>> paramPartialFunction);
/*     */   
/*     */   PartialFunction<StopEvent<S, D>, BoxedUnit> akka$actor$FSM$$terminateEvent();
/*     */   
/*     */   @TraitSetter
/*     */   void akka$actor$FSM$$terminateEvent_$eq(PartialFunction<StopEvent<S, D>, BoxedUnit> paramPartialFunction);
/*     */   
/*     */   List<PartialFunction<Tuple2<S, S>, BoxedUnit>> akka$actor$FSM$$transitionEvent();
/*     */   
/*     */   @TraitSetter
/*     */   void akka$actor$FSM$$transitionEvent_$eq(List<PartialFunction<Tuple2<S, S>, BoxedUnit>> paramList);
/*     */   
/*     */   PartialFunction<Object, BoxedUnit> receive();
/*     */   
/*     */   void processEvent(Event<D> paramEvent, Object paramObject);
/*     */   
/*     */   void applyState(State<S, D> paramState);
/*     */   
/*     */   void makeTransition(State<S, D> paramState);
/*     */   
/*     */   void postStop();
/*     */   
/*     */   void logTermination(Reason paramReason);
/*     */   
/*     */   public static class NullFunction$ implements PartialFunction<Object, scala.runtime.Nothing$> {
/*     */     public static final NullFunction$ MODULE$;
/*     */     
/*     */     public <A1, B1> PartialFunction<A1, B1> orElse(PartialFunction that) {
/*  22 */       return PartialFunction.class.orElse(this, that);
/*     */     }
/*     */     
/*     */     public <C> PartialFunction<Object, C> andThen(Function1 k) {
/*  22 */       return PartialFunction.class.andThen(this, k);
/*     */     }
/*     */     
/*     */     public Function1<Object, Option<scala.runtime.Nothing$>> lift() {
/*  22 */       return PartialFunction.class.lift(this);
/*     */     }
/*     */     
/*     */     public <A1, B1> B1 applyOrElse(Object x, Function1 default) {
/*  22 */       return (B1)PartialFunction.class.applyOrElse(this, x, default);
/*     */     }
/*     */     
/*     */     public <U> Function1<Object, Object> runWith(Function1 action) {
/*  22 */       return PartialFunction.class.runWith(this, action);
/*     */     }
/*     */     
/*     */     public boolean apply$mcZD$sp(double v1) {
/*  22 */       return Function1.class.apply$mcZD$sp((Function1)this, v1);
/*     */     }
/*     */     
/*     */     public double apply$mcDD$sp(double v1) {
/*  22 */       return Function1.class.apply$mcDD$sp((Function1)this, v1);
/*     */     }
/*     */     
/*     */     public float apply$mcFD$sp(double v1) {
/*  22 */       return Function1.class.apply$mcFD$sp((Function1)this, v1);
/*     */     }
/*     */     
/*     */     public int apply$mcID$sp(double v1) {
/*  22 */       return Function1.class.apply$mcID$sp((Function1)this, v1);
/*     */     }
/*     */     
/*     */     public long apply$mcJD$sp(double v1) {
/*  22 */       return Function1.class.apply$mcJD$sp((Function1)this, v1);
/*     */     }
/*     */     
/*     */     public void apply$mcVD$sp(double v1) {
/*  22 */       Function1.class.apply$mcVD$sp((Function1)this, v1);
/*     */     }
/*     */     
/*     */     public boolean apply$mcZF$sp(float v1) {
/*  22 */       return Function1.class.apply$mcZF$sp((Function1)this, v1);
/*     */     }
/*     */     
/*     */     public double apply$mcDF$sp(float v1) {
/*  22 */       return Function1.class.apply$mcDF$sp((Function1)this, v1);
/*     */     }
/*     */     
/*     */     public float apply$mcFF$sp(float v1) {
/*  22 */       return Function1.class.apply$mcFF$sp((Function1)this, v1);
/*     */     }
/*     */     
/*     */     public int apply$mcIF$sp(float v1) {
/*  22 */       return Function1.class.apply$mcIF$sp((Function1)this, v1);
/*     */     }
/*     */     
/*     */     public long apply$mcJF$sp(float v1) {
/*  22 */       return Function1.class.apply$mcJF$sp((Function1)this, v1);
/*     */     }
/*     */     
/*     */     public void apply$mcVF$sp(float v1) {
/*  22 */       Function1.class.apply$mcVF$sp((Function1)this, v1);
/*     */     }
/*     */     
/*     */     public boolean apply$mcZI$sp(int v1) {
/*  22 */       return Function1.class.apply$mcZI$sp((Function1)this, v1);
/*     */     }
/*     */     
/*     */     public double apply$mcDI$sp(int v1) {
/*  22 */       return Function1.class.apply$mcDI$sp((Function1)this, v1);
/*     */     }
/*     */     
/*     */     public float apply$mcFI$sp(int v1) {
/*  22 */       return Function1.class.apply$mcFI$sp((Function1)this, v1);
/*     */     }
/*     */     
/*     */     public int apply$mcII$sp(int v1) {
/*  22 */       return Function1.class.apply$mcII$sp((Function1)this, v1);
/*     */     }
/*     */     
/*     */     public long apply$mcJI$sp(int v1) {
/*  22 */       return Function1.class.apply$mcJI$sp((Function1)this, v1);
/*     */     }
/*     */     
/*     */     public void apply$mcVI$sp(int v1) {
/*  22 */       Function1.class.apply$mcVI$sp((Function1)this, v1);
/*     */     }
/*     */     
/*     */     public boolean apply$mcZJ$sp(long v1) {
/*  22 */       return Function1.class.apply$mcZJ$sp((Function1)this, v1);
/*     */     }
/*     */     
/*     */     public double apply$mcDJ$sp(long v1) {
/*  22 */       return Function1.class.apply$mcDJ$sp((Function1)this, v1);
/*     */     }
/*     */     
/*     */     public float apply$mcFJ$sp(long v1) {
/*  22 */       return Function1.class.apply$mcFJ$sp((Function1)this, v1);
/*     */     }
/*     */     
/*     */     public int apply$mcIJ$sp(long v1) {
/*  22 */       return Function1.class.apply$mcIJ$sp((Function1)this, v1);
/*     */     }
/*     */     
/*     */     public long apply$mcJJ$sp(long v1) {
/*  22 */       return Function1.class.apply$mcJJ$sp((Function1)this, v1);
/*     */     }
/*     */     
/*     */     public void apply$mcVJ$sp(long v1) {
/*  22 */       Function1.class.apply$mcVJ$sp((Function1)this, v1);
/*     */     }
/*     */     
/*     */     public <A> Function1<A, scala.runtime.Nothing$> compose(Function1 g) {
/*  22 */       return Function1.class.compose((Function1)this, g);
/*     */     }
/*     */     
/*     */     public <A> Function1<A, Object> compose$mcZD$sp(Function1 g) {
/*  22 */       return Function1.class.compose$mcZD$sp((Function1)this, g);
/*     */     }
/*     */     
/*     */     public <A> Function1<A, Object> compose$mcDD$sp(Function1 g) {
/*  22 */       return Function1.class.compose$mcDD$sp((Function1)this, g);
/*     */     }
/*     */     
/*     */     public <A> Function1<A, Object> compose$mcFD$sp(Function1 g) {
/*  22 */       return Function1.class.compose$mcFD$sp((Function1)this, g);
/*     */     }
/*     */     
/*     */     public <A> Function1<A, Object> compose$mcID$sp(Function1 g) {
/*  22 */       return Function1.class.compose$mcID$sp((Function1)this, g);
/*     */     }
/*     */     
/*     */     public <A> Function1<A, Object> compose$mcJD$sp(Function1 g) {
/*  22 */       return Function1.class.compose$mcJD$sp((Function1)this, g);
/*     */     }
/*     */     
/*     */     public <A> Function1<A, BoxedUnit> compose$mcVD$sp(Function1 g) {
/*  22 */       return Function1.class.compose$mcVD$sp((Function1)this, g);
/*     */     }
/*     */     
/*     */     public <A> Function1<A, Object> compose$mcZF$sp(Function1 g) {
/*  22 */       return Function1.class.compose$mcZF$sp((Function1)this, g);
/*     */     }
/*     */     
/*     */     public <A> Function1<A, Object> compose$mcDF$sp(Function1 g) {
/*  22 */       return Function1.class.compose$mcDF$sp((Function1)this, g);
/*     */     }
/*     */     
/*     */     public <A> Function1<A, Object> compose$mcFF$sp(Function1 g) {
/*  22 */       return Function1.class.compose$mcFF$sp((Function1)this, g);
/*     */     }
/*     */     
/*     */     public <A> Function1<A, Object> compose$mcIF$sp(Function1 g) {
/*  22 */       return Function1.class.compose$mcIF$sp((Function1)this, g);
/*     */     }
/*     */     
/*     */     public <A> Function1<A, Object> compose$mcJF$sp(Function1 g) {
/*  22 */       return Function1.class.compose$mcJF$sp((Function1)this, g);
/*     */     }
/*     */     
/*     */     public <A> Function1<A, BoxedUnit> compose$mcVF$sp(Function1 g) {
/*  22 */       return Function1.class.compose$mcVF$sp((Function1)this, g);
/*     */     }
/*     */     
/*     */     public <A> Function1<A, Object> compose$mcZI$sp(Function1 g) {
/*  22 */       return Function1.class.compose$mcZI$sp((Function1)this, g);
/*     */     }
/*     */     
/*     */     public <A> Function1<A, Object> compose$mcDI$sp(Function1 g) {
/*  22 */       return Function1.class.compose$mcDI$sp((Function1)this, g);
/*     */     }
/*     */     
/*     */     public <A> Function1<A, Object> compose$mcFI$sp(Function1 g) {
/*  22 */       return Function1.class.compose$mcFI$sp((Function1)this, g);
/*     */     }
/*     */     
/*     */     public <A> Function1<A, Object> compose$mcII$sp(Function1 g) {
/*  22 */       return Function1.class.compose$mcII$sp((Function1)this, g);
/*     */     }
/*     */     
/*     */     public <A> Function1<A, Object> compose$mcJI$sp(Function1 g) {
/*  22 */       return Function1.class.compose$mcJI$sp((Function1)this, g);
/*     */     }
/*     */     
/*     */     public <A> Function1<A, BoxedUnit> compose$mcVI$sp(Function1 g) {
/*  22 */       return Function1.class.compose$mcVI$sp((Function1)this, g);
/*     */     }
/*     */     
/*     */     public <A> Function1<A, Object> compose$mcZJ$sp(Function1 g) {
/*  22 */       return Function1.class.compose$mcZJ$sp((Function1)this, g);
/*     */     }
/*     */     
/*     */     public <A> Function1<A, Object> compose$mcDJ$sp(Function1 g) {
/*  22 */       return Function1.class.compose$mcDJ$sp((Function1)this, g);
/*     */     }
/*     */     
/*     */     public <A> Function1<A, Object> compose$mcFJ$sp(Function1 g) {
/*  22 */       return Function1.class.compose$mcFJ$sp((Function1)this, g);
/*     */     }
/*     */     
/*     */     public <A> Function1<A, Object> compose$mcIJ$sp(Function1 g) {
/*  22 */       return Function1.class.compose$mcIJ$sp((Function1)this, g);
/*     */     }
/*     */     
/*     */     public <A> Function1<A, Object> compose$mcJJ$sp(Function1 g) {
/*  22 */       return Function1.class.compose$mcJJ$sp((Function1)this, g);
/*     */     }
/*     */     
/*     */     public <A> Function1<A, BoxedUnit> compose$mcVJ$sp(Function1 g) {
/*  22 */       return Function1.class.compose$mcVJ$sp((Function1)this, g);
/*     */     }
/*     */     
/*     */     public <A> Function1<Object, A> andThen$mcZD$sp(Function1 g) {
/*  22 */       return Function1.class.andThen$mcZD$sp((Function1)this, g);
/*     */     }
/*     */     
/*     */     public <A> Function1<Object, A> andThen$mcDD$sp(Function1 g) {
/*  22 */       return Function1.class.andThen$mcDD$sp((Function1)this, g);
/*     */     }
/*     */     
/*     */     public <A> Function1<Object, A> andThen$mcFD$sp(Function1 g) {
/*  22 */       return Function1.class.andThen$mcFD$sp((Function1)this, g);
/*     */     }
/*     */     
/*     */     public <A> Function1<Object, A> andThen$mcID$sp(Function1 g) {
/*  22 */       return Function1.class.andThen$mcID$sp((Function1)this, g);
/*     */     }
/*     */     
/*     */     public <A> Function1<Object, A> andThen$mcJD$sp(Function1 g) {
/*  22 */       return Function1.class.andThen$mcJD$sp((Function1)this, g);
/*     */     }
/*     */     
/*     */     public <A> Function1<Object, A> andThen$mcVD$sp(Function1 g) {
/*  22 */       return Function1.class.andThen$mcVD$sp((Function1)this, g);
/*     */     }
/*     */     
/*     */     public <A> Function1<Object, A> andThen$mcZF$sp(Function1 g) {
/*  22 */       return Function1.class.andThen$mcZF$sp((Function1)this, g);
/*     */     }
/*     */     
/*     */     public <A> Function1<Object, A> andThen$mcDF$sp(Function1 g) {
/*  22 */       return Function1.class.andThen$mcDF$sp((Function1)this, g);
/*     */     }
/*     */     
/*     */     public <A> Function1<Object, A> andThen$mcFF$sp(Function1 g) {
/*  22 */       return Function1.class.andThen$mcFF$sp((Function1)this, g);
/*     */     }
/*     */     
/*     */     public <A> Function1<Object, A> andThen$mcIF$sp(Function1 g) {
/*  22 */       return Function1.class.andThen$mcIF$sp((Function1)this, g);
/*     */     }
/*     */     
/*     */     public <A> Function1<Object, A> andThen$mcJF$sp(Function1 g) {
/*  22 */       return Function1.class.andThen$mcJF$sp((Function1)this, g);
/*     */     }
/*     */     
/*     */     public <A> Function1<Object, A> andThen$mcVF$sp(Function1 g) {
/*  22 */       return Function1.class.andThen$mcVF$sp((Function1)this, g);
/*     */     }
/*     */     
/*     */     public <A> Function1<Object, A> andThen$mcZI$sp(Function1 g) {
/*  22 */       return Function1.class.andThen$mcZI$sp((Function1)this, g);
/*     */     }
/*     */     
/*     */     public <A> Function1<Object, A> andThen$mcDI$sp(Function1 g) {
/*  22 */       return Function1.class.andThen$mcDI$sp((Function1)this, g);
/*     */     }
/*     */     
/*     */     public <A> Function1<Object, A> andThen$mcFI$sp(Function1 g) {
/*  22 */       return Function1.class.andThen$mcFI$sp((Function1)this, g);
/*     */     }
/*     */     
/*     */     public <A> Function1<Object, A> andThen$mcII$sp(Function1 g) {
/*  22 */       return Function1.class.andThen$mcII$sp((Function1)this, g);
/*     */     }
/*     */     
/*     */     public <A> Function1<Object, A> andThen$mcJI$sp(Function1 g) {
/*  22 */       return Function1.class.andThen$mcJI$sp((Function1)this, g);
/*     */     }
/*     */     
/*     */     public <A> Function1<Object, A> andThen$mcVI$sp(Function1 g) {
/*  22 */       return Function1.class.andThen$mcVI$sp((Function1)this, g);
/*     */     }
/*     */     
/*     */     public <A> Function1<Object, A> andThen$mcZJ$sp(Function1 g) {
/*  22 */       return Function1.class.andThen$mcZJ$sp((Function1)this, g);
/*     */     }
/*     */     
/*     */     public <A> Function1<Object, A> andThen$mcDJ$sp(Function1 g) {
/*  22 */       return Function1.class.andThen$mcDJ$sp((Function1)this, g);
/*     */     }
/*     */     
/*     */     public <A> Function1<Object, A> andThen$mcFJ$sp(Function1 g) {
/*  22 */       return Function1.class.andThen$mcFJ$sp((Function1)this, g);
/*     */     }
/*     */     
/*     */     public <A> Function1<Object, A> andThen$mcIJ$sp(Function1 g) {
/*  22 */       return Function1.class.andThen$mcIJ$sp((Function1)this, g);
/*     */     }
/*     */     
/*     */     public <A> Function1<Object, A> andThen$mcJJ$sp(Function1 g) {
/*  22 */       return Function1.class.andThen$mcJJ$sp((Function1)this, g);
/*     */     }
/*     */     
/*     */     public <A> Function1<Object, A> andThen$mcVJ$sp(Function1 g) {
/*  22 */       return Function1.class.andThen$mcVJ$sp((Function1)this, g);
/*     */     }
/*     */     
/*     */     public String toString() {
/*  22 */       return Function1.class.toString((Function1)this);
/*     */     }
/*     */     
/*     */     public NullFunction$() {
/*  22 */       MODULE$ = this;
/*  22 */       Function1.class.$init$((Function1)this);
/*  22 */       PartialFunction.class.$init$(this);
/*     */     }
/*     */     
/*     */     public boolean isDefinedAt(Object o) {
/*  23 */       return false;
/*     */     }
/*     */     
/*     */     public scala.runtime.Nothing$ apply(Object o) {
/*  24 */       return scala.sys.package$.MODULE$.error("undefined");
/*     */     }
/*     */   }
/*     */   
/*     */   public static class CurrentState<S> implements Product, Serializable {
/*     */     private final ActorRef fsmRef;
/*     */     
/*     */     private final S state;
/*     */     
/*     */     public ActorRef fsmRef() {
/*  32 */       return this.fsmRef;
/*     */     }
/*     */     
/*     */     public S state() {
/*  32 */       return this.state;
/*     */     }
/*     */     
/*     */     public <S> CurrentState<S> copy(ActorRef fsmRef, Object state) {
/*  32 */       return new CurrentState(fsmRef, (S)state);
/*     */     }
/*     */     
/*     */     public <S> ActorRef copy$default$1() {
/*  32 */       return fsmRef();
/*     */     }
/*     */     
/*     */     public <S> S copy$default$2() {
/*  32 */       return state();
/*     */     }
/*     */     
/*     */     public String productPrefix() {
/*  32 */       return "CurrentState";
/*     */     }
/*     */     
/*     */     public int productArity() {
/*  32 */       return 2;
/*     */     }
/*     */     
/*     */     public Object productElement(int x$1) {
/*  32 */       int i = x$1;
/*  32 */       switch (i) {
/*     */         default:
/*  32 */           throw new IndexOutOfBoundsException(BoxesRunTime.boxToInteger(x$1).toString());
/*     */         case 1:
/*     */         
/*     */         case 0:
/*     */           break;
/*     */       } 
/*  32 */       return fsmRef();
/*     */     }
/*     */     
/*     */     public Iterator<Object> productIterator() {
/*  32 */       return scala.runtime.ScalaRunTime$.MODULE$.typedProductIterator(this);
/*     */     }
/*     */     
/*     */     public boolean canEqual(Object x$1) {
/*  32 */       return x$1 instanceof CurrentState;
/*     */     }
/*     */     
/*     */     public int hashCode() {
/*  32 */       return scala.runtime.ScalaRunTime$.MODULE$._hashCode(this);
/*     */     }
/*     */     
/*     */     public String toString() {
/*  32 */       return scala.runtime.ScalaRunTime$.MODULE$._toString(this);
/*     */     }
/*     */     
/*     */     public boolean equals(Object x$1) {
/*     */       // Byte code:
/*     */       //   0: aload_0
/*     */       //   1: aload_1
/*     */       //   2: if_acmpeq -> 95
/*     */       //   5: aload_1
/*     */       //   6: astore_2
/*     */       //   7: aload_2
/*     */       //   8: instanceof akka/actor/FSM$CurrentState
/*     */       //   11: ifeq -> 19
/*     */       //   14: iconst_1
/*     */       //   15: istore_3
/*     */       //   16: goto -> 21
/*     */       //   19: iconst_0
/*     */       //   20: istore_3
/*     */       //   21: iload_3
/*     */       //   22: ifeq -> 99
/*     */       //   25: aload_1
/*     */       //   26: checkcast akka/actor/FSM$CurrentState
/*     */       //   29: astore #4
/*     */       //   31: aload_0
/*     */       //   32: invokevirtual fsmRef : ()Lakka/actor/ActorRef;
/*     */       //   35: aload #4
/*     */       //   37: invokevirtual fsmRef : ()Lakka/actor/ActorRef;
/*     */       //   40: astore #5
/*     */       //   42: dup
/*     */       //   43: ifnonnull -> 55
/*     */       //   46: pop
/*     */       //   47: aload #5
/*     */       //   49: ifnull -> 63
/*     */       //   52: goto -> 91
/*     */       //   55: aload #5
/*     */       //   57: invokevirtual equals : (Ljava/lang/Object;)Z
/*     */       //   60: ifeq -> 91
/*     */       //   63: aload_0
/*     */       //   64: invokevirtual state : ()Ljava/lang/Object;
/*     */       //   67: aload #4
/*     */       //   69: invokevirtual state : ()Ljava/lang/Object;
/*     */       //   72: invokestatic equals : (Ljava/lang/Object;Ljava/lang/Object;)Z
/*     */       //   75: ifeq -> 91
/*     */       //   78: aload #4
/*     */       //   80: aload_0
/*     */       //   81: invokevirtual canEqual : (Ljava/lang/Object;)Z
/*     */       //   84: ifeq -> 91
/*     */       //   87: iconst_1
/*     */       //   88: goto -> 92
/*     */       //   91: iconst_0
/*     */       //   92: ifeq -> 99
/*     */       //   95: iconst_1
/*     */       //   96: goto -> 100
/*     */       //   99: iconst_0
/*     */       //   100: ireturn
/*     */       // Line number table:
/*     */       //   Java source line number -> byte code offset
/*     */       //   #32	-> 0
/*     */       //   #63	-> 14
/*     */       //   #32	-> 21
/*     */       // Local variable table:
/*     */       //   start	length	slot	name	descriptor
/*     */       //   0	101	0	this	Lakka/actor/FSM$CurrentState;
/*     */       //   0	101	1	x$1	Ljava/lang/Object;
/*     */     }
/*     */     
/*     */     public CurrentState(ActorRef fsmRef, Object state) {
/*  32 */       Product.class.$init$(this);
/*     */     }
/*     */   }
/*     */   
/*     */   public static class CurrentState$ implements Serializable {
/*     */     public static final CurrentState$ MODULE$;
/*     */     
/*     */     public final String toString() {
/*  32 */       return "CurrentState";
/*     */     }
/*     */     
/*     */     public <S> FSM.CurrentState<S> apply(ActorRef fsmRef, Object state) {
/*  32 */       return new FSM.CurrentState<S>(fsmRef, (S)state);
/*     */     }
/*     */     
/*     */     public <S> Option<Tuple2<ActorRef, S>> unapply(FSM.CurrentState x$0) {
/*  32 */       return (x$0 == null) ? (Option<Tuple2<ActorRef, S>>)scala.None$.MODULE$ : (Option<Tuple2<ActorRef, S>>)new Some(new Tuple2(x$0.fsmRef(), x$0.state()));
/*     */     }
/*     */     
/*     */     private Object readResolve() {
/*  32 */       return MODULE$;
/*     */     }
/*     */     
/*     */     public CurrentState$() {
/*  32 */       MODULE$ = this;
/*     */     }
/*     */   }
/*     */   
/*     */   public static class Transition<S> implements Product, Serializable {
/*     */     private final ActorRef fsmRef;
/*     */     
/*     */     private final S from;
/*     */     
/*     */     private final S to;
/*     */     
/*     */     public ActorRef fsmRef() {
/*  38 */       return this.fsmRef;
/*     */     }
/*     */     
/*     */     public S from() {
/*  38 */       return this.from;
/*     */     }
/*     */     
/*     */     public S to() {
/*  38 */       return this.to;
/*     */     }
/*     */     
/*     */     public <S> Transition<S> copy(ActorRef fsmRef, Object from, Object to) {
/*  38 */       return new Transition(fsmRef, (S)from, (S)to);
/*     */     }
/*     */     
/*     */     public <S> ActorRef copy$default$1() {
/*  38 */       return fsmRef();
/*     */     }
/*     */     
/*     */     public <S> S copy$default$2() {
/*  38 */       return from();
/*     */     }
/*     */     
/*     */     public <S> S copy$default$3() {
/*  38 */       return to();
/*     */     }
/*     */     
/*     */     public String productPrefix() {
/*  38 */       return "Transition";
/*     */     }
/*     */     
/*     */     public int productArity() {
/*  38 */       return 3;
/*     */     }
/*     */     
/*     */     public Object productElement(int x$1) {
/*  38 */       int i = x$1;
/*  38 */       switch (i) {
/*     */         default:
/*  38 */           throw new IndexOutOfBoundsException(BoxesRunTime.boxToInteger(x$1).toString());
/*     */         case 2:
/*     */         
/*     */         case 1:
/*     */         
/*     */         case 0:
/*     */           break;
/*     */       } 
/*  38 */       return fsmRef();
/*     */     }
/*     */     
/*     */     public Iterator<Object> productIterator() {
/*  38 */       return scala.runtime.ScalaRunTime$.MODULE$.typedProductIterator(this);
/*     */     }
/*     */     
/*     */     public boolean canEqual(Object x$1) {
/*  38 */       return x$1 instanceof Transition;
/*     */     }
/*     */     
/*     */     public int hashCode() {
/*  38 */       return scala.runtime.ScalaRunTime$.MODULE$._hashCode(this);
/*     */     }
/*     */     
/*     */     public String toString() {
/*  38 */       return scala.runtime.ScalaRunTime$.MODULE$._toString(this);
/*     */     }
/*     */     
/*     */     public boolean equals(Object x$1) {
/*     */       // Byte code:
/*     */       //   0: aload_0
/*     */       //   1: aload_1
/*     */       //   2: if_acmpeq -> 110
/*     */       //   5: aload_1
/*     */       //   6: astore_2
/*     */       //   7: aload_2
/*     */       //   8: instanceof akka/actor/FSM$Transition
/*     */       //   11: ifeq -> 19
/*     */       //   14: iconst_1
/*     */       //   15: istore_3
/*     */       //   16: goto -> 21
/*     */       //   19: iconst_0
/*     */       //   20: istore_3
/*     */       //   21: iload_3
/*     */       //   22: ifeq -> 114
/*     */       //   25: aload_1
/*     */       //   26: checkcast akka/actor/FSM$Transition
/*     */       //   29: astore #4
/*     */       //   31: aload_0
/*     */       //   32: invokevirtual fsmRef : ()Lakka/actor/ActorRef;
/*     */       //   35: aload #4
/*     */       //   37: invokevirtual fsmRef : ()Lakka/actor/ActorRef;
/*     */       //   40: astore #5
/*     */       //   42: dup
/*     */       //   43: ifnonnull -> 55
/*     */       //   46: pop
/*     */       //   47: aload #5
/*     */       //   49: ifnull -> 63
/*     */       //   52: goto -> 106
/*     */       //   55: aload #5
/*     */       //   57: invokevirtual equals : (Ljava/lang/Object;)Z
/*     */       //   60: ifeq -> 106
/*     */       //   63: aload_0
/*     */       //   64: invokevirtual from : ()Ljava/lang/Object;
/*     */       //   67: aload #4
/*     */       //   69: invokevirtual from : ()Ljava/lang/Object;
/*     */       //   72: invokestatic equals : (Ljava/lang/Object;Ljava/lang/Object;)Z
/*     */       //   75: ifeq -> 106
/*     */       //   78: aload_0
/*     */       //   79: invokevirtual to : ()Ljava/lang/Object;
/*     */       //   82: aload #4
/*     */       //   84: invokevirtual to : ()Ljava/lang/Object;
/*     */       //   87: invokestatic equals : (Ljava/lang/Object;Ljava/lang/Object;)Z
/*     */       //   90: ifeq -> 106
/*     */       //   93: aload #4
/*     */       //   95: aload_0
/*     */       //   96: invokevirtual canEqual : (Ljava/lang/Object;)Z
/*     */       //   99: ifeq -> 106
/*     */       //   102: iconst_1
/*     */       //   103: goto -> 107
/*     */       //   106: iconst_0
/*     */       //   107: ifeq -> 114
/*     */       //   110: iconst_1
/*     */       //   111: goto -> 115
/*     */       //   114: iconst_0
/*     */       //   115: ireturn
/*     */       // Line number table:
/*     */       //   Java source line number -> byte code offset
/*     */       //   #38	-> 0
/*     */       //   #63	-> 14
/*     */       //   #38	-> 21
/*     */       // Local variable table:
/*     */       //   start	length	slot	name	descriptor
/*     */       //   0	116	0	this	Lakka/actor/FSM$Transition;
/*     */       //   0	116	1	x$1	Ljava/lang/Object;
/*     */     }
/*     */     
/*     */     public Transition(ActorRef fsmRef, Object from, Object to) {
/*  38 */       Product.class.$init$(this);
/*     */     }
/*     */   }
/*     */   
/*     */   public static class Transition$ implements Serializable {
/*     */     public static final Transition$ MODULE$;
/*     */     
/*     */     public final String toString() {
/*  38 */       return "Transition";
/*     */     }
/*     */     
/*     */     public <S> FSM.Transition<S> apply(ActorRef fsmRef, Object from, Object to) {
/*  38 */       return new FSM.Transition<S>(fsmRef, (S)from, (S)to);
/*     */     }
/*     */     
/*     */     public <S> Option<Tuple3<ActorRef, S, S>> unapply(FSM.Transition x$0) {
/*  38 */       return (x$0 == null) ? (Option<Tuple3<ActorRef, S, S>>)scala.None$.MODULE$ : (Option<Tuple3<ActorRef, S, S>>)new Some(new Tuple3(x$0.fsmRef(), x$0.from(), x$0.to()));
/*     */     }
/*     */     
/*     */     private Object readResolve() {
/*  38 */       return MODULE$;
/*     */     }
/*     */     
/*     */     public Transition$() {
/*  38 */       MODULE$ = this;
/*     */     }
/*     */   }
/*     */   
/*     */   public static class SubscribeTransitionCallBack implements Product, Serializable {
/*     */     private final ActorRef actorRef;
/*     */     
/*     */     public ActorRef actorRef() {
/*  45 */       return this.actorRef;
/*     */     }
/*     */     
/*     */     public SubscribeTransitionCallBack copy(ActorRef actorRef) {
/*  45 */       return new SubscribeTransitionCallBack(actorRef);
/*     */     }
/*     */     
/*     */     public ActorRef copy$default$1() {
/*  45 */       return actorRef();
/*     */     }
/*     */     
/*     */     public String productPrefix() {
/*  45 */       return "SubscribeTransitionCallBack";
/*     */     }
/*     */     
/*     */     public int productArity() {
/*  45 */       return 1;
/*     */     }
/*     */     
/*     */     public Object productElement(int x$1) {
/*  45 */       int i = x$1;
/*  45 */       switch (i) {
/*     */         default:
/*  45 */           throw new IndexOutOfBoundsException(BoxesRunTime.boxToInteger(x$1).toString());
/*     */         case 0:
/*     */           break;
/*     */       } 
/*  45 */       return actorRef();
/*     */     }
/*     */     
/*     */     public Iterator<Object> productIterator() {
/*  45 */       return scala.runtime.ScalaRunTime$.MODULE$.typedProductIterator(this);
/*     */     }
/*     */     
/*     */     public boolean canEqual(Object x$1) {
/*  45 */       return x$1 instanceof SubscribeTransitionCallBack;
/*     */     }
/*     */     
/*     */     public int hashCode() {
/*  45 */       return scala.runtime.ScalaRunTime$.MODULE$._hashCode(this);
/*     */     }
/*     */     
/*     */     public String toString() {
/*  45 */       return scala.runtime.ScalaRunTime$.MODULE$._toString(this);
/*     */     }
/*     */     
/*     */     public boolean equals(Object x$1) {
/*     */       // Byte code:
/*     */       //   0: aload_0
/*     */       //   1: aload_1
/*     */       //   2: if_acmpeq -> 80
/*     */       //   5: aload_1
/*     */       //   6: astore_2
/*     */       //   7: aload_2
/*     */       //   8: instanceof akka/actor/FSM$SubscribeTransitionCallBack
/*     */       //   11: ifeq -> 19
/*     */       //   14: iconst_1
/*     */       //   15: istore_3
/*     */       //   16: goto -> 21
/*     */       //   19: iconst_0
/*     */       //   20: istore_3
/*     */       //   21: iload_3
/*     */       //   22: ifeq -> 84
/*     */       //   25: aload_1
/*     */       //   26: checkcast akka/actor/FSM$SubscribeTransitionCallBack
/*     */       //   29: astore #4
/*     */       //   31: aload_0
/*     */       //   32: invokevirtual actorRef : ()Lakka/actor/ActorRef;
/*     */       //   35: aload #4
/*     */       //   37: invokevirtual actorRef : ()Lakka/actor/ActorRef;
/*     */       //   40: astore #5
/*     */       //   42: dup
/*     */       //   43: ifnonnull -> 55
/*     */       //   46: pop
/*     */       //   47: aload #5
/*     */       //   49: ifnull -> 63
/*     */       //   52: goto -> 76
/*     */       //   55: aload #5
/*     */       //   57: invokevirtual equals : (Ljava/lang/Object;)Z
/*     */       //   60: ifeq -> 76
/*     */       //   63: aload #4
/*     */       //   65: aload_0
/*     */       //   66: invokevirtual canEqual : (Ljava/lang/Object;)Z
/*     */       //   69: ifeq -> 76
/*     */       //   72: iconst_1
/*     */       //   73: goto -> 77
/*     */       //   76: iconst_0
/*     */       //   77: ifeq -> 84
/*     */       //   80: iconst_1
/*     */       //   81: goto -> 85
/*     */       //   84: iconst_0
/*     */       //   85: ireturn
/*     */       // Line number table:
/*     */       //   Java source line number -> byte code offset
/*     */       //   #45	-> 0
/*     */       //   #63	-> 14
/*     */       //   #45	-> 21
/*     */       // Local variable table:
/*     */       //   start	length	slot	name	descriptor
/*     */       //   0	86	0	this	Lakka/actor/FSM$SubscribeTransitionCallBack;
/*     */       //   0	86	1	x$1	Ljava/lang/Object;
/*     */     }
/*     */     
/*     */     public SubscribeTransitionCallBack(ActorRef actorRef) {
/*  45 */       Product.class.$init$(this);
/*     */     }
/*     */   }
/*     */   
/*     */   public static class SubscribeTransitionCallBack$ extends AbstractFunction1<ActorRef, SubscribeTransitionCallBack> implements Serializable {
/*     */     public static final SubscribeTransitionCallBack$ MODULE$;
/*     */     
/*     */     public final String toString() {
/*  45 */       return "SubscribeTransitionCallBack";
/*     */     }
/*     */     
/*     */     public FSM.SubscribeTransitionCallBack apply(ActorRef actorRef) {
/*  45 */       return new FSM.SubscribeTransitionCallBack(actorRef);
/*     */     }
/*     */     
/*     */     public Option<ActorRef> unapply(FSM.SubscribeTransitionCallBack x$0) {
/*  45 */       return (x$0 == null) ? (Option<ActorRef>)scala.None$.MODULE$ : (Option<ActorRef>)new Some(x$0.actorRef());
/*     */     }
/*     */     
/*     */     private Object readResolve() {
/*  45 */       return MODULE$;
/*     */     }
/*     */     
/*     */     public SubscribeTransitionCallBack$() {
/*  45 */       MODULE$ = this;
/*     */     }
/*     */   }
/*     */   
/*     */   public static class UnsubscribeTransitionCallBack implements Product, Serializable {
/*     */     private final ActorRef actorRef;
/*     */     
/*     */     public ActorRef actorRef() {
/*  51 */       return this.actorRef;
/*     */     }
/*     */     
/*     */     public UnsubscribeTransitionCallBack copy(ActorRef actorRef) {
/*  51 */       return new UnsubscribeTransitionCallBack(actorRef);
/*     */     }
/*     */     
/*     */     public ActorRef copy$default$1() {
/*  51 */       return actorRef();
/*     */     }
/*     */     
/*     */     public String productPrefix() {
/*  51 */       return "UnsubscribeTransitionCallBack";
/*     */     }
/*     */     
/*     */     public int productArity() {
/*  51 */       return 1;
/*     */     }
/*     */     
/*     */     public Object productElement(int x$1) {
/*  51 */       int i = x$1;
/*  51 */       switch (i) {
/*     */         default:
/*  51 */           throw new IndexOutOfBoundsException(BoxesRunTime.boxToInteger(x$1).toString());
/*     */         case 0:
/*     */           break;
/*     */       } 
/*  51 */       return actorRef();
/*     */     }
/*     */     
/*     */     public Iterator<Object> productIterator() {
/*  51 */       return scala.runtime.ScalaRunTime$.MODULE$.typedProductIterator(this);
/*     */     }
/*     */     
/*     */     public boolean canEqual(Object x$1) {
/*  51 */       return x$1 instanceof UnsubscribeTransitionCallBack;
/*     */     }
/*     */     
/*     */     public int hashCode() {
/*  51 */       return scala.runtime.ScalaRunTime$.MODULE$._hashCode(this);
/*     */     }
/*     */     
/*     */     public String toString() {
/*  51 */       return scala.runtime.ScalaRunTime$.MODULE$._toString(this);
/*     */     }
/*     */     
/*     */     public boolean equals(Object x$1) {
/*     */       // Byte code:
/*     */       //   0: aload_0
/*     */       //   1: aload_1
/*     */       //   2: if_acmpeq -> 80
/*     */       //   5: aload_1
/*     */       //   6: astore_2
/*     */       //   7: aload_2
/*     */       //   8: instanceof akka/actor/FSM$UnsubscribeTransitionCallBack
/*     */       //   11: ifeq -> 19
/*     */       //   14: iconst_1
/*     */       //   15: istore_3
/*     */       //   16: goto -> 21
/*     */       //   19: iconst_0
/*     */       //   20: istore_3
/*     */       //   21: iload_3
/*     */       //   22: ifeq -> 84
/*     */       //   25: aload_1
/*     */       //   26: checkcast akka/actor/FSM$UnsubscribeTransitionCallBack
/*     */       //   29: astore #4
/*     */       //   31: aload_0
/*     */       //   32: invokevirtual actorRef : ()Lakka/actor/ActorRef;
/*     */       //   35: aload #4
/*     */       //   37: invokevirtual actorRef : ()Lakka/actor/ActorRef;
/*     */       //   40: astore #5
/*     */       //   42: dup
/*     */       //   43: ifnonnull -> 55
/*     */       //   46: pop
/*     */       //   47: aload #5
/*     */       //   49: ifnull -> 63
/*     */       //   52: goto -> 76
/*     */       //   55: aload #5
/*     */       //   57: invokevirtual equals : (Ljava/lang/Object;)Z
/*     */       //   60: ifeq -> 76
/*     */       //   63: aload #4
/*     */       //   65: aload_0
/*     */       //   66: invokevirtual canEqual : (Ljava/lang/Object;)Z
/*     */       //   69: ifeq -> 76
/*     */       //   72: iconst_1
/*     */       //   73: goto -> 77
/*     */       //   76: iconst_0
/*     */       //   77: ifeq -> 84
/*     */       //   80: iconst_1
/*     */       //   81: goto -> 85
/*     */       //   84: iconst_0
/*     */       //   85: ireturn
/*     */       // Line number table:
/*     */       //   Java source line number -> byte code offset
/*     */       //   #51	-> 0
/*     */       //   #63	-> 14
/*     */       //   #51	-> 21
/*     */       // Local variable table:
/*     */       //   start	length	slot	name	descriptor
/*     */       //   0	86	0	this	Lakka/actor/FSM$UnsubscribeTransitionCallBack;
/*     */       //   0	86	1	x$1	Ljava/lang/Object;
/*     */     }
/*     */     
/*     */     public UnsubscribeTransitionCallBack(ActorRef actorRef) {
/*  51 */       Product.class.$init$(this);
/*     */     }
/*     */   }
/*     */   
/*     */   public static class UnsubscribeTransitionCallBack$ extends AbstractFunction1<ActorRef, UnsubscribeTransitionCallBack> implements Serializable {
/*     */     public static final UnsubscribeTransitionCallBack$ MODULE$;
/*     */     
/*     */     public final String toString() {
/*  51 */       return "UnsubscribeTransitionCallBack";
/*     */     }
/*     */     
/*     */     public FSM.UnsubscribeTransitionCallBack apply(ActorRef actorRef) {
/*  51 */       return new FSM.UnsubscribeTransitionCallBack(actorRef);
/*     */     }
/*     */     
/*     */     public Option<ActorRef> unapply(FSM.UnsubscribeTransitionCallBack x$0) {
/*  51 */       return (x$0 == null) ? (Option<ActorRef>)scala.None$.MODULE$ : (Option<ActorRef>)new Some(x$0.actorRef());
/*     */     }
/*     */     
/*     */     private Object readResolve() {
/*  51 */       return MODULE$;
/*     */     }
/*     */     
/*     */     public UnsubscribeTransitionCallBack$() {
/*  51 */       MODULE$ = this;
/*     */     }
/*     */   }
/*     */   
/*     */   public static class Normal$ implements Reason, Product, Serializable {
/*     */     public static final Normal$ MODULE$;
/*     */     
/*     */     public String productPrefix() {
/*  61 */       return "Normal";
/*     */     }
/*     */     
/*     */     public int productArity() {
/*  61 */       return 0;
/*     */     }
/*     */     
/*     */     public Object productElement(int x$1) {
/*  61 */       int i = x$1;
/*  61 */       throw new IndexOutOfBoundsException(BoxesRunTime.boxToInteger(x$1).toString());
/*     */     }
/*     */     
/*     */     public Iterator<Object> productIterator() {
/*  61 */       return scala.runtime.ScalaRunTime$.MODULE$.typedProductIterator(this);
/*     */     }
/*     */     
/*     */     public boolean canEqual(Object x$1) {
/*  61 */       return x$1 instanceof Normal$;
/*     */     }
/*     */     
/*     */     public int hashCode() {
/*  61 */       return -1955878649;
/*     */     }
/*     */     
/*     */     public String toString() {
/*  61 */       return "Normal";
/*     */     }
/*     */     
/*     */     private Object readResolve() {
/*  61 */       return MODULE$;
/*     */     }
/*     */     
/*     */     public Normal$() {
/*  61 */       MODULE$ = this;
/*  61 */       Product.class.$init$(this);
/*     */     }
/*     */   }
/*     */   
/*     */   public static class Shutdown$ implements Reason, Product, Serializable {
/*     */     public static final Shutdown$ MODULE$;
/*     */     
/*     */     public String productPrefix() {
/*  67 */       return "Shutdown";
/*     */     }
/*     */     
/*     */     public int productArity() {
/*  67 */       return 0;
/*     */     }
/*     */     
/*     */     public Object productElement(int x$1) {
/*  67 */       int i = x$1;
/*  67 */       throw new IndexOutOfBoundsException(BoxesRunTime.boxToInteger(x$1).toString());
/*     */     }
/*     */     
/*     */     public Iterator<Object> productIterator() {
/*  67 */       return scala.runtime.ScalaRunTime$.MODULE$.typedProductIterator(this);
/*     */     }
/*     */     
/*     */     public boolean canEqual(Object x$1) {
/*  67 */       return x$1 instanceof Shutdown$;
/*     */     }
/*     */     
/*     */     public int hashCode() {
/*  67 */       return -104699274;
/*     */     }
/*     */     
/*     */     public String toString() {
/*  67 */       return "Shutdown";
/*     */     }
/*     */     
/*     */     private Object readResolve() {
/*  67 */       return MODULE$;
/*     */     }
/*     */     
/*     */     public Shutdown$() {
/*  67 */       MODULE$ = this;
/*  67 */       Product.class.$init$(this);
/*     */     }
/*     */   }
/*     */   
/*     */   public static class Failure implements Reason, Product, Serializable {
/*     */     private final Object cause;
/*     */     
/*     */     public Object cause() {
/*  74 */       return this.cause;
/*     */     }
/*     */     
/*     */     public Failure copy(Object cause) {
/*  74 */       return new Failure(cause);
/*     */     }
/*     */     
/*     */     public Object copy$default$1() {
/*  74 */       return cause();
/*     */     }
/*     */     
/*     */     public String productPrefix() {
/*  74 */       return "Failure";
/*     */     }
/*     */     
/*     */     public int productArity() {
/*  74 */       return 1;
/*     */     }
/*     */     
/*     */     public Object productElement(int x$1) {
/*  74 */       int i = x$1;
/*  74 */       switch (i) {
/*     */         default:
/*  74 */           throw new IndexOutOfBoundsException(BoxesRunTime.boxToInteger(x$1).toString());
/*     */         case 0:
/*     */           break;
/*     */       } 
/*  74 */       return cause();
/*     */     }
/*     */     
/*     */     public Iterator<Object> productIterator() {
/*  74 */       return scala.runtime.ScalaRunTime$.MODULE$.typedProductIterator(this);
/*     */     }
/*     */     
/*     */     public boolean canEqual(Object x$1) {
/*  74 */       return x$1 instanceof Failure;
/*     */     }
/*     */     
/*     */     public int hashCode() {
/*  74 */       return scala.runtime.ScalaRunTime$.MODULE$._hashCode(this);
/*     */     }
/*     */     
/*     */     public String toString() {
/*  74 */       return scala.runtime.ScalaRunTime$.MODULE$._toString(this);
/*     */     }
/*     */     
/*     */     public boolean equals(Object x$1) {
/*  74 */       if (this != x$1) {
/*     */         boolean bool;
/*  74 */         Object object = x$1;
/*  74 */         if (object instanceof Failure) {
/*     */           bool = true;
/*     */         } else {
/*     */           bool = false;
/*     */         } 
/*  74 */         if (bool) {
/*  74 */           Failure failure = (Failure)x$1;
/*  74 */           if ((BoxesRunTime.equals(cause(), failure.cause()) && failure.canEqual(this)));
/*     */         } 
/*  74 */         return false;
/*     */       } 
/*     */     }
/*     */     
/*     */     public Failure(Object cause) {
/*  74 */       Product.class.$init$(this);
/*     */     }
/*     */   }
/*     */   
/*     */   public static class Failure$ extends AbstractFunction1<Object, Failure> implements Serializable {
/*     */     public static final Failure$ MODULE$;
/*     */     
/*     */     public final String toString() {
/*  74 */       return "Failure";
/*     */     }
/*     */     
/*     */     public FSM.Failure apply(Object cause) {
/*  74 */       return new FSM.Failure(cause);
/*     */     }
/*     */     
/*     */     public Option<Object> unapply(FSM.Failure x$0) {
/*  74 */       return (x$0 == null) ? (Option<Object>)scala.None$.MODULE$ : (Option<Object>)new Some(x$0.cause());
/*     */     }
/*     */     
/*     */     private Object readResolve() {
/*  74 */       return MODULE$;
/*     */     }
/*     */     
/*     */     public Failure$() {
/*  74 */       MODULE$ = this;
/*     */     }
/*     */   }
/*     */   
/*     */   public static class StateTimeout$ implements Product, Serializable {
/*     */     public static final StateTimeout$ MODULE$;
/*     */     
/*     */     public String productPrefix() {
/*  79 */       return "StateTimeout";
/*     */     }
/*     */     
/*     */     public int productArity() {
/*  79 */       return 0;
/*     */     }
/*     */     
/*     */     public Object productElement(int x$1) {
/*  79 */       int i = x$1;
/*  79 */       throw new IndexOutOfBoundsException(BoxesRunTime.boxToInteger(x$1).toString());
/*     */     }
/*     */     
/*     */     public Iterator<Object> productIterator() {
/*  79 */       return scala.runtime.ScalaRunTime$.MODULE$.typedProductIterator(this);
/*     */     }
/*     */     
/*     */     public boolean canEqual(Object x$1) {
/*  79 */       return x$1 instanceof StateTimeout$;
/*     */     }
/*     */     
/*     */     public int hashCode() {
/*  79 */       return -976330832;
/*     */     }
/*     */     
/*     */     public String toString() {
/*  79 */       return "StateTimeout";
/*     */     }
/*     */     
/*     */     private Object readResolve() {
/*  79 */       return MODULE$;
/*     */     }
/*     */     
/*     */     public StateTimeout$() {
/*  84 */       MODULE$ = this;
/*  84 */       Product.class.$init$(this);
/*     */     }
/*     */   }
/*     */   
/*     */   public static class TimeoutMarker implements Product, Serializable {
/*     */     private final long generation;
/*     */     
/*     */     public long generation() {
/*  84 */       return this.generation;
/*     */     }
/*     */     
/*     */     public TimeoutMarker copy(long generation) {
/*  84 */       return new TimeoutMarker(generation);
/*     */     }
/*     */     
/*     */     public long copy$default$1() {
/*  84 */       return generation();
/*     */     }
/*     */     
/*     */     public String productPrefix() {
/*  84 */       return "TimeoutMarker";
/*     */     }
/*     */     
/*     */     public int productArity() {
/*  84 */       return 1;
/*     */     }
/*     */     
/*     */     public Object productElement(int x$1) {
/*  84 */       int i = x$1;
/*  84 */       switch (i) {
/*     */         default:
/*  84 */           throw new IndexOutOfBoundsException(BoxesRunTime.boxToInteger(x$1).toString());
/*     */         case 0:
/*     */           break;
/*     */       } 
/*  84 */       return BoxesRunTime.boxToLong(generation());
/*     */     }
/*     */     
/*     */     public Iterator<Object> productIterator() {
/*  84 */       return scala.runtime.ScalaRunTime$.MODULE$.typedProductIterator(this);
/*     */     }
/*     */     
/*     */     public boolean canEqual(Object x$1) {
/*  84 */       return x$1 instanceof TimeoutMarker;
/*     */     }
/*     */     
/*     */     public int hashCode() {
/*  84 */       int i = -889275714;
/*  84 */       i = Statics.mix(i, Statics.longHash(generation()));
/*  84 */       return Statics.finalizeHash(i, 1);
/*     */     }
/*     */     
/*     */     public String toString() {
/*  84 */       return scala.runtime.ScalaRunTime$.MODULE$._toString(this);
/*     */     }
/*     */     
/*     */     public boolean equals(Object x$1) {
/*  84 */       if (this != x$1) {
/*     */         boolean bool;
/*  84 */         Object object = x$1;
/*  84 */         if (object instanceof TimeoutMarker) {
/*     */           bool = true;
/*     */         } else {
/*     */           bool = false;
/*     */         } 
/*  84 */         if (bool) {
/*  84 */           TimeoutMarker timeoutMarker = (TimeoutMarker)x$1;
/*  84 */           if ((generation() == timeoutMarker.generation() && timeoutMarker.canEqual(this)));
/*     */         } 
/*  84 */         return false;
/*     */       } 
/*     */     }
/*     */     
/*     */     public TimeoutMarker(long generation) {
/*  84 */       Product.class.$init$(this);
/*     */     }
/*     */   }
/*     */   
/*     */   public static class TimeoutMarker$ extends AbstractFunction1<Object, TimeoutMarker> implements Serializable {
/*     */     public static final TimeoutMarker$ MODULE$;
/*     */     
/*     */     public final String toString() {
/*  84 */       return "TimeoutMarker";
/*     */     }
/*     */     
/*     */     public FSM.TimeoutMarker apply(long generation) {
/*  84 */       return new FSM.TimeoutMarker(generation);
/*     */     }
/*     */     
/*     */     public Option<Object> unapply(FSM.TimeoutMarker x$0) {
/*  84 */       return (x$0 == null) ? (Option<Object>)scala.None$.MODULE$ : (Option<Object>)new Some(BoxesRunTime.boxToLong(x$0.generation()));
/*     */     }
/*     */     
/*     */     private Object readResolve() {
/*  84 */       return MODULE$;
/*     */     }
/*     */     
/*     */     public TimeoutMarker$() {
/*  84 */       MODULE$ = this;
/*     */     }
/*     */   }
/*     */   
/*     */   public static class Timer implements NoSerializationVerificationNeeded, Product, Serializable {
/*     */     private final String name;
/*     */     
/*     */     private final Object msg;
/*     */     
/*     */     private final boolean repeat;
/*     */     
/*     */     private final int generation;
/*     */     
/*     */     private Option<Cancellable> ref;
/*     */     
/*     */     private final Scheduler scheduler;
/*     */     
/*     */     private final ExecutionContextExecutor executionContext;
/*     */     
/*     */     public String name() {
/*  90 */       return this.name;
/*     */     }
/*     */     
/*     */     public Object msg() {
/*  90 */       return this.msg;
/*     */     }
/*     */     
/*     */     public boolean repeat() {
/*  90 */       return this.repeat;
/*     */     }
/*     */     
/*     */     public int generation() {
/*  90 */       return this.generation;
/*     */     }
/*     */     
/*     */     public Timer copy(String name, Object msg, boolean repeat, int generation, ActorContext context) {
/*  90 */       return new Timer(name, msg, repeat, generation, context);
/*     */     }
/*     */     
/*     */     public String copy$default$1() {
/*  90 */       return name();
/*     */     }
/*     */     
/*     */     public Object copy$default$2() {
/*  90 */       return msg();
/*     */     }
/*     */     
/*     */     public boolean copy$default$3() {
/*  90 */       return repeat();
/*     */     }
/*     */     
/*     */     public int copy$default$4() {
/*  90 */       return generation();
/*     */     }
/*     */     
/*     */     public String productPrefix() {
/*  90 */       return "Timer";
/*     */     }
/*     */     
/*     */     public int productArity() {
/*  90 */       return 4;
/*     */     }
/*     */     
/*     */     public Object productElement(int x$1) {
/*  90 */       int i = x$1;
/*  90 */       switch (i) {
/*     */         default:
/*  90 */           throw new IndexOutOfBoundsException(BoxesRunTime.boxToInteger(x$1).toString());
/*     */         case 3:
/*     */         
/*     */         case 2:
/*     */         
/*     */         case 1:
/*     */         
/*     */         case 0:
/*     */           break;
/*     */       } 
/*  90 */       return name();
/*     */     }
/*     */     
/*     */     public Iterator<Object> productIterator() {
/*  90 */       return scala.runtime.ScalaRunTime$.MODULE$.typedProductIterator(this);
/*     */     }
/*     */     
/*     */     public boolean canEqual(Object x$1) {
/*  90 */       return x$1 instanceof Timer;
/*     */     }
/*     */     
/*     */     public int hashCode() {
/*  90 */       int i = -889275714;
/*  90 */       i = Statics.mix(i, Statics.anyHash(name()));
/*  90 */       i = Statics.mix(i, Statics.anyHash(msg()));
/*  90 */       i = Statics.mix(i, repeat() ? 1231 : 1237);
/*  90 */       i = Statics.mix(i, generation());
/*  90 */       return Statics.finalizeHash(i, 4);
/*     */     }
/*     */     
/*     */     public String toString() {
/*  90 */       return scala.runtime.ScalaRunTime$.MODULE$._toString(this);
/*     */     }
/*     */     
/*     */     public boolean equals(Object x$1) {
/*     */       // Byte code:
/*     */       //   0: aload_0
/*     */       //   1: aload_1
/*     */       //   2: if_acmpeq -> 119
/*     */       //   5: aload_1
/*     */       //   6: astore_2
/*     */       //   7: aload_2
/*     */       //   8: instanceof akka/actor/FSM$Timer
/*     */       //   11: ifeq -> 19
/*     */       //   14: iconst_1
/*     */       //   15: istore_3
/*     */       //   16: goto -> 21
/*     */       //   19: iconst_0
/*     */       //   20: istore_3
/*     */       //   21: iload_3
/*     */       //   22: ifeq -> 123
/*     */       //   25: aload_1
/*     */       //   26: checkcast akka/actor/FSM$Timer
/*     */       //   29: astore #4
/*     */       //   31: aload_0
/*     */       //   32: invokevirtual name : ()Ljava/lang/String;
/*     */       //   35: aload #4
/*     */       //   37: invokevirtual name : ()Ljava/lang/String;
/*     */       //   40: astore #5
/*     */       //   42: dup
/*     */       //   43: ifnonnull -> 55
/*     */       //   46: pop
/*     */       //   47: aload #5
/*     */       //   49: ifnull -> 63
/*     */       //   52: goto -> 115
/*     */       //   55: aload #5
/*     */       //   57: invokevirtual equals : (Ljava/lang/Object;)Z
/*     */       //   60: ifeq -> 115
/*     */       //   63: aload_0
/*     */       //   64: invokevirtual msg : ()Ljava/lang/Object;
/*     */       //   67: aload #4
/*     */       //   69: invokevirtual msg : ()Ljava/lang/Object;
/*     */       //   72: invokestatic equals : (Ljava/lang/Object;Ljava/lang/Object;)Z
/*     */       //   75: ifeq -> 115
/*     */       //   78: aload_0
/*     */       //   79: invokevirtual repeat : ()Z
/*     */       //   82: aload #4
/*     */       //   84: invokevirtual repeat : ()Z
/*     */       //   87: if_icmpne -> 115
/*     */       //   90: aload_0
/*     */       //   91: invokevirtual generation : ()I
/*     */       //   94: aload #4
/*     */       //   96: invokevirtual generation : ()I
/*     */       //   99: if_icmpne -> 115
/*     */       //   102: aload #4
/*     */       //   104: aload_0
/*     */       //   105: invokevirtual canEqual : (Ljava/lang/Object;)Z
/*     */       //   108: ifeq -> 115
/*     */       //   111: iconst_1
/*     */       //   112: goto -> 116
/*     */       //   115: iconst_0
/*     */       //   116: ifeq -> 123
/*     */       //   119: iconst_1
/*     */       //   120: goto -> 124
/*     */       //   123: iconst_0
/*     */       //   124: ireturn
/*     */       // Line number table:
/*     */       //   Java source line number -> byte code offset
/*     */       //   #90	-> 0
/*     */       //   #63	-> 14
/*     */       //   #90	-> 21
/*     */       // Local variable table:
/*     */       //   start	length	slot	name	descriptor
/*     */       //   0	125	0	this	Lakka/actor/FSM$Timer;
/*     */       //   0	125	1	x$1	Ljava/lang/Object;
/*     */     }
/*     */     
/*     */     public Timer(String name, Object msg, boolean repeat, int generation, ActorContext context) {
/*  90 */       Product.class.$init$(this);
/*  93 */       this.scheduler = context.system().scheduler();
/*  94 */       this.executionContext = context.dispatcher();
/*     */     }
/*     */     
/*     */     private Option<Cancellable> ref() {
/*     */       return this.ref;
/*     */     }
/*     */     
/*     */     private void ref_$eq(Option<Cancellable> x$1) {
/*     */       this.ref = x$1;
/*     */     }
/*     */     
/*     */     private Scheduler scheduler() {
/*     */       return this.scheduler;
/*     */     }
/*     */     
/*     */     private ExecutionContextExecutor executionContext() {
/*  94 */       return this.executionContext;
/*     */     }
/*     */     
/*     */     public void schedule(ActorRef actor, FiniteDuration timeout) {
/*  98 */       FiniteDuration x$3 = timeout, x$4 = timeout;
/*  98 */       ActorRef x$5 = actor;
/*  98 */       Timer x$6 = this;
/*  98 */       ExecutionContextExecutor x$7 = executionContext();
/*  98 */       ActorRef x$8 = scheduler().schedule$default$6(x$3, x$4, x$5, x$6);
/*  99 */       FiniteDuration x$9 = timeout;
/*  99 */       ActorRef x$10 = actor;
/*  99 */       Timer x$11 = this;
/*  99 */       ExecutionContextExecutor x$12 = executionContext();
/*  99 */       ActorRef x$13 = scheduler().scheduleOnce$default$5(x$9, x$10, x$11);
/*  99 */       ref_$eq((Option<Cancellable>)new Some(repeat() ? scheduler().schedule(x$3, x$4, x$5, x$6, (ExecutionContext)x$7, x$8) : scheduler().scheduleOnce(x$9, x$10, x$11, (ExecutionContext)x$12, x$13)));
/*     */     }
/*     */     
/*     */     public void cancel() {
/* 102 */       if (ref().isDefined()) {
/* 103 */         ((Cancellable)ref().get()).cancel();
/* 104 */         ref_$eq((Option<Cancellable>)scala.None$.MODULE$);
/*     */       } 
/*     */     }
/*     */   }
/*     */   
/*     */   public static class Timer$ implements Serializable {
/*     */     public static final Timer$ MODULE$;
/*     */     
/*     */     public final String toString() {
/*     */       return "Timer";
/*     */     }
/*     */     
/*     */     public FSM.Timer apply(String name, Object msg, boolean repeat, int generation, ActorContext context) {
/*     */       return new FSM.Timer(name, msg, repeat, generation, context);
/*     */     }
/*     */     
/*     */     public Option<Tuple4<String, Object, Object, Object>> unapply(FSM.Timer x$0) {
/*     */       return (x$0 == null) ? (Option<Tuple4<String, Object, Object, Object>>)scala.None$.MODULE$ : (Option<Tuple4<String, Object, Object, Object>>)new Some(new Tuple4(x$0.name(), x$0.msg(), BoxesRunTime.boxToBoolean(x$0.repeat()), BoxesRunTime.boxToInteger(x$0.generation())));
/*     */     }
/*     */     
/*     */     private Object readResolve() {
/*     */       return MODULE$;
/*     */     }
/*     */     
/*     */     public Timer$() {
/*     */       MODULE$ = this;
/*     */     }
/*     */   }
/*     */   
/*     */   public static class $minus$greater$ {
/*     */     public static final $minus$greater$ MODULE$;
/*     */     
/*     */     public $minus$greater$() {
/* 112 */       MODULE$ = this;
/*     */     }
/*     */     
/*     */     public <S> Some<Tuple2<S, S>> unapply(Tuple2 in) {
/* 113 */       return new Some(in);
/*     */     }
/*     */   }
/*     */   
/*     */   public static class LogEntry<S, D> implements Product, Serializable {
/*     */     private final S stateName;
/*     */     
/*     */     private final D stateData;
/*     */     
/*     */     private final Object event;
/*     */     
/*     */     public S stateName() {
/* 119 */       return this.stateName;
/*     */     }
/*     */     
/*     */     public D stateData() {
/* 119 */       return this.stateData;
/*     */     }
/*     */     
/*     */     public Object event() {
/* 119 */       return this.event;
/*     */     }
/*     */     
/*     */     public <S, D> LogEntry<S, D> copy(Object stateName, Object stateData, Object event) {
/* 119 */       return new LogEntry((S)stateName, (D)stateData, event);
/*     */     }
/*     */     
/*     */     public <S, D> S copy$default$1() {
/* 119 */       return stateName();
/*     */     }
/*     */     
/*     */     public <S, D> D copy$default$2() {
/* 119 */       return stateData();
/*     */     }
/*     */     
/*     */     public <S, D> Object copy$default$3() {
/* 119 */       return event();
/*     */     }
/*     */     
/*     */     public String productPrefix() {
/* 119 */       return "LogEntry";
/*     */     }
/*     */     
/*     */     public int productArity() {
/* 119 */       return 3;
/*     */     }
/*     */     
/*     */     public Object productElement(int x$1) {
/* 119 */       int i = x$1;
/* 119 */       switch (i) {
/*     */         default:
/* 119 */           throw new IndexOutOfBoundsException(BoxesRunTime.boxToInteger(x$1).toString());
/*     */         case 2:
/*     */         
/*     */         case 1:
/*     */         
/*     */         case 0:
/*     */           break;
/*     */       } 
/* 119 */       return stateName();
/*     */     }
/*     */     
/*     */     public Iterator<Object> productIterator() {
/* 119 */       return scala.runtime.ScalaRunTime$.MODULE$.typedProductIterator(this);
/*     */     }
/*     */     
/*     */     public boolean canEqual(Object x$1) {
/* 119 */       return x$1 instanceof LogEntry;
/*     */     }
/*     */     
/*     */     public int hashCode() {
/* 119 */       return scala.runtime.ScalaRunTime$.MODULE$._hashCode(this);
/*     */     }
/*     */     
/*     */     public String toString() {
/* 119 */       return scala.runtime.ScalaRunTime$.MODULE$._toString(this);
/*     */     }
/*     */     
/*     */     public boolean equals(Object x$1) {
/* 119 */       if (this != x$1) {
/*     */         boolean bool;
/* 119 */         Object object = x$1;
/* 119 */         if (object instanceof LogEntry) {
/*     */           bool = true;
/*     */         } else {
/*     */           bool = false;
/*     */         } 
/* 119 */         if (bool) {
/* 119 */           LogEntry logEntry = (LogEntry)x$1;
/* 119 */           if ((BoxesRunTime.equals(stateName(), logEntry.stateName()) && BoxesRunTime.equals(stateData(), logEntry.stateData()) && BoxesRunTime.equals(event(), logEntry.event()) && logEntry.canEqual(this)));
/*     */         } 
/* 119 */         return false;
/*     */       } 
/*     */     }
/*     */     
/*     */     public LogEntry(Object stateName, Object stateData, Object event) {
/* 119 */       Product.class.$init$(this);
/*     */     }
/*     */   }
/*     */   
/*     */   public static class LogEntry$ implements Serializable {
/*     */     public static final LogEntry$ MODULE$;
/*     */     
/*     */     public final String toString() {
/* 119 */       return "LogEntry";
/*     */     }
/*     */     
/*     */     public <S, D> FSM.LogEntry<S, D> apply(Object stateName, Object stateData, Object event) {
/* 119 */       return new FSM.LogEntry<S, D>((S)stateName, (D)stateData, event);
/*     */     }
/*     */     
/*     */     public <S, D> Option<Tuple3<S, D, Object>> unapply(FSM.LogEntry x$0) {
/* 119 */       return (x$0 == null) ? (Option<Tuple3<S, D, Object>>)scala.None$.MODULE$ : (Option<Tuple3<S, D, Object>>)new Some(new Tuple3(x$0.stateName(), x$0.stateData(), x$0.event()));
/*     */     }
/*     */     
/*     */     private Object readResolve() {
/* 119 */       return MODULE$;
/*     */     }
/*     */     
/*     */     public LogEntry$() {
/* 119 */       MODULE$ = this;
/*     */     }
/*     */   }
/*     */   
/*     */   public static class State<S, D> implements Product, Serializable {
/*     */     private final S stateName;
/*     */     
/*     */     private final D stateData;
/*     */     
/*     */     private final Option<FiniteDuration> timeout;
/*     */     
/*     */     private final Option<FSM.Reason> stopReason;
/*     */     
/*     */     private final List<Object> replies;
/*     */     
/*     */     public S stateName() {
/* 126 */       return this.stateName;
/*     */     }
/*     */     
/*     */     public D stateData() {
/* 126 */       return this.stateData;
/*     */     }
/*     */     
/*     */     public Option<FiniteDuration> timeout() {
/* 126 */       return this.timeout;
/*     */     }
/*     */     
/*     */     public Option<FSM.Reason> stopReason() {
/* 126 */       return this.stopReason;
/*     */     }
/*     */     
/*     */     public List<Object> replies() {
/* 126 */       return this.replies;
/*     */     }
/*     */     
/*     */     public <S, D> State<S, D> copy(Object stateName, Object stateData, Option<FiniteDuration> timeout, Option<FSM.Reason> stopReason, List<Object> replies) {
/* 126 */       return new State((S)stateName, (D)stateData, timeout, stopReason, replies);
/*     */     }
/*     */     
/*     */     public <S, D> S copy$default$1() {
/* 126 */       return stateName();
/*     */     }
/*     */     
/*     */     public <S, D> D copy$default$2() {
/* 126 */       return stateData();
/*     */     }
/*     */     
/*     */     public <S, D> Option<FiniteDuration> copy$default$3() {
/* 126 */       return timeout();
/*     */     }
/*     */     
/*     */     public <S, D> Option<FSM.Reason> copy$default$4() {
/* 126 */       return stopReason();
/*     */     }
/*     */     
/*     */     public <S, D> List<Object> copy$default$5() {
/* 126 */       return replies();
/*     */     }
/*     */     
/*     */     public String productPrefix() {
/* 126 */       return "State";
/*     */     }
/*     */     
/*     */     public int productArity() {
/* 126 */       return 5;
/*     */     }
/*     */     
/*     */     public Object productElement(int x$1) {
/* 126 */       int i = x$1;
/* 126 */       switch (i) {
/*     */         default:
/* 126 */           throw new IndexOutOfBoundsException(BoxesRunTime.boxToInteger(x$1).toString());
/*     */         case 4:
/*     */         
/*     */         case 3:
/*     */         
/*     */         case 2:
/*     */         
/*     */         case 1:
/*     */         
/*     */         case 0:
/*     */           break;
/*     */       } 
/* 126 */       return stateName();
/*     */     }
/*     */     
/*     */     public Iterator<Object> productIterator() {
/* 126 */       return scala.runtime.ScalaRunTime$.MODULE$.typedProductIterator(this);
/*     */     }
/*     */     
/*     */     public boolean canEqual(Object x$1) {
/* 126 */       return x$1 instanceof State;
/*     */     }
/*     */     
/*     */     public int hashCode() {
/* 126 */       return scala.runtime.ScalaRunTime$.MODULE$._hashCode(this);
/*     */     }
/*     */     
/*     */     public String toString() {
/* 126 */       return scala.runtime.ScalaRunTime$.MODULE$._toString(this);
/*     */     }
/*     */     
/*     */     public boolean equals(Object x$1) {
/*     */       // Byte code:
/*     */       //   0: aload_0
/*     */       //   1: aload_1
/*     */       //   2: if_acmpeq -> 174
/*     */       //   5: aload_1
/*     */       //   6: astore_2
/*     */       //   7: aload_2
/*     */       //   8: instanceof akka/actor/FSM$State
/*     */       //   11: ifeq -> 19
/*     */       //   14: iconst_1
/*     */       //   15: istore_3
/*     */       //   16: goto -> 21
/*     */       //   19: iconst_0
/*     */       //   20: istore_3
/*     */       //   21: iload_3
/*     */       //   22: ifeq -> 178
/*     */       //   25: aload_1
/*     */       //   26: checkcast akka/actor/FSM$State
/*     */       //   29: astore #4
/*     */       //   31: aload_0
/*     */       //   32: invokevirtual stateName : ()Ljava/lang/Object;
/*     */       //   35: aload #4
/*     */       //   37: invokevirtual stateName : ()Ljava/lang/Object;
/*     */       //   40: invokestatic equals : (Ljava/lang/Object;Ljava/lang/Object;)Z
/*     */       //   43: ifeq -> 170
/*     */       //   46: aload_0
/*     */       //   47: invokevirtual stateData : ()Ljava/lang/Object;
/*     */       //   50: aload #4
/*     */       //   52: invokevirtual stateData : ()Ljava/lang/Object;
/*     */       //   55: invokestatic equals : (Ljava/lang/Object;Ljava/lang/Object;)Z
/*     */       //   58: ifeq -> 170
/*     */       //   61: aload_0
/*     */       //   62: invokevirtual timeout : ()Lscala/Option;
/*     */       //   65: aload #4
/*     */       //   67: invokevirtual timeout : ()Lscala/Option;
/*     */       //   70: astore #5
/*     */       //   72: dup
/*     */       //   73: ifnonnull -> 85
/*     */       //   76: pop
/*     */       //   77: aload #5
/*     */       //   79: ifnull -> 93
/*     */       //   82: goto -> 170
/*     */       //   85: aload #5
/*     */       //   87: invokevirtual equals : (Ljava/lang/Object;)Z
/*     */       //   90: ifeq -> 170
/*     */       //   93: aload_0
/*     */       //   94: invokevirtual stopReason : ()Lscala/Option;
/*     */       //   97: aload #4
/*     */       //   99: invokevirtual stopReason : ()Lscala/Option;
/*     */       //   102: astore #6
/*     */       //   104: dup
/*     */       //   105: ifnonnull -> 117
/*     */       //   108: pop
/*     */       //   109: aload #6
/*     */       //   111: ifnull -> 125
/*     */       //   114: goto -> 170
/*     */       //   117: aload #6
/*     */       //   119: invokevirtual equals : (Ljava/lang/Object;)Z
/*     */       //   122: ifeq -> 170
/*     */       //   125: aload_0
/*     */       //   126: invokevirtual replies : ()Lscala/collection/immutable/List;
/*     */       //   129: aload #4
/*     */       //   131: invokevirtual replies : ()Lscala/collection/immutable/List;
/*     */       //   134: astore #7
/*     */       //   136: dup
/*     */       //   137: ifnonnull -> 149
/*     */       //   140: pop
/*     */       //   141: aload #7
/*     */       //   143: ifnull -> 157
/*     */       //   146: goto -> 170
/*     */       //   149: aload #7
/*     */       //   151: invokevirtual equals : (Ljava/lang/Object;)Z
/*     */       //   154: ifeq -> 170
/*     */       //   157: aload #4
/*     */       //   159: aload_0
/*     */       //   160: invokevirtual canEqual : (Ljava/lang/Object;)Z
/*     */       //   163: ifeq -> 170
/*     */       //   166: iconst_1
/*     */       //   167: goto -> 171
/*     */       //   170: iconst_0
/*     */       //   171: ifeq -> 178
/*     */       //   174: iconst_1
/*     */       //   175: goto -> 179
/*     */       //   178: iconst_0
/*     */       //   179: ireturn
/*     */       // Line number table:
/*     */       //   Java source line number -> byte code offset
/*     */       //   #126	-> 0
/*     */       //   #63	-> 14
/*     */       //   #126	-> 21
/*     */       // Local variable table:
/*     */       //   start	length	slot	name	descriptor
/*     */       //   0	180	0	this	Lakka/actor/FSM$State;
/*     */       //   0	180	1	x$1	Ljava/lang/Object;
/*     */     }
/*     */     
/*     */     public State(Object stateName, Object stateData, Option<FiniteDuration> timeout, Option<FSM.Reason> stopReason, List<Object> replies) {
/* 126 */       Product.class.$init$(this);
/*     */     }
/*     */     
/*     */     public State<S, D> forMax(Duration timeout) {
/*     */       State<Object, Object> state;
/* 135 */       Duration duration = timeout;
/* 136 */       if (duration instanceof FiniteDuration) {
/* 136 */         FiniteDuration finiteDuration = (FiniteDuration)duration;
/* 136 */         Some x$14 = new Some(finiteDuration);
/* 136 */         Object x$15 = copy$default$1(), x$16 = copy$default$2();
/* 136 */         Option<FSM.Reason> x$17 = copy$default$4();
/* 136 */         List x$18 = copy$default$5();
/* 136 */         state = copy(x$15, x$16, (Option<FiniteDuration>)x$14, x$17, x$18);
/*     */       } else {
/* 137 */         scala.None$ x$19 = scala.None$.MODULE$;
/* 137 */         Object x$20 = copy$default$1(), x$21 = copy$default$2();
/* 137 */         Option<FSM.Reason> x$22 = copy$default$4();
/* 137 */         List x$23 = copy$default$5();
/* 137 */         state = copy(x$20, x$21, (Option<FiniteDuration>)x$19, x$22, x$23);
/*     */       } 
/*     */       return (State)state;
/*     */     }
/*     */     
/*     */     public State<S, D> replying(Object replyValue) {
/* 146 */       Object object1 = replyValue;
/* 146 */       List x$24 = replies().$colon$colon(object1);
/* 146 */       Object x$25 = copy$default$1(), x$26 = copy$default$2();
/* 146 */       Option<FiniteDuration> x$27 = copy$default$3();
/* 146 */       Option<FSM.Reason> x$28 = copy$default$4();
/* 146 */       return copy((S)x$25, (D)x$26, x$27, x$28, x$24);
/*     */     }
/*     */     
/*     */     public State<S, D> using(Object nextStateDate) {
/* 154 */       Object x$29 = nextStateDate, x$30 = copy$default$1();
/* 154 */       Option<FiniteDuration> x$31 = copy$default$3();
/* 154 */       Option<FSM.Reason> x$32 = copy$default$4();
/* 154 */       List x$33 = copy$default$5();
/* 154 */       return copy((S)x$30, (D)x$29, x$31, x$32, x$33);
/*     */     }
/*     */     
/*     */     public State<S, D> withStopReason(FSM.Reason reason) {
/* 161 */       Some x$34 = new Some(reason);
/* 161 */       Object x$35 = copy$default$1(), x$36 = copy$default$2();
/* 161 */       Option<FiniteDuration> x$37 = copy$default$3();
/* 161 */       List x$38 = copy$default$5();
/* 161 */       return copy((S)x$35, (D)x$36, x$37, (Option<FSM.Reason>)x$34, x$38);
/*     */     }
/*     */   }
/*     */   
/*     */   public static class State$ implements Serializable {
/*     */     public static final State$ MODULE$;
/*     */     
/*     */     public final String toString() {
/*     */       return "State";
/*     */     }
/*     */     
/*     */     public <S, D> FSM.State<S, D> apply(Object stateName, Object stateData, Option<FiniteDuration> timeout, Option<FSM.Reason> stopReason, List replies) {
/*     */       return new FSM.State<S, D>((S)stateName, (D)stateData, timeout, stopReason, replies);
/*     */     }
/*     */     
/*     */     public <S, D> Option<Tuple5<S, D, Option<FiniteDuration>, Option<FSM.Reason>, List<Object>>> unapply(FSM.State x$0) {
/*     */       return (x$0 == null) ? (Option<Tuple5<S, D, Option<FiniteDuration>, Option<FSM.Reason>, List<Object>>>)scala.None$.MODULE$ : (Option<Tuple5<S, D, Option<FiniteDuration>, Option<FSM.Reason>, List<Object>>>)new Some(new Tuple5(x$0.stateName(), x$0.stateData(), x$0.timeout(), x$0.stopReason(), x$0.replies()));
/*     */     }
/*     */     
/*     */     public <S, D> Option<FiniteDuration> $lessinit$greater$default$3() {
/*     */       return (Option<FiniteDuration>)scala.None$.MODULE$;
/*     */     }
/*     */     
/*     */     public <S, D> Option<FSM.Reason> $lessinit$greater$default$4() {
/*     */       return (Option<FSM.Reason>)scala.None$.MODULE$;
/*     */     }
/*     */     
/*     */     public <S, D> List<Object> $lessinit$greater$default$5() {
/*     */       return (List<Object>)scala.collection.immutable.Nil$.MODULE$;
/*     */     }
/*     */     
/*     */     public <S, D> Option<FiniteDuration> apply$default$3() {
/*     */       return (Option<FiniteDuration>)scala.None$.MODULE$;
/*     */     }
/*     */     
/*     */     public <S, D> Option<FSM.Reason> apply$default$4() {
/*     */       return (Option<FSM.Reason>)scala.None$.MODULE$;
/*     */     }
/*     */     
/*     */     public <S, D> List<Object> apply$default$5() {
/*     */       return (List<Object>)scala.collection.immutable.Nil$.MODULE$;
/*     */     }
/*     */     
/*     */     private Object readResolve() {
/*     */       return MODULE$;
/*     */     }
/*     */     
/*     */     public State$() {
/*     */       MODULE$ = this;
/*     */     }
/*     */   }
/*     */   
/*     */   public static class Event$ implements Serializable {
/*     */     public static final Event$ MODULE$;
/*     */     
/*     */     public final String toString() {
/* 168 */       return "Event";
/*     */     }
/*     */     
/*     */     public <D> FSM.Event<D> apply(Object event, Object stateData) {
/* 168 */       return new FSM.Event<D>(event, (D)stateData);
/*     */     }
/*     */     
/*     */     public <D> Option<Tuple2<Object, D>> unapply(FSM.Event x$0) {
/* 168 */       return (x$0 == null) ? (Option<Tuple2<Object, D>>)scala.None$.MODULE$ : (Option<Tuple2<Object, D>>)new Some(new Tuple2(x$0.event(), x$0.stateData()));
/*     */     }
/*     */     
/*     */     private Object readResolve() {
/* 168 */       return MODULE$;
/*     */     }
/*     */     
/*     */     public Event$() {
/* 168 */       MODULE$ = this;
/*     */     }
/*     */   }
/*     */   
/*     */   public static class Event<D> implements NoSerializationVerificationNeeded, Product, Serializable {
/*     */     private final Object event;
/*     */     
/*     */     private final D stateData;
/*     */     
/*     */     public Object event() {
/* 168 */       return this.event;
/*     */     }
/*     */     
/*     */     public D stateData() {
/* 168 */       return this.stateData;
/*     */     }
/*     */     
/*     */     public <D> Event<D> copy(Object event, Object stateData) {
/* 168 */       return new Event(event, (D)stateData);
/*     */     }
/*     */     
/*     */     public <D> Object copy$default$1() {
/* 168 */       return event();
/*     */     }
/*     */     
/*     */     public <D> D copy$default$2() {
/* 168 */       return stateData();
/*     */     }
/*     */     
/*     */     public String productPrefix() {
/* 168 */       return "Event";
/*     */     }
/*     */     
/*     */     public int productArity() {
/* 168 */       return 2;
/*     */     }
/*     */     
/*     */     public Object productElement(int x$1) {
/* 168 */       int i = x$1;
/* 168 */       switch (i) {
/*     */         default:
/* 168 */           throw new IndexOutOfBoundsException(BoxesRunTime.boxToInteger(x$1).toString());
/*     */         case 1:
/*     */         
/*     */         case 0:
/*     */           break;
/*     */       } 
/* 168 */       return event();
/*     */     }
/*     */     
/*     */     public Iterator<Object> productIterator() {
/* 168 */       return scala.runtime.ScalaRunTime$.MODULE$.typedProductIterator(this);
/*     */     }
/*     */     
/*     */     public boolean canEqual(Object x$1) {
/* 168 */       return x$1 instanceof Event;
/*     */     }
/*     */     
/*     */     public int hashCode() {
/* 168 */       return scala.runtime.ScalaRunTime$.MODULE$._hashCode(this);
/*     */     }
/*     */     
/*     */     public String toString() {
/* 168 */       return scala.runtime.ScalaRunTime$.MODULE$._toString(this);
/*     */     }
/*     */     
/*     */     public boolean equals(Object x$1) {
/* 168 */       if (this != x$1) {
/*     */         boolean bool;
/* 168 */         Object object = x$1;
/* 168 */         if (object instanceof Event) {
/*     */           bool = true;
/*     */         } else {
/*     */           bool = false;
/*     */         } 
/* 168 */         if (bool) {
/* 168 */           Event event = (Event)x$1;
/* 168 */           if ((BoxesRunTime.equals(event(), event.event()) && BoxesRunTime.equals(stateData(), event.stateData()) && event.canEqual(this)));
/*     */         } 
/* 168 */         return false;
/*     */       } 
/*     */     }
/*     */     
/*     */     public Event(Object event, Object stateData) {
/* 168 */       Product.class.$init$(this);
/*     */     }
/*     */   }
/*     */   
/*     */   public static class StopEvent$ implements Serializable {
/*     */     public static final StopEvent$ MODULE$;
/*     */     
/*     */     public final String toString() {
/* 174 */       return "StopEvent";
/*     */     }
/*     */     
/*     */     public <S, D> FSM.StopEvent<S, D> apply(FSM.Reason reason, Object currentState, Object stateData) {
/* 174 */       return new FSM.StopEvent<S, D>(reason, (S)currentState, (D)stateData);
/*     */     }
/*     */     
/*     */     public <S, D> Option<Tuple3<FSM.Reason, S, D>> unapply(FSM.StopEvent x$0) {
/* 174 */       return (x$0 == null) ? (Option<Tuple3<FSM.Reason, S, D>>)scala.None$.MODULE$ : (Option<Tuple3<FSM.Reason, S, D>>)new Some(new Tuple3(x$0.reason(), x$0.currentState(), x$0.stateData()));
/*     */     }
/*     */     
/*     */     private Object readResolve() {
/* 174 */       return MODULE$;
/*     */     }
/*     */     
/*     */     public StopEvent$() {
/* 174 */       MODULE$ = this;
/*     */     }
/*     */   }
/*     */   
/*     */   public static class StopEvent<S, D> implements NoSerializationVerificationNeeded, Product, Serializable {
/*     */     private final FSM.Reason reason;
/*     */     
/*     */     private final S currentState;
/*     */     
/*     */     private final D stateData;
/*     */     
/*     */     public FSM.Reason reason() {
/* 174 */       return this.reason;
/*     */     }
/*     */     
/*     */     public S currentState() {
/* 174 */       return this.currentState;
/*     */     }
/*     */     
/*     */     public D stateData() {
/* 174 */       return this.stateData;
/*     */     }
/*     */     
/*     */     public <S, D> StopEvent<S, D> copy(FSM.Reason reason, Object currentState, Object stateData) {
/* 174 */       return new StopEvent(reason, (S)currentState, (D)stateData);
/*     */     }
/*     */     
/*     */     public <S, D> FSM.Reason copy$default$1() {
/* 174 */       return reason();
/*     */     }
/*     */     
/*     */     public <S, D> S copy$default$2() {
/* 174 */       return currentState();
/*     */     }
/*     */     
/*     */     public <S, D> D copy$default$3() {
/* 174 */       return stateData();
/*     */     }
/*     */     
/*     */     public String productPrefix() {
/* 174 */       return "StopEvent";
/*     */     }
/*     */     
/*     */     public int productArity() {
/* 174 */       return 3;
/*     */     }
/*     */     
/*     */     public Object productElement(int x$1) {
/* 174 */       int i = x$1;
/* 174 */       switch (i) {
/*     */         default:
/* 174 */           throw new IndexOutOfBoundsException(BoxesRunTime.boxToInteger(x$1).toString());
/*     */         case 2:
/*     */         
/*     */         case 1:
/*     */         
/*     */         case 0:
/*     */           break;
/*     */       } 
/* 174 */       return reason();
/*     */     }
/*     */     
/*     */     public Iterator<Object> productIterator() {
/* 174 */       return scala.runtime.ScalaRunTime$.MODULE$.typedProductIterator(this);
/*     */     }
/*     */     
/*     */     public boolean canEqual(Object x$1) {
/* 174 */       return x$1 instanceof StopEvent;
/*     */     }
/*     */     
/*     */     public int hashCode() {
/* 174 */       return scala.runtime.ScalaRunTime$.MODULE$._hashCode(this);
/*     */     }
/*     */     
/*     */     public String toString() {
/* 174 */       return scala.runtime.ScalaRunTime$.MODULE$._toString(this);
/*     */     }
/*     */     
/*     */     public boolean equals(Object x$1) {
/*     */       // Byte code:
/*     */       //   0: aload_0
/*     */       //   1: aload_1
/*     */       //   2: if_acmpeq -> 110
/*     */       //   5: aload_1
/*     */       //   6: astore_2
/*     */       //   7: aload_2
/*     */       //   8: instanceof akka/actor/FSM$StopEvent
/*     */       //   11: ifeq -> 19
/*     */       //   14: iconst_1
/*     */       //   15: istore_3
/*     */       //   16: goto -> 21
/*     */       //   19: iconst_0
/*     */       //   20: istore_3
/*     */       //   21: iload_3
/*     */       //   22: ifeq -> 114
/*     */       //   25: aload_1
/*     */       //   26: checkcast akka/actor/FSM$StopEvent
/*     */       //   29: astore #4
/*     */       //   31: aload_0
/*     */       //   32: invokevirtual reason : ()Lakka/actor/FSM$Reason;
/*     */       //   35: aload #4
/*     */       //   37: invokevirtual reason : ()Lakka/actor/FSM$Reason;
/*     */       //   40: astore #5
/*     */       //   42: dup
/*     */       //   43: ifnonnull -> 55
/*     */       //   46: pop
/*     */       //   47: aload #5
/*     */       //   49: ifnull -> 63
/*     */       //   52: goto -> 106
/*     */       //   55: aload #5
/*     */       //   57: invokevirtual equals : (Ljava/lang/Object;)Z
/*     */       //   60: ifeq -> 106
/*     */       //   63: aload_0
/*     */       //   64: invokevirtual currentState : ()Ljava/lang/Object;
/*     */       //   67: aload #4
/*     */       //   69: invokevirtual currentState : ()Ljava/lang/Object;
/*     */       //   72: invokestatic equals : (Ljava/lang/Object;Ljava/lang/Object;)Z
/*     */       //   75: ifeq -> 106
/*     */       //   78: aload_0
/*     */       //   79: invokevirtual stateData : ()Ljava/lang/Object;
/*     */       //   82: aload #4
/*     */       //   84: invokevirtual stateData : ()Ljava/lang/Object;
/*     */       //   87: invokestatic equals : (Ljava/lang/Object;Ljava/lang/Object;)Z
/*     */       //   90: ifeq -> 106
/*     */       //   93: aload #4
/*     */       //   95: aload_0
/*     */       //   96: invokevirtual canEqual : (Ljava/lang/Object;)Z
/*     */       //   99: ifeq -> 106
/*     */       //   102: iconst_1
/*     */       //   103: goto -> 107
/*     */       //   106: iconst_0
/*     */       //   107: ifeq -> 114
/*     */       //   110: iconst_1
/*     */       //   111: goto -> 115
/*     */       //   114: iconst_0
/*     */       //   115: ireturn
/*     */       // Line number table:
/*     */       //   Java source line number -> byte code offset
/*     */       //   #174	-> 0
/*     */       //   #63	-> 14
/*     */       //   #174	-> 21
/*     */       // Local variable table:
/*     */       //   start	length	slot	name	descriptor
/*     */       //   0	116	0	this	Lakka/actor/FSM$StopEvent;
/*     */       //   0	116	1	x$1	Ljava/lang/Object;
/*     */     }
/*     */     
/*     */     public StopEvent(FSM.Reason reason, Object currentState, Object stateData) {
/* 174 */       Product.class.$init$(this);
/*     */     }
/*     */   }
/*     */   
/*     */   public class TransformHelper {
/*     */     private final PartialFunction<FSM.Event<D>, FSM.State<S, D>> func;
/*     */     
/*     */     public TransformHelper(FSM $outer, PartialFunction<FSM.Event<D>, FSM.State<S, D>> func) {}
/*     */     
/*     */     public PartialFunction<FSM.Event<D>, FSM.State<S, D>> using(PartialFunction andThen) {
/* 351 */       return this.func.andThen((Function1)andThen.orElse((PartialFunction)new FSM$TransformHelper$$anonfun$using$1(this)));
/*     */     }
/*     */     
/*     */     public class FSM$TransformHelper$$anonfun$using$1 extends AbstractPartialFunction<FSM.State<S, D>, FSM.State<S, D>> implements Serializable {
/*     */       public static final long serialVersionUID = 0L;
/*     */       
/*     */       public final <A1 extends FSM.State<S, D>, B1> B1 applyOrElse(FSM.State x1, Function1 default) {
/*     */         FSM.State state;
/* 351 */         return (B1)(state = x1);
/*     */       }
/*     */       
/*     */       public final boolean isDefinedAt(FSM.State x1) {
/* 351 */         FSM.State state = x1;
/* 351 */         return true;
/*     */       }
/*     */       
/*     */       public FSM$TransformHelper$$anonfun$using$1(FSM.TransformHelper $outer) {}
/*     */     }
/*     */   }
/*     */   
/*     */   public class FSM$$anon$1 implements PartialFunction<Tuple2<S, S>, BoxedUnit> {
/*     */     private final Function2 transitionHandler$1;
/*     */     
/*     */     public <A1 extends Tuple2<S, S>, B1> PartialFunction<A1, B1> orElse(PartialFunction that) {
/* 440 */       return PartialFunction.class.orElse(this, that);
/*     */     }
/*     */     
/*     */     public <C> PartialFunction<Tuple2<S, S>, C> andThen(Function1 k) {
/* 440 */       return PartialFunction.class.andThen(this, k);
/*     */     }
/*     */     
/*     */     public Function1<Tuple2<S, S>, Option<BoxedUnit>> lift() {
/* 440 */       return PartialFunction.class.lift(this);
/*     */     }
/*     */     
/*     */     public <A1 extends Tuple2<S, S>, B1> B1 applyOrElse(Object x, Function1 default) {
/* 440 */       return (B1)PartialFunction.class.applyOrElse(this, x, default);
/*     */     }
/*     */     
/*     */     public <U> Function1<Tuple2<S, S>, Object> runWith(Function1 action) {
/* 440 */       return PartialFunction.class.runWith(this, action);
/*     */     }
/*     */     
/*     */     public boolean apply$mcZD$sp(double v1) {
/* 440 */       return Function1.class.apply$mcZD$sp((Function1)this, v1);
/*     */     }
/*     */     
/*     */     public double apply$mcDD$sp(double v1) {
/* 440 */       return Function1.class.apply$mcDD$sp((Function1)this, v1);
/*     */     }
/*     */     
/*     */     public float apply$mcFD$sp(double v1) {
/* 440 */       return Function1.class.apply$mcFD$sp((Function1)this, v1);
/*     */     }
/*     */     
/*     */     public int apply$mcID$sp(double v1) {
/* 440 */       return Function1.class.apply$mcID$sp((Function1)this, v1);
/*     */     }
/*     */     
/*     */     public long apply$mcJD$sp(double v1) {
/* 440 */       return Function1.class.apply$mcJD$sp((Function1)this, v1);
/*     */     }
/*     */     
/*     */     public void apply$mcVD$sp(double v1) {
/* 440 */       Function1.class.apply$mcVD$sp((Function1)this, v1);
/*     */     }
/*     */     
/*     */     public boolean apply$mcZF$sp(float v1) {
/* 440 */       return Function1.class.apply$mcZF$sp((Function1)this, v1);
/*     */     }
/*     */     
/*     */     public double apply$mcDF$sp(float v1) {
/* 440 */       return Function1.class.apply$mcDF$sp((Function1)this, v1);
/*     */     }
/*     */     
/*     */     public float apply$mcFF$sp(float v1) {
/* 440 */       return Function1.class.apply$mcFF$sp((Function1)this, v1);
/*     */     }
/*     */     
/*     */     public int apply$mcIF$sp(float v1) {
/* 440 */       return Function1.class.apply$mcIF$sp((Function1)this, v1);
/*     */     }
/*     */     
/*     */     public long apply$mcJF$sp(float v1) {
/* 440 */       return Function1.class.apply$mcJF$sp((Function1)this, v1);
/*     */     }
/*     */     
/*     */     public void apply$mcVF$sp(float v1) {
/* 440 */       Function1.class.apply$mcVF$sp((Function1)this, v1);
/*     */     }
/*     */     
/*     */     public boolean apply$mcZI$sp(int v1) {
/* 440 */       return Function1.class.apply$mcZI$sp((Function1)this, v1);
/*     */     }
/*     */     
/*     */     public double apply$mcDI$sp(int v1) {
/* 440 */       return Function1.class.apply$mcDI$sp((Function1)this, v1);
/*     */     }
/*     */     
/*     */     public float apply$mcFI$sp(int v1) {
/* 440 */       return Function1.class.apply$mcFI$sp((Function1)this, v1);
/*     */     }
/*     */     
/*     */     public int apply$mcII$sp(int v1) {
/* 440 */       return Function1.class.apply$mcII$sp((Function1)this, v1);
/*     */     }
/*     */     
/*     */     public long apply$mcJI$sp(int v1) {
/* 440 */       return Function1.class.apply$mcJI$sp((Function1)this, v1);
/*     */     }
/*     */     
/*     */     public void apply$mcVI$sp(int v1) {
/* 440 */       Function1.class.apply$mcVI$sp((Function1)this, v1);
/*     */     }
/*     */     
/*     */     public boolean apply$mcZJ$sp(long v1) {
/* 440 */       return Function1.class.apply$mcZJ$sp((Function1)this, v1);
/*     */     }
/*     */     
/*     */     public double apply$mcDJ$sp(long v1) {
/* 440 */       return Function1.class.apply$mcDJ$sp((Function1)this, v1);
/*     */     }
/*     */     
/*     */     public float apply$mcFJ$sp(long v1) {
/* 440 */       return Function1.class.apply$mcFJ$sp((Function1)this, v1);
/*     */     }
/*     */     
/*     */     public int apply$mcIJ$sp(long v1) {
/* 440 */       return Function1.class.apply$mcIJ$sp((Function1)this, v1);
/*     */     }
/*     */     
/*     */     public long apply$mcJJ$sp(long v1) {
/* 440 */       return Function1.class.apply$mcJJ$sp((Function1)this, v1);
/*     */     }
/*     */     
/*     */     public void apply$mcVJ$sp(long v1) {
/* 440 */       Function1.class.apply$mcVJ$sp((Function1)this, v1);
/*     */     }
/*     */     
/*     */     public <A> Function1<A, BoxedUnit> compose(Function1 g) {
/* 440 */       return Function1.class.compose((Function1)this, g);
/*     */     }
/*     */     
/*     */     public <A> Function1<A, Object> compose$mcZD$sp(Function1 g) {
/* 440 */       return Function1.class.compose$mcZD$sp((Function1)this, g);
/*     */     }
/*     */     
/*     */     public <A> Function1<A, Object> compose$mcDD$sp(Function1 g) {
/* 440 */       return Function1.class.compose$mcDD$sp((Function1)this, g);
/*     */     }
/*     */     
/*     */     public <A> Function1<A, Object> compose$mcFD$sp(Function1 g) {
/* 440 */       return Function1.class.compose$mcFD$sp((Function1)this, g);
/*     */     }
/*     */     
/*     */     public <A> Function1<A, Object> compose$mcID$sp(Function1 g) {
/* 440 */       return Function1.class.compose$mcID$sp((Function1)this, g);
/*     */     }
/*     */     
/*     */     public <A> Function1<A, Object> compose$mcJD$sp(Function1 g) {
/* 440 */       return Function1.class.compose$mcJD$sp((Function1)this, g);
/*     */     }
/*     */     
/*     */     public <A> Function1<A, BoxedUnit> compose$mcVD$sp(Function1 g) {
/* 440 */       return Function1.class.compose$mcVD$sp((Function1)this, g);
/*     */     }
/*     */     
/*     */     public <A> Function1<A, Object> compose$mcZF$sp(Function1 g) {
/* 440 */       return Function1.class.compose$mcZF$sp((Function1)this, g);
/*     */     }
/*     */     
/*     */     public <A> Function1<A, Object> compose$mcDF$sp(Function1 g) {
/* 440 */       return Function1.class.compose$mcDF$sp((Function1)this, g);
/*     */     }
/*     */     
/*     */     public <A> Function1<A, Object> compose$mcFF$sp(Function1 g) {
/* 440 */       return Function1.class.compose$mcFF$sp((Function1)this, g);
/*     */     }
/*     */     
/*     */     public <A> Function1<A, Object> compose$mcIF$sp(Function1 g) {
/* 440 */       return Function1.class.compose$mcIF$sp((Function1)this, g);
/*     */     }
/*     */     
/*     */     public <A> Function1<A, Object> compose$mcJF$sp(Function1 g) {
/* 440 */       return Function1.class.compose$mcJF$sp((Function1)this, g);
/*     */     }
/*     */     
/*     */     public <A> Function1<A, BoxedUnit> compose$mcVF$sp(Function1 g) {
/* 440 */       return Function1.class.compose$mcVF$sp((Function1)this, g);
/*     */     }
/*     */     
/*     */     public <A> Function1<A, Object> compose$mcZI$sp(Function1 g) {
/* 440 */       return Function1.class.compose$mcZI$sp((Function1)this, g);
/*     */     }
/*     */     
/*     */     public <A> Function1<A, Object> compose$mcDI$sp(Function1 g) {
/* 440 */       return Function1.class.compose$mcDI$sp((Function1)this, g);
/*     */     }
/*     */     
/*     */     public <A> Function1<A, Object> compose$mcFI$sp(Function1 g) {
/* 440 */       return Function1.class.compose$mcFI$sp((Function1)this, g);
/*     */     }
/*     */     
/*     */     public <A> Function1<A, Object> compose$mcII$sp(Function1 g) {
/* 440 */       return Function1.class.compose$mcII$sp((Function1)this, g);
/*     */     }
/*     */     
/*     */     public <A> Function1<A, Object> compose$mcJI$sp(Function1 g) {
/* 440 */       return Function1.class.compose$mcJI$sp((Function1)this, g);
/*     */     }
/*     */     
/*     */     public <A> Function1<A, BoxedUnit> compose$mcVI$sp(Function1 g) {
/* 440 */       return Function1.class.compose$mcVI$sp((Function1)this, g);
/*     */     }
/*     */     
/*     */     public <A> Function1<A, Object> compose$mcZJ$sp(Function1 g) {
/* 440 */       return Function1.class.compose$mcZJ$sp((Function1)this, g);
/*     */     }
/*     */     
/*     */     public <A> Function1<A, Object> compose$mcDJ$sp(Function1 g) {
/* 440 */       return Function1.class.compose$mcDJ$sp((Function1)this, g);
/*     */     }
/*     */     
/*     */     public <A> Function1<A, Object> compose$mcFJ$sp(Function1 g) {
/* 440 */       return Function1.class.compose$mcFJ$sp((Function1)this, g);
/*     */     }
/*     */     
/*     */     public <A> Function1<A, Object> compose$mcIJ$sp(Function1 g) {
/* 440 */       return Function1.class.compose$mcIJ$sp((Function1)this, g);
/*     */     }
/*     */     
/*     */     public <A> Function1<A, Object> compose$mcJJ$sp(Function1 g) {
/* 440 */       return Function1.class.compose$mcJJ$sp((Function1)this, g);
/*     */     }
/*     */     
/*     */     public <A> Function1<A, BoxedUnit> compose$mcVJ$sp(Function1 g) {
/* 440 */       return Function1.class.compose$mcVJ$sp((Function1)this, g);
/*     */     }
/*     */     
/*     */     public <A> Function1<Object, A> andThen$mcZD$sp(Function1 g) {
/* 440 */       return Function1.class.andThen$mcZD$sp((Function1)this, g);
/*     */     }
/*     */     
/*     */     public <A> Function1<Object, A> andThen$mcDD$sp(Function1 g) {
/* 440 */       return Function1.class.andThen$mcDD$sp((Function1)this, g);
/*     */     }
/*     */     
/*     */     public <A> Function1<Object, A> andThen$mcFD$sp(Function1 g) {
/* 440 */       return Function1.class.andThen$mcFD$sp((Function1)this, g);
/*     */     }
/*     */     
/*     */     public <A> Function1<Object, A> andThen$mcID$sp(Function1 g) {
/* 440 */       return Function1.class.andThen$mcID$sp((Function1)this, g);
/*     */     }
/*     */     
/*     */     public <A> Function1<Object, A> andThen$mcJD$sp(Function1 g) {
/* 440 */       return Function1.class.andThen$mcJD$sp((Function1)this, g);
/*     */     }
/*     */     
/*     */     public <A> Function1<Object, A> andThen$mcVD$sp(Function1 g) {
/* 440 */       return Function1.class.andThen$mcVD$sp((Function1)this, g);
/*     */     }
/*     */     
/*     */     public <A> Function1<Object, A> andThen$mcZF$sp(Function1 g) {
/* 440 */       return Function1.class.andThen$mcZF$sp((Function1)this, g);
/*     */     }
/*     */     
/*     */     public <A> Function1<Object, A> andThen$mcDF$sp(Function1 g) {
/* 440 */       return Function1.class.andThen$mcDF$sp((Function1)this, g);
/*     */     }
/*     */     
/*     */     public <A> Function1<Object, A> andThen$mcFF$sp(Function1 g) {
/* 440 */       return Function1.class.andThen$mcFF$sp((Function1)this, g);
/*     */     }
/*     */     
/*     */     public <A> Function1<Object, A> andThen$mcIF$sp(Function1 g) {
/* 440 */       return Function1.class.andThen$mcIF$sp((Function1)this, g);
/*     */     }
/*     */     
/*     */     public <A> Function1<Object, A> andThen$mcJF$sp(Function1 g) {
/* 440 */       return Function1.class.andThen$mcJF$sp((Function1)this, g);
/*     */     }
/*     */     
/*     */     public <A> Function1<Object, A> andThen$mcVF$sp(Function1 g) {
/* 440 */       return Function1.class.andThen$mcVF$sp((Function1)this, g);
/*     */     }
/*     */     
/*     */     public <A> Function1<Object, A> andThen$mcZI$sp(Function1 g) {
/* 440 */       return Function1.class.andThen$mcZI$sp((Function1)this, g);
/*     */     }
/*     */     
/*     */     public <A> Function1<Object, A> andThen$mcDI$sp(Function1 g) {
/* 440 */       return Function1.class.andThen$mcDI$sp((Function1)this, g);
/*     */     }
/*     */     
/*     */     public <A> Function1<Object, A> andThen$mcFI$sp(Function1 g) {
/* 440 */       return Function1.class.andThen$mcFI$sp((Function1)this, g);
/*     */     }
/*     */     
/*     */     public <A> Function1<Object, A> andThen$mcII$sp(Function1 g) {
/* 440 */       return Function1.class.andThen$mcII$sp((Function1)this, g);
/*     */     }
/*     */     
/*     */     public <A> Function1<Object, A> andThen$mcJI$sp(Function1 g) {
/* 440 */       return Function1.class.andThen$mcJI$sp((Function1)this, g);
/*     */     }
/*     */     
/*     */     public <A> Function1<Object, A> andThen$mcVI$sp(Function1 g) {
/* 440 */       return Function1.class.andThen$mcVI$sp((Function1)this, g);
/*     */     }
/*     */     
/*     */     public <A> Function1<Object, A> andThen$mcZJ$sp(Function1 g) {
/* 440 */       return Function1.class.andThen$mcZJ$sp((Function1)this, g);
/*     */     }
/*     */     
/*     */     public <A> Function1<Object, A> andThen$mcDJ$sp(Function1 g) {
/* 440 */       return Function1.class.andThen$mcDJ$sp((Function1)this, g);
/*     */     }
/*     */     
/*     */     public <A> Function1<Object, A> andThen$mcFJ$sp(Function1 g) {
/* 440 */       return Function1.class.andThen$mcFJ$sp((Function1)this, g);
/*     */     }
/*     */     
/*     */     public <A> Function1<Object, A> andThen$mcIJ$sp(Function1 g) {
/* 440 */       return Function1.class.andThen$mcIJ$sp((Function1)this, g);
/*     */     }
/*     */     
/*     */     public <A> Function1<Object, A> andThen$mcJJ$sp(Function1 g) {
/* 440 */       return Function1.class.andThen$mcJJ$sp((Function1)this, g);
/*     */     }
/*     */     
/*     */     public <A> Function1<Object, A> andThen$mcVJ$sp(Function1 g) {
/* 440 */       return Function1.class.andThen$mcVJ$sp((Function1)this, g);
/*     */     }
/*     */     
/*     */     public String toString() {
/* 440 */       return Function1.class.toString((Function1)this);
/*     */     }
/*     */     
/*     */     public FSM$$anon$1(FSM $outer, Function2 transitionHandler$1) {
/* 440 */       Function1.class.$init$((Function1)this);
/* 440 */       PartialFunction.class.$init$(this);
/*     */     }
/*     */     
/*     */     public boolean isDefinedAt(Tuple2 in) {
/* 441 */       return true;
/*     */     }
/*     */     
/*     */     public void apply(Tuple2 in) {
/* 442 */       this.transitionHandler$1.apply(in._1(), in._2());
/*     */     }
/*     */   }
/*     */   
/*     */   public class FSM$$anonfun$register$1 extends AbstractFunction0<Option<FiniteDuration>> implements Serializable {
/*     */     public static final long serialVersionUID = 0L;
/*     */     
/*     */     private final Object name$1;
/*     */     
/*     */     public final Option<FiniteDuration> apply() {
/* 519 */       return (Option<FiniteDuration>)this.$outer.akka$actor$FSM$$stateTimeouts().apply(this.name$1);
/*     */     }
/*     */     
/*     */     public FSM$$anonfun$register$1(FSM $outer, Object name$1) {}
/*     */   }
/*     */   
/*     */   public class $anonfun$1 extends AbstractPartialFunction<Event<D>, State<S, D>> implements Serializable {
/*     */     public static final long serialVersionUID = 0L;
/*     */     
/*     */     public final <A1 extends FSM.Event<D>, B1> B1 applyOrElse(FSM.Event x2, Function1 default) {
/*     */       Object object;
/* 529 */       FSM.Event event = x2;
/* 529 */       if (event != null) {
/* 530 */         Object value = event.event();
/* 531 */         this.$outer.log().warning((new StringBuilder()).append("unhandled event ").append(value).append(" in state ").append(this.$outer.stateName()).toString());
/* 532 */         object = this.$outer.stay();
/*     */       } else {
/*     */         object = default.apply(x2);
/*     */       } 
/*     */       return (B1)object;
/*     */     }
/*     */     
/*     */     public final boolean isDefinedAt(FSM.Event x2) {
/*     */       boolean bool;
/*     */       FSM.Event event = x2;
/*     */       if (event != null) {
/*     */         bool = true;
/*     */       } else {
/*     */         bool = false;
/*     */       } 
/*     */       return bool;
/*     */     }
/*     */     
/*     */     public $anonfun$1(FSM $outer) {}
/*     */   }
/*     */   
/*     */   public class FSM$$anonfun$handleTransition$1 extends AbstractFunction1<PartialFunction<Tuple2<S, S>, BoxedUnit>, BoxedUnit> implements Serializable {
/*     */     public static final long serialVersionUID = 0L;
/*     */     
/*     */     private final Tuple2 tuple$1;
/*     */     
/*     */     public final void apply(PartialFunction te) {
/* 547 */       if (te.isDefinedAt(this.tuple$1))
/* 547 */         te.apply(this.tuple$1); 
/*     */     }
/*     */     
/*     */     public FSM$$anonfun$handleTransition$1(FSM $outer, Tuple2 tuple$1) {}
/*     */   }
/*     */   
/*     */   public class FSM$$anonfun$receive$1 extends AbstractPartialFunction.mcVL.sp<Object> implements Serializable {
/*     */     public static final long serialVersionUID = 0L;
/*     */     
/*     */     public final <A1, B1> B1 applyOrElse(Object x3, Function1 default) {
/*     */       BoxedUnit boxedUnit;
/* 555 */       Object object = x3;
/* 556 */       if (object instanceof FSM.TimeoutMarker) {
/* 556 */         FSM.TimeoutMarker timeoutMarker = (FSM.TimeoutMarker)object;
/* 556 */         long gen = timeoutMarker.generation();
/* 558 */         FSM$class.akka$actor$FSM$$processMsg(this.$outer, this.$outer.StateTimeout(), "state timeout");
/* 558 */         boxedUnit = (this.$outer.akka$actor$FSM$$generation() == gen) ? BoxedUnit.UNIT : BoxedUnit.UNIT;
/* 560 */       } else if (object instanceof FSM.Timer) {
/* 560 */         FSM.Timer timer = (FSM.Timer)object;
/* 560 */         String name = timer.name();
/* 560 */         Object msg = timer.msg();
/* 560 */         boolean repeat = timer.repeat();
/* 560 */         int gen = timer.generation();
/* 562 */         if (this.$outer.akka$actor$FSM$$timeoutFuture().isDefined()) {
/* 563 */           ((Cancellable)this.$outer.akka$actor$FSM$$timeoutFuture().get()).cancel();
/* 564 */           this.$outer.akka$actor$FSM$$timeoutFuture_$eq((Option<Cancellable>)scala.None$.MODULE$);
/*     */         } 
/* 566 */         this.$outer.akka$actor$FSM$$generation_$eq(this.$outer.akka$actor$FSM$$generation() + 1L);
/* 567 */         repeat ? BoxedUnit.UNIT : 
/* 568 */           this.$outer.akka$actor$FSM$$timers().$minus$eq(name);
/* 570 */         FSM$class.akka$actor$FSM$$processMsg(this.$outer, msg, timer);
/* 570 */         boxedUnit = (this.$outer.akka$actor$FSM$$timers().contains(name) && ((FSM.Timer)this.$outer.akka$actor$FSM$$timers().apply(name)).generation() == gen) ? BoxedUnit.UNIT : BoxedUnit.UNIT;
/* 572 */       } else if (object instanceof FSM.SubscribeTransitionCallBack) {
/* 572 */         FSM.SubscribeTransitionCallBack subscribeTransitionCallBack = (FSM.SubscribeTransitionCallBack)object;
/* 572 */         ActorRef actorRef = subscribeTransitionCallBack.actorRef();
/* 574 */         this.$outer.listeners().add(actorRef);
/* 576 */         package$.MODULE$.actorRef2Scala(actorRef).$bang(new FSM.CurrentState(this.$outer.self(), this.$outer.akka$actor$FSM$$currentState().stateName()), this.$outer.self());
/* 576 */         boxedUnit = BoxedUnit.UNIT;
/* 577 */       } else if (object instanceof Listen) {
/* 577 */         Listen listen = (Listen)object;
/* 577 */         ActorRef actorRef = listen.listener();
/* 579 */         this.$outer.listeners().add(actorRef);
/* 581 */         package$.MODULE$.actorRef2Scala(actorRef).$bang(new FSM.CurrentState(this.$outer.self(), this.$outer.akka$actor$FSM$$currentState().stateName()), this.$outer.self());
/* 581 */         boxedUnit = BoxedUnit.UNIT;
/* 582 */       } else if (object instanceof FSM.UnsubscribeTransitionCallBack) {
/* 582 */         FSM.UnsubscribeTransitionCallBack unsubscribeTransitionCallBack = (FSM.UnsubscribeTransitionCallBack)object;
/* 582 */         ActorRef actorRef = unsubscribeTransitionCallBack.actorRef();
/* 583 */         this.$outer.listeners().remove(actorRef);
/* 583 */         boxedUnit = BoxedUnit.UNIT;
/* 584 */       } else if (object instanceof Deafen) {
/* 584 */         Deafen deafen = (Deafen)object;
/* 584 */         ActorRef actorRef = deafen.listener();
/* 585 */         this.$outer.listeners().remove(actorRef);
/* 585 */         boxedUnit = BoxedUnit.UNIT;
/*     */       } else {
/* 587 */         if (this.$outer.akka$actor$FSM$$timeoutFuture().isDefined()) {
/* 588 */           ((Cancellable)this.$outer.akka$actor$FSM$$timeoutFuture().get()).cancel();
/* 589 */           this.$outer.akka$actor$FSM$$timeoutFuture_$eq((Option<Cancellable>)scala.None$.MODULE$);
/*     */         } 
/* 591 */         this.$outer.akka$actor$FSM$$generation_$eq(this.$outer.akka$actor$FSM$$generation() + 1L);
/* 592 */         FSM$class.akka$actor$FSM$$processMsg(this.$outer, object, this.$outer.sender());
/* 592 */         boxedUnit = BoxedUnit.UNIT;
/*     */       } 
/*     */       return (B1)boxedUnit;
/*     */     }
/*     */     
/*     */     public final boolean isDefinedAt(Object x3) {
/*     */       boolean bool;
/*     */       Object object = x3;
/*     */       if (object instanceof FSM.TimeoutMarker) {
/*     */         bool = true;
/*     */       } else if (object instanceof FSM.Timer) {
/*     */         bool = true;
/*     */       } else if (object instanceof FSM.SubscribeTransitionCallBack) {
/*     */         bool = true;
/*     */       } else if (object instanceof Listen) {
/*     */         bool = true;
/*     */       } else if (object instanceof FSM.UnsubscribeTransitionCallBack) {
/*     */         bool = true;
/*     */       } else if (object instanceof Deafen) {
/*     */         bool = true;
/*     */       } else {
/*     */         bool = true;
/*     */       } 
/*     */       return bool;
/*     */     }
/*     */     
/*     */     public FSM$$anonfun$receive$1(FSM $outer) {}
/*     */   }
/*     */   
/*     */   public class FSM$$anonfun$applyState$1 extends AbstractFunction1<Object, BoxedUnit> implements Serializable {
/*     */     public static final long serialVersionUID = 0L;
/*     */     
/*     */     public final void apply(Object r) {
/* 616 */       package$.MODULE$.actorRef2Scala(this.$outer.sender()).$bang(r, this.$outer.self());
/*     */     }
/*     */     
/*     */     public FSM$$anonfun$applyState$1(FSM $outer) {}
/*     */   }
/*     */   
/*     */   public class FSM$$anonfun$makeTransition$1 extends AbstractFunction1<Object, BoxedUnit> implements Serializable {
/*     */     public static final long serialVersionUID = 0L;
/*     */     
/*     */     public final void apply(Object r) {
/* 626 */       package$.MODULE$.actorRef2Scala(this.$outer.sender()).$bang(r, this.$outer.self());
/*     */     }
/*     */     
/*     */     public FSM$$anonfun$makeTransition$1(FSM $outer) {}
/*     */   }
/*     */   
/*     */   public class FSM$$anonfun$terminate$1 extends AbstractFunction1<Timer, BoxedUnit> implements Serializable {
/*     */     public static final long serialVersionUID = 0L;
/*     */     
/*     */     public final void apply(FSM.Timer timer) {
/* 666 */       timer.cancel();
/*     */     }
/*     */     
/*     */     public FSM$$anonfun$terminate$1(FSM $outer) {}
/*     */   }
/*     */   
/*     */   public static interface Reason {}
/*     */ }


/* Location:              D:\#source-code\TheFlightSims\TFSLibrary\World2Xplane\World2XPlane.jar!\akka\actor\FSM.class
 * Java compiler version: 6 (50.0)
 * JD-Core Version:       1.1.3
 */