/*     */ package akka.actor;
/*     */ 
/*     */ import akka.japi.Option;
/*     */ import akka.serialization.Serialization;
/*     */ import akka.serialization.Serializer;
/*     */ import akka.util.Timeout;
/*     */ import java.io.ObjectStreamException;
/*     */ import java.lang.reflect.InvocationHandler;
/*     */ import java.lang.reflect.InvocationTargetException;
/*     */ import java.lang.reflect.Method;
/*     */ import java.util.concurrent.atomic.AtomicReference;
/*     */ import scala.Function0;
/*     */ import scala.Function1;
/*     */ import scala.MatchError;
/*     */ import scala.Option;
/*     */ import scala.PartialFunction;
/*     */ import scala.Product;
/*     */ import scala.Serializable;
/*     */ import scala.Some;
/*     */ import scala.Tuple2;
/*     */ import scala.Tuple3;
/*     */ import scala.Tuple4;
/*     */ import scala.collection.Iterator;
/*     */ import scala.collection.Seq;
/*     */ import scala.collection.immutable.Seq;
/*     */ import scala.concurrent.ExecutionContextExecutor;
/*     */ import scala.concurrent.Future;
/*     */ import scala.concurrent.duration.FiniteDuration;
/*     */ import scala.reflect.ScalaSignature;
/*     */ import scala.runtime.AbstractFunction0;
/*     */ import scala.runtime.AbstractFunction1;
/*     */ import scala.runtime.AbstractFunction2;
/*     */ import scala.runtime.AbstractFunction4;
/*     */ import scala.runtime.AbstractPartialFunction;
/*     */ import scala.runtime.BoxedUnit;
/*     */ import scala.runtime.BoxesRunTime;
/*     */ import scala.util.Failure;
/*     */ import scala.util.Success;
/*     */ import scala.util.Try;
/*     */ 
/*     */ @ScalaSignature(bytes = "\006\001\031er!B\001\003\021\0039\021A\003+za\026$\027i\031;pe*\0211\001B\001\006C\016$xN\035\006\002\013\005!\021m[6b\007\001\001\"\001C\005\016\003\t1QA\003\002\t\002-\021!\002V=qK\022\f5\r^8s'\021IAB\005\r\021\0055\001R\"\001\b\013\003=\tQa]2bY\006L!!\005\b\003\r\005s\027PU3g!\rA1#F\005\003)\t\0211\"\022=uK:\034\030n\0348JIB\021\001BF\005\003/\t\0211\003V=qK\022\f5\r^8s\013b$XM\\:j_:\004\"\001C\r\n\005i\021!aE#yi\026t7/[8o\023\022\004&o\034<jI\026\024\b\"\002\017\n\t\003i\022A\002\037j]&$h\bF\001\b\021\025y\022\002\"\021!\003\r9W\r\036\013\003+\005BQA\t\020A\002\r\naa]=ti\026l\007C\001\005%\023\t)#AA\006BGR|'oU=ti\026l\007\"B\024\n\t\003A\023A\0027p_.,\b\017F\001*\035\tA\001\001C\003,\023\021\005A&A\bde\026\fG/Z#yi\026t7/[8o)\t)R\006C\003#U\001\007a\006\005\002\t_%\021\001G\001\002\024\013b$XM\0343fI\006\033Go\034:TsN$X-\034\005\006e%!\taM\001\006CB\004H.\037\013\003i]\002\"\001C\033\n\005Y\022!!\005+za\026$\027i\031;pe\032\0137\r^8ss\")\001(\ra\001s\00591m\0348uKb$\bC\001\005;\023\tY$A\001\007BGR|'oQ8oi\026DH\017C\003 \023\021\005Q\b\006\0025}!)\001\b\020a\001s\031!\001)\003!B\005)iU\r\0365pI\016\013G\016\\\n\0051\021U\t\005\002\016\007&\021AI\004\002\b!J|G-^2u!\tia)\003\002H\035\ta1+\032:jC2L'0\0312mK\"A\021j\020BK\002\023\005!*\001\004nKRDw\016Z\013\002\027B\021AjU\007\002\033*\021ajT\001\be\0264G.Z2u\025\t\001\026+\001\003mC:<'\"\001*\002\t)\fg/Y\005\003)6\023a!T3uQ>$\007\002\003,@\005#\005\013\021B&\002\0175,G\017[8eA!A\001l\020BK\002\023\005\021,\001\006qCJ\fW.\032;feN,\022A\027\t\004\033mc\021B\001/\017\005\025\t%O]1z\021!qvH!E!\002\023Q\026a\0039be\006lW\r^3sg\002BQ\001H \005\002\001$2!Y2e!\t\021w(D\001\n\021\025Iu\f1\001L\021\025Av\f1\001[\021\0251w\b\"\001h\003!I7o\0248f/\006LX#\0015\021\0055I\027B\0016\017\005\035\021un\0347fC:DQ\001\\ \005\002\035\fQB]3ukJt7OR;ukJ,\007\"\0028@\t\0039\027A\004:fiV\024hn\035&PaRLwN\034\005\006a~\"\taZ\001\016e\026$XO\0358t\037B$\030n\0348\t\013IzD\021\001:\025\0051\031\b\"\002;r\001\004a\021\001C5ogR\fgnY3\t\013Y|D\021B<\002\031]\024\030\016^3SKBd\027mY3\025\0031AC!^=\002\030A\031QB\037?\n\005mt!A\002;ie><8\017\005\002~}2\001AAB@\001\005\004\t\tAA\001U#\021\t\031!!\003\021\0075\t)!C\002\002\b9\021qAT8uQ&tw\r\005\003\002\f\005EabA\007\002\016%\031\021q\002\b\002\017A\f7m[1hK&!\0211CA\013\005%!\006N]8xC\ndWMC\002\002\0209\031#!!\007\021\t\005m\021\021E\007\003\003;Q1!a\bR\003\tIw.\003\003\002$\005u!!F(cU\026\034Go\025;sK\006lW\t_2faRLwN\034\005\n\003Oy\024\021!C\001\003S\tAaY8qsR)\021-a\013\002.!A\021*!\n\021\002\003\0071\n\003\005Y\003K\001\n\0211\001[\021%\t\tdPI\001\n\003\t\031$\001\bd_BLH\005Z3gCVdG\017J\031\026\005\005U\"fA&\0028-\022\021\021\b\t\005\003w\t)%\004\002\002>)!\021qHA!\003%)hn\0315fG.,GMC\002\002D9\t!\"\0318o_R\fG/[8o\023\021\t9%!\020\003#Ut7\r[3dW\026$g+\031:jC:\034W\rC\005\002L}\n\n\021\"\001\002N\005q1m\0349zI\021,g-Y;mi\022\022TCAA(U\rQ\026q\007\005\n\003'z\024\021!C!\003+\nQ\002\035:pIV\034G\017\025:fM&DXCAA,!\021\tI&a\027\016\003=K1!!\030P\005\031\031FO]5oO\"I\021\021M \002\002\023\005\0211M\001\raJ|G-^2u\003JLG/_\013\003\003K\0022!DA4\023\r\tIG\004\002\004\023:$\b\"CA7\005\005I\021AA8\0039\001(o\0343vGR,E.Z7f]R$B!!\035\002xA\031Q\"a\035\n\007\005UdBA\002B]fD!\"!\037\002l\005\005\t\031AA3\003\rAH%\r\005\n\003{z\024\021!C!\003\nq\002\035:pIV\034G/\023;fe\006$xN]\013\003\003\003\003b!a!\002\n\006ETBAAC\025\r\t9ID\001\013G>dG.Z2uS>t\027\002BAF\003\013\023\001\"\023;fe\006$xN\035\005\n\003\037{\024\021!C\001\003#\013\001bY1o\013F,\030\r\034\013\004Q\006M\005BCA=\003\033\013\t\0211\001\002r!I\021qS \002\002\023\005\023\021T\001\tQ\006\034\bnQ8eKR\021\021Q\r\005\n\003;{\024\021!C!\003?\013\001\002^8TiJLgn\032\013\003\003/B\021\"a)@\003\003%\t%!*\002\r\025\fX/\0317t)\rA\027q\025\005\013\003s\n\t+!AA\002\005Et!CAV\023\005\005\t\022AAW\003)iU\r\0365pI\016\013G\016\034\t\004E\006=f\001\003!\n\003\003E\t!!-\024\013\005=\0261W#\021\017\005U\0261X&[C6\021\021q\027\006\004\003ss\021a\002:v]RLW.Z\005\005\003{\0139LA\tBEN$(/Y2u\rVt7\r^5p]JBq\001HAX\t\003\t\t\r\006\002\002.\"Q\021QTAX\003\003%)%a(\t\023I\ny+!A\005\002\006\035G#B1\002J\006-\007BB%\002F\002\0071\n\003\004Y\003\013\004\rA\027\005\013\003\037\fy+!A\005\002\006E\027aB;oCB\004H.\037\013\005\003'\fy\016E\003\016\003+\fI.C\002\002X:\021aa\0249uS>t\007#B\007\002\\.S\026bAAo\035\t1A+\0369mKJB\021\"!9\002N\006\005\t\031A1\002\007a$\003\007\003\006\002f\006=\026\021!C\005\003O\f1B]3bIJ+7o\0347wKR\021\021\021\036\t\005\0033\nY/C\002\002n>\023aa\0242kK\016$haBAy\023\001#\0211\037\002\025'\026\024\030.\0317ju\026$W*\032;i_\022\034\025\r\0347\024\013\005=HBQ#\t\027\005]\030q\036BK\002\023\005\021\021`\001\n_^tWM\035+za\026,\"!a?1\t\005u(Q\002\t\007\003\024)Aa\003\017\0075\021\t!C\002\003\0049\ta\001\025:fI\0264\027\002\002B\004\005\023\021Qa\0217bgNT1Aa\001\017!\ri(Q\002\003\r\005\037\021\t\"!A\001\002\013\005!Q\004\002\004?\022*\004b\003B\n\003_\024\t\022)A\005\005+\t!b\\<oKJ$\026\020]3!a\021\0219Ba\007\021\r\005}(Q\001B\r!\ri(1\004\003\r\005\037\021\t\"!A\001\002\013\005!QD\t\005\003\007\t\t\bC\006\003\"\005=(Q3A\005\002\t\r\022AC7fi\"|GMT1nKV\021!Q\005\t\005\003\0249#\003\003\002^\t%\001b\003B\026\003_\024\t\022)A\005\005K\t1\"\\3uQ>$g*Y7fA!Y!qFAx\005+\007I\021\001B\031\0039\001\030M]1nKR,'\017V=qKN,\"Aa\r\021\t5Y&Q\007\031\005\005o\021Y\004\005\004\002\000\n\025!\021\b\t\004{\nmB\001\004B\037\005\t\t\021!A\003\002\tu!aA0%m!Y!\021IAx\005#\005\013\021\002B\"\003=\001\030M]1nKR,'\017V=qKN\004\003\003B\007\\\005\013\002DAa\022\003LA1\021q B\003\005\023\0022! B&\t1\021iDa\020\002\002\003\005)\021\001B\017\021-\021y%a<\003\026\004%\tA!\025\002)M,'/[1mSj,G\rU1sC6,G/\032:t+\t\021\031\006\005\003\0167\nU\003#C\007\003X\005\025$1\fB;\023\r\021IF\004\002\007)V\004H.Z\0321\t\tu#\021\r\t\007\003\024)Aa\030\021\007u\024\t\007\002\007\003d\t\025\024\021!A\001\006\003\021iBA\002`I]B1Ba\032\002p\nE\t\025!\003\003j\005)2/\032:jC2L'0\0323QCJ\fW.\032;feN\004\003\003B\007\\\005W\002\022\"\004B,\003K\022iG!\0361\t\t=$1\017\t\007\003\024)A!\035\021\007u\024\031\b\002\007\003d\t\025\024\021!A\001\006\003\021i\002\005\003\0167\n]\004cA\007\003z%\031!1\020\b\003\t\tKH/\032\005\b9\005=H\021\001B@))\021\tIa!\003\016\n=%1\024\t\004E\006=\b\002CA|\005{\002\rA!\"1\t\t\035%1\022\t\007\003\024)A!#\021\007u\024Y\t\002\007\003\020\t\r\025\021!A\001\006\003\021i\002\003\005\003\"\tu\004\031\001B\023\021!\021yC! A\002\tE\005\003B\007\\\005'\003DA!&\003\032B1\021q B\003\005/\0032! BM\t1\021iDa$\002\002\003\005)\021\001B\017\021!\021yE! A\002\tu\005\003B\007\\\005?\003\022\"\004B,\003K\022\tK!\0361\t\t\r&q\025\t\007\003\024)A!*\021\007u\0249\013\002\007\003d\tm\025\021!A\001\006\003\021i\002C\004\002f\006=H\021B<)\r\t%&QVA\f!\021i!Pa,\021\007u\024\t\f\002\004\000\001\t\007\021\021\001\005\013\003O\ty/!A\005\002\tUFC\003BA\005o\023ILa/\003>\"Q\021q\037BZ!\003\005\rA!\"\t\025\t\005\"1\027I\001\002\004\021)\003\003\006\0030\tM\006\023!a\001\005#C!Ba\024\0034B\005\t\031\001BO\021)\t\t$a<\022\002\023\005!\021Y\013\003\005\007\004DA!2\003N*\"!qYA\034!\031\tIF!3\003L&\031!qA(\021\007u\024i\r\002\007\003\020\t}\026\021!A\001\006\003\021i\002\003\006\002L\005=\030\023!C\001\005#,\"Aa5+\t\t\025\022q\007\005\013\005/\fy/%A\005\002\te\027AD2paf$C-\0324bk2$HeM\013\003\0057TCAa\r\0028!Q!q\\Ax#\003%\tA!9\002\035\r|\007/\037\023eK\032\fW\017\034;%iU\021!1\035\026\005\005'\n9\004\003\006\002T\005=\030\021!C!\003+B!\"!\031\002p\006\005I\021AA2\021)\ti'a<\002\002\023\005!1\036\013\005\003c\022i\017\003\006\002z\t%\030\021!a\001\003KB!\"! \002p\006\005I\021IA@\021)\ty)a<\002\002\023\005!1\037\013\004Q\nU\bBCA=\005c\f\t\0211\001\002r!Q\021qSAx\003\003%\t%!'\t\025\005u\025q^A\001\n\003\ny\n\003\006\002$\006=\030\021!C!\005{$2\001\033B\000\021)\tIHa?\002\002\003\007\021\021O\004\013\007\007I\021\021!E\001\t\r\025\021\001F*fe&\fG.\033>fI6+G\017[8e\007\006dG\016E\002c\007\0171!\"!=\n\003\003E\t\001BB\005'\025\0319aa\003F!9\t)l!\004\004\022\t\0252\021DB\022\005\003KAaa\004\0028\n\t\022IY:ue\006\034GOR;oGRLwN\034\0331\t\rM1q\003\t\007\003\024)a!\006\021\007u\0349\002\002\007\003\020\r\035\021\021!A\001\006\003\021i\002\005\003\0167\016m\001\007BB\017\007C\001b!a@\003\006\r}\001cA?\004\"\021a!QHB\004\003\003\005\tQ!\001\003\036A!QbWB\023!%i!qKA3\007O\021)\b\r\003\004*\r5\002CBA\000\005\013\031Y\003E\002~\007[!ABa\031\004\b\005\005\t\021!B\001\005;Aq\001HB\004\t\003\031\t\004\006\002\004\006!Q\021QTB\004\003\003%)%a(\t\023I\0329!!A\005\002\016]BC\003BA\007s\031\031e!\022\004R!A\021q_B\033\001\004\031Y\004\r\003\004>\r\005\003CBA\000\005\013\031y\004E\002~\007\003\"ABa\004\004:\005\005\t\021!B\001\005;A\001B!\t\0046\001\007!Q\005\005\t\005_\031)\0041\001\004HA!QbWB%a\021\031Yea\024\021\r\005}(QAB'!\ri8q\n\003\r\005{\031)%!A\001\002\013\005!Q\004\005\t\005\037\032)\0041\001\004TA!QbWB+!%i!qKA3\007/\022)\b\r\003\004Z\ru\003CBA\000\005\013\031Y\006E\002~\007;\"ABa\031\004R\005\005\t\021!B\001\005;A!\"a4\004\b\005\005I\021QB1)\021\031\031g!!1\t\r\0254\021\017\t\006\033\005U7q\r\t\f\033\r%4QNA,\007g\032I(C\002\004l9\021a\001V;qY\026$\004CBA-\005\023\034y\007E\002~\007c\"ABa\004\004`\005\005\t\021!B\001\005;\001B!D.\004vA\"1q\017B\036!\031\tIF!3\003:A!QbWB>!%i!qKA3\007{\022)\b\r\003\004\000\t\005\004CBA-\005\023\024y\006\003\006\002b\016}\023\021!a\001\005\003C!\"!:\004\b\005\005I\021BAt\021%\0319)\003b\001\n\023\031I)A\007tK24'+\0324fe\026t7-Z\013\003\007\027\003R!!\027\004\0162I1aa$P\005-!\006N]3bI2{7-\0317\t\021\rM\025\002)A\005\007\027\013ab]3mMJ+g-\032:f]\016,\007\005C\005\004\030&\021\r\021\"\003\004\032\006q1-\036:sK:$8i\0348uKb$XCABN!\025\tIf!$:\021!\031y*\003Q\001\n\rm\025aD2veJ,g\016^\"p]R,\007\020\036\021\b\017\r\r\026\002##\004&\006aa*\0367m%\026\034\bo\0348tKB\031!ma*\007\017\r%\026\002##\004,\naa*\0367m%\026\034\bo\0348tKN)1q\025\007C\013\"9Ada*\005\002\r=FCABS\021)\t\031fa*\002\002\023\005\023Q\013\005\013\003C\0329+!A\005\002\005\r\004BCA7\007O\013\t\021\"\001\0048R!\021\021OB]\021)\tIh!.\002\002\003\007\021Q\r\005\013\003{\0329+!A\005B\005}\004BCAH\007O\013\t\021\"\001\004@R\031\001n!1\t\025\005e4QXA\001\002\004\t\t\b\003\006\002\030\016\035\026\021!C!\0033C!\"!(\004(\006\005I\021IAP\021)\t)oa*\002\002\023%\021q\035\025\007\007O\033Ym!5\021\0075\031i-C\002\004P:\021\001cU3sS\006dg+\032:tS>tW+\023#\037\003\005Aca!)\004L\016E\007bBBl\023\021\0051\021\\\001\005g\026dg-\006\003\004\\\016}WCABo!\ri8q\034\003\b\016U'\031ABq#\r\t\031\001\004\005\007q%!\ta!:\026\003eBqa!;\n\t\007\031Y/\001\006eSN\004\030\r^2iKJ,\"a!<\021\t\r=8Q_\007\003\007cT1aa=\017\003)\031wN\\2veJ,g\016^\005\005\007o\034\tP\001\rFq\026\034W\017^5p]\016{g\016^3yi\026CXmY;u_J4aAC\005\001\t\rmXCBB\t?!\031dE\003\004z2\031y\020E\002\t\t\003I1\001b\001\003\005\025\t5\r^8s\021-!9a!?\003\006\004%\t\001\"\003\002\021A\024x\016_=WCJ,\"\001b\003\021\r\0215A\021\004C\017\033\t!yA\003\003\005\022\021M\021AB1u_6L7M\003\003\004t\022U!b\001C\f#\006!Q\017^5m\023\021!Y\002b\004\003\037\005#x.\\5d%\0264WM]3oG\026\0042! C\020\t!!\tc!?C\002\r\005(!\001*\t\027\021\0252\021 B\001B\003%A1B\001\naJ|\0070\037,be\002B1\002\"\013\004z\n\005I\025!\003\005,\005q1M]3bi\026Len\035;b]\016,\007#B\007\005.\021E\022b\001C\030\035\tAAHY=oC6,g\bE\002~\tg!qa`B}\005\004!)$\005\003\002\004\021u\001b\003C\035\007s\024\t\021)A\005\tw\t!\"\0338uKJ4\027mY3t!\031!i\004b\021\005H5\021Aq\b\006\005\t\003\n))A\005j[6,H/\0312mK&!AQ\tC \005\r\031V-\035\031\005\t\023\"i\005\005\004\002\000\n\025A1\n\t\004{\0225C\001\004C(\to\t\t\021!A\003\002\tu!aA0%q!9Ad!?\005\002\021MC\003\003C+\t/\"I\006b\027\021\017\t\034I\020\"\b\0052!AAq\001C)\001\004!Y\001C\005\005*\021EC\0211\001\005,!AA\021\bC)\001\004!i\006\005\004\005>\021\rCq\f\031\005\tC\")\007\005\004\002\000\n\025A1\r\t\004{\022\025D\001\004C(\t7\n\t\021!A\003\002\tu\001B\003C5\007s\024\r\021\"\003\005l\005\021Q.Z\013\003\tcA\021\002b\034\004z\002\006I\001\"\r\002\0075,\007\005\003\005\005t\reH\021\tC;\003I\031X\017]3sm&\034xN]*ue\006$XmZ=\026\005\021]\004c\001\005\005z%\031A1\020\002\003%M+\b/\032:wSN|'o\025;sCR,w-\037\005\t\t\032I\020\"\021\005\002\006A\001O]3Ti\006\024H\017\006\002\005\004B\031Q\002\"\"\n\007\021\035eB\001\003V]&$\b\002\003CF\007s$\t\005\"!\002\021A|7\017^*u_BD\001\002b$\004z\022\005C\021S\001\013aJ,'+Z:uCJ$HC\002CB\t'#)\013\003\005\005\026\0225\005\031\001CL\003\031\021X-Y:p]B!A\021TA\t\035\021!Y*!\004\017\t\021uE1U\007\003\t?S1\001\")\007\003\031a$o\\8u}%\tq\002\003\005\005(\0225\005\031\001CU\003\035iWm]:bO\026\004R!DAk\003cB\001\002\",\004z\022\005CqV\001\fa>\034HOU3ti\006\024H\017\006\003\005\004\022E\006\002\003CK\tW\003\r\001b&\t\021\021U6\021 C\t\to\0131b^5uQ\016{g\016^3yiV!A\021\030C_)\021!Y\fb0\021\007u$i\fB\004\000\tg\023\rA!\b\t\023\021\005G1\027CA\002\021\r\027AC;oSR|emV8sWB)Q\002\"\f\005<\"AAqYB}\t\003!I-A\004sK\016,\027N^3\026\005\021-\007cB\007\005N\006ED1Q\005\004\t\037t!a\004)beRL\027\r\034$v]\016$\030n\0348\t\033\021M7\021`A\001\002\023%A\021\021Ck\0039\031X\017]3sIA\024Xm\025;beRLA\001b \005\002!iA\021\\B}\003\003\005I\021\002CA\t7\fab];qKJ$\003o\\:u'R|\007/\003\003\005\f\022\005\001\"\004Cp\007s\f\t\021!C\005\tC$)/A\ttkB,'\017\n9pgR\024Vm\035;beR$B\001b!\005d\"AAQ\023Co\001\004!9*\003\003\005.\022\005a!\003Cu\023A\005\031\023\001Cv\005)\031V\017]3sm&\034xN]\n\004\tOd\001\002\003C:\tO4\t\001b<\025\005\021]d!\003Cz\023A\005\031\023\001C{\005!\021VmY3jm\026\0248c\001Cy\031!AA\021 Cy\r\003!Y0A\005p]J+7-Z5wKR1A1\021C\tD\001\002b*\005x\002\007\021\021\017\005\t\013\003!9\0201\001\006\004\00511/\0328eKJ\0042\001CC\003\023\r)9A\001\002\t\003\016$xN\035*fM\032IQ1B\005\021\002G\005QQ\002\002\t!J,7\013^1siN\031Q\021\002\007\t\021\021}T\021\002D\001\t\0033\021\"b\005\n!\003\r\n!\"\006\003\021A{7\017^*u_B\0342!\"\005\r\021!!Y)\"\005\007\002\021\005e!CC\016\023A\005\031\023AC\017\005)\001&/\032*fgR\f'\017^\n\004\0133a\001\002\003CH\01331\t!\"\t\025\r\021\rU1EC\023\021!!)*b\bA\002\021]\005\002\003CT\013?\001\r\001\"+\007\023\025%\022\002%A\022\002\025-\"a\003)pgR\024Vm\035;beR\0342!b\n\r\021!!i+b\n\007\002\025=B\003\002CB\013cA\001\002\"&\006.\001\007Aq\023\004\b\013kI\001\001BC\034\005m!\026\020]3e\003\016$xN]%om>\034\027\r^5p]\"\013g\016\0327feN9Q1GAu\013s)\005c\001'\006<%\031QQH'\003#%sgo\\2bi&|g\016S1oI2,'\017C\006\006B\025M\"Q1A\005\002\025\r\023!C3yi\026t7/[8o+\005)\002BCC$\013g\021\t\021)A\005+\005QQ\r\037;f]NLwN\034\021)\t\025\025S1\n\t\004\033\0255\023bAC(\035\tIAO]1og&,g\016\036\005\f\013'*\031D!b\001\n\003))&\001\005bGR|'OV1s+\t)9\006\005\004\005\016\021eQ1\001\005\f\0137*\031D!A!\002\023)9&A\005bGR|'OV1sA!\"Q\021LC&\021-)\t'b\r\003\006\004%\t!b\031\002\017QLW.Z8viV\021QQ\r\t\005\013O*Y'\004\002\006j)\031Aq\003\003\n\t\0255T\021\016\002\b)&lWm\\;u\021-)\t(b\r\003\002\003\006I!\"\032\002\021QLW.Z8vi\002BC!b\034\006L!9A$b\r\005\002\025]D\003CC=\013w*i(b \021\007\t,\031\004C\004\006B\025U\004\031A\013\t\021\025MSQ\017a\001\013/B\001\"\"\031\006v\001\007QQ\r\005\b\007\025MB\021ACB+\t)\031\001\003\005\006\b\026MB\021ACE\003\031IgN^8lKR9A\"b#\006\020\026E\005bBCG\013\013\003\r\001D\001\006aJ|\0070\037\005\007\023\026\025\005\031A&\t\017\025MUQ\021a\0015\006!\021M]4tQ\031)))b&\006\036B!QB_CM!\riX1\024\003\007\002\021\r!!\001$\005\021]\005B\002<\0064\021%q\017\013\004\006 \026\r\026q\003\t\005\033i,)\013E\002~\013O#aa \001C\002\005\005aaBCV\023\001#QQ\026\002&'\026\024\030.\0317ju\026$G+\0379fI\006\033Go\034:J]Z|7-\031;j_:D\025M\0343mKJ\034R!\"+\r\005\026C!bACU\005+\007I\021ACB\021-)\031,\"+\003\022\003\006I!b\001\002\r\005\034Go\034:!\021-)\t'\"+\003\026\004%\t!b.\026\005\025e\006\003BC^\013\003l!!\"0\013\t\025}6\021_\001\tIV\024\030\r^5p]&!Q1YC_\00591\025N\\5uK\022+(/\031;j_:D1\"\"\035\006*\nE\t\025!\003\006:\"9A$\"+\005\002\025%GCBCf\013\033,y\rE\002c\013SCqaACd\001\004)\031\001\003\005\006b\025\035\007\031AC]\021\035\t)/\"+\005\n]Dc!\"5\006V\006]\001\003B\007{\013/\0042!`Cm\t\031y\bA1\001\002\002!AQQ\\CU\t\003)y.A\017u_RK\b/\0323BGR|'/\0238w_\016\fG/[8o\021\006tG\r\\3s)\021)I(\"9\t\r\t*Y\0161\001$\021)\t9#\"+\002\002\023\005QQ\035\013\007\013\027,9/\";\t\023\r)\031\017%AA\002\025\r\001BCC1\013G\004\n\0211\001\006:\"Q\021\021GCU#\003%\t!\"<\026\005\025=(\006BC\002\003oA!\"a\023\006*F\005I\021ACz+\t))P\013\003\006:\006]\002BCA*\013S\013\t\021\"\021\002V!Q\021\021MCU\003\003%\t!a\031\t\025\0055T\021VA\001\n\003)i\020\006\003\002r\025}\bBCA=\013w\f\t\0211\001\002f!Q\021QPCU\003\003%\t%a \t\025\005=U\021VA\001\n\0031)\001F\002i\r\017A!\"!\037\007\004\005\005\t\031AA9\021)\t9*\"+\002\002\023\005\023\021\024\005\013\003;+I+!A\005B\005}\005BCAR\013S\013\t\021\"\021\007\020Q\031\001N\"\005\t\025\005edQBA\001\002\004\t\th\002\006\007\026%\t\t\021#\001\005\r/\tQeU3sS\006d\027N_3e)f\004X\rZ!di>\024\030J\034<pG\006$\030n\0348IC:$G.\032:\021\007\t4IB\002\006\006,&\t\t\021#\001\005\r7\031RA\"\007\007\036\025\003\"\"!.\002<\026\rQ\021XCf\021\035ab\021\004C\001\rC!\"Ab\006\t\025\005ue\021DA\001\n\013\ny\nC\0053\r3\t\t\021\"!\007(Q1Q1\032D\025\rWAqa\001D\023\001\004)\031\001\003\005\006b\031\025\002\031AC]\021)\tyM\"\007\002\002\023\005eq\006\013\005\rc1)\004E\003\016\003+4\031\004E\004\016\0037,\031!\"/\t\025\005\005hQFA\001\002\004)Y\r\003\006\002f\032e\021\021!C\005\003O\004")
/*     */ public final class TypedActor {
/*     */   public static boolean equals(Object paramObject) {
/*     */     return TypedActor$.MODULE$.equals(paramObject);
/*     */   }
/*     */   
/*     */   public static int hashCode() {
/*     */     return TypedActor$.MODULE$.hashCode();
/*     */   }
/*     */   
/*     */   public static Extension apply(ActorSystem paramActorSystem) {
/*     */     return TypedActor$.MODULE$.apply(paramActorSystem);
/*     */   }
/*     */   
/*     */   public static ExecutionContextExecutor dispatcher() {
/*     */     return TypedActor$.MODULE$.dispatcher();
/*     */   }
/*     */   
/*     */   public static ActorContext context() {
/*     */     return TypedActor$.MODULE$.context();
/*     */   }
/*     */   
/*     */   public static <T> T self() {
/*     */     return TypedActor$.MODULE$.self();
/*     */   }
/*     */   
/*     */   public static TypedActorFactory get(ActorContext paramActorContext) {
/*     */     return TypedActor$.MODULE$.get(paramActorContext);
/*     */   }
/*     */   
/*     */   public static TypedActorFactory apply(ActorContext paramActorContext) {
/*     */     return TypedActor$.MODULE$.apply(paramActorContext);
/*     */   }
/*     */   
/*     */   public static TypedActorExtension createExtension(ExtendedActorSystem paramExtendedActorSystem) {
/*     */     return TypedActor$.MODULE$.createExtension(paramExtendedActorSystem);
/*     */   }
/*     */   
/*     */   public static TypedActor$ lookup() {
/*     */     return TypedActor$.MODULE$.lookup();
/*     */   }
/*     */   
/*     */   public static TypedActorExtension get(ActorSystem paramActorSystem) {
/*     */     return TypedActor$.MODULE$.get(paramActorSystem);
/*     */   }
/*     */   
/*     */   public static class MethodCall implements Product, Serializable {
/*     */     private final Method method;
/*     */     
/*     */     private final Object[] parameters;
/*     */     
/*     */     public Method method() {
/* 131 */       return this.method;
/*     */     }
/*     */     
/*     */     public Object[] parameters() {
/* 131 */       return this.parameters;
/*     */     }
/*     */     
/*     */     public MethodCall copy(Method method, Object[] parameters) {
/* 131 */       return new MethodCall(method, parameters);
/*     */     }
/*     */     
/*     */     public Method copy$default$1() {
/* 131 */       return method();
/*     */     }
/*     */     
/*     */     public Object[] copy$default$2() {
/* 131 */       return parameters();
/*     */     }
/*     */     
/*     */     public String productPrefix() {
/* 131 */       return "MethodCall";
/*     */     }
/*     */     
/*     */     public int productArity() {
/* 131 */       return 2;
/*     */     }
/*     */     
/*     */     public Object productElement(int x$1) {
/* 131 */       int i = x$1;
/* 131 */       switch (i) {
/*     */         default:
/* 131 */           throw new IndexOutOfBoundsException(BoxesRunTime.boxToInteger(x$1).toString());
/*     */         case 1:
/*     */         
/*     */         case 0:
/*     */           break;
/*     */       } 
/* 131 */       return method();
/*     */     }
/*     */     
/*     */     public Iterator<Object> productIterator() {
/* 131 */       return scala.runtime.ScalaRunTime$.MODULE$.typedProductIterator(this);
/*     */     }
/*     */     
/*     */     public boolean canEqual(Object x$1) {
/* 131 */       return x$1 instanceof MethodCall;
/*     */     }
/*     */     
/*     */     public int hashCode() {
/* 131 */       return scala.runtime.ScalaRunTime$.MODULE$._hashCode(this);
/*     */     }
/*     */     
/*     */     public String toString() {
/* 131 */       return scala.runtime.ScalaRunTime$.MODULE$._toString(this);
/*     */     }
/*     */     
/*     */     public boolean equals(Object x$1) {
/*     */       // Byte code:
/*     */       //   0: aload_0
/*     */       //   1: aload_1
/*     */       //   2: if_acmpeq -> 92
/*     */       //   5: aload_1
/*     */       //   6: astore_2
/*     */       //   7: aload_2
/*     */       //   8: instanceof akka/actor/TypedActor$MethodCall
/*     */       //   11: ifeq -> 19
/*     */       //   14: iconst_1
/*     */       //   15: istore_3
/*     */       //   16: goto -> 21
/*     */       //   19: iconst_0
/*     */       //   20: istore_3
/*     */       //   21: iload_3
/*     */       //   22: ifeq -> 96
/*     */       //   25: aload_1
/*     */       //   26: checkcast akka/actor/TypedActor$MethodCall
/*     */       //   29: astore #4
/*     */       //   31: aload_0
/*     */       //   32: invokevirtual method : ()Ljava/lang/reflect/Method;
/*     */       //   35: aload #4
/*     */       //   37: invokevirtual method : ()Ljava/lang/reflect/Method;
/*     */       //   40: astore #5
/*     */       //   42: dup
/*     */       //   43: ifnonnull -> 55
/*     */       //   46: pop
/*     */       //   47: aload #5
/*     */       //   49: ifnull -> 63
/*     */       //   52: goto -> 88
/*     */       //   55: aload #5
/*     */       //   57: invokevirtual equals : (Ljava/lang/Object;)Z
/*     */       //   60: ifeq -> 88
/*     */       //   63: aload_0
/*     */       //   64: invokevirtual parameters : ()[Ljava/lang/Object;
/*     */       //   67: aload #4
/*     */       //   69: invokevirtual parameters : ()[Ljava/lang/Object;
/*     */       //   72: if_acmpne -> 88
/*     */       //   75: aload #4
/*     */       //   77: aload_0
/*     */       //   78: invokevirtual canEqual : (Ljava/lang/Object;)Z
/*     */       //   81: ifeq -> 88
/*     */       //   84: iconst_1
/*     */       //   85: goto -> 89
/*     */       //   88: iconst_0
/*     */       //   89: ifeq -> 96
/*     */       //   92: iconst_1
/*     */       //   93: goto -> 97
/*     */       //   96: iconst_0
/*     */       //   97: ireturn
/*     */       // Line number table:
/*     */       //   Java source line number -> byte code offset
/*     */       //   #131	-> 0
/*     */       //   #63	-> 14
/*     */       //   #131	-> 21
/*     */       // Local variable table:
/*     */       //   start	length	slot	name	descriptor
/*     */       //   0	98	0	this	Lakka/actor/TypedActor$MethodCall;
/*     */       //   0	98	1	x$1	Ljava/lang/Object;
/*     */     }
/*     */     
/*     */     public MethodCall(Method method, Object[] parameters) {
/* 131 */       Product.class.$init$(this);
/*     */     }
/*     */     
/*     */     public boolean isOneWay() {
/* 133 */       Class<void> clazz = void.class;
/* 133 */       if (method().getReturnType() == null) {
/* 133 */         method().getReturnType();
/* 133 */         if (clazz != null);
/* 133 */       } else if (method().getReturnType().equals(clazz)) {
/*     */       
/*     */       } 
/*     */     }
/*     */     
/*     */     public boolean returnsFuture() {
/* 134 */       return Future.class.isAssignableFrom(method().getReturnType());
/*     */     }
/*     */     
/*     */     public boolean returnsJOption() {
/* 135 */       return Option.class.isAssignableFrom(method().getReturnType());
/*     */     }
/*     */     
/*     */     public boolean returnsOption() {
/* 136 */       return Option.class.isAssignableFrom(method().getReturnType());
/*     */     }
/*     */     
/*     */     public Object apply(Object instance) {
/*     */       try {
/* 144 */         Object object, arrayOfObject[] = parameters();
/* 145 */         if (arrayOfObject == null) {
/* 145 */           object = method().invoke(instance, new Object[0]);
/* 146 */         } else if (arrayOfObject.length == 0) {
/* 146 */           object = method().invoke(instance, new Object[0]);
/*     */         } else {
/* 147 */           object = method().invoke(instance, arrayOfObject);
/*     */         } 
/*     */         return object;
/*     */       } catch (InvocationTargetException invocationTargetException) {
/* 149 */         throw invocationTargetException.getTargetException();
/*     */       } 
/*     */     }
/*     */     
/*     */     private Object writeReplace() throws ObjectStreamException {
/*     */       TypedActor.SerializedMethodCall serializedMethodCall;
/* 151 */       Object[] arrayOfObject = parameters();
/* 152 */       if (arrayOfObject == null) {
/* 152 */         null;
/* 152 */         serializedMethodCall = new TypedActor.SerializedMethodCall(method().getDeclaringClass(), method().getName(), method().getParameterTypes(), null);
/* 153 */       } else if (arrayOfObject.length == 0) {
/* 153 */         serializedMethodCall = new TypedActor.SerializedMethodCall(method().getDeclaringClass(), method().getName(), method().getParameterTypes(), (Tuple3<Object, Class<?>, byte[]>[])scala.Array$.MODULE$.apply((Seq)scala.collection.immutable.Nil$.MODULE$, scala.reflect.ClassTag$.MODULE$.apply(Tuple3.class)));
/*     */       } else {
/* 155 */         Serialization serialization = (Serialization)akka.serialization.SerializationExtension$.MODULE$.apply((ActorSystem)akka.serialization.JavaSerializer$.MODULE$.currentSystem().value());
/* 156 */         Tuple3[] serializedParameters = (Tuple3[])scala.Array$.MODULE$.ofDim(arrayOfObject.length, scala.reflect.ClassTag$.MODULE$.apply(Tuple3.class));
/* 156 */         scala.runtime.RichInt$.MODULE$
/* 157 */           .until$extension0(scala.Predef$.MODULE$.intWrapper(0), arrayOfObject.length).foreach$mVc$sp((Function1)new TypedActor$MethodCall$$anonfun$writeReplace$1(this, serialization, serializedParameters, arrayOfObject));
/* 164 */         serializedMethodCall = new TypedActor.SerializedMethodCall(method().getDeclaringClass(), method().getName(), method().getParameterTypes(), (Tuple3<Object, Class<?>, byte[]>[])serializedParameters);
/*     */       } 
/*     */       return serializedMethodCall;
/*     */     }
/*     */     
/*     */     public class TypedActor$MethodCall$$anonfun$writeReplace$1 extends AbstractFunction1.mcVI.sp implements Serializable {
/*     */       public static final long serialVersionUID = 0L;
/*     */       
/*     */       private final Serialization serialization$1;
/*     */       
/*     */       private final Tuple3[] serializedParameters$1;
/*     */       
/*     */       private final Object[] x1$1;
/*     */       
/*     */       public final void apply(int i) {
/*     */         apply$mcVI$sp(i);
/*     */       }
/*     */       
/*     */       public TypedActor$MethodCall$$anonfun$writeReplace$1(TypedActor.MethodCall $outer, Serialization serialization$1, Tuple3[] serializedParameters$1, Object[] x1$1) {}
/*     */       
/*     */       public void apply$mcVI$sp(int i) {
/*     */         Object p = this.x1$1[i];
/*     */         Serializer s = this.serialization$1.findSerializerFor(p);
/*     */         null;
/*     */         Class<?> m = s.includeManifest() ? p.getClass() : null;
/*     */         this.serializedParameters$1[i] = new Tuple3(BoxesRunTime.boxToInteger(s.identifier()), m, s.toBinary(this.$outer.parameters()[i]));
/*     */       }
/*     */     }
/*     */   }
/*     */   
/*     */   public static class MethodCall$ extends AbstractFunction2<Method, Object[], MethodCall> implements Serializable {
/*     */     public static final MethodCall$ MODULE$;
/*     */     
/*     */     public final String toString() {
/*     */       return "MethodCall";
/*     */     }
/*     */     
/*     */     public TypedActor.MethodCall apply(Method method, Object[] parameters) {
/*     */       return new TypedActor.MethodCall(method, parameters);
/*     */     }
/*     */     
/*     */     public Option<Tuple2<Method, Object[]>> unapply(TypedActor.MethodCall x$0) {
/*     */       return (x$0 == null) ? (Option<Tuple2<Method, Object[]>>)scala.None$.MODULE$ : (Option<Tuple2<Method, Object[]>>)new Some(new Tuple2(x$0.method(), x$0.parameters()));
/*     */     }
/*     */     
/*     */     private Object readResolve() {
/*     */       return MODULE$;
/*     */     }
/*     */     
/*     */     public MethodCall$() {
/*     */       MODULE$ = this;
/*     */     }
/*     */     
/*     */     public class TypedActor$MethodCall$$anonfun$writeReplace$1 extends AbstractFunction1.mcVI.sp implements Serializable {
/*     */       public static final long serialVersionUID = 0L;
/*     */       
/*     */       private final Serialization serialization$1;
/*     */       
/*     */       private final Tuple3[] serializedParameters$1;
/*     */       
/*     */       private final Object[] x1$1;
/*     */       
/*     */       public final void apply(int i) {
/*     */         apply$mcVI$sp(i);
/*     */       }
/*     */       
/*     */       public TypedActor$MethodCall$$anonfun$writeReplace$1(TypedActor.MethodCall $outer, Serialization serialization$1, Tuple3[] serializedParameters$1, Object[] x1$1) {}
/*     */       
/*     */       public void apply$mcVI$sp(int i) {
/*     */         Object p = this.x1$1[i];
/*     */         Serializer s = this.serialization$1.findSerializerFor(p);
/*     */         null;
/*     */         Class<?> m = s.includeManifest() ? p.getClass() : null;
/*     */         this.serializedParameters$1[i] = new Tuple3(BoxesRunTime.boxToInteger(s.identifier()), m, s.toBinary(this.$outer.parameters()[i]));
/*     */       }
/*     */     }
/*     */   }
/*     */   
/*     */   public static class SerializedMethodCall implements Product, Serializable {
/*     */     private final Class<?> ownerType;
/*     */     
/*     */     private final String methodName;
/*     */     
/*     */     private final Class<?>[] parameterTypes;
/*     */     
/*     */     private final Tuple3<Object, Class<?>, byte[]>[] serializedParameters;
/*     */     
/*     */     public Class<?> ownerType() {
/* 173 */       return this.ownerType;
/*     */     }
/*     */     
/*     */     public String methodName() {
/* 173 */       return this.methodName;
/*     */     }
/*     */     
/*     */     public Class<?>[] parameterTypes() {
/* 173 */       return this.parameterTypes;
/*     */     }
/*     */     
/*     */     public Tuple3<Object, Class<?>, byte[]>[] serializedParameters() {
/* 173 */       return this.serializedParameters;
/*     */     }
/*     */     
/*     */     public SerializedMethodCall copy(Class<?> ownerType, String methodName, Class[] parameterTypes, Tuple3[] serializedParameters) {
/* 173 */       return new SerializedMethodCall(ownerType, methodName, parameterTypes, (Tuple3<Object, Class<?>, byte[]>[])serializedParameters);
/*     */     }
/*     */     
/*     */     public Class<?> copy$default$1() {
/* 173 */       return ownerType();
/*     */     }
/*     */     
/*     */     public String copy$default$2() {
/* 173 */       return methodName();
/*     */     }
/*     */     
/*     */     public Class<?>[] copy$default$3() {
/* 173 */       return parameterTypes();
/*     */     }
/*     */     
/*     */     public Tuple3<Object, Class<?>, byte[]>[] copy$default$4() {
/* 173 */       return serializedParameters();
/*     */     }
/*     */     
/*     */     public String productPrefix() {
/* 173 */       return "SerializedMethodCall";
/*     */     }
/*     */     
/*     */     public int productArity() {
/* 173 */       return 4;
/*     */     }
/*     */     
/*     */     public Object productElement(int x$1) {
/* 173 */       int i = x$1;
/* 173 */       switch (i) {
/*     */         default:
/* 173 */           throw new IndexOutOfBoundsException(BoxesRunTime.boxToInteger(x$1).toString());
/*     */         case 3:
/*     */         
/*     */         case 2:
/*     */         
/*     */         case 1:
/*     */         
/*     */         case 0:
/*     */           break;
/*     */       } 
/* 173 */       return ownerType();
/*     */     }
/*     */     
/*     */     public Iterator<Object> productIterator() {
/* 173 */       return scala.runtime.ScalaRunTime$.MODULE$.typedProductIterator(this);
/*     */     }
/*     */     
/*     */     public boolean canEqual(Object x$1) {
/* 173 */       return x$1 instanceof SerializedMethodCall;
/*     */     }
/*     */     
/*     */     public int hashCode() {
/* 173 */       return scala.runtime.ScalaRunTime$.MODULE$._hashCode(this);
/*     */     }
/*     */     
/*     */     public String toString() {
/* 173 */       return scala.runtime.ScalaRunTime$.MODULE$._toString(this);
/*     */     }
/*     */     
/*     */     public boolean equals(Object x$1) {
/*     */       // Byte code:
/*     */       //   0: aload_0
/*     */       //   1: aload_1
/*     */       //   2: if_acmpeq -> 136
/*     */       //   5: aload_1
/*     */       //   6: astore_2
/*     */       //   7: aload_2
/*     */       //   8: instanceof akka/actor/TypedActor$SerializedMethodCall
/*     */       //   11: ifeq -> 19
/*     */       //   14: iconst_1
/*     */       //   15: istore_3
/*     */       //   16: goto -> 21
/*     */       //   19: iconst_0
/*     */       //   20: istore_3
/*     */       //   21: iload_3
/*     */       //   22: ifeq -> 140
/*     */       //   25: aload_1
/*     */       //   26: checkcast akka/actor/TypedActor$SerializedMethodCall
/*     */       //   29: astore #4
/*     */       //   31: aload_0
/*     */       //   32: invokevirtual ownerType : ()Ljava/lang/Class;
/*     */       //   35: aload #4
/*     */       //   37: invokevirtual ownerType : ()Ljava/lang/Class;
/*     */       //   40: astore #5
/*     */       //   42: dup
/*     */       //   43: ifnonnull -> 55
/*     */       //   46: pop
/*     */       //   47: aload #5
/*     */       //   49: ifnull -> 63
/*     */       //   52: goto -> 132
/*     */       //   55: aload #5
/*     */       //   57: invokevirtual equals : (Ljava/lang/Object;)Z
/*     */       //   60: ifeq -> 132
/*     */       //   63: aload_0
/*     */       //   64: invokevirtual methodName : ()Ljava/lang/String;
/*     */       //   67: aload #4
/*     */       //   69: invokevirtual methodName : ()Ljava/lang/String;
/*     */       //   72: astore #6
/*     */       //   74: dup
/*     */       //   75: ifnonnull -> 87
/*     */       //   78: pop
/*     */       //   79: aload #6
/*     */       //   81: ifnull -> 95
/*     */       //   84: goto -> 132
/*     */       //   87: aload #6
/*     */       //   89: invokevirtual equals : (Ljava/lang/Object;)Z
/*     */       //   92: ifeq -> 132
/*     */       //   95: aload_0
/*     */       //   96: invokevirtual parameterTypes : ()[Ljava/lang/Class;
/*     */       //   99: aload #4
/*     */       //   101: invokevirtual parameterTypes : ()[Ljava/lang/Class;
/*     */       //   104: if_acmpne -> 132
/*     */       //   107: aload_0
/*     */       //   108: invokevirtual serializedParameters : ()[Lscala/Tuple3;
/*     */       //   111: aload #4
/*     */       //   113: invokevirtual serializedParameters : ()[Lscala/Tuple3;
/*     */       //   116: if_acmpne -> 132
/*     */       //   119: aload #4
/*     */       //   121: aload_0
/*     */       //   122: invokevirtual canEqual : (Ljava/lang/Object;)Z
/*     */       //   125: ifeq -> 132
/*     */       //   128: iconst_1
/*     */       //   129: goto -> 133
/*     */       //   132: iconst_0
/*     */       //   133: ifeq -> 140
/*     */       //   136: iconst_1
/*     */       //   137: goto -> 141
/*     */       //   140: iconst_0
/*     */       //   141: ireturn
/*     */       // Line number table:
/*     */       //   Java source line number -> byte code offset
/*     */       //   #173	-> 0
/*     */       //   #63	-> 14
/*     */       //   #173	-> 21
/*     */       // Local variable table:
/*     */       //   start	length	slot	name	descriptor
/*     */       //   0	142	0	this	Lakka/actor/TypedActor$SerializedMethodCall;
/*     */       //   0	142	1	x$1	Ljava/lang/Object;
/*     */     }
/*     */     
/*     */     public SerializedMethodCall(Class<?> ownerType, String methodName, Class[] parameterTypes, Tuple3[] serializedParameters) {
/* 173 */       Product.class.$init$(this);
/*     */     }
/*     */     
/*     */     private Object readResolve() throws ObjectStreamException {
/*     */       Object[] arrayOfObject;
/* 178 */       ExtendedActorSystem system = (ExtendedActorSystem)akka.serialization.JavaSerializer$.MODULE$.currentSystem().value();
/* 179 */       if (system == null)
/* 179 */         throw new IllegalStateException(
/* 180 */             "Trying to deserialize a SerializedMethodCall without an ActorSystem in scope. Use akka.serialization.Serialization.currentSystem.withValue(system) { ... }"); 
/* 182 */       Serialization serialization = (Serialization)akka.serialization.SerializationExtension$.MODULE$.apply(system);
/* 183 */       Tuple3[] arrayOfTuple3 = (Tuple3[])serializedParameters();
/* 184 */       if (arrayOfTuple3 == null) {
/* 184 */         null;
/* 184 */         arrayOfObject = null;
/* 185 */       } else if (arrayOfTuple3.length == 0) {
/* 185 */         arrayOfObject = (Object[])scala.Array$.MODULE$.apply((Seq)scala.collection.immutable.Nil$.MODULE$, scala.reflect.ClassTag$.MODULE$.AnyRef());
/*     */       } else {
/* 187 */         Object[] deserializedParameters = (Object[])scala.Array$.MODULE$.ofDim(arrayOfTuple3.length, scala.reflect.ClassTag$.MODULE$.AnyRef());
/* 187 */         scala.runtime.RichInt$.MODULE$
/* 188 */           .until$extension0(scala.Predef$.MODULE$.intWrapper(0), arrayOfTuple3.length).foreach$mVc$sp((Function1)new TypedActor$SerializedMethodCall$$anonfun$readResolve$1(this, serialization, deserializedParameters, arrayOfTuple3));
/* 194 */         arrayOfObject = deserializedParameters;
/*     */       } 
/*     */       return new TypedActor.MethodCall(ownerType().getDeclaredMethod(methodName(), parameterTypes()), arrayOfObject);
/*     */     }
/*     */     
/*     */     public class TypedActor$SerializedMethodCall$$anonfun$readResolve$1 extends AbstractFunction1.mcVI.sp implements Serializable {
/*     */       public static final long serialVersionUID = 0L;
/*     */       
/*     */       private final Serialization serialization$2;
/*     */       
/*     */       private final Object[] deserializedParameters$1;
/*     */       
/*     */       private final Tuple3[] x1$2;
/*     */       
/*     */       public final void apply(int i) {
/*     */         apply$mcVI$sp(i);
/*     */       }
/*     */       
/*     */       public TypedActor$SerializedMethodCall$$anonfun$readResolve$1(TypedActor.SerializedMethodCall $outer, Serialization serialization$2, Object[] deserializedParameters$1, Tuple3[] x1$2) {}
/*     */       
/*     */       public void apply$mcVI$sp(int i) {
/*     */         Tuple3 tuple3 = this.x1$2[i];
/*     */         if (tuple3 != null) {
/*     */           int sId = BoxesRunTime.unboxToInt(tuple3._1());
/*     */           Class manifest = (Class)tuple3._2();
/*     */           byte[] bytes = (byte[])tuple3._3();
/*     */           Tuple3 tuple32 = new Tuple3(BoxesRunTime.boxToInteger(sId), manifest, bytes), tuple31 = tuple32;
/*     */           int j = BoxesRunTime.unboxToInt(tuple31._1());
/*     */           Class clazz1 = (Class)tuple31._2();
/*     */           byte[] arrayOfByte1 = (byte[])tuple31._3();
/*     */           this.deserializedParameters$1[i] = ((Serializer)this.serialization$2.serializerByIdentity().apply(BoxesRunTime.boxToInteger(j))).fromBinary(arrayOfByte1, scala.Option$.MODULE$.apply(clazz1));
/*     */           return;
/*     */         } 
/*     */         throw new MatchError(tuple3);
/*     */       }
/*     */     }
/*     */   }
/*     */   
/*     */   public static class SerializedMethodCall$ extends AbstractFunction4<Class<?>, String, Class<?>[], Tuple3<Object, Class<?>, byte[]>[], SerializedMethodCall> implements Serializable {
/*     */     public static final SerializedMethodCall$ MODULE$;
/*     */     
/*     */     public final String toString() {
/*     */       return "SerializedMethodCall";
/*     */     }
/*     */     
/*     */     public TypedActor.SerializedMethodCall apply(Class<?> ownerType, String methodName, Class[] parameterTypes, Tuple3[] serializedParameters) {
/*     */       return new TypedActor.SerializedMethodCall(ownerType, methodName, parameterTypes, (Tuple3<Object, Class<?>, byte[]>[])serializedParameters);
/*     */     }
/*     */     
/*     */     public Option<Tuple4<Class<Object>, String, Class<?>[], Tuple3<Object, Class<?>, byte[]>[]>> unapply(TypedActor.SerializedMethodCall x$0) {
/*     */       return (x$0 == null) ? (Option<Tuple4<Class<Object>, String, Class<?>[], Tuple3<Object, Class<?>, byte[]>[]>>)scala.None$.MODULE$ : (Option<Tuple4<Class<Object>, String, Class<?>[], Tuple3<Object, Class<?>, byte[]>[]>>)new Some(new Tuple4(x$0.ownerType(), x$0.methodName(), x$0.parameterTypes(), x$0.serializedParameters()));
/*     */     }
/*     */     
/*     */     private Object readResolve() {
/*     */       return MODULE$;
/*     */     }
/*     */     
/*     */     public SerializedMethodCall$() {
/*     */       MODULE$ = this;
/*     */     }
/*     */     
/*     */     public class TypedActor$SerializedMethodCall$$anonfun$readResolve$1 extends AbstractFunction1.mcVI.sp implements Serializable {
/*     */       public static final long serialVersionUID = 0L;
/*     */       
/*     */       private final Serialization serialization$2;
/*     */       
/*     */       private final Object[] deserializedParameters$1;
/*     */       
/*     */       private final Tuple3[] x1$2;
/*     */       
/*     */       public final void apply(int i) {
/*     */         apply$mcVI$sp(i);
/*     */       }
/*     */       
/*     */       public TypedActor$SerializedMethodCall$$anonfun$readResolve$1(TypedActor.SerializedMethodCall $outer, Serialization serialization$2, Object[] deserializedParameters$1, Tuple3[] x1$2) {}
/*     */       
/*     */       public void apply$mcVI$sp(int i) {
/*     */         Tuple3 tuple3 = this.x1$2[i];
/*     */         if (tuple3 != null) {
/*     */           int sId = BoxesRunTime.unboxToInt(tuple3._1());
/*     */           Class manifest = (Class)tuple3._2();
/*     */           byte[] bytes = (byte[])tuple3._3();
/*     */           Tuple3 tuple32 = new Tuple3(BoxesRunTime.boxToInteger(sId), manifest, bytes), tuple31 = tuple32;
/*     */           int j = BoxesRunTime.unboxToInt(tuple31._1());
/*     */           Class clazz1 = (Class)tuple31._2();
/*     */           byte[] arrayOfByte1 = (byte[])tuple31._3();
/*     */           this.deserializedParameters$1[i] = ((Serializer)this.serialization$2.serializerByIdentity().apply(BoxesRunTime.boxToInteger(j))).fromBinary(arrayOfByte1, scala.Option$.MODULE$.apply(clazz1));
/*     */           return;
/*     */         } 
/*     */         throw new MatchError(tuple3);
/*     */       }
/*     */     }
/*     */   }
/*     */   
/*     */   public static class NullResponse$ implements Product, Serializable {
/*     */     public static final NullResponse$ MODULE$;
/*     */     
/*     */     public static final long serialVersionUID = 1L;
/*     */     
/*     */     public String productPrefix() {
/* 203 */       return "NullResponse";
/*     */     }
/*     */     
/*     */     public int productArity() {
/* 203 */       return 0;
/*     */     }
/*     */     
/*     */     public Object productElement(int x$1) {
/* 203 */       int i = x$1;
/* 203 */       throw new IndexOutOfBoundsException(BoxesRunTime.boxToInteger(x$1).toString());
/*     */     }
/*     */     
/*     */     public Iterator<Object> productIterator() {
/* 203 */       return scala.runtime.ScalaRunTime$.MODULE$.typedProductIterator(this);
/*     */     }
/*     */     
/*     */     public boolean canEqual(Object x$1) {
/* 203 */       return x$1 instanceof NullResponse$;
/*     */     }
/*     */     
/*     */     public int hashCode() {
/* 203 */       return -267248888;
/*     */     }
/*     */     
/*     */     public String toString() {
/* 203 */       return "NullResponse";
/*     */     }
/*     */     
/*     */     private Object readResolve() {
/* 203 */       return MODULE$;
/*     */     }
/*     */     
/*     */     public NullResponse$() {
/* 223 */       MODULE$ = this;
/* 223 */       Product.class.$init$(this);
/*     */     }
/*     */   }
/*     */   
/*     */   public static class TypedActor<R, T extends R> implements Actor {
/*     */     private final AtomicReference<R> proxyVar;
/*     */     
/*     */     private final T akka$actor$TypedActor$TypedActor$$me;
/*     */     
/*     */     private final ActorContext context;
/*     */     
/*     */     private final ActorRef self;
/*     */     
/*     */     public ActorContext context() {
/* 246 */       return this.context;
/*     */     }
/*     */     
/*     */     public final ActorRef self() {
/* 246 */       return this.self;
/*     */     }
/*     */     
/*     */     public void akka$actor$Actor$_setter_$context_$eq(ActorContext x$1) {
/* 246 */       this.context = x$1;
/*     */     }
/*     */     
/*     */     public final void akka$actor$Actor$_setter_$self_$eq(ActorRef x$1) {
/* 246 */       this.self = x$1;
/*     */     }
/*     */     
/*     */     public final ActorRef sender() {
/* 246 */       return Actor$class.sender(this);
/*     */     }
/*     */     
/*     */     public void aroundReceive(PartialFunction receive, Object msg) {
/* 246 */       Actor$class.aroundReceive(this, receive, msg);
/*     */     }
/*     */     
/*     */     public void aroundPreStart() {
/* 246 */       Actor$class.aroundPreStart(this);
/*     */     }
/*     */     
/*     */     public void aroundPostStop() {
/* 246 */       Actor$class.aroundPostStop(this);
/*     */     }
/*     */     
/*     */     public void aroundPreRestart(Throwable reason, Option message) {
/* 246 */       Actor$class.aroundPreRestart(this, reason, message);
/*     */     }
/*     */     
/*     */     public void aroundPostRestart(Throwable reason) {
/* 246 */       Actor$class.aroundPostRestart(this, reason);
/*     */     }
/*     */     
/*     */     public void unhandled(Object message) {
/* 246 */       Actor$class.unhandled(this, message);
/*     */     }
/*     */     
/*     */     public AtomicReference<R> proxyVar() {
/* 246 */       return this.proxyVar;
/*     */     }
/*     */     
/*     */     public TypedActor(AtomicReference<R> proxyVar, Function0<R> createInstance, Seq<Class<?>> interfaces) {
/* 246 */       Actor$class.$init$(this);
/* 248 */       ((InternalActorRef)context().parent()).isLocal() ? BoxedUnit.UNIT : 
/* 249 */         TypedActor$.MODULE$.get(context().system()).<R, R>createActorRefProxy(
/* 250 */           TypedProps$.MODULE$.apply(interfaces, createInstance), proxyVar, (Function0<ActorRef>)new TypedActor$TypedActor$$anonfun$3(this));
/* 252 */       this.akka$actor$TypedActor$TypedActor$$me = withContext(createInstance);
/*     */     }
/*     */     
/*     */     public class TypedActor$TypedActor$$anonfun$3 extends AbstractFunction0<ActorRef> implements Serializable {
/*     */       public static final long serialVersionUID = 0L;
/*     */       
/*     */       public final ActorRef apply() {
/*     */         return this.$outer.context().self();
/*     */       }
/*     */       
/*     */       public TypedActor$TypedActor$$anonfun$3(TypedActor.TypedActor $outer) {}
/*     */     }
/*     */     
/*     */     public T akka$actor$TypedActor$TypedActor$$me() {
/* 252 */       return this.akka$actor$TypedActor$TypedActor$$me;
/*     */     }
/*     */     
/*     */     public SupervisorStrategy supervisorStrategy() {
/*     */       SupervisorStrategy supervisorStrategy;
/* 254 */       T t = akka$actor$TypedActor$TypedActor$$me();
/* 255 */       if (t instanceof TypedActor.Supervisor) {
/* 255 */         T t1 = t;
/* 255 */         supervisorStrategy = ((TypedActor.Supervisor)t1).supervisorStrategy();
/*     */       } else {
/* 256 */         supervisorStrategy = Actor$class.supervisorStrategy(this);
/*     */       } 
/*     */       return supervisorStrategy;
/*     */     }
/*     */     
/*     */     public void preStart() {
/* 259 */       withContext(
/* 260 */           (Function0)new TypedActor$TypedActor$$anonfun$preStart$1(this));
/*     */     }
/*     */     
/*     */     public class TypedActor$TypedActor$$anonfun$preStart$1 extends AbstractFunction0.mcV.sp implements Serializable {
/*     */       public static final long serialVersionUID = 0L;
/*     */       
/*     */       public final void apply() {
/* 260 */         apply$mcV$sp();
/*     */       }
/*     */       
/*     */       public void apply$mcV$sp() {
/* 260 */         Object object = this.$outer.akka$actor$TypedActor$TypedActor$$me();
/* 261 */         if (object instanceof TypedActor.PreStart) {
/* 261 */           Object object1 = object;
/* 261 */           ((TypedActor.PreStart)object1).preStart();
/* 261 */           BoxedUnit boxedUnit = BoxedUnit.UNIT;
/*     */         } else {
/* 262 */           this.$outer.akka$actor$TypedActor$TypedActor$$super$preStart();
/* 262 */           BoxedUnit boxedUnit = BoxedUnit.UNIT;
/*     */         } 
/*     */       }
/*     */       
/*     */       public TypedActor$TypedActor$$anonfun$preStart$1(TypedActor.TypedActor $outer) {}
/*     */     }
/*     */     
/*     */     public void akka$actor$TypedActor$TypedActor$$super$preStart() {
/* 262 */       Actor$class.preStart(this);
/*     */     }
/*     */     
/*     */     public void postStop() {
/*     */       try {
/* 267 */         withContext(
/* 268 */             (Function0)new TypedActor$TypedActor$$anonfun$postStop$1(this));
/*     */         return;
/*     */       } finally {
/* 274 */         TypedActor.TypedActorInvocationHandler typedActorInvocationHandler = ((TypedActorExtension)TypedActor$.MODULE$.apply(context().system())).invocationHandlerFor(proxyVar().get());
/* 275 */         if (typedActorInvocationHandler == null) {
/* 275 */           BoxedUnit boxedUnit = BoxedUnit.UNIT;
/*     */         } else {
/* 277 */           typedActorInvocationHandler.actorVar().set(context().system().deadLetters());
/* 278 */           null;
/* 278 */           proxyVar().set(null);
/* 278 */           BoxedUnit boxedUnit = BoxedUnit.UNIT;
/*     */         } 
/*     */       } 
/*     */     }
/*     */     
/*     */     public class TypedActor$TypedActor$$anonfun$postStop$1 extends AbstractFunction0.mcV.sp implements Serializable {
/*     */       public static final long serialVersionUID = 0L;
/*     */       
/*     */       public final void apply() {
/*     */         apply$mcV$sp();
/*     */       }
/*     */       
/*     */       public void apply$mcV$sp() {
/*     */         Object object = this.$outer.akka$actor$TypedActor$TypedActor$$me();
/*     */         if (object instanceof TypedActor.PostStop) {
/*     */           Object object1 = object;
/*     */           ((TypedActor.PostStop)object1).postStop();
/*     */           BoxedUnit boxedUnit = BoxedUnit.UNIT;
/*     */         } else {
/*     */           this.$outer.akka$actor$TypedActor$TypedActor$$super$postStop();
/*     */           BoxedUnit boxedUnit = BoxedUnit.UNIT;
/*     */         } 
/*     */       }
/*     */       
/*     */       public TypedActor$TypedActor$$anonfun$postStop$1(TypedActor.TypedActor $outer) {}
/*     */     }
/*     */     
/*     */     public void akka$actor$TypedActor$TypedActor$$super$postStop() {
/*     */       Actor$class.postStop(this);
/*     */     }
/*     */     
/*     */     public void preRestart(Throwable reason, Option message) {
/* 282 */       withContext(
/* 283 */           (Function0)new TypedActor$TypedActor$$anonfun$preRestart$1(this, reason, (TypedActor<R, T>)message));
/*     */     }
/*     */     
/*     */     public class TypedActor$TypedActor$$anonfun$preRestart$1 extends AbstractFunction0.mcV.sp implements Serializable {
/*     */       public static final long serialVersionUID = 0L;
/*     */       
/*     */       private final Throwable reason$1;
/*     */       
/*     */       private final Option message$1;
/*     */       
/*     */       public final void apply() {
/* 283 */         apply$mcV$sp();
/*     */       }
/*     */       
/*     */       public void apply$mcV$sp() {
/* 283 */         Object object = this.$outer.akka$actor$TypedActor$TypedActor$$me();
/* 284 */         if (object instanceof TypedActor.PreRestart) {
/* 284 */           Object object1 = object;
/* 284 */           ((TypedActor.PreRestart)object1).preRestart(this.reason$1, this.message$1);
/* 284 */           BoxedUnit boxedUnit = BoxedUnit.UNIT;
/*     */         } else {
/* 285 */           this.$outer.context().children().foreach((Function1)new TypedActor$TypedActor$$anonfun$preRestart$1$$anonfun$apply$mcV$sp$1(this));
/* 285 */           BoxedUnit boxedUnit = BoxedUnit.UNIT;
/*     */         } 
/*     */       }
/*     */       
/*     */       public TypedActor$TypedActor$$anonfun$preRestart$1(TypedActor.TypedActor $outer, Throwable reason$1, Option message$1) {}
/*     */       
/*     */       public class TypedActor$TypedActor$$anonfun$preRestart$1$$anonfun$apply$mcV$sp$1 extends AbstractFunction1<ActorRef, BoxedUnit> implements Serializable {
/*     */         public static final long serialVersionUID = 0L;
/*     */         
/*     */         public final void apply(ActorRef actor) {
/* 285 */           this.$outer.akka$actor$TypedActor$TypedActor$$anonfun$$$outer().context().stop(actor);
/*     */         }
/*     */         
/*     */         public TypedActor$TypedActor$$anonfun$preRestart$1$$anonfun$apply$mcV$sp$1(TypedActor$TypedActor$$anonfun$preRestart$1 $outer) {}
/*     */       }
/*     */     }
/*     */     
/*     */     public void postRestart(Throwable reason) {
/* 289 */       withContext(
/* 290 */           (Function0)new TypedActor$TypedActor$$anonfun$postRestart$1(this, (TypedActor<R, T>)reason));
/*     */     }
/*     */     
/*     */     public class TypedActor$TypedActor$$anonfun$postRestart$1 extends AbstractFunction0.mcV.sp implements Serializable {
/*     */       public static final long serialVersionUID = 0L;
/*     */       
/*     */       private final Throwable reason$2;
/*     */       
/*     */       public final void apply() {
/* 290 */         apply$mcV$sp();
/*     */       }
/*     */       
/*     */       public void apply$mcV$sp() {
/* 290 */         Object object = this.$outer.akka$actor$TypedActor$TypedActor$$me();
/* 291 */         if (object instanceof TypedActor.PostRestart) {
/* 291 */           Object object1 = object;
/* 291 */           ((TypedActor.PostRestart)object1).postRestart(this.reason$2);
/* 291 */           BoxedUnit boxedUnit = BoxedUnit.UNIT;
/*     */         } else {
/* 292 */           this.$outer.akka$actor$TypedActor$TypedActor$$super$postRestart(this.reason$2);
/* 292 */           BoxedUnit boxedUnit = BoxedUnit.UNIT;
/*     */         } 
/*     */       }
/*     */       
/*     */       public TypedActor$TypedActor$$anonfun$postRestart$1(TypedActor.TypedActor $outer, Throwable reason$2) {}
/*     */     }
/*     */     
/*     */     public void akka$actor$TypedActor$TypedActor$$super$postRestart(Throwable reason) {
/* 292 */       Actor$class.postRestart(this, reason);
/*     */     }
/*     */     
/*     */     public <T> T withContext(Function0 unitOfWork) {
/* 297 */       TypedActor$.MODULE$.akka$actor$TypedActor$$selfReference().set(proxyVar().get());
/* 298 */       TypedActor$.MODULE$.akka$actor$TypedActor$$currentContext().set(context());
/*     */       try {
/* 299 */         return (T)unitOfWork.apply();
/*     */       } finally {
/* 300 */         null;
/* 300 */         TypedActor$.MODULE$.akka$actor$TypedActor$$selfReference().set(null);
/* 301 */         null;
/* 301 */         TypedActor$.MODULE$.akka$actor$TypedActor$$currentContext().set(null);
/*     */       } 
/*     */     }
/*     */     
/*     */     public PartialFunction<Object, BoxedUnit> receive() {
/* 305 */       return (PartialFunction<Object, BoxedUnit>)new TypedActor$TypedActor$$anonfun$receive$1(this);
/*     */     }
/*     */     
/*     */     public class TypedActor$TypedActor$$anonfun$receive$1 extends AbstractPartialFunction.mcVL.sp<Object> implements Serializable {
/*     */       public static final long serialVersionUID = 0L;
/*     */       
/*     */       public final <A1, B1> B1 applyOrElse(Object x1, Function1 default) {
/* 305 */         Object object2, object1 = x1;
/* 306 */         if (object1 instanceof TypedActor.MethodCall) {
/* 306 */           TypedActor.MethodCall methodCall = (TypedActor.MethodCall)object1;
/* 306 */           this.$outer.withContext(
/* 307 */               (Function0)new TypedActor$TypedActor$$anonfun$receive$1$$anonfun$applyOrElse$2(this, ($anonfun$receive$1)methodCall));
/*     */           object2 = BoxedUnit.UNIT;
/* 330 */         } else if (this.$outer.akka$actor$TypedActor$TypedActor$$me() instanceof TypedActor.Receiver) {
/* 330 */           object2 = this.$outer.withContext(
/* 331 */               (Function0)new TypedActor$TypedActor$$anonfun$receive$1$$anonfun$applyOrElse$1(this, ($anonfun$receive$1)object1));
/*     */         } else {
/*     */           object2 = default.apply(x1);
/*     */         } 
/*     */         return (B1)object2;
/*     */       }
/*     */       
/*     */       public final boolean isDefinedAt(Object x1) {
/*     */         boolean bool;
/*     */         Object object = x1;
/*     */         if (object instanceof TypedActor.MethodCall) {
/*     */           bool = true;
/*     */         } else if (this.$outer.akka$actor$TypedActor$TypedActor$$me() instanceof TypedActor.Receiver) {
/*     */           bool = true;
/*     */         } else {
/*     */           bool = false;
/*     */         } 
/*     */         return bool;
/*     */       }
/*     */       
/*     */       public TypedActor$TypedActor$$anonfun$receive$1(TypedActor.TypedActor $outer) {}
/*     */       
/*     */       public class TypedActor$TypedActor$$anonfun$receive$1$$anonfun$applyOrElse$2 extends AbstractFunction0<Object> implements Serializable {
/*     */         public static final long serialVersionUID = 0L;
/*     */         
/*     */         private final TypedActor.MethodCall x2$1;
/*     */         
/*     */         public final Object apply() {
/*     */           // Byte code:
/*     */           //   0: aload_0
/*     */           //   1: getfield x2$1 : Lakka/actor/TypedActor$MethodCall;
/*     */           //   4: invokevirtual isOneWay : ()Z
/*     */           //   7: ifeq -> 30
/*     */           //   10: aload_0
/*     */           //   11: getfield x2$1 : Lakka/actor/TypedActor$MethodCall;
/*     */           //   14: aload_0
/*     */           //   15: getfield $outer : Lakka/actor/TypedActor$TypedActor$$anonfun$receive$1;
/*     */           //   18: invokevirtual akka$actor$TypedActor$TypedActor$$anonfun$$$outer : ()Lakka/actor/TypedActor$TypedActor;
/*     */           //   21: invokevirtual akka$actor$TypedActor$TypedActor$$me : ()Ljava/lang/Object;
/*     */           //   24: invokevirtual apply : (Ljava/lang/Object;)Ljava/lang/Object;
/*     */           //   27: goto -> 202
/*     */           //   30: aload_0
/*     */           //   31: getfield $outer : Lakka/actor/TypedActor$TypedActor$$anonfun$receive$1;
/*     */           //   34: invokevirtual akka$actor$TypedActor$TypedActor$$anonfun$$$outer : ()Lakka/actor/TypedActor$TypedActor;
/*     */           //   37: invokevirtual sender : ()Lakka/actor/ActorRef;
/*     */           //   40: astore #6
/*     */           //   42: aload_0
/*     */           //   43: getfield x2$1 : Lakka/actor/TypedActor$MethodCall;
/*     */           //   46: aload_0
/*     */           //   47: getfield $outer : Lakka/actor/TypedActor$TypedActor$$anonfun$receive$1;
/*     */           //   50: invokevirtual akka$actor$TypedActor$TypedActor$$anonfun$$$outer : ()Lakka/actor/TypedActor$TypedActor;
/*     */           //   53: invokevirtual akka$actor$TypedActor$TypedActor$$me : ()Ljava/lang/Object;
/*     */           //   56: invokevirtual apply : (Ljava/lang/Object;)Ljava/lang/Object;
/*     */           //   59: astore #7
/*     */           //   61: aload #7
/*     */           //   63: instanceof scala/concurrent/Future
/*     */           //   66: ifeq -> 130
/*     */           //   69: aload #7
/*     */           //   71: checkcast scala/concurrent/Future
/*     */           //   74: astore #8
/*     */           //   76: aload_0
/*     */           //   77: getfield x2$1 : Lakka/actor/TypedActor$MethodCall;
/*     */           //   80: invokevirtual returnsFuture : ()Z
/*     */           //   83: ifeq -> 130
/*     */           //   86: aload_0
/*     */           //   87: getfield $outer : Lakka/actor/TypedActor$TypedActor$$anonfun$receive$1;
/*     */           //   90: invokevirtual akka$actor$TypedActor$TypedActor$$anonfun$$$outer : ()Lakka/actor/TypedActor$TypedActor;
/*     */           //   93: invokevirtual context : ()Lakka/actor/ActorContext;
/*     */           //   96: invokeinterface dispatcher : ()Lscala/concurrent/ExecutionContextExecutor;
/*     */           //   101: astore #10
/*     */           //   103: aload #8
/*     */           //   105: new akka/actor/TypedActor$TypedActor$$anonfun$receive$1$$anonfun$applyOrElse$2$$anonfun$apply$2
/*     */           //   108: dup
/*     */           //   109: aload_0
/*     */           //   110: aload #6
/*     */           //   112: invokespecial <init> : (Lakka/actor/TypedActor$TypedActor$$anonfun$receive$1$$anonfun$applyOrElse$2;Lakka/actor/ActorRef;)V
/*     */           //   115: aload #10
/*     */           //   117: invokeinterface onComplete : (Lscala/Function1;Lscala/concurrent/ExecutionContext;)V
/*     */           //   122: getstatic scala/runtime/BoxedUnit.UNIT : Lscala/runtime/BoxedUnit;
/*     */           //   125: astore #9
/*     */           //   127: goto -> 199
/*     */           //   130: aload #7
/*     */           //   132: ifnonnull -> 169
/*     */           //   135: getstatic akka/actor/package$.MODULE$ : Lakka/actor/package$;
/*     */           //   138: aload #6
/*     */           //   140: invokevirtual actorRef2Scala : (Lakka/actor/ActorRef;)Lakka/actor/ScalaActorRef;
/*     */           //   143: getstatic akka/actor/TypedActor$NullResponse$.MODULE$ : Lakka/actor/TypedActor$NullResponse$;
/*     */           //   146: aload_0
/*     */           //   147: getfield $outer : Lakka/actor/TypedActor$TypedActor$$anonfun$receive$1;
/*     */           //   150: invokevirtual akka$actor$TypedActor$TypedActor$$anonfun$$$outer : ()Lakka/actor/TypedActor$TypedActor;
/*     */           //   153: invokevirtual self : ()Lakka/actor/ActorRef;
/*     */           //   156: invokeinterface $bang : (Ljava/lang/Object;Lakka/actor/ActorRef;)V
/*     */           //   161: getstatic scala/runtime/BoxedUnit.UNIT : Lscala/runtime/BoxedUnit;
/*     */           //   164: astore #9
/*     */           //   166: goto -> 199
/*     */           //   169: getstatic akka/actor/package$.MODULE$ : Lakka/actor/package$;
/*     */           //   172: aload #6
/*     */           //   174: invokevirtual actorRef2Scala : (Lakka/actor/ActorRef;)Lakka/actor/ScalaActorRef;
/*     */           //   177: aload #7
/*     */           //   179: aload_0
/*     */           //   180: getfield $outer : Lakka/actor/TypedActor$TypedActor$$anonfun$receive$1;
/*     */           //   183: invokevirtual akka$actor$TypedActor$TypedActor$$anonfun$$$outer : ()Lakka/actor/TypedActor$TypedActor;
/*     */           //   186: invokevirtual self : ()Lakka/actor/ActorRef;
/*     */           //   189: invokeinterface $bang : (Ljava/lang/Object;Lakka/actor/ActorRef;)V
/*     */           //   194: getstatic scala/runtime/BoxedUnit.UNIT : Lscala/runtime/BoxedUnit;
/*     */           //   197: astore #9
/*     */           //   199: getstatic scala/runtime/BoxedUnit.UNIT : Lscala/runtime/BoxedUnit;
/*     */           //   202: areturn
/*     */           //   203: astore_1
/*     */           //   204: aload_1
/*     */           //   205: astore_2
/*     */           //   206: getstatic scala/util/control/NonFatal$.MODULE$ : Lscala/util/control/NonFatal$;
/*     */           //   209: aload_2
/*     */           //   210: invokevirtual unapply : (Ljava/lang/Throwable;)Lscala/Option;
/*     */           //   213: astore_3
/*     */           //   214: aload_3
/*     */           //   215: invokevirtual isEmpty : ()Z
/*     */           //   218: ifeq -> 223
/*     */           //   221: aload_1
/*     */           //   222: athrow
/*     */           //   223: aload_3
/*     */           //   224: invokevirtual get : ()Ljava/lang/Object;
/*     */           //   227: checkcast java/lang/Throwable
/*     */           //   230: astore #4
/*     */           //   232: getstatic akka/actor/package$.MODULE$ : Lakka/actor/package$;
/*     */           //   235: aload_0
/*     */           //   236: getfield $outer : Lakka/actor/TypedActor$TypedActor$$anonfun$receive$1;
/*     */           //   239: invokevirtual akka$actor$TypedActor$TypedActor$$anonfun$$$outer : ()Lakka/actor/TypedActor$TypedActor;
/*     */           //   242: invokevirtual sender : ()Lakka/actor/ActorRef;
/*     */           //   245: invokevirtual actorRef2Scala : (Lakka/actor/ActorRef;)Lakka/actor/ScalaActorRef;
/*     */           //   248: new akka/actor/Status$Failure
/*     */           //   251: dup
/*     */           //   252: aload #4
/*     */           //   254: invokespecial <init> : (Ljava/lang/Throwable;)V
/*     */           //   257: aload_0
/*     */           //   258: getfield $outer : Lakka/actor/TypedActor$TypedActor$$anonfun$receive$1;
/*     */           //   261: invokevirtual akka$actor$TypedActor$TypedActor$$anonfun$$$outer : ()Lakka/actor/TypedActor$TypedActor;
/*     */           //   264: invokevirtual self : ()Lakka/actor/ActorRef;
/*     */           //   267: invokeinterface $bang : (Ljava/lang/Object;Lakka/actor/ActorRef;)V
/*     */           //   272: aload #4
/*     */           //   274: athrow
/*     */           // Line number table:
/*     */           //   Java source line number -> byte code offset
/*     */           //   #307	-> 0
/*     */           //   #310	-> 30
/*     */           //   #311	-> 42
/*     */           //   #312	-> 61
/*     */           //   #313	-> 86
/*     */           //   #314	-> 103
/*     */           //   #312	-> 125
/*     */           //   #319	-> 130
/*     */           //   #320	-> 169
/*     */           //   #311	-> 199
/*     */           //   #307	-> 202
/*     */           //   #309	-> 203
/*     */           //   #323	-> 206
/*     */           //   #309	-> 221
/*     */           //   #305	-> 223
/*     */           //   #323	-> 224
/*     */           //   #324	-> 232
/*     */           //   #325	-> 272
/*     */           // Local variable table:
/*     */           //   start	length	slot	name	descriptor
/*     */           //   0	275	0	this	Lakka/actor/TypedActor$TypedActor$$anonfun$receive$1$$anonfun$applyOrElse$2;
/*     */           //   42	160	6	s	Lakka/actor/ActorRef;
/*     */           //   103	22	10	dispatcher	Lscala/concurrent/ExecutionContextExecutor;
/*     */           //   232	43	4	e	Ljava/lang/Throwable;
/*     */           // Exception table:
/*     */           //   from	to	target	type
/*     */           //   30	202	203	finally
/*     */         }
/*     */         
/*     */         public TypedActor$TypedActor$$anonfun$receive$1$$anonfun$applyOrElse$2(TypedActor$TypedActor$$anonfun$receive$1 $outer, TypedActor.MethodCall x2$1) {}
/*     */         
/*     */         public class TypedActor$TypedActor$$anonfun$receive$1$$anonfun$applyOrElse$2$$anonfun$apply$2 extends AbstractFunction1<Try<Object>, BoxedUnit> implements Serializable {
/*     */           public static final long serialVersionUID = 0L;
/*     */           
/*     */           private final ActorRef s$1;
/*     */           
/*     */           public TypedActor$TypedActor$$anonfun$receive$1$$anonfun$applyOrElse$2$$anonfun$apply$2(TypedActor$TypedActor$$anonfun$receive$1$$anonfun$applyOrElse$2 $outer, ActorRef s$1) {}
/*     */           
/*     */           public final void apply(Try x0$1) {
/*     */             boolean bool = false;
/*     */             null;
/*     */             Success success = null;
/*     */             Try try_ = x0$1;
/*     */             if (try_ instanceof Success) {
/*     */               bool = true;
/*     */               success = (Success)try_;
/*     */               Object object = success.value();
/*     */               if (object == null) {
/*     */                 package$.MODULE$.actorRef2Scala(this.s$1).$bang(TypedActor.NullResponse$.MODULE$, this.$outer.akka$actor$TypedActor$TypedActor$$anonfun$$anonfun$$$outer().akka$actor$TypedActor$TypedActor$$anonfun$$$outer().self());
/*     */                 BoxedUnit boxedUnit = BoxedUnit.UNIT;
/*     */                 return;
/*     */               } 
/*     */             } 
/*     */             if (bool) {
/*     */               Object result = success.value();
/*     */               package$.MODULE$.actorRef2Scala(this.s$1).$bang(result, this.$outer.akka$actor$TypedActor$TypedActor$$anonfun$$anonfun$$$outer().akka$actor$TypedActor$TypedActor$$anonfun$$$outer().self());
/*     */               BoxedUnit boxedUnit = BoxedUnit.UNIT;
/*     */             } else {
/*     */               if (try_ instanceof Failure) {
/*     */                 Failure failure = (Failure)try_;
/*     */                 Throwable f = failure.exception();
/*     */                 package$.MODULE$.actorRef2Scala(this.s$1).$bang(new Status.Failure(f), this.$outer.akka$actor$TypedActor$TypedActor$$anonfun$$anonfun$$$outer().akka$actor$TypedActor$TypedActor$$anonfun$$$outer().self());
/*     */                 BoxedUnit boxedUnit = BoxedUnit.UNIT;
/*     */                 return;
/*     */               } 
/*     */               throw new MatchError(try_);
/*     */             } 
/*     */           }
/*     */         }
/*     */       }
/*     */       
/*     */       public class TypedActor$TypedActor$$anonfun$receive$1$$anonfun$applyOrElse$1 extends AbstractFunction0.mcV.sp implements Serializable {
/*     */         public static final long serialVersionUID = 0L;
/*     */         
/*     */         private final Object x1$3;
/*     */         
/*     */         public final void apply() {
/* 331 */           apply$mcV$sp();
/*     */         }
/*     */         
/*     */         public void apply$mcV$sp() {
/* 331 */           ((TypedActor.Receiver)this.$outer.akka$actor$TypedActor$TypedActor$$anonfun$$$outer().akka$actor$TypedActor$TypedActor$$me()).onReceive(this.x1$3, this.$outer.akka$actor$TypedActor$TypedActor$$anonfun$$$outer().sender());
/*     */         }
/*     */         
/*     */         public TypedActor$TypedActor$$anonfun$receive$1$$anonfun$applyOrElse$1(TypedActor$TypedActor$$anonfun$receive$1 $outer, Object x1$3) {}
/*     */       }
/*     */     }
/*     */   }
/*     */   
/*     */   public static class TypedActorInvocationHandler implements InvocationHandler, Serializable {
/*     */     private final transient TypedActorExtension extension;
/*     */     
/*     */     private final transient AtomicReference<ActorRef> actorVar;
/*     */     
/*     */     private final transient Timeout timeout;
/*     */     
/*     */     public TypedActorExtension extension() {
/* 407 */       return this.extension;
/*     */     }
/*     */     
/*     */     public AtomicReference<ActorRef> actorVar() {
/* 407 */       return this.actorVar;
/*     */     }
/*     */     
/*     */     public Timeout timeout() {
/* 407 */       return this.timeout;
/*     */     }
/*     */     
/*     */     public TypedActorInvocationHandler(TypedActorExtension extension, AtomicReference<ActorRef> actorVar, Timeout timeout) {}
/*     */     
/*     */     public ActorRef actor() {
/* 409 */       return actorVar().get();
/*     */     }
/*     */     
/*     */     public Object invoke(Object proxy, Method method, Object[] args) throws Throwable {
/*     */       // Byte code:
/*     */       //   0: aload_2
/*     */       //   1: invokevirtual getName : ()Ljava/lang/String;
/*     */       //   4: astore #4
/*     */       //   6: ldc 'toString'
/*     */       //   8: aload #4
/*     */       //   10: astore #5
/*     */       //   12: dup
/*     */       //   13: ifnonnull -> 25
/*     */       //   16: pop
/*     */       //   17: aload #5
/*     */       //   19: ifnull -> 33
/*     */       //   22: goto -> 45
/*     */       //   25: aload #5
/*     */       //   27: invokevirtual equals : (Ljava/lang/Object;)Z
/*     */       //   30: ifeq -> 45
/*     */       //   33: aload_0
/*     */       //   34: invokevirtual actor : ()Lakka/actor/ActorRef;
/*     */       //   37: invokevirtual toString : ()Ljava/lang/String;
/*     */       //   40: astore #6
/*     */       //   42: goto -> 699
/*     */       //   45: ldc 'equals'
/*     */       //   47: aload #4
/*     */       //   49: astore #7
/*     */       //   51: dup
/*     */       //   52: ifnonnull -> 64
/*     */       //   55: pop
/*     */       //   56: aload #7
/*     */       //   58: ifnull -> 72
/*     */       //   61: goto -> 135
/*     */       //   64: aload #7
/*     */       //   66: invokevirtual equals : (Ljava/lang/Object;)Z
/*     */       //   69: ifeq -> 135
/*     */       //   72: aload_3
/*     */       //   73: arraylength
/*     */       //   74: iconst_1
/*     */       //   75: if_icmpne -> 85
/*     */       //   78: aload_1
/*     */       //   79: aload_3
/*     */       //   80: iconst_0
/*     */       //   81: aaload
/*     */       //   82: if_acmpeq -> 122
/*     */       //   85: aload_0
/*     */       //   86: invokevirtual actor : ()Lakka/actor/ActorRef;
/*     */       //   89: aload_0
/*     */       //   90: invokevirtual extension : ()Lakka/actor/TypedActorExtension;
/*     */       //   93: aload_3
/*     */       //   94: iconst_0
/*     */       //   95: aaload
/*     */       //   96: invokevirtual getActorRefFor : (Ljava/lang/Object;)Lakka/actor/ActorRef;
/*     */       //   99: astore #8
/*     */       //   101: dup
/*     */       //   102: ifnonnull -> 114
/*     */       //   105: pop
/*     */       //   106: aload #8
/*     */       //   108: ifnull -> 122
/*     */       //   111: goto -> 126
/*     */       //   114: aload #8
/*     */       //   116: invokevirtual equals : (Ljava/lang/Object;)Z
/*     */       //   119: ifeq -> 126
/*     */       //   122: iconst_1
/*     */       //   123: goto -> 127
/*     */       //   126: iconst_0
/*     */       //   127: invokestatic boxToBoolean : (Z)Ljava/lang/Boolean;
/*     */       //   130: astore #6
/*     */       //   132: goto -> 699
/*     */       //   135: ldc 'hashCode'
/*     */       //   137: aload #4
/*     */       //   139: astore #9
/*     */       //   141: dup
/*     */       //   142: ifnonnull -> 154
/*     */       //   145: pop
/*     */       //   146: aload #9
/*     */       //   148: ifnull -> 162
/*     */       //   151: goto -> 177
/*     */       //   154: aload #9
/*     */       //   156: invokevirtual equals : (Ljava/lang/Object;)Z
/*     */       //   159: ifeq -> 177
/*     */       //   162: aload_0
/*     */       //   163: invokevirtual actor : ()Lakka/actor/ActorRef;
/*     */       //   166: invokevirtual hashCode : ()I
/*     */       //   169: invokestatic boxToInteger : (I)Ljava/lang/Integer;
/*     */       //   172: astore #6
/*     */       //   174: goto -> 699
/*     */       //   177: aload_0
/*     */       //   178: invokevirtual extension : ()Lakka/actor/TypedActorExtension;
/*     */       //   181: invokevirtual system : ()Lakka/actor/ExtendedActorSystem;
/*     */       //   184: invokevirtual dispatcher : ()Lscala/concurrent/ExecutionContextExecutor;
/*     */       //   187: astore #10
/*     */       //   189: new akka/actor/TypedActor$MethodCall
/*     */       //   192: dup
/*     */       //   193: aload_2
/*     */       //   194: aload_3
/*     */       //   195: invokespecial <init> : (Ljava/lang/reflect/Method;[Ljava/lang/Object;)V
/*     */       //   198: astore #11
/*     */       //   200: aload #11
/*     */       //   202: invokevirtual isOneWay : ()Z
/*     */       //   205: ifeq -> 254
/*     */       //   208: getstatic akka/actor/package$.MODULE$ : Lakka/actor/package$;
/*     */       //   211: aload_0
/*     */       //   212: invokevirtual actor : ()Lakka/actor/ActorRef;
/*     */       //   215: invokevirtual actorRef2Scala : (Lakka/actor/ActorRef;)Lakka/actor/ScalaActorRef;
/*     */       //   218: astore #13
/*     */       //   220: aload #11
/*     */       //   222: astore #14
/*     */       //   224: aload #13
/*     */       //   226: aload #14
/*     */       //   228: invokeinterface $bang$default$2 : (Ljava/lang/Object;)Lakka/actor/ActorRef;
/*     */       //   233: astore #15
/*     */       //   235: aload #13
/*     */       //   237: aload #14
/*     */       //   239: aload #15
/*     */       //   241: invokeinterface $bang : (Ljava/lang/Object;Lakka/actor/ActorRef;)V
/*     */       //   246: aconst_null
/*     */       //   247: pop
/*     */       //   248: aconst_null
/*     */       //   249: astore #12
/*     */       //   251: goto -> 695
/*     */       //   254: aload #11
/*     */       //   256: invokevirtual returnsFuture : ()Z
/*     */       //   259: ifeq -> 298
/*     */       //   262: getstatic akka/pattern/package$.MODULE$ : Lakka/pattern/package$;
/*     */       //   265: aload_0
/*     */       //   266: invokevirtual actor : ()Lakka/actor/ActorRef;
/*     */       //   269: aload #11
/*     */       //   271: aload_0
/*     */       //   272: invokevirtual timeout : ()Lakka/util/Timeout;
/*     */       //   275: invokevirtual ask : (Lakka/actor/ActorRef;Ljava/lang/Object;Lakka/util/Timeout;)Lscala/concurrent/Future;
/*     */       //   278: new akka/actor/TypedActor$TypedActorInvocationHandler$$anonfun$invoke$1
/*     */       //   281: dup
/*     */       //   282: aload_0
/*     */       //   283: invokespecial <init> : (Lakka/actor/TypedActor$TypedActorInvocationHandler;)V
/*     */       //   286: aload #10
/*     */       //   288: invokeinterface map : (Lscala/Function1;Lscala/concurrent/ExecutionContext;)Lscala/concurrent/Future;
/*     */       //   293: astore #12
/*     */       //   295: goto -> 695
/*     */       //   298: aload #11
/*     */       //   300: invokevirtual returnsJOption : ()Z
/*     */       //   303: ifne -> 314
/*     */       //   306: aload #11
/*     */       //   308: invokevirtual returnsOption : ()Z
/*     */       //   311: ifeq -> 358
/*     */       //   314: getstatic akka/pattern/package$.MODULE$ : Lakka/pattern/package$;
/*     */       //   317: aload_0
/*     */       //   318: invokevirtual actor : ()Lakka/actor/ActorRef;
/*     */       //   321: aload #11
/*     */       //   323: aload_0
/*     */       //   324: invokevirtual timeout : ()Lakka/util/Timeout;
/*     */       //   327: invokevirtual ask : (Lakka/actor/ActorRef;Ljava/lang/Object;Lakka/util/Timeout;)Lscala/concurrent/Future;
/*     */       //   330: astore #16
/*     */       //   332: getstatic scala/concurrent/Await$.MODULE$ : Lscala/concurrent/Await$;
/*     */       //   335: aload #16
/*     */       //   337: aload_0
/*     */       //   338: invokevirtual timeout : ()Lakka/util/Timeout;
/*     */       //   341: invokevirtual duration : ()Lscala/concurrent/duration/FiniteDuration;
/*     */       //   344: invokevirtual ready : (Lscala/concurrent/Awaitable;Lscala/concurrent/duration/Duration;)Lscala/concurrent/Awaitable;
/*     */       //   347: checkcast scala/concurrent/Future
/*     */       //   350: invokeinterface value : ()Lscala/Option;
/*     */       //   355: goto -> 440
/*     */       //   358: getstatic scala/concurrent/Await$.MODULE$ : Lscala/concurrent/Await$;
/*     */       //   361: getstatic akka/pattern/package$.MODULE$ : Lakka/pattern/package$;
/*     */       //   364: aload_0
/*     */       //   365: invokevirtual actor : ()Lakka/actor/ActorRef;
/*     */       //   368: aload #11
/*     */       //   370: aload_0
/*     */       //   371: invokevirtual timeout : ()Lakka/util/Timeout;
/*     */       //   374: invokevirtual ask : (Lakka/actor/ActorRef;Ljava/lang/Object;Lakka/util/Timeout;)Lscala/concurrent/Future;
/*     */       //   377: aload_0
/*     */       //   378: invokevirtual timeout : ()Lakka/util/Timeout;
/*     */       //   381: invokevirtual duration : ()Lscala/concurrent/duration/FiniteDuration;
/*     */       //   384: invokevirtual result : (Lscala/concurrent/Awaitable;Lscala/concurrent/duration/Duration;)Ljava/lang/Object;
/*     */       //   387: astore #32
/*     */       //   389: getstatic akka/actor/TypedActor$NullResponse$.MODULE$ : Lakka/actor/TypedActor$NullResponse$;
/*     */       //   392: aload #32
/*     */       //   394: astore #33
/*     */       //   396: dup
/*     */       //   397: ifnonnull -> 409
/*     */       //   400: pop
/*     */       //   401: aload #33
/*     */       //   403: ifnull -> 417
/*     */       //   406: goto -> 425
/*     */       //   409: aload #33
/*     */       //   411: invokevirtual equals : (Ljava/lang/Object;)Z
/*     */       //   414: ifeq -> 425
/*     */       //   417: aconst_null
/*     */       //   418: pop
/*     */       //   419: aconst_null
/*     */       //   420: astore #34
/*     */       //   422: goto -> 429
/*     */       //   425: aload #32
/*     */       //   427: astore #34
/*     */       //   429: aload #34
/*     */       //   431: astore #12
/*     */       //   433: goto -> 695
/*     */       //   436: pop
/*     */       //   437: getstatic scala/None$.MODULE$ : Lscala/None$;
/*     */       //   440: astore #17
/*     */       //   442: getstatic scala/None$.MODULE$ : Lscala/None$;
/*     */       //   445: aload #17
/*     */       //   447: astore #18
/*     */       //   449: dup
/*     */       //   450: ifnonnull -> 462
/*     */       //   453: pop
/*     */       //   454: aload #18
/*     */       //   456: ifnull -> 470
/*     */       //   459: goto -> 476
/*     */       //   462: aload #18
/*     */       //   464: invokevirtual equals : (Ljava/lang/Object;)Z
/*     */       //   467: ifeq -> 476
/*     */       //   470: iconst_1
/*     */       //   471: istore #19
/*     */       //   473: goto -> 617
/*     */       //   476: aload #17
/*     */       //   478: instanceof scala/Some
/*     */       //   481: ifeq -> 557
/*     */       //   484: aload #17
/*     */       //   486: checkcast scala/Some
/*     */       //   489: astore #20
/*     */       //   491: aload #20
/*     */       //   493: invokevirtual x : ()Ljava/lang/Object;
/*     */       //   496: checkcast scala/util/Try
/*     */       //   499: astore #21
/*     */       //   501: aload #21
/*     */       //   503: instanceof scala/util/Success
/*     */       //   506: ifeq -> 557
/*     */       //   509: aload #21
/*     */       //   511: checkcast scala/util/Success
/*     */       //   514: astore #22
/*     */       //   516: aload #22
/*     */       //   518: invokevirtual value : ()Ljava/lang/Object;
/*     */       //   521: astore #23
/*     */       //   523: getstatic akka/actor/TypedActor$NullResponse$.MODULE$ : Lakka/actor/TypedActor$NullResponse$;
/*     */       //   526: aload #23
/*     */       //   528: astore #24
/*     */       //   530: dup
/*     */       //   531: ifnonnull -> 543
/*     */       //   534: pop
/*     */       //   535: aload #24
/*     */       //   537: ifnull -> 551
/*     */       //   540: goto -> 557
/*     */       //   543: aload #24
/*     */       //   545: invokevirtual equals : (Ljava/lang/Object;)Z
/*     */       //   548: ifeq -> 557
/*     */       //   551: iconst_1
/*     */       //   552: istore #19
/*     */       //   554: goto -> 617
/*     */       //   557: aload #17
/*     */       //   559: instanceof scala/Some
/*     */       //   562: ifeq -> 614
/*     */       //   565: aload #17
/*     */       //   567: checkcast scala/Some
/*     */       //   570: astore #25
/*     */       //   572: aload #25
/*     */       //   574: invokevirtual x : ()Ljava/lang/Object;
/*     */       //   577: checkcast scala/util/Try
/*     */       //   580: astore #26
/*     */       //   582: aload #26
/*     */       //   584: instanceof scala/util/Failure
/*     */       //   587: ifeq -> 614
/*     */       //   590: aload #26
/*     */       //   592: checkcast scala/util/Failure
/*     */       //   595: astore #27
/*     */       //   597: aload #27
/*     */       //   599: invokevirtual exception : ()Ljava/lang/Throwable;
/*     */       //   602: instanceof akka/pattern/AskTimeoutException
/*     */       //   605: ifeq -> 614
/*     */       //   608: iconst_1
/*     */       //   609: istore #19
/*     */       //   611: goto -> 617
/*     */       //   614: iconst_0
/*     */       //   615: istore #19
/*     */       //   617: iload #19
/*     */       //   619: ifeq -> 647
/*     */       //   622: aload #11
/*     */       //   624: invokevirtual returnsJOption : ()Z
/*     */       //   627: ifeq -> 639
/*     */       //   630: getstatic akka/japi/Option$.MODULE$ : Lakka/japi/Option$;
/*     */       //   633: invokevirtual none : ()Lakka/japi/Option;
/*     */       //   636: goto -> 642
/*     */       //   639: getstatic scala/None$.MODULE$ : Lscala/None$;
/*     */       //   642: astore #28
/*     */       //   644: goto -> 691
/*     */       //   647: aload #17
/*     */       //   649: instanceof scala/Some
/*     */       //   652: ifeq -> 702
/*     */       //   655: aload #17
/*     */       //   657: checkcast scala/Some
/*     */       //   660: astore #29
/*     */       //   662: aload #29
/*     */       //   664: invokevirtual x : ()Ljava/lang/Object;
/*     */       //   667: checkcast scala/util/Try
/*     */       //   670: astore #30
/*     */       //   672: aload #30
/*     */       //   674: instanceof scala/util/Try
/*     */       //   677: ifeq -> 702
/*     */       //   680: aload #30
/*     */       //   682: astore #31
/*     */       //   684: aload #31
/*     */       //   686: invokevirtual get : ()Ljava/lang/Object;
/*     */       //   689: astore #28
/*     */       //   691: aload #28
/*     */       //   693: astore #12
/*     */       //   695: aload #12
/*     */       //   697: astore #6
/*     */       //   699: aload #6
/*     */       //   701: areturn
/*     */       //   702: new scala/MatchError
/*     */       //   705: dup
/*     */       //   706: aload #17
/*     */       //   708: invokespecial <init> : (Ljava/lang/Object;)V
/*     */       //   711: athrow
/*     */       // Line number table:
/*     */       //   Java source line number -> byte code offset
/*     */       //   #411	-> 0
/*     */       //   #412	-> 6
/*     */       //   #413	-> 45
/*     */       //   #414	-> 135
/*     */       //   #416	-> 177
/*     */       //   #418	-> 189
/*     */       //   #419	-> 200
/*     */       //   #420	-> 208
/*     */       //   #419	-> 249
/*     */       //   #421	-> 254
/*     */       //   #425	-> 298
/*     */       //   #426	-> 314
/*     */       //   #427	-> 332
/*     */       //   #433	-> 358
/*     */       //   #434	-> 389
/*     */       //   #435	-> 425
/*     */       //   #433	-> 429
/*     */       //   #427	-> 436
/*     */       //   #428	-> 442
/*     */       //   #427	-> 597
/*     */       //   #428	-> 599
/*     */       //   #429	-> 622
/*     */       //   #430	-> 647
/*     */       //   #431	-> 684
/*     */       //   #427	-> 691
/*     */       //   #425	-> 693
/*     */       //   #418	-> 695
/*     */       //   #415	-> 697
/*     */       //   #411	-> 699
/*     */       //   #427	-> 702
/*     */       // Local variable table:
/*     */       //   start	length	slot	name	descriptor
/*     */       //   0	712	0	this	Lakka/actor/TypedActor$TypedActorInvocationHandler;
/*     */       //   0	712	1	proxy	Ljava/lang/Object;
/*     */       //   0	712	2	method	Ljava/lang/reflect/Method;
/*     */       //   0	712	3	args	[Ljava/lang/Object;
/*     */       //   189	508	10	dispatcher	Lscala/concurrent/ExecutionContextExecutor;
/*     */       //   220	26	13	qual$2	Lakka/actor/ScalaActorRef;
/*     */       //   224	22	14	x$4	Lakka/actor/TypedActor$MethodCall;
/*     */       //   235	11	15	x$5	Lakka/actor/ActorRef;
/*     */       //   332	361	16	f	Lscala/concurrent/Future;
/*     */       //   672	40	30	t	Lscala/util/Try;
/*     */       // Exception table:
/*     */       //   from	to	target	type
/*     */       //   332	358	436	java/util/concurrent/TimeoutException
/*     */     }
/*     */     
/*     */     public class TypedActor$TypedActorInvocationHandler$$anonfun$invoke$1 extends AbstractFunction1<Object, Object> implements Serializable {
/*     */       public static final long serialVersionUID = 0L;
/*     */       
/*     */       public final Object apply(Object x0$2) {
/* 421 */         Object object1 = x0$2;
/* 422 */         Object object2 = object1;
/* 422 */         if (TypedActor.NullResponse$.MODULE$ == null) {
/* 422 */           if (object2 != null)
/* 423 */             Object object = object1; 
/*     */         } else {
/*     */           if (TypedActor.NullResponse$.MODULE$.equals(object2)) {
/*     */             null;
/*     */             return null;
/*     */           } 
/* 423 */           Object object = object1;
/*     */         } 
/*     */         null;
/*     */         return null;
/*     */       }
/*     */       
/*     */       public TypedActor$TypedActorInvocationHandler$$anonfun$invoke$1(TypedActor.TypedActorInvocationHandler $outer) {}
/*     */     }
/*     */     
/*     */     private Object writeReplace() throws ObjectStreamException {
/* 439 */       return new TypedActor.SerializedTypedActorInvocationHandler(actor(), timeout().duration());
/*     */     }
/*     */   }
/*     */   
/*     */   public static class SerializedTypedActorInvocationHandler implements Product, Serializable {
/*     */     private final ActorRef actor;
/*     */     
/*     */     private final FiniteDuration timeout;
/*     */     
/*     */     public ActorRef actor() {
/* 445 */       return this.actor;
/*     */     }
/*     */     
/*     */     public FiniteDuration timeout() {
/* 445 */       return this.timeout;
/*     */     }
/*     */     
/*     */     public SerializedTypedActorInvocationHandler copy(ActorRef actor, FiniteDuration timeout) {
/* 445 */       return new SerializedTypedActorInvocationHandler(actor, timeout);
/*     */     }
/*     */     
/*     */     public ActorRef copy$default$1() {
/* 445 */       return actor();
/*     */     }
/*     */     
/*     */     public FiniteDuration copy$default$2() {
/* 445 */       return timeout();
/*     */     }
/*     */     
/*     */     public String productPrefix() {
/* 445 */       return "SerializedTypedActorInvocationHandler";
/*     */     }
/*     */     
/*     */     public int productArity() {
/* 445 */       return 2;
/*     */     }
/*     */     
/*     */     public Object productElement(int x$1) {
/* 445 */       int i = x$1;
/* 445 */       switch (i) {
/*     */         default:
/* 445 */           throw new IndexOutOfBoundsException(BoxesRunTime.boxToInteger(x$1).toString());
/*     */         case 1:
/*     */         
/*     */         case 0:
/*     */           break;
/*     */       } 
/* 445 */       return actor();
/*     */     }
/*     */     
/*     */     public Iterator<Object> productIterator() {
/* 445 */       return scala.runtime.ScalaRunTime$.MODULE$.typedProductIterator(this);
/*     */     }
/*     */     
/*     */     public boolean canEqual(Object x$1) {
/* 445 */       return x$1 instanceof SerializedTypedActorInvocationHandler;
/*     */     }
/*     */     
/*     */     public int hashCode() {
/* 445 */       return scala.runtime.ScalaRunTime$.MODULE$._hashCode(this);
/*     */     }
/*     */     
/*     */     public String toString() {
/* 445 */       return scala.runtime.ScalaRunTime$.MODULE$._toString(this);
/*     */     }
/*     */     
/*     */     public boolean equals(Object x$1) {
/*     */       // Byte code:
/*     */       //   0: aload_0
/*     */       //   1: aload_1
/*     */       //   2: if_acmpeq -> 112
/*     */       //   5: aload_1
/*     */       //   6: astore_2
/*     */       //   7: aload_2
/*     */       //   8: instanceof akka/actor/TypedActor$SerializedTypedActorInvocationHandler
/*     */       //   11: ifeq -> 19
/*     */       //   14: iconst_1
/*     */       //   15: istore_3
/*     */       //   16: goto -> 21
/*     */       //   19: iconst_0
/*     */       //   20: istore_3
/*     */       //   21: iload_3
/*     */       //   22: ifeq -> 116
/*     */       //   25: aload_1
/*     */       //   26: checkcast akka/actor/TypedActor$SerializedTypedActorInvocationHandler
/*     */       //   29: astore #4
/*     */       //   31: aload_0
/*     */       //   32: invokevirtual actor : ()Lakka/actor/ActorRef;
/*     */       //   35: aload #4
/*     */       //   37: invokevirtual actor : ()Lakka/actor/ActorRef;
/*     */       //   40: astore #5
/*     */       //   42: dup
/*     */       //   43: ifnonnull -> 55
/*     */       //   46: pop
/*     */       //   47: aload #5
/*     */       //   49: ifnull -> 63
/*     */       //   52: goto -> 108
/*     */       //   55: aload #5
/*     */       //   57: invokevirtual equals : (Ljava/lang/Object;)Z
/*     */       //   60: ifeq -> 108
/*     */       //   63: aload_0
/*     */       //   64: invokevirtual timeout : ()Lscala/concurrent/duration/FiniteDuration;
/*     */       //   67: aload #4
/*     */       //   69: invokevirtual timeout : ()Lscala/concurrent/duration/FiniteDuration;
/*     */       //   72: astore #6
/*     */       //   74: dup
/*     */       //   75: ifnonnull -> 87
/*     */       //   78: pop
/*     */       //   79: aload #6
/*     */       //   81: ifnull -> 95
/*     */       //   84: goto -> 108
/*     */       //   87: aload #6
/*     */       //   89: invokevirtual equals : (Ljava/lang/Object;)Z
/*     */       //   92: ifeq -> 108
/*     */       //   95: aload #4
/*     */       //   97: aload_0
/*     */       //   98: invokevirtual canEqual : (Ljava/lang/Object;)Z
/*     */       //   101: ifeq -> 108
/*     */       //   104: iconst_1
/*     */       //   105: goto -> 109
/*     */       //   108: iconst_0
/*     */       //   109: ifeq -> 116
/*     */       //   112: iconst_1
/*     */       //   113: goto -> 117
/*     */       //   116: iconst_0
/*     */       //   117: ireturn
/*     */       // Line number table:
/*     */       //   Java source line number -> byte code offset
/*     */       //   #445	-> 0
/*     */       //   #63	-> 14
/*     */       //   #445	-> 21
/*     */       // Local variable table:
/*     */       //   start	length	slot	name	descriptor
/*     */       //   0	118	0	this	Lakka/actor/TypedActor$SerializedTypedActorInvocationHandler;
/*     */       //   0	118	1	x$1	Ljava/lang/Object;
/*     */     }
/*     */     
/*     */     public SerializedTypedActorInvocationHandler(ActorRef actor, FiniteDuration timeout) {
/* 445 */       Product.class.$init$(this);
/*     */     }
/*     */     
/*     */     private Object readResolve() throws ObjectStreamException {
/* 446 */       ExtendedActorSystem extendedActorSystem = (ExtendedActorSystem)akka.serialization.JavaSerializer$.MODULE$.currentSystem().value();
/* 447 */       if (extendedActorSystem == null)
/* 447 */         throw new IllegalStateException("SerializedTypedActorInvocationHandler.readResolve requires that JavaSerializer.currentSystem.value is set to a non-null value"); 
/* 448 */       return toTypedActorInvocationHandler(extendedActorSystem);
/*     */     }
/*     */     
/*     */     public TypedActor.TypedActorInvocationHandler toTypedActorInvocationHandler(ActorSystem system) {
/* 452 */       return new TypedActor.TypedActorInvocationHandler((TypedActorExtension)TypedActor$.MODULE$.apply(system), new AtomicReference<ActorRef>(actor()), new Timeout(timeout()));
/*     */     }
/*     */   }
/*     */   
/*     */   public static class SerializedTypedActorInvocationHandler$ extends AbstractFunction2<ActorRef, FiniteDuration, SerializedTypedActorInvocationHandler> implements Serializable {
/*     */     public static final SerializedTypedActorInvocationHandler$ MODULE$;
/*     */     
/*     */     public final String toString() {
/*     */       return "SerializedTypedActorInvocationHandler";
/*     */     }
/*     */     
/*     */     public TypedActor.SerializedTypedActorInvocationHandler apply(ActorRef actor, FiniteDuration timeout) {
/*     */       return new TypedActor.SerializedTypedActorInvocationHandler(actor, timeout);
/*     */     }
/*     */     
/*     */     public Option<Tuple2<ActorRef, FiniteDuration>> unapply(TypedActor.SerializedTypedActorInvocationHandler x$0) {
/*     */       return (x$0 == null) ? (Option<Tuple2<ActorRef, FiniteDuration>>)scala.None$.MODULE$ : (Option<Tuple2<ActorRef, FiniteDuration>>)new Some(new Tuple2(x$0.actor(), x$0.timeout()));
/*     */     }
/*     */     
/*     */     private Object readResolve() {
/*     */       return MODULE$;
/*     */     }
/*     */     
/*     */     public SerializedTypedActorInvocationHandler$() {
/*     */       MODULE$ = this;
/*     */     }
/*     */   }
/*     */   
/*     */   public static interface Receiver {
/*     */     void onReceive(Object param1Object, ActorRef param1ActorRef);
/*     */   }
/*     */   
/*     */   public static interface PreStart {
/*     */     void preStart();
/*     */   }
/*     */   
/*     */   public static interface PostStop {
/*     */     void postStop();
/*     */   }
/*     */   
/*     */   public static interface Supervisor {
/*     */     SupervisorStrategy supervisorStrategy();
/*     */   }
/*     */   
/*     */   public static interface PreRestart {
/*     */     void preRestart(Throwable param1Throwable, Option<Object> param1Option);
/*     */   }
/*     */   
/*     */   public static interface PostRestart {
/*     */     void postRestart(Throwable param1Throwable);
/*     */   }
/*     */ }


/* Location:              D:\#source-code\TheFlightSims\TFSLibrary\World2Xplane\World2XPlane.jar!\akka\actor\TypedActor.class
 * Java compiler version: 6 (50.0)
 * JD-Core Version:       1.1.3
 */