/*    */ package scala.xml.dtd;
/*    */ 
/*    */ import scala.Function1;
/*    */ import scala.PartialFunction;
/*    */ import scala.Serializable;
/*    */ import scala.collection.IterableLike;
/*    */ import scala.collection.Seq;
/*    */ import scala.collection.immutable.Set;
/*    */ import scala.collection.mutable.StringBuilder;
/*    */ import scala.runtime.AbstractFunction1;
/*    */ import scala.runtime.AbstractPartialFunction;
/*    */ import scala.runtime.BoxedUnit;
/*    */ import scala.runtime.BoxesRunTime;
/*    */ import scala.util.regexp.Base;
/*    */ import scala.util.regexp.WordExp;
/*    */ 
/*    */ public final class ContentModel$ extends WordExp {
/*    */   public static final ContentModel$ MODULE$;
/*    */   
/*    */   private ContentModel$() {
/* 19 */     MODULE$ = this;
/*    */   }
/*    */   
/*    */   public boolean isMixed(ContentModel cm) {
/* 31 */     return scala.PartialFunction$.MODULE$.cond(cm, (PartialFunction)new ContentModel$$anonfun$isMixed$1());
/*    */   }
/*    */   
/*    */   public static class ContentModel$$anonfun$isMixed$1 extends AbstractPartialFunction.mcZL.sp<ContentModel> implements Serializable {
/*    */     public static final long serialVersionUID = 0L;
/*    */     
/*    */     public final <A1 extends ContentModel, B1> B1 applyOrElse(ContentModel x1, Function1 default) {
/*    */       Object object;
/* 31 */       if (x1 instanceof MIXED) {
/* 31 */         object = BoxesRunTime.boxToBoolean(true);
/*    */       } else {
/* 31 */         object = default.apply(x1);
/*    */       } 
/* 31 */       return (B1)object;
/*    */     }
/*    */     
/*    */     public final boolean isDefinedAt(ContentModel x1) {
/*    */       boolean bool;
/* 31 */       if (x1 instanceof MIXED) {
/* 31 */         bool = true;
/*    */       } else {
/* 31 */         bool = false;
/*    */       } 
/* 31 */       return bool;
/*    */     }
/*    */   }
/*    */   
/*    */   public boolean containsText(ContentModel cm) {
/* 32 */     PCDATA$ pCDATA$ = PCDATA$.MODULE$;
/* 32 */     if (cm == null) {
/* 32 */       if (pCDATA$ != null) {
/* 32 */         if (isMixed(cm));
/* 32 */         return false;
/*    */       } 
/* 32 */     } else if (!cm.equals(pCDATA$)) {
/* 32 */       if (isMixed(cm));
/* 32 */       return false;
/*    */     } 
/*    */   }
/*    */   
/*    */   public ContentModel parse(String s) {
/* 33 */     return ContentModelParser$.MODULE$.parse(s);
/*    */   }
/*    */   
/*    */   public final Set scala$xml$dtd$ContentModel$$traverse$1(Base.RegExp r) {
/*    */     // Byte code:
/*    */     //   0: aload_1
/*    */     //   1: instanceof scala/util/regexp/WordExp$Letter
/*    */     //   4: ifeq -> 62
/*    */     //   7: aload_1
/*    */     //   8: checkcast scala/util/regexp/WordExp$Letter
/*    */     //   11: astore_2
/*    */     //   12: aload_2
/*    */     //   13: invokevirtual a : ()Lscala/util/regexp/WordExp$Label;
/*    */     //   16: ifnull -> 62
/*    */     //   19: getstatic scala/Predef$.MODULE$ : Lscala/Predef$;
/*    */     //   22: invokevirtual Set : ()Lscala/collection/immutable/Set$;
/*    */     //   25: getstatic scala/Predef$.MODULE$ : Lscala/Predef$;
/*    */     //   28: iconst_1
/*    */     //   29: anewarray java/lang/String
/*    */     //   32: dup
/*    */     //   33: iconst_0
/*    */     //   34: aload_2
/*    */     //   35: invokevirtual a : ()Lscala/util/regexp/WordExp$Label;
/*    */     //   38: checkcast scala/xml/dtd/ContentModel$ElemName
/*    */     //   41: invokevirtual name : ()Ljava/lang/String;
/*    */     //   44: aastore
/*    */     //   45: checkcast [Ljava/lang/Object;
/*    */     //   48: invokevirtual wrapRefArray : ([Ljava/lang/Object;)Lscala/collection/mutable/WrappedArray;
/*    */     //   51: invokevirtual apply : (Lscala/collection/Seq;)Lscala/collection/GenTraversable;
/*    */     //   54: checkcast scala/collection/immutable/Set
/*    */     //   57: astore #8
/*    */     //   59: goto -> 235
/*    */     //   62: aload_1
/*    */     //   63: instanceof scala/util/regexp/Base$Star
/*    */     //   66: ifeq -> 82
/*    */     //   69: aload_1
/*    */     //   70: checkcast scala/util/regexp/Base$Star
/*    */     //   73: astore_3
/*    */     //   74: aload_3
/*    */     //   75: invokevirtual r : ()Lscala/util/regexp/Base$RegExp;
/*    */     //   78: astore_1
/*    */     //   79: goto -> 0
/*    */     //   82: aload_1
/*    */     //   83: instanceof scala/util/regexp/Base$Sequ
/*    */     //   86: ifeq -> 160
/*    */     //   89: aload_1
/*    */     //   90: checkcast scala/util/regexp/Base$Sequ
/*    */     //   93: astore #4
/*    */     //   95: aload_0
/*    */     //   96: invokevirtual Sequ : ()Lscala/util/regexp/Base$Sequ$;
/*    */     //   99: aload #4
/*    */     //   101: invokevirtual unapplySeq : (Lscala/util/regexp/Base$Sequ;)Lscala/Some;
/*    */     //   104: astore #5
/*    */     //   106: aload #5
/*    */     //   108: invokevirtual isEmpty : ()Z
/*    */     //   111: ifne -> 160
/*    */     //   114: getstatic scala/Predef$.MODULE$ : Lscala/Predef$;
/*    */     //   117: invokevirtual Set : ()Lscala/collection/immutable/Set$;
/*    */     //   120: aload #5
/*    */     //   122: invokevirtual get : ()Ljava/lang/Object;
/*    */     //   125: checkcast scala/collection/TraversableLike
/*    */     //   128: new scala/xml/dtd/ContentModel$$anonfun$scala$xml$dtd$ContentModel$$traverse$1$1
/*    */     //   131: dup
/*    */     //   132: invokespecial <init> : ()V
/*    */     //   135: getstatic scala/collection/Seq$.MODULE$ : Lscala/collection/Seq$;
/*    */     //   138: invokevirtual canBuildFrom : ()Lscala/collection/generic/CanBuildFrom;
/*    */     //   141: invokeinterface flatMap : (Lscala/Function1;Lscala/collection/generic/CanBuildFrom;)Ljava/lang/Object;
/*    */     //   146: checkcast scala/collection/Seq
/*    */     //   149: invokevirtual apply : (Lscala/collection/Seq;)Lscala/collection/GenTraversable;
/*    */     //   152: checkcast scala/collection/immutable/Set
/*    */     //   155: astore #8
/*    */     //   157: goto -> 235
/*    */     //   160: aload_1
/*    */     //   161: instanceof scala/util/regexp/Base$Alt
/*    */     //   164: ifeq -> 238
/*    */     //   167: aload_1
/*    */     //   168: checkcast scala/util/regexp/Base$Alt
/*    */     //   171: astore #6
/*    */     //   173: aload_0
/*    */     //   174: invokevirtual Alt : ()Lscala/util/regexp/Base$Alt$;
/*    */     //   177: aload #6
/*    */     //   179: invokevirtual unapplySeq : (Lscala/util/regexp/Base$Alt;)Lscala/Some;
/*    */     //   182: astore #7
/*    */     //   184: aload #7
/*    */     //   186: invokevirtual isEmpty : ()Z
/*    */     //   189: ifne -> 238
/*    */     //   192: getstatic scala/Predef$.MODULE$ : Lscala/Predef$;
/*    */     //   195: invokevirtual Set : ()Lscala/collection/immutable/Set$;
/*    */     //   198: aload #7
/*    */     //   200: invokevirtual get : ()Ljava/lang/Object;
/*    */     //   203: checkcast scala/collection/TraversableLike
/*    */     //   206: new scala/xml/dtd/ContentModel$$anonfun$scala$xml$dtd$ContentModel$$traverse$1$2
/*    */     //   209: dup
/*    */     //   210: invokespecial <init> : ()V
/*    */     //   213: getstatic scala/collection/Seq$.MODULE$ : Lscala/collection/Seq$;
/*    */     //   216: invokevirtual canBuildFrom : ()Lscala/collection/generic/CanBuildFrom;
/*    */     //   219: invokeinterface flatMap : (Lscala/Function1;Lscala/collection/generic/CanBuildFrom;)Ljava/lang/Object;
/*    */     //   224: checkcast scala/collection/Seq
/*    */     //   227: invokevirtual apply : (Lscala/collection/Seq;)Lscala/collection/GenTraversable;
/*    */     //   230: checkcast scala/collection/immutable/Set
/*    */     //   233: astore #8
/*    */     //   235: aload #8
/*    */     //   237: areturn
/*    */     //   238: new scala/MatchError
/*    */     //   241: dup
/*    */     //   242: aload_1
/*    */     //   243: invokespecial <init> : (Ljava/lang/Object;)V
/*    */     //   246: athrow
/*    */     // Line number table:
/*    */     //   Java source line number -> byte code offset
/*    */     //   #37	-> 0
/*    */     //   #36	-> 0
/*    */     //   #36	-> 35
/*    */     //   #37	-> 41
/*    */     //   #38	-> 62
/*    */     //   #36	-> 74
/*    */     //   #38	-> 75
/*    */     //   #39	-> 82
/*    */     //   #36	-> 120
/*    */     //   #39	-> 122
/*    */     //   #40	-> 160
/*    */     //   #36	-> 198
/*    */     //   #40	-> 200
/*    */     //   #36	-> 235
/*    */     // Local variable table:
/*    */     //   start	length	slot	name	descriptor
/*    */     //   0	247	0	this	Lscala/xml/dtd/ContentModel$;
/*    */     //   0	247	1	r	Lscala/util/regexp/Base$RegExp;
/*    */   }
/*    */   
/*    */   public static class ContentModel$$anonfun$scala$xml$dtd$ContentModel$$traverse$1$1 extends AbstractFunction1<Base.RegExp, Set<String>> implements Serializable {
/*    */     public static final long serialVersionUID = 0L;
/*    */     
/*    */     public final Set<String> apply(Base.RegExp r) {
/* 39 */       return ContentModel$.MODULE$.scala$xml$dtd$ContentModel$$traverse$1(r);
/*    */     }
/*    */   }
/*    */   
/*    */   public static class ContentModel$$anonfun$scala$xml$dtd$ContentModel$$traverse$1$2 extends AbstractFunction1<Base.RegExp, Set<String>> implements Serializable {
/*    */     public static final long serialVersionUID = 0L;
/*    */     
/*    */     public final Set<String> apply(Base.RegExp r) {
/* 40 */       return ContentModel$.MODULE$.scala$xml$dtd$ContentModel$$traverse$1(r);
/*    */     }
/*    */   }
/*    */   
/*    */   public Set<String> getLabels(Base.RegExp r) {
/* 43 */     return scala$xml$dtd$ContentModel$$traverse$1(r);
/*    */   }
/*    */   
/*    */   public String buildString(Base.RegExp r) {
/* 46 */     return scala.xml.Utility$.MODULE$.sbToString((Function1)new ContentModel$$anonfun$buildString$1(r));
/*    */   }
/*    */   
/*    */   public static class ContentModel$$anonfun$buildString$1 extends AbstractFunction1<StringBuilder, BoxedUnit> implements Serializable {
/*    */     public static final long serialVersionUID = 0L;
/*    */     
/*    */     private final Base.RegExp r$1;
/*    */     
/*    */     public final void apply(StringBuilder x$1) {
/* 46 */       ContentModel$.MODULE$.buildString(this.r$1, x$1);
/*    */     }
/*    */     
/*    */     public ContentModel$$anonfun$buildString$1(Base.RegExp r$1) {}
/*    */   }
/*    */   
/*    */   private void buildString(Seq rs, StringBuilder sb, char sep) {
/* 50 */     buildString((Base.RegExp)rs.head(), sb);
/* 51 */     ((IterableLike)rs.tail()).foreach((Function1)new ContentModel$$anonfun$buildString$2(sb, sep));
/*    */   }
/*    */   
/*    */   public static class ContentModel$$anonfun$buildString$2 extends AbstractFunction1<Base.RegExp, StringBuilder> implements Serializable {
/*    */     public static final long serialVersionUID = 0L;
/*    */     
/*    */     private final StringBuilder sb$1;
/*    */     
/*    */     private final char sep$1;
/*    */     
/*    */     public ContentModel$$anonfun$buildString$2(StringBuilder sb$1, char sep$1) {}
/*    */     
/*    */     public final StringBuilder apply(Base.RegExp z) {
/* 52 */       this.sb$1.append(this.sep$1);
/* 53 */       return ContentModel$.MODULE$.buildString(z, this.sb$1);
/*    */     }
/*    */   }
/*    */   
/*    */   public StringBuilder buildString(ContentModel c, StringBuilder sb) {
/*    */     // Byte code:
/*    */     //   0: getstatic scala/xml/dtd/ANY$.MODULE$ : Lscala/xml/dtd/ANY$;
/*    */     //   3: dup
/*    */     //   4: ifnonnull -> 15
/*    */     //   7: pop
/*    */     //   8: aload_1
/*    */     //   9: ifnull -> 22
/*    */     //   12: goto -> 33
/*    */     //   15: aload_1
/*    */     //   16: invokevirtual equals : (Ljava/lang/Object;)Z
/*    */     //   19: ifeq -> 33
/*    */     //   22: aload_2
/*    */     //   23: ldc 'ANY'
/*    */     //   25: invokevirtual append : (Ljava/lang/String;)Lscala/collection/mutable/StringBuilder;
/*    */     //   28: astore #4
/*    */     //   30: goto -> 136
/*    */     //   33: getstatic scala/xml/dtd/EMPTY$.MODULE$ : Lscala/xml/dtd/EMPTY$;
/*    */     //   36: dup
/*    */     //   37: ifnonnull -> 48
/*    */     //   40: pop
/*    */     //   41: aload_1
/*    */     //   42: ifnull -> 55
/*    */     //   45: goto -> 66
/*    */     //   48: aload_1
/*    */     //   49: invokevirtual equals : (Ljava/lang/Object;)Z
/*    */     //   52: ifeq -> 66
/*    */     //   55: aload_2
/*    */     //   56: ldc 'EMPTY'
/*    */     //   58: invokevirtual append : (Ljava/lang/String;)Lscala/collection/mutable/StringBuilder;
/*    */     //   61: astore #4
/*    */     //   63: goto -> 136
/*    */     //   66: getstatic scala/xml/dtd/PCDATA$.MODULE$ : Lscala/xml/dtd/PCDATA$;
/*    */     //   69: dup
/*    */     //   70: ifnonnull -> 81
/*    */     //   73: pop
/*    */     //   74: aload_1
/*    */     //   75: ifnull -> 88
/*    */     //   78: goto -> 99
/*    */     //   81: aload_1
/*    */     //   82: invokevirtual equals : (Ljava/lang/Object;)Z
/*    */     //   85: ifeq -> 99
/*    */     //   88: aload_2
/*    */     //   89: ldc '(#PCDATA)'
/*    */     //   91: invokevirtual append : (Ljava/lang/String;)Lscala/collection/mutable/StringBuilder;
/*    */     //   94: astore #4
/*    */     //   96: goto -> 136
/*    */     //   99: aload_1
/*    */     //   100: instanceof scala/xml/dtd/ELEMENTS
/*    */     //   103: ifeq -> 111
/*    */     //   106: iconst_1
/*    */     //   107: istore_3
/*    */     //   108: goto -> 125
/*    */     //   111: aload_1
/*    */     //   112: instanceof scala/xml/dtd/MIXED
/*    */     //   115: ifeq -> 123
/*    */     //   118: iconst_1
/*    */     //   119: istore_3
/*    */     //   120: goto -> 125
/*    */     //   123: iconst_0
/*    */     //   124: istore_3
/*    */     //   125: iload_3
/*    */     //   126: ifeq -> 139
/*    */     //   129: aload_1
/*    */     //   130: aload_2
/*    */     //   131: invokevirtual buildString : (Lscala/collection/mutable/StringBuilder;)Lscala/collection/mutable/StringBuilder;
/*    */     //   134: astore #4
/*    */     //   136: aload #4
/*    */     //   138: areturn
/*    */     //   139: new scala/MatchError
/*    */     //   142: dup
/*    */     //   143: aload_1
/*    */     //   144: invokespecial <init> : (Ljava/lang/Object;)V
/*    */     //   147: athrow
/*    */     // Line number table:
/*    */     //   Java source line number -> byte code offset
/*    */     //   #58	-> 0
/*    */     //   #57	-> 0
/*    */     //   #59	-> 33
/*    */     //   #60	-> 66
/*    */     //   #61	-> 99
/*    */     //   #57	-> 136
/*    */     // Local variable table:
/*    */     //   start	length	slot	name	descriptor
/*    */     //   0	148	0	this	Lscala/xml/dtd/ContentModel$;
/*    */     //   0	148	1	c	Lscala/xml/dtd/ContentModel;
/*    */     //   0	148	2	sb	Lscala/collection/mutable/StringBuilder;
/*    */   }
/*    */   
/*    */   public StringBuilder buildString(Base.RegExp r, StringBuilder sb) {
/*    */     // Byte code:
/*    */     //   0: aload_0
/*    */     //   1: invokevirtual Eps : ()Lscala/util/regexp/Base$Eps$;
/*    */     //   4: dup
/*    */     //   5: ifnonnull -> 16
/*    */     //   8: pop
/*    */     //   9: aload_1
/*    */     //   10: ifnull -> 23
/*    */     //   13: goto -> 29
/*    */     //   16: aload_1
/*    */     //   17: invokevirtual equals : (Ljava/lang/Object;)Z
/*    */     //   20: ifeq -> 29
/*    */     //   23: aload_2
/*    */     //   24: astore #10
/*    */     //   26: goto -> 249
/*    */     //   29: aload_1
/*    */     //   30: instanceof scala/util/regexp/Base$Sequ
/*    */     //   33: ifeq -> 92
/*    */     //   36: aload_1
/*    */     //   37: checkcast scala/util/regexp/Base$Sequ
/*    */     //   40: astore_3
/*    */     //   41: aload_0
/*    */     //   42: invokevirtual Sequ : ()Lscala/util/regexp/Base$Sequ$;
/*    */     //   45: aload_3
/*    */     //   46: invokevirtual unapplySeq : (Lscala/util/regexp/Base$Sequ;)Lscala/Some;
/*    */     //   49: astore #4
/*    */     //   51: aload #4
/*    */     //   53: invokevirtual isEmpty : ()Z
/*    */     //   56: ifne -> 92
/*    */     //   59: aload_2
/*    */     //   60: bipush #40
/*    */     //   62: invokevirtual append : (C)Lscala/collection/mutable/StringBuilder;
/*    */     //   65: pop
/*    */     //   66: aload_0
/*    */     //   67: aload #4
/*    */     //   69: invokevirtual get : ()Ljava/lang/Object;
/*    */     //   72: checkcast scala/collection/Seq
/*    */     //   75: aload_2
/*    */     //   76: bipush #44
/*    */     //   78: invokespecial buildString : (Lscala/collection/Seq;Lscala/collection/mutable/StringBuilder;C)V
/*    */     //   81: aload_2
/*    */     //   82: bipush #41
/*    */     //   84: invokevirtual append : (C)Lscala/collection/mutable/StringBuilder;
/*    */     //   87: astore #10
/*    */     //   89: goto -> 249
/*    */     //   92: aload_1
/*    */     //   93: instanceof scala/util/regexp/Base$Alt
/*    */     //   96: ifeq -> 157
/*    */     //   99: aload_1
/*    */     //   100: checkcast scala/util/regexp/Base$Alt
/*    */     //   103: astore #5
/*    */     //   105: aload_0
/*    */     //   106: invokevirtual Alt : ()Lscala/util/regexp/Base$Alt$;
/*    */     //   109: aload #5
/*    */     //   111: invokevirtual unapplySeq : (Lscala/util/regexp/Base$Alt;)Lscala/Some;
/*    */     //   114: astore #6
/*    */     //   116: aload #6
/*    */     //   118: invokevirtual isEmpty : ()Z
/*    */     //   121: ifne -> 157
/*    */     //   124: aload_2
/*    */     //   125: bipush #40
/*    */     //   127: invokevirtual append : (C)Lscala/collection/mutable/StringBuilder;
/*    */     //   130: pop
/*    */     //   131: aload_0
/*    */     //   132: aload #6
/*    */     //   134: invokevirtual get : ()Ljava/lang/Object;
/*    */     //   137: checkcast scala/collection/Seq
/*    */     //   140: aload_2
/*    */     //   141: bipush #124
/*    */     //   143: invokespecial buildString : (Lscala/collection/Seq;Lscala/collection/mutable/StringBuilder;C)V
/*    */     //   146: aload_2
/*    */     //   147: bipush #41
/*    */     //   149: invokevirtual append : (C)Lscala/collection/mutable/StringBuilder;
/*    */     //   152: astore #10
/*    */     //   154: goto -> 249
/*    */     //   157: aload_1
/*    */     //   158: instanceof scala/util/regexp/Base$Star
/*    */     //   161: ifeq -> 211
/*    */     //   164: aload_1
/*    */     //   165: checkcast scala/util/regexp/Base$Star
/*    */     //   168: astore #7
/*    */     //   170: aload #7
/*    */     //   172: invokevirtual r : ()Lscala/util/regexp/Base$RegExp;
/*    */     //   175: ifnull -> 211
/*    */     //   178: aload #7
/*    */     //   180: invokevirtual r : ()Lscala/util/regexp/Base$RegExp;
/*    */     //   183: astore #8
/*    */     //   185: aload_2
/*    */     //   186: bipush #40
/*    */     //   188: invokevirtual append : (C)Lscala/collection/mutable/StringBuilder;
/*    */     //   191: pop
/*    */     //   192: aload_0
/*    */     //   193: aload #8
/*    */     //   195: aload_2
/*    */     //   196: invokevirtual buildString : (Lscala/util/regexp/Base$RegExp;Lscala/collection/mutable/StringBuilder;)Lscala/collection/mutable/StringBuilder;
/*    */     //   199: pop
/*    */     //   200: aload_2
/*    */     //   201: ldc ')*'
/*    */     //   203: invokevirtual append : (Ljava/lang/String;)Lscala/collection/mutable/StringBuilder;
/*    */     //   206: astore #10
/*    */     //   208: goto -> 249
/*    */     //   211: aload_1
/*    */     //   212: instanceof scala/util/regexp/WordExp$Letter
/*    */     //   215: ifeq -> 252
/*    */     //   218: aload_1
/*    */     //   219: checkcast scala/util/regexp/WordExp$Letter
/*    */     //   222: astore #9
/*    */     //   224: aload #9
/*    */     //   226: invokevirtual a : ()Lscala/util/regexp/WordExp$Label;
/*    */     //   229: ifnull -> 252
/*    */     //   232: aload_2
/*    */     //   233: aload #9
/*    */     //   235: invokevirtual a : ()Lscala/util/regexp/WordExp$Label;
/*    */     //   238: checkcast scala/xml/dtd/ContentModel$ElemName
/*    */     //   241: invokevirtual name : ()Ljava/lang/String;
/*    */     //   244: invokevirtual append : (Ljava/lang/String;)Lscala/collection/mutable/StringBuilder;
/*    */     //   247: astore #10
/*    */     //   249: aload #10
/*    */     //   251: areturn
/*    */     //   252: new scala/MatchError
/*    */     //   255: dup
/*    */     //   256: aload_1
/*    */     //   257: invokespecial <init> : (Ljava/lang/Object;)V
/*    */     //   260: athrow
/*    */     // Line number table:
/*    */     //   Java source line number -> byte code offset
/*    */     //   #66	-> 0
/*    */     //   #65	-> 0
/*    */     //   #67	-> 23
/*    */     //   #68	-> 29
/*    */     //   #69	-> 59
/*    */     //   #65	-> 67
/*    */     //   #69	-> 69
/*    */     //   #68	-> 87
/*    */     //   #70	-> 92
/*    */     //   #71	-> 124
/*    */     //   #65	-> 132
/*    */     //   #71	-> 134
/*    */     //   #70	-> 152
/*    */     //   #72	-> 157
/*    */     //   #65	-> 170
/*    */     //   #72	-> 172
/*    */     //   #65	-> 178
/*    */     //   #72	-> 180
/*    */     //   #73	-> 185
/*    */     //   #72	-> 206
/*    */     //   #74	-> 211
/*    */     //   #75	-> 232
/*    */     //   #74	-> 233
/*    */     //   #65	-> 235
/*    */     //   #75	-> 241
/*    */     //   #65	-> 249
/*    */     // Local variable table:
/*    */     //   start	length	slot	name	descriptor
/*    */     //   0	261	0	this	Lscala/xml/dtd/ContentModel$;
/*    */     //   0	261	1	r	Lscala/util/regexp/Base$RegExp;
/*    */     //   0	261	2	sb	Lscala/collection/mutable/StringBuilder;
/*    */   }
/*    */   
/*    */   public class ContentModel$$anonfun$toString$1 extends AbstractFunction1<StringBuilder, BoxedUnit> implements Serializable {
/*    */     public static final long serialVersionUID = 0L;
/*    */     
/*    */     public final void apply(StringBuilder sb) {
/* 82 */       this.$outer.buildString(sb);
/*    */     }
/*    */     
/*    */     public ContentModel$$anonfun$toString$1(ContentModel $outer) {}
/*    */   }
/*    */ }


/* Location:              D:\#source-code\TheFlightSims\TFSLibrary\World2Xplane\World2XPlane.jar!\scala\xml\dtd\ContentModel$.class
 * Java compiler version: 6 (50.0)
 * JD-Core Version:       1.1.3
 */